Workbook

Sheet Inputs
B1: Fator de escala | C1: Fonte já na unidade final = 1 · fonte em milhares = 0,001 | D1: 1 | F1: MODELO-BASE VAZIO — preencha os valores nas linhas abaixo e as datas de primeiro e último trimestre no painel de premissas
B2: COD | C2: Conta (como divulgada) | D2: Fonte · ORIGEM · unidade | E2: 1T20 | F2: 2T20 | G2: 3T20 | H2: 4T20 | I2: 1T21 | J2: 2T21 | K2: 3T21 | L2: 4T21 | M2: 1T22 | N2: 2T22 | O2: 3T22 | P2: 4T22 | Q2: 1T23 | R2: 2T23 | S2: 3T23 | T2: 4T23 | U2: 1T24 | V2: 2T24 | W2: 3T24 | X2: 4T24 | Y2: 1T25 | Z2: 2T25 | AA2: 3T25 | AB2: 4T25 | AC2: 1T26 | AD2: 2T26 | AE2: 3T26 | AF2: 4T26 | AG2: 1T27 | AH2: 2T27 | AI2: 3T27 | AJ2: 4T27 | AK2: 1T28 | AL2: 2T28 | AM2: 3T28 | AN2: 4T28 | AO2: 1T29 | AP2: 2T29 | AQ2: 3T29 | AR2: 4T29 | AS2: 1T30 | AT2: 2T30 | AU2: 3T30 | AV2: 4T30
C5: ATIVO
B6: disp | C6: Disponibilidades | D6: preencher: aba e linha da fonte · fonte · moeda
B7: aplic_mo | C7: Aplicações no Mercado Aberto | D7: preencher: aba e linha da fonte · fonte · moeda
B8: aplic_di | C8: Aplicações em Depósitos Interfinanceiros | D8: preencher: aba e linha da fonte · fonte · moeda
B9: aplic_rg | C9: Recursos Garantidores das Provisões Técnicas | D9: preencher: aba e linha da fonte · fonte · moeda
B10: aplic_pdd | C10: (Provisão para Perda de Crédito Esperada) | D10: preencher: aba e linha da fonte · fonte · moeda
B11: tvm_prop | C11: Carteira própria | D11: preencher: aba e linha da fonte · fonte · moeda
B12: tvm_vinc | C12: Vinculados | D12: preencher: aba e linha da fonte · fonte · moeda
B13: tvm_rg | C13: Recursos Garantidores das Provisões Técnicas | D13: preencher: aba e linha da fonte · fonte · moeda
B14: tvm_pdd | C14: (Provisão para Perda de Crédito Esperada) | D14: preencher: aba e linha da fonte · fonte · moeda
B15: deriv_a | C15: Derivativos | D15: preencher: aba e linha da fonte · fonte · moeda
B16: cred_op | C16: Operações de Crédito, Arrendamentos e Outros Créditos | D16: preencher: aba e linha da fonte · fonte · moeda
B17: cred_tvm | C17: Títulos e Valores Mobiliários | D17: preencher: aba e linha da fonte · fonte · moeda
... B25: intang | C25: Ágio e Intangível | D25: preencher: aba e linha da fonte · fonte · moeda
C27: PASSIVO
B28: dep_vista | C28: Depósitos à Vista | D28: preencher: aba e linha da fonte · fonte · moeda
B29: dep_poup | C29: Depósitos de Poupança | D29: preencher: aba e linha da fonte · fonte · moeda
B30: dep_inter | C30: Depósitos Interfinanceiros | D30: preencher: aba e linha da fonte · fonte · moeda
B31: dep_prazo | C31: Depósitos a Prazo | D31: preencher: aba e linha da fonte · fonte · moeda
B32: dep_out | C32: Outros Depósitos | D32: preencher: aba e linha da fonte · fonte · moeda
B33: mo_prop | C33: Carteira Própria | D33: preencher: aba e linha da fonte · fonte · moeda
B34: mo_terc | C34: Carteira de Terceiros | D34: preencher: aba e linha da fonte · fonte · moeda
B35: mo_livre | C35: Carteira de Livre Movimentação | D35: preencher: aba e linha da fonte · fonte · moeda
B36: div_emis | C36: Recursos de Emissões (LF, LCI, LCA, LIG) | D36: preencher: aba e linha da fonte · fonte · moeda
B37: div_ext | C37: Obrigações por TVM no Exterior | D37: preencher: aba e linha da fonte · fonte · moeda
B38: div_coe | C38: Captação por Certificados de Operações Estruturadas | D38: preencher: aba e linha da fonte · fonte · moeda
B39: div_sub | C39: Instrumentos de Dívida Subordinada | D39: preencher: aba e linha da fonte · fonte · moeda
... B48: out_p | C48: Outros Passivos | D48: preencher: aba e linha da fonte · fonte · moeda
C50: PATRIMÔNIO LÍQUIDO
B51: cap_social | C51: Capital Social | D51: preencher: aba e linha da fonte · fonte · moeda
B52: res_cap | C52: Reservas de Capital | D52: preencher: aba e linha da fonte · fonte · moeda
B53: res_luc | C53: Reservas de Lucros | D53: preencher: aba e linha da fonte · fonte · moeda
B54: ora | C54: Outros Resultados Abrangentes | D54: preencher: aba e linha da fonte · fonte · moeda
B55: tesour | C55: (Ações em Tesouraria) | D55: preencher: aba e linha da fonte · fonte · moeda
B56: minor | C56: Participação de Acionistas Não Controladores | D56: preencher: aba e linha da fonte · fonte · moeda
C58: DEMONSTRAÇÃO DO RESULTADO
B59: rec_cred | C59: Resultado com Operações de Concessão de Crédito | D59: preencher: aba e linha da fonte · fonte · moeda
B60: rec_tvm | C60: Resultado de TVM, Derivativos e Outros | D60: preencher: aba e linha da fonte · fonte · moeda
B61: rec_rg | C61: Receitas Fin. de Recursos Garantidores de Prov. Técnicas | D61: preencher: aba e linha da fonte · fonte · moeda
B62: rec_aplic | C62: Resultado das Aplicações Interfinanceiras de Liquidez | D62: preencher: aba e linha da fonte · fonte · moeda
B63: desp_dep | C63: (Depósitos e Captações no Mercado Aberto) | D63: preencher: aba e linha da fonte · fonte · moeda
B64: desp_div | C64: (Instrumentos de Dívida) | D64: preencher: aba e linha da fonte · fonte · moeda
B65: desp_emp | C65: (Empréstimos e Repasses) | D65: preencher: aba e linha da fonte · fonte · moeda
B66: desp_prov_tec | C66: (Despesas Fin. de Provisões Técnicas) | D66: preencher: aba e linha da fonte · fonte · moeda
B67: pdd_desp | C67: (Despesa de Provisão para Perda Esperada) | D67: preencher: aba e linha da fonte · fonte · moeda
B68: pdd_recup | C68: Recuperação de Créditos Baixados como Prejuízo | D68: preencher: aba e linha da fonte · fonte · moeda
B69: serv | C69: Receitas de Prestação de Serviços e Tarifas Bancárias | D69: preencher: aba e linha da fonte · fonte · moeda
B70: seguros | C70: Resultado de Seguros, Previdência e Capitalização | D70: preencher: aba e linha da fonte · fonte · moeda
... B83: ll_minor | C83: (Participação de Não Controladores) | D83: preencher: aba e linha da fonte · fonte · moeda
C85: DADOS COMPLEMENTARES
B86: cart_ampl | C86: Carteira de crédito ampliada | D86: preencher: aba e linha da fonte · fonte · moeda
B87: cart_pf | C87: Pessoa física | D87: preencher: aba e linha da fonte · fonte · moeda
B88: cart_pj | C88: Pessoa jurídica | D88: preencher: aba e linha da fonte · fonte · moeda
B89: est1 | C89: Carteira em Estágio 1 | D89: preencher: aba e linha da fonte · fonte · moeda
B90: est2 | C90: Carteira em Estágio 2 | D90: preencher: aba e linha da fonte · fonte · moeda
B91: est3 | C91: Carteira em Estágio 3 | D91: preencher: aba e linha da fonte · fonte · moeda
B92: prov_e1 | C92: Saldo de provisão — Estágio 1 | D92: preencher: aba e linha da fonte · fonte · moeda
B93: prov_e2 | C93: Saldo de provisão — Estágio 2 | D93: preencher: aba e linha da fonte · fonte · moeda
B94: prov_e3 | C94: Saldo de provisão — Estágio 3 | D94: preencher: aba e linha da fonte · fonte · moeda
B95: prov_tot | C95: Saldo total de provisão | D95: preencher: aba e linha da fonte · fonte · moeda
B96: npl90 | C96: Operações vencidas acima de 90 dias | D96: preencher: aba e linha da fonte · fonte · moeda
B97: npl15 | C97: Operações vencidas de 15 a 90 dias | D97: preencher: aba e linha da fonte · fonte · moeda
... B148: adm_out | C148: (Demais despesas administrativas) | D148: preencher: aba e linha da fonte · fonte · moeda
C150: Linhas derivadas por fórmula dentro da própria Inputs
C153: Espaço livre até a linha 190 para novas linhas de origem. Qualquer linha acrescentada aqui com um código existente é somada automaticamente pela Inputs (2), sem editar fórmula.
C196: IDENTIFICAÇÃO E MERCADO | D196: COMPANY & MARKET DATA
C197: Instituição | D197: Institution
C198: Ticker | D198: Ticker
C199: Segmento / norma contábil | D199: Segment / accounting standard
C200: Moeda de reporte | D200: Reporting currency | E200: R$ | BI200: Escolha a moeda aqui. Os títulos do Model, da Inputs (2) e do Valuation leem esta célula, então trocar BRL por USD renomeia a planilha inteira. O que a célula não faz é converter valor: conversão de moeda é outra coisa.
C201: Escala dos valores | D201: Scale | E201: milhões
C202: Unidade monetária (moeda + escala) | D202: Currency unit | E202: =E200&" "&E201 -> R$ milhões
C203: Último trimestre reportado (data de fechamento) | D203: Last reported quarter | BI203: Esta data controla todo o modelo: colunas entre o primeiro e o último trimestre são lidas como realizado; as demais são projetadas.
C204: Primeiro trimestre com dado na fonte | D204: First quarter covered by the source | BI204: Séries que começam depois da grade do modelo: as colunas anteriores ficam fora do realizado em vez de entrar como zero realizado.
C205: Data-base do valuation | D205: Valuation date
C206: ="Preço da ação ("&Inputs!$E$200&")" -> Preço da ação (R$) | D206: Share price | BI206: Preço e quantidade de ações são premissa sua, não vêm da série histórica. A quantidade de ações entra em milhões, na mesma escala do modelo, para o LPA e o VPA saírem por ação.
C207: Ações ordinárias (milhões) | D207: Common shares (mn)
C208: Ações preferenciais (milhões) | D208: Preferred shares (mn)
C209: (-) Ações em tesouraria (milhões) | D209: (-) Treasury shares (mn)
C210: Ações ex-tesouraria (milhões) | D210: Shares ex-treasury (mn) | E210: =E207+E208+E209 -> 0
C211: ="Market cap ("&Inputs!$E$202&")" -> Market cap (R$ milhões) | D211: Market capitalisation | E211: =E206*E210 -> 0
C213: GRADE DE PERÍODOS | D213: PERIOD GRID
C214: Data de fechamento | D214: Period end | E214: =DATE(2020,4,1)-1 -> 43921 | F214: =DATE(2020,7,1)-1 -> 44012 | G214: =DATE(2020,10,1)-1 -> 44104 | H214: =DATE(2020,13,1)-1 -> 44196 | I214: =H214 -> 44196 | J214: =DATE(2021,4,1)-1 -> 44286 | K214: =DATE(2021,7,1)-1 -> 44377 | L214: =DATE(2021,10,1)-1 -> 44469 | M214: =DATE(2021,13,1)-1 -> 44561 | N214: =M214 -> 44561 | O214: =DATE(2022,4,1)-1 -> 44651 | P214: =DATE(2022,7,1)-1 -> 44742 | Q214: =DATE(2022,10,1)-1 -> 44834 | R214: =DATE(2022,13,1)-1 -> 44926 | S214: =R214 -> 44926 | T214: =DATE(2023,4,1)-1 -> 45016 | U214: =DATE(2023,7,1)-1 -> 45107 | V214: =DATE(2023,10,1)-1 -> 45199 | W214: =DATE(2023,13,1)-1 -> 45291 | X214: =W214 -> 45291 | Y214: =DATE(2024,4,1)-1 -> 45382 | Z214: =DATE(2024,7,1)-1 -> 45473 | AA214: =DATE(2024,10,1)-1 -> 45565 | AB214: =DATE(2024,13,1)-1 -> 45657 | AC214: =AB214 -> 45657 | AD214: =DATE(2025,4,1)-1 -> 45747 | AE214: =DATE(2025,7,1)-1 -> 45838 | AF214: =DATE(2025,10,1)-1 -> 45930 | AG214: =DATE(2025,13,1)-1 -> 46022 | AH214: =AG214 -> 46022 | AI214: =DATE(2026,4,1)-1 -> 46112 | AJ214: =DATE(2026,7,1)-1 -> 46203 | AK214: =DATE(2026,10,1)-1 -> 46295 | AL214: =DATE(2026,13,1)-1 -> 46387 | AM214: =AL214 -> 46387 | AN214: =DATE(2027,4,1)-1 -> 46477 | AO214: =DATE(2027,7,1)-1 -> 46568 | AP214: =DATE(2027,10,1)-1 -> 46660 | AQ214: =DATE(2027,13,1)-1 -> 46752 | AR214: =AQ214 -> 46752 | AS214: =DATE(2028,4,1)-1 -> 46843 | AT214: =DATE(2028,7,1)-1 -> 46934 | AU214: =DATE(2028,10,1)-1 -> 47026 | AV214: =DATE(2028,13,1)-1 -> 47118 | AW214: =AV214 -> 47118 | AX214: =DATE(2029,4,1)-1 -> 47208 | AY214: =DATE(2029,7,1)-1 -> 47299 | AZ214: =DATE(2029,10,1)-1 -> 47391 | BA214: =DATE(2029,13,1)-1 -> 47483 | BB214: =BA214 -> 47483 | BC214: =DATE(2030,4,1)-1 -> 47573 | BD214: =DATE(2030,7,1)-1 -> 47664 | BE214: =DATE(2030,10,1)-1 -> 47756 | BF214: =DATE(2030,13,1)-1 -> 47848 | BG214: =BF214 -> 47848
C215: Ano | D215: Year | E215: 2020 | F215: 2020 | G215: 2020 | H215: 2020 | I215: 2020 | J215: 2021 | K215: 2021 | L215: 2021 | M215: 2021 | N215: 2021 | O215: 2022 | P215: 2022 | Q215: 2022 | R215: 2022 | S215: 2022 | T215: 2023 | U215: 2023 | V215: 2023 | W215: 2023 | X215: 2023 | Y215: 2024 | Z215: 2024 | AA215: 2024 | AB215: 2024 | AC215: 2024 | AD215: 2025 | AE215: 2025 | AF215: 2025 | AG215: 2025 | AH215: 2025 | AI215: 2026 | AJ215: 2026 | AK215: 2026 | AL215: 2026 | AM215: 2026 | AN215: 2027 | AO215: 2027 | AP215: 2027 | AQ215: 2027 | AR215: 2027 | AS215: 2028 | AT215: 2028 | AU215: 2028 | AV215: 2028 | AW215: 2028 | AX215: 2029 | AY215: 2029 | AZ215: 2029 | BA215: 2029 | BB215: 2029 | BC215: 2030 | BD215: 2030 | BE215: 2030 | BF215: 2030 | BG215: 2030
C216: Período | D216: Period | E216: ="1Q"&RIGHT(E215,2) -> 1Q20 | F216: ="2Q"&RIGHT(F215,2) -> 2Q20 | G216: ="3Q"&RIGHT(G215,2) -> 3Q20 | H216: ="4Q"&RIGHT(H215,2) -> 4Q20 | I216: ="FY"&RIGHT(I215,2) -> FY20 | J216: ="1Q"&RIGHT(J215,2) -> 1Q21 | K216: ="2Q"&RIGHT(K215,2) -> 2Q21 | L216: ="3Q"&RIGHT(L215,2) -> 3Q21 | M216: ="4Q"&RIGHT(M215,2) -> 4Q21 | N216: ="FY"&RIGHT(N215,2) -> FY21 | O216: ="1Q"&RIGHT(O215,2) -> 1Q22 | P216: ="2Q"&RIGHT(P215,2) -> 2Q22 | Q216: ="3Q"&RIGHT(Q215,2) -> 3Q22 | R216: ="4Q"&RIGHT(R215,2) -> 4Q22 | S216: ="FY"&RIGHT(S215,2) -> FY22 | T216: ="1Q"&RIGHT(T215,2) -> 1Q23 | U216: ="2Q"&RIGHT(U215,2) -> 2Q23 | V216: ="3Q"&RIGHT(V215,2) -> 3Q23 | W216: ="4Q"&RIGHT(W215,2) -> 4Q23 | X216: ="FY"&RIGHT(X215,2) -> FY23 | Y216: ="1Q"&RIGHT(Y215,2) -> 1Q24 | Z216: ="2Q"&RIGHT(Z215,2) -> 2Q24 | AA216: ="3Q"&RIGHT(AA215,2) -> 3Q24 | AB216: ="4Q"&RIGHT(AB215,2) -> 4Q24 | AC216: ="FY"&RIGHT(AC215,2) -> FY24 | AD216: ="1Q"&RIGHT(AD215,2) -> 1Q25 | AE216: ="2Q"&RIGHT(AE215,2) -> 2Q25 | AF216: ="3Q"&RIGHT(AF215,2) -> 3Q25 | AG216: ="4Q"&RIGHT(AG215,2) -> 4Q25 | AH216: ="FY"&RIGHT(AH215,2) -> FY25 | AI216: ="1Q"&RIGHT(AI215,2) -> 1Q26 | AJ216: ="2Q"&RIGHT(AJ215,2) -> 2Q26 | AK216: ="3Q"&RIGHT(AK215,2) -> 3Q26 | AL216: ="4Q"&RIGHT(AL215,2) -> 4Q26 | AM216: ="FY"&RIGHT(AM215,2) -> FY26 | AN216: ="1Q"&RIGHT(AN215,2) -> 1Q27 | AO216: ="2Q"&RIGHT(AO215,2) -> 2Q27 | AP216: ="3Q"&RIGHT(AP215,2) -> 3Q27 | AQ216: ="4Q"&RIGHT(AQ215,2) -> 4Q27 | AR216: ="FY"&RIGHT(AR215,2) -> FY27 | AS216: ="1Q"&RIGHT(AS215,2) -> 1Q28 | AT216: ="2Q"&RIGHT(AT215,2) -> 2Q28 | AU216: ="3Q"&RIGHT(AU215,2) -> 3Q28 | AV216: ="4Q"&RIGHT(AV215,2) -> 4Q28 | AW216: ="FY"&RIGHT(AW215,2) -> FY28 | AX216: ="1Q"&RIGHT(AX215,2) -> 1Q29 | AY216: ="2Q"&RIGHT(AY215,2) -> 2Q29 | AZ216: ="3Q"&RIGHT(AZ215,2) -> 3Q29 | BA216: ="4Q"&RIGHT(BA215,2) -> 4Q29 | BB216: ="FY"&RIGHT(BB215,2) -> FY29 | BC216: ="1Q"&RIGHT(BC215,2) -> 1Q30 | BD216: ="2Q"&RIGHT(BD215,2) -> 2Q30 | BE216: ="3Q"&RIGHT(BE215,2) -> 3Q30 | BF216: ="4Q"&RIGHT(BF215,2) -> 4Q30 | BG216: ="FY"&RIGHT(BG215,2) -> FY30
C217: Realizado (1) / Projetado (0) | D217: Actual (1) / Forecast (0) | E217: =IF(AND(E214>=Inputs!$E$204,E214<=Inputs!$E$203),1,0) -> 0 | F217: =IF(AND(F214>=Inputs!$E$204,F214<=Inputs!$E$203),1,0) -> 0 | G217: =IF(AND(G214>=Inputs!$E$204,G214<=Inputs!$E$203),1,0) -> 0 | H217: =IF(AND(H214>=Inputs!$E$204,H214<=Inputs!$E$203),1,0) -> 0 | I217: =IF(AND(I214>=Inputs!$E$204,I214<=Inputs!$E$203),1,0) -> 0 | J217: =IF(AND(J214>=Inputs!$E$204,J214<=Inputs!$E$203),1,0) -> 0 | K217: =IF(AND(K214>=Inputs!$E$204,K214<=Inputs!$E$203),1,0) -> 0 | L217: =IF(AND(L214>=Inputs!$E$204,L214<=Inputs!$E$203),1,0) -> 0 | ... BG217: =IF(AND(BG214>=Inputs!$E$204,BG214<=Inputs!$E$203),1,0) -> 0 | BI217: Não editar: derivado da data do último trimestre reportado.
C219: DRIVERS IMPLÍCITOS NO HISTÓRICO — CALCULADOS DA INPUTS (2) | D219: IMPLIED DRIVERS — DERIVED FROM REPORTED DATA | BI219: Espelho das premissas dos blocos abaixo, calculado do reportado. Serve para você ver a variação realizada antes de escolher a projeção. Nenhuma linha daqui é lida pelo Model, então não há referência circular: basta copiar o número que fizer sentido para a célula amarela do bloco correspondente. Coluna sem dado na fonte fica vazia.
C220: Crédito, tesouraria e funding — realizado | D220: Loans, treasury and funding — actual
C221: Carteira de crédito bruta — crescimento % QoQ | D221: Gross loan growth QoQ | F221: =IFERROR(IF(('Inputs (2)'!E18+'Inputs (2)'!E19)=0,"",('Inputs (2)'!F18+'Inputs (2)'!F19)/('Inputs (2)'!E18+'Inputs (2)'!E19)-1),"") | G221: =IFERROR(IF(('Inputs (2)'!F18+'Inputs (2)'!F19)=0,"",('Inputs (2)'!G18+'Inputs (2)'!G19)/('Inputs (2)'!F18+'Inputs (2)'!F19)-1),"") | H221: =IFERROR(IF(('Inputs (2)'!G18+'Inputs (2)'!G19)=0,"",('Inputs (2)'!H18+'Inputs (2)'!H19)/('Inputs (2)'!G18+'Inputs (2)'!G19)-1),"") | J221: =IFERROR(IF(('Inputs (2)'!H18+'Inputs (2)'!H19)=0,"",('Inputs (2)'!J18+'Inputs (2)'!J19)/('Inputs (2)'!H18+'Inputs (2)'!H19)-1),"") | K221: =IFERROR(IF(('Inputs (2)'!J18+'Inputs (2)'!J19)=0,"",('Inputs (2)'!K18+'Inputs (2)'!K19)/('Inputs (2)'!J18+'Inputs (2)'!J19)-1),"") | L221: =IFERROR(IF(('Inputs (2)'!K18+'Inputs (2)'!K19)=0,"",('Inputs (2)'!L18+'Inputs (2)'!L19)/('Inputs (2)'!K18+'Inputs (2)'!K19)-1),"") | M221: =IFERROR(IF(('Inputs (2)'!L18+'Inputs (2)'!L19)=0,"",('Inputs (2)'!M18+'Inputs (2)'!M19)/('Inputs (2)'!L18+'Inputs (2)'!L19)-1),"") | N221: =IFERROR(IF(('Inputs (2)'!I18+'Inputs (2)'!I19)=0,"",('Inputs (2)'!N18+'Inputs (2)'!N19)/('Inputs (2)'!I18+'Inputs (2)'!I19)-1),"") | O221: =IFERROR(IF(('Inputs (2)'!M18+'Inputs (2)'!M19)=0,"",('Inputs (2)'!O18+'Inputs (2)'!O19)/('Inputs (2)'!M18+'Inputs (2)'!M19)-1),"") | P221: =IFERROR(IF(('Inputs (2)'!O18+'Inputs (2)'!O19)=0,"",('Inputs (2)'!P18+'Inputs (2)'!P19)/('Inputs (2)'!O18+'Inputs (2)'!O19)-1),"") | Q221: =IFERROR(IF(('Inputs (2)'!P18+'Inputs (2)'!P19)=0,"",('Inputs (2)'!Q18+'Inputs (2)'!Q19)/('Inputs (2)'!P18+'Inputs (2)'!P19)-1),"") | R221: =IFERROR(IF(('Inputs (2)'!Q18+'Inputs (2)'!Q19)=0,"",('Inputs (2)'!R18+'Inputs (2)'!R19)/('Inputs (2)'!Q18+'Inputs (2)'!Q19)-1),"") | S221: =IFERROR(IF(('Inputs (2)'!N18+'Inputs (2)'!N19)=0,"",('Inputs (2)'!S18+'Inputs (2)'!S19)/('Inputs (2)'!N18+'Inputs (2)'!N19)-1),"") | T221: =IFERROR(IF(('Inputs (2)'!R18+'Inputs (2)'!R19)=0,"",('Inputs (2)'!T18+'Inputs (2)'!T19)/('Inputs (2)'!R18+'Inputs (2)'!R19)-1),"") | U221: =IFERROR(IF(('Inputs (2)'!T18+'Inputs (2)'!T19)=0,"",('Inputs (2)'!U18+'Inputs (2)'!U19)/('Inputs (2)'!T18+'Inputs (2)'!T19)-1),"") | V221: =IFERROR(IF(('Inputs (2)'!U18+'Inputs (2)'!U19)=0,"",('Inputs (2)'!V18+'Inputs (2)'!V19)/('Inputs (2)'!U18+'Inputs (2)'!U19)-1),"") | W221: =IFERROR(IF(('Inputs (2)'!V18+'Inputs (2)'!V19)=0,"",('Inputs (2)'!W18+'Inputs (2)'!W19)/('Inputs (2)'!V18+'Inputs (2)'!V19)-1),"") | X221: =IFERROR(IF(('Inputs (2)'!S18+'Inputs (2)'!S19)=0,"",('Inputs (2)'!X18+'Inputs (2)'!X19)/('Inputs (2)'!S18+'Inputs (2)'!S19)-1),"") | Y221: =IFERROR(IF(('Inputs (2)'!W18+'Inputs (2)'!W19)=0,"",('Inputs (2)'!Y18+'Inputs (2)'!Y19)/('Inputs (2)'!W18+'Inputs (2)'!W19)-1),"") | Z221: =IFERROR(IF(('Inputs (2)'!Y18+'Inputs (2)'!Y19)=0,"",('Inputs (2)'!Z18+'Inputs (2)'!Z19)/('Inputs (2)'!Y18+'Inputs (2)'!Y19)-1),"") | AA221: =IFERROR(IF(('Inputs (2)'!Z18+'Inputs (2)'!Z19)=0,"",('Inputs (2)'!AA18+'Inputs (2)'!AA19)/('Inputs (2)'!Z18+'Inputs (2)'!Z19)-1),"") | AB221: =IFERROR(IF(('Inputs (2)'!AA18+'Inputs (2)'!AA19)=0,"",('Inputs (2)'!AB18+'Inputs (2)'!AB19)/('Inputs (2)'!AA18+'Inputs (2)'!AA19)-1),"") | AC221: =IFERROR(IF(('Inputs (2)'!X18+'Inputs (2)'!X19)=0,"",('Inputs (2)'!AC18+'Inputs (2)'!AC19)/('Inputs (2)'!X18+'Inputs (2)'!X19)-1),"") | AD221: =IFERROR(IF(('Inputs (2)'!AB18+'Inputs (2)'!AB19)=0,"",('Inputs (2)'!AD18+'Inputs (2)'!AD19)/('Inputs (2)'!AB18+'Inputs (2)'!AB19)-1),"") | AE221: =IFERROR(IF(('Inputs (2)'!AD18+'Inputs (2)'!AD19)=0,"",('Inputs (2)'!AE18+'Inputs (2)'!AE19)/('Inputs (2)'!AD18+'Inputs (2)'!AD19)-1),"") | AF221: =IFERROR(IF(('Inputs (2)'!AE18+'Inputs (2)'!AE19)=0,"",('Inputs (2)'!AF18+'Inputs (2)'!AF19)/('Inputs (2)'!AE18+'Inputs (2)'!AE19)-1),"") | AG221: =IFERROR(IF(('Inputs (2)'!AF18+'Inputs (2)'!AF19)=0,"",('Inputs (2)'!AG18+'Inputs (2)'!AG19)/('Inputs (2)'!AF18+'Inputs (2)'!AF19)-1),"") | AH221: =IFERROR(IF(('Inputs (2)'!AC18+'Inputs (2)'!AC19)=0,"",('Inputs (2)'!AH18+'Inputs (2)'!AH19)/('Inputs (2)'!AC18+'Inputs (2)'!AC19)-1),"") | AI221: =IFERROR(IF(('Inputs (2)'!AG18+'Inputs (2)'!AG19)=0,"",('Inputs (2)'!AI18+'Inputs (2)'!AI19)/('Inputs (2)'!AG18+'Inputs (2)'!AG19)-1),"") | AJ221: =IFERROR(IF(('Inputs (2)'!AI18+'Inputs (2)'!AI19)=0,"",('Inputs (2)'!AJ18+'Inputs (2)'!AJ19)/('Inputs (2)'!AI18+'Inputs (2)'!AI19)-1),"") | AK221: =IFERROR(IF(('Inputs (2)'!AJ18+'Inputs (2)'!AJ19)=0,"",('Inputs (2)'!AK18+'Inputs (2)'!AK19)/('Inputs (2)'!AJ18+'Inputs (2)'!AJ19)-1),"") | AL221: =IFERROR(IF(('Inputs (2)'!AK18+'Inputs (2)'!AK19)=0,"",('Inputs (2)'!AL18+'Inputs (2)'!AL19)/('Inputs (2)'!AK18+'Inputs (2)'!AK19)-1),"") | AM221: =IFERROR(IF(('Inputs (2)'!AH18+'Inputs (2)'!AH19)=0,"",('Inputs (2)'!AM18+'Inputs (2)'!AM19)/('Inputs (2)'!AH18+'Inputs (2)'!AH19)-1),"") | AN221: =IFERROR(IF(('Inputs (2)'!AL18+'Inputs (2)'!AL19)=0,"",('Inputs (2)'!AN18+'Inputs (2)'!AN19)/('Inputs (2)'!AL18+'Inputs (2)'!AL19)-1),"") | AO221: =IFERROR(IF(('Inputs (2)'!AN18+'Inputs (2)'!AN19)=0,"",('Inputs (2)'!AO18+'Inputs (2)'!AO19)/('Inputs (2)'!AN18+'Inputs (2)'!AN19)-1),"") | AP221: =IFERROR(IF(('Inputs (2)'!AO18+'Inputs (2)'!AO19)=0,"",('Inputs (2)'!AP18+'Inputs (2)'!AP19)/('Inputs (2)'!AO18+'Inputs (2)'!AO19)-1),"") | AQ221: =IFERROR(IF(('Inputs (2)'!AP18+'Inputs (2)'!AP19)=0,"",('Inputs (2)'!AQ18+'Inputs (2)'!AQ19)/('Inputs (2)'!AP18+'Inputs (2)'!AP19)-1),"") | AR221: =IFERROR(IF(('Inputs (2)'!AM18+'Inputs (2)'!AM19)=0,"",('Inputs (2)'!AR18+'Inputs (2)'!AR19)/('Inputs (2)'!AM18+'Inputs (2)'!AM19)-1),"") | AS221: =IFERROR(IF(('Inputs (2)'!AQ18+'Inputs (2)'!AQ19)=0,"",('Inputs (2)'!AS18+'Inputs (2)'!AS19)/('Inputs (2)'!AQ18+'Inputs (2)'!AQ19)-1),"") | AT221: =IFERROR(IF(('Inputs (2)'!AS18+'Inputs (2)'!AS19)=0,"",('Inputs (2)'!AT18+'Inputs (2)'!AT19)/('Inputs (2)'!AS18+'Inputs (2)'!AS19)-1),"") | AU221: =IFERROR(IF(('Inputs (2)'!AT18+'Inputs (2)'!AT19)=0,"",('Inputs (2)'!AU18+'Inputs (2)'!AU19)/('Inputs (2)'!AT18+'Inputs (2)'!AT19)-1),"") | AV221: =IFERROR(IF(('Inputs (2)'!AU18+'Inputs (2)'!AU19)=0,"",('Inputs (2)'!AV18+'Inputs (2)'!AV19)/('Inputs (2)'!AU18+'Inputs (2)'!AU19)-1),"") | AW221: =IFERROR(IF(('Inputs (2)'!AR18+'Inputs (2)'!AR19)=0,"",('Inputs (2)'!AW18+'Inputs (2)'!AW19)/('Inputs (2)'!AR18+'Inputs (2)'!AR19)-1),"") | AX221: =IFERROR(IF(('Inputs (2)'!AV18+'Inputs (2)'!AV19)=0,"",('Inputs (2)'!AX18+'Inputs (2)'!AX19)/('Inputs (2)'!AV18+'Inputs (2)'!AV19)-1),"") | AY221: =IFERROR(IF(('Inputs (2)'!AX18+'Inputs (2)'!AX19)=0,"",('Inputs (2)'!AY18+'Inputs (2)'!AY19)/('Inputs (2)'!AX18+'Inputs (2)'!AX19)-1),"") | AZ221: =IFERROR(IF(('Inputs (2)'!AY18+'Inputs (2)'!AY19)=0,"",('Inputs (2)'!AZ18+'Inputs (2)'!AZ19)/('Inputs (2)'!AY18+'Inputs (2)'!AY19)-1),"") | BA221: =IFERROR(IF(('Inputs (2)'!AZ18+'Inputs (2)'!AZ19)=0,"",('Inputs (2)'!BA18+'Inputs (2)'!BA19)/('Inputs (2)'!AZ18+'Inputs (2)'!AZ19)-1),"") | BB221: =IFERROR(IF(('Inputs (2)'!AW18+'Inputs (2)'!AW19)=0,"",('Inputs (2)'!BB18+'Inputs (2)'!BB19)/('Inputs (2)'!AW18+'Inputs (2)'!AW19)-1),"") | BC221: =IFERROR(IF(('Inputs (2)'!BA18+'Inputs (2)'!BA19)=0,"",('Inputs (2)'!BC18+'Inputs (2)'!BC19)/('Inputs (2)'!BA18+'Inputs (2)'!BA19)-1),"") | BD221: =IFERROR(IF(('Inputs (2)'!BC18+'Inputs (2)'!BC19)=0,"",('Inputs (2)'!BD18+'Inputs (2)'!BD19)/('Inputs (2)'!BC18+'Inputs (2)'!BC19)-1),"") | BE221: =IFERROR(IF(('Inputs (2)'!BD18+'Inputs (2)'!BD19)=0,"",('Inputs (2)'!BE18+'Inputs (2)'!BE19)/('Inputs (2)'!BD18+'Inputs (2)'!BD19)-1),"") | BF221: =IFERROR(IF(('Inputs (2)'!BE18+'Inputs (2)'!BE19)=0,"",('Inputs (2)'!BF18+'Inputs (2)'!BF19)/('Inputs (2)'!BE18+'Inputs (2)'!BE19)-1),"") | BG221: =IFERROR(IF(('Inputs (2)'!BB18+'Inputs (2)'!BB19)=0,"",('Inputs (2)'!BG18+'Inputs (2)'!BG19)/('Inputs (2)'!BB18+'Inputs (2)'!BB19)-1),"")
C222: Taxa média da carteira de crédito (% a.a.) | D222: Average loan yield | E222: =IFERROR(IF(OR(('Inputs (2)'!E18+'Inputs (2)'!E19)=0,('Inputs (2)'!E71)=0),"",('Inputs (2)'!E71)*4/('Inputs (2)'!E18+'Inputs (2)'!E19)),"") | F222: =IFERROR(IF(OR(AVERAGE(('Inputs (2)'!E18+'Inputs (2)'!E19),('Inputs (2)'!F18+'Inputs (2)'!F19))=0,('Inputs (2)'!F71)=0),"",('Inputs (2)'!F71)*4/AVERAGE(('Inputs (2)'!E18+'Inputs (2)'!E19),('Inputs (2)'!F18+'Inputs (2)'!F19))),"") | G222: =IFERROR(IF(OR(AVERAGE(('Inputs (2)'!F18+'Inputs (2)'!F19),('Inputs (2)'!G18+'Inputs (2)'!G19))=0,('Inputs (2)'!G71)=0),"",('Inputs (2)'!G71)*4/AVERAGE(('Inputs (2)'!F18+'Inputs (2)'!F19),('Inputs (2)'!G18+'Inputs (2)'!G19))),"") | H222: =IFERROR(IF(OR(AVERAGE(('Inputs (2)'!G18+'Inputs (2)'!G19),('Inputs (2)'!H18+'Inputs (2)'!H19))=0,('Inputs (2)'!H71)=0),"",('Inputs (2)'!H71)*4/AVERAGE(('Inputs (2)'!G18+'Inputs (2)'!G19),('Inputs (2)'!H18+'Inputs (2)'!H19))),"") | I222: =IFERROR(IF(OR(('Inputs (2)'!I18+'Inputs (2)'!I19)=0,('Inputs (2)'!I71)=0),"",('Inputs (2)'!I71)/('Inputs (2)'!I18+'Inputs (2)'!I19)),"") | J222: =IFERROR(IF(OR(AVERAGE(('Inputs (2)'!H18+'Inputs (2)'!H19),('Inputs (2)'!J18+'Inputs (2)'!J19))=0,('Inputs (2)'!J71)=0),"",('Inputs (2)'!J71)*4/AVERAGE(('Inputs (2)'!H18+'Inputs (2)'!H19),('Inputs (2)'!J18+'Inputs (2)'!J19))),"") | K222: =IFERROR(IF(OR(AVERAGE(('Inputs (2)'!J18+'Inputs (2)'!J19),('Inputs (2)'!K18+'Inputs (2)'!K19))=0,('Inputs (2)'!K71)=0),"",('Inputs (2)'!K71)*4/AVERAGE(('Inputs (2)'!J18+'Inputs (2)'!J19),('Inputs (2)'!K18+'Inputs (2)'!K19))),"") | L222: =IFERROR(IF(OR(AVERAGE(('Inputs (2)'!K18+'Inputs (2)'!K19),('Inputs (2)'!L18+'Inputs (2)'!L19))=0,('Inputs (2)'!L71)=0),"",('Inputs (2)'!L71)*4/AVERAGE(('Inputs (2)'!K18+'Inputs (2)'!K19),('Inputs (2)'!L18+'Inputs (2)'!L19))),"") | M222: =IFERROR(IF(OR(AVERAGE(('Inputs (2)'!L18+'Inputs (2)'!L19),('Inputs (2)'!M18+'Inputs (2)'!M19))=0,('Inputs (2)'!M71)=0),"",('Inputs (2)'!M71)*4/AVERAGE(('Inputs (2)'!L18+'Inputs (2)'!L19),('Inputs (2)'!M18+'Inputs (2)'!M19))),"") | N222: =IFERROR(IF(OR(AVERAGE(('Inputs (2)'!I18+'Inputs (2)'!I19),('Inputs (2)'!N18+'Inputs (2)'!N19))=0,('Inputs (2)'!N71)=0),"",('Inputs (2)'!N71)/AVERAGE(('Inputs (2)'!I18+'Inputs (2)'!I19),('Inputs (2)'!N18+'Inputs (2)'!N19))),"") | O222: =IFERROR(IF(OR(AVERAGE(('Inputs (2)'!M18+'Inputs (2)'!M19),('Inputs (2)'!O18+'Inputs (2)'!O19))=0,('Inputs (2)'!O71)=0),"",('Inputs (2)'!O71)*4/AVERAGE(('Inputs (2)'!M18+'Inputs (2)'!M19),('Inputs (2)'!O18+'Inputs (2)'!O19))),"") | P222: =IFERROR(IF(OR(AVERAGE(('Inputs (2)'!O18+'Inputs (2)'!O19),('Inputs (2)'!P18+'Inputs (2)'!P19))=0,('Inputs (2)'!P71)=0),"",('Inputs (2)'!P71)*4/AVERAGE(('Inputs (2)'!O18+'Inputs (2)'!O19),('Inputs (2)'!P18+'Inputs (2)'!P19))),"") | Q222: =IFERROR(IF(OR(AVERAGE(('Inputs (2)'!P18+'Inputs (2)'!P19),('Inputs (2)'!Q18+'Inputs (2)'!Q19))=0,('Inputs (2)'!Q71)=0),"",('Inputs (2)'!Q71)*4/AVERAGE(('Inputs (2)'!P18+'Inputs (2)'!P19),('Inputs (2)'!Q18+'Inputs (2)'!Q19))),"") | R222: =IFERROR(IF(OR(AVERAGE(('Inputs (2)'!Q18+'Inputs (2)'!Q19),('Inputs (2)'!R18+'Inputs (2)'!R19))=0,('Inputs (2)'!R71)=0),"",('Inputs (2)'!R71)*4/AVERAGE(('Inputs (2)'!Q18+'Inputs (2)'!Q19),('Inputs (2)'!R18+'Inputs (2)'!R19))),"") | S222: =IFERROR(IF(OR(AVERAGE(('Inputs (2)'!N18+'Inputs (2)'!N19),('Inputs (2)'!S18+'Inputs (2)'!S19))=0,('Inputs (2)'!S71)=0),"",('Inputs (2)'!S71)/AVERAGE(('Inputs (2)'!N18+'Inputs (2)'!N19),('Inputs (2)'!S18+'Inputs (2)'!S19))),"") | T222: =IFERROR(IF(OR(AVERAGE(('Inputs (2)'!R18+'Inputs (2)'!R19),('Inputs (2)'!T18+'Inputs (2)'!T19))=0,('Inputs (2)'!T71)=0),"",('Inputs (2)'!T71)*4/AVERAGE(('Inputs (2)'!R18+'Inputs (2)'!R19),('Inputs (2)'!T18+'Inputs (2)'!T19))),"") | U222: =IFERROR(IF(OR(AVERAGE(('Inputs (2)'!T18+'Inputs (2)'!T19),('Inputs (2)'!U18+'Inputs (2)'!U19))=0,('Inputs (2)'!U71)=0),"",('Inputs (2)'!U71)*4/AVERAGE(('Inputs (2)'!T18+'Inputs (2)'!T19),('Inputs (2)'!U18+'Inputs (2)'!U19))),"") | V222: =IFERROR(IF(OR(AVERAGE(('Inputs (2)'!U18+'Inputs (2)'!U19),('Inputs (2)'!V18+'Inputs (2)'!V19))=0,('Inputs (2)'!V71)=0),"",('Inputs (2)'!V71)*4/AVERAGE(('Inputs (2)'!U18+'Inputs (2)'!U19),('Inputs (2)'!V18+'Inputs (2)'!V19))),"") | W222: =IFERROR(IF(OR(AVERAGE(('Inputs (2)'!V18+'Inputs (2)'!V19),('Inputs (2)'!W18+'Inputs (2)'!W19))=0,('Inputs (2)'!W71)=0),"",('Inputs (2)'!W71)*4/AVERAGE(('Inputs (2)'!V18+'Inputs (2)'!V19),('Inputs (2)'!W18+'Inputs (2)'!W19))),"") | X222: =IFERROR(IF(OR(AVERAGE(('Inputs (2)'!S18+'Inputs (2)'!S19),('Inputs (2)'!X18+'Inputs (2)'!X19))=0,('Inputs (2)'!X71)=0),"",('Inputs (2)'!X71)/AVERAGE(('Inputs (2)'!S18+'Inputs (2)'!S19),('Inputs (2)'!X18+'Inputs (2)'!X19))),"") | Y222: =IFERROR(IF(OR(AVERAGE(('Inputs (2)'!W18+'Inputs (2)'!W19),('Inputs (2)'!Y18+'Inputs (2)'!Y19))=0,('Inputs (2)'!Y71)=0),"",('Inputs (2)'!Y71)*4/AVERAGE(('Inputs (2)'!W18+'Inputs (2)'!W19),('Inputs (2)'!Y18+'Inputs (2)'!Y19))),"") | Z222: =IFERROR(IF(OR(AVERAGE(('Inputs (2)'!Y18+'Inputs (2)'!Y19),('Inputs (2)'!Z18+'Inputs (2)'!Z19))=0,('Inputs (2)'!Z71)=0),"",('Inputs (2)'!Z71)*4/AVERAGE(('Inputs (2)'!Y18+'Inputs (2)'!Y19),('Inputs (2)'!Z18+'Inputs (2)'!Z19))),"") | AA222: =IFERROR(IF(OR(AVERAGE(('Inputs (2)'!Z18+'Inputs (2)'!Z19),('Inputs (2)'!AA18+'Inputs (2)'!AA19))=0,('Inputs (2)'!AA71)=0),"",('Inputs (2)'!AA71)*4/AVERAGE(('Inputs (2)'!Z18+'Inputs (2)'!Z19),('Inputs (2)'!AA18+'Inputs (2)'!AA19))),"") | AB222: =IFERROR(IF(OR(AVERAGE(('Inputs (2)'!AA18+'Inputs (2)'!AA19),('Inputs (2)'!AB18+'Inputs (2)'!AB19))=0,('Inputs (2)'!AB71)=0),"",('Inputs (2)'!AB71)*4/AVERAGE(('Inputs (2)'!AA18+'Inputs (2)'!AA19),('Inputs (2)'!AB18+'Inputs (2)'!AB19))),"") | AC222: =IFERROR(IF(OR(AVERAGE(('Inputs (2)'!X18+'Inputs (2)'!X19),('Inputs (2)'!AC18+'Inputs (2)'!AC19))=0,('Inputs (2)'!AC71)=0),"",('Inputs (2)'!AC71)/AVERAGE(('Inputs (2)'!X18+'Inputs (2)'!X19),('Inputs (2)'!AC18+'Inputs (2)'!AC19))),"") | AD222: =IFERROR(IF(OR(AVERAGE(('Inputs (2)'!AB18+'Inputs (2)'!AB19),('Inputs (2)'!AD18+'Inputs (2)'!AD19))=0,('Inputs (2)'!AD71)=0),"",('Inputs (2)'!AD71)*4/AVERAGE(('Inputs (2)'!AB18+'Inputs (2)'!AB19),('Inputs (2)'!AD18+'Inputs (2)'!AD19))),"") | AE222: =IFERROR(IF(OR(AVERAGE(('Inputs (2)'!AD18+'Inputs (2)'!AD19),('Inputs (2)'!AE18+'Inputs (2)'!AE19))=0,('Inputs (2)'!AE71)=0),"",('Inputs (2)'!AE71)*4/AVERAGE(('Inputs (2)'!AD18+'Inputs (2)'!AD19),('Inputs (2)'!AE18+'Inputs (2)'!AE19))),"") | AF222: =IFERROR(IF(OR(AVERAGE(('Inputs (2)'!AE18+'Inputs (2)'!AE19),('Inputs (2)'!AF18+'Inputs (2)'!AF19))=0,('Inputs (2)'!AF71)=0),"",('Inputs (2)'!AF71)*4/AVERAGE(('Inputs (2)'!AE18+'Inputs (2)'!AE19),('Inputs (2)'!AF18+'Inputs (2)'!AF19))),"") | AG222: =IFERROR(IF(OR(AVERAGE(('Inputs (2)'!AF18+'Inputs (2)'!AF19),('Inputs (2)'!AG18+'Inputs (2)'!AG19))=0,('Inputs (2)'!AG71)=0),"",('Inputs (2)'!AG71)*4/AVERAGE(('Inputs (2)'!AF18+'Inputs (2)'!AF19),('Inputs (2)'!AG18+'Inputs (2)'!AG19))),"") | AH222: =IFERROR(IF(OR(AVERAGE(('Inputs (2)'!AC18+'Inputs (2)'!AC19),('Inputs (2)'!AH18+'Inputs (2)'!AH19))=0,('Inputs (2)'!AH71)=0),"",('Inputs (2)'!AH71)/AVERAGE(('Inputs (2)'!AC18+'Inputs (2)'!AC19),('Inputs (2)'!AH18+'Inputs (2)'!AH19))),"") | AI222: =IFERROR(IF(OR(AVERAGE(('Inputs (2)'!AG18+'Inputs (2)'!AG19),('Inputs (2)'!AI18+'Inputs (2)'!AI19))=0,('Inputs (2)'!AI71)=0),"",('Inputs (2)'!AI71)*4/AVERAGE(('Inputs (2)'!AG18+'Inputs (2)'!AG19),('Inputs (2)'!AI18+'Inputs (2)'!AI19))),"") | AJ222: =IFERROR(IF(OR(AVERAGE(('Inputs (2)'!AI18+'Inputs (2)'!AI19),('Inputs (2)'!AJ18+'Inputs (2)'!AJ19))=0,('Inputs (2)'!AJ71)=0),"",('Inputs (2)'!AJ71)*4/AVERAGE(('Inputs (2)'!AI18+'Inputs (2)'!AI19),('Inputs (2)'!AJ18+'Inputs (2)'!AJ19))),"") | AK222: =IFERROR(IF(OR(AVERAGE(('Inputs (2)'!AJ18+'Inputs (2)'!AJ19),('Inputs (2)'!AK18+'Inputs (2)'!AK19))=0,('Inputs (2)'!AK71)=0),"",('Inputs (2)'!AK71)*4/AVERAGE(('Inputs (2)'!AJ18+'Inputs (2)'!AJ19),('Inputs (2)'!AK18+'Inputs (2)'!AK19))),"") | AL222: =IFERROR(IF(OR(AVERAGE(('Inputs (2)'!AK18+'Inputs (2)'!AK19),('Inputs (2)'!AL18+'Inputs (2)'!AL19))=0,('Inputs (2)'!AL71)=0),"",('Inputs (2)'!AL71)*4/AVERAGE(('Inputs (2)'!AK18+'Inputs (2)'!AK19),('Inputs (2)'!AL18+'Inputs (2)'!AL19))),"") | AM222: =IFERROR(IF(OR(AVERAGE(('Inputs (2)'!AH18+'Inputs (2)'!AH19),('Inputs (2)'!AM18+'Inputs (2)'!AM19))=0,('Inputs (2)'!AM71)=0),"",('Inputs (2)'!AM71)/AVERAGE(('Inputs (2)'!AH18+'Inputs (2)'!AH19),('Inputs (2)'!AM18+'Inputs (2)'!AM19))),"") | AN222: =IFERROR(IF(OR(AVERAGE(('Inputs (2)'!AL18+'Inputs (2)'!AL19),('Inputs (2)'!AN18+'Inputs (2)'!AN19))=0,('Inputs (2)'!AN71)=0),"",('Inputs (2)'!AN71)*4/AVERAGE(('Inputs (2)'!AL18+'Inputs (2)'!AL19),('Inputs (2)'!AN18+'Inputs (2)'!AN19))),"") | AO222: =IFERROR(IF(OR(AVERAGE(('Inputs (2)'!AN18+'Inputs (2)'!AN19),('Inputs (2)'!AO18+'Inputs (2)'!AO19))=0,('Inputs (2)'!AO71)=0),"",('Inputs (2)'!AO71)*4/AVERAGE(('Inputs (2)'!AN18+'Inputs (2)'!AN19),('Inputs (2)'!AO18+'Inputs (2)'!AO19))),"") | AP222: =IFERROR(IF(OR(AVERAGE(('Inputs (2)'!AO18+'Inputs (2)'!AO19),('Inputs (2)'!AP18+'Inputs (2)'!AP19))=0,('Inputs (2)'!AP71)=0),"",('Inputs (2)'!AP71)*4/AVERAGE(('Inputs (2)'!AO18+'Inputs (2)'!AO19),('Inputs (2)'!AP18+'Inputs (2)'!AP19))),"") | AQ222: =IFERROR(IF(OR(AVERAGE(('Inputs (2)'!AP18+'Inputs (2)'!AP19),('Inputs (2)'!AQ18+'Inputs (2)'!AQ19))=0,('Inputs (2)'!AQ71)=0),"",('Inputs (2)'!AQ71)*4/AVERAGE(('Inputs (2)'!AP18+'Inputs (2)'!AP19),('Inputs (2)'!AQ18+'Inputs (2)'!AQ19))),"") | AR222: =IFERROR(IF(OR(AVERAGE(('Inputs (2)'!AM18+'Inputs (2)'!AM19),('Inputs (2)'!AR18+'Inputs (2)'!AR19))=0,('Inputs (2)'!AR71)=0),"",('Inputs (2)'!AR71)/AVERAGE(('Inputs (2)'!AM18+'Inputs (2)'!AM19),('Inputs (2)'!AR18+'Inputs (2)'!AR19))),"") | AS222: =IFERROR(IF(OR(AVERAGE(('Inputs (2)'!AQ18+'Inputs (2)'!AQ19),('Inputs (2)'!AS18+'Inputs (2)'!AS19))=0,('Inputs (2)'!AS71)=0),"",('Inputs (2)'!AS71)*4/AVERAGE(('Inputs (2)'!AQ18+'Inputs (2)'!AQ19),('Inputs (2)'!AS18+'Inputs (2)'!AS19))),"") | AT222: =IFERROR(IF(OR(AVERAGE(('Inputs (2)'!AS18+'Inputs (2)'!AS19),('Inputs (2)'!AT18+'Inputs (2)'!AT19))=0,('Inputs (2)'!AT71)=0),"",('Inputs (2)'!AT71)*4/AVERAGE(('Inputs (2)'!AS18+'Inputs (2)'!AS19),('Inputs (2)'!AT18+'Inputs (2)'!AT19))),"") | AU222: =IFERROR(IF(OR(AVERAGE(('Inputs (2)'!AT18+'Inputs (2)'!AT19),('Inputs (2)'!AU18+'Inputs (2)'!AU19))=0,('Inputs (2)'!AU71)=0),"",('Inputs (2)'!AU71)*4/AVERAGE(('Inputs (2)'!AT18+'Inputs (2)'!AT19),('Inputs (2)'!AU18+'Inputs (2)'!AU19))),"") | AV222: =IFERROR(IF(OR(AVERAGE(('Inputs (2)'!AU18+'Inputs (2)'!AU19),('Inputs (2)'!AV18+'Inputs (2)'!AV19))=0,('Inputs (2)'!AV71)=0),"",('Inputs (2)'!AV71)*4/AVERAGE(('Inputs (2)'!AU18+'Inputs (2)'!AU19),('Inputs (2)'!AV18+'Inputs (2)'!AV19))),"") | AW222: =IFERROR(IF(OR(AVERAGE(('Inputs (2)'!AR18+'Inputs (2)'!AR19),('Inputs (2)'!AW18+'Inputs (2)'!AW19))=0,('Inputs (2)'!AW71)=0),"",('Inputs (2)'!AW71)/AVERAGE(('Inputs (2)'!AR18+'Inputs (2)'!AR19),('Inputs (2)'!AW18+'Inputs (2)'!AW19))),"") | AX222: =IFERROR(IF(OR(AVERAGE(('Inputs (2)'!AV18+'Inputs (2)'!AV19),('Inputs (2)'!AX18+'Inputs (2)'!AX19))=0,('Inputs (2)'!AX71)=0),"",('Inputs (2)'!AX71)*4/AVERAGE(('Inputs (2)'!AV18+'Inputs (2)'!AV19),('Inputs (2)'!AX18+'Inputs (2)'!AX19))),"") | AY222: =IFERROR(IF(OR(AVERAGE(('Inputs (2)'!AX18+'Inputs (2)'!AX19),('Inputs (2)'!AY18+'Inputs (2)'!AY19))=0,('Inputs (2)'!AY71)=0),"",('Inputs (2)'!AY71)*4/AVERAGE(('Inputs (2)'!AX18+'Inputs (2)'!AX19),('Inputs (2)'!AY18+'Inputs (2)'!AY19))),"") | AZ222: =IFERROR(IF(OR(AVERAGE(('Inputs (2)'!AY18+'Inputs (2)'!AY19),('Inputs (2)'!AZ18+'Inputs (2)'!AZ19))=0,('Inputs (2)'!AZ71)=0),"",('Inputs (2)'!AZ71)*4/AVERAGE(('Inputs (2)'!AY18+'Inputs (2)'!AY19),('Inputs (2)'!AZ18+'Inputs (2)'!AZ19))),"") | BA222: =IFERROR(IF(OR(AVERAGE(('Inputs (2)'!AZ18+'Inputs (2)'!AZ19),('Inputs (2)'!BA18+'Inputs (2)'!BA19))=0,('Inputs (2)'!BA71)=0),"",('Inputs (2)'!BA71)*4/AVERAGE(('Inputs (2)'!AZ18+'Inputs (2)'!AZ19),('Inputs (2)'!BA18+'Inputs (2)'!BA19))),"") | BB222: =IFERROR(IF(OR(AVERAGE(('Inputs (2)'!AW18+'Inputs (2)'!AW19),('Inputs (2)'!BB18+'Inputs (2)'!BB19))=0,('Inputs (2)'!BB71)=0),"",('Inputs (2)'!BB71)/AVERAGE(('Inputs (2)'!AW18+'Inputs (2)'!AW19),('Inputs (2)'!BB18+'Inputs (2)'!BB19))),"") | BC222: =IFERROR(IF(OR(AVERAGE(('Inputs (2)'!BA18+'Inputs (2)'!BA19),('Inputs (2)'!BC18+'Inputs (2)'!BC19))=0,('Inputs (2)'!BC71)=0),"",('Inputs (2)'!BC71)*4/AVERAGE(('Inputs (2)'!BA18+'Inputs (2)'!BA19),('Inputs (2)'!BC18+'Inputs (2)'!BC19))),"") | BD222: =IFERROR(IF(OR(AVERAGE(('Inputs (2)'!BC18+'Inputs (2)'!BC19),('Inputs (2)'!BD18+'Inputs (2)'!BD19))=0,('Inputs (2)'!BD71)=0),"",('Inputs (2)'!BD71)*4/AVERAGE(('Inputs (2)'!BC18+'Inputs (2)'!BC19),('Inputs (2)'!BD18+'Inputs (2)'!BD19))),"") | BE222: =IFERROR(IF(OR(AVERAGE(('Inputs (2)'!BD18+'Inputs (2)'!BD19),('Inputs (2)'!BE18+'Inputs (2)'!BE19))=0,('Inputs (2)'!BE71)=0),"",('Inputs (2)'!BE71)*4/AVERAGE(('Inputs (2)'!BD18+'Inputs (2)'!BD19),('Inputs (2)'!BE18+'Inputs (2)'!BE19))),"") | BF222: =IFERROR(IF(OR(AVERAGE(('Inputs (2)'!BE18+'Inputs (2)'!BE19),('Inputs (2)'!BF18+'Inputs (2)'!BF19))=0,('Inputs (2)'!BF71)=0),"",('Inputs (2)'!BF71)*4/AVERAGE(('Inputs (2)'!BE18+'Inputs (2)'!BE19),('Inputs (2)'!BF18+'Inputs (2)'!BF19))),"") | BG222: =IFERROR(IF(OR(AVERAGE(('Inputs (2)'!BB18+'Inputs (2)'!BB19),('Inputs (2)'!BG18+'Inputs (2)'!BG19))=0,('Inputs (2)'!BG71)=0),"",('Inputs (2)'!BG71)/AVERAGE(('Inputs (2)'!BB18+'Inputs (2)'!BB19),('Inputs (2)'!BG18+'Inputs (2)'!BG19))),"")
C223: Custo do crédito (% da carteira média, a.a.) | D223: Cost of risk | E223: =IFERROR(IF(OR(ABS(('Inputs (2)'!E18+'Inputs (2)'!E19))=0,('Inputs (2)'!E82)=0),"",ABS('Inputs (2)'!E82)*4/ABS(('Inputs (2)'!E18+'Inputs (2)'!E19))),"") | F223: =IFERROR(IF(OR(ABS(AVERAGE(('Inputs (2)'!E18+'Inputs (2)'!E19),('Inputs (2)'!F18+'Inputs (2)'!F19)))=0,('Inputs (2)'!F82)=0),"",ABS('Inputs (2)'!F82)*4/ABS(AVERAGE(('Inputs (2)'!E18+'Inputs (2)'!E19),('Inputs (2)'!F18+'Inputs (2)'!F19)))),"") | G223: =IFERROR(IF(OR(ABS(AVERAGE(('Inputs (2)'!F18+'Inputs (2)'!F19),('Inputs (2)'!G18+'Inputs (2)'!G19)))=0,('Inputs (2)'!G82)=0),"",ABS('Inputs (2)'!G82)*4/ABS(AVERAGE(('Inputs (2)'!F18+'Inputs (2)'!F19),('Inputs (2)'!G18+'Inputs (2)'!G19)))),"") | H223: =IFERROR(IF(OR(ABS(AVERAGE(('Inputs (2)'!G18+'Inputs (2)'!G19),('Inputs (2)'!H18+'Inputs (2)'!H19)))=0,('Inputs (2)'!H82)=0),"",ABS('Inputs (2)'!H82)*4/ABS(AVERAGE(('Inputs (2)'!G18+'Inputs (2)'!G19),('Inputs (2)'!H18+'Inputs (2)'!H19)))),"") | I223: =IFERROR(IF(OR(ABS(('Inputs (2)'!I18+'Inputs (2)'!I19))=0,('Inputs (2)'!I82)=0),"",ABS('Inputs (2)'!I82)/ABS(('Inputs (2)'!I18+'Inputs (2)'!I19))),"") | J223: =IFERROR(IF(OR(ABS(AVERAGE(('Inputs (2)'!H18+'Inputs (2)'!H19),('Inputs (2)'!J18+'Inputs (2)'!J19)))=0,('Inputs (2)'!J82)=0),"",ABS('Inputs (2)'!J82)*4/ABS(AVERAGE(('Inputs (2)'!H18+'Inputs (2)'!H19),('Inputs (2)'!J18+'Inputs (2)'!J19)))),"") | K223: =IFERROR(IF(OR(ABS(AVERAGE(('Inputs (2)'!J18+'Inputs (2)'!J19),('Inputs (2)'!K18+'Inputs (2)'!K19)))=0,('Inputs (2)'!K82)=0),"",ABS('Inputs (2)'!K82)*4/ABS(AVERAGE(('Inputs (2)'!J18+'Inputs (2)'!J19),('Inputs (2)'!K18+'Inputs (2)'!K19)))),"") | L223: =IFERROR(IF(OR(ABS(AVERAGE(('Inputs (2)'!K18+'Inputs (2)'!K19),('Inputs (2)'!L18+'Inputs (2)'!L19)))=0,('Inputs (2)'!L82)=0),"",ABS('Inputs (2)'!L82)*4/ABS(AVERAGE(('Inputs (2)'!K18+'Inputs (2)'!K19),('Inputs (2)'!L18+'Inputs (2)'!L19)))),"") | M223: =IFERROR(IF(OR(ABS(AVERAGE(('Inputs (2)'!L18+'Inputs (2)'!L19),('Inputs (2)'!M18+'Inputs (2)'!M19)))=0,('Inputs (2)'!M82)=0),"",ABS('Inputs (2)'!M82)*4/ABS(AVERAGE(('Inputs (2)'!L18+'Inputs (2)'!L19),('Inputs (2)'!M18+'Inputs (2)'!M19)))),"") | N223: =IFERROR(IF(OR(ABS(AVERAGE(('Inputs (2)'!I18+'Inputs (2)'!I19),('Inputs (2)'!N18+'Inputs (2)'!N19)))=0,('Inputs (2)'!N82)=0),"",ABS('Inputs (2)'!N82)/ABS(AVERAGE(('Inputs (2)'!I18+'Inputs (2)'!I19),('Inputs (2)'!N18+'Inputs (2)'!N19)))),"") | O223: =IFERROR(IF(OR(ABS(AVERAGE(('Inputs (2)'!M18+'Inputs (2)'!M19),('Inputs (2)'!O18+'Inputs (2)'!O19)))=0,('Inputs (2)'!O82)=0),"",ABS('Inputs (2)'!O82)*4/ABS(AVERAGE(('Inputs (2)'!M18+'Inputs (2)'!M19),('Inputs (2)'!O18+'Inputs (2)'!O19)))),"") | P223: =IFERROR(IF(OR(ABS(AVERAGE(('Inputs (2)'!O18+'Inputs (2)'!O19),('Inputs (2)'!P18+'Inputs (2)'!P19)))=0,('Inputs (2)'!P82)=0),"",ABS('Inputs (2)'!P82)*4/ABS(AVERAGE(('Inputs (2)'!O18+'Inputs (2)'!O19),('Inputs (2)'!P18+'Inputs (2)'!P19)))),"") | Q223: =IFERROR(IF(OR(ABS(AVERAGE(('Inputs (2)'!P18+'Inputs (2)'!P19),('Inputs (2)'!Q18+'Inputs (2)'!Q19)))=0,('Inputs (2)'!Q82)=0),"",ABS('Inputs (2)'!Q82)*4/ABS(AVERAGE(('Inputs (2)'!P18+'Inputs (2)'!P19),('Inputs (2)'!Q18+'Inputs (2)'!Q19)))),"") | R223: =IFERROR(IF(OR(ABS(AVERAGE(('Inputs (2)'!Q18+'Inputs (2)'!Q19),('Inputs (2)'!R18+'Inputs (2)'!R19)))=0,('Inputs (2)'!R82)=0),"",ABS('Inputs (2)'!R82)*4/ABS(AVERAGE(('Inputs (2)'!Q18+'Inputs (2)'!Q19),('Inputs (2)'!R18+'Inputs (2)'!R19)))),"") | S223: =IFERROR(IF(OR(ABS(AVERAGE(('Inputs (2)'!N18+'Inputs (2)'!N19),('Inputs (2)'!S18+'Inputs (2)'!S19)))=0,('Inputs (2)'!S82)=0),"",ABS('Inputs (2)'!S82)/ABS(AVERAGE(('Inputs (2)'!N18+'Inputs (2)'!N19),('Inputs (2)'!S18+'Inputs (2)'!S19)))),"") | T223: =IFERROR(IF(OR(ABS(AVERAGE(('Inputs (2)'!R18+'Inputs (2)'!R19),('Inputs (2)'!T18+'Inputs (2)'!T19)))=0,('Inputs (2)'!T82)=0),"",ABS('Inputs (2)'!T82)*4/ABS(AVERAGE(('Inputs (2)'!R18+'Inputs (2)'!R19),('Inputs (2)'!T18+'Inputs (2)'!T19)))),"") | U223: =IFERROR(IF(OR(ABS(AVERAGE(('Inputs (2)'!T18+'Inputs (2)'!T19),('Inputs (2)'!U18+'Inputs (2)'!U19)))=0,('Inputs (2)'!U82)=0),"",ABS('Inputs (2)'!U82)*4/ABS(AVERAGE(('Inputs (2)'!T18+'Inputs (2)'!T19),('Inputs (2)'!U18+'Inputs (2)'!U19)))),"") | V223: =IFERROR(IF(OR(ABS(AVERAGE(('Inputs (2)'!U18+'Inputs (2)'!U19),('Inputs (2)'!V18+'Inputs (2)'!V19)))=0,('Inputs (2)'!V82)=0),"",ABS('Inputs (2)'!V82)*4/ABS(AVERAGE(('Inputs (2)'!U18+'Inputs (2)'!U19),('Inputs (2)'!V18+'Inputs (2)'!V19)))),"") | W223: =IFERROR(IF(OR(ABS(AVERAGE(('Inputs (2)'!V18+'Inputs (2)'!V19),('Inputs (2)'!W18+'Inputs (2)'!W19)))=0,('Inputs (2)'!W82)=0),"",ABS('Inputs (2)'!W82)*4/ABS(AVERAGE(('Inputs (2)'!V18+'Inputs (2)'!V19),('Inputs (2)'!W18+'Inputs (2)'!W19)))),"") | X223: =IFERROR(IF(OR(ABS(AVERAGE(('Inputs (2)'!S18+'Inputs (2)'!S19),('Inputs (2)'!X18+'Inputs (2)'!X19)))=0,('Inputs (2)'!X82)=0),"",ABS('Inputs (2)'!X82)/ABS(AVERAGE(('Inputs (2)'!S18+'Inputs (2)'!S19),('Inputs (2)'!X18+'Inputs (2)'!X19)))),"") | Y223: =IFERROR(IF(OR(ABS(AVERAGE(('Inputs (2)'!W18+'Inputs (2)'!W19),('Inputs (2)'!Y18+'Inputs (2)'!Y19)))=0,('Inputs (2)'!Y82)=0),"",ABS('Inputs (2)'!Y82)*4/ABS(AVERAGE(('Inputs (2)'!W18+'Inputs (2)'!W19),('Inputs (2)'!Y18+'Inputs (2)'!Y19)))),"") | Z223: =IFERROR(IF(OR(ABS(AVERAGE(('Inputs (2)'!Y18+'Inputs (2)'!Y19),('Inputs (2)'!Z18+'Inputs (2)'!Z19)))=0,('Inputs (2)'!Z82)=0),"",ABS('Inputs (2)'!Z82)*4/ABS(AVERAGE(('Inputs (2)'!Y18+'Inputs (2)'!Y19),('Inputs (2)'!Z18+'Inputs (2)'!Z19)))),"") | AA223: =IFERROR(IF(OR(ABS(AVERAGE(('Inputs (2)'!Z18+'Inputs (2)'!Z19),('Inputs (2)'!AA18+'Inputs (2)'!AA19)))=0,('Inputs (2)'!AA82)=0),"",ABS('Inputs (2)'!AA82)*4/ABS(AVERAGE(('Inputs (2)'!Z18+'Inputs (2)'!Z19),('Inputs (2)'!AA18+'Inputs (2)'!AA19)))),"") | AB223: =IFERROR(IF(OR(ABS(AVERAGE(('Inputs (2)'!AA18+'Inputs (2)'!AA19),('Inputs (2)'!AB18+'Inputs (2)'!AB19)))=0,('Inputs (2)'!AB82)=0),"",ABS('Inputs (2)'!AB82)*4/ABS(AVERAGE(('Inputs (2)'!AA18+'Inputs (2)'!AA19),('Inputs (2)'!AB18+'Inputs (2)'!AB19)))),"") | AC223: =IFERROR(IF(OR(ABS(AVERAGE(('Inputs (2)'!X18+'Inputs (2)'!X19),('Inputs (2)'!AC18+'Inputs (2)'!AC19)))=0,('Inputs (2)'!AC82)=0),"",ABS('Inputs (2)'!AC82)/ABS(AVERAGE(('Inputs (2)'!X18+'Inputs (2)'!X19),('Inputs (2)'!AC18+'Inputs (2)'!AC19)))),"") | AD223: =IFERROR(IF(OR(ABS(AVERAGE(('Inputs (2)'!AB18+'Inputs (2)'!AB19),('Inputs (2)'!AD18+'Inputs (2)'!AD19)))=0,('Inputs (2)'!AD82)=0),"",ABS('Inputs (2)'!AD82)*4/ABS(AVERAGE(('Inputs (2)'!AB18+'Inputs (2)'!AB19),('Inputs (2)'!AD18+'Inputs (2)'!AD19)))),"") | AE223: =IFERROR(IF(OR(ABS(AVERAGE(('Inputs (2)'!AD18+'Inputs (2)'!AD19),('Inputs (2)'!AE18+'Inputs (2)'!AE19)))=0,('Inputs (2)'!AE82)=0),"",ABS('Inputs (2)'!AE82)*4/ABS(AVERAGE(('Inputs (2)'!AD18+'Inputs (2)'!AD19),('Inputs (2)'!AE18+'Inputs (2)'!AE19)))),"") | AF223: =IFERROR(IF(OR(ABS(AVERAGE(('Inputs (2)'!AE18+'Inputs (2)'!AE19),('Inputs (2)'!AF18+'Inputs (2)'!AF19)))=0,('Inputs (2)'!AF82)=0),"",ABS('Inputs (2)'!AF82)*4/ABS(AVERAGE(('Inputs (2)'!AE18+'Inputs (2)'!AE19),('Inputs (2)'!AF18+'Inputs (2)'!AF19)))),"") | AG223: =IFERROR(IF(OR(ABS(AVERAGE(('Inputs (2)'!AF18+'Inputs (2)'!AF19),('Inputs (2)'!AG18+'Inputs (2)'!AG19)))=0,('Inputs (2)'!AG82)=0),"",ABS('Inputs (2)'!AG82)*4/ABS(AVERAGE(('Inputs (2)'!AF18+'Inputs (2)'!AF19),('Inputs (2)'!AG18+'Inputs (2)'!AG19)))),"") | AH223: =IFERROR(IF(OR(ABS(AVERAGE(('Inputs (2)'!AC18+'Inputs (2)'!AC19),('Inputs (2)'!AH18+'Inputs (2)'!AH19)))=0,('Inputs (2)'!AH82)=0),"",ABS('Inputs (2)'!AH82)/ABS(AVERAGE(('Inputs (2)'!AC18+'Inputs (2)'!AC19),('Inputs (2)'!AH18+'Inputs (2)'!AH19)))),"") | AI223: =IFERROR(IF(OR(ABS(AVERAGE(('Inputs (2)'!AG18+'Inputs (2)'!AG19),('Inputs (2)'!AI18+'Inputs (2)'!AI19)))=0,('Inputs (2)'!AI82)=0),"",ABS('Inputs (2)'!AI82)*4/ABS(AVERAGE(('Inputs (2)'!AG18+'Inputs (2)'!AG19),('Inputs (2)'!AI18+'Inputs (2)'!AI19)))),"") | AJ223: =IFERROR(IF(OR(ABS(AVERAGE(('Inputs (2)'!AI18+'Inputs (2)'!AI19),('Inputs (2)'!AJ18+'Inputs (2)'!AJ19)))=0,('Inputs (2)'!AJ82)=0),"",ABS('Inputs (2)'!AJ82)*4/ABS(AVERAGE(('Inputs (2)'!AI18+'Inputs (2)'!AI19),('Inputs (2)'!AJ18+'Inputs (2)'!AJ19)))),"") | AK223: =IFERROR(IF(OR(ABS(AVERAGE(('Inputs (2)'!AJ18+'Inputs (2)'!AJ19),('Inputs (2)'!AK18+'Inputs (2)'!AK19)))=0,('Inputs (2)'!AK82)=0),"",ABS('Inputs (2)'!AK82)*4/ABS(AVERAGE(('Inputs (2)'!AJ18+'Inputs (2)'!AJ19),('Inputs (2)'!AK18+'Inputs (2)'!AK19)))),"") | AL223: =IFERROR(IF(OR(ABS(AVERAGE(('Inputs (2)'!AK18+'Inputs (2)'!AK19),('Inputs (2)'!AL18+'Inputs (2)'!AL19)))=0,('Inputs (2)'!AL82)=0),"",ABS('Inputs (2)'!AL82)*4/ABS(AVERAGE(('Inputs (2)'!AK18+'Inputs (2)'!AK19),('Inputs (2)'!AL18+'Inputs (2)'!AL19)))),"") | AM223: =IFERROR(IF(OR(ABS(AVERAGE(('Inputs (2)'!AH18+'Inputs (2)'!AH19),('Inputs (2)'!AM18+'Inputs (2)'!AM19)))=0,('Inputs (2)'!AM82)=0),"",ABS('Inputs (2)'!AM82)/ABS(AVERAGE(('Inputs (2)'!AH18+'Inputs (2)'!AH19),('Inputs (2)'!AM18+'Inputs (2)'!AM19)))),"") | AN223: =IFERROR(IF(OR(ABS(AVERAGE(('Inputs (2)'!AL18+'Inputs (2)'!AL19),('Inputs (2)'!AN18+'Inputs (2)'!AN19)))=0,('Inputs (2)'!AN82)=0),"",ABS('Inputs (2)'!AN82)*4/ABS(AVERAGE(('Inputs (2)'!AL18+'Inputs (2)'!AL19),('Inputs (2)'!AN18+'Inputs (2)'!AN19)))),"") | AO223: =IFERROR(IF(OR(ABS(AVERAGE(('Inputs (2)'!AN18+'Inputs (2)'!AN19),('Inputs (2)'!AO18+'Inputs (2)'!AO19)))=0,('Inputs (2)'!AO82)=0),"",ABS('Inputs (2)'!AO82)*4/ABS(AVERAGE(('Inputs (2)'!AN18+'Inputs (2)'!AN19),('Inputs (2)'!AO18+'Inputs (2)'!AO19)))),"") | AP223: =IFERROR(IF(OR(ABS(AVERAGE(('Inputs (2)'!AO18+'Inputs (2)'!AO19),('Inputs (2)'!AP18+'Inputs (2)'!AP19)))=0,('Inputs (2)'!AP82)=0),"",ABS('Inputs (2)'!AP82)*4/ABS(AVERAGE(('Inputs (2)'!AO18+'Inputs (2)'!AO19),('Inputs (2)'!AP18+'Inputs (2)'!AP19)))),"") | AQ223: =IFERROR(IF(OR(ABS(AVERAGE(('Inputs (2)'!AP18+'Inputs (2)'!AP19),('Inputs (2)'!AQ18+'Inputs (2)'!AQ19)))=0,('Inputs (2)'!AQ82)=0),"",ABS('Inputs (2)'!AQ82)*4/ABS(AVERAGE(('Inputs (2)'!AP18+'Inputs (2)'!AP19),('Inputs (2)'!AQ18+'Inputs (2)'!AQ19)))),"") | AR223: =IFERROR(IF(OR(ABS(AVERAGE(('Inputs (2)'!AM18+'Inputs (2)'!AM19),('Inputs (2)'!AR18+'Inputs (2)'!AR19)))=0,('Inputs (2)'!AR82)=0),"",ABS('Inputs (2)'!AR82)/ABS(AVERAGE(('Inputs (2)'!AM18+'Inputs (2)'!AM19),('Inputs (2)'!AR18+'Inputs (2)'!AR19)))),"") | AS223: =IFERROR(IF(OR(ABS(AVERAGE(('Inputs (2)'!AQ18+'Inputs (2)'!AQ19),('Inputs (2)'!AS18+'Inputs (2)'!AS19)))=0,('Inputs (2)'!AS82)=0),"",ABS('Inputs (2)'!AS82)*4/ABS(AVERAGE(('Inputs (2)'!AQ18+'Inputs (2)'!AQ19),('Inputs (2)'!AS18+'Inputs (2)'!AS19)))),"") | AT223: =IFERROR(IF(OR(ABS(AVERAGE(('Inputs (2)'!AS18+'Inputs (2)'!AS19),('Inputs (2)'!AT18+'Inputs (2)'!AT19)))=0,('Inputs (2)'!AT82)=0),"",ABS('Inputs (2)'!AT82)*4/ABS(AVERAGE(('Inputs (2)'!AS18+'Inputs (2)'!AS19),('Inputs (2)'!AT18+'Inputs (2)'!AT19)))),"") | AU223: =IFERROR(IF(OR(ABS(AVERAGE(('Inputs (2)'!AT18+'Inputs (2)'!AT19),('Inputs (2)'!AU18+'Inputs (2)'!AU19)))=0,('Inputs (2)'!AU82)=0),"",ABS('Inputs (2)'!AU82)*4/ABS(AVERAGE(('Inputs (2)'!AT18+'Inputs (2)'!AT19),('Inputs (2)'!AU18+'Inputs (2)'!AU19)))),"") | AV223: =IFERROR(IF(OR(ABS(AVERAGE(('Inputs (2)'!AU18+'Inputs (2)'!AU19),('Inputs (2)'!AV18+'Inputs (2)'!AV19)))=0,('Inputs (2)'!AV82)=0),"",ABS('Inputs (2)'!AV82)*4/ABS(AVERAGE(('Inputs (2)'!AU18+'Inputs (2)'!AU19),('Inputs (2)'!AV18+'Inputs (2)'!AV19)))),"") | AW223: =IFERROR(IF(OR(ABS(AVERAGE(('Inputs (2)'!AR18+'Inputs (2)'!AR19),('Inputs (2)'!AW18+'Inputs (2)'!AW19)))=0,('Inputs (2)'!AW82)=0),"",ABS('Inputs (2)'!AW82)/ABS(AVERAGE(('Inputs (2)'!AR18+'Inputs (2)'!AR19),('Inputs (2)'!AW18+'Inputs (2)'!AW19)))),"") | AX223: =IFERROR(IF(OR(ABS(AVERAGE(('Inputs (2)'!AV18+'Inputs (2)'!AV19),('Inputs (2)'!AX18+'Inputs (2)'!AX19)))=0,('Inputs (2)'!AX82)=0),"",ABS('Inputs (2)'!AX82)*4/ABS(AVERAGE(('Inputs (2)'!AV18+'Inputs (2)'!AV19),('Inputs (2)'!AX18+'Inputs (2)'!AX19)))),"") | AY223: =IFERROR(IF(OR(ABS(AVERAGE(('Inputs (2)'!AX18+'Inputs (2)'!AX19),('Inputs (2)'!AY18+'Inputs (2)'!AY19)))=0,('Inputs (2)'!AY82)=0),"",ABS('Inputs (2)'!AY82)*4/ABS(AVERAGE(('Inputs (2)'!AX18+'Inputs (2)'!AX19),('Inputs (2)'!AY18+'Inputs (2)'!AY19)))),"") | AZ223: =IFERROR(IF(OR(ABS(AVERAGE(('Inputs (2)'!AY18+'Inputs (2)'!AY19),('Inputs (2)'!AZ18+'Inputs (2)'!AZ19)))=0,('Inputs (2)'!AZ82)=0),"",ABS('Inputs (2)'!AZ82)*4/ABS(AVERAGE(('Inputs (2)'!AY18+'Inputs (2)'!AY19),('Inputs (2)'!AZ18+'Inputs (2)'!AZ19)))),"") | BA223: =IFERROR(IF(OR(ABS(AVERAGE(('Inputs (2)'!AZ18+'Inputs (2)'!AZ19),('Inputs (2)'!BA18+'Inputs (2)'!BA19)))=0,('Inputs (2)'!BA82)=0),"",ABS('Inputs (2)'!BA82)*4/ABS(AVERAGE(('Inputs (2)'!AZ18+'Inputs (2)'!AZ19),('Inputs (2)'!BA18+'Inputs (2)'!BA19)))),"") | BB223: =IFERROR(IF(OR(ABS(AVERAGE(('Inputs (2)'!AW18+'Inputs (2)'!AW19),('Inputs (2)'!BB18+'Inputs (2)'!BB19)))=0,('Inputs (2)'!BB82)=0),"",ABS('Inputs (2)'!BB82)/ABS(AVERAGE(('Inputs (2)'!AW18+'Inputs (2)'!AW19),('Inputs (2)'!BB18+'Inputs (2)'!BB19)))),"") | BC223: =IFERROR(IF(OR(ABS(AVERAGE(('Inputs (2)'!BA18+'Inputs (2)'!BA19),('Inputs (2)'!BC18+'Inputs (2)'!BC19)))=0,('Inputs (2)'!BC82)=0),"",ABS('Inputs (2)'!BC82)*4/ABS(AVERAGE(('Inputs (2)'!BA18+'Inputs (2)'!BA19),('Inputs (2)'!BC18+'Inputs (2)'!BC19)))),"") | BD223: =IFERROR(IF(OR(ABS(AVERAGE(('Inputs (2)'!BC18+'Inputs (2)'!BC19),('Inputs (2)'!BD18+'Inputs (2)'!BD19)))=0,('Inputs (2)'!BD82)=0),"",ABS('Inputs (2)'!BD82)*4/ABS(AVERAGE(('Inputs (2)'!BC18+'Inputs (2)'!BC19),('Inputs (2)'!BD18+'Inputs (2)'!BD19)))),"") | BE223: =IFERROR(IF(OR(ABS(AVERAGE(('Inputs (2)'!BD18+'Inputs (2)'!BD19),('Inputs (2)'!BE18+'Inputs (2)'!BE19)))=0,('Inputs (2)'!BE82)=0),"",ABS('Inputs (2)'!BE82)*4/ABS(AVERAGE(('Inputs (2)'!BD18+'Inputs (2)'!BD19),('Inputs (2)'!BE18+'Inputs (2)'!BE19)))),"") | BF223: =IFERROR(IF(OR(ABS(AVERAGE(('Inputs (2)'!BE18+'Inputs (2)'!BE19),('Inputs (2)'!BF18+'Inputs (2)'!BF19)))=0,('Inputs (2)'!BF82)=0),"",ABS('Inputs (2)'!BF82)*4/ABS(AVERAGE(('Inputs (2)'!BE18+'Inputs (2)'!BE19),('Inputs (2)'!BF18+'Inputs (2)'!BF19)))),"") | BG223: =IFERROR(IF(OR(ABS(AVERAGE(('Inputs (2)'!BB18+'Inputs (2)'!BB19),('Inputs (2)'!BG18+'Inputs (2)'!BG19)))=0,('Inputs (2)'!BG82)=0),"",ABS('Inputs (2)'!BG82)/ABS(AVERAGE(('Inputs (2)'!BB18+'Inputs (2)'!BB19),('Inputs (2)'!BG18+'Inputs (2)'!BG19)))),"")
C224: Write-off (% da carteira média, a.a.) | D224: Write-offs | E224: =IFERROR(IF(OR(ABS(('Inputs (2)'!E18+'Inputs (2)'!E19))=0,('Inputs (2)'!E123)=0),"",ABS('Inputs (2)'!E123)*4/ABS(('Inputs (2)'!E18+'Inputs (2)'!E19))),"") | F224: =IFERROR(IF(OR(ABS(AVERAGE(('Inputs (2)'!E18+'Inputs (2)'!E19),('Inputs (2)'!F18+'Inputs (2)'!F19)))=0,('Inputs (2)'!F123)=0),"",ABS('Inputs (2)'!F123)*4/ABS(AVERAGE(('Inputs (2)'!E18+'Inputs (2)'!E19),('Inputs (2)'!F18+'Inputs (2)'!F19)))),"") | G224: =IFERROR(IF(OR(ABS(AVERAGE(('Inputs (2)'!F18+'Inputs (2)'!F19),('Inputs (2)'!G18+'Inputs (2)'!G19)))=0,('Inputs (2)'!G123)=0),"",ABS('Inputs (2)'!G123)*4/ABS(AVERAGE(('Inputs (2)'!F18+'Inputs (2)'!F19),('Inputs (2)'!G18+'Inputs (2)'!G19)))),"") | H224: =IFERROR(IF(OR(ABS(AVERAGE(('Inputs (2)'!G18+'Inputs (2)'!G19),('Inputs (2)'!H18+'Inputs (2)'!H19)))=0,('Inputs (2)'!H123)=0),"",ABS('Inputs (2)'!H123)*4/ABS(AVERAGE(('Inputs (2)'!G18+'Inputs (2)'!G19),('Inputs (2)'!H18+'Inputs (2)'!H19)))),"") | I224: =IFERROR(IF(OR(ABS(('Inputs (2)'!I18+'Inputs (2)'!I19))=0,('Inputs (2)'!I123)=0),"",ABS('Inputs (2)'!I123)/ABS(('Inputs (2)'!I18+'Inputs (2)'!I19))),"") | J224: =IFERROR(IF(OR(ABS(AVERAGE(('Inputs (2)'!H18+'Inputs (2)'!H19),('Inputs (2)'!J18+'Inputs (2)'!J19)))=0,('Inputs (2)'!J123)=0),"",ABS('Inputs (2)'!J123)*4/ABS(AVERAGE(('Inputs (2)'!H18+'Inputs (2)'!H19),('Inputs (2)'!J18+'Inputs (2)'!J19)))),"") | K224: =IFERROR(IF(OR(ABS(AVERAGE(('Inputs (2)'!J18+'Inputs (2)'!J19),('Inputs (2)'!K18+'Inputs (2)'!K19)))=0,('Inputs (2)'!K123)=0),"",ABS('Inputs (2)'!K123)*4/ABS(AVERAGE(('Inputs (2)'!J18+'Inputs (2)'!J19),('Inputs (2)'!K18+'Inputs (2)'!K19)))),"") | L224: =IFERROR(IF(OR(ABS(AVERAGE(('Inputs (2)'!K18+'Inputs (2)'!K19),('Inputs (2)'!L18+'Inputs (2)'!L19)))=0,('Inputs (2)'!L123)=0),"",ABS('Inputs (2)'!L123)*4/ABS(AVERAGE(('Inputs (2)'!K18+'Inputs (2)'!K19),('Inputs (2)'!L18+'Inputs (2)'!L19)))),"") | M224: =IFERROR(IF(OR(ABS(AVERAGE(('Inputs (2)'!L18+'Inputs (2)'!L19),('Inputs (2)'!M18+'Inputs (2)'!M19)))=0,('Inputs (2)'!M123)=0),"",ABS('Inputs (2)'!M123)*4/ABS(AVERAGE(('Inputs (2)'!L18+'Inputs (2)'!L19),('Inputs (2)'!M18+'Inputs (2)'!M19)))),"") | N224: =IFERROR(IF(OR(ABS(AVERAGE(('Inputs (2)'!I18+'Inputs (2)'!I19),('Inputs (2)'!N18+'Inputs (2)'!N19)))=0,('Inputs (2)'!N123)=0),"",ABS('Inputs (2)'!N123)/ABS(AVERAGE(('Inputs (2)'!I18+'Inputs (2)'!I19),('Inputs (2)'!N18+'Inputs (2)'!N19)))),"") | O224: =IFERROR(IF(OR(ABS(AVERAGE(('Inputs (2)'!M18+'Inputs (2)'!M19),('Inputs (2)'!O18+'Inputs (2)'!O19)))=0,('Inputs (2)'!O123)=0),"",ABS('Inputs (2)'!O123)*4/ABS(AVERAGE(('Inputs (2)'!M18+'Inputs (2)'!M19),('Inputs (2)'!O18+'Inputs (2)'!O19)))),"") | P224: =IFERROR(IF(OR(ABS(AVERAGE(('Inputs (2)'!O18+'Inputs (2)'!O19),('Inputs (2)'!P18+'Inputs (2)'!P19)))=0,('Inputs (2)'!P123)=0),"",ABS('Inputs (2)'!P123)*4/ABS(AVERAGE(('Inputs (2)'!O18+'Inputs (2)'!O19),('Inputs (2)'!P18+'Inputs (2)'!P19)))),"") | Q224: =IFERROR(IF(OR(ABS(AVERAGE(('Inputs (2)'!P18+'Inputs (2)'!P19),('Inputs (2)'!Q18+'Inputs (2)'!Q19)))=0,('Inputs (2)'!Q123)=0),"",ABS('Inputs (2)'!Q123)*4/ABS(AVERAGE(('Inputs (2)'!P18+'Inputs (2)'!P19),('Inputs (2)'!Q18+'Inputs (2)'!Q19)))),"") | R224: =IFERROR(IF(OR(ABS(AVERAGE(('Inputs (2)'!Q18+'Inputs (2)'!Q19),('Inputs (2)'!R18+'Inputs (2)'!R19)))=0,('Inputs (2)'!R123)=0),"",ABS('Inputs (2)'!R123)*4/ABS(AVERAGE(('Inputs (2)'!Q18+'Inputs (2)'!Q19),('Inputs (2)'!R18+'Inputs (2)'!R19)))),"") | S224: =IFERROR(IF(OR(ABS(AVERAGE(('Inputs (2)'!N18+'Inputs (2)'!N19),('Inputs (2)'!S18+'Inputs (2)'!S19)))=0,('Inputs (2)'!S123)=0),"",ABS('Inputs (2)'!S123)/ABS(AVERAGE(('Inputs (2)'!N18+'Inputs (2)'!N19),('Inputs (2)'!S18+'Inputs (2)'!S19)))),"") | T224: =IFERROR(IF(OR(ABS(AVERAGE(('Inputs (2)'!R18+'Inputs (2)'!R19),('Inputs (2)'!T18+'Inputs (2)'!T19)))=0,('Inputs (2)'!T123)=0),"",ABS('Inputs (2)'!T123)*4/ABS(AVERAGE(('Inputs (2)'!R18+'Inputs (2)'!R19),('Inputs (2)'!T18+'Inputs (2)'!T19)))),"") | U224: =IFERROR(IF(OR(ABS(AVERAGE(('Inputs (2)'!T18+'Inputs (2)'!T19),('Inputs (2)'!U18+'Inputs (2)'!U19)))=0,('Inputs (2)'!U123)=0),"",ABS('Inputs (2)'!U123)*4/ABS(AVERAGE(('Inputs (2)'!T18+'Inputs (2)'!T19),('Inputs (2)'!U18+'Inputs (2)'!U19)))),"") | V224: =IFERROR(IF(OR(ABS(AVERAGE(('Inputs (2)'!U18+'Inputs (2)'!U19),('Inputs (2)'!V18+'Inputs (2)'!V19)))=0,('Inputs (2)'!V123)=0),"",ABS('Inputs (2)'!V123)*4/ABS(AVERAGE(('Inputs (2)'!U18+'Inputs (2)'!U19),('Inputs (2)'!V18+'Inputs (2)'!V19)))),"") | W224: =IFERROR(IF(OR(ABS(AVERAGE(('Inputs (2)'!V18+'Inputs (2)'!V19),('Inputs (2)'!W18+'Inputs (2)'!W19)))=0,('Inputs (2)'!W123)=0),"",ABS('Inputs (2)'!W123)*4/ABS(AVERAGE(('Inputs (2)'!V18+'Inputs (2)'!V19),('Inputs (2)'!W18+'Inputs (2)'!W19)))),"") | X224: =IFERROR(IF(OR(ABS(AVERAGE(('Inputs (2)'!S18+'Inputs (2)'!S19),('Inputs (2)'!X18+'Inputs (2)'!X19)))=0,('Inputs (2)'!X123)=0),"",ABS('Inputs (2)'!X123)/ABS(AVERAGE(('Inputs (2)'!S18+'Inputs (2)'!S19),('Inputs (2)'!X18+'Inputs (2)'!X19)))),"") | Y224: =IFERROR(IF(OR(ABS(AVERAGE(('Inputs (2)'!W18+'Inputs (2)'!W19),('Inputs (2)'!Y18+'Inputs (2)'!Y19)))=0,('Inputs (2)'!Y123)=0),"",ABS('Inputs (2)'!Y123)*4/ABS(AVERAGE(('Inputs (2)'!W18+'Inputs (2)'!W19),('Inputs (2)'!Y18+'Inputs (2)'!Y19)))),"") | Z224: =IFERROR(IF(OR(ABS(AVERAGE(('Inputs (2)'!Y18+'Inputs (2)'!Y19),('Inputs (2)'!Z18+'Inputs (2)'!Z19)))=0,('Inputs (2)'!Z123)=0),"",ABS('Inputs (2)'!Z123)*4/ABS(AVERAGE(('Inputs (2)'!Y18+'Inputs (2)'!Y19),('Inputs (2)'!Z18+'Inputs (2)'!Z19)))),"") | AA224: =IFERROR(IF(OR(ABS(AVERAGE(('Inputs (2)'!Z18+'Inputs (2)'!Z19),('Inputs (2)'!AA18+'Inputs (2)'!AA19)))=0,('Inputs (2)'!AA123)=0),"",ABS('Inputs (2)'!AA123)*4/ABS(AVERAGE(('Inputs (2)'!Z18+'Inputs (2)'!Z19),('Inputs (2)'!AA18+'Inputs (2)'!AA19)))),"") | AB224: =IFERROR(IF(OR(ABS(AVERAGE(('Inputs (2)'!AA18+'Inputs (2)'!AA19),('Inputs (2)'!AB18+'Inputs (2)'!AB19)))=0,('Inputs (2)'!AB123)=0),"",ABS('Inputs (2)'!AB123)*4/ABS(AVERAGE(('Inputs (2)'!AA18+'Inputs (2)'!AA19),('Inputs (2)'!AB18+'Inputs (2)'!AB19)))),"") | AC224: =IFERROR(IF(OR(ABS(AVERAGE(('Inputs (2)'!X18+'Inputs (2)'!X19),('Inputs (2)'!AC18+'Inputs (2)'!AC19)))=0,('Inputs (2)'!AC123)=0),"",ABS('Inputs (2)'!AC123)/ABS(AVERAGE(('Inputs (2)'!X18+'Inputs (2)'!X19),('Inputs (2)'!AC18+'Inputs (2)'!AC19)))),"") | AD224: =IFERROR(IF(OR(ABS(AVERAGE(('Inputs (2)'!AB18+'Inputs (2)'!AB19),('Inputs (2)'!AD18+'Inputs (2)'!AD19)))=0,('Inputs (2)'!AD123)=0),"",ABS('Inputs (2)'!AD123)*4/ABS(AVERAGE(('Inputs (2)'!AB18+'Inputs (2)'!AB19),('Inputs (2)'!AD18+'Inputs (2)'!AD19)))),"") | AE224: =IFERROR(IF(OR(ABS(AVERAGE(('Inputs (2)'!AD18+'Inputs (2)'!AD19),('Inputs (2)'!AE18+'Inputs (2)'!AE19)))=0,('Inputs (2)'!AE123)=0),"",ABS('Inputs (2)'!AE123)*4/ABS(AVERAGE(('Inputs (2)'!AD18+'Inputs (2)'!AD19),('Inputs (2)'!AE18+'Inputs (2)'!AE19)))),"") | AF224: =IFERROR(IF(OR(ABS(AVERAGE(('Inputs (2)'!AE18+'Inputs (2)'!AE19),('Inputs (2)'!AF18+'Inputs (2)'!AF19)))=0,('Inputs (2)'!AF123)=0),"",ABS('Inputs (2)'!AF123)*4/ABS(AVERAGE(('Inputs (2)'!AE18+'Inputs (2)'!AE19),('Inputs (2)'!AF18+'Inputs (2)'!AF19)))),"") | AG224: =IFERROR(IF(OR(ABS(AVERAGE(('Inputs (2)'!AF18+'Inputs (2)'!AF19),('Inputs (2)'!AG18+'Inputs (2)'!AG19)))=0,('Inputs (2)'!AG123)=0),"",ABS('Inputs (2)'!AG123)*4/ABS(AVERAGE(('Inputs (2)'!AF18+'Inputs (2)'!AF19),('Inputs (2)'!AG18+'Inputs (2)'!AG19)))),"") | AH224: =IFERROR(IF(OR(ABS(AVERAGE(('Inputs (2)'!AC18+'Inputs (2)'!AC19),('Inputs (2)'!AH18+'Inputs (2)'!AH19)))=0,('Inputs (2)'!AH123)=0),"",ABS('Inputs (2)'!AH123)/ABS(AVERAGE(('Inputs (2)'!AC18+'Inputs (2)'!AC19),('Inputs (2)'!AH18+'Inputs (2)'!AH19)))),"") | AI224: =IFERROR(IF(OR(ABS(AVERAGE(('Inputs (2)'!AG18+'Inputs (2)'!AG19),('Inputs (2)'!AI18+'Inputs (2)'!AI19)))=0,('Inputs (2)'!AI123)=0),"",ABS('Inputs (2)'!AI123)*4/ABS(AVERAGE(('Inputs (2)'!AG18+'Inputs (2)'!AG19),('Inputs (2)'!AI18+'Inputs (2)'!AI19)))),"") | AJ224: =IFERROR(IF(OR(ABS(AVERAGE(('Inputs (2)'!AI18+'Inputs (2)'!AI19),('Inputs (2)'!AJ18+'Inputs (2)'!AJ19)))=0,('Inputs (2)'!AJ123)=0),"",ABS('Inputs (2)'!AJ123)*4/ABS(AVERAGE(('Inputs (2)'!AI18+'Inputs (2)'!AI19),('Inputs (2)'!AJ18+'Inputs (2)'!AJ19)))),"") | AK224: =IFERROR(IF(OR(ABS(AVERAGE(('Inputs (2)'!AJ18+'Inputs (2)'!AJ19),('Inputs (2)'!AK18+'Inputs (2)'!AK19)))=0,('Inputs (2)'!AK123)=0),"",ABS('Inputs (2)'!AK123)*4/ABS(AVERAGE(('Inputs (2)'!AJ18+'Inputs (2)'!AJ19),('Inputs (2)'!AK18+'Inputs (2)'!AK19)))),"") | AL224: =IFERROR(IF(OR(ABS(AVERAGE(('Inputs (2)'!AK18+'Inputs (2)'!AK19),('Inputs (2)'!AL18+'Inputs (2)'!AL19)))=0,('Inputs (2)'!AL123)=0),"",ABS('Inputs (2)'!AL123)*4/ABS(AVERAGE(('Inputs (2)'!AK18+'Inputs (2)'!AK19),('Inputs (2)'!AL18+'Inputs (2)'!AL19)))),"") | AM224: =IFERROR(IF(OR(ABS(AVERAGE(('Inputs (2)'!AH18+'Inputs (2)'!AH19),('Inputs (2)'!AM18+'Inputs (2)'!AM19)))=0,('Inputs (2)'!AM123)=0),"",ABS('Inputs (2)'!AM123)/ABS(AVERAGE(('Inputs (2)'!AH18+'Inputs (2)'!AH19),('Inputs (2)'!AM18+'Inputs (2)'!AM19)))),"") | AN224: =IFERROR(IF(OR(ABS(AVERAGE(('Inputs (2)'!AL18+'Inputs (2)'!AL19),('Inputs (2)'!AN18+'Inputs (2)'!AN19)))=0,('Inputs (2)'!AN123)=0),"",ABS('Inputs (2)'!AN123)*4/ABS(AVERAGE(('Inputs (2)'!AL18+'Inputs (2)'!AL19),('Inputs (2)'!AN18+'Inputs (2)'!AN19)))),"") | AO224: =IFERROR(IF(OR(ABS(AVERAGE(('Inputs (2)'!AN18+'Inputs (2)'!AN19),('Inputs (2)'!AO18+'Inputs (2)'!AO19)))=0,('Inputs (2)'!AO123)=0),"",ABS('Inputs (2)'!AO123)*4/ABS(AVERAGE(('Inputs (2)'!AN18+'Inputs (2)'!AN19),('Inputs (2)'!AO18+'Inputs (2)'!AO19)))),"") | AP224: =IFERROR(IF(OR(ABS(AVERAGE(('Inputs (2)'!AO18+'Inputs (2)'!AO19),('Inputs (2)'!AP18+'Inputs (2)'!AP19)))=0,('Inputs (2)'!AP123)=0),"",ABS('Inputs (2)'!AP123)*4/ABS(AVERAGE(('Inputs (2)'!AO18+'Inputs (2)'!AO19),('Inputs (2)'!AP18+'Inputs (2)'!AP19)))),"") | AQ224: =IFERROR(IF(OR(ABS(AVERAGE(('Inputs (2)'!AP18+'Inputs (2)'!AP19),('Inputs (2)'!AQ18+'Inputs (2)'!AQ19)))=0,('Inputs (2)'!AQ123)=0),"",ABS('Inputs (2)'!AQ123)*4/ABS(AVERAGE(('Inputs (2)'!AP18+'Inputs (2)'!AP19),('Inputs (2)'!AQ18+'Inputs (2)'!AQ19)))),"") | AR224: =IFERROR(IF(OR(ABS(AVERAGE(('Inputs (2)'!AM18+'Inputs (2)'!AM19),('Inputs (2)'!AR18+'Inputs (2)'!AR19)))=0,('Inputs (2)'!AR123)=0),"",ABS('Inputs (2)'!AR123)/ABS(AVERAGE(('Inputs (2)'!AM18+'Inputs (2)'!AM19),('Inputs (2)'!AR18+'Inputs (2)'!AR19)))),"") | AS224: =IFERROR(IF(OR(ABS(AVERAGE(('Inputs (2)'!AQ18+'Inputs (2)'!AQ19),('Inputs (2)'!AS18+'Inputs (2)'!AS19)))=0,('Inputs (2)'!AS123)=0),"",ABS('Inputs (2)'!AS123)*4/ABS(AVERAGE(('Inputs (2)'!AQ18+'Inputs (2)'!AQ19),('Inputs (2)'!AS18+'Inputs (2)'!AS19)))),"") | AT224: =IFERROR(IF(OR(ABS(AVERAGE(('Inputs (2)'!AS18+'Inputs (2)'!AS19),('Inputs (2)'!AT18+'Inputs (2)'!AT19)))=0,('Inputs (2)'!AT123)=0),"",ABS('Inputs (2)'!AT123)*4/ABS(AVERAGE(('Inputs (2)'!AS18+'Inputs (2)'!AS19),('Inputs (2)'!AT18+'Inputs (2)'!AT19)))),"") | AU224: =IFERROR(IF(OR(ABS(AVERAGE(('Inputs (2)'!AT18+'Inputs (2)'!AT19),('Inputs (2)'!AU18+'Inputs (2)'!AU19)))=0,('Inputs (2)'!AU123)=0),"",ABS('Inputs (2)'!AU123)*4/ABS(AVERAGE(('Inputs (2)'!AT18+'Inputs (2)'!AT19),('Inputs (2)'!AU18+'Inputs (2)'!AU19)))),"") | AV224: =IFERROR(IF(OR(ABS(AVERAGE(('Inputs (2)'!AU18+'Inputs (2)'!AU19),('Inputs (2)'!AV18+'Inputs (2)'!AV19)))=0,('Inputs (2)'!AV123)=0),"",ABS('Inputs (2)'!AV123)*4/ABS(AVERAGE(('Inputs (2)'!AU18+'Inputs (2)'!AU19),('Inputs (2)'!AV18+'Inputs (2)'!AV19)))),"") | AW224: =IFERROR(IF(OR(ABS(AVERAGE(('Inputs (2)'!AR18+'Inputs (2)'!AR19),('Inputs (2)'!AW18+'Inputs (2)'!AW19)))=0,('Inputs (2)'!AW123)=0),"",ABS('Inputs (2)'!AW123)/ABS(AVERAGE(('Inputs (2)'!AR18+'Inputs (2)'!AR19),('Inputs (2)'!AW18+'Inputs (2)'!AW19)))),"") | AX224: =IFERROR(IF(OR(ABS(AVERAGE(('Inputs (2)'!AV18+'Inputs (2)'!AV19),('Inputs (2)'!AX18+'Inputs (2)'!AX19)))=0,('Inputs (2)'!AX123)=0),"",ABS('Inputs (2)'!AX123)*4/ABS(AVERAGE(('Inputs (2)'!AV18+'Inputs (2)'!AV19),('Inputs (2)'!AX18+'Inputs (2)'!AX19)))),"") | AY224: =IFERROR(IF(OR(ABS(AVERAGE(('Inputs (2)'!AX18+'Inputs (2)'!AX19),('Inputs (2)'!AY18+'Inputs (2)'!AY19)))=0,('Inputs (2)'!AY123)=0),"",ABS('Inputs (2)'!AY123)*4/ABS(AVERAGE(('Inputs (2)'!AX18+'Inputs (2)'!AX19),('Inputs (2)'!AY18+'Inputs (2)'!AY19)))),"") | AZ224: =IFERROR(IF(OR(ABS(AVERAGE(('Inputs (2)'!AY18+'Inputs (2)'!AY19),('Inputs (2)'!AZ18+'Inputs (2)'!AZ19)))=0,('Inputs (2)'!AZ123)=0),"",ABS('Inputs (2)'!AZ123)*4/ABS(AVERAGE(('Inputs (2)'!AY18+'Inputs (2)'!AY19),('Inputs (2)'!AZ18+'Inputs (2)'!AZ19)))),"") | BA224: =IFERROR(IF(OR(ABS(AVERAGE(('Inputs (2)'!AZ18+'Inputs (2)'!AZ19),('Inputs (2)'!BA18+'Inputs (2)'!BA19)))=0,('Inputs (2)'!BA123)=0),"",ABS('Inputs (2)'!BA123)*4/ABS(AVERAGE(('Inputs (2)'!AZ18+'Inputs (2)'!AZ19),('Inputs (2)'!BA18+'Inputs (2)'!BA19)))),"") | BB224: =IFERROR(IF(OR(ABS(AVERAGE(('Inputs (2)'!AW18+'Inputs (2)'!AW19),('Inputs (2)'!BB18+'Inputs (2)'!BB19)))=0,('Inputs (2)'!BB123)=0),"",ABS('Inputs (2)'!BB123)/ABS(AVERAGE(('Inputs (2)'!AW18+'Inputs (2)'!AW19),('Inputs (2)'!BB18+'Inputs (2)'!BB19)))),"") | BC224: =IFERROR(IF(OR(ABS(AVERAGE(('Inputs (2)'!BA18+'Inputs (2)'!BA19),('Inputs (2)'!BC18+'Inputs (2)'!BC19)))=0,('Inputs (2)'!BC123)=0),"",ABS('Inputs (2)'!BC123)*4/ABS(AVERAGE(('Inputs (2)'!BA18+'Inputs (2)'!BA19),('Inputs (2)'!BC18+'Inputs (2)'!BC19)))),"") | BD224: =IFERROR(IF(OR(ABS(AVERAGE(('Inputs (2)'!BC18+'Inputs (2)'!BC19),('Inputs (2)'!BD18+'Inputs (2)'!BD19)))=0,('Inputs (2)'!BD123)=0),"",ABS('Inputs (2)'!BD123)*4/ABS(AVERAGE(('Inputs (2)'!BC18+'Inputs (2)'!BC19),('Inputs (2)'!BD18+'Inputs (2)'!BD19)))),"") | BE224: =IFERROR(IF(OR(ABS(AVERAGE(('Inputs (2)'!BD18+'Inputs (2)'!BD19),('Inputs (2)'!BE18+'Inputs (2)'!BE19)))=0,('Inputs (2)'!BE123)=0),"",ABS('Inputs (2)'!BE123)*4/ABS(AVERAGE(('Inputs (2)'!BD18+'Inputs (2)'!BD19),('Inputs (2)'!BE18+'Inputs (2)'!BE19)))),"") | BF224: =IFERROR(IF(OR(ABS(AVERAGE(('Inputs (2)'!BE18+'Inputs (2)'!BE19),('Inputs (2)'!BF18+'Inputs (2)'!BF19)))=0,('Inputs (2)'!BF123)=0),"",ABS('Inputs (2)'!BF123)*4/ABS(AVERAGE(('Inputs (2)'!BE18+'Inputs (2)'!BE19),('Inputs (2)'!BF18+'Inputs (2)'!BF19)))),"") | BG224: =IFERROR(IF(OR(ABS(AVERAGE(('Inputs (2)'!BB18+'Inputs (2)'!BB19),('Inputs (2)'!BG18+'Inputs (2)'!BG19)))=0,('Inputs (2)'!BG123)=0),"",ABS('Inputs (2)'!BG123)/ABS(AVERAGE(('Inputs (2)'!BB18+'Inputs (2)'!BB19),('Inputs (2)'!BG18+'Inputs (2)'!BG19)))),"")
C225: Recuperação de créditos baixados (% da despesa de PDD) | D225: Recoveries | E225: =IFERROR(IF(OR(ABS('Inputs (2)'!E82)=0,('Inputs (2)'!E83)=0),"",ABS('Inputs (2)'!E83)/ABS('Inputs (2)'!E82)),"") | F225: =IFERROR(IF(OR(ABS('Inputs (2)'!F82)=0,('Inputs (2)'!F83)=0),"",ABS('Inputs (2)'!F83)/ABS('Inputs (2)'!F82)),"") | G225: =IFERROR(IF(OR(ABS('Inputs (2)'!G82)=0,('Inputs (2)'!G83)=0),"",ABS('Inputs (2)'!G83)/ABS('Inputs (2)'!G82)),"") | H225: =IFERROR(IF(OR(ABS('Inputs (2)'!H82)=0,('Inputs (2)'!H83)=0),"",ABS('Inputs (2)'!H83)/ABS('Inputs (2)'!H82)),"") | I225: =IFERROR(IF(OR(ABS('Inputs (2)'!I82)=0,('Inputs (2)'!I83)=0),"",ABS('Inputs (2)'!I83)/ABS('Inputs (2)'!I82)),"") | J225: =IFERROR(IF(OR(ABS('Inputs (2)'!J82)=0,('Inputs (2)'!J83)=0),"",ABS('Inputs (2)'!J83)/ABS('Inputs (2)'!J82)),"") | K225: =IFERROR(IF(OR(ABS('Inputs (2)'!K82)=0,('Inputs (2)'!K83)=0),"",ABS('Inputs (2)'!K83)/ABS('Inputs (2)'!K82)),"") | L225: =IFERROR(IF(OR(ABS('Inputs (2)'!L82)=0,('Inputs (2)'!L83)=0),"",ABS('Inputs (2)'!L83)/ABS('Inputs (2)'!L82)),"") | ... BG225: =IFERROR(IF(OR(ABS('Inputs (2)'!BG82)=0,('Inputs (2)'!BG83)=0),"",ABS('Inputs (2)'!BG83)/ABS('Inputs (2)'!BG82)),"")
C226: TVM e aplicações — crescimento % QoQ | D226: Securities growth QoQ | F226: =IFERROR(IF(('Inputs (2)'!E11+'Inputs (2)'!E6)=0,"",('Inputs (2)'!F11+'Inputs (2)'!F6)/('Inputs (2)'!E11+'Inputs (2)'!E6)-1),"") | G226: =IFERROR(IF(('Inputs (2)'!F11+'Inputs (2)'!F6)=0,"",('Inputs (2)'!G11+'Inputs (2)'!G6)/('Inputs (2)'!F11+'Inputs (2)'!F6)-1),"") | H226: =IFERROR(IF(('Inputs (2)'!G11+'Inputs (2)'!G6)=0,"",('Inputs (2)'!H11+'Inputs (2)'!H6)/('Inputs (2)'!G11+'Inputs (2)'!G6)-1),"") | J226: =IFERROR(IF(('Inputs (2)'!H11+'Inputs (2)'!H6)=0,"",('Inputs (2)'!J11+'Inputs (2)'!J6)/('Inputs (2)'!H11+'Inputs (2)'!H6)-1),"") | K226: =IFERROR(IF(('Inputs (2)'!J11+'Inputs (2)'!J6)=0,"",('Inputs (2)'!K11+'Inputs (2)'!K6)/('Inputs (2)'!J11+'Inputs (2)'!J6)-1),"") | L226: =IFERROR(IF(('Inputs (2)'!K11+'Inputs (2)'!K6)=0,"",('Inputs (2)'!L11+'Inputs (2)'!L6)/('Inputs (2)'!K11+'Inputs (2)'!K6)-1),"") | M226: =IFERROR(IF(('Inputs (2)'!L11+'Inputs (2)'!L6)=0,"",('Inputs (2)'!M11+'Inputs (2)'!M6)/('Inputs (2)'!L11+'Inputs (2)'!L6)-1),"") | N226: =IFERROR(IF(('Inputs (2)'!I11+'Inputs (2)'!I6)=0,"",('Inputs (2)'!N11+'Inputs (2)'!N6)/('Inputs (2)'!I11+'Inputs (2)'!I6)-1),"") | O226: =IFERROR(IF(('Inputs (2)'!M11+'Inputs (2)'!M6)=0,"",('Inputs (2)'!O11+'Inputs (2)'!O6)/('Inputs (2)'!M11+'Inputs (2)'!M6)-1),"") | P226: =IFERROR(IF(('Inputs (2)'!O11+'Inputs (2)'!O6)=0,"",('Inputs (2)'!P11+'Inputs (2)'!P6)/('Inputs (2)'!O11+'Inputs (2)'!O6)-1),"") | Q226: =IFERROR(IF(('Inputs (2)'!P11+'Inputs (2)'!P6)=0,"",('Inputs (2)'!Q11+'Inputs (2)'!Q6)/('Inputs (2)'!P11+'Inputs (2)'!P6)-1),"") | R226: =IFERROR(IF(('Inputs (2)'!Q11+'Inputs (2)'!Q6)=0,"",('Inputs (2)'!R11+'Inputs (2)'!R6)/('Inputs (2)'!Q11+'Inputs (2)'!Q6)-1),"") | S226: =IFERROR(IF(('Inputs (2)'!N11+'Inputs (2)'!N6)=0,"",('Inputs (2)'!S11+'Inputs (2)'!S6)/('Inputs (2)'!N11+'Inputs (2)'!N6)-1),"") | T226: =IFERROR(IF(('Inputs (2)'!R11+'Inputs (2)'!R6)=0,"",('Inputs (2)'!T11+'Inputs (2)'!T6)/('Inputs (2)'!R11+'Inputs (2)'!R6)-1),"") | U226: =IFERROR(IF(('Inputs (2)'!T11+'Inputs (2)'!T6)=0,"",('Inputs (2)'!U11+'Inputs (2)'!U6)/('Inputs (2)'!T11+'Inputs (2)'!T6)-1),"") | V226: =IFERROR(IF(('Inputs (2)'!U11+'Inputs (2)'!U6)=0,"",('Inputs (2)'!V11+'Inputs (2)'!V6)/('Inputs (2)'!U11+'Inputs (2)'!U6)-1),"") | W226: =IFERROR(IF(('Inputs (2)'!V11+'Inputs (2)'!V6)=0,"",('Inputs (2)'!W11+'Inputs (2)'!W6)/('Inputs (2)'!V11+'Inputs (2)'!V6)-1),"") | X226: =IFERROR(IF(('Inputs (2)'!S11+'Inputs (2)'!S6)=0,"",('Inputs (2)'!X11+'Inputs (2)'!X6)/('Inputs (2)'!S11+'Inputs (2)'!S6)-1),"") | Y226: =IFERROR(IF(('Inputs (2)'!W11+'Inputs (2)'!W6)=0,"",('Inputs (2)'!Y11+'Inputs (2)'!Y6)/('Inputs (2)'!W11+'Inputs (2)'!W6)-1),"") | Z226: =IFERROR(IF(('Inputs (2)'!Y11+'Inputs (2)'!Y6)=0,"",('Inputs (2)'!Z11+'Inputs (2)'!Z6)/('Inputs (2)'!Y11+'Inputs (2)'!Y6)-1),"") | AA226: =IFERROR(IF(('Inputs (2)'!Z11+'Inputs (2)'!Z6)=0,"",('Inputs (2)'!AA11+'Inputs (2)'!AA6)/('Inputs (2)'!Z11+'Inputs (2)'!Z6)-1),"") | AB226: =IFERROR(IF(('Inputs (2)'!AA11+'Inputs (2)'!AA6)=0,"",('Inputs (2)'!AB11+'Inputs (2)'!AB6)/('Inputs (2)'!AA11+'Inputs (2)'!AA6)-1),"") | AC226: =IFERROR(IF(('Inputs (2)'!X11+'Inputs (2)'!X6)=0,"",('Inputs (2)'!AC11+'Inputs (2)'!AC6)/('Inputs (2)'!X11+'Inputs (2)'!X6)-1),"") | AD226: =IFERROR(IF(('Inputs (2)'!AB11+'Inputs (2)'!AB6)=0,"",('Inputs (2)'!AD11+'Inputs (2)'!AD6)/('Inputs (2)'!AB11+'Inputs (2)'!AB6)-1),"") | AE226: =IFERROR(IF(('Inputs (2)'!AD11+'Inputs (2)'!AD6)=0,"",('Inputs (2)'!AE11+'Inputs (2)'!AE6)/('Inputs (2)'!AD11+'Inputs (2)'!AD6)-1),"") | AF226: =IFERROR(IF(('Inputs (2)'!AE11+'Inputs (2)'!AE6)=0,"",('Inputs (2)'!AF11+'Inputs (2)'!AF6)/('Inputs (2)'!AE11+'Inputs (2)'!AE6)-1),"") | AG226: =IFERROR(IF(('Inputs (2)'!AF11+'Inputs (2)'!AF6)=0,"",('Inputs (2)'!AG11+'Inputs (2)'!AG6)/('Inputs (2)'!AF11+'Inputs (2)'!AF6)-1),"") | AH226: =IFERROR(IF(('Inputs (2)'!AC11+'Inputs (2)'!AC6)=0,"",('Inputs (2)'!AH11+'Inputs (2)'!AH6)/('Inputs (2)'!AC11+'Inputs (2)'!AC6)-1),"") | AI226: =IFERROR(IF(('Inputs (2)'!AG11+'Inputs (2)'!AG6)=0,"",('Inputs (2)'!AI11+'Inputs (2)'!AI6)/('Inputs (2)'!AG11+'Inputs (2)'!AG6)-1),"") | AJ226: =IFERROR(IF(('Inputs (2)'!AI11+'Inputs (2)'!AI6)=0,"",('Inputs (2)'!AJ11+'Inputs (2)'!AJ6)/('Inputs (2)'!AI11+'Inputs (2)'!AI6)-1),"") | AK226: =IFERROR(IF(('Inputs (2)'!AJ11+'Inputs (2)'!AJ6)=0,"",('Inputs (2)'!AK11+'Inputs (2)'!AK6)/('Inputs (2)'!AJ11+'Inputs (2)'!AJ6)-1),"") | AL226: =IFERROR(IF(('Inputs (2)'!AK11+'Inputs (2)'!AK6)=0,"",('Inputs (2)'!AL11+'Inputs (2)'!AL6)/('Inputs (2)'!AK11+'Inputs (2)'!AK6)-1),"") | AM226: =IFERROR(IF(('Inputs (2)'!AH11+'Inputs (2)'!AH6)=0,"",('Inputs (2)'!AM11+'Inputs (2)'!AM6)/('Inputs (2)'!AH11+'Inputs (2)'!AH6)-1),"") | AN226: =IFERROR(IF(('Inputs (2)'!AL11+'Inputs (2)'!AL6)=0,"",('Inputs (2)'!AN11+'Inputs (2)'!AN6)/('Inputs (2)'!AL11+'Inputs (2)'!AL6)-1),"") | AO226: =IFERROR(IF(('Inputs (2)'!AN11+'Inputs (2)'!AN6)=0,"",('Inputs (2)'!AO11+'Inputs (2)'!AO6)/('Inputs (2)'!AN11+'Inputs (2)'!AN6)-1),"") | AP226: =IFERROR(IF(('Inputs (2)'!AO11+'Inputs (2)'!AO6)=0,"",('Inputs (2)'!AP11+'Inputs (2)'!AP6)/('Inputs (2)'!AO11+'Inputs (2)'!AO6)-1),"") | AQ226: =IFERROR(IF(('Inputs (2)'!AP11+'Inputs (2)'!AP6)=0,"",('Inputs (2)'!AQ11+'Inputs (2)'!AQ6)/('Inputs (2)'!AP11+'Inputs (2)'!AP6)-1),"") | AR226: =IFERROR(IF(('Inputs (2)'!AM11+'Inputs (2)'!AM6)=0,"",('Inputs (2)'!AR11+'Inputs (2)'!AR6)/('Inputs (2)'!AM11+'Inputs (2)'!AM6)-1),"") | AS226: =IFERROR(IF(('Inputs (2)'!AQ11+'Inputs (2)'!AQ6)=0,"",('Inputs (2)'!AS11+'Inputs (2)'!AS6)/('Inputs (2)'!AQ11+'Inputs (2)'!AQ6)-1),"") | AT226: =IFERROR(IF(('Inputs (2)'!AS11+'Inputs (2)'!AS6)=0,"",('Inputs (2)'!AT11+'Inputs (2)'!AT6)/('Inputs (2)'!AS11+'Inputs (2)'!AS6)-1),"") | AU226: =IFERROR(IF(('Inputs (2)'!AT11+'Inputs (2)'!AT6)=0,"",('Inputs (2)'!AU11+'Inputs (2)'!AU6)/('Inputs (2)'!AT11+'Inputs (2)'!AT6)-1),"") | AV226: =IFERROR(IF(('Inputs (2)'!AU11+'Inputs (2)'!AU6)=0,"",('Inputs (2)'!AV11+'Inputs (2)'!AV6)/('Inputs (2)'!AU11+'Inputs (2)'!AU6)-1),"") | AW226: =IFERROR(IF(('Inputs (2)'!AR11+'Inputs (2)'!AR6)=0,"",('Inputs (2)'!AW11+'Inputs (2)'!AW6)/('Inputs (2)'!AR11+'Inputs (2)'!AR6)-1),"") | AX226: =IFERROR(IF(('Inputs (2)'!AV11+'Inputs (2)'!AV6)=0,"",('Inputs (2)'!AX11+'Inputs (2)'!AX6)/('Inputs (2)'!AV11+'Inputs (2)'!AV6)-1),"") | AY226: =IFERROR(IF(('Inputs (2)'!AX11+'Inputs (2)'!AX6)=0,"",('Inputs (2)'!AY11+'Inputs (2)'!AY6)/('Inputs (2)'!AX11+'Inputs (2)'!AX6)-1),"") | AZ226: =IFERROR(IF(('Inputs (2)'!AY11+'Inputs (2)'!AY6)=0,"",('Inputs (2)'!AZ11+'Inputs (2)'!AZ6)/('Inputs (2)'!AY11+'Inputs (2)'!AY6)-1),"") | BA226: =IFERROR(IF(('Inputs (2)'!AZ11+'Inputs (2)'!AZ6)=0,"",('Inputs (2)'!BA11+'Inputs (2)'!BA6)/('Inputs (2)'!AZ11+'Inputs (2)'!AZ6)-1),"") | BB226: =IFERROR(IF(('Inputs (2)'!AW11+'Inputs (2)'!AW6)=0,"",('Inputs (2)'!BB11+'Inputs (2)'!BB6)/('Inputs (2)'!AW11+'Inputs (2)'!AW6)-1),"") | BC226: =IFERROR(IF(('Inputs (2)'!BA11+'Inputs (2)'!BA6)=0,"",('Inputs (2)'!BC11+'Inputs (2)'!BC6)/('Inputs (2)'!BA11+'Inputs (2)'!BA6)-1),"") | BD226: =IFERROR(IF(('Inputs (2)'!BC11+'Inputs (2)'!BC6)=0,"",('Inputs (2)'!BD11+'Inputs (2)'!BD6)/('Inputs (2)'!BC11+'Inputs (2)'!BC6)-1),"") | BE226: =IFERROR(IF(('Inputs (2)'!BD11+'Inputs (2)'!BD6)=0,"",('Inputs (2)'!BE11+'Inputs (2)'!BE6)/('Inputs (2)'!BD11+'Inputs (2)'!BD6)-1),"") | BF226: =IFERROR(IF(('Inputs (2)'!BE11+'Inputs (2)'!BE6)=0,"",('Inputs (2)'!BF11+'Inputs (2)'!BF6)/('Inputs (2)'!BE11+'Inputs (2)'!BE6)-1),"") | BG226: =IFERROR(IF(('Inputs (2)'!BB11+'Inputs (2)'!BB6)=0,"",('Inputs (2)'!BG11+'Inputs (2)'!BG6)/('Inputs (2)'!BB11+'Inputs (2)'!BB6)-1),"")
C227: Rendimento médio de TVM e aplicações (% a.a.) | D227: Securities yield | E227: =IFERROR(IF(OR(('Inputs (2)'!E11+'Inputs (2)'!E6)=0,('Inputs (2)'!E72+'Inputs (2)'!E74)=0),"",('Inputs (2)'!E72+'Inputs (2)'!E74)*4/('Inputs (2)'!E11+'Inputs (2)'!E6)),"") | F227: =IFERROR(IF(OR(AVERAGE(('Inputs (2)'!E11+'Inputs (2)'!E6),('Inputs (2)'!F11+'Inputs (2)'!F6))=0,('Inputs (2)'!F72+'Inputs (2)'!F74)=0),"",('Inputs (2)'!F72+'Inputs (2)'!F74)*4/AVERAGE(('Inputs (2)'!E11+'Inputs (2)'!E6),('Inputs (2)'!F11+'Inputs (2)'!F6))),"") | G227: =IFERROR(IF(OR(AVERAGE(('Inputs (2)'!F11+'Inputs (2)'!F6),('Inputs (2)'!G11+'Inputs (2)'!G6))=0,('Inputs (2)'!G72+'Inputs (2)'!G74)=0),"",('Inputs (2)'!G72+'Inputs (2)'!G74)*4/AVERAGE(('Inputs (2)'!F11+'Inputs (2)'!F6),('Inputs (2)'!G11+'Inputs (2)'!G6))),"") | H227: =IFERROR(IF(OR(AVERAGE(('Inputs (2)'!G11+'Inputs (2)'!G6),('Inputs (2)'!H11+'Inputs (2)'!H6))=0,('Inputs (2)'!H72+'Inputs (2)'!H74)=0),"",('Inputs (2)'!H72+'Inputs (2)'!H74)*4/AVERAGE(('Inputs (2)'!G11+'Inputs (2)'!G6),('Inputs (2)'!H11+'Inputs (2)'!H6))),"") | I227: =IFERROR(IF(OR(('Inputs (2)'!I11+'Inputs (2)'!I6)=0,('Inputs (2)'!I72+'Inputs (2)'!I74)=0),"",('Inputs (2)'!I72+'Inputs (2)'!I74)/('Inputs (2)'!I11+'Inputs (2)'!I6)),"") | J227: =IFERROR(IF(OR(AVERAGE(('Inputs (2)'!H11+'Inputs (2)'!H6),('Inputs (2)'!J11+'Inputs (2)'!J6))=0,('Inputs (2)'!J72+'Inputs (2)'!J74)=0),"",('Inputs (2)'!J72+'Inputs (2)'!J74)*4/AVERAGE(('Inputs (2)'!H11+'Inputs (2)'!H6),('Inputs (2)'!J11+'Inputs (2)'!J6))),"") | K227: =IFERROR(IF(OR(AVERAGE(('Inputs (2)'!J11+'Inputs (2)'!J6),('Inputs (2)'!K11+'Inputs (2)'!K6))=0,('Inputs (2)'!K72+'Inputs (2)'!K74)=0),"",('Inputs (2)'!K72+'Inputs (2)'!K74)*4/AVERAGE(('Inputs (2)'!J11+'Inputs (2)'!J6),('Inputs (2)'!K11+'Inputs (2)'!K6))),"") | L227: =IFERROR(IF(OR(AVERAGE(('Inputs (2)'!K11+'Inputs (2)'!K6),('Inputs (2)'!L11+'Inputs (2)'!L6))=0,('Inputs (2)'!L72+'Inputs (2)'!L74)=0),"",('Inputs (2)'!L72+'Inputs (2)'!L74)*4/AVERAGE(('Inputs (2)'!K11+'Inputs (2)'!K6),('Inputs (2)'!L11+'Inputs (2)'!L6))),"") | M227: =IFERROR(IF(OR(AVERAGE(('Inputs (2)'!L11+'Inputs (2)'!L6),('Inputs (2)'!M11+'Inputs (2)'!M6))=0,('Inputs (2)'!M72+'Inputs (2)'!M74)=0),"",('Inputs (2)'!M72+'Inputs (2)'!M74)*4/AVERAGE(('Inputs (2)'!L11+'Inputs (2)'!L6),('Inputs (2)'!M11+'Inputs (2)'!M6))),"") | N227: =IFERROR(IF(OR(AVERAGE(('Inputs (2)'!I11+'Inputs (2)'!I6),('Inputs (2)'!N11+'Inputs (2)'!N6))=0,('Inputs (2)'!N72+'Inputs (2)'!N74)=0),"",('Inputs (2)'!N72+'Inputs (2)'!N74)/AVERAGE(('Inputs (2)'!I11+'Inputs (2)'!I6),('Inputs (2)'!N11+'Inputs (2)'!N6))),"") | O227: =IFERROR(IF(OR(AVERAGE(('Inputs (2)'!M11+'Inputs (2)'!M6),('Inputs (2)'!O11+'Inputs (2)'!O6))=0,('Inputs (2)'!O72+'Inputs (2)'!O74)=0),"",('Inputs (2)'!O72+'Inputs (2)'!O74)*4/AVERAGE(('Inputs (2)'!M11+'Inputs (2)'!M6),('Inputs (2)'!O11+'Inputs (2)'!O6))),"") | P227: =IFERROR(IF(OR(AVERAGE(('Inputs (2)'!O11+'Inputs (2)'!O6),('Inputs (2)'!P11+'Inputs (2)'!P6))=0,('Inputs (2)'!P72+'Inputs (2)'!P74)=0),"",('Inputs (2)'!P72+'Inputs (2)'!P74)*4/AVERAGE(('Inputs (2)'!O11+'Inputs (2)'!O6),('Inputs (2)'!P11+'Inputs (2)'!P6))),"") | Q227: =IFERROR(IF(OR(AVERAGE(('Inputs (2)'!P11+'Inputs (2)'!P6),('Inputs (2)'!Q11+'Inputs (2)'!Q6))=0,('Inputs (2)'!Q72+'Inputs (2)'!Q74)=0),"",('Inputs (2)'!Q72+'Inputs (2)'!Q74)*4/AVERAGE(('Inputs (2)'!P11+'Inputs (2)'!P6),('Inputs (2)'!Q11+'Inputs (2)'!Q6))),"") | R227: =IFERROR(IF(OR(AVERAGE(('Inputs (2)'!Q11+'Inputs (2)'!Q6),('Inputs (2)'!R11+'Inputs (2)'!R6))=0,('Inputs (2)'!R72+'Inputs (2)'!R74)=0),"",('Inputs (2)'!R72+'Inputs (2)'!R74)*4/AVERAGE(('Inputs (2)'!Q11+'Inputs (2)'!Q6),('Inputs (2)'!R11+'Inputs (2)'!R6))),"") | S227: =IFERROR(IF(OR(AVERAGE(('Inputs (2)'!N11+'Inputs (2)'!N6),('Inputs (2)'!S11+'Inputs (2)'!S6))=0,('Inputs (2)'!S72+'Inputs (2)'!S74)=0),"",('Inputs (2)'!S72+'Inputs (2)'!S74)/AVERAGE(('Inputs (2)'!N11+'Inputs (2)'!N6),('Inputs (2)'!S11+'Inputs (2)'!S6))),"") | T227: =IFERROR(IF(OR(AVERAGE(('Inputs (2)'!R11+'Inputs (2)'!R6),('Inputs (2)'!T11+'Inputs (2)'!T6))=0,('Inputs (2)'!T72+'Inputs (2)'!T74)=0),"",('Inputs (2)'!T72+'Inputs (2)'!T74)*4/AVERAGE(('Inputs (2)'!R11+'Inputs (2)'!R6),('Inputs (2)'!T11+'Inputs (2)'!T6))),"") | U227: =IFERROR(IF(OR(AVERAGE(('Inputs (2)'!T11+'Inputs (2)'!T6),('Inputs (2)'!U11+'Inputs (2)'!U6))=0,('Inputs (2)'!U72+'Inputs (2)'!U74)=0),"",('Inputs (2)'!U72+'Inputs (2)'!U74)*4/AVERAGE(('Inputs (2)'!T11+'Inputs (2)'!T6),('Inputs (2)'!U11+'Inputs (2)'!U6))),"") | V227: =IFERROR(IF(OR(AVERAGE(('Inputs (2)'!U11+'Inputs (2)'!U6),('Inputs (2)'!V11+'Inputs (2)'!V6))=0,('Inputs (2)'!V72+'Inputs (2)'!V74)=0),"",('Inputs (2)'!V72+'Inputs (2)'!V74)*4/AVERAGE(('Inputs (2)'!U11+'Inputs (2)'!U6),('Inputs (2)'!V11+'Inputs (2)'!V6))),"") | W227: =IFERROR(IF(OR(AVERAGE(('Inputs (2)'!V11+'Inputs (2)'!V6),('Inputs (2)'!W11+'Inputs (2)'!W6))=0,('Inputs (2)'!W72+'Inputs (2)'!W74)=0),"",('Inputs (2)'!W72+'Inputs (2)'!W74)*4/AVERAGE(('Inputs (2)'!V11+'Inputs (2)'!V6),('Inputs (2)'!W11+'Inputs (2)'!W6))),"") | X227: =IFERROR(IF(OR(AVERAGE(('Inputs (2)'!S11+'Inputs (2)'!S6),('Inputs (2)'!X11+'Inputs (2)'!X6))=0,('Inputs (2)'!X72+'Inputs (2)'!X74)=0),"",('Inputs (2)'!X72+'Inputs (2)'!X74)/AVERAGE(('Inputs (2)'!S11+'Inputs (2)'!S6),('Inputs (2)'!X11+'Inputs (2)'!X6))),"") | Y227: =IFERROR(IF(OR(AVERAGE(('Inputs (2)'!W11+'Inputs (2)'!W6),('Inputs (2)'!Y11+'Inputs (2)'!Y6))=0,('Inputs (2)'!Y72+'Inputs (2)'!Y74)=0),"",('Inputs (2)'!Y72+'Inputs (2)'!Y74)*4/AVERAGE(('Inputs (2)'!W11+'Inputs (2)'!W6),('Inputs (2)'!Y11+'Inputs (2)'!Y6))),"") | Z227: =IFERROR(IF(OR(AVERAGE(('Inputs (2)'!Y11+'Inputs (2)'!Y6),('Inputs (2)'!Z11+'Inputs (2)'!Z6))=0,('Inputs (2)'!Z72+'Inputs (2)'!Z74)=0),"",('Inputs (2)'!Z72+'Inputs (2)'!Z74)*4/AVERAGE(('Inputs (2)'!Y11+'Inputs (2)'!Y6),('Inputs (2)'!Z11+'Inputs (2)'!Z6))),"") | AA227: =IFERROR(IF(OR(AVERAGE(('Inputs (2)'!Z11+'Inputs (2)'!Z6),('Inputs (2)'!AA11+'Inputs (2)'!AA6))=0,('Inputs (2)'!AA72+'Inputs (2)'!AA74)=0),"",('Inputs (2)'!AA72+'Inputs (2)'!AA74)*4/AVERAGE(('Inputs (2)'!Z11+'Inputs (2)'!Z6),('Inputs (2)'!AA11+'Inputs (2)'!AA6))),"") | AB227: =IFERROR(IF(OR(AVERAGE(('Inputs (2)'!AA11+'Inputs (2)'!AA6),('Inputs (2)'!AB11+'Inputs (2)'!AB6))=0,('Inputs (2)'!AB72+'Inputs (2)'!AB74)=0),"",('Inputs (2)'!AB72+'Inputs (2)'!AB74)*4/AVERAGE(('Inputs (2)'!AA11+'Inputs (2)'!AA6),('Inputs (2)'!AB11+'Inputs (2)'!AB6))),"") | AC227: =IFERROR(IF(OR(AVERAGE(('Inputs (2)'!X11+'Inputs (2)'!X6),('Inputs (2)'!AC11+'Inputs (2)'!AC6))=0,('Inputs (2)'!AC72+'Inputs (2)'!AC74)=0),"",('Inputs (2)'!AC72+'Inputs (2)'!AC74)/AVERAGE(('Inputs (2)'!X11+'Inputs (2)'!X6),('Inputs (2)'!AC11+'Inputs (2)'!AC6))),"") | AD227: =IFERROR(IF(OR(AVERAGE(('Inputs (2)'!AB11+'Inputs (2)'!AB6),('Inputs (2)'!AD11+'Inputs (2)'!AD6))=0,('Inputs (2)'!AD72+'Inputs (2)'!AD74)=0),"",('Inputs (2)'!AD72+'Inputs (2)'!AD74)*4/AVERAGE(('Inputs (2)'!AB11+'Inputs (2)'!AB6),('Inputs (2)'!AD11+'Inputs (2)'!AD6))),"") | AE227: =IFERROR(IF(OR(AVERAGE(('Inputs (2)'!AD11+'Inputs (2)'!AD6),('Inputs (2)'!AE11+'Inputs (2)'!AE6))=0,('Inputs (2)'!AE72+'Inputs (2)'!AE74)=0),"",('Inputs (2)'!AE72+'Inputs (2)'!AE74)*4/AVERAGE(('Inputs (2)'!AD11+'Inputs (2)'!AD6),('Inputs (2)'!AE11+'Inputs (2)'!AE6))),"") | AF227: =IFERROR(IF(OR(AVERAGE(('Inputs (2)'!AE11+'Inputs (2)'!AE6),('Inputs (2)'!AF11+'Inputs (2)'!AF6))=0,('Inputs (2)'!AF72+'Inputs (2)'!AF74)=0),"",('Inputs (2)'!AF72+'Inputs (2)'!AF74)*4/AVERAGE(('Inputs (2)'!AE11+'Inputs (2)'!AE6),('Inputs (2)'!AF11+'Inputs (2)'!AF6))),"") | AG227: =IFERROR(IF(OR(AVERAGE(('Inputs (2)'!AF11+'Inputs (2)'!AF6),('Inputs (2)'!AG11+'Inputs (2)'!AG6))=0,('Inputs (2)'!AG72+'Inputs (2)'!AG74)=0),"",('Inputs (2)'!AG72+'Inputs (2)'!AG74)*4/AVERAGE(('Inputs (2)'!AF11+'Inputs (2)'!AF6),('Inputs (2)'!AG11+'Inputs (2)'!AG6))),"") | AH227: =IFERROR(IF(OR(AVERAGE(('Inputs (2)'!AC11+'Inputs (2)'!AC6),('Inputs (2)'!AH11+'Inputs (2)'!AH6))=0,('Inputs (2)'!AH72+'Inputs (2)'!AH74)=0),"",('Inputs (2)'!AH72+'Inputs (2)'!AH74)/AVERAGE(('Inputs (2)'!AC11+'Inputs (2)'!AC6),('Inputs (2)'!AH11+'Inputs (2)'!AH6))),"") | AI227: =IFERROR(IF(OR(AVERAGE(('Inputs (2)'!AG11+'Inputs (2)'!AG6),('Inputs (2)'!AI11+'Inputs (2)'!AI6))=0,('Inputs (2)'!AI72+'Inputs (2)'!AI74)=0),"",('Inputs (2)'!AI72+'Inputs (2)'!AI74)*4/AVERAGE(('Inputs (2)'!AG11+'Inputs (2)'!AG6),('Inputs (2)'!AI11+'Inputs (2)'!AI6))),"") | AJ227: =IFERROR(IF(OR(AVERAGE(('Inputs (2)'!AI11+'Inputs (2)'!AI6),('Inputs (2)'!AJ11+'Inputs (2)'!AJ6))=0,('Inputs (2)'!AJ72+'Inputs (2)'!AJ74)=0),"",('Inputs (2)'!AJ72+'Inputs (2)'!AJ74)*4/AVERAGE(('Inputs (2)'!AI11+'Inputs (2)'!AI6),('Inputs (2)'!AJ11+'Inputs (2)'!AJ6))),"") | AK227: =IFERROR(IF(OR(AVERAGE(('Inputs (2)'!AJ11+'Inputs (2)'!AJ6),('Inputs (2)'!AK11+'Inputs (2)'!AK6))=0,('Inputs (2)'!AK72+'Inputs (2)'!AK74)=0),"",('Inputs (2)'!AK72+'Inputs (2)'!AK74)*4/AVERAGE(('Inputs (2)'!AJ11+'Inputs (2)'!AJ6),('Inputs (2)'!AK11+'Inputs (2)'!AK6))),"") | AL227: =IFERROR(IF(OR(AVERAGE(('Inputs (2)'!AK11+'Inputs (2)'!AK6),('Inputs (2)'!AL11+'Inputs (2)'!AL6))=0,('Inputs (2)'!AL72+'Inputs (2)'!AL74)=0),"",('Inputs (2)'!AL72+'Inputs (2)'!AL74)*4/AVERAGE(('Inputs (2)'!AK11+'Inputs (2)'!AK6),('Inputs (2)'!AL11+'Inputs (2)'!AL6))),"") | AM227: =IFERROR(IF(OR(AVERAGE(('Inputs (2)'!AH11+'Inputs (2)'!AH6),('Inputs (2)'!AM11+'Inputs (2)'!AM6))=0,('Inputs (2)'!AM72+'Inputs (2)'!AM74)=0),"",('Inputs (2)'!AM72+'Inputs (2)'!AM74)/AVERAGE(('Inputs (2)'!AH11+'Inputs (2)'!AH6),('Inputs (2)'!AM11+'Inputs (2)'!AM6))),"") | AN227: =IFERROR(IF(OR(AVERAGE(('Inputs (2)'!AL11+'Inputs (2)'!AL6),('Inputs (2)'!AN11+'Inputs (2)'!AN6))=0,('Inputs (2)'!AN72+'Inputs (2)'!AN74)=0),"",('Inputs (2)'!AN72+'Inputs (2)'!AN74)*4/AVERAGE(('Inputs (2)'!AL11+'Inputs (2)'!AL6),('Inputs (2)'!AN11+'Inputs (2)'!AN6))),"") | AO227: =IFERROR(IF(OR(AVERAGE(('Inputs (2)'!AN11+'Inputs (2)'!AN6),('Inputs (2)'!AO11+'Inputs (2)'!AO6))=0,('Inputs (2)'!AO72+'Inputs (2)'!AO74)=0),"",('Inputs (2)'!AO72+'Inputs (2)'!AO74)*4/AVERAGE(('Inputs (2)'!AN11+'Inputs (2)'!AN6),('Inputs (2)'!AO11+'Inputs (2)'!AO6))),"") | AP227: =IFERROR(IF(OR(AVERAGE(('Inputs (2)'!AO11+'Inputs (2)'!AO6),('Inputs (2)'!AP11+'Inputs (2)'!AP6))=0,('Inputs (2)'!AP72+'Inputs (2)'!AP74)=0),"",('Inputs (2)'!AP72+'Inputs (2)'!AP74)*4/AVERAGE(('Inputs (2)'!AO11+'Inputs (2)'!AO6),('Inputs (2)'!AP11+'Inputs (2)'!AP6))),"") | AQ227: =IFERROR(IF(OR(AVERAGE(('Inputs (2)'!AP11+'Inputs (2)'!AP6),('Inputs (2)'!AQ11+'Inputs (2)'!AQ6))=0,('Inputs (2)'!AQ72+'Inputs (2)'!AQ74)=0),"",('Inputs (2)'!AQ72+'Inputs (2)'!AQ74)*4/AVERAGE(('Inputs (2)'!AP11+'Inputs (2)'!AP6),('Inputs (2)'!AQ11+'Inputs (2)'!AQ6))),"") | AR227: =IFERROR(IF(OR(AVERAGE(('Inputs (2)'!AM11+'Inputs (2)'!AM6),('Inputs (2)'!AR11+'Inputs (2)'!AR6))=0,('Inputs (2)'!AR72+'Inputs (2)'!AR74)=0),"",('Inputs (2)'!AR72+'Inputs (2)'!AR74)/AVERAGE(('Inputs (2)'!AM11+'Inputs (2)'!AM6),('Inputs (2)'!AR11+'Inputs (2)'!AR6))),"") | AS227: =IFERROR(IF(OR(AVERAGE(('Inputs (2)'!AQ11+'Inputs (2)'!AQ6),('Inputs (2)'!AS11+'Inputs (2)'!AS6))=0,('Inputs (2)'!AS72+'Inputs (2)'!AS74)=0),"",('Inputs (2)'!AS72+'Inputs (2)'!AS74)*4/AVERAGE(('Inputs (2)'!AQ11+'Inputs (2)'!AQ6),('Inputs (2)'!AS11+'Inputs (2)'!AS6))),"") | AT227: =IFERROR(IF(OR(AVERAGE(('Inputs (2)'!AS11+'Inputs (2)'!AS6),('Inputs (2)'!AT11+'Inputs (2)'!AT6))=0,('Inputs (2)'!AT72+'Inputs (2)'!AT74)=0),"",('Inputs (2)'!AT72+'Inputs (2)'!AT74)*4/AVERAGE(('Inputs (2)'!AS11+'Inputs (2)'!AS6),('Inputs (2)'!AT11+'Inputs (2)'!AT6))),"") | AU227: =IFERROR(IF(OR(AVERAGE(('Inputs (2)'!AT11+'Inputs (2)'!AT6),('Inputs (2)'!AU11+'Inputs (2)'!AU6))=0,('Inputs (2)'!AU72+'Inputs (2)'!AU74)=0),"",('Inputs (2)'!AU72+'Inputs (2)'!AU74)*4/AVERAGE(('Inputs (2)'!AT11+'Inputs (2)'!AT6),('Inputs (2)'!AU11+'Inputs (2)'!AU6))),"") | AV227: =IFERROR(IF(OR(AVERAGE(('Inputs (2)'!AU11+'Inputs (2)'!AU6),('Inputs (2)'!AV11+'Inputs (2)'!AV6))=0,('Inputs (2)'!AV72+'Inputs (2)'!AV74)=0),"",('Inputs (2)'!AV72+'Inputs (2)'!AV74)*4/AVERAGE(('Inputs (2)'!AU11+'Inputs (2)'!AU6),('Inputs (2)'!AV11+'Inputs (2)'!AV6))),"") | AW227: =IFERROR(IF(OR(AVERAGE(('Inputs (2)'!AR11+'Inputs (2)'!AR6),('Inputs (2)'!AW11+'Inputs (2)'!AW6))=0,('Inputs (2)'!AW72+'Inputs (2)'!AW74)=0),"",('Inputs (2)'!AW72+'Inputs (2)'!AW74)/AVERAGE(('Inputs (2)'!AR11+'Inputs (2)'!AR6),('Inputs (2)'!AW11+'Inputs (2)'!AW6))),"") | AX227: =IFERROR(IF(OR(AVERAGE(('Inputs (2)'!AV11+'Inputs (2)'!AV6),('Inputs (2)'!AX11+'Inputs (2)'!AX6))=0,('Inputs (2)'!AX72+'Inputs (2)'!AX74)=0),"",('Inputs (2)'!AX72+'Inputs (2)'!AX74)*4/AVERAGE(('Inputs (2)'!AV11+'Inputs (2)'!AV6),('Inputs (2)'!AX11+'Inputs (2)'!AX6))),"") | AY227: =IFERROR(IF(OR(AVERAGE(('Inputs (2)'!AX11+'Inputs (2)'!AX6),('Inputs (2)'!AY11+'Inputs (2)'!AY6))=0,('Inputs (2)'!AY72+'Inputs (2)'!AY74)=0),"",('Inputs (2)'!AY72+'Inputs (2)'!AY74)*4/AVERAGE(('Inputs (2)'!AX11+'Inputs (2)'!AX6),('Inputs (2)'!AY11+'Inputs (2)'!AY6))),"") | AZ227: =IFERROR(IF(OR(AVERAGE(('Inputs (2)'!AY11+'Inputs (2)'!AY6),('Inputs (2)'!AZ11+'Inputs (2)'!AZ6))=0,('Inputs (2)'!AZ72+'Inputs (2)'!AZ74)=0),"",('Inputs (2)'!AZ72+'Inputs (2)'!AZ74)*4/AVERAGE(('Inputs (2)'!AY11+'Inputs (2)'!AY6),('Inputs (2)'!AZ11+'Inputs (2)'!AZ6))),"") | BA227: =IFERROR(IF(OR(AVERAGE(('Inputs (2)'!AZ11+'Inputs (2)'!AZ6),('Inputs (2)'!BA11+'Inputs (2)'!BA6))=0,('Inputs (2)'!BA72+'Inputs (2)'!BA74)=0),"",('Inputs (2)'!BA72+'Inputs (2)'!BA74)*4/AVERAGE(('Inputs (2)'!AZ11+'Inputs (2)'!AZ6),('Inputs (2)'!BA11+'Inputs (2)'!BA6))),"") | BB227: =IFERROR(IF(OR(AVERAGE(('Inputs (2)'!AW11+'Inputs (2)'!AW6),('Inputs (2)'!BB11+'Inputs (2)'!BB6))=0,('Inputs (2)'!BB72+'Inputs (2)'!BB74)=0),"",('Inputs (2)'!BB72+'Inputs (2)'!BB74)/AVERAGE(('Inputs (2)'!AW11+'Inputs (2)'!AW6),('Inputs (2)'!BB11+'Inputs (2)'!BB6))),"") | BC227: =IFERROR(IF(OR(AVERAGE(('Inputs (2)'!BA11+'Inputs (2)'!BA6),('Inputs (2)'!BC11+'Inputs (2)'!BC6))=0,('Inputs (2)'!BC72+'Inputs (2)'!BC74)=0),"",('Inputs (2)'!BC72+'Inputs (2)'!BC74)*4/AVERAGE(('Inputs (2)'!BA11+'Inputs (2)'!BA6),('Inputs (2)'!BC11+'Inputs (2)'!BC6))),"") | BD227: =IFERROR(IF(OR(AVERAGE(('Inputs (2)'!BC11+'Inputs (2)'!BC6),('Inputs (2)'!BD11+'Inputs (2)'!BD6))=0,('Inputs (2)'!BD72+'Inputs (2)'!BD74)=0),"",('Inputs (2)'!BD72+'Inputs (2)'!BD74)*4/AVERAGE(('Inputs (2)'!BC11+'Inputs (2)'!BC6),('Inputs (2)'!BD11+'Inputs (2)'!BD6))),"") | BE227: =IFERROR(IF(OR(AVERAGE(('Inputs (2)'!BD11+'Inputs (2)'!BD6),('Inputs (2)'!BE11+'Inputs (2)'!BE6))=0,('Inputs (2)'!BE72+'Inputs (2)'!BE74)=0),"",('Inputs (2)'!BE72+'Inputs (2)'!BE74)*4/AVERAGE(('Inputs (2)'!BD11+'Inputs (2)'!BD6),('Inputs (2)'!BE11+'Inputs (2)'!BE6))),"") | BF227: =IFERROR(IF(OR(AVERAGE(('Inputs (2)'!BE11+'Inputs (2)'!BE6),('Inputs (2)'!BF11+'Inputs (2)'!BF6))=0,('Inputs (2)'!BF72+'Inputs (2)'!BF74)=0),"",('Inputs (2)'!BF72+'Inputs (2)'!BF74)*4/AVERAGE(('Inputs (2)'!BE11+'Inputs (2)'!BE6),('Inputs (2)'!BF11+'Inputs (2)'!BF6))),"") | BG227: =IFERROR(IF(OR(AVERAGE(('Inputs (2)'!BB11+'Inputs (2)'!BB6),('Inputs (2)'!BG11+'Inputs (2)'!BG6))=0,('Inputs (2)'!BG72+'Inputs (2)'!BG74)=0),"",('Inputs (2)'!BG72+'Inputs (2)'!BG74)/AVERAGE(('Inputs (2)'!BB11+'Inputs (2)'!BB6),('Inputs (2)'!BG11+'Inputs (2)'!BG6))),"")
C228: Depósitos — crescimento % QoQ | D228: Deposits growth QoQ | F228: =IFERROR(IF(('Inputs (2)'!E32)=0,"",('Inputs (2)'!F32)/('Inputs (2)'!E32)-1),"") | G228: =IFERROR(IF(('Inputs (2)'!F32)=0,"",('Inputs (2)'!G32)/('Inputs (2)'!F32)-1),"") | H228: =IFERROR(IF(('Inputs (2)'!G32)=0,"",('Inputs (2)'!H32)/('Inputs (2)'!G32)-1),"") | J228: =IFERROR(IF(('Inputs (2)'!H32)=0,"",('Inputs (2)'!J32)/('Inputs (2)'!H32)-1),"") | K228: =IFERROR(IF(('Inputs (2)'!J32)=0,"",('Inputs (2)'!K32)/('Inputs (2)'!J32)-1),"") | L228: =IFERROR(IF(('Inputs (2)'!K32)=0,"",('Inputs (2)'!L32)/('Inputs (2)'!K32)-1),"") | M228: =IFERROR(IF(('Inputs (2)'!L32)=0,"",('Inputs (2)'!M32)/('Inputs (2)'!L32)-1),"") | N228: =IFERROR(IF(('Inputs (2)'!I32)=0,"",('Inputs (2)'!N32)/('Inputs (2)'!I32)-1),"") | O228: =IFERROR(IF(('Inputs (2)'!M32)=0,"",('Inputs (2)'!O32)/('Inputs (2)'!M32)-1),"") | P228: =IFERROR(IF(('Inputs (2)'!O32)=0,"",('Inputs (2)'!P32)/('Inputs (2)'!O32)-1),"") | Q228: =IFERROR(IF(('Inputs (2)'!P32)=0,"",('Inputs (2)'!Q32)/('Inputs (2)'!P32)-1),"") | R228: =IFERROR(IF(('Inputs (2)'!Q32)=0,"",('Inputs (2)'!R32)/('Inputs (2)'!Q32)-1),"") | S228: =IFERROR(IF(('Inputs (2)'!N32)=0,"",('Inputs (2)'!S32)/('Inputs (2)'!N32)-1),"") | T228: =IFERROR(IF(('Inputs (2)'!R32)=0,"",('Inputs (2)'!T32)/('Inputs (2)'!R32)-1),"") | U228: =IFERROR(IF(('Inputs (2)'!T32)=0,"",('Inputs (2)'!U32)/('Inputs (2)'!T32)-1),"") | V228: =IFERROR(IF(('Inputs (2)'!U32)=0,"",('Inputs (2)'!V32)/('Inputs (2)'!U32)-1),"") | W228: =IFERROR(IF(('Inputs (2)'!V32)=0,"",('Inputs (2)'!W32)/('Inputs (2)'!V32)-1),"") | X228: =IFERROR(IF(('Inputs (2)'!S32)=0,"",('Inputs (2)'!X32)/('Inputs (2)'!S32)-1),"") | Y228: =IFERROR(IF(('Inputs (2)'!W32)=0,"",('Inputs (2)'!Y32)/('Inputs (2)'!W32)-1),"") | Z228: =IFERROR(IF(('Inputs (2)'!Y32)=0,"",('Inputs (2)'!Z32)/('Inputs (2)'!Y32)-1),"") | AA228: =IFERROR(IF(('Inputs (2)'!Z32)=0,"",('Inputs (2)'!AA32)/('Inputs (2)'!Z32)-1),"") | AB228: =IFERROR(IF(('Inputs (2)'!AA32)=0,"",('Inputs (2)'!AB32)/('Inputs (2)'!AA32)-1),"") | AC228: =IFERROR(IF(('Inputs (2)'!X32)=0,"",('Inputs (2)'!AC32)/('Inputs (2)'!X32)-1),"") | AD228: =IFERROR(IF(('Inputs (2)'!AB32)=0,"",('Inputs (2)'!AD32)/('Inputs (2)'!AB32)-1),"") | AE228: =IFERROR(IF(('Inputs (2)'!AD32)=0,"",('Inputs (2)'!AE32)/('Inputs (2)'!AD32)-1),"") | AF228: =IFERROR(IF(('Inputs (2)'!AE32)=0,"",('Inputs (2)'!AF32)/('Inputs (2)'!AE32)-1),"") | AG228: =IFERROR(IF(('Inputs (2)'!AF32)=0,"",('Inputs (2)'!AG32)/('Inputs (2)'!AF32)-1),"") | AH228: =IFERROR(IF(('Inputs (2)'!AC32)=0,"",('Inputs (2)'!AH32)/('Inputs (2)'!AC32)-1),"") | AI228: =IFERROR(IF(('Inputs (2)'!AG32)=0,"",('Inputs (2)'!AI32)/('Inputs (2)'!AG32)-1),"") | AJ228: =IFERROR(IF(('Inputs (2)'!AI32)=0,"",('Inputs (2)'!AJ32)/('Inputs (2)'!AI32)-1),"") | AK228: =IFERROR(IF(('Inputs (2)'!AJ32)=0,"",('Inputs (2)'!AK32)/('Inputs (2)'!AJ32)-1),"") | AL228: =IFERROR(IF(('Inputs (2)'!AK32)=0,"",('Inputs (2)'!AL32)/('Inputs (2)'!AK32)-1),"") | AM228: =IFERROR(IF(('Inputs (2)'!AH32)=0,"",('Inputs (2)'!AM32)/('Inputs (2)'!AH32)-1),"") | AN228: =IFERROR(IF(('Inputs (2)'!AL32)=0,"",('Inputs (2)'!AN32)/('Inputs (2)'!AL32)-1),"") | AO228: =IFERROR(IF(('Inputs (2)'!AN32)=0,"",('Inputs (2)'!AO32)/('Inputs (2)'!AN32)-1),"") | AP228: =IFERROR(IF(('Inputs (2)'!AO32)=0,"",('Inputs (2)'!AP32)/('Inputs (2)'!AO32)-1),"") | AQ228: =IFERROR(IF(('Inputs (2)'!AP32)=0,"",('Inputs (2)'!AQ32)/('Inputs (2)'!AP32)-1),"") | AR228: =IFERROR(IF(('Inputs (2)'!AM32)=0,"",('Inputs (2)'!AR32)/('Inputs (2)'!AM32)-1),"") | AS228: =IFERROR(IF(('Inputs (2)'!AQ32)=0,"",('Inputs (2)'!AS32)/('Inputs (2)'!AQ32)-1),"") | AT228: =IFERROR(IF(('Inputs (2)'!AS32)=0,"",('Inputs (2)'!AT32)/('Inputs (2)'!AS32)-1),"") | AU228: =IFERROR(IF(('Inputs (2)'!AT32)=0,"",('Inputs (2)'!AU32)/('Inputs (2)'!AT32)-1),"") | AV228: =IFERROR(IF(('Inputs (2)'!AU32)=0,"",('Inputs (2)'!AV32)/('Inputs (2)'!AU32)-1),"") | AW228: =IFERROR(IF(('Inputs (2)'!AR32)=0,"",('Inputs (2)'!AW32)/('Inputs (2)'!AR32)-1),"") | AX228: =IFERROR(IF(('Inputs (2)'!AV32)=0,"",('Inputs (2)'!AX32)/('Inputs (2)'!AV32)-1),"") | AY228: =IFERROR(IF(('Inputs (2)'!AX32)=0,"",('Inputs (2)'!AY32)/('Inputs (2)'!AX32)-1),"") | AZ228: =IFERROR(IF(('Inputs (2)'!AY32)=0,"",('Inputs (2)'!AZ32)/('Inputs (2)'!AY32)-1),"") | BA228: =IFERROR(IF(('Inputs (2)'!AZ32)=0,"",('Inputs (2)'!BA32)/('Inputs (2)'!AZ32)-1),"") | BB228: =IFERROR(IF(('Inputs (2)'!AW32)=0,"",('Inputs (2)'!BB32)/('Inputs (2)'!AW32)-1),"") | BC228: =IFERROR(IF(('Inputs (2)'!BA32)=0,"",('Inputs (2)'!BC32)/('Inputs (2)'!BA32)-1),"") | BD228: =IFERROR(IF(('Inputs (2)'!BC32)=0,"",('Inputs (2)'!BD32)/('Inputs (2)'!BC32)-1),"") | BE228: =IFERROR(IF(('Inputs (2)'!BD32)=0,"",('Inputs (2)'!BE32)/('Inputs (2)'!BD32)-1),"") | BF228: =IFERROR(IF(('Inputs (2)'!BE32)=0,"",('Inputs (2)'!BF32)/('Inputs (2)'!BE32)-1),"") | BG228: =IFERROR(IF(('Inputs (2)'!BB32)=0,"",('Inputs (2)'!BG32)/('Inputs (2)'!BB32)-1),"")
C229: Instrumentos de dívida — crescimento % QoQ | D229: Debt growth QoQ | F229: =IFERROR(IF(('Inputs (2)'!E42)=0,"",('Inputs (2)'!F42)/('Inputs (2)'!E42)-1),"") | G229: =IFERROR(IF(('Inputs (2)'!F42)=0,"",('Inputs (2)'!G42)/('Inputs (2)'!F42)-1),"") | H229: =IFERROR(IF(('Inputs (2)'!G42)=0,"",('Inputs (2)'!H42)/('Inputs (2)'!G42)-1),"") | J229: =IFERROR(IF(('Inputs (2)'!H42)=0,"",('Inputs (2)'!J42)/('Inputs (2)'!H42)-1),"") | K229: =IFERROR(IF(('Inputs (2)'!J42)=0,"",('Inputs (2)'!K42)/('Inputs (2)'!J42)-1),"") | L229: =IFERROR(IF(('Inputs (2)'!K42)=0,"",('Inputs (2)'!L42)/('Inputs (2)'!K42)-1),"") | M229: =IFERROR(IF(('Inputs (2)'!L42)=0,"",('Inputs (2)'!M42)/('Inputs (2)'!L42)-1),"") | N229: =IFERROR(IF(('Inputs (2)'!I42)=0,"",('Inputs (2)'!N42)/('Inputs (2)'!I42)-1),"") | O229: =IFERROR(IF(('Inputs (2)'!M42)=0,"",('Inputs (2)'!O42)/('Inputs (2)'!M42)-1),"") | P229: =IFERROR(IF(('Inputs (2)'!O42)=0,"",('Inputs (2)'!P42)/('Inputs (2)'!O42)-1),"") | Q229: =IFERROR(IF(('Inputs (2)'!P42)=0,"",('Inputs (2)'!Q42)/('Inputs (2)'!P42)-1),"") | R229: =IFERROR(IF(('Inputs (2)'!Q42)=0,"",('Inputs (2)'!R42)/('Inputs (2)'!Q42)-1),"") | S229: =IFERROR(IF(('Inputs (2)'!N42)=0,"",('Inputs (2)'!S42)/('Inputs (2)'!N42)-1),"") | T229: =IFERROR(IF(('Inputs (2)'!R42)=0,"",('Inputs (2)'!T42)/('Inputs (2)'!R42)-1),"") | U229: =IFERROR(IF(('Inputs (2)'!T42)=0,"",('Inputs (2)'!U42)/('Inputs (2)'!T42)-1),"") | V229: =IFERROR(IF(('Inputs (2)'!U42)=0,"",('Inputs (2)'!V42)/('Inputs (2)'!U42)-1),"") | W229: =IFERROR(IF(('Inputs (2)'!V42)=0,"",('Inputs (2)'!W42)/('Inputs (2)'!V42)-1),"") | X229: =IFERROR(IF(('Inputs (2)'!S42)=0,"",('Inputs (2)'!X42)/('Inputs (2)'!S42)-1),"") | Y229: =IFERROR(IF(('Inputs (2)'!W42)=0,"",('Inputs (2)'!Y42)/('Inputs (2)'!W42)-1),"") | Z229: =IFERROR(IF(('Inputs (2)'!Y42)=0,"",('Inputs (2)'!Z42)/('Inputs (2)'!Y42)-1),"") | AA229: =IFERROR(IF(('Inputs (2)'!Z42)=0,"",('Inputs (2)'!AA42)/('Inputs (2)'!Z42)-1),"") | AB229: =IFERROR(IF(('Inputs (2)'!AA42)=0,"",('Inputs (2)'!AB42)/('Inputs (2)'!AA42)-1),"") | AC229: =IFERROR(IF(('Inputs (2)'!X42)=0,"",('Inputs (2)'!AC42)/('Inputs (2)'!X42)-1),"") | AD229: =IFERROR(IF(('Inputs (2)'!AB42)=0,"",('Inputs (2)'!AD42)/('Inputs (2)'!AB42)-1),"") | AE229: =IFERROR(IF(('Inputs (2)'!AD42)=0,"",('Inputs (2)'!AE42)/('Inputs (2)'!AD42)-1),"") | AF229: =IFERROR(IF(('Inputs (2)'!AE42)=0,"",('Inputs (2)'!AF42)/('Inputs (2)'!AE42)-1),"") | AG229: =IFERROR(IF(('Inputs (2)'!AF42)=0,"",('Inputs (2)'!AG42)/('Inputs (2)'!AF42)-1),"") | AH229: =IFERROR(IF(('Inputs (2)'!AC42)=0,"",('Inputs (2)'!AH42)/('Inputs (2)'!AC42)-1),"") | AI229: =IFERROR(IF(('Inputs (2)'!AG42)=0,"",('Inputs (2)'!AI42)/('Inputs (2)'!AG42)-1),"") | AJ229: =IFERROR(IF(('Inputs (2)'!AI42)=0,"",('Inputs (2)'!AJ42)/('Inputs (2)'!AI42)-1),"") | AK229: =IFERROR(IF(('Inputs (2)'!AJ42)=0,"",('Inputs (2)'!AK42)/('Inputs (2)'!AJ42)-1),"") | AL229: =IFERROR(IF(('Inputs (2)'!AK42)=0,"",('Inputs (2)'!AL42)/('Inputs (2)'!AK42)-1),"") | AM229: =IFERROR(IF(('Inputs (2)'!AH42)=0,"",('Inputs (2)'!AM42)/('Inputs (2)'!AH42)-1),"") | AN229: =IFERROR(IF(('Inputs (2)'!AL42)=0,"",('Inputs (2)'!AN42)/('Inputs (2)'!AL42)-1),"") | AO229: =IFERROR(IF(('Inputs (2)'!AN42)=0,"",('Inputs (2)'!AO42)/('Inputs (2)'!AN42)-1),"") | AP229: =IFERROR(IF(('Inputs (2)'!AO42)=0,"",('Inputs (2)'!AP42)/('Inputs (2)'!AO42)-1),"") | AQ229: =IFERROR(IF(('Inputs (2)'!AP42)=0,"",('Inputs (2)'!AQ42)/('Inputs (2)'!AP42)-1),"") | AR229: =IFERROR(IF(('Inputs (2)'!AM42)=0,"",('Inputs (2)'!AR42)/('Inputs (2)'!AM42)-1),"") | AS229: =IFERROR(IF(('Inputs (2)'!AQ42)=0,"",('Inputs (2)'!AS42)/('Inputs (2)'!AQ42)-1),"") | AT229: =IFERROR(IF(('Inputs (2)'!AS42)=0,"",('Inputs (2)'!AT42)/('Inputs (2)'!AS42)-1),"") | AU229: =IFERROR(IF(('Inputs (2)'!AT42)=0,"",('Inputs (2)'!AU42)/('Inputs (2)'!AT42)-1),"") | AV229: =IFERROR(IF(('Inputs (2)'!AU42)=0,"",('Inputs (2)'!AV42)/('Inputs (2)'!AU42)-1),"") | AW229: =IFERROR(IF(('Inputs (2)'!AR42)=0,"",('Inputs (2)'!AW42)/('Inputs (2)'!AR42)-1),"") | AX229: =IFERROR(IF(('Inputs (2)'!AV42)=0,"",('Inputs (2)'!AX42)/('Inputs (2)'!AV42)-1),"") | AY229: =IFERROR(IF(('Inputs (2)'!AX42)=0,"",('Inputs (2)'!AY42)/('Inputs (2)'!AX42)-1),"") | AZ229: =IFERROR(IF(('Inputs (2)'!AY42)=0,"",('Inputs (2)'!AZ42)/('Inputs (2)'!AY42)-1),"") | BA229: =IFERROR(IF(('Inputs (2)'!AZ42)=0,"",('Inputs (2)'!BA42)/('Inputs (2)'!AZ42)-1),"") | BB229: =IFERROR(IF(('Inputs (2)'!AW42)=0,"",('Inputs (2)'!BB42)/('Inputs (2)'!AW42)-1),"") | BC229: =IFERROR(IF(('Inputs (2)'!BA42)=0,"",('Inputs (2)'!BC42)/('Inputs (2)'!BA42)-1),"") | BD229: =IFERROR(IF(('Inputs (2)'!BC42)=0,"",('Inputs (2)'!BD42)/('Inputs (2)'!BC42)-1),"") | BE229: =IFERROR(IF(('Inputs (2)'!BD42)=0,"",('Inputs (2)'!BE42)/('Inputs (2)'!BD42)-1),"") | BF229: =IFERROR(IF(('Inputs (2)'!BE42)=0,"",('Inputs (2)'!BF42)/('Inputs (2)'!BE42)-1),"") | BG229: =IFERROR(IF(('Inputs (2)'!BB42)=0,"",('Inputs (2)'!BG42)/('Inputs (2)'!BB42)-1),"")
C230: Empréstimos e repasses — crescimento % QoQ | D230: Borrowings growth QoQ | F230: =IFERROR(IF(('Inputs (2)'!E47)=0,"",('Inputs (2)'!F47)/('Inputs (2)'!E47)-1),"") | G230: =IFERROR(IF(('Inputs (2)'!F47)=0,"",('Inputs (2)'!G47)/('Inputs (2)'!F47)-1),"") | H230: =IFERROR(IF(('Inputs (2)'!G47)=0,"",('Inputs (2)'!H47)/('Inputs (2)'!G47)-1),"") | J230: =IFERROR(IF(('Inputs (2)'!H47)=0,"",('Inputs (2)'!J47)/('Inputs (2)'!H47)-1),"") | K230: =IFERROR(IF(('Inputs (2)'!J47)=0,"",('Inputs (2)'!K47)/('Inputs (2)'!J47)-1),"") | L230: =IFERROR(IF(('Inputs (2)'!K47)=0,"",('Inputs (2)'!L47)/('Inputs (2)'!K47)-1),"") | M230: =IFERROR(IF(('Inputs (2)'!L47)=0,"",('Inputs (2)'!M47)/('Inputs (2)'!L47)-1),"") | N230: =IFERROR(IF(('Inputs (2)'!I47)=0,"",('Inputs (2)'!N47)/('Inputs (2)'!I47)-1),"") | O230: =IFERROR(IF(('Inputs (2)'!M47)=0,"",('Inputs (2)'!O47)/('Inputs (2)'!M47)-1),"") | P230: =IFERROR(IF(('Inputs (2)'!O47)=0,"",('Inputs (2)'!P47)/('Inputs (2)'!O47)-1),"") | Q230: =IFERROR(IF(('Inputs (2)'!P47)=0,"",('Inputs (2)'!Q47)/('Inputs (2)'!P47)-1),"") | R230: =IFERROR(IF(('Inputs (2)'!Q47)=0,"",('Inputs (2)'!R47)/('Inputs (2)'!Q47)-1),"") | S230: =IFERROR(IF(('Inputs (2)'!N47)=0,"",('Inputs (2)'!S47)/('Inputs (2)'!N47)-1),"") | T230: =IFERROR(IF(('Inputs (2)'!R47)=0,"",('Inputs (2)'!T47)/('Inputs (2)'!R47)-1),"") | U230: =IFERROR(IF(('Inputs (2)'!T47)=0,"",('Inputs (2)'!U47)/('Inputs (2)'!T47)-1),"") | V230: =IFERROR(IF(('Inputs (2)'!U47)=0,"",('Inputs (2)'!V47)/('Inputs (2)'!U47)-1),"") | W230: =IFERROR(IF(('Inputs (2)'!V47)=0,"",('Inputs (2)'!W47)/('Inputs (2)'!V47)-1),"") | X230: =IFERROR(IF(('Inputs (2)'!S47)=0,"",('Inputs (2)'!X47)/('Inputs (2)'!S47)-1),"") | Y230: =IFERROR(IF(('Inputs (2)'!W47)=0,"",('Inputs (2)'!Y47)/('Inputs (2)'!W47)-1),"") | Z230: =IFERROR(IF(('Inputs (2)'!Y47)=0,"",('Inputs (2)'!Z47)/('Inputs (2)'!Y47)-1),"") | AA230: =IFERROR(IF(('Inputs (2)'!Z47)=0,"",('Inputs (2)'!AA47)/('Inputs (2)'!Z47)-1),"") | AB230: =IFERROR(IF(('Inputs (2)'!AA47)=0,"",('Inputs (2)'!AB47)/('Inputs (2)'!AA47)-1),"") | AC230: =IFERROR(IF(('Inputs (2)'!X47)=0,"",('Inputs (2)'!AC47)/('Inputs (2)'!X47)-1),"") | AD230: =IFERROR(IF(('Inputs (2)'!AB47)=0,"",('Inputs (2)'!AD47)/('Inputs (2)'!AB47)-1),"") | AE230: =IFERROR(IF(('Inputs (2)'!AD47)=0,"",('Inputs (2)'!AE47)/('Inputs (2)'!AD47)-1),"") | AF230: =IFERROR(IF(('Inputs (2)'!AE47)=0,"",('Inputs (2)'!AF47)/('Inputs (2)'!AE47)-1),"") | AG230: =IFERROR(IF(('Inputs (2)'!AF47)=0,"",('Inputs (2)'!AG47)/('Inputs (2)'!AF47)-1),"") | AH230: =IFERROR(IF(('Inputs (2)'!AC47)=0,"",('Inputs (2)'!AH47)/('Inputs (2)'!AC47)-1),"") | AI230: =IFERROR(IF(('Inputs (2)'!AG47)=0,"",('Inputs (2)'!AI47)/('Inputs (2)'!AG47)-1),"") | AJ230: =IFERROR(IF(('Inputs (2)'!AI47)=0,"",('Inputs (2)'!AJ47)/('Inputs (2)'!AI47)-1),"") | AK230: =IFERROR(IF(('Inputs (2)'!AJ47)=0,"",('Inputs (2)'!AK47)/('Inputs (2)'!AJ47)-1),"") | AL230: =IFERROR(IF(('Inputs (2)'!AK47)=0,"",('Inputs (2)'!AL47)/('Inputs (2)'!AK47)-1),"") | AM230: =IFERROR(IF(('Inputs (2)'!AH47)=0,"",('Inputs (2)'!AM47)/('Inputs (2)'!AH47)-1),"") | AN230: =IFERROR(IF(('Inputs (2)'!AL47)=0,"",('Inputs (2)'!AN47)/('Inputs (2)'!AL47)-1),"") | AO230: =IFERROR(IF(('Inputs (2)'!AN47)=0,"",('Inputs (2)'!AO47)/('Inputs (2)'!AN47)-1),"") | AP230: =IFERROR(IF(('Inputs (2)'!AO47)=0,"",('Inputs (2)'!AP47)/('Inputs (2)'!AO47)-1),"") | AQ230: =IFERROR(IF(('Inputs (2)'!AP47)=0,"",('Inputs (2)'!AQ47)/('Inputs (2)'!AP47)-1),"") | AR230: =IFERROR(IF(('Inputs (2)'!AM47)=0,"",('Inputs (2)'!AR47)/('Inputs (2)'!AM47)-1),"") | AS230: =IFERROR(IF(('Inputs (2)'!AQ47)=0,"",('Inputs (2)'!AS47)/('Inputs (2)'!AQ47)-1),"") | AT230: =IFERROR(IF(('Inputs (2)'!AS47)=0,"",('Inputs (2)'!AT47)/('Inputs (2)'!AS47)-1),"") | AU230: =IFERROR(IF(('Inputs (2)'!AT47)=0,"",('Inputs (2)'!AU47)/('Inputs (2)'!AT47)-1),"") | AV230: =IFERROR(IF(('Inputs (2)'!AU47)=0,"",('Inputs (2)'!AV47)/('Inputs (2)'!AU47)-1),"") | AW230: =IFERROR(IF(('Inputs (2)'!AR47)=0,"",('Inputs (2)'!AW47)/('Inputs (2)'!AR47)-1),"") | AX230: =IFERROR(IF(('Inputs (2)'!AV47)=0,"",('Inputs (2)'!AX47)/('Inputs (2)'!AV47)-1),"") | AY230: =IFERROR(IF(('Inputs (2)'!AX47)=0,"",('Inputs (2)'!AY47)/('Inputs (2)'!AX47)-1),"") | AZ230: =IFERROR(IF(('Inputs (2)'!AY47)=0,"",('Inputs (2)'!AZ47)/('Inputs (2)'!AY47)-1),"") | BA230: =IFERROR(IF(('Inputs (2)'!AZ47)=0,"",('Inputs (2)'!BA47)/('Inputs (2)'!AZ47)-1),"") | BB230: =IFERROR(IF(('Inputs (2)'!AW47)=0,"",('Inputs (2)'!BB47)/('Inputs (2)'!AW47)-1),"") | BC230: =IFERROR(IF(('Inputs (2)'!BA47)=0,"",('Inputs (2)'!BC47)/('Inputs (2)'!BA47)-1),"") | BD230: =IFERROR(IF(('Inputs (2)'!BC47)=0,"",('Inputs (2)'!BD47)/('Inputs (2)'!BC47)-1),"") | BE230: =IFERROR(IF(('Inputs (2)'!BD47)=0,"",('Inputs (2)'!BE47)/('Inputs (2)'!BD47)-1),"") | BF230: =IFERROR(IF(('Inputs (2)'!BE47)=0,"",('Inputs (2)'!BF47)/('Inputs (2)'!BE47)-1),"") | BG230: =IFERROR(IF(('Inputs (2)'!BB47)=0,"",('Inputs (2)'!BG47)/('Inputs (2)'!BB47)-1),"")
...

Sheet Inputs (2)
C1: ="Demonstrações reportadas — valores em "&Inputs!$E$202 -> Demonstrações reportadas — valores em R$ milhões | D1: Reported financials | E1: =DATE(2020,4,1)-1 -> 43921 | F1: =DATE(2020,7,1)-1 -> 44012 | G1: =DATE(2020,10,1)-1 -> 44104 | H1: =DATE(2020,13,1)-1 -> 44196 | I1: =H1 -> 44196 | J1: =DATE(2021,4,1)-1 -> 44286 | K1: =DATE(2021,7,1)-1 -> 44377 | L1: =DATE(2021,10,1)-1 -> 44469 | M1: =DATE(2021,13,1)-1 -> 44561 | N1: =M1 -> 44561 | O1: =DATE(2022,4,1)-1 -> 44651 | P1: =DATE(2022,7,1)-1 -> 44742 | Q1: =DATE(2022,10,1)-1 -> 44834 | R1: =DATE(2022,13,1)-1 -> 44926 | S1: =R1 -> 44926 | T1: =DATE(2023,4,1)-1 -> 45016 | U1: =DATE(2023,7,1)-1 -> 45107 | V1: =DATE(2023,10,1)-1 -> 45199 | W1: =DATE(2023,13,1)-1 -> 45291 | X1: =W1 -> 45291 | Y1: =DATE(2024,4,1)-1 -> 45382 | Z1: =DATE(2024,7,1)-1 -> 45473 | AA1: =DATE(2024,10,1)-1 -> 45565 | AB1: =DATE(2024,13,1)-1 -> 45657 | AC1: =AB1 -> 45657 | AD1: =DATE(2025,4,1)-1 -> 45747 | AE1: =DATE(2025,7,1)-1 -> 45838 | AF1: =DATE(2025,10,1)-1 -> 45930 | AG1: =DATE(2025,13,1)-1 -> 46022 | AH1: =AG1 -> 46022 | AI1: =DATE(2026,4,1)-1 -> 46112 | AJ1: =DATE(2026,7,1)-1 -> 46203 | AK1: =DATE(2026,10,1)-1 -> 46295 | AL1: =DATE(2026,13,1)-1 -> 46387 | AM1: =AL1 -> 46387 | AN1: =DATE(2027,4,1)-1 -> 46477 | AO1: =DATE(2027,7,1)-1 -> 46568 | AP1: =DATE(2027,10,1)-1 -> 46660 | AQ1: =DATE(2027,13,1)-1 -> 46752 | AR1: =AQ1 -> 46752 | AS1: =DATE(2028,4,1)-1 -> 46843 | AT1: =DATE(2028,7,1)-1 -> 46934 | AU1: =DATE(2028,10,1)-1 -> 47026 | AV1: =DATE(2028,13,1)-1 -> 47118 | AW1: =AV1 -> 47118 | AX1: =DATE(2029,4,1)-1 -> 47208 | AY1: =DATE(2029,7,1)-1 -> 47299 | AZ1: =DATE(2029,10,1)-1 -> 47391 | BA1: =DATE(2029,13,1)-1 -> 47483 | BB1: =BA1 -> 47483 | BC1: =DATE(2030,4,1)-1 -> 47573 | BD1: =DATE(2030,7,1)-1 -> 47664 | BE1: =DATE(2030,10,1)-1 -> 47756 | BF1: =DATE(2030,13,1)-1 -> 47848 | BG1: =BF1 -> 47848
B2: COD | E2: 2020 | F2: 2020 | G2: 2020 | H2: 2020 | I2: 2020 | J2: 2021 | K2: 2021 | L2: 2021 | M2: 2021 | N2: 2021 | O2: 2022 | P2: 2022 | Q2: 2022 | R2: 2022 | S2: 2022 | T2: 2023 | U2: 2023 | V2: 2023 | W2: 2023 | X2: 2023 | Y2: 2024 | Z2: 2024 | AA2: 2024 | AB2: 2024 | AC2: 2024 | AD2: 2025 | AE2: 2025 | AF2: 2025 | AG2: 2025 | AH2: 2025 | AI2: 2026 | AJ2: 2026 | AK2: 2026 | AL2: 2026 | AM2: 2026 | AN2: 2027 | AO2: 2027 | AP2: 2027 | AQ2: 2027 | AR2: 2027 | AS2: 2028 | AT2: 2028 | AU2: 2028 | AV2: 2028 | AW2: 2028 | AX2: 2029 | AY2: 2029 | AZ2: 2029 | BA2: 2029 | BB2: 2029 | BC2: 2030 | BD2: 2030 | BE2: 2030 | BF2: 2030 | BG2: 2030
C3: Período | D3: Period | E3: ="1Q"&RIGHT(E2,2) -> 1Q20 | F3: ="2Q"&RIGHT(F2,2) -> 2Q20 | G3: ="3Q"&RIGHT(G2,2) -> 3Q20 | H3: ="4Q"&RIGHT(H2,2) -> 4Q20 | I3: ="FY"&RIGHT(I2,2) -> FY20 | J3: ="1Q"&RIGHT(J2,2) -> 1Q21 | K3: ="2Q"&RIGHT(K2,2) -> 2Q21 | L3: ="3Q"&RIGHT(L2,2) -> 3Q21 | M3: ="4Q"&RIGHT(M2,2) -> 4Q21 | N3: ="FY"&RIGHT(N2,2) -> FY21 | O3: ="1Q"&RIGHT(O2,2) -> 1Q22 | P3: ="2Q"&RIGHT(P2,2) -> 2Q22 | Q3: ="3Q"&RIGHT(Q2,2) -> 3Q22 | R3: ="4Q"&RIGHT(R2,2) -> 4Q22 | S3: ="FY"&RIGHT(S2,2) -> FY22 | T3: ="1Q"&RIGHT(T2,2) -> 1Q23 | U3: ="2Q"&RIGHT(U2,2) -> 2Q23 | V3: ="3Q"&RIGHT(V2,2) -> 3Q23 | W3: ="4Q"&RIGHT(W2,2) -> 4Q23 | X3: ="FY"&RIGHT(X2,2) -> FY23 | Y3: ="1Q"&RIGHT(Y2,2) -> 1Q24 | Z3: ="2Q"&RIGHT(Z2,2) -> 2Q24 | AA3: ="3Q"&RIGHT(AA2,2) -> 3Q24 | AB3: ="4Q"&RIGHT(AB2,2) -> 4Q24 | AC3: ="FY"&RIGHT(AC2,2) -> FY24 | AD3: ="1Q"&RIGHT(AD2,2) -> 1Q25 | AE3: ="2Q"&RIGHT(AE2,2) -> 2Q25 | AF3: ="3Q"&RIGHT(AF2,2) -> 3Q25 | AG3: ="4Q"&RIGHT(AG2,2) -> 4Q25 | AH3: ="FY"&RIGHT(AH2,2) -> FY25 | AI3: ="1Q"&RIGHT(AI2,2) -> 1Q26 | AJ3: ="2Q"&RIGHT(AJ2,2) -> 2Q26 | AK3: ="3Q"&RIGHT(AK2,2) -> 3Q26 | AL3: ="4Q"&RIGHT(AL2,2) -> 4Q26 | AM3: ="FY"&RIGHT(AM2,2) -> FY26 | AN3: ="1Q"&RIGHT(AN2,2) -> 1Q27 | AO3: ="2Q"&RIGHT(AO2,2) -> 2Q27 | AP3: ="3Q"&RIGHT(AP2,2) -> 3Q27 | AQ3: ="4Q"&RIGHT(AQ2,2) -> 4Q27 | AR3: ="FY"&RIGHT(AR2,2) -> FY27 | AS3: ="1Q"&RIGHT(AS2,2) -> 1Q28 | AT3: ="2Q"&RIGHT(AT2,2) -> 2Q28 | AU3: ="3Q"&RIGHT(AU2,2) -> 3Q28 | AV3: ="4Q"&RIGHT(AV2,2) -> 4Q28 | AW3: ="FY"&RIGHT(AW2,2) -> FY28 | AX3: ="1Q"&RIGHT(AX2,2) -> 1Q29 | AY3: ="2Q"&RIGHT(AY2,2) -> 2Q29 | AZ3: ="3Q"&RIGHT(AZ2,2) -> 3Q29 | BA3: ="4Q"&RIGHT(BA2,2) -> 4Q29 | BB3: ="FY"&RIGHT(BB2,2) -> FY29 | BC3: ="1Q"&RIGHT(BC2,2) -> 1Q30 | BD3: ="2Q"&RIGHT(BD2,2) -> 2Q30 | BE3: ="3Q"&RIGHT(BE2,2) -> 3Q30 | BF3: ="4Q"&RIGHT(BF2,2) -> 4Q30 | BG3: ="FY"&RIGHT(BG2,2) -> FY30
C4: ATIVO | D4: ASSETS
B5: disp | C5: Disponibilidades | D5: Cash and Cash Equivalents | E5: =IF(ISNA(SUMIFS(INDEX(Inputs!$B$2:$AZ$190,,MATCH(SUBSTITUTE(E$3,"Q","T"),Inputs!$B$2:$AZ$2,0)),Inputs!$B$2:$B$190,$B5)*Inputs!$D$1),"",SUMIFS(INDEX(Inputs!$B$2:$AZ$190,,MATCH(SUBSTITUTE(E$3,"Q","T"),Inputs!$B$2:$AZ$2,0)),Inputs!$B$2:$B$190,$B5)*Inputs!$D$1) -> 0 | F5: =IF(ISNA(SUMIFS(INDEX(Inputs!$B$2:$AZ$190,,MATCH(SUBSTITUTE(F$3,"Q","T"),Inputs!$B$2:$AZ$2,0)),Inputs!$B$2:$B$190,$B5)*Inputs!$D$1),"",SUMIFS(INDEX(Inputs!$B$2:$AZ$190,,MATCH(SUBSTITUTE(F$3,"Q","T"),Inputs!$B$2:$AZ$2,0)),Inputs!$B$2:$B$190,$B5)*Inputs!$D$1) -> 0 | G5: =IF(ISNA(SUMIFS(INDEX(Inputs!$B$2:$AZ$190,,MATCH(SUBSTITUTE(G$3,"Q","T"),Inputs!$B$2:$AZ$2,0)),Inputs!$B$2:$B$190,$B5)*Inputs!$D$1),"",SUMIFS(INDEX(Inputs!$B$2:$AZ$190,,MATCH(SUBSTITUTE(G$3,"Q","T"),Inputs!$B$2:$AZ$2,0)),Inputs!$B$2:$B$190,$B5)*Inputs!$D$1) -> 0 | H5: =IF(ISNA(SUMIFS(INDEX(Inputs!$B$2:$AZ$190,,MATCH(SUBSTITUTE(H$3,"Q","T"),Inputs!$B$2:$AZ$2,0)),Inputs!$B$2:$B$190,$B5)*Inputs!$D$1),"",SUMIFS(INDEX(Inputs!$B$2:$AZ$190,,MATCH(SUBSTITUTE(H$3,"Q","T"),Inputs!$B$2:$AZ$2,0)),Inputs!$B$2:$B$190,$B5)*Inputs!$D$1) -> 0 | I5: =H5 -> 0 | J5: =IF(ISNA(SUMIFS(INDEX(Inputs!$B$2:$AZ$190,,MATCH(SUBSTITUTE(J$3,"Q","T"),Inputs!$B$2:$AZ$2,0)),Inputs!$B$2:$B$190,$B5)*Inputs!$D$1),"",SUMIFS(INDEX(Inputs!$B$2:$AZ$190,,MATCH(SUBSTITUTE(J$3,"Q","T"),Inputs!$B$2:$AZ$2,0)),Inputs!$B$2:$B$190,$B5)*Inputs!$D$1) -> 0 | K5: =IF(ISNA(SUMIFS(INDEX(Inputs!$B$2:$AZ$190,,MATCH(SUBSTITUTE(K$3,"Q","T"),Inputs!$B$2:$AZ$2,0)),Inputs!$B$2:$B$190,$B5)*Inputs!$D$1),"",SUMIFS(INDEX(Inputs!$B$2:$AZ$190,,MATCH(SUBSTITUTE(K$3,"Q","T"),Inputs!$B$2:$AZ$2,0)),Inputs!$B$2:$B$190,$B5)*Inputs!$D$1) -> 0 | L5: =IF(ISNA(SUMIFS(INDEX(Inputs!$B$2:$AZ$190,,MATCH(SUBSTITUTE(L$3,"Q","T"),Inputs!$B$2:$AZ$2,0)),Inputs!$B$2:$B$190,$B5)*Inputs!$D$1),"",SUMIFS(INDEX(Inputs!$B$2:$AZ$190,,MATCH(SUBSTITUTE(L$3,"Q","T"),Inputs!$B$2:$AZ$2,0)),Inputs!$B$2:$B$190,$B5)*Inputs!$D$1) -> 0 | M5: =IF(ISNA(SUMIFS(INDEX(Inputs!$B$2:$AZ$190,,MATCH(SUBSTITUTE(M$3,"Q","T"),Inputs!$B$2:$AZ$2,0)),Inputs!$B$2:$B$190,$B5)*Inputs!$D$1),"",SUMIFS(INDEX(Inputs!$B$2:$AZ$190,,MATCH(SUBSTITUTE(M$3,"Q","T"),Inputs!$B$2:$AZ$2,0)),Inputs!$B$2:$B$190,$B5)*Inputs!$D$1) -> 0 | N5: =M5 -> 0 | O5: =IF(ISNA(SUMIFS(INDEX(Inputs!$B$2:$AZ$190,,MATCH(SUBSTITUTE(O$3,"Q","T"),Inputs!$B$2:$AZ$2,0)),Inputs!$B$2:$B$190,$B5)*Inputs!$D$1),"",SUMIFS(INDEX(Inputs!$B$2:$AZ$190,,MATCH(SUBSTITUTE(O$3,"Q","T"),Inputs!$B$2:$AZ$2,0)),Inputs!$B$2:$B$190,$B5)*Inputs!$D$1) -> 0 | P5: =IF(ISNA(SUMIFS(INDEX(Inputs!$B$2:$AZ$190,,MATCH(SUBSTITUTE(P$3,"Q","T"),Inputs!$B$2:$AZ$2,0)),Inputs!$B$2:$B$190,$B5)*Inputs!$D$1),"",SUMIFS(INDEX(Inputs!$B$2:$AZ$190,,MATCH(SUBSTITUTE(P$3,"Q","T"),Inputs!$B$2:$AZ$2,0)),Inputs!$B$2:$B$190,$B5)*Inputs!$D$1) -> 0 | Q5: =IF(ISNA(SUMIFS(INDEX(Inputs!$B$2:$AZ$190,,MATCH(SUBSTITUTE(Q$3,"Q","T"),Inputs!$B$2:$AZ$2,0)),Inputs!$B$2:$B$190,$B5)*Inputs!$D$1),"",SUMIFS(INDEX(Inputs!$B$2:$AZ$190,,MATCH(SUBSTITUTE(Q$3,"Q","T"),Inputs!$B$2:$AZ$2,0)),Inputs!$B$2:$B$190,$B5)*Inputs!$D$1) -> 0 | R5: =IF(ISNA(SUMIFS(INDEX(Inputs!$B$2:$AZ$190,,MATCH(SUBSTITUTE(R$3,"Q","T"),Inputs!$B$2:$AZ$2,0)),Inputs!$B$2:$B$190,$B5)*Inputs!$D$1),"",SUMIFS(INDEX(Inputs!$B$2:$AZ$190,,MATCH(SUBSTITUTE(R$3,"Q","T"),Inputs!$B$2:$AZ$2,0)),Inputs!$B$2:$B$190,$B5)*Inputs!$D$1) -> 0 | S5: =R5 -> 0 | T5: =IF(ISNA(SUMIFS(INDEX(Inputs!$B$2:$AZ$190,,MATCH(SUBSTITUTE(T$3,"Q","T"),Inputs!$B$2:$AZ$2,0)),Inputs!$B$2:$B$190,$B5)*Inputs!$D$1),"",SUMIFS(INDEX(Inputs!$B$2:$AZ$190,,MATCH(SUBSTITUTE(T$3,"Q","T"),Inputs!$B$2:$AZ$2,0)),Inputs!$B$2:$B$190,$B5)*Inputs!$D$1) -> 0 | U5: =IF(ISNA(SUMIFS(INDEX(Inputs!$B$2:$AZ$190,,MATCH(SUBSTITUTE(U$3,"Q","T"),Inputs!$B$2:$AZ$2,0)),Inputs!$B$2:$B$190,$B5)*Inputs!$D$1),"",SUMIFS(INDEX(Inputs!$B$2:$AZ$190,,MATCH(SUBSTITUTE(U$3,"Q","T"),Inputs!$B$2:$AZ$2,0)),Inputs!$B$2:$B$190,$B5)*Inputs!$D$1) -> 0 | V5: =IF(ISNA(SUMIFS(INDEX(Inputs!$B$2:$AZ$190,,MATCH(SUBSTITUTE(V$3,"Q","T"),Inputs!$B$2:$AZ$2,0)),Inputs!$B$2:$B$190,$B5)*Inputs!$D$1),"",SUMIFS(INDEX(Inputs!$B$2:$AZ$190,,MATCH(SUBSTITUTE(V$3,"Q","T"),Inputs!$B$2:$AZ$2,0)),Inputs!$B$2:$B$190,$B5)*Inputs!$D$1) -> 0 | W5: =IF(ISNA(SUMIFS(INDEX(Inputs!$B$2:$AZ$190,,MATCH(SUBSTITUTE(W$3,"Q","T"),Inputs!$B$2:$AZ$2,0)),Inputs!$B$2:$B$190,$B5)*Inputs!$D$1),"",SUMIFS(INDEX(Inputs!$B$2:$AZ$190,,MATCH(SUBSTITUTE(W$3,"Q","T"),Inputs!$B$2:$AZ$2,0)),Inputs!$B$2:$B$190,$B5)*Inputs!$D$1) -> 0 | X5: =W5 -> 0 | Y5: =IF(ISNA(SUMIFS(INDEX(Inputs!$B$2:$AZ$190,,MATCH(SUBSTITUTE(Y$3,"Q","T"),Inputs!$B$2:$AZ$2,0)),Inputs!$B$2:$B$190,$B5)*Inputs!$D$1),"",SUMIFS(INDEX(Inputs!$B$2:$AZ$190,,MATCH(SUBSTITUTE(Y$3,"Q","T"),Inputs!$B$2:$AZ$2,0)),Inputs!$B$2:$B$190,$B5)*Inputs!$D$1) -> 0 | Z5: =IF(ISNA(SUMIFS(INDEX(Inputs!$B$2:$AZ$190,,MATCH(SUBSTITUTE(Z$3,"Q","T"),Inputs!$B$2:$AZ$2,0)),Inputs!$B$2:$B$190,$B5)*Inputs!$D$1),"",SUMIFS(INDEX(Inputs!$B$2:$AZ$190,,MATCH(SUBSTITUTE(Z$3,"Q","T"),Inputs!$B$2:$AZ$2,0)),Inputs!$B$2:$B$190,$B5)*Inputs!$D$1) -> 0 | AA5: =IF(ISNA(SUMIFS(INDEX(Inputs!$B$2:$AZ$190,,MATCH(SUBSTITUTE(AA$3,"Q","T"),Inputs!$B$2:$AZ$2,0)),Inputs!$B$2:$B$190,$B5)*Inputs!$D$1),"",SUMIFS(INDEX(Inputs!$B$2:$AZ$190,,MATCH(SUBSTITUTE(AA$3,"Q","T"),Inputs!$B$2:$AZ$2,0)),Inputs!$B$2:$B$190,$B5)*Inputs!$D$1) -> 0 | AB5: =IF(ISNA(SUMIFS(INDEX(Inputs!$B$2:$AZ$190,,MATCH(SUBSTITUTE(AB$3,"Q","T"),Inputs!$B$2:$AZ$2,0)),Inputs!$B$2:$B$190,$B5)*Inputs!$D$1),"",SUMIFS(INDEX(Inputs!$B$2:$AZ$190,,MATCH(SUBSTITUTE(AB$3,"Q","T"),Inputs!$B$2:$AZ$2,0)),Inputs!$B$2:$B$190,$B5)*Inputs!$D$1) -> 0 | AC5: =AB5 -> 0 | AD5: =IF(ISNA(SUMIFS(INDEX(Inputs!$B$2:$AZ$190,,MATCH(SUBSTITUTE(AD$3,"Q","T"),Inputs!$B$2:$AZ$2,0)),Inputs!$B$2:$B$190,$B5)*Inputs!$D$1),"",SUMIFS(INDEX(Inputs!$B$2:$AZ$190,,MATCH(SUBSTITUTE(AD$3,"Q","T"),Inputs!$B$2:$AZ$2,0)),Inputs!$B$2:$B$190,$B5)*Inputs!$D$1) -> 0 | AE5: =IF(ISNA(SUMIFS(INDEX(Inputs!$B$2:$AZ$190,,MATCH(SUBSTITUTE(AE$3,"Q","T"),Inputs!$B$2:$AZ$2,0)),Inputs!$B$2:$B$190,$B5)*Inputs!$D$1),"",SUMIFS(INDEX(Inputs!$B$2:$AZ$190,,MATCH(SUBSTITUTE(AE$3,"Q","T"),Inputs!$B$2:$AZ$2,0)),Inputs!$B$2:$B$190,$B5)*Inputs!$D$1) -> 0 | AF5: =IF(ISNA(SUMIFS(INDEX(Inputs!$B$2:$AZ$190,,MATCH(SUBSTITUTE(AF$3,"Q","T"),Inputs!$B$2:$AZ$2,0)),Inputs!$B$2:$B$190,$B5)*Inputs!$D$1),"",SUMIFS(INDEX(Inputs!$B$2:$AZ$190,,MATCH(SUBSTITUTE(AF$3,"Q","T"),Inputs!$B$2:$AZ$2,0)),Inputs!$B$2:$B$190,$B5)*Inputs!$D$1) -> 0 | AG5: =IF(ISNA(SUMIFS(INDEX(Inputs!$B$2:$AZ$190,,MATCH(SUBSTITUTE(AG$3,"Q","T"),Inputs!$B$2:$AZ$2,0)),Inputs!$B$2:$B$190,$B5)*Inputs!$D$1),"",SUMIFS(INDEX(Inputs!$B$2:$AZ$190,,MATCH(SUBSTITUTE(AG$3,"Q","T"),Inputs!$B$2:$AZ$2,0)),Inputs!$B$2:$B$190,$B5)*Inputs!$D$1) -> 0 | AH5: =AG5 -> 0 | AI5: =IF(ISNA(SUMIFS(INDEX(Inputs!$B$2:$AZ$190,,MATCH(SUBSTITUTE(AI$3,"Q","T"),Inputs!$B$2:$AZ$2,0)),Inputs!$B$2:$B$190,$B5)*Inputs!$D$1),"",SUMIFS(INDEX(Inputs!$B$2:$AZ$190,,MATCH(SUBSTITUTE(AI$3,"Q","T"),Inputs!$B$2:$AZ$2,0)),Inputs!$B$2:$B$190,$B5)*Inputs!$D$1) -> 0 | AJ5: =IF(ISNA(SUMIFS(INDEX(Inputs!$B$2:$AZ$190,,MATCH(SUBSTITUTE(AJ$3,"Q","T"),Inputs!$B$2:$AZ$2,0)),Inputs!$B$2:$B$190,$B5)*Inputs!$D$1),"",SUMIFS(INDEX(Inputs!$B$2:$AZ$190,,MATCH(SUBSTITUTE(AJ$3,"Q","T"),Inputs!$B$2:$AZ$2,0)),Inputs!$B$2:$B$190,$B5)*Inputs!$D$1) -> 0 | AK5: =IF(ISNA(SUMIFS(INDEX(Inputs!$B$2:$AZ$190,,MATCH(SUBSTITUTE(AK$3,"Q","T"),Inputs!$B$2:$AZ$2,0)),Inputs!$B$2:$B$190,$B5)*Inputs!$D$1),"",SUMIFS(INDEX(Inputs!$B$2:$AZ$190,,MATCH(SUBSTITUTE(AK$3,"Q","T"),Inputs!$B$2:$AZ$2,0)),Inputs!$B$2:$B$190,$B5)*Inputs!$D$1) -> 0 | AL5: =IF(ISNA(SUMIFS(INDEX(Inputs!$B$2:$AZ$190,,MATCH(SUBSTITUTE(AL$3,"Q","T"),Inputs!$B$2:$AZ$2,0)),Inputs!$B$2:$B$190,$B5)*Inputs!$D$1),"",SUMIFS(INDEX(Inputs!$B$2:$AZ$190,,MATCH(SUBSTITUTE(AL$3,"Q","T"),Inputs!$B$2:$AZ$2,0)),Inputs!$B$2:$B$190,$B5)*Inputs!$D$1) -> 0 | AM5: =AL5 -> 0 | AN5: =IF(ISNA(SUMIFS(INDEX(Inputs!$B$2:$AZ$190,,MATCH(SUBSTITUTE(AN$3,"Q","T"),Inputs!$B$2:$AZ$2,0)),Inputs!$B$2:$B$190,$B5)*Inputs!$D$1),"",SUMIFS(INDEX(Inputs!$B$2:$AZ$190,,MATCH(SUBSTITUTE(AN$3,"Q","T"),Inputs!$B$2:$AZ$2,0)),Inputs!$B$2:$B$190,$B5)*Inputs!$D$1) -> 0 | AO5: =IF(ISNA(SUMIFS(INDEX(Inputs!$B$2:$AZ$190,,MATCH(SUBSTITUTE(AO$3,"Q","T"),Inputs!$B$2:$AZ$2,0)),Inputs!$B$2:$B$190,$B5)*Inputs!$D$1),"",SUMIFS(INDEX(Inputs!$B$2:$AZ$190,,MATCH(SUBSTITUTE(AO$3,"Q","T"),Inputs!$B$2:$AZ$2,0)),Inputs!$B$2:$B$190,$B5)*Inputs!$D$1) -> 0 | AP5: =IF(ISNA(SUMIFS(INDEX(Inputs!$B$2:$AZ$190,,MATCH(SUBSTITUTE(AP$3,"Q","T"),Inputs!$B$2:$AZ$2,0)),Inputs!$B$2:$B$190,$B5)*Inputs!$D$1),"",SUMIFS(INDEX(Inputs!$B$2:$AZ$190,,MATCH(SUBSTITUTE(AP$3,"Q","T"),Inputs!$B$2:$AZ$2,0)),Inputs!$B$2:$B$190,$B5)*Inputs!$D$1) -> 0 | AQ5: =IF(ISNA(SUMIFS(INDEX(Inputs!$B$2:$AZ$190,,MATCH(SUBSTITUTE(AQ$3,"Q","T"),Inputs!$B$2:$AZ$2,0)),Inputs!$B$2:$B$190,$B5)*Inputs!$D$1),"",SUMIFS(INDEX(Inputs!$B$2:$AZ$190,,MATCH(SUBSTITUTE(AQ$3,"Q","T"),Inputs!$B$2:$AZ$2,0)),Inputs!$B$2:$B$190,$B5)*Inputs!$D$1) -> 0 | AR5: =AQ5 -> 0 | AS5: =IF(ISNA(SUMIFS(INDEX(Inputs!$B$2:$AZ$190,,MATCH(SUBSTITUTE(AS$3,"Q","T"),Inputs!$B$2:$AZ$2,0)),Inputs!$B$2:$B$190,$B5)*Inputs!$D$1),"",SUMIFS(INDEX(Inputs!$B$2:$AZ$190,,MATCH(SUBSTITUTE(AS$3,"Q","T"),Inputs!$B$2:$AZ$2,0)),Inputs!$B$2:$B$190,$B5)*Inputs!$D$1) -> 0 | AT5: =IF(ISNA(SUMIFS(INDEX(Inputs!$B$2:$AZ$190,,MATCH(SUBSTITUTE(AT$3,"Q","T"),Inputs!$B$2:$AZ$2,0)),Inputs!$B$2:$B$190,$B5)*Inputs!$D$1),"",SUMIFS(INDEX(Inputs!$B$2:$AZ$190,,MATCH(SUBSTITUTE(AT$3,"Q","T"),Inputs!$B$2:$AZ$2,0)),Inputs!$B$2:$B$190,$B5)*Inputs!$D$1) -> 0 | AU5: =IF(ISNA(SUMIFS(INDEX(Inputs!$B$2:$AZ$190,,MATCH(SUBSTITUTE(AU$3,"Q","T"),Inputs!$B$2:$AZ$2,0)),Inputs!$B$2:$B$190,$B5)*Inputs!$D$1),"",SUMIFS(INDEX(Inputs!$B$2:$AZ$190,,MATCH(SUBSTITUTE(AU$3,"Q","T"),Inputs!$B$2:$AZ$2,0)),Inputs!$B$2:$B$190,$B5)*Inputs!$D$1) -> 0 | AV5: =IF(ISNA(SUMIFS(INDEX(Inputs!$B$2:$AZ$190,,MATCH(SUBSTITUTE(AV$3,"Q","T"),Inputs!$B$2:$AZ$2,0)),Inputs!$B$2:$B$190,$B5)*Inputs!$D$1),"",SUMIFS(INDEX(Inputs!$B$2:$AZ$190,,MATCH(SUBSTITUTE(AV$3,"Q","T"),Inputs!$B$2:$AZ$2,0)),Inputs!$B$2:$B$190,$B5)*Inputs!$D$1) -> 0 | AW5: =AV5 -> 0 | AX5: =IF(ISNA(SUMIFS(INDEX(Inputs!$B$2:$AZ$190,,MATCH(SUBSTITUTE(AX$3,"Q","T"),Inputs!$B$2:$AZ$2,0)),Inputs!$B$2:$B$190,$B5)*Inputs!$D$1),"",SUMIFS(INDEX(Inputs!$B$2:$AZ$190,,MATCH(SUBSTITUTE(AX$3,"Q","T"),Inputs!$B$2:$AZ$2,0)),Inputs!$B$2:$B$190,$B5)*Inputs!$D$1) -> 0 | AY5: =IF(ISNA(SUMIFS(INDEX(Inputs!$B$2:$AZ$190,,MATCH(SUBSTITUTE(AY$3,"Q","T"),Inputs!$B$2:$AZ$2,0)),Inputs!$B$2:$B$190,$B5)*Inputs!$D$1),"",SUMIFS(INDEX(Inputs!$B$2:$AZ$190,,MATCH(SUBSTITUTE(AY$3,"Q","T"),Inputs!$B$2:$AZ$2,0)),Inputs!$B$2:$B$190,$B5)*Inputs!$D$1) -> 0 | AZ5: =IF(ISNA(SUMIFS(INDEX(Inputs!$B$2:$AZ$190,,MATCH(SUBSTITUTE(AZ$3,"Q","T"),Inputs!$B$2:$AZ$2,0)),Inputs!$B$2:$B$190,$B5)*Inputs!$D$1),"",SUMIFS(INDEX(Inputs!$B$2:$AZ$190,,MATCH(SUBSTITUTE(AZ$3,"Q","T"),Inputs!$B$2:$AZ$2,0)),Inputs!$B$2:$B$190,$B5)*Inputs!$D$1) -> 0 | BA5: =IF(ISNA(SUMIFS(INDEX(Inputs!$B$2:$AZ$190,,MATCH(SUBSTITUTE(BA$3,"Q","T"),Inputs!$B$2:$AZ$2,0)),Inputs!$B$2:$B$190,$B5)*Inputs!$D$1),"",SUMIFS(INDEX(Inputs!$B$2:$AZ$190,,MATCH(SUBSTITUTE(BA$3,"Q","T"),Inputs!$B$2:$AZ$2,0)),Inputs!$B$2:$B$190,$B5)*Inputs!$D$1) -> 0 | BB5: =BA5 -> 0 | BC5: =IF(ISNA(SUMIFS(INDEX(Inputs!$B$2:$AZ$190,,MATCH(SUBSTITUTE(BC$3,"Q","T"),Inputs!$B$2:$AZ$2,0)),Inputs!$B$2:$B$190,$B5)*Inputs!$D$1),"",SUMIFS(INDEX(Inputs!$B$2:$AZ$190,,MATCH(SUBSTITUTE(BC$3,"Q","T"),Inputs!$B$2:$AZ$2,0)),Inputs!$B$2:$B$190,$B5)*Inputs!$D$1) -> 0 | BD5: =IF(ISNA(SUMIFS(INDEX(Inputs!$B$2:$AZ$190,,MATCH(SUBSTITUTE(BD$3,"Q","T"),Inputs!$B$2:$AZ$2,0)),Inputs!$B$2:$B$190,$B5)*Inputs!$D$1),"",SUMIFS(INDEX(Inputs!$B$2:$AZ$190,,MATCH(SUBSTITUTE(BD$3,"Q","T"),Inputs!$B$2:$AZ$2,0)),Inputs!$B$2:$B$190,$B5)*Inputs!$D$1) -> 0 | BE5: =IF(ISNA(SUMIFS(INDEX(Inputs!$B$2:$AZ$190,,MATCH(SUBSTITUTE(BE$3,"Q","T"),Inputs!$B$2:$AZ$2,0)),Inputs!$B$2:$B$190,$B5)*Inputs!$D$1),"",SUMIFS(INDEX(Inputs!$B$2:$AZ$190,,MATCH(SUBSTITUTE(BE$3,"Q","T"),Inputs!$B$2:$AZ$2,0)),Inputs!$B$2:$B$190,$B5)*Inputs!$D$1) -> 0 | BF5: =IF(ISNA(SUMIFS(INDEX(Inputs!$B$2:$AZ$190,,MATCH(SUBSTITUTE(BF$3,"Q","T"),Inputs!$B$2:$AZ$2,0)),Inputs!$B$2:$B$190,$B5)*Inputs!$D$1),"",SUMIFS(INDEX(Inputs!$B$2:$AZ$190,,MATCH(SUBSTITUTE(BF$3,"Q","T"),Inputs!$B$2:$AZ$2,0)),Inputs!$B$2:$B$190,$B5)*Inputs!$D$1) -> 0 | BG5: =BF5 -> 0
C6: Aplicações Interfinanceiras de Liquidez | D6: Interbank Investments | E6: =IFERROR(E7+E8+E9+E10,"") -> 0 | F6: =IFERROR(F7+F8+F9+F10,"") -> 0 | G6: =IFERROR(G7+G8+G9+G10,"") -> 0 | H6: =IFERROR(H7+H8+H9+H10,"") -> 0 | I6: =H6 -> 0 | J6: =IFERROR(J7+J8+J9+J10,"") -> 0 | K6: =IFERROR(K7+K8+K9+K10,"") -> 0 | L6: =IFERROR(L7+L8+L9+L10,"") -> 0 | M6: =IFERROR(M7+M8+M9+M10,"") -> 0 | N6: =M6 -> 0 | O6: =IFERROR(O7+O8+O9+O10,"") -> 0 | P6: =IFERROR(P7+P8+P9+P10,"") -> 0 | Q6: =IFERROR(Q7+Q8+Q9+Q10,"") -> 0 | R6: =IFERROR(R7+R8+R9+R10,"") -> 0 | S6: =R6 -> 0 | T6: =IFERROR(T7+T8+T9+T10,"") -> 0 | U6: =IFERROR(U7+U8+U9+U10,"") -> 0 | V6: =IFERROR(V7+V8+V9+V10,"") -> 0 | W6: =IFERROR(W7+W8+W9+W10,"") -> 0 | X6: =W6 -> 0 | Y6: =IFERROR(Y7+Y8+Y9+Y10,"") -> 0 | Z6: =IFERROR(Z7+Z8+Z9+Z10,"") -> 0 | AA6: =IFERROR(AA7+AA8+AA9+AA10,"") -> 0 | AB6: =IFERROR(AB7+AB8+AB9+AB10,"") -> 0 | AC6: =AB6 -> 0 | AD6: =IFERROR(AD7+AD8+AD9+AD10,"") -> 0 | AE6: =IFERROR(AE7+AE8+AE9+AE10,"") -> 0 | AF6: =IFERROR(AF7+AF8+AF9+AF10,"") -> 0 | AG6: =IFERROR(AG7+AG8+AG9+AG10,"") -> 0 | AH6: =AG6 -> 0 | AI6: =IFERROR(AI7+AI8+AI9+AI10,"") -> 0 | AJ6: =IFERROR(AJ7+AJ8+AJ9+AJ10,"") -> 0 | AK6: =IFERROR(AK7+AK8+AK9+AK10,"") -> 0 | AL6: =IFERROR(AL7+AL8+AL9+AL10,"") -> 0 | AM6: =AL6 -> 0 | AN6: =IFERROR(AN7+AN8+AN9+AN10,"") -> 0 | AO6: =IFERROR(AO7+AO8+AO9+AO10,"") -> 0 | AP6: =IFERROR(AP7+AP8+AP9+AP10,"") -> 0 | AQ6: =IFERROR(AQ7+AQ8+AQ9+AQ10,"") -> 0 | AR6: =AQ6 -> 0 | AS6: =IFERROR(AS7+AS8+AS9+AS10,"") -> 0 | AT6: =IFERROR(AT7+AT8+AT9+AT10,"") -> 0 | AU6: =IFERROR(AU7+AU8+AU9+AU10,"") -> 0 | AV6: =IFERROR(AV7+AV8+AV9+AV10,"") -> 0 | AW6: =AV6 -> 0 | AX6: =IFERROR(AX7+AX8+AX9+AX10,"") -> 0 | AY6: =IFERROR(AY7+AY8+AY9+AY10,"") -> 0 | AZ6: =IFERROR(AZ7+AZ8+AZ9+AZ10,"") -> 0 | BA6: =IFERROR(BA7+BA8+BA9+BA10,"") -> 0 | BB6: =BA6 -> 0 | BC6: =IFERROR(BC7+BC8+BC9+BC10,"") -> 0 | BD6: =IFERROR(BD7+BD8+BD9+BD10,"") -> 0 | BE6: =IFERROR(BE7+BE8+BE9+BE10,"") -> 0 | BF6: =IFERROR(BF7+BF8+BF9+BF10,"") -> 0 | BG6: =BF6 -> 0
B7: aplic_mo | C7: Aplicações no Mercado Aberto | D7: Open Market Investments | E7: =IF(ISNA(SUMIFS(INDEX(Inputs!$B$2:$AZ$190,,MATCH(SUBSTITUTE(E$3,"Q","T"),Inputs!$B$2:$AZ$2,0)),Inputs!$B$2:$B$190,$B7)*Inputs!$D$1),"",SUMIFS(INDEX(Inputs!$B$2:$AZ$190,,MATCH(SUBSTITUTE(E$3,"Q","T"),Inputs!$B$2:$AZ$2,0)),Inputs!$B$2:$B$190,$B7)*Inputs!$D$1) -> 0 | F7: =IF(ISNA(SUMIFS(INDEX(Inputs!$B$2:$AZ$190,,MATCH(SUBSTITUTE(F$3,"Q","T"),Inputs!$B$2:$AZ$2,0)),Inputs!$B$2:$B$190,$B7)*Inputs!$D$1),"",SUMIFS(INDEX(Inputs!$B$2:$AZ$190,,MATCH(SUBSTITUTE(F$3,"Q","T"),Inputs!$B$2:$AZ$2,0)),Inputs!$B$2:$B$190,$B7)*Inputs!$D$1) -> 0 | G7: =IF(ISNA(SUMIFS(INDEX(Inputs!$B$2:$AZ$190,,MATCH(SUBSTITUTE(G$3,"Q","T"),Inputs!$B$2:$AZ$2,0)),Inputs!$B$2:$B$190,$B7)*Inputs!$D$1),"",SUMIFS(INDEX(Inputs!$B$2:$AZ$190,,MATCH(SUBSTITUTE(G$3,"Q","T"),Inputs!$B$2:$AZ$2,0)),Inputs!$B$2:$B$190,$B7)*Inputs!$D$1) -> 0 | H7: =IF(ISNA(SUMIFS(INDEX(Inputs!$B$2:$AZ$190,,MATCH(SUBSTITUTE(H$3,"Q","T"),Inputs!$B$2:$AZ$2,0)),Inputs!$B$2:$B$190,$B7)*Inputs!$D$1),"",SUMIFS(INDEX(Inputs!$B$2:$AZ$190,,MATCH(SUBSTITUTE(H$3,"Q","T"),Inputs!$B$2:$AZ$2,0)),Inputs!$B$2:$B$190,$B7)*Inputs!$D$1) -> 0 | I7: =H7 -> 0 | J7: =IF(ISNA(SUMIFS(INDEX(Inputs!$B$2:$AZ$190,,MATCH(SUBSTITUTE(J$3,"Q","T"),Inputs!$B$2:$AZ$2,0)),Inputs!$B$2:$B$190,$B7)*Inputs!$D$1),"",SUMIFS(INDEX(Inputs!$B$2:$AZ$190,,MATCH(SUBSTITUTE(J$3,"Q","T"),Inputs!$B$2:$AZ$2,0)),Inputs!$B$2:$B$190,$B7)*Inputs!$D$1) -> 0 | K7: =IF(ISNA(SUMIFS(INDEX(Inputs!$B$2:$AZ$190,,MATCH(SUBSTITUTE(K$3,"Q","T"),Inputs!$B$2:$AZ$2,0)),Inputs!$B$2:$B$190,$B7)*Inputs!$D$1),"",SUMIFS(INDEX(Inputs!$B$2:$AZ$190,,MATCH(SUBSTITUTE(K$3,"Q","T"),Inputs!$B$2:$AZ$2,0)),Inputs!$B$2:$B$190,$B7)*Inputs!$D$1) -> 0 | L7: =IF(ISNA(SUMIFS(INDEX(Inputs!$B$2:$AZ$190,,MATCH(SUBSTITUTE(L$3,"Q","T"),Inputs!$B$2:$AZ$2,0)),Inputs!$B$2:$B$190,$B7)*Inputs!$D$1),"",SUMIFS(INDEX(Inputs!$B$2:$AZ$190,,MATCH(SUBSTITUTE(L$3,"Q","T"),Inputs!$B$2:$AZ$2,0)),Inputs!$B$2:$B$190,$B7)*Inputs!$D$1) -> 0 | M7: =IF(ISNA(SUMIFS(INDEX(Inputs!$B$2:$AZ$190,,MATCH(SUBSTITUTE(M$3,"Q","T"),Inputs!$B$2:$AZ$2,0)),Inputs!$B$2:$B$190,$B7)*Inputs!$D$1),"",SUMIFS(INDEX(Inputs!$B$2:$AZ$190,,MATCH(SUBSTITUTE(M$3,"Q","T"),Inputs!$B$2:$AZ$2,0)),Inputs!$B$2:$B$190,$B7)*Inputs!$D$1) -> 0 | N7: =M7 -> 0 | O7: =IF(ISNA(SUMIFS(INDEX(Inputs!$B$2:$AZ$190,,MATCH(SUBSTITUTE(O$3,"Q","T"),Inputs!$B$2:$AZ$2,0)),Inputs!$B$2:$B$190,$B7)*Inputs!$D$1),"",SUMIFS(INDEX(Inputs!$B$2:$AZ$190,,MATCH(SUBSTITUTE(O$3,"Q","T"),Inputs!$B$2:$AZ$2,0)),Inputs!$B$2:$B$190,$B7)*Inputs!$D$1) -> 0 | P7: =IF(ISNA(SUMIFS(INDEX(Inputs!$B$2:$AZ$190,,MATCH(SUBSTITUTE(P$3,"Q","T"),Inputs!$B$2:$AZ$2,0)),Inputs!$B$2:$B$190,$B7)*Inputs!$D$1),"",SUMIFS(INDEX(Inputs!$B$2:$AZ$190,,MATCH(SUBSTITUTE(P$3,"Q","T"),Inputs!$B$2:$AZ$2,0)),Inputs!$B$2:$B$190,$B7)*Inputs!$D$1) -> 0 | Q7: =IF(ISNA(SUMIFS(INDEX(Inputs!$B$2:$AZ$190,,MATCH(SUBSTITUTE(Q$3,"Q","T"),Inputs!$B$2:$AZ$2,0)),Inputs!$B$2:$B$190,$B7)*Inputs!$D$1),"",SUMIFS(INDEX(Inputs!$B$2:$AZ$190,,MATCH(SUBSTITUTE(Q$3,"Q","T"),Inputs!$B$2:$AZ$2,0)),Inputs!$B$2:$B$190,$B7)*Inputs!$D$1) -> 0 | R7: =IF(ISNA(SUMIFS(INDEX(Inputs!$B$2:$AZ$190,,MATCH(SUBSTITUTE(R$3,"Q","T"),Inputs!$B$2:$AZ$2,0)),Inputs!$B$2:$B$190,$B7)*Inputs!$D$1),"",SUMIFS(INDEX(Inputs!$B$2:$AZ$190,,MATCH(SUBSTITUTE(R$3,"Q","T"),Inputs!$B$2:$AZ$2,0)),Inputs!$B$2:$B$190,$B7)*Inputs!$D$1) -> 0 | S7: =R7 -> 0 | T7: =IF(ISNA(SUMIFS(INDEX(Inputs!$B$2:$AZ$190,,MATCH(SUBSTITUTE(T$3,"Q","T"),Inputs!$B$2:$AZ$2,0)),Inputs!$B$2:$B$190,$B7)*Inputs!$D$1),"",SUMIFS(INDEX(Inputs!$B$2:$AZ$190,,MATCH(SUBSTITUTE(T$3,"Q","T"),Inputs!$B$2:$AZ$2,0)),Inputs!$B$2:$B$190,$B7)*Inputs!$D$1) -> 0 | U7: =IF(ISNA(SUMIFS(INDEX(Inputs!$B$2:$AZ$190,,MATCH(SUBSTITUTE(U$3,"Q","T"),Inputs!$B$2:$AZ$2,0)),Inputs!$B$2:$B$190,$B7)*Inputs!$D$1),"",SUMIFS(INDEX(Inputs!$B$2:$AZ$190,,MATCH(SUBSTITUTE(U$3,"Q","T"),Inputs!$B$2:$AZ$2,0)),Inputs!$B$2:$B$190,$B7)*Inputs!$D$1) -> 0 | V7: =IF(ISNA(SUMIFS(INDEX(Inputs!$B$2:$AZ$190,,MATCH(SUBSTITUTE(V$3,"Q","T"),Inputs!$B$2:$AZ$2,0)),Inputs!$B$2:$B$190,$B7)*Inputs!$D$1),"",SUMIFS(INDEX(Inputs!$B$2:$AZ$190,,MATCH(SUBSTITUTE(V$3,"Q","T"),Inputs!$B$2:$AZ$2,0)),Inputs!$B$2:$B$190,$B7)*Inputs!$D$1) -> 0 | W7: =IF(ISNA(SUMIFS(INDEX(Inputs!$B$2:$AZ$190,,MATCH(SUBSTITUTE(W$3,"Q","T"),Inputs!$B$2:$AZ$2,0)),Inputs!$B$2:$B$190,$B7)*Inputs!$D$1),"",SUMIFS(INDEX(Inputs!$B$2:$AZ$190,,MATCH(SUBSTITUTE(W$3,"Q","T"),Inputs!$B$2:$AZ$2,0)),Inputs!$B$2:$B$190,$B7)*Inputs!$D$1) -> 0 | X7: =W7 -> 0 | Y7: =IF(ISNA(SUMIFS(INDEX(Inputs!$B$2:$AZ$190,,MATCH(SUBSTITUTE(Y$3,"Q","T"),Inputs!$B$2:$AZ$2,0)),Inputs!$B$2:$B$190,$B7)*Inputs!$D$1),"",SUMIFS(INDEX(Inputs!$B$2:$AZ$190,,MATCH(SUBSTITUTE(Y$3,"Q","T"),Inputs!$B$2:$AZ$2,0)),Inputs!$B$2:$B$190,$B7)*Inputs!$D$1) -> 0 | Z7: =IF(ISNA(SUMIFS(INDEX(Inputs!$B$2:$AZ$190,,MATCH(SUBSTITUTE(Z$3,"Q","T"),Inputs!$B$2:$AZ$2,0)),Inputs!$B$2:$B$190,$B7)*Inputs!$D$1),"",SUMIFS(INDEX(Inputs!$B$2:$AZ$190,,MATCH(SUBSTITUTE(Z$3,"Q","T"),Inputs!$B$2:$AZ$2,0)),Inputs!$B$2:$B$190,$B7)*Inputs!$D$1) -> 0 | AA7: =IF(ISNA(SUMIFS(INDEX(Inputs!$B$2:$AZ$190,,MATCH(SUBSTITUTE(AA$3,"Q","T"),Inputs!$B$2:$AZ$2,0)),Inputs!$B$2:$B$190,$B7)*Inputs!$D$1),"",SUMIFS(INDEX(Inputs!$B$2:$AZ$190,,MATCH(SUBSTITUTE(AA$3,"Q","T"),Inputs!$B$2:$AZ$2,0)),Inputs!$B$2:$B$190,$B7)*Inputs!$D$1) -> 0 | AB7: =IF(ISNA(SUMIFS(INDEX(Inputs!$B$2:$AZ$190,,MATCH(SUBSTITUTE(AB$3,"Q","T"),Inputs!$B$2:$AZ$2,0)),Inputs!$B$2:$B$190,$B7)*Inputs!$D$1),"",SUMIFS(INDEX(Inputs!$B$2:$AZ$190,,MATCH(SUBSTITUTE(AB$3,"Q","T"),Inputs!$B$2:$AZ$2,0)),Inputs!$B$2:$B$190,$B7)*Inputs!$D$1) -> 0 | AC7: =AB7 -> 0 | AD7: =IF(ISNA(SUMIFS(INDEX(Inputs!$B$2:$AZ$190,,MATCH(SUBSTITUTE(AD$3,"Q","T"),Inputs!$B$2:$AZ$2,0)),Inputs!$B$2:$B$190,$B7)*Inputs!$D$1),"",SUMIFS(INDEX(Inputs!$B$2:$AZ$190,,MATCH(SUBSTITUTE(AD$3,"Q","T"),Inputs!$B$2:$AZ$2,0)),Inputs!$B$2:$B$190,$B7)*Inputs!$D$1) -> 0 | AE7: =IF(ISNA(SUMIFS(INDEX(Inputs!$B$2:$AZ$190,,MATCH(SUBSTITUTE(AE$3,"Q","T"),Inputs!$B$2:$AZ$2,0)),Inputs!$B$2:$B$190,$B7)*Inputs!$D$1),"",SUMIFS(INDEX(Inputs!$B$2:$AZ$190,,MATCH(SUBSTITUTE(AE$3,"Q","T"),Inputs!$B$2:$AZ$2,0)),Inputs!$B$2:$B$190,$B7)*Inputs!$D$1) -> 0 | AF7: =IF(ISNA(SUMIFS(INDEX(Inputs!$B$2:$AZ$190,,MATCH(SUBSTITUTE(AF$3,"Q","T"),Inputs!$B$2:$AZ$2,0)),Inputs!$B$2:$B$190,$B7)*Inputs!$D$1),"",SUMIFS(INDEX(Inputs!$B$2:$AZ$190,,MATCH(SUBSTITUTE(AF$3,"Q","T"),Inputs!$B$2:$AZ$2,0)),Inputs!$B$2:$B$190,$B7)*Inputs!$D$1) -> 0 | AG7: =IF(ISNA(SUMIFS(INDEX(Inputs!$B$2:$AZ$190,,MATCH(SUBSTITUTE(AG$3,"Q","T"),Inputs!$B$2:$AZ$2,0)),Inputs!$B$2:$B$190,$B7)*Inputs!$D$1),"",SUMIFS(INDEX(Inputs!$B$2:$AZ$190,,MATCH(SUBSTITUTE(AG$3,"Q","T"),Inputs!$B$2:$AZ$2,0)),Inputs!$B$2:$B$190,$B7)*Inputs!$D$1) -> 0 | AH7: =AG7 -> 0 | AI7: =IF(ISNA(SUMIFS(INDEX(Inputs!$B$2:$AZ$190,,MATCH(SUBSTITUTE(AI$3,"Q","T"),Inputs!$B$2:$AZ$2,0)),Inputs!$B$2:$B$190,$B7)*Inputs!$D$1),"",SUMIFS(INDEX(Inputs!$B$2:$AZ$190,,MATCH(SUBSTITUTE(AI$3,"Q","T"),Inputs!$B$2:$AZ$2,0)),Inputs!$B$2:$B$190,$B7)*Inputs!$D$1) -> 0 | AJ7: =IF(ISNA(SUMIFS(INDEX(Inputs!$B$2:$AZ$190,,MATCH(SUBSTITUTE(AJ$3,"Q","T"),Inputs!$B$2:$AZ$2,0)),Inputs!$B$2:$B$190,$B7)*Inputs!$D$1),"",SUMIFS(INDEX(Inputs!$B$2:$AZ$190,,MATCH(SUBSTITUTE(AJ$3,"Q","T"),Inputs!$B$2:$AZ$2,0)),Inputs!$B$2:$B$190,$B7)*Inputs!$D$1) -> 0 | AK7: =IF(ISNA(SUMIFS(INDEX(Inputs!$B$2:$AZ$190,,MATCH(SUBSTITUTE(AK$3,"Q","T"),Inputs!$B$2:$AZ$2,0)),Inputs!$B$2:$B$190,$B7)*Inputs!$D$1),"",SUMIFS(INDEX(Inputs!$B$2:$AZ$190,,MATCH(SUBSTITUTE(AK$3,"Q","T"),Inputs!$B$2:$AZ$2,0)),Inputs!$B$2:$B$190,$B7)*Inputs!$D$1) -> 0 | AL7: =IF(ISNA(SUMIFS(INDEX(Inputs!$B$2:$AZ$190,,MATCH(SUBSTITUTE(AL$3,"Q","T"),Inputs!$B$2:$AZ$2,0)),Inputs!$B$2:$B$190,$B7)*Inputs!$D$1),"",SUMIFS(INDEX(Inputs!$B$2:$AZ$190,,MATCH(SUBSTITUTE(AL$3,"Q","T"),Inputs!$B$2:$AZ$2,0)),Inputs!$B$2:$B$190,$B7)*Inputs!$D$1) -> 0 | AM7: =AL7 -> 0 | AN7: =IF(ISNA(SUMIFS(INDEX(Inputs!$B$2:$AZ$190,,MATCH(SUBSTITUTE(AN$3,"Q","T"),Inputs!$B$2:$AZ$2,0)),Inputs!$B$2:$B$190,$B7)*Inputs!$D$1),"",SUMIFS(INDEX(Inputs!$B$2:$AZ$190,,MATCH(SUBSTITUTE(AN$3,"Q","T"),Inputs!$B$2:$AZ$2,0)),Inputs!$B$2:$B$190,$B7)*Inputs!$D$1) -> 0 | AO7: =IF(ISNA(SUMIFS(INDEX(Inputs!$B$2:$AZ$190,,MATCH(SUBSTITUTE(AO$3,"Q","T"),Inputs!$B$2:$AZ$2,0)),Inputs!$B$2:$B$190,$B7)*Inputs!$D$1),"",SUMIFS(INDEX(Inputs!$B$2:$AZ$190,,MATCH(SUBSTITUTE(AO$3,"Q","T"),Inputs!$B$2:$AZ$2,0)),Inputs!$B$2:$B$190,$B7)*Inputs!$D$1) -> 0 | AP7: =IF(ISNA(SUMIFS(INDEX(Inputs!$B$2:$AZ$190,,MATCH(SUBSTITUTE(AP$3,"Q","T"),Inputs!$B$2:$AZ$2,0)),Inputs!$B$2:$B$190,$B7)*Inputs!$D$1),"",SUMIFS(INDEX(Inputs!$B$2:$AZ$190,,MATCH(SUBSTITUTE(AP$3,"Q","T"),Inputs!$B$2:$AZ$2,0)),Inputs!$B$2:$B$190,$B7)*Inputs!$D$1) -> 0 | AQ7: =IF(ISNA(SUMIFS(INDEX(Inputs!$B$2:$AZ$190,,MATCH(SUBSTITUTE(AQ$3,"Q","T"),Inputs!$B$2:$AZ$2,0)),Inputs!$B$2:$B$190,$B7)*Inputs!$D$1),"",SUMIFS(INDEX(Inputs!$B$2:$AZ$190,,MATCH(SUBSTITUTE(AQ$3,"Q","T"),Inputs!$B$2:$AZ$2,0)),Inputs!$B$2:$B$190,$B7)*Inputs!$D$1) -> 0 | AR7: =AQ7 -> 0 | AS7: =IF(ISNA(SUMIFS(INDEX(Inputs!$B$2:$AZ$190,,MATCH(SUBSTITUTE(AS$3,"Q","T"),Inputs!$B$2:$AZ$2,0)),Inputs!$B$2:$B$190,$B7)*Inputs!$D$1),"",SUMIFS(INDEX(Inputs!$B$2:$AZ$190,,MATCH(SUBSTITUTE(AS$3,"Q","T"),Inputs!$B$2:$AZ$2,0)),Inputs!$B$2:$B$190,$B7)*Inputs!$D$1) -> 0 | AT7: =IF(ISNA(SUMIFS(INDEX(Inputs!$B$2:$AZ$190,,MATCH(SUBSTITUTE(AT$3,"Q","T"),Inputs!$B$2:$AZ$2,0)),Inputs!$B$2:$B$190,$B7)*Inputs!$D$1),"",SUMIFS(INDEX(Inputs!$B$2:$AZ$190,,MATCH(SUBSTITUTE(AT$3,"Q","T"),Inputs!$B$2:$AZ$2,0)),Inputs!$B$2:$B$190,$B7)*Inputs!$D$1) -> 0 | AU7: =IF(ISNA(SUMIFS(INDEX(Inputs!$B$2:$AZ$190,,MATCH(SUBSTITUTE(AU$3,"Q","T"),Inputs!$B$2:$AZ$2,0)),Inputs!$B$2:$B$190,$B7)*Inputs!$D$1),"",SUMIFS(INDEX(Inputs!$B$2:$AZ$190,,MATCH(SUBSTITUTE(AU$3,"Q","T"),Inputs!$B$2:$AZ$2,0)),Inputs!$B$2:$B$190,$B7)*Inputs!$D$1) -> 0 | AV7: =IF(ISNA(SUMIFS(INDEX(Inputs!$B$2:$AZ$190,,MATCH(SUBSTITUTE(AV$3,"Q","T"),Inputs!$B$2:$AZ$2,0)),Inputs!$B$2:$B$190,$B7)*Inputs!$D$1),"",SUMIFS(INDEX(Inputs!$B$2:$AZ$190,,MATCH(SUBSTITUTE(AV$3,"Q","T"),Inputs!$B$2:$AZ$2,0)),Inputs!$B$2:$B$190,$B7)*Inputs!$D$1) -> 0 | AW7: =AV7 -> 0 | AX7: =IF(ISNA(SUMIFS(INDEX(Inputs!$B$2:$AZ$190,,MATCH(SUBSTITUTE(AX$3,"Q","T"),Inputs!$B$2:$AZ$2,0)),Inputs!$B$2:$B$190,$B7)*Inputs!$D$1),"",SUMIFS(INDEX(Inputs!$B$2:$AZ$190,,MATCH(SUBSTITUTE(AX$3,"Q","T"),Inputs!$B$2:$AZ$2,0)),Inputs!$B$2:$B$190,$B7)*Inputs!$D$1) -> 0 | AY7: =IF(ISNA(SUMIFS(INDEX(Inputs!$B$2:$AZ$190,,MATCH(SUBSTITUTE(AY$3,"Q","T"),Inputs!$B$2:$AZ$2,0)),Inputs!$B$2:$B$190,$B7)*Inputs!$D$1),"",SUMIFS(INDEX(Inputs!$B$2:$AZ$190,,MATCH(SUBSTITUTE(AY$3,"Q","T"),Inputs!$B$2:$AZ$2,0)),Inputs!$B$2:$B$190,$B7)*Inputs!$D$1) -> 0 | AZ7: =IF(ISNA(SUMIFS(INDEX(Inputs!$B$2:$AZ$190,,MATCH(SUBSTITUTE(AZ$3,"Q","T"),Inputs!$B$2:$AZ$2,0)),Inputs!$B$2:$B$190,$B7)*Inputs!$D$1),"",SUMIFS(INDEX(Inputs!$B$2:$AZ$190,,MATCH(SUBSTITUTE(AZ$3,"Q","T"),Inputs!$B$2:$AZ$2,0)),Inputs!$B$2:$B$190,$B7)*Inputs!$D$1) -> 0 | BA7: =IF(ISNA(SUMIFS(INDEX(Inputs!$B$2:$AZ$190,,MATCH(SUBSTITUTE(BA$3,"Q","T"),Inputs!$B$2:$AZ$2,0)),Inputs!$B$2:$B$190,$B7)*Inputs!$D$1),"",SUMIFS(INDEX(Inputs!$B$2:$AZ$190,,MATCH(SUBSTITUTE(BA$3,"Q","T"),Inputs!$B$2:$AZ$2,0)),Inputs!$B$2:$B$190,$B7)*Inputs!$D$1) -> 0 | BB7: =BA7 -> 0 | BC7: =IF(ISNA(SUMIFS(INDEX(Inputs!$B$2:$AZ$190,,MATCH(SUBSTITUTE(BC$3,"Q","T"),Inputs!$B$2:$AZ$2,0)),Inputs!$B$2:$B$190,$B7)*Inputs!$D$1),"",SUMIFS(INDEX(Inputs!$B$2:$AZ$190,,MATCH(SUBSTITUTE(BC$3,"Q","T"),Inputs!$B$2:$AZ$2,0)),Inputs!$B$2:$B$190,$B7)*Inputs!$D$1) -> 0 | BD7: =IF(ISNA(SUMIFS(INDEX(Inputs!$B$2:$AZ$190,,MATCH(SUBSTITUTE(BD$3,"Q","T"),Inputs!$B$2:$AZ$2,0)),Inputs!$B$2:$B$190,$B7)*Inputs!$D$1),"",SUMIFS(INDEX(Inputs!$B$2:$AZ$190,,MATCH(SUBSTITUTE(BD$3,"Q","T"),Inputs!$B$2:$AZ$2,0)),Inputs!$B$2:$B$190,$B7)*Inputs!$D$1) -> 0 | BE7: =IF(ISNA(SUMIFS(INDEX(Inputs!$B$2:$AZ$190,,MATCH(SUBSTITUTE(BE$3,"Q","T"),Inputs!$B$2:$AZ$2,0)),Inputs!$B$2:$B$190,$B7)*Inputs!$D$1),"",SUMIFS(INDEX(Inputs!$B$2:$AZ$190,,MATCH(SUBSTITUTE(BE$3,"Q","T"),Inputs!$B$2:$AZ$2,0)),Inputs!$B$2:$B$190,$B7)*Inputs!$D$1) -> 0 | BF7: =IF(ISNA(SUMIFS(INDEX(Inputs!$B$2:$AZ$190,,MATCH(SUBSTITUTE(BF$3,"Q","T"),Inputs!$B$2:$AZ$2,0)),Inputs!$B$2:$B$190,$B7)*Inputs!$D$1),"",SUMIFS(INDEX(Inputs!$B$2:$AZ$190,,MATCH(SUBSTITUTE(BF$3,"Q","T"),Inputs!$B$2:$AZ$2,0)),Inputs!$B$2:$B$190,$B7)*Inputs!$D$1) -> 0 | BG7: =BF7 -> 0
B8: aplic_di | C8: Aplicações em Depósitos Interfinanceiros | D8: Interbank Deposits | E8: =IF(ISNA(SUMIFS(INDEX(Inputs!$B$2:$AZ$190,,MATCH(SUBSTITUTE(E$3,"Q","T"),Inputs!$B$2:$AZ$2,0)),Inputs!$B$2:$B$190,$B8)*Inputs!$D$1),"",SUMIFS(INDEX(Inputs!$B$2:$AZ$190,,MATCH(SUBSTITUTE(E$3,"Q","T"),Inputs!$B$2:$AZ$2,0)),Inputs!$B$2:$B$190,$B8)*Inputs!$D$1) -> 0 | F8: =IF(ISNA(SUMIFS(INDEX(Inputs!$B$2:$AZ$190,,MATCH(SUBSTITUTE(F$3,"Q","T"),Inputs!$B$2:$AZ$2,0)),Inputs!$B$2:$B$190,$B8)*Inputs!$D$1),"",SUMIFS(INDEX(Inputs!$B$2:$AZ$190,,MATCH(SUBSTITUTE(F$3,"Q","T"),Inputs!$B$2:$AZ$2,0)),Inputs!$B$2:$B$190,$B8)*Inputs!$D$1) -> 0 | G8: =IF(ISNA(SUMIFS(INDEX(Inputs!$B$2:$AZ$190,,MATCH(SUBSTITUTE(G$3,"Q","T"),Inputs!$B$2:$AZ$2,0)),Inputs!$B$2:$B$190,$B8)*Inputs!$D$1),"",SUMIFS(INDEX(Inputs!$B$2:$AZ$190,,MATCH(SUBSTITUTE(G$3,"Q","T"),Inputs!$B$2:$AZ$2,0)),Inputs!$B$2:$B$190,$B8)*Inputs!$D$1) -> 0 | H8: =IF(ISNA(SUMIFS(INDEX(Inputs!$B$2:$AZ$190,,MATCH(SUBSTITUTE(H$3,"Q","T"),Inputs!$B$2:$AZ$2,0)),Inputs!$B$2:$B$190,$B8)*Inputs!$D$1),"",SUMIFS(INDEX(Inputs!$B$2:$AZ$190,,MATCH(SUBSTITUTE(H$3,"Q","T"),Inputs!$B$2:$AZ$2,0)),Inputs!$B$2:$B$190,$B8)*Inputs!$D$1) -> 0 | I8: =H8 -> 0 | J8: =IF(ISNA(SUMIFS(INDEX(Inputs!$B$2:$AZ$190,,MATCH(SUBSTITUTE(J$3,"Q","T"),Inputs!$B$2:$AZ$2,0)),Inputs!$B$2:$B$190,$B8)*Inputs!$D$1),"",SUMIFS(INDEX(Inputs!$B$2:$AZ$190,,MATCH(SUBSTITUTE(J$3,"Q","T"),Inputs!$B$2:$AZ$2,0)),Inputs!$B$2:$B$190,$B8)*Inputs!$D$1) -> 0 | K8: =IF(ISNA(SUMIFS(INDEX(Inputs!$B$2:$AZ$190,,MATCH(SUBSTITUTE(K$3,"Q","T"),Inputs!$B$2:$AZ$2,0)),Inputs!$B$2:$B$190,$B8)*Inputs!$D$1),"",SUMIFS(INDEX(Inputs!$B$2:$AZ$190,,MATCH(SUBSTITUTE(K$3,"Q","T"),Inputs!$B$2:$AZ$2,0)),Inputs!$B$2:$B$190,$B8)*Inputs!$D$1) -> 0 | L8: =IF(ISNA(SUMIFS(INDEX(Inputs!$B$2:$AZ$190,,MATCH(SUBSTITUTE(L$3,"Q","T"),Inputs!$B$2:$AZ$2,0)),Inputs!$B$2:$B$190,$B8)*Inputs!$D$1),"",SUMIFS(INDEX(Inputs!$B$2:$AZ$190,,MATCH(SUBSTITUTE(L$3,"Q","T"),Inputs!$B$2:$AZ$2,0)),Inputs!$B$2:$B$190,$B8)*Inputs!$D$1) -> 0 | M8: =IF(ISNA(SUMIFS(INDEX(Inputs!$B$2:$AZ$190,,MATCH(SUBSTITUTE(M$3,"Q","T"),Inputs!$B$2:$AZ$2,0)),Inputs!$B$2:$B$190,$B8)*Inputs!$D$1),"",SUMIFS(INDEX(Inputs!$B$2:$AZ$190,,MATCH(SUBSTITUTE(M$3,"Q","T"),Inputs!$B$2:$AZ$2,0)),Inputs!$B$2:$B$190,$B8)*Inputs!$D$1) -> 0 | N8: =M8 -> 0 | O8: =IF(ISNA(SUMIFS(INDEX(Inputs!$B$2:$AZ$190,,MATCH(SUBSTITUTE(O$3,"Q","T"),Inputs!$B$2:$AZ$2,0)),Inputs!$B$2:$B$190,$B8)*Inputs!$D$1),"",SUMIFS(INDEX(Inputs!$B$2:$AZ$190,,MATCH(SUBSTITUTE(O$3,"Q","T"),Inputs!$B$2:$AZ$2,0)),Inputs!$B$2:$B$190,$B8)*Inputs!$D$1) -> 0 | P8: =IF(ISNA(SUMIFS(INDEX(Inputs!$B$2:$AZ$190,,MATCH(SUBSTITUTE(P$3,"Q","T"),Inputs!$B$2:$AZ$2,0)),Inputs!$B$2:$B$190,$B8)*Inputs!$D$1),"",SUMIFS(INDEX(Inputs!$B$2:$AZ$190,,MATCH(SUBSTITUTE(P$3,"Q","T"),Inputs!$B$2:$AZ$2,0)),Inputs!$B$2:$B$190,$B8)*Inputs!$D$1) -> 0 | Q8: =IF(ISNA(SUMIFS(INDEX(Inputs!$B$2:$AZ$190,,MATCH(SUBSTITUTE(Q$3,"Q","T"),Inputs!$B$2:$AZ$2,0)),Inputs!$B$2:$B$190,$B8)*Inputs!$D$1),"",SUMIFS(INDEX(Inputs!$B$2:$AZ$190,,MATCH(SUBSTITUTE(Q$3,"Q","T"),Inputs!$B$2:$AZ$2,0)),Inputs!$B$2:$B$190,$B8)*Inputs!$D$1) -> 0 | R8: =IF(ISNA(SUMIFS(INDEX(Inputs!$B$2:$AZ$190,,MATCH(SUBSTITUTE(R$3,"Q","T"),Inputs!$B$2:$AZ$2,0)),Inputs!$B$2:$B$190,$B8)*Inputs!$D$1),"",SUMIFS(INDEX(Inputs!$B$2:$AZ$190,,MATCH(SUBSTITUTE(R$3,"Q","T"),Inputs!$B$2:$AZ$2,0)),Inputs!$B$2:$B$190,$B8)*Inputs!$D$1) -> 0 | S8: =R8 -> 0 | T8: =IF(ISNA(SUMIFS(INDEX(Inputs!$B$2:$AZ$190,,MATCH(SUBSTITUTE(T$3,"Q","T"),Inputs!$B$2:$AZ$2,0)),Inputs!$B$2:$B$190,$B8)*Inputs!$D$1),"",SUMIFS(INDEX(Inputs!$B$2:$AZ$190,,MATCH(SUBSTITUTE(T$3,"Q","T"),Inputs!$B$2:$AZ$2,0)),Inputs!$B$2:$B$190,$B8)*Inputs!$D$1) -> 0 | U8: =IF(ISNA(SUMIFS(INDEX(Inputs!$B$2:$AZ$190,,MATCH(SUBSTITUTE(U$3,"Q","T"),Inputs!$B$2:$AZ$2,0)),Inputs!$B$2:$B$190,$B8)*Inputs!$D$1),"",SUMIFS(INDEX(Inputs!$B$2:$AZ$190,,MATCH(SUBSTITUTE(U$3,"Q","T"),Inputs!$B$2:$AZ$2,0)),Inputs!$B$2:$B$190,$B8)*Inputs!$D$1) -> 0 | V8: =IF(ISNA(SUMIFS(INDEX(Inputs!$B$2:$AZ$190,,MATCH(SUBSTITUTE(V$3,"Q","T"),Inputs!$B$2:$AZ$2,0)),Inputs!$B$2:$B$190,$B8)*Inputs!$D$1),"",SUMIFS(INDEX(Inputs!$B$2:$AZ$190,,MATCH(SUBSTITUTE(V$3,"Q","T"),Inputs!$B$2:$AZ$2,0)),Inputs!$B$2:$B$190,$B8)*Inputs!$D$1) -> 0 | W8: =IF(ISNA(SUMIFS(INDEX(Inputs!$B$2:$AZ$190,,MATCH(SUBSTITUTE(W$3,"Q","T"),Inputs!$B$2:$AZ$2,0)),Inputs!$B$2:$B$190,$B8)*Inputs!$D$1),"",SUMIFS(INDEX(Inputs!$B$2:$AZ$190,,MATCH(SUBSTITUTE(W$3,"Q","T"),Inputs!$B$2:$AZ$2,0)),Inputs!$B$2:$B$190,$B8)*Inputs!$D$1) -> 0 | X8: =W8 -> 0 | Y8: =IF(ISNA(SUMIFS(INDEX(Inputs!$B$2:$AZ$190,,MATCH(SUBSTITUTE(Y$3,"Q","T"),Inputs!$B$2:$AZ$2,0)),Inputs!$B$2:$B$190,$B8)*Inputs!$D$1),"",SUMIFS(INDEX(Inputs!$B$2:$AZ$190,,MATCH(SUBSTITUTE(Y$3,"Q","T"),Inputs!$B$2:$AZ$2,0)),Inputs!$B$2:$B$190,$B8)*Inputs!$D$1) -> 0 | Z8: =IF(ISNA(SUMIFS(INDEX(Inputs!$B$2:$AZ$190,,MATCH(SUBSTITUTE(Z$3,"Q","T"),Inputs!$B$2:$AZ$2,0)),Inputs!$B$2:$B$190,$B8)*Inputs!$D$1),"",SUMIFS(INDEX(Inputs!$B$2:$AZ$190,,MATCH(SUBSTITUTE(Z$3,"Q","T"),Inputs!$B$2:$AZ$2,0)),Inputs!$B$2:$B$190,$B8)*Inputs!$D$1) -> 0 | AA8: =IF(ISNA(SUMIFS(INDEX(Inputs!$B$2:$AZ$190,,MATCH(SUBSTITUTE(AA$3,"Q","T"),Inputs!$B$2:$AZ$2,0)),Inputs!$B$2:$B$190,$B8)*Inputs!$D$1),"",SUMIFS(INDEX(Inputs!$B$2:$AZ$190,,MATCH(SUBSTITUTE(AA$3,"Q","T"),Inputs!$B$2:$AZ$2,0)),Inputs!$B$2:$B$190,$B8)*Inputs!$D$1) -> 0 | AB8: =IF(ISNA(SUMIFS(INDEX(Inputs!$B$2:$AZ$190,,MATCH(SUBSTITUTE(AB$3,"Q","T"),Inputs!$B$2:$AZ$2,0)),Inputs!$B$2:$B$190,$B8)*Inputs!$D$1),"",SUMIFS(INDEX(Inputs!$B$2:$AZ$190,,MATCH(SUBSTITUTE(AB$3,"Q","T"),Inputs!$B$2:$AZ$2,0)),Inputs!$B$2:$B$190,$B8)*Inputs!$D$1) -> 0 | AC8: =AB8 -> 0 | AD8: =IF(ISNA(SUMIFS(INDEX(Inputs!$B$2:$AZ$190,,MATCH(SUBSTITUTE(AD$3,"Q","T"),Inputs!$B$2:$AZ$2,0)),Inputs!$B$2:$B$190,$B8)*Inputs!$D$1),"",SUMIFS(INDEX(Inputs!$B$2:$AZ$190,,MATCH(SUBSTITUTE(AD$3,"Q","T"),Inputs!$B$2:$AZ$2,0)),Inputs!$B$2:$B$190,$B8)*Inputs!$D$1) -> 0 | AE8: =IF(ISNA(SUMIFS(INDEX(Inputs!$B$2:$AZ$190,,MATCH(SUBSTITUTE(AE$3,"Q","T"),Inputs!$B$2:$AZ$2,0)),Inputs!$B$2:$B$190,$B8)*Inputs!$D$1),"",SUMIFS(INDEX(Inputs!$B$2:$AZ$190,,MATCH(SUBSTITUTE(AE$3,"Q","T"),Inputs!$B$2:$AZ$2,0)),Inputs!$B$2:$B$190,$B8)*Inputs!$D$1) -> 0 | AF8: =IF(ISNA(SUMIFS(INDEX(Inputs!$B$2:$AZ$190,,MATCH(SUBSTITUTE(AF$3,"Q","T"),Inputs!$B$2:$AZ$2,0)),Inputs!$B$2:$B$190,$B8)*Inputs!$D$1),"",SUMIFS(INDEX(Inputs!$B$2:$AZ$190,,MATCH(SUBSTITUTE(AF$3,"Q","T"),Inputs!$B$2:$AZ$2,0)),Inputs!$B$2:$B$190,$B8)*Inputs!$D$1) -> 0 | AG8: =IF(ISNA(SUMIFS(INDEX(Inputs!$B$2:$AZ$190,,MATCH(SUBSTITUTE(AG$3,"Q","T"),Inputs!$B$2:$AZ$2,0)),Inputs!$B$2:$B$190,$B8)*Inputs!$D$1),"",SUMIFS(INDEX(Inputs!$B$2:$AZ$190,,MATCH(SUBSTITUTE(AG$3,"Q","T"),Inputs!$B$2:$AZ$2,0)),Inputs!$B$2:$B$190,$B8)*Inputs!$D$1) -> 0 | AH8: =AG8 -> 0 | AI8: =IF(ISNA(SUMIFS(INDEX(Inputs!$B$2:$AZ$190,,MATCH(SUBSTITUTE(AI$3,"Q","T"),Inputs!$B$2:$AZ$2,0)),Inputs!$B$2:$B$190,$B8)*Inputs!$D$1),"",SUMIFS(INDEX(Inputs!$B$2:$AZ$190,,MATCH(SUBSTITUTE(AI$3,"Q","T"),Inputs!$B$2:$AZ$2,0)),Inputs!$B$2:$B$190,$B8)*Inputs!$D$1) -> 0 | AJ8: =IF(ISNA(SUMIFS(INDEX(Inputs!$B$2:$AZ$190,,MATCH(SUBSTITUTE(AJ$3,"Q","T"),Inputs!$B$2:$AZ$2,0)),Inputs!$B$2:$B$190,$B8)*Inputs!$D$1),"",SUMIFS(INDEX(Inputs!$B$2:$AZ$190,,MATCH(SUBSTITUTE(AJ$3,"Q","T"),Inputs!$B$2:$AZ$2,0)),Inputs!$B$2:$B$190,$B8)*Inputs!$D$1) -> 0 | AK8: =IF(ISNA(SUMIFS(INDEX(Inputs!$B$2:$AZ$190,,MATCH(SUBSTITUTE(AK$3,"Q","T"),Inputs!$B$2:$AZ$2,0)),Inputs!$B$2:$B$190,$B8)*Inputs!$D$1),"",SUMIFS(INDEX(Inputs!$B$2:$AZ$190,,MATCH(SUBSTITUTE(AK$3,"Q","T"),Inputs!$B$2:$AZ$2,0)),Inputs!$B$2:$B$190,$B8)*Inputs!$D$1) -> 0 | AL8: =IF(ISNA(SUMIFS(INDEX(Inputs!$B$2:$AZ$190,,MATCH(SUBSTITUTE(AL$3,"Q","T"),Inputs!$B$2:$AZ$2,0)),Inputs!$B$2:$B$190,$B8)*Inputs!$D$1),"",SUMIFS(INDEX(Inputs!$B$2:$AZ$190,,MATCH(SUBSTITUTE(AL$3,"Q","T"),Inputs!$B$2:$AZ$2,0)),Inputs!$B$2:$B$190,$B8)*Inputs!$D$1) -> 0 | AM8: =AL8 -> 0 | AN8: =IF(ISNA(SUMIFS(INDEX(Inputs!$B$2:$AZ$190,,MATCH(SUBSTITUTE(AN$3,"Q","T"),Inputs!$B$2:$AZ$2,0)),Inputs!$B$2:$B$190,$B8)*Inputs!$D$1),"",SUMIFS(INDEX(Inputs!$B$2:$AZ$190,,MATCH(SUBSTITUTE(AN$3,"Q","T"),Inputs!$B$2:$AZ$2,0)),Inputs!$B$2:$B$190,$B8)*Inputs!$D$1) -> 0 | AO8: =IF(ISNA(SUMIFS(INDEX(Inputs!$B$2:$AZ$190,,MATCH(SUBSTITUTE(AO$3,"Q","T"),Inputs!$B$2:$AZ$2,0)),Inputs!$B$2:$B$190,$B8)*Inputs!$D$1),"",SUMIFS(INDEX(Inputs!$B$2:$AZ$190,,MATCH(SUBSTITUTE(AO$3,"Q","T"),Inputs!$B$2:$AZ$2,0)),Inputs!$B$2:$B$190,$B8)*Inputs!$D$1) -> 0 | AP8: =IF(ISNA(SUMIFS(INDEX(Inputs!$B$2:$AZ$190,,MATCH(SUBSTITUTE(AP$3,"Q","T"),Inputs!$B$2:$AZ$2,0)),Inputs!$B$2:$B$190,$B8)*Inputs!$D$1),"",SUMIFS(INDEX(Inputs!$B$2:$AZ$190,,MATCH(SUBSTITUTE(AP$3,"Q","T"),Inputs!$B$2:$AZ$2,0)),Inputs!$B$2:$B$190,$B8)*Inputs!$D$1) -> 0 | AQ8: =IF(ISNA(SUMIFS(INDEX(Inputs!$B$2:$AZ$190,,MATCH(SUBSTITUTE(AQ$3,"Q","T"),Inputs!$B$2:$AZ$2,0)),Inputs!$B$2:$B$190,$B8)*Inputs!$D$1),"",SUMIFS(INDEX(Inputs!$B$2:$AZ$190,,MATCH(SUBSTITUTE(AQ$3,"Q","T"),Inputs!$B$2:$AZ$2,0)),Inputs!$B$2:$B$190,$B8)*Inputs!$D$1) -> 0 | AR8: =AQ8 -> 0 | AS8: =IF(ISNA(SUMIFS(INDEX(Inputs!$B$2:$AZ$190,,MATCH(SUBSTITUTE(AS$3,"Q","T"),Inputs!$B$2:$AZ$2,0)),Inputs!$B$2:$B$190,$B8)*Inputs!$D$1),"",SUMIFS(INDEX(Inputs!$B$2:$AZ$190,,MATCH(SUBSTITUTE(AS$3,"Q","T"),Inputs!$B$2:$AZ$2,0)),Inputs!$B$2:$B$190,$B8)*Inputs!$D$1) -> 0 | AT8: =IF(ISNA(SUMIFS(INDEX(Inputs!$B$2:$AZ$190,,MATCH(SUBSTITUTE(AT$3,"Q","T"),Inputs!$B$2:$AZ$2,0)),Inputs!$B$2:$B$190,$B8)*Inputs!$D$1),"",SUMIFS(INDEX(Inputs!$B$2:$AZ$190,,MATCH(SUBSTITUTE(AT$3,"Q","T"),Inputs!$B$2:$AZ$2,0)),Inputs!$B$2:$B$190,$B8)*Inputs!$D$1) -> 0 | AU8: =IF(ISNA(SUMIFS(INDEX(Inputs!$B$2:$AZ$190,,MATCH(SUBSTITUTE(AU$3,"Q","T"),Inputs!$B$2:$AZ$2,0)),Inputs!$B$2:$B$190,$B8)*Inputs!$D$1),"",SUMIFS(INDEX(Inputs!$B$2:$AZ$190,,MATCH(SUBSTITUTE(AU$3,"Q","T"),Inputs!$B$2:$AZ$2,0)),Inputs!$B$2:$B$190,$B8)*Inputs!$D$1) -> 0 | AV8: =IF(ISNA(SUMIFS(INDEX(Inputs!$B$2:$AZ$190,,MATCH(SUBSTITUTE(AV$3,"Q","T"),Inputs!$B$2:$AZ$2,0)),Inputs!$B$2:$B$190,$B8)*Inputs!$D$1),"",SUMIFS(INDEX(Inputs!$B$2:$AZ$190,,MATCH(SUBSTITUTE(AV$3,"Q","T"),Inputs!$B$2:$AZ$2,0)),Inputs!$B$2:$B$190,$B8)*Inputs!$D$1) -> 0 | AW8: =AV8 -> 0 | AX8: =IF(ISNA(SUMIFS(INDEX(Inputs!$B$2:$AZ$190,,MATCH(SUBSTITUTE(AX$3,"Q","T"),Inputs!$B$2:$AZ$2,0)),Inputs!$B$2:$B$190,$B8)*Inputs!$D$1),"",SUMIFS(INDEX(Inputs!$B$2:$AZ$190,,MATCH(SUBSTITUTE(AX$3,"Q","T"),Inputs!$B$2:$AZ$2,0)),Inputs!$B$2:$B$190,$B8)*Inputs!$D$1) -> 0 | AY8: =IF(ISNA(SUMIFS(INDEX(Inputs!$B$2:$AZ$190,,MATCH(SUBSTITUTE(AY$3,"Q","T"),Inputs!$B$2:$AZ$2,0)),Inputs!$B$2:$B$190,$B8)*Inputs!$D$1),"",SUMIFS(INDEX(Inputs!$B$2:$AZ$190,,MATCH(SUBSTITUTE(AY$3,"Q","T"),Inputs!$B$2:$AZ$2,0)),Inputs!$B$2:$B$190,$B8)*Inputs!$D$1) -> 0 | AZ8: =IF(ISNA(SUMIFS(INDEX(Inputs!$B$2:$AZ$190,,MATCH(SUBSTITUTE(AZ$3,"Q","T"),Inputs!$B$2:$AZ$2,0)),Inputs!$B$2:$B$190,$B8)*Inputs!$D$1),"",SUMIFS(INDEX(Inputs!$B$2:$AZ$190,,MATCH(SUBSTITUTE(AZ$3,"Q","T"),Inputs!$B$2:$AZ$2,0)),Inputs!$B$2:$B$190,$B8)*Inputs!$D$1) -> 0 | BA8: =IF(ISNA(SUMIFS(INDEX(Inputs!$B$2:$AZ$190,,MATCH(SUBSTITUTE(BA$3,"Q","T"),Inputs!$B$2:$AZ$2,0)),Inputs!$B$2:$B$190,$B8)*Inputs!$D$1),"",SUMIFS(INDEX(Inputs!$B$2:$AZ$190,,MATCH(SUBSTITUTE(BA$3,"Q","T"),Inputs!$B$2:$AZ$2,0)),Inputs!$B$2:$B$190,$B8)*Inputs!$D$1) -> 0 | BB8: =BA8 -> 0 | BC8: =IF(ISNA(SUMIFS(INDEX(Inputs!$B$2:$AZ$190,,MATCH(SUBSTITUTE(BC$3,"Q","T"),Inputs!$B$2:$AZ$2,0)),Inputs!$B$2:$B$190,$B8)*Inputs!$D$1),"",SUMIFS(INDEX(Inputs!$B$2:$AZ$190,,MATCH(SUBSTITUTE(BC$3,"Q","T"),Inputs!$B$2:$AZ$2,0)),Inputs!$B$2:$B$190,$B8)*Inputs!$D$1) -> 0 | BD8: =IF(ISNA(SUMIFS(INDEX(Inputs!$B$2:$AZ$190,,MATCH(SUBSTITUTE(BD$3,"Q","T"),Inputs!$B$2:$AZ$2,0)),Inputs!$B$2:$B$190,$B8)*Inputs!$D$1),"",SUMIFS(INDEX(Inputs!$B$2:$AZ$190,,MATCH(SUBSTITUTE(BD$3,"Q","T"),Inputs!$B$2:$AZ$2,0)),Inputs!$B$2:$B$190,$B8)*Inputs!$D$1) -> 0 | BE8: =IF(ISNA(SUMIFS(INDEX(Inputs!$B$2:$AZ$190,,MATCH(SUBSTITUTE(BE$3,"Q","T"),Inputs!$B$2:$AZ$2,0)),Inputs!$B$2:$B$190,$B8)*Inputs!$D$1),"",SUMIFS(INDEX(Inputs!$B$2:$AZ$190,,MATCH(SUBSTITUTE(BE$3,"Q","T"),Inputs!$B$2:$AZ$2,0)),Inputs!$B$2:$B$190,$B8)*Inputs!$D$1) -> 0 | BF8: =IF(ISNA(SUMIFS(INDEX(Inputs!$B$2:$AZ$190,,MATCH(SUBSTITUTE(BF$3,"Q","T"),Inputs!$B$2:$AZ$2,0)),Inputs!$B$2:$B$190,$B8)*Inputs!$D$1),"",SUMIFS(INDEX(Inputs!$B$2:$AZ$190,,MATCH(SUBSTITUTE(BF$3,"Q","T"),Inputs!$B$2:$AZ$2,0)),Inputs!$B$2:$B$190,$B8)*Inputs!$D$1) -> 0 | BG8: =BF8 -> 0
B9: aplic_rg | C9: Recursos Garantidores das Provisões Técnicas | D9: Assets Guaranteeing Technical Provisions | E9: =IF(ISNA(SUMIFS(INDEX(Inputs!$B$2:$AZ$190,,MATCH(SUBSTITUTE(E$3,"Q","T"),Inputs!$B$2:$AZ$2,0)),Inputs!$B$2:$B$190,$B9)*Inputs!$D$1),"",SUMIFS(INDEX(Inputs!$B$2:$AZ$190,,MATCH(SUBSTITUTE(E$3,"Q","T"),Inputs!$B$2:$AZ$2,0)),Inputs!$B$2:$B$190,$B9)*Inputs!$D$1) -> 0 | F9: =IF(ISNA(SUMIFS(INDEX(Inputs!$B$2:$AZ$190,,MATCH(SUBSTITUTE(F$3,"Q","T"),Inputs!$B$2:$AZ$2,0)),Inputs!$B$2:$B$190,$B9)*Inputs!$D$1),"",SUMIFS(INDEX(Inputs!$B$2:$AZ$190,,MATCH(SUBSTITUTE(F$3,"Q","T"),Inputs!$B$2:$AZ$2,0)),Inputs!$B$2:$B$190,$B9)*Inputs!$D$1) -> 0 | G9: =IF(ISNA(SUMIFS(INDEX(Inputs!$B$2:$AZ$190,,MATCH(SUBSTITUTE(G$3,"Q","T"),Inputs!$B$2:$AZ$2,0)),Inputs!$B$2:$B$190,$B9)*Inputs!$D$1),"",SUMIFS(INDEX(Inputs!$B$2:$AZ$190,,MATCH(SUBSTITUTE(G$3,"Q","T"),Inputs!$B$2:$AZ$2,0)),Inputs!$B$2:$B$190,$B9)*Inputs!$D$1) -> 0 | H9: =IF(ISNA(SUMIFS(INDEX(Inputs!$B$2:$AZ$190,,MATCH(SUBSTITUTE(H$3,"Q","T"),Inputs!$B$2:$AZ$2,0)),Inputs!$B$2:$B$190,$B9)*Inputs!$D$1),"",SUMIFS(INDEX(Inputs!$B$2:$AZ$190,,MATCH(SUBSTITUTE(H$3,"Q","T"),Inputs!$B$2:$AZ$2,0)),Inputs!$B$2:$B$190,$B9)*Inputs!$D$1) -> 0 | I9: =H9 -> 0 | J9: =IF(ISNA(SUMIFS(INDEX(Inputs!$B$2:$AZ$190,,MATCH(SUBSTITUTE(J$3,"Q","T"),Inputs!$B$2:$AZ$2,0)),Inputs!$B$2:$B$190,$B9)*Inputs!$D$1),"",SUMIFS(INDEX(Inputs!$B$2:$AZ$190,,MATCH(SUBSTITUTE(J$3,"Q","T"),Inputs!$B$2:$AZ$2,0)),Inputs!$B$2:$B$190,$B9)*Inputs!$D$1) -> 0 | K9: =IF(ISNA(SUMIFS(INDEX(Inputs!$B$2:$AZ$190,,MATCH(SUBSTITUTE(K$3,"Q","T"),Inputs!$B$2:$AZ$2,0)),Inputs!$B$2:$B$190,$B9)*Inputs!$D$1),"",SUMIFS(INDEX(Inputs!$B$2:$AZ$190,,MATCH(SUBSTITUTE(K$3,"Q","T"),Inputs!$B$2:$AZ$2,0)),Inputs!$B$2:$B$190,$B9)*Inputs!$D$1) -> 0 | L9: =IF(ISNA(SUMIFS(INDEX(Inputs!$B$2:$AZ$190,,MATCH(SUBSTITUTE(L$3,"Q","T"),Inputs!$B$2:$AZ$2,0)),Inputs!$B$2:$B$190,$B9)*Inputs!$D$1),"",SUMIFS(INDEX(Inputs!$B$2:$AZ$190,,MATCH(SUBSTITUTE(L$3,"Q","T"),Inputs!$B$2:$AZ$2,0)),Inputs!$B$2:$B$190,$B9)*Inputs!$D$1) -> 0 | M9: =IF(ISNA(SUMIFS(INDEX(Inputs!$B$2:$AZ$190,,MATCH(SUBSTITUTE(M$3,"Q","T"),Inputs!$B$2:$AZ$2,0)),Inputs!$B$2:$B$190,$B9)*Inputs!$D$1),"",SUMIFS(INDEX(Inputs!$B$2:$AZ$190,,MATCH(SUBSTITUTE(M$3,"Q","T"),Inputs!$B$2:$AZ$2,0)),Inputs!$B$2:$B$190,$B9)*Inputs!$D$1) -> 0 | N9: =M9 -> 0 | O9: =IF(ISNA(SUMIFS(INDEX(Inputs!$B$2:$AZ$190,,MATCH(SUBSTITUTE(O$3,"Q","T"),Inputs!$B$2:$AZ$2,0)),Inputs!$B$2:$B$190,$B9)*Inputs!$D$1),"",SUMIFS(INDEX(Inputs!$B$2:$AZ$190,,MATCH(SUBSTITUTE(O$3,"Q","T"),Inputs!$B$2:$AZ$2,0)),Inputs!$B$2:$B$190,$B9)*Inputs!$D$1) -> 0 | P9: =IF(ISNA(SUMIFS(INDEX(Inputs!$B$2:$AZ$190,,MATCH(SUBSTITUTE(P$3,"Q","T"),Inputs!$B$2:$AZ$2,0)),Inputs!$B$2:$B$190,$B9)*Inputs!$D$1),"",SUMIFS(INDEX(Inputs!$B$2:$AZ$190,,MATCH(SUBSTITUTE(P$3,"Q","T"),Inputs!$B$2:$AZ$2,0)),Inputs!$B$2:$B$190,$B9)*Inputs!$D$1) -> 0 | Q9: =IF(ISNA(SUMIFS(INDEX(Inputs!$B$2:$AZ$190,,MATCH(SUBSTITUTE(Q$3,"Q","T"),Inputs!$B$2:$AZ$2,0)),Inputs!$B$2:$B$190,$B9)*Inputs!$D$1),"",SUMIFS(INDEX(Inputs!$B$2:$AZ$190,,MATCH(SUBSTITUTE(Q$3,"Q","T"),Inputs!$B$2:$AZ$2,0)),Inputs!$B$2:$B$190,$B9)*Inputs!$D$1) -> 0 | R9: =IF(ISNA(SUMIFS(INDEX(Inputs!$B$2:$AZ$190,,MATCH(SUBSTITUTE(R$3,"Q","T"),Inputs!$B$2:$AZ$2,0)),Inputs!$B$2:$B$190,$B9)*Inputs!$D$1),"",SUMIFS(INDEX(Inputs!$B$2:$AZ$190,,MATCH(SUBSTITUTE(R$3,"Q","T"),Inputs!$B$2:$AZ$2,0)),Inputs!$B$2:$B$190,$B9)*Inputs!$D$1) -> 0 | S9: =R9 -> 0 | T9: =IF(ISNA(SUMIFS(INDEX(Inputs!$B$2:$AZ$190,,MATCH(SUBSTITUTE(T$3,"Q","T"),Inputs!$B$2:$AZ$2,0)),Inputs!$B$2:$B$190,$B9)*Inputs!$D$1),"",SUMIFS(INDEX(Inputs!$B$2:$AZ$190,,MATCH(SUBSTITUTE(T$3,"Q","T"),Inputs!$B$2:$AZ$2,0)),Inputs!$B$2:$B$190,$B9)*Inputs!$D$1) -> 0 | U9: =IF(ISNA(SUMIFS(INDEX(Inputs!$B$2:$AZ$190,,MATCH(SUBSTITUTE(U$3,"Q","T"),Inputs!$B$2:$AZ$2,0)),Inputs!$B$2:$B$190,$B9)*Inputs!$D$1),"",SUMIFS(INDEX(Inputs!$B$2:$AZ$190,,MATCH(SUBSTITUTE(U$3,"Q","T"),Inputs!$B$2:$AZ$2,0)),Inputs!$B$2:$B$190,$B9)*Inputs!$D$1) -> 0 | V9: =IF(ISNA(SUMIFS(INDEX(Inputs!$B$2:$AZ$190,,MATCH(SUBSTITUTE(V$3,"Q","T"),Inputs!$B$2:$AZ$2,0)),Inputs!$B$2:$B$190,$B9)*Inputs!$D$1),"",SUMIFS(INDEX(Inputs!$B$2:$AZ$190,,MATCH(SUBSTITUTE(V$3,"Q","T"),Inputs!$B$2:$AZ$2,0)),Inputs!$B$2:$B$190,$B9)*Inputs!$D$1) -> 0 | W9: =IF(ISNA(SUMIFS(INDEX(Inputs!$B$2:$AZ$190,,MATCH(SUBSTITUTE(W$3,"Q","T"),Inputs!$B$2:$AZ$2,0)),Inputs!$B$2:$B$190,$B9)*Inputs!$D$1),"",SUMIFS(INDEX(Inputs!$B$2:$AZ$190,,MATCH(SUBSTITUTE(W$3,"Q","T"),Inputs!$B$2:$AZ$2,0)),Inputs!$B$2:$B$190,$B9)*Inputs!$D$1) -> 0 | X9: =W9 -> 0 | Y9: =IF(ISNA(SUMIFS(INDEX(Inputs!$B$2:$AZ$190,,MATCH(SUBSTITUTE(Y$3,"Q","T"),Inputs!$B$2:$AZ$2,0)),Inputs!$B$2:$B$190,$B9)*Inputs!$D$1),"",SUMIFS(INDEX(Inputs!$B$2:$AZ$190,,MATCH(SUBSTITUTE(Y$3,"Q","T"),Inputs!$B$2:$AZ$2,0)),Inputs!$B$2:$B$190,$B9)*Inputs!$D$1) -> 0 | Z9: =IF(ISNA(SUMIFS(INDEX(Inputs!$B$2:$AZ$190,,MATCH(SUBSTITUTE(Z$3,"Q","T"),Inputs!$B$2:$AZ$2,0)),Inputs!$B$2:$B$190,$B9)*Inputs!$D$1),"",SUMIFS(INDEX(Inputs!$B$2:$AZ$190,,MATCH(SUBSTITUTE(Z$3,"Q","T"),Inputs!$B$2:$AZ$2,0)),Inputs!$B$2:$B$190,$B9)*Inputs!$D$1) -> 0 | AA9: =IF(ISNA(SUMIFS(INDEX(Inputs!$B$2:$AZ$190,,MATCH(SUBSTITUTE(AA$3,"Q","T"),Inputs!$B$2:$AZ$2,0)),Inputs!$B$2:$B$190,$B9)*Inputs!$D$1),"",SUMIFS(INDEX(Inputs!$B$2:$AZ$190,,MATCH(SUBSTITUTE(AA$3,"Q","T"),Inputs!$B$2:$AZ$2,0)),Inputs!$B$2:$B$190,$B9)*Inputs!$D$1) -> 0 | AB9: =IF(ISNA(SUMIFS(INDEX(Inputs!$B$2:$AZ$190,,MATCH(SUBSTITUTE(AB$3,"Q","T"),Inputs!$B$2:$AZ$2,0)),Inputs!$B$2:$B$190,$B9)*Inputs!$D$1),"",SUMIFS(INDEX(Inputs!$B$2:$AZ$190,,MATCH(SUBSTITUTE(AB$3,"Q","T"),Inputs!$B$2:$AZ$2,0)),Inputs!$B$2:$B$190,$B9)*Inputs!$D$1) -> 0 | AC9: =AB9 -> 0 | AD9: =IF(ISNA(SUMIFS(INDEX(Inputs!$B$2:$AZ$190,,MATCH(SUBSTITUTE(AD$3,"Q","T"),Inputs!$B$2:$AZ$2,0)),Inputs!$B$2:$B$190,$B9)*Inputs!$D$1),"",SUMIFS(INDEX(Inputs!$B$2:$AZ$190,,MATCH(SUBSTITUTE(AD$3,"Q","T"),Inputs!$B$2:$AZ$2,0)),Inputs!$B$2:$B$190,$B9)*Inputs!$D$1) -> 0 | AE9: =IF(ISNA(SUMIFS(INDEX(Inputs!$B$2:$AZ$190,,MATCH(SUBSTITUTE(AE$3,"Q","T"),Inputs!$B$2:$AZ$2,0)),Inputs!$B$2:$B$190,$B9)*Inputs!$D$1),"",SUMIFS(INDEX(Inputs!$B$2:$AZ$190,,MATCH(SUBSTITUTE(AE$3,"Q","T"),Inputs!$B$2:$AZ$2,0)),Inputs!$B$2:$B$190,$B9)*Inputs!$D$1) -> 0 | AF9: =IF(ISNA(SUMIFS(INDEX(Inputs!$B$2:$AZ$190,,MATCH(SUBSTITUTE(AF$3,"Q","T"),Inputs!$B$2:$AZ$2,0)),Inputs!$B$2:$B$190,$B9)*Inputs!$D$1),"",SUMIFS(INDEX(Inputs!$B$2:$AZ$190,,MATCH(SUBSTITUTE(AF$3,"Q","T"),Inputs!$B$2:$AZ$2,0)),Inputs!$B$2:$B$190,$B9)*Inputs!$D$1) -> 0 | AG9: =IF(ISNA(SUMIFS(INDEX(Inputs!$B$2:$AZ$190,,MATCH(SUBSTITUTE(AG$3,"Q","T"),Inputs!$B$2:$AZ$2,0)),Inputs!$B$2:$B$190,$B9)*Inputs!$D$1),"",SUMIFS(INDEX(Inputs!$B$2:$AZ$190,,MATCH(SUBSTITUTE(AG$3,"Q","T"),Inputs!$B$2:$AZ$2,0)),Inputs!$B$2:$B$190,$B9)*Inputs!$D$1) -> 0 | AH9: =AG9 -> 0 | AI9: =IF(ISNA(SUMIFS(INDEX(Inputs!$B$2:$AZ$190,,MATCH(SUBSTITUTE(AI$3,"Q","T"),Inputs!$B$2:$AZ$2,0)),Inputs!$B$2:$B$190,$B9)*Inputs!$D$1),"",SUMIFS(INDEX(Inputs!$B$2:$AZ$190,,MATCH(SUBSTITUTE(AI$3,"Q","T"),Inputs!$B$2:$AZ$2,0)),Inputs!$B$2:$B$190,$B9)*Inputs!$D$1) -> 0 | AJ9: =IF(ISNA(SUMIFS(INDEX(Inputs!$B$2:$AZ$190,,MATCH(SUBSTITUTE(AJ$3,"Q","T"),Inputs!$B$2:$AZ$2,0)),Inputs!$B$2:$B$190,$B9)*Inputs!$D$1),"",SUMIFS(INDEX(Inputs!$B$2:$AZ$190,,MATCH(SUBSTITUTE(AJ$3,"Q","T"),Inputs!$B$2:$AZ$2,0)),Inputs!$B$2:$B$190,$B9)*Inputs!$D$1) -> 0 | AK9: =IF(ISNA(SUMIFS(INDEX(Inputs!$B$2:$AZ$190,,MATCH(SUBSTITUTE(AK$3,"Q","T"),Inputs!$B$2:$AZ$2,0)),Inputs!$B$2:$B$190,$B9)*Inputs!$D$1),"",SUMIFS(INDEX(Inputs!$B$2:$AZ$190,,MATCH(SUBSTITUTE(AK$3,"Q","T"),Inputs!$B$2:$AZ$2,0)),Inputs!$B$2:$B$190,$B9)*Inputs!$D$1) -> 0 | AL9: =IF(ISNA(SUMIFS(INDEX(Inputs!$B$2:$AZ$190,,MATCH(SUBSTITUTE(AL$3,"Q","T"),Inputs!$B$2:$AZ$2,0)),Inputs!$B$2:$B$190,$B9)*Inputs!$D$1),"",SUMIFS(INDEX(Inputs!$B$2:$AZ$190,,MATCH(SUBSTITUTE(AL$3,"Q","T"),Inputs!$B$2:$AZ$2,0)),Inputs!$B$2:$B$190,$B9)*Inputs!$D$1) -> 0 | AM9: =AL9 -> 0 | AN9: =IF(ISNA(SUMIFS(INDEX(Inputs!$B$2:$AZ$190,,MATCH(SUBSTITUTE(AN$3,"Q","T"),Inputs!$B$2:$AZ$2,0)),Inputs!$B$2:$B$190,$B9)*Inputs!$D$1),"",SUMIFS(INDEX(Inputs!$B$2:$AZ$190,,MATCH(SUBSTITUTE(AN$3,"Q","T"),Inputs!$B$2:$AZ$2,0)),Inputs!$B$2:$B$190,$B9)*Inputs!$D$1) -> 0 | AO9: =IF(ISNA(SUMIFS(INDEX(Inputs!$B$2:$AZ$190,,MATCH(SUBSTITUTE(AO$3,"Q","T"),Inputs!$B$2:$AZ$2,0)),Inputs!$B$2:$B$190,$B9)*Inputs!$D$1),"",SUMIFS(INDEX(Inputs!$B$2:$AZ$190,,MATCH(SUBSTITUTE(AO$3,"Q","T"),Inputs!$B$2:$AZ$2,0)),Inputs!$B$2:$B$190,$B9)*Inputs!$D$1) -> 0 | AP9: =IF(ISNA(SUMIFS(INDEX(Inputs!$B$2:$AZ$190,,MATCH(SUBSTITUTE(AP$3,"Q","T"),Inputs!$B$2:$AZ$2,0)),Inputs!$B$2:$B$190,$B9)*Inputs!$D$1),"",SUMIFS(INDEX(Inputs!$B$2:$AZ$190,,MATCH(SUBSTITUTE(AP$3,"Q","T"),Inputs!$B$2:$AZ$2,0)),Inputs!$B$2:$B$190,$B9)*Inputs!$D$1) -> 0 | AQ9: =IF(ISNA(SUMIFS(INDEX(Inputs!$B$2:$AZ$190,,MATCH(SUBSTITUTE(AQ$3,"Q","T"),Inputs!$B$2:$AZ$2,0)),Inputs!$B$2:$B$190,$B9)*Inputs!$D$1),"",SUMIFS(INDEX(Inputs!$B$2:$AZ$190,,MATCH(SUBSTITUTE(AQ$3,"Q","T"),Inputs!$B$2:$AZ$2,0)),Inputs!$B$2:$B$190,$B9)*Inputs!$D$1) -> 0 | AR9: =AQ9 -> 0 | AS9: =IF(ISNA(SUMIFS(INDEX(Inputs!$B$2:$AZ$190,,MATCH(SUBSTITUTE(AS$3,"Q","T"),Inputs!$B$2:$AZ$2,0)),Inputs!$B$2:$B$190,$B9)*Inputs!$D$1),"",SUMIFS(INDEX(Inputs!$B$2:$AZ$190,,MATCH(SUBSTITUTE(AS$3,"Q","T"),Inputs!$B$2:$AZ$2,0)),Inputs!$B$2:$B$190,$B9)*Inputs!$D$1) -> 0 | AT9: =IF(ISNA(SUMIFS(INDEX(Inputs!$B$2:$AZ$190,,MATCH(SUBSTITUTE(AT$3,"Q","T"),Inputs!$B$2:$AZ$2,0)),Inputs!$B$2:$B$190,$B9)*Inputs!$D$1),"",SUMIFS(INDEX(Inputs!$B$2:$AZ$190,,MATCH(SUBSTITUTE(AT$3,"Q","T"),Inputs!$B$2:$AZ$2,0)),Inputs!$B$2:$B$190,$B9)*Inputs!$D$1) -> 0 | AU9: =IF(ISNA(SUMIFS(INDEX(Inputs!$B$2:$AZ$190,,MATCH(SUBSTITUTE(AU$3,"Q","T"),Inputs!$B$2:$AZ$2,0)),Inputs!$B$2:$B$190,$B9)*Inputs!$D$1),"",SUMIFS(INDEX(Inputs!$B$2:$AZ$190,,MATCH(SUBSTITUTE(AU$3,"Q","T"),Inputs!$B$2:$AZ$2,0)),Inputs!$B$2:$B$190,$B9)*Inputs!$D$1) -> 0 | AV9: =IF(ISNA(SUMIFS(INDEX(Inputs!$B$2:$AZ$190,,MATCH(SUBSTITUTE(AV$3,"Q","T"),Inputs!$B$2:$AZ$2,0)),Inputs!$B$2:$B$190,$B9)*Inputs!$D$1),"",SUMIFS(INDEX(Inputs!$B$2:$AZ$190,,MATCH(SUBSTITUTE(AV$3,"Q","T"),Inputs!$B$2:$AZ$2,0)),Inputs!$B$2:$B$190,$B9)*Inputs!$D$1) -> 0 | AW9: =AV9 -> 0 | AX9: =IF(ISNA(SUMIFS(INDEX(Inputs!$B$2:$AZ$190,,MATCH(SUBSTITUTE(AX$3,"Q","T"),Inputs!$B$2:$AZ$2,0)),Inputs!$B$2:$B$190,$B9)*Inputs!$D$1),"",SUMIFS(INDEX(Inputs!$B$2:$AZ$190,,MATCH(SUBSTITUTE(AX$3,"Q","T"),Inputs!$B$2:$AZ$2,0)),Inputs!$B$2:$B$190,$B9)*Inputs!$D$1) -> 0 | AY9: =IF(ISNA(SUMIFS(INDEX(Inputs!$B$2:$AZ$190,,MATCH(SUBSTITUTE(AY$3,"Q","T"),Inputs!$B$2:$AZ$2,0)),Inputs!$B$2:$B$190,$B9)*Inputs!$D$1),"",SUMIFS(INDEX(Inputs!$B$2:$AZ$190,,MATCH(SUBSTITUTE(AY$3,"Q","T"),Inputs!$B$2:$AZ$2,0)),Inputs!$B$2:$B$190,$B9)*Inputs!$D$1) -> 0 | AZ9: =IF(ISNA(SUMIFS(INDEX(Inputs!$B$2:$AZ$190,,MATCH(SUBSTITUTE(AZ$3,"Q","T"),Inputs!$B$2:$AZ$2,0)),Inputs!$B$2:$B$190,$B9)*Inputs!$D$1),"",SUMIFS(INDEX(Inputs!$B$2:$AZ$190,,MATCH(SUBSTITUTE(AZ$3,"Q","T"),Inputs!$B$2:$AZ$2,0)),Inputs!$B$2:$B$190,$B9)*Inputs!$D$1) -> 0 | BA9: =IF(ISNA(SUMIFS(INDEX(Inputs!$B$2:$AZ$190,,MATCH(SUBSTITUTE(BA$3,"Q","T"),Inputs!$B$2:$AZ$2,0)),Inputs!$B$2:$B$190,$B9)*Inputs!$D$1),"",SUMIFS(INDEX(Inputs!$B$2:$AZ$190,,MATCH(SUBSTITUTE(BA$3,"Q","T"),Inputs!$B$2:$AZ$2,0)),Inputs!$B$2:$B$190,$B9)*Inputs!$D$1) -> 0 | BB9: =BA9 -> 0 | BC9: =IF(ISNA(SUMIFS(INDEX(Inputs!$B$2:$AZ$190,,MATCH(SUBSTITUTE(BC$3,"Q","T"),Inputs!$B$2:$AZ$2,0)),Inputs!$B$2:$B$190,$B9)*Inputs!$D$1),"",SUMIFS(INDEX(Inputs!$B$2:$AZ$190,,MATCH(SUBSTITUTE(BC$3,"Q","T"),Inputs!$B$2:$AZ$2,0)),Inputs!$B$2:$B$190,$B9)*Inputs!$D$1) -> 0 | BD9: =IF(ISNA(SUMIFS(INDEX(Inputs!$B$2:$AZ$190,,MATCH(SUBSTITUTE(BD$3,"Q","T"),Inputs!$B$2:$AZ$2,0)),Inputs!$B$2:$B$190,$B9)*Inputs!$D$1),"",SUMIFS(INDEX(Inputs!$B$2:$AZ$190,,MATCH(SUBSTITUTE(BD$3,"Q","T"),Inputs!$B$2:$AZ$2,0)),Inputs!$B$2:$B$190,$B9)*Inputs!$D$1) -> 0 | BE9: =IF(ISNA(SUMIFS(INDEX(Inputs!$B$2:$AZ$190,,MATCH(SUBSTITUTE(BE$3,"Q","T"),Inputs!$B$2:$AZ$2,0)),Inputs!$B$2:$B$190,$B9)*Inputs!$D$1),"",SUMIFS(INDEX(Inputs!$B$2:$AZ$190,,MATCH(SUBSTITUTE(BE$3,"Q","T"),Inputs!$B$2:$AZ$2,0)),Inputs!$B$2:$B$190,$B9)*Inputs!$D$1) -> 0 | BF9: =IF(ISNA(SUMIFS(INDEX(Inputs!$B$2:$AZ$190,,MATCH(SUBSTITUTE(BF$3,"Q","T"),Inputs!$B$2:$AZ$2,0)),Inputs!$B$2:$B$190,$B9)*Inputs!$D$1),"",SUMIFS(INDEX(Inputs!$B$2:$AZ$190,,MATCH(SUBSTITUTE(BF$3,"Q","T"),Inputs!$B$2:$AZ$2,0)),Inputs!$B$2:$B$190,$B9)*Inputs!$D$1) -> 0 | BG9: =BF9 -> 0
B10: aplic_pdd | C10: (Provisão para Perda de Crédito Esperada) | D10: (Allowance for Expected Credit Losses) | E10: =IF(ISNA(SUMIFS(INDEX(Inputs!$B$2:$AZ$190,,MATCH(SUBSTITUTE(E$3,"Q","T"),Inputs!$B$2:$AZ$2,0)),Inputs!$B$2:$B$190,$B10)*Inputs!$D$1),"",SUMIFS(INDEX(Inputs!$B$2:$AZ$190,,MATCH(SUBSTITUTE(E$3,"Q","T"),Inputs!$B$2:$AZ$2,0)),Inputs!$B$2:$B$190,$B10)*Inputs!$D$1) -> 0 | F10: =IF(ISNA(SUMIFS(INDEX(Inputs!$B$2:$AZ$190,,MATCH(SUBSTITUTE(F$3,"Q","T"),Inputs!$B$2:$AZ$2,0)),Inputs!$B$2:$B$190,$B10)*Inputs!$D$1),"",SUMIFS(INDEX(Inputs!$B$2:$AZ$190,,MATCH(SUBSTITUTE(F$3,"Q","T"),Inputs!$B$2:$AZ$2,0)),Inputs!$B$2:$B$190,$B10)*Inputs!$D$1) -> 0 | G10: =IF(ISNA(SUMIFS(INDEX(Inputs!$B$2:$AZ$190,,MATCH(SUBSTITUTE(G$3,"Q","T"),Inputs!$B$2:$AZ$2,0)),Inputs!$B$2:$B$190,$B10)*Inputs!$D$1),"",SUMIFS(INDEX(Inputs!$B$2:$AZ$190,,MATCH(SUBSTITUTE(G$3,"Q","T"),Inputs!$B$2:$AZ$2,0)),Inputs!$B$2:$B$190,$B10)*Inputs!$D$1) -> 0 | H10: =IF(ISNA(SUMIFS(INDEX(Inputs!$B$2:$AZ$190,,MATCH(SUBSTITUTE(H$3,"Q","T"),Inputs!$B$2:$AZ$2,0)),Inputs!$B$2:$B$190,$B10)*Inputs!$D$1),"",SUMIFS(INDEX(Inputs!$B$2:$AZ$190,,MATCH(SUBSTITUTE(H$3,"Q","T"),Inputs!$B$2:$AZ$2,0)),Inputs!$B$2:$B$190,$B10)*Inputs!$D$1) -> 0 | I10: =H10 -> 0 | J10: =IF(ISNA(SUMIFS(INDEX(Inputs!$B$2:$AZ$190,,MATCH(SUBSTITUTE(J$3,"Q","T"),Inputs!$B$2:$AZ$2,0)),Inputs!$B$2:$B$190,$B10)*Inputs!$D$1),"",SUMIFS(INDEX(Inputs!$B$2:$AZ$190,,MATCH(SUBSTITUTE(J$3,"Q","T"),Inputs!$B$2:$AZ$2,0)),Inputs!$B$2:$B$190,$B10)*Inputs!$D$1) -> 0 | K10: =IF(ISNA(SUMIFS(INDEX(Inputs!$B$2:$AZ$190,,MATCH(SUBSTITUTE(K$3,"Q","T"),Inputs!$B$2:$AZ$2,0)),Inputs!$B$2:$B$190,$B10)*Inputs!$D$1),"",SUMIFS(INDEX(Inputs!$B$2:$AZ$190,,MATCH(SUBSTITUTE(K$3,"Q","T"),Inputs!$B$2:$AZ$2,0)),Inputs!$B$2:$B$190,$B10)*Inputs!$D$1) -> 0 | L10: =IF(ISNA(SUMIFS(INDEX(Inputs!$B$2:$AZ$190,,MATCH(SUBSTITUTE(L$3,"Q","T"),Inputs!$B$2:$AZ$2,0)),Inputs!$B$2:$B$190,$B10)*Inputs!$D$1),"",SUMIFS(INDEX(Inputs!$B$2:$AZ$190,,MATCH(SUBSTITUTE(L$3,"Q","T"),Inputs!$B$2:$AZ$2,0)),Inputs!$B$2:$B$190,$B10)*Inputs!$D$1) -> 0 | M10: =IF(ISNA(SUMIFS(INDEX(Inputs!$B$2:$AZ$190,,MATCH(SUBSTITUTE(M$3,"Q","T"),Inputs!$B$2:$AZ$2,0)),Inputs!$B$2:$B$190,$B10)*Inputs!$D$1),"",SUMIFS(INDEX(Inputs!$B$2:$AZ$190,,MATCH(SUBSTITUTE(M$3,"Q","T"),Inputs!$B$2:$AZ$2,0)),Inputs!$B$2:$B$190,$B10)*Inputs!$D$1) -> 0 | N10: =M10 -> 0 | O10: =IF(ISNA(SUMIFS(INDEX(Inputs!$B$2:$AZ$190,,MATCH(SUBSTITUTE(O$3,"Q","T"),Inputs!$B$2:$AZ$2,0)),Inputs!$B$2:$B$190,$B10)*Inputs!$D$1),"",SUMIFS(INDEX(Inputs!$B$2:$AZ$190,,MATCH(SUBSTITUTE(O$3,"Q","T"),Inputs!$B$2:$AZ$2,0)),Inputs!$B$2:$B$190,$B10)*Inputs!$D$1) -> 0 | P10: =IF(ISNA(SUMIFS(INDEX(Inputs!$B$2:$AZ$190,,MATCH(SUBSTITUTE(P$3,"Q","T"),Inputs!$B$2:$AZ$2,0)),Inputs!$B$2:$B$190,$B10)*Inputs!$D$1),"",SUMIFS(INDEX(Inputs!$B$2:$AZ$190,,MATCH(SUBSTITUTE(P$3,"Q","T"),Inputs!$B$2:$AZ$2,0)),Inputs!$B$2:$B$190,$B10)*Inputs!$D$1) -> 0 | Q10: =IF(ISNA(SUMIFS(INDEX(Inputs!$B$2:$AZ$190,,MATCH(SUBSTITUTE(Q$3,"Q","T"),Inputs!$B$2:$AZ$2,0)),Inputs!$B$2:$B$190,$B10)*Inputs!$D$1),"",SUMIFS(INDEX(Inputs!$B$2:$AZ$190,,MATCH(SUBSTITUTE(Q$3,"Q","T"),Inputs!$B$2:$AZ$2,0)),Inputs!$B$2:$B$190,$B10)*Inputs!$D$1) -> 0 | R10: =IF(ISNA(SUMIFS(INDEX(Inputs!$B$2:$AZ$190,,MATCH(SUBSTITUTE(R$3,"Q","T"),Inputs!$B$2:$AZ$2,0)),Inputs!$B$2:$B$190,$B10)*Inputs!$D$1),"",SUMIFS(INDEX(Inputs!$B$2:$AZ$190,,MATCH(SUBSTITUTE(R$3,"Q","T"),Inputs!$B$2:$AZ$2,0)),Inputs!$B$2:$B$190,$B10)*Inputs!$D$1) -> 0 | S10: =R10 -> 0 | T10: =IF(ISNA(SUMIFS(INDEX(Inputs!$B$2:$AZ$190,,MATCH(SUBSTITUTE(T$3,"Q","T"),Inputs!$B$2:$AZ$2,0)),Inputs!$B$2:$B$190,$B10)*Inputs!$D$1),"",SUMIFS(INDEX(Inputs!$B$2:$AZ$190,,MATCH(SUBSTITUTE(T$3,"Q","T"),Inputs!$B$2:$AZ$2,0)),Inputs!$B$2:$B$190,$B10)*Inputs!$D$1) -> 0 | U10: =IF(ISNA(SUMIFS(INDEX(Inputs!$B$2:$AZ$190,,MATCH(SUBSTITUTE(U$3,"Q","T"),Inputs!$B$2:$AZ$2,0)),Inputs!$B$2:$B$190,$B10)*Inputs!$D$1),"",SUMIFS(INDEX(Inputs!$B$2:$AZ$190,,MATCH(SUBSTITUTE(U$3,"Q","T"),Inputs!$B$2:$AZ$2,0)),Inputs!$B$2:$B$190,$B10)*Inputs!$D$1) -> 0 | V10: =IF(ISNA(SUMIFS(INDEX(Inputs!$B$2:$AZ$190,,MATCH(SUBSTITUTE(V$3,"Q","T"),Inputs!$B$2:$AZ$2,0)),Inputs!$B$2:$B$190,$B10)*Inputs!$D$1),"",SUMIFS(INDEX(Inputs!$B$2:$AZ$190,,MATCH(SUBSTITUTE(V$3,"Q","T"),Inputs!$B$2:$AZ$2,0)),Inputs!$B$2:$B$190,$B10)*Inputs!$D$1) -> 0 | W10: =IF(ISNA(SUMIFS(INDEX(Inputs!$B$2:$AZ$190,,MATCH(SUBSTITUTE(W$3,"Q","T"),Inputs!$B$2:$AZ$2,0)),Inputs!$B$2:$B$190,$B10)*Inputs!$D$1),"",SUMIFS(INDEX(Inputs!$B$2:$AZ$190,,MATCH(SUBSTITUTE(W$3,"Q","T"),Inputs!$B$2:$AZ$2,0)),Inputs!$B$2:$B$190,$B10)*Inputs!$D$1) -> 0 | X10: =W10 -> 0 | Y10: =IF(ISNA(SUMIFS(INDEX(Inputs!$B$2:$AZ$190,,MATCH(SUBSTITUTE(Y$3,"Q","T"),Inputs!$B$2:$AZ$2,0)),Inputs!$B$2:$B$190,$B10)*Inputs!$D$1),"",SUMIFS(INDEX(Inputs!$B$2:$AZ$190,,MATCH(SUBSTITUTE(Y$3,"Q","T"),Inputs!$B$2:$AZ$2,0)),Inputs!$B$2:$B$190,$B10)*Inputs!$D$1) -> 0 | Z10: =IF(ISNA(SUMIFS(INDEX(Inputs!$B$2:$AZ$190,,MATCH(SUBSTITUTE(Z$3,"Q","T"),Inputs!$B$2:$AZ$2,0)),Inputs!$B$2:$B$190,$B10)*Inputs!$D$1),"",SUMIFS(INDEX(Inputs!$B$2:$AZ$190,,MATCH(SUBSTITUTE(Z$3,"Q","T"),Inputs!$B$2:$AZ$2,0)),Inputs!$B$2:$B$190,$B10)*Inputs!$D$1) -> 0 | AA10: =IF(ISNA(SUMIFS(INDEX(Inputs!$B$2:$AZ$190,,MATCH(SUBSTITUTE(AA$3,"Q","T"),Inputs!$B$2:$AZ$2,0)),Inputs!$B$2:$B$190,$B10)*Inputs!$D$1),"",SUMIFS(INDEX(Inputs!$B$2:$AZ$190,,MATCH(SUBSTITUTE(AA$3,"Q","T"),Inputs!$B$2:$AZ$2,0)),Inputs!$B$2:$B$190,$B10)*Inputs!$D$1) -> 0 | AB10: =IF(ISNA(SUMIFS(INDEX(Inputs!$B$2:$AZ$190,,MATCH(SUBSTITUTE(AB$3,"Q","T"),Inputs!$B$2:$AZ$2,0)),Inputs!$B$2:$B$190,$B10)*Inputs!$D$1),"",SUMIFS(INDEX(Inputs!$B$2:$AZ$190,,MATCH(SUBSTITUTE(AB$3,"Q","T"),Inputs!$B$2:$AZ$2,0)),Inputs!$B$2:$B$190,$B10)*Inputs!$D$1) -> 0 | AC10: =AB10 -> 0 | AD10: =IF(ISNA(SUMIFS(INDEX(Inputs!$B$2:$AZ$190,,MATCH(SUBSTITUTE(AD$3,"Q","T"),Inputs!$B$2:$AZ$2,0)),Inputs!$B$2:$B$190,$B10)*Inputs!$D$1),"",SUMIFS(INDEX(Inputs!$B$2:$AZ$190,,MATCH(SUBSTITUTE(AD$3,"Q","T"),Inputs!$B$2:$AZ$2,0)),Inputs!$B$2:$B$190,$B10)*Inputs!$D$1) -> 0 | AE10: =IF(ISNA(SUMIFS(INDEX(Inputs!$B$2:$AZ$190,,MATCH(SUBSTITUTE(AE$3,"Q","T"),Inputs!$B$2:$AZ$2,0)),Inputs!$B$2:$B$190,$B10)*Inputs!$D$1),"",SUMIFS(INDEX(Inputs!$B$2:$AZ$190,,MATCH(SUBSTITUTE(AE$3,"Q","T"),Inputs!$B$2:$AZ$2,0)),Inputs!$B$2:$B$190,$B10)*Inputs!$D$1) -> 0 | AF10: =IF(ISNA(SUMIFS(INDEX(Inputs!$B$2:$AZ$190,,MATCH(SUBSTITUTE(AF$3,"Q","T"),Inputs!$B$2:$AZ$2,0)),Inputs!$B$2:$B$190,$B10)*Inputs!$D$1),"",SUMIFS(INDEX(Inputs!$B$2:$AZ$190,,MATCH(SUBSTITUTE(AF$3,"Q","T"),Inputs!$B$2:$AZ$2,0)),Inputs!$B$2:$B$190,$B10)*Inputs!$D$1) -> 0 | AG10: =IF(ISNA(SUMIFS(INDEX(Inputs!$B$2:$AZ$190,,MATCH(SUBSTITUTE(AG$3,"Q","T"),Inputs!$B$2:$AZ$2,0)),Inputs!$B$2:$B$190,$B10)*Inputs!$D$1),"",SUMIFS(INDEX(Inputs!$B$2:$AZ$190,,MATCH(SUBSTITUTE(AG$3,"Q","T"),Inputs!$B$2:$AZ$2,0)),Inputs!$B$2:$B$190,$B10)*Inputs!$D$1) -> 0 | AH10: =AG10 -> 0 | AI10: =IF(ISNA(SUMIFS(INDEX(Inputs!$B$2:$AZ$190,,MATCH(SUBSTITUTE(AI$3,"Q","T"),Inputs!$B$2:$AZ$2,0)),Inputs!$B$2:$B$190,$B10)*Inputs!$D$1),"",SUMIFS(INDEX(Inputs!$B$2:$AZ$190,,MATCH(SUBSTITUTE(AI$3,"Q","T"),Inputs!$B$2:$AZ$2,0)),Inputs!$B$2:$B$190,$B10)*Inputs!$D$1) -> 0 | AJ10: =IF(ISNA(SUMIFS(INDEX(Inputs!$B$2:$AZ$190,,MATCH(SUBSTITUTE(AJ$3,"Q","T"),Inputs!$B$2:$AZ$2,0)),Inputs!$B$2:$B$190,$B10)*Inputs!$D$1),"",SUMIFS(INDEX(Inputs!$B$2:$AZ$190,,MATCH(SUBSTITUTE(AJ$3,"Q","T"),Inputs!$B$2:$AZ$2,0)),Inputs!$B$2:$B$190,$B10)*Inputs!$D$1) -> 0 | AK10: =IF(ISNA(SUMIFS(INDEX(Inputs!$B$2:$AZ$190,,MATCH(SUBSTITUTE(AK$3,"Q","T"),Inputs!$B$2:$AZ$2,0)),Inputs!$B$2:$B$190,$B10)*Inputs!$D$1),"",SUMIFS(INDEX(Inputs!$B$2:$AZ$190,,MATCH(SUBSTITUTE(AK$3,"Q","T"),Inputs!$B$2:$AZ$2,0)),Inputs!$B$2:$B$190,$B10)*Inputs!$D$1) -> 0 | AL10: =IF(ISNA(SUMIFS(INDEX(Inputs!$B$2:$AZ$190,,MATCH(SUBSTITUTE(AL$3,"Q","T"),Inputs!$B$2:$AZ$2,0)),Inputs!$B$2:$B$190,$B10)*Inputs!$D$1),"",SUMIFS(INDEX(Inputs!$B$2:$AZ$190,,MATCH(SUBSTITUTE(AL$3,"Q","T"),Inputs!$B$2:$AZ$2,0)),Inputs!$B$2:$B$190,$B10)*Inputs!$D$1) -> 0 | AM10: =AL10 -> 0 | AN10: =IF(ISNA(SUMIFS(INDEX(Inputs!$B$2:$AZ$190,,MATCH(SUBSTITUTE(AN$3,"Q","T"),Inputs!$B$2:$AZ$2,0)),Inputs!$B$2:$B$190,$B10)*Inputs!$D$1),"",SUMIFS(INDEX(Inputs!$B$2:$AZ$190,,MATCH(SUBSTITUTE(AN$3,"Q","T"),Inputs!$B$2:$AZ$2,0)),Inputs!$B$2:$B$190,$B10)*Inputs!$D$1) -> 0 | AO10: =IF(ISNA(SUMIFS(INDEX(Inputs!$B$2:$AZ$190,,MATCH(SUBSTITUTE(AO$3,"Q","T"),Inputs!$B$2:$AZ$2,0)),Inputs!$B$2:$B$190,$B10)*Inputs!$D$1),"",SUMIFS(INDEX(Inputs!$B$2:$AZ$190,,MATCH(SUBSTITUTE(AO$3,"Q","T"),Inputs!$B$2:$AZ$2,0)),Inputs!$B$2:$B$190,$B10)*Inputs!$D$1) -> 0 | AP10: =IF(ISNA(SUMIFS(INDEX(Inputs!$B$2:$AZ$190,,MATCH(SUBSTITUTE(AP$3,"Q","T"),Inputs!$B$2:$AZ$2,0)),Inputs!$B$2:$B$190,$B10)*Inputs!$D$1),"",SUMIFS(INDEX(Inputs!$B$2:$AZ$190,,MATCH(SUBSTITUTE(AP$3,"Q","T"),Inputs!$B$2:$AZ$2,0)),Inputs!$B$2:$B$190,$B10)*Inputs!$D$1) -> 0 | AQ10: =IF(ISNA(SUMIFS(INDEX(Inputs!$B$2:$AZ$190,,MATCH(SUBSTITUTE(AQ$3,"Q","T"),Inputs!$B$2:$AZ$2,0)),Inputs!$B$2:$B$190,$B10)*Inputs!$D$1),"",SUMIFS(INDEX(Inputs!$B$2:$AZ$190,,MATCH(SUBSTITUTE(AQ$3,"Q","T"),Inputs!$B$2:$AZ$2,0)),Inputs!$B$2:$B$190,$B10)*Inputs!$D$1) -> 0 | AR10: =AQ10 -> 0 | AS10: =IF(ISNA(SUMIFS(INDEX(Inputs!$B$2:$AZ$190,,MATCH(SUBSTITUTE(AS$3,"Q","T"),Inputs!$B$2:$AZ$2,0)),Inputs!$B$2:$B$190,$B10)*Inputs!$D$1),"",SUMIFS(INDEX(Inputs!$B$2:$AZ$190,,MATCH(SUBSTITUTE(AS$3,"Q","T"),Inputs!$B$2:$AZ$2,0)),Inputs!$B$2:$B$190,$B10)*Inputs!$D$1) -> 0 | AT10: =IF(ISNA(SUMIFS(INDEX(Inputs!$B$2:$AZ$190,,MATCH(SUBSTITUTE(AT$3,"Q","T"),Inputs!$B$2:$AZ$2,0)),Inputs!$B$2:$B$190,$B10)*Inputs!$D$1),"",SUMIFS(INDEX(Inputs!$B$2:$AZ$190,,MATCH(SUBSTITUTE(AT$3,"Q","T"),Inputs!$B$2:$AZ$2,0)),Inputs!$B$2:$B$190,$B10)*Inputs!$D$1) -> 0 | AU10: =IF(ISNA(SUMIFS(INDEX(Inputs!$B$2:$AZ$190,,MATCH(SUBSTITUTE(AU$3,"Q","T"),Inputs!$B$2:$AZ$2,0)),Inputs!$B$2:$B$190,$B10)*Inputs!$D$1),"",SUMIFS(INDEX(Inputs!$B$2:$AZ$190,,MATCH(SUBSTITUTE(AU$3,"Q","T"),Inputs!$B$2:$AZ$2,0)),Inputs!$B$2:$B$190,$B10)*Inputs!$D$1) -> 0 | AV10: =IF(ISNA(SUMIFS(INDEX(Inputs!$B$2:$AZ$190,,MATCH(SUBSTITUTE(AV$3,"Q","T"),Inputs!$B$2:$AZ$2,0)),Inputs!$B$2:$B$190,$B10)*Inputs!$D$1),"",SUMIFS(INDEX(Inputs!$B$2:$AZ$190,,MATCH(SUBSTITUTE(AV$3,"Q","T"),Inputs!$B$2:$AZ$2,0)),Inputs!$B$2:$B$190,$B10)*Inputs!$D$1) -> 0 | AW10: =AV10 -> 0 | AX10: =IF(ISNA(SUMIFS(INDEX(Inputs!$B$2:$AZ$190,,MATCH(SUBSTITUTE(AX$3,"Q","T"),Inputs!$B$2:$AZ$2,0)),Inputs!$B$2:$B$190,$B10)*Inputs!$D$1),"",SUMIFS(INDEX(Inputs!$B$2:$AZ$190,,MATCH(SUBSTITUTE(AX$3,"Q","T"),Inputs!$B$2:$AZ$2,0)),Inputs!$B$2:$B$190,$B10)*Inputs!$D$1) -> 0 | AY10: =IF(ISNA(SUMIFS(INDEX(Inputs!$B$2:$AZ$190,,MATCH(SUBSTITUTE(AY$3,"Q","T"),Inputs!$B$2:$AZ$2,0)),Inputs!$B$2:$B$190,$B10)*Inputs!$D$1),"",SUMIFS(INDEX(Inputs!$B$2:$AZ$190,,MATCH(SUBSTITUTE(AY$3,"Q","T"),Inputs!$B$2:$AZ$2,0)),Inputs!$B$2:$B$190,$B10)*Inputs!$D$1) -> 0 | AZ10: =IF(ISNA(SUMIFS(INDEX(Inputs!$B$2:$AZ$190,,MATCH(SUBSTITUTE(AZ$3,"Q","T"),Inputs!$B$2:$AZ$2,0)),Inputs!$B$2:$B$190,$B10)*Inputs!$D$1),"",SUMIFS(INDEX(Inputs!$B$2:$AZ$190,,MATCH(SUBSTITUTE(AZ$3,"Q","T"),Inputs!$B$2:$AZ$2,0)),Inputs!$B$2:$B$190,$B10)*Inputs!$D$1) -> 0 | BA10: =IF(ISNA(SUMIFS(INDEX(Inputs!$B$2:$AZ$190,,MATCH(SUBSTITUTE(BA$3,"Q","T"),Inputs!$B$2:$AZ$2,0)),Inputs!$B$2:$B$190,$B10)*Inputs!$D$1),"",SUMIFS(INDEX(Inputs!$B$2:$AZ$190,,MATCH(SUBSTITUTE(BA$3,"Q","T"),Inputs!$B$2:$AZ$2,0)),Inputs!$B$2:$B$190,$B10)*Inputs!$D$1) -> 0 | BB10: =BA10 -> 0 | BC10: =IF(ISNA(SUMIFS(INDEX(Inputs!$B$2:$AZ$190,,MATCH(SUBSTITUTE(BC$3,"Q","T"),Inputs!$B$2:$AZ$2,0)),Inputs!$B$2:$B$190,$B10)*Inputs!$D$1),"",SUMIFS(INDEX(Inputs!$B$2:$AZ$190,,MATCH(SUBSTITUTE(BC$3,"Q","T"),Inputs!$B$2:$AZ$2,0)),Inputs!$B$2:$B$190,$B10)*Inputs!$D$1) -> 0 | BD10: =IF(ISNA(SUMIFS(INDEX(Inputs!$B$2:$AZ$190,,MATCH(SUBSTITUTE(BD$3,"Q","T"),Inputs!$B$2:$AZ$2,0)),Inputs!$B$2:$B$190,$B10)*Inputs!$D$1),"",SUMIFS(INDEX(Inputs!$B$2:$AZ$190,,MATCH(SUBSTITUTE(BD$3,"Q","T"),Inputs!$B$2:$AZ$2,0)),Inputs!$B$2:$B$190,$B10)*Inputs!$D$1) -> 0 | BE10: =IF(ISNA(SUMIFS(INDEX(Inputs!$B$2:$AZ$190,,MATCH(SUBSTITUTE(BE$3,"Q","T"),Inputs!$B$2:$AZ$2,0)),Inputs!$B$2:$B$190,$B10)*Inputs!$D$1),"",SUMIFS(INDEX(Inputs!$B$2:$AZ$190,,MATCH(SUBSTITUTE(BE$3,"Q","T"),Inputs!$B$2:$AZ$2,0)),Inputs!$B$2:$B$190,$B10)*Inputs!$D$1) -> 0 | BF10: =IF(ISNA(SUMIFS(INDEX(Inputs!$B$2:$AZ$190,,MATCH(SUBSTITUTE(BF$3,"Q","T"),Inputs!$B$2:$AZ$2,0)),Inputs!$B$2:$B$190,$B10)*Inputs!$D$1),"",SUMIFS(INDEX(Inputs!$B$2:$AZ$190,,MATCH(SUBSTITUTE(BF$3,"Q","T"),Inputs!$B$2:$AZ$2,0)),Inputs!$B$2:$B$190,$B10)*Inputs!$D$1) -> 0 | BG10: =BF10 -> 0
C11: Títulos e Valores Mobiliários | D11: Securities | E11: =IFERROR(E12+E13+E14+E15,"") -> 0 | F11: =IFERROR(F12+F13+F14+F15,"") -> 0 | G11: =IFERROR(G12+G13+G14+G15,"") -> 0 | H11: =IFERROR(H12+H13+H14+H15,"") -> 0 | I11: =H11 -> 0 | J11: =IFERROR(J12+J13+J14+J15,"") -> 0 | K11: =IFERROR(K12+K13+K14+K15,"") -> 0 | L11: =IFERROR(L12+L13+L14+L15,"") -> 0 | M11: =IFERROR(M12+M13+M14+M15,"") -> 0 | N11: =M11 -> 0 | O11: =IFERROR(O12+O13+O14+O15,"") -> 0 | P11: =IFERROR(P12+P13+P14+P15,"") -> 0 | Q11: =IFERROR(Q12+Q13+Q14+Q15,"") -> 0 | R11: =IFERROR(R12+R13+R14+R15,"") -> 0 | S11: =R11 -> 0 | T11: =IFERROR(T12+T13+T14+T15,"") -> 0 | U11: =IFERROR(U12+U13+U14+U15,"") -> 0 | V11: =IFERROR(V12+V13+V14+V15,"") -> 0 | W11: =IFERROR(W12+W13+W14+W15,"") -> 0 | X11: =W11 -> 0 | Y11: =IFERROR(Y12+Y13+Y14+Y15,"") -> 0 | Z11: =IFERROR(Z12+Z13+Z14+Z15,"") -> 0 | AA11: =IFERROR(AA12+AA13+AA14+AA15,"") -> 0 | AB11: =IFERROR(AB12+AB13+AB14+AB15,"") -> 0 | AC11: =AB11 -> 0 | AD11: =IFERROR(AD12+AD13+AD14+AD15,"") -> 0 | AE11: =IFERROR(AE12+AE13+AE14+AE15,"") -> 0 | AF11: =IFERROR(AF12+AF13+AF14+AF15,"") -> 0 | AG11: =IFERROR(AG12+AG13+AG14+AG15,"") -> 0 | AH11: =AG11 -> 0 | AI11: =IFERROR(AI12+AI13+AI14+AI15,"") -> 0 | AJ11: =IFERROR(AJ12+AJ13+AJ14+AJ15,"") -> 0 | AK11: =IFERROR(AK12+AK13+AK14+AK15,"") -> 0 | AL11: =IFERROR(AL12+AL13+AL14+AL15,"") -> 0 | AM11: =AL11 -> 0 | AN11: =IFERROR(AN12+AN13+AN14+AN15,"") -> 0 | AO11: =IFERROR(AO12+AO13+AO14+AO15,"") -> 0 | AP11: =IFERROR(AP12+AP13+AP14+AP15,"") -> 0 | AQ11: =IFERROR(AQ12+AQ13+AQ14+AQ15,"") -> 0 | AR11: =AQ11 -> 0 | AS11: =IFERROR(AS12+AS13+AS14+AS15,"") -> 0 | AT11: =IFERROR(AT12+AT13+AT14+AT15,"") -> 0 | AU11: =IFERROR(AU12+AU13+AU14+AU15,"") -> 0 | AV11: =IFERROR(AV12+AV13+AV14+AV15,"") -> 0 | AW11: =AV11 -> 0 | AX11: =IFERROR(AX12+AX13+AX14+AX15,"") -> 0 | AY11: =IFERROR(AY12+AY13+AY14+AY15,"") -> 0 | AZ11: =IFERROR(AZ12+AZ13+AZ14+AZ15,"") -> 0 | BA11: =IFERROR(BA12+BA13+BA14+BA15,"") -> 0 | BB11: =BA11 -> 0 | BC11: =IFERROR(BC12+BC13+BC14+BC15,"") -> 0 | BD11: =IFERROR(BD12+BD13+BD14+BD15,"") -> 0 | BE11: =IFERROR(BE12+BE13+BE14+BE15,"") -> 0 | BF11: =IFERROR(BF12+BF13+BF14+BF15,"") -> 0 | BG11: =BF11 -> 0
B12: tvm_prop | C12: Carteira própria | D12: Own Portfolio | E12: =IF(ISNA(SUMIFS(INDEX(Inputs!$B$2:$AZ$190,,MATCH(SUBSTITUTE(E$3,"Q","T"),Inputs!$B$2:$AZ$2,0)),Inputs!$B$2:$B$190,$B12)*Inputs!$D$1),"",SUMIFS(INDEX(Inputs!$B$2:$AZ$190,,MATCH(SUBSTITUTE(E$3,"Q","T"),Inputs!$B$2:$AZ$2,0)),Inputs!$B$2:$B$190,$B12)*Inputs!$D$1) -> 0 | F12: =IF(ISNA(SUMIFS(INDEX(Inputs!$B$2:$AZ$190,,MATCH(SUBSTITUTE(F$3,"Q","T"),Inputs!$B$2:$AZ$2,0)),Inputs!$B$2:$B$190,$B12)*Inputs!$D$1),"",SUMIFS(INDEX(Inputs!$B$2:$AZ$190,,MATCH(SUBSTITUTE(F$3,"Q","T"),Inputs!$B$2:$AZ$2,0)),Inputs!$B$2:$B$190,$B12)*Inputs!$D$1) -> 0 | G12: =IF(ISNA(SUMIFS(INDEX(Inputs!$B$2:$AZ$190,,MATCH(SUBSTITUTE(G$3,"Q","T"),Inputs!$B$2:$AZ$2,0)),Inputs!$B$2:$B$190,$B12)*Inputs!$D$1),"",SUMIFS(INDEX(Inputs!$B$2:$AZ$190,,MATCH(SUBSTITUTE(G$3,"Q","T"),Inputs!$B$2:$AZ$2,0)),Inputs!$B$2:$B$190,$B12)*Inputs!$D$1) -> 0 | H12: =IF(ISNA(SUMIFS(INDEX(Inputs!$B$2:$AZ$190,,MATCH(SUBSTITUTE(H$3,"Q","T"),Inputs!$B$2:$AZ$2,0)),Inputs!$B$2:$B$190,$B12)*Inputs!$D$1),"",SUMIFS(INDEX(Inputs!$B$2:$AZ$190,,MATCH(SUBSTITUTE(H$3,"Q","T"),Inputs!$B$2:$AZ$2,0)),Inputs!$B$2:$B$190,$B12)*Inputs!$D$1) -> 0 | I12: =H12 -> 0 | J12: =IF(ISNA(SUMIFS(INDEX(Inputs!$B$2:$AZ$190,,MATCH(SUBSTITUTE(J$3,"Q","T"),Inputs!$B$2:$AZ$2,0)),Inputs!$B$2:$B$190,$B12)*Inputs!$D$1),"",SUMIFS(INDEX(Inputs!$B$2:$AZ$190,,MATCH(SUBSTITUTE(J$3,"Q","T"),Inputs!$B$2:$AZ$2,0)),Inputs!$B$2:$B$190,$B12)*Inputs!$D$1) -> 0 | K12: =IF(ISNA(SUMIFS(INDEX(Inputs!$B$2:$AZ$190,,MATCH(SUBSTITUTE(K$3,"Q","T"),Inputs!$B$2:$AZ$2,0)),Inputs!$B$2:$B$190,$B12)*Inputs!$D$1),"",SUMIFS(INDEX(Inputs!$B$2:$AZ$190,,MATCH(SUBSTITUTE(K$3,"Q","T"),Inputs!$B$2:$AZ$2,0)),Inputs!$B$2:$B$190,$B12)*Inputs!$D$1) -> 0 | L12: =IF(ISNA(SUMIFS(INDEX(Inputs!$B$2:$AZ$190,,MATCH(SUBSTITUTE(L$3,"Q","T"),Inputs!$B$2:$AZ$2,0)),Inputs!$B$2:$B$190,$B12)*Inputs!$D$1),"",SUMIFS(INDEX(Inputs!$B$2:$AZ$190,,MATCH(SUBSTITUTE(L$3,"Q","T"),Inputs!$B$2:$AZ$2,0)),Inputs!$B$2:$B$190,$B12)*Inputs!$D$1) -> 0 | M12: =IF(ISNA(SUMIFS(INDEX(Inputs!$B$2:$AZ$190,,MATCH(SUBSTITUTE(M$3,"Q","T"),Inputs!$B$2:$AZ$2,0)),Inputs!$B$2:$B$190,$B12)*Inputs!$D$1),"",SUMIFS(INDEX(Inputs!$B$2:$AZ$190,,MATCH(SUBSTITUTE(M$3,"Q","T"),Inputs!$B$2:$AZ$2,0)),Inputs!$B$2:$B$190,$B12)*Inputs!$D$1) -> 0 | N12: =M12 -> 0 | O12: =IF(ISNA(SUMIFS(INDEX(Inputs!$B$2:$AZ$190,,MATCH(SUBSTITUTE(O$3,"Q","T"),Inputs!$B$2:$AZ$2,0)),Inputs!$B$2:$B$190,$B12)*Inputs!$D$1),"",SUMIFS(INDEX(Inputs!$B$2:$AZ$190,,MATCH(SUBSTITUTE(O$3,"Q","T"),Inputs!$B$2:$AZ$2,0)),Inputs!$B$2:$B$190,$B12)*Inputs!$D$1) -> 0 | P12: =IF(ISNA(SUMIFS(INDEX(Inputs!$B$2:$AZ$190,,MATCH(SUBSTITUTE(P$3,"Q","T"),Inputs!$B$2:$AZ$2,0)),Inputs!$B$2:$B$190,$B12)*Inputs!$D$1),"",SUMIFS(INDEX(Inputs!$B$2:$AZ$190,,MATCH(SUBSTITUTE(P$3,"Q","T"),Inputs!$B$2:$AZ$2,0)),Inputs!$B$2:$B$190,$B12)*Inputs!$D$1) -> 0 | Q12: =IF(ISNA(SUMIFS(INDEX(Inputs!$B$2:$AZ$190,,MATCH(SUBSTITUTE(Q$3,"Q","T"),Inputs!$B$2:$AZ$2,0)),Inputs!$B$2:$B$190,$B12)*Inputs!$D$1),"",SUMIFS(INDEX(Inputs!$B$2:$AZ$190,,MATCH(SUBSTITUTE(Q$3,"Q","T"),Inputs!$B$2:$AZ$2,0)),Inputs!$B$2:$B$190,$B12)*Inputs!$D$1) -> 0 | R12: =IF(ISNA(SUMIFS(INDEX(Inputs!$B$2:$AZ$190,,MATCH(SUBSTITUTE(R$3,"Q","T"),Inputs!$B$2:$AZ$2,0)),Inputs!$B$2:$B$190,$B12)*Inputs!$D$1),"",SUMIFS(INDEX(Inputs!$B$2:$AZ$190,,MATCH(SUBSTITUTE(R$3,"Q","T"),Inputs!$B$2:$AZ$2,0)),Inputs!$B$2:$B$190,$B12)*Inputs!$D$1) -> 0 | S12: =R12 -> 0 | T12: =IF(ISNA(SUMIFS(INDEX(Inputs!$B$2:$AZ$190,,MATCH(SUBSTITUTE(T$3,"Q","T"),Inputs!$B$2:$AZ$2,0)),Inputs!$B$2:$B$190,$B12)*Inputs!$D$1),"",SUMIFS(INDEX(Inputs!$B$2:$AZ$190,,MATCH(SUBSTITUTE(T$3,"Q","T"),Inputs!$B$2:$AZ$2,0)),Inputs!$B$2:$B$190,$B12)*Inputs!$D$1) -> 0 | U12: =IF(ISNA(SUMIFS(INDEX(Inputs!$B$2:$AZ$190,,MATCH(SUBSTITUTE(U$3,"Q","T"),Inputs!$B$2:$AZ$2,0)),Inputs!$B$2:$B$190,$B12)*Inputs!$D$1),"",SUMIFS(INDEX(Inputs!$B$2:$AZ$190,,MATCH(SUBSTITUTE(U$3,"Q","T"),Inputs!$B$2:$AZ$2,0)),Inputs!$B$2:$B$190,$B12)*Inputs!$D$1) -> 0 | V12: =IF(ISNA(SUMIFS(INDEX(Inputs!$B$2:$AZ$190,,MATCH(SUBSTITUTE(V$3,"Q","T"),Inputs!$B$2:$AZ$2,0)),Inputs!$B$2:$B$190,$B12)*Inputs!$D$1),"",SUMIFS(INDEX(Inputs!$B$2:$AZ$190,,MATCH(SUBSTITUTE(V$3,"Q","T"),Inputs!$B$2:$AZ$2,0)),Inputs!$B$2:$B$190,$B12)*Inputs!$D$1) -> 0 | W12: =IF(ISNA(SUMIFS(INDEX(Inputs!$B$2:$AZ$190,,MATCH(SUBSTITUTE(W$3,"Q","T"),Inputs!$B$2:$AZ$2,0)),Inputs!$B$2:$B$190,$B12)*Inputs!$D$1),"",SUMIFS(INDEX(Inputs!$B$2:$AZ$190,,MATCH(SUBSTITUTE(W$3,"Q","T"),Inputs!$B$2:$AZ$2,0)),Inputs!$B$2:$B$190,$B12)*Inputs!$D$1) -> 0 | X12: =W12 -> 0 | Y12: =IF(ISNA(SUMIFS(INDEX(Inputs!$B$2:$AZ$190,,MATCH(SUBSTITUTE(Y$3,"Q","T"),Inputs!$B$2:$AZ$2,0)),Inputs!$B$2:$B$190,$B12)*Inputs!$D$1),"",SUMIFS(INDEX(Inputs!$B$2:$AZ$190,,MATCH(SUBSTITUTE(Y$3,"Q","T"),Inputs!$B$2:$AZ$2,0)),Inputs!$B$2:$B$190,$B12)*Inputs!$D$1) -> 0 | Z12: =IF(ISNA(SUMIFS(INDEX(Inputs!$B$2:$AZ$190,,MATCH(SUBSTITUTE(Z$3,"Q","T"),Inputs!$B$2:$AZ$2,0)),Inputs!$B$2:$B$190,$B12)*Inputs!$D$1),"",SUMIFS(INDEX(Inputs!$B$2:$AZ$190,,MATCH(SUBSTITUTE(Z$3,"Q","T"),Inputs!$B$2:$AZ$2,0)),Inputs!$B$2:$B$190,$B12)*Inputs!$D$1) -> 0 | AA12: =IF(ISNA(SUMIFS(INDEX(Inputs!$B$2:$AZ$190,,MATCH(SUBSTITUTE(AA$3,"Q","T"),Inputs!$B$2:$AZ$2,0)),Inputs!$B$2:$B$190,$B12)*Inputs!$D$1),"",SUMIFS(INDEX(Inputs!$B$2:$AZ$190,,MATCH(SUBSTITUTE(AA$3,"Q","T"),Inputs!$B$2:$AZ$2,0)),Inputs!$B$2:$B$190,$B12)*Inputs!$D$1) -> 0 | AB12: =IF(ISNA(SUMIFS(INDEX(Inputs!$B$2:$AZ$190,,MATCH(SUBSTITUTE(AB$3,"Q","T"),Inputs!$B$2:$AZ$2,0)),Inputs!$B$2:$B$190,$B12)*Inputs!$D$1),"",SUMIFS(INDEX(Inputs!$B$2:$AZ$190,,MATCH(SUBSTITUTE(AB$3,"Q","T"),Inputs!$B$2:$AZ$2,0)),Inputs!$B$2:$B$190,$B12)*Inputs!$D$1) -> 0 | AC12: =AB12 -> 0 | AD12: =IF(ISNA(SUMIFS(INDEX(Inputs!$B$2:$AZ$190,,MATCH(SUBSTITUTE(AD$3,"Q","T"),Inputs!$B$2:$AZ$2,0)),Inputs!$B$2:$B$190,$B12)*Inputs!$D$1),"",SUMIFS(INDEX(Inputs!$B$2:$AZ$190,,MATCH(SUBSTITUTE(AD$3,"Q","T"),Inputs!$B$2:$AZ$2,0)),Inputs!$B$2:$B$190,$B12)*Inputs!$D$1) -> 0 | AE12: =IF(ISNA(SUMIFS(INDEX(Inputs!$B$2:$AZ$190,,MATCH(SUBSTITUTE(AE$3,"Q","T"),Inputs!$B$2:$AZ$2,0)),Inputs!$B$2:$B$190,$B12)*Inputs!$D$1),"",SUMIFS(INDEX(Inputs!$B$2:$AZ$190,,MATCH(SUBSTITUTE(AE$3,"Q","T"),Inputs!$B$2:$AZ$2,0)),Inputs!$B$2:$B$190,$B12)*Inputs!$D$1) -> 0 | AF12: =IF(ISNA(SUMIFS(INDEX(Inputs!$B$2:$AZ$190,,MATCH(SUBSTITUTE(AF$3,"Q","T"),Inputs!$B$2:$AZ$2,0)),Inputs!$B$2:$B$190,$B12)*Inputs!$D$1),"",SUMIFS(INDEX(Inputs!$B$2:$AZ$190,,MATCH(SUBSTITUTE(AF$3,"Q","T"),Inputs!$B$2:$AZ$2,0)),Inputs!$B$2:$B$190,$B12)*Inputs!$D$1) -> 0 | AG12: =IF(ISNA(SUMIFS(INDEX(Inputs!$B$2:$AZ$190,,MATCH(SUBSTITUTE(AG$3,"Q","T"),Inputs!$B$2:$AZ$2,0)),Inputs!$B$2:$B$190,$B12)*Inputs!$D$1),"",SUMIFS(INDEX(Inputs!$B$2:$AZ$190,,MATCH(SUBSTITUTE(AG$3,"Q","T"),Inputs!$B$2:$AZ$2,0)),Inputs!$B$2:$B$190,$B12)*Inputs!$D$1) -> 0 | AH12: =AG12 -> 0 | AI12: =IF(ISNA(SUMIFS(INDEX(Inputs!$B$2:$AZ$190,,MATCH(SUBSTITUTE(AI$3,"Q","T"),Inputs!$B$2:$AZ$2,0)),Inputs!$B$2:$B$190,$B12)*Inputs!$D$1),"",SUMIFS(INDEX(Inputs!$B$2:$AZ$190,,MATCH(SUBSTITUTE(AI$3,"Q","T"),Inputs!$B$2:$AZ$2,0)),Inputs!$B$2:$B$190,$B12)*Inputs!$D$1) -> 0 | AJ12: =IF(ISNA(SUMIFS(INDEX(Inputs!$B$2:$AZ$190,,MATCH(SUBSTITUTE(AJ$3,"Q","T"),Inputs!$B$2:$AZ$2,0)),Inputs!$B$2:$B$190,$B12)*Inputs!$D$1),"",SUMIFS(INDEX(Inputs!$B$2:$AZ$190,,MATCH(SUBSTITUTE(AJ$3,"Q","T"),Inputs!$B$2:$AZ$2,0)),Inputs!$B$2:$B$190,$B12)*Inputs!$D$1) -> 0 | AK12: =IF(ISNA(SUMIFS(INDEX(Inputs!$B$2:$AZ$190,,MATCH(SUBSTITUTE(AK$3,"Q","T"),Inputs!$B$2:$AZ$2,0)),Inputs!$B$2:$B$190,$B12)*Inputs!$D$1),"",SUMIFS(INDEX(Inputs!$B$2:$AZ$190,,MATCH(SUBSTITUTE(AK$3,"Q","T"),Inputs!$B$2:$AZ$2,0)),Inputs!$B$2:$B$190,$B12)*Inputs!$D$1) -> 0 | AL12: =IF(ISNA(SUMIFS(INDEX(Inputs!$B$2:$AZ$190,,MATCH(SUBSTITUTE(AL$3,"Q","T"),Inputs!$B$2:$AZ$2,0)),Inputs!$B$2:$B$190,$B12)*Inputs!$D$1),"",SUMIFS(INDEX(Inputs!$B$2:$AZ$190,,MATCH(SUBSTITUTE(AL$3,"Q","T"),Inputs!$B$2:$AZ$2,0)),Inputs!$B$2:$B$190,$B12)*Inputs!$D$1) -> 0 | AM12: =AL12 -> 0 | AN12: =IF(ISNA(SUMIFS(INDEX(Inputs!$B$2:$AZ$190,,MATCH(SUBSTITUTE(AN$3,"Q","T"),Inputs!$B$2:$AZ$2,0)),Inputs!$B$2:$B$190,$B12)*Inputs!$D$1),"",SUMIFS(INDEX(Inputs!$B$2:$AZ$190,,MATCH(SUBSTITUTE(AN$3,"Q","T"),Inputs!$B$2:$AZ$2,0)),Inputs!$B$2:$B$190,$B12)*Inputs!$D$1) -> 0 | AO12: =IF(ISNA(SUMIFS(INDEX(Inputs!$B$2:$AZ$190,,MATCH(SUBSTITUTE(AO$3,"Q","T"),Inputs!$B$2:$AZ$2,0)),Inputs!$B$2:$B$190,$B12)*Inputs!$D$1),"",SUMIFS(INDEX(Inputs!$B$2:$AZ$190,,MATCH(SUBSTITUTE(AO$3,"Q","T"),Inputs!$B$2:$AZ$2,0)),Inputs!$B$2:$B$190,$B12)*Inputs!$D$1) -> 0 | AP12: =IF(ISNA(SUMIFS(INDEX(Inputs!$B$2:$AZ$190,,MATCH(SUBSTITUTE(AP$3,"Q","T"),Inputs!$B$2:$AZ$2,0)),Inputs!$B$2:$B$190,$B12)*Inputs!$D$1),"",SUMIFS(INDEX(Inputs!$B$2:$AZ$190,,MATCH(SUBSTITUTE(AP$3,"Q","T"),Inputs!$B$2:$AZ$2,0)),Inputs!$B$2:$B$190,$B12)*Inputs!$D$1) -> 0 | AQ12: =IF(ISNA(SUMIFS(INDEX(Inputs!$B$2:$AZ$190,,MATCH(SUBSTITUTE(AQ$3,"Q","T"),Inputs!$B$2:$AZ$2,0)),Inputs!$B$2:$B$190,$B12)*Inputs!$D$1),"",SUMIFS(INDEX(Inputs!$B$2:$AZ$190,,MATCH(SUBSTITUTE(AQ$3,"Q","T"),Inputs!$B$2:$AZ$2,0)),Inputs!$B$2:$B$190,$B12)*Inputs!$D$1) -> 0 | AR12: =AQ12 -> 0 | AS12: =IF(ISNA(SUMIFS(INDEX(Inputs!$B$2:$AZ$190,,MATCH(SUBSTITUTE(AS$3,"Q","T"),Inputs!$B$2:$AZ$2,0)),Inputs!$B$2:$B$190,$B12)*Inputs!$D$1),"",SUMIFS(INDEX(Inputs!$B$2:$AZ$190,,MATCH(SUBSTITUTE(AS$3,"Q","T"),Inputs!$B$2:$AZ$2,0)),Inputs!$B$2:$B$190,$B12)*Inputs!$D$1) -> 0 | AT12: =IF(ISNA(SUMIFS(INDEX(Inputs!$B$2:$AZ$190,,MATCH(SUBSTITUTE(AT$3,"Q","T"),Inputs!$B$2:$AZ$2,0)),Inputs!$B$2:$B$190,$B12)*Inputs!$D$1),"",SUMIFS(INDEX(Inputs!$B$2:$AZ$190,,MATCH(SUBSTITUTE(AT$3,"Q","T"),Inputs!$B$2:$AZ$2,0)),Inputs!$B$2:$B$190,$B12)*Inputs!$D$1) -> 0 | AU12: =IF(ISNA(SUMIFS(INDEX(Inputs!$B$2:$AZ$190,,MATCH(SUBSTITUTE(AU$3,"Q","T"),Inputs!$B$2:$AZ$2,0)),Inputs!$B$2:$B$190,$B12)*Inputs!$D$1),"",SUMIFS(INDEX(Inputs!$B$2:$AZ$190,,MATCH(SUBSTITUTE(AU$3,"Q","T"),Inputs!$B$2:$AZ$2,0)),Inputs!$B$2:$B$190,$B12)*Inputs!$D$1) -> 0 | AV12: =IF(ISNA(SUMIFS(INDEX(Inputs!$B$2:$AZ$190,,MATCH(SUBSTITUTE(AV$3,"Q","T"),Inputs!$B$2:$AZ$2,0)),Inputs!$B$2:$B$190,$B12)*Inputs!$D$1),"",SUMIFS(INDEX(Inputs!$B$2:$AZ$190,,MATCH(SUBSTITUTE(AV$3,"Q","T"),Inputs!$B$2:$AZ$2,0)),Inputs!$B$2:$B$190,$B12)*Inputs!$D$1) -> 0 | AW12: =AV12 -> 0 | AX12: =IF(ISNA(SUMIFS(INDEX(Inputs!$B$2:$AZ$190,,MATCH(SUBSTITUTE(AX$3,"Q","T"),Inputs!$B$2:$AZ$2,0)),Inputs!$B$2:$B$190,$B12)*Inputs!$D$1),"",SUMIFS(INDEX(Inputs!$B$2:$AZ$190,,MATCH(SUBSTITUTE(AX$3,"Q","T"),Inputs!$B$2:$AZ$2,0)),Inputs!$B$2:$B$190,$B12)*Inputs!$D$1) -> 0 | AY12: =IF(ISNA(SUMIFS(INDEX(Inputs!$B$2:$AZ$190,,MATCH(SUBSTITUTE(AY$3,"Q","T"),Inputs!$B$2:$AZ$2,0)),Inputs!$B$2:$B$190,$B12)*Inputs!$D$1),"",SUMIFS(INDEX(Inputs!$B$2:$AZ$190,,MATCH(SUBSTITUTE(AY$3,"Q","T"),Inputs!$B$2:$AZ$2,0)),Inputs!$B$2:$B$190,$B12)*Inputs!$D$1) -> 0 | AZ12: =IF(ISNA(SUMIFS(INDEX(Inputs!$B$2:$AZ$190,,MATCH(SUBSTITUTE(AZ$3,"Q","T"),Inputs!$B$2:$AZ$2,0)),Inputs!$B$2:$B$190,$B12)*Inputs!$D$1),"",SUMIFS(INDEX(Inputs!$B$2:$AZ$190,,MATCH(SUBSTITUTE(AZ$3,"Q","T"),Inputs!$B$2:$AZ$2,0)),Inputs!$B$2:$B$190,$B12)*Inputs!$D$1) -> 0 | BA12: =IF(ISNA(SUMIFS(INDEX(Inputs!$B$2:$AZ$190,,MATCH(SUBSTITUTE(BA$3,"Q","T"),Inputs!$B$2:$AZ$2,0)),Inputs!$B$2:$B$190,$B12)*Inputs!$D$1),"",SUMIFS(INDEX(Inputs!$B$2:$AZ$190,,MATCH(SUBSTITUTE(BA$3,"Q","T"),Inputs!$B$2:$AZ$2,0)),Inputs!$B$2:$B$190,$B12)*Inputs!$D$1) -> 0 | BB12: =BA12 -> 0 | BC12: =IF(ISNA(SUMIFS(INDEX(Inputs!$B$2:$AZ$190,,MATCH(SUBSTITUTE(BC$3,"Q","T"),Inputs!$B$2:$AZ$2,0)),Inputs!$B$2:$B$190,$B12)*Inputs!$D$1),"",SUMIFS(INDEX(Inputs!$B$2:$AZ$190,,MATCH(SUBSTITUTE(BC$3,"Q","T"),Inputs!$B$2:$AZ$2,0)),Inputs!$B$2:$B$190,$B12)*Inputs!$D$1) -> 0 | BD12: =IF(ISNA(SUMIFS(INDEX(Inputs!$B$2:$AZ$190,,MATCH(SUBSTITUTE(BD$3,"Q","T"),Inputs!$B$2:$AZ$2,0)),Inputs!$B$2:$B$190,$B12)*Inputs!$D$1),"",SUMIFS(INDEX(Inputs!$B$2:$AZ$190,,MATCH(SUBSTITUTE(BD$3,"Q","T"),Inputs!$B$2:$AZ$2,0)),Inputs!$B$2:$B$190,$B12)*Inputs!$D$1) -> 0 | BE12: =IF(ISNA(SUMIFS(INDEX(Inputs!$B$2:$AZ$190,,MATCH(SUBSTITUTE(BE$3,"Q","T"),Inputs!$B$2:$AZ$2,0)),Inputs!$B$2:$B$190,$B12)*Inputs!$D$1),"",SUMIFS(INDEX(Inputs!$B$2:$AZ$190,,MATCH(SUBSTITUTE(BE$3,"Q","T"),Inputs!$B$2:$AZ$2,0)),Inputs!$B$2:$B$190,$B12)*Inputs!$D$1) -> 0 | BF12: =IF(ISNA(SUMIFS(INDEX(Inputs!$B$2:$AZ$190,,MATCH(SUBSTITUTE(BF$3,"Q","T"),Inputs!$B$2:$AZ$2,0)),Inputs!$B$2:$B$190,$B12)*Inputs!$D$1),"",SUMIFS(INDEX(Inputs!$B$2:$AZ$190,,MATCH(SUBSTITUTE(BF$3,"Q","T"),Inputs!$B$2:$AZ$2,0)),Inputs!$B$2:$B$190,$B12)*Inputs!$D$1) -> 0 | BG12: =BF12 -> 0
B13: tvm_vinc | C13: Vinculados | D13: Pledged / Restricted | E13: =IF(ISNA(SUMIFS(INDEX(Inputs!$B$2:$AZ$190,,MATCH(SUBSTITUTE(E$3,"Q","T"),Inputs!$B$2:$AZ$2,0)),Inputs!$B$2:$B$190,$B13)*Inputs!$D$1),"",SUMIFS(INDEX(Inputs!$B$2:$AZ$190,,MATCH(SUBSTITUTE(E$3,"Q","T"),Inputs!$B$2:$AZ$2,0)),Inputs!$B$2:$B$190,$B13)*Inputs!$D$1) -> 0 | F13: =IF(ISNA(SUMIFS(INDEX(Inputs!$B$2:$AZ$190,,MATCH(SUBSTITUTE(F$3,"Q","T"),Inputs!$B$2:$AZ$2,0)),Inputs!$B$2:$B$190,$B13)*Inputs!$D$1),"",SUMIFS(INDEX(Inputs!$B$2:$AZ$190,,MATCH(SUBSTITUTE(F$3,"Q","T"),Inputs!$B$2:$AZ$2,0)),Inputs!$B$2:$B$190,$B13)*Inputs!$D$1) -> 0 | G13: =IF(ISNA(SUMIFS(INDEX(Inputs!$B$2:$AZ$190,,MATCH(SUBSTITUTE(G$3,"Q","T"),Inputs!$B$2:$AZ$2,0)),Inputs!$B$2:$B$190,$B13)*Inputs!$D$1),"",SUMIFS(INDEX(Inputs!$B$2:$AZ$190,,MATCH(SUBSTITUTE(G$3,"Q","T"),Inputs!$B$2:$AZ$2,0)),Inputs!$B$2:$B$190,$B13)*Inputs!$D$1) -> 0 | H13: =IF(ISNA(SUMIFS(INDEX(Inputs!$B$2:$AZ$190,,MATCH(SUBSTITUTE(H$3,"Q","T"),Inputs!$B$2:$AZ$2,0)),Inputs!$B$2:$B$190,$B13)*Inputs!$D$1),"",SUMIFS(INDEX(Inputs!$B$2:$AZ$190,,MATCH(SUBSTITUTE(H$3,"Q","T"),Inputs!$B$2:$AZ$2,0)),Inputs!$B$2:$B$190,$B13)*Inputs!$D$1) -> 0 | I13: =H13 -> 0 | J13: =IF(ISNA(SUMIFS(INDEX(Inputs!$B$2:$AZ$190,,MATCH(SUBSTITUTE(J$3,"Q","T"),Inputs!$B$2:$AZ$2,0)),Inputs!$B$2:$B$190,$B13)*Inputs!$D$1),"",SUMIFS(INDEX(Inputs!$B$2:$AZ$190,,MATCH(SUBSTITUTE(J$3,"Q","T"),Inputs!$B$2:$AZ$2,0)),Inputs!$B$2:$B$190,$B13)*Inputs!$D$1) -> 0 | K13: =IF(ISNA(SUMIFS(INDEX(Inputs!$B$2:$AZ$190,,MATCH(SUBSTITUTE(K$3,"Q","T"),Inputs!$B$2:$AZ$2,0)),Inputs!$B$2:$B$190,$B13)*Inputs!$D$1),"",SUMIFS(INDEX(Inputs!$B$2:$AZ$190,,MATCH(SUBSTITUTE(K$3,"Q","T"),Inputs!$B$2:$AZ$2,0)),Inputs!$B$2:$B$190,$B13)*Inputs!$D$1) -> 0 | L13: =IF(ISNA(SUMIFS(INDEX(Inputs!$B$2:$AZ$190,,MATCH(SUBSTITUTE(L$3,"Q","T"),Inputs!$B$2:$AZ$2,0)),Inputs!$B$2:$B$190,$B13)*Inputs!$D$1),"",SUMIFS(INDEX(Inputs!$B$2:$AZ$190,,MATCH(SUBSTITUTE(L$3,"Q","T"),Inputs!$B$2:$AZ$2,0)),Inputs!$B$2:$B$190,$B13)*Inputs!$D$1) -> 0 | M13: =IF(ISNA(SUMIFS(INDEX(Inputs!$B$2:$AZ$190,,MATCH(SUBSTITUTE(M$3,"Q","T"),Inputs!$B$2:$AZ$2,0)),Inputs!$B$2:$B$190,$B13)*Inputs!$D$1),"",SUMIFS(INDEX(Inputs!$B$2:$AZ$190,,MATCH(SUBSTITUTE(M$3,"Q","T"),Inputs!$B$2:$AZ$2,0)),Inputs!$B$2:$B$190,$B13)*Inputs!$D$1) -> 0 | N13: =M13 -> 0 | O13: =IF(ISNA(SUMIFS(INDEX(Inputs!$B$2:$AZ$190,,MATCH(SUBSTITUTE(O$3,"Q","T"),Inputs!$B$2:$AZ$2,0)),Inputs!$B$2:$B$190,$B13)*Inputs!$D$1),"",SUMIFS(INDEX(Inputs!$B$2:$AZ$190,,MATCH(SUBSTITUTE(O$3,"Q","T"),Inputs!$B$2:$AZ$2,0)),Inputs!$B$2:$B$190,$B13)*Inputs!$D$1) -> 0 | P13: =IF(ISNA(SUMIFS(INDEX(Inputs!$B$2:$AZ$190,,MATCH(SUBSTITUTE(P$3,"Q","T"),Inputs!$B$2:$AZ$2,0)),Inputs!$B$2:$B$190,$B13)*Inputs!$D$1),"",SUMIFS(INDEX(Inputs!$B$2:$AZ$190,,MATCH(SUBSTITUTE(P$3,"Q","T"),Inputs!$B$2:$AZ$2,0)),Inputs!$B$2:$B$190,$B13)*Inputs!$D$1) -> 0 | Q13: =IF(ISNA(SUMIFS(INDEX(Inputs!$B$2:$AZ$190,,MATCH(SUBSTITUTE(Q$3,"Q","T"),Inputs!$B$2:$AZ$2,0)),Inputs!$B$2:$B$190,$B13)*Inputs!$D$1),"",SUMIFS(INDEX(Inputs!$B$2:$AZ$190,,MATCH(SUBSTITUTE(Q$3,"Q","T"),Inputs!$B$2:$AZ$2,0)),Inputs!$B$2:$B$190,$B13)*Inputs!$D$1) -> 0 | R13: =IF(ISNA(SUMIFS(INDEX(Inputs!$B$2:$AZ$190,,MATCH(SUBSTITUTE(R$3,"Q","T"),Inputs!$B$2:$AZ$2,0)),Inputs!$B$2:$B$190,$B13)*Inputs!$D$1),"",SUMIFS(INDEX(Inputs!$B$2:$AZ$190,,MATCH(SUBSTITUTE(R$3,"Q","T"),Inputs!$B$2:$AZ$2,0)),Inputs!$B$2:$B$190,$B13)*Inputs!$D$1) -> 0 | S13: =R13 -> 0 | T13: =IF(ISNA(SUMIFS(INDEX(Inputs!$B$2:$AZ$190,,MATCH(SUBSTITUTE(T$3,"Q","T"),Inputs!$B$2:$AZ$2,0)),Inputs!$B$2:$B$190,$B13)*Inputs!$D$1),"",SUMIFS(INDEX(Inputs!$B$2:$AZ$190,,MATCH(SUBSTITUTE(T$3,"Q","T"),Inputs!$B$2:$AZ$2,0)),Inputs!$B$2:$B$190,$B13)*Inputs!$D$1) -> 0 | U13: =IF(ISNA(SUMIFS(INDEX(Inputs!$B$2:$AZ$190,,MATCH(SUBSTITUTE(U$3,"Q","T"),Inputs!$B$2:$AZ$2,0)),Inputs!$B$2:$B$190,$B13)*Inputs!$D$1),"",SUMIFS(INDEX(Inputs!$B$2:$AZ$190,,MATCH(SUBSTITUTE(U$3,"Q","T"),Inputs!$B$2:$AZ$2,0)),Inputs!$B$2:$B$190,$B13)*Inputs!$D$1) -> 0 | V13: =IF(ISNA(SUMIFS(INDEX(Inputs!$B$2:$AZ$190,,MATCH(SUBSTITUTE(V$3,"Q","T"),Inputs!$B$2:$AZ$2,0)),Inputs!$B$2:$B$190,$B13)*Inputs!$D$1),"",SUMIFS(INDEX(Inputs!$B$2:$AZ$190,,MATCH(SUBSTITUTE(V$3,"Q","T"),Inputs!$B$2:$AZ$2,0)),Inputs!$B$2:$B$190,$B13)*Inputs!$D$1) -> 0 | W13: =IF(ISNA(SUMIFS(INDEX(Inputs!$B$2:$AZ$190,,MATCH(SUBSTITUTE(W$3,"Q","T"),Inputs!$B$2:$AZ$2,0)),Inputs!$B$2:$B$190,$B13)*Inputs!$D$1),"",SUMIFS(INDEX(Inputs!$B$2:$AZ$190,,MATCH(SUBSTITUTE(W$3,"Q","T"),Inputs!$B$2:$AZ$2,0)),Inputs!$B$2:$B$190,$B13)*Inputs!$D$1) -> 0 | X13: =W13 -> 0 | Y13: =IF(ISNA(SUMIFS(INDEX(Inputs!$B$2:$AZ$190,,MATCH(SUBSTITUTE(Y$3,"Q","T"),Inputs!$B$2:$AZ$2,0)),Inputs!$B$2:$B$190,$B13)*Inputs!$D$1),"",SUMIFS(INDEX(Inputs!$B$2:$AZ$190,,MATCH(SUBSTITUTE(Y$3,"Q","T"),Inputs!$B$2:$AZ$2,0)),Inputs!$B$2:$B$190,$B13)*Inputs!$D$1) -> 0 | Z13: =IF(ISNA(SUMIFS(INDEX(Inputs!$B$2:$AZ$190,,MATCH(SUBSTITUTE(Z$3,"Q","T"),Inputs!$B$2:$AZ$2,0)),Inputs!$B$2:$B$190,$B13)*Inputs!$D$1),"",SUMIFS(INDEX(Inputs!$B$2:$AZ$190,,MATCH(SUBSTITUTE(Z$3,"Q","T"),Inputs!$B$2:$AZ$2,0)),Inputs!$B$2:$B$190,$B13)*Inputs!$D$1) -> 0 | AA13: =IF(ISNA(SUMIFS(INDEX(Inputs!$B$2:$AZ$190,,MATCH(SUBSTITUTE(AA$3,"Q","T"),Inputs!$B$2:$AZ$2,0)),Inputs!$B$2:$B$190,$B13)*Inputs!$D$1),"",SUMIFS(INDEX(Inputs!$B$2:$AZ$190,,MATCH(SUBSTITUTE(AA$3,"Q","T"),Inputs!$B$2:$AZ$2,0)),Inputs!$B$2:$B$190,$B13)*Inputs!$D$1) -> 0 | AB13: =IF(ISNA(SUMIFS(INDEX(Inputs!$B$2:$AZ$190,,MATCH(SUBSTITUTE(AB$3,"Q","T"),Inputs!$B$2:$AZ$2,0)),Inputs!$B$2:$B$190,$B13)*Inputs!$D$1),"",SUMIFS(INDEX(Inputs!$B$2:$AZ$190,,MATCH(SUBSTITUTE(AB$3,"Q","T"),Inputs!$B$2:$AZ$2,0)),Inputs!$B$2:$B$190,$B13)*Inputs!$D$1) -> 0 | AC13: =AB13 -> 0 | AD13: =IF(ISNA(SUMIFS(INDEX(Inputs!$B$2:$AZ$190,,MATCH(SUBSTITUTE(AD$3,"Q","T"),Inputs!$B$2:$AZ$2,0)),Inputs!$B$2:$B$190,$B13)*Inputs!$D$1),"",SUMIFS(INDEX(Inputs!$B$2:$AZ$190,,MATCH(SUBSTITUTE(AD$3,"Q","T"),Inputs!$B$2:$AZ$2,0)),Inputs!$B$2:$B$190,$B13)*Inputs!$D$1) -> 0 | AE13: =IF(ISNA(SUMIFS(INDEX(Inputs!$B$2:$AZ$190,,MATCH(SUBSTITUTE(AE$3,"Q","T"),Inputs!$B$2:$AZ$2,0)),Inputs!$B$2:$B$190,$B13)*Inputs!$D$1),"",SUMIFS(INDEX(Inputs!$B$2:$AZ$190,,MATCH(SUBSTITUTE(AE$3,"Q","T"),Inputs!$B$2:$AZ$2,0)),Inputs!$B$2:$B$190,$B13)*Inputs!$D$1) -> 0 | AF13: =IF(ISNA(SUMIFS(INDEX(Inputs!$B$2:$AZ$190,,MATCH(SUBSTITUTE(AF$3,"Q","T"),Inputs!$B$2:$AZ$2,0)),Inputs!$B$2:$B$190,$B13)*Inputs!$D$1),"",SUMIFS(INDEX(Inputs!$B$2:$AZ$190,,MATCH(SUBSTITUTE(AF$3,"Q","T"),Inputs!$B$2:$AZ$2,0)),Inputs!$B$2:$B$190,$B13)*Inputs!$D$1) -> 0 | AG13: =IF(ISNA(SUMIFS(INDEX(Inputs!$B$2:$AZ$190,,MATCH(SUBSTITUTE(AG$3,"Q","T"),Inputs!$B$2:$AZ$2,0)),Inputs!$B$2:$B$190,$B13)*Inputs!$D$1),"",SUMIFS(INDEX(Inputs!$B$2:$AZ$190,,MATCH(SUBSTITUTE(AG$3,"Q","T"),Inputs!$B$2:$AZ$2,0)),Inputs!$B$2:$B$190,$B13)*Inputs!$D$1) -> 0 | AH13: =AG13 -> 0 | AI13: =IF(ISNA(SUMIFS(INDEX(Inputs!$B$2:$AZ$190,,MATCH(SUBSTITUTE(AI$3,"Q","T"),Inputs!$B$2:$AZ$2,0)),Inputs!$B$2:$B$190,$B13)*Inputs!$D$1),"",SUMIFS(INDEX(Inputs!$B$2:$AZ$190,,MATCH(SUBSTITUTE(AI$3,"Q","T"),Inputs!$B$2:$AZ$2,0)),Inputs!$B$2:$B$190,$B13)*Inputs!$D$1) -> 0 | AJ13: =IF(ISNA(SUMIFS(INDEX(Inputs!$B$2:$AZ$190,,MATCH(SUBSTITUTE(AJ$3,"Q","T"),Inputs!$B$2:$AZ$2,0)),Inputs!$B$2:$B$190,$B13)*Inputs!$D$1),"",SUMIFS(INDEX(Inputs!$B$2:$AZ$190,,MATCH(SUBSTITUTE(AJ$3,"Q","T"),Inputs!$B$2:$AZ$2,0)),Inputs!$B$2:$B$190,$B13)*Inputs!$D$1) -> 0 | AK13: =IF(ISNA(SUMIFS(INDEX(Inputs!$B$2:$AZ$190,,MATCH(SUBSTITUTE(AK$3,"Q","T"),Inputs!$B$2:$AZ$2,0)),Inputs!$B$2:$B$190,$B13)*Inputs!$D$1),"",SUMIFS(INDEX(Inputs!$B$2:$AZ$190,,MATCH(SUBSTITUTE(AK$3,"Q","T"),Inputs!$B$2:$AZ$2,0)),Inputs!$B$2:$B$190,$B13)*Inputs!$D$1) -> 0 | AL13: =IF(ISNA(SUMIFS(INDEX(Inputs!$B$2:$AZ$190,,MATCH(SUBSTITUTE(AL$3,"Q","T"),Inputs!$B$2:$AZ$2,0)),Inputs!$B$2:$B$190,$B13)*Inputs!$D$1),"",SUMIFS(INDEX(Inputs!$B$2:$AZ$190,,MATCH(SUBSTITUTE(AL$3,"Q","T"),Inputs!$B$2:$AZ$2,0)),Inputs!$B$2:$B$190,$B13)*Inputs!$D$1) -> 0 | AM13: =AL13 -> 0 | AN13: =IF(ISNA(SUMIFS(INDEX(Inputs!$B$2:$AZ$190,,MATCH(SUBSTITUTE(AN$3,"Q","T"),Inputs!$B$2:$AZ$2,0)),Inputs!$B$2:$B$190,$B13)*Inputs!$D$1),"",SUMIFS(INDEX(Inputs!$B$2:$AZ$190,,MATCH(SUBSTITUTE(AN$3,"Q","T"),Inputs!$B$2:$AZ$2,0)),Inputs!$B$2:$B$190,$B13)*Inputs!$D$1) -> 0 | AO13: =IF(ISNA(SUMIFS(INDEX(Inputs!$B$2:$AZ$190,,MATCH(SUBSTITUTE(AO$3,"Q","T"),Inputs!$B$2:$AZ$2,0)),Inputs!$B$2:$B$190,$B13)*Inputs!$D$1),"",SUMIFS(INDEX(Inputs!$B$2:$AZ$190,,MATCH(SUBSTITUTE(AO$3,"Q","T"),Inputs!$B$2:$AZ$2,0)),Inputs!$B$2:$B$190,$B13)*Inputs!$D$1) -> 0 | AP13: =IF(ISNA(SUMIFS(INDEX(Inputs!$B$2:$AZ$190,,MATCH(SUBSTITUTE(AP$3,"Q","T"),Inputs!$B$2:$AZ$2,0)),Inputs!$B$2:$B$190,$B13)*Inputs!$D$1),"",SUMIFS(INDEX(Inputs!$B$2:$AZ$190,,MATCH(SUBSTITUTE(AP$3,"Q","T"),Inputs!$B$2:$AZ$2,0)),Inputs!$B$2:$B$190,$B13)*Inputs!$D$1) -> 0 | AQ13: =IF(ISNA(SUMIFS(INDEX(Inputs!$B$2:$AZ$190,,MATCH(SUBSTITUTE(AQ$3,"Q","T"),Inputs!$B$2:$AZ$2,0)),Inputs!$B$2:$B$190,$B13)*Inputs!$D$1),"",SUMIFS(INDEX(Inputs!$B$2:$AZ$190,,MATCH(SUBSTITUTE(AQ$3,"Q","T"),Inputs!$B$2:$AZ$2,0)),Inputs!$B$2:$B$190,$B13)*Inputs!$D$1) -> 0 | AR13: =AQ13 -> 0 | AS13: =IF(ISNA(SUMIFS(INDEX(Inputs!$B$2:$AZ$190,,MATCH(SUBSTITUTE(AS$3,"Q","T"),Inputs!$B$2:$AZ$2,0)),Inputs!$B$2:$B$190,$B13)*Inputs!$D$1),"",SUMIFS(INDEX(Inputs!$B$2:$AZ$190,,MATCH(SUBSTITUTE(AS$3,"Q","T"),Inputs!$B$2:$AZ$2,0)),Inputs!$B$2:$B$190,$B13)*Inputs!$D$1) -> 0 | AT13: =IF(ISNA(SUMIFS(INDEX(Inputs!$B$2:$AZ$190,,MATCH(SUBSTITUTE(AT$3,"Q","T"),Inputs!$B$2:$AZ$2,0)),Inputs!$B$2:$B$190,$B13)*Inputs!$D$1),"",SUMIFS(INDEX(Inputs!$B$2:$AZ$190,,MATCH(SUBSTITUTE(AT$3,"Q","T"),Inputs!$B$2:$AZ$2,0)),Inputs!$B$2:$B$190,$B13)*Inputs!$D$1) -> 0 | AU13: =IF(ISNA(SUMIFS(INDEX(Inputs!$B$2:$AZ$190,,MATCH(SUBSTITUTE(AU$3,"Q","T"),Inputs!$B$2:$AZ$2,0)),Inputs!$B$2:$B$190,$B13)*Inputs!$D$1),"",SUMIFS(INDEX(Inputs!$B$2:$AZ$190,,MATCH(SUBSTITUTE(AU$3,"Q","T"),Inputs!$B$2:$AZ$2,0)),Inputs!$B$2:$B$190,$B13)*Inputs!$D$1) -> 0 | AV13: =IF(ISNA(SUMIFS(INDEX(Inputs!$B$2:$AZ$190,,MATCH(SUBSTITUTE(AV$3,"Q","T"),Inputs!$B$2:$AZ$2,0)),Inputs!$B$2:$B$190,$B13)*Inputs!$D$1),"",SUMIFS(INDEX(Inputs!$B$2:$AZ$190,,MATCH(SUBSTITUTE(AV$3,"Q","T"),Inputs!$B$2:$AZ$2,0)),Inputs!$B$2:$B$190,$B13)*Inputs!$D$1) -> 0 | AW13: =AV13 -> 0 | AX13: =IF(ISNA(SUMIFS(INDEX(Inputs!$B$2:$AZ$190,,MATCH(SUBSTITUTE(AX$3,"Q","T"),Inputs!$B$2:$AZ$2,0)),Inputs!$B$2:$B$190,$B13)*Inputs!$D$1),"",SUMIFS(INDEX(Inputs!$B$2:$AZ$190,,MATCH(SUBSTITUTE(AX$3,"Q","T"),Inputs!$B$2:$AZ$2,0)),Inputs!$B$2:$B$190,$B13)*Inputs!$D$1) -> 0 | AY13: =IF(ISNA(SUMIFS(INDEX(Inputs!$B$2:$AZ$190,,MATCH(SUBSTITUTE(AY$3,"Q","T"),Inputs!$B$2:$AZ$2,0)),Inputs!$B$2:$B$190,$B13)*Inputs!$D$1),"",SUMIFS(INDEX(Inputs!$B$2:$AZ$190,,MATCH(SUBSTITUTE(AY$3,"Q","T"),Inputs!$B$2:$AZ$2,0)),Inputs!$B$2:$B$190,$B13)*Inputs!$D$1) -> 0 | AZ13: =IF(ISNA(SUMIFS(INDEX(Inputs!$B$2:$AZ$190,,MATCH(SUBSTITUTE(AZ$3,"Q","T"),Inputs!$B$2:$AZ$2,0)),Inputs!$B$2:$B$190,$B13)*Inputs!$D$1),"",SUMIFS(INDEX(Inputs!$B$2:$AZ$190,,MATCH(SUBSTITUTE(AZ$3,"Q","T"),Inputs!$B$2:$AZ$2,0)),Inputs!$B$2:$B$190,$B13)*Inputs!$D$1) -> 0 | BA13: =IF(ISNA(SUMIFS(INDEX(Inputs!$B$2:$AZ$190,,MATCH(SUBSTITUTE(BA$3,"Q","T"),Inputs!$B$2:$AZ$2,0)),Inputs!$B$2:$B$190,$B13)*Inputs!$D$1),"",SUMIFS(INDEX(Inputs!$B$2:$AZ$190,,MATCH(SUBSTITUTE(BA$3,"Q","T"),Inputs!$B$2:$AZ$2,0)),Inputs!$B$2:$B$190,$B13)*Inputs!$D$1) -> 0 | BB13: =BA13 -> 0 | BC13: =IF(ISNA(SUMIFS(INDEX(Inputs!$B$2:$AZ$190,,MATCH(SUBSTITUTE(BC$3,"Q","T"),Inputs!$B$2:$AZ$2,0)),Inputs!$B$2:$B$190,$B13)*Inputs!$D$1),"",SUMIFS(INDEX(Inputs!$B$2:$AZ$190,,MATCH(SUBSTITUTE(BC$3,"Q","T"),Inputs!$B$2:$AZ$2,0)),Inputs!$B$2:$B$190,$B13)*Inputs!$D$1) -> 0 | BD13: =IF(ISNA(SUMIFS(INDEX(Inputs!$B$2:$AZ$190,,MATCH(SUBSTITUTE(BD$3,"Q","T"),Inputs!$B$2:$AZ$2,0)),Inputs!$B$2:$B$190,$B13)*Inputs!$D$1),"",SUMIFS(INDEX(Inputs!$B$2:$AZ$190,,MATCH(SUBSTITUTE(BD$3,"Q","T"),Inputs!$B$2:$AZ$2,0)),Inputs!$B$2:$B$190,$B13)*Inputs!$D$1) -> 0 | BE13: =IF(ISNA(SUMIFS(INDEX(Inputs!$B$2:$AZ$190,,MATCH(SUBSTITUTE(BE$3,"Q","T"),Inputs!$B$2:$AZ$2,0)),Inputs!$B$2:$B$190,$B13)*Inputs!$D$1),"",SUMIFS(INDEX(Inputs!$B$2:$AZ$190,,MATCH(SUBSTITUTE(BE$3,"Q","T"),Inputs!$B$2:$AZ$2,0)),Inputs!$B$2:$B$190,$B13)*Inputs!$D$1) -> 0 | BF13: =IF(ISNA(SUMIFS(INDEX(Inputs!$B$2:$AZ$190,,MATCH(SUBSTITUTE(BF$3,"Q","T"),Inputs!$B$2:$AZ$2,0)),Inputs!$B$2:$B$190,$B13)*Inputs!$D$1),"",SUMIFS(INDEX(Inputs!$B$2:$AZ$190,,MATCH(SUBSTITUTE(BF$3,"Q","T"),Inputs!$B$2:$AZ$2,0)),Inputs!$B$2:$B$190,$B13)*Inputs!$D$1) -> 0 | BG13: =BF13 -> 0
