Workbook
Name beta_observed: Valuation!$D$93
Name beta_observed_unlevered: #REF!
Name beta_unlev_comps: #REF!
Name cirkbreak: #REF!
Name costdebtfirm: #REF!
Name costequity: #REF!
Name Debt: #REF!
Name debt_weight: #REF!
Name last_close: Valuation!$G$7
Name Market_Equity: #REF!
Name midyear: #REF!
Name Net_Debt: #REF!
Name range: #REF!
Name Stub_year_fraction: #REF!
Name ticker: Valuation!$D$7
Name Useful_Life_of_Depreciable_PP_E: "PPElife"
Name beta_observed: #REF!
Name ticker: #REF!
Name costdebtfirm: Valuation!$D$86
Name costequity: Valuation!$D$94
Name debt: Valuation!$G$88
Name debt_weight: Valuation!$J$88
Name g: Valuation!$D$63
Name market_equity: Valuation!$G$89
Name noplat_t1: Valuation!$D$65
Name relevered_beta: Valuation!$M$102
Name risk_free_rate: Valuation!$D$91
Name risk_premium: Valuation!$D$92
Name ronic: Valuation!$D$64
Name stub_year_fraction: Valuation!$D$11
Name totalcap: Valuation!$G$90
Name wacc: Valuation!$D$12
Name scenario: Valuation!$E$8

Sheet Inputs
A1: Fator p/ milhões: | B1: 0.001 | D1: Grupo Mateus (GMAT3) - fonte: Dados Historicos 2T26 do RI (abas Balanco Patrimonial, DRE, Fluxo de Caixa, N de lojas, Evolucao da Area de Vendas) + releases trimestrais 3T20-2T26 (receita bruta por segmento, receita liquida por regiao, SSS, lucro dos nao controladores). Moeda: BRL. Brutos em R$ mil. Consolidado.
J2: Trimestre na fonte | K2: 1T20 | L2: 2T20 | M2: 3T20 | N2: 4T20 | O2: 1T21 | P2: 2T21 | Q2: 3T21 | R2: 4T21 | S2: 1T22 | T2: 2T22 | U2: 3T22 | V2: 4T22 | W2: 1T23 | X2: 2T23 | Y2: 3T23 | Z2: 4T23 | AA2: 1T24 | AB2: 2T24 | AC2: 3T24 | AD2: 4T24 | AE2: 1T25 | AF2: 2T25 | AG2: 3T25 | AH2: 4T25 | AI2: 1T26 | AJ2: 2T26
A4: COD1 | B4: SINAL1 | C4: COD2 | D4: SINAL2 | E4: COD3 | F4: SINAL3 | G4: UNID | H4: Conta (PT) / origem | I4: Account (EN) | J4: ORIGEM | K4: 1Q20 | L4: 2Q20 | M4: 3Q20 | N4: 4Q20 | O4: 1Q21 | P4: 2Q21 | Q4: 3Q21 | R4: 4Q21 | S4: 1Q22 | T4: 2Q22 | U4: 3Q22 | V4: 4Q22 | W4: 1Q23 | X4: 2Q23 | Y4: 3Q23 | Z4: 4Q23 | AA4: 1Q24 | AB4: 2Q24 | AC4: 3Q24 | AD4: 4Q24 | AE4: 1Q25 | AF4: 2Q25 | AG4: 3Q25 | AH4: 4Q25 | AI4: 1Q26 | AJ4: 2Q26
H5: DRE - TRIMESTRE ISOLADO (aba DRE; R$ mil). 3T24, 4T24, 1T25 e 2T25: colunas "Reapresentacao" (CPC 23, nota 3.1 do ITR 2T26). Soma dos trimestres = ano (conferido)
A6: 1 | B6: 1 | G6: moeda | H6: Receita liquida de vendas (DRE l.6) | J6: fonte | K6: 2409284.4 | L6: 2889003.3 | M6: 3463454.2 | N6: 3635295.9 | O6: 3362273.1 | P6: 3724341.7 | Q6: 4349125 | R6: 4441117.2 | S6: 4578779.5 | T6: 5201989 | U6: 5923131 | V6: 6064577 | W6: 5867879.7 | X6: 6429472 | Y6: 6934929 | Z6: 7541305.3 | AA6: 7382470.6 | AB6: 7638924.4 | AC6: 8337057 | AD6: 8726977 | AE6: 8331305 | AF6: 8779636.4 | AG6: 10763538 | AH6: 10549923 | AI6: 9402270 | AJ6: 9852461
A7: 2 | B7: 1 | G7: moeda | H7: Custo dos servicos prestados e mercadorias vendidas (DRE l.7) | J7: fonte | K7: -1805748 | L7: -2195072 | M7: -2625787 | N7: -2781019.9 | O7: -2560194.1 | P7: -2861692.3 | Q7: -3311219 | R7: -3441309.6 | S7: -3553067.3 | T7: -4019431 | U7: -4568982 | V7: -4752905 | W7: -4574505.7 | X7: -4985038 | Y7: -5374203 | Z7: -5849003.3 | AA7: -5732716 | AB7: -5926460 | AC7: -6479360 | AD7: -6821183 | AE7: -6478662 | AF7: -6685998 | AG7: -8470764 | AH7: -8175217.4 | AI7: -7251758 | AJ7: -7541266
A8: 3 | B8: 1 | G8: moeda | H8: Despesas comerciais, administrativas e gerais (DRE l.13; inclui a D&A, devolvida abaixo) | J8: fonte | K8: -463885.89 | L8: -454361.11 | M8: -560733 | N8: -637644 | O8: -610097.06 | P8: -645362.94 | Q8: -723325 | R8: -748223 | S8: -807035.2 | T8: -858244.8 | U8: -953504 | V8: -992449 | W8: -981450.33 | X8: -1058239 | Y8: -1147111 | Z8: -1203353.6 | AA8: -1244723.6 | AB8: -1236882 | AC8: -1310428 | AD8: -1369239.5 | AE8: -1373306 | AF8: -1428519 | AG8: -1769134 | AH8: -1873881 | AI8: -1798334 | AJ8: -1796066
A9: 3 | B9: 1 | G9: moeda | H9: Outras receitas (despesas) operacionais, liquidas (DRE l.14) | J9: fonte | K9: -143.26486 | L9: -100.73514 | M9: -935 | N9: -1923 | O9: -10481.574 | P9: -2207.6126 | Q9: -54456 | R9: 7879 | S9: 11130.955 | T9: 1745 | U9: -12453 | V9: 102003 | W9: 1067 | X9: 27385 | Y9: 413 | Z9: 53065.045 | AA9: 421 | AB9: -18179 | AC9: 5492 | AD9: 4281 | AE9: 1301 | AF9: -2721 | AG9: 147417 | AH9: -47369.189 | AI9: 32416 | AJ9: -11212
A10: 6 | B10: 1 | G10: moeda | H10: Receitas financeiras (DRE l.20) | J10: fonte | K10: 16478.863 | L10: 18931.137 | M10: 18504 | N10: 29563 | O10: 25690.766 | P10: 31700.554 | Q10: 44510 | R10: 39361 | S10: 44146.335 | T10: 36200.665 | U10: 47128 | V10: 56191 | W10: 63202 | X10: 62773 | Y10: 63855 | Z10: 52167 | AA10: 54595.66 | AB10: 71540.34 | AC10: 58966 | AD10: 82206 | AE10: 69356 | AF10: 58754 | AG10: 87088 | AH10: 96761 | AI10: 87895 | AJ10: 90775
A11: 5 | B11: 1 | G11: moeda | H11: Despesas financeiras (DRE l.21; inclui MDR de cartao e juros de arrendamento IFRS 16) | J11: fonte | K11: -54162.167 | L11: -63048.833 | M11: -57591 | N11: -53821 | O11: -50470 | P11: -56216 | Q11: -91211 | R11: -71983 | S11: -73218 | T11: -94761.779 | U11: -137924 | V11: -154732.22 | W11: -135960 | X11: -166879 | Y11: -163903 | Z11: -180578 | AA11: -187301.66 | AB11: -198208.74 | AC11: -208790 | AD11: -244955.6 | AE11: -250609 | AF11: -267809 | AG11: -305637 | AH11: -403524 | AI11: -310031 | AJ11: -338073
A12: 7 | B12: 1 | G12: moeda | H12: IR e CS - corrente (DRE l.26) | J12: fonte | K12: 0 | L12: 0 | M12: -6948 | N12: 5004 | O12: 0 | P12: 0 | Q12: 0 | R12: -18759 | S12: -1524.4414 | T12: -3374 | U12: -6525 | V12: -12096 | W12: -541 | X12: -16241 | Y12: -383 | Z12: -25485 | AA12: -96230.245 | AB12: -138067.3 | AC12: -124370 | AD12: -11818 | AE12: -97399 | AF12: -10341 | AG12: 300127 | AH12: 106038 | AI12: -13946 | AJ12: -14247
A13: 7 | B13: 1 | G13: moeda | H13: IR e CS - diferido (DRE l.27) | J13: fonte | K13: 0 | L13: 0 | M13: 5704 | N13: -2031 | O13: 0 | P13: 0 | Q13: 0 | R13: 0 | S13: 0 | T13: 0 | U13: 0 | V13: 0 | W13: 0 | X13: 0 | Y13: 0 | Z13: 0 | AA13: 63862 | AB13: 134676.56 | AC13: 76694 | AD13: -43036 | AE13: 74334 | AF13: -47225 | AG13: 93938 | AH13: 90221 | AI13: 42410 | AJ13: -426
G14: moeda | H14: Lucro liquido combinado do periodo (DRE l.30; inclui nao controladores) - memoria | J14: memoria | K14: 101823.97 | L14: 195351.8 | M14: 235668.23 | N14: 193424 | O14: 156721.15 | P14: 190563.35 | Q14: 213424 | R14: 208082.63 | S14: 199211.84 | T14: 264123.08 | U14: 290871 | V14: 310588.78 | W14: 239691.67 | X14: 293233 | Y14: 313597 | Z14: 388117.45 | AA14: 240377.78 | AB14: 327344.21 | AC14: 355261 | AD14: 323231.9 | AE14: 276320 | AF14: 395777 | AG14: 846573 | AH14: 342951 | AI14: 190922 | AJ14: 241946
A15: 9 | B15: -1 | G15: moeda | H15: Lucro liquido atribuido aos nao controladores (releases; so aberto a partir do 3T25). COD 9 com sinal -1 (entra negativo quando positivo) [0 em 22 per.: conta vazia/"-" na fonte] | J15: release | K15: 0 | L15: 0 | M15: 0 | N15: 0 | O15: 0 | P15: 0 | Q15: 0 | R15: 0 | S15: 0 | T15: 0 | U15: 0 | V15: 0 | W15: 0 | X15: 0 | Y15: 0 | Z15: 0 | AA15: 0 | AB15: 0 | AC15: 0 | AD15: 0 | AE15: 0 | AF15: 0 | AG15: -3973 | AH15: 18687 | AI15: -21959 | AJ15: 5141
G16: moeda | H16: Depreciacao (DRE l.32) - memoria | J16: memoria | K16: 22718 | L16: 24931 | M16: 33748 | N16: 27495 | O16: 37608 | P16: 44295 | Q16: 51000 | R16: 48048 | S16: 48188 | T16: 57144 | U16: 55727 | V16: 58720 | W16: 63128 | X16: 61086 | Y16: 59994 | Z16: 24736 | AA16: 61651 | AB16: 49812 | AC16: 54035 | AD16: 45106 | AE16: 58799 | AF16: 60696 | AG16: 92906 | AH16: 99632 | AI16: 90048 | AJ16: 101359
G17: moeda | H17: Depreciacao de arrendamento (DRE l.33) - memoria | J17: memoria | K17: 16845 | L17: 28857 | M17: 9179 | N17: 16191 | O17: 20121 | P17: 19438 | Q17: 20918 | R17: 19017 | S17: 24007 | T17: 26586 | U17: 28493 | V17: 30302 | W17: 34873 | X17: 31059 | Y17: 38534 | Z17: 39982 | AA17: 42920 | AB17: 35497 | AC17: 41459 | AD17: 46266 | AE17: 46495 | AF17: 52397 | AG17: 69259 | AH17: 59412 | AI17: 68402 | AJ17: 76331
G18: moeda | H18: Despesa financeira de arrendamento (DRE l.34) - memoria (dentro das despesas financeiras) | J18: memoria | K18: 6731 | L18: 10670 | M18: 6046 | N18: 9356 | O18: 9862 | P18: 11161 | Q18: 20776 | R18: 19908 | S18: 15643 | T18: 25884 | U18: 31271 | V18: 32003 | W18: 33876 | X18: 38493.442 | Y18: 45535.558 | Z18: 51083 | AA18: 52406 | AB18: 52037 | AC18: 57862 | AD18: 37900 | AE18: 69390 | AF18: 81621 | AG18: 101981 | AH18: 103425 | AI18: 101261 | AJ18: 107983
G19: moeda | H19: EBITDA (DRE l.36, como divulgado, pos IFRS 16) - memoria | J19: memoria | K19: 179070.27 | L19: 293257.5 | M19: 318926.23 | N19: 258395 | O19: 239229.39 | P19: 278811.79 | Q19: 332043 | R19: 326528.63 | S19: 302002.95 | T19: 409788.2 | U19: 472412 | V19: 510248 | W19: 410991.67 | X19: 505725 | Y19: 512556 | Z19: 606731.45 | AA19: 510023.03 | AB19: 542712.35 | AC19: 648255 | AD19: 632207.5 | AE19: 585932 | AF19: 775491.43 | AG19: 833222 | AH19: 612499 | AI19: 543044 | AJ19: 681607
G20: moeda | H20: EBIT - lucro operacional antes do resultado financeiro (DRE l.17) - memoria | J20: memoria | K20: 139507.27 | L20: 239469.5 | M20: 275999.23 | N20: 214709 | O20: 181500.39 | P20: 215078.79 | Q20: 260125 | R20: 259463.63 | S20: 229807.95 | T20: 326058.2 | U20: 388192 | V20: 421226 | W20: 312990.67 | X20: 413580 | Y20: 414028 | Z20: 542013.45 | AA20: 405452.03 | AB20: 457403.35 | AC20: 552761 | AD20: 540835.5 | AE20: 480638 | AF20: 662398.43 | AG20: 671057 | AH20: 453455 | AI20: 384594 | AJ20: 503917
H21: DFC - ACUMULADO NO ANO (aba Fluxo de Caixa; R$ mil). Comeca no 1T21; 2020 so tem a coluna anual
G22: moeda | H22: JCP pagos + distribuicao de lucros (DFC l.56 + l.57, acum.). 2020: 0 (coluna anual 2020 da DFC = 0) | J22: memoria | K22: 0 | L22: 0 | M22: 0 | N22: 0 | O22: 0 | P22: 0 | Q22: 0 | R22: 0 | S22: 0 | T22: 0 | U22: 0 | V22: 0 | W22: 0 | X22: 0 | Y22: 0 | Z22: 0 | AA22: 0 | AB22: 0 | AC22: 0 | AD22: -81047 | AE22: 0 | AF22: 0 | AG22: 0 | AH22: -145544 | AI22: 0 | AJ22: 0
G23: moeda | H23: Recompra de acoes (DFC l.60, acum.) - memoria | J23: memoria | O23: 0 | P23: 0 | Q23: 0 | R23: 0 | S23: 0 | T23: 0 | U23: 0 | V23: 0 | W23: 0 | X23: 0 | Y23: -7465 | Z23: -7465 | AA23: 0 | AB23: -10818 | AC23: -10818 | AD23: -10818 | AE23: -16204 | AF23: -16204 | AG23: -33210 | AH23: -33210 | AI23: 0 | AJ23: 0
G24: moeda | H24: Aquisicao de imobilizado + intangivel - capex (DFC l.41 + l.44, acum.) - memoria | J24: memoria | O24: -290590.11 | P24: -555453 | Q24: -803544 | R24: -1435300 | S24: -324135 | T24: -552686 | U24: -726033 | V24: -869159 | W24: -234333 | X24: -503970 | Y24: -880975 | Z24: -1212623 | AA24: -345586 | AB24: -659585 | AC24: -904087 | AD24: -1268652 | AE24: -355847 | AF24: -611441 | AG24: -924353 | AH24: -1145137 | AI24: -219609 | AJ24: -162223
H25: DERIVADAS (formula nesta aba)
A26: 4 | B26: -1 | C26: 3 | D26: 1 | G26: moeda | H26: D&A = depreciacao + depreciacao de arrendamento (DRE l.32 + l.33 = EBITDA - EBIT). COD1=4 lanca; COD2=3 devolve ao SG&A | J26: derivada | K26: =K16+K17 -> 39563 | L26: =L16+L17 -> 53788 | M26: =M16+M17 -> 42927 | N26: =N16+N17 -> 43686 | O26: =O16+O17 -> 57729 | P26: =P16+P17 -> 63733 | Q26: =Q16+Q17 -> 71918 | R26: =R16+R17 -> 67065 | ... AJ26: =AJ16+AJ17 -> 177690
A27: 10 | B27: 1 | G27: moeda | H27: JCP e dividendos pagos (DFC, trimestralizado; ja negativo na fonte) | J27: derivada | K27: =N(K22) -> 0 | L27: =N(L22)-N(K22) -> 0 | M27: =N(M22)-N(L22) -> 0 | N27: =N(N22)-N(M22) -> 0 | O27: =N(O22) -> 0 | P27: =N(P22)-N(O22) -> 0 | Q27: =N(Q22)-N(P22) -> 0 | R27: =N(R22)-N(Q22) -> 0 | S27: =N(S22) -> 0 | T27: =N(T22)-N(S22) -> 0 | U27: =N(U22)-N(T22) -> 0 | V27: =N(V22)-N(U22) -> 0 | W27: =N(W22) -> 0 | X27: =N(X22)-N(W22) -> 0 | Y27: =N(Y22)-N(X22) -> 0 | Z27: =N(Z22)-N(Y22) -> 0 | AA27: =N(AA22) -> 0 | AB27: =N(AB22)-N(AA22) -> 0 | AC27: =N(AC22)-N(AB22) -> 0 | AD27: =N(AD22)-N(AC22) -> -81047 | AE27: =N(AE22) -> 0 | AF27: =N(AF22)-N(AE22) -> 0 | AG27: =N(AG22)-N(AF22) -> 0 | AH27: =N(AH22)-N(AG22) -> -145544 | AI27: =N(AI22) -> 0 | AJ27: =N(AJ22)-N(AI22) -> 0
G28: moeda | H28: Capex (DFC, trimestralizado; 2020 sem DFC trimestral) - memoria | J28: derivada | O28: =N(O24) -> -290590.11 | P28: =N(P24)-N(O24) -> -264862.89 | Q28: =N(Q24)-N(P24) -> -248091 | R28: =N(R24)-N(Q24) -> -631756 | S28: =N(S24) -> -324135 | T28: =N(T24)-N(S24) -> -228551 | U28: =N(U24)-N(T24) -> -173347 | V28: =N(V24)-N(U24) -> -143126 | W28: =N(W24) -> -234333 | X28: =N(X24)-N(W24) -> -269637 | Y28: =N(Y24)-N(X24) -> -377005 | Z28: =N(Z24)-N(Y24) -> -331648 | AA28: =N(AA24) -> -345586 | AB28: =N(AB24)-N(AA24) -> -313999 | AC28: =N(AC24)-N(AB24) -> -244502 | AD28: =N(AD24)-N(AC24) -> -364565 | AE28: =N(AE24) -> -355847 | AF28: =N(AF24)-N(AE24) -> -255594 | AG28: =N(AG24)-N(AF24) -> -312912 | AH28: =N(AH24)-N(AG24) -> -220784 | AI28: =N(AI24) -> -219609 | AJ28: =N(AJ24)-N(AI24) -> 57386
A29: 44 | B29: 1 | G29: moeda | H29: Lucro liquido atribuido ao Grupo Mateus = combinado - nao controladores. COD 44 alimenta o check IS do Model (linha 4) | J29: derivada | K29: =K14-N(K15) -> 101823.97 | L29: =L14-N(L15) -> 195351.8 | M29: =M14-N(M15) -> 235668.23 | N29: =N14-N(N15) -> 193424 | O29: =O14-N(O15) -> 156721.15 | P29: =P14-N(P15) -> 190563.35 | Q29: =Q14-N(Q15) -> 213424 | R29: =R14-N(R15) -> 208082.63 | ... AJ29: =AJ14-N(AJ15) -> 236805
H30: BALANCO (aba Balanco Patrimonial; R$ mil, fim de trimestre). Sem coluna Mar.20 na fonte: 1Q20 fica vazio (#N/A no Model). Dez.24, Mar.25 e Jun.25 reapresentados
A31: 11 | B31: 1 | G31: moeda | H31: Caixa e equivalentes de caixa (BP l.7) | J31: fonte | L31: 944126 | M31: 811985 | N31: 2112385 | O31: 1796587.1 | P31: 1687023 | Q31: 959079 | R31: 877255 | S31: 618570 | T31: 889893 | U31: 694792 | V31: 1795647 | W31: 1671461 | X31: 1355789 | Y31: 1116813 | Z31: 1289138 | AA31: 1341031 | AB31: 1240114 | AC31: 698687 | AD31: 1664167 | AE31: 1520551 | AF31: 1027777 | AG31: 1182893 | AH31: 1801712 | AI31: 1984238 | AJ31: 1631590
A32: 12 | B32: 1 | G32: moeda | H32: Contas a receber (BP l.8) | J32: fonte | L32: 964031 | M32: 995203.23 | N32: 1305457.6 | O32: 1277833.9 | P32: 1462541.6 | Q32: 1544314 | R32: 1816264 | S32: 1872825 | T32: 2080076.4 | U32: 2377348.3 | V32: 2548256.3 | W32: 2385043.3 | X32: 2582667 | Y32: 2868599 | Z32: 3457628 | AA32: 3085517 | AB32: 3181456.7 | AC32: 3509695 | AD32: 3399130 | AE32: 3650849 | AF32: 3621480 | AG32: 3964078 | AH32: 4080890 | AI32: 4013107 | AJ32: 3959317
A33: 13 | B33: 1 | G33: moeda | H33: Estoques (BP l.9) | J33: fonte | L33: 1587934 | M33: 2092272.7 | N33: 2617533 | O33: 2637474.4 | P33: 2826493 | Q33: 3492306 | R33: 3498630 | S33: 3803451 | T33: 3994994 | U33: 4666193 | V33: 3985375 | W33: 4436302 | X33: 4693948 | Y33: 4939475 | Z33: 5087655 | AA33: 4957342 | AB33: 5294057 | AC33: 5963407 | AD33: 4939518 | AE33: 5242901 | AF33: 5020008 | AG33: 5730287 | AH33: 5170062 | AI33: 5221233 | AJ33: 5736020
A34: 16 | B34: 1 | G34: moeda | H34: Tributos a recuperar (BP l.10) | J34: fonte | L34: 26293 | M34: 89935.836 | N34: 21882 | O34: 96079.427 | P34: 87231.102 | Q34: 92043 | R34: 67338 | S34: 105261 | T34: 88476 | U34: 106728 | V34: 379672 | W34: 388410 | X34: 326169 | Y34: 249090 | Z34: 419631 | AA34: 459811 | AB34: 527238 | AC34: 527556 | AD34: 605142 | AE34: 684671 | AF34: 683545 | AG34: 1122231 | AH34: 1312606 | AI34: 1307822 | AJ34: 1294163
A35: 16 | B35: 1 | G35: moeda | H35: Outros ativos CP (BP l.11) | J35: fonte | L35: 11679 | M35: 8636.8904 | N35: 8757.6049 | O35: 12175.463 | P35: 46294 | Q35: 118729 | R35: 12670 | S35: 29611 | T35: 30402 | U35: 41710 | V35: 91317 | W35: 140407 | X35: 118904 | Y35: 132658 | Z35: 116483 | AA35: 160371 | AB35: 186466 | AC35: 233914 | AD35: 253517 | AE35: 312504 | AF35: 363516 | AG35: 388556 | AH35: 388275 | AI35: 426112 | AJ35: 454790
A36: 11 | B36: 1 | G36: moeda | H36: Aplicações financeiras (BP l.15) | J36: fonte | L36: 14603 | M36: 4931.0724 | N36: 14965.107 | O36: 1359.6197 | P36: 1357.1943 | Q36: 1338 | R36: 3071 | S36: 2370 | T36: 1287 | U36: 1815 | V36: 1508 | W36: 1204 | X36: 1681 | Y36: 824 | Z36: 882 | AA36: 264 | AB36: 331 | AC36: 112 | AD36: 46 | AE36: 46 | AF36: 46 | AG36: 46 | AH36: 0 | AI36: 0 | AJ36: 0
A37: 22 | B37: 1 | G37: moeda | H37: Partes relacionadas (BP l.16) | J37: fonte | L37: 48406 | M37: 46416.913 | N37: 22165.795 | O37: 8402.2568 | P37: 19673.121 | Q37: 6767 | R37: 7321 | S37: 7285 | T37: 8607 | U37: 5824.6817 | V37: 7237.6335 | W37: 6438.9209 | X37: 6568 | Y37: 5616 | Z37: 103.81072 | AA37: 47 | AB37: 18 | AC37: 32 | AD37: 114 | AE37: 47 | AF37: 71.10598 | AG37: 95 | AH37: 39 | AI37: 30 | AJ37: 0
A38: 22 | B38: 1 | G38: moeda | H38: Tributos a recuperar (BP l.17) | J38: fonte | L38: 89579 | M38: 39974.063 | N38: 140240 | O38: 78592.85 | P38: 95340.877 | Q38: 112499 | R38: 135289 | S38: 117179 | T38: 139337 | U38: 155282 | V38: 165856 | W38: 177915 | X38: 300858 | Y38: 320271 | Z38: 239491 | AA38: 245638 | AB38: 262028 | AC38: 278177 | AD38: 227784 | AE38: 244789 | AF38: 486035 | AG38: 600278 | AH38: 548224 | AI38: 577770 | AJ38: 674844
A39: 14 | B39: 1 | G39: moeda | H39: Imposto de renda e contribuição social diferidos (BP l.18) | J39: fonte | L39: 0 | M39: 0 | N39: 0 | O39: 0 | P39: 0 | Q39: 0 | R39: 0 | S39: 0 | T39: 0 | U39: 0 | V39: 0 | W39: 0 | X39: 0 | Y39: 0 | Z39: 0 | AA39: 42100 | AB39: 139576 | AC39: 203290 | AD39: 503543 | AE39: 599643 | AF39: 306893 | AG39: 802623 | AH39: 866468 | AI39: 908878 | AJ39: 899443
A40: 22 | B40: 1 | G40: moeda | H40: Outros ativos (BP l.19) | J40: fonte | L40: 479 | M40: 912.77114 | N40: 1618.6523 | O40: 1528.2724 | P40: 1012.1359 | Q40: 21663 | R40: 28868 | S40: 28421 | T40: 33049 | U40: 39870 | V40: 42746 | W40: 48895 | X40: 99377 | Y40: 87216 | Z40: 84444 | AA40: 95970 | AB40: 102885 | AC40: 106667 | AD40: 81824 | AE40: 65887 | AF40: 201382 | AG40: 65589 | AH40: 110796 | AI40: 142466 | AJ40: 161601
A41: 22 | B41: 1 | G41: moeda | H41: Depósitos judiciais (BP l.20) | J41: fonte | L41: 13300 | M41: 14947.113 | N41: 14757.345 | O41: 15148.746 | P41: 15320.57 | Q41: 15900 | R41: 16340 | S41: 16480 | T41: 17840 | U41: 19502 | V41: 20808 | W41: 22319 | X41: 24494 | Y41: 26300 | Z41: 27436 | AA41: 30604 | AB41: 28768 | AC41: 29568 | AD41: 30637 | AE41: 29720 | AF41: 24282 | AG41: 25800 | AH41: 19357 | AI41: 18802 | AJ41: 18219
A42: 19 | B42: 1 | G42: moeda | H42: Ativos de direito de uso (BP l.21) | J42: fonte | L42: 464426 | M42: 539476.82 | N42: 597051.36 | O42: 662079.67 | P42: 703265.99 | Q42: 830842 | R42: 907504 | S42: 998229 | T42: 1194760 | U42: 1257424 | V42: 1260815 | W42: 1330053 | X42: 1564699 | Y42: 1774395 | Z42: 1850811 | AA42: 2021405 | AB42: 1866203 | AC42: 1884077 | AD42: 2036014 | AE42: 2339617 | AF42: 2641269 | AG42: 3539580 | AH42: 3654264 | AI42: 3696106 | AJ42: 3867883
... A69: 35 | B69: 1 | G69: moeda | H69: Patrimônio líquido atribuído à participação dos acionistas não controladores (BP l.63) | J69: fonte | L69: 63302.648 | M69: 63553 | N69: 63284 | O69: 64457 | P69: 67415 | Q69: 70928 | R69: 73394 | S69: 75890 | T69: 79272 | U69: 82943 | V69: 86379 | W69: 89272.4 | X69: 93836 | Y69: 98030 | Z69: 101241 | AA69: 103804 | AB69: 108517 | AC69: 121956 | AD69: 76683 | AE69: 79696 | AF69: 85385 | AG69: 1058071 | AH69: 1083859 | AI69: 1061900 | AJ69: 1160623
H70: BALANCO - totais divulgados (memoria)
G71: moeda | H71: Total do ativo (BP l.27) | J71: memoria | L71: 5130344 | M71: 5760519.8 | N71: 8198710.4 | O71: 8181505.3 | P71: 8758601.3 | Q71: 9205963 | R71: 9954991 | S71: 10460070 | T71: 11434974 | U71: 12387779 | V71: 13263938 | W71: 13726170 | X71: 14378139 | Y71: 15056338 | Z71: 16357296 | AA71: 16519334 | AB71: 17131008 | AC71: 17900655 | AD71: 18228167 | AE71: 19342417 | AF71: 19666720 | AG71: 23696093 | AH71: 24352014 | AI71: 24737405 | AJ71: 25153122
G72: moeda | H72: Total do passivo e do patrimônio líquido (BP l.66) | 2T23 e 3T23 dos releases 2T24/3T24 (planilha soma sem as partes relacionadas) | J72: memoria | L72: 5130343.6 | M72: 5760520.2 | N72: 8198711.9 | O72: 8181505.3 | P72: 8758601.6 | Q72: 9205963 | R72: 9954991 | S72: 10460070 | T72: 11434974 | U72: 12387779 | V72: 13263938 | W72: 13726170 | X72: 14378139 | Y72: 15056338 | Z72: 16357296 | AA72: 16519334 | AB72: 17131008 | AC72: 17900655 | AD72: 18228167 | AE72: 19342417 | AF72: 19666720 | AG72: 23696093 | AH72: 24352014 | AI72: 24737405 | AJ72: 25153122
G73: moeda | H73: Total do patrimônio líquido (BP l.64) | J73: memoria | L73: 2316158.6 | M73: 2551805.1 | N73: 5707540.5 | O73: 5864260.5 | P73: 6054825.2 | Q73: 6268249 | R73: 6476581 | S73: 6675795.2 | T73: 6940347 | U73: 7231270 | V73: 7541985 | W73: 7781596.4 | X73: 8076004 | Y73: 8385411 | Z73: 8773513 | AA73: 8917604 | AB73: 9100834 | AC73: 9396716 | AD73: 9232293 | AE73: 9356337 | AF73: 9612422 | AG73: 11251398 | AH73: 11467816 | AI73: 11997572 | AJ73: 12345241
H74: CHECKS (devem ser 0)
G75: moeda | H75: CHECK: receita + custo + despesas op. + resultado financeiro + IR - lucro liquido combinado | J75: derivada | K75: =ROUND(K6+K7+K8+K9+K10+K11+K12+K13-K14,0) -> 0 | L75: =ROUND(L6+L7+L8+L9+L10+L11+L12+L13-L14,0) -> 0 | M75: =ROUND(M6+M7+M8+M9+M10+M11+M12+M13-M14,0) -> 0 | N75: =ROUND(N6+N7+N8+N9+N10+N11+N12+N13-N14,0) -> 0 | O75: =ROUND(O6+O7+O8+O9+O10+O11+O12+O13-O14,0) -> 0 | P75: =ROUND(P6+P7+P8+P9+P10+P11+P12+P13-P14,0) -> 0 | Q75: =ROUND(Q6+Q7+Q8+Q9+Q10+Q11+Q12+Q13-Q14,0) -> 0 | R75: =ROUND(R6+R7+R8+R9+R10+R11+R12+R13-R14,0) -> 0 | ... AJ75: =ROUND(AJ6+AJ7+AJ8+AJ9+AJ10+AJ11+AJ12+AJ13-AJ14,0) -> 0
G76: moeda | H76: CHECK: D&A (l.32 + l.33) + EBIT - EBITDA divulgado | J76: derivada | K76: =ROUND(K26+K20-K19,0) -> 0 | L76: =ROUND(L26+L20-L19,0) -> 0 | M76: =ROUND(M26+M20-M19,0) -> 0 | N76: =ROUND(N26+N20-N19,0) -> 0 | O76: =ROUND(O26+O20-O19,0) -> 0 | P76: =ROUND(P26+P20-P19,0) -> 0 | Q76: =ROUND(Q26+Q20-Q19,0) -> 0 | R76: =ROUND(R26+R20-R19,0) -> 0 | ... AJ76: =ROUND(AJ26+AJ20-AJ19,0) -> 0
G77: moeda | H77: CHECK: contas de ativo - ativo total | J77: derivada | K77: =ROUND(K31+K32+K33+K34+K35+K36+K37+K38+K39+K40+K41+K42+K43+K44+K45-K71,0) -> 0 | L77: =ROUND(L31+L32+L33+L34+L35+L36+L37+L38+L39+L40+L41+L42+L43+L44+L45-L71,0) -> 0 | M77: =ROUND(M31+M32+M33+M34+M35+M36+M37+M38+M39+M40+M41+M42+M43+M44+M45-M71,0) -> 0 | N77: =ROUND(N31+N32+N33+N34+N35+N36+N37+N38+N39+N40+N41+N42+N43+N44+N45-N71,0) -> 0 | O77: =ROUND(O31+O32+O33+O34+O35+O36+O37+O38+O39+O40+O41+O42+O43+O44+O45-O71,0) -> 0 | P77: =ROUND(P31+P32+P33+P34+P35+P36+P37+P38+P39+P40+P41+P42+P43+P44+P45-P71,0) -> 0 | Q77: =ROUND(Q31+Q32+Q33+Q34+Q35+Q36+Q37+Q38+Q39+Q40+Q41+Q42+Q43+Q44+Q45-Q71,0) -> 0 | R77: =ROUND(R31+R32+R33+R34+R35+R36+R37+R38+R39+R40+R41+R42+R43+R44+R45-R71,0) -> 0 | ... AJ77: =ROUND(AJ31+AJ32+AJ33+AJ34+AJ35+AJ36+AJ37+AJ38+AJ39+AJ40+AJ41+AJ42+AJ43+AJ44+AJ45-AJ71,0) -> 0
G78: moeda | H78: CHECK: passivo + PL - passivo total | J78: derivada | K78: =ROUND(K46+K47+K48+K49+K50+K51+K52+K53+K54+K55+K56+K57+K58+K59+K60+K61+K62+K63+K64+K65+K66+K67+K68+K69-K72,0) -> 0 | L78: =ROUND(L46+L47+L48+L49+L50+L51+L52+L53+L54+L55+L56+L57+L58+L59+L60+L61+L62+L63+L64+L65+L66+L67+L68+L69-L72,0) -> 0 | M78: =ROUND(M46+M47+M48+M49+M50+M51+M52+M53+M54+M55+M56+M57+M58+M59+M60+M61+M62+M63+M64+M65+M66+M67+M68+M69-M72,0) -> 0 | N78: =ROUND(N46+N47+N48+N49+N50+N51+N52+N53+N54+N55+N56+N57+N58+N59+N60+N61+N62+N63+N64+N65+N66+N67+N68+N69-N72,0) -> 0 | O78: =ROUND(O46+O47+O48+O49+O50+O51+O52+O53+O54+O55+O56+O57+O58+O59+O60+O61+O62+O63+O64+O65+O66+O67+O68+O69-O72,0) -> 0 | P78: =ROUND(P46+P47+P48+P49+P50+P51+P52+P53+P54+P55+P56+P57+P58+P59+P60+P61+P62+P63+P64+P65+P66+P67+P68+P69-P72,0) -> 0 | Q78: =ROUND(Q46+Q47+Q48+Q49+Q50+Q51+Q52+Q53+Q54+Q55+Q56+Q57+Q58+Q59+Q60+Q61+Q62+Q63+Q64+Q65+Q66+Q67+Q68+Q69-Q72,0) -> 0 | R78: =ROUND(R46+R47+R48+R49+R50+R51+R52+R53+R54+R55+R56+R57+R58+R59+R60+R61+R62+R63+R64+R65+R66+R67+R68+R69-R72,0) -> 0 | ... AJ78: =ROUND(AJ46+AJ47+AJ48+AJ49+AJ50+AJ51+AJ52+AJ53+AJ54+AJ55+AJ56+AJ57+AJ58+AJ59+AJ60+AJ61+AJ62+AJ63+AJ64+AJ65+AJ66+AJ67+AJ68+AJ69-AJ72,0) -> 0
H79: [vazio] cod 8 Equity in affiliates: sem equivalencia na DRE
H80: [vazio] cod 20 Goodwill: nao aberto (dentro do intangivel, inclui a combinacao com o Novo Atacarejo)
H81: [vazio] cod 28 Revolver: sem linha propria (emprestimos CP no cod 27)
H82: [vazio] cod 32 Convertible debt: inexistente
H83: [vazio] cod 36 Convertible Preferred Stock: inexistente
H84: [vazio] cod 39 ORA: sem linha propria na fonte
H85: [vazio] cod 40 Other equity: sem linha propria
H86: Nota: nao controladores no resultado (cod 9) so a partir do 3T25 (releases); antes disso a DRE do release nao separa e o PL de nao controladores era < R$ 125 mi. NI do Model = lucro atribuido ao Grupo Mateus.
H88: DRIVERS DE RECEITA (codigos 45+; UNID "un" = sem fator: R$ milhoes, lojas, m2 e %). Receita por segmento e por regiao e SSS: releases. Lojas e area: abas N de lojas e Evolucao da Area de Vendas.
A89: 45 | B89: 1 | G89: un | H89: Receita bruta de mercadorias - Atacarejo (Mix Mateus; inclui Novo Atacarejo a partir do 3T25) (R$ milhoes) | J89: release | K89: 1251 | L89: 1552 | M89: 1933 | N89: 2076 | O89: 1827 | P89: 2003 | Q89: 2381 | R89: 2485 | S89: 2514 | T89: 2956 | U89: 3478 | V89: 3584 | W89: 3523 | X89: 3899 | Y89: 4209 | Z89: 4753 | AA89: 4683 | AB89: 4765 | AC89: 5304 | AD89: 5620 | AE89: 5252 | AF89: 5541 | AG89: 7530 | AH89: 7354
A90: 46 | B90: 1 | G90: un | H90: Receita bruta de mercadorias - Varejo (Super/Hiper, Camino) (R$ milhoes) | J90: release | K90: 806 | L90: 869 | M90: 1021 | N90: 1183 | O90: 1114 | P90: 1215 | Q90: 1435 | R90: 1465 | S90: 1474 | T90: 1622 | U90: 1829 | V90: 1883 | W90: 1757 | X90: 1877 | Y90: 2047 | Z90: 2096 | AA90: 2036 | AB90: 2055 | AC90: 2164 | AD90: 2244 | AE90: 2110 | AF90: 2143 | AG90: 2228 | AH90: 2326
A91: 47 | B91: 1 | G91: un | H91: Receita bruta de mercadorias - Eletro (R$ milhoes) | J91: release | K91: 120 | L91: 155 | M91: 252 | N91: 269 | O91: 196 | P91: 243 | Q91: 264 | R91: 292 | S91: 256 | T91: 281 | U91: 288 | V91: 292 | W91: 234 | X91: 294 | Y91: 316 | Z91: 339 | AA91: 261 | AB91: 315 | AC91: 337 | AD91: 354 | AE91: 254 | AF91: 277 | AG91: 283 | AH91: 339
A92: 48 | B92: 1 | G92: un | H92: Receita bruta de mercadorias - Atacado B2B (R$ milhoes) | J92: release | K92: 613 | L92: 788 | M92: 731 | N92: 732 | O92: 662 | P92: 741 | Q92: 804 | R92: 813 | S92: 928 | T92: 997 | U92: 1069 | V92: 1079 | W92: 1078 | X92: 1187 | Y92: 1236 | Z92: 1400 | AA92: 1400 | AB92: 1534 | AC92: 1625 | AD92: 1690 | AE92: 1816 | AF92: 1986 | AG92: 2060 | AH92: 2052
A93: 49 | B93: 1 | G93: un | H93: Receita liquida - Grupo Mateus MA, PA, PI, CE, SE e BA (R$ milhoes; desde 3T25) | J93: release | AG93: 7869 | AH93: 7723 | AI93: 7012 | AJ93: 7387
A94: 50 | B94: 1 | G94: un | H94: Receita liquida - combinacao Grupo Mateus + Novo Atacarejo PE, PB e AL (R$ milhoes; 3T25 = Mateus PE/PB/AL 1.431 + Novo Atacarejo 1.464) | J94: release | AG94: 2895 | AH94: 2827 | AI94: 2390 | AJ94: 2466
A95: 51 | B95: 1 | G95: un | H95: Lojas - Atacarejo e Food Service (Mix Mateus) (fim do periodo) | J95: fonte | K95: 26 | L95: 29 | M95: 30 | N95: 33 | O95: 35 | P95: 38 | Q95: 40 | R95: 42 | S95: 48 | T95: 50 | U95: 53 | V95: 58 | W95: 62 | X95: 64 | Y95: 69 | Z95: 80 | AA95: 82 | AB95: 84 | AC95: 88 | AD95: 90 | AE95: 92 | AF95: 96 | AG95: 98 | AH95: 102 | AI95: 105 | AJ95: 77
A96: 52 | B96: 1 | G96: un | H96: Lojas - Novo Atacarejo (fim do periodo) | J96: fonte | K96: 0 | L96: 0 | M96: 0 | N96: 0 | O96: 0 | P96: 0 | Q96: 0 | R96: 0 | S96: 0 | T96: 0 | U96: 0 | V96: 0 | W96: 0 | X96: 0 | Y96: 0 | Z96: 0 | AA96: 0 | AB96: 0 | AC96: 0 | AD96: 0 | AE96: 0 | AF96: 0 | AG96: 36 | AH96: 37 | AI96: 37 | AJ96: 67
A97: 53 | B97: 1 | G97: un | H97: Lojas - Varejo (Super/Hiper + Camino) (fim do periodo) | J97: fonte | K97: 40 | L97: 41 | M97: 44 | N97: 49 | O97: 55 | P97: 56 | Q97: 57 | R97: 61 | S97: 68 | T97: 69 | U97: 70 | V97: 70 | W97: 70 | X97: 71 | Y97: 72 | Z97: 73 | AA97: 73 | AB97: 76 | AC97: 76 | AD97: 78 | AE97: 80 | AF97: 80 | AG97: 81 | AH97: 85 | AI97: 86 | AJ97: 90
A98: 54 | B98: 1 | G98: un | H98: Lojas - Eletro (fim do periodo) | J98: fonte | K98: 61 | L98: 67 | M98: 71 | N98: 77 | O98: 80 | P98: 88 | Q98: 92 | R98: 99 | S98: 102 | T98: 103 | U98: 103 | V98: 104 | W98: 106 | X98: 104 | Y98: 105 | Z98: 105 | AA98: 104 | AB98: 104 | AC98: 104 | AD98: 104 | AE98: 104 | AF98: 95 | AG98: 91 | AH98: 78 | AI98: 78 | AJ98: 78
A99: 55 | B99: 1 | G99: un | H99: Lojas - Farmacia (fim do periodo) | J99: fonte | K99: 0 | L99: 0 | M99: 0 | N99: 0 | O99: 0 | P99: 0 | Q99: 0 | R99: 0 | S99: 0 | T99: 0 | U99: 0 | V99: 0 | W99: 0 | X99: 0 | Y99: 0 | Z99: 0 | AA99: 0 | AB99: 0 | AC99: 0 | AD99: 0 | AE99: 0 | AF99: 0 | AG99: 0 | AH99: 0 | AI99: 0 | AJ99: 1
A100: 56 | B100: 1 | G100: un | H100: Area de vendas - Atacarejo (m2; a aba diz "mil m2" mas os valores estao em m2) | J100: fonte | K100: 130570.48 | L100: 144829.26 | M100: 149591.26 | N100: 162362.56 | O100: 172313.37 | P100: 186618.84 | Q100: 195258 | R100: 204422 | S100: 236290 | T100: 247402 | U100: 258719 | V100: 281028 | W100: 297424.35 | X100: 304425 | Y100: 321276.35 | Z100: 362853.97 | AA100: 370218.7 | AB100: 376739.59 | AC100: 391853.79 | AD100: 401125.4 | AE100: 408033.4 | AF100: 425229.96 | AG100: 433065.96 | AH100: 445430.38 | AI100: 455002 | AJ100: 346191.38
A101: 57 | B101: 1 | G101: un | H101: Area de vendas - Novo Atacarejo (m2) | J101: fonte | K101: 0 | L101: 0 | M101: 0 | N101: 0 | O101: 0 | P101: 0 | Q101: 0 | R101: 0 | S101: 0 | T101: 0 | U101: 0 | V101: 0 | W101: 0 | X101: 0 | Y101: 0 | Z101: 0 | AA101: 0 | AB101: 0 | AC101: 0 | AD101: 0 | AE101: 0 | AF101: 0 | AG101: 137197 | AH101: 140920.05 | AI101: 140920 | AJ101: 257161.53
A102: 58 | B102: 1 | G102: un | H102: Area de vendas - Varejo (m2) | J102: fonte | K102: 71735.123 | L102: 72492.063 | M102: 76358.813 | N102: 85579.873 | O102: 93923.233 | P102: 95641.283 | Q102: 97277 | R102: 105812 | S102: 116745 | T102: 118729 | U102: 120216 | V102: 120216 | W102: 120216 | X102: 121271 | Y102: 123571 | Z102: 124372 | AA102: 124372 | AB102: 127274.29 | AC102: 127274.29 | AD102: 132684.29 | AE102: 134494.29 | AF102: 135281.94 | AG102: 135690.94 | AH102: 142699.48 | AI102: 144400 | AJ102: 149842.19
A103: 59 | B103: 1 | G103: un | H103: Area de vendas - Eletro (m2) | J103: fonte | K103: 68149.51 | L103: 72341.67 | M103: 75060.34 | N103: 80834.32 | O103: 83575.38 | P103: 89891.6 | Q103: 93233 | R103: 97593 | S103: 99641 | T103: 100220 | U103: 98723 | V103: 99247 | W103: 100463.39 | X103: 99299 | Y103: 99578.32 | Z103: 99578.32 | AA103: 98939 | AB103: 99459.56 | AC103: 98696.41 | AD103: 98696.41 | AE103: 98588.5 | AF103: 91357.36 | AG103: 87184 | AH103: 72402.32 | AI103: 72402 | AJ103: 72402
A104: 60 | B104: 1 | G104: un | H104: Area de vendas - Farmacia (m2) | J104: fonte | K104: 0 | L104: 0 | M104: 0 | N104: 0 | O104: 0 | P104: 0 | Q104: 0 | R104: 0 | S104: 0 | T104: 0 | U104: 0 | V104: 0 | W104: 0 | X104: 0 | Y104: 0 | Z104: 0 | AA104: 0 | AB104: 0 | AC104: 0 | AD104: 0 | AE104: 0 | AF104: 0 | AG104: 0 | AH104: 0 | AI104: 0 | AJ104: 771
A105: 61 | B105: 1 | G105: un | H105: SSS consolidado sem ajuste calendario (%) - releases (1T20 e 1T21 divulgados arredondados: 7% e 10%) | J105: release | K105: 0.07 | L105: 0.238 | M105: 0.237 | N105: 0.213 | O105: 0.1 | P105: 0.018 | Q105: 0.015 | R105: 0.014 | S105: 0.127 | T105: 0.167 | U105: 0.117 | V105: 0.117 | W105: 0.113 | X105: 0.104 | Y105: 0.043 | Z105: 0.088 | AA105: 0.096 | AB105: 0.048 | AC105: 0.077 | AD105: 0.059 | AE105: 0.052 | AF105: 0.061 | AG105: 0.028 | AH105: -0.011 | AI105: -0.073 | AJ105: -0.08
H106: Fontes da receita por segmento: 1T20 e 2T20: comparativos dos releases 1T21 e 2T21; 3T20: comparativo do 3T21; 4T21 a 4T22: release 4T22 (PDFs de 2022 sao imagem, lidos na tabela "Destaques por Segmento" e graficos do 4T22); demais: release do proprio trimestre. 3T25: Atacarejo = Mix Mateus 5.804 + Novo Atacarejo 1.726 (no 4T25 a Cia ja divulga somado). 1T26 e 2T26: a Cia deixou de abrir a receita por segmento
H107: Receita bruta de mercadorias = antes de devolucoes e sem receita de servicos (conceito dos releases). Lojas 2T26: 30 lojas Mateus de PE/PB/AL migraram para a bandeira Novo Atacarejo (Atacarejo 102 -> 77; Novo 37 -> 67).
H143: CONVENCOES
H144: Linhas de origem: 5 a 107. As formulas da Inputs (2) varrem as linhas 5 a 140; as linhas 108 a 140 estao livres para novas contas.
H145: Periodos: colunas K a AJ (1Q20 a 2Q26 = 1T20 a 2T26).
H146: Brutos em R$ mil, como na fonte. A Inputs (2) multiplica pelo fator da celula B1 (0,001) e entrega R$ milhoes.
H147: ORIGEM: fonte = copiado da planilha; release = digitado do release do trimestre; memoria = como divulgado, sem codigo; derivada = formula nesta aba.
H148: Codigos 45 a 61: drivers de receita (memoria); alimentam o bloco logo abaixo da receita liquida no Model.

Sheet Inputs (2)
A1: =COUNTIF($B$3:$B$1048576,$B$1) -> 1 | B1: =MAX($B$3:$B$1048576) -> 61
D2: 1Q21 | E2: 2Q21 | F2: 3Q21 | G2: 4Q21 | H2: 2021 | I2: 1Q22 | J2: 2Q22 | K2: 3Q22 | L2: 4Q22 | M2: 2022 | N2: 1Q23 | O2: 2Q23 | P2: 3Q23 | Q2: 4Q23 | R2: 2023 | S2: 1Q24 | T2: 2Q24 | U2: 3Q24 | V2: 4Q24 | W2: 2024 | X2: 1Q25 | Y2: 2Q25 | Z2: 3Q25 | AA2: 4Q25 | AB2: 2025 | AC2: 1Q26 | AD2: 2Q26 | AE2: 3Q26 | AF2: 4Q26 | AG2: 2026 | AH2: 1Q20 | AI2: 2Q20 | AJ2: 3Q20 | AK2: 4Q20 | AL2: 2020 | AN2: Sem dado na fonte: 3Q26, 4Q26 e 2026 (rotulo em cinza). 2020 fica nas colunas AH-AL.
B4: 1 | C4: Net Revenues | D4: =IF(ISNA(MATCH(D$2,Inputs!$K$4:$AJ$4,0)),NA(),IF(SUMPRODUCT((Inputs!$A$5:$A$140=$B4)*ISNUMBER(INDEX(Inputs!$K$5:$AJ$140,0,MATCH(D$2,Inputs!$K$4:$AJ$4,0))))+SUMPRODUCT((Inputs!$C$5:$C$140=$B4)*ISNUMBER(INDEX(Inputs!$K$5:$AJ$140,0,MATCH(D$2,Inputs!$K$4:$AJ$4,0))))+SUMPRODUCT((Inputs!$E$5:$E$140=$B4)*ISNUMBER(INDEX(Inputs!$K$5:$AJ$140,0,MATCH(D$2,Inputs!$K$4:$AJ$4,0))))=0,NA(),SUMPRODUCT((Inputs!$A$5:$A$140=$B4)*Inputs!$B$5:$B$140*(((Inputs!$G$5:$G$140="moeda")+(Inputs!$G$5:$G$140="acoes"))*Inputs!$B$1+((Inputs!$G$5:$G$140<>"moeda")*(Inputs!$G$5:$G$140<>"acoes")))*INDEX(Inputs!$K$5:$AJ$140,0,MATCH(D$2,Inputs!$K$4:$AJ$4,0)))+SUMPRODUCT((Inputs!$C$5:$C$140=$B4)*Inputs!$D$5:$D$140*(((Inputs!$G$5:$G$140="moeda")+(Inputs!$G$5:$G$140="acoes"))*Inputs!$B$1+((Inputs!$G$5:$G$140<>"moeda")*(Inputs!$G$5:$G$140<>"acoes")))*INDEX(Inputs!$K$5:$AJ$140,0,MATCH(D$2,Inputs!$K$4:$AJ$4,0)))+SUMPRODUCT((Inputs!$E$5:$E$140=$B4)*Inputs!$F$5:$F$140*(((Inputs!$G$5:$G$140="moeda")+(Inputs!$G$5:$G$140="acoes"))*Inputs!$B$1+((Inputs!$G$5:$G$140<>"moeda")*(Inputs!$G$5:$G$140<>"acoes")))*INDEX(Inputs!$K$5:$AJ$140,0,MATCH(D$2,Inputs!$K$4:$AJ$4,0))))) -> 3362.2731 | E4: =IF(ISNA(MATCH(E$2,Inputs!$K$4:$AJ$4,0)),NA(),IF(SUMPRODUCT((Inputs!$A$5:$A$140=$B4)*ISNUMBER(INDEX(Inputs!$K$5:$AJ$140,0,MATCH(E$2,Inputs!$K$4:$AJ$4,0))))+SUMPRODUCT((Inputs!$C$5:$C$140=$B4)*ISNUMBER(INDEX(Inputs!$K$5:$AJ$140,0,MATCH(E$2,Inputs!$K$4:$AJ$4,0))))+SUMPRODUCT((Inputs!$E$5:$E$140=$B4)*ISNUMBER(INDEX(Inputs!$K$5:$AJ$140,0,MATCH(E$2,Inputs!$K$4:$AJ$4,0))))=0,NA(),SUMPRODUCT((Inputs!$A$5:$A$140=$B4)*Inputs!$B$5:$B$140*(((Inputs!$G$5:$G$140="moeda")+(Inputs!$G$5:$G$140="acoes"))*Inputs!$B$1+((Inputs!$G$5:$G$140<>"moeda")*(Inputs!$G$5:$G$140<>"acoes")))*INDEX(Inputs!$K$5:$AJ$140,0,MATCH(E$2,Inputs!$K$4:$AJ$4,0)))+SUMPRODUCT((Inputs!$C$5:$C$140=$B4)*Inputs!$D$5:$D$140*(((Inputs!$G$5:$G$140="moeda")+(Inputs!$G$5:$G$140="acoes"))*Inputs!$B$1+((Inputs!$G$5:$G$140<>"moeda")*(Inputs!$G$5:$G$140<>"acoes")))*INDEX(Inputs!$K$5:$AJ$140,0,MATCH(E$2,Inputs!$K$4:$AJ$4,0)))+SUMPRODUCT((Inputs!$E$5:$E$140=$B4)*Inputs!$F$5:$F$140*(((Inputs!$G$5:$G$140="moeda")+(Inputs!$G$5:$G$140="acoes"))*Inputs!$B$1+((Inputs!$G$5:$G$140<>"moeda")*(Inputs!$G$5:$G$140<>"acoes")))*INDEX(Inputs!$K$5:$AJ$140,0,MATCH(E$2,Inputs!$K$4:$AJ$4,0))))) -> 3724.3417 | F4: =IF(ISNA(MATCH(F$2,Inputs!$K$4:$AJ$4,0)),NA(),IF(SUMPRODUCT((Inputs!$A$5:$A$140=$B4)*ISNUMBER(INDEX(Inputs!$K$5:$AJ$140,0,MATCH(F$2,Inputs!$K$4:$AJ$4,0))))+SUMPRODUCT((Inputs!$C$5:$C$140=$B4)*ISNUMBER(INDEX(Inputs!$K$5:$AJ$140,0,MATCH(F$2,Inputs!$K$4:$AJ$4,0))))+SUMPRODUCT((Inputs!$E$5:$E$140=$B4)*ISNUMBER(INDEX(Inputs!$K$5:$AJ$140,0,MATCH(F$2,Inputs!$K$4:$AJ$4,0))))=0,NA(),SUMPRODUCT((Inputs!$A$5:$A$140=$B4)*Inputs!$B$5:$B$140*(((Inputs!$G$5:$G$140="moeda")+(Inputs!$G$5:$G$140="acoes"))*Inputs!$B$1+((Inputs!$G$5:$G$140<>"moeda")*(Inputs!$G$5:$G$140<>"acoes")))*INDEX(Inputs!$K$5:$AJ$140,0,MATCH(F$2,Inputs!$K$4:$AJ$4,0)))+SUMPRODUCT((Inputs!$C$5:$C$140=$B4)*Inputs!$D$5:$D$140*(((Inputs!$G$5:$G$140="moeda")+(Inputs!$G$5:$G$140="acoes"))*Inputs!$B$1+((Inputs!$G$5:$G$140<>"moeda")*(Inputs!$G$5:$G$140<>"acoes")))*INDEX(Inputs!$K$5:$AJ$140,0,MATCH(F$2,Inputs!$K$4:$AJ$4,0)))+SUMPRODUCT((Inputs!$E$5:$E$140=$B4)*Inputs!$F$5:$F$140*(((Inputs!$G$5:$G$140="moeda")+(Inputs!$G$5:$G$140="acoes"))*Inputs!$B$1+((Inputs!$G$5:$G$140<>"moeda")*(Inputs!$G$5:$G$140<>"acoes")))*INDEX(Inputs!$K$5:$AJ$140,0,MATCH(F$2,Inputs!$K$4:$AJ$4,0))))) -> 4349.125 | G4: =IF(ISNA(MATCH(G$2,Inputs!$K$4:$AJ$4,0)),NA(),IF(SUMPRODUCT((Inputs!$A$5:$A$140=$B4)*ISNUMBER(INDEX(Inputs!$K$5:$AJ$140,0,MATCH(G$2,Inputs!$K$4:$AJ$4,0))))+SUMPRODUCT((Inputs!$C$5:$C$140=$B4)*ISNUMBER(INDEX(Inputs!$K$5:$AJ$140,0,MATCH(G$2,Inputs!$K$4:$AJ$4,0))))+SUMPRODUCT((Inputs!$E$5:$E$140=$B4)*ISNUMBER(INDEX(Inputs!$K$5:$AJ$140,0,MATCH(G$2,Inputs!$K$4:$AJ$4,0))))=0,NA(),SUMPRODUCT((Inputs!$A$5:$A$140=$B4)*Inputs!$B$5:$B$140*(((Inputs!$G$5:$G$140="moeda")+(Inputs!$G$5:$G$140="acoes"))*Inputs!$B$1+((Inputs!$G$5:$G$140<>"moeda")*(Inputs!$G$5:$G$140<>"acoes")))*INDEX(Inputs!$K$5:$AJ$140,0,MATCH(G$2,Inputs!$K$4:$AJ$4,0)))+SUMPRODUCT((Inputs!$C$5:$C$140=$B4)*Inputs!$D$5:$D$140*(((Inputs!$G$5:$G$140="moeda")+(Inputs!$G$5:$G$140="acoes"))*Inputs!$B$1+((Inputs!$G$5:$G$140<>"moeda")*(Inputs!$G$5:$G$140<>"acoes")))*INDEX(Inputs!$K$5:$AJ$140,0,MATCH(G$2,Inputs!$K$4:$AJ$4,0)))+SUMPRODUCT((Inputs!$E$5:$E$140=$B4)*Inputs!$F$5:$F$140*(((Inputs!$G$5:$G$140="moeda")+(Inputs!$G$5:$G$140="acoes"))*Inputs!$B$1+((Inputs!$G$5:$G$140<>"moeda")*(Inputs!$G$5:$G$140<>"acoes")))*INDEX(Inputs!$K$5:$AJ$140,0,MATCH(G$2,Inputs!$K$4:$AJ$4,0))))) -> 4441.1172 | H4: =SUM(D4:G4) -> 15876.857 | I4: =IF(ISNA(MATCH(I$2,Inputs!$K$4:$AJ$4,0)),NA(),IF(SUMPRODUCT((Inputs!$A$5:$A$140=$B4)*ISNUMBER(INDEX(Inputs!$K$5:$AJ$140,0,MATCH(I$2,Inputs!$K$4:$AJ$4,0))))+SUMPRODUCT((Inputs!$C$5:$C$140=$B4)*ISNUMBER(INDEX(Inputs!$K$5:$AJ$140,0,MATCH(I$2,Inputs!$K$4:$AJ$4,0))))+SUMPRODUCT((Inputs!$E$5:$E$140=$B4)*ISNUMBER(INDEX(Inputs!$K$5:$AJ$140,0,MATCH(I$2,Inputs!$K$4:$AJ$4,0))))=0,NA(),SUMPRODUCT((Inputs!$A$5:$A$140=$B4)*Inputs!$B$5:$B$140*(((Inputs!$G$5:$G$140="moeda")+(Inputs!$G$5:$G$140="acoes"))*Inputs!$B$1+((Inputs!$G$5:$G$140<>"moeda")*(Inputs!$G$5:$G$140<>"acoes")))*INDEX(Inputs!$K$5:$AJ$140,0,MATCH(I$2,Inputs!$K$4:$AJ$4,0)))+SUMPRODUCT((Inputs!$C$5:$C$140=$B4)*Inputs!$D$5:$D$140*(((Inputs!$G$5:$G$140="moeda")+(Inputs!$G$5:$G$140="acoes"))*Inputs!$B$1+((Inputs!$G$5:$G$140<>"moeda")*(Inputs!$G$5:$G$140<>"acoes")))*INDEX(Inputs!$K$5:$AJ$140,0,MATCH(I$2,Inputs!$K$4:$AJ$4,0)))+SUMPRODUCT((Inputs!$E$5:$E$140=$B4)*Inputs!$F$5:$F$140*(((Inputs!$G$5:$G$140="moeda")+(Inputs!$G$5:$G$140="acoes"))*Inputs!$B$1+((Inputs!$G$5:$G$140<>"moeda")*(Inputs!$G$5:$G$140<>"acoes")))*INDEX(Inputs!$K$5:$AJ$140,0,MATCH(I$2,Inputs!$K$4:$AJ$4,0))))) -> 4578.7795 | J4: =IF(ISNA(MATCH(J$2,Inputs!$K$4:$AJ$4,0)),NA(),IF(SUMPRODUCT((Inputs!$A$5:$A$140=$B4)*ISNUMBER(INDEX(Inputs!$K$5:$AJ$140,0,MATCH(J$2,Inputs!$K$4:$AJ$4,0))))+SUMPRODUCT((Inputs!$C$5:$C$140=$B4)*ISNUMBER(INDEX(Inputs!$K$5:$AJ$140,0,MATCH(J$2,Inputs!$K$4:$AJ$4,0))))+SUMPRODUCT((Inputs!$E$5:$E$140=$B4)*ISNUMBER(INDEX(Inputs!$K$5:$AJ$140,0,MATCH(J$2,Inputs!$K$4:$AJ$4,0))))=0,NA(),SUMPRODUCT((Inputs!$A$5:$A$140=$B4)*Inputs!$B$5:$B$140*(((Inputs!$G$5:$G$140="moeda")+(Inputs!$G$5:$G$140="acoes"))*Inputs!$B$1+((Inputs!$G$5:$G$140<>"moeda")*(Inputs!$G$5:$G$140<>"acoes")))*INDEX(Inputs!$K$5:$AJ$140,0,MATCH(J$2,Inputs!$K$4:$AJ$4,0)))+SUMPRODUCT((Inputs!$C$5:$C$140=$B4)*Inputs!$D$5:$D$140*(((Inputs!$G$5:$G$140="moeda")+(Inputs!$G$5:$G$140="acoes"))*Inputs!$B$1+((Inputs!$G$5:$G$140<>"moeda")*(Inputs!$G$5:$G$140<>"acoes")))*INDEX(Inputs!$K$5:$AJ$140,0,MATCH(J$2,Inputs!$K$4:$AJ$4,0)))+SUMPRODUCT((Inputs!$E$5:$E$140=$B4)*Inputs!$F$5:$F$140*(((Inputs!$G$5:$G$140="moeda")+(Inputs!$G$5:$G$140="acoes"))*Inputs!$B$1+((Inputs!$G$5:$G$140<>"moeda")*(Inputs!$G$5:$G$140<>"acoes")))*INDEX(Inputs!$K$5:$AJ$140,0,MATCH(J$2,Inputs!$K$4:$AJ$4,0))))) -> 5201.989 | K4: =IF(ISNA(MATCH(K$2,Inputs!$K$4:$AJ$4,0)),NA(),IF(SUMPRODUCT((Inputs!$A$5:$A$140=$B4)*ISNUMBER(INDEX(Inputs!$K$5:$AJ$140,0,MATCH(K$2,Inputs!$K$4:$AJ$4,0))))+SUMPRODUCT((Inputs!$C$5:$C$140=$B4)*ISNUMBER(INDEX(Inputs!$K$5:$AJ$140,0,MATCH(K$2,Inputs!$K$4:$AJ$4,0))))+SUMPRODUCT((Inputs!$E$5:$E$140=$B4)*ISNUMBER(INDEX(Inputs!$K$5:$AJ$140,0,MATCH(K$2,Inputs!$K$4:$AJ$4,0))))=0,NA(),SUMPRODUCT((Inputs!$A$5:$A$140=$B4)*Inputs!$B$5:$B$140*(((Inputs!$G$5:$G$140="moeda")+(Inputs!$G$5:$G$140="acoes"))*Inputs!$B$1+((Inputs!$G$5:$G$140<>"moeda")*(Inputs!$G$5:$G$140<>"acoes")))*INDEX(Inputs!$K$5:$AJ$140,0,MATCH(K$2,Inputs!$K$4:$AJ$4,0)))+SUMPRODUCT((Inputs!$C$5:$C$140=$B4)*Inputs!$D$5:$D$140*(((Inputs!$G$5:$G$140="moeda")+(Inputs!$G$5:$G$140="acoes"))*Inputs!$B$1+((Inputs!$G$5:$G$140<>"moeda")*(Inputs!$G$5:$G$140<>"acoes")))*INDEX(Inputs!$K$5:$AJ$140,0,MATCH(K$2,Inputs!$K$4:$AJ$4,0)))+SUMPRODUCT((Inputs!$E$5:$E$140=$B4)*Inputs!$F$5:$F$140*(((Inputs!$G$5:$G$140="moeda")+(Inputs!$G$5:$G$140="acoes"))*Inputs!$B$1+((Inputs!$G$5:$G$140<>"moeda")*(Inputs!$G$5:$G$140<>"acoes")))*INDEX(Inputs!$K$5:$AJ$140,0,MATCH(K$2,Inputs!$K$4:$AJ$4,0))))) -> 5923.131 | L4: =IF(ISNA(MATCH(L$2,Inputs!$K$4:$AJ$4,0)),NA(),IF(SUMPRODUCT((Inputs!$A$5:$A$140=$B4)*ISNUMBER(INDEX(Inputs!$K$5:$AJ$140,0,MATCH(L$2,Inputs!$K$4:$AJ$4,0))))+SUMPRODUCT((Inputs!$C$5:$C$140=$B4)*ISNUMBER(INDEX(Inputs!$K$5:$AJ$140,0,MATCH(L$2,Inputs!$K$4:$AJ$4,0))))+SUMPRODUCT((Inputs!$E$5:$E$140=$B4)*ISNUMBER(INDEX(Inputs!$K$5:$AJ$140,0,MATCH(L$2,Inputs!$K$4:$AJ$4,0))))=0,NA(),SUMPRODUCT((Inputs!$A$5:$A$140=$B4)*Inputs!$B$5:$B$140*(((Inputs!$G$5:$G$140="moeda")+(Inputs!$G$5:$G$140="acoes"))*Inputs!$B$1+((Inputs!$G$5:$G$140<>"moeda")*(Inputs!$G$5:$G$140<>"acoes")))*INDEX(Inputs!$K$5:$AJ$140,0,MATCH(L$2,Inputs!$K$4:$AJ$4,0)))+SUMPRODUCT((Inputs!$C$5:$C$140=$B4)*Inputs!$D$5:$D$140*(((Inputs!$G$5:$G$140="moeda")+(Inputs!$G$5:$G$140="acoes"))*Inputs!$B$1+((Inputs!$G$5:$G$140<>"moeda")*(Inputs!$G$5:$G$140<>"acoes")))*INDEX(Inputs!$K$5:$AJ$140,0,MATCH(L$2,Inputs!$K$4:$AJ$4,0)))+SUMPRODUCT((Inputs!$E$5:$E$140=$B4)*Inputs!$F$5:$F$140*(((Inputs!$G$5:$G$140="moeda")+(Inputs!$G$5:$G$140="acoes"))*Inputs!$B$1+((Inputs!$G$5:$G$140<>"moeda")*(Inputs!$G$5:$G$140<>"acoes")))*INDEX(Inputs!$K$5:$AJ$140,0,MATCH(L$2,Inputs!$K$4:$AJ$4,0))))) -> 6064.577 | M4: =SUM(I4:L4) -> 21768.476 | N4: =IF(ISNA(MATCH(N$2,Inputs!$K$4:$AJ$4,0)),NA(),IF(SUMPRODUCT((Inputs!$A$5:$A$140=$B4)*ISNUMBER(INDEX(Inputs!$K$5:$AJ$140,0,MATCH(N$2,Inputs!$K$4:$AJ$4,0))))+SUMPRODUCT((Inputs!$C$5:$C$140=$B4)*ISNUMBER(INDEX(Inputs!$K$5:$AJ$140,0,MATCH(N$2,Inputs!$K$4:$AJ$4,0))))+SUMPRODUCT((Inputs!$E$5:$E$140=$B4)*ISNUMBER(INDEX(Inputs!$K$5:$AJ$140,0,MATCH(N$2,Inputs!$K$4:$AJ$4,0))))=0,NA(),SUMPRODUCT((Inputs!$A$5:$A$140=$B4)*Inputs!$B$5:$B$140*(((Inputs!$G$5:$G$140="moeda")+(Inputs!$G$5:$G$140="acoes"))*Inputs!$B$1+((Inputs!$G$5:$G$140<>"moeda")*(Inputs!$G$5:$G$140<>"acoes")))*INDEX(Inputs!$K$5:$AJ$140,0,MATCH(N$2,Inputs!$K$4:$AJ$4,0)))+SUMPRODUCT((Inputs!$C$5:$C$140=$B4)*Inputs!$D$5:$D$140*(((Inputs!$G$5:$G$140="moeda")+(Inputs!$G$5:$G$140="acoes"))*Inputs!$B$1+((Inputs!$G$5:$G$140<>"moeda")*(Inputs!$G$5:$G$140<>"acoes")))*INDEX(Inputs!$K$5:$AJ$140,0,MATCH(N$2,Inputs!$K$4:$AJ$4,0)))+SUMPRODUCT((Inputs!$E$5:$E$140=$B4)*Inputs!$F$5:$F$140*(((Inputs!$G$5:$G$140="moeda")+(Inputs!$G$5:$G$140="acoes"))*Inputs!$B$1+((Inputs!$G$5:$G$140<>"moeda")*(Inputs!$G$5:$G$140<>"acoes")))*INDEX(Inputs!$K$5:$AJ$140,0,MATCH(N$2,Inputs!$K$4:$AJ$4,0))))) -> 5867.8797 | O4: =IF(ISNA(MATCH(O$2,Inputs!$K$4:$AJ$4,0)),NA(),IF(SUMPRODUCT((Inputs!$A$5:$A$140=$B4)*ISNUMBER(INDEX(Inputs!$K$5:$AJ$140,0,MATCH(O$2,Inputs!$K$4:$AJ$4,0))))+SUMPRODUCT((Inputs!$C$5:$C$140=$B4)*ISNUMBER(INDEX(Inputs!$K$5:$AJ$140,0,MATCH(O$2,Inputs!$K$4:$AJ$4,0))))+SUMPRODUCT((Inputs!$E$5:$E$140=$B4)*ISNUMBER(INDEX(Inputs!$K$5:$AJ$140,0,MATCH(O$2,Inputs!$K$4:$AJ$4,0))))=0,NA(),SUMPRODUCT((Inputs!$A$5:$A$140=$B4)*Inputs!$B$5:$B$140*(((Inputs!$G$5:$G$140="moeda")+(Inputs!$G$5:$G$140="acoes"))*Inputs!$B$1+((Inputs!$G$5:$G$140<>"moeda")*(Inputs!$G$5:$G$140<>"acoes")))*INDEX(Inputs!$K$5:$AJ$140,0,MATCH(O$2,Inputs!$K$4:$AJ$4,0)))+SUMPRODUCT((Inputs!$C$5:$C$140=$B4)*Inputs!$D$5:$D$140*(((Inputs!$G$5:$G$140="moeda")+(Inputs!$G$5:$G$140="acoes"))*Inputs!$B$1+((Inputs!$G$5:$G$140<>"moeda")*(Inputs!$G$5:$G$140<>"acoes")))*INDEX(Inputs!$K$5:$AJ$140,0,MATCH(O$2,Inputs!$K$4:$AJ$4,0)))+SUMPRODUCT((Inputs!$E$5:$E$140=$B4)*Inputs!$F$5:$F$140*(((Inputs!$G$5:$G$140="moeda")+(Inputs!$G$5:$G$140="acoes"))*Inputs!$B$1+((Inputs!$G$5:$G$140<>"moeda")*(Inputs!$G$5:$G$140<>"acoes")))*INDEX(Inputs!$K$5:$AJ$140,0,MATCH(O$2,Inputs!$K$4:$AJ$4,0))))) -> 6429.472 | P4: =IF(ISNA(MATCH(P$2,Inputs!$K$4:$AJ$4,0)),NA(),IF(SUMPRODUCT((Inputs!$A$5:$A$140=$B4)*ISNUMBER(INDEX(Inputs!$K$5:$AJ$140,0,MATCH(P$2,Inputs!$K$4:$AJ$4,0))))+SUMPRODUCT((Inputs!$C$5:$C$140=$B4)*ISNUMBER(INDEX(Inputs!$K$5:$AJ$140,0,MATCH(P$2,Inputs!$K$4:$AJ$4,0))))+SUMPRODUCT((Inputs!$E$5:$E$140=$B4)*ISNUMBER(INDEX(Inputs!$K$5:$AJ$140,0,MATCH(P$2,Inputs!$K$4:$AJ$4,0))))=0,NA(),SUMPRODUCT((Inputs!$A$5:$A$140=$B4)*Inputs!$B$5:$B$140*(((Inputs!$G$5:$G$140="moeda")+(Inputs!$G$5:$G$140="acoes"))*Inputs!$B$1+((Inputs!$G$5:$G$140<>"moeda")*(Inputs!$G$5:$G$140<>"acoes")))*INDEX(Inputs!$K$5:$AJ$140,0,MATCH(P$2,Inputs!$K$4:$AJ$4,0)))+SUMPRODUCT((Inputs!$C$5:$C$140=$B4)*Inputs!$D$5:$D$140*(((Inputs!$G$5:$G$140="moeda")+(Inputs!$G$5:$G$140="acoes"))*Inputs!$B$1+((Inputs!$G$5:$G$140<>"moeda")*(Inputs!$G$5:$G$140<>"acoes")))*INDEX(Inputs!$K$5:$AJ$140,0,MATCH(P$2,Inputs!$K$4:$AJ$4,0)))+SUMPRODUCT((Inputs!$E$5:$E$140=$B4)*Inputs!$F$5:$F$140*(((Inputs!$G$5:$G$140="moeda")+(Inputs!$G$5:$G$140="acoes"))*Inputs!$B$1+((Inputs!$G$5:$G$140<>"moeda")*(Inputs!$G$5:$G$140<>"acoes")))*INDEX(Inputs!$K$5:$AJ$140,0,MATCH(P$2,Inputs!$K$4:$AJ$4,0))))) -> 6934.929 | Q4: =IF(ISNA(MATCH(Q$2,Inputs!$K$4:$AJ$4,0)),NA(),IF(SUMPRODUCT((Inputs!$A$5:$A$140=$B4)*ISNUMBER(INDEX(Inputs!$K$5:$AJ$140,0,MATCH(Q$2,Inputs!$K$4:$AJ$4,0))))+SUMPRODUCT((Inputs!$C$5:$C$140=$B4)*ISNUMBER(INDEX(Inputs!$K$5:$AJ$140,0,MATCH(Q$2,Inputs!$K$4:$AJ$4,0))))+SUMPRODUCT((Inputs!$E$5:$E$140=$B4)*ISNUMBER(INDEX(Inputs!$K$5:$AJ$140,0,MATCH(Q$2,Inputs!$K$4:$AJ$4,0))))=0,NA(),SUMPRODUCT((Inputs!$A$5:$A$140=$B4)*Inputs!$B$5:$B$140*(((Inputs!$G$5:$G$140="moeda")+(Inputs!$G$5:$G$140="acoes"))*Inputs!$B$1+((Inputs!$G$5:$G$140<>"moeda")*(Inputs!$G$5:$G$140<>"acoes")))*INDEX(Inputs!$K$5:$AJ$140,0,MATCH(Q$2,Inputs!$K$4:$AJ$4,0)))+SUMPRODUCT((Inputs!$C$5:$C$140=$B4)*Inputs!$D$5:$D$140*(((Inputs!$G$5:$G$140="moeda")+(Inputs!$G$5:$G$140="acoes"))*Inputs!$B$1+((Inputs!$G$5:$G$140<>"moeda")*(Inputs!$G$5:$G$140<>"acoes")))*INDEX(Inputs!$K$5:$AJ$140,0,MATCH(Q$2,Inputs!$K$4:$AJ$4,0)))+SUMPRODUCT((Inputs!$E$5:$E$140=$B4)*Inputs!$F$5:$F$140*(((Inputs!$G$5:$G$140="moeda")+(Inputs!$G$5:$G$140="acoes"))*Inputs!$B$1+((Inputs!$G$5:$G$140<>"moeda")*(Inputs!$G$5:$G$140<>"acoes")))*INDEX(Inputs!$K$5:$AJ$140,0,MATCH(Q$2,Inputs!$K$4:$AJ$4,0))))) -> 7541.3053 | R4: =SUM(N4:Q4) -> 26773.586 | S4: =IF(ISNA(MATCH(S$2,Inputs!$K$4:$AJ$4,0)),NA(),IF(SUMPRODUCT((Inputs!$A$5:$A$140=$B4)*ISNUMBER(INDEX(Inputs!$K$5:$AJ$140,0,MATCH(S$2,Inputs!$K$4:$AJ$4,0))))+SUMPRODUCT((Inputs!$C$5:$C$140=$B4)*ISNUMBER(INDEX(Inputs!$K$5:$AJ$140,0,MATCH(S$2,Inputs!$K$4:$AJ$4,0))))+SUMPRODUCT((Inputs!$E$5:$E$140=$B4)*ISNUMBER(INDEX(Inputs!$K$5:$AJ$140,0,MATCH(S$2,Inputs!$K$4:$AJ$4,0))))=0,NA(),SUMPRODUCT((Inputs!$A$5:$A$140=$B4)*Inputs!$B$5:$B$140*(((Inputs!$G$5:$G$140="moeda")+(Inputs!$G$5:$G$140="acoes"))*Inputs!$B$1+((Inputs!$G$5:$G$140<>"moeda")*(Inputs!$G$5:$G$140<>"acoes")))*INDEX(Inputs!$K$5:$AJ$140,0,MATCH(S$2,Inputs!$K$4:$AJ$4,0)))+SUMPRODUCT((Inputs!$C$5:$C$140=$B4)*Inputs!$D$5:$D$140*(((Inputs!$G$5:$G$140="moeda")+(Inputs!$G$5:$G$140="acoes"))*Inputs!$B$1+((Inputs!$G$5:$G$140<>"moeda")*(Inputs!$G$5:$G$140<>"acoes")))*INDEX(Inputs!$K$5:$AJ$140,0,MATCH(S$2,Inputs!$K$4:$AJ$4,0)))+SUMPRODUCT((Inputs!$E$5:$E$140=$B4)*Inputs!$F$5:$F$140*(((Inputs!$G$5:$G$140="moeda")+(Inputs!$G$5:$G$140="acoes"))*Inputs!$B$1+((Inputs!$G$5:$G$140<>"moeda")*(Inputs!$G$5:$G$140<>"acoes")))*INDEX(Inputs!$K$5:$AJ$140,0,MATCH(S$2,Inputs!$K$4:$AJ$4,0))))) -> 7382.4706 | T4: =IF(ISNA(MATCH(T$2,Inputs!$K$4:$AJ$4,0)),NA(),IF(SUMPRODUCT((Inputs!$A$5:$A$140=$B4)*ISNUMBER(INDEX(Inputs!$K$5:$AJ$140,0,MATCH(T$2,Inputs!$K$4:$AJ$4,0))))+SUMPRODUCT((Inputs!$C$5:$C$140=$B4)*ISNUMBER(INDEX(Inputs!$K$5:$AJ$140,0,MATCH(T$2,Inputs!$K$4:$AJ$4,0))))+SUMPRODUCT((Inputs!$E$5:$E$140=$B4)*ISNUMBER(INDEX(Inputs!$K$5:$AJ$140,0,MATCH(T$2,Inputs!$K$4:$AJ$4,0))))=0,NA(),SUMPRODUCT((Inputs!$A$5:$A$140=$B4)*Inputs!$B$5:$B$140*(((Inputs!$G$5:$G$140="moeda")+(Inputs!$G$5:$G$140="acoes"))*Inputs!$B$1+((Inputs!$G$5:$G$140<>"moeda")*(Inputs!$G$5:$G$140<>"acoes")))*INDEX(Inputs!$K$5:$AJ$140,0,MATCH(T$2,Inputs!$K$4:$AJ$4,0)))+SUMPRODUCT((Inputs!$C$5:$C$140=$B4)*Inputs!$D$5:$D$140*(((Inputs!$G$5:$G$140="moeda")+(Inputs!$G$5:$G$140="acoes"))*Inputs!$B$1+((Inputs!$G$5:$G$140<>"moeda")*(Inputs!$G$5:$G$140<>"acoes")))*INDEX(Inputs!$K$5:$AJ$140,0,MATCH(T$2,Inputs!$K$4:$AJ$4,0)))+SUMPRODUCT((Inputs!$E$5:$E$140=$B4)*Inputs!$F$5:$F$140*(((Inputs!$G$5:$G$140="moeda")+(Inputs!$G$5:$G$140="acoes"))*Inputs!$B$1+((Inputs!$G$5:$G$140<>"moeda")*(Inputs!$G$5:$G$140<>"acoes")))*INDEX(Inputs!$K$5:$AJ$140,0,MATCH(T$2,Inputs!$K$4:$AJ$4,0))))) -> 7638.9244 | U4: =IF(ISNA(MATCH(U$2,Inputs!$K$4:$AJ$4,0)),NA(),IF(SUMPRODUCT((Inputs!$A$5:$A$140=$B4)*ISNUMBER(INDEX(Inputs!$K$5:$AJ$140,0,MATCH(U$2,Inputs!$K$4:$AJ$4,0))))+SUMPRODUCT((Inputs!$C$5:$C$140=$B4)*ISNUMBER(INDEX(Inputs!$K$5:$AJ$140,0,MATCH(U$2,Inputs!$K$4:$AJ$4,0))))+SUMPRODUCT((Inputs!$E$5:$E$140=$B4)*ISNUMBER(INDEX(Inputs!$K$5:$AJ$140,0,MATCH(U$2,Inputs!$K$4:$AJ$4,0))))=0,NA(),SUMPRODUCT((Inputs!$A$5:$A$140=$B4)*Inputs!$B$5:$B$140*(((Inputs!$G$5:$G$140="moeda")+(Inputs!$G$5:$G$140="acoes"))*Inputs!$B$1+((Inputs!$G$5:$G$140<>"moeda")*(Inputs!$G$5:$G$140<>"acoes")))*INDEX(Inputs!$K$5:$AJ$140,0,MATCH(U$2,Inputs!$K$4:$AJ$4,0)))+SUMPRODUCT((Inputs!$C$5:$C$140=$B4)*Inputs!$D$5:$D$140*(((Inputs!$G$5:$G$140="moeda")+(Inputs!$G$5:$G$140="acoes"))*Inputs!$B$1+((Inputs!$G$5:$G$140<>"moeda")*(Inputs!$G$5:$G$140<>"acoes")))*INDEX(Inputs!$K$5:$AJ$140,0,MATCH(U$2,Inputs!$K$4:$AJ$4,0)))+SUMPRODUCT((Inputs!$E$5:$E$140=$B4)*Inputs!$F$5:$F$140*(((Inputs!$G$5:$G$140="moeda")+(Inputs!$G$5:$G$140="acoes"))*Inputs!$B$1+((Inputs!$G$5:$G$140<>"moeda")*(Inputs!$G$5:$G$140<>"acoes")))*INDEX(Inputs!$K$5:$AJ$140,0,MATCH(U$2,Inputs!$K$4:$AJ$4,0))))) -> 8337.057 | V4: =IF(ISNA(MATCH(V$2,Inputs!$K$4:$AJ$4,0)),NA(),IF(SUMPRODUCT((Inputs!$A$5:$A$140=$B4)*ISNUMBER(INDEX(Inputs!$K$5:$AJ$140,0,MATCH(V$2,Inputs!$K$4:$AJ$4,0))))+SUMPRODUCT((Inputs!$C$5:$C$140=$B4)*ISNUMBER(INDEX(Inputs!$K$5:$AJ$140,0,MATCH(V$2,Inputs!$K$4:$AJ$4,0))))+SUMPRODUCT((Inputs!$E$5:$E$140=$B4)*ISNUMBER(INDEX(Inputs!$K$5:$AJ$140,0,MATCH(V$2,Inputs!$K$4:$AJ$4,0))))=0,NA(),SUMPRODUCT((Inputs!$A$5:$A$140=$B4)*Inputs!$B$5:$B$140*(((Inputs!$G$5:$G$140="moeda")+(Inputs!$G$5:$G$140="acoes"))*Inputs!$B$1+((Inputs!$G$5:$G$140<>"moeda")*(Inputs!$G$5:$G$140<>"acoes")))*INDEX(Inputs!$K$5:$AJ$140,0,MATCH(V$2,Inputs!$K$4:$AJ$4,0)))+SUMPRODUCT((Inputs!$C$5:$C$140=$B4)*Inputs!$D$5:$D$140*(((Inputs!$G$5:$G$140="moeda")+(Inputs!$G$5:$G$140="acoes"))*Inputs!$B$1+((Inputs!$G$5:$G$140<>"moeda")*(Inputs!$G$5:$G$140<>"acoes")))*INDEX(Inputs!$K$5:$AJ$140,0,MATCH(V$2,Inputs!$K$4:$AJ$4,0)))+SUMPRODUCT((Inputs!$E$5:$E$140=$B4)*Inputs!$F$5:$F$140*(((Inputs!$G$5:$G$140="moeda")+(Inputs!$G$5:$G$140="acoes"))*Inputs!$B$1+((Inputs!$G$5:$G$140<>"moeda")*(Inputs!$G$5:$G$140<>"acoes")))*INDEX(Inputs!$K$5:$AJ$140,0,MATCH(V$2,Inputs!$K$4:$AJ$4,0))))) -> 8726.977 | W4: =SUM(S4:V4) -> 32085.429 | X4: =IF(ISNA(MATCH(X$2,Inputs!$K$4:$AJ$4,0)),NA(),IF(SUMPRODUCT((Inputs!$A$5:$A$140=$B4)*ISNUMBER(INDEX(Inputs!$K$5:$AJ$140,0,MATCH(X$2,Inputs!$K$4:$AJ$4,0))))+SUMPRODUCT((Inputs!$C$5:$C$140=$B4)*ISNUMBER(INDEX(Inputs!$K$5:$AJ$140,0,MATCH(X$2,Inputs!$K$4:$AJ$4,0))))+SUMPRODUCT((Inputs!$E$5:$E$140=$B4)*ISNUMBER(INDEX(Inputs!$K$5:$AJ$140,0,MATCH(X$2,Inputs!$K$4:$AJ$4,0))))=0,NA(),SUMPRODUCT((Inputs!$A$5:$A$140=$B4)*Inputs!$B$5:$B$140*(((Inputs!$G$5:$G$140="moeda")+(Inputs!$G$5:$G$140="acoes"))*Inputs!$B$1+((Inputs!$G$5:$G$140<>"moeda")*(Inputs!$G$5:$G$140<>"acoes")))*INDEX(Inputs!$K$5:$AJ$140,0,MATCH(X$2,Inputs!$K$4:$AJ$4,0)))+SUMPRODUCT((Inputs!$C$5:$C$140=$B4)*Inputs!$D$5:$D$140*(((Inputs!$G$5:$G$140="moeda")+(Inputs!$G$5:$G$140="acoes"))*Inputs!$B$1+((Inputs!$G$5:$G$140<>"moeda")*(Inputs!$G$5:$G$140<>"acoes")))*INDEX(Inputs!$K$5:$AJ$140,0,MATCH(X$2,Inputs!$K$4:$AJ$4,0)))+SUMPRODUCT((Inputs!$E$5:$E$140=$B4)*Inputs!$F$5:$F$140*(((Inputs!$G$5:$G$140="moeda")+(Inputs!$G$5:$G$140="acoes"))*Inputs!$B$1+((Inputs!$G$5:$G$140<>"moeda")*(Inputs!$G$5:$G$140<>"acoes")))*INDEX(Inputs!$K$5:$AJ$140,0,MATCH(X$2,Inputs!$K$4:$AJ$4,0))))) -> 8331.305 | Y4: =IF(ISNA(MATCH(Y$2,Inputs!$K$4:$AJ$4,0)),NA(),IF(SUMPRODUCT((Inputs!$A$5:$A$140=$B4)*ISNUMBER(INDEX(Inputs!$K$5:$AJ$140,0,MATCH(Y$2,Inputs!$K$4:$AJ$4,0))))+SUMPRODUCT((Inputs!$C$5:$C$140=$B4)*ISNUMBER(INDEX(Inputs!$K$5:$AJ$140,0,MATCH(Y$2,Inputs!$K$4:$AJ$4,0))))+SUMPRODUCT((Inputs!$E$5:$E$140=$B4)*ISNUMBER(INDEX(Inputs!$K$5:$AJ$140,0,MATCH(Y$2,Inputs!$K$4:$AJ$4,0))))=0,NA(),SUMPRODUCT((Inputs!$A$5:$A$140=$B4)*Inputs!$B$5:$B$140*(((Inputs!$G$5:$G$140="moeda")+(Inputs!$G$5:$G$140="acoes"))*Inputs!$B$1+((Inputs!$G$5:$G$140<>"moeda")*(Inputs!$G$5:$G$140<>"acoes")))*INDEX(Inputs!$K$5:$AJ$140,0,MATCH(Y$2,Inputs!$K$4:$AJ$4,0)))+SUMPRODUCT((Inputs!$C$5:$C$140=$B4)*Inputs!$D$5:$D$140*(((Inputs!$G$5:$G$140="moeda")+(Inputs!$G$5:$G$140="acoes"))*Inputs!$B$1+((Inputs!$G$5:$G$140<>"moeda")*(Inputs!$G$5:$G$140<>"acoes")))*INDEX(Inputs!$K$5:$AJ$140,0,MATCH(Y$2,Inputs!$K$4:$AJ$4,0)))+SUMPRODUCT((Inputs!$E$5:$E$140=$B4)*Inputs!$F$5:$F$140*(((Inputs!$G$5:$G$140="moeda")+(Inputs!$G$5:$G$140="acoes"))*Inputs!$B$1+((Inputs!$G$5:$G$140<>"moeda")*(Inputs!$G$5:$G$140<>"acoes")))*INDEX(Inputs!$K$5:$AJ$140,0,MATCH(Y$2,Inputs!$K$4:$AJ$4,0))))) -> 8779.6364 | Z4: =IF(ISNA(MATCH(Z$2,Inputs!$K$4:$AJ$4,0)),NA(),IF(SUMPRODUCT((Inputs!$A$5:$A$140=$B4)*ISNUMBER(INDEX(Inputs!$K$5:$AJ$140,0,MATCH(Z$2,Inputs!$K$4:$AJ$4,0))))+SUMPRODUCT((Inputs!$C$5:$C$140=$B4)*ISNUMBER(INDEX(Inputs!$K$5:$AJ$140,0,MATCH(Z$2,Inputs!$K$4:$AJ$4,0))))+SUMPRODUCT((Inputs!$E$5:$E$140=$B4)*ISNUMBER(INDEX(Inputs!$K$5:$AJ$140,0,MATCH(Z$2,Inputs!$K$4:$AJ$4,0))))=0,NA(),SUMPRODUCT((Inputs!$A$5:$A$140=$B4)*Inputs!$B$5:$B$140*(((Inputs!$G$5:$G$140="moeda")+(Inputs!$G$5:$G$140="acoes"))*Inputs!$B$1+((Inputs!$G$5:$G$140<>"moeda")*(Inputs!$G$5:$G$140<>"acoes")))*INDEX(Inputs!$K$5:$AJ$140,0,MATCH(Z$2,Inputs!$K$4:$AJ$4,0)))+SUMPRODUCT((Inputs!$C$5:$C$140=$B4)*Inputs!$D$5:$D$140*(((Inputs!$G$5:$G$140="moeda")+(Inputs!$G$5:$G$140="acoes"))*Inputs!$B$1+((Inputs!$G$5:$G$140<>"moeda")*(Inputs!$G$5:$G$140<>"acoes")))*INDEX(Inputs!$K$5:$AJ$140,0,MATCH(Z$2,Inputs!$K$4:$AJ$4,0)))+SUMPRODUCT((Inputs!$E$5:$E$140=$B4)*Inputs!$F$5:$F$140*(((Inputs!$G$5:$G$140="moeda")+(Inputs!$G$5:$G$140="acoes"))*Inputs!$B$1+((Inputs!$G$5:$G$140<>"moeda")*(Inputs!$G$5:$G$140<>"acoes")))*INDEX(Inputs!$K$5:$AJ$140,0,MATCH(Z$2,Inputs!$K$4:$AJ$4,0))))) -> 10763.538 | AA4: =IF(ISNA(MATCH(AA$2,Inputs!$K$4:$AJ$4,0)),NA(),IF(SUMPRODUCT((Inputs!$A$5:$A$140=$B4)*ISNUMBER(INDEX(Inputs!$K$5:$AJ$140,0,MATCH(AA$2,Inputs!$K$4:$AJ$4,0))))+SUMPRODUCT((Inputs!$C$5:$C$140=$B4)*ISNUMBER(INDEX(Inputs!$K$5:$AJ$140,0,MATCH(AA$2,Inputs!$K$4:$AJ$4,0))))+SUMPRODUCT((Inputs!$E$5:$E$140=$B4)*ISNUMBER(INDEX(Inputs!$K$5:$AJ$140,0,MATCH(AA$2,Inputs!$K$4:$AJ$4,0))))=0,NA(),SUMPRODUCT((Inputs!$A$5:$A$140=$B4)*Inputs!$B$5:$B$140*(((Inputs!$G$5:$G$140="moeda")+(Inputs!$G$5:$G$140="acoes"))*Inputs!$B$1+((Inputs!$G$5:$G$140<>"moeda")*(Inputs!$G$5:$G$140<>"acoes")))*INDEX(Inputs!$K$5:$AJ$140,0,MATCH(AA$2,Inputs!$K$4:$AJ$4,0)))+SUMPRODUCT((Inputs!$C$5:$C$140=$B4)*Inputs!$D$5:$D$140*(((Inputs!$G$5:$G$140="moeda")+(Inputs!$G$5:$G$140="acoes"))*Inputs!$B$1+((Inputs!$G$5:$G$140<>"moeda")*(Inputs!$G$5:$G$140<>"acoes")))*INDEX(Inputs!$K$5:$AJ$140,0,MATCH(AA$2,Inputs!$K$4:$AJ$4,0)))+SUMPRODUCT((Inputs!$E$5:$E$140=$B4)*Inputs!$F$5:$F$140*(((Inputs!$G$5:$G$140="moeda")+(Inputs!$G$5:$G$140="acoes"))*Inputs!$B$1+((Inputs!$G$5:$G$140<>"moeda")*(Inputs!$G$5:$G$140<>"acoes")))*INDEX(Inputs!$K$5:$AJ$140,0,MATCH(AA$2,Inputs!$K$4:$AJ$4,0))))) -> 10549.923 | AB4: =SUM(X4:AA4) -> 38424.402 | AC4: =IF(ISNA(MATCH(AC$2,Inputs!$K$4:$AJ$4,0)),NA(),IF(SUMPRODUCT((Inputs!$A$5:$A$140=$B4)*ISNUMBER(INDEX(Inputs!$K$5:$AJ$140,0,MATCH(AC$2,Inputs!$K$4:$AJ$4,0))))+SUMPRODUCT((Inputs!$C$5:$C$140=$B4)*ISNUMBER(INDEX(Inputs!$K$5:$AJ$140,0,MATCH(AC$2,Inputs!$K$4:$AJ$4,0))))+SUMPRODUCT((Inputs!$E$5:$E$140=$B4)*ISNUMBER(INDEX(Inputs!$K$5:$AJ$140,0,MATCH(AC$2,Inputs!$K$4:$AJ$4,0))))=0,NA(),SUMPRODUCT((Inputs!$A$5:$A$140=$B4)*Inputs!$B$5:$B$140*(((Inputs!$G$5:$G$140="moeda")+(Inputs!$G$5:$G$140="acoes"))*Inputs!$B$1+((Inputs!$G$5:$G$140<>"moeda")*(Inputs!$G$5:$G$140<>"acoes")))*INDEX(Inputs!$K$5:$AJ$140,0,MATCH(AC$2,Inputs!$K$4:$AJ$4,0)))+SUMPRODUCT((Inputs!$C$5:$C$140=$B4)*Inputs!$D$5:$D$140*(((Inputs!$G$5:$G$140="moeda")+(Inputs!$G$5:$G$140="acoes"))*Inputs!$B$1+((Inputs!$G$5:$G$140<>"moeda")*(Inputs!$G$5:$G$140<>"acoes")))*INDEX(Inputs!$K$5:$AJ$140,0,MATCH(AC$2,Inputs!$K$4:$AJ$4,0)))+SUMPRODUCT((Inputs!$E$5:$E$140=$B4)*Inputs!$F$5:$F$140*(((Inputs!$G$5:$G$140="moeda")+(Inputs!$G$5:$G$140="acoes"))*Inputs!$B$1+((Inputs!$G$5:$G$140<>"moeda")*(Inputs!$G$5:$G$140<>"acoes")))*INDEX(Inputs!$K$5:$AJ$140,0,MATCH(AC$2,Inputs!$K$4:$AJ$4,0))))) -> 9402.27 | AD4: =IF(ISNA(MATCH(AD$2,Inputs!$K$4:$AJ$4,0)),NA(),IF(SUMPRODUCT((Inputs!$A$5:$A$140=$B4)*ISNUMBER(INDEX(Inputs!$K$5:$AJ$140,0,MATCH(AD$2,Inputs!$K$4:$AJ$4,0))))+SUMPRODUCT((Inputs!$C$5:$C$140=$B4)*ISNUMBER(INDEX(Inputs!$K$5:$AJ$140,0,MATCH(AD$2,Inputs!$K$4:$AJ$4,0))))+SUMPRODUCT((Inputs!$E$5:$E$140=$B4)*ISNUMBER(INDEX(Inputs!$K$5:$AJ$140,0,MATCH(AD$2,Inputs!$K$4:$AJ$4,0))))=0,NA(),SUMPRODUCT((Inputs!$A$5:$A$140=$B4)*Inputs!$B$5:$B$140*(((Inputs!$G$5:$G$140="moeda")+(Inputs!$G$5:$G$140="acoes"))*Inputs!$B$1+((Inputs!$G$5:$G$140<>"moeda")*(Inputs!$G$5:$G$140<>"acoes")))*INDEX(Inputs!$K$5:$AJ$140,0,MATCH(AD$2,Inputs!$K$4:$AJ$4,0)))+SUMPRODUCT((Inputs!$C$5:$C$140=$B4)*Inputs!$D$5:$D$140*(((Inputs!$G$5:$G$140="moeda")+(Inputs!$G$5:$G$140="acoes"))*Inputs!$B$1+((Inputs!$G$5:$G$140<>"moeda")*(Inputs!$G$5:$G$140<>"acoes")))*INDEX(Inputs!$K$5:$AJ$140,0,MATCH(AD$2,Inputs!$K$4:$AJ$4,0)))+SUMPRODUCT((Inputs!$E$5:$E$140=$B4)*Inputs!$F$5:$F$140*(((Inputs!$G$5:$G$140="moeda")+(Inputs!$G$5:$G$140="acoes"))*Inputs!$B$1+((Inputs!$G$5:$G$140<>"moeda")*(Inputs!$G$5:$G$140<>"acoes")))*INDEX(Inputs!$K$5:$AJ$140,0,MATCH(AD$2,Inputs!$K$4:$AJ$4,0))))) -> 9852.461 | AE4: =IF(ISNA(MATCH(AE$2,Inputs!$K$4:$AJ$4,0)),NA(),IF(SUMPRODUCT((Inputs!$A$5:$A$140=$B4)*ISNUMBER(INDEX(Inputs!$K$5:$AJ$140,0,MATCH(AE$2,Inputs!$K$4:$AJ$4,0))))+SUMPRODUCT((Inputs!$C$5:$C$140=$B4)*ISNUMBER(INDEX(Inputs!$K$5:$AJ$140,0,MATCH(AE$2,Inputs!$K$4:$AJ$4,0))))+SUMPRODUCT((Inputs!$E$5:$E$140=$B4)*ISNUMBER(INDEX(Inputs!$K$5:$AJ$140,0,MATCH(AE$2,Inputs!$K$4:$AJ$4,0))))=0,NA(),SUMPRODUCT((Inputs!$A$5:$A$140=$B4)*Inputs!$B$5:$B$140*(((Inputs!$G$5:$G$140="moeda")+(Inputs!$G$5:$G$140="acoes"))*Inputs!$B$1+((Inputs!$G$5:$G$140<>"moeda")*(Inputs!$G$5:$G$140<>"acoes")))*INDEX(Inputs!$K$5:$AJ$140,0,MATCH(AE$2,Inputs!$K$4:$AJ$4,0)))+SUMPRODUCT((Inputs!$C$5:$C$140=$B4)*Inputs!$D$5:$D$140*(((Inputs!$G$5:$G$140="moeda")+(Inputs!$G$5:$G$140="acoes"))*Inputs!$B$1+((Inputs!$G$5:$G$140<>"moeda")*(Inputs!$G$5:$G$140<>"acoes")))*INDEX(Inputs!$K$5:$AJ$140,0,MATCH(AE$2,Inputs!$K$4:$AJ$4,0)))+SUMPRODUCT((Inputs!$E$5:$E$140=$B4)*Inputs!$F$5:$F$140*(((Inputs!$G$5:$G$140="moeda")+(Inputs!$G$5:$G$140="acoes"))*Inputs!$B$1+((Inputs!$G$5:$G$140<>"moeda")*(Inputs!$G$5:$G$140<>"acoes")))*INDEX(Inputs!$K$5:$AJ$140,0,MATCH(AE$2,Inputs!$K$4:$AJ$4,0))))) -> #N/A | AF4: =IF(ISNA(MATCH(AF$2,Inputs!$K$4:$AJ$4,0)),NA(),IF(SUMPRODUCT((Inputs!$A$5:$A$140=$B4)*ISNUMBER(INDEX(Inputs!$K$5:$AJ$140,0,MATCH(AF$2,Inputs!$K$4:$AJ$4,0))))+SUMPRODUCT((Inputs!$C$5:$C$140=$B4)*ISNUMBER(INDEX(Inputs!$K$5:$AJ$140,0,MATCH(AF$2,Inputs!$K$4:$AJ$4,0))))+SUMPRODUCT((Inputs!$E$5:$E$140=$B4)*ISNUMBER(INDEX(Inputs!$K$5:$AJ$140,0,MATCH(AF$2,Inputs!$K$4:$AJ$4,0))))=0,NA(),SUMPRODUCT((Inputs!$A$5:$A$140=$B4)*Inputs!$B$5:$B$140*(((Inputs!$G$5:$G$140="moeda")+(Inputs!$G$5:$G$140="acoes"))*Inputs!$B$1+((Inputs!$G$5:$G$140<>"moeda")*(Inputs!$G$5:$G$140<>"acoes")))*INDEX(Inputs!$K$5:$AJ$140,0,MATCH(AF$2,Inputs!$K$4:$AJ$4,0)))+SUMPRODUCT((Inputs!$C$5:$C$140=$B4)*Inputs!$D$5:$D$140*(((Inputs!$G$5:$G$140="moeda")+(Inputs!$G$5:$G$140="acoes"))*Inputs!$B$1+((Inputs!$G$5:$G$140<>"moeda")*(Inputs!$G$5:$G$140<>"acoes")))*INDEX(Inputs!$K$5:$AJ$140,0,MATCH(AF$2,Inputs!$K$4:$AJ$4,0)))+SUMPRODUCT((Inputs!$E$5:$E$140=$B4)*Inputs!$F$5:$F$140*(((Inputs!$G$5:$G$140="moeda")+(Inputs!$G$5:$G$140="acoes"))*Inputs!$B$1+((Inputs!$G$5:$G$140<>"moeda")*(Inputs!$G$5:$G$140<>"acoes")))*INDEX(Inputs!$K$5:$AJ$140,0,MATCH(AF$2,Inputs!$K$4:$AJ$4,0))))) -> #N/A | AG4: =SUM(AC4:AF4) -> #N/A | AH4: =IF(ISNA(MATCH(AH$2,Inputs!$K$4:$AJ$4,0)),NA(),IF(SUMPRODUCT((Inputs!$A$5:$A$140=$B4)*ISNUMBER(INDEX(Inputs!$K$5:$AJ$140,0,MATCH(AH$2,Inputs!$K$4:$AJ$4,0))))+SUMPRODUCT((Inputs!$C$5:$C$140=$B4)*ISNUMBER(INDEX(Inputs!$K$5:$AJ$140,0,MATCH(AH$2,Inputs!$K$4:$AJ$4,0))))+SUMPRODUCT((Inputs!$E$5:$E$140=$B4)*ISNUMBER(INDEX(Inputs!$K$5:$AJ$140,0,MATCH(AH$2,Inputs!$K$4:$AJ$4,0))))=0,NA(),SUMPRODUCT((Inputs!$A$5:$A$140=$B4)*Inputs!$B$5:$B$140*(((Inputs!$G$5:$G$140="moeda")+(Inputs!$G$5:$G$140="acoes"))*Inputs!$B$1+((Inputs!$G$5:$G$140<>"moeda")*(Inputs!$G$5:$G$140<>"acoes")))*INDEX(Inputs!$K$5:$AJ$140,0,MATCH(AH$2,Inputs!$K$4:$AJ$4,0)))+SUMPRODUCT((Inputs!$C$5:$C$140=$B4)*Inputs!$D$5:$D$140*(((Inputs!$G$5:$G$140="moeda")+(Inputs!$G$5:$G$140="acoes"))*Inputs!$B$1+((Inputs!$G$5:$G$140<>"moeda")*(Inputs!$G$5:$G$140<>"acoes")))*INDEX(Inputs!$K$5:$AJ$140,0,MATCH(AH$2,Inputs!$K$4:$AJ$4,0)))+SUMPRODUCT((Inputs!$E$5:$E$140=$B4)*Inputs!$F$5:$F$140*(((Inputs!$G$5:$G$140="moeda")+(Inputs!$G$5:$G$140="acoes"))*Inputs!$B$1+((Inputs!$G$5:$G$140<>"moeda")*(Inputs!$G$5:$G$140<>"acoes")))*INDEX(Inputs!$K$5:$AJ$140,0,MATCH(AH$2,Inputs!$K$4:$AJ$4,0))))) -> 2409.2844 | AI4: =IF(ISNA(MATCH(AI$2,Inputs!$K$4:$AJ$4,0)),NA(),IF(SUMPRODUCT((Inputs!$A$5:$A$140=$B4)*ISNUMBER(INDEX(Inputs!$K$5:$AJ$140,0,MATCH(AI$2,Inputs!$K$4:$AJ$4,0))))+SUMPRODUCT((Inputs!$C$5:$C$140=$B4)*ISNUMBER(INDEX(Inputs!$K$5:$AJ$140,0,MATCH(AI$2,Inputs!$K$4:$AJ$4,0))))+SUMPRODUCT((Inputs!$E$5:$E$140=$B4)*ISNUMBER(INDEX(Inputs!$K$5:$AJ$140,0,MATCH(AI$2,Inputs!$K$4:$AJ$4,0))))=0,NA(),SUMPRODUCT((Inputs!$A$5:$A$140=$B4)*Inputs!$B$5:$B$140*(((Inputs!$G$5:$G$140="moeda")+(Inputs!$G$5:$G$140="acoes"))*Inputs!$B$1+((Inputs!$G$5:$G$140<>"moeda")*(Inputs!$G$5:$G$140<>"acoes")))*INDEX(Inputs!$K$5:$AJ$140,0,MATCH(AI$2,Inputs!$K$4:$AJ$4,0)))+SUMPRODUCT((Inputs!$C$5:$C$140=$B4)*Inputs!$D$5:$D$140*(((Inputs!$G$5:$G$140="moeda")+(Inputs!$G$5:$G$140="acoes"))*Inputs!$B$1+((Inputs!$G$5:$G$140<>"moeda")*(Inputs!$G$5:$G$140<>"acoes")))*INDEX(Inputs!$K$5:$AJ$140,0,MATCH(AI$2,Inputs!$K$4:$AJ$4,0)))+SUMPRODUCT((Inputs!$E$5:$E$140=$B4)*Inputs!$F$5:$F$140*(((Inputs!$G$5:$G$140="moeda")+(Inputs!$G$5:$G$140="acoes"))*Inputs!$B$1+((Inputs!$G$5:$G$140<>"moeda")*(Inputs!$G$5:$G$140<>"acoes")))*INDEX(Inputs!$K$5:$AJ$140,0,MATCH(AI$2,Inputs!$K$4:$AJ$4,0))))) -> 2889.0033 | AJ4: =IF(ISNA(MATCH(AJ$2,Inputs!$K$4:$AJ$4,0)),NA(),IF(SUMPRODUCT((Inputs!$A$5:$A$140=$B4)*ISNUMBER(INDEX(Inputs!$K$5:$AJ$140,0,MATCH(AJ$2,Inputs!$K$4:$AJ$4,0))))+SUMPRODUCT((Inputs!$C$5:$C$140=$B4)*ISNUMBER(INDEX(Inputs!$K$5:$AJ$140,0,MATCH(AJ$2,Inputs!$K$4:$AJ$4,0))))+SUMPRODUCT((Inputs!$E$5:$E$140=$B4)*ISNUMBER(INDEX(Inputs!$K$5:$AJ$140,0,MATCH(AJ$2,Inputs!$K$4:$AJ$4,0))))=0,NA(),SUMPRODUCT((Inputs!$A$5:$A$140=$B4)*Inputs!$B$5:$B$140*(((Inputs!$G$5:$G$140="moeda")+(Inputs!$G$5:$G$140="acoes"))*Inputs!$B$1+((Inputs!$G$5:$G$140<>"moeda")*(Inputs!$G$5:$G$140<>"acoes")))*INDEX(Inputs!$K$5:$AJ$140,0,MATCH(AJ$2,Inputs!$K$4:$AJ$4,0)))+SUMPRODUCT((Inputs!$C$5:$C$140=$B4)*Inputs!$D$5:$D$140*(((Inputs!$G$5:$G$140="moeda")+(Inputs!$G$5:$G$140="acoes"))*Inputs!$B$1+((Inputs!$G$5:$G$140<>"moeda")*(Inputs!$G$5:$G$140<>"acoes")))*INDEX(Inputs!$K$5:$AJ$140,0,MATCH(AJ$2,Inputs!$K$4:$AJ$4,0)))+SUMPRODUCT((Inputs!$E$5:$E$140=$B4)*Inputs!$F$5:$F$140*(((Inputs!$G$5:$G$140="moeda")+(Inputs!$G$5:$G$140="acoes"))*Inputs!$B$1+((Inputs!$G$5:$G$140<>"moeda")*(Inputs!$G$5:$G$140<>"acoes")))*INDEX(Inputs!$K$5:$AJ$140,0,MATCH(AJ$2,Inputs!$K$4:$AJ$4,0))))) -> 3463.4542 | AK4: =IF(ISNA(MATCH(AK$2,Inputs!$K$4:$AJ$4,0)),NA(),IF(SUMPRODUCT((Inputs!$A$5:$A$140=$B4)*ISNUMBER(INDEX(Inputs!$K$5:$AJ$140,0,MATCH(AK$2,Inputs!$K$4:$AJ$4,0))))+SUMPRODUCT((Inputs!$C$5:$C$140=$B4)*ISNUMBER(INDEX(Inputs!$K$5:$AJ$140,0,MATCH(AK$2,Inputs!$K$4:$AJ$4,0))))+SUMPRODUCT((Inputs!$E$5:$E$140=$B4)*ISNUMBER(INDEX(Inputs!$K$5:$AJ$140,0,MATCH(AK$2,Inputs!$K$4:$AJ$4,0))))=0,NA(),SUMPRODUCT((Inputs!$A$5:$A$140=$B4)*Inputs!$B$5:$B$140*(((Inputs!$G$5:$G$140="moeda")+(Inputs!$G$5:$G$140="acoes"))*Inputs!$B$1+((Inputs!$G$5:$G$140<>"moeda")*(Inputs!$G$5:$G$140<>"acoes")))*INDEX(Inputs!$K$5:$AJ$140,0,MATCH(AK$2,Inputs!$K$4:$AJ$4,0)))+SUMPRODUCT((Inputs!$C$5:$C$140=$B4)*Inputs!$D$5:$D$140*(((Inputs!$G$5:$G$140="moeda")+(Inputs!$G$5:$G$140="acoes"))*Inputs!$B$1+((Inputs!$G$5:$G$140<>"moeda")*(Inputs!$G$5:$G$140<>"acoes")))*INDEX(Inputs!$K$5:$AJ$140,0,MATCH(AK$2,Inputs!$K$4:$AJ$4,0)))+SUMPRODUCT((Inputs!$E$5:$E$140=$B4)*Inputs!$F$5:$F$140*(((Inputs!$G$5:$G$140="moeda")+(Inputs!$G$5:$G$140="acoes"))*Inputs!$B$1+((Inputs!$G$5:$G$140<>"moeda")*(Inputs!$G$5:$G$140<>"acoes")))*INDEX(Inputs!$K$5:$AJ$140,0,MATCH(AK$2,Inputs!$K$4:$AJ$4,0))))) -> 3635.2959 | AL4: =SUM(AH4:AK4) -> 12397.038
B5: 2 | C5: COGS (cash) | D5: =IF(ISNA(MATCH(D$2,Inputs!$K$4:$AJ$4,0)),NA(),IF(SUMPRODUCT((Inputs!$A$5:$A$140=$B5)*ISNUMBER(INDEX(Inputs!$K$5:$AJ$140,0,MATCH(D$2,Inputs!$K$4:$AJ$4,0))))+SUMPRODUCT((Inputs!$C$5:$C$140=$B5)*ISNUMBER(INDEX(Inputs!$K$5:$AJ$140,0,MATCH(D$2,Inputs!$K$4:$AJ$4,0))))+SUMPRODUCT((Inputs!$E$5:$E$140=$B5)*ISNUMBER(INDEX(Inputs!$K$5:$AJ$140,0,MATCH(D$2,Inputs!$K$4:$AJ$4,0))))=0,NA(),SUMPRODUCT((Inputs!$A$5:$A$140=$B5)*Inputs!$B$5:$B$140*(((Inputs!$G$5:$G$140="moeda")+(Inputs!$G$5:$G$140="acoes"))*Inputs!$B$1+((Inputs!$G$5:$G$140<>"moeda")*(Inputs!$G$5:$G$140<>"acoes")))*INDEX(Inputs!$K$5:$AJ$140,0,MATCH(D$2,Inputs!$K$4:$AJ$4,0)))+SUMPRODUCT((Inputs!$C$5:$C$140=$B5)*Inputs!$D$5:$D$140*(((Inputs!$G$5:$G$140="moeda")+(Inputs!$G$5:$G$140="acoes"))*Inputs!$B$1+((Inputs!$G$5:$G$140<>"moeda")*(Inputs!$G$5:$G$140<>"acoes")))*INDEX(Inputs!$K$5:$AJ$140,0,MATCH(D$2,Inputs!$K$4:$AJ$4,0)))+SUMPRODUCT((Inputs!$E$5:$E$140=$B5)*Inputs!$F$5:$F$140*(((Inputs!$G$5:$G$140="moeda")+(Inputs!$G$5:$G$140="acoes"))*Inputs!$B$1+((Inputs!$G$5:$G$140<>"moeda")*(Inputs!$G$5:$G$140<>"acoes")))*INDEX(Inputs!$K$5:$AJ$140,0,MATCH(D$2,Inputs!$K$4:$AJ$4,0))))) -> -2560.1941 | E5: =IF(ISNA(MATCH(E$2,Inputs!$K$4:$AJ$4,0)),NA(),IF(SUMPRODUCT((Inputs!$A$5:$A$140=$B5)*ISNUMBER(INDEX(Inputs!$K$5:$AJ$140,0,MATCH(E$2,Inputs!$K$4:$AJ$4,0))))+SUMPRODUCT((Inputs!$C$5:$C$140=$B5)*ISNUMBER(INDEX(Inputs!$K$5:$AJ$140,0,MATCH(E$2,Inputs!$K$4:$AJ$4,0))))+SUMPRODUCT((Inputs!$E$5:$E$140=$B5)*ISNUMBER(INDEX(Inputs!$K$5:$AJ$140,0,MATCH(E$2,Inputs!$K$4:$AJ$4,0))))=0,NA(),SUMPRODUCT((Inputs!$A$5:$A$140=$B5)*Inputs!$B$5:$B$140*(((Inputs!$G$5:$G$140="moeda")+(Inputs!$G$5:$G$140="acoes"))*Inputs!$B$1+((Inputs!$G$5:$G$140<>"moeda")*(Inputs!$G$5:$G$140<>"acoes")))*INDEX(Inputs!$K$5:$AJ$140,0,MATCH(E$2,Inputs!$K$4:$AJ$4,0)))+SUMPRODUCT((Inputs!$C$5:$C$140=$B5)*Inputs!$D$5:$D$140*(((Inputs!$G$5:$G$140="moeda")+(Inputs!$G$5:$G$140="acoes"))*Inputs!$B$1+((Inputs!$G$5:$G$140<>"moeda")*(Inputs!$G$5:$G$140<>"acoes")))*INDEX(Inputs!$K$5:$AJ$140,0,MATCH(E$2,Inputs!$K$4:$AJ$4,0)))+SUMPRODUCT((Inputs!$E$5:$E$140=$B5)*Inputs!$F$5:$F$140*(((Inputs!$G$5:$G$140="moeda")+(Inputs!$G$5:$G$140="acoes"))*Inputs!$B$1+((Inputs!$G$5:$G$140<>"moeda")*(Inputs!$G$5:$G$140<>"acoes")))*INDEX(Inputs!$K$5:$AJ$140,0,MATCH(E$2,Inputs!$K$4:$AJ$4,0))))) -> -2861.6923 | F5: =IF(ISNA(MATCH(F$2,Inputs!$K$4:$AJ$4,0)),NA(),IF(SUMPRODUCT((Inputs!$A$5:$A$140=$B5)*ISNUMBER(INDEX(Inputs!$K$5:$AJ$140,0,MATCH(F$2,Inputs!$K$4:$AJ$4,0))))+SUMPRODUCT((Inputs!$C$5:$C$140=$B5)*ISNUMBER(INDEX(Inputs!$K$5:$AJ$140,0,MATCH(F$2,Inputs!$K$4:$AJ$4,0))))+SUMPRODUCT((Inputs!$E$5:$E$140=$B5)*ISNUMBER(INDEX(Inputs!$K$5:$AJ$140,0,MATCH(F$2,Inputs!$K$4:$AJ$4,0))))=0,NA(),SUMPRODUCT((Inputs!$A$5:$A$140=$B5)*Inputs!$B$5:$B$140*(((Inputs!$G$5:$G$140="moeda")+(Inputs!$G$5:$G$140="acoes"))*Inputs!$B$1+((Inputs!$G$5:$G$140<>"moeda")*(Inputs!$G$5:$G$140<>"acoes")))*INDEX(Inputs!$K$5:$AJ$140,0,MATCH(F$2,Inputs!$K$4:$AJ$4,0)))+SUMPRODUCT((Inputs!$C$5:$C$140=$B5)*Inputs!$D$5:$D$140*(((Inputs!$G$5:$G$140="moeda")+(Inputs!$G$5:$G$140="acoes"))*Inputs!$B$1+((Inputs!$G$5:$G$140<>"moeda")*(Inputs!$G$5:$G$140<>"acoes")))*INDEX(Inputs!$K$5:$AJ$140,0,MATCH(F$2,Inputs!$K$4:$AJ$4,0)))+SUMPRODUCT((Inputs!$E$5:$E$140=$B5)*Inputs!$F$5:$F$140*(((Inputs!$G$5:$G$140="moeda")+(Inputs!$G$5:$G$140="acoes"))*Inputs!$B$1+((Inputs!$G$5:$G$140<>"moeda")*(Inputs!$G$5:$G$140<>"acoes")))*INDEX(Inputs!$K$5:$AJ$140,0,MATCH(F$2,Inputs!$K$4:$AJ$4,0))))) -> -3311.219 | G5: =IF(ISNA(MATCH(G$2,Inputs!$K$4:$AJ$4,0)),NA(),IF(SUMPRODUCT((Inputs!$A$5:$A$140=$B5)*ISNUMBER(INDEX(Inputs!$K$5:$AJ$140,0,MATCH(G$2,Inputs!$K$4:$AJ$4,0))))+SUMPRODUCT((Inputs!$C$5:$C$140=$B5)*ISNUMBER(INDEX(Inputs!$K$5:$AJ$140,0,MATCH(G$2,Inputs!$K$4:$AJ$4,0))))+SUMPRODUCT((Inputs!$E$5:$E$140=$B5)*ISNUMBER(INDEX(Inputs!$K$5:$AJ$140,0,MATCH(G$2,Inputs!$K$4:$AJ$4,0))))=0,NA(),SUMPRODUCT((Inputs!$A$5:$A$140=$B5)*Inputs!$B$5:$B$140*(((Inputs!$G$5:$G$140="moeda")+(Inputs!$G$5:$G$140="acoes"))*Inputs!$B$1+((Inputs!$G$5:$G$140<>"moeda")*(Inputs!$G$5:$G$140<>"acoes")))*INDEX(Inputs!$K$5:$AJ$140,0,MATCH(G$2,Inputs!$K$4:$AJ$4,0)))+SUMPRODUCT((Inputs!$C$5:$C$140=$B5)*Inputs!$D$5:$D$140*(((Inputs!$G$5:$G$140="moeda")+(Inputs!$G$5:$G$140="acoes"))*Inputs!$B$1+((Inputs!$G$5:$G$140<>"moeda")*(Inputs!$G$5:$G$140<>"acoes")))*INDEX(Inputs!$K$5:$AJ$140,0,MATCH(G$2,Inputs!$K$4:$AJ$4,0)))+SUMPRODUCT((Inputs!$E$5:$E$140=$B5)*Inputs!$F$5:$F$140*(((Inputs!$G$5:$G$140="moeda")+(Inputs!$G$5:$G$140="acoes"))*Inputs!$B$1+((Inputs!$G$5:$G$140<>"moeda")*(Inputs!$G$5:$G$140<>"acoes")))*INDEX(Inputs!$K$5:$AJ$140,0,MATCH(G$2,Inputs!$K$4:$AJ$4,0))))) -> -3441.3096 | H5: =SUM(D5:G5) -> -12174.415 | I5: =IF(ISNA(MATCH(I$2,Inputs!$K$4:$AJ$4,0)),NA(),IF(SUMPRODUCT((Inputs!$A$5:$A$140=$B5)*ISNUMBER(INDEX(Inputs!$K$5:$AJ$140,0,MATCH(I$2,Inputs!$K$4:$AJ$4,0))))+SUMPRODUCT((Inputs!$C$5:$C$140=$B5)*ISNUMBER(INDEX(Inputs!$K$5:$AJ$140,0,MATCH(I$2,Inputs!$K$4:$AJ$4,0))))+SUMPRODUCT((Inputs!$E$5:$E$140=$B5)*ISNUMBER(INDEX(Inputs!$K$5:$AJ$140,0,MATCH(I$2,Inputs!$K$4:$AJ$4,0))))=0,NA(),SUMPRODUCT((Inputs!$A$5:$A$140=$B5)*Inputs!$B$5:$B$140*(((Inputs!$G$5:$G$140="moeda")+(Inputs!$G$5:$G$140="acoes"))*Inputs!$B$1+((Inputs!$G$5:$G$140<>"moeda")*(Inputs!$G$5:$G$140<>"acoes")))*INDEX(Inputs!$K$5:$AJ$140,0,MATCH(I$2,Inputs!$K$4:$AJ$4,0)))+SUMPRODUCT((Inputs!$C$5:$C$140=$B5)*Inputs!$D$5:$D$140*(((Inputs!$G$5:$G$140="moeda")+(Inputs!$G$5:$G$140="acoes"))*Inputs!$B$1+((Inputs!$G$5:$G$140<>"moeda")*(Inputs!$G$5:$G$140<>"acoes")))*INDEX(Inputs!$K$5:$AJ$140,0,MATCH(I$2,Inputs!$K$4:$AJ$4,0)))+SUMPRODUCT((Inputs!$E$5:$E$140=$B5)*Inputs!$F$5:$F$140*(((Inputs!$G$5:$G$140="moeda")+(Inputs!$G$5:$G$140="acoes"))*Inputs!$B$1+((Inputs!$G$5:$G$140<>"moeda")*(Inputs!$G$5:$G$140<>"acoes")))*INDEX(Inputs!$K$5:$AJ$140,0,MATCH(I$2,Inputs!$K$4:$AJ$4,0))))) -> -3553.0673 | J5: =IF(ISNA(MATCH(J$2,Inputs!$K$4:$AJ$4,0)),NA(),IF(SUMPRODUCT((Inputs!$A$5:$A$140=$B5)*ISNUMBER(INDEX(Inputs!$K$5:$AJ$140,0,MATCH(J$2,Inputs!$K$4:$AJ$4,0))))+SUMPRODUCT((Inputs!$C$5:$C$140=$B5)*ISNUMBER(INDEX(Inputs!$K$5:$AJ$140,0,MATCH(J$2,Inputs!$K$4:$AJ$4,0))))+SUMPRODUCT((Inputs!$E$5:$E$140=$B5)*ISNUMBER(INDEX(Inputs!$K$5:$AJ$140,0,MATCH(J$2,Inputs!$K$4:$AJ$4,0))))=0,NA(),SUMPRODUCT((Inputs!$A$5:$A$140=$B5)*Inputs!$B$5:$B$140*(((Inputs!$G$5:$G$140="moeda")+(Inputs!$G$5:$G$140="acoes"))*Inputs!$B$1+((Inputs!$G$5:$G$140<>"moeda")*(Inputs!$G$5:$G$140<>"acoes")))*INDEX(Inputs!$K$5:$AJ$140,0,MATCH(J$2,Inputs!$K$4:$AJ$4,0)))+SUMPRODUCT((Inputs!$C$5:$C$140=$B5)*Inputs!$D$5:$D$140*(((Inputs!$G$5:$G$140="moeda")+(Inputs!$G$5:$G$140="acoes"))*Inputs!$B$1+((Inputs!$G$5:$G$140<>"moeda")*(Inputs!$G$5:$G$140<>"acoes")))*INDEX(Inputs!$K$5:$AJ$140,0,MATCH(J$2,Inputs!$K$4:$AJ$4,0)))+SUMPRODUCT((Inputs!$E$5:$E$140=$B5)*Inputs!$F$5:$F$140*(((Inputs!$G$5:$G$140="moeda")+(Inputs!$G$5:$G$140="acoes"))*Inputs!$B$1+((Inputs!$G$5:$G$140<>"moeda")*(Inputs!$G$5:$G$140<>"acoes")))*INDEX(Inputs!$K$5:$AJ$140,0,MATCH(J$2,Inputs!$K$4:$AJ$4,0))))) -> -4019.431 | K5: =IF(ISNA(MATCH(K$2,Inputs!$K$4:$AJ$4,0)),NA(),IF(SUMPRODUCT((Inputs!$A$5:$A$140=$B5)*ISNUMBER(INDEX(Inputs!$K$5:$AJ$140,0,MATCH(K$2,Inputs!$K$4:$AJ$4,0))))+SUMPRODUCT((Inputs!$C$5:$C$140=$B5)*ISNUMBER(INDEX(Inputs!$K$5:$AJ$140,0,MATCH(K$2,Inputs!$K$4:$AJ$4,0))))+SUMPRODUCT((Inputs!$E$5:$E$140=$B5)*ISNUMBER(INDEX(Inputs!$K$5:$AJ$140,0,MATCH(K$2,Inputs!$K$4:$AJ$4,0))))=0,NA(),SUMPRODUCT((Inputs!$A$5:$A$140=$B5)*Inputs!$B$5:$B$140*(((Inputs!$G$5:$G$140="moeda")+(Inputs!$G$5:$G$140="acoes"))*Inputs!$B$1+((Inputs!$G$5:$G$140<>"moeda")*(Inputs!$G$5:$G$140<>"acoes")))*INDEX(Inputs!$K$5:$AJ$140,0,MATCH(K$2,Inputs!$K$4:$AJ$4,0)))+SUMPRODUCT((Inputs!$C$5:$C$140=$B5)*Inputs!$D$5:$D$140*(((Inputs!$G$5:$G$140="moeda")+(Inputs!$G$5:$G$140="acoes"))*Inputs!$B$1+((Inputs!$G$5:$G$140<>"moeda")*(Inputs!$G$5:$G$140<>"acoes")))*INDEX(Inputs!$K$5:$AJ$140,0,MATCH(K$2,Inputs!$K$4:$AJ$4,0)))+SUMPRODUCT((Inputs!$E$5:$E$140=$B5)*Inputs!$F$5:$F$140*(((Inputs!$G$5:$G$140="moeda")+(Inputs!$G$5:$G$140="acoes"))*Inputs!$B$1+((Inputs!$G$5:$G$140<>"moeda")*(Inputs!$G$5:$G$140<>"acoes")))*INDEX(Inputs!$K$5:$AJ$140,0,MATCH(K$2,Inputs!$K$4:$AJ$4,0))))) -> -4568.982 | L5: =IF(ISNA(MATCH(L$2,Inputs!$K$4:$AJ$4,0)),NA(),IF(SUMPRODUCT((Inputs!$A$5:$A$140=$B5)*ISNUMBER(INDEX(Inputs!$K$5:$AJ$140,0,MATCH(L$2,Inputs!$K$4:$AJ$4,0))))+SUMPRODUCT((Inputs!$C$5:$C$140=$B5)*ISNUMBER(INDEX(Inputs!$K$5:$AJ$140,0,MATCH(L$2,Inputs!$K$4:$AJ$4,0))))+SUMPRODUCT((Inputs!$E$5:$E$140=$B5)*ISNUMBER(INDEX(Inputs!$K$5:$AJ$140,0,MATCH(L$2,Inputs!$K$4:$AJ$4,0))))=0,NA(),SUMPRODUCT((Inputs!$A$5:$A$140=$B5)*Inputs!$B$5:$B$140*(((Inputs!$G$5:$G$140="moeda")+(Inputs!$G$5:$G$140="acoes"))*Inputs!$B$1+((Inputs!$G$5:$G$140<>"moeda")*(Inputs!$G$5:$G$140<>"acoes")))*INDEX(Inputs!$K$5:$AJ$140,0,MATCH(L$2,Inputs!$K$4:$AJ$4,0)))+SUMPRODUCT((Inputs!$C$5:$C$140=$B5)*Inputs!$D$5:$D$140*(((Inputs!$G$5:$G$140="moeda")+(Inputs!$G$5:$G$140="acoes"))*Inputs!$B$1+((Inputs!$G$5:$G$140<>"moeda")*(Inputs!$G$5:$G$140<>"acoes")))*INDEX(Inputs!$K$5:$AJ$140,0,MATCH(L$2,Inputs!$K$4:$AJ$4,0)))+SUMPRODUCT((Inputs!$E$5:$E$140=$B5)*Inputs!$F$5:$F$140*(((Inputs!$G$5:$G$140="moeda")+(Inputs!$G$5:$G$140="acoes"))*Inputs!$B$1+((Inputs!$G$5:$G$140<>"moeda")*(Inputs!$G$5:$G$140<>"acoes")))*INDEX(Inputs!$K$5:$AJ$140,0,MATCH(L$2,Inputs!$K$4:$AJ$4,0))))) -> -4752.905 | M5: =SUM(I5:L5) -> -16894.385 | N5: =IF(ISNA(MATCH(N$2,Inputs!$K$4:$AJ$4,0)),NA(),IF(SUMPRODUCT((Inputs!$A$5:$A$140=$B5)*ISNUMBER(INDEX(Inputs!$K$5:$AJ$140,0,MATCH(N$2,Inputs!$K$4:$AJ$4,0))))+SUMPRODUCT((Inputs!$C$5:$C$140=$B5)*ISNUMBER(INDEX(Inputs!$K$5:$AJ$140,0,MATCH(N$2,Inputs!$K$4:$AJ$4,0))))+SUMPRODUCT((Inputs!$E$5:$E$140=$B5)*ISNUMBER(INDEX(Inputs!$K$5:$AJ$140,0,MATCH(N$2,Inputs!$K$4:$AJ$4,0))))=0,NA(),SUMPRODUCT((Inputs!$A$5:$A$140=$B5)*Inputs!$B$5:$B$140*(((Inputs!$G$5:$G$140="moeda")+(Inputs!$G$5:$G$140="acoes"))*Inputs!$B$1+((Inputs!$G$5:$G$140<>"moeda")*(Inputs!$G$5:$G$140<>"acoes")))*INDEX(Inputs!$K$5:$AJ$140,0,MATCH(N$2,Inputs!$K$4:$AJ$4,0)))+SUMPRODUCT((Inputs!$C$5:$C$140=$B5)*Inputs!$D$5:$D$140*(((Inputs!$G$5:$G$140="moeda")+(Inputs!$G$5:$G$140="acoes"))*Inputs!$B$1+((Inputs!$G$5:$G$140<>"moeda")*(Inputs!$G$5:$G$140<>"acoes")))*INDEX(Inputs!$K$5:$AJ$140,0,MATCH(N$2,Inputs!$K$4:$AJ$4,0)))+SUMPRODUCT((Inputs!$E$5:$E$140=$B5)*Inputs!$F$5:$F$140*(((Inputs!$G$5:$G$140="moeda")+(Inputs!$G$5:$G$140="acoes"))*Inputs!$B$1+((Inputs!$G$5:$G$140<>"moeda")*(Inputs!$G$5:$G$140<>"acoes")))*INDEX(Inputs!$K$5:$AJ$140,0,MATCH(N$2,Inputs!$K$4:$AJ$4,0))))) -> -4574.5057 | O5: =IF(ISNA(MATCH(O$2,Inputs!$K$4:$AJ$4,0)),NA(),IF(SUMPRODUCT((Inputs!$A$5:$A$140=$B5)*ISNUMBER(INDEX(Inputs!$K$5:$AJ$140,0,MATCH(O$2,Inputs!$K$4:$AJ$4,0))))+SUMPRODUCT((Inputs!$C$5:$C$140=$B5)*ISNUMBER(INDEX(Inputs!$K$5:$AJ$140,0,MATCH(O$2,Inputs!$K$4:$AJ$4,0))))+SUMPRODUCT((Inputs!$E$5:$E$140=$B5)*ISNUMBER(INDEX(Inputs!$K$5:$AJ$140,0,MATCH(O$2,Inputs!$K$4:$AJ$4,0))))=0,NA(),SUMPRODUCT((Inputs!$A$5:$A$140=$B5)*Inputs!$B$5:$B$140*(((Inputs!$G$5:$G$140="moeda")+(Inputs!$G$5:$G$140="acoes"))*Inputs!$B$1+((Inputs!$G$5:$G$140<>"moeda")*(Inputs!$G$5:$G$140<>"acoes")))*INDEX(Inputs!$K$5:$AJ$140,0,MATCH(O$2,Inputs!$K$4:$AJ$4,0)))+SUMPRODUCT((Inputs!$C$5:$C$140=$B5)*Inputs!$D$5:$D$140*(((Inputs!$G$5:$G$140="moeda")+(Inputs!$G$5:$G$140="acoes"))*Inputs!$B$1+((Inputs!$G$5:$G$140<>"moeda")*(Inputs!$G$5:$G$140<>"acoes")))*INDEX(Inputs!$K$5:$AJ$140,0,MATCH(O$2,Inputs!$K$4:$AJ$4,0)))+SUMPRODUCT((Inputs!$E$5:$E$140=$B5)*Inputs!$F$5:$F$140*(((Inputs!$G$5:$G$140="moeda")+(Inputs!$G$5:$G$140="acoes"))*Inputs!$B$1+((Inputs!$G$5:$G$140<>"moeda")*(Inputs!$G$5:$G$140<>"acoes")))*INDEX(Inputs!$K$5:$AJ$140,0,MATCH(O$2,Inputs!$K$4:$AJ$4,0))))) -> -4985.038 | P5: =IF(ISNA(MATCH(P$2,Inputs!$K$4:$AJ$4,0)),NA(),IF(SUMPRODUCT((Inputs!$A$5:$A$140=$B5)*ISNUMBER(INDEX(Inputs!$K$5:$AJ$140,0,MATCH(P$2,Inputs!$K$4:$AJ$4,0))))+SUMPRODUCT((Inputs!$C$5:$C$140=$B5)*ISNUMBER(INDEX(Inputs!$K$5:$AJ$140,0,MATCH(P$2,Inputs!$K$4:$AJ$4,0))))+SUMPRODUCT((Inputs!$E$5:$E$140=$B5)*ISNUMBER(INDEX(Inputs!$K$5:$AJ$140,0,MATCH(P$2,Inputs!$K$4:$AJ$4,0))))=0,NA(),SUMPRODUCT((Inputs!$A$5:$A$140=$B5)*Inputs!$B$5:$B$140*(((Inputs!$G$5:$G$140="moeda")+(Inputs!$G$5:$G$140="acoes"))*Inputs!$B$1+((Inputs!$G$5:$G$140<>"moeda")*(Inputs!$G$5:$G$140<>"acoes")))*INDEX(Inputs!$K$5:$AJ$140,0,MATCH(P$2,Inputs!$K$4:$AJ$4,0)))+SUMPRODUCT((Inputs!$C$5:$C$140=$B5)*Inputs!$D$5:$D$140*(((Inputs!$G$5:$G$140="moeda")+(Inputs!$G$5:$G$140="acoes"))*Inputs!$B$1+((Inputs!$G$5:$G$140<>"moeda")*(Inputs!$G$5:$G$140<>"acoes")))*INDEX(Inputs!$K$5:$AJ$140,0,MATCH(P$2,Inputs!$K$4:$AJ$4,0)))+SUMPRODUCT((Inputs!$E$5:$E$140=$B5)*Inputs!$F$5:$F$140*(((Inputs!$G$5:$G$140="moeda")+(Inputs!$G$5:$G$140="acoes"))*Inputs!$B$1+((Inputs!$G$5:$G$140<>"moeda")*(Inputs!$G$5:$G$140<>"acoes")))*INDEX(Inputs!$K$5:$AJ$140,0,MATCH(P$2,Inputs!$K$4:$AJ$4,0))))) -> -5374.203 | Q5: =IF(ISNA(MATCH(Q$2,Inputs!$K$4:$AJ$4,0)),NA(),IF(SUMPRODUCT((Inputs!$A$5:$A$140=$B5)*ISNUMBER(INDEX(Inputs!$K$5:$AJ$140,0,MATCH(Q$2,Inputs!$K$4:$AJ$4,0))))+SUMPRODUCT((Inputs!$C$5:$C$140=$B5)*ISNUMBER(INDEX(Inputs!$K$5:$AJ$140,0,MATCH(Q$2,Inputs!$K$4:$AJ$4,0))))+SUMPRODUCT((Inputs!$E$5:$E$140=$B5)*ISNUMBER(INDEX(Inputs!$K$5:$AJ$140,0,MATCH(Q$2,Inputs!$K$4:$AJ$4,0))))=0,NA(),SUMPRODUCT((Inputs!$A$5:$A$140=$B5)*Inputs!$B$5:$B$140*(((Inputs!$G$5:$G$140="moeda")+(Inputs!$G$5:$G$140="acoes"))*Inputs!$B$1+((Inputs!$G$5:$G$140<>"moeda")*(Inputs!$G$5:$G$140<>"acoes")))*INDEX(Inputs!$K$5:$AJ$140,0,MATCH(Q$2,Inputs!$K$4:$AJ$4,0)))+SUMPRODUCT((Inputs!$C$5:$C$140=$B5)*Inputs!$D$5:$D$140*(((Inputs!$G$5:$G$140="moeda")+(Inputs!$G$5:$G$140="acoes"))*Inputs!$B$1+((Inputs!$G$5:$G$140<>"moeda")*(Inputs!$G$5:$G$140<>"acoes")))*INDEX(Inputs!$K$5:$AJ$140,0,MATCH(Q$2,Inputs!$K$4:$AJ$4,0)))+SUMPRODUCT((Inputs!$E$5:$E$140=$B5)*Inputs!$F$5:$F$140*(((Inputs!$G$5:$G$140="moeda")+(Inputs!$G$5:$G$140="acoes"))*Inputs!$B$1+((Inputs!$G$5:$G$140<>"moeda")*(Inputs!$G$5:$G$140<>"acoes")))*INDEX(Inputs!$K$5:$AJ$140,0,MATCH(Q$2,Inputs!$K$4:$AJ$4,0))))) -> -5849.0033 | R5: =SUM(N5:Q5) -> -20782.75 | S5: =IF(ISNA(MATCH(S$2,Inputs!$K$4:$AJ$4,0)),NA(),IF(SUMPRODUCT((Inputs!$A$5:$A$140=$B5)*ISNUMBER(INDEX(Inputs!$K$5:$AJ$140,0,MATCH(S$2,Inputs!$K$4:$AJ$4,0))))+SUMPRODUCT((Inputs!$C$5:$C$140=$B5)*ISNUMBER(INDEX(Inputs!$K$5:$AJ$140,0,MATCH(S$2,Inputs!$K$4:$AJ$4,0))))+SUMPRODUCT((Inputs!$E$5:$E$140=$B5)*ISNUMBER(INDEX(Inputs!$K$5:$AJ$140,0,MATCH(S$2,Inputs!$K$4:$AJ$4,0))))=0,NA(),SUMPRODUCT((Inputs!$A$5:$A$140=$B5)*Inputs!$B$5:$B$140*(((Inputs!$G$5:$G$140="moeda")+(Inputs!$G$5:$G$140="acoes"))*Inputs!$B$1+((Inputs!$G$5:$G$140<>"moeda")*(Inputs!$G$5:$G$140<>"acoes")))*INDEX(Inputs!$K$5:$AJ$140,0,MATCH(S$2,Inputs!$K$4:$AJ$4,0)))+SUMPRODUCT((Inputs!$C$5:$C$140=$B5)*Inputs!$D$5:$D$140*(((Inputs!$G$5:$G$140="moeda")+(Inputs!$G$5:$G$140="acoes"))*Inputs!$B$1+((Inputs!$G$5:$G$140<>"moeda")*(Inputs!$G$5:$G$140<>"acoes")))*INDEX(Inputs!$K$5:$AJ$140,0,MATCH(S$2,Inputs!$K$4:$AJ$4,0)))+SUMPRODUCT((Inputs!$E$5:$E$140=$B5)*Inputs!$F$5:$F$140*(((Inputs!$G$5:$G$140="moeda")+(Inputs!$G$5:$G$140="acoes"))*Inputs!$B$1+((Inputs!$G$5:$G$140<>"moeda")*(Inputs!$G$5:$G$140<>"acoes")))*INDEX(Inputs!$K$5:$AJ$140,0,MATCH(S$2,Inputs!$K$4:$AJ$4,0))))) -> -5732.716 | T5: =IF(ISNA(MATCH(T$2,Inputs!$K$4:$AJ$4,0)),NA(),IF(SUMPRODUCT((Inputs!$A$5:$A$140=$B5)*ISNUMBER(INDEX(Inputs!$K$5:$AJ$140,0,MATCH(T$2,Inputs!$K$4:$AJ$4,0))))+SUMPRODUCT((Inputs!$C$5:$C$140=$B5)*ISNUMBER(INDEX(Inputs!$K$5:$AJ$140,0,MATCH(T$2,Inputs!$K$4:$AJ$4,0))))+SUMPRODUCT((Inputs!$E$5:$E$140=$B5)*ISNUMBER(INDEX(Inputs!$K$5:$AJ$140,0,MATCH(T$2,Inputs!$K$4:$AJ$4,0))))=0,NA(),SUMPRODUCT((Inputs!$A$5:$A$140=$B5)*Inputs!$B$5:$B$140*(((Inputs!$G$5:$G$140="moeda")+(Inputs!$G$5:$G$140="acoes"))*Inputs!$B$1+((Inputs!$G$5:$G$140<>"moeda")*(Inputs!$G$5:$G$140<>"acoes")))*INDEX(Inputs!$K$5:$AJ$140,0,MATCH(T$2,Inputs!$K$4:$AJ$4,0)))+SUMPRODUCT((Inputs!$C$5:$C$140=$B5)*Inputs!$D$5:$D$140*(((Inputs!$G$5:$G$140="moeda")+(Inputs!$G$5:$G$140="acoes"))*Inputs!$B$1+((Inputs!$G$5:$G$140<>"moeda")*(Inputs!$G$5:$G$140<>"acoes")))*INDEX(Inputs!$K$5:$AJ$140,0,MATCH(T$2,Inputs!$K$4:$AJ$4,0)))+SUMPRODUCT((Inputs!$E$5:$E$140=$B5)*Inputs!$F$5:$F$140*(((Inputs!$G$5:$G$140="moeda")+(Inputs!$G$5:$G$140="acoes"))*Inputs!$B$1+((Inputs!$G$5:$G$140<>"moeda")*(Inputs!$G$5:$G$140<>"acoes")))*INDEX(Inputs!$K$5:$AJ$140,0,MATCH(T$2,Inputs!$K$4:$AJ$4,0))))) -> -5926.46 | U5: =IF(ISNA(MATCH(U$2,Inputs!$K$4:$AJ$4,0)),NA(),IF(SUMPRODUCT((Inputs!$A$5:$A$140=$B5)*ISNUMBER(INDEX(Inputs!$K$5:$AJ$140,0,MATCH(U$2,Inputs!$K$4:$AJ$4,0))))+SUMPRODUCT((Inputs!$C$5:$C$140=$B5)*ISNUMBER(INDEX(Inputs!$K$5:$AJ$140,0,MATCH(U$2,Inputs!$K$4:$AJ$4,0))))+SUMPRODUCT((Inputs!$E$5:$E$140=$B5)*ISNUMBER(INDEX(Inputs!$K$5:$AJ$140,0,MATCH(U$2,Inputs!$K$4:$AJ$4,0))))=0,NA(),SUMPRODUCT((Inputs!$A$5:$A$140=$B5)*Inputs!$B$5:$B$140*(((Inputs!$G$5:$G$140="moeda")+(Inputs!$G$5:$G$140="acoes"))*Inputs!$B$1+((Inputs!$G$5:$G$140<>"moeda")*(Inputs!$G$5:$G$140<>"acoes")))*INDEX(Inputs!$K$5:$AJ$140,0,MATCH(U$2,Inputs!$K$4:$AJ$4,0)))+SUMPRODUCT((Inputs!$C$5:$C$140=$B5)*Inputs!$D$5:$D$140*(((Inputs!$G$5:$G$140="moeda")+(Inputs!$G$5:$G$140="acoes"))*Inputs!$B$1+((Inputs!$G$5:$G$140<>"moeda")*(Inputs!$G$5:$G$140<>"acoes")))*INDEX(Inputs!$K$5:$AJ$140,0,MATCH(U$2,Inputs!$K$4:$AJ$4,0)))+SUMPRODUCT((Inputs!$E$5:$E$140=$B5)*Inputs!$F$5:$F$140*(((Inputs!$G$5:$G$140="moeda")+(Inputs!$G$5:$G$140="acoes"))*Inputs!$B$1+((Inputs!$G$5:$G$140<>"moeda")*(Inputs!$G$5:$G$140<>"acoes")))*INDEX(Inputs!$K$5:$AJ$140,0,MATCH(U$2,Inputs!$K$4:$AJ$4,0))))) -> -6479.36 | V5: =IF(ISNA(MATCH(V$2,Inputs!$K$4:$AJ$4,0)),NA(),IF(SUMPRODUCT((Inputs!$A$5:$A$140=$B5)*ISNUMBER(INDEX(Inputs!$K$5:$AJ$140,0,MATCH(V$2,Inputs!$K$4:$AJ$4,0))))+SUMPRODUCT((Inputs!$C$5:$C$140=$B5)*ISNUMBER(INDEX(Inputs!$K$5:$AJ$140,0,MATCH(V$2,Inputs!$K$4:$AJ$4,0))))+SUMPRODUCT((Inputs!$E$5:$E$140=$B5)*ISNUMBER(INDEX(Inputs!$K$5:$AJ$140,0,MATCH(V$2,Inputs!$K$4:$AJ$4,0))))=0,NA(),SUMPRODUCT((Inputs!$A$5:$A$140=$B5)*Inputs!$B$5:$B$140*(((Inputs!$G$5:$G$140="moeda")+(Inputs!$G$5:$G$140="acoes"))*Inputs!$B$1+((Inputs!$G$5:$G$140<>"moeda")*(Inputs!$G$5:$G$140<>"acoes")))*INDEX(Inputs!$K$5:$AJ$140,0,MATCH(V$2,Inputs!$K$4:$AJ$4,0)))+SUMPRODUCT((Inputs!$C$5:$C$140=$B5)*Inputs!$D$5:$D$140*(((Inputs!$G$5:$G$140="moeda")+(Inputs!$G$5:$G$140="acoes"))*Inputs!$B$1+((Inputs!$G$5:$G$140<>"moeda")*(Inputs!$G$5:$G$140<>"acoes")))*INDEX(Inputs!$K$5:$AJ$140,0,MATCH(V$2,Inputs!$K$4:$AJ$4,0)))+SUMPRODUCT((Inputs!$E$5:$E$140=$B5)*Inputs!$F$5:$F$140*(((Inputs!$G$5:$G$140="moeda")+(Inputs!$G$5:$G$140="acoes"))*Inputs!$B$1+((Inputs!$G$5:$G$140<>"moeda")*(Inputs!$G$5:$G$140<>"acoes")))*INDEX(Inputs!$K$5:$AJ$140,0,MATCH(V$2,Inputs!$K$4:$AJ$4,0))))) -> -6821.183 | W5: =SUM(S5:V5) -> -24959.719 | X5: =IF(ISNA(MATCH(X$2,Inputs!$K$4:$AJ$4,0)),NA(),IF(SUMPRODUCT((Inputs!$A$5:$A$140=$B5)*ISNUMBER(INDEX(Inputs!$K$5:$AJ$140,0,MATCH(X$2,Inputs!$K$4:$AJ$4,0))))+SUMPRODUCT((Inputs!$C$5:$C$140=$B5)*ISNUMBER(INDEX(Inputs!$K$5:$AJ$140,0,MATCH(X$2,Inputs!$K$4:$AJ$4,0))))+SUMPRODUCT((Inputs!$E$5:$E$140=$B5)*ISNUMBER(INDEX(Inputs!$K$5:$AJ$140,0,MATCH(X$2,Inputs!$K$4:$AJ$4,0))))=0,NA(),SUMPRODUCT((Inputs!$A$5:$A$140=$B5)*Inputs!$B$5:$B$140*(((Inputs!$G$5:$G$140="moeda")+(Inputs!$G$5:$G$140="acoes"))*Inputs!$B$1+((Inputs!$G$5:$G$140<>"moeda")*(Inputs!$G$5:$G$140<>"acoes")))*INDEX(Inputs!$K$5:$AJ$140,0,MATCH(X$2,Inputs!$K$4:$AJ$4,0)))+SUMPRODUCT((Inputs!$C$5:$C$140=$B5)*Inputs!$D$5:$D$140*(((Inputs!$G$5:$G$140="moeda")+(Inputs!$G$5:$G$140="acoes"))*Inputs!$B$1+((Inputs!$G$5:$G$140<>"moeda")*(Inputs!$G$5:$G$140<>"acoes")))*INDEX(Inputs!$K$5:$AJ$140,0,MATCH(X$2,Inputs!$K$4:$AJ$4,0)))+SUMPRODUCT((Inputs!$E$5:$E$140=$B5)*Inputs!$F$5:$F$140*(((Inputs!$G$5:$G$140="moeda")+(Inputs!$G$5:$G$140="acoes"))*Inputs!$B$1+((Inputs!$G$5:$G$140<>"moeda")*(Inputs!$G$5:$G$140<>"acoes")))*INDEX(Inputs!$K$5:$AJ$140,0,MATCH(X$2,Inputs!$K$4:$AJ$4,0))))) -> -6478.662 | Y5: =IF(ISNA(MATCH(Y$2,Inputs!$K$4:$AJ$4,0)),NA(),IF(SUMPRODUCT((Inputs!$A$5:$A$140=$B5)*ISNUMBER(INDEX(Inputs!$K$5:$AJ$140,0,MATCH(Y$2,Inputs!$K$4:$AJ$4,0))))+SUMPRODUCT((Inputs!$C$5:$C$140=$B5)*ISNUMBER(INDEX(Inputs!$K$5:$AJ$140,0,MATCH(Y$2,Inputs!$K$4:$AJ$4,0))))+SUMPRODUCT((Inputs!$E$5:$E$140=$B5)*ISNUMBER(INDEX(Inputs!$K$5:$AJ$140,0,MATCH(Y$2,Inputs!$K$4:$AJ$4,0))))=0,NA(),SUMPRODUCT((Inputs!$A$5:$A$140=$B5)*Inputs!$B$5:$B$140*(((Inputs!$G$5:$G$140="moeda")+(Inputs!$G$5:$G$140="acoes"))*Inputs!$B$1+((Inputs!$G$5:$G$140<>"moeda")*(Inputs!$G$5:$G$140<>"acoes")))*INDEX(Inputs!$K$5:$AJ$140,0,MATCH(Y$2,Inputs!$K$4:$AJ$4,0)))+SUMPRODUCT((Inputs!$C$5:$C$140=$B5)*Inputs!$D$5:$D$140*(((Inputs!$G$5:$G$140="moeda")+(Inputs!$G$5:$G$140="acoes"))*Inputs!$B$1+((Inputs!$G$5:$G$140<>"moeda")*(Inputs!$G$5:$G$140<>"acoes")))*INDEX(Inputs!$K$5:$AJ$140,0,MATCH(Y$2,Inputs!$K$4:$AJ$4,0)))+SUMPRODUCT((Inputs!$E$5:$E$140=$B5)*Inputs!$F$5:$F$140*(((Inputs!$G$5:$G$140="moeda")+(Inputs!$G$5:$G$140="acoes"))*Inputs!$B$1+((Inputs!$G$5:$G$140<>"moeda")*(Inputs!$G$5:$G$140<>"acoes")))*INDEX(Inputs!$K$5:$AJ$140,0,MATCH(Y$2,Inputs!$K$4:$AJ$4,0))))) -> -6685.998 | Z5: =IF(ISNA(MATCH(Z$2,Inputs!$K$4:$AJ$4,0)),NA(),IF(SUMPRODUCT((Inputs!$A$5:$A$140=$B5)*ISNUMBER(INDEX(Inputs!$K$5:$AJ$140,0,MATCH(Z$2,Inputs!$K$4:$AJ$4,0))))+SUMPRODUCT((Inputs!$C$5:$C$140=$B5)*ISNUMBER(INDEX(Inputs!$K$5:$AJ$140,0,MATCH(Z$2,Inputs!$K$4:$AJ$4,0))))+SUMPRODUCT((Inputs!$E$5:$E$140=$B5)*ISNUMBER(INDEX(Inputs!$K$5:$AJ$140,0,MATCH(Z$2,Inputs!$K$4:$AJ$4,0))))=0,NA(),SUMPRODUCT((Inputs!$A$5:$A$140=$B5)*Inputs!$B$5:$B$140*(((Inputs!$G$5:$G$140="moeda")+(Inputs!$G$5:$G$140="acoes"))*Inputs!$B$1+((Inputs!$G$5:$G$140<>"moeda")*(Inputs!$G$5:$G$140<>"acoes")))*INDEX(Inputs!$K$5:$AJ$140,0,MATCH(Z$2,Inputs!$K$4:$AJ$4,0)))+SUMPRODUCT((Inputs!$C$5:$C$140=$B5)*Inputs!$D$5:$D$140*(((Inputs!$G$5:$G$140="moeda")+(Inputs!$G$5:$G$140="acoes"))*Inputs!$B$1+((Inputs!$G$5:$G$140<>"moeda")*(Inputs!$G$5:$G$140<>"acoes")))*INDEX(Inputs!$K$5:$AJ$140,0,MATCH(Z$2,Inputs!$K$4:$AJ$4,0)))+SUMPRODUCT((Inputs!$E$5:$E$140=$B5)*Inputs!$F$5:$F$140*(((Inputs!$G$5:$G$140="moeda")+(Inputs!$G$5:$G$140="acoes"))*Inputs!$B$1+((Inputs!$G$5:$G$140<>"moeda")*(Inputs!$G$5:$G$140<>"acoes")))*INDEX(Inputs!$K$5:$AJ$140,0,MATCH(Z$2,Inputs!$K$4:$AJ$4,0))))) -> -8470.764 | AA5: =IF(ISNA(MATCH(AA$2,Inputs!$K$4:$AJ$4,0)),NA(),IF(SUMPRODUCT((Inputs!$A$5:$A$140=$B5)*ISNUMBER(INDEX(Inputs!$K$5:$AJ$140,0,MATCH(AA$2,Inputs!$K$4:$AJ$4,0))))+SUMPRODUCT((Inputs!$C$5:$C$140=$B5)*ISNUMBER(INDEX(Inputs!$K$5:$AJ$140,0,MATCH(AA$2,Inputs!$K$4:$AJ$4,0))))+SUMPRODUCT((Inputs!$E$5:$E$140=$B5)*ISNUMBER(INDEX(Inputs!$K$5:$AJ$140,0,MATCH(AA$2,Inputs!$K$4:$AJ$4,0))))=0,NA(),SUMPRODUCT((Inputs!$A$5:$A$140=$B5)*Inputs!$B$5:$B$140*(((Inputs!$G$5:$G$140="moeda")+(Inputs!$G$5:$G$140="acoes"))*Inputs!$B$1+((Inputs!$G$5:$G$140<>"moeda")*(Inputs!$G$5:$G$140<>"acoes")))*INDEX(Inputs!$K$5:$AJ$140,0,MATCH(AA$2,Inputs!$K$4:$AJ$4,0)))+SUMPRODUCT((Inputs!$C$5:$C$140=$B5)*Inputs!$D$5:$D$140*(((Inputs!$G$5:$G$140="moeda")+(Inputs!$G$5:$G$140="acoes"))*Inputs!$B$1+((Inputs!$G$5:$G$140<>"moeda")*(Inputs!$G$5:$G$140<>"acoes")))*INDEX(Inputs!$K$5:$AJ$140,0,MATCH(AA$2,Inputs!$K$4:$AJ$4,0)))+SUMPRODUCT((Inputs!$E$5:$E$140=$B5)*Inputs!$F$5:$F$140*(((Inputs!$G$5:$G$140="moeda")+(Inputs!$G$5:$G$140="acoes"))*Inputs!$B$1+((Inputs!$G$5:$G$140<>"moeda")*(Inputs!$G$5:$G$140<>"acoes")))*INDEX(Inputs!$K$5:$AJ$140,0,MATCH(AA$2,Inputs!$K$4:$AJ$4,0))))) -> -8175.2174 | AB5: =SUM(X5:AA5) -> -29810.641 | AC5: =IF(ISNA(MATCH(AC$2,Inputs!$K$4:$AJ$4,0)),NA(),IF(SUMPRODUCT((Inputs!$A$5:$A$140=$B5)*ISNUMBER(INDEX(Inputs!$K$5:$AJ$140,0,MATCH(AC$2,Inputs!$K$4:$AJ$4,0))))+SUMPRODUCT((Inputs!$C$5:$C$140=$B5)*ISNUMBER(INDEX(Inputs!$K$5:$AJ$140,0,MATCH(AC$2,Inputs!$K$4:$AJ$4,0))))+SUMPRODUCT((Inputs!$E$5:$E$140=$B5)*ISNUMBER(INDEX(Inputs!$K$5:$AJ$140,0,MATCH(AC$2,Inputs!$K$4:$AJ$4,0))))=0,NA(),SUMPRODUCT((Inputs!$A$5:$A$140=$B5)*Inputs!$B$5:$B$140*(((Inputs!$G$5:$G$140="moeda")+(Inputs!$G$5:$G$140="acoes"))*Inputs!$B$1+((Inputs!$G$5:$G$140<>"moeda")*(Inputs!$G$5:$G$140<>"acoes")))*INDEX(Inputs!$K$5:$AJ$140,0,MATCH(AC$2,Inputs!$K$4:$AJ$4,0)))+SUMPRODUCT((Inputs!$C$5:$C$140=$B5)*Inputs!$D$5:$D$140*(((Inputs!$G$5:$G$140="moeda")+(Inputs!$G$5:$G$140="acoes"))*Inputs!$B$1+((Inputs!$G$5:$G$140<>"moeda")*(Inputs!$G$5:$G$140<>"acoes")))*INDEX(Inputs!$K$5:$AJ$140,0,MATCH(AC$2,Inputs!$K$4:$AJ$4,0)))+SUMPRODUCT((Inputs!$E$5:$E$140=$B5)*Inputs!$F$5:$F$140*(((Inputs!$G$5:$G$140="moeda")+(Inputs!$G$5:$G$140="acoes"))*Inputs!$B$1+((Inputs!$G$5:$G$140<>"moeda")*(Inputs!$G$5:$G$140<>"acoes")))*INDEX(Inputs!$K$5:$AJ$140,0,MATCH(AC$2,Inputs!$K$4:$AJ$4,0))))) -> -7251.758 | AD5: =IF(ISNA(MATCH(AD$2,Inputs!$K$4:$AJ$4,0)),NA(),IF(SUMPRODUCT((Inputs!$A$5:$A$140=$B5)*ISNUMBER(INDEX(Inputs!$K$5:$AJ$140,0,MATCH(AD$2,Inputs!$K$4:$AJ$4,0))))+SUMPRODUCT((Inputs!$C$5:$C$140=$B5)*ISNUMBER(INDEX(Inputs!$K$5:$AJ$140,0,MATCH(AD$2,Inputs!$K$4:$AJ$4,0))))+SUMPRODUCT((Inputs!$E$5:$E$140=$B5)*ISNUMBER(INDEX(Inputs!$K$5:$AJ$140,0,MATCH(AD$2,Inputs!$K$4:$AJ$4,0))))=0,NA(),SUMPRODUCT((Inputs!$A$5:$A$140=$B5)*Inputs!$B$5:$B$140*(((Inputs!$G$5:$G$140="moeda")+(Inputs!$G$5:$G$140="acoes"))*Inputs!$B$1+((Inputs!$G$5:$G$140<>"moeda")*(Inputs!$G$5:$G$140<>"acoes")))*INDEX(Inputs!$K$5:$AJ$140,0,MATCH(AD$2,Inputs!$K$4:$AJ$4,0)))+SUMPRODUCT((Inputs!$C$5:$C$140=$B5)*Inputs!$D$5:$D$140*(((Inputs!$G$5:$G$140="moeda")+(Inputs!$G$5:$G$140="acoes"))*Inputs!$B$1+((Inputs!$G$5:$G$140<>"moeda")*(Inputs!$G$5:$G$140<>"acoes")))*INDEX(Inputs!$K$5:$AJ$140,0,MATCH(AD$2,Inputs!$K$4:$AJ$4,0)))+SUMPRODUCT((Inputs!$E$5:$E$140=$B5)*Inputs!$F$5:$F$140*(((Inputs!$G$5:$G$140="moeda")+(Inputs!$G$5:$G$140="acoes"))*Inputs!$B$1+((Inputs!$G$5:$G$140<>"moeda")*(Inputs!$G$5:$G$140<>"acoes")))*INDEX(Inputs!$K$5:$AJ$140,0,MATCH(AD$2,Inputs!$K$4:$AJ$4,0))))) -> -7541.266 | AE5: =IF(ISNA(MATCH(AE$2,Inputs!$K$4:$AJ$4,0)),NA(),IF(SUMPRODUCT((Inputs!$A$5:$A$140=$B5)*ISNUMBER(INDEX(Inputs!$K$5:$AJ$140,0,MATCH(AE$2,Inputs!$K$4:$AJ$4,0))))+SUMPRODUCT((Inputs!$C$5:$C$140=$B5)*ISNUMBER(INDEX(Inputs!$K$5:$AJ$140,0,MATCH(AE$2,Inputs!$K$4:$AJ$4,0))))+SUMPRODUCT((Inputs!$E$5:$E$140=$B5)*ISNUMBER(INDEX(Inputs!$K$5:$AJ$140,0,MATCH(AE$2,Inputs!$K$4:$AJ$4,0))))=0,NA(),SUMPRODUCT((Inputs!$A$5:$A$140=$B5)*Inputs!$B$5:$B$140*(((Inputs!$G$5:$G$140="moeda")+(Inputs!$G$5:$G$140="acoes"))*Inputs!$B$1+((Inputs!$G$5:$G$140<>"moeda")*(Inputs!$G$5:$G$140<>"acoes")))*INDEX(Inputs!$K$5:$AJ$140,0,MATCH(AE$2,Inputs!$K$4:$AJ$4,0)))+SUMPRODUCT((Inputs!$C$5:$C$140=$B5)*Inputs!$D$5:$D$140*(((Inputs!$G$5:$G$140="moeda")+(Inputs!$G$5:$G$140="acoes"))*Inputs!$B$1+((Inputs!$G$5:$G$140<>"moeda")*(Inputs!$G$5:$G$140<>"acoes")))*INDEX(Inputs!$K$5:$AJ$140,0,MATCH(AE$2,Inputs!$K$4:$AJ$4,0)))+SUMPRODUCT((Inputs!$E$5:$E$140=$B5)*Inputs!$F$5:$F$140*(((Inputs!$G$5:$G$140="moeda")+(Inputs!$G$5:$G$140="acoes"))*Inputs!$B$1+((Inputs!$G$5:$G$140<>"moeda")*(Inputs!$G$5:$G$140<>"acoes")))*INDEX(Inputs!$K$5:$AJ$140,0,MATCH(AE$2,Inputs!$K$4:$AJ$4,0))))) -> #N/A | AF5: =IF(ISNA(MATCH(AF$2,Inputs!$K$4:$AJ$4,0)),NA(),IF(SUMPRODUCT((Inputs!$A$5:$A$140=$B5)*ISNUMBER(INDEX(Inputs!$K$5:$AJ$140,0,MATCH(AF$2,Inputs!$K$4:$AJ$4,0))))+SUMPRODUCT((Inputs!$C$5:$C$140=$B5)*ISNUMBER(INDEX(Inputs!$K$5:$AJ$140,0,MATCH(AF$2,Inputs!$K$4:$AJ$4,0))))+SUMPRODUCT((Inputs!$E$5:$E$140=$B5)*ISNUMBER(INDEX(Inputs!$K$5:$AJ$140,0,MATCH(AF$2,Inputs!$K$4:$AJ$4,0))))=0,NA(),SUMPRODUCT((Inputs!$A$5:$A$140=$B5)*Inputs!$B$5:$B$140*(((Inputs!$G$5:$G$140="moeda")+(Inputs!$G$5:$G$140="acoes"))*Inputs!$B$1+((Inputs!$G$5:$G$140<>"moeda")*(Inputs!$G$5:$G$140<>"acoes")))*INDEX(Inputs!$K$5:$AJ$140,0,MATCH(AF$2,Inputs!$K$4:$AJ$4,0)))+SUMPRODUCT((Inputs!$C$5:$C$140=$B5)*Inputs!$D$5:$D$140*(((Inputs!$G$5:$G$140="moeda")+(Inputs!$G$5:$G$140="acoes"))*Inputs!$B$1+((Inputs!$G$5:$G$140<>"moeda")*(Inputs!$G$5:$G$140<>"acoes")))*INDEX(Inputs!$K$5:$AJ$140,0,MATCH(AF$2,Inputs!$K$4:$AJ$4,0)))+SUMPRODUCT((Inputs!$E$5:$E$140=$B5)*Inputs!$F$5:$F$140*(((Inputs!$G$5:$G$140="moeda")+(Inputs!$G$5:$G$140="acoes"))*Inputs!$B$1+((Inputs!$G$5:$G$140<>"moeda")*(Inputs!$G$5:$G$140<>"acoes")))*INDEX(Inputs!$K$5:$AJ$140,0,MATCH(AF$2,Inputs!$K$4:$AJ$4,0))))) -> #N/A | AG5: =SUM(AC5:AF5) -> #N/A | AH5: =IF(ISNA(MATCH(AH$2,Inputs!$K$4:$AJ$4,0)),NA(),IF(SUMPRODUCT((Inputs!$A$5:$A$140=$B5)*ISNUMBER(INDEX(Inputs!$K$5:$AJ$140,0,MATCH(AH$2,Inputs!$K$4:$AJ$4,0))))+SUMPRODUCT((Inputs!$C$5:$C$140=$B5)*ISNUMBER(INDEX(Inputs!$K$5:$AJ$140,0,MATCH(AH$2,Inputs!$K$4:$AJ$4,0))))+SUMPRODUCT((Inputs!$E$5:$E$140=$B5)*ISNUMBER(INDEX(Inputs!$K$5:$AJ$140,0,MATCH(AH$2,Inputs!$K$4:$AJ$4,0))))=0,NA(),SUMPRODUCT((Inputs!$A$5:$A$140=$B5)*Inputs!$B$5:$B$140*(((Inputs!$G$5:$G$140="moeda")+(Inputs!$G$5:$G$140="acoes"))*Inputs!$B$1+((Inputs!$G$5:$G$140<>"moeda")*(Inputs!$G$5:$G$140<>"acoes")))*INDEX(Inputs!$K$5:$AJ$140,0,MATCH(AH$2,Inputs!$K$4:$AJ$4,0)))+SUMPRODUCT((Inputs!$C$5:$C$140=$B5)*Inputs!$D$5:$D$140*(((Inputs!$G$5:$G$140="moeda")+(Inputs!$G$5:$G$140="acoes"))*Inputs!$B$1+((Inputs!$G$5:$G$140<>"moeda")*(Inputs!$G$5:$G$140<>"acoes")))*INDEX(Inputs!$K$5:$AJ$140,0,MATCH(AH$2,Inputs!$K$4:$AJ$4,0)))+SUMPRODUCT((Inputs!$E$5:$E$140=$B5)*Inputs!$F$5:$F$140*(((Inputs!$G$5:$G$140="moeda")+(Inputs!$G$5:$G$140="acoes"))*Inputs!$B$1+((Inputs!$G$5:$G$140<>"moeda")*(Inputs!$G$5:$G$140<>"acoes")))*INDEX(Inputs!$K$5:$AJ$140,0,MATCH(AH$2,Inputs!$K$4:$AJ$4,0))))) -> -1805.748 | AI5: =IF(ISNA(MATCH(AI$2,Inputs!$K$4:$AJ$4,0)),NA(),IF(SUMPRODUCT((Inputs!$A$5:$A$140=$B5)*ISNUMBER(INDEX(Inputs!$K$5:$AJ$140,0,MATCH(AI$2,Inputs!$K$4:$AJ$4,0))))+SUMPRODUCT((Inputs!$C$5:$C$140=$B5)*ISNUMBER(INDEX(Inputs!$K$5:$AJ$140,0,MATCH(AI$2,Inputs!$K$4:$AJ$4,0))))+SUMPRODUCT((Inputs!$E$5:$E$140=$B5)*ISNUMBER(INDEX(Inputs!$K$5:$AJ$140,0,MATCH(AI$2,Inputs!$K$4:$AJ$4,0))))=0,NA(),SUMPRODUCT((Inputs!$A$5:$A$140=$B5)*Inputs!$B$5:$B$140*(((Inputs!$G$5:$G$140="moeda")+(Inputs!$G$5:$G$140="acoes"))*Inputs!$B$1+((Inputs!$G$5:$G$140<>"moeda")*(Inputs!$G$5:$G$140<>"acoes")))*INDEX(Inputs!$K$5:$AJ$140,0,MATCH(AI$2,Inputs!$K$4:$AJ$4,0)))+SUMPRODUCT((Inputs!$C$5:$C$140=$B5)*Inputs!$D$5:$D$140*(((Inputs!$G$5:$G$140="moeda")+(Inputs!$G$5:$G$140="acoes"))*Inputs!$B$1+((Inputs!$G$5:$G$140<>"moeda")*(Inputs!$G$5:$G$140<>"acoes")))*INDEX(Inputs!$K$5:$AJ$140,0,MATCH(AI$2,Inputs!$K$4:$AJ$4,0)))+SUMPRODUCT((Inputs!$E$5:$E$140=$B5)*Inputs!$F$5:$F$140*(((Inputs!$G$5:$G$140="moeda")+(Inputs!$G$5:$G$140="acoes"))*Inputs!$B$1+((Inputs!$G$5:$G$140<>"moeda")*(Inputs!$G$5:$G$140<>"acoes")))*INDEX(Inputs!$K$5:$AJ$140,0,MATCH(AI$2,Inputs!$K$4:$AJ$4,0))))) -> -2195.072 | AJ5: =IF(ISNA(MATCH(AJ$2,Inputs!$K$4:$AJ$4,0)),NA(),IF(SUMPRODUCT((Inputs!$A$5:$A$140=$B5)*ISNUMBER(INDEX(Inputs!$K$5:$AJ$140,0,MATCH(AJ$2,Inputs!$K$4:$AJ$4,0))))+SUMPRODUCT((Inputs!$C$5:$C$140=$B5)*ISNUMBER(INDEX(Inputs!$K$5:$AJ$140,0,MATCH(AJ$2,Inputs!$K$4:$AJ$4,0))))+SUMPRODUCT((Inputs!$E$5:$E$140=$B5)*ISNUMBER(INDEX(Inputs!$K$5:$AJ$140,0,MATCH(AJ$2,Inputs!$K$4:$AJ$4,0))))=0,NA(),SUMPRODUCT((Inputs!$A$5:$A$140=$B5)*Inputs!$B$5:$B$140*(((Inputs!$G$5:$G$140="moeda")+(Inputs!$G$5:$G$140="acoes"))*Inputs!$B$1+((Inputs!$G$5:$G$140<>"moeda")*(Inputs!$G$5:$G$140<>"acoes")))*INDEX(Inputs!$K$5:$AJ$140,0,MATCH(AJ$2,Inputs!$K$4:$AJ$4,0)))+SUMPRODUCT((Inputs!$C$5:$C$140=$B5)*Inputs!$D$5:$D$140*(((Inputs!$G$5:$G$140="moeda")+(Inputs!$G$5:$G$140="acoes"))*Inputs!$B$1+((Inputs!$G$5:$G$140<>"moeda")*(Inputs!$G$5:$G$140<>"acoes")))*INDEX(Inputs!$K$5:$AJ$140,0,MATCH(AJ$2,Inputs!$K$4:$AJ$4,0)))+SUMPRODUCT((Inputs!$E$5:$E$140=$B5)*Inputs!$F$5:$F$140*(((Inputs!$G$5:$G$140="moeda")+(Inputs!$G$5:$G$140="acoes"))*Inputs!$B$1+((Inputs!$G$5:$G$140<>"moeda")*(Inputs!$G$5:$G$140<>"acoes")))*INDEX(Inputs!$K$5:$AJ$140,0,MATCH(AJ$2,Inputs!$K$4:$AJ$4,0))))) -> -2625.787 | AK5: =IF(ISNA(MATCH(AK$2,Inputs!$K$4:$AJ$4,0)),NA(),IF(SUMPRODUCT((Inputs!$A$5:$A$140=$B5)*ISNUMBER(INDEX(Inputs!$K$5:$AJ$140,0,MATCH(AK$2,Inputs!$K$4:$AJ$4,0))))+SUMPRODUCT((Inputs!$C$5:$C$140=$B5)*ISNUMBER(INDEX(Inputs!$K$5:$AJ$140,0,MATCH(AK$2,Inputs!$K$4:$AJ$4,0))))+SUMPRODUCT((Inputs!$E$5:$E$140=$B5)*ISNUMBER(INDEX(Inputs!$K$5:$AJ$140,0,MATCH(AK$2,Inputs!$K$4:$AJ$4,0))))=0,NA(),SUMPRODUCT((Inputs!$A$5:$A$140=$B5)*Inputs!$B$5:$B$140*(((Inputs!$G$5:$G$140="moeda")+(Inputs!$G$5:$G$140="acoes"))*Inputs!$B$1+((Inputs!$G$5:$G$140<>"moeda")*(Inputs!$G$5:$G$140<>"acoes")))*INDEX(Inputs!$K$5:$AJ$140,0,MATCH(AK$2,Inputs!$K$4:$AJ$4,0)))+SUMPRODUCT((Inputs!$C$5:$C$140=$B5)*Inputs!$D$5:$D$140*(((Inputs!$G$5:$G$140="moeda")+(Inputs!$G$5:$G$140="acoes"))*Inputs!$B$1+((Inputs!$G$5:$G$140<>"moeda")*(Inputs!$G$5:$G$140<>"acoes")))*INDEX(Inputs!$K$5:$AJ$140,0,MATCH(AK$2,Inputs!$K$4:$AJ$4,0)))+SUMPRODUCT((Inputs!$E$5:$E$140=$B5)*Inputs!$F$5:$F$140*(((Inputs!$G$5:$G$140="moeda")+(Inputs!$G$5:$G$140="acoes"))*Inputs!$B$1+((Inputs!$G$5:$G$140<>"moeda")*(Inputs!$G$5:$G$140<>"acoes")))*INDEX(Inputs!$K$5:$AJ$140,0,MATCH(AK$2,Inputs!$K$4:$AJ$4,0))))) -> -2781.0199 | AL5: =SUM(AH5:AK5) -> -9407.6269
B6: 3 | C6: SG&A and Other (cash) | D6: =IF(ISNA(MATCH(D$2,Inputs!$K$4:$AJ$4,0)),NA(),IF(SUMPRODUCT((Inputs!$A$5:$A$140=$B6)*ISNUMBER(INDEX(Inputs!$K$5:$AJ$140,0,MATCH(D$2,Inputs!$K$4:$AJ$4,0))))+SUMPRODUCT((Inputs!$C$5:$C$140=$B6)*ISNUMBER(INDEX(Inputs!$K$5:$AJ$140,0,MATCH(D$2,Inputs!$K$4:$AJ$4,0))))+SUMPRODUCT((Inputs!$E$5:$E$140=$B6)*ISNUMBER(INDEX(Inputs!$K$5:$AJ$140,0,MATCH(D$2,Inputs!$K$4:$AJ$4,0))))=0,NA(),SUMPRODUCT((Inputs!$A$5:$A$140=$B6)*Inputs!$B$5:$B$140*(((Inputs!$G$5:$G$140="moeda")+(Inputs!$G$5:$G$140="acoes"))*Inputs!$B$1+((Inputs!$G$5:$G$140<>"moeda")*(Inputs!$G$5:$G$140<>"acoes")))*INDEX(Inputs!$K$5:$AJ$140,0,MATCH(D$2,Inputs!$K$4:$AJ$4,0)))+SUMPRODUCT((Inputs!$C$5:$C$140=$B6)*Inputs!$D$5:$D$140*(((Inputs!$G$5:$G$140="moeda")+(Inputs!$G$5:$G$140="acoes"))*Inputs!$B$1+((Inputs!$G$5:$G$140<>"moeda")*(Inputs!$G$5:$G$140<>"acoes")))*INDEX(Inputs!$K$5:$AJ$140,0,MATCH(D$2,Inputs!$K$4:$AJ$4,0)))+SUMPRODUCT((Inputs!$E$5:$E$140=$B6)*Inputs!$F$5:$F$140*(((Inputs!$G$5:$G$140="moeda")+(Inputs!$G$5:$G$140="acoes"))*Inputs!$B$1+((Inputs!$G$5:$G$140<>"moeda")*(Inputs!$G$5:$G$140<>"acoes")))*INDEX(Inputs!$K$5:$AJ$140,0,MATCH(D$2,Inputs!$K$4:$AJ$4,0))))) -> -562.84964 | E6: =IF(ISNA(MATCH(E$2,Inputs!$K$4:$AJ$4,0)),NA(),IF(SUMPRODUCT((Inputs!$A$5:$A$140=$B6)*ISNUMBER(INDEX(Inputs!$K$5:$AJ$140,0,MATCH(E$2,Inputs!$K$4:$AJ$4,0))))+SUMPRODUCT((Inputs!$C$5:$C$140=$B6)*ISNUMBER(INDEX(Inputs!$K$5:$AJ$140,0,MATCH(E$2,Inputs!$K$4:$AJ$4,0))))+SUMPRODUCT((Inputs!$E$5:$E$140=$B6)*ISNUMBER(INDEX(Inputs!$K$5:$AJ$140,0,MATCH(E$2,Inputs!$K$4:$AJ$4,0))))=0,NA(),SUMPRODUCT((Inputs!$A$5:$A$140=$B6)*Inputs!$B$5:$B$140*(((Inputs!$G$5:$G$140="moeda")+(Inputs!$G$5:$G$140="acoes"))*Inputs!$B$1+((Inputs!$G$5:$G$140<>"moeda")*(Inputs!$G$5:$G$140<>"acoes")))*INDEX(Inputs!$K$5:$AJ$140,0,MATCH(E$2,Inputs!$K$4:$AJ$4,0)))+SUMPRODUCT((Inputs!$C$5:$C$140=$B6)*Inputs!$D$5:$D$140*(((Inputs!$G$5:$G$140="moeda")+(Inputs!$G$5:$G$140="acoes"))*Inputs!$B$1+((Inputs!$G$5:$G$140<>"moeda")*(Inputs!$G$5:$G$140<>"acoes")))*INDEX(Inputs!$K$5:$AJ$140,0,MATCH(E$2,Inputs!$K$4:$AJ$4,0)))+SUMPRODUCT((Inputs!$E$5:$E$140=$B6)*Inputs!$F$5:$F$140*(((Inputs!$G$5:$G$140="moeda")+(Inputs!$G$5:$G$140="acoes"))*Inputs!$B$1+((Inputs!$G$5:$G$140<>"moeda")*(Inputs!$G$5:$G$140<>"acoes")))*INDEX(Inputs!$K$5:$AJ$140,0,MATCH(E$2,Inputs!$K$4:$AJ$4,0))))) -> -583.83755 | F6: =IF(ISNA(MATCH(F$2,Inputs!$K$4:$AJ$4,0)),NA(),IF(SUMPRODUCT((Inputs!$A$5:$A$140=$B6)*ISNUMBER(INDEX(Inputs!$K$5:$AJ$140,0,MATCH(F$2,Inputs!$K$4:$AJ$4,0))))+SUMPRODUCT((Inputs!$C$5:$C$140=$B6)*ISNUMBER(INDEX(Inputs!$K$5:$AJ$140,0,MATCH(F$2,Inputs!$K$4:$AJ$4,0))))+SUMPRODUCT((Inputs!$E$5:$E$140=$B6)*ISNUMBER(INDEX(Inputs!$K$5:$AJ$140,0,MATCH(F$2,Inputs!$K$4:$AJ$4,0))))=0,NA(),SUMPRODUCT((Inputs!$A$5:$A$140=$B6)*Inputs!$B$5:$B$140*(((Inputs!$G$5:$G$140="moeda")+(Inputs!$G$5:$G$140="acoes"))*Inputs!$B$1+((Inputs!$G$5:$G$140<>"moeda")*(Inputs!$G$5:$G$140<>"acoes")))*INDEX(Inputs!$K$5:$AJ$140,0,MATCH(F$2,Inputs!$K$4:$AJ$4,0)))+SUMPRODUCT((Inputs!$C$5:$C$140=$B6)*Inputs!$D$5:$D$140*(((Inputs!$G$5:$G$140="moeda")+(Inputs!$G$5:$G$140="acoes"))*Inputs!$B$1+((Inputs!$G$5:$G$140<>"moeda")*(Inputs!$G$5:$G$140<>"acoes")))*INDEX(Inputs!$K$5:$AJ$140,0,MATCH(F$2,Inputs!$K$4:$AJ$4,0)))+SUMPRODUCT((Inputs!$E$5:$E$140=$B6)*Inputs!$F$5:$F$140*(((Inputs!$G$5:$G$140="moeda")+(Inputs!$G$5:$G$140="acoes"))*Inputs!$B$1+((Inputs!$G$5:$G$140<>"moeda")*(Inputs!$G$5:$G$140<>"acoes")))*INDEX(Inputs!$K$5:$AJ$140,0,MATCH(F$2,Inputs!$K$4:$AJ$4,0))))) -> -705.863 | G6: =IF(ISNA(MATCH(G$2,Inputs!$K$4:$AJ$4,0)),NA(),IF(SUMPRODUCT((Inputs!$A$5:$A$140=$B6)*ISNUMBER(INDEX(Inputs!$K$5:$AJ$140,0,MATCH(G$2,Inputs!$K$4:$AJ$4,0))))+SUMPRODUCT((Inputs!$C$5:$C$140=$B6)*ISNUMBER(INDEX(Inputs!$K$5:$AJ$140,0,MATCH(G$2,Inputs!$K$4:$AJ$4,0))))+SUMPRODUCT((Inputs!$E$5:$E$140=$B6)*ISNUMBER(INDEX(Inputs!$K$5:$AJ$140,0,MATCH(G$2,Inputs!$K$4:$AJ$4,0))))=0,NA(),SUMPRODUCT((Inputs!$A$5:$A$140=$B6)*Inputs!$B$5:$B$140*(((Inputs!$G$5:$G$140="moeda")+(Inputs!$G$5:$G$140="acoes"))*Inputs!$B$1+((Inputs!$G$5:$G$140<>"moeda")*(Inputs!$G$5:$G$140<>"acoes")))*INDEX(Inputs!$K$5:$AJ$140,0,MATCH(G$2,Inputs!$K$4:$AJ$4,0)))+SUMPRODUCT((Inputs!$C$5:$C$140=$B6)*Inputs!$D$5:$D$140*(((Inputs!$G$5:$G$140="moeda")+(Inputs!$G$5:$G$140="acoes"))*Inputs!$B$1+((Inputs!$G$5:$G$140<>"moeda")*(Inputs!$G$5:$G$140<>"acoes")))*INDEX(Inputs!$K$5:$AJ$140,0,MATCH(G$2,Inputs!$K$4:$AJ$4,0)))+SUMPRODUCT((Inputs!$E$5:$E$140=$B6)*Inputs!$F$5:$F$140*(((Inputs!$G$5:$G$140="moeda")+(Inputs!$G$5:$G$140="acoes"))*Inputs!$B$1+((Inputs!$G$5:$G$140<>"moeda")*(Inputs!$G$5:$G$140<>"acoes")))*INDEX(Inputs!$K$5:$AJ$140,0,MATCH(G$2,Inputs!$K$4:$AJ$4,0))))) -> -673.279 | H6: =SUM(D6:G6) -> -2525.8292 | I6: =IF(ISNA(MATCH(I$2,Inputs!$K$4:$AJ$4,0)),NA(),IF(SUMPRODUCT((Inputs!$A$5:$A$140=$B6)*ISNUMBER(INDEX(Inputs!$K$5:$AJ$140,0,MATCH(I$2,Inputs!$K$4:$AJ$4,0))))+SUMPRODUCT((Inputs!$C$5:$C$140=$B6)*ISNUMBER(INDEX(Inputs!$K$5:$AJ$140,0,MATCH(I$2,Inputs!$K$4:$AJ$4,0))))+SUMPRODUCT((Inputs!$E$5:$E$140=$B6)*ISNUMBER(INDEX(Inputs!$K$5:$AJ$140,0,MATCH(I$2,Inputs!$K$4:$AJ$4,0))))=0,NA(),SUMPRODUCT((Inputs!$A$5:$A$140=$B6)*Inputs!$B$5:$B$140*(((Inputs!$G$5:$G$140="moeda")+(Inputs!$G$5:$G$140="acoes"))*Inputs!$B$1+((Inputs!$G$5:$G$140<>"moeda")*(Inputs!$G$5:$G$140<>"acoes")))*INDEX(Inputs!$K$5:$AJ$140,0,MATCH(I$2,Inputs!$K$4:$AJ$4,0)))+SUMPRODUCT((Inputs!$C$5:$C$140=$B6)*Inputs!$D$5:$D$140*(((Inputs!$G$5:$G$140="moeda")+(Inputs!$G$5:$G$140="acoes"))*Inputs!$B$1+((Inputs!$G$5:$G$140<>"moeda")*(Inputs!$G$5:$G$140<>"acoes")))*INDEX(Inputs!$K$5:$AJ$140,0,MATCH(I$2,Inputs!$K$4:$AJ$4,0)))+SUMPRODUCT((Inputs!$E$5:$E$140=$B6)*Inputs!$F$5:$F$140*(((Inputs!$G$5:$G$140="moeda")+(Inputs!$G$5:$G$140="acoes"))*Inputs!$B$1+((Inputs!$G$5:$G$140<>"moeda")*(Inputs!$G$5:$G$140<>"acoes")))*INDEX(Inputs!$K$5:$AJ$140,0,MATCH(I$2,Inputs!$K$4:$AJ$4,0))))) -> -723.70924 | J6: =IF(ISNA(MATCH(J$2,Inputs!$K$4:$AJ$4,0)),NA(),IF(SUMPRODUCT((Inputs!$A$5:$A$140=$B6)*ISNUMBER(INDEX(Inputs!$K$5:$AJ$140,0,MATCH(J$2,Inputs!$K$4:$AJ$4,0))))+SUMPRODUCT((Inputs!$C$5:$C$140=$B6)*ISNUMBER(INDEX(Inputs!$K$5:$AJ$140,0,MATCH(J$2,Inputs!$K$4:$AJ$4,0))))+SUMPRODUCT((Inputs!$E$5:$E$140=$B6)*ISNUMBER(INDEX(Inputs!$K$5:$AJ$140,0,MATCH(J$2,Inputs!$K$4:$AJ$4,0))))=0,NA(),SUMPRODUCT((Inputs!$A$5:$A$140=$B6)*Inputs!$B$5:$B$140*(((Inputs!$G$5:$G$140="moeda")+(Inputs!$G$5:$G$140="acoes"))*Inputs!$B$1+((Inputs!$G$5:$G$140<>"moeda")*(Inputs!$G$5:$G$140<>"acoes")))*INDEX(Inputs!$K$5:$AJ$140,0,MATCH(J$2,Inputs!$K$4:$AJ$4,0)))+SUMPRODUCT((Inputs!$C$5:$C$140=$B6)*Inputs!$D$5:$D$140*(((Inputs!$G$5:$G$140="moeda")+(Inputs!$G$5:$G$140="acoes"))*Inputs!$B$1+((Inputs!$G$5:$G$140<>"moeda")*(Inputs!$G$5:$G$140<>"acoes")))*INDEX(Inputs!$K$5:$AJ$140,0,MATCH(J$2,Inputs!$K$4:$AJ$4,0)))+SUMPRODUCT((Inputs!$E$5:$E$140=$B6)*Inputs!$F$5:$F$140*(((Inputs!$G$5:$G$140="moeda")+(Inputs!$G$5:$G$140="acoes"))*Inputs!$B$1+((Inputs!$G$5:$G$140<>"moeda")*(Inputs!$G$5:$G$140<>"acoes")))*INDEX(Inputs!$K$5:$AJ$140,0,MATCH(J$2,Inputs!$K$4:$AJ$4,0))))) -> -772.7698 | K6: =IF(ISNA(MATCH(K$2,Inputs!$K$4:$AJ$4,0)),NA(),IF(SUMPRODUCT((Inputs!$A$5:$A$140=$B6)*ISNUMBER(INDEX(Inputs!$K$5:$AJ$140,0,MATCH(K$2,Inputs!$K$4:$AJ$4,0))))+SUMPRODUCT((Inputs!$C$5:$C$140=$B6)*ISNUMBER(INDEX(Inputs!$K$5:$AJ$140,0,MATCH(K$2,Inputs!$K$4:$AJ$4,0))))+SUMPRODUCT((Inputs!$E$5:$E$140=$B6)*ISNUMBER(INDEX(Inputs!$K$5:$AJ$140,0,MATCH(K$2,Inputs!$K$4:$AJ$4,0))))=0,NA(),SUMPRODUCT((Inputs!$A$5:$A$140=$B6)*Inputs!$B$5:$B$140*(((Inputs!$G$5:$G$140="moeda")+(Inputs!$G$5:$G$140="acoes"))*Inputs!$B$1+((Inputs!$G$5:$G$140<>"moeda")*(Inputs!$G$5:$G$140<>"acoes")))*INDEX(Inputs!$K$5:$AJ$140,0,MATCH(K$2,Inputs!$K$4:$AJ$4,0)))+SUMPRODUCT((Inputs!$C$5:$C$140=$B6)*Inputs!$D$5:$D$140*(((Inputs!$G$5:$G$140="moeda")+(Inputs!$G$5:$G$140="acoes"))*Inputs!$B$1+((Inputs!$G$5:$G$140<>"moeda")*(Inputs!$G$5:$G$140<>"acoes")))*INDEX(Inputs!$K$5:$AJ$140,0,MATCH(K$2,Inputs!$K$4:$AJ$4,0)))+SUMPRODUCT((Inputs!$E$5:$E$140=$B6)*Inputs!$F$5:$F$140*(((Inputs!$G$5:$G$140="moeda")+(Inputs!$G$5:$G$140="acoes"))*Inputs!$B$1+((Inputs!$G$5:$G$140<>"moeda")*(Inputs!$G$5:$G$140<>"acoes")))*INDEX(Inputs!$K$5:$AJ$140,0,MATCH(K$2,Inputs!$K$4:$AJ$4,0))))) -> -881.737 | L6: =IF(ISNA(MATCH(L$2,Inputs!$K$4:$AJ$4,0)),NA(),IF(SUMPRODUCT((Inputs!$A$5:$A$140=$B6)*ISNUMBER(INDEX(Inputs!$K$5:$AJ$140,0,MATCH(L$2,Inputs!$K$4:$AJ$4,0))))+SUMPRODUCT((Inputs!$C$5:$C$140=$B6)*ISNUMBER(INDEX(Inputs!$K$5:$AJ$140,0,MATCH(L$2,Inputs!$K$4:$AJ$4,0))))+SUMPRODUCT((Inputs!$E$5:$E$140=$B6)*ISNUMBER(INDEX(Inputs!$K$5:$AJ$140,0,MATCH(L$2,Inputs!$K$4:$AJ$4,0))))=0,NA(),SUMPRODUCT((Inputs!$A$5:$A$140=$B6)*Inputs!$B$5:$B$140*(((Inputs!$G$5:$G$140="moeda")+(Inputs!$G$5:$G$140="acoes"))*Inputs!$B$1+((Inputs!$G$5:$G$140<>"moeda")*(Inputs!$G$5:$G$140<>"acoes")))*INDEX(Inputs!$K$5:$AJ$140,0,MATCH(L$2,Inputs!$K$4:$AJ$4,0)))+SUMPRODUCT((Inputs!$C$5:$C$140=$B6)*Inputs!$D$5:$D$140*(((Inputs!$G$5:$G$140="moeda")+(Inputs!$G$5:$G$140="acoes"))*Inputs!$B$1+((Inputs!$G$5:$G$140<>"moeda")*(Inputs!$G$5:$G$140<>"acoes")))*INDEX(Inputs!$K$5:$AJ$140,0,MATCH(L$2,Inputs!$K$4:$AJ$4,0)))+SUMPRODUCT((Inputs!$E$5:$E$140=$B6)*Inputs!$F$5:$F$140*(((Inputs!$G$5:$G$140="moeda")+(Inputs!$G$5:$G$140="acoes"))*Inputs!$B$1+((Inputs!$G$5:$G$140<>"moeda")*(Inputs!$G$5:$G$140<>"acoes")))*INDEX(Inputs!$K$5:$AJ$140,0,MATCH(L$2,Inputs!$K$4:$AJ$4,0))))) -> -801.424 | M6: =SUM(I6:L6) -> -3179.64 | N6: =IF(ISNA(MATCH(N$2,Inputs!$K$4:$AJ$4,0)),NA(),IF(SUMPRODUCT((Inputs!$A$5:$A$140=$B6)*ISNUMBER(INDEX(Inputs!$K$5:$AJ$140,0,MATCH(N$2,Inputs!$K$4:$AJ$4,0))))+SUMPRODUCT((Inputs!$C$5:$C$140=$B6)*ISNUMBER(INDEX(Inputs!$K$5:$AJ$140,0,MATCH(N$2,Inputs!$K$4:$AJ$4,0))))+SUMPRODUCT((Inputs!$E$5:$E$140=$B6)*ISNUMBER(INDEX(Inputs!$K$5:$AJ$140,0,MATCH(N$2,Inputs!$K$4:$AJ$4,0))))=0,NA(),SUMPRODUCT((Inputs!$A$5:$A$140=$B6)*Inputs!$B$5:$B$140*(((Inputs!$G$5:$G$140="moeda")+(Inputs!$G$5:$G$140="acoes"))*Inputs!$B$1+((Inputs!$G$5:$G$140<>"moeda")*(Inputs!$G$5:$G$140<>"acoes")))*INDEX(Inputs!$K$5:$AJ$140,0,MATCH(N$2,Inputs!$K$4:$AJ$4,0)))+SUMPRODUCT((Inputs!$C$5:$C$140=$B6)*Inputs!$D$5:$D$140*(((Inputs!$G$5:$G$140="moeda")+(Inputs!$G$5:$G$140="acoes"))*Inputs!$B$1+((Inputs!$G$5:$G$140<>"moeda")*(Inputs!$G$5:$G$140<>"acoes")))*INDEX(Inputs!$K$5:$AJ$140,0,MATCH(N$2,Inputs!$K$4:$AJ$4,0)))+SUMPRODUCT((Inputs!$E$5:$E$140=$B6)*Inputs!$F$5:$F$140*(((Inputs!$G$5:$G$140="moeda")+(Inputs!$G$5:$G$140="acoes"))*Inputs!$B$1+((Inputs!$G$5:$G$140<>"moeda")*(Inputs!$G$5:$G$140<>"acoes")))*INDEX(Inputs!$K$5:$AJ$140,0,MATCH(N$2,Inputs!$K$4:$AJ$4,0))))) -> -882.38233 | O6: =IF(ISNA(MATCH(O$2,Inputs!$K$4:$AJ$4,0)),NA(),IF(SUMPRODUCT((Inputs!$A$5:$A$140=$B6)*ISNUMBER(INDEX(Inputs!$K$5:$AJ$140,0,MATCH(O$2,Inputs!$K$4:$AJ$4,0))))+SUMPRODUCT((Inputs!$C$5:$C$140=$B6)*ISNUMBER(INDEX(Inputs!$K$5:$AJ$140,0,MATCH(O$2,Inputs!$K$4:$AJ$4,0))))+SUMPRODUCT((Inputs!$E$5:$E$140=$B6)*ISNUMBER(INDEX(Inputs!$K$5:$AJ$140,0,MATCH(O$2,Inputs!$K$4:$AJ$4,0))))=0,NA(),SUMPRODUCT((Inputs!$A$5:$A$140=$B6)*Inputs!$B$5:$B$140*(((Inputs!$G$5:$G$140="moeda")+(Inputs!$G$5:$G$140="acoes"))*Inputs!$B$1+((Inputs!$G$5:$G$140<>"moeda")*(Inputs!$G$5:$G$140<>"acoes")))*INDEX(Inputs!$K$5:$AJ$140,0,MATCH(O$2,Inputs!$K$4:$AJ$4,0)))+SUMPRODUCT((Inputs!$C$5:$C$140=$B6)*Inputs!$D$5:$D$140*(((Inputs!$G$5:$G$140="moeda")+(Inputs!$G$5:$G$140="acoes"))*Inputs!$B$1+((Inputs!$G$5:$G$140<>"moeda")*(Inputs!$G$5:$G$140<>"acoes")))*INDEX(Inputs!$K$5:$AJ$140,0,MATCH(O$2,Inputs!$K$4:$AJ$4,0)))+SUMPRODUCT((Inputs!$E$5:$E$140=$B6)*Inputs!$F$5:$F$140*(((Inputs!$G$5:$G$140="moeda")+(Inputs!$G$5:$G$140="acoes"))*Inputs!$B$1+((Inputs!$G$5:$G$140<>"moeda")*(Inputs!$G$5:$G$140<>"acoes")))*INDEX(Inputs!$K$5:$AJ$140,0,MATCH(O$2,Inputs!$K$4:$AJ$4,0))))) -> -938.709 | P6: =IF(ISNA(MATCH(P$2,Inputs!$K$4:$AJ$4,0)),NA(),IF(SUMPRODUCT((Inputs!$A$5:$A$140=$B6)*ISNUMBER(INDEX(Inputs!$K$5:$AJ$140,0,MATCH(P$2,Inputs!$K$4:$AJ$4,0))))+SUMPRODUCT((Inputs!$C$5:$C$140=$B6)*ISNUMBER(INDEX(Inputs!$K$5:$AJ$140,0,MATCH(P$2,Inputs!$K$4:$AJ$4,0))))+SUMPRODUCT((Inputs!$E$5:$E$140=$B6)*ISNUMBER(INDEX(Inputs!$K$5:$AJ$140,0,MATCH(P$2,Inputs!$K$4:$AJ$4,0))))=0,NA(),SUMPRODUCT((Inputs!$A$5:$A$140=$B6)*Inputs!$B$5:$B$140*(((Inputs!$G$5:$G$140="moeda")+(Inputs!$G$5:$G$140="acoes"))*Inputs!$B$1+((Inputs!$G$5:$G$140<>"moeda")*(Inputs!$G$5:$G$140<>"acoes")))*INDEX(Inputs!$K$5:$AJ$140,0,MATCH(P$2,Inputs!$K$4:$AJ$4,0)))+SUMPRODUCT((Inputs!$C$5:$C$140=$B6)*Inputs!$D$5:$D$140*(((Inputs!$G$5:$G$140="moeda")+(Inputs!$G$5:$G$140="acoes"))*Inputs!$B$1+((Inputs!$G$5:$G$140<>"moeda")*(Inputs!$G$5:$G$140<>"acoes")))*INDEX(Inputs!$K$5:$AJ$140,0,MATCH(P$2,Inputs!$K$4:$AJ$4,0)))+SUMPRODUCT((Inputs!$E$5:$E$140=$B6)*Inputs!$F$5:$F$140*(((Inputs!$G$5:$G$140="moeda")+(Inputs!$G$5:$G$140="acoes"))*Inputs!$B$1+((Inputs!$G$5:$G$140<>"moeda")*(Inputs!$G$5:$G$140<>"acoes")))*INDEX(Inputs!$K$5:$AJ$140,0,MATCH(P$2,Inputs!$K$4:$AJ$4,0))))) -> -1048.17 | Q6: =IF(ISNA(MATCH(Q$2,Inputs!$K$4:$AJ$4,0)),NA(),IF(SUMPRODUCT((Inputs!$A$5:$A$140=$B6)*ISNUMBER(INDEX(Inputs!$K$5:$AJ$140,0,MATCH(Q$2,Inputs!$K$4:$AJ$4,0))))+SUMPRODUCT((Inputs!$C$5:$C$140=$B6)*ISNUMBER(INDEX(Inputs!$K$5:$AJ$140,0,MATCH(Q$2,Inputs!$K$4:$AJ$4,0))))+SUMPRODUCT((Inputs!$E$5:$E$140=$B6)*ISNUMBER(INDEX(Inputs!$K$5:$AJ$140,0,MATCH(Q$2,Inputs!$K$4:$AJ$4,0))))=0,NA(),SUMPRODUCT((Inputs!$A$5:$A$140=$B6)*Inputs!$B$5:$B$140*(((Inputs!$G$5:$G$140="moeda")+(Inputs!$G$5:$G$140="acoes"))*Inputs!$B$1+((Inputs!$G$5:$G$140<>"moeda")*(Inputs!$G$5:$G$140<>"acoes")))*INDEX(Inputs!$K$5:$AJ$140,0,MATCH(Q$2,Inputs!$K$4:$AJ$4,0)))+SUMPRODUCT((Inputs!$C$5:$C$140=$B6)*Inputs!$D$5:$D$140*(((Inputs!$G$5:$G$140="moeda")+(Inputs!$G$5:$G$140="acoes"))*Inputs!$B$1+((Inputs!$G$5:$G$140<>"moeda")*(Inputs!$G$5:$G$140<>"acoes")))*INDEX(Inputs!$K$5:$AJ$140,0,MATCH(Q$2,Inputs!$K$4:$AJ$4,0)))+SUMPRODUCT((Inputs!$E$5:$E$140=$B6)*Inputs!$F$5:$F$140*(((Inputs!$G$5:$G$140="moeda")+(Inputs!$G$5:$G$140="acoes"))*Inputs!$B$1+((Inputs!$G$5:$G$140<>"moeda")*(Inputs!$G$5:$G$140<>"acoes")))*INDEX(Inputs!$K$5:$AJ$140,0,MATCH(Q$2,Inputs!$K$4:$AJ$4,0))))) -> -1085.5705 | R6: =SUM(N6:Q6) -> -3954.8318 | S6: =IF(ISNA(MATCH(S$2,Inputs!$K$4:$AJ$4,0)),NA(),IF(SUMPRODUCT((Inputs!$A$5:$A$140=$B6)*ISNUMBER(INDEX(Inputs!$K$5:$AJ$140,0,MATCH(S$2,Inputs!$K$4:$AJ$4,0))))+SUMPRODUCT((Inputs!$C$5:$C$140=$B6)*ISNUMBER(INDEX(Inputs!$K$5:$AJ$140,0,MATCH(S$2,Inputs!$K$4:$AJ$4,0))))+SUMPRODUCT((Inputs!$E$5:$E$140=$B6)*ISNUMBER(INDEX(Inputs!$K$5:$AJ$140,0,MATCH(S$2,Inputs!$K$4:$AJ$4,0))))=0,NA(),SUMPRODUCT((Inputs!$A$5:$A$140=$B6)*Inputs!$B$5:$B$140*(((Inputs!$G$5:$G$140="moeda")+(Inputs!$G$5:$G$140="acoes"))*Inputs!$B$1+((Inputs!$G$5:$G$140<>"moeda")*(Inputs!$G$5:$G$140<>"acoes")))*INDEX(Inputs!$K$5:$AJ$140,0,MATCH(S$2,Inputs!$K$4:$AJ$4,0)))+SUMPRODUCT((Inputs!$C$5:$C$140=$B6)*Inputs!$D$5:$D$140*(((Inputs!$G$5:$G$140="moeda")+(Inputs!$G$5:$G$140="acoes"))*Inputs!$B$1+((Inputs!$G$5:$G$140<>"moeda")*(Inputs!$G$5:$G$140<>"acoes")))*INDEX(Inputs!$K$5:$AJ$140,0,MATCH(S$2,Inputs!$K$4:$AJ$4,0)))+SUMPRODUCT((Inputs!$E$5:$E$140=$B6)*Inputs!$F$5:$F$140*(((Inputs!$G$5:$G$140="moeda")+(Inputs!$G$5:$G$140="acoes"))*Inputs!$B$1+((Inputs!$G$5:$G$140<>"moeda")*(Inputs!$G$5:$G$140<>"acoes")))*INDEX(Inputs!$K$5:$AJ$140,0,MATCH(S$2,Inputs!$K$4:$AJ$4,0))))) -> -1139.7316 | T6: =IF(ISNA(MATCH(T$2,Inputs!$K$4:$AJ$4,0)),NA(),IF(SUMPRODUCT((Inputs!$A$5:$A$140=$B6)*ISNUMBER(INDEX(Inputs!$K$5:$AJ$140,0,MATCH(T$2,Inputs!$K$4:$AJ$4,0))))+SUMPRODUCT((Inputs!$C$5:$C$140=$B6)*ISNUMBER(INDEX(Inputs!$K$5:$AJ$140,0,MATCH(T$2,Inputs!$K$4:$AJ$4,0))))+SUMPRODUCT((Inputs!$E$5:$E$140=$B6)*ISNUMBER(INDEX(Inputs!$K$5:$AJ$140,0,MATCH(T$2,Inputs!$K$4:$AJ$4,0))))=0,NA(),SUMPRODUCT((Inputs!$A$5:$A$140=$B6)*Inputs!$B$5:$B$140*(((Inputs!$G$5:$G$140="moeda")+(Inputs!$G$5:$G$140="acoes"))*Inputs!$B$1+((Inputs!$G$5:$G$140<>"moeda")*(Inputs!$G$5:$G$140<>"acoes")))*INDEX(Inputs!$K$5:$AJ$140,0,MATCH(T$2,Inputs!$K$4:$AJ$4,0)))+SUMPRODUCT((Inputs!$C$5:$C$140=$B6)*Inputs!$D$5:$D$140*(((Inputs!$G$5:$G$140="moeda")+(Inputs!$G$5:$G$140="acoes"))*Inputs!$B$1+((Inputs!$G$5:$G$140<>"moeda")*(Inputs!$G$5:$G$140<>"acoes")))*INDEX(Inputs!$K$5:$AJ$140,0,MATCH(T$2,Inputs!$K$4:$AJ$4,0)))+SUMPRODUCT((Inputs!$E$5:$E$140=$B6)*Inputs!$F$5:$F$140*(((Inputs!$G$5:$G$140="moeda")+(Inputs!$G$5:$G$140="acoes"))*Inputs!$B$1+((Inputs!$G$5:$G$140<>"moeda")*(Inputs!$G$5:$G$140<>"acoes")))*INDEX(Inputs!$K$5:$AJ$140,0,MATCH(T$2,Inputs!$K$4:$AJ$4,0))))) -> -1169.752 | U6: =IF(ISNA(MATCH(U$2,Inputs!$K$4:$AJ$4,0)),NA(),IF(SUMPRODUCT((Inputs!$A$5:$A$140=$B6)*ISNUMBER(INDEX(Inputs!$K$5:$AJ$140,0,MATCH(U$2,Inputs!$K$4:$AJ$4,0))))+SUMPRODUCT((Inputs!$C$5:$C$140=$B6)*ISNUMBER(INDEX(Inputs!$K$5:$AJ$140,0,MATCH(U$2,Inputs!$K$4:$AJ$4,0))))+SUMPRODUCT((Inputs!$E$5:$E$140=$B6)*ISNUMBER(INDEX(Inputs!$K$5:$AJ$140,0,MATCH(U$2,Inputs!$K$4:$AJ$4,0))))=0,NA(),SUMPRODUCT((Inputs!$A$5:$A$140=$B6)*Inputs!$B$5:$B$140*(((Inputs!$G$5:$G$140="moeda")+(Inputs!$G$5:$G$140="acoes"))*Inputs!$B$1+((Inputs!$G$5:$G$140<>"moeda")*(Inputs!$G$5:$G$140<>"acoes")))*INDEX(Inputs!$K$5:$AJ$140,0,MATCH(U$2,Inputs!$K$4:$AJ$4,0)))+SUMPRODUCT((Inputs!$C$5:$C$140=$B6)*Inputs!$D$5:$D$140*(((Inputs!$G$5:$G$140="moeda")+(Inputs!$G$5:$G$140="acoes"))*Inputs!$B$1+((Inputs!$G$5:$G$140<>"moeda")*(Inputs!$G$5:$G$140<>"acoes")))*INDEX(Inputs!$K$5:$AJ$140,0,MATCH(U$2,Inputs!$K$4:$AJ$4,0)))+SUMPRODUCT((Inputs!$E$5:$E$140=$B6)*Inputs!$F$5:$F$140*(((Inputs!$G$5:$G$140="moeda")+(Inputs!$G$5:$G$140="acoes"))*Inputs!$B$1+((Inputs!$G$5:$G$140<>"moeda")*(Inputs!$G$5:$G$140<>"acoes")))*INDEX(Inputs!$K$5:$AJ$140,0,MATCH(U$2,Inputs!$K$4:$AJ$4,0))))) -> -1209.442 | V6: =IF(ISNA(MATCH(V$2,Inputs!$K$4:$AJ$4,0)),NA(),IF(SUMPRODUCT((Inputs!$A$5:$A$140=$B6)*ISNUMBER(INDEX(Inputs!$K$5:$AJ$140,0,MATCH(V$2,Inputs!$K$4:$AJ$4,0))))+SUMPRODUCT((Inputs!$C$5:$C$140=$B6)*ISNUMBER(INDEX(Inputs!$K$5:$AJ$140,0,MATCH(V$2,Inputs!$K$4:$AJ$4,0))))+SUMPRODUCT((Inputs!$E$5:$E$140=$B6)*ISNUMBER(INDEX(Inputs!$K$5:$AJ$140,0,MATCH(V$2,Inputs!$K$4:$AJ$4,0))))=0,NA(),SUMPRODUCT((Inputs!$A$5:$A$140=$B6)*Inputs!$B$5:$B$140*(((Inputs!$G$5:$G$140="moeda")+(Inputs!$G$5:$G$140="acoes"))*Inputs!$B$1+((Inputs!$G$5:$G$140<>"moeda")*(Inputs!$G$5:$G$140<>"acoes")))*INDEX(Inputs!$K$5:$AJ$140,0,MATCH(V$2,Inputs!$K$4:$AJ$4,0)))+SUMPRODUCT((Inputs!$C$5:$C$140=$B6)*Inputs!$D$5:$D$140*(((Inputs!$G$5:$G$140="moeda")+(Inputs!$G$5:$G$140="acoes"))*Inputs!$B$1+((Inputs!$G$5:$G$140<>"moeda")*(Inputs!$G$5:$G$140<>"acoes")))*INDEX(Inputs!$K$5:$AJ$140,0,MATCH(V$2,Inputs!$K$4:$AJ$4,0)))+SUMPRODUCT((Inputs!$E$5:$E$140=$B6)*Inputs!$F$5:$F$140*(((Inputs!$G$5:$G$140="moeda")+(Inputs!$G$5:$G$140="acoes"))*Inputs!$B$1+((Inputs!$G$5:$G$140<>"moeda")*(Inputs!$G$5:$G$140<>"acoes")))*INDEX(Inputs!$K$5:$AJ$140,0,MATCH(V$2,Inputs!$K$4:$AJ$4,0))))) -> -1273.5865 | W6: =SUM(S6:V6) -> -4792.5121 | X6: =IF(ISNA(MATCH(X$2,Inputs!$K$4:$AJ$4,0)),NA(),IF(SUMPRODUCT((Inputs!$A$5:$A$140=$B6)*ISNUMBER(INDEX(Inputs!$K$5:$AJ$140,0,MATCH(X$2,Inputs!$K$4:$AJ$4,0))))+SUMPRODUCT((Inputs!$C$5:$C$140=$B6)*ISNUMBER(INDEX(Inputs!$K$5:$AJ$140,0,MATCH(X$2,Inputs!$K$4:$AJ$4,0))))+SUMPRODUCT((Inputs!$E$5:$E$140=$B6)*ISNUMBER(INDEX(Inputs!$K$5:$AJ$140,0,MATCH(X$2,Inputs!$K$4:$AJ$4,0))))=0,NA(),SUMPRODUCT((Inputs!$A$5:$A$140=$B6)*Inputs!$B$5:$B$140*(((Inputs!$G$5:$G$140="moeda")+(Inputs!$G$5:$G$140="acoes"))*Inputs!$B$1+((Inputs!$G$5:$G$140<>"moeda")*(Inputs!$G$5:$G$140<>"acoes")))*INDEX(Inputs!$K$5:$AJ$140,0,MATCH(X$2,Inputs!$K$4:$AJ$4,0)))+SUMPRODUCT((Inputs!$C$5:$C$140=$B6)*Inputs!$D$5:$D$140*(((Inputs!$G$5:$G$140="moeda")+(Inputs!$G$5:$G$140="acoes"))*Inputs!$B$1+((Inputs!$G$5:$G$140<>"moeda")*(Inputs!$G$5:$G$140<>"acoes")))*INDEX(Inputs!$K$5:$AJ$140,0,MATCH(X$2,Inputs!$K$4:$AJ$4,0)))+SUMPRODUCT((Inputs!$E$5:$E$140=$B6)*Inputs!$F$5:$F$140*(((Inputs!$G$5:$G$140="moeda")+(Inputs!$G$5:$G$140="acoes"))*Inputs!$B$1+((Inputs!$G$5:$G$140<>"moeda")*(Inputs!$G$5:$G$140<>"acoes")))*INDEX(Inputs!$K$5:$AJ$140,0,MATCH(X$2,Inputs!$K$4:$AJ$4,0))))) -> -1266.711 | Y6: =IF(ISNA(MATCH(Y$2,Inputs!$K$4:$AJ$4,0)),NA(),IF(SUMPRODUCT((Inputs!$A$5:$A$140=$B6)*ISNUMBER(INDEX(Inputs!$K$5:$AJ$140,0,MATCH(Y$2,Inputs!$K$4:$AJ$4,0))))+SUMPRODUCT((Inputs!$C$5:$C$140=$B6)*ISNUMBER(INDEX(Inputs!$K$5:$AJ$140,0,MATCH(Y$2,Inputs!$K$4:$AJ$4,0))))+SUMPRODUCT((Inputs!$E$5:$E$140=$B6)*ISNUMBER(INDEX(Inputs!$K$5:$AJ$140,0,MATCH(Y$2,Inputs!$K$4:$AJ$4,0))))=0,NA(),SUMPRODUCT((Inputs!$A$5:$A$140=$B6)*Inputs!$B$5:$B$140*(((Inputs!$G$5:$G$140="moeda")+(Inputs!$G$5:$G$140="acoes"))*Inputs!$B$1+((Inputs!$G$5:$G$140<>"moeda")*(Inputs!$G$5:$G$140<>"acoes")))*INDEX(Inputs!$K$5:$AJ$140,0,MATCH(Y$2,Inputs!$K$4:$AJ$4,0)))+SUMPRODUCT((Inputs!$C$5:$C$140=$B6)*Inputs!$D$5:$D$140*(((Inputs!$G$5:$G$140="moeda")+(Inputs!$G$5:$G$140="acoes"))*Inputs!$B$1+((Inputs!$G$5:$G$140<>"moeda")*(Inputs!$G$5:$G$140<>"acoes")))*INDEX(Inputs!$K$5:$AJ$140,0,MATCH(Y$2,Inputs!$K$4:$AJ$4,0)))+SUMPRODUCT((Inputs!$E$5:$E$140=$B6)*Inputs!$F$5:$F$140*(((Inputs!$G$5:$G$140="moeda")+(Inputs!$G$5:$G$140="acoes"))*Inputs!$B$1+((Inputs!$G$5:$G$140<>"moeda")*(Inputs!$G$5:$G$140<>"acoes")))*INDEX(Inputs!$K$5:$AJ$140,0,MATCH(Y$2,Inputs!$K$4:$AJ$4,0))))) -> -1318.147 | Z6: =IF(ISNA(MATCH(Z$2,Inputs!$K$4:$AJ$4,0)),NA(),IF(SUMPRODUCT((Inputs!$A$5:$A$140=$B6)*ISNUMBER(INDEX(Inputs!$K$5:$AJ$140,0,MATCH(Z$2,Inputs!$K$4:$AJ$4,0))))+SUMPRODUCT((Inputs!$C$5:$C$140=$B6)*ISNUMBER(INDEX(Inputs!$K$5:$AJ$140,0,MATCH(Z$2,Inputs!$K$4:$AJ$4,0))))+SUMPRODUCT((Inputs!$E$5:$E$140=$B6)*ISNUMBER(INDEX(Inputs!$K$5:$AJ$140,0,MATCH(Z$2,Inputs!$K$4:$AJ$4,0))))=0,NA(),SUMPRODUCT((Inputs!$A$5:$A$140=$B6)*Inputs!$B$5:$B$140*(((Inputs!$G$5:$G$140="moeda")+(Inputs!$G$5:$G$140="acoes"))*Inputs!$B$1+((Inputs!$G$5:$G$140<>"moeda")*(Inputs!$G$5:$G$140<>"acoes")))*INDEX(Inputs!$K$5:$AJ$140,0,MATCH(Z$2,Inputs!$K$4:$AJ$4,0)))+SUMPRODUCT((Inputs!$C$5:$C$140=$B6)*Inputs!$D$5:$D$140*(((Inputs!$G$5:$G$140="moeda")+(Inputs!$G$5:$G$140="acoes"))*Inputs!$B$1+((Inputs!$G$5:$G$140<>"moeda")*(Inputs!$G$5:$G$140<>"acoes")))*INDEX(Inputs!$K$5:$AJ$140,0,MATCH(Z$2,Inputs!$K$4:$AJ$4,0)))+SUMPRODUCT((Inputs!$E$5:$E$140=$B6)*Inputs!$F$5:$F$140*(((Inputs!$G$5:$G$140="moeda")+(Inputs!$G$5:$G$140="acoes"))*Inputs!$B$1+((Inputs!$G$5:$G$140<>"moeda")*(Inputs!$G$5:$G$140<>"acoes")))*INDEX(Inputs!$K$5:$AJ$140,0,MATCH(Z$2,Inputs!$K$4:$AJ$4,0))))) -> -1459.552 | AA6: =IF(ISNA(MATCH(AA$2,Inputs!$K$4:$AJ$4,0)),NA(),IF(SUMPRODUCT((Inputs!$A$5:$A$140=$B6)*ISNUMBER(INDEX(Inputs!$K$5:$AJ$140,0,MATCH(AA$2,Inputs!$K$4:$AJ$4,0))))+SUMPRODUCT((Inputs!$C$5:$C$140=$B6)*ISNUMBER(INDEX(Inputs!$K$5:$AJ$140,0,MATCH(AA$2,Inputs!$K$4:$AJ$4,0))))+SUMPRODUCT((Inputs!$E$5:$E$140=$B6)*ISNUMBER(INDEX(Inputs!$K$5:$AJ$140,0,MATCH(AA$2,Inputs!$K$4:$AJ$4,0))))=0,NA(),SUMPRODUCT((Inputs!$A$5:$A$140=$B6)*Inputs!$B$5:$B$140*(((Inputs!$G$5:$G$140="moeda")+(Inputs!$G$5:$G$140="acoes"))*Inputs!$B$1+((Inputs!$G$5:$G$140<>"moeda")*(Inputs!$G$5:$G$140<>"acoes")))*INDEX(Inputs!$K$5:$AJ$140,0,MATCH(AA$2,Inputs!$K$4:$AJ$4,0)))+SUMPRODUCT((Inputs!$C$5:$C$140=$B6)*Inputs!$D$5:$D$140*(((Inputs!$G$5:$G$140="moeda")+(Inputs!$G$5:$G$140="acoes"))*Inputs!$B$1+((Inputs!$G$5:$G$140<>"moeda")*(Inputs!$G$5:$G$140<>"acoes")))*INDEX(Inputs!$K$5:$AJ$140,0,MATCH(AA$2,Inputs!$K$4:$AJ$4,0)))+SUMPRODUCT((Inputs!$E$5:$E$140=$B6)*Inputs!$F$5:$F$140*(((Inputs!$G$5:$G$140="moeda")+(Inputs!$G$5:$G$140="acoes"))*Inputs!$B$1+((Inputs!$G$5:$G$140<>"moeda")*(Inputs!$G$5:$G$140<>"acoes")))*INDEX(Inputs!$K$5:$AJ$140,0,MATCH(AA$2,Inputs!$K$4:$AJ$4,0))))) -> -1762.2062 | AB6: =SUM(X6:AA6) -> -5806.6162 | AC6: =IF(ISNA(MATCH(AC$2,Inputs!$K$4:$AJ$4,0)),NA(),IF(SUMPRODUCT((Inputs!$A$5:$A$140=$B6)*ISNUMBER(INDEX(Inputs!$K$5:$AJ$140,0,MATCH(AC$2,Inputs!$K$4:$AJ$4,0))))+SUMPRODUCT((Inputs!$C$5:$C$140=$B6)*ISNUMBER(INDEX(Inputs!$K$5:$AJ$140,0,MATCH(AC$2,Inputs!$K$4:$AJ$4,0))))+SUMPRODUCT((Inputs!$E$5:$E$140=$B6)*ISNUMBER(INDEX(Inputs!$K$5:$AJ$140,0,MATCH(AC$2,Inputs!$K$4:$AJ$4,0))))=0,NA(),SUMPRODUCT((Inputs!$A$5:$A$140=$B6)*Inputs!$B$5:$B$140*(((Inputs!$G$5:$G$140="moeda")+(Inputs!$G$5:$G$140="acoes"))*Inputs!$B$1+((Inputs!$G$5:$G$140<>"moeda")*(Inputs!$G$5:$G$140<>"acoes")))*INDEX(Inputs!$K$5:$AJ$140,0,MATCH(AC$2,Inputs!$K$4:$AJ$4,0)))+SUMPRODUCT((Inputs!$C$5:$C$140=$B6)*Inputs!$D$5:$D$140*(((Inputs!$G$5:$G$140="moeda")+(Inputs!$G$5:$G$140="acoes"))*Inputs!$B$1+((Inputs!$G$5:$G$140<>"moeda")*(Inputs!$G$5:$G$140<>"acoes")))*INDEX(Inputs!$K$5:$AJ$140,0,MATCH(AC$2,Inputs!$K$4:$AJ$4,0)))+SUMPRODUCT((Inputs!$E$5:$E$140=$B6)*Inputs!$F$5:$F$140*(((Inputs!$G$5:$G$140="moeda")+(Inputs!$G$5:$G$140="acoes"))*Inputs!$B$1+((Inputs!$G$5:$G$140<>"moeda")*(Inputs!$G$5:$G$140<>"acoes")))*INDEX(Inputs!$K$5:$AJ$140,0,MATCH(AC$2,Inputs!$K$4:$AJ$4,0))))) -> -1607.468 | AD6: =IF(ISNA(MATCH(AD$2,Inputs!$K$4:$AJ$4,0)),NA(),IF(SUMPRODUCT((Inputs!$A$5:$A$140=$B6)*ISNUMBER(INDEX(Inputs!$K$5:$AJ$140,0,MATCH(AD$2,Inputs!$K$4:$AJ$4,0))))+SUMPRODUCT((Inputs!$C$5:$C$140=$B6)*ISNUMBER(INDEX(Inputs!$K$5:$AJ$140,0,MATCH(AD$2,Inputs!$K$4:$AJ$4,0))))+SUMPRODUCT((Inputs!$E$5:$E$140=$B6)*ISNUMBER(INDEX(Inputs!$K$5:$AJ$140,0,MATCH(AD$2,Inputs!$K$4:$AJ$4,0))))=0,NA(),SUMPRODUCT((Inputs!$A$5:$A$140=$B6)*Inputs!$B$5:$B$140*(((Inputs!$G$5:$G$140="moeda")+(Inputs!$G$5:$G$140="acoes"))*Inputs!$B$1+((Inputs!$G$5:$G$140<>"moeda")*(Inputs!$G$5:$G$140<>"acoes")))*INDEX(Inputs!$K$5:$AJ$140,0,MATCH(AD$2,Inputs!$K$4:$AJ$4,0)))+SUMPRODUCT((Inputs!$C$5:$C$140=$B6)*Inputs!$D$5:$D$140*(((Inputs!$G$5:$G$140="moeda")+(Inputs!$G$5:$G$140="acoes"))*Inputs!$B$1+((Inputs!$G$5:$G$140<>"moeda")*(Inputs!$G$5:$G$140<>"acoes")))*INDEX(Inputs!$K$5:$AJ$140,0,MATCH(AD$2,Inputs!$K$4:$AJ$4,0)))+SUMPRODUCT((Inputs!$E$5:$E$140=$B6)*Inputs!$F$5:$F$140*(((Inputs!$G$5:$G$140="moeda")+(Inputs!$G$5:$G$140="acoes"))*Inputs!$B$1+((Inputs!$G$5:$G$140<>"moeda")*(Inputs!$G$5:$G$140<>"acoes")))*INDEX(Inputs!$K$5:$AJ$140,0,MATCH(AD$2,Inputs!$K$4:$AJ$4,0))))) -> -1629.588 | AE6: =IF(ISNA(MATCH(AE$2,Inputs!$K$4:$AJ$4,0)),NA(),IF(SUMPRODUCT((Inputs!$A$5:$A$140=$B6)*ISNUMBER(INDEX(Inputs!$K$5:$AJ$140,0,MATCH(AE$2,Inputs!$K$4:$AJ$4,0))))+SUMPRODUCT((Inputs!$C$5:$C$140=$B6)*ISNUMBER(INDEX(Inputs!$K$5:$AJ$140,0,MATCH(AE$2,Inputs!$K$4:$AJ$4,0))))+SUMPRODUCT((Inputs!$E$5:$E$140=$B6)*ISNUMBER(INDEX(Inputs!$K$5:$AJ$140,0,MATCH(AE$2,Inputs!$K$4:$AJ$4,0))))=0,NA(),SUMPRODUCT((Inputs!$A$5:$A$140=$B6)*Inputs!$B$5:$B$140*(((Inputs!$G$5:$G$140="moeda")+(Inputs!$G$5:$G$140="acoes"))*Inputs!$B$1+((Inputs!$G$5:$G$140<>"moeda")*(Inputs!$G$5:$G$140<>"acoes")))*INDEX(Inputs!$K$5:$AJ$140,0,MATCH(AE$2,Inputs!$K$4:$AJ$4,0)))+SUMPRODUCT((Inputs!$C$5:$C$140=$B6)*Inputs!$D$5:$D$140*(((Inputs!$G$5:$G$140="moeda")+(Inputs!$G$5:$G$140="acoes"))*Inputs!$B$1+((Inputs!$G$5:$G$140<>"moeda")*(Inputs!$G$5:$G$140<>"acoes")))*INDEX(Inputs!$K$5:$AJ$140,0,MATCH(AE$2,Inputs!$K$4:$AJ$4,0)))+SUMPRODUCT((Inputs!$E$5:$E$140=$B6)*Inputs!$F$5:$F$140*(((Inputs!$G$5:$G$140="moeda")+(Inputs!$G$5:$G$140="acoes"))*Inputs!$B$1+((Inputs!$G$5:$G$140<>"moeda")*(Inputs!$G$5:$G$140<>"acoes")))*INDEX(Inputs!$K$5:$AJ$140,0,MATCH(AE$2,Inputs!$K$4:$AJ$4,0))))) -> #N/A | AF6: =IF(ISNA(MATCH(AF$2,Inputs!$K$4:$AJ$4,0)),NA(),IF(SUMPRODUCT((Inputs!$A$5:$A$140=$B6)*ISNUMBER(INDEX(Inputs!$K$5:$AJ$140,0,MATCH(AF$2,Inputs!$K$4:$AJ$4,0))))+SUMPRODUCT((Inputs!$C$5:$C$140=$B6)*ISNUMBER(INDEX(Inputs!$K$5:$AJ$140,0,MATCH(AF$2,Inputs!$K$4:$AJ$4,0))))+SUMPRODUCT((Inputs!$E$5:$E$140=$B6)*ISNUMBER(INDEX(Inputs!$K$5:$AJ$140,0,MATCH(AF$2,Inputs!$K$4:$AJ$4,0))))=0,NA(),SUMPRODUCT((Inputs!$A$5:$A$140=$B6)*Inputs!$B$5:$B$140*(((Inputs!$G$5:$G$140="moeda")+(Inputs!$G$5:$G$140="acoes"))*Inputs!$B$1+((Inputs!$G$5:$G$140<>"moeda")*(Inputs!$G$5:$G$140<>"acoes")))*INDEX(Inputs!$K$5:$AJ$140,0,MATCH(AF$2,Inputs!$K$4:$AJ$4,0)))+SUMPRODUCT((Inputs!$C$5:$C$140=$B6)*Inputs!$D$5:$D$140*(((Inputs!$G$5:$G$140="moeda")+(Inputs!$G$5:$G$140="acoes"))*Inputs!$B$1+((Inputs!$G$5:$G$140<>"moeda")*(Inputs!$G$5:$G$140<>"acoes")))*INDEX(Inputs!$K$5:$AJ$140,0,MATCH(AF$2,Inputs!$K$4:$AJ$4,0)))+SUMPRODUCT((Inputs!$E$5:$E$140=$B6)*Inputs!$F$5:$F$140*(((Inputs!$G$5:$G$140="moeda")+(Inputs!$G$5:$G$140="acoes"))*Inputs!$B$1+((Inputs!$G$5:$G$140<>"moeda")*(Inputs!$G$5:$G$140<>"acoes")))*INDEX(Inputs!$K$5:$AJ$140,0,MATCH(AF$2,Inputs!$K$4:$AJ$4,0))))) -> #N/A | AG6: =SUM(AC6:AF6) -> #N/A | AH6: =IF(ISNA(MATCH(AH$2,Inputs!$K$4:$AJ$4,0)),NA(),IF(SUMPRODUCT((Inputs!$A$5:$A$140=$B6)*ISNUMBER(INDEX(Inputs!$K$5:$AJ$140,0,MATCH(AH$2,Inputs!$K$4:$AJ$4,0))))+SUMPRODUCT((Inputs!$C$5:$C$140=$B6)*ISNUMBER(INDEX(Inputs!$K$5:$AJ$140,0,MATCH(AH$2,Inputs!$K$4:$AJ$4,0))))+SUMPRODUCT((Inputs!$E$5:$E$140=$B6)*ISNUMBER(INDEX(Inputs!$K$5:$AJ$140,0,MATCH(AH$2,Inputs!$K$4:$AJ$4,0))))=0,NA(),SUMPRODUCT((Inputs!$A$5:$A$140=$B6)*Inputs!$B$5:$B$140*(((Inputs!$G$5:$G$140="moeda")+(Inputs!$G$5:$G$140="acoes"))*Inputs!$B$1+((Inputs!$G$5:$G$140<>"moeda")*(Inputs!$G$5:$G$140<>"acoes")))*INDEX(Inputs!$K$5:$AJ$140,0,MATCH(AH$2,Inputs!$K$4:$AJ$4,0)))+SUMPRODUCT((Inputs!$C$5:$C$140=$B6)*Inputs!$D$5:$D$140*(((Inputs!$G$5:$G$140="moeda")+(Inputs!$G$5:$G$140="acoes"))*Inputs!$B$1+((Inputs!$G$5:$G$140<>"moeda")*(Inputs!$G$5:$G$140<>"acoes")))*INDEX(Inputs!$K$5:$AJ$140,0,MATCH(AH$2,Inputs!$K$4:$AJ$4,0)))+SUMPRODUCT((Inputs!$E$5:$E$140=$B6)*Inputs!$F$5:$F$140*(((Inputs!$G$5:$G$140="moeda")+(Inputs!$G$5:$G$140="acoes"))*Inputs!$B$1+((Inputs!$G$5:$G$140<>"moeda")*(Inputs!$G$5:$G$140<>"acoes")))*INDEX(Inputs!$K$5:$AJ$140,0,MATCH(AH$2,Inputs!$K$4:$AJ$4,0))))) -> -424.46615 | AI6: =IF(ISNA(MATCH(AI$2,Inputs!$K$4:$AJ$4,0)),NA(),IF(SUMPRODUCT((Inputs!$A$5:$A$140=$B6)*ISNUMBER(INDEX(Inputs!$K$5:$AJ$140,0,MATCH(AI$2,Inputs!$K$4:$AJ$4,0))))+SUMPRODUCT((Inputs!$C$5:$C$140=$B6)*ISNUMBER(INDEX(Inputs!$K$5:$AJ$140,0,MATCH(AI$2,Inputs!$K$4:$AJ$4,0))))+SUMPRODUCT((Inputs!$E$5:$E$140=$B6)*ISNUMBER(INDEX(Inputs!$K$5:$AJ$140,0,MATCH(AI$2,Inputs!$K$4:$AJ$4,0))))=0,NA(),SUMPRODUCT((Inputs!$A$5:$A$140=$B6)*Inputs!$B$5:$B$140*(((Inputs!$G$5:$G$140="moeda")+(Inputs!$G$5:$G$140="acoes"))*Inputs!$B$1+((Inputs!$G$5:$G$140<>"moeda")*(Inputs!$G$5:$G$140<>"acoes")))*INDEX(Inputs!$K$5:$AJ$140,0,MATCH(AI$2,Inputs!$K$4:$AJ$4,0)))+SUMPRODUCT((Inputs!$C$5:$C$140=$B6)*Inputs!$D$5:$D$140*(((Inputs!$G$5:$G$140="moeda")+(Inputs!$G$5:$G$140="acoes"))*Inputs!$B$1+((Inputs!$G$5:$G$140<>"moeda")*(Inputs!$G$5:$G$140<>"acoes")))*INDEX(Inputs!$K$5:$AJ$140,0,MATCH(AI$2,Inputs!$K$4:$AJ$4,0)))+SUMPRODUCT((Inputs!$E$5:$E$140=$B6)*Inputs!$F$5:$F$140*(((Inputs!$G$5:$G$140="moeda")+(Inputs!$G$5:$G$140="acoes"))*Inputs!$B$1+((Inputs!$G$5:$G$140<>"moeda")*(Inputs!$G$5:$G$140<>"acoes")))*INDEX(Inputs!$K$5:$AJ$140,0,MATCH(AI$2,Inputs!$K$4:$AJ$4,0))))) -> -400.67385 | AJ6: =IF(ISNA(MATCH(AJ$2,Inputs!$K$4:$AJ$4,0)),NA(),IF(SUMPRODUCT((Inputs!$A$5:$A$140=$B6)*ISNUMBER(INDEX(Inputs!$K$5:$AJ$140,0,MATCH(AJ$2,Inputs!$K$4:$AJ$4,0))))+SUMPRODUCT((Inputs!$C$5:$C$140=$B6)*ISNUMBER(INDEX(Inputs!$K$5:$AJ$140,0,MATCH(AJ$2,Inputs!$K$4:$AJ$4,0))))+SUMPRODUCT((Inputs!$E$5:$E$140=$B6)*ISNUMBER(INDEX(Inputs!$K$5:$AJ$140,0,MATCH(AJ$2,Inputs!$K$4:$AJ$4,0))))=0,NA(),SUMPRODUCT((Inputs!$A$5:$A$140=$B6)*Inputs!$B$5:$B$140*(((Inputs!$G$5:$G$140="moeda")+(Inputs!$G$5:$G$140="acoes"))*Inputs!$B$1+((Inputs!$G$5:$G$140<>"moeda")*(Inputs!$G$5:$G$140<>"acoes")))*INDEX(Inputs!$K$5:$AJ$140,0,MATCH(AJ$2,Inputs!$K$4:$AJ$4,0)))+SUMPRODUCT((Inputs!$C$5:$C$140=$B6)*Inputs!$D$5:$D$140*(((Inputs!$G$5:$G$140="moeda")+(Inputs!$G$5:$G$140="acoes"))*Inputs!$B$1+((Inputs!$G$5:$G$140<>"moeda")*(Inputs!$G$5:$G$140<>"acoes")))*INDEX(Inputs!$K$5:$AJ$140,0,MATCH(AJ$2,Inputs!$K$4:$AJ$4,0)))+SUMPRODUCT((Inputs!$E$5:$E$140=$B6)*Inputs!$F$5:$F$140*(((Inputs!$G$5:$G$140="moeda")+(Inputs!$G$5:$G$140="acoes"))*Inputs!$B$1+((Inputs!$G$5:$G$140<>"moeda")*(Inputs!$G$5:$G$140<>"acoes")))*INDEX(Inputs!$K$5:$AJ$140,0,MATCH(AJ$2,Inputs!$K$4:$AJ$4,0))))) -> -518.741 | AK6: =IF(ISNA(MATCH(AK$2,Inputs!$K$4:$AJ$4,0)),NA(),IF(SUMPRODUCT((Inputs!$A$5:$A$140=$B6)*ISNUMBER(INDEX(Inputs!$K$5:$AJ$140,0,MATCH(AK$2,Inputs!$K$4:$AJ$4,0))))+SUMPRODUCT((Inputs!$C$5:$C$140=$B6)*ISNUMBER(INDEX(Inputs!$K$5:$AJ$140,0,MATCH(AK$2,Inputs!$K$4:$AJ$4,0))))+SUMPRODUCT((Inputs!$E$5:$E$140=$B6)*ISNUMBER(INDEX(Inputs!$K$5:$AJ$140,0,MATCH(AK$2,Inputs!$K$4:$AJ$4,0))))=0,NA(),SUMPRODUCT((Inputs!$A$5:$A$140=$B6)*Inputs!$B$5:$B$140*(((Inputs!$G$5:$G$140="moeda")+(Inputs!$G$5:$G$140="acoes"))*Inputs!$B$1+((Inputs!$G$5:$G$140<>"moeda")*(Inputs!$G$5:$G$140<>"acoes")))*INDEX(Inputs!$K$5:$AJ$140,0,MATCH(AK$2,Inputs!$K$4:$AJ$4,0)))+SUMPRODUCT((Inputs!$C$5:$C$140=$B6)*Inputs!$D$5:$D$140*(((Inputs!$G$5:$G$140="moeda")+(Inputs!$G$5:$G$140="acoes"))*Inputs!$B$1+((Inputs!$G$5:$G$140<>"moeda")*(Inputs!$G$5:$G$140<>"acoes")))*INDEX(Inputs!$K$5:$AJ$140,0,MATCH(AK$2,Inputs!$K$4:$AJ$4,0)))+SUMPRODUCT((Inputs!$E$5:$E$140=$B6)*Inputs!$F$5:$F$140*(((Inputs!$G$5:$G$140="moeda")+(Inputs!$G$5:$G$140="acoes"))*Inputs!$B$1+((Inputs!$G$5:$G$140<>"moeda")*(Inputs!$G$5:$G$140<>"acoes")))*INDEX(Inputs!$K$5:$AJ$140,0,MATCH(AK$2,Inputs!$K$4:$AJ$4,0))))) -> -595.881 | AL6: =SUM(AH6:AK6) -> -1939.762
B7: 4 | C7: D&A | D7: =IF(ISNA(MATCH(D$2,Inputs!$K$4:$AJ$4,0)),NA(),IF(SUMPRODUCT((Inputs!$A$5:$A$140=$B7)*ISNUMBER(INDEX(Inputs!$K$5:$AJ$140,0,MATCH(D$2,Inputs!$K$4:$AJ$4,0))))+SUMPRODUCT((Inputs!$C$5:$C$140=$B7)*ISNUMBER(INDEX(Inputs!$K$5:$AJ$140,0,MATCH(D$2,Inputs!$K$4:$AJ$4,0))))+SUMPRODUCT((Inputs!$E$5:$E$140=$B7)*ISNUMBER(INDEX(Inputs!$K$5:$AJ$140,0,MATCH(D$2,Inputs!$K$4:$AJ$4,0))))=0,NA(),SUMPRODUCT((Inputs!$A$5:$A$140=$B7)*Inputs!$B$5:$B$140*(((Inputs!$G$5:$G$140="moeda")+(Inputs!$G$5:$G$140="acoes"))*Inputs!$B$1+((Inputs!$G$5:$G$140<>"moeda")*(Inputs!$G$5:$G$140<>"acoes")))*INDEX(Inputs!$K$5:$AJ$140,0,MATCH(D$2,Inputs!$K$4:$AJ$4,0)))+SUMPRODUCT((Inputs!$C$5:$C$140=$B7)*Inputs!$D$5:$D$140*(((Inputs!$G$5:$G$140="moeda")+(Inputs!$G$5:$G$140="acoes"))*Inputs!$B$1+((Inputs!$G$5:$G$140<>"moeda")*(Inputs!$G$5:$G$140<>"acoes")))*INDEX(Inputs!$K$5:$AJ$140,0,MATCH(D$2,Inputs!$K$4:$AJ$4,0)))+SUMPRODUCT((Inputs!$E$5:$E$140=$B7)*Inputs!$F$5:$F$140*(((Inputs!$G$5:$G$140="moeda")+(Inputs!$G$5:$G$140="acoes"))*Inputs!$B$1+((Inputs!$G$5:$G$140<>"moeda")*(Inputs!$G$5:$G$140<>"acoes")))*INDEX(Inputs!$K$5:$AJ$140,0,MATCH(D$2,Inputs!$K$4:$AJ$4,0))))) -> -57.729 | E7: =IF(ISNA(MATCH(E$2,Inputs!$K$4:$AJ$4,0)),NA(),IF(SUMPRODUCT((Inputs!$A$5:$A$140=$B7)*ISNUMBER(INDEX(Inputs!$K$5:$AJ$140,0,MATCH(E$2,Inputs!$K$4:$AJ$4,0))))+SUMPRODUCT((Inputs!$C$5:$C$140=$B7)*ISNUMBER(INDEX(Inputs!$K$5:$AJ$140,0,MATCH(E$2,Inputs!$K$4:$AJ$4,0))))+SUMPRODUCT((Inputs!$E$5:$E$140=$B7)*ISNUMBER(INDEX(Inputs!$K$5:$AJ$140,0,MATCH(E$2,Inputs!$K$4:$AJ$4,0))))=0,NA(),SUMPRODUCT((Inputs!$A$5:$A$140=$B7)*Inputs!$B$5:$B$140*(((Inputs!$G$5:$G$140="moeda")+(Inputs!$G$5:$G$140="acoes"))*Inputs!$B$1+((Inputs!$G$5:$G$140<>"moeda")*(Inputs!$G$5:$G$140<>"acoes")))*INDEX(Inputs!$K$5:$AJ$140,0,MATCH(E$2,Inputs!$K$4:$AJ$4,0)))+SUMPRODUCT((Inputs!$C$5:$C$140=$B7)*Inputs!$D$5:$D$140*(((Inputs!$G$5:$G$140="moeda")+(Inputs!$G$5:$G$140="acoes"))*Inputs!$B$1+((Inputs!$G$5:$G$140<>"moeda")*(Inputs!$G$5:$G$140<>"acoes")))*INDEX(Inputs!$K$5:$AJ$140,0,MATCH(E$2,Inputs!$K$4:$AJ$4,0)))+SUMPRODUCT((Inputs!$E$5:$E$140=$B7)*Inputs!$F$5:$F$140*(((Inputs!$G$5:$G$140="moeda")+(Inputs!$G$5:$G$140="acoes"))*Inputs!$B$1+((Inputs!$G$5:$G$140<>"moeda")*(Inputs!$G$5:$G$140<>"acoes")))*INDEX(Inputs!$K$5:$AJ$140,0,MATCH(E$2,Inputs!$K$4:$AJ$4,0))))) -> -63.733 | F7: =IF(ISNA(MATCH(F$2,Inputs!$K$4:$AJ$4,0)),NA(),IF(SUMPRODUCT((Inputs!$A$5:$A$140=$B7)*ISNUMBER(INDEX(Inputs!$K$5:$AJ$140,0,MATCH(F$2,Inputs!$K$4:$AJ$4,0))))+SUMPRODUCT((Inputs!$C$5:$C$140=$B7)*ISNUMBER(INDEX(Inputs!$K$5:$AJ$140,0,MATCH(F$2,Inputs!$K$4:$AJ$4,0))))+SUMPRODUCT((Inputs!$E$5:$E$140=$B7)*ISNUMBER(INDEX(Inputs!$K$5:$AJ$140,0,MATCH(F$2,Inputs!$K$4:$AJ$4,0))))=0,NA(),SUMPRODUCT((Inputs!$A$5:$A$140=$B7)*Inputs!$B$5:$B$140*(((Inputs!$G$5:$G$140="moeda")+(Inputs!$G$5:$G$140="acoes"))*Inputs!$B$1+((Inputs!$G$5:$G$140<>"moeda")*(Inputs!$G$5:$G$140<>"acoes")))*INDEX(Inputs!$K$5:$AJ$140,0,MATCH(F$2,Inputs!$K$4:$AJ$4,0)))+SUMPRODUCT((Inputs!$C$5:$C$140=$B7)*Inputs!$D$5:$D$140*(((Inputs!$G$5:$G$140="moeda")+(Inputs!$G$5:$G$140="acoes"))*Inputs!$B$1+((Inputs!$G$5:$G$140<>"moeda")*(Inputs!$G$5:$G$140<>"acoes")))*INDEX(Inputs!$K$5:$AJ$140,0,MATCH(F$2,Inputs!$K$4:$AJ$4,0)))+SUMPRODUCT((Inputs!$E$5:$E$140=$B7)*Inputs!$F$5:$F$140*(((Inputs!$G$5:$G$140="moeda")+(Inputs!$G$5:$G$140="acoes"))*Inputs!$B$1+((Inputs!$G$5:$G$140<>"moeda")*(Inputs!$G$5:$G$140<>"acoes")))*INDEX(Inputs!$K$5:$AJ$140,0,MATCH(F$2,Inputs!$K$4:$AJ$4,0))))) -> -71.918 | G7: =IF(ISNA(MATCH(G$2,Inputs!$K$4:$AJ$4,0)),NA(),IF(SUMPRODUCT((Inputs!$A$5:$A$140=$B7)*ISNUMBER(INDEX(Inputs!$K$5:$AJ$140,0,MATCH(G$2,Inputs!$K$4:$AJ$4,0))))+SUMPRODUCT((Inputs!$C$5:$C$140=$B7)*ISNUMBER(INDEX(Inputs!$K$5:$AJ$140,0,MATCH(G$2,Inputs!$K$4:$AJ$4,0))))+SUMPRODUCT((Inputs!$E$5:$E$140=$B7)*ISNUMBER(INDEX(Inputs!$K$5:$AJ$140,0,MATCH(G$2,Inputs!$K$4:$AJ$4,0))))=0,NA(),SUMPRODUCT((Inputs!$A$5:$A$140=$B7)*Inputs!$B$5:$B$140*(((Inputs!$G$5:$G$140="moeda")+(Inputs!$G$5:$G$140="acoes"))*Inputs!$B$1+((Inputs!$G$5:$G$140<>"moeda")*(Inputs!$G$5:$G$140<>"acoes")))*INDEX(Inputs!$K$5:$AJ$140,0,MATCH(G$2,Inputs!$K$4:$AJ$4,0)))+SUMPRODUCT((Inputs!$C$5:$C$140=$B7)*Inputs!$D$5:$D$140*(((Inputs!$G$5:$G$140="moeda")+(Inputs!$G$5:$G$140="acoes"))*Inputs!$B$1+((Inputs!$G$5:$G$140<>"moeda")*(Inputs!$G$5:$G$140<>"acoes")))*INDEX(Inputs!$K$5:$AJ$140,0,MATCH(G$2,Inputs!$K$4:$AJ$4,0)))+SUMPRODUCT((Inputs!$E$5:$E$140=$B7)*Inputs!$F$5:$F$140*(((Inputs!$G$5:$G$140="moeda")+(Inputs!$G$5:$G$140="acoes"))*Inputs!$B$1+((Inputs!$G$5:$G$140<>"moeda")*(Inputs!$G$5:$G$140<>"acoes")))*INDEX(Inputs!$K$5:$AJ$140,0,MATCH(G$2,Inputs!$K$4:$AJ$4,0))))) -> -67.065 | H7: =SUM(D7:G7) -> -260.445 | I7: =IF(ISNA(MATCH(I$2,Inputs!$K$4:$AJ$4,0)),NA(),IF(SUMPRODUCT((Inputs!$A$5:$A$140=$B7)*ISNUMBER(INDEX(Inputs!$K$5:$AJ$140,0,MATCH(I$2,Inputs!$K$4:$AJ$4,0))))+SUMPRODUCT((Inputs!$C$5:$C$140=$B7)*ISNUMBER(INDEX(Inputs!$K$5:$AJ$140,0,MATCH(I$2,Inputs!$K$4:$AJ$4,0))))+SUMPRODUCT((Inputs!$E$5:$E$140=$B7)*ISNUMBER(INDEX(Inputs!$K$5:$AJ$140,0,MATCH(I$2,Inputs!$K$4:$AJ$4,0))))=0,NA(),SUMPRODUCT((Inputs!$A$5:$A$140=$B7)*Inputs!$B$5:$B$140*(((Inputs!$G$5:$G$140="moeda")+(Inputs!$G$5:$G$140="acoes"))*Inputs!$B$1+((Inputs!$G$5:$G$140<>"moeda")*(Inputs!$G$5:$G$140<>"acoes")))*INDEX(Inputs!$K$5:$AJ$140,0,MATCH(I$2,Inputs!$K$4:$AJ$4,0)))+SUMPRODUCT((Inputs!$C$5:$C$140=$B7)*Inputs!$D$5:$D$140*(((Inputs!$G$5:$G$140="moeda")+(Inputs!$G$5:$G$140="acoes"))*Inputs!$B$1+((Inputs!$G$5:$G$140<>"moeda")*(Inputs!$G$5:$G$140<>"acoes")))*INDEX(Inputs!$K$5:$AJ$140,0,MATCH(I$2,Inputs!$K$4:$AJ$4,0)))+SUMPRODUCT((Inputs!$E$5:$E$140=$B7)*Inputs!$F$5:$F$140*(((Inputs!$G$5:$G$140="moeda")+(Inputs!$G$5:$G$140="acoes"))*Inputs!$B$1+((Inputs!$G$5:$G$140<>"moeda")*(Inputs!$G$5:$G$140<>"acoes")))*INDEX(Inputs!$K$5:$AJ$140,0,MATCH(I$2,Inputs!$K$4:$AJ$4,0))))) -> -72.195 | J7: =IF(ISNA(MATCH(J$2,Inputs!$K$4:$AJ$4,0)),NA(),IF(SUMPRODUCT((Inputs!$A$5:$A$140=$B7)*ISNUMBER(INDEX(Inputs!$K$5:$AJ$140,0,MATCH(J$2,Inputs!$K$4:$AJ$4,0))))+SUMPRODUCT((Inputs!$C$5:$C$140=$B7)*ISNUMBER(INDEX(Inputs!$K$5:$AJ$140,0,MATCH(J$2,Inputs!$K$4:$AJ$4,0))))+SUMPRODUCT((Inputs!$E$5:$E$140=$B7)*ISNUMBER(INDEX(Inputs!$K$5:$AJ$140,0,MATCH(J$2,Inputs!$K$4:$AJ$4,0))))=0,NA(),SUMPRODUCT((Inputs!$A$5:$A$140=$B7)*Inputs!$B$5:$B$140*(((Inputs!$G$5:$G$140="moeda")+(Inputs!$G$5:$G$140="acoes"))*Inputs!$B$1+((Inputs!$G$5:$G$140<>"moeda")*(Inputs!$G$5:$G$140<>"acoes")))*INDEX(Inputs!$K$5:$AJ$140,0,MATCH(J$2,Inputs!$K$4:$AJ$4,0)))+SUMPRODUCT((Inputs!$C$5:$C$140=$B7)*Inputs!$D$5:$D$140*(((Inputs!$G$5:$G$140="moeda")+(Inputs!$G$5:$G$140="acoes"))*Inputs!$B$1+((Inputs!$G$5:$G$140<>"moeda")*(Inputs!$G$5:$G$140<>"acoes")))*INDEX(Inputs!$K$5:$AJ$140,0,MATCH(J$2,Inputs!$K$4:$AJ$4,0)))+SUMPRODUCT((Inputs!$E$5:$E$140=$B7)*Inputs!$F$5:$F$140*(((Inputs!$G$5:$G$140="moeda")+(Inputs!$G$5:$G$140="acoes"))*Inputs!$B$1+((Inputs!$G$5:$G$140<>"moeda")*(Inputs!$G$5:$G$140<>"acoes")))*INDEX(Inputs!$K$5:$AJ$140,0,MATCH(J$2,Inputs!$K$4:$AJ$4,0))))) -> -83.73 | K7: =IF(ISNA(MATCH(K$2,Inputs!$K$4:$AJ$4,0)),NA(),IF(SUMPRODUCT((Inputs!$A$5:$A$140=$B7)*ISNUMBER(INDEX(Inputs!$K$5:$AJ$140,0,MATCH(K$2,Inputs!$K$4:$AJ$4,0))))+SUMPRODUCT((Inputs!$C$5:$C$140=$B7)*ISNUMBER(INDEX(Inputs!$K$5:$AJ$140,0,MATCH(K$2,Inputs!$K$4:$AJ$4,0))))+SUMPRODUCT((Inputs!$E$5:$E$140=$B7)*ISNUMBER(INDEX(Inputs!$K$5:$AJ$140,0,MATCH(K$2,Inputs!$K$4:$AJ$4,0))))=0,NA(),SUMPRODUCT((Inputs!$A$5:$A$140=$B7)*Inputs!$B$5:$B$140*(((Inputs!$G$5:$G$140="moeda")+(Inputs!$G$5:$G$140="acoes"))*Inputs!$B$1+((Inputs!$G$5:$G$140<>"moeda")*(Inputs!$G$5:$G$140<>"acoes")))*INDEX(Inputs!$K$5:$AJ$140,0,MATCH(K$2,Inputs!$K$4:$AJ$4,0)))+SUMPRODUCT((Inputs!$C$5:$C$140=$B7)*Inputs!$D$5:$D$140*(((Inputs!$G$5:$G$140="moeda")+(Inputs!$G$5:$G$140="acoes"))*Inputs!$B$1+((Inputs!$G$5:$G$140<>"moeda")*(Inputs!$G$5:$G$140<>"acoes")))*INDEX(Inputs!$K$5:$AJ$140,0,MATCH(K$2,Inputs!$K$4:$AJ$4,0)))+SUMPRODUCT((Inputs!$E$5:$E$140=$B7)*Inputs!$F$5:$F$140*(((Inputs!$G$5:$G$140="moeda")+(Inputs!$G$5:$G$140="acoes"))*Inputs!$B$1+((Inputs!$G$5:$G$140<>"moeda")*(Inputs!$G$5:$G$140<>"acoes")))*INDEX(Inputs!$K$5:$AJ$140,0,MATCH(K$2,Inputs!$K$4:$AJ$4,0))))) -> -84.22 | L7: =IF(ISNA(MATCH(L$2,Inputs!$K$4:$AJ$4,0)),NA(),IF(SUMPRODUCT((Inputs!$A$5:$A$140=$B7)*ISNUMBER(INDEX(Inputs!$K$5:$AJ$140,0,MATCH(L$2,Inputs!$K$4:$AJ$4,0))))+SUMPRODUCT((Inputs!$C$5:$C$140=$B7)*ISNUMBER(INDEX(Inputs!$K$5:$AJ$140,0,MATCH(L$2,Inputs!$K$4:$AJ$4,0))))+SUMPRODUCT((Inputs!$E$5:$E$140=$B7)*ISNUMBER(INDEX(Inputs!$K$5:$AJ$140,0,MATCH(L$2,Inputs!$K$4:$AJ$4,0))))=0,NA(),SUMPRODUCT((Inputs!$A$5:$A$140=$B7)*Inputs!$B$5:$B$140*(((Inputs!$G$5:$G$140="moeda")+(Inputs!$G$5:$G$140="acoes"))*Inputs!$B$1+((Inputs!$G$5:$G$140<>"moeda")*(Inputs!$G$5:$G$140<>"acoes")))*INDEX(Inputs!$K$5:$AJ$140,0,MATCH(L$2,Inputs!$K$4:$AJ$4,0)))+SUMPRODUCT((Inputs!$C$5:$C$140=$B7)*Inputs!$D$5:$D$140*(((Inputs!$G$5:$G$140="moeda")+(Inputs!$G$5:$G$140="acoes"))*Inputs!$B$1+((Inputs!$G$5:$G$140<>"moeda")*(Inputs!$G$5:$G$140<>"acoes")))*INDEX(Inputs!$K$5:$AJ$140,0,MATCH(L$2,Inputs!$K$4:$AJ$4,0)))+SUMPRODUCT((Inputs!$E$5:$E$140=$B7)*Inputs!$F$5:$F$140*(((Inputs!$G$5:$G$140="moeda")+(Inputs!$G$5:$G$140="acoes"))*Inputs!$B$1+((Inputs!$G$5:$G$140<>"moeda")*(Inputs!$G$5:$G$140<>"acoes")))*INDEX(Inputs!$K$5:$AJ$140,0,MATCH(L$2,Inputs!$K$4:$AJ$4,0))))) -> -89.022 | M7: =SUM(I7:L7) -> -329.167 | N7: =IF(ISNA(MATCH(N$2,Inputs!$K$4:$AJ$4,0)),NA(),IF(SUMPRODUCT((Inputs!$A$5:$A$140=$B7)*ISNUMBER(INDEX(Inputs!$K$5:$AJ$140,0,MATCH(N$2,Inputs!$K$4:$AJ$4,0))))+SUMPRODUCT((Inputs!$C$5:$C$140=$B7)*ISNUMBER(INDEX(Inputs!$K$5:$AJ$140,0,MATCH(N$2,Inputs!$K$4:$AJ$4,0))))+SUMPRODUCT((Inputs!$E$5:$E$140=$B7)*ISNUMBER(INDEX(Inputs!$K$5:$AJ$140,0,MATCH(N$2,Inputs!$K$4:$AJ$4,0))))=0,NA(),SUMPRODUCT((Inputs!$A$5:$A$140=$B7)*Inputs!$B$5:$B$140*(((Inputs!$G$5:$G$140="moeda")+(Inputs!$G$5:$G$140="acoes"))*Inputs!$B$1+((Inputs!$G$5:$G$140<>"moeda")*(Inputs!$G$5:$G$140<>"acoes")))*INDEX(Inputs!$K$5:$AJ$140,0,MATCH(N$2,Inputs!$K$4:$AJ$4,0)))+SUMPRODUCT((Inputs!$C$5:$C$140=$B7)*Inputs!$D$5:$D$140*(((Inputs!$G$5:$G$140="moeda")+(Inputs!$G$5:$G$140="acoes"))*Inputs!$B$1+((Inputs!$G$5:$G$140<>"moeda")*(Inputs!$G$5:$G$140<>"acoes")))*INDEX(Inputs!$K$5:$AJ$140,0,MATCH(N$2,Inputs!$K$4:$AJ$4,0)))+SUMPRODUCT((Inputs!$E$5:$E$140=$B7)*Inputs!$F$5:$F$140*(((Inputs!$G$5:$G$140="moeda")+(Inputs!$G$5:$G$140="acoes"))*Inputs!$B$1+((Inputs!$G$5:$G$140<>"moeda")*(Inputs!$G$5:$G$140<>"acoes")))*INDEX(Inputs!$K$5:$AJ$140,0,MATCH(N$2,Inputs!$K$4:$AJ$4,0))))) -> -98.001 | O7: =IF(ISNA(MATCH(O$2,Inputs!$K$4:$AJ$4,0)),NA(),IF(SUMPRODUCT((Inputs!$A$5:$A$140=$B7)*ISNUMBER(INDEX(Inputs!$K$5:$AJ$140,0,MATCH(O$2,Inputs!$K$4:$AJ$4,0))))+SUMPRODUCT((Inputs!$C$5:$C$140=$B7)*ISNUMBER(INDEX(Inputs!$K$5:$AJ$140,0,MATCH(O$2,Inputs!$K$4:$AJ$4,0))))+SUMPRODUCT((Inputs!$E$5:$E$140=$B7)*ISNUMBER(INDEX(Inputs!$K$5:$AJ$140,0,MATCH(O$2,Inputs!$K$4:$AJ$4,0))))=0,NA(),SUMPRODUCT((Inputs!$A$5:$A$140=$B7)*Inputs!$B$5:$B$140*(((Inputs!$G$5:$G$140="moeda")+(Inputs!$G$5:$G$140="acoes"))*Inputs!$B$1+((Inputs!$G$5:$G$140<>"moeda")*(Inputs!$G$5:$G$140<>"acoes")))*INDEX(Inputs!$K$5:$AJ$140,0,MATCH(O$2,Inputs!$K$4:$AJ$4,0)))+SUMPRODUCT((Inputs!$C$5:$C$140=$B7)*Inputs!$D$5:$D$140*(((Inputs!$G$5:$G$140="moeda")+(Inputs!$G$5:$G$140="acoes"))*Inputs!$B$1+((Inputs!$G$5:$G$140<>"moeda")*(Inputs!$G$5:$G$140<>"acoes")))*INDEX(Inputs!$K$5:$AJ$140,0,MATCH(O$2,Inputs!$K$4:$AJ$4,0)))+SUMPRODUCT((Inputs!$E$5:$E$140=$B7)*Inputs!$F$5:$F$140*(((Inputs!$G$5:$G$140="moeda")+(Inputs!$G$5:$G$140="acoes"))*Inputs!$B$1+((Inputs!$G$5:$G$140<>"moeda")*(Inputs!$G$5:$G$140<>"acoes")))*INDEX(Inputs!$K$5:$AJ$140,0,MATCH(O$2,Inputs!$K$4:$AJ$4,0))))) -> -92.145 | P7: =IF(ISNA(MATCH(P$2,Inputs!$K$4:$AJ$4,0)),NA(),IF(SUMPRODUCT((Inputs!$A$5:$A$140=$B7)*ISNUMBER(INDEX(Inputs!$K$5:$AJ$140,0,MATCH(P$2,Inputs!$K$4:$AJ$4,0))))+SUMPRODUCT((Inputs!$C$5:$C$140=$B7)*ISNUMBER(INDEX(Inputs!$K$5:$AJ$140,0,MATCH(P$2,Inputs!$K$4:$AJ$4,0))))+SUMPRODUCT((Inputs!$E$5:$E$140=$B7)*ISNUMBER(INDEX(Inputs!$K$5:$AJ$140,0,MATCH(P$2,Inputs!$K$4:$AJ$4,0))))=0,NA(),SUMPRODUCT((Inputs!$A$5:$A$140=$B7)*Inputs!$B$5:$B$140*(((Inputs!$G$5:$G$140="moeda")+(Inputs!$G$5:$G$140="acoes"))*Inputs!$B$1+((Inputs!$G$5:$G$140<>"moeda")*(Inputs!$G$5:$G$140<>"acoes")))*INDEX(Inputs!$K$5:$AJ$140,0,MATCH(P$2,Inputs!$K$4:$AJ$4,0)))+SUMPRODUCT((Inputs!$C$5:$C$140=$B7)*Inputs!$D$5:$D$140*(((Inputs!$G$5:$G$140="moeda")+(Inputs!$G$5:$G$140="acoes"))*Inputs!$B$1+((Inputs!$G$5:$G$140<>"moeda")*(Inputs!$G$5:$G$140<>"acoes")))*INDEX(Inputs!$K$5:$AJ$140,0,MATCH(P$2,Inputs!$K$4:$AJ$4,0)))+SUMPRODUCT((Inputs!$E$5:$E$140=$B7)*Inputs!$F$5:$F$140*(((Inputs!$G$5:$G$140="moeda")+(Inputs!$G$5:$G$140="acoes"))*Inputs!$B$1+((Inputs!$G$5:$G$140<>"moeda")*(Inputs!$G$5:$G$140<>"acoes")))*INDEX(Inputs!$K$5:$AJ$140,0,MATCH(P$2,Inputs!$K$4:$AJ$4,0))))) -> -98.528 | Q7: =IF(ISNA(MATCH(Q$2,Inputs!$K$4:$AJ$4,0)),NA(),IF(SUMPRODUCT((Inputs!$A$5:$A$140=$B7)*ISNUMBER(INDEX(Inputs!$K$5:$AJ$140,0,MATCH(Q$2,Inputs!$K$4:$AJ$4,0))))+SUMPRODUCT((Inputs!$C$5:$C$140=$B7)*ISNUMBER(INDEX(Inputs!$K$5:$AJ$140,0,MATCH(Q$2,Inputs!$K$4:$AJ$4,0))))+SUMPRODUCT((Inputs!$E$5:$E$140=$B7)*ISNUMBER(INDEX(Inputs!$K$5:$AJ$140,0,MATCH(Q$2,Inputs!$K$4:$AJ$4,0))))=0,NA(),SUMPRODUCT((Inputs!$A$5:$A$140=$B7)*Inputs!$B$5:$B$140*(((Inputs!$G$5:$G$140="moeda")+(Inputs!$G$5:$G$140="acoes"))*Inputs!$B$1+((Inputs!$G$5:$G$140<>"moeda")*(Inputs!$G$5:$G$140<>"acoes")))*INDEX(Inputs!$K$5:$AJ$140,0,MATCH(Q$2,Inputs!$K$4:$AJ$4,0)))+SUMPRODUCT((Inputs!$C$5:$C$140=$B7)*Inputs!$D$5:$D$140*(((Inputs!$G$5:$G$140="moeda")+(Inputs!$G$5:$G$140="acoes"))*Inputs!$B$1+((Inputs!$G$5:$G$140<>"moeda")*(Inputs!$G$5:$G$140<>"acoes")))*INDEX(Inputs!$K$5:$AJ$140,0,MATCH(Q$2,Inputs!$K$4:$AJ$4,0)))+SUMPRODUCT((Inputs!$E$5:$E$140=$B7)*Inputs!$F$5:$F$140*(((Inputs!$G$5:$G$140="moeda")+(Inputs!$G$5:$G$140="acoes"))*Inputs!$B$1+((Inputs!$G$5:$G$140<>"moeda")*(Inputs!$G$5:$G$140<>"acoes")))*INDEX(Inputs!$K$5:$AJ$140,0,MATCH(Q$2,Inputs!$K$4:$AJ$4,0))))) -> -64.718 | R7: =SUM(N7:Q7) -> -353.392 | S7: =IF(ISNA(MATCH(S$2,Inputs!$K$4:$AJ$4,0)),NA(),IF(SUMPRODUCT((Inputs!$A$5:$A$140=$B7)*ISNUMBER(INDEX(Inputs!$K$5:$AJ$140,0,MATCH(S$2,Inputs!$K$4:$AJ$4,0))))+SUMPRODUCT((Inputs!$C$5:$C$140=$B7)*ISNUMBER(INDEX(Inputs!$K$5:$AJ$140,0,MATCH(S$2,Inputs!$K$4:$AJ$4,0))))+SUMPRODUCT((Inputs!$E$5:$E$140=$B7)*ISNUMBER(INDEX(Inputs!$K$5:$AJ$140,0,MATCH(S$2,Inputs!$K$4:$AJ$4,0))))=0,NA(),SUMPRODUCT((Inputs!$A$5:$A$140=$B7)*Inputs!$B$5:$B$140*(((Inputs!$G$5:$G$140="moeda")+(Inputs!$G$5:$G$140="acoes"))*Inputs!$B$1+((Inputs!$G$5:$G$140<>"moeda")*(Inputs!$G$5:$G$140<>"acoes")))*INDEX(Inputs!$K$5:$AJ$140,0,MATCH(S$2,Inputs!$K$4:$AJ$4,0)))+SUMPRODUCT((Inputs!$C$5:$C$140=$B7)*Inputs!$D$5:$D$140*(((Inputs!$G$5:$G$140="moeda")+(Inputs!$G$5:$G$140="acoes"))*Inputs!$B$1+((Inputs!$G$5:$G$140<>"moeda")*(Inputs!$G$5:$G$140<>"acoes")))*INDEX(Inputs!$K$5:$AJ$140,0,MATCH(S$2,Inputs!$K$4:$AJ$4,0)))+SUMPRODUCT((Inputs!$E$5:$E$140=$B7)*Inputs!$F$5:$F$140*(((Inputs!$G$5:$G$140="moeda")+(Inputs!$G$5:$G$140="acoes"))*Inputs!$B$1+((Inputs!$G$5:$G$140<>"moeda")*(Inputs!$G$5:$G$140<>"acoes")))*INDEX(Inputs!$K$5:$AJ$140,0,MATCH(S$2,Inputs!$K$4:$AJ$4,0))))) -> -104.571 | T7: =IF(ISNA(MATCH(T$2,Inputs!$K$4:$AJ$4,0)),NA(),IF(SUMPRODUCT((Inputs!$A$5:$A$140=$B7)*ISNUMBER(INDEX(Inputs!$K$5:$AJ$140,0,MATCH(T$2,Inputs!$K$4:$AJ$4,0))))+SUMPRODUCT((Inputs!$C$5:$C$140=$B7)*ISNUMBER(INDEX(Inputs!$K$5:$AJ$140,0,MATCH(T$2,Inputs!$K$4:$AJ$4,0))))+SUMPRODUCT((Inputs!$E$5:$E$140=$B7)*ISNUMBER(INDEX(Inputs!$K$5:$AJ$140,0,MATCH(T$2,Inputs!$K$4:$AJ$4,0))))=0,NA(),SUMPRODUCT((Inputs!$A$5:$A$140=$B7)*Inputs!$B$5:$B$140*(((Inputs!$G$5:$G$140="moeda")+(Inputs!$G$5:$G$140="acoes"))*Inputs!$B$1+((Inputs!$G$5:$G$140<>"moeda")*(Inputs!$G$5:$G$140<>"acoes")))*INDEX(Inputs!$K$5:$AJ$140,0,MATCH(T$2,Inputs!$K$4:$AJ$4,0)))+SUMPRODUCT((Inputs!$C$5:$C$140=$B7)*Inputs!$D$5:$D$140*(((Inputs!$G$5:$G$140="moeda")+(Inputs!$G$5:$G$140="acoes"))*Inputs!$B$1+((Inputs!$G$5:$G$140<>"moeda")*(Inputs!$G$5:$G$140<>"acoes")))*INDEX(Inputs!$K$5:$AJ$140,0,MATCH(T$2,Inputs!$K$4:$AJ$4,0)))+SUMPRODUCT((Inputs!$E$5:$E$140=$B7)*Inputs!$F$5:$F$140*(((Inputs!$G$5:$G$140="moeda")+(Inputs!$G$5:$G$140="acoes"))*Inputs!$B$1+((Inputs!$G$5:$G$140<>"moeda")*(Inputs!$G$5:$G$140<>"acoes")))*INDEX(Inputs!$K$5:$AJ$140,0,MATCH(T$2,Inputs!$K$4:$AJ$4,0))))) -> -85.309 | U7: =IF(ISNA(MATCH(U$2,Inputs!$K$4:$AJ$4,0)),NA(),IF(SUMPRODUCT((Inputs!$A$5:$A$140=$B7)*ISNUMBER(INDEX(Inputs!$K$5:$AJ$140,0,MATCH(U$2,Inputs!$K$4:$AJ$4,0))))+SUMPRODUCT((Inputs!$C$5:$C$140=$B7)*ISNUMBER(INDEX(Inputs!$K$5:$AJ$140,0,MATCH(U$2,Inputs!$K$4:$AJ$4,0))))+SUMPRODUCT((Inputs!$E$5:$E$140=$B7)*ISNUMBER(INDEX(Inputs!$K$5:$AJ$140,0,MATCH(U$2,Inputs!$K$4:$AJ$4,0))))=0,NA(),SUMPRODUCT((Inputs!$A$5:$A$140=$B7)*Inputs!$B$5:$B$140*(((Inputs!$G$5:$G$140="moeda")+(Inputs!$G$5:$G$140="acoes"))*Inputs!$B$1+((Inputs!$G$5:$G$140<>"moeda")*(Inputs!$G$5:$G$140<>"acoes")))*INDEX(Inputs!$K$5:$AJ$140,0,MATCH(U$2,Inputs!$K$4:$AJ$4,0)))+SUMPRODUCT((Inputs!$C$5:$C$140=$B7)*Inputs!$D$5:$D$140*(((Inputs!$G$5:$G$140="moeda")+(Inputs!$G$5:$G$140="acoes"))*Inputs!$B$1+((Inputs!$G$5:$G$140<>"moeda")*(Inputs!$G$5:$G$140<>"acoes")))*INDEX(Inputs!$K$5:$AJ$140,0,MATCH(U$2,Inputs!$K$4:$AJ$4,0)))+SUMPRODUCT((Inputs!$E$5:$E$140=$B7)*Inputs!$F$5:$F$140*(((Inputs!$G$5:$G$140="moeda")+(Inputs!$G$5:$G$140="acoes"))*Inputs!$B$1+((Inputs!$G$5:$G$140<>"moeda")*(Inputs!$G$5:$G$140<>"acoes")))*INDEX(Inputs!$K$5:$AJ$140,0,MATCH(U$2,Inputs!$K$4:$AJ$4,0))))) -> -95.494 | V7: =IF(ISNA(MATCH(V$2,Inputs!$K$4:$AJ$4,0)),NA(),IF(SUMPRODUCT((Inputs!$A$5:$A$140=$B7)*ISNUMBER(INDEX(Inputs!$K$5:$AJ$140,0,MATCH(V$2,Inputs!$K$4:$AJ$4,0))))+SUMPRODUCT((Inputs!$C$5:$C$140=$B7)*ISNUMBER(INDEX(Inputs!$K$5:$AJ$140,0,MATCH(V$2,Inputs!$K$4:$AJ$4,0))))+SUMPRODUCT((Inputs!$E$5:$E$140=$B7)*ISNUMBER(INDEX(Inputs!$K$5:$AJ$140,0,MATCH(V$2,Inputs!$K$4:$AJ$4,0))))=0,NA(),SUMPRODUCT((Inputs!$A$5:$A$140=$B7)*Inputs!$B$5:$B$140*(((Inputs!$G$5:$G$140="moeda")+(Inputs!$G$5:$G$140="acoes"))*Inputs!$B$1+((Inputs!$G$5:$G$140<>"moeda")*(Inputs!$G$5:$G$140<>"acoes")))*INDEX(Inputs!$K$5:$AJ$140,0,MATCH(V$2,Inputs!$K$4:$AJ$4,0)))+SUMPRODUCT((Inputs!$C$5:$C$140=$B7)*Inputs!$D$5:$D$140*(((Inputs!$G$5:$G$140="moeda")+(Inputs!$G$5:$G$140="acoes"))*Inputs!$B$1+((Inputs!$G$5:$G$140<>"moeda")*(Inputs!$G$5:$G$140<>"acoes")))*INDEX(Inputs!$K$5:$AJ$140,0,MATCH(V$2,Inputs!$K$4:$AJ$4,0)))+SUMPRODUCT((Inputs!$E$5:$E$140=$B7)*Inputs!$F$5:$F$140*(((Inputs!$G$5:$G$140="moeda")+(Inputs!$G$5:$G$140="acoes"))*Inputs!$B$1+((Inputs!$G$5:$G$140<>"moeda")*(Inputs!$G$5:$G$140<>"acoes")))*INDEX(Inputs!$K$5:$AJ$140,0,MATCH(V$2,Inputs!$K$4:$AJ$4,0))))) -> -91.372 | W7: =SUM(S7:V7) -> -376.746 | X7: =IF(ISNA(MATCH(X$2,Inputs!$K$4:$AJ$4,0)),NA(),IF(SUMPRODUCT((Inputs!$A$5:$A$140=$B7)*ISNUMBER(INDEX(Inputs!$K$5:$AJ$140,0,MATCH(X$2,Inputs!$K$4:$AJ$4,0))))+SUMPRODUCT((Inputs!$C$5:$C$140=$B7)*ISNUMBER(INDEX(Inputs!$K$5:$AJ$140,0,MATCH(X$2,Inputs!$K$4:$AJ$4,0))))+SUMPRODUCT((Inputs!$E$5:$E$140=$B7)*ISNUMBER(INDEX(Inputs!$K$5:$AJ$140,0,MATCH(X$2,Inputs!$K$4:$AJ$4,0))))=0,NA(),SUMPRODUCT((Inputs!$A$5:$A$140=$B7)*Inputs!$B$5:$B$140*(((Inputs!$G$5:$G$140="moeda")+(Inputs!$G$5:$G$140="acoes"))*Inputs!$B$1+((Inputs!$G$5:$G$140<>"moeda")*(Inputs!$G$5:$G$140<>"acoes")))*INDEX(Inputs!$K$5:$AJ$140,0,MATCH(X$2,Inputs!$K$4:$AJ$4,0)))+SUMPRODUCT((Inputs!$C$5:$C$140=$B7)*Inputs!$D$5:$D$140*(((Inputs!$G$5:$G$140="moeda")+(Inputs!$G$5:$G$140="acoes"))*Inputs!$B$1+((Inputs!$G$5:$G$140<>"moeda")*(Inputs!$G$5:$G$140<>"acoes")))*INDEX(Inputs!$K$5:$AJ$140,0,MATCH(X$2,Inputs!$K$4:$AJ$4,0)))+SUMPRODUCT((Inputs!$E$5:$E$140=$B7)*Inputs!$F$5:$F$140*(((Inputs!$G$5:$G$140="moeda")+(Inputs!$G$5:$G$140="acoes"))*Inputs!$B$1+((Inputs!$G$5:$G$140<>"moeda")*(Inputs!$G$5:$G$140<>"acoes")))*INDEX(Inputs!$K$5:$AJ$140,0,MATCH(X$2,Inputs!$K$4:$AJ$4,0))))) -> -105.294 | Y7: =IF(ISNA(MATCH(Y$2,Inputs!$K$4:$AJ$4,0)),NA(),IF(SUMPRODUCT((Inputs!$A$5:$A$140=$B7)*ISNUMBER(INDEX(Inputs!$K$5:$AJ$140,0,MATCH(Y$2,Inputs!$K$4:$AJ$4,0))))+SUMPRODUCT((Inputs!$C$5:$C$140=$B7)*ISNUMBER(INDEX(Inputs!$K$5:$AJ$140,0,MATCH(Y$2,Inputs!$K$4:$AJ$4,0))))+SUMPRODUCT((Inputs!$E$5:$E$140=$B7)*ISNUMBER(INDEX(Inputs!$K$5:$AJ$140,0,MATCH(Y$2,Inputs!$K$4:$AJ$4,0))))=0,NA(),SUMPRODUCT((Inputs!$A$5:$A$140=$B7)*Inputs!$B$5:$B$140*(((Inputs!$G$5:$G$140="moeda")+(Inputs!$G$5:$G$140="acoes"))*Inputs!$B$1+((Inputs!$G$5:$G$140<>"moeda")*(Inputs!$G$5:$G$140<>"acoes")))*INDEX(Inputs!$K$5:$AJ$140,0,MATCH(Y$2,Inputs!$K$4:$AJ$4,0)))+SUMPRODUCT((Inputs!$C$5:$C$140=$B7)*Inputs!$D$5:$D$140*(((Inputs!$G$5:$G$140="moeda")+(Inputs!$G$5:$G$140="acoes"))*Inputs!$B$1+((Inputs!$G$5:$G$140<>"moeda")*(Inputs!$G$5:$G$140<>"acoes")))*INDEX(Inputs!$K$5:$AJ$140,0,MATCH(Y$2,Inputs!$K$4:$AJ$4,0)))+SUMPRODUCT((Inputs!$E$5:$E$140=$B7)*Inputs!$F$5:$F$140*(((Inputs!$G$5:$G$140="moeda")+(Inputs!$G$5:$G$140="acoes"))*Inputs!$B$1+((Inputs!$G$5:$G$140<>"moeda")*(Inputs!$G$5:$G$140<>"acoes")))*INDEX(Inputs!$K$5:$AJ$140,0,MATCH(Y$2,Inputs!$K$4:$AJ$4,0))))) -> -113.093 | Z7: =IF(ISNA(MATCH(Z$2,Inputs!$K$4:$AJ$4,0)),NA(),IF(SUMPRODUCT((Inputs!$A$5:$A$140=$B7)*ISNUMBER(INDEX(Inputs!$K$5:$AJ$140,0,MATCH(Z$2,Inputs!$K$4:$AJ$4,0))))+SUMPRODUCT((Inputs!$C$5:$C$140=$B7)*ISNUMBER(INDEX(Inputs!$K$5:$AJ$140,0,MATCH(Z$2,Inputs!$K$4:$AJ$4,0))))+SUMPRODUCT((Inputs!$E$5:$E$140=$B7)*ISNUMBER(INDEX(Inputs!$K$5:$AJ$140,0,MATCH(Z$2,Inputs!$K$4:$AJ$4,0))))=0,NA(),SUMPRODUCT((Inputs!$A$5:$A$140=$B7)*Inputs!$B$5:$B$140*(((Inputs!$G$5:$G$140="moeda")+(Inputs!$G$5:$G$140="acoes"))*Inputs!$B$1+((Inputs!$G$5:$G$140<>"moeda")*(Inputs!$G$5:$G$140<>"acoes")))*INDEX(Inputs!$K$5:$AJ$140,0,MATCH(Z$2,Inputs!$K$4:$AJ$4,0)))+SUMPRODUCT((Inputs!$C$5:$C$140=$B7)*Inputs!$D$5:$D$140*(((Inputs!$G$5:$G$140="moeda")+(Inputs!$G$5:$G$140="acoes"))*Inputs!$B$1+((Inputs!$G$5:$G$140<>"moeda")*(Inputs!$G$5:$G$140<>"acoes")))*INDEX(Inputs!$K$5:$AJ$140,0,MATCH(Z$2,Inputs!$K$4:$AJ$4,0)))+SUMPRODUCT((Inputs!$E$5:$E$140=$B7)*Inputs!$F$5:$F$140*(((Inputs!$G$5:$G$140="moeda")+(Inputs!$G$5:$G$140="acoes"))*Inputs!$B$1+((Inputs!$G$5:$G$140<>"moeda")*(Inputs!$G$5:$G$140<>"acoes")))*INDEX(Inputs!$K$5:$AJ$140,0,MATCH(Z$2,Inputs!$K$4:$AJ$4,0))))) -> -162.165 | AA7: =IF(ISNA(MATCH(AA$2,Inputs!$K$4:$AJ$4,0)),NA(),IF(SUMPRODUCT((Inputs!$A$5:$A$140=$B7)*ISNUMBER(INDEX(Inputs!$K$5:$AJ$140,0,MATCH(AA$2,Inputs!$K$4:$AJ$4,0))))+SUMPRODUCT((Inputs!$C$5:$C$140=$B7)*ISNUMBER(INDEX(Inputs!$K$5:$AJ$140,0,MATCH(AA$2,Inputs!$K$4:$AJ$4,0))))+SUMPRODUCT((Inputs!$E$5:$E$140=$B7)*ISNUMBER(INDEX(Inputs!$K$5:$AJ$140,0,MATCH(AA$2,Inputs!$K$4:$AJ$4,0))))=0,NA(),SUMPRODUCT((Inputs!$A$5:$A$140=$B7)*Inputs!$B$5:$B$140*(((Inputs!$G$5:$G$140="moeda")+(Inputs!$G$5:$G$140="acoes"))*Inputs!$B$1+((Inputs!$G$5:$G$140<>"moeda")*(Inputs!$G$5:$G$140<>"acoes")))*INDEX(Inputs!$K$5:$AJ$140,0,MATCH(AA$2,Inputs!$K$4:$AJ$4,0)))+SUMPRODUCT((Inputs!$C$5:$C$140=$B7)*Inputs!$D$5:$D$140*(((Inputs!$G$5:$G$140="moeda")+(Inputs!$G$5:$G$140="acoes"))*Inputs!$B$1+((Inputs!$G$5:$G$140<>"moeda")*(Inputs!$G$5:$G$140<>"acoes")))*INDEX(Inputs!$K$5:$AJ$140,0,MATCH(AA$2,Inputs!$K$4:$AJ$4,0)))+SUMPRODUCT((Inputs!$E$5:$E$140=$B7)*Inputs!$F$5:$F$140*(((Inputs!$G$5:$G$140="moeda")+(Inputs!$G$5:$G$140="acoes"))*Inputs!$B$1+((Inputs!$G$5:$G$140<>"moeda")*(Inputs!$G$5:$G$140<>"acoes")))*INDEX(Inputs!$K$5:$AJ$140,0,MATCH(AA$2,Inputs!$K$4:$AJ$4,0))))) -> -159.044 | AB7: =SUM(X7:AA7) -> -539.596 | AC7: =IF(ISNA(MATCH(AC$2,Inputs!$K$4:$AJ$4,0)),NA(),IF(SUMPRODUCT((Inputs!$A$5:$A$140=$B7)*ISNUMBER(INDEX(Inputs!$K$5:$AJ$140,0,MATCH(AC$2,Inputs!$K$4:$AJ$4,0))))+SUMPRODUCT((Inputs!$C$5:$C$140=$B7)*ISNUMBER(INDEX(Inputs!$K$5:$AJ$140,0,MATCH(AC$2,Inputs!$K$4:$AJ$4,0))))+SUMPRODUCT((Inputs!$E$5:$E$140=$B7)*ISNUMBER(INDEX(Inputs!$K$5:$AJ$140,0,MATCH(AC$2,Inputs!$K$4:$AJ$4,0))))=0,NA(),SUMPRODUCT((Inputs!$A$5:$A$140=$B7)*Inputs!$B$5:$B$140*(((Inputs!$G$5:$G$140="moeda")+(Inputs!$G$5:$G$140="acoes"))*Inputs!$B$1+((Inputs!$G$5:$G$140<>"moeda")*(Inputs!$G$5:$G$140<>"acoes")))*INDEX(Inputs!$K$5:$AJ$140,0,MATCH(AC$2,Inputs!$K$4:$AJ$4,0)))+SUMPRODUCT((Inputs!$C$5:$C$140=$B7)*Inputs!$D$5:$D$140*(((Inputs!$G$5:$G$140="moeda")+(Inputs!$G$5:$G$140="acoes"))*Inputs!$B$1+((Inputs!$G$5:$G$140<>"moeda")*(Inputs!$G$5:$G$140<>"acoes")))*INDEX(Inputs!$K$5:$AJ$140,0,MATCH(AC$2,Inputs!$K$4:$AJ$4,0)))+SUMPRODUCT((Inputs!$E$5:$E$140=$B7)*Inputs!$F$5:$F$140*(((Inputs!$G$5:$G$140="moeda")+(Inputs!$G$5:$G$140="acoes"))*Inputs!$B$1+((Inputs!$G$5:$G$140<>"moeda")*(Inputs!$G$5:$G$140<>"acoes")))*INDEX(Inputs!$K$5:$AJ$140,0,MATCH(AC$2,Inputs!$K$4:$AJ$4,0))))) -> -158.45 | AD7: =IF(ISNA(MATCH(AD$2,Inputs!$K$4:$AJ$4,0)),NA(),IF(SUMPRODUCT((Inputs!$A$5:$A$140=$B7)*ISNUMBER(INDEX(Inputs!$K$5:$AJ$140,0,MATCH(AD$2,Inputs!$K$4:$AJ$4,0))))+SUMPRODUCT((Inputs!$C$5:$C$140=$B7)*ISNUMBER(INDEX(Inputs!$K$5:$AJ$140,0,MATCH(AD$2,Inputs!$K$4:$AJ$4,0))))+SUMPRODUCT((Inputs!$E$5:$E$140=$B7)*ISNUMBER(INDEX(Inputs!$K$5:$AJ$140,0,MATCH(AD$2,Inputs!$K$4:$AJ$4,0))))=0,NA(),SUMPRODUCT((Inputs!$A$5:$A$140=$B7)*Inputs!$B$5:$B$140*(((Inputs!$G$5:$G$140="moeda")+(Inputs!$G$5:$G$140="acoes"))*Inputs!$B$1+((Inputs!$G$5:$G$140<>"moeda")*(Inputs!$G$5:$G$140<>"acoes")))*INDEX(Inputs!$K$5:$AJ$140,0,MATCH(AD$2,Inputs!$K$4:$AJ$4,0)))+SUMPRODUCT((Inputs!$C$5:$C$140=$B7)*Inputs!$D$5:$D$140*(((Inputs!$G$5:$G$140="moeda")+(Inputs!$G$5:$G$140="acoes"))*Inputs!$B$1+((Inputs!$G$5:$G$140<>"moeda")*(Inputs!$G$5:$G$140<>"acoes")))*INDEX(Inputs!$K$5:$AJ$140,0,MATCH(AD$2,Inputs!$K$4:$AJ$4,0)))+SUMPRODUCT((Inputs!$E$5:$E$140=$B7)*Inputs!$F$5:$F$140*(((Inputs!$G$5:$G$140="moeda")+(Inputs!$G$5:$G$140="acoes"))*Inputs!$B$1+((Inputs!$G$5:$G$140<>"moeda")*(Inputs!$G$5:$G$140<>"acoes")))*INDEX(Inputs!$K$5:$AJ$140,0,MATCH(AD$2,Inputs!$K$4:$AJ$4,0))))) -> -177.69 | AE7: =IF(ISNA(MATCH(AE$2,Inputs!$K$4:$AJ$4,0)),NA(),IF(SUMPRODUCT((Inputs!$A$5:$A$140=$B7)*ISNUMBER(INDEX(Inputs!$K$5:$AJ$140,0,MATCH(AE$2,Inputs!$K$4:$AJ$4,0))))+SUMPRODUCT((Inputs!$C$5:$C$140=$B7)*ISNUMBER(INDEX(Inputs!$K$5:$AJ$140,0,MATCH(AE$2,Inputs!$K$4:$AJ$4,0))))+SUMPRODUCT((Inputs!$E$5:$E$140=$B7)*ISNUMBER(INDEX(Inputs!$K$5:$AJ$140,0,MATCH(AE$2,Inputs!$K$4:$AJ$4,0))))=0,NA(),SUMPRODUCT((Inputs!$A$5:$A$140=$B7)*Inputs!$B$5:$B$140*(((Inputs!$G$5:$G$140="moeda")+(Inputs!$G$5:$G$140="acoes"))*Inputs!$B$1+((Inputs!$G$5:$G$140<>"moeda")*(Inputs!$G$5:$G$140<>"acoes")))*INDEX(Inputs!$K$5:$AJ$140,0,MATCH(AE$2,Inputs!$K$4:$AJ$4,0)))+SUMPRODUCT((Inputs!$C$5:$C$140=$B7)*Inputs!$D$5:$D$140*(((Inputs!$G$5:$G$140="moeda")+(Inputs!$G$5:$G$140="acoes"))*Inputs!$B$1+((Inputs!$G$5:$G$140<>"moeda")*(Inputs!$G$5:$G$140<>"acoes")))*INDEX(Inputs!$K$5:$AJ$140,0,MATCH(AE$2,Inputs!$K$4:$AJ$4,0)))+SUMPRODUCT((Inputs!$E$5:$E$140=$B7)*Inputs!$F$5:$F$140*(((Inputs!$G$5:$G$140="moeda")+(Inputs!$G$5:$G$140="acoes"))*Inputs!$B$1+((Inputs!$G$5:$G$140<>"moeda")*(Inputs!$G$5:$G$140<>"acoes")))*INDEX(Inputs!$K$5:$AJ$140,0,MATCH(AE$2,Inputs!$K$4:$AJ$4,0))))) -> #N/A | AF7: =IF(ISNA(MATCH(AF$2,Inputs!$K$4:$AJ$4,0)),NA(),IF(SUMPRODUCT((Inputs!$A$5:$A$140=$B7)*ISNUMBER(INDEX(Inputs!$K$5:$AJ$140,0,MATCH(AF$2,Inputs!$K$4:$AJ$4,0))))+SUMPRODUCT((Inputs!$C$5:$C$140=$B7)*ISNUMBER(INDEX(Inputs!$K$5:$AJ$140,0,MATCH(AF$2,Inputs!$K$4:$AJ$4,0))))+SUMPRODUCT((Inputs!$E$5:$E$140=$B7)*ISNUMBER(INDEX(Inputs!$K$5:$AJ$140,0,MATCH(AF$2,Inputs!$K$4:$AJ$4,0))))=0,NA(),SUMPRODUCT((Inputs!$A$5:$A$140=$B7)*Inputs!$B$5:$B$140*(((Inputs!$G$5:$G$140="moeda")+(Inputs!$G$5:$G$140="acoes"))*Inputs!$B$1+((Inputs!$G$5:$G$140<>"moeda")*(Inputs!$G$5:$G$140<>"acoes")))*INDEX(Inputs!$K$5:$AJ$140,0,MATCH(AF$2,Inputs!$K$4:$AJ$4,0)))+SUMPRODUCT((Inputs!$C$5:$C$140=$B7)*Inputs!$D$5:$D$140*(((Inputs!$G$5:$G$140="moeda")+(Inputs!$G$5:$G$140="acoes"))*Inputs!$B$1+((Inputs!$G$5:$G$140<>"moeda")*(Inputs!$G$5:$G$140<>"acoes")))*INDEX(Inputs!$K$5:$AJ$140,0,MATCH(AF$2,Inputs!$K$4:$AJ$4,0)))+SUMPRODUCT((Inputs!$E$5:$E$140=$B7)*Inputs!$F$5:$F$140*(((Inputs!$G$5:$G$140="moeda")+(Inputs!$G$5:$G$140="acoes"))*Inputs!$B$1+((Inputs!$G$5:$G$140<>"moeda")*(Inputs!$G$5:$G$140<>"acoes")))*INDEX(Inputs!$K$5:$AJ$140,0,MATCH(AF$2,Inputs!$K$4:$AJ$4,0))))) -> #N/A | AG7: =SUM(AC7:AF7) -> #N/A | AH7: =IF(ISNA(MATCH(AH$2,Inputs!$K$4:$AJ$4,0)),NA(),IF(SUMPRODUCT((Inputs!$A$5:$A$140=$B7)*ISNUMBER(INDEX(Inputs!$K$5:$AJ$140,0,MATCH(AH$2,Inputs!$K$4:$AJ$4,0))))+SUMPRODUCT((Inputs!$C$5:$C$140=$B7)*ISNUMBER(INDEX(Inputs!$K$5:$AJ$140,0,MATCH(AH$2,Inputs!$K$4:$AJ$4,0))))+SUMPRODUCT((Inputs!$E$5:$E$140=$B7)*ISNUMBER(INDEX(Inputs!$K$5:$AJ$140,0,MATCH(AH$2,Inputs!$K$4:$AJ$4,0))))=0,NA(),SUMPRODUCT((Inputs!$A$5:$A$140=$B7)*Inputs!$B$5:$B$140*(((Inputs!$G$5:$G$140="moeda")+(Inputs!$G$5:$G$140="acoes"))*Inputs!$B$1+((Inputs!$G$5:$G$140<>"moeda")*(Inputs!$G$5:$G$140<>"acoes")))*INDEX(Inputs!$K$5:$AJ$140,0,MATCH(AH$2,Inputs!$K$4:$AJ$4,0)))+SUMPRODUCT((Inputs!$C$5:$C$140=$B7)*Inputs!$D$5:$D$140*(((Inputs!$G$5:$G$140="moeda")+(Inputs!$G$5:$G$140="acoes"))*Inputs!$B$1+((Inputs!$G$5:$G$140<>"moeda")*(Inputs!$G$5:$G$140<>"acoes")))*INDEX(Inputs!$K$5:$AJ$140,0,MATCH(AH$2,Inputs!$K$4:$AJ$4,0)))+SUMPRODUCT((Inputs!$E$5:$E$140=$B7)*Inputs!$F$5:$F$140*(((Inputs!$G$5:$G$140="moeda")+(Inputs!$G$5:$G$140="acoes"))*Inputs!$B$1+((Inputs!$G$5:$G$140<>"moeda")*(Inputs!$G$5:$G$140<>"acoes")))*INDEX(Inputs!$K$5:$AJ$140,0,MATCH(AH$2,Inputs!$K$4:$AJ$4,0))))) -> -39.563 | AI7: =IF(ISNA(MATCH(AI$2,Inputs!$K$4:$AJ$4,0)),NA(),IF(SUMPRODUCT((Inputs!$A$5:$A$140=$B7)*ISNUMBER(INDEX(Inputs!$K$5:$AJ$140,0,MATCH(AI$2,Inputs!$K$4:$AJ$4,0))))+SUMPRODUCT((Inputs!$C$5:$C$140=$B7)*ISNUMBER(INDEX(Inputs!$K$5:$AJ$140,0,MATCH(AI$2,Inputs!$K$4:$AJ$4,0))))+SUMPRODUCT((Inputs!$E$5:$E$140=$B7)*ISNUMBER(INDEX(Inputs!$K$5:$AJ$140,0,MATCH(AI$2,Inputs!$K$4:$AJ$4,0))))=0,NA(),SUMPRODUCT((Inputs!$A$5:$A$140=$B7)*Inputs!$B$5:$B$140*(((Inputs!$G$5:$G$140="moeda")+(Inputs!$G$5:$G$140="acoes"))*Inputs!$B$1+((Inputs!$G$5:$G$140<>"moeda")*(Inputs!$G$5:$G$140<>"acoes")))*INDEX(Inputs!$K$5:$AJ$140,0,MATCH(AI$2,Inputs!$K$4:$AJ$4,0)))+SUMPRODUCT((Inputs!$C$5:$C$140=$B7)*Inputs!$D$5:$D$140*(((Inputs!$G$5:$G$140="moeda")+(Inputs!$G$5:$G$140="acoes"))*Inputs!$B$1+((Inputs!$G$5:$G$140<>"moeda")*(Inputs!$G$5:$G$140<>"acoes")))*INDEX(Inputs!$K$5:$AJ$140,0,MATCH(AI$2,Inputs!$K$4:$AJ$4,0)))+SUMPRODUCT((Inputs!$E$5:$E$140=$B7)*Inputs!$F$5:$F$140*(((Inputs!$G$5:$G$140="moeda")+(Inputs!$G$5:$G$140="acoes"))*Inputs!$B$1+((Inputs!$G$5:$G$140<>"moeda")*(Inputs!$G$5:$G$140<>"acoes")))*INDEX(Inputs!$K$5:$AJ$140,0,MATCH(AI$2,Inputs!$K$4:$AJ$4,0))))) -> -53.788 | AJ7: =IF(ISNA(MATCH(AJ$2,Inputs!$K$4:$AJ$4,0)),NA(),IF(SUMPRODUCT((Inputs!$A$5:$A$140=$B7)*ISNUMBER(INDEX(Inputs!$K$5:$AJ$140,0,MATCH(AJ$2,Inputs!$K$4:$AJ$4,0))))+SUMPRODUCT((Inputs!$C$5:$C$140=$B7)*ISNUMBER(INDEX(Inputs!$K$5:$AJ$140,0,MATCH(AJ$2,Inputs!$K$4:$AJ$4,0))))+SUMPRODUCT((Inputs!$E$5:$E$140=$B7)*ISNUMBER(INDEX(Inputs!$K$5:$AJ$140,0,MATCH(AJ$2,Inputs!$K$4:$AJ$4,0))))=0,NA(),SUMPRODUCT((Inputs!$A$5:$A$140=$B7)*Inputs!$B$5:$B$140*(((Inputs!$G$5:$G$140="moeda")+(Inputs!$G$5:$G$140="acoes"))*Inputs!$B$1+((Inputs!$G$5:$G$140<>"moeda")*(Inputs!$G$5:$G$140<>"acoes")))*INDEX(Inputs!$K$5:$AJ$140,0,MATCH(AJ$2,Inputs!$K$4:$AJ$4,0)))+SUMPRODUCT((Inputs!$C$5:$C$140=$B7)*Inputs!$D$5:$D$140*(((Inputs!$G$5:$G$140="moeda")+(Inputs!$G$5:$G$140="acoes"))*Inputs!$B$1+((Inputs!$G$5:$G$140<>"moeda")*(Inputs!$G$5:$G$140<>"acoes")))*INDEX(Inputs!$K$5:$AJ$140,0,MATCH(AJ$2,Inputs!$K$4:$AJ$4,0)))+SUMPRODUCT((Inputs!$E$5:$E$140=$B7)*Inputs!$F$5:$F$140*(((Inputs!$G$5:$G$140="moeda")+(Inputs!$G$5:$G$140="acoes"))*Inputs!$B$1+((Inputs!$G$5:$G$140<>"moeda")*(Inputs!$G$5:$G$140<>"acoes")))*INDEX(Inputs!$K$5:$AJ$140,0,MATCH(AJ$2,Inputs!$K$4:$AJ$4,0))))) -> -42.927 | AK7: =IF(ISNA(MATCH(AK$2,Inputs!$K$4:$AJ$4,0)),NA(),IF(SUMPRODUCT((Inputs!$A$5:$A$140=$B7)*ISNUMBER(INDEX(Inputs!$K$5:$AJ$140,0,MATCH(AK$2,Inputs!$K$4:$AJ$4,0))))+SUMPRODUCT((Inputs!$C$5:$C$140=$B7)*ISNUMBER(INDEX(Inputs!$K$5:$AJ$140,0,MATCH(AK$2,Inputs!$K$4:$AJ$4,0))))+SUMPRODUCT((Inputs!$E$5:$E$140=$B7)*ISNUMBER(INDEX(Inputs!$K$5:$AJ$140,0,MATCH(AK$2,Inputs!$K$4:$AJ$4,0))))=0,NA(),SUMPRODUCT((Inputs!$A$5:$A$140=$B7)*Inputs!$B$5:$B$140*(((Inputs!$G$5:$G$140="moeda")+(Inputs!$G$5:$G$140="acoes"))*Inputs!$B$1+((Inputs!$G$5:$G$140<>"moeda")*(Inputs!$G$5:$G$140<>"acoes")))*INDEX(Inputs!$K$5:$AJ$140,0,MATCH(AK$2,Inputs!$K$4:$AJ$4,0)))+SUMPRODUCT((Inputs!$C$5:$C$140=$B7)*Inputs!$D$5:$D$140*(((Inputs!$G$5:$G$140="moeda")+(Inputs!$G$5:$G$140="acoes"))*Inputs!$B$1+((Inputs!$G$5:$G$140<>"moeda")*(Inputs!$G$5:$G$140<>"acoes")))*INDEX(Inputs!$K$5:$AJ$140,0,MATCH(AK$2,Inputs!$K$4:$AJ$4,0)))+SUMPRODUCT((Inputs!$E$5:$E$140=$B7)*Inputs!$F$5:$F$140*(((Inputs!$G$5:$G$140="moeda")+(Inputs!$G$5:$G$140="acoes"))*Inputs!$B$1+((Inputs!$G$5:$G$140<>"moeda")*(Inputs!$G$5:$G$140<>"acoes")))*INDEX(Inputs!$K$5:$AJ$140,0,MATCH(AK$2,Inputs!$K$4:$AJ$4,0))))) -> -43.686 | AL7: =SUM(AH7:AK7) -> -179.964
B8: 5 | C8: Interest Expense | D8: =IF(ISNA(MATCH(D$2,Inputs!$K$4:$AJ$4,0)),NA(),IF(SUMPRODUCT((Inputs!$A$5:$A$140=$B8)*ISNUMBER(INDEX(Inputs!$K$5:$AJ$140,0,MATCH(D$2,Inputs!$K$4:$AJ$4,0))))+SUMPRODUCT((Inputs!$C$5:$C$140=$B8)*ISNUMBER(INDEX(Inputs!$K$5:$AJ$140,0,MATCH(D$2,Inputs!$K$4:$AJ$4,0))))+SUMPRODUCT((Inputs!$E$5:$E$140=$B8)*ISNUMBER(INDEX(Inputs!$K$5:$AJ$140,0,MATCH(D$2,Inputs!$K$4:$AJ$4,0))))=0,NA(),SUMPRODUCT((Inputs!$A$5:$A$140=$B8)*Inputs!$B$5:$B$140*(((Inputs!$G$5:$G$140="moeda")+(Inputs!$G$5:$G$140="acoes"))*Inputs!$B$1+((Inputs!$G$5:$G$140<>"moeda")*(Inputs!$G$5:$G$140<>"acoes")))*INDEX(Inputs!$K$5:$AJ$140,0,MATCH(D$2,Inputs!$K$4:$AJ$4,0)))+SUMPRODUCT((Inputs!$C$5:$C$140=$B8)*Inputs!$D$5:$D$140*(((Inputs!$G$5:$G$140="moeda")+(Inputs!$G$5:$G$140="acoes"))*Inputs!$B$1+((Inputs!$G$5:$G$140<>"moeda")*(Inputs!$G$5:$G$140<>"acoes")))*INDEX(Inputs!$K$5:$AJ$140,0,MATCH(D$2,Inputs!$K$4:$AJ$4,0)))+SUMPRODUCT((Inputs!$E$5:$E$140=$B8)*Inputs!$F$5:$F$140*(((Inputs!$G$5:$G$140="moeda")+(Inputs!$G$5:$G$140="acoes"))*Inputs!$B$1+((Inputs!$G$5:$G$140<>"moeda")*(Inputs!$G$5:$G$140<>"acoes")))*INDEX(Inputs!$K$5:$AJ$140,0,MATCH(D$2,Inputs!$K$4:$AJ$4,0))))) -> -50.47 | E8: =IF(ISNA(MATCH(E$2,Inputs!$K$4:$AJ$4,0)),NA(),IF(SUMPRODUCT((Inputs!$A$5:$A$140=$B8)*ISNUMBER(INDEX(Inputs!$K$5:$AJ$140,0,MATCH(E$2,Inputs!$K$4:$AJ$4,0))))+SUMPRODUCT((Inputs!$C$5:$C$140=$B8)*ISNUMBER(INDEX(Inputs!$K$5:$AJ$140,0,MATCH(E$2,Inputs!$K$4:$AJ$4,0))))+SUMPRODUCT((Inputs!$E$5:$E$140=$B8)*ISNUMBER(INDEX(Inputs!$K$5:$AJ$140,0,MATCH(E$2,Inputs!$K$4:$AJ$4,0))))=0,NA(),SUMPRODUCT((Inputs!$A$5:$A$140=$B8)*Inputs!$B$5:$B$140*(((Inputs!$G$5:$G$140="moeda")+(Inputs!$G$5:$G$140="acoes"))*Inputs!$B$1+((Inputs!$G$5:$G$140<>"moeda")*(Inputs!$G$5:$G$140<>"acoes")))*INDEX(Inputs!$K$5:$AJ$140,0,MATCH(E$2,Inputs!$K$4:$AJ$4,0)))+SUMPRODUCT((Inputs!$C$5:$C$140=$B8)*Inputs!$D$5:$D$140*(((Inputs!$G$5:$G$140="moeda")+(Inputs!$G$5:$G$140="acoes"))*Inputs!$B$1+((Inputs!$G$5:$G$140<>"moeda")*(Inputs!$G$5:$G$140<>"acoes")))*INDEX(Inputs!$K$5:$AJ$140,0,MATCH(E$2,Inputs!$K$4:$AJ$4,0)))+SUMPRODUCT((Inputs!$E$5:$E$140=$B8)*Inputs!$F$5:$F$140*(((Inputs!$G$5:$G$140="moeda")+(Inputs!$G$5:$G$140="acoes"))*Inputs!$B$1+((Inputs!$G$5:$G$140<>"moeda")*(Inputs!$G$5:$G$140<>"acoes")))*INDEX(Inputs!$K$5:$AJ$140,0,MATCH(E$2,Inputs!$K$4:$AJ$4,0))))) -> -56.216 | F8: =IF(ISNA(MATCH(F$2,Inputs!$K$4:$AJ$4,0)),NA(),IF(SUMPRODUCT((Inputs!$A$5:$A$140=$B8)*ISNUMBER(INDEX(Inputs!$K$5:$AJ$140,0,MATCH(F$2,Inputs!$K$4:$AJ$4,0))))+SUMPRODUCT((Inputs!$C$5:$C$140=$B8)*ISNUMBER(INDEX(Inputs!$K$5:$AJ$140,0,MATCH(F$2,Inputs!$K$4:$AJ$4,0))))+SUMPRODUCT((Inputs!$E$5:$E$140=$B8)*ISNUMBER(INDEX(Inputs!$K$5:$AJ$140,0,MATCH(F$2,Inputs!$K$4:$AJ$4,0))))=0,NA(),SUMPRODUCT((Inputs!$A$5:$A$140=$B8)*Inputs!$B$5:$B$140*(((Inputs!$G$5:$G$140="moeda")+(Inputs!$G$5:$G$140="acoes"))*Inputs!$B$1+((Inputs!$G$5:$G$140<>"moeda")*(Inputs!$G$5:$G$140<>"acoes")))*INDEX(Inputs!$K$5:$AJ$140,0,MATCH(F$2,Inputs!$K$4:$AJ$4,0)))+SUMPRODUCT((Inputs!$C$5:$C$140=$B8)*Inputs!$D$5:$D$140*(((Inputs!$G$5:$G$140="moeda")+(Inputs!$G$5:$G$140="acoes"))*Inputs!$B$1+((Inputs!$G$5:$G$140<>"moeda")*(Inputs!$G$5:$G$140<>"acoes")))*INDEX(Inputs!$K$5:$AJ$140,0,MATCH(F$2,Inputs!$K$4:$AJ$4,0)))+SUMPRODUCT((Inputs!$E$5:$E$140=$B8)*Inputs!$F$5:$F$140*(((Inputs!$G$5:$G$140="moeda")+(Inputs!$G$5:$G$140="acoes"))*Inputs!$B$1+((Inputs!$G$5:$G$140<>"moeda")*(Inputs!$G$5:$G$140<>"acoes")))*INDEX(Inputs!$K$5:$AJ$140,0,MATCH(F$2,Inputs!$K$4:$AJ$4,0))))) -> -91.211 | G8: =IF(ISNA(MATCH(G$2,Inputs!$K$4:$AJ$4,0)),NA(),IF(SUMPRODUCT((Inputs!$A$5:$A$140=$B8)*ISNUMBER(INDEX(Inputs!$K$5:$AJ$140,0,MATCH(G$2,Inputs!$K$4:$AJ$4,0))))+SUMPRODUCT((Inputs!$C$5:$C$140=$B8)*ISNUMBER(INDEX(Inputs!$K$5:$AJ$140,0,MATCH(G$2,Inputs!$K$4:$AJ$4,0))))+SUMPRODUCT((Inputs!$E$5:$E$140=$B8)*ISNUMBER(INDEX(Inputs!$K$5:$AJ$140,0,MATCH(G$2,Inputs!$K$4:$AJ$4,0))))=0,NA(),SUMPRODUCT((Inputs!$A$5:$A$140=$B8)*Inputs!$B$5:$B$140*(((Inputs!$G$5:$G$140="moeda")+(Inputs!$G$5:$G$140="acoes"))*Inputs!$B$1+((Inputs!$G$5:$G$140<>"moeda")*(Inputs!$G$5:$G$140<>"acoes")))*INDEX(Inputs!$K$5:$AJ$140,0,MATCH(G$2,Inputs!$K$4:$AJ$4,0)))+SUMPRODUCT((Inputs!$C$5:$C$140=$B8)*Inputs!$D$5:$D$140*(((Inputs!$G$5:$G$140="moeda")+(Inputs!$G$5:$G$140="acoes"))*Inputs!$B$1+((Inputs!$G$5:$G$140<>"moeda")*(Inputs!$G$5:$G$140<>"acoes")))*INDEX(Inputs!$K$5:$AJ$140,0,MATCH(G$2,Inputs!$K$4:$AJ$4,0)))+SUMPRODUCT((Inputs!$E$5:$E$140=$B8)*Inputs!$F$5:$F$140*(((Inputs!$G$5:$G$140="moeda")+(Inputs!$G$5:$G$140="acoes"))*Inputs!$B$1+((Inputs!$G$5:$G$140<>"moeda")*(Inputs!$G$5:$G$140<>"acoes")))*INDEX(Inputs!$K$5:$AJ$140,0,MATCH(G$2,Inputs!$K$4:$AJ$4,0))))) -> -71.983 | H8: =SUM(D8:G8) -> -269.88 | I8: =IF(ISNA(MATCH(I$2,Inputs!$K$4:$AJ$4,0)),NA(),IF(SUMPRODUCT((Inputs!$A$5:$A$140=$B8)*ISNUMBER(INDEX(Inputs!$K$5:$AJ$140,0,MATCH(I$2,Inputs!$K$4:$AJ$4,0))))+SUMPRODUCT((Inputs!$C$5:$C$140=$B8)*ISNUMBER(INDEX(Inputs!$K$5:$AJ$140,0,MATCH(I$2,Inputs!$K$4:$AJ$4,0))))+SUMPRODUCT((Inputs!$E$5:$E$140=$B8)*ISNUMBER(INDEX(Inputs!$K$5:$AJ$140,0,MATCH(I$2,Inputs!$K$4:$AJ$4,0))))=0,NA(),SUMPRODUCT((Inputs!$A$5:$A$140=$B8)*Inputs!$B$5:$B$140*(((Inputs!$G$5:$G$140="moeda")+(Inputs!$G$5:$G$140="acoes"))*Inputs!$B$1+((Inputs!$G$5:$G$140<>"moeda")*(Inputs!$G$5:$G$140<>"acoes")))*INDEX(Inputs!$K$5:$AJ$140,0,MATCH(I$2,Inputs!$K$4:$AJ$4,0)))+SUMPRODUCT((Inputs!$C$5:$C$140=$B8)*Inputs!$D$5:$D$140*(((Inputs!$G$5:$G$140="moeda")+(Inputs!$G$5:$G$140="acoes"))*Inputs!$B$1+((Inputs!$G$5:$G$140<>"moeda")*(Inputs!$G$5:$G$140<>"acoes")))*INDEX(Inputs!$K$5:$AJ$140,0,MATCH(I$2,Inputs!$K$4:$AJ$4,0)))+SUMPRODUCT((Inputs!$E$5:$E$140=$B8)*Inputs!$F$5:$F$140*(((Inputs!$G$5:$G$140="moeda")+(Inputs!$G$5:$G$140="acoes"))*Inputs!$B$1+((Inputs!$G$5:$G$140<>"moeda")*(Inputs!$G$5:$G$140<>"acoes")))*INDEX(Inputs!$K$5:$AJ$140,0,MATCH(I$2,Inputs!$K$4:$AJ$4,0))))) -> -73.218 | J8: =IF(ISNA(MATCH(J$2,Inputs!$K$4:$AJ$4,0)),NA(),IF(SUMPRODUCT((Inputs!$A$5:$A$140=$B8)*ISNUMBER(INDEX(Inputs!$K$5:$AJ$140,0,MATCH(J$2,Inputs!$K$4:$AJ$4,0))))+SUMPRODUCT((Inputs!$C$5:$C$140=$B8)*ISNUMBER(INDEX(Inputs!$K$5:$AJ$140,0,MATCH(J$2,Inputs!$K$4:$AJ$4,0))))+SUMPRODUCT((Inputs!$E$5:$E$140=$B8)*ISNUMBER(INDEX(Inputs!$K$5:$AJ$140,0,MATCH(J$2,Inputs!$K$4:$AJ$4,0))))=0,NA(),SUMPRODUCT((Inputs!$A$5:$A$140=$B8)*Inputs!$B$5:$B$140*(((Inputs!$G$5:$G$140="moeda")+(Inputs!$G$5:$G$140="acoes"))*Inputs!$B$1+((Inputs!$G$5:$G$140<>"moeda")*(Inputs!$G$5:$G$140<>"acoes")))*INDEX(Inputs!$K$5:$AJ$140,0,MATCH(J$2,Inputs!$K$4:$AJ$4,0)))+SUMPRODUCT((Inputs!$C$5:$C$140=$B8)*Inputs!$D$5:$D$140*(((Inputs!$G$5:$G$140="moeda")+(Inputs!$G$5:$G$140="acoes"))*Inputs!$B$1+((Inputs!$G$5:$G$140<>"moeda")*(Inputs!$G$5:$G$140<>"acoes")))*INDEX(Inputs!$K$5:$AJ$140,0,MATCH(J$2,Inputs!$K$4:$AJ$4,0)))+SUMPRODUCT((Inputs!$E$5:$E$140=$B8)*Inputs!$F$5:$F$140*(((Inputs!$G$5:$G$140="moeda")+(Inputs!$G$5:$G$140="acoes"))*Inputs!$B$1+((Inputs!$G$5:$G$140<>"moeda")*(Inputs!$G$5:$G$140<>"acoes")))*INDEX(Inputs!$K$5:$AJ$140,0,MATCH(J$2,Inputs!$K$4:$AJ$4,0))))) -> -94.761779 | K8: =IF(ISNA(MATCH(K$2,Inputs!$K$4:$AJ$4,0)),NA(),IF(SUMPRODUCT((Inputs!$A$5:$A$140=$B8)*ISNUMBER(INDEX(Inputs!$K$5:$AJ$140,0,MATCH(K$2,Inputs!$K$4:$AJ$4,0))))+SUMPRODUCT((Inputs!$C$5:$C$140=$B8)*ISNUMBER(INDEX(Inputs!$K$5:$AJ$140,0,MATCH(K$2,Inputs!$K$4:$AJ$4,0))))+SUMPRODUCT((Inputs!$E$5:$E$140=$B8)*ISNUMBER(INDEX(Inputs!$K$5:$AJ$140,0,MATCH(K$2,Inputs!$K$4:$AJ$4,0))))=0,NA(),SUMPRODUCT((Inputs!$A$5:$A$140=$B8)*Inputs!$B$5:$B$140*(((Inputs!$G$5:$G$140="moeda")+(Inputs!$G$5:$G$140="acoes"))*Inputs!$B$1+((Inputs!$G$5:$G$140<>"moeda")*(Inputs!$G$5:$G$140<>"acoes")))*INDEX(Inputs!$K$5:$AJ$140,0,MATCH(K$2,Inputs!$K$4:$AJ$4,0)))+SUMPRODUCT((Inputs!$C$5:$C$140=$B8)*Inputs!$D$5:$D$140*(((Inputs!$G$5:$G$140="moeda")+(Inputs!$G$5:$G$140="acoes"))*Inputs!$B$1+((Inputs!$G$5:$G$140<>"moeda")*(Inputs!$G$5:$G$140<>"acoes")))*INDEX(Inputs!$K$5:$AJ$140,0,MATCH(K$2,Inputs!$K$4:$AJ$4,0)))+SUMPRODUCT((Inputs!$E$5:$E$140=$B8)*Inputs!$F$5:$F$140*(((Inputs!$G$5:$G$140="moeda")+(Inputs!$G$5:$G$140="acoes"))*Inputs!$B$1+((Inputs!$G$5:$G$140<>"moeda")*(Inputs!$G$5:$G$140<>"acoes")))*INDEX(Inputs!$K$5:$AJ$140,0,MATCH(K$2,Inputs!$K$4:$AJ$4,0))))) -> -137.924 | L8: =IF(ISNA(MATCH(L$2,Inputs!$K$4:$AJ$4,0)),NA(),IF(SUMPRODUCT((Inputs!$A$5:$A$140=$B8)*ISNUMBER(INDEX(Inputs!$K$5:$AJ$140,0,MATCH(L$2,Inputs!$K$4:$AJ$4,0))))+SUMPRODUCT((Inputs!$C$5:$C$140=$B8)*ISNUMBER(INDEX(Inputs!$K$5:$AJ$140,0,MATCH(L$2,Inputs!$K$4:$AJ$4,0))))+SUMPRODUCT((Inputs!$E$5:$E$140=$B8)*ISNUMBER(INDEX(Inputs!$K$5:$AJ$140,0,MATCH(L$2,Inputs!$K$4:$AJ$4,0))))=0,NA(),SUMPRODUCT((Inputs!$A$5:$A$140=$B8)*Inputs!$B$5:$B$140*(((Inputs!$G$5:$G$140="moeda")+(Inputs!$G$5:$G$140="acoes"))*Inputs!$B$1+((Inputs!$G$5:$G$140<>"moeda")*(Inputs!$G$5:$G$140<>"acoes")))*INDEX(Inputs!$K$5:$AJ$140,0,MATCH(L$2,Inputs!$K$4:$AJ$4,0)))+SUMPRODUCT((Inputs!$C$5:$C$140=$B8)*Inputs!$D$5:$D$140*(((Inputs!$G$5:$G$140="moeda")+(Inputs!$G$5:$G$140="acoes"))*Inputs!$B$1+((Inputs!$G$5:$G$140<>"moeda")*(Inputs!$G$5:$G$140<>"acoes")))*INDEX(Inputs!$K$5:$AJ$140,0,MATCH(L$2,Inputs!$K$4:$AJ$4,0)))+SUMPRODUCT((Inputs!$E$5:$E$140=$B8)*Inputs!$F$5:$F$140*(((Inputs!$G$5:$G$140="moeda")+(Inputs!$G$5:$G$140="acoes"))*Inputs!$B$1+((Inputs!$G$5:$G$140<>"moeda")*(Inputs!$G$5:$G$140<>"acoes")))*INDEX(Inputs!$K$5:$AJ$140,0,MATCH(L$2,Inputs!$K$4:$AJ$4,0))))) -> -154.73222 | M8: =SUM(I8:L8) -> -460.636 | N8: =IF(ISNA(MATCH(N$2,Inputs!$K$4:$AJ$4,0)),NA(),IF(SUMPRODUCT((Inputs!$A$5:$A$140=$B8)*ISNUMBER(INDEX(Inputs!$K$5:$AJ$140,0,MATCH(N$2,Inputs!$K$4:$AJ$4,0))))+SUMPRODUCT((Inputs!$C$5:$C$140=$B8)*ISNUMBER(INDEX(Inputs!$K$5:$AJ$140,0,MATCH(N$2,Inputs!$K$4:$AJ$4,0))))+SUMPRODUCT((Inputs!$E$5:$E$140=$B8)*ISNUMBER(INDEX(Inputs!$K$5:$AJ$140,0,MATCH(N$2,Inputs!$K$4:$AJ$4,0))))=0,NA(),SUMPRODUCT((Inputs!$A$5:$A$140=$B8)*Inputs!$B$5:$B$140*(((Inputs!$G$5:$G$140="moeda")+(Inputs!$G$5:$G$140="acoes"))*Inputs!$B$1+((Inputs!$G$5:$G$140<>"moeda")*(Inputs!$G$5:$G$140<>"acoes")))*INDEX(Inputs!$K$5:$AJ$140,0,MATCH(N$2,Inputs!$K$4:$AJ$4,0)))+SUMPRODUCT((Inputs!$C$5:$C$140=$B8)*Inputs!$D$5:$D$140*(((Inputs!$G$5:$G$140="moeda")+(Inputs!$G$5:$G$140="acoes"))*Inputs!$B$1+((Inputs!$G$5:$G$140<>"moeda")*(Inputs!$G$5:$G$140<>"acoes")))*INDEX(Inputs!$K$5:$AJ$140,0,MATCH(N$2,Inputs!$K$4:$AJ$4,0)))+SUMPRODUCT((Inputs!$E$5:$E$140=$B8)*Inputs!$F$5:$F$140*(((Inputs!$G$5:$G$140="moeda")+(Inputs!$G$5:$G$140="acoes"))*Inputs!$B$1+((Inputs!$G$5:$G$140<>"moeda")*(Inputs!$G$5:$G$140<>"acoes")))*INDEX(Inputs!$K$5:$AJ$140,0,MATCH(N$2,Inputs!$K$4:$AJ$4,0))))) -> -135.96 | O8: =IF(ISNA(MATCH(O$2,Inputs!$K$4:$AJ$4,0)),NA(),IF(SUMPRODUCT((Inputs!$A$5:$A$140=$B8)*ISNUMBER(INDEX(Inputs!$K$5:$AJ$140,0,MATCH(O$2,Inputs!$K$4:$AJ$4,0))))+SUMPRODUCT((Inputs!$C$5:$C$140=$B8)*ISNUMBER(INDEX(Inputs!$K$5:$AJ$140,0,MATCH(O$2,Inputs!$K$4:$AJ$4,0))))+SUMPRODUCT((Inputs!$E$5:$E$140=$B8)*ISNUMBER(INDEX(Inputs!$K$5:$AJ$140,0,MATCH(O$2,Inputs!$K$4:$AJ$4,0))))=0,NA(),SUMPRODUCT((Inputs!$A$5:$A$140=$B8)*Inputs!$B$5:$B$140*(((Inputs!$G$5:$G$140="moeda")+(Inputs!$G$5:$G$140="acoes"))*Inputs!$B$1+((Inputs!$G$5:$G$140<>"moeda")*(Inputs!$G$5:$G$140<>"acoes")))*INDEX(Inputs!$K$5:$AJ$140,0,MATCH(O$2,Inputs!$K$4:$AJ$4,0)))+SUMPRODUCT((Inputs!$C$5:$C$140=$B8)*Inputs!$D$5:$D$140*(((Inputs!$G$5:$G$140="moeda")+(Inputs!$G$5:$G$140="acoes"))*Inputs!$B$1+((Inputs!$G$5:$G$140<>"moeda")*(Inputs!$G$5:$G$140<>"acoes")))*INDEX(Inputs!$K$5:$AJ$140,0,MATCH(O$2,Inputs!$K$4:$AJ$4,0)))+SUMPRODUCT((Inputs!$E$5:$E$140=$B8)*Inputs!$F$5:$F$140*(((Inputs!$G$5:$G$140="moeda")+(Inputs!$G$5:$G$140="acoes"))*Inputs!$B$1+((Inputs!$G$5:$G$140<>"moeda")*(Inputs!$G$5:$G$140<>"acoes")))*INDEX(Inputs!$K$5:$AJ$140,0,MATCH(O$2,Inputs!$K$4:$AJ$4,0))))) -> -166.879 | P8: =IF(ISNA(MATCH(P$2,Inputs!$K$4:$AJ$4,0)),NA(),IF(SUMPRODUCT((Inputs!$A$5:$A$140=$B8)*ISNUMBER(INDEX(Inputs!$K$5:$AJ$140,0,MATCH(P$2,Inputs!$K$4:$AJ$4,0))))+SUMPRODUCT((Inputs!$C$5:$C$140=$B8)*ISNUMBER(INDEX(Inputs!$K$5:$AJ$140,0,MATCH(P$2,Inputs!$K$4:$AJ$4,0))))+SUMPRODUCT((Inputs!$E$5:$E$140=$B8)*ISNUMBER(INDEX(Inputs!$K$5:$AJ$140,0,MATCH(P$2,Inputs!$K$4:$AJ$4,0))))=0,NA(),SUMPRODUCT((Inputs!$A$5:$A$140=$B8)*Inputs!$B$5:$B$140*(((Inputs!$G$5:$G$140="moeda")+(Inputs!$G$5:$G$140="acoes"))*Inputs!$B$1+((Inputs!$G$5:$G$140<>"moeda")*(Inputs!$G$5:$G$140<>"acoes")))*INDEX(Inputs!$K$5:$AJ$140,0,MATCH(P$2,Inputs!$K$4:$AJ$4,0)))+SUMPRODUCT((Inputs!$C$5:$C$140=$B8)*Inputs!$D$5:$D$140*(((Inputs!$G$5:$G$140="moeda")+(Inputs!$G$5:$G$140="acoes"))*Inputs!$B$1+((Inputs!$G$5:$G$140<>"moeda")*(Inputs!$G$5:$G$140<>"acoes")))*INDEX(Inputs!$K$5:$AJ$140,0,MATCH(P$2,Inputs!$K$4:$AJ$4,0)))+SUMPRODUCT((Inputs!$E$5:$E$140=$B8)*Inputs!$F$5:$F$140*(((Inputs!$G$5:$G$140="moeda")+(Inputs!$G$5:$G$140="acoes"))*Inputs!$B$1+((Inputs!$G$5:$G$140<>"moeda")*(Inputs!$G$5:$G$140<>"acoes")))*INDEX(Inputs!$K$5:$AJ$140,0,MATCH(P$2,Inputs!$K$4:$AJ$4,0))))) -> -163.903 | Q8: =IF(ISNA(MATCH(Q$2,Inputs!$K$4:$AJ$4,0)),NA(),IF(SUMPRODUCT((Inputs!$A$5:$A$140=$B8)*ISNUMBER(INDEX(Inputs!$K$5:$AJ$140,0,MATCH(Q$2,Inputs!$K$4:$AJ$4,0))))+SUMPRODUCT((Inputs!$C$5:$C$140=$B8)*ISNUMBER(INDEX(Inputs!$K$5:$AJ$140,0,MATCH(Q$2,Inputs!$K$4:$AJ$4,0))))+SUMPRODUCT((Inputs!$E$5:$E$140=$B8)*ISNUMBER(INDEX(Inputs!$K$5:$AJ$140,0,MATCH(Q$2,Inputs!$K$4:$AJ$4,0))))=0,NA(),SUMPRODUCT((Inputs!$A$5:$A$140=$B8)*Inputs!$B$5:$B$140*(((Inputs!$G$5:$G$140="moeda")+(Inputs!$G$5:$G$140="acoes"))*Inputs!$B$1+((Inputs!$G$5:$G$140<>"moeda")*(Inputs!$G$5:$G$140<>"acoes")))*INDEX(Inputs!$K$5:$AJ$140,0,MATCH(Q$2,Inputs!$K$4:$AJ$4,0)))+SUMPRODUCT((Inputs!$C$5:$C$140=$B8)*Inputs!$D$5:$D$140*(((Inputs!$G$5:$G$140="moeda")+(Inputs!$G$5:$G$140="acoes"))*Inputs!$B$1+((Inputs!$G$5:$G$140<>"moeda")*(Inputs!$G$5:$G$140<>"acoes")))*INDEX(Inputs!$K$5:$AJ$140,0,MATCH(Q$2,Inputs!$K$4:$AJ$4,0)))+SUMPRODUCT((Inputs!$E$5:$E$140=$B8)*Inputs!$F$5:$F$140*(((Inputs!$G$5:$G$140="moeda")+(Inputs!$G$5:$G$140="acoes"))*Inputs!$B$1+((Inputs!$G$5:$G$140<>"moeda")*(Inputs!$G$5:$G$140<>"acoes")))*INDEX(Inputs!$K$5:$AJ$140,0,MATCH(Q$2,Inputs!$K$4:$AJ$4,0))))) -> -180.578 | R8: =SUM(N8:Q8) -> -647.32 | S8: =IF(ISNA(MATCH(S$2,Inputs!$K$4:$AJ$4,0)),NA(),IF(SUMPRODUCT((Inputs!$A$5:$A$140=$B8)*ISNUMBER(INDEX(Inputs!$K$5:$AJ$140,0,MATCH(S$2,Inputs!$K$4:$AJ$4,0))))+SUMPRODUCT((Inputs!$C$5:$C$140=$B8)*ISNUMBER(INDEX(Inputs!$K$5:$AJ$140,0,MATCH(S$2,Inputs!$K$4:$AJ$4,0))))+SUMPRODUCT((Inputs!$E$5:$E$140=$B8)*ISNUMBER(INDEX(Inputs!$K$5:$AJ$140,0,MATCH(S$2,Inputs!$K$4:$AJ$4,0))))=0,NA(),SUMPRODUCT((Inputs!$A$5:$A$140=$B8)*Inputs!$B$5:$B$140*(((Inputs!$G$5:$G$140="moeda")+(Inputs!$G$5:$G$140="acoes"))*Inputs!$B$1+((Inputs!$G$5:$G$140<>"moeda")*(Inputs!$G$5:$G$140<>"acoes")))*INDEX(Inputs!$K$5:$AJ$140,0,MATCH(S$2,Inputs!$K$4:$AJ$4,0)))+SUMPRODUCT((Inputs!$C$5:$C$140=$B8)*Inputs!$D$5:$D$140*(((Inputs!$G$5:$G$140="moeda")+(Inputs!$G$5:$G$140="acoes"))*Inputs!$B$1+((Inputs!$G$5:$G$140<>"moeda")*(Inputs!$G$5:$G$140<>"acoes")))*INDEX(Inputs!$K$5:$AJ$140,0,MATCH(S$2,Inputs!$K$4:$AJ$4,0)))+SUMPRODUCT((Inputs!$E$5:$E$140=$B8)*Inputs!$F$5:$F$140*(((Inputs!$G$5:$G$140="moeda")+(Inputs!$G$5:$G$140="acoes"))*Inputs!$B$1+((Inputs!$G$5:$G$140<>"moeda")*(Inputs!$G$5:$G$140<>"acoes")))*INDEX(Inputs!$K$5:$AJ$140,0,MATCH(S$2,Inputs!$K$4:$AJ$4,0))))) -> -187.30166 | T8: =IF(ISNA(MATCH(T$2,Inputs!$K$4:$AJ$4,0)),NA(),IF(SUMPRODUCT((Inputs!$A$5:$A$140=$B8)*ISNUMBER(INDEX(Inputs!$K$5:$AJ$140,0,MATCH(T$2,Inputs!$K$4:$AJ$4,0))))+SUMPRODUCT((Inputs!$C$5:$C$140=$B8)*ISNUMBER(INDEX(Inputs!$K$5:$AJ$140,0,MATCH(T$2,Inputs!$K$4:$AJ$4,0))))+SUMPRODUCT((Inputs!$E$5:$E$140=$B8)*ISNUMBER(INDEX(Inputs!$K$5:$AJ$140,0,MATCH(T$2,Inputs!$K$4:$AJ$4,0))))=0,NA(),SUMPRODUCT((Inputs!$A$5:$A$140=$B8)*Inputs!$B$5:$B$140*(((Inputs!$G$5:$G$140="moeda")+(Inputs!$G$5:$G$140="acoes"))*Inputs!$B$1+((Inputs!$G$5:$G$140<>"moeda")*(Inputs!$G$5:$G$140<>"acoes")))*INDEX(Inputs!$K$5:$AJ$140,0,MATCH(T$2,Inputs!$K$4:$AJ$4,0)))+SUMPRODUCT((Inputs!$C$5:$C$140=$B8)*Inputs!$D$5:$D$140*(((Inputs!$G$5:$G$140="moeda")+(Inputs!$G$5:$G$140="acoes"))*Inputs!$B$1+((Inputs!$G$5:$G$140<>"moeda")*(Inputs!$G$5:$G$140<>"acoes")))*INDEX(Inputs!$K$5:$AJ$140,0,MATCH(T$2,Inputs!$K$4:$AJ$4,0)))+SUMPRODUCT((Inputs!$E$5:$E$140=$B8)*Inputs!$F$5:$F$140*(((Inputs!$G$5:$G$140="moeda")+(Inputs!$G$5:$G$140="acoes"))*Inputs!$B$1+((Inputs!$G$5:$G$140<>"moeda")*(Inputs!$G$5:$G$140<>"acoes")))*INDEX(Inputs!$K$5:$AJ$140,0,MATCH(T$2,Inputs!$K$4:$AJ$4,0))))) -> -198.20874 | U8: =IF(ISNA(MATCH(U$2,Inputs!$K$4:$AJ$4,0)),NA(),IF(SUMPRODUCT((Inputs!$A$5:$A$140=$B8)*ISNUMBER(INDEX(Inputs!$K$5:$AJ$140,0,MATCH(U$2,Inputs!$K$4:$AJ$4,0))))+SUMPRODUCT((Inputs!$C$5:$C$140=$B8)*ISNUMBER(INDEX(Inputs!$K$5:$AJ$140,0,MATCH(U$2,Inputs!$K$4:$AJ$4,0))))+SUMPRODUCT((Inputs!$E$5:$E$140=$B8)*ISNUMBER(INDEX(Inputs!$K$5:$AJ$140,0,MATCH(U$2,Inputs!$K$4:$AJ$4,0))))=0,NA(),SUMPRODUCT((Inputs!$A$5:$A$140=$B8)*Inputs!$B$5:$B$140*(((Inputs!$G$5:$G$140="moeda")+(Inputs!$G$5:$G$140="acoes"))*Inputs!$B$1+((Inputs!$G$5:$G$140<>"moeda")*(Inputs!$G$5:$G$140<>"acoes")))*INDEX(Inputs!$K$5:$AJ$140,0,MATCH(U$2,Inputs!$K$4:$AJ$4,0)))+SUMPRODUCT((Inputs!$C$5:$C$140=$B8)*Inputs!$D$5:$D$140*(((Inputs!$G$5:$G$140="moeda")+(Inputs!$G$5:$G$140="acoes"))*Inputs!$B$1+((Inputs!$G$5:$G$140<>"moeda")*(Inputs!$G$5:$G$140<>"acoes")))*INDEX(Inputs!$K$5:$AJ$140,0,MATCH(U$2,Inputs!$K$4:$AJ$4,0)))+SUMPRODUCT((Inputs!$E$5:$E$140=$B8)*Inputs!$F$5:$F$140*(((Inputs!$G$5:$G$140="moeda")+(Inputs!$G$5:$G$140="acoes"))*Inputs!$B$1+((Inputs!$G$5:$G$140<>"moeda")*(Inputs!$G$5:$G$140<>"acoes")))*INDEX(Inputs!$K$5:$AJ$140,0,MATCH(U$2,Inputs!$K$4:$AJ$4,0))))) -> -208.79 | V8: =IF(ISNA(MATCH(V$2,Inputs!$K$4:$AJ$4,0)),NA(),IF(SUMPRODUCT((Inputs!$A$5:$A$140=$B8)*ISNUMBER(INDEX(Inputs!$K$5:$AJ$140,0,MATCH(V$2,Inputs!$K$4:$AJ$4,0))))+SUMPRODUCT((Inputs!$C$5:$C$140=$B8)*ISNUMBER(INDEX(Inputs!$K$5:$AJ$140,0,MATCH(V$2,Inputs!$K$4:$AJ$4,0))))+SUMPRODUCT((Inputs!$E$5:$E$140=$B8)*ISNUMBER(INDEX(Inputs!$K$5:$AJ$140,0,MATCH(V$2,Inputs!$K$4:$AJ$4,0))))=0,NA(),SUMPRODUCT((Inputs!$A$5:$A$140=$B8)*Inputs!$B$5:$B$140*(((Inputs!$G$5:$G$140="moeda")+(Inputs!$G$5:$G$140="acoes"))*Inputs!$B$1+((Inputs!$G$5:$G$140<>"moeda")*(Inputs!$G$5:$G$140<>"acoes")))*INDEX(Inputs!$K$5:$AJ$140,0,MATCH(V$2,Inputs!$K$4:$AJ$4,0)))+SUMPRODUCT((Inputs!$C$5:$C$140=$B8)*Inputs!$D$5:$D$140*(((Inputs!$G$5:$G$140="moeda")+(Inputs!$G$5:$G$140="acoes"))*Inputs!$B$1+((Inputs!$G$5:$G$140<>"moeda")*(Inputs!$G$5:$G$140<>"acoes")))*INDEX(Inputs!$K$5:$AJ$140,0,MATCH(V$2,Inputs!$K$4:$AJ$4,0)))+SUMPRODUCT((Inputs!$E$5:$E$140=$B8)*Inputs!$F$5:$F$140*(((Inputs!$G$5:$G$140="moeda")+(Inputs!$G$5:$G$140="acoes"))*Inputs!$B$1+((Inputs!$G$5:$G$140<>"moeda")*(Inputs!$G$5:$G$140<>"acoes")))*INDEX(Inputs!$K$5:$AJ$140,0,MATCH(V$2,Inputs!$K$4:$AJ$4,0))))) -> -244.9556 | W8: =SUM(S8:V8) -> -839.256 | X8: =IF(ISNA(MATCH(X$2,Inputs!$K$4:$AJ$4,0)),NA(),IF(SUMPRODUCT((Inputs!$A$5:$A$140=$B8)*ISNUMBER(INDEX(Inputs!$K$5:$AJ$140,0,MATCH(X$2,Inputs!$K$4:$AJ$4,0))))+SUMPRODUCT((Inputs!$C$5:$C$140=$B8)*ISNUMBER(INDEX(Inputs!$K$5:$AJ$140,0,MATCH(X$2,Inputs!$K$4:$AJ$4,0))))+SUMPRODUCT((Inputs!$E$5:$E$140=$B8)*ISNUMBER(INDEX(Inputs!$K$5:$AJ$140,0,MATCH(X$2,Inputs!$K$4:$AJ$4,0))))=0,NA(),SUMPRODUCT((Inputs!$A$5:$A$140=$B8)*Inputs!$B$5:$B$140*(((Inputs!$G$5:$G$140="moeda")+(Inputs!$G$5:$G$140="acoes"))*Inputs!$B$1+((Inputs!$G$5:$G$140<>"moeda")*(Inputs!$G$5:$G$140<>"acoes")))*INDEX(Inputs!$K$5:$AJ$140,0,MATCH(X$2,Inputs!$K$4:$AJ$4,0)))+SUMPRODUCT((Inputs!$C$5:$C$140=$B8)*Inputs!$D$5:$D$140*(((Inputs!$G$5:$G$140="moeda")+(Inputs!$G$5:$G$140="acoes"))*Inputs!$B$1+((Inputs!$G$5:$G$140<>"moeda")*(Inputs!$G$5:$G$140<>"acoes")))*INDEX(Inputs!$K$5:$AJ$140,0,MATCH(X$2,Inputs!$K$4:$AJ$4,0)))+SUMPRODUCT((Inputs!$E$5:$E$140=$B8)*Inputs!$F$5:$F$140*(((Inputs!$G$5:$G$140="moeda")+(Inputs!$G$5:$G$140="acoes"))*Inputs!$B$1+((Inputs!$G$5:$G$140<>"moeda")*(Inputs!$G$5:$G$140<>"acoes")))*INDEX(Inputs!$K$5:$AJ$140,0,MATCH(X$2,Inputs!$K$4:$AJ$4,0))))) -> -250.609 | Y8: =IF(ISNA(MATCH(Y$2,Inputs!$K$4:$AJ$4,0)),NA(),IF(SUMPRODUCT((Inputs!$A$5:$A$140=$B8)*ISNUMBER(INDEX(Inputs!$K$5:$AJ$140,0,MATCH(Y$2,Inputs!$K$4:$AJ$4,0))))+SUMPRODUCT((Inputs!$C$5:$C$140=$B8)*ISNUMBER(INDEX(Inputs!$K$5:$AJ$140,0,MATCH(Y$2,Inputs!$K$4:$AJ$4,0))))+SUMPRODUCT((Inputs!$E$5:$E$140=$B8)*ISNUMBER(INDEX(Inputs!$K$5:$AJ$140,0,MATCH(Y$2,Inputs!$K$4:$AJ$4,0))))=0,NA(),SUMPRODUCT((Inputs!$A$5:$A$140=$B8)*Inputs!$B$5:$B$140*(((Inputs!$G$5:$G$140="moeda")+(Inputs!$G$5:$G$140="acoes"))*Inputs!$B$1+((Inputs!$G$5:$G$140<>"moeda")*(Inputs!$G$5:$G$140<>"acoes")))*INDEX(Inputs!$K$5:$AJ$140,0,MATCH(Y$2,Inputs!$K$4:$AJ$4,0)))+SUMPRODUCT((Inputs!$C$5:$C$140=$B8)*Inputs!$D$5:$D$140*(((Inputs!$G$5:$G$140="moeda")+(Inputs!$G$5:$G$140="acoes"))*Inputs!$B$1+((Inputs!$G$5:$G$140<>"moeda")*(Inputs!$G$5:$G$140<>"acoes")))*INDEX(Inputs!$K$5:$AJ$140,0,MATCH(Y$2,Inputs!$K$4:$AJ$4,0)))+SUMPRODUCT((Inputs!$E$5:$E$140=$B8)*Inputs!$F$5:$F$140*(((Inputs!$G$5:$G$140="moeda")+(Inputs!$G$5:$G$140="acoes"))*Inputs!$B$1+((Inputs!$G$5:$G$140<>"moeda")*(Inputs!$G$5:$G$140<>"acoes")))*INDEX(Inputs!$K$5:$AJ$140,0,MATCH(Y$2,Inputs!$K$4:$AJ$4,0))))) -> -267.809 | Z8: =IF(ISNA(MATCH(Z$2,Inputs!$K$4:$AJ$4,0)),NA(),IF(SUMPRODUCT((Inputs!$A$5:$A$140=$B8)*ISNUMBER(INDEX(Inputs!$K$5:$AJ$140,0,MATCH(Z$2,Inputs!$K$4:$AJ$4,0))))+SUMPRODUCT((Inputs!$C$5:$C$140=$B8)*ISNUMBER(INDEX(Inputs!$K$5:$AJ$140,0,MATCH(Z$2,Inputs!$K$4:$AJ$4,0))))+SUMPRODUCT((Inputs!$E$5:$E$140=$B8)*ISNUMBER(INDEX(Inputs!$K$5:$AJ$140,0,MATCH(Z$2,Inputs!$K$4:$AJ$4,0))))=0,NA(),SUMPRODUCT((Inputs!$A$5:$A$140=$B8)*Inputs!$B$5:$B$140*(((Inputs!$G$5:$G$140="moeda")+(Inputs!$G$5:$G$140="acoes"))*Inputs!$B$1+((Inputs!$G$5:$G$140<>"moeda")*(Inputs!$G$5:$G$140<>"acoes")))*INDEX(Inputs!$K$5:$AJ$140,0,MATCH(Z$2,Inputs!$K$4:$AJ$4,0)))+SUMPRODUCT((Inputs!$C$5:$C$140=$B8)*Inputs!$D$5:$D$140*(((Inputs!$G$5:$G$140="moeda")+(Inputs!$G$5:$G$140="acoes"))*Inputs!$B$1+((Inputs!$G$5:$G$140<>"moeda")*(Inputs!$G$5:$G$140<>"acoes")))*INDEX(Inputs!$K$5:$AJ$140,0,MATCH(Z$2,Inputs!$K$4:$AJ$4,0)))+SUMPRODUCT((Inputs!$E$5:$E$140=$B8)*Inputs!$F$5:$F$140*(((Inputs!$G$5:$G$140="moeda")+(Inputs!$G$5:$G$140="acoes"))*Inputs!$B$1+((Inputs!$G$5:$G$140<>"moeda")*(Inputs!$G$5:$G$140<>"acoes")))*INDEX(Inputs!$K$5:$AJ$140,0,MATCH(Z$2,Inputs!$K$4:$AJ$4,0))))) -> -305.637 | AA8: =IF(ISNA(MATCH(AA$2,Inputs!$K$4:$AJ$4,0)),NA(),IF(SUMPRODUCT((Inputs!$A$5:$A$140=$B8)*ISNUMBER(INDEX(Inputs!$K$5:$AJ$140,0,MATCH(AA$2,Inputs!$K$4:$AJ$4,0))))+SUMPRODUCT((Inputs!$C$5:$C$140=$B8)*ISNUMBER(INDEX(Inputs!$K$5:$AJ$140,0,MATCH(AA$2,Inputs!$K$4:$AJ$4,0))))+SUMPRODUCT((Inputs!$E$5:$E$140=$B8)*ISNUMBER(INDEX(Inputs!$K$5:$AJ$140,0,MATCH(AA$2,Inputs!$K$4:$AJ$4,0))))=0,NA(),SUMPRODUCT((Inputs!$A$5:$A$140=$B8)*Inputs!$B$5:$B$140*(((Inputs!$G$5:$G$140="moeda")+(Inputs!$G$5:$G$140="acoes"))*Inputs!$B$1+((Inputs!$G$5:$G$140<>"moeda")*(Inputs!$G$5:$G$140<>"acoes")))*INDEX(Inputs!$K$5:$AJ$140,0,MATCH(AA$2,Inputs!$K$4:$AJ$4,0)))+SUMPRODUCT((Inputs!$C$5:$C$140=$B8)*Inputs!$D$5:$D$140*(((Inputs!$G$5:$G$140="moeda")+(Inputs!$G$5:$G$140="acoes"))*Inputs!$B$1+((Inputs!$G$5:$G$140<>"moeda")*(Inputs!$G$5:$G$140<>"acoes")))*INDEX(Inputs!$K$5:$AJ$140,0,MATCH(AA$2,Inputs!$K$4:$AJ$4,0)))+SUMPRODUCT((Inputs!$E$5:$E$140=$B8)*Inputs!$F$5:$F$140*(((Inputs!$G$5:$G$140="moeda")+(Inputs!$G$5:$G$140="acoes"))*Inputs!$B$1+((Inputs!$G$5:$G$140<>"moeda")*(Inputs!$G$5:$G$140<>"acoes")))*INDEX(Inputs!$K$5:$AJ$140,0,MATCH(AA$2,Inputs!$K$4:$AJ$4,0))))) -> -403.524 | AB8: =SUM(X8:AA8) -> -1227.579 | AC8: =IF(ISNA(MATCH(AC$2,Inputs!$K$4:$AJ$4,0)),NA(),IF(SUMPRODUCT((Inputs!$A$5:$A$140=$B8)*ISNUMBER(INDEX(Inputs!$K$5:$AJ$140,0,MATCH(AC$2,Inputs!$K$4:$AJ$4,0))))+SUMPRODUCT((Inputs!$C$5:$C$140=$B8)*ISNUMBER(INDEX(Inputs!$K$5:$AJ$140,0,MATCH(AC$2,Inputs!$K$4:$AJ$4,0))))+SUMPRODUCT((Inputs!$E$5:$E$140=$B8)*ISNUMBER(INDEX(Inputs!$K$5:$AJ$140,0,MATCH(AC$2,Inputs!$K$4:$AJ$4,0))))=0,NA(),SUMPRODUCT((Inputs!$A$5:$A$140=$B8)*Inputs!$B$5:$B$140*(((Inputs!$G$5:$G$140="moeda")+(Inputs!$G$5:$G$140="acoes"))*Inputs!$B$1+((Inputs!$G$5:$G$140<>"moeda")*(Inputs!$G$5:$G$140<>"acoes")))*INDEX(Inputs!$K$5:$AJ$140,0,MATCH(AC$2,Inputs!$K$4:$AJ$4,0)))+SUMPRODUCT((Inputs!$C$5:$C$140=$B8)*Inputs!$D$5:$D$140*(((Inputs!$G$5:$G$140="moeda")+(Inputs!$G$5:$G$140="acoes"))*Inputs!$B$1+((Inputs!$G$5:$G$140<>"moeda")*(Inputs!$G$5:$G$140<>"acoes")))*INDEX(Inputs!$K$5:$AJ$140,0,MATCH(AC$2,Inputs!$K$4:$AJ$4,0)))+SUMPRODUCT((Inputs!$E$5:$E$140=$B8)*Inputs!$F$5:$F$140*(((Inputs!$G$5:$G$140="moeda")+(Inputs!$G$5:$G$140="acoes"))*Inputs!$B$1+((Inputs!$G$5:$G$140<>"moeda")*(Inputs!$G$5:$G$140<>"acoes")))*INDEX(Inputs!$K$5:$AJ$140,0,MATCH(AC$2,Inputs!$K$4:$AJ$4,0))))) -> -310.031 | AD8: =IF(ISNA(MATCH(AD$2,Inputs!$K$4:$AJ$4,0)),NA(),IF(SUMPRODUCT((Inputs!$A$5:$A$140=$B8)*ISNUMBER(INDEX(Inputs!$K$5:$AJ$140,0,MATCH(AD$2,Inputs!$K$4:$AJ$4,0))))+SUMPRODUCT((Inputs!$C$5:$C$140=$B8)*ISNUMBER(INDEX(Inputs!$K$5:$AJ$140,0,MATCH(AD$2,Inputs!$K$4:$AJ$4,0))))+SUMPRODUCT((Inputs!$E$5:$E$140=$B8)*ISNUMBER(INDEX(Inputs!$K$5:$AJ$140,0,MATCH(AD$2,Inputs!$K$4:$AJ$4,0))))=0,NA(),SUMPRODUCT((Inputs!$A$5:$A$140=$B8)*Inputs!$B$5:$B$140*(((Inputs!$G$5:$G$140="moeda")+(Inputs!$G$5:$G$140="acoes"))*Inputs!$B$1+((Inputs!$G$5:$G$140<>"moeda")*(Inputs!$G$5:$G$140<>"acoes")))*INDEX(Inputs!$K$5:$AJ$140,0,MATCH(AD$2,Inputs!$K$4:$AJ$4,0)))+SUMPRODUCT((Inputs!$C$5:$C$140=$B8)*Inputs!$D$5:$D$140*(((Inputs!$G$5:$G$140="moeda")+(Inputs!$G$5:$G$140="acoes"))*Inputs!$B$1+((Inputs!$G$5:$G$140<>"moeda")*(Inputs!$G$5:$G$140<>"acoes")))*INDEX(Inputs!$K$5:$AJ$140,0,MATCH(AD$2,Inputs!$K$4:$AJ$4,0)))+SUMPRODUCT((Inputs!$E$5:$E$140=$B8)*Inputs!$F$5:$F$140*(((Inputs!$G$5:$G$140="moeda")+(Inputs!$G$5:$G$140="acoes"))*Inputs!$B$1+((Inputs!$G$5:$G$140<>"moeda")*(Inputs!$G$5:$G$140<>"acoes")))*INDEX(Inputs!$K$5:$AJ$140,0,MATCH(AD$2,Inputs!$K$4:$AJ$4,0))))) -> -338.073 | AE8: =IF(ISNA(MATCH(AE$2,Inputs!$K$4:$AJ$4,0)),NA(),IF(SUMPRODUCT((Inputs!$A$5:$A$140=$B8)*ISNUMBER(INDEX(Inputs!$K$5:$AJ$140,0,MATCH(AE$2,Inputs!$K$4:$AJ$4,0))))+SUMPRODUCT((Inputs!$C$5:$C$140=$B8)*ISNUMBER(INDEX(Inputs!$K$5:$AJ$140,0,MATCH(AE$2,Inputs!$K$4:$AJ$4,0))))+SUMPRODUCT((Inputs!$E$5:$E$140=$B8)*ISNUMBER(INDEX(Inputs!$K$5:$AJ$140,0,MATCH(AE$2,Inputs!$K$4:$AJ$4,0))))=0,NA(),SUMPRODUCT((Inputs!$A$5:$A$140=$B8)*Inputs!$B$5:$B$140*(((Inputs!$G$5:$G$140="moeda")+(Inputs!$G$5:$G$140="acoes"))*Inputs!$B$1+((Inputs!$G$5:$G$140<>"moeda")*(Inputs!$G$5:$G$140<>"acoes")))*INDEX(Inputs!$K$5:$AJ$140,0,MATCH(AE$2,Inputs!$K$4:$AJ$4,0)))+SUMPRODUCT((Inputs!$C$5:$C$140=$B8)*Inputs!$D$5:$D$140*(((Inputs!$G$5:$G$140="moeda")+(Inputs!$G$5:$G$140="acoes"))*Inputs!$B$1+((Inputs!$G$5:$G$140<>"moeda")*(Inputs!$G$5:$G$140<>"acoes")))*INDEX(Inputs!$K$5:$AJ$140,0,MATCH(AE$2,Inputs!$K$4:$AJ$4,0)))+SUMPRODUCT((Inputs!$E$5:$E$140=$B8)*Inputs!$F$5:$F$140*(((Inputs!$G$5:$G$140="moeda")+(Inputs!$G$5:$G$140="acoes"))*Inputs!$B$1+((Inputs!$G$5:$G$140<>"moeda")*(Inputs!$G$5:$G$140<>"acoes")))*INDEX(Inputs!$K$5:$AJ$140,0,MATCH(AE$2,Inputs!$K$4:$AJ$4,0))))) -> #N/A | AF8: =IF(ISNA(MATCH(AF$2,Inputs!$K$4:$AJ$4,0)),NA(),IF(SUMPRODUCT((Inputs!$A$5:$A$140=$B8)*ISNUMBER(INDEX(Inputs!$K$5:$AJ$140,0,MATCH(AF$2,Inputs!$K$4:$AJ$4,0))))+SUMPRODUCT((Inputs!$C$5:$C$140=$B8)*ISNUMBER(INDEX(Inputs!$K$5:$AJ$140,0,MATCH(AF$2,Inputs!$K$4:$AJ$4,0))))+SUMPRODUCT((Inputs!$E$5:$E$140=$B8)*ISNUMBER(INDEX(Inputs!$K$5:$AJ$140,0,MATCH(AF$2,Inputs!$K$4:$AJ$4,0))))=0,NA(),SUMPRODUCT((Inputs!$A$5:$A$140=$B8)*Inputs!$B$5:$B$140*(((Inputs!$G$5:$G$140="moeda")+(Inputs!$G$5:$G$140="acoes"))*Inputs!$B$1+((Inputs!$G$5:$G$140<>"moeda")*(Inputs!$G$5:$G$140<>"acoes")))*INDEX(Inputs!$K$5:$AJ$140,0,MATCH(AF$2,Inputs!$K$4:$AJ$4,0)))+SUMPRODUCT((Inputs!$C$5:$C$140=$B8)*Inputs!$D$5:$D$140*(((Inputs!$G$5:$G$140="moeda")+(Inputs!$G$5:$G$140="acoes"))*Inputs!$B$1+((Inputs!$G$5:$G$140<>"moeda")*(Inputs!$G$5:$G$140<>"acoes")))*INDEX(Inputs!$K$5:$AJ$140,0,MATCH(AF$2,Inputs!$K$4:$AJ$4,0)))+SUMPRODUCT((Inputs!$E$5:$E$140=$B8)*Inputs!$F$5:$F$140*(((Inputs!$G$5:$G$140="moeda")+(Inputs!$G$5:$G$140="acoes"))*Inputs!$B$1+((Inputs!$G$5:$G$140<>"moeda")*(Inputs!$G$5:$G$140<>"acoes")))*INDEX(Inputs!$K$5:$AJ$140,0,MATCH(AF$2,Inputs!$K$4:$AJ$4,0))))) -> #N/A | AG8: =SUM(AC8:AF8) -> #N/A | AH8: =IF(ISNA(MATCH(AH$2,Inputs!$K$4:$AJ$4,0)),NA(),IF(SUMPRODUCT((Inputs!$A$5:$A$140=$B8)*ISNUMBER(INDEX(Inputs!$K$5:$AJ$140,0,MATCH(AH$2,Inputs!$K$4:$AJ$4,0))))+SUMPRODUCT((Inputs!$C$5:$C$140=$B8)*ISNUMBER(INDEX(Inputs!$K$5:$AJ$140,0,MATCH(AH$2,Inputs!$K$4:$AJ$4,0))))+SUMPRODUCT((Inputs!$E$5:$E$140=$B8)*ISNUMBER(INDEX(Inputs!$K$5:$AJ$140,0,MATCH(AH$2,Inputs!$K$4:$AJ$4,0))))=0,NA(),SUMPRODUCT((Inputs!$A$5:$A$140=$B8)*Inputs!$B$5:$B$140*(((Inputs!$G$5:$G$140="moeda")+(Inputs!$G$5:$G$140="acoes"))*Inputs!$B$1+((Inputs!$G$5:$G$140<>"moeda")*(Inputs!$G$5:$G$140<>"acoes")))*INDEX(Inputs!$K$5:$AJ$140,0,MATCH(AH$2,Inputs!$K$4:$AJ$4,0)))+SUMPRODUCT((Inputs!$C$5:$C$140=$B8)*Inputs!$D$5:$D$140*(((Inputs!$G$5:$G$140="moeda")+(Inputs!$G$5:$G$140="acoes"))*Inputs!$B$1+((Inputs!$G$5:$G$140<>"moeda")*(Inputs!$G$5:$G$140<>"acoes")))*INDEX(Inputs!$K$5:$AJ$140,0,MATCH(AH$2,Inputs!$K$4:$AJ$4,0)))+SUMPRODUCT((Inputs!$E$5:$E$140=$B8)*Inputs!$F$5:$F$140*(((Inputs!$G$5:$G$140="moeda")+(Inputs!$G$5:$G$140="acoes"))*Inputs!$B$1+((Inputs!$G$5:$G$140<>"moeda")*(Inputs!$G$5:$G$140<>"acoes")))*INDEX(Inputs!$K$5:$AJ$140,0,MATCH(AH$2,Inputs!$K$4:$AJ$4,0))))) -> -54.162167 | AI8: =IF(ISNA(MATCH(AI$2,Inputs!$K$4:$AJ$4,0)),NA(),IF(SUMPRODUCT((Inputs!$A$5:$A$140=$B8)*ISNUMBER(INDEX(Inputs!$K$5:$AJ$140,0,MATCH(AI$2,Inputs!$K$4:$AJ$4,0))))+SUMPRODUCT((Inputs!$C$5:$C$140=$B8)*ISNUMBER(INDEX(Inputs!$K$5:$AJ$140,0,MATCH(AI$2,Inputs!$K$4:$AJ$4,0))))+SUMPRODUCT((Inputs!$E$5:$E$140=$B8)*ISNUMBER(INDEX(Inputs!$K$5:$AJ$140,0,MATCH(AI$2,Inputs!$K$4:$AJ$4,0))))=0,NA(),SUMPRODUCT((Inputs!$A$5:$A$140=$B8)*Inputs!$B$5:$B$140*(((Inputs!$G$5:$G$140="moeda")+(Inputs!$G$5:$G$140="acoes"))*Inputs!$B$1+((Inputs!$G$5:$G$140<>"moeda")*(Inputs!$G$5:$G$140<>"acoes")))*INDEX(Inputs!$K$5:$AJ$140,0,MATCH(AI$2,Inputs!$K$4:$AJ$4,0)))+SUMPRODUCT((Inputs!$C$5:$C$140=$B8)*Inputs!$D$5:$D$140*(((Inputs!$G$5:$G$140="moeda")+(Inputs!$G$5:$G$140="acoes"))*Inputs!$B$1+((Inputs!$G$5:$G$140<>"moeda")*(Inputs!$G$5:$G$140<>"acoes")))*INDEX(Inputs!$K$5:$AJ$140,0,MATCH(AI$2,Inputs!$K$4:$AJ$4,0)))+SUMPRODUCT((Inputs!$E$5:$E$140=$B8)*Inputs!$F$5:$F$140*(((Inputs!$G$5:$G$140="moeda")+(Inputs!$G$5:$G$140="acoes"))*Inputs!$B$1+((Inputs!$G$5:$G$140<>"moeda")*(Inputs!$G$5:$G$140<>"acoes")))*INDEX(Inputs!$K$5:$AJ$140,0,MATCH(AI$2,Inputs!$K$4:$AJ$4,0))))) -> -63.048833 | AJ8: =IF(ISNA(MATCH(AJ$2,Inputs!$K$4:$AJ$4,0)),NA(),IF(SUMPRODUCT((Inputs!$A$5:$A$140=$B8)*ISNUMBER(INDEX(Inputs!$K$5:$AJ$140,0,MATCH(AJ$2,Inputs!$K$4:$AJ$4,0))))+SUMPRODUCT((Inputs!$C$5:$C$140=$B8)*ISNUMBER(INDEX(Inputs!$K$5:$AJ$140,0,MATCH(AJ$2,Inputs!$K$4:$AJ$4,0))))+SUMPRODUCT((Inputs!$E$5:$E$140=$B8)*ISNUMBER(INDEX(Inputs!$K$5:$AJ$140,0,MATCH(AJ$2,Inputs!$K$4:$AJ$4,0))))=0,NA(),SUMPRODUCT((Inputs!$A$5:$A$140=$B8)*Inputs!$B$5:$B$140*(((Inputs!$G$5:$G$140="moeda")+(Inputs!$G$5:$G$140="acoes"))*Inputs!$B$1+((Inputs!$G$5:$G$140<>"moeda")*(Inputs!$G$5:$G$140<>"acoes")))*INDEX(Inputs!$K$5:$AJ$140,0,MATCH(AJ$2,Inputs!$K$4:$AJ$4,0)))+SUMPRODUCT((Inputs!$C$5:$C$140=$B8)*Inputs!$D$5:$D$140*(((Inputs!$G$5:$G$140="moeda")+(Inputs!$G$5:$G$140="acoes"))*Inputs!$B$1+((Inputs!$G$5:$G$140<>"moeda")*(Inputs!$G$5:$G$140<>"acoes")))*INDEX(Inputs!$K$5:$AJ$140,0,MATCH(AJ$2,Inputs!$K$4:$AJ$4,0)))+SUMPRODUCT((Inputs!$E$5:$E$140=$B8)*Inputs!$F$5:$F$140*(((Inputs!$G$5:$G$140="moeda")+(Inputs!$G$5:$G$140="acoes"))*Inputs!$B$1+((Inputs!$G$5:$G$140<>"moeda")*(Inputs!$G$5:$G$140<>"acoes")))*INDEX(Inputs!$K$5:$AJ$140,0,MATCH(AJ$2,Inputs!$K$4:$AJ$4,0))))) -> -57.591 | AK8: =IF(ISNA(MATCH(AK$2,Inputs!$K$4:$AJ$4,0)),NA(),IF(SUMPRODUCT((Inputs!$A$5:$A$140=$B8)*ISNUMBER(INDEX(Inputs!$K$5:$AJ$140,0,MATCH(AK$2,Inputs!$K$4:$AJ$4,0))))+SUMPRODUCT((Inputs!$C$5:$C$140=$B8)*ISNUMBER(INDEX(Inputs!$K$5:$AJ$140,0,MATCH(AK$2,Inputs!$K$4:$AJ$4,0))))+SUMPRODUCT((Inputs!$E$5:$E$140=$B8)*ISNUMBER(INDEX(Inputs!$K$5:$AJ$140,0,MATCH(AK$2,Inputs!$K$4:$AJ$4,0))))=0,NA(),SUMPRODUCT((Inputs!$A$5:$A$140=$B8)*Inputs!$B$5:$B$140*(((Inputs!$G$5:$G$140="moeda")+(Inputs!$G$5:$G$140="acoes"))*Inputs!$B$1+((Inputs!$G$5:$G$140<>"moeda")*(Inputs!$G$5:$G$140<>"acoes")))*INDEX(Inputs!$K$5:$AJ$140,0,MATCH(AK$2,Inputs!$K$4:$AJ$4,0)))+SUMPRODUCT((Inputs!$C$5:$C$140=$B8)*Inputs!$D$5:$D$140*(((Inputs!$G$5:$G$140="moeda")+(Inputs!$G$5:$G$140="acoes"))*Inputs!$B$1+((Inputs!$G$5:$G$140<>"moeda")*(Inputs!$G$5:$G$140<>"acoes")))*INDEX(Inputs!$K$5:$AJ$140,0,MATCH(AK$2,Inputs!$K$4:$AJ$4,0)))+SUMPRODUCT((Inputs!$E$5:$E$140=$B8)*Inputs!$F$5:$F$140*(((Inputs!$G$5:$G$140="moeda")+(Inputs!$G$5:$G$140="acoes"))*Inputs!$B$1+((Inputs!$G$5:$G$140<>"moeda")*(Inputs!$G$5:$G$140<>"acoes")))*INDEX(Inputs!$K$5:$AJ$140,0,MATCH(AK$2,Inputs!$K$4:$AJ$4,0))))) -> -53.821 | AL8: =SUM(AH8:AK8) -> -228.623
