Workbook
Name beta_observed: Valuation!$D$93
Name last_close: Valuation!$G$7
Name ticker: Valuation!$D$7
Name Useful_Life_of_Depreciable_PP_E: "PPElife"
Name beta_observed: #REF!
Name ticker: #REF!
Name costdebtfirm: Valuation!$D$86
Name costequity: Valuation!$D$94
Name debt: Valuation!$G$88
Name debt_weight: Valuation!$J$88
Name g: Valuation!$D$63
Name market_equity: Valuation!$G$89
Name noplat_t1: Valuation!$D$65
Name relevered_beta: Valuation!$M$102
Name risk_free_rate: Valuation!$D$91
Name risk_premium: Valuation!$D$92
Name ronic: Valuation!$D$64
Name stub_year_fraction: Valuation!$D$11
Name totalcap: Valuation!$G$90
Name wacc: Valuation!$D$12

Sheet Inputs
A1: Base histórica (R$ mil) - AUREN ENERGIA S.A. (AURE3) - CVM ITR/DFP consolidado
A2: Fonte / conta original | B2: Código | C2: Conta padronizada | D2: 1Q21 | E2: 2Q21 | F2: 3Q21 | G2: 4Q21 | H2: 2021 | I2: 1Q22 | J2: 2Q22 | K2: 3Q22 | L2: 4Q22 | M2: 2022 | N2: 1Q23 | O2: 2Q23 | P2: 3Q23 | Q2: 4Q23 | R2: 2023 | S2: 1Q24 | T2: 2Q24 | U2: 3Q24 | V2: 4Q24 | W2: 2024 | X2: 1Q25 | Y2: 2Q25 | Z2: 3Q25 | AA2: 4Q25 | AB2: 2025 | AC2: 1Q26 | AD2: 2Q26 | AE2: 3Q26 | AF2: 4Q26 | AG2: 2026
A3: Fonte: CVM dados abertos (ITR/DFP consolidado, CVM 026620) - R$ mil, trimestre isolado | C3: Unidade original: R$ mil | a Inputs (2) divide por 1.000 -> R$ milhões
A4: DRE - CVM ITR/DFP consolidado (Auren Energia S.A., CVM 026620), R$ mil, trimestre isolado (4T = ano - 9M)
A5: CVM DRE 3.01 Receita de venda de bens e/ou serviços | B5: 1 | C5: Net Revenues | D5: 552151 | E5: 581104 | F5: 616194 | G5: 767313 | H5: =SUM(D5:G5) -> 2516762 | I5: 1145258 | J5: 1346655 | K5: 1538901 | L5: 1484892 | M5: =SUM(I5:L5) -> 5515706 | N5: 1414510 | O5: 1437088 | P5: 1626590 | Q5: 1703702 | R5: =SUM(N5:Q5) -> 6181890 | S5: 1397531 | T5: 1450045 | U5: 2046511 | V5: 3165864 | W5: =SUM(S5:V5) -> 8059951 | X5: 2952303 | Y5: 2885529 | Z5: 3537391 | AA5: 3801729 | AB5: =SUM(X5:AA5) -> 13176952 | AC5: 3074535 | AD5: 3055499
A6: CVM DRE 3.02 Custo dos bens e serviços vendidos (inclui D&A) | B6: 2 | C6: COGS (cash) | D6: -277630 | E6: -402476 | F6: 189049 | G6: -592360 | H6: =SUM(D6:G6) -> -1083417 | I6: -863207 | J6: -1046341 | K6: -1234077 | L6: -1228998 | M6: =SUM(I6:L6) -> -4372623 | N6: -1081144 | O6: -1095526 | P6: -1299153 | Q6: -1373123 | R6: =SUM(N6:Q6) -> -4848946 | S6: -1106505 | T6: -1128505 | U6: -1726989 | V6: -2668949 | W6: =SUM(S6:V6) -> -6630948 | X6: -2116034 | Y6: -2390092 | Z6: -3200700 | AA6: -3319390 | AB6: =SUM(X6:AA6) -> -11026216 | AC6: -2587081 | AD6: -2603261
A7: (+) estorno da D&A embutida no custo, relançada no código 4 (a CVM não separa D&A entre custo e despesa; toda a D&A sai do custo) | B7: 2 | C7: COGS (cash) | D7: 132593 | E7: 131573 | F7: 145397 | G7: 149432 | H7: =SUM(D7:G7) -> 558995 | I7: 157304 | J7: 161190 | K7: 161353 | L7: 117907 | M7: =SUM(I7:L7) -> 597754 | N7: 168327 | O7: 169666 | P7: 169643 | Q7: 169639 | R7: =SUM(N7:Q7) -> 677275 | S7: 166381 | T7: 175177 | U7: 182611 | V7: 189021 | W7: =SUM(S7:V7) -> 713190 | X7: 458196 | Y7: 521747 | Z7: 465553 | AA7: 477467 | AB7: =SUM(X7:AA7) -> 1922963 | AC7: 466831 | AD7: 465443
A8: CVM DRE 3.04 Despesas/receitas operacionais (G&A + outras receitas e despesas) | B8: 3 | C8: SG&A and Other (cash) | D8: -37007 | E8: -72009 | F8: -98542 | G8: -5338 | H8: =SUM(D8:G8) -> -212896 | I8: -105652 | J8: -117078 | K8: 89362 | L8: 381350 | M8: =SUM(I8:L8) -> 247982 | N8: -19582 | O8: -65205 | P8: -101973 | Q8: -72270 | R8: =SUM(N8:Q8) -> -259030 | S8: 208815 | T8: -45123 | U8: 189880 | V8: -490910 | W8: =SUM(S8:V8) -> -137338 | X8: 155190 | Y8: -485413 | Z8: -79727 | AA8: 575338 | AB8: =SUM(X8:AA8) -> 165388 | AC8: -582682 | AD8: -67320
A9: (-) estorno da equivalência patrimonial (3.04.06), lançada no código 8 | B9: 3 | C9: SG&A and Other (cash) | D9: 0 | E9: 0 | F9: 0 | G9: 0 | H9: =SUM(D9:G9) -> 0 | I9: -29051 | J9: -54940 | K9: -52300 | L9: 5632 | M9: =SUM(I9:L9) -> -130659 | N9: -30229 | O9: 11887 | P9: -45027 | Q9: -9943 | R9: =SUM(N9:Q9) -> -73312 | S9: -66578 | T9: -53524 | U9: -58434 | V9: 14152 | W9: =SUM(S9:V9) -> -164384 | X9: -72147 | Y9: -14758 | Z9: -58193 | AA9: -60249 | AB9: =SUM(X9:AA9) -> -205347 | AC9: -71487 | AD9: -39594
A10: D&A - DVA 7.04.01 até 2T22; DFC 6.01.01 (depreciação e amortização + amortização de mais-valia/ágio) a partir de 3T22 | B10: 4 | C10: D&A | D10: -132593 | E10: -131573 | F10: -145397 | G10: -149432 | H10: =SUM(D10:G10) -> -558995 | I10: -157304 | J10: -161190 | K10: -161353 | L10: -117907 | M10: =SUM(I10:L10) -> -597754 | N10: -168327 | O10: -169666 | P10: -169643 | Q10: -169639 | R10: =SUM(N10:Q10) -> -677275 | S10: -166381 | T10: -175177 | U10: -182611 | V10: -189021 | W10: =SUM(S10:V10) -> -713190 | X10: -458196 | Y10: -521747 | Z10: -465553 | AA10: -477467 | AB10: =SUM(X10:AA10) -> -1922963 | AC10: -466831 | AD10: -465443
A11: CVM DRE 3.06.02 Despesas financeiras | B11: 5 | C11: Interest Expense | D11: -164756 | E11: -211669 | F11: -193237 | G11: -238999 | H11: =SUM(D11:G11) -> -808661 | I11: -250510 | J11: -291340 | K11: -165812 | L11: -468975 | M11: =SUM(I11:L11) -> -1176637 | N11: -272035 | O11: -497689 | P11: -194621 | Q11: -215024 | R11: =SUM(N11:Q11) -> -1179369 | S11: -258839 | T11: -255757 | U11: -243887 | V11: -717696 | W11: =SUM(S11:V11) -> -1476179 | X11: -1008815 | Y11: -879279 | Z11: -869780 | AA11: -783788 | AB11: =SUM(X11:AA11) -> -3541662 | AC11: -867481 | AD11: -1018168
A12: CVM DRE 3.06.01 Receitas financeiras | B12: 6 | C12: Nonoperating Income / (Loss) | D12: 13753 | E12: 11716 | F12: 41663 | G12: 33412 | H12: =SUM(D12:G12) -> 100544 | I12: 86074 | J12: 103888 | K12: 112759 | L12: 2536191 | M12: =SUM(I12:L12) -> 2838912 | N12: 254848 | O12: 473238 | P12: 74493 | Q12: 138783 | R12: =SUM(N12:Q12) -> 941362 | S12: 149860 | T12: 119705 | U12: 141262 | V12: 304060 | W12: =SUM(S12:V12) -> 714887 | X12: 276738 | Y12: 234752 | Z12: 244490 | AA12: 351744 | AB12: =SUM(X12:AA12) -> 1107724 | AC12: 277650 | AD12: 286022
A13: CVM DRE 3.08 IR e CS sobre o lucro | B13: 7 | C13: Taxes | D13: -46947 | E13: 7108 | F13: -238601 | G13: 16235 | H13: =SUM(D13:G13) -> -262205 | I13: -14548 | J13: 2189 | K13: -111046 | L13: -251321 | M13: =SUM(I13:L13) -> -374726 | N13: -66645 | O13: -69024 | P13: -943452 | Q13: -74475 | R13: =SUM(N13:Q13) -> -1153596 | S13: -137244 | T13: -49276 | U13: -135947 | V13: 63963 | W13: =SUM(S13:V13) -> -258504 | X13: -205385 | Y13: 71650 | Z13: -35369 | AA13: -270957 | AB13: =SUM(X13:AA13) -> -440061 | AC13: 83453 | AD13: -31833
A14: CVM DRE 3.04.06 Resultado de equivalência patrimonial | B14: 8 | C14: Equity in Income of Affiliates, after tax (enter as +) | D14: 0 | E14: 0 | F14: 0 | G14: 0 | H14: =SUM(D14:G14) -> 0 | I14: 29051 | J14: 54940 | K14: 52300 | L14: -5632 | M14: =SUM(I14:L14) -> 130659 | N14: 30229 | O14: -11887 | P14: 45027 | Q14: 9943 | R14: =SUM(N14:Q14) -> 73312 | S14: 66578 | T14: 53524 | U14: 58434 | V14: -14152 | W14: =SUM(S14:V14) -> 164384 | X14: 72147 | Y14: 14758 | Z14: 58193 | AA14: 60249 | AB14: =SUM(X14:AA14) -> 205347 | AC14: 71487 | AD14: 39594
A15: CVM DRE 3.11.02 Lucro atribuído a não controladores (sinal invertido) | B15: 9 | C15: Minority Interest Expense, after tax (enter as - ) | D15: -29436 | E15: 15169 | F15: -234281 | G15: 34187 | H15: =SUM(D15:G15) -> -214361 | I15: -4214 | J15: 0 | K15: 0 | L15: 0 | M15: =SUM(I15:L15) -> -4214 | N15: 0 | O15: 0 | P15: 0 | Q15: 0 | R15: =SUM(N15:Q15) -> 0 | S15: 0 | T15: 0 | U15: 0 | V15: -20931 | W15: =SUM(S15:V15) -> -20931 | X15: -45501 | Y15: -52537 | Z15: 6661 | AA15: -14780 | AB15: =SUM(X15:AA15) -> -106157 | AC15: -19732 | AD15: -31886
A16: CVM DFC 6.03 Pagamento de dividendos e JCP (caixa) | B16: 10 | C16: Common Dividends | D16: -3475 | E16: -352302 | F16: -146582 | G16: -3 | H16: =SUM(D16:G16) -> -502362 | I16: 0 | J16: -99991 | K16: 0 | L16: -3 | M16: =SUM(I16:L16) -> -99994 | N16: 0 | O16: -1499809 | P16: 0 | Q16: -1499817 | R16: =SUM(N16:Q16) -> -2999626 | S16: -399948 | T16: -1 | U16: -1 | V16: 0 | W16: =SUM(S16:V16) -> -399950 | X16: -99648 | Y16: -61408 | Z16: -89327 | AA16: 8548 | AB16: =SUM(X16:AA16) -> -241835 | AC16: -42966 | AD16: 148
A17: CVM DRE 3.11.01 Lucro atribuído aos controladores (1T24-3T24: 3.11, pois a ITR não separou e não havia minoritários) | B17: 44 | C17: Net income reported (controladores) - memo p/ check | D17: 10128 | E17: -71057 | F17: 82245 | G17: 14450 | H17: =SUM(D17:G17) -> 35766 | I17: -6799 | J17: -2027 | K17: 230086 | L17: 2453140 | M17: =SUM(I17:L17) -> 2674400 | N17: 229952 | O17: 182882 | P17: -838116 | Q17: 107593 | R17: =SUM(N17:Q17) -> -317689 | S17: 253618 | T17: 91089 | U17: 270830 | V17: -364599 | W17: =SUM(S17:V17) -> 250938 | X17: 8496 | Y17: -615390 | Z17: -397034 | AA17: 339896 | AB17: =SUM(X17:AA17) -> -664032 | AC17: -621338 | AD17: -410947
A18: DRE - memória (sem código)
A19: CVM DRE 3.03 Resultado bruto | D19: 274521 | E19: 178628 | F19: 805243 | G19: 174953 | H19: =SUM(D19:G19) -> 1433345 | I19: 282051 | J19: 300314 | K19: 304824 | L19: 255894 | M19: =SUM(I19:L19) -> 1143083 | N19: 333366 | O19: 341562 | P19: 327437 | Q19: 330579 | R19: =SUM(N19:Q19) -> 1332944 | S19: 291026 | T19: 321540 | U19: 319522 | V19: 496915 | W19: =SUM(S19:V19) -> 1429003 | X19: 836269 | Y19: 495437 | Z19: 336691 | AA19: 482339 | AB19: =SUM(X19:AA19) -> 2150736 | AC19: 487454 | AD19: 452238
A20: CVM DRE 3.05 Resultado antes do resultado financeiro (EBIT) | D20: 237514 | E20: 106619 | F20: 706701 | G20: 169615 | H20: =SUM(D20:G20) -> 1220449 | I20: 176399 | J20: 183236 | K20: 394186 | L20: 637244 | M20: =SUM(I20:L20) -> 1391065 | N20: 313784 | O20: 276357 | P20: 225464 | Q20: 258309 | R20: =SUM(N20:Q20) -> 1073914 | S20: 499841 | T20: 276417 | U20: 509402 | V20: 6005 | W20: =SUM(S20:V20) -> 1291665 | X20: 991459 | Y20: 10024 | Z20: 256964 | AA20: 1057677 | AB20: =SUM(X20:AA20) -> 2316124 | AC20: -95228 | AD20: 384918
A21: CVM DRE 3.07 Resultado antes dos tributos | D21: 86511 | E21: -93334 | F21: 555127 | G21: -35972 | H21: =SUM(D21:G21) -> 512332 | I21: 11963 | J21: -4216 | K21: 341133 | L21: 2704460 | M21: =SUM(I21:L21) -> 3053340 | N21: 296597 | O21: 251906 | P21: 105336 | Q21: 182068 | R21: =SUM(N21:Q21) -> 835907 | S21: 390862 | T21: 140365 | U21: 406777 | V21: -407631 | W21: =SUM(S21:V21) -> 530373 | X21: 259382 | Y21: -634503 | Z21: -368326 | AA21: 625633 | AB21: =SUM(X21:AA21) -> -117814 | AC21: -685059 | AD21: -347228
A22: CVM DRE 3.11 Lucro consolidado do período | D22: 39564 | E22: -86226 | F22: 316526 | G22: -19737 | H22: =SUM(D22:G22) -> 250127 | I22: -2585 | J22: -2027 | K22: 230087 | L22: 2453139 | M22: =SUM(I22:L22) -> 2678614 | N22: 229952 | O22: 182882 | P22: -838116 | Q22: 107593 | R22: =SUM(N22:Q22) -> -317689 | S22: 253618 | T22: 91089 | U22: 270830 | V22: -343668 | W22: =SUM(S22:V22) -> 271869 | X22: 53997 | Y22: -562853 | Z22: -403695 | AA22: 354676 | AB22: =SUM(X22:AA22) -> -557875 | AC22: -601606 | AD22: -379061
A23: Receita líquida PRO FORMA (Auren + AES Brasil) - Planilha Interativa da RI; base antiga do modelo, só comparação | H23: =SUM(D23:G23) -> 0 | M23: =SUM(I23:L23) -> 0 | N23: 2180778.4 | O23: 2186623.6 | P23: 2523976.2 | Q23: 2666055.3 | R23: =SUM(N23:Q23) -> 9557433.5 | S23: 2209357.2 | T23: 2307884.5 | U23: 3134682.4 | V23: 3598925 | W23: =SUM(S23:V23) -> 11250849 | AB23: =SUM(X23:AA23) -> 0
A24: BALANÇO - CVM ITR/DFP consolidado, R$ mil, saldo no fim do trimestre
A25: CVM BPA 1.01.01 Caixa e Equivalentes de Caixa | B25: 11 | C25: Cash and equivalents (inc. investment securities) | D25: 1292369 | E25: 1189841 | F25: 1376313 | G25: 1595818 | H25: =G25 -> 1595818 | I25: 3049185 | J25: 3211067 | K25: 2881084 | L25: 3125959 | M25: =L25 -> 3125959 | N25: 3344668 | O25: 6225732 | P25: 4904741 | Q25: 3238394 | R25: =Q25 -> 3238394 | S25: 3094615 | T25: 4992046 | U25: 5281323 | V25: 7200549 | W25: =V25 -> 7200549 | X25: 6131027 | Y25: 4907414 | Z25: 4479368 | AA25: 3826127 | AB25: =AA25 -> 3826127 | AC25: 2959416 | AD25: 2949774
A26: CVM BPA 1.01.02 Aplicações Financeiras | B26: 11 | C26: Cash and equivalents (inc. investment securities) | D26: 0 | E26: 0 | F26: 0 | G26: 77751 | H26: =G26 -> 77751 | I26: 124662 | J26: 142899 | K26: 102612 | L26: 105347 | M26: =L26 -> 105347 | N26: 57999 | O26: 59610 | P26: 0 | Q26: 0 | R26: =Q26 -> 0 | S26: 0 | T26: 0 | U26: 14398 | V26: 2629 | W26: =V26 -> 2629 | X26: 31449 | Y26: 25754 | Z26: 596314 | AA26: 556295 | AB26: =AA26 -> 556295 | AC26: 612466 | AD26: 689034
A27: CVM BPA 1.01.03 Contas a Receber | B27: 12 | C27: Accounts receivable | D27: 382854 | E27: 325707 | F27: 330258 | G27: 328631 | H27: =G27 -> 328631 | I27: 556035 | J27: 549634 | K27: 625916 | L27: 617860 | M27: =L27 -> 617860 | N27: 577274 | O27: 569731 | P27: 656783 | Q27: 679476 | R27: =Q27 -> 679476 | S27: 569252 | T27: 575060 | U27: 919196 | V27: 1492867 | W27: =V27 -> 1492867 | X27: 1404559 | Y27: 1229784 | Z27: 1543172 | AA27: 1712414 | AB27: =AA27 -> 1712414 | AC27: 1637335 | AD27: 1408699
A28: CVM BPA 1.01.06 Tributos a Recuperar | B28: 16 | C28: Other current assets | D28: 75820 | E28: 83320 | F28: 80249 | G28: 36714 | H28: =G28 -> 36714 | I28: 72760 | J28: 92617 | K28: 111149 | L28: 105993 | M28: =L28 -> 105993 | N28: 129838 | O28: 175907 | P28: 225719 | Q28: 139249 | R28: =Q28 -> 139249 | S28: 162883 | T28: 176234 | U28: 220418 | V28: 261258 | W28: =V28 -> 261258 | X28: 255502 | Y28: 305604 | Z28: 331172 | AA28: 289189 | AB28: =AA28 -> 289189 | AC28: 304052 | AD28: 346199
A29: CVM BPA 1.01.08 Outros Ativos Circulantes | B29: 16 | C29: Other current assets | D29: 77884 | E29: 86212 | F29: 91761 | G29: 313085 | H29: =G29 -> 313085 | I29: 1663133 | J29: 1954073 | K29: 1779248 | L29: 2313337 | M29: =L29 -> 2313337 | N29: 2790493 | O29: 2161634 | P29: 2002402 | Q29: 1880742 | R29: =Q29 -> 1880742 | S29: 1521179 | T29: 1572587 | U29: 3241231 | V29: 2180491 | W29: =V29 -> 2180491 | X29: 3271444 | Y29: 2264697 | Z29: 1869303 | AA29: 2076082 | AB29: =AA29 -> 2076082 | AC29: 1896154 | AD29: 1735662
A30: CVM BPA 1.02.01 Ativo Realizável a Longo Prazo | B30: 22 | C30: Other non-current assets | D30: 5953955 | E30: 5970796 | F30: 5566187 | G30: 5858557 | H30: =G30 -> 5858557 | I30: 8838579 | J30: 8847640 | K30: 8821900 | L30: 10824096 | M30: =L30 -> 10824096 | N30: 11362362 | O30: 7910031 | P30: 6898457 | Q30: 6626900 | R30: =Q30 -> 6626900 | S30: 5996230 | T30: 5739551 | U30: 5553418 | V30: 5665802 | W30: =V30 -> 5665802 | X30: 5493592 | Y30: 5187745 | Z30: 4903780 | AA30: 5364266 | AB30: =AA30 -> 5364266 | AC30: 5437925 | AD30: 5429087
A31: (-) estorno IR e CS diferidos (1.02.01.07), lançado no código 14 | B31: 22 | C31: Other non-current assets | D31: -3908905 | E31: -3908192 | F31: -3444995 | G31: -3408893 | H31: =G31 -> -3408893 | I31: -3416808 | J31: -3430877 | K31: -3370826 | L31: -3000824 | M31: =L31 -> -3000824 | N31: -2992037 | O31: -2922766 | P31: -2601196 | Q31: -2698782 | R31: =Q31 -> -2698782 | S31: -2697332 | T31: -2660554 | U31: -2642872 | V31: -2172103 | W31: =V31 -> -2172103 | X31: -2129196 | Y31: -1964087 | Z31: -1995197 | AA31: -1942725 | AB31: =AA31 -> -1942725 | AC31: -1956126 | AD31: -1997881
A32: CVM BPA 1.02.01.07 Tributos Diferidos | B32: 14 | C32: Deferred income taxes | D32: 3908905 | E32: 3908192 | F32: 3444995 | G32: 3408893 | H32: =G32 -> 3408893 | I32: 3416808 | J32: 3430877 | K32: 3370826 | L32: 3000824 | M32: =L32 -> 3000824 | N32: 2992037 | O32: 2922766 | P32: 2601196 | Q32: 2698782 | R32: =Q32 -> 2698782 | S32: 2697332 | T32: 2660554 | U32: 2642872 | V32: 2172103 | W32: =V32 -> 2172103 | X32: 2129196 | Y32: 1964087 | Z32: 1995197 | AA32: 1942725 | AB32: =AA32 -> 1942725 | AC32: 1956126 | AD32: 1997881
A33: CVM BPA 1.02.02 Investimentos | B33: 17 | C33: Equity in affiliates | D33: 0 | E33: 0 | F33: 0 | G33: 0 | H33: =G33 -> 0 | I33: 1101829 | J33: 1015723 | K33: 1077880 | L33: 2161751 | M33: =L33 -> 2161751 | N33: 2192011 | O33: 2127074 | P33: 2111609 | Q33: 2057307 | R33: =Q33 -> 2057307 | S33: 2111899 | T33: 2047967 | U33: 2105551 | V33: 2261558 | W33: =V33 -> 2261558 | X33: 2299011 | Y33: 2216541 | Z33: 2133085 | AA33: 2131020 | AB33: =AA33 -> 2131020 | AC33: 2113512 | AD33: 2043198
A34: CVM BPA 1.02.03 Imobilizado | B34: 18 | C34: PP&E | D34: 8724325 | E34: 8631332 | F34: 8896198 | G34: 8985565 | H34: =G34 -> 8985565 | I34: 9177205 | J34: 9748982 | K34: 10149734 | L34: 10440742 | M34: =L34 -> 10440742 | N34: 10664521 | O34: 11223531 | P34: 11879298 | Q34: 11914036 | R34: =Q34 -> 11914036 | S34: 11795286 | T34: 11729447 | U34: 11641070 | V34: 26353080 | W34: =V34 -> 26353080 | X34: 26150092 | Y34: 25955934 | Z34: 25867570 | AA34: 25570358 | AB34: =AA34 -> 25570358 | AC34: 25348441 | AD34: 25157620
A35: (-) estorno direito de uso (1.02.03.02), lançado no código 19 | B35: 18 | C35: PP&E | D35: -6068 | E35: -6051 | F35: -5670 | G35: -5283 | H35: =G35 -> -5283 | I35: -6519 | J35: -5425 | K35: -80327 | L35: -43707 | M35: =L35 -> -43707 | N35: -44522 | O35: -45236 | P35: -65324 | Q35: -64689 | R35: =Q35 -> -64689 | S35: -62706 | T35: -60861 | U35: -69260 | V35: -149284 | W35: =V35 -> -149284 | X35: -149110 | Y35: -145660 | Z35: -142547 | AA35: -140111 | AB35: =AA35 -> -140111 | AC35: -141310 | AD35: -136850
A36: CVM BPA 1.02.03.02 Direito de Uso em Arrendamento | B36: 19 | C36: Right-of-use-assets | D36: 6068 | E36: 6051 | F36: 5670 | G36: 5283 | H36: =G36 -> 5283 | I36: 6519 | J36: 5425 | K36: 80327 | L36: 43707 | M36: =L36 -> 43707 | N36: 44522 | O36: 45236 | P36: 65324 | Q36: 64689 | R36: =Q36 -> 64689 | S36: 62706 | T36: 60861 | U36: 69260 | V36: 149284 | W36: =V36 -> 149284 | X36: 149110 | Y36: 145660 | Z36: 142547 | AA36: 140111 | AB36: =AA36 -> 140111 | AC36: 141310 | AD36: 136850
... A59: CVM BPP 2.03.09 Participação dos Acionistas Não Controladores | B59: 35 | C59: Minority interest | D59: 4277955 | E59: 4293710 | F59: 4768398 | G59: 4589112 | H59: =G59 -> 4589112 | I59: 0 | J59: 0 | K59: 0 | L59: 0 | M59: =L59 -> 0 | N59: 0 | O59: 0 | P59: 0 | Q59: 0 | R59: =Q59 -> 0 | S59: 0 | T59: 0 | U59: 0 | V59: 1281658 | W59: =V59 -> 1281658 | X59: 1327231 | Y59: 1379839 | Z59: 1288751 | AA59: 1266701 | AB59: =AA59 -> 1266701 | AC59: 1213632 | AD59: 1245517
A60: BALANÇO - totais divulgados (memória)
A61: CVM BPA 1 Ativo total | D61: 18260942 | E61: 18026959 | F61: 18525946 | G61: 19562553 | H61: =G61 -> 19562553 | I61: 28452306 | J61: 29391370 | K61: 29337895 | L61: 32282893 | M61: =L61 -> 32282893 | N61: 33694157 | O61: 33010352 | P61: 31219220 | Q61: 28994557 | R61: =Q61 -> 28994557 | S61: 27694357 | T61: 29259449 | U61: 31492257 | V61: 52754117 | W61: =V61 -> 52754117 | X61: 52266696 | Y61: 49202800 | Z61: 48833477 | AA61: 48727388 | AB61: =AA61 -> 48727388 | AC61: 47381486 | AD61: 46710105
A62: CVM BPP 2.01 + 2.02 Passivo circulante + não circulante (reconstruído pelas contas) | D62: 10078095 | E62: 9598964 | F62: 9380655 | G62: 10516038 | H62: =G62 -> 10516038 | I62: 15632029 | J62: 16659168 | K62: 16387368 | L62: 17029815 | M62: =L62 -> 17029815 | N62: 18210646 | O62: 18224390 | P62: 17256820 | Q62: 16625604 | R62: =Q62 -> 16625604 | S62: 15470892 | T62: 16943915 | U62: 18904972 | V62: 38270763 | W62: =V62 -> 38270763 | X62: 37687948 | Y62: 35139197 | Z62: 35269194 | AA62: 34951925 | AB62: =AA62 -> 34951925 | AC62: 34258293 | AD62: 33957255
A63: CVM BPP 2.03 Patrimônio líquido consolidado | D63: 8182847 | E63: 8427995 | F63: 9145291 | G63: 9046515 | H63: =G63 -> 9046515 | I63: 12820277 | J63: 12732202 | K63: 12950527 | L63: 15253078 | M63: =L63 -> 15253078 | N63: 15483511 | O63: 14785962 | P63: 13962400 | Q63: 12368953 | R63: =Q63 -> 12368953 | S63: 12223465 | T63: 12315534 | U63: 12587285 | V63: 14483354 | W63: =V63 -> 14483354 | X63: 14578748 | Y63: 14063603 | Z63: 13564283 | AA63: 13775463 | AB63: =AA63 -> 13775463 | AC63: 13123193 | AD63: 12752850
A65: Notas:
A66: 1) Fonte única: ITR/DFP consolidados da CVM (dados abertos), R$ mil; a Inputs (2) divide por 1.000 (R$ milhões). Trimestres de fluxo: 3M quando a ITR traz, senão acumulado do ano menos o trimestre anterior.
A67: 2) 2023-2024 são o REPORTADO (sem AES Brasil até out/24). O pro forma da RI (Auren + AES) ficou só como memória acima e na linha 41 do Model (base do bloco de receita).
A68: 3) 2T22: a ITR veio sem as contas-mãe 2.01.05, 2.01.06 e 2.02.04 e com 2.02.02 incompleta; os saldos foram reconstruídos pela soma das contas filhas (o total bate com o passivo total divulgado).
A69: 4) Caixa (código 11) = caixa e equivalentes + aplicações financeiras. Fundo de liquidez/conta reserva de longo prazo fica em outros ativos (restrito).
A70: 5) Fluxo de caixa de 1T21 sem saldo inicial (dez/20 fora da grade): as variações do 1T21 no Model não são interpretáveis.

Sheet Inputs (2)
A1: =IF(Control!B3="","EMPRESA",Control!B3) -> Auren Energia S.A. | B1: Código | C1: Conta padronizada | D1: 2021 | E1: 2021 | F1: 2021 | G1: 2021 | H1: 2021 | I1: 2022 | J1: 2022 | K1: 2022 | L1: 2022 | M1: 2022 | N1: 2023 | O1: 2023 | P1: 2023 | Q1: 2023 | R1: 2023 | S1: 2024 | T1: 2024 | U1: 2024 | V1: 2024 | W1: 2024 | X1: 2025 | Y1: 2025 | Z1: 2025 | AA1: 2025 | AB1: 2025 | AC1: 2026 | AD1: 2026 | AE1: 2026 | AF1: 2026 | AG1: 2026
A2: R$ milhões | C2: Período | D2: 1Q21 | E2: 2Q21 | F2: 3Q21 | G2: 4Q21 | H2: 2021 | I2: 1Q22 | J2: 2Q22 | K2: 3Q22 | L2: 4Q22 | M2: 2022 | N2: 1Q23 | O2: 2Q23 | P2: 3Q23 | Q2: 4Q23 | R2: 2023 | S2: 1Q24 | T2: 2Q24 | U2: 3Q24 | V2: 4Q24 | W2: 2024 | X2: 1Q25 | Y2: 2Q25 | Z2: 3Q25 | AA2: 4Q25 | AB2: 2025 | AC2: 1Q26 | AD2: 2Q26 | AE2: 3Q26 | AF2: 4Q26 | AG2: 2026
A3: Actual flag | C3: 0 = sem dados / 1 = realizado | D3: 1 | E3: 1 | F3: 1 | G3: 1 | H3: 1 | I3: 1 | J3: 1 | K3: 1 | L3: 1 | M3: 1 | N3: 1 | O3: 1 | P3: 1 | Q3: 1 | R3: 1 | S3: 1 | T3: 1 | U3: 1 | V3: 1 | W3: 1 | X3: 1 | Y3: 1 | Z3: 1 | AA3: 1 | AB3: 1 | AC3: 1 | AD3: 1 | AE3: 0 | AF3: 0 | AG3: 0
B4: 1 | C4: Net Revenues | D4: =IF(D$3=0,"",SUMIFS(INDEX(Inputs!$D$4:$AG$100,0,MATCH(D$2,Inputs!$D$2:$AG$2,0)),Inputs!$B$4:$B$100,$B4)/1000) -> 552.151 | E4: =IF(E$3=0,"",SUMIFS(INDEX(Inputs!$D$4:$AG$100,0,MATCH(E$2,Inputs!$D$2:$AG$2,0)),Inputs!$B$4:$B$100,$B4)/1000) -> 581.104 | F4: =IF(F$3=0,"",SUMIFS(INDEX(Inputs!$D$4:$AG$100,0,MATCH(F$2,Inputs!$D$2:$AG$2,0)),Inputs!$B$4:$B$100,$B4)/1000) -> 616.194 | G4: =IF(G$3=0,"",SUMIFS(INDEX(Inputs!$D$4:$AG$100,0,MATCH(G$2,Inputs!$D$2:$AG$2,0)),Inputs!$B$4:$B$100,$B4)/1000) -> 767.313 | H4: =IF(COUNT(D4:G4)=4,SUM(D4:G4),"") -> 2516.762 | I4: =IF(I$3=0,"",SUMIFS(INDEX(Inputs!$D$4:$AG$100,0,MATCH(I$2,Inputs!$D$2:$AG$2,0)),Inputs!$B$4:$B$100,$B4)/1000) -> 1145.258 | J4: =IF(J$3=0,"",SUMIFS(INDEX(Inputs!$D$4:$AG$100,0,MATCH(J$2,Inputs!$D$2:$AG$2,0)),Inputs!$B$4:$B$100,$B4)/1000) -> 1346.655 | K4: =IF(K$3=0,"",SUMIFS(INDEX(Inputs!$D$4:$AG$100,0,MATCH(K$2,Inputs!$D$2:$AG$2,0)),Inputs!$B$4:$B$100,$B4)/1000) -> 1538.901 | L4: =IF(L$3=0,"",SUMIFS(INDEX(Inputs!$D$4:$AG$100,0,MATCH(L$2,Inputs!$D$2:$AG$2,0)),Inputs!$B$4:$B$100,$B4)/1000) -> 1484.892 | M4: =IF(COUNT(I4:L4)=4,SUM(I4:L4),"") -> 5515.706 | N4: =IF(N$3=0,"",SUMIFS(INDEX(Inputs!$D$4:$AG$100,0,MATCH(N$2,Inputs!$D$2:$AG$2,0)),Inputs!$B$4:$B$100,$B4)/1000) -> 1414.51 | O4: =IF(O$3=0,"",SUMIFS(INDEX(Inputs!$D$4:$AG$100,0,MATCH(O$2,Inputs!$D$2:$AG$2,0)),Inputs!$B$4:$B$100,$B4)/1000) -> 1437.088 | P4: =IF(P$3=0,"",SUMIFS(INDEX(Inputs!$D$4:$AG$100,0,MATCH(P$2,Inputs!$D$2:$AG$2,0)),Inputs!$B$4:$B$100,$B4)/1000) -> 1626.59 | Q4: =IF(Q$3=0,"",SUMIFS(INDEX(Inputs!$D$4:$AG$100,0,MATCH(Q$2,Inputs!$D$2:$AG$2,0)),Inputs!$B$4:$B$100,$B4)/1000) -> 1703.702 | R4: =IF(COUNT(N4:Q4)=4,SUM(N4:Q4),"") -> 6181.89 | S4: =IF(S$3=0,"",SUMIFS(INDEX(Inputs!$D$4:$AG$100,0,MATCH(S$2,Inputs!$D$2:$AG$2,0)),Inputs!$B$4:$B$100,$B4)/1000) -> 1397.531 | T4: =IF(T$3=0,"",SUMIFS(INDEX(Inputs!$D$4:$AG$100,0,MATCH(T$2,Inputs!$D$2:$AG$2,0)),Inputs!$B$4:$B$100,$B4)/1000) -> 1450.045 | U4: =IF(U$3=0,"",SUMIFS(INDEX(Inputs!$D$4:$AG$100,0,MATCH(U$2,Inputs!$D$2:$AG$2,0)),Inputs!$B$4:$B$100,$B4)/1000) -> 2046.511 | V4: =IF(V$3=0,"",SUMIFS(INDEX(Inputs!$D$4:$AG$100,0,MATCH(V$2,Inputs!$D$2:$AG$2,0)),Inputs!$B$4:$B$100,$B4)/1000) -> 3165.864 | W4: =IF(COUNT(S4:V4)=4,SUM(S4:V4),"") -> 8059.951 | X4: =IF(X$3=0,"",SUMIFS(INDEX(Inputs!$D$4:$AG$100,0,MATCH(X$2,Inputs!$D$2:$AG$2,0)),Inputs!$B$4:$B$100,$B4)/1000) -> 2952.303 | Y4: =IF(Y$3=0,"",SUMIFS(INDEX(Inputs!$D$4:$AG$100,0,MATCH(Y$2,Inputs!$D$2:$AG$2,0)),Inputs!$B$4:$B$100,$B4)/1000) -> 2885.529 | Z4: =IF(Z$3=0,"",SUMIFS(INDEX(Inputs!$D$4:$AG$100,0,MATCH(Z$2,Inputs!$D$2:$AG$2,0)),Inputs!$B$4:$B$100,$B4)/1000) -> 3537.391 | AA4: =IF(AA$3=0,"",SUMIFS(INDEX(Inputs!$D$4:$AG$100,0,MATCH(AA$2,Inputs!$D$2:$AG$2,0)),Inputs!$B$4:$B$100,$B4)/1000) -> 3801.729 | AB4: =IF(COUNT(X4:AA4)=4,SUM(X4:AA4),"") -> 13176.952 | AC4: =IF(AC$3=0,"",SUMIFS(INDEX(Inputs!$D$4:$AG$100,0,MATCH(AC$2,Inputs!$D$2:$AG$2,0)),Inputs!$B$4:$B$100,$B4)/1000) -> 3074.535 | AD4: =IF(AD$3=0,"",SUMIFS(INDEX(Inputs!$D$4:$AG$100,0,MATCH(AD$2,Inputs!$D$2:$AG$2,0)),Inputs!$B$4:$B$100,$B4)/1000) -> 3055.499 | AE4: =IF(AE$3=0,"",SUMIFS(INDEX(Inputs!$D$4:$AG$100,0,MATCH(AE$2,Inputs!$D$2:$AG$2,0)),Inputs!$B$4:$B$100,$B4)/1000) | AF4: =IF(AF$3=0,"",SUMIFS(INDEX(Inputs!$D$4:$AG$100,0,MATCH(AF$2,Inputs!$D$2:$AG$2,0)),Inputs!$B$4:$B$100,$B4)/1000) | AG4: =IF(COUNT(AC4:AF4)=4,SUM(AC4:AF4),"")
B5: 2 | C5: COGS (cash) | D5: =IF(D$3=0,"",SUMIFS(INDEX(Inputs!$D$4:$AG$100,0,MATCH(D$2,Inputs!$D$2:$AG$2,0)),Inputs!$B$4:$B$100,$B5)/1000) -> -145.037 | E5: =IF(E$3=0,"",SUMIFS(INDEX(Inputs!$D$4:$AG$100,0,MATCH(E$2,Inputs!$D$2:$AG$2,0)),Inputs!$B$4:$B$100,$B5)/1000) -> -270.903 | F5: =IF(F$3=0,"",SUMIFS(INDEX(Inputs!$D$4:$AG$100,0,MATCH(F$2,Inputs!$D$2:$AG$2,0)),Inputs!$B$4:$B$100,$B5)/1000) -> 334.446 | G5: =IF(G$3=0,"",SUMIFS(INDEX(Inputs!$D$4:$AG$100,0,MATCH(G$2,Inputs!$D$2:$AG$2,0)),Inputs!$B$4:$B$100,$B5)/1000) -> -442.928 | H5: =IF(COUNT(D5:G5)=4,SUM(D5:G5),"") -> -524.422 | I5: =IF(I$3=0,"",SUMIFS(INDEX(Inputs!$D$4:$AG$100,0,MATCH(I$2,Inputs!$D$2:$AG$2,0)),Inputs!$B$4:$B$100,$B5)/1000) -> -705.903 | J5: =IF(J$3=0,"",SUMIFS(INDEX(Inputs!$D$4:$AG$100,0,MATCH(J$2,Inputs!$D$2:$AG$2,0)),Inputs!$B$4:$B$100,$B5)/1000) -> -885.151 | K5: =IF(K$3=0,"",SUMIFS(INDEX(Inputs!$D$4:$AG$100,0,MATCH(K$2,Inputs!$D$2:$AG$2,0)),Inputs!$B$4:$B$100,$B5)/1000) -> -1072.724 | L5: =IF(L$3=0,"",SUMIFS(INDEX(Inputs!$D$4:$AG$100,0,MATCH(L$2,Inputs!$D$2:$AG$2,0)),Inputs!$B$4:$B$100,$B5)/1000) -> -1111.091 | M5: =IF(COUNT(I5:L5)=4,SUM(I5:L5),"") -> -3774.869 | N5: =IF(N$3=0,"",SUMIFS(INDEX(Inputs!$D$4:$AG$100,0,MATCH(N$2,Inputs!$D$2:$AG$2,0)),Inputs!$B$4:$B$100,$B5)/1000) -> -912.817 | O5: =IF(O$3=0,"",SUMIFS(INDEX(Inputs!$D$4:$AG$100,0,MATCH(O$2,Inputs!$D$2:$AG$2,0)),Inputs!$B$4:$B$100,$B5)/1000) -> -925.86 | P5: =IF(P$3=0,"",SUMIFS(INDEX(Inputs!$D$4:$AG$100,0,MATCH(P$2,Inputs!$D$2:$AG$2,0)),Inputs!$B$4:$B$100,$B5)/1000) -> -1129.51 | Q5: =IF(Q$3=0,"",SUMIFS(INDEX(Inputs!$D$4:$AG$100,0,MATCH(Q$2,Inputs!$D$2:$AG$2,0)),Inputs!$B$4:$B$100,$B5)/1000) -> -1203.484 | R5: =IF(COUNT(N5:Q5)=4,SUM(N5:Q5),"") -> -4171.671 | S5: =IF(S$3=0,"",SUMIFS(INDEX(Inputs!$D$4:$AG$100,0,MATCH(S$2,Inputs!$D$2:$AG$2,0)),Inputs!$B$4:$B$100,$B5)/1000) -> -940.124 | T5: =IF(T$3=0,"",SUMIFS(INDEX(Inputs!$D$4:$AG$100,0,MATCH(T$2,Inputs!$D$2:$AG$2,0)),Inputs!$B$4:$B$100,$B5)/1000) -> -953.328 | U5: =IF(U$3=0,"",SUMIFS(INDEX(Inputs!$D$4:$AG$100,0,MATCH(U$2,Inputs!$D$2:$AG$2,0)),Inputs!$B$4:$B$100,$B5)/1000) -> -1544.378 | V5: =IF(V$3=0,"",SUMIFS(INDEX(Inputs!$D$4:$AG$100,0,MATCH(V$2,Inputs!$D$2:$AG$2,0)),Inputs!$B$4:$B$100,$B5)/1000) -> -2479.928 | W5: =IF(COUNT(S5:V5)=4,SUM(S5:V5),"") -> -5917.758 | X5: =IF(X$3=0,"",SUMIFS(INDEX(Inputs!$D$4:$AG$100,0,MATCH(X$2,Inputs!$D$2:$AG$2,0)),Inputs!$B$4:$B$100,$B5)/1000) -> -1657.838 | Y5: =IF(Y$3=0,"",SUMIFS(INDEX(Inputs!$D$4:$AG$100,0,MATCH(Y$2,Inputs!$D$2:$AG$2,0)),Inputs!$B$4:$B$100,$B5)/1000) -> -1868.345 | Z5: =IF(Z$3=0,"",SUMIFS(INDEX(Inputs!$D$4:$AG$100,0,MATCH(Z$2,Inputs!$D$2:$AG$2,0)),Inputs!$B$4:$B$100,$B5)/1000) -> -2735.147 | AA5: =IF(AA$3=0,"",SUMIFS(INDEX(Inputs!$D$4:$AG$100,0,MATCH(AA$2,Inputs!$D$2:$AG$2,0)),Inputs!$B$4:$B$100,$B5)/1000) -> -2841.923 | AB5: =IF(COUNT(X5:AA5)=4,SUM(X5:AA5),"") -> -9103.253 | AC5: =IF(AC$3=0,"",SUMIFS(INDEX(Inputs!$D$4:$AG$100,0,MATCH(AC$2,Inputs!$D$2:$AG$2,0)),Inputs!$B$4:$B$100,$B5)/1000) -> -2120.25 | AD5: =IF(AD$3=0,"",SUMIFS(INDEX(Inputs!$D$4:$AG$100,0,MATCH(AD$2,Inputs!$D$2:$AG$2,0)),Inputs!$B$4:$B$100,$B5)/1000) -> -2137.818 | AE5: =IF(AE$3=0,"",SUMIFS(INDEX(Inputs!$D$4:$AG$100,0,MATCH(AE$2,Inputs!$D$2:$AG$2,0)),Inputs!$B$4:$B$100,$B5)/1000) | AF5: =IF(AF$3=0,"",SUMIFS(INDEX(Inputs!$D$4:$AG$100,0,MATCH(AF$2,Inputs!$D$2:$AG$2,0)),Inputs!$B$4:$B$100,$B5)/1000) | AG5: =IF(COUNT(AC5:AF5)=4,SUM(AC5:AF5),"")
B6: 3 | C6: SG&A and Other (cash) | D6: =IF(D$3=0,"",SUMIFS(INDEX(Inputs!$D$4:$AG$100,0,MATCH(D$2,Inputs!$D$2:$AG$2,0)),Inputs!$B$4:$B$100,$B6)/1000) -> -37.007 | E6: =IF(E$3=0,"",SUMIFS(INDEX(Inputs!$D$4:$AG$100,0,MATCH(E$2,Inputs!$D$2:$AG$2,0)),Inputs!$B$4:$B$100,$B6)/1000) -> -72.009 | F6: =IF(F$3=0,"",SUMIFS(INDEX(Inputs!$D$4:$AG$100,0,MATCH(F$2,Inputs!$D$2:$AG$2,0)),Inputs!$B$4:$B$100,$B6)/1000) -> -98.542 | G6: =IF(G$3=0,"",SUMIFS(INDEX(Inputs!$D$4:$AG$100,0,MATCH(G$2,Inputs!$D$2:$AG$2,0)),Inputs!$B$4:$B$100,$B6)/1000) -> -5.338 | H6: =IF(COUNT(D6:G6)=4,SUM(D6:G6),"") -> -212.896 | I6: =IF(I$3=0,"",SUMIFS(INDEX(Inputs!$D$4:$AG$100,0,MATCH(I$2,Inputs!$D$2:$AG$2,0)),Inputs!$B$4:$B$100,$B6)/1000) -> -134.703 | J6: =IF(J$3=0,"",SUMIFS(INDEX(Inputs!$D$4:$AG$100,0,MATCH(J$2,Inputs!$D$2:$AG$2,0)),Inputs!$B$4:$B$100,$B6)/1000) -> -172.018 | K6: =IF(K$3=0,"",SUMIFS(INDEX(Inputs!$D$4:$AG$100,0,MATCH(K$2,Inputs!$D$2:$AG$2,0)),Inputs!$B$4:$B$100,$B6)/1000) -> 37.062 | L6: =IF(L$3=0,"",SUMIFS(INDEX(Inputs!$D$4:$AG$100,0,MATCH(L$2,Inputs!$D$2:$AG$2,0)),Inputs!$B$4:$B$100,$B6)/1000) -> 386.982 | M6: =IF(COUNT(I6:L6)=4,SUM(I6:L6),"") -> 117.323 | N6: =IF(N$3=0,"",SUMIFS(INDEX(Inputs!$D$4:$AG$100,0,MATCH(N$2,Inputs!$D$2:$AG$2,0)),Inputs!$B$4:$B$100,$B6)/1000) -> -49.811 | O6: =IF(O$3=0,"",SUMIFS(INDEX(Inputs!$D$4:$AG$100,0,MATCH(O$2,Inputs!$D$2:$AG$2,0)),Inputs!$B$4:$B$100,$B6)/1000) -> -53.318 | P6: =IF(P$3=0,"",SUMIFS(INDEX(Inputs!$D$4:$AG$100,0,MATCH(P$2,Inputs!$D$2:$AG$2,0)),Inputs!$B$4:$B$100,$B6)/1000) -> -147 | Q6: =IF(Q$3=0,"",SUMIFS(INDEX(Inputs!$D$4:$AG$100,0,MATCH(Q$2,Inputs!$D$2:$AG$2,0)),Inputs!$B$4:$B$100,$B6)/1000) -> -82.213 | R6: =IF(COUNT(N6:Q6)=4,SUM(N6:Q6),"") -> -332.342 | S6: =IF(S$3=0,"",SUMIFS(INDEX(Inputs!$D$4:$AG$100,0,MATCH(S$2,Inputs!$D$2:$AG$2,0)),Inputs!$B$4:$B$100,$B6)/1000) -> 142.237 | T6: =IF(T$3=0,"",SUMIFS(INDEX(Inputs!$D$4:$AG$100,0,MATCH(T$2,Inputs!$D$2:$AG$2,0)),Inputs!$B$4:$B$100,$B6)/1000) -> -98.647 | U6: =IF(U$3=0,"",SUMIFS(INDEX(Inputs!$D$4:$AG$100,0,MATCH(U$2,Inputs!$D$2:$AG$2,0)),Inputs!$B$4:$B$100,$B6)/1000) -> 131.446 | V6: =IF(V$3=0,"",SUMIFS(INDEX(Inputs!$D$4:$AG$100,0,MATCH(V$2,Inputs!$D$2:$AG$2,0)),Inputs!$B$4:$B$100,$B6)/1000) -> -476.758 | W6: =IF(COUNT(S6:V6)=4,SUM(S6:V6),"") -> -301.722 | X6: =IF(X$3=0,"",SUMIFS(INDEX(Inputs!$D$4:$AG$100,0,MATCH(X$2,Inputs!$D$2:$AG$2,0)),Inputs!$B$4:$B$100,$B6)/1000) -> 83.043 | Y6: =IF(Y$3=0,"",SUMIFS(INDEX(Inputs!$D$4:$AG$100,0,MATCH(Y$2,Inputs!$D$2:$AG$2,0)),Inputs!$B$4:$B$100,$B6)/1000) -> -500.171 | Z6: =IF(Z$3=0,"",SUMIFS(INDEX(Inputs!$D$4:$AG$100,0,MATCH(Z$2,Inputs!$D$2:$AG$2,0)),Inputs!$B$4:$B$100,$B6)/1000) -> -137.92 | AA6: =IF(AA$3=0,"",SUMIFS(INDEX(Inputs!$D$4:$AG$100,0,MATCH(AA$2,Inputs!$D$2:$AG$2,0)),Inputs!$B$4:$B$100,$B6)/1000) -> 515.089 | AB6: =IF(COUNT(X6:AA6)=4,SUM(X6:AA6),"") -> -39.959 | AC6: =IF(AC$3=0,"",SUMIFS(INDEX(Inputs!$D$4:$AG$100,0,MATCH(AC$2,Inputs!$D$2:$AG$2,0)),Inputs!$B$4:$B$100,$B6)/1000) -> -654.169 | AD6: =IF(AD$3=0,"",SUMIFS(INDEX(Inputs!$D$4:$AG$100,0,MATCH(AD$2,Inputs!$D$2:$AG$2,0)),Inputs!$B$4:$B$100,$B6)/1000) -> -106.914 | AE6: =IF(AE$3=0,"",SUMIFS(INDEX(Inputs!$D$4:$AG$100,0,MATCH(AE$2,Inputs!$D$2:$AG$2,0)),Inputs!$B$4:$B$100,$B6)/1000) | AF6: =IF(AF$3=0,"",SUMIFS(INDEX(Inputs!$D$4:$AG$100,0,MATCH(AF$2,Inputs!$D$2:$AG$2,0)),Inputs!$B$4:$B$100,$B6)/1000) | AG6: =IF(COUNT(AC6:AF6)=4,SUM(AC6:AF6),"")
B7: 4 | C7: D&A | D7: =IF(D$3=0,"",SUMIFS(INDEX(Inputs!$D$4:$AG$100,0,MATCH(D$2,Inputs!$D$2:$AG$2,0)),Inputs!$B$4:$B$100,$B7)/1000) -> -132.593 | E7: =IF(E$3=0,"",SUMIFS(INDEX(Inputs!$D$4:$AG$100,0,MATCH(E$2,Inputs!$D$2:$AG$2,0)),Inputs!$B$4:$B$100,$B7)/1000) -> -131.573 | F7: =IF(F$3=0,"",SUMIFS(INDEX(Inputs!$D$4:$AG$100,0,MATCH(F$2,Inputs!$D$2:$AG$2,0)),Inputs!$B$4:$B$100,$B7)/1000) -> -145.397 | G7: =IF(G$3=0,"",SUMIFS(INDEX(Inputs!$D$4:$AG$100,0,MATCH(G$2,Inputs!$D$2:$AG$2,0)),Inputs!$B$4:$B$100,$B7)/1000) -> -149.432 | H7: =IF(COUNT(D7:G7)=4,SUM(D7:G7),"") -> -558.995 | I7: =IF(I$3=0,"",SUMIFS(INDEX(Inputs!$D$4:$AG$100,0,MATCH(I$2,Inputs!$D$2:$AG$2,0)),Inputs!$B$4:$B$100,$B7)/1000) -> -157.304 | J7: =IF(J$3=0,"",SUMIFS(INDEX(Inputs!$D$4:$AG$100,0,MATCH(J$2,Inputs!$D$2:$AG$2,0)),Inputs!$B$4:$B$100,$B7)/1000) -> -161.19 | K7: =IF(K$3=0,"",SUMIFS(INDEX(Inputs!$D$4:$AG$100,0,MATCH(K$2,Inputs!$D$2:$AG$2,0)),Inputs!$B$4:$B$100,$B7)/1000) -> -161.353 | L7: =IF(L$3=0,"",SUMIFS(INDEX(Inputs!$D$4:$AG$100,0,MATCH(L$2,Inputs!$D$2:$AG$2,0)),Inputs!$B$4:$B$100,$B7)/1000) -> -117.907 | M7: =IF(COUNT(I7:L7)=4,SUM(I7:L7),"") -> -597.754 | N7: =IF(N$3=0,"",SUMIFS(INDEX(Inputs!$D$4:$AG$100,0,MATCH(N$2,Inputs!$D$2:$AG$2,0)),Inputs!$B$4:$B$100,$B7)/1000) -> -168.327 | O7: =IF(O$3=0,"",SUMIFS(INDEX(Inputs!$D$4:$AG$100,0,MATCH(O$2,Inputs!$D$2:$AG$2,0)),Inputs!$B$4:$B$100,$B7)/1000) -> -169.666 | P7: =IF(P$3=0,"",SUMIFS(INDEX(Inputs!$D$4:$AG$100,0,MATCH(P$2,Inputs!$D$2:$AG$2,0)),Inputs!$B$4:$B$100,$B7)/1000) -> -169.643 | Q7: =IF(Q$3=0,"",SUMIFS(INDEX(Inputs!$D$4:$AG$100,0,MATCH(Q$2,Inputs!$D$2:$AG$2,0)),Inputs!$B$4:$B$100,$B7)/1000) -> -169.639 | R7: =IF(COUNT(N7:Q7)=4,SUM(N7:Q7),"") -> -677.275 | S7: =IF(S$3=0,"",SUMIFS(INDEX(Inputs!$D$4:$AG$100,0,MATCH(S$2,Inputs!$D$2:$AG$2,0)),Inputs!$B$4:$B$100,$B7)/1000) -> -166.381 | T7: =IF(T$3=0,"",SUMIFS(INDEX(Inputs!$D$4:$AG$100,0,MATCH(T$2,Inputs!$D$2:$AG$2,0)),Inputs!$B$4:$B$100,$B7)/1000) -> -175.177 | U7: =IF(U$3=0,"",SUMIFS(INDEX(Inputs!$D$4:$AG$100,0,MATCH(U$2,Inputs!$D$2:$AG$2,0)),Inputs!$B$4:$B$100,$B7)/1000) -> -182.611 | V7: =IF(V$3=0,"",SUMIFS(INDEX(Inputs!$D$4:$AG$100,0,MATCH(V$2,Inputs!$D$2:$AG$2,0)),Inputs!$B$4:$B$100,$B7)/1000) -> -189.021 | W7: =IF(COUNT(S7:V7)=4,SUM(S7:V7),"") -> -713.19 | X7: =IF(X$3=0,"",SUMIFS(INDEX(Inputs!$D$4:$AG$100,0,MATCH(X$2,Inputs!$D$2:$AG$2,0)),Inputs!$B$4:$B$100,$B7)/1000) -> -458.196 | Y7: =IF(Y$3=0,"",SUMIFS(INDEX(Inputs!$D$4:$AG$100,0,MATCH(Y$2,Inputs!$D$2:$AG$2,0)),Inputs!$B$4:$B$100,$B7)/1000) -> -521.747 | Z7: =IF(Z$3=0,"",SUMIFS(INDEX(Inputs!$D$4:$AG$100,0,MATCH(Z$2,Inputs!$D$2:$AG$2,0)),Inputs!$B$4:$B$100,$B7)/1000) -> -465.553 | AA7: =IF(AA$3=0,"",SUMIFS(INDEX(Inputs!$D$4:$AG$100,0,MATCH(AA$2,Inputs!$D$2:$AG$2,0)),Inputs!$B$4:$B$100,$B7)/1000) -> -477.467 | AB7: =IF(COUNT(X7:AA7)=4,SUM(X7:AA7),"") -> -1922.963 | AC7: =IF(AC$3=0,"",SUMIFS(INDEX(Inputs!$D$4:$AG$100,0,MATCH(AC$2,Inputs!$D$2:$AG$2,0)),Inputs!$B$4:$B$100,$B7)/1000) -> -466.831 | AD7: =IF(AD$3=0,"",SUMIFS(INDEX(Inputs!$D$4:$AG$100,0,MATCH(AD$2,Inputs!$D$2:$AG$2,0)),Inputs!$B$4:$B$100,$B7)/1000) -> -465.443 | AE7: =IF(AE$3=0,"",SUMIFS(INDEX(Inputs!$D$4:$AG$100,0,MATCH(AE$2,Inputs!$D$2:$AG$2,0)),Inputs!$B$4:$B$100,$B7)/1000) | AF7: =IF(AF$3=0,"",SUMIFS(INDEX(Inputs!$D$4:$AG$100,0,MATCH(AF$2,Inputs!$D$2:$AG$2,0)),Inputs!$B$4:$B$100,$B7)/1000) | AG7: =IF(COUNT(AC7:AF7)=4,SUM(AC7:AF7),"")
B8: 5 | C8: Interest Expense | D8: =IF(D$3=0,"",SUMIFS(INDEX(Inputs!$D$4:$AG$100,0,MATCH(D$2,Inputs!$D$2:$AG$2,0)),Inputs!$B$4:$B$100,$B8)/1000) -> -164.756 | E8: =IF(E$3=0,"",SUMIFS(INDEX(Inputs!$D$4:$AG$100,0,MATCH(E$2,Inputs!$D$2:$AG$2,0)),Inputs!$B$4:$B$100,$B8)/1000) -> -211.669 | F8: =IF(F$3=0,"",SUMIFS(INDEX(Inputs!$D$4:$AG$100,0,MATCH(F$2,Inputs!$D$2:$AG$2,0)),Inputs!$B$4:$B$100,$B8)/1000) -> -193.237 | G8: =IF(G$3=0,"",SUMIFS(INDEX(Inputs!$D$4:$AG$100,0,MATCH(G$2,Inputs!$D$2:$AG$2,0)),Inputs!$B$4:$B$100,$B8)/1000) -> -238.999 | H8: =IF(COUNT(D8:G8)=4,SUM(D8:G8),"") -> -808.661 | I8: =IF(I$3=0,"",SUMIFS(INDEX(Inputs!$D$4:$AG$100,0,MATCH(I$2,Inputs!$D$2:$AG$2,0)),Inputs!$B$4:$B$100,$B8)/1000) -> -250.51 | J8: =IF(J$3=0,"",SUMIFS(INDEX(Inputs!$D$4:$AG$100,0,MATCH(J$2,Inputs!$D$2:$AG$2,0)),Inputs!$B$4:$B$100,$B8)/1000) -> -291.34 | K8: =IF(K$3=0,"",SUMIFS(INDEX(Inputs!$D$4:$AG$100,0,MATCH(K$2,Inputs!$D$2:$AG$2,0)),Inputs!$B$4:$B$100,$B8)/1000) -> -165.812 | L8: =IF(L$3=0,"",SUMIFS(INDEX(Inputs!$D$4:$AG$100,0,MATCH(L$2,Inputs!$D$2:$AG$2,0)),Inputs!$B$4:$B$100,$B8)/1000) -> -468.975 | M8: =IF(COUNT(I8:L8)=4,SUM(I8:L8),"") -> -1176.637 | N8: =IF(N$3=0,"",SUMIFS(INDEX(Inputs!$D$4:$AG$100,0,MATCH(N$2,Inputs!$D$2:$AG$2,0)),Inputs!$B$4:$B$100,$B8)/1000) -> -272.035 | O8: =IF(O$3=0,"",SUMIFS(INDEX(Inputs!$D$4:$AG$100,0,MATCH(O$2,Inputs!$D$2:$AG$2,0)),Inputs!$B$4:$B$100,$B8)/1000) -> -497.689 | P8: =IF(P$3=0,"",SUMIFS(INDEX(Inputs!$D$4:$AG$100,0,MATCH(P$2,Inputs!$D$2:$AG$2,0)),Inputs!$B$4:$B$100,$B8)/1000) -> -194.621 | Q8: =IF(Q$3=0,"",SUMIFS(INDEX(Inputs!$D$4:$AG$100,0,MATCH(Q$2,Inputs!$D$2:$AG$2,0)),Inputs!$B$4:$B$100,$B8)/1000) -> -215.024 | R8: =IF(COUNT(N8:Q8)=4,SUM(N8:Q8),"") -> -1179.369 | S8: =IF(S$3=0,"",SUMIFS(INDEX(Inputs!$D$4:$AG$100,0,MATCH(S$2,Inputs!$D$2:$AG$2,0)),Inputs!$B$4:$B$100,$B8)/1000) -> -258.839 | T8: =IF(T$3=0,"",SUMIFS(INDEX(Inputs!$D$4:$AG$100,0,MATCH(T$2,Inputs!$D$2:$AG$2,0)),Inputs!$B$4:$B$100,$B8)/1000) -> -255.757 | U8: =IF(U$3=0,"",SUMIFS(INDEX(Inputs!$D$4:$AG$100,0,MATCH(U$2,Inputs!$D$2:$AG$2,0)),Inputs!$B$4:$B$100,$B8)/1000) -> -243.887 | V8: =IF(V$3=0,"",SUMIFS(INDEX(Inputs!$D$4:$AG$100,0,MATCH(V$2,Inputs!$D$2:$AG$2,0)),Inputs!$B$4:$B$100,$B8)/1000) -> -717.696 | W8: =IF(COUNT(S8:V8)=4,SUM(S8:V8),"") -> -1476.179 | X8: =IF(X$3=0,"",SUMIFS(INDEX(Inputs!$D$4:$AG$100,0,MATCH(X$2,Inputs!$D$2:$AG$2,0)),Inputs!$B$4:$B$100,$B8)/1000) -> -1008.815 | Y8: =IF(Y$3=0,"",SUMIFS(INDEX(Inputs!$D$4:$AG$100,0,MATCH(Y$2,Inputs!$D$2:$AG$2,0)),Inputs!$B$4:$B$100,$B8)/1000) -> -879.279 | Z8: =IF(Z$3=0,"",SUMIFS(INDEX(Inputs!$D$4:$AG$100,0,MATCH(Z$2,Inputs!$D$2:$AG$2,0)),Inputs!$B$4:$B$100,$B8)/1000) -> -869.78 | AA8: =IF(AA$3=0,"",SUMIFS(INDEX(Inputs!$D$4:$AG$100,0,MATCH(AA$2,Inputs!$D$2:$AG$2,0)),Inputs!$B$4:$B$100,$B8)/1000) -> -783.788 | AB8: =IF(COUNT(X8:AA8)=4,SUM(X8:AA8),"") -> -3541.662 | AC8: =IF(AC$3=0,"",SUMIFS(INDEX(Inputs!$D$4:$AG$100,0,MATCH(AC$2,Inputs!$D$2:$AG$2,0)),Inputs!$B$4:$B$100,$B8)/1000) -> -867.481 | AD8: =IF(AD$3=0,"",SUMIFS(INDEX(Inputs!$D$4:$AG$100,0,MATCH(AD$2,Inputs!$D$2:$AG$2,0)),Inputs!$B$4:$B$100,$B8)/1000) -> -1018.168 | AE8: =IF(AE$3=0,"",SUMIFS(INDEX(Inputs!$D$4:$AG$100,0,MATCH(AE$2,Inputs!$D$2:$AG$2,0)),Inputs!$B$4:$B$100,$B8)/1000) | AF8: =IF(AF$3=0,"",SUMIFS(INDEX(Inputs!$D$4:$AG$100,0,MATCH(AF$2,Inputs!$D$2:$AG$2,0)),Inputs!$B$4:$B$100,$B8)/1000) | AG8: =IF(COUNT(AC8:AF8)=4,SUM(AC8:AF8),"")
B9: 6 | C9: Nonoperating Income / (Loss) | D9: =IF(D$3=0,"",SUMIFS(INDEX(Inputs!$D$4:$AG$100,0,MATCH(D$2,Inputs!$D$2:$AG$2,0)),Inputs!$B$4:$B$100,$B9)/1000) -> 13.753 | E9: =IF(E$3=0,"",SUMIFS(INDEX(Inputs!$D$4:$AG$100,0,MATCH(E$2,Inputs!$D$2:$AG$2,0)),Inputs!$B$4:$B$100,$B9)/1000) -> 11.716 | F9: =IF(F$3=0,"",SUMIFS(INDEX(Inputs!$D$4:$AG$100,0,MATCH(F$2,Inputs!$D$2:$AG$2,0)),Inputs!$B$4:$B$100,$B9)/1000) -> 41.663 | G9: =IF(G$3=0,"",SUMIFS(INDEX(Inputs!$D$4:$AG$100,0,MATCH(G$2,Inputs!$D$2:$AG$2,0)),Inputs!$B$4:$B$100,$B9)/1000) -> 33.412 | H9: =IF(COUNT(D9:G9)=4,SUM(D9:G9),"") -> 100.544 | I9: =IF(I$3=0,"",SUMIFS(INDEX(Inputs!$D$4:$AG$100,0,MATCH(I$2,Inputs!$D$2:$AG$2,0)),Inputs!$B$4:$B$100,$B9)/1000) -> 86.074 | J9: =IF(J$3=0,"",SUMIFS(INDEX(Inputs!$D$4:$AG$100,0,MATCH(J$2,Inputs!$D$2:$AG$2,0)),Inputs!$B$4:$B$100,$B9)/1000) -> 103.888 | K9: =IF(K$3=0,"",SUMIFS(INDEX(Inputs!$D$4:$AG$100,0,MATCH(K$2,Inputs!$D$2:$AG$2,0)),Inputs!$B$4:$B$100,$B9)/1000) -> 112.759 | L9: =IF(L$3=0,"",SUMIFS(INDEX(Inputs!$D$4:$AG$100,0,MATCH(L$2,Inputs!$D$2:$AG$2,0)),Inputs!$B$4:$B$100,$B9)/1000) -> 2536.191 | M9: =IF(COUNT(I9:L9)=4,SUM(I9:L9),"") -> 2838.912 | N9: =IF(N$3=0,"",SUMIFS(INDEX(Inputs!$D$4:$AG$100,0,MATCH(N$2,Inputs!$D$2:$AG$2,0)),Inputs!$B$4:$B$100,$B9)/1000) -> 254.848 | O9: =IF(O$3=0,"",SUMIFS(INDEX(Inputs!$D$4:$AG$100,0,MATCH(O$2,Inputs!$D$2:$AG$2,0)),Inputs!$B$4:$B$100,$B9)/1000) -> 473.238 | P9: =IF(P$3=0,"",SUMIFS(INDEX(Inputs!$D$4:$AG$100,0,MATCH(P$2,Inputs!$D$2:$AG$2,0)),Inputs!$B$4:$B$100,$B9)/1000) -> 74.493 | Q9: =IF(Q$3=0,"",SUMIFS(INDEX(Inputs!$D$4:$AG$100,0,MATCH(Q$2,Inputs!$D$2:$AG$2,0)),Inputs!$B$4:$B$100,$B9)/1000) -> 138.783 | R9: =IF(COUNT(N9:Q9)=4,SUM(N9:Q9),"") -> 941.362 | S9: =IF(S$3=0,"",SUMIFS(INDEX(Inputs!$D$4:$AG$100,0,MATCH(S$2,Inputs!$D$2:$AG$2,0)),Inputs!$B$4:$B$100,$B9)/1000) -> 149.86 | T9: =IF(T$3=0,"",SUMIFS(INDEX(Inputs!$D$4:$AG$100,0,MATCH(T$2,Inputs!$D$2:$AG$2,0)),Inputs!$B$4:$B$100,$B9)/1000) -> 119.705 | U9: =IF(U$3=0,"",SUMIFS(INDEX(Inputs!$D$4:$AG$100,0,MATCH(U$2,Inputs!$D$2:$AG$2,0)),Inputs!$B$4:$B$100,$B9)/1000) -> 141.262 | V9: =IF(V$3=0,"",SUMIFS(INDEX(Inputs!$D$4:$AG$100,0,MATCH(V$2,Inputs!$D$2:$AG$2,0)),Inputs!$B$4:$B$100,$B9)/1000) -> 304.06 | W9: =IF(COUNT(S9:V9)=4,SUM(S9:V9),"") -> 714.887 | X9: =IF(X$3=0,"",SUMIFS(INDEX(Inputs!$D$4:$AG$100,0,MATCH(X$2,Inputs!$D$2:$AG$2,0)),Inputs!$B$4:$B$100,$B9)/1000) -> 276.738 | Y9: =IF(Y$3=0,"",SUMIFS(INDEX(Inputs!$D$4:$AG$100,0,MATCH(Y$2,Inputs!$D$2:$AG$2,0)),Inputs!$B$4:$B$100,$B9)/1000) -> 234.752 | Z9: =IF(Z$3=0,"",SUMIFS(INDEX(Inputs!$D$4:$AG$100,0,MATCH(Z$2,Inputs!$D$2:$AG$2,0)),Inputs!$B$4:$B$100,$B9)/1000) -> 244.49 | AA9: =IF(AA$3=0,"",SUMIFS(INDEX(Inputs!$D$4:$AG$100,0,MATCH(AA$2,Inputs!$D$2:$AG$2,0)),Inputs!$B$4:$B$100,$B9)/1000) -> 351.744 | AB9: =IF(COUNT(X9:AA9)=4,SUM(X9:AA9),"") -> 1107.724 | AC9: =IF(AC$3=0,"",SUMIFS(INDEX(Inputs!$D$4:$AG$100,0,MATCH(AC$2,Inputs!$D$2:$AG$2,0)),Inputs!$B$4:$B$100,$B9)/1000) -> 277.65 | AD9: =IF(AD$3=0,"",SUMIFS(INDEX(Inputs!$D$4:$AG$100,0,MATCH(AD$2,Inputs!$D$2:$AG$2,0)),Inputs!$B$4:$B$100,$B9)/1000) -> 286.022 | AE9: =IF(AE$3=0,"",SUMIFS(INDEX(Inputs!$D$4:$AG$100,0,MATCH(AE$2,Inputs!$D$2:$AG$2,0)),Inputs!$B$4:$B$100,$B9)/1000) | AF9: =IF(AF$3=0,"",SUMIFS(INDEX(Inputs!$D$4:$AG$100,0,MATCH(AF$2,Inputs!$D$2:$AG$2,0)),Inputs!$B$4:$B$100,$B9)/1000) | AG9: =IF(COUNT(AC9:AF9)=4,SUM(AC9:AF9),"")
B10: 7 | C10: Taxes | D10: =IF(D$3=0,"",SUMIFS(INDEX(Inputs!$D$4:$AG$100,0,MATCH(D$2,Inputs!$D$2:$AG$2,0)),Inputs!$B$4:$B$100,$B10)/1000) -> -46.947 | E10: =IF(E$3=0,"",SUMIFS(INDEX(Inputs!$D$4:$AG$100,0,MATCH(E$2,Inputs!$D$2:$AG$2,0)),Inputs!$B$4:$B$100,$B10)/1000) -> 7.108 | F10: =IF(F$3=0,"",SUMIFS(INDEX(Inputs!$D$4:$AG$100,0,MATCH(F$2,Inputs!$D$2:$AG$2,0)),Inputs!$B$4:$B$100,$B10)/1000) -> -238.601 | G10: =IF(G$3=0,"",SUMIFS(INDEX(Inputs!$D$4:$AG$100,0,MATCH(G$2,Inputs!$D$2:$AG$2,0)),Inputs!$B$4:$B$100,$B10)/1000) -> 16.235 | H10: =IF(COUNT(D10:G10)=4,SUM(D10:G10),"") -> -262.205 | I10: =IF(I$3=0,"",SUMIFS(INDEX(Inputs!$D$4:$AG$100,0,MATCH(I$2,Inputs!$D$2:$AG$2,0)),Inputs!$B$4:$B$100,$B10)/1000) -> -14.548 | J10: =IF(J$3=0,"",SUMIFS(INDEX(Inputs!$D$4:$AG$100,0,MATCH(J$2,Inputs!$D$2:$AG$2,0)),Inputs!$B$4:$B$100,$B10)/1000) -> 2.189 | K10: =IF(K$3=0,"",SUMIFS(INDEX(Inputs!$D$4:$AG$100,0,MATCH(K$2,Inputs!$D$2:$AG$2,0)),Inputs!$B$4:$B$100,$B10)/1000) -> -111.046 | L10: =IF(L$3=0,"",SUMIFS(INDEX(Inputs!$D$4:$AG$100,0,MATCH(L$2,Inputs!$D$2:$AG$2,0)),Inputs!$B$4:$B$100,$B10)/1000) -> -251.321 | M10: =IF(COUNT(I10:L10)=4,SUM(I10:L10),"") -> -374.726 | N10: =IF(N$3=0,"",SUMIFS(INDEX(Inputs!$D$4:$AG$100,0,MATCH(N$2,Inputs!$D$2:$AG$2,0)),Inputs!$B$4:$B$100,$B10)/1000) -> -66.645 | O10: =IF(O$3=0,"",SUMIFS(INDEX(Inputs!$D$4:$AG$100,0,MATCH(O$2,Inputs!$D$2:$AG$2,0)),Inputs!$B$4:$B$100,$B10)/1000) -> -69.024 | P10: =IF(P$3=0,"",SUMIFS(INDEX(Inputs!$D$4:$AG$100,0,MATCH(P$2,Inputs!$D$2:$AG$2,0)),Inputs!$B$4:$B$100,$B10)/1000) -> -943.452 | Q10: =IF(Q$3=0,"",SUMIFS(INDEX(Inputs!$D$4:$AG$100,0,MATCH(Q$2,Inputs!$D$2:$AG$2,0)),Inputs!$B$4:$B$100,$B10)/1000) -> -74.475 | R10: =IF(COUNT(N10:Q10)=4,SUM(N10:Q10),"") -> -1153.596 | S10: =IF(S$3=0,"",SUMIFS(INDEX(Inputs!$D$4:$AG$100,0,MATCH(S$2,Inputs!$D$2:$AG$2,0)),Inputs!$B$4:$B$100,$B10)/1000) -> -137.244 | T10: =IF(T$3=0,"",SUMIFS(INDEX(Inputs!$D$4:$AG$100,0,MATCH(T$2,Inputs!$D$2:$AG$2,0)),Inputs!$B$4:$B$100,$B10)/1000) -> -49.276 | U10: =IF(U$3=0,"",SUMIFS(INDEX(Inputs!$D$4:$AG$100,0,MATCH(U$2,Inputs!$D$2:$AG$2,0)),Inputs!$B$4:$B$100,$B10)/1000) -> -135.947 | V10: =IF(V$3=0,"",SUMIFS(INDEX(Inputs!$D$4:$AG$100,0,MATCH(V$2,Inputs!$D$2:$AG$2,0)),Inputs!$B$4:$B$100,$B10)/1000) -> 63.963 | W10: =IF(COUNT(S10:V10)=4,SUM(S10:V10),"") -> -258.504 | X10: =IF(X$3=0,"",SUMIFS(INDEX(Inputs!$D$4:$AG$100,0,MATCH(X$2,Inputs!$D$2:$AG$2,0)),Inputs!$B$4:$B$100,$B10)/1000) -> -205.385 | Y10: =IF(Y$3=0,"",SUMIFS(INDEX(Inputs!$D$4:$AG$100,0,MATCH(Y$2,Inputs!$D$2:$AG$2,0)),Inputs!$B$4:$B$100,$B10)/1000) -> 71.65 | Z10: =IF(Z$3=0,"",SUMIFS(INDEX(Inputs!$D$4:$AG$100,0,MATCH(Z$2,Inputs!$D$2:$AG$2,0)),Inputs!$B$4:$B$100,$B10)/1000) -> -35.369 | AA10: =IF(AA$3=0,"",SUMIFS(INDEX(Inputs!$D$4:$AG$100,0,MATCH(AA$2,Inputs!$D$2:$AG$2,0)),Inputs!$B$4:$B$100,$B10)/1000) -> -270.957 | AB10: =IF(COUNT(X10:AA10)=4,SUM(X10:AA10),"") -> -440.061 | AC10: =IF(AC$3=0,"",SUMIFS(INDEX(Inputs!$D$4:$AG$100,0,MATCH(AC$2,Inputs!$D$2:$AG$2,0)),Inputs!$B$4:$B$100,$B10)/1000) -> 83.453 | AD10: =IF(AD$3=0,"",SUMIFS(INDEX(Inputs!$D$4:$AG$100,0,MATCH(AD$2,Inputs!$D$2:$AG$2,0)),Inputs!$B$4:$B$100,$B10)/1000) -> -31.833 | AE10: =IF(AE$3=0,"",SUMIFS(INDEX(Inputs!$D$4:$AG$100,0,MATCH(AE$2,Inputs!$D$2:$AG$2,0)),Inputs!$B$4:$B$100,$B10)/1000) | AF10: =IF(AF$3=0,"",SUMIFS(INDEX(Inputs!$D$4:$AG$100,0,MATCH(AF$2,Inputs!$D$2:$AG$2,0)),Inputs!$B$4:$B$100,$B10)/1000) | AG10: =IF(COUNT(AC10:AF10)=4,SUM(AC10:AF10),"")
B11: 8 | C11: Equity in Income of Affiliates, after tax (enter as +) | D11: =IF(D$3=0,"",SUMIFS(INDEX(Inputs!$D$4:$AG$100,0,MATCH(D$2,Inputs!$D$2:$AG$2,0)),Inputs!$B$4:$B$100,$B11)/1000) -> 0 | E11: =IF(E$3=0,"",SUMIFS(INDEX(Inputs!$D$4:$AG$100,0,MATCH(E$2,Inputs!$D$2:$AG$2,0)),Inputs!$B$4:$B$100,$B11)/1000) -> 0 | F11: =IF(F$3=0,"",SUMIFS(INDEX(Inputs!$D$4:$AG$100,0,MATCH(F$2,Inputs!$D$2:$AG$2,0)),Inputs!$B$4:$B$100,$B11)/1000) -> 0 | G11: =IF(G$3=0,"",SUMIFS(INDEX(Inputs!$D$4:$AG$100,0,MATCH(G$2,Inputs!$D$2:$AG$2,0)),Inputs!$B$4:$B$100,$B11)/1000) -> 0 | H11: =IF(COUNT(D11:G11)=4,SUM(D11:G11),"") -> 0 | I11: =IF(I$3=0,"",SUMIFS(INDEX(Inputs!$D$4:$AG$100,0,MATCH(I$2,Inputs!$D$2:$AG$2,0)),Inputs!$B$4:$B$100,$B11)/1000) -> 29.051 | J11: =IF(J$3=0,"",SUMIFS(INDEX(Inputs!$D$4:$AG$100,0,MATCH(J$2,Inputs!$D$2:$AG$2,0)),Inputs!$B$4:$B$100,$B11)/1000) -> 54.94 | K11: =IF(K$3=0,"",SUMIFS(INDEX(Inputs!$D$4:$AG$100,0,MATCH(K$2,Inputs!$D$2:$AG$2,0)),Inputs!$B$4:$B$100,$B11)/1000) -> 52.3 | L11: =IF(L$3=0,"",SUMIFS(INDEX(Inputs!$D$4:$AG$100,0,MATCH(L$2,Inputs!$D$2:$AG$2,0)),Inputs!$B$4:$B$100,$B11)/1000) -> -5.632 | M11: =IF(COUNT(I11:L11)=4,SUM(I11:L11),"") -> 130.659 | N11: =IF(N$3=0,"",SUMIFS(INDEX(Inputs!$D$4:$AG$100,0,MATCH(N$2,Inputs!$D$2:$AG$2,0)),Inputs!$B$4:$B$100,$B11)/1000) -> 30.229 | O11: =IF(O$3=0,"",SUMIFS(INDEX(Inputs!$D$4:$AG$100,0,MATCH(O$2,Inputs!$D$2:$AG$2,0)),Inputs!$B$4:$B$100,$B11)/1000) -> -11.887 | P11: =IF(P$3=0,"",SUMIFS(INDEX(Inputs!$D$4:$AG$100,0,MATCH(P$2,Inputs!$D$2:$AG$2,0)),Inputs!$B$4:$B$100,$B11)/1000) -> 45.027 | Q11: =IF(Q$3=0,"",SUMIFS(INDEX(Inputs!$D$4:$AG$100,0,MATCH(Q$2,Inputs!$D$2:$AG$2,0)),Inputs!$B$4:$B$100,$B11)/1000) -> 9.943 | R11: =IF(COUNT(N11:Q11)=4,SUM(N11:Q11),"") -> 73.312 | S11: =IF(S$3=0,"",SUMIFS(INDEX(Inputs!$D$4:$AG$100,0,MATCH(S$2,Inputs!$D$2:$AG$2,0)),Inputs!$B$4:$B$100,$B11)/1000) -> 66.578 | T11: =IF(T$3=0,"",SUMIFS(INDEX(Inputs!$D$4:$AG$100,0,MATCH(T$2,Inputs!$D$2:$AG$2,0)),Inputs!$B$4:$B$100,$B11)/1000) -> 53.524 | U11: =IF(U$3=0,"",SUMIFS(INDEX(Inputs!$D$4:$AG$100,0,MATCH(U$2,Inputs!$D$2:$AG$2,0)),Inputs!$B$4:$B$100,$B11)/1000) -> 58.434 | V11: =IF(V$3=0,"",SUMIFS(INDEX(Inputs!$D$4:$AG$100,0,MATCH(V$2,Inputs!$D$2:$AG$2,0)),Inputs!$B$4:$B$100,$B11)/1000) -> -14.152 | W11: =IF(COUNT(S11:V11)=4,SUM(S11:V11),"") -> 164.384 | X11: =IF(X$3=0,"",SUMIFS(INDEX(Inputs!$D$4:$AG$100,0,MATCH(X$2,Inputs!$D$2:$AG$2,0)),Inputs!$B$4:$B$100,$B11)/1000) -> 72.147 | Y11: =IF(Y$3=0,"",SUMIFS(INDEX(Inputs!$D$4:$AG$100,0,MATCH(Y$2,Inputs!$D$2:$AG$2,0)),Inputs!$B$4:$B$100,$B11)/1000) -> 14.758 | Z11: =IF(Z$3=0,"",SUMIFS(INDEX(Inputs!$D$4:$AG$100,0,MATCH(Z$2,Inputs!$D$2:$AG$2,0)),Inputs!$B$4:$B$100,$B11)/1000) -> 58.193 | AA11: =IF(AA$3=0,"",SUMIFS(INDEX(Inputs!$D$4:$AG$100,0,MATCH(AA$2,Inputs!$D$2:$AG$2,0)),Inputs!$B$4:$B$100,$B11)/1000) -> 60.249 | AB11: =IF(COUNT(X11:AA11)=4,SUM(X11:AA11),"") -> 205.347 | AC11: =IF(AC$3=0,"",SUMIFS(INDEX(Inputs!$D$4:$AG$100,0,MATCH(AC$2,Inputs!$D$2:$AG$2,0)),Inputs!$B$4:$B$100,$B11)/1000) -> 71.487 | AD11: =IF(AD$3=0,"",SUMIFS(INDEX(Inputs!$D$4:$AG$100,0,MATCH(AD$2,Inputs!$D$2:$AG$2,0)),Inputs!$B$4:$B$100,$B11)/1000) -> 39.594 | AE11: =IF(AE$3=0,"",SUMIFS(INDEX(Inputs!$D$4:$AG$100,0,MATCH(AE$2,Inputs!$D$2:$AG$2,0)),Inputs!$B$4:$B$100,$B11)/1000) | AF11: =IF(AF$3=0,"",SUMIFS(INDEX(Inputs!$D$4:$AG$100,0,MATCH(AF$2,Inputs!$D$2:$AG$2,0)),Inputs!$B$4:$B$100,$B11)/1000) | AG11: =IF(COUNT(AC11:AF11)=4,SUM(AC11:AF11),"")
B12: 9 | C12: Minority Interest Expense, after tax (enter as - ) | D12: =IF(D$3=0,"",SUMIFS(INDEX(Inputs!$D$4:$AG$100,0,MATCH(D$2,Inputs!$D$2:$AG$2,0)),Inputs!$B$4:$B$100,$B12)/1000) -> -29.436 | E12: =IF(E$3=0,"",SUMIFS(INDEX(Inputs!$D$4:$AG$100,0,MATCH(E$2,Inputs!$D$2:$AG$2,0)),Inputs!$B$4:$B$100,$B12)/1000) -> 15.169 | F12: =IF(F$3=0,"",SUMIFS(INDEX(Inputs!$D$4:$AG$100,0,MATCH(F$2,Inputs!$D$2:$AG$2,0)),Inputs!$B$4:$B$100,$B12)/1000) -> -234.281 | G12: =IF(G$3=0,"",SUMIFS(INDEX(Inputs!$D$4:$AG$100,0,MATCH(G$2,Inputs!$D$2:$AG$2,0)),Inputs!$B$4:$B$100,$B12)/1000) -> 34.187 | H12: =IF(COUNT(D12:G12)=4,SUM(D12:G12),"") -> -214.361 | I12: =IF(I$3=0,"",SUMIFS(INDEX(Inputs!$D$4:$AG$100,0,MATCH(I$2,Inputs!$D$2:$AG$2,0)),Inputs!$B$4:$B$100,$B12)/1000) -> -4.214 | J12: =IF(J$3=0,"",SUMIFS(INDEX(Inputs!$D$4:$AG$100,0,MATCH(J$2,Inputs!$D$2:$AG$2,0)),Inputs!$B$4:$B$100,$B12)/1000) -> 0 | K12: =IF(K$3=0,"",SUMIFS(INDEX(Inputs!$D$4:$AG$100,0,MATCH(K$2,Inputs!$D$2:$AG$2,0)),Inputs!$B$4:$B$100,$B12)/1000) -> 0 | L12: =IF(L$3=0,"",SUMIFS(INDEX(Inputs!$D$4:$AG$100,0,MATCH(L$2,Inputs!$D$2:$AG$2,0)),Inputs!$B$4:$B$100,$B12)/1000) -> 0 | M12: =IF(COUNT(I12:L12)=4,SUM(I12:L12),"") -> -4.214 | N12: =IF(N$3=0,"",SUMIFS(INDEX(Inputs!$D$4:$AG$100,0,MATCH(N$2,Inputs!$D$2:$AG$2,0)),Inputs!$B$4:$B$100,$B12)/1000) -> 0 | O12: =IF(O$3=0,"",SUMIFS(INDEX(Inputs!$D$4:$AG$100,0,MATCH(O$2,Inputs!$D$2:$AG$2,0)),Inputs!$B$4:$B$100,$B12)/1000) -> 0 | P12: =IF(P$3=0,"",SUMIFS(INDEX(Inputs!$D$4:$AG$100,0,MATCH(P$2,Inputs!$D$2:$AG$2,0)),Inputs!$B$4:$B$100,$B12)/1000) -> 0 | Q12: =IF(Q$3=0,"",SUMIFS(INDEX(Inputs!$D$4:$AG$100,0,MATCH(Q$2,Inputs!$D$2:$AG$2,0)),Inputs!$B$4:$B$100,$B12)/1000) -> 0 | R12: =IF(COUNT(N12:Q12)=4,SUM(N12:Q12),"") -> 0 | S12: =IF(S$3=0,"",SUMIFS(INDEX(Inputs!$D$4:$AG$100,0,MATCH(S$2,Inputs!$D$2:$AG$2,0)),Inputs!$B$4:$B$100,$B12)/1000) -> 0 | T12: =IF(T$3=0,"",SUMIFS(INDEX(Inputs!$D$4:$AG$100,0,MATCH(T$2,Inputs!$D$2:$AG$2,0)),Inputs!$B$4:$B$100,$B12)/1000) -> 0 | U12: =IF(U$3=0,"",SUMIFS(INDEX(Inputs!$D$4:$AG$100,0,MATCH(U$2,Inputs!$D$2:$AG$2,0)),Inputs!$B$4:$B$100,$B12)/1000) -> 0 | V12: =IF(V$3=0,"",SUMIFS(INDEX(Inputs!$D$4:$AG$100,0,MATCH(V$2,Inputs!$D$2:$AG$2,0)),Inputs!$B$4:$B$100,$B12)/1000) -> -20.931 | W12: =IF(COUNT(S12:V12)=4,SUM(S12:V12),"") -> -20.931 | X12: =IF(X$3=0,"",SUMIFS(INDEX(Inputs!$D$4:$AG$100,0,MATCH(X$2,Inputs!$D$2:$AG$2,0)),Inputs!$B$4:$B$100,$B12)/1000) -> -45.501 | Y12: =IF(Y$3=0,"",SUMIFS(INDEX(Inputs!$D$4:$AG$100,0,MATCH(Y$2,Inputs!$D$2:$AG$2,0)),Inputs!$B$4:$B$100,$B12)/1000) -> -52.537 | Z12: =IF(Z$3=0,"",SUMIFS(INDEX(Inputs!$D$4:$AG$100,0,MATCH(Z$2,Inputs!$D$2:$AG$2,0)),Inputs!$B$4:$B$100,$B12)/1000) -> 6.661 | AA12: =IF(AA$3=0,"",SUMIFS(INDEX(Inputs!$D$4:$AG$100,0,MATCH(AA$2,Inputs!$D$2:$AG$2,0)),Inputs!$B$4:$B$100,$B12)/1000) -> -14.78 | AB12: =IF(COUNT(X12:AA12)=4,SUM(X12:AA12),"") -> -106.157 | AC12: =IF(AC$3=0,"",SUMIFS(INDEX(Inputs!$D$4:$AG$100,0,MATCH(AC$2,Inputs!$D$2:$AG$2,0)),Inputs!$B$4:$B$100,$B12)/1000) -> -19.732 | AD12: =IF(AD$3=0,"",SUMIFS(INDEX(Inputs!$D$4:$AG$100,0,MATCH(AD$2,Inputs!$D$2:$AG$2,0)),Inputs!$B$4:$B$100,$B12)/1000) -> -31.886 | AE12: =IF(AE$3=0,"",SUMIFS(INDEX(Inputs!$D$4:$AG$100,0,MATCH(AE$2,Inputs!$D$2:$AG$2,0)),Inputs!$B$4:$B$100,$B12)/1000) | AF12: =IF(AF$3=0,"",SUMIFS(INDEX(Inputs!$D$4:$AG$100,0,MATCH(AF$2,Inputs!$D$2:$AG$2,0)),Inputs!$B$4:$B$100,$B12)/1000) | AG12: =IF(COUNT(AC12:AF12)=4,SUM(AC12:AF12),"")
B13: 10 | C13: Common Dividends | D13: =IF(D$3=0,"",SUMIFS(INDEX(Inputs!$D$4:$AG$100,0,MATCH(D$2,Inputs!$D$2:$AG$2,0)),Inputs!$B$4:$B$100,$B13)/1000) -> -3.475 | E13: =IF(E$3=0,"",SUMIFS(INDEX(Inputs!$D$4:$AG$100,0,MATCH(E$2,Inputs!$D$2:$AG$2,0)),Inputs!$B$4:$B$100,$B13)/1000) -> -352.302 | F13: =IF(F$3=0,"",SUMIFS(INDEX(Inputs!$D$4:$AG$100,0,MATCH(F$2,Inputs!$D$2:$AG$2,0)),Inputs!$B$4:$B$100,$B13)/1000) -> -146.582 | G13: =IF(G$3=0,"",SUMIFS(INDEX(Inputs!$D$4:$AG$100,0,MATCH(G$2,Inputs!$D$2:$AG$2,0)),Inputs!$B$4:$B$100,$B13)/1000) -> -0.003 | H13: =IF(COUNT(D13:G13)=4,SUM(D13:G13),"") -> -502.362 | I13: =IF(I$3=0,"",SUMIFS(INDEX(Inputs!$D$4:$AG$100,0,MATCH(I$2,Inputs!$D$2:$AG$2,0)),Inputs!$B$4:$B$100,$B13)/1000) -> 0 | J13: =IF(J$3=0,"",SUMIFS(INDEX(Inputs!$D$4:$AG$100,0,MATCH(J$2,Inputs!$D$2:$AG$2,0)),Inputs!$B$4:$B$100,$B13)/1000) -> -99.991 | K13: =IF(K$3=0,"",SUMIFS(INDEX(Inputs!$D$4:$AG$100,0,MATCH(K$2,Inputs!$D$2:$AG$2,0)),Inputs!$B$4:$B$100,$B13)/1000) -> 0 | L13: =IF(L$3=0,"",SUMIFS(INDEX(Inputs!$D$4:$AG$100,0,MATCH(L$2,Inputs!$D$2:$AG$2,0)),Inputs!$B$4:$B$100,$B13)/1000) -> -0.003 | M13: =IF(COUNT(I13:L13)=4,SUM(I13:L13),"") -> -99.994 | N13: =IF(N$3=0,"",SUMIFS(INDEX(Inputs!$D$4:$AG$100,0,MATCH(N$2,Inputs!$D$2:$AG$2,0)),Inputs!$B$4:$B$100,$B13)/1000) -> 0 | O13: =IF(O$3=0,"",SUMIFS(INDEX(Inputs!$D$4:$AG$100,0,MATCH(O$2,Inputs!$D$2:$AG$2,0)),Inputs!$B$4:$B$100,$B13)/1000) -> -1499.809 | P13: =IF(P$3=0,"",SUMIFS(INDEX(Inputs!$D$4:$AG$100,0,MATCH(P$2,Inputs!$D$2:$AG$2,0)),Inputs!$B$4:$B$100,$B13)/1000) -> 0 | Q13: =IF(Q$3=0,"",SUMIFS(INDEX(Inputs!$D$4:$AG$100,0,MATCH(Q$2,Inputs!$D$2:$AG$2,0)),Inputs!$B$4:$B$100,$B13)/1000) -> -1499.817 | R13: =IF(COUNT(N13:Q13)=4,SUM(N13:Q13),"") -> -2999.626 | S13: =IF(S$3=0,"",SUMIFS(INDEX(Inputs!$D$4:$AG$100,0,MATCH(S$2,Inputs!$D$2:$AG$2,0)),Inputs!$B$4:$B$100,$B13)/1000) -> -399.948 | T13: =IF(T$3=0,"",SUMIFS(INDEX(Inputs!$D$4:$AG$100,0,MATCH(T$2,Inputs!$D$2:$AG$2,0)),Inputs!$B$4:$B$100,$B13)/1000) -> -0.001 | U13: =IF(U$3=0,"",SUMIFS(INDEX(Inputs!$D$4:$AG$100,0,MATCH(U$2,Inputs!$D$2:$AG$2,0)),Inputs!$B$4:$B$100,$B13)/1000) -> -0.001 | V13: =IF(V$3=0,"",SUMIFS(INDEX(Inputs!$D$4:$AG$100,0,MATCH(V$2,Inputs!$D$2:$AG$2,0)),Inputs!$B$4:$B$100,$B13)/1000) -> 0 | W13: =IF(COUNT(S13:V13)=4,SUM(S13:V13),"") -> -399.95 | X13: =IF(X$3=0,"",SUMIFS(INDEX(Inputs!$D$4:$AG$100,0,MATCH(X$2,Inputs!$D$2:$AG$2,0)),Inputs!$B$4:$B$100,$B13)/1000) -> -99.648 | Y13: =IF(Y$3=0,"",SUMIFS(INDEX(Inputs!$D$4:$AG$100,0,MATCH(Y$2,Inputs!$D$2:$AG$2,0)),Inputs!$B$4:$B$100,$B13)/1000) -> -61.408 | Z13: =IF(Z$3=0,"",SUMIFS(INDEX(Inputs!$D$4:$AG$100,0,MATCH(Z$2,Inputs!$D$2:$AG$2,0)),Inputs!$B$4:$B$100,$B13)/1000) -> -89.327 | AA13: =IF(AA$3=0,"",SUMIFS(INDEX(Inputs!$D$4:$AG$100,0,MATCH(AA$2,Inputs!$D$2:$AG$2,0)),Inputs!$B$4:$B$100,$B13)/1000) -> 8.548 | AB13: =IF(COUNT(X13:AA13)=4,SUM(X13:AA13),"") -> -241.835 | AC13: =IF(AC$3=0,"",SUMIFS(INDEX(Inputs!$D$4:$AG$100,0,MATCH(AC$2,Inputs!$D$2:$AG$2,0)),Inputs!$B$4:$B$100,$B13)/1000) -> -42.966 | AD13: =IF(AD$3=0,"",SUMIFS(INDEX(Inputs!$D$4:$AG$100,0,MATCH(AD$2,Inputs!$D$2:$AG$2,0)),Inputs!$B$4:$B$100,$B13)/1000) -> 0.148 | AE13: =IF(AE$3=0,"",SUMIFS(INDEX(Inputs!$D$4:$AG$100,0,MATCH(AE$2,Inputs!$D$2:$AG$2,0)),Inputs!$B$4:$B$100,$B13)/1000) | AF13: =IF(AF$3=0,"",SUMIFS(INDEX(Inputs!$D$4:$AG$100,0,MATCH(AF$2,Inputs!$D$2:$AG$2,0)),Inputs!$B$4:$B$100,$B13)/1000) | AG13: =IF(COUNT(AC13:AF13)=4,SUM(AC13:AF13),"")
B15: 11 | C15: Cash and equivalents (inc. investment securities) | D15: =IF(D$3=0,"",SUMIFS(INDEX(Inputs!$D$4:$AG$100,0,MATCH(D$2,Inputs!$D$2:$AG$2,0)),Inputs!$B$4:$B$100,$B15)/1000) -> 1292.369 | E15: =IF(E$3=0,"",SUMIFS(INDEX(Inputs!$D$4:$AG$100,0,MATCH(E$2,Inputs!$D$2:$AG$2,0)),Inputs!$B$4:$B$100,$B15)/1000) -> 1189.841 | F15: =IF(F$3=0,"",SUMIFS(INDEX(Inputs!$D$4:$AG$100,0,MATCH(F$2,Inputs!$D$2:$AG$2,0)),Inputs!$B$4:$B$100,$B15)/1000) -> 1376.313 | G15: =IF(G$3=0,"",SUMIFS(INDEX(Inputs!$D$4:$AG$100,0,MATCH(G$2,Inputs!$D$2:$AG$2,0)),Inputs!$B$4:$B$100,$B15)/1000) -> 1673.569 | H15: =IF(G15="","",G15) -> 1673.569 | I15: =IF(I$3=0,"",SUMIFS(INDEX(Inputs!$D$4:$AG$100,0,MATCH(I$2,Inputs!$D$2:$AG$2,0)),Inputs!$B$4:$B$100,$B15)/1000) -> 3173.847 | J15: =IF(J$3=0,"",SUMIFS(INDEX(Inputs!$D$4:$AG$100,0,MATCH(J$2,Inputs!$D$2:$AG$2,0)),Inputs!$B$4:$B$100,$B15)/1000) -> 3353.966 | K15: =IF(K$3=0,"",SUMIFS(INDEX(Inputs!$D$4:$AG$100,0,MATCH(K$2,Inputs!$D$2:$AG$2,0)),Inputs!$B$4:$B$100,$B15)/1000) -> 2983.696 | L15: =IF(L$3=0,"",SUMIFS(INDEX(Inputs!$D$4:$AG$100,0,MATCH(L$2,Inputs!$D$2:$AG$2,0)),Inputs!$B$4:$B$100,$B15)/1000) -> 3231.306 | M15: =IF(L15="","",L15) -> 3231.306 | N15: =IF(N$3=0,"",SUMIFS(INDEX(Inputs!$D$4:$AG$100,0,MATCH(N$2,Inputs!$D$2:$AG$2,0)),Inputs!$B$4:$B$100,$B15)/1000) -> 3402.667 | O15: =IF(O$3=0,"",SUMIFS(INDEX(Inputs!$D$4:$AG$100,0,MATCH(O$2,Inputs!$D$2:$AG$2,0)),Inputs!$B$4:$B$100,$B15)/1000) -> 6285.342 | P15: =IF(P$3=0,"",SUMIFS(INDEX(Inputs!$D$4:$AG$100,0,MATCH(P$2,Inputs!$D$2:$AG$2,0)),Inputs!$B$4:$B$100,$B15)/1000) -> 4904.741 | Q15: =IF(Q$3=0,"",SUMIFS(INDEX(Inputs!$D$4:$AG$100,0,MATCH(Q$2,Inputs!$D$2:$AG$2,0)),Inputs!$B$4:$B$100,$B15)/1000) -> 3238.394 | R15: =IF(Q15="","",Q15) -> 3238.394 | S15: =IF(S$3=0,"",SUMIFS(INDEX(Inputs!$D$4:$AG$100,0,MATCH(S$2,Inputs!$D$2:$AG$2,0)),Inputs!$B$4:$B$100,$B15)/1000) -> 3094.615 | T15: =IF(T$3=0,"",SUMIFS(INDEX(Inputs!$D$4:$AG$100,0,MATCH(T$2,Inputs!$D$2:$AG$2,0)),Inputs!$B$4:$B$100,$B15)/1000) -> 4992.046 | U15: =IF(U$3=0,"",SUMIFS(INDEX(Inputs!$D$4:$AG$100,0,MATCH(U$2,Inputs!$D$2:$AG$2,0)),Inputs!$B$4:$B$100,$B15)/1000) -> 5295.721 | V15: =IF(V$3=0,"",SUMIFS(INDEX(Inputs!$D$4:$AG$100,0,MATCH(V$2,Inputs!$D$2:$AG$2,0)),Inputs!$B$4:$B$100,$B15)/1000) -> 7203.178 | W15: =IF(V15="","",V15) -> 7203.178 | X15: =IF(X$3=0,"",SUMIFS(INDEX(Inputs!$D$4:$AG$100,0,MATCH(X$2,Inputs!$D$2:$AG$2,0)),Inputs!$B$4:$B$100,$B15)/1000) -> 6162.476 | Y15: =IF(Y$3=0,"",SUMIFS(INDEX(Inputs!$D$4:$AG$100,0,MATCH(Y$2,Inputs!$D$2:$AG$2,0)),Inputs!$B$4:$B$100,$B15)/1000) -> 4933.168 | Z15: =IF(Z$3=0,"",SUMIFS(INDEX(Inputs!$D$4:$AG$100,0,MATCH(Z$2,Inputs!$D$2:$AG$2,0)),Inputs!$B$4:$B$100,$B15)/1000) -> 5075.682 | AA15: =IF(AA$3=0,"",SUMIFS(INDEX(Inputs!$D$4:$AG$100,0,MATCH(AA$2,Inputs!$D$2:$AG$2,0)),Inputs!$B$4:$B$100,$B15)/1000) -> 4382.422 | AB15: =IF(AA15="","",AA15) -> 4382.422 | AC15: =IF(AC$3=0,"",SUMIFS(INDEX(Inputs!$D$4:$AG$100,0,MATCH(AC$2,Inputs!$D$2:$AG$2,0)),Inputs!$B$4:$B$100,$B15)/1000) -> 3571.882 | AD15: =IF(AD$3=0,"",SUMIFS(INDEX(Inputs!$D$4:$AG$100,0,MATCH(AD$2,Inputs!$D$2:$AG$2,0)),Inputs!$B$4:$B$100,$B15)/1000) -> 3638.808 | AE15: =IF(AE$3=0,"",SUMIFS(INDEX(Inputs!$D$4:$AG$100,0,MATCH(AE$2,Inputs!$D$2:$AG$2,0)),Inputs!$B$4:$B$100,$B15)/1000) | AF15: =IF(AF$3=0,"",SUMIFS(INDEX(Inputs!$D$4:$AG$100,0,MATCH(AF$2,Inputs!$D$2:$AG$2,0)),Inputs!$B$4:$B$100,$B15)/1000) | AG15: =IF(AF15="","",AF15)
B16: 12 | C16: Accounts receivable | D16: =IF(D$3=0,"",SUMIFS(INDEX(Inputs!$D$4:$AG$100,0,MATCH(D$2,Inputs!$D$2:$AG$2,0)),Inputs!$B$4:$B$100,$B16)/1000) -> 382.854 | E16: =IF(E$3=0,"",SUMIFS(INDEX(Inputs!$D$4:$AG$100,0,MATCH(E$2,Inputs!$D$2:$AG$2,0)),Inputs!$B$4:$B$100,$B16)/1000) -> 325.707 | F16: =IF(F$3=0,"",SUMIFS(INDEX(Inputs!$D$4:$AG$100,0,MATCH(F$2,Inputs!$D$2:$AG$2,0)),Inputs!$B$4:$B$100,$B16)/1000) -> 330.258 | G16: =IF(G$3=0,"",SUMIFS(INDEX(Inputs!$D$4:$AG$100,0,MATCH(G$2,Inputs!$D$2:$AG$2,0)),Inputs!$B$4:$B$100,$B16)/1000) -> 328.631 | H16: =IF(G16="","",G16) -> 328.631 | I16: =IF(I$3=0,"",SUMIFS(INDEX(Inputs!$D$4:$AG$100,0,MATCH(I$2,Inputs!$D$2:$AG$2,0)),Inputs!$B$4:$B$100,$B16)/1000) -> 556.035 | J16: =IF(J$3=0,"",SUMIFS(INDEX(Inputs!$D$4:$AG$100,0,MATCH(J$2,Inputs!$D$2:$AG$2,0)),Inputs!$B$4:$B$100,$B16)/1000) -> 549.634 | K16: =IF(K$3=0,"",SUMIFS(INDEX(Inputs!$D$4:$AG$100,0,MATCH(K$2,Inputs!$D$2:$AG$2,0)),Inputs!$B$4:$B$100,$B16)/1000) -> 625.916 | L16: =IF(L$3=0,"",SUMIFS(INDEX(Inputs!$D$4:$AG$100,0,MATCH(L$2,Inputs!$D$2:$AG$2,0)),Inputs!$B$4:$B$100,$B16)/1000) -> 617.86 | M16: =IF(L16="","",L16) -> 617.86 | N16: =IF(N$3=0,"",SUMIFS(INDEX(Inputs!$D$4:$AG$100,0,MATCH(N$2,Inputs!$D$2:$AG$2,0)),Inputs!$B$4:$B$100,$B16)/1000) -> 577.274 | O16: =IF(O$3=0,"",SUMIFS(INDEX(Inputs!$D$4:$AG$100,0,MATCH(O$2,Inputs!$D$2:$AG$2,0)),Inputs!$B$4:$B$100,$B16)/1000) -> 569.731 | P16: =IF(P$3=0,"",SUMIFS(INDEX(Inputs!$D$4:$AG$100,0,MATCH(P$2,Inputs!$D$2:$AG$2,0)),Inputs!$B$4:$B$100,$B16)/1000) -> 656.783 | Q16: =IF(Q$3=0,"",SUMIFS(INDEX(Inputs!$D$4:$AG$100,0,MATCH(Q$2,Inputs!$D$2:$AG$2,0)),Inputs!$B$4:$B$100,$B16)/1000) -> 679.476 | R16: =IF(Q16="","",Q16) -> 679.476 | S16: =IF(S$3=0,"",SUMIFS(INDEX(Inputs!$D$4:$AG$100,0,MATCH(S$2,Inputs!$D$2:$AG$2,0)),Inputs!$B$4:$B$100,$B16)/1000) -> 569.252 | T16: =IF(T$3=0,"",SUMIFS(INDEX(Inputs!$D$4:$AG$100,0,MATCH(T$2,Inputs!$D$2:$AG$2,0)),Inputs!$B$4:$B$100,$B16)/1000) -> 575.06 | U16: =IF(U$3=0,"",SUMIFS(INDEX(Inputs!$D$4:$AG$100,0,MATCH(U$2,Inputs!$D$2:$AG$2,0)),Inputs!$B$4:$B$100,$B16)/1000) -> 919.196 | V16: =IF(V$3=0,"",SUMIFS(INDEX(Inputs!$D$4:$AG$100,0,MATCH(V$2,Inputs!$D$2:$AG$2,0)),Inputs!$B$4:$B$100,$B16)/1000) -> 1492.867 | W16: =IF(V16="","",V16) -> 1492.867 | X16: =IF(X$3=0,"",SUMIFS(INDEX(Inputs!$D$4:$AG$100,0,MATCH(X$2,Inputs!$D$2:$AG$2,0)),Inputs!$B$4:$B$100,$B16)/1000) -> 1404.559 | Y16: =IF(Y$3=0,"",SUMIFS(INDEX(Inputs!$D$4:$AG$100,0,MATCH(Y$2,Inputs!$D$2:$AG$2,0)),Inputs!$B$4:$B$100,$B16)/1000) -> 1229.784 | Z16: =IF(Z$3=0,"",SUMIFS(INDEX(Inputs!$D$4:$AG$100,0,MATCH(Z$2,Inputs!$D$2:$AG$2,0)),Inputs!$B$4:$B$100,$B16)/1000) -> 1543.172 | AA16: =IF(AA$3=0,"",SUMIFS(INDEX(Inputs!$D$4:$AG$100,0,MATCH(AA$2,Inputs!$D$2:$AG$2,0)),Inputs!$B$4:$B$100,$B16)/1000) -> 1712.414 | AB16: =IF(AA16="","",AA16) -> 1712.414 | AC16: =IF(AC$3=0,"",SUMIFS(INDEX(Inputs!$D$4:$AG$100,0,MATCH(AC$2,Inputs!$D$2:$AG$2,0)),Inputs!$B$4:$B$100,$B16)/1000) -> 1637.335 | AD16: =IF(AD$3=0,"",SUMIFS(INDEX(Inputs!$D$4:$AG$100,0,MATCH(AD$2,Inputs!$D$2:$AG$2,0)),Inputs!$B$4:$B$100,$B16)/1000) -> 1408.699 | AE16: =IF(AE$3=0,"",SUMIFS(INDEX(Inputs!$D$4:$AG$100,0,MATCH(AE$2,Inputs!$D$2:$AG$2,0)),Inputs!$B$4:$B$100,$B16)/1000) | AF16: =IF(AF$3=0,"",SUMIFS(INDEX(Inputs!$D$4:$AG$100,0,MATCH(AF$2,Inputs!$D$2:$AG$2,0)),Inputs!$B$4:$B$100,$B16)/1000) | AG16: =IF(AF16="","",AF16)
B17: 13 | C17: Inventories | D17: =IF(D$3=0,"",SUMIFS(INDEX(Inputs!$D$4:$AG$100,0,MATCH(D$2,Inputs!$D$2:$AG$2,0)),Inputs!$B$4:$B$100,$B17)/1000) -> 0 | E17: =IF(E$3=0,"",SUMIFS(INDEX(Inputs!$D$4:$AG$100,0,MATCH(E$2,Inputs!$D$2:$AG$2,0)),Inputs!$B$4:$B$100,$B17)/1000) -> 0 | F17: =IF(F$3=0,"",SUMIFS(INDEX(Inputs!$D$4:$AG$100,0,MATCH(F$2,Inputs!$D$2:$AG$2,0)),Inputs!$B$4:$B$100,$B17)/1000) -> 0 | G17: =IF(G$3=0,"",SUMIFS(INDEX(Inputs!$D$4:$AG$100,0,MATCH(G$2,Inputs!$D$2:$AG$2,0)),Inputs!$B$4:$B$100,$B17)/1000) -> 0 | H17: =IF(G17="","",G17) -> 0 | I17: =IF(I$3=0,"",SUMIFS(INDEX(Inputs!$D$4:$AG$100,0,MATCH(I$2,Inputs!$D$2:$AG$2,0)),Inputs!$B$4:$B$100,$B17)/1000) -> 0 | J17: =IF(J$3=0,"",SUMIFS(INDEX(Inputs!$D$4:$AG$100,0,MATCH(J$2,Inputs!$D$2:$AG$2,0)),Inputs!$B$4:$B$100,$B17)/1000) -> 0 | K17: =IF(K$3=0,"",SUMIFS(INDEX(Inputs!$D$4:$AG$100,0,MATCH(K$2,Inputs!$D$2:$AG$2,0)),Inputs!$B$4:$B$100,$B17)/1000) -> 0 | L17: =IF(L$3=0,"",SUMIFS(INDEX(Inputs!$D$4:$AG$100,0,MATCH(L$2,Inputs!$D$2:$AG$2,0)),Inputs!$B$4:$B$100,$B17)/1000) -> 0 | M17: =IF(L17="","",L17) -> 0 | N17: =IF(N$3=0,"",SUMIFS(INDEX(Inputs!$D$4:$AG$100,0,MATCH(N$2,Inputs!$D$2:$AG$2,0)),Inputs!$B$4:$B$100,$B17)/1000) -> 0 | O17: =IF(O$3=0,"",SUMIFS(INDEX(Inputs!$D$4:$AG$100,0,MATCH(O$2,Inputs!$D$2:$AG$2,0)),Inputs!$B$4:$B$100,$B17)/1000) -> 0 | P17: =IF(P$3=0,"",SUMIFS(INDEX(Inputs!$D$4:$AG$100,0,MATCH(P$2,Inputs!$D$2:$AG$2,0)),Inputs!$B$4:$B$100,$B17)/1000) -> 0 | Q17: =IF(Q$3=0,"",SUMIFS(INDEX(Inputs!$D$4:$AG$100,0,MATCH(Q$2,Inputs!$D$2:$AG$2,0)),Inputs!$B$4:$B$100,$B17)/1000) -> 0 | R17: =IF(Q17="","",Q17) -> 0 | S17: =IF(S$3=0,"",SUMIFS(INDEX(Inputs!$D$4:$AG$100,0,MATCH(S$2,Inputs!$D$2:$AG$2,0)),Inputs!$B$4:$B$100,$B17)/1000) -> 0 | T17: =IF(T$3=0,"",SUMIFS(INDEX(Inputs!$D$4:$AG$100,0,MATCH(T$2,Inputs!$D$2:$AG$2,0)),Inputs!$B$4:$B$100,$B17)/1000) -> 0 | U17: =IF(U$3=0,"",SUMIFS(INDEX(Inputs!$D$4:$AG$100,0,MATCH(U$2,Inputs!$D$2:$AG$2,0)),Inputs!$B$4:$B$100,$B17)/1000) -> 0 | V17: =IF(V$3=0,"",SUMIFS(INDEX(Inputs!$D$4:$AG$100,0,MATCH(V$2,Inputs!$D$2:$AG$2,0)),Inputs!$B$4:$B$100,$B17)/1000) -> 0 | W17: =IF(V17="","",V17) -> 0 | X17: =IF(X$3=0,"",SUMIFS(INDEX(Inputs!$D$4:$AG$100,0,MATCH(X$2,Inputs!$D$2:$AG$2,0)),Inputs!$B$4:$B$100,$B17)/1000) -> 0 | Y17: =IF(Y$3=0,"",SUMIFS(INDEX(Inputs!$D$4:$AG$100,0,MATCH(Y$2,Inputs!$D$2:$AG$2,0)),Inputs!$B$4:$B$100,$B17)/1000) -> 0 | Z17: =IF(Z$3=0,"",SUMIFS(INDEX(Inputs!$D$4:$AG$100,0,MATCH(Z$2,Inputs!$D$2:$AG$2,0)),Inputs!$B$4:$B$100,$B17)/1000) -> 0 | AA17: =IF(AA$3=0,"",SUMIFS(INDEX(Inputs!$D$4:$AG$100,0,MATCH(AA$2,Inputs!$D$2:$AG$2,0)),Inputs!$B$4:$B$100,$B17)/1000) -> 0 | AB17: =IF(AA17="","",AA17) -> 0 | AC17: =IF(AC$3=0,"",SUMIFS(INDEX(Inputs!$D$4:$AG$100,0,MATCH(AC$2,Inputs!$D$2:$AG$2,0)),Inputs!$B$4:$B$100,$B17)/1000) -> 0 | AD17: =IF(AD$3=0,"",SUMIFS(INDEX(Inputs!$D$4:$AG$100,0,MATCH(AD$2,Inputs!$D$2:$AG$2,0)),Inputs!$B$4:$B$100,$B17)/1000) -> 0 | AE17: =IF(AE$3=0,"",SUMIFS(INDEX(Inputs!$D$4:$AG$100,0,MATCH(AE$2,Inputs!$D$2:$AG$2,0)),Inputs!$B$4:$B$100,$B17)/1000) | AF17: =IF(AF$3=0,"",SUMIFS(INDEX(Inputs!$D$4:$AG$100,0,MATCH(AF$2,Inputs!$D$2:$AG$2,0)),Inputs!$B$4:$B$100,$B17)/1000) | AG17: =IF(AF17="","",AF17)
B18: 14 | C18: Deferred income taxes | D18: =IF(D$3=0,"",SUMIFS(INDEX(Inputs!$D$4:$AG$100,0,MATCH(D$2,Inputs!$D$2:$AG$2,0)),Inputs!$B$4:$B$100,$B18)/1000) -> 3908.905 | E18: =IF(E$3=0,"",SUMIFS(INDEX(Inputs!$D$4:$AG$100,0,MATCH(E$2,Inputs!$D$2:$AG$2,0)),Inputs!$B$4:$B$100,$B18)/1000) -> 3908.192 | F18: =IF(F$3=0,"",SUMIFS(INDEX(Inputs!$D$4:$AG$100,0,MATCH(F$2,Inputs!$D$2:$AG$2,0)),Inputs!$B$4:$B$100,$B18)/1000) -> 3444.995 | G18: =IF(G$3=0,"",SUMIFS(INDEX(Inputs!$D$4:$AG$100,0,MATCH(G$2,Inputs!$D$2:$AG$2,0)),Inputs!$B$4:$B$100,$B18)/1000) -> 3408.893 | H18: =IF(G18="","",G18) -> 3408.893 | I18: =IF(I$3=0,"",SUMIFS(INDEX(Inputs!$D$4:$AG$100,0,MATCH(I$2,Inputs!$D$2:$AG$2,0)),Inputs!$B$4:$B$100,$B18)/1000) -> 3416.808 | J18: =IF(J$3=0,"",SUMIFS(INDEX(Inputs!$D$4:$AG$100,0,MATCH(J$2,Inputs!$D$2:$AG$2,0)),Inputs!$B$4:$B$100,$B18)/1000) -> 3430.877 | K18: =IF(K$3=0,"",SUMIFS(INDEX(Inputs!$D$4:$AG$100,0,MATCH(K$2,Inputs!$D$2:$AG$2,0)),Inputs!$B$4:$B$100,$B18)/1000) -> 3370.826 | L18: =IF(L$3=0,"",SUMIFS(INDEX(Inputs!$D$4:$AG$100,0,MATCH(L$2,Inputs!$D$2:$AG$2,0)),Inputs!$B$4:$B$100,$B18)/1000) -> 3000.824 | M18: =IF(L18="","",L18) -> 3000.824 | N18: =IF(N$3=0,"",SUMIFS(INDEX(Inputs!$D$4:$AG$100,0,MATCH(N$2,Inputs!$D$2:$AG$2,0)),Inputs!$B$4:$B$100,$B18)/1000) -> 2992.037 | O18: =IF(O$3=0,"",SUMIFS(INDEX(Inputs!$D$4:$AG$100,0,MATCH(O$2,Inputs!$D$2:$AG$2,0)),Inputs!$B$4:$B$100,$B18)/1000) -> 2922.766 | P18: =IF(P$3=0,"",SUMIFS(INDEX(Inputs!$D$4:$AG$100,0,MATCH(P$2,Inputs!$D$2:$AG$2,0)),Inputs!$B$4:$B$100,$B18)/1000) -> 2601.196 | Q18: =IF(Q$3=0,"",SUMIFS(INDEX(Inputs!$D$4:$AG$100,0,MATCH(Q$2,Inputs!$D$2:$AG$2,0)),Inputs!$B$4:$B$100,$B18)/1000) -> 2698.782 | R18: =IF(Q18="","",Q18) -> 2698.782 | S18: =IF(S$3=0,"",SUMIFS(INDEX(Inputs!$D$4:$AG$100,0,MATCH(S$2,Inputs!$D$2:$AG$2,0)),Inputs!$B$4:$B$100,$B18)/1000) -> 2697.332 | T18: =IF(T$3=0,"",SUMIFS(INDEX(Inputs!$D$4:$AG$100,0,MATCH(T$2,Inputs!$D$2:$AG$2,0)),Inputs!$B$4:$B$100,$B18)/1000) -> 2660.554 | U18: =IF(U$3=0,"",SUMIFS(INDEX(Inputs!$D$4:$AG$100,0,MATCH(U$2,Inputs!$D$2:$AG$2,0)),Inputs!$B$4:$B$100,$B18)/1000) -> 2642.872 | V18: =IF(V$3=0,"",SUMIFS(INDEX(Inputs!$D$4:$AG$100,0,MATCH(V$2,Inputs!$D$2:$AG$2,0)),Inputs!$B$4:$B$100,$B18)/1000) -> 2172.103 | W18: =IF(V18="","",V18) -> 2172.103 | X18: =IF(X$3=0,"",SUMIFS(INDEX(Inputs!$D$4:$AG$100,0,MATCH(X$2,Inputs!$D$2:$AG$2,0)),Inputs!$B$4:$B$100,$B18)/1000) -> 2129.196 | Y18: =IF(Y$3=0,"",SUMIFS(INDEX(Inputs!$D$4:$AG$100,0,MATCH(Y$2,Inputs!$D$2:$AG$2,0)),Inputs!$B$4:$B$100,$B18)/1000) -> 1964.087 | Z18: =IF(Z$3=0,"",SUMIFS(INDEX(Inputs!$D$4:$AG$100,0,MATCH(Z$2,Inputs!$D$2:$AG$2,0)),Inputs!$B$4:$B$100,$B18)/1000) -> 1995.197 | AA18: =IF(AA$3=0,"",SUMIFS(INDEX(Inputs!$D$4:$AG$100,0,MATCH(AA$2,Inputs!$D$2:$AG$2,0)),Inputs!$B$4:$B$100,$B18)/1000) -> 1942.725 | AB18: =IF(AA18="","",AA18) -> 1942.725 | AC18: =IF(AC$3=0,"",SUMIFS(INDEX(Inputs!$D$4:$AG$100,0,MATCH(AC$2,Inputs!$D$2:$AG$2,0)),Inputs!$B$4:$B$100,$B18)/1000) -> 1956.126 | AD18: =IF(AD$3=0,"",SUMIFS(INDEX(Inputs!$D$4:$AG$100,0,MATCH(AD$2,Inputs!$D$2:$AG$2,0)),Inputs!$B$4:$B$100,$B18)/1000) -> 1997.881 | AE18: =IF(AE$3=0,"",SUMIFS(INDEX(Inputs!$D$4:$AG$100,0,MATCH(AE$2,Inputs!$D$2:$AG$2,0)),Inputs!$B$4:$B$100,$B18)/1000) | AF18: =IF(AF$3=0,"",SUMIFS(INDEX(Inputs!$D$4:$AG$100,0,MATCH(AF$2,Inputs!$D$2:$AG$2,0)),Inputs!$B$4:$B$100,$B18)/1000) | AG18: =IF(AF18="","",AF18)
B19: 15 | C19: Prepaid expenses | D19: =IF(D$3=0,"",SUMIFS(INDEX(Inputs!$D$4:$AG$100,0,MATCH(D$2,Inputs!$D$2:$AG$2,0)),Inputs!$B$4:$B$100,$B19)/1000) -> 0 | E19: =IF(E$3=0,"",SUMIFS(INDEX(Inputs!$D$4:$AG$100,0,MATCH(E$2,Inputs!$D$2:$AG$2,0)),Inputs!$B$4:$B$100,$B19)/1000) -> 0 | F19: =IF(F$3=0,"",SUMIFS(INDEX(Inputs!$D$4:$AG$100,0,MATCH(F$2,Inputs!$D$2:$AG$2,0)),Inputs!$B$4:$B$100,$B19)/1000) -> 0 | G19: =IF(G$3=0,"",SUMIFS(INDEX(Inputs!$D$4:$AG$100,0,MATCH(G$2,Inputs!$D$2:$AG$2,0)),Inputs!$B$4:$B$100,$B19)/1000) -> 0 | H19: =IF(G19="","",G19) -> 0 | I19: =IF(I$3=0,"",SUMIFS(INDEX(Inputs!$D$4:$AG$100,0,MATCH(I$2,Inputs!$D$2:$AG$2,0)),Inputs!$B$4:$B$100,$B19)/1000) -> 0 | J19: =IF(J$3=0,"",SUMIFS(INDEX(Inputs!$D$4:$AG$100,0,MATCH(J$2,Inputs!$D$2:$AG$2,0)),Inputs!$B$4:$B$100,$B19)/1000) -> 0 | K19: =IF(K$3=0,"",SUMIFS(INDEX(Inputs!$D$4:$AG$100,0,MATCH(K$2,Inputs!$D$2:$AG$2,0)),Inputs!$B$4:$B$100,$B19)/1000) -> 0 | L19: =IF(L$3=0,"",SUMIFS(INDEX(Inputs!$D$4:$AG$100,0,MATCH(L$2,Inputs!$D$2:$AG$2,0)),Inputs!$B$4:$B$100,$B19)/1000) -> 0 | M19: =IF(L19="","",L19) -> 0 | N19: =IF(N$3=0,"",SUMIFS(INDEX(Inputs!$D$4:$AG$100,0,MATCH(N$2,Inputs!$D$2:$AG$2,0)),Inputs!$B$4:$B$100,$B19)/1000) -> 0 | O19: =IF(O$3=0,"",SUMIFS(INDEX(Inputs!$D$4:$AG$100,0,MATCH(O$2,Inputs!$D$2:$AG$2,0)),Inputs!$B$4:$B$100,$B19)/1000) -> 0 | P19: =IF(P$3=0,"",SUMIFS(INDEX(Inputs!$D$4:$AG$100,0,MATCH(P$2,Inputs!$D$2:$AG$2,0)),Inputs!$B$4:$B$100,$B19)/1000) -> 0 | Q19: =IF(Q$3=0,"",SUMIFS(INDEX(Inputs!$D$4:$AG$100,0,MATCH(Q$2,Inputs!$D$2:$AG$2,0)),Inputs!$B$4:$B$100,$B19)/1000) -> 0 | R19: =IF(Q19="","",Q19) -> 0 | S19: =IF(S$3=0,"",SUMIFS(INDEX(Inputs!$D$4:$AG$100,0,MATCH(S$2,Inputs!$D$2:$AG$2,0)),Inputs!$B$4:$B$100,$B19)/1000) -> 0 | T19: =IF(T$3=0,"",SUMIFS(INDEX(Inputs!$D$4:$AG$100,0,MATCH(T$2,Inputs!$D$2:$AG$2,0)),Inputs!$B$4:$B$100,$B19)/1000) -> 0 | U19: =IF(U$3=0,"",SUMIFS(INDEX(Inputs!$D$4:$AG$100,0,MATCH(U$2,Inputs!$D$2:$AG$2,0)),Inputs!$B$4:$B$100,$B19)/1000) -> 0 | V19: =IF(V$3=0,"",SUMIFS(INDEX(Inputs!$D$4:$AG$100,0,MATCH(V$2,Inputs!$D$2:$AG$2,0)),Inputs!$B$4:$B$100,$B19)/1000) -> 0 | W19: =IF(V19="","",V19) -> 0 | X19: =IF(X$3=0,"",SUMIFS(INDEX(Inputs!$D$4:$AG$100,0,MATCH(X$2,Inputs!$D$2:$AG$2,0)),Inputs!$B$4:$B$100,$B19)/1000) -> 0 | Y19: =IF(Y$3=0,"",SUMIFS(INDEX(Inputs!$D$4:$AG$100,0,MATCH(Y$2,Inputs!$D$2:$AG$2,0)),Inputs!$B$4:$B$100,$B19)/1000) -> 0 | Z19: =IF(Z$3=0,"",SUMIFS(INDEX(Inputs!$D$4:$AG$100,0,MATCH(Z$2,Inputs!$D$2:$AG$2,0)),Inputs!$B$4:$B$100,$B19)/1000) -> 0 | AA19: =IF(AA$3=0,"",SUMIFS(INDEX(Inputs!$D$4:$AG$100,0,MATCH(AA$2,Inputs!$D$2:$AG$2,0)),Inputs!$B$4:$B$100,$B19)/1000) -> 0 | AB19: =IF(AA19="","",AA19) -> 0 | AC19: =IF(AC$3=0,"",SUMIFS(INDEX(Inputs!$D$4:$AG$100,0,MATCH(AC$2,Inputs!$D$2:$AG$2,0)),Inputs!$B$4:$B$100,$B19)/1000) -> 0 | AD19: =IF(AD$3=0,"",SUMIFS(INDEX(Inputs!$D$4:$AG$100,0,MATCH(AD$2,Inputs!$D$2:$AG$2,0)),Inputs!$B$4:$B$100,$B19)/1000) -> 0 | AE19: =IF(AE$3=0,"",SUMIFS(INDEX(Inputs!$D$4:$AG$100,0,MATCH(AE$2,Inputs!$D$2:$AG$2,0)),Inputs!$B$4:$B$100,$B19)/1000) | AF19: =IF(AF$3=0,"",SUMIFS(INDEX(Inputs!$D$4:$AG$100,0,MATCH(AF$2,Inputs!$D$2:$AG$2,0)),Inputs!$B$4:$B$100,$B19)/1000) | AG19: =IF(AF19="","",AF19)
B20: 16 | C20: Other current assets | D20: =IF(D$3=0,"",SUMIFS(INDEX(Inputs!$D$4:$AG$100,0,MATCH(D$2,Inputs!$D$2:$AG$2,0)),Inputs!$B$4:$B$100,$B20)/1000) -> 153.704 | E20: =IF(E$3=0,"",SUMIFS(INDEX(Inputs!$D$4:$AG$100,0,MATCH(E$2,Inputs!$D$2:$AG$2,0)),Inputs!$B$4:$B$100,$B20)/1000) -> 169.532 | F20: =IF(F$3=0,"",SUMIFS(INDEX(Inputs!$D$4:$AG$100,0,MATCH(F$2,Inputs!$D$2:$AG$2,0)),Inputs!$B$4:$B$100,$B20)/1000) -> 172.01 | G20: =IF(G$3=0,"",SUMIFS(INDEX(Inputs!$D$4:$AG$100,0,MATCH(G$2,Inputs!$D$2:$AG$2,0)),Inputs!$B$4:$B$100,$B20)/1000) -> 349.799 | H20: =IF(G20="","",G20) -> 349.799 | I20: =IF(I$3=0,"",SUMIFS(INDEX(Inputs!$D$4:$AG$100,0,MATCH(I$2,Inputs!$D$2:$AG$2,0)),Inputs!$B$4:$B$100,$B20)/1000) -> 1735.893 | J20: =IF(J$3=0,"",SUMIFS(INDEX(Inputs!$D$4:$AG$100,0,MATCH(J$2,Inputs!$D$2:$AG$2,0)),Inputs!$B$4:$B$100,$B20)/1000) -> 2046.69 | K20: =IF(K$3=0,"",SUMIFS(INDEX(Inputs!$D$4:$AG$100,0,MATCH(K$2,Inputs!$D$2:$AG$2,0)),Inputs!$B$4:$B$100,$B20)/1000) -> 1890.397 | L20: =IF(L$3=0,"",SUMIFS(INDEX(Inputs!$D$4:$AG$100,0,MATCH(L$2,Inputs!$D$2:$AG$2,0)),Inputs!$B$4:$B$100,$B20)/1000) -> 2419.33 | M20: =IF(L20="","",L20) -> 2419.33 | N20: =IF(N$3=0,"",SUMIFS(INDEX(Inputs!$D$4:$AG$100,0,MATCH(N$2,Inputs!$D$2:$AG$2,0)),Inputs!$B$4:$B$100,$B20)/1000) -> 2920.331 | O20: =IF(O$3=0,"",SUMIFS(INDEX(Inputs!$D$4:$AG$100,0,MATCH(O$2,Inputs!$D$2:$AG$2,0)),Inputs!$B$4:$B$100,$B20)/1000) -> 2337.541 | P20: =IF(P$3=0,"",SUMIFS(INDEX(Inputs!$D$4:$AG$100,0,MATCH(P$2,Inputs!$D$2:$AG$2,0)),Inputs!$B$4:$B$100,$B20)/1000) -> 2228.121 | Q20: =IF(Q$3=0,"",SUMIFS(INDEX(Inputs!$D$4:$AG$100,0,MATCH(Q$2,Inputs!$D$2:$AG$2,0)),Inputs!$B$4:$B$100,$B20)/1000) -> 2019.991 | R20: =IF(Q20="","",Q20) -> 2019.991 | S20: =IF(S$3=0,"",SUMIFS(INDEX(Inputs!$D$4:$AG$100,0,MATCH(S$2,Inputs!$D$2:$AG$2,0)),Inputs!$B$4:$B$100,$B20)/1000) -> 1684.062 | T20: =IF(T$3=0,"",SUMIFS(INDEX(Inputs!$D$4:$AG$100,0,MATCH(T$2,Inputs!$D$2:$AG$2,0)),Inputs!$B$4:$B$100,$B20)/1000) -> 1748.821 | U20: =IF(U$3=0,"",SUMIFS(INDEX(Inputs!$D$4:$AG$100,0,MATCH(U$2,Inputs!$D$2:$AG$2,0)),Inputs!$B$4:$B$100,$B20)/1000) -> 3461.649 | V20: =IF(V$3=0,"",SUMIFS(INDEX(Inputs!$D$4:$AG$100,0,MATCH(V$2,Inputs!$D$2:$AG$2,0)),Inputs!$B$4:$B$100,$B20)/1000) -> 2441.749 | W20: =IF(V20="","",V20) -> 2441.749 | X20: =IF(X$3=0,"",SUMIFS(INDEX(Inputs!$D$4:$AG$100,0,MATCH(X$2,Inputs!$D$2:$AG$2,0)),Inputs!$B$4:$B$100,$B20)/1000) -> 3526.946 | Y20: =IF(Y$3=0,"",SUMIFS(INDEX(Inputs!$D$4:$AG$100,0,MATCH(Y$2,Inputs!$D$2:$AG$2,0)),Inputs!$B$4:$B$100,$B20)/1000) -> 2570.301 | Z20: =IF(Z$3=0,"",SUMIFS(INDEX(Inputs!$D$4:$AG$100,0,MATCH(Z$2,Inputs!$D$2:$AG$2,0)),Inputs!$B$4:$B$100,$B20)/1000) -> 2200.475 | AA20: =IF(AA$3=0,"",SUMIFS(INDEX(Inputs!$D$4:$AG$100,0,MATCH(AA$2,Inputs!$D$2:$AG$2,0)),Inputs!$B$4:$B$100,$B20)/1000) -> 2365.271 | AB20: =IF(AA20="","",AA20) -> 2365.271 | AC20: =IF(AC$3=0,"",SUMIFS(INDEX(Inputs!$D$4:$AG$100,0,MATCH(AC$2,Inputs!$D$2:$AG$2,0)),Inputs!$B$4:$B$100,$B20)/1000) -> 2200.206 | AD20: =IF(AD$3=0,"",SUMIFS(INDEX(Inputs!$D$4:$AG$100,0,MATCH(AD$2,Inputs!$D$2:$AG$2,0)),Inputs!$B$4:$B$100,$B20)/1000) -> 2081.861 | AE20: =IF(AE$3=0,"",SUMIFS(INDEX(Inputs!$D$4:$AG$100,0,MATCH(AE$2,Inputs!$D$2:$AG$2,0)),Inputs!$B$4:$B$100,$B20)/1000) | AF20: =IF(AF$3=0,"",SUMIFS(INDEX(Inputs!$D$4:$AG$100,0,MATCH(AF$2,Inputs!$D$2:$AG$2,0)),Inputs!$B$4:$B$100,$B20)/1000) | AG20: =IF(AF20="","",AF20)
B21: 17 | C21: Equity in affiliates | D21: =IF(D$3=0,"",SUMIFS(INDEX(Inputs!$D$4:$AG$100,0,MATCH(D$2,Inputs!$D$2:$AG$2,0)),Inputs!$B$4:$B$100,$B21)/1000) -> 0 | E21: =IF(E$3=0,"",SUMIFS(INDEX(Inputs!$D$4:$AG$100,0,MATCH(E$2,Inputs!$D$2:$AG$2,0)),Inputs!$B$4:$B$100,$B21)/1000) -> 0 | F21: =IF(F$3=0,"",SUMIFS(INDEX(Inputs!$D$4:$AG$100,0,MATCH(F$2,Inputs!$D$2:$AG$2,0)),Inputs!$B$4:$B$100,$B21)/1000) -> 0 | G21: =IF(G$3=0,"",SUMIFS(INDEX(Inputs!$D$4:$AG$100,0,MATCH(G$2,Inputs!$D$2:$AG$2,0)),Inputs!$B$4:$B$100,$B21)/1000) -> 0 | H21: =IF(G21="","",G21) -> 0 | I21: =IF(I$3=0,"",SUMIFS(INDEX(Inputs!$D$4:$AG$100,0,MATCH(I$2,Inputs!$D$2:$AG$2,0)),Inputs!$B$4:$B$100,$B21)/1000) -> 1101.829 | J21: =IF(J$3=0,"",SUMIFS(INDEX(Inputs!$D$4:$AG$100,0,MATCH(J$2,Inputs!$D$2:$AG$2,0)),Inputs!$B$4:$B$100,$B21)/1000) -> 1015.723 | K21: =IF(K$3=0,"",SUMIFS(INDEX(Inputs!$D$4:$AG$100,0,MATCH(K$2,Inputs!$D$2:$AG$2,0)),Inputs!$B$4:$B$100,$B21)/1000) -> 1077.88 | L21: =IF(L$3=0,"",SUMIFS(INDEX(Inputs!$D$4:$AG$100,0,MATCH(L$2,Inputs!$D$2:$AG$2,0)),Inputs!$B$4:$B$100,$B21)/1000) -> 2161.751 | M21: =IF(L21="","",L21) -> 2161.751 | N21: =IF(N$3=0,"",SUMIFS(INDEX(Inputs!$D$4:$AG$100,0,MATCH(N$2,Inputs!$D$2:$AG$2,0)),Inputs!$B$4:$B$100,$B21)/1000) -> 2192.011 | O21: =IF(O$3=0,"",SUMIFS(INDEX(Inputs!$D$4:$AG$100,0,MATCH(O$2,Inputs!$D$2:$AG$2,0)),Inputs!$B$4:$B$100,$B21)/1000) -> 2127.074 | P21: =IF(P$3=0,"",SUMIFS(INDEX(Inputs!$D$4:$AG$100,0,MATCH(P$2,Inputs!$D$2:$AG$2,0)),Inputs!$B$4:$B$100,$B21)/1000) -> 2111.609 | Q21: =IF(Q$3=0,"",SUMIFS(INDEX(Inputs!$D$4:$AG$100,0,MATCH(Q$2,Inputs!$D$2:$AG$2,0)),Inputs!$B$4:$B$100,$B21)/1000) -> 2057.307 | R21: =IF(Q21="","",Q21) -> 2057.307 | S21: =IF(S$3=0,"",SUMIFS(INDEX(Inputs!$D$4:$AG$100,0,MATCH(S$2,Inputs!$D$2:$AG$2,0)),Inputs!$B$4:$B$100,$B21)/1000) -> 2111.899 | T21: =IF(T$3=0,"",SUMIFS(INDEX(Inputs!$D$4:$AG$100,0,MATCH(T$2,Inputs!$D$2:$AG$2,0)),Inputs!$B$4:$B$100,$B21)/1000) -> 2047.967 | U21: =IF(U$3=0,"",SUMIFS(INDEX(Inputs!$D$4:$AG$100,0,MATCH(U$2,Inputs!$D$2:$AG$2,0)),Inputs!$B$4:$B$100,$B21)/1000) -> 2105.551 | V21: =IF(V$3=0,"",SUMIFS(INDEX(Inputs!$D$4:$AG$100,0,MATCH(V$2,Inputs!$D$2:$AG$2,0)),Inputs!$B$4:$B$100,$B21)/1000) -> 2261.558 | W21: =IF(V21="","",V21) -> 2261.558 | X21: =IF(X$3=0,"",SUMIFS(INDEX(Inputs!$D$4:$AG$100,0,MATCH(X$2,Inputs!$D$2:$AG$2,0)),Inputs!$B$4:$B$100,$B21)/1000) -> 2299.011 | Y21: =IF(Y$3=0,"",SUMIFS(INDEX(Inputs!$D$4:$AG$100,0,MATCH(Y$2,Inputs!$D$2:$AG$2,0)),Inputs!$B$4:$B$100,$B21)/1000) -> 2216.541 | Z21: =IF(Z$3=0,"",SUMIFS(INDEX(Inputs!$D$4:$AG$100,0,MATCH(Z$2,Inputs!$D$2:$AG$2,0)),Inputs!$B$4:$B$100,$B21)/1000) -> 2133.085 | AA21: =IF(AA$3=0,"",SUMIFS(INDEX(Inputs!$D$4:$AG$100,0,MATCH(AA$2,Inputs!$D$2:$AG$2,0)),Inputs!$B$4:$B$100,$B21)/1000) -> 2131.02 | AB21: =IF(AA21="","",AA21) -> 2131.02 | AC21: =IF(AC$3=0,"",SUMIFS(INDEX(Inputs!$D$4:$AG$100,0,MATCH(AC$2,Inputs!$D$2:$AG$2,0)),Inputs!$B$4:$B$100,$B21)/1000) -> 2113.512 | AD21: =IF(AD$3=0,"",SUMIFS(INDEX(Inputs!$D$4:$AG$100,0,MATCH(AD$2,Inputs!$D$2:$AG$2,0)),Inputs!$B$4:$B$100,$B21)/1000) -> 2043.198 | AE21: =IF(AE$3=0,"",SUMIFS(INDEX(Inputs!$D$4:$AG$100,0,MATCH(AE$2,Inputs!$D$2:$AG$2,0)),Inputs!$B$4:$B$100,$B21)/1000) | AF21: =IF(AF$3=0,"",SUMIFS(INDEX(Inputs!$D$4:$AG$100,0,MATCH(AF$2,Inputs!$D$2:$AG$2,0)),Inputs!$B$4:$B$100,$B21)/1000) | AG21: =IF(AF21="","",AF21)
B22: 18 | C22: PP&E | D22: =IF(D$3=0,"",SUMIFS(INDEX(Inputs!$D$4:$AG$100,0,MATCH(D$2,Inputs!$D$2:$AG$2,0)),Inputs!$B$4:$B$100,$B22)/1000) -> 8718.257 | E22: =IF(E$3=0,"",SUMIFS(INDEX(Inputs!$D$4:$AG$100,0,MATCH(E$2,Inputs!$D$2:$AG$2,0)),Inputs!$B$4:$B$100,$B22)/1000) -> 8625.281 | F22: =IF(F$3=0,"",SUMIFS(INDEX(Inputs!$D$4:$AG$100,0,MATCH(F$2,Inputs!$D$2:$AG$2,0)),Inputs!$B$4:$B$100,$B22)/1000) -> 8890.528 | G22: =IF(G$3=0,"",SUMIFS(INDEX(Inputs!$D$4:$AG$100,0,MATCH(G$2,Inputs!$D$2:$AG$2,0)),Inputs!$B$4:$B$100,$B22)/1000) -> 8980.282 | H22: =IF(G22="","",G22) -> 8980.282 | I22: =IF(I$3=0,"",SUMIFS(INDEX(Inputs!$D$4:$AG$100,0,MATCH(I$2,Inputs!$D$2:$AG$2,0)),Inputs!$B$4:$B$100,$B22)/1000) -> 9170.686 | J22: =IF(J$3=0,"",SUMIFS(INDEX(Inputs!$D$4:$AG$100,0,MATCH(J$2,Inputs!$D$2:$AG$2,0)),Inputs!$B$4:$B$100,$B22)/1000) -> 9743.557 | K22: =IF(K$3=0,"",SUMIFS(INDEX(Inputs!$D$4:$AG$100,0,MATCH(K$2,Inputs!$D$2:$AG$2,0)),Inputs!$B$4:$B$100,$B22)/1000) -> 10069.407 | L22: =IF(L$3=0,"",SUMIFS(INDEX(Inputs!$D$4:$AG$100,0,MATCH(L$2,Inputs!$D$2:$AG$2,0)),Inputs!$B$4:$B$100,$B22)/1000) -> 10397.035 | M22: =IF(L22="","",L22) -> 10397.035 | N22: =IF(N$3=0,"",SUMIFS(INDEX(Inputs!$D$4:$AG$100,0,MATCH(N$2,Inputs!$D$2:$AG$2,0)),Inputs!$B$4:$B$100,$B22)/1000) -> 10619.999 | O22: =IF(O$3=0,"",SUMIFS(INDEX(Inputs!$D$4:$AG$100,0,MATCH(O$2,Inputs!$D$2:$AG$2,0)),Inputs!$B$4:$B$100,$B22)/1000) -> 11178.295 | P22: =IF(P$3=0,"",SUMIFS(INDEX(Inputs!$D$4:$AG$100,0,MATCH(P$2,Inputs!$D$2:$AG$2,0)),Inputs!$B$4:$B$100,$B22)/1000) -> 11813.974 | Q22: =IF(Q$3=0,"",SUMIFS(INDEX(Inputs!$D$4:$AG$100,0,MATCH(Q$2,Inputs!$D$2:$AG$2,0)),Inputs!$B$4:$B$100,$B22)/1000) -> 11849.347 | R22: =IF(Q22="","",Q22) -> 11849.347 | S22: =IF(S$3=0,"",SUMIFS(INDEX(Inputs!$D$4:$AG$100,0,MATCH(S$2,Inputs!$D$2:$AG$2,0)),Inputs!$B$4:$B$100,$B22)/1000) -> 11732.58 | T22: =IF(T$3=0,"",SUMIFS(INDEX(Inputs!$D$4:$AG$100,0,MATCH(T$2,Inputs!$D$2:$AG$2,0)),Inputs!$B$4:$B$100,$B22)/1000) -> 11668.586 | U22: =IF(U$3=0,"",SUMIFS(INDEX(Inputs!$D$4:$AG$100,0,MATCH(U$2,Inputs!$D$2:$AG$2,0)),Inputs!$B$4:$B$100,$B22)/1000) -> 11571.81 | V22: =IF(V$3=0,"",SUMIFS(INDEX(Inputs!$D$4:$AG$100,0,MATCH(V$2,Inputs!$D$2:$AG$2,0)),Inputs!$B$4:$B$100,$B22)/1000) -> 26203.796 | W22: =IF(V22="","",V22) -> 26203.796 | X22: =IF(X$3=0,"",SUMIFS(INDEX(Inputs!$D$4:$AG$100,0,MATCH(X$2,Inputs!$D$2:$AG$2,0)),Inputs!$B$4:$B$100,$B22)/1000) -> 26000.982 | Y22: =IF(Y$3=0,"",SUMIFS(INDEX(Inputs!$D$4:$AG$100,0,MATCH(Y$2,Inputs!$D$2:$AG$2,0)),Inputs!$B$4:$B$100,$B22)/1000) -> 25810.274 | Z22: =IF(Z$3=0,"",SUMIFS(INDEX(Inputs!$D$4:$AG$100,0,MATCH(Z$2,Inputs!$D$2:$AG$2,0)),Inputs!$B$4:$B$100,$B22)/1000) -> 25725.023 | AA22: =IF(AA$3=0,"",SUMIFS(INDEX(Inputs!$D$4:$AG$100,0,MATCH(AA$2,Inputs!$D$2:$AG$2,0)),Inputs!$B$4:$B$100,$B22)/1000) -> 25430.247 | AB22: =IF(AA22="","",AA22) -> 25430.247 | AC22: =IF(AC$3=0,"",SUMIFS(INDEX(Inputs!$D$4:$AG$100,0,MATCH(AC$2,Inputs!$D$2:$AG$2,0)),Inputs!$B$4:$B$100,$B22)/1000) -> 25207.131 | AD22: =IF(AD$3=0,"",SUMIFS(INDEX(Inputs!$D$4:$AG$100,0,MATCH(AD$2,Inputs!$D$2:$AG$2,0)),Inputs!$B$4:$B$100,$B22)/1000) -> 25020.77 | AE22: =IF(AE$3=0,"",SUMIFS(INDEX(Inputs!$D$4:$AG$100,0,MATCH(AE$2,Inputs!$D$2:$AG$2,0)),Inputs!$B$4:$B$100,$B22)/1000) | AF22: =IF(AF$3=0,"",SUMIFS(INDEX(Inputs!$D$4:$AG$100,0,MATCH(AF$2,Inputs!$D$2:$AG$2,0)),Inputs!$B$4:$B$100,$B22)/1000) | AG22: =IF(AF22="","",AF22)
B23: 19 | C23: Right-of-use-assets | D23: =IF(D$3=0,"",SUMIFS(INDEX(Inputs!$D$4:$AG$100,0,MATCH(D$2,Inputs!$D$2:$AG$2,0)),Inputs!$B$4:$B$100,$B23)/1000) -> 6.068 | E23: =IF(E$3=0,"",SUMIFS(INDEX(Inputs!$D$4:$AG$100,0,MATCH(E$2,Inputs!$D$2:$AG$2,0)),Inputs!$B$4:$B$100,$B23)/1000) -> 6.051 | F23: =IF(F$3=0,"",SUMIFS(INDEX(Inputs!$D$4:$AG$100,0,MATCH(F$2,Inputs!$D$2:$AG$2,0)),Inputs!$B$4:$B$100,$B23)/1000) -> 5.67 | G23: =IF(G$3=0,"",SUMIFS(INDEX(Inputs!$D$4:$AG$100,0,MATCH(G$2,Inputs!$D$2:$AG$2,0)),Inputs!$B$4:$B$100,$B23)/1000) -> 5.283 | H23: =IF(G23="","",G23) -> 5.283 | I23: =IF(I$3=0,"",SUMIFS(INDEX(Inputs!$D$4:$AG$100,0,MATCH(I$2,Inputs!$D$2:$AG$2,0)),Inputs!$B$4:$B$100,$B23)/1000) -> 6.519 | J23: =IF(J$3=0,"",SUMIFS(INDEX(Inputs!$D$4:$AG$100,0,MATCH(J$2,Inputs!$D$2:$AG$2,0)),Inputs!$B$4:$B$100,$B23)/1000) -> 5.425 | K23: =IF(K$3=0,"",SUMIFS(INDEX(Inputs!$D$4:$AG$100,0,MATCH(K$2,Inputs!$D$2:$AG$2,0)),Inputs!$B$4:$B$100,$B23)/1000) -> 80.327 | L23: =IF(L$3=0,"",SUMIFS(INDEX(Inputs!$D$4:$AG$100,0,MATCH(L$2,Inputs!$D$2:$AG$2,0)),Inputs!$B$4:$B$100,$B23)/1000) -> 43.707 | M23: =IF(L23="","",L23) -> 43.707 | N23: =IF(N$3=0,"",SUMIFS(INDEX(Inputs!$D$4:$AG$100,0,MATCH(N$2,Inputs!$D$2:$AG$2,0)),Inputs!$B$4:$B$100,$B23)/1000) -> 44.522 | O23: =IF(O$3=0,"",SUMIFS(INDEX(Inputs!$D$4:$AG$100,0,MATCH(O$2,Inputs!$D$2:$AG$2,0)),Inputs!$B$4:$B$100,$B23)/1000) -> 45.236 | P23: =IF(P$3=0,"",SUMIFS(INDEX(Inputs!$D$4:$AG$100,0,MATCH(P$2,Inputs!$D$2:$AG$2,0)),Inputs!$B$4:$B$100,$B23)/1000) -> 65.324 | Q23: =IF(Q$3=0,"",SUMIFS(INDEX(Inputs!$D$4:$AG$100,0,MATCH(Q$2,Inputs!$D$2:$AG$2,0)),Inputs!$B$4:$B$100,$B23)/1000) -> 64.689 | R23: =IF(Q23="","",Q23) -> 64.689 | S23: =IF(S$3=0,"",SUMIFS(INDEX(Inputs!$D$4:$AG$100,0,MATCH(S$2,Inputs!$D$2:$AG$2,0)),Inputs!$B$4:$B$100,$B23)/1000) -> 62.706 | T23: =IF(T$3=0,"",SUMIFS(INDEX(Inputs!$D$4:$AG$100,0,MATCH(T$2,Inputs!$D$2:$AG$2,0)),Inputs!$B$4:$B$100,$B23)/1000) -> 60.861 | U23: =IF(U$3=0,"",SUMIFS(INDEX(Inputs!$D$4:$AG$100,0,MATCH(U$2,Inputs!$D$2:$AG$2,0)),Inputs!$B$4:$B$100,$B23)/1000) -> 69.26 | V23: =IF(V$3=0,"",SUMIFS(INDEX(Inputs!$D$4:$AG$100,0,MATCH(V$2,Inputs!$D$2:$AG$2,0)),Inputs!$B$4:$B$100,$B23)/1000) -> 149.284 | W23: =IF(V23="","",V23) -> 149.284 | X23: =IF(X$3=0,"",SUMIFS(INDEX(Inputs!$D$4:$AG$100,0,MATCH(X$2,Inputs!$D$2:$AG$2,0)),Inputs!$B$4:$B$100,$B23)/1000) -> 149.11 | Y23: =IF(Y$3=0,"",SUMIFS(INDEX(Inputs!$D$4:$AG$100,0,MATCH(Y$2,Inputs!$D$2:$AG$2,0)),Inputs!$B$4:$B$100,$B23)/1000) -> 145.66 | Z23: =IF(Z$3=0,"",SUMIFS(INDEX(Inputs!$D$4:$AG$100,0,MATCH(Z$2,Inputs!$D$2:$AG$2,0)),Inputs!$B$4:$B$100,$B23)/1000) -> 142.547 | AA23: =IF(AA$3=0,"",SUMIFS(INDEX(Inputs!$D$4:$AG$100,0,MATCH(AA$2,Inputs!$D$2:$AG$2,0)),Inputs!$B$4:$B$100,$B23)/1000) -> 140.111 | AB23: =IF(AA23="","",AA23) -> 140.111 | AC23: =IF(AC$3=0,"",SUMIFS(INDEX(Inputs!$D$4:$AG$100,0,MATCH(AC$2,Inputs!$D$2:$AG$2,0)),Inputs!$B$4:$B$100,$B23)/1000) -> 141.31 | AD23: =IF(AD$3=0,"",SUMIFS(INDEX(Inputs!$D$4:$AG$100,0,MATCH(AD$2,Inputs!$D$2:$AG$2,0)),Inputs!$B$4:$B$100,$B23)/1000) -> 136.85 | AE23: =IF(AE$3=0,"",SUMIFS(INDEX(Inputs!$D$4:$AG$100,0,MATCH(AE$2,Inputs!$D$2:$AG$2,0)),Inputs!$B$4:$B$100,$B23)/1000) | AF23: =IF(AF$3=0,"",SUMIFS(INDEX(Inputs!$D$4:$AG$100,0,MATCH(AF$2,Inputs!$D$2:$AG$2,0)),Inputs!$B$4:$B$100,$B23)/1000) | AG23: =IF(AF23="","",AF23)
B24: 20 | C24: Goodwill | D24: =IF(D$3=0,"",SUMIFS(INDEX(Inputs!$D$4:$AG$100,0,MATCH(D$2,Inputs!$D$2:$AG$2,0)),Inputs!$B$4:$B$100,$B24)/1000) -> 0 | E24: =IF(E$3=0,"",SUMIFS(INDEX(Inputs!$D$4:$AG$100,0,MATCH(E$2,Inputs!$D$2:$AG$2,0)),Inputs!$B$4:$B$100,$B24)/1000) -> 0 | F24: =IF(F$3=0,"",SUMIFS(INDEX(Inputs!$D$4:$AG$100,0,MATCH(F$2,Inputs!$D$2:$AG$2,0)),Inputs!$B$4:$B$100,$B24)/1000) -> 0 | G24: =IF(G$3=0,"",SUMIFS(INDEX(Inputs!$D$4:$AG$100,0,MATCH(G$2,Inputs!$D$2:$AG$2,0)),Inputs!$B$4:$B$100,$B24)/1000) -> 0 | H24: =IF(G24="","",G24) -> 0 | I24: =IF(I$3=0,"",SUMIFS(INDEX(Inputs!$D$4:$AG$100,0,MATCH(I$2,Inputs!$D$2:$AG$2,0)),Inputs!$B$4:$B$100,$B24)/1000) -> 0 | J24: =IF(J$3=0,"",SUMIFS(INDEX(Inputs!$D$4:$AG$100,0,MATCH(J$2,Inputs!$D$2:$AG$2,0)),Inputs!$B$4:$B$100,$B24)/1000) -> 0 | K24: =IF(K$3=0,"",SUMIFS(INDEX(Inputs!$D$4:$AG$100,0,MATCH(K$2,Inputs!$D$2:$AG$2,0)),Inputs!$B$4:$B$100,$B24)/1000) -> 0 | L24: =IF(L$3=0,"",SUMIFS(INDEX(Inputs!$D$4:$AG$100,0,MATCH(L$2,Inputs!$D$2:$AG$2,0)),Inputs!$B$4:$B$100,$B24)/1000) -> 0 | M24: =IF(L24="","",L24) -> 0 | N24: =IF(N$3=0,"",SUMIFS(INDEX(Inputs!$D$4:$AG$100,0,MATCH(N$2,Inputs!$D$2:$AG$2,0)),Inputs!$B$4:$B$100,$B24)/1000) -> 0 | O24: =IF(O$3=0,"",SUMIFS(INDEX(Inputs!$D$4:$AG$100,0,MATCH(O$2,Inputs!$D$2:$AG$2,0)),Inputs!$B$4:$B$100,$B24)/1000) -> 0 | P24: =IF(P$3=0,"",SUMIFS(INDEX(Inputs!$D$4:$AG$100,0,MATCH(P$2,Inputs!$D$2:$AG$2,0)),Inputs!$B$4:$B$100,$B24)/1000) -> 0 | Q24: =IF(Q$3=0,"",SUMIFS(INDEX(Inputs!$D$4:$AG$100,0,MATCH(Q$2,Inputs!$D$2:$AG$2,0)),Inputs!$B$4:$B$100,$B24)/1000) -> 0 | R24: =IF(Q24="","",Q24) -> 0 | S24: =IF(S$3=0,"",SUMIFS(INDEX(Inputs!$D$4:$AG$100,0,MATCH(S$2,Inputs!$D$2:$AG$2,0)),Inputs!$B$4:$B$100,$B24)/1000) -> 0 | T24: =IF(T$3=0,"",SUMIFS(INDEX(Inputs!$D$4:$AG$100,0,MATCH(T$2,Inputs!$D$2:$AG$2,0)),Inputs!$B$4:$B$100,$B24)/1000) -> 0 | U24: =IF(U$3=0,"",SUMIFS(INDEX(Inputs!$D$4:$AG$100,0,MATCH(U$2,Inputs!$D$2:$AG$2,0)),Inputs!$B$4:$B$100,$B24)/1000) -> 0 | V24: =IF(V$3=0,"",SUMIFS(INDEX(Inputs!$D$4:$AG$100,0,MATCH(V$2,Inputs!$D$2:$AG$2,0)),Inputs!$B$4:$B$100,$B24)/1000) -> 0 | W24: =IF(V24="","",V24) -> 0 | X24: =IF(X$3=0,"",SUMIFS(INDEX(Inputs!$D$4:$AG$100,0,MATCH(X$2,Inputs!$D$2:$AG$2,0)),Inputs!$B$4:$B$100,$B24)/1000) -> 0 | Y24: =IF(Y$3=0,"",SUMIFS(INDEX(Inputs!$D$4:$AG$100,0,MATCH(Y$2,Inputs!$D$2:$AG$2,0)),Inputs!$B$4:$B$100,$B24)/1000) -> 0 | Z24: =IF(Z$3=0,"",SUMIFS(INDEX(Inputs!$D$4:$AG$100,0,MATCH(Z$2,Inputs!$D$2:$AG$2,0)),Inputs!$B$4:$B$100,$B24)/1000) -> 0 | AA24: =IF(AA$3=0,"",SUMIFS(INDEX(Inputs!$D$4:$AG$100,0,MATCH(AA$2,Inputs!$D$2:$AG$2,0)),Inputs!$B$4:$B$100,$B24)/1000) -> 0 | AB24: =IF(AA24="","",AA24) -> 0 | AC24: =IF(AC$3=0,"",SUMIFS(INDEX(Inputs!$D$4:$AG$100,0,MATCH(AC$2,Inputs!$D$2:$AG$2,0)),Inputs!$B$4:$B$100,$B24)/1000) -> 0 | AD24: =IF(AD$3=0,"",SUMIFS(INDEX(Inputs!$D$4:$AG$100,0,MATCH(AD$2,Inputs!$D$2:$AG$2,0)),Inputs!$B$4:$B$100,$B24)/1000) -> 0 | AE24: =IF(AE$3=0,"",SUMIFS(INDEX(Inputs!$D$4:$AG$100,0,MATCH(AE$2,Inputs!$D$2:$AG$2,0)),Inputs!$B$4:$B$100,$B24)/1000) | AF24: =IF(AF$3=0,"",SUMIFS(INDEX(Inputs!$D$4:$AG$100,0,MATCH(AF$2,Inputs!$D$2:$AG$2,0)),Inputs!$B$4:$B$100,$B24)/1000) | AG24: =IF(AF24="","",AF24)
B25: 21 | C25: Intangibles | D25: =IF(D$3=0,"",SUMIFS(INDEX(Inputs!$D$4:$AG$100,0,MATCH(D$2,Inputs!$D$2:$AG$2,0)),Inputs!$B$4:$B$100,$B25)/1000) -> 1753.735 | E25: =IF(E$3=0,"",SUMIFS(INDEX(Inputs!$D$4:$AG$100,0,MATCH(E$2,Inputs!$D$2:$AG$2,0)),Inputs!$B$4:$B$100,$B25)/1000) -> 1739.751 | F25: =IF(F$3=0,"",SUMIFS(INDEX(Inputs!$D$4:$AG$100,0,MATCH(F$2,Inputs!$D$2:$AG$2,0)),Inputs!$B$4:$B$100,$B25)/1000) -> 2184.98 | G25: =IF(G$3=0,"",SUMIFS(INDEX(Inputs!$D$4:$AG$100,0,MATCH(G$2,Inputs!$D$2:$AG$2,0)),Inputs!$B$4:$B$100,$B25)/1000) -> 2366.432 | H25: =IF(G25="","",G25) -> 2366.432 | I25: =IF(I$3=0,"",SUMIFS(INDEX(Inputs!$D$4:$AG$100,0,MATCH(I$2,Inputs!$D$2:$AG$2,0)),Inputs!$B$4:$B$100,$B25)/1000) -> 3868.918 | J25: =IF(J$3=0,"",SUMIFS(INDEX(Inputs!$D$4:$AG$100,0,MATCH(J$2,Inputs!$D$2:$AG$2,0)),Inputs!$B$4:$B$100,$B25)/1000) -> 3828.735 | K25: =IF(K$3=0,"",SUMIFS(INDEX(Inputs!$D$4:$AG$100,0,MATCH(K$2,Inputs!$D$2:$AG$2,0)),Inputs!$B$4:$B$100,$B25)/1000) -> 3788.372 | L25: =IF(L$3=0,"",SUMIFS(INDEX(Inputs!$D$4:$AG$100,0,MATCH(L$2,Inputs!$D$2:$AG$2,0)),Inputs!$B$4:$B$100,$B25)/1000) -> 2587.808 | M25: =IF(L25="","",L25) -> 2587.808 | N25: =IF(N$3=0,"",SUMIFS(INDEX(Inputs!$D$4:$AG$100,0,MATCH(N$2,Inputs!$D$2:$AG$2,0)),Inputs!$B$4:$B$100,$B25)/1000) -> 2574.991 | O25: =IF(O$3=0,"",SUMIFS(INDEX(Inputs!$D$4:$AG$100,0,MATCH(O$2,Inputs!$D$2:$AG$2,0)),Inputs!$B$4:$B$100,$B25)/1000) -> 2557.102 | P25: =IF(P$3=0,"",SUMIFS(INDEX(Inputs!$D$4:$AG$100,0,MATCH(P$2,Inputs!$D$2:$AG$2,0)),Inputs!$B$4:$B$100,$B25)/1000) -> 2540.211 | Q25: =IF(Q$3=0,"",SUMIFS(INDEX(Inputs!$D$4:$AG$100,0,MATCH(Q$2,Inputs!$D$2:$AG$2,0)),Inputs!$B$4:$B$100,$B25)/1000) -> 2458.453 | R25: =IF(Q25="","",Q25) -> 2458.453 | S25: =IF(S$3=0,"",SUMIFS(INDEX(Inputs!$D$4:$AG$100,0,MATCH(S$2,Inputs!$D$2:$AG$2,0)),Inputs!$B$4:$B$100,$B25)/1000) -> 2443.013 | T25: =IF(T$3=0,"",SUMIFS(INDEX(Inputs!$D$4:$AG$100,0,MATCH(T$2,Inputs!$D$2:$AG$2,0)),Inputs!$B$4:$B$100,$B25)/1000) -> 2426.557 | U25: =IF(U$3=0,"",SUMIFS(INDEX(Inputs!$D$4:$AG$100,0,MATCH(U$2,Inputs!$D$2:$AG$2,0)),Inputs!$B$4:$B$100,$B25)/1000) -> 2515.652 | V25: =IF(V$3=0,"",SUMIFS(INDEX(Inputs!$D$4:$AG$100,0,MATCH(V$2,Inputs!$D$2:$AG$2,0)),Inputs!$B$4:$B$100,$B25)/1000) -> 7335.883 | W25: =IF(V25="","",V25) -> 7335.883 | X25: =IF(X$3=0,"",SUMIFS(INDEX(Inputs!$D$4:$AG$100,0,MATCH(X$2,Inputs!$D$2:$AG$2,0)),Inputs!$B$4:$B$100,$B25)/1000) -> 7230.02 | Y25: =IF(Y$3=0,"",SUMIFS(INDEX(Inputs!$D$4:$AG$100,0,MATCH(Y$2,Inputs!$D$2:$AG$2,0)),Inputs!$B$4:$B$100,$B25)/1000) -> 7109.327 | Z25: =IF(Z$3=0,"",SUMIFS(INDEX(Inputs!$D$4:$AG$100,0,MATCH(Z$2,Inputs!$D$2:$AG$2,0)),Inputs!$B$4:$B$100,$B25)/1000) -> 7109.713 | AA25: =IF(AA$3=0,"",SUMIFS(INDEX(Inputs!$D$4:$AG$100,0,MATCH(AA$2,Inputs!$D$2:$AG$2,0)),Inputs!$B$4:$B$100,$B25)/1000) -> 7201.637 | AB25: =IF(AA25="","",AA25) -> 7201.637 | AC25: =IF(AC$3=0,"",SUMIFS(INDEX(Inputs!$D$4:$AG$100,0,MATCH(AC$2,Inputs!$D$2:$AG$2,0)),Inputs!$B$4:$B$100,$B25)/1000) -> 7072.185 | AD25: =IF(AD$3=0,"",SUMIFS(INDEX(Inputs!$D$4:$AG$100,0,MATCH(AD$2,Inputs!$D$2:$AG$2,0)),Inputs!$B$4:$B$100,$B25)/1000) -> 6950.832 | AE25: =IF(AE$3=0,"",SUMIFS(INDEX(Inputs!$D$4:$AG$100,0,MATCH(AE$2,Inputs!$D$2:$AG$2,0)),Inputs!$B$4:$B$100,$B25)/1000) | AF25: =IF(AF$3=0,"",SUMIFS(INDEX(Inputs!$D$4:$AG$100,0,MATCH(AF$2,Inputs!$D$2:$AG$2,0)),Inputs!$B$4:$B$100,$B25)/1000) | AG25: =IF(AF25="","",AF25)
B26: 22 | C26: Other non-current assets | D26: =IF(D$3=0,"",SUMIFS(INDEX(Inputs!$D$4:$AG$100,0,MATCH(D$2,Inputs!$D$2:$AG$2,0)),Inputs!$B$4:$B$100,$B26)/1000) -> 2045.05 | E26: =IF(E$3=0,"",SUMIFS(INDEX(Inputs!$D$4:$AG$100,0,MATCH(E$2,Inputs!$D$2:$AG$2,0)),Inputs!$B$4:$B$100,$B26)/1000) -> 2062.604 | F26: =IF(F$3=0,"",SUMIFS(INDEX(Inputs!$D$4:$AG$100,0,MATCH(F$2,Inputs!$D$2:$AG$2,0)),Inputs!$B$4:$B$100,$B26)/1000) -> 2121.192 | G26: =IF(G$3=0,"",SUMIFS(INDEX(Inputs!$D$4:$AG$100,0,MATCH(G$2,Inputs!$D$2:$AG$2,0)),Inputs!$B$4:$B$100,$B26)/1000) -> 2449.664 | H26: =IF(G26="","",G26) -> 2449.664 | I26: =IF(I$3=0,"",SUMIFS(INDEX(Inputs!$D$4:$AG$100,0,MATCH(I$2,Inputs!$D$2:$AG$2,0)),Inputs!$B$4:$B$100,$B26)/1000) -> 5421.771 | J26: =IF(J$3=0,"",SUMIFS(INDEX(Inputs!$D$4:$AG$100,0,MATCH(J$2,Inputs!$D$2:$AG$2,0)),Inputs!$B$4:$B$100,$B26)/1000) -> 5416.763 | K26: =IF(K$3=0,"",SUMIFS(INDEX(Inputs!$D$4:$AG$100,0,MATCH(K$2,Inputs!$D$2:$AG$2,0)),Inputs!$B$4:$B$100,$B26)/1000) -> 5451.074 | L26: =IF(L$3=0,"",SUMIFS(INDEX(Inputs!$D$4:$AG$100,0,MATCH(L$2,Inputs!$D$2:$AG$2,0)),Inputs!$B$4:$B$100,$B26)/1000) -> 7823.272 | M26: =IF(L26="","",L26) -> 7823.272 | N26: =IF(N$3=0,"",SUMIFS(INDEX(Inputs!$D$4:$AG$100,0,MATCH(N$2,Inputs!$D$2:$AG$2,0)),Inputs!$B$4:$B$100,$B26)/1000) -> 8370.325 | O26: =IF(O$3=0,"",SUMIFS(INDEX(Inputs!$D$4:$AG$100,0,MATCH(O$2,Inputs!$D$2:$AG$2,0)),Inputs!$B$4:$B$100,$B26)/1000) -> 4987.265 | P26: =IF(P$3=0,"",SUMIFS(INDEX(Inputs!$D$4:$AG$100,0,MATCH(P$2,Inputs!$D$2:$AG$2,0)),Inputs!$B$4:$B$100,$B26)/1000) -> 4297.261 | Q26: =IF(Q$3=0,"",SUMIFS(INDEX(Inputs!$D$4:$AG$100,0,MATCH(Q$2,Inputs!$D$2:$AG$2,0)),Inputs!$B$4:$B$100,$B26)/1000) -> 3928.118 | R26: =IF(Q26="","",Q26) -> 3928.118 | S26: =IF(S$3=0,"",SUMIFS(INDEX(Inputs!$D$4:$AG$100,0,MATCH(S$2,Inputs!$D$2:$AG$2,0)),Inputs!$B$4:$B$100,$B26)/1000) -> 3298.898 | T26: =IF(T$3=0,"",SUMIFS(INDEX(Inputs!$D$4:$AG$100,0,MATCH(T$2,Inputs!$D$2:$AG$2,0)),Inputs!$B$4:$B$100,$B26)/1000) -> 3078.997 | U26: =IF(U$3=0,"",SUMIFS(INDEX(Inputs!$D$4:$AG$100,0,MATCH(U$2,Inputs!$D$2:$AG$2,0)),Inputs!$B$4:$B$100,$B26)/1000) -> 2910.546 | V26: =IF(V$3=0,"",SUMIFS(INDEX(Inputs!$D$4:$AG$100,0,MATCH(V$2,Inputs!$D$2:$AG$2,0)),Inputs!$B$4:$B$100,$B26)/1000) -> 3493.699 | W26: =IF(V26="","",V26) -> 3493.699 | X26: =IF(X$3=0,"",SUMIFS(INDEX(Inputs!$D$4:$AG$100,0,MATCH(X$2,Inputs!$D$2:$AG$2,0)),Inputs!$B$4:$B$100,$B26)/1000) -> 3364.396 | Y26: =IF(Y$3=0,"",SUMIFS(INDEX(Inputs!$D$4:$AG$100,0,MATCH(Y$2,Inputs!$D$2:$AG$2,0)),Inputs!$B$4:$B$100,$B26)/1000) -> 3223.658 | Z26: =IF(Z$3=0,"",SUMIFS(INDEX(Inputs!$D$4:$AG$100,0,MATCH(Z$2,Inputs!$D$2:$AG$2,0)),Inputs!$B$4:$B$100,$B26)/1000) -> 2908.583 | AA26: =IF(AA$3=0,"",SUMIFS(INDEX(Inputs!$D$4:$AG$100,0,MATCH(AA$2,Inputs!$D$2:$AG$2,0)),Inputs!$B$4:$B$100,$B26)/1000) -> 3421.541 | AB26: =IF(AA26="","",AA26) -> 3421.541 | AC26: =IF(AC$3=0,"",SUMIFS(INDEX(Inputs!$D$4:$AG$100,0,MATCH(AC$2,Inputs!$D$2:$AG$2,0)),Inputs!$B$4:$B$100,$B26)/1000) -> 3481.799 | AD26: =IF(AD$3=0,"",SUMIFS(INDEX(Inputs!$D$4:$AG$100,0,MATCH(AD$2,Inputs!$D$2:$AG$2,0)),Inputs!$B$4:$B$100,$B26)/1000) -> 3431.206 | AE26: =IF(AE$3=0,"",SUMIFS(INDEX(Inputs!$D$4:$AG$100,0,MATCH(AE$2,Inputs!$D$2:$AG$2,0)),Inputs!$B$4:$B$100,$B26)/1000) | AF26: =IF(AF$3=0,"",SUMIFS(INDEX(Inputs!$D$4:$AG$100,0,MATCH(AF$2,Inputs!$D$2:$AG$2,0)),Inputs!$B$4:$B$100,$B26)/1000) | AG26: =IF(AF26="","",AF26)
... B47: 41 | C47: Retained earnings | D47: =IF(D$3=0,"",SUMIFS(INDEX(Inputs!$D$4:$AG$100,0,MATCH(D$2,Inputs!$D$2:$AG$2,0)),Inputs!$B$4:$B$100,$B47)/1000) -> 1570.953 | E47: =IF(E$3=0,"",SUMIFS(INDEX(Inputs!$D$4:$AG$100,0,MATCH(E$2,Inputs!$D$2:$AG$2,0)),Inputs!$B$4:$B$100,$B47)/1000) -> 1779.198 | F47: =IF(F$3=0,"",SUMIFS(INDEX(Inputs!$D$4:$AG$100,0,MATCH(F$2,Inputs!$D$2:$AG$2,0)),Inputs!$B$4:$B$100,$B47)/1000) -> 1861.443 | G47: =IF(G$3=0,"",SUMIFS(INDEX(Inputs!$D$4:$AG$100,0,MATCH(G$2,Inputs!$D$2:$AG$2,0)),Inputs!$B$4:$B$100,$B47)/1000) -> 1861.941 | H47: =IF(G47="","",G47) -> 1861.941 | I47: =IF(I$3=0,"",SUMIFS(INDEX(Inputs!$D$4:$AG$100,0,MATCH(I$2,Inputs!$D$2:$AG$2,0)),Inputs!$B$4:$B$100,$B47)/1000) -> 1855.142 | J47: =IF(J$3=0,"",SUMIFS(INDEX(Inputs!$D$4:$AG$100,0,MATCH(J$2,Inputs!$D$2:$AG$2,0)),Inputs!$B$4:$B$100,$B47)/1000) -> 1767.067 | K47: =IF(K$3=0,"",SUMIFS(INDEX(Inputs!$D$4:$AG$100,0,MATCH(K$2,Inputs!$D$2:$AG$2,0)),Inputs!$B$4:$B$100,$B47)/1000) -> 1997.153 | L47: =IF(L$3=0,"",SUMIFS(INDEX(Inputs!$D$4:$AG$100,0,MATCH(L$2,Inputs!$D$2:$AG$2,0)),Inputs!$B$4:$B$100,$B47)/1000) -> 3815.124 | M47: =IF(L47="","",L47) -> 3815.124 | N47: =IF(N$3=0,"",SUMIFS(INDEX(Inputs!$D$4:$AG$100,0,MATCH(N$2,Inputs!$D$2:$AG$2,0)),Inputs!$B$4:$B$100,$B47)/1000) -> 4045.076 | O47: =IF(O$3=0,"",SUMIFS(INDEX(Inputs!$D$4:$AG$100,0,MATCH(O$2,Inputs!$D$2:$AG$2,0)),Inputs!$B$4:$B$100,$B47)/1000) -> 3363.127 | P47: =IF(P$3=0,"",SUMIFS(INDEX(Inputs!$D$4:$AG$100,0,MATCH(P$2,Inputs!$D$2:$AG$2,0)),Inputs!$B$4:$B$100,$B47)/1000) -> 2525.011 | Q47: =IF(Q$3=0,"",SUMIFS(INDEX(Inputs!$D$4:$AG$100,0,MATCH(Q$2,Inputs!$D$2:$AG$2,0)),Inputs!$B$4:$B$100,$B47)/1000) -> 1132.604 | R47: =IF(Q47="","",Q47) -> 1132.604 | S47: =IF(S$3=0,"",SUMIFS(INDEX(Inputs!$D$4:$AG$100,0,MATCH(S$2,Inputs!$D$2:$AG$2,0)),Inputs!$B$4:$B$100,$B47)/1000) -> 986.222 | T47: =IF(T$3=0,"",SUMIFS(INDEX(Inputs!$D$4:$AG$100,0,MATCH(T$2,Inputs!$D$2:$AG$2,0)),Inputs!$B$4:$B$100,$B47)/1000) -> 1077.311 | U47: =IF(U$3=0,"",SUMIFS(INDEX(Inputs!$D$4:$AG$100,0,MATCH(U$2,Inputs!$D$2:$AG$2,0)),Inputs!$B$4:$B$100,$B47)/1000) -> 1348.141 | V47: =IF(V$3=0,"",SUMIFS(INDEX(Inputs!$D$4:$AG$100,0,MATCH(V$2,Inputs!$D$2:$AG$2,0)),Inputs!$B$4:$B$100,$B47)/1000) -> 923.944 | W47: =IF(V47="","",V47) -> 923.944 | X47: =IF(X$3=0,"",SUMIFS(INDEX(Inputs!$D$4:$AG$100,0,MATCH(X$2,Inputs!$D$2:$AG$2,0)),Inputs!$B$4:$B$100,$B47)/1000) -> 932.44 | Y47: =IF(Y$3=0,"",SUMIFS(INDEX(Inputs!$D$4:$AG$100,0,MATCH(Y$2,Inputs!$D$2:$AG$2,0)),Inputs!$B$4:$B$100,$B47)/1000) -> 317.05 | Z47: =IF(Z$3=0,"",SUMIFS(INDEX(Inputs!$D$4:$AG$100,0,MATCH(Z$2,Inputs!$D$2:$AG$2,0)),Inputs!$B$4:$B$100,$B47)/1000) -> -79.984 | AA47: =IF(AA$3=0,"",SUMIFS(INDEX(Inputs!$D$4:$AG$100,0,MATCH(AA$2,Inputs!$D$2:$AG$2,0)),Inputs!$B$4:$B$100,$B47)/1000) -> 259.912 | AB47: =IF(AA47="","",AA47) -> 259.912 | AC47: =IF(AC$3=0,"",SUMIFS(INDEX(Inputs!$D$4:$AG$100,0,MATCH(AC$2,Inputs!$D$2:$AG$2,0)),Inputs!$B$4:$B$100,$B47)/1000) -> -361.426 | AD47: =IF(AD$3=0,"",SUMIFS(INDEX(Inputs!$D$4:$AG$100,0,MATCH(AD$2,Inputs!$D$2:$AG$2,0)),Inputs!$B$4:$B$100,$B47)/1000) -> -772.373 | AE47: =IF(AE$3=0,"",SUMIFS(INDEX(Inputs!$D$4:$AG$100,0,MATCH(AE$2,Inputs!$D$2:$AG$2,0)),Inputs!$B$4:$B$100,$B47)/1000) | AF47: =IF(AF$3=0,"",SUMIFS(INDEX(Inputs!$D$4:$AG$100,0,MATCH(AF$2,Inputs!$D$2:$AG$2,0)),Inputs!$B$4:$B$100,$B47)/1000) | AG47: =IF(AF47="","",AF47)
B48: 44 | C48: Net income reported (controladores) - memo p/ check IS [Model linha 4] | D48: =IF(D$3=0,"",SUMIFS(INDEX(Inputs!$D$4:$AG$100,0,MATCH(D$2,Inputs!$D$2:$AG$2,0)),Inputs!$B$4:$B$100,$B48)/1000) -> 10.128 | E48: =IF(E$3=0,"",SUMIFS(INDEX(Inputs!$D$4:$AG$100,0,MATCH(E$2,Inputs!$D$2:$AG$2,0)),Inputs!$B$4:$B$100,$B48)/1000) -> -71.057 | F48: =IF(F$3=0,"",SUMIFS(INDEX(Inputs!$D$4:$AG$100,0,MATCH(F$2,Inputs!$D$2:$AG$2,0)),Inputs!$B$4:$B$100,$B48)/1000) -> 82.245 | G48: =IF(G$3=0,"",SUMIFS(INDEX(Inputs!$D$4:$AG$100,0,MATCH(G$2,Inputs!$D$2:$AG$2,0)),Inputs!$B$4:$B$100,$B48)/1000) -> 14.45 | H48: =IF(COUNT(D48:G48)=4,SUM(D48:G48),"") -> 35.766 | I48: =IF(I$3=0,"",SUMIFS(INDEX(Inputs!$D$4:$AG$100,0,MATCH(I$2,Inputs!$D$2:$AG$2,0)),Inputs!$B$4:$B$100,$B48)/1000) -> -6.799 | J48: =IF(J$3=0,"",SUMIFS(INDEX(Inputs!$D$4:$AG$100,0,MATCH(J$2,Inputs!$D$2:$AG$2,0)),Inputs!$B$4:$B$100,$B48)/1000) -> -2.027 | K48: =IF(K$3=0,"",SUMIFS(INDEX(Inputs!$D$4:$AG$100,0,MATCH(K$2,Inputs!$D$2:$AG$2,0)),Inputs!$B$4:$B$100,$B48)/1000) -> 230.086 | L48: =IF(L$3=0,"",SUMIFS(INDEX(Inputs!$D$4:$AG$100,0,MATCH(L$2,Inputs!$D$2:$AG$2,0)),Inputs!$B$4:$B$100,$B48)/1000) -> 2453.14 | M48: =IF(COUNT(I48:L48)=4,SUM(I48:L48),"") -> 2674.4 | N48: =IF(N$3=0,"",SUMIFS(INDEX(Inputs!$D$4:$AG$100,0,MATCH(N$2,Inputs!$D$2:$AG$2,0)),Inputs!$B$4:$B$100,$B48)/1000) -> 229.952 | O48: =IF(O$3=0,"",SUMIFS(INDEX(Inputs!$D$4:$AG$100,0,MATCH(O$2,Inputs!$D$2:$AG$2,0)),Inputs!$B$4:$B$100,$B48)/1000) -> 182.882 | P48: =IF(P$3=0,"",SUMIFS(INDEX(Inputs!$D$4:$AG$100,0,MATCH(P$2,Inputs!$D$2:$AG$2,0)),Inputs!$B$4:$B$100,$B48)/1000) -> -838.116 | Q48: =IF(Q$3=0,"",SUMIFS(INDEX(Inputs!$D$4:$AG$100,0,MATCH(Q$2,Inputs!$D$2:$AG$2,0)),Inputs!$B$4:$B$100,$B48)/1000) -> 107.593 | R48: =IF(COUNT(N48:Q48)=4,SUM(N48:Q48),"") -> -317.689 | S48: =IF(S$3=0,"",SUMIFS(INDEX(Inputs!$D$4:$AG$100,0,MATCH(S$2,Inputs!$D$2:$AG$2,0)),Inputs!$B$4:$B$100,$B48)/1000) -> 253.618 | T48: =IF(T$3=0,"",SUMIFS(INDEX(Inputs!$D$4:$AG$100,0,MATCH(T$2,Inputs!$D$2:$AG$2,0)),Inputs!$B$4:$B$100,$B48)/1000) -> 91.089 | U48: =IF(U$3=0,"",SUMIFS(INDEX(Inputs!$D$4:$AG$100,0,MATCH(U$2,Inputs!$D$2:$AG$2,0)),Inputs!$B$4:$B$100,$B48)/1000) -> 270.83 | V48: =IF(V$3=0,"",SUMIFS(INDEX(Inputs!$D$4:$AG$100,0,MATCH(V$2,Inputs!$D$2:$AG$2,0)),Inputs!$B$4:$B$100,$B48)/1000) -> -364.599 | W48: =IF(COUNT(S48:V48)=4,SUM(S48:V48),"") -> 250.938 | X48: =IF(X$3=0,"",SUMIFS(INDEX(Inputs!$D$4:$AG$100,0,MATCH(X$2,Inputs!$D$2:$AG$2,0)),Inputs!$B$4:$B$100,$B48)/1000) -> 8.496 | Y48: =IF(Y$3=0,"",SUMIFS(INDEX(Inputs!$D$4:$AG$100,0,MATCH(Y$2,Inputs!$D$2:$AG$2,0)),Inputs!$B$4:$B$100,$B48)/1000) -> -615.39 | Z48: =IF(Z$3=0,"",SUMIFS(INDEX(Inputs!$D$4:$AG$100,0,MATCH(Z$2,Inputs!$D$2:$AG$2,0)),Inputs!$B$4:$B$100,$B48)/1000) -> -397.034 | AA48: =IF(AA$3=0,"",SUMIFS(INDEX(Inputs!$D$4:$AG$100,0,MATCH(AA$2,Inputs!$D$2:$AG$2,0)),Inputs!$B$4:$B$100,$B48)/1000) -> 339.896 | AB48: =IF(COUNT(X48:AA48)=4,SUM(X48:AA48),"") -> -664.032 | AC48: =IF(AC$3=0,"",SUMIFS(INDEX(Inputs!$D$4:$AG$100,0,MATCH(AC$2,Inputs!$D$2:$AG$2,0)),Inputs!$B$4:$B$100,$B48)/1000) -> -621.338 | AD48: =IF(AD$3=0,"",SUMIFS(INDEX(Inputs!$D$4:$AG$100,0,MATCH(AD$2,Inputs!$D$2:$AG$2,0)),Inputs!$B$4:$B$100,$B48)/1000) -> -410.947 | AE48: =IF(AE$3=0,"",SUMIFS(INDEX(Inputs!$D$4:$AG$100,0,MATCH(AE$2,Inputs!$D$2:$AG$2,0)),Inputs!$B$4:$B$100,$B48)/1000) | AF48: =IF(AF$3=0,"",SUMIFS(INDEX(Inputs!$D$4:$AG$100,0,MATCH(AF$2,Inputs!$D$2:$AG$2,0)),Inputs!$B$4:$B$100,$B48)/1000) | AG48: =IF(COUNT(AC48:AF48)=4,SUM(AC48:AF48),"")

Sheet Model
C1: CHECKS | I1: =IF(I2="","",SUM(I2,I3)) -> 0 | J1: =IF(J2="","",SUM(J2,J3)) -> 0 | K1: =IF(K2="","",SUM(K2,K3)) -> 0 | L1: =IF(L2="","",SUM(L2,L3)) -> 0 | M1: =IF(M2="","",SUM(M2,M3)) -> 0 | N1: =IF(N2="","",SUM(N2,N3)) -> 4.7073456e-14 | O1: =IF(O2="","",SUM(O2,O3)) -> 2.0428104e-14 | P1: =IF(P2="","",SUM(P2,P3)) -> 0.001 | ... BF1: =IF(BF2="","",SUM(BF2,BF3)) -> 0
C2: BS | I2: =IF(COUNT(I196,I272)<2,"",ABS(I196-I272)) -> 0 | J2: =IF(COUNT(J196,J272)<2,"",ABS(J196-J272)) -> 0 | K2: =IF(COUNT(K196,K272)<2,"",ABS(K196-K272)) -> 0 | L2: =IF(COUNT(L196,L272)<2,"",ABS(L196-L272)) -> 0 | M2: =IF(COUNT(M196,M272)<2,"",ABS(M196-M272)) -> 0 | N2: =IF(COUNT(N196,N272)<2,"",ABS(N196-N272)) -> 0 | O2: =IF(COUNT(O196,O272)<2,"",ABS(O196-O272)) -> 0 | P2: =IF(COUNT(P196,P272)<2,"",ABS(P196-P272)) -> 0 | ... BF2: =IF(COUNT(BF196,BF272)<2,"",ABS(BF196-BF272)) -> 0
C3: IS | I3: =IF(COUNT(I4,I136)<2,"",ABS(I136-I4)) -> 0 | J3: =IF(COUNT(J4,J136)<2,"",ABS(J136-J4)) -> 0 | K3: =IF(COUNT(K4,K136)<2,"",ABS(K136-K4)) -> 0 | L3: =IF(COUNT(L4,L136)<2,"",ABS(L136-L4)) -> 0 | M3: =IF(COUNT(M4,M136)<2,"",ABS(M136-M4)) -> 0 | N3: =IF(COUNT(N4,N136)<2,"",ABS(N136-N4)) -> 4.7073456e-14 | O3: =IF(COUNT(O4,O136)<2,"",ABS(O136-O4)) -> 2.0428104e-14 | P3: =IF(COUNT(P4,P136)<2,"",ABS(P136-P4)) -> 0.001 | ... AI3: =IF(COUNT(AI4,AI136)<2,"",ABS(AI136-AI4)) -> 0
C4: Net Income reportado (controladores, CVM) - base do check IS | I4: ='Inputs (2)'!D48 -> 10.128 | J4: ='Inputs (2)'!E48 -> -71.057 | K4: ='Inputs (2)'!F48 -> 82.245 | L4: ='Inputs (2)'!G48 -> 14.45 | M4: ='Inputs (2)'!H48 -> 35.766 | N4: ='Inputs (2)'!I48 -> -6.799 | O4: ='Inputs (2)'!J48 -> -2.027 | P4: ='Inputs (2)'!K48 -> 230.086 | ... AI4: ='Inputs (2)'!AD48 -> -410.947
B5: 45930 | I5: 44286 | J5: =DATE(YEAR(I5),MONTH(I5)+3,DAY(I5)-1) -> 44377 | K5: =DATE(YEAR(J5),MONTH(J5)+3,DAY(J5)) -> 44469 | L5: =DATE(YEAR(K5),MONTH(K5)+3,DAY(K5)+1) -> 44561 | M5: =L5 -> 44561 | N5: =DATE(YEAR(M5),MONTH(M5)+3,DAY(M5)) -> 44651 | O5: =DATE(YEAR(N5),MONTH(N5)+3,DAY(N5)-1) -> 44742 | P5: =DATE(YEAR(O5),MONTH(O5)+3,DAY(O5)) -> 44834 | Q5: =DATE(YEAR(P5),MONTH(P5)+3,DAY(P5)+1) -> 44926 | R5: =Q5 -> 44926 | S5: =DATE(YEAR(R5),MONTH(R5)+3,DAY(R5)) -> 45016 | T5: =DATE(YEAR(S5),MONTH(S5)+3,DAY(S5))-1 -> 45107 | U5: =DATE(YEAR(T5),MONTH(T5)+3,DAY(T5)) -> 45199 | V5: =DATE(YEAR(U5),MONTH(U5)+3,DAY(U5))+1 -> 45291 | W5: =V5 -> 45291 | X5: =DATE(YEAR(W5),MONTH(W5)+3,DAY(W5)) -> 45382 | Y5: =DATE(YEAR(X5),MONTH(X5)+3,DAY(X5))-1 -> 45473 | Z5: =DATE(YEAR(Y5),MONTH(Y5)+3,DAY(Y5)) -> 45565 | AA5: =DATE(YEAR(Z5),MONTH(Z5)+3,DAY(Z5))+1 -> 45657 | AB5: =AA5 -> 45657 | AC5: =DATE(YEAR(AB5),MONTH(AB5)+3,DAY(AB5)) -> 45747 | AD5: =DATE(YEAR(AC5),MONTH(AC5)+3,DAY(AC5))-1 -> 45838 | AE5: =DATE(YEAR(AD5),MONTH(AD5)+3,DAY(AD5)) -> 45930 | AF5: =DATE(YEAR(AE5),MONTH(AE5)+3,DAY(AE5))+1 -> 46022 | AG5: =AF5 -> 46022 | AH5: =DATE(YEAR(AG5),MONTH(AG5)+3,DAY(AG5)) -> 46112 | AI5: =DATE(YEAR(AH5),MONTH(AH5)+3,DAY(AH5))-1 -> 46203 | AJ5: =DATE(YEAR(AI5),MONTH(AI5)+3,DAY(AI5)) -> 46295 | AK5: =DATE(YEAR(AJ5),MONTH(AJ5)+3,DAY(AJ5))+1 -> 46387 | AL5: =AK5 -> 46387 | AM5: =DATE(YEAR(AL5),MONTH(AL5)+3,DAY(AL5)) -> 46477 | AN5: =DATE(YEAR(AM5),MONTH(AM5)+3,DAY(AM5))-1 -> 46568 | AO5: =DATE(YEAR(AN5),MONTH(AN5)+3,DAY(AN5)) -> 46660 | AP5: =DATE(YEAR(AO5),MONTH(AO5)+3,DAY(AO5))+1 -> 46752 | AQ5: =AP5 -> 46752 | AR5: =DATE(YEAR(AQ5),MONTH(AQ5)+3,DAY(AQ5)) -> 46843 | AS5: =DATE(YEAR(AR5),MONTH(AR5)+3,DAY(AR5))-1 -> 46934 | AT5: =DATE(YEAR(AS5),MONTH(AS5)+3,DAY(AS5)) -> 47026 | AU5: =DATE(YEAR(AT5),MONTH(AT5)+3,DAY(AT5))+1 -> 47118 | AV5: =AU5 -> 47118 | AW5: =DATE(YEAR(AV5),MONTH(AV5)+3,DAY(AV5)) -> 47208 | AX5: =DATE(YEAR(AW5),MONTH(AW5)+3,DAY(AW5))-1 -> 47299 | AY5: =DATE(YEAR(AX5),MONTH(AX5)+3,DAY(AX5)) -> 47391 | AZ5: =DATE(YEAR(AY5),MONTH(AY5)+3,DAY(AY5))+1 -> 47483 | BA5: =AZ5 -> 47483 | BB5: =DATE(YEAR(BA5),MONTH(BA5)+3,DAY(BA5)) -> 47573 | BC5: =DATE(YEAR(BB5),MONTH(BB5)+3,DAY(BB5))-1 -> 47664 | BD5: =DATE(YEAR(BC5),MONTH(BC5)+3,DAY(BC5)) -> 47756 | BE5: =DATE(YEAR(BD5),MONTH(BD5)+3,DAY(BD5))+1 -> 47848 | BF5: =BE5 -> 47848
I6: =YEAR(I5) -> 2021 | J6: =YEAR(J5) -> 2021 | K6: =YEAR(K5) -> 2021 | L6: =YEAR(L5) -> 2021 | M6: =YEAR(M5) -> 2021 | N6: =YEAR(N5) -> 2022 | O6: =YEAR(O5) -> 2022 | P6: =YEAR(P5) -> 2022 | ... BF6: =YEAR(BF5) -> 2030
H7: 2020 | I7: ="1Q"&RIGHT(I6,2) -> 1Q21 | J7: ="2Q"&RIGHT(J6,2) -> 2Q21 | K7: ="3Q"&RIGHT(K6,2) -> 3Q21 | L7: ="4Q"&RIGHT(L6,2) -> 4Q21 | M7: =H7+1 -> 2021 | N7: ="1Q"&RIGHT(N6,2) -> 1Q22 | O7: ="2Q"&RIGHT(O6,2) -> 2Q22 | P7: ="3Q"&RIGHT(P6,2) -> 3Q22 | Q7: ="4Q"&RIGHT(Q6,2) -> 4Q22 | R7: =M7+1 -> 2022 | S7: ="1Q"&RIGHT(S6,2) -> 1Q23 | T7: ="2Q"&RIGHT(T6,2) -> 2Q23 | U7: ="3Q"&RIGHT(U6,2) -> 3Q23 | V7: ="4Q"&RIGHT(V6,2) -> 4Q23 | W7: =R7+1 -> 2023 | X7: ="1Q"&RIGHT(X6,2) -> 1Q24 | Y7: ="2Q"&RIGHT(Y6,2) -> 2Q24 | Z7: ="3Q"&RIGHT(Z6,2) -> 3Q24 | AA7: ="4Q"&RIGHT(AA6,2) -> 4Q24 | AB7: =W7+1 -> 2024 | AC7: ="1Q"&RIGHT(AC6,2) -> 1Q25 | AD7: ="2Q"&RIGHT(AD6,2) -> 2Q25 | AE7: ="3Q"&RIGHT(AE6,2) -> 3Q25 | AF7: ="4Q"&RIGHT(AF6,2) -> 4Q25 | AG7: =AB7+1 -> 2025 | AH7: ="1Q"&RIGHT(AH6,2) -> 1Q26 | AI7: ="2Q"&RIGHT(AI6,2) -> 2Q26 | AJ7: ="3Q"&RIGHT(AJ6,2) -> 3Q26 | AK7: ="4Q"&RIGHT(AK6,2) -> 4Q26 | AL7: =AG7+1 -> 2026 | AM7: ="1Q"&RIGHT(AM6,2) -> 1Q27 | AN7: ="2Q"&RIGHT(AN6,2) -> 2Q27 | AO7: ="3Q"&RIGHT(AO6,2) -> 3Q27 | AP7: ="4Q"&RIGHT(AP6,2) -> 4Q27 | AQ7: =AL7+1 -> 2027 | AR7: ="1Q"&RIGHT(AR6,2) -> 1Q28 | AS7: ="2Q"&RIGHT(AS6,2) -> 2Q28 | AT7: ="3Q"&RIGHT(AT6,2) -> 3Q28 | AU7: ="4Q"&RIGHT(AU6,2) -> 4Q28 | AV7: =AQ7+1 -> 2028 | AW7: ="1Q"&RIGHT(AW6,2) -> 1Q29 | AX7: ="2Q"&RIGHT(AX6,2) -> 2Q29 | AY7: ="3Q"&RIGHT(AY6,2) -> 3Q29 | AZ7: ="4Q"&RIGHT(AZ6,2) -> 4Q29 | BA7: =AV7+1 -> 2029 | BB7: ="1Q"&RIGHT(BB6,2) -> 1Q30 | BC7: ="2Q"&RIGHT(BC6,2) -> 2Q30 | BD7: ="3Q"&RIGHT(BD6,2) -> 3Q30 | BE7: ="4Q"&RIGHT(BE6,2) -> 4Q30 | BF7: =BA7+1 -> 2030
C8: IPCA | M8: 0.1006 | R8: 0.0579 | W8: 0.0468 | AB8: 0.0483 | AG8: 0.0468
C9: GDP BRAZIL | M9: 0.046
C10: CDI | M10: 0.0442 | R10: 0.1239 | W10: 0.1304 | AB10: 0.1064 | AG10: 0.1464
C13: Income Statement | I13: =I7 -> 1Q21 | J13: =J7 -> 2Q21 | K13: =K7 -> 3Q21 | L13: =L7 -> 4Q21 | M13: =M7 -> 2021 | N13: =N7 -> 1Q22 | O13: =O7 -> 2Q22 | P13: =P7 -> 3Q22 | ... BF13: =BF7 -> 2030
C15: Net Revenues | I15: ='Inputs (2)'!D4 -> 552.151 | J15: ='Inputs (2)'!E4 -> 581.104 | K15: ='Inputs (2)'!F4 -> 616.194 | L15: ='Inputs (2)'!G4 -> 767.313 | M15: ='Inputs (2)'!H4 -> 2516.762 | N15: ='Inputs (2)'!I4 -> 1145.258 | O15: ='Inputs (2)'!J4 -> 1346.655 | P15: ='Inputs (2)'!K4 -> 1538.901 | ... AI15: ='Inputs (2)'!AD4 -> 3055.499 | AJ15: =IF(ISNUMBER(AJ40),AJ40,AE15*(1+AJ16)) -> 4051.3094 | AK15: =IF(ISNUMBER(AK40),AK40,AF15*(1+AK16)) -> 4354.0509 | AL15: =SUM(AH15:AK15) -> 14535.394 | AM15: =IF(ISNUMBER(AM40),AM40,AH15*(1+AM16)) -> 3521.2089 | AN15: =IF(ISNUMBER(AN40),AN40,AI15*(1+AN16)) -> 3499.4073 | AO15: =IF(ISNUMBER(AO40),AO40,AJ15*(1+AO16)) -> 4639.8909 | AP15: =IF(ISNUMBER(AP40),AP40,AK15*(1+AP16)) -> 4986.6152 | AQ15: =SUM(AM15:AP15) -> 16647.122 | AR15: =IF(ISNUMBER(AR40),AR40,AM15*(1+AR16)) -> 4015.1703 | AS15: =IF(ISNUMBER(AS40),AS40,AN15*(1+AS16)) -> 3990.3104 | AT15: =IF(ISNUMBER(AT40),AT40,AO15*(1+AT16)) -> 5290.783 | AU15: =IF(ISNUMBER(AU40),AU40,AP15*(1+AU16)) -> 5686.1464 | AV15: =SUM(AR15:AU15) -> 18982.41 | AW15: =IF(ISNUMBER(AW40),AW40,AR15*(1+AW16)) -> 4558.3497 | AX15: =IF(ISNUMBER(AX40),AX40,AS15*(1+AX16)) -> 4530.1267 | AY15: =IF(ISNUMBER(AY40),AY40,AT15*(1+AY16)) -> 6006.5295 | AZ15: =IF(ISNUMBER(AZ40),AZ40,AU15*(1+AZ16)) -> 6455.3784 | BA15: =SUM(AW15:AZ15) -> 21550.384 | BB15: =IF(ISNUMBER(BB40),BB40,AW15*(1+BB16)) -> 5152.2196 | BC15: =IF(ISNUMBER(BC40),BC40,AX15*(1+BC16)) -> 5120.3196 | BD15: =IF(ISNUMBER(BD40),BD40,AY15*(1+BD16)) -> 6789.0709 | BE15: =IF(ISNUMBER(BE40),BE40,AZ15*(1+BE16)) -> 7296.3966 | BF15: =SUM(BB15:BE15) -> 24358.007
C16: % YoY (2025: contra 2024 pro forma com AES, linha 41) | N16: =IFERROR(N15/I15-1,"") -> 1.0741754 | O16: =IFERROR(O15/J15-1,"") -> 1.3174079 | P16: =IFERROR(P15/K15-1,"") -> 1.4974294 | Q16: =IFERROR(Q15/L15-1,"") -> 0.93518421 | R16: =IFERROR(R15/M15-1,"") -> 1.1915882 | S16: =IFERROR(S15/N15-1,"") -> 0.23510161 | T16: =IFERROR(T15/O15-1,"") -> 0.0671538 | U16: =IFERROR(U15/P15-1,"") -> 0.056981573 | ... AB16: =IFERROR(AB15/W15-1,"") -> 0.30380046 | AC16: =IFERROR(AC15/X41-1,"") -> 0.3362725 | AD16: =IFERROR(AD15/Y41-1,"") -> 0.2502915 | AE16: =IFERROR(AE15/Z41-1,"") -> 0.12846885 | AF16: =IFERROR(AF15/AA41-1,"") -> 0.056351272 | AG16: =IFERROR(AG15/AB41-1,"") -> 0.17119624 | AH16: =IFERROR(AH15/AC15-1,"") -> 0.041402254 | AI16: =IFERROR(AI15/AD15-1,"") -> 0.058904277 | AJ16: =Control!$B$18 -> 0.14528178 | AK16: =Control!$B$18 -> 0.14528178 | AL16: =IFERROR(AL15/AG15-1,"") -> 0.10309231 | AM16: =Control!$C$18 -> 0.14528178 | AN16: =Control!$C$18 -> 0.14528178 | AO16: =Control!$C$18 -> 0.14528178 | AP16: =Control!$C$18 -> 0.14528178 | AQ16: =IFERROR(AQ15/AL15-1,"") -> 0.14528178 | AR16: =Control!$D$18 -> 0.14028178 | AS16: =Control!$D$18 -> 0.14028178 | AT16: =Control!$D$18 -> 0.14028178 | AU16: =Control!$D$18 -> 0.14028178 | AV16: =IFERROR(AV15/AQ15-1,"") -> 0.14028178 | AW16: =Control!$E$18 -> 0.13528178 | AX16: =Control!$E$18 -> 0.13528178 | AY16: =Control!$E$18 -> 0.13528178 | AZ16: =Control!$E$18 -> 0.13528178 | BA16: =IFERROR(BA15/AV15-1,"") -> 0.13528178 | BB16: =Control!$F$18 -> 0.13028178 | BC16: =Control!$F$18 -> 0.13028178 | BD16: =Control!$F$18 -> 0.13028178 | BE16: =Control!$F$18 -> 0.13028178 | BF16: =IFERROR(BF15/BA15-1,"") -> 0.13028178
C17: Check Receita (só de 1T25 em diante; até 4T24 o build é pro forma e a receita reportada é a CVM) | AC17: =IF(AND(ISNUMBER(AC15),ISNUMBER(AC40)),IF(AC15<>0,ROUND(AC15-AC40,3),""),"") -> 0 | AD17: =IF(AND(ISNUMBER(AD15),ISNUMBER(AD40)),IF(AD15<>0,ROUND(AD15-AD40,3),""),"") -> 0 | AE17: =IF(AND(ISNUMBER(AE15),ISNUMBER(AE40)),IF(AE15<>0,ROUND(AE15-AE40,3),""),"") -> 0 | AF17: =IF(AND(ISNUMBER(AF15),ISNUMBER(AF40)),IF(AF15<>0,ROUND(AF15-AF40,3),""),"") -> 0 | AG17: =IF(AND(ISNUMBER(AG15),ISNUMBER(AG40)),IF(AG15<>0,ROUND(AG15-AG40,3),""),"") -> 0 | AH17: =IF(AND(ISNUMBER(AH15),ISNUMBER(AH40)),IF(AH15<>0,ROUND(AH15-AH40,3),""),"") -> 0 | AI17: =IF(AND(ISNUMBER(AI15),ISNUMBER(AI40)),IF(AI15<>0,ROUND(AI15-AI40,3),""),"") -> 0 | AJ17: =IF(AND(ISNUMBER(AJ15),ISNUMBER(AJ40)),IF(AJ15<>0,ROUND(AJ15-AJ40,3),""),"") | ... BF17: =IF(AND(ISNUMBER(BF15),ISNUMBER(BF40)),IF(BF15<>0,ROUND(BF15-BF40,3),""),"")
C19: Revenue Build - por segmento (R$ mn) - 2021-22: Auren sem AES | 2023 em diante: proforma com AES Brasil
C20: Geração
C21: Geração hidrelétrica (MW médios) | I21: 870 | J21: 768 | K21: 750 | L21: 766 | M21: =IF(COUNT(I21:L21)=4,SUMPRODUCT(I21:L21,I25:L25)/M25,"") -> 788.10959 | N21: 821 | O21: 728 | P21: 835 | Q21: 825 | R21: =IF(COUNT(N21:Q21)=4,SUMPRODUCT(N21:Q21,N25:Q25)/R25,"") -> 802.35068 | V21: 2463 | W21: 2333 | X21: 2087 | Y21: 1534 | Z21: 1663.7 | AA21: 2033.1 | AB21: =IF(COUNT(X21:AA21)=4,SUMPRODUCT(X21:AA21,X25:AA25)/AB25,"") -> 1829.5536 | AC21: 2576.8 | AD21: 1784.4 | AE21: 1589.4 | AF21: 1812.6 | AG21: =IF(COUNT(AC21:AF21)=4,SUMPRODUCT(AC21:AF21,AC25:AF25)/AG25,"") -> 1937.7436 | AH21: 2062.2 | AI21: 1943.3 | AL21: =IF(COUNT(AH21:AK21)=4,SUMPRODUCT(AH21:AK21,AH25:AK25)/AL25,"") | AQ21: =IF(COUNT(AM21:AP21)=4,SUMPRODUCT(AM21:AP21,AM25:AP25)/AQ25,"") | AV21: =IF(COUNT(AR21:AU21)=4,SUMPRODUCT(AR21:AU21,AR25:AU25)/AV25,"") | BA21: =IF(COUNT(AW21:AZ21)=4,SUMPRODUCT(AW21:AZ21,AW25:AZ25)/BA25,"") | BF21: =IF(COUNT(BB21:BE21)=4,SUMPRODUCT(BB21:BE21,BB25:BE25)/BF25,"")
C22: Geração eólica (MW médios) | I22: 108 | J22: 199 | K22: 302 | L22: 155 | M22: =IF(COUNT(I22:L22)=4,SUMPRODUCT(I22:L22,I25:L25)/M25,"") -> 191.43288 | N22: 132 | O22: 294 | P22: 540 | Q22: 348 | R22: =IF(COUNT(N22:Q22)=4,SUMPRODUCT(N22:Q22,N25:Q25)/R25,"") -> 329.67123 | V22: 1074 | W22: 998 | X22: 704.3 | Y22: 1137 | Z22: 1473.7 | AA22: 1238.6 | AB22: =IF(COUNT(X22:AA22)=4,SUMPRODUCT(X22:AA22,X25:AA25)/AB25,"") -> 1139.5899 | AC22: 994.9 | AD22: 1279.2 | AE22: 1510.5 | AF22: 1178.2 | AG22: =IF(COUNT(AC22:AF22)=4,SUMPRODUCT(AC22:AF22,AC25:AF25)/AG25,"") -> 1241.9414 | AH22: 835.2 | AI22: 1152.5 | AL22: =IF(COUNT(AH22:AK22)=4,SUMPRODUCT(AH22:AK22,AH25:AK25)/AL25,"") | AQ22: =IF(COUNT(AM22:AP22)=4,SUMPRODUCT(AM22:AP22,AM25:AP25)/AQ25,"") | AV22: =IF(COUNT(AR22:AU22)=4,SUMPRODUCT(AR22:AU22,AR25:AU25)/AV25,"") | BA22: =IF(COUNT(AW22:AZ22)=4,SUMPRODUCT(AW22:AZ22,AW25:AZ25)/BA25,"") | BF22: =IF(COUNT(BB22:BE22)=4,SUMPRODUCT(BB22:BE22,BB25:BE25)/BF25,"")
C23: Geração solar (MW médios) | M23: =IF(COUNT(I23:L23)=4,SUMPRODUCT(I23:L23,I25:L25)/M25,"") | R23: =IF(COUNT(N23:Q23)=4,SUMPRODUCT(N23:Q23,N25:Q25)/R25,"") | V23: 70 | W23: 64 | X23: 93.1 | Y23: 112 | Z23: 168.8 | AA23: 189.4 | AB23: =IF(COUNT(X23:AA23)=4,SUMPRODUCT(X23:AA23,X25:AA25)/AB25,"") -> 141.03415 | AC23: 205.2 | AD23: 144.3 | AE23: 163.2 | AF23: 178.2 | AG23: =IF(COUNT(AC23:AF23)=4,SUMPRODUCT(AC23:AF23,AC25:AF25)/AG25,"") -> 172.62493 | AH23: 186.9 | AI23: 154.6 | AL23: =IF(COUNT(AH23:AK23)=4,SUMPRODUCT(AH23:AK23,AH25:AK25)/AL25,"") | AQ23: =IF(COUNT(AM23:AP23)=4,SUMPRODUCT(AM23:AP23,AM25:AP25)/AQ25,"") | AV23: =IF(COUNT(AR23:AU23)=4,SUMPRODUCT(AR23:AU23,AR25:AU25)/AV25,"") | BA23: =IF(COUNT(AW23:AZ23)=4,SUMPRODUCT(AW23:AZ23,AW25:AZ25)/BA25,"") | BF23: =IF(COUNT(BB23:BE23)=4,SUMPRODUCT(BB23:BE23,BB25:BE25)/BF25,"")
C24: Geração total (MW médios) | I24: =IF(COUNT(I21,I22)=2,SUM(I21:I23),"") -> 978 | J24: =IF(COUNT(J21,J22)=2,SUM(J21:J23),"") -> 967 | K24: =IF(COUNT(K21,K22)=2,SUM(K21:K23),"") -> 1052 | L24: =IF(COUNT(L21,L22)=2,SUM(L21:L23),"") -> 921 | M24: =IF(COUNT(M21,M22)=2,SUM(M21:M23),"") -> 979.54247 | N24: =IF(COUNT(N21,N22)=2,SUM(N21:N23),"") -> 953 | O24: =IF(COUNT(O21,O22)=2,SUM(O21:O23),"") -> 1022 | P24: =IF(COUNT(P21,P22)=2,SUM(P21:P23),"") -> 1375 | ... V24: =IF(COUNT(V21,V22)=2,SUM(V21:V23),"") -> 3607 | W24: =SUM(W21:W23) -> 3395 | X24: =IF(COUNT(X21,X22)=2,SUM(X21:X23),"") -> 2884.4 | Y24: =IF(COUNT(Y21,Y22)=2,SUM(Y21:Y23),"") -> 2783 | Z24: =IF(COUNT(Z21,Z22)=2,SUM(Z21:Z23),"") -> 3306.2 | AA24: =IF(COUNT(AA21,AA22)=2,SUM(AA21:AA23),"") -> 3461.1 | AB24: =IF(COUNT(AB21,AB22)=2,SUM(AB21:AB23),"") -> 3110.1776 | AC24: =IF(COUNT(AC21,AC22)=2,SUM(AC21:AC23),"") -> 3776.9 | AD24: =IF(COUNT(AD21,AD22)=2,SUM(AD21:AD23),"") -> 3207.9 | AE24: =IF(COUNT(AE21,AE22)=2,SUM(AE21:AE23),"") -> 3263.1 | ... BF24: =IF(COUNT(BF21,BF22)=2,SUM(BF21:BF23),"")
C25: Horas no período | I25: =24*(I$5-EOMONTH(I$5,-3)) -> 2160 | J25: =24*(J$5-EOMONTH(J$5,-3)) -> 2184 | K25: =24*(K$5-EOMONTH(K$5,-3)) -> 2208 | L25: =24*(L$5-EOMONTH(L$5,-3)) -> 2208 | M25: =SUM(I25:L25) -> 8760 | N25: =24*(N$5-EOMONTH(N$5,-3)) -> 2160 | O25: =24*(O$5-EOMONTH(O$5,-3)) -> 2184 | P25: =24*(P$5-EOMONTH(P$5,-3)) -> 2208 | Q25: =24*(Q$5-EOMONTH(Q$5,-3)) -> 2208 | R25: =SUM(N25:Q25) -> 8760 | S25: =24*(S$5-EOMONTH(S$5,-3)) -> 2160 | T25: =24*(T$5-EOMONTH(T$5,-3)) -> 2184 | U25: =24*(U$5-EOMONTH(U$5,-3)) -> 2208 | V25: =24*(V$5-EOMONTH(V$5,-3)) -> 2208 | W25: =SUM(S25:V25) -> 8760 | X25: =24*(X$5-EOMONTH(X$5,-3)) -> 2184 | Y25: =24*(Y$5-EOMONTH(Y$5,-3)) -> 2184 | Z25: =24*(Z$5-EOMONTH(Z$5,-3)) -> 2208 | AA25: =24*(AA$5-EOMONTH(AA$5,-3)) -> 2208 | AB25: =SUM(X25:AA25) -> 8784 | AC25: =24*(AC$5-EOMONTH(AC$5,-3)) -> 2160 | AD25: =24*(AD$5-EOMONTH(AD$5,-3)) -> 2184 | AE25: =24*(AE$5-EOMONTH(AE$5,-3)) -> 2208 | AF25: =24*(AF$5-EOMONTH(AF$5,-3)) -> 2208 | AG25: =SUM(AC25:AF25) -> 8760 | AH25: =24*(AH$5-EOMONTH(AH$5,-3)) -> 2160 | AI25: =24*(AI$5-EOMONTH(AI$5,-3)) -> 2184 | AJ25: =24*(AJ$5-EOMONTH(AJ$5,-3)) -> 2208 | AK25: =24*(AK$5-EOMONTH(AK$5,-3)) -> 2208 | AL25: =SUM(AH25:AK25) -> 8760 | AM25: =24*(AM$5-EOMONTH(AM$5,-3)) -> 2160 | AN25: =24*(AN$5-EOMONTH(AN$5,-3)) -> 2184 | AO25: =24*(AO$5-EOMONTH(AO$5,-3)) -> 2208 | AP25: =24*(AP$5-EOMONTH(AP$5,-3)) -> 2208 | AQ25: =SUM(AM25:AP25) -> 8760 | AR25: =24*(AR$5-EOMONTH(AR$5,-3)) -> 2184 | AS25: =24*(AS$5-EOMONTH(AS$5,-3)) -> 2184 | AT25: =24*(AT$5-EOMONTH(AT$5,-3)) -> 2208 | AU25: =24*(AU$5-EOMONTH(AU$5,-3)) -> 2208 | AV25: =SUM(AR25:AU25) -> 8784 | AW25: =24*(AW$5-EOMONTH(AW$5,-3)) -> 2160 | AX25: =24*(AX$5-EOMONTH(AX$5,-3)) -> 2184 | AY25: =24*(AY$5-EOMONTH(AY$5,-3)) -> 2208 | AZ25: =24*(AZ$5-EOMONTH(AZ$5,-3)) -> 2208 | BA25: =SUM(AW25:AZ25) -> 8760 | BB25: =24*(BB$5-EOMONTH(BB$5,-3)) -> 2160 | BC25: =24*(BC$5-EOMONTH(BC$5,-3)) -> 2184 | BD25: =24*(BD$5-EOMONTH(BD$5,-3)) -> 2208 | BE25: =24*(BE$5-EOMONTH(BE$5,-3)) -> 2208 | BF25: =SUM(BB25:BE25) -> 8760
C26: Energia gerada (GWh) | I26: =IF(ISNUMBER(I24),I24*I25/1000,"") -> 2112.48 | J26: =IF(ISNUMBER(J24),J24*J25/1000,"") -> 2111.928 | K26: =IF(ISNUMBER(K24),K24*K25/1000,"") -> 2322.816 | L26: =IF(ISNUMBER(L24),L24*L25/1000,"") -> 2033.568 | M26: =IF(COUNT(I26:L26)=4,SUM(I26:L26),"") -> 8580.792 | N26: =IF(ISNUMBER(N24),N24*N25/1000,"") -> 2058.48 | O26: =IF(ISNUMBER(O24),O24*O25/1000,"") -> 2232.048 | P26: =IF(ISNUMBER(P24),P24*P25/1000,"") -> 3036 | Q26: =IF(ISNUMBER(Q24),Q24*Q25/1000,"") -> 2589.984 | R26: =IF(COUNT(N26:Q26)=4,SUM(N26:Q26),"") -> 9916.512 | S26: =IF(ISNUMBER(S24),S24*S25/1000,"") | T26: =IF(ISNUMBER(T24),T24*T25/1000,"") | U26: =IF(ISNUMBER(U24),U24*U25/1000,"") | V26: =IF(ISNUMBER(V24),V24*V25/1000,"") -> 7964.256 | W26: =W24*W25/1000 -> 29740.2 | X26: =IF(ISNUMBER(X24),X24*X25/1000,"") -> 6299.5296 | Y26: =IF(ISNUMBER(Y24),Y24*Y25/1000,"") -> 6078.072 | Z26: =IF(ISNUMBER(Z24),Z24*Z25/1000,"") -> 7300.0896 | AA26: =IF(ISNUMBER(AA24),AA24*AA25/1000,"") -> 7642.1088 | AB26: =IF(COUNT(X26:AA26)=4,SUM(X26:AA26),"") -> 27319.8 | AC26: =IF(ISNUMBER(AC24),AC24*AC25/1000,"") -> 8158.104 | AD26: =IF(ISNUMBER(AD24),AD24*AD25/1000,"") -> 7006.0536 | AE26: =IF(ISNUMBER(AE24),AE24*AE25/1000,"") -> 7204.9248 | AF26: =IF(ISNUMBER(AF24),AF24*AF25/1000,"") -> 6997.152 | AG26: =IF(COUNT(AC26:AF26)=4,SUM(AC26:AF26),"") -> 29366.234 | AH26: =IF(ISNUMBER(AH24),AH24*AH25/1000,"") -> 6662.088 | AI26: =IF(ISNUMBER(AI24),AI24*AI25/1000,"") -> 7098.8736 | AJ26: =IF(ISNUMBER(AJ24),AJ24*AJ25/1000,"") | AK26: =IF(ISNUMBER(AK24),AK24*AK25/1000,"") | AL26: =IF(COUNT(AH26:AK26)=4,SUM(AH26:AK26),"") | AM26: =IF(ISNUMBER(AM24),AM24*AM25/1000,"") | AN26: =IF(ISNUMBER(AN24),AN24*AN25/1000,"") | AO26: =IF(ISNUMBER(AO24),AO24*AO25/1000,"") | AP26: =IF(ISNUMBER(AP24),AP24*AP25/1000,"") | AQ26: =IF(COUNT(AM26:AP26)=4,SUM(AM26:AP26),"") | AR26: =IF(ISNUMBER(AR24),AR24*AR25/1000,"") | AS26: =IF(ISNUMBER(AS24),AS24*AS25/1000,"") | AT26: =IF(ISNUMBER(AT24),AT24*AT25/1000,"") | AU26: =IF(ISNUMBER(AU24),AU24*AU25/1000,"") | AV26: =IF(COUNT(AR26:AU26)=4,SUM(AR26:AU26),"") | AW26: =IF(ISNUMBER(AW24),AW24*AW25/1000,"") | AX26: =IF(ISNUMBER(AX24),AX24*AX25/1000,"") | AY26: =IF(ISNUMBER(AY24),AY24*AY25/1000,"") | AZ26: =IF(ISNUMBER(AZ24),AZ24*AZ25/1000,"") | BA26: =IF(COUNT(AW26:AZ26)=4,SUM(AW26:AZ26),"") | BB26: =IF(ISNUMBER(BB24),BB24*BB25/1000,"") | BC26: =IF(ISNUMBER(BC24),BC24*BC25/1000,"") | BD26: =IF(ISNUMBER(BD24),BD24*BD25/1000,"") | BE26: =IF(ISNUMBER(BE24),BE24*BE25/1000,"") | BF26: =IF(COUNT(BB26:BE26)=4,SUM(BB26:BE26),"")
C27: Receita líquida de geração por MWh gerado (R$/MWh) | I27: =IFERROR(I28/I26*1000,"") -> 239.33954 | J27: =IFERROR(J28/J26*1000,"") -> 193.80396 | K27: =IFERROR(K28/K26*1000,"") -> 176.65024 | L27: =IFERROR(L28/L26*1000,"") -> 255.26562 | M27: =IFERROR(M28/M26*1000,"") -> 214.93657 | N27: =IFERROR(N28/N26*1000,"") -> 266.70116 | O27: =IFERROR(O28/O26*1000,"") -> 244.25998 | P27: =IFERROR(P28/P26*1000,"") -> 188.93742 | ... AI27: =IFERROR(AI28/AI26*1000,"") -> 248.72284 | AL27: =IFERROR(AL28/AL26*1000,"") | AQ27: =IFERROR(AQ28/AQ26*1000,"") | AV27: =IFERROR(AV28/AV26*1000,"") | BA27: =IFERROR(BA28/BA26*1000,"") | BF27: =IFERROR(BF28/BF26*1000,"")
C28: Receita líquida - Geração | I28: =I29+I30 -> 505.6 | J28: =J29+J30 -> 409.3 | K28: =K29+K30 -> 410.326 | L28: =L29+L30 -> 519.1 | M28: =IF(COUNT(I28:L28)=4,SUM(I28:L28),"") -> 1844.326 | N28: =N29+N30 -> 548.999 | O28: =O29+O30 -> 545.2 | P28: =P29+P30 -> 573.614 | Q28: =Q29+Q30 -> 588.1 | R28: =IF(COUNT(N28:Q28)=4,SUM(N28:Q28),"") -> 2255.913 | S28: 1251.7967 | T28: 1296.7953 | U28: 1431.8365 | V28: 1535.058 | W28: =IF(COUNT(S28:V28)=4,SUM(S28:V28),"") -> 5515.4865 | X28: 1326.1714 | Y28: 1363.8172 | Z28: 1603.1247 | AA28: 1795.5233 | AB28: =IF(COUNT(X28:AA28)=4,SUM(X28:AA28),"") -> 6088.6365 | AC28: 1621.001 | AD28: 1596.775 | AE28: 1636.05 | AF28: 1702.279 | AG28: =IF(COUNT(AC28:AF28)=4,SUM(AC28:AF28),"") -> 6556.105 | AH28: 1734.43 | AI28: 1765.652 | AJ28: =IF(COUNT(AJ26,AJ27)=2,AJ26*AJ27/1000,"") | AK28: =IF(COUNT(AK26,AK27)=2,AK26*AK27/1000,"") | AL28: =IF(COUNT(AH28:AK28)=4,SUM(AH28:AK28),"") | AM28: =IF(COUNT(AM26,AM27)=2,AM26*AM27/1000,"") | AN28: =IF(COUNT(AN26,AN27)=2,AN26*AN27/1000,"") | AO28: =IF(COUNT(AO26,AO27)=2,AO26*AO27/1000,"") | AP28: =IF(COUNT(AP26,AP27)=2,AP26*AP27/1000,"") | AQ28: =IF(COUNT(AM28:AP28)=4,SUM(AM28:AP28),"") | AR28: =IF(COUNT(AR26,AR27)=2,AR26*AR27/1000,"") | AS28: =IF(COUNT(AS26,AS27)=2,AS26*AS27/1000,"") | AT28: =IF(COUNT(AT26,AT27)=2,AT26*AT27/1000,"") | AU28: =IF(COUNT(AU26,AU27)=2,AU26*AU27/1000,"") | AV28: =IF(COUNT(AR28:AU28)=4,SUM(AR28:AU28),"") | AW28: =IF(COUNT(AW26,AW27)=2,AW26*AW27/1000,"") | AX28: =IF(COUNT(AX26,AX27)=2,AX26*AX27/1000,"") | AY28: =IF(COUNT(AY26,AY27)=2,AY26*AY27/1000,"") | AZ28: =IF(COUNT(AZ26,AZ27)=2,AZ26*AZ27/1000,"") | BA28: =IF(COUNT(AW28:AZ28)=4,SUM(AW28:AZ28),"") | BB28: =IF(COUNT(BB26,BB27)=2,BB26*BB27/1000,"") | BC28: =IF(COUNT(BC26,BC27)=2,BC26*BC27/1000,"") | BD28: =IF(COUNT(BD26,BD27)=2,BD26*BD27/1000,"") | BE28: =IF(COUNT(BE26,BE27)=2,BE26*BE27/1000,"") | BF28: =IF(COUNT(BB28:BE28)=4,SUM(BB28:BE28),"")
C29: Hidrelétrica | I29: 402.9 | J29: 353.4 | K29: 366.194 | L29: 390.5 | M29: =IF(COUNT(I29:L29)=4,SUM(I29:L29),"") -> 1512.994 | N29: 434.56 | O29: 409.8 | P29: 424.63 | Q29: 436.1 | R29: =IF(COUNT(N29:Q29)=4,SUM(N29:Q29),"") -> 1705.09 | W29: =IF(COUNT(S29:V29)=4,SUM(S29:V29),"") | AB29: =IF(COUNT(X29:AA29)=4,SUM(X29:AA29),"") | AC29: 989.315 | AD29: 1025.678 | AE29: 1036.118 | AF29: 1146.635 | AG29: =IF(COUNT(AC29:AF29)=4,SUM(AC29:AF29),"") -> 4197.746 | AH29: 1026.504 | AI29: 1001.865 | AL29: =IF(COUNT(AH29:AK29)=4,SUM(AH29:AK29),"") | AQ29: =IF(COUNT(AM29:AP29)=4,SUM(AM29:AP29),"") | AV29: =IF(COUNT(AR29:AU29)=4,SUM(AR29:AU29),"") | BA29: =IF(COUNT(AW29:AZ29)=4,SUM(AW29:AZ29),"") | BF29: =IF(COUNT(BB29:BE29)=4,SUM(BB29:BE29),"")
C30: Eólica | I30: 102.7 | J30: 55.9 | K30: 44.132 | L30: 128.6 | M30: =IF(COUNT(I30:L30)=4,SUM(I30:L30),"") -> 331.332 | N30: 114.439 | O30: 135.4 | P30: 148.984 | Q30: 152 | R30: =IF(COUNT(N30:Q30)=4,SUM(N30:Q30),"") -> 550.823 | W30: =IF(COUNT(S30:V30)=4,SUM(S30:V30),"") | AB30: =IF(COUNT(X30:AA30)=4,SUM(X30:AA30),"") | AC30: 598.287 | AD30: 638.558 | AE30: 625.168 | AF30: 619.044 | AG30: =IF(COUNT(AC30:AF30)=4,SUM(AC30:AF30),"") -> 2481.057 | AH30: 620.868 | AI30: 697.722 | AL30: =IF(COUNT(AH30:AK30)=4,SUM(AH30:AK30),"") | AQ30: =IF(COUNT(AM30:AP30)=4,SUM(AM30:AP30),"") | AV30: =IF(COUNT(AR30:AU30)=4,SUM(AR30:AU30),"") | BA30: =IF(COUNT(AW30:AZ30)=4,SUM(AW30:AZ30),"") | BF30: =IF(COUNT(BB30:BE30)=4,SUM(BB30:BE30),"")
C31: Solar | M31: =IF(COUNT(I31:L31)=4,SUM(I31:L31),"") | R31: =IF(COUNT(N31:Q31)=4,SUM(N31:Q31),"") | W31: =IF(COUNT(S31:V31)=4,SUM(S31:V31),"") | AB31: =IF(COUNT(X31:AA31)=4,SUM(X31:AA31),"") | AC31: 130.587 | AD31: 107.332 | AE31: 134.956 | AF31: 112.189 | AG31: =IF(COUNT(AC31:AF31)=4,SUM(AC31:AF31),"") -> 485.064 | AH31: 133.372 | AI31: 101.595 | AL31: =IF(COUNT(AH31:AK31)=4,SUM(AH31:AK31),"") | AQ31: =IF(COUNT(AM31:AP31)=4,SUM(AM31:AP31),"") | AV31: =IF(COUNT(AR31:AU31)=4,SUM(AR31:AU31),"") | BA31: =IF(COUNT(AW31:AZ31)=4,SUM(AW31:AZ31),"") | BF31: =IF(COUNT(BB31:BE31)=4,SUM(BB31:BE31),"")
C32: Eliminações da geração | M32: =IF(COUNT(I32:L32)=4,SUM(I32:L32),"") | R32: =IF(COUNT(N32:Q32)=4,SUM(N32:Q32),"") | W32: =IF(COUNT(S32:V32)=4,SUM(S32:V32),"") | AB32: =IF(COUNT(X32:AA32)=4,SUM(X32:AA32),"") | AC32: =AC28-AC29-AC30-AC31 -> -97.188 | AD32: =AD28-AD29-AD30-AD31 -> -174.793 | AE32: =AE28-AE29-AE30-AE31 -> -160.192 | AF32: =AF28-AF29-AF30-AF31 -> -175.589 | AG32: =IF(COUNT(AC32:AF32)=4,SUM(AC32:AF32),"") -> -607.762 | AH32: =AH28-AH29-AH30-AH31 -> -46.314 | AI32: =AI28-AI29-AI30-AI31 -> -35.53 | AL32: =IF(COUNT(AH32:AK32)=4,SUM(AH32:AK32),"") | AQ32: =IF(COUNT(AM32:AP32)=4,SUM(AM32:AP32),"") | AV32: =IF(COUNT(AR32:AU32)=4,SUM(AR32:AU32),"") | BA32: =IF(COUNT(AW32:AZ32)=4,SUM(AW32:AZ32),"") | BF32: =IF(COUNT(BB32:BE32)=4,SUM(BB32:BE32),"")
C33: Comercialização
C34: Volume de vendas (MW médios) | M34: =IF(COUNT(I34:L34)=4,SUMPRODUCT(I34:L34,I25:L25)/M25,"") | R34: =IF(COUNT(N34:Q34)=4,SUMPRODUCT(N34:Q34,N25:Q25)/R25,"") | W34: =IF(COUNT(S34:V34)=4,SUMPRODUCT(S34:V34,S25:V25)/W25,"") | AB34: =IF(COUNT(X34:AA34)=4,SUMPRODUCT(X34:AA34,X25:AA25)/AB25,"") | AG34: =IF(COUNT(AC34:AF34)=4,SUMPRODUCT(AC34:AF34,AC25:AF25)/AG25,"") | AL34: =IF(COUNT(AH34:AK34)=4,SUMPRODUCT(AH34:AK34,AH25:AK25)/AL25,"") | AQ34: =IF(COUNT(AM34:AP34)=4,SUMPRODUCT(AM34:AP34,AM25:AP25)/AQ25,"") | AV34: =IF(COUNT(AR34:AU34)=4,SUMPRODUCT(AR34:AU34,AR25:AU25)/AV25,"") | BA34: =IF(COUNT(AW34:AZ34)=4,SUMPRODUCT(AW34:AZ34,AW25:AZ25)/BA25,"") | BF34: =IF(COUNT(BB34:BE34)=4,SUMPRODUCT(BB34:BE34,BB25:BE25)/BF25,"")
C35: Preço médio de venda (R$/MWh) | M35: =IFERROR(M36/(M34*M25)*1000000,"") | R35: =IFERROR(R36/(R34*R25)*1000000,"") | W35: =IFERROR(W36/(W34*W25)*1000000,"") | AB35: =IFERROR(AB36/(AB34*AB25)*1000000,"") | AG35: =IFERROR(AG36/(AG34*AG25)*1000000,"") | AL35: =IFERROR(AL36/(AL34*AL25)*1000000,"") | AQ35: =IFERROR(AQ36/(AQ34*AQ25)*1000000,"") | AV35: =IFERROR(AV36/(AV34*AV25)*1000000,"") | BA35: =IFERROR(BA36/(BA34*BA25)*1000000,"") | BF35: =IFERROR(BF36/(BF34*BF25)*1000000,"")
C36: Receita líquida - Comercialização | I36: 1002.4 | J36: 999.8 | K36: 1599.608 | L36: 1462.9 | M36: =IF(COUNT(I36:L36)=4,SUM(I36:L36),"") -> 5064.708 | N36: 1015.193 | O36: 956.7 | P36: 1218.969 | Q36: 1181 | R36: =IF(COUNT(N36:Q36)=4,SUM(N36:Q36),"") -> 4371.862 | S36: 1074.1614 | T36: 1089.0826 | U36: 1328.4402 | V36: 1416.6193 | W36: =IF(COUNT(S36:V36)=4,SUM(S36:V36),"") -> 4908.3035 | X36: 1205.3762 | Y36: 1231.0475 | Z36: 2040.5144 | AA36: 2602.86 | AB36: =IF(COUNT(X36:AA36)=4,SUM(X36:AA36),"") -> 7079.798 | AC36: 1787.787 | AD36: 1894.174 | AE36: 2646.332 | AF36: 2916.108 | AG36: =IF(COUNT(AC36:AF36)=4,SUM(AC36:AF36),"") -> 9244.401 | AH36: 2025.027 | AI36: 1999.532 | AJ36: =IF(COUNT(AJ34,AJ35)=2,AJ34*AJ25*AJ35/1000000,"") | AK36: =IF(COUNT(AK34,AK35)=2,AK34*AK25*AK35/1000000,"") | AL36: =IF(COUNT(AH36:AK36)=4,SUM(AH36:AK36),"") | AM36: =IF(COUNT(AM34,AM35)=2,AM34*AM25*AM35/1000000,"") | AN36: =IF(COUNT(AN34,AN35)=2,AN34*AN25*AN35/1000000,"") | AO36: =IF(COUNT(AO34,AO35)=2,AO34*AO25*AO35/1000000,"") | AP36: =IF(COUNT(AP34,AP35)=2,AP34*AP25*AP35/1000000,"") | AQ36: =IF(COUNT(AM36:AP36)=4,SUM(AM36:AP36),"") | AR36: =IF(COUNT(AR34,AR35)=2,AR34*AR25*AR35/1000000,"") | AS36: =IF(COUNT(AS34,AS35)=2,AS34*AS25*AS35/1000000,"") | AT36: =IF(COUNT(AT34,AT35)=2,AT34*AT25*AT35/1000000,"") | AU36: =IF(COUNT(AU34,AU35)=2,AU34*AU25*AU35/1000000,"") | AV36: =IF(COUNT(AR36:AU36)=4,SUM(AR36:AU36),"") | AW36: =IF(COUNT(AW34,AW35)=2,AW34*AW25*AW35/1000000,"") | AX36: =IF(COUNT(AX34,AX35)=2,AX34*AX25*AX35/1000000,"") | AY36: =IF(COUNT(AY34,AY35)=2,AY34*AY25*AY35/1000000,"") | AZ36: =IF(COUNT(AZ34,AZ35)=2,AZ34*AZ25*AZ35/1000000,"") | BA36: =IF(COUNT(AW36:AZ36)=4,SUM(AW36:AZ36),"") | BB36: =IF(COUNT(BB34,BB35)=2,BB34*BB25*BB35/1000000,"") | BC36: =IF(COUNT(BC34,BC35)=2,BC34*BC25*BC35/1000000,"") | BD36: =IF(COUNT(BD34,BD35)=2,BD34*BD25*BD35/1000000,"") | BE36: =IF(COUNT(BE34,BE35)=2,BE34*BE25*BE35/1000000,"") | BF36: =IF(COUNT(BB36:BE36)=4,SUM(BB36:BE36),"")
C37: Holding e Pipeline (receita líquida) | M37: =IF(COUNT(I37:L37)>0,SUM(I37:L37),"") | R37: =IF(COUNT(N37:Q37)>0,SUM(N37:Q37),"") | S37: 18.236 | T37: 20.464 | U37: 20.352 | V37: 22.701 | W37: =IF(COUNT(S37:V37)>0,SUM(S37:V37),"") -> 81.753 | AB37: =IF(COUNT(X37:AA37)>0,SUM(X37:AA37),"") | AG37: =IF(COUNT(AC37:AF37)>0,SUM(AC37:AF37),"") | AL37: =IF(COUNT(AH37:AK37)>0,SUM(AH37:AK37),"") | AQ37: =IF(COUNT(AM37:AP37)>0,SUM(AM37:AP37),"") | AV37: =IF(COUNT(AR37:AU37)>0,SUM(AR37:AU37),"") | BA37: =IF(COUNT(AW37:AZ37)>0,SUM(AW37:AZ37),"") | BF37: =IF(COUNT(BB37:BE37)>0,SUM(BB37:BE37),"")
C38: Eliminações (% da receita de comercialização) | I38: =IFERROR(I39/I36,"") -> -0.11193136 | J38: =IFERROR(J39/J36,"") -> -0.079415883 | K38: =IFERROR(K39/K36,"") -> -0.081299293 | L38: =IFERROR(L39/L36,"") -> -0.07519311 | M38: =IFERROR(M39/M36,"") -> -0.085226434 | N38: =IFERROR(N39/N36,"") -> -0.17731111 | O38: =IFERROR(O39/O36,"") -> -0.16232884 | P38: =IFERROR(P39/P36,"") -> -0.20811194 | ... AI38: =IFERROR(AI39/AI36,"") -> -0.35492555 | AJ38: =IF(ISNUMBER(AI38),AI38,"") -> -0.35492555 | AK38: =IF(ISNUMBER(AJ38),AJ38,"") -> -0.35492555 | AL38: =IFERROR(AL39/AL36,"") | AM38: =IF(ISNUMBER(AK38),AK38,"") -> -0.35492555 | AN38: =IF(ISNUMBER(AM38),AM38,"") -> -0.35492555 | AO38: =IF(ISNUMBER(AN38),AN38,"") -> -0.35492555 | AP38: =IF(ISNUMBER(AO38),AO38,"") -> -0.35492555 | AQ38: =IFERROR(AQ39/AQ36,"") | AR38: =IF(ISNUMBER(AP38),AP38,"") -> -0.35492555 | AS38: =IF(ISNUMBER(AR38),AR38,"") -> -0.35492555 | AT38: =IF(ISNUMBER(AS38),AS38,"") -> -0.35492555 | AU38: =IF(ISNUMBER(AT38),AT38,"") -> -0.35492555 | AV38: =IFERROR(AV39/AV36,"") | AW38: =IF(ISNUMBER(AU38),AU38,"") -> -0.35492555 | AX38: =IF(ISNUMBER(AW38),AW38,"") -> -0.35492555 | AY38: =IF(ISNUMBER(AX38),AX38,"") -> -0.35492555 | AZ38: =IF(ISNUMBER(AY38),AY38,"") -> -0.35492555 | BA38: =IFERROR(BA39/BA36,"") | BB38: =IF(ISNUMBER(AZ38),AZ38,"") -> -0.35492555 | BC38: =IF(ISNUMBER(BB38),BB38,"") -> -0.35492555 | BD38: =IF(ISNUMBER(BC38),BC38,"") -> -0.35492555 | BE38: =IF(ISNUMBER(BD38),BD38,"") -> -0.35492555 | BF38: =IFERROR(BF39/BF36,"")
C39: Eliminações | I39: -112.2 | J39: -79.4 | K39: -130.047 | L39: -110 | M39: =IF(COUNT(I39:L39)=4,SUM(I39:L39),"") -> -431.647 | N39: -180.005 | O39: -155.3 | P39: -253.682 | Q39: -284.2 | R39: =IF(COUNT(N39:Q39)=4,SUM(N39:Q39),"") -> -873.187 | S39: -163.41568 | T39: -219.71828 | U39: -256.65246 | V39: -308.32303 | W39: =IF(COUNT(S39:V39)=4,SUM(S39:V39),"") -> -948.10945 | X39: -322.19036 | Y39: -286.98016 | Z39: -508.95671 | AA39: -799.45832 | AB39: =IF(COUNT(X39:AA39)=4,SUM(X39:AA39),"") -> -1917.5855 | AC39: -456.485 | AD39: -605.42 | AE39: -744.991 | AF39: -816.658 | AG39: =IF(COUNT(AC39:AF39)=4,SUM(AC39:AF39),"") -> -2623.554 | AH39: -684.922 | AI39: -709.685 | AJ39: =IF(COUNT(AJ36,AJ38)=2,AJ36*AJ38,"") | AK39: =IF(COUNT(AK36,AK38)=2,AK36*AK38,"") | AL39: =IF(COUNT(AH39:AK39)=4,SUM(AH39:AK39),"") | AM39: =IF(COUNT(AM36,AM38)=2,AM36*AM38,"") | AN39: =IF(COUNT(AN36,AN38)=2,AN36*AN38,"") | AO39: =IF(COUNT(AO36,AO38)=2,AO36*AO38,"") | AP39: =IF(COUNT(AP36,AP38)=2,AP36*AP38,"") | AQ39: =IF(COUNT(AM39:AP39)=4,SUM(AM39:AP39),"") | AR39: =IF(COUNT(AR36,AR38)=2,AR36*AR38,"") | AS39: =IF(COUNT(AS36,AS38)=2,AS36*AS38,"") | AT39: =IF(COUNT(AT36,AT38)=2,AT36*AT38,"") | AU39: =IF(COUNT(AU36,AU38)=2,AU36*AU38,"") | AV39: =IF(COUNT(AR39:AU39)=4,SUM(AR39:AU39),"") | AW39: =IF(COUNT(AW36,AW38)=2,AW36*AW38,"") | AX39: =IF(COUNT(AX36,AX38)=2,AX36*AX38,"") | AY39: =IF(COUNT(AY36,AY38)=2,AY36*AY38,"") | AZ39: =IF(COUNT(AZ36,AZ38)=2,AZ36*AZ38,"") | BA39: =IF(COUNT(AW39:AZ39)=4,SUM(AW39:AZ39),"") | BB39: =IF(COUNT(BB36,BB38)=2,BB36*BB38,"") | BC39: =IF(COUNT(BC36,BC38)=2,BC36*BC38,"") | BD39: =IF(COUNT(BD36,BD38)=2,BD36*BD38,"") | BE39: =IF(COUNT(BE36,BE38)=2,BE36*BE38,"") | BF39: =IF(COUNT(BB39:BE39)=4,SUM(BB39:BE39),"")
C40: Receita líquida construída | I40: =I28+I36+N(I37)+I39 -> 1395.8 | J40: =J28+J36+N(J37)+J39 -> 1329.7 | K40: =K28+K36+N(K37)+K39 -> 1879.887 | L40: =L28+L36+N(L37)+L39 -> 1872 | M40: =IF(COUNT(I40:L40)=4,SUM(I40:L40),"") -> 6477.387 | N40: =N28+N36+N(N37)+N39 -> 1384.187 | O40: =O28+O36+N(O37)+O39 -> 1346.6 | P40: =P28+P36+N(P37)+P39 -> 1538.901 | Q40: =Q28+Q36+N(Q37)+Q39 -> 1484.9 | R40: =IF(COUNT(N40:Q40)=4,SUM(N40:Q40),"") -> 5754.588 | S40: =S28+S36+N(S37)+S39 -> 2180.7784 | T40: =T28+T36+N(T37)+T39 -> 2186.6236 | U40: =U28+U36+N(U37)+U39 -> 2523.9762 | V40: =V28+V36+N(V37)+V39 -> 2666.0553 | W40: =IF(COUNT(S40:V40)=4,SUM(S40:V40),"") -> 9557.4335 | X40: =X28+X36+N(X37)+X39 -> 2209.3572 | Y40: =Y28+Y36+N(Y37)+Y39 -> 2307.8845 | Z40: =Z28+Z36+N(Z37)+Z39 -> 3134.6824 | AA40: =AA28+AA36+N(AA37)+AA39 -> 3598.925 | AB40: =IF(COUNT(X40:AA40)=4,SUM(X40:AA40),"") -> 11250.849 | AC40: =AC28+AC36+N(AC37)+AC39 -> 2952.303 | AD40: =AD28+AD36+N(AD37)+AD39 -> 2885.529 | AE40: =AE28+AE36+N(AE37)+AE39 -> 3537.391 | AF40: =AF28+AF36+N(AF37)+AF39 -> 3801.729 | AG40: =IF(COUNT(AC40:AF40)=4,SUM(AC40:AF40),"") -> 13176.952 | AH40: =AH28+AH36+N(AH37)+AH39 -> 3074.535 | AI40: =AI28+AI36+N(AI37)+AI39 -> 3055.499 | AJ40: =IF(COUNT(AJ28,AJ36,AJ39)=3,AJ28+AJ36+N(AJ37)+AJ39,"") | AK40: =IF(COUNT(AK28,AK36,AK39)=3,AK28+AK36+N(AK37)+AK39,"") | AL40: =IF(COUNT(AH40:AK40)=4,SUM(AH40:AK40),"") | AM40: =IF(COUNT(AM28,AM36,AM39)=3,AM28+AM36+N(AM37)+AM39,"") | AN40: =IF(COUNT(AN28,AN36,AN39)=3,AN28+AN36+N(AN37)+AN39,"") | AO40: =IF(COUNT(AO28,AO36,AO39)=3,AO28+AO36+N(AO37)+AO39,"") | AP40: =IF(COUNT(AP28,AP36,AP39)=3,AP28+AP36+N(AP37)+AP39,"") | AQ40: =IF(COUNT(AM40:AP40)=4,SUM(AM40:AP40),"") | AR40: =IF(COUNT(AR28,AR36,AR39)=3,AR28+AR36+N(AR37)+AR39,"") | AS40: =IF(COUNT(AS28,AS36,AS39)=3,AS28+AS36+N(AS37)+AS39,"") | AT40: =IF(COUNT(AT28,AT36,AT39)=3,AT28+AT36+N(AT37)+AT39,"") | AU40: =IF(COUNT(AU28,AU36,AU39)=3,AU28+AU36+N(AU37)+AU39,"") | AV40: =IF(COUNT(AR40:AU40)=4,SUM(AR40:AU40),"") | AW40: =IF(COUNT(AW28,AW36,AW39)=3,AW28+AW36+N(AW37)+AW39,"") | AX40: =IF(COUNT(AX28,AX36,AX39)=3,AX28+AX36+N(AX37)+AX39,"") | AY40: =IF(COUNT(AY28,AY36,AY39)=3,AY28+AY36+N(AY37)+AY39,"") | AZ40: =IF(COUNT(AZ28,AZ36,AZ39)=3,AZ28+AZ36+N(AZ37)+AZ39,"") | BA40: =IF(COUNT(AW40:AZ40)=4,SUM(AW40:AZ40),"") | BB40: =IF(COUNT(BB28,BB36,BB39)=3,BB28+BB36+N(BB37)+BB39,"") | BC40: =IF(COUNT(BC28,BC36,BC39)=3,BC28+BC36+N(BC37)+BC39,"") | BD40: =IF(COUNT(BD28,BD36,BD39)=3,BD28+BD36+N(BD37)+BD39,"") | BE40: =IF(COUNT(BE28,BE36,BE39)=3,BE28+BE36+N(BE37)+BE39,"") | BF40: =IF(COUNT(BB40:BE40)=4,SUM(BB40:BE40),"")
C41: Receita líquida da base do build (pro forma Auren + CESP/VGE em 2021-1T22 e Auren + AES em 2023-4T24, releases/RI; reportada a partir de 1T25) | I41: 1395.6 | J41: 1329.8 | K41: 1879.887 | L41: 1872.1 | M41: 6477.4 | N41: 1384.187 | O41: 1346.7 | P41: 1538.901 | Q41: 1484.9 | R41: 5754.6 | S41: 2180.778 | T41: 2186.624 | U41: 2523.976 | V41: 2666.055 | W41: =SUM(S41:V41) -> 9557.433 | X41: 2209.357 | Y41: 2307.885 | Z41: 3134.682 | AA41: 3598.925 | AB41: =SUM(X41:AA41) -> 11250.849 | AC41: =IF(ISNUMBER(AC15),AC15,"") -> 2952.303 | AD41: =IF(ISNUMBER(AD15),AD15,"") -> 2885.529 | AE41: =IF(ISNUMBER(AE15),AE15,"") -> 3537.391 | AF41: =IF(ISNUMBER(AF15),AF15,"") -> 3801.729 | AG41: =IF(ISNUMBER(AG15),AG15,"") -> 13176.952 | AH41: =IF(ISNUMBER(AH15),AH15,"") -> 3074.535 | AI41: =IF(ISNUMBER(AI15),AI15,"") -> 3055.499 | AJ41: =IF(ISNUMBER(AJ15),AJ15,"") -> 4051.3094 | ... BF41: =IF(ISNUMBER(BF15),BF15,"") -> 24358.007
C42: Check: reportada menos construída | I42: =IF(AND(ISNUMBER(I41),ISNUMBER(I40)),ROUND(I41-I40,1),"") -> -0.2 | J42: =IF(AND(ISNUMBER(J41),ISNUMBER(J40)),ROUND(J41-J40,1),"") -> 0.1 | K42: =IF(AND(ISNUMBER(K41),ISNUMBER(K40)),ROUND(K41-K40,1),"") -> 0 | L42: =IF(AND(ISNUMBER(L41),ISNUMBER(L40)),ROUND(L41-L40,1),"") -> 0.1 | M42: =IF(AND(ISNUMBER(M41),ISNUMBER(M40)),ROUND(M41-M40,1),"") -> 0 | N42: =IF(AND(ISNUMBER(N41),ISNUMBER(N40)),ROUND(N41-N40,1),"") -> 0 | O42: =IF(AND(ISNUMBER(O41),ISNUMBER(O40)),ROUND(O41-O40,1),"") -> 0.1 | P42: =IF(AND(ISNUMBER(P41),ISNUMBER(P40)),ROUND(P41-P40,1),"") -> 0 | ... BF42: =IF(AND(ISNUMBER(BF41),ISNUMBER(BF40)),ROUND(BF41-BF40,1),"")
C43: Referência da empresa - balanço energético (release 2T26)
C44: Geração: vendas totais ACR + ACL (MW médios) | AL44: 4147 | AQ44: 3831 | AV44: 3674 | BA44: 3063 | BF44: 2801
C45: Geração: preço médio de venda (R$/MWh) | AL45: 196 | AQ45: 212 | AV45: 210 | BA45: 216 | BF45: 222
C46: Geração: recursos próprios - garantia física (MW médios) | AL46: 3678 | AQ46: 3777 | AV46: 3777 | BA46: 3777 | BF46: 3777
C47: Geração: compras para revenda (MW médios) | AL47: 914 | AQ47: 596 | AV47: 485 | BA47: 320 | BF47: 320
C48: Geração: energia descontratada (MW médios) | AL48: 445 | AQ48: 542 | AV48: 588 | BA48: 1034 | BF48: 1296
C49: Comercialização: vendas (MW médios) | AL49: 5177 | AQ49: 2923 | AV49: 2121 | BA49: 1230 | BF49: 962
C50: Geração: receita contratada implícita (R$ mn) = vendas x preço x horas | AL50: =AL44*AL45*AL25/1000000 -> 7120.2331 | AQ50: =AQ44*AQ45*AQ25/1000000 -> 7114.6267 | AV50: =AV44*AV45*AV25/1000000 -> 6777.2074 | BA50: =BA44*BA45*BA25/1000000 -> 5795.6861 | BF50: =BF44*BF45*BF25/1000000 -> 5447.1607
C51: Fonte: 2021-2022 = releases 1T22 a 4T22 da Auren (CESP + Votorantim Energia, proforma desde jan/21, sem AES Brasil); 2023 em diante = Planilha Interativa 2T26 (proforma com AES Brasil) e releases 4T24 a 2T26 (geração). Quebra de perímetro em 1T23. Geração proforma de 1T23 a 3T23 não foi publicada por trimestre. Volume e preço da Comercialização não são divulgados por trimestre. Azul = fonte | verde = derivado de dois números da fonte | preto = fórmula | amarelo = premissa a preencher
C53: COGS (cash) | I53: ='Inputs (2)'!D5 -> -145.037 | J53: ='Inputs (2)'!E5 -> -270.903 | K53: ='Inputs (2)'!F5 -> 334.446 | L53: ='Inputs (2)'!G5 -> -442.928 | M53: ='Inputs (2)'!H5 -> -524.422 | N53: ='Inputs (2)'!I5 -> -705.903 | O53: ='Inputs (2)'!J5 -> -885.151 | P53: ='Inputs (2)'!K5 -> -1072.724 | ... AI53: ='Inputs (2)'!AD5 -> -2137.818 | AJ53: =-(1-AJ54)*AJ15 -> -2781.2591 | AK53: =-(1-AK54)*AK15 -> -2989.0937 | AL53: =SUM(AH53:AK53) -> -10028.421 | AM53: =-(1-AM54)*AM15 -> -2417.3404 | AN53: =-(1-AN54)*AN15 -> -2402.3735 | AO53: =-(1-AO54)*AO15 -> -3185.3253 | AP53: =-(1-AP54)*AP15 -> -3423.3546 | AQ53: =SUM(AM53:AP53) -> -11428.394 | AR53: =-(1-AR54)*AR15 -> -2756.4493 | AS53: =-(1-AS54)*AS15 -> -2739.3827 | AT53: =-(1-AT54)*AT15 -> -3632.1684 | AU53: =-(1-AU54)*AU15 -> -3903.5888 | AV53: =SUM(AR53:AU53) -> -13031.589 | AW53: =-(1-AW54)*AW15 -> -3129.3466 | AX53: =-(1-AX54)*AX15 -> -3109.9712 | AY53: =-(1-AY54)*AY15 -> -4123.5346 | AZ53: =-(1-AZ54)*AZ15 -> -4431.6733 | BA53: =SUM(AW53:AZ53) -> -14794.526 | BB53: =-(1-BB54)*BB15 -> -3537.0434 | BC53: =-(1-BC54)*BC15 -> -3515.1438 | BD53: =-(1-BD54)*BD15 -> -4660.756 | BE53: =-(1-BE54)*BE15 -> -5009.0395 | BF53: =SUM(BB53:BE53) -> -16721.983
C54: % Gross Margin | I54: =IFERROR((I15+I53)/I$15,"") -> 0.73732367 | J54: =IFERROR((J15+J53)/J$15,"") -> 0.53381322 | K54: =IFERROR((K15+K53)/K$15,"") -> 1.5427609 | L54: =IFERROR((L15+L53)/L$15,"") -> 0.42275447 | M54: =IFERROR((M15+M53)/M$15,"") -> 0.79162829 | N54: =IFERROR((N15+N53)/N$15,"") -> 0.38362971 | O54: =IFERROR((O15+O53)/O$15,"") -> 0.34270396 | P54: =IFERROR((P15+P53)/P$15,"") -> 0.30292852 | ... AI54: =IFERROR((AI15+AI53)/AI$15,"") -> 0.30033752 | AJ54: =Control!$B$19 -> 0.31349133 | AK54: =Control!$B$19 -> 0.31349133 | AL54: =IFERROR((AL15+AL53)/AL$15,"") -> 0.31006889 | AM54: =Control!$C$19 -> 0.31349133 | AN54: =Control!$C$19 -> 0.31349133 | AO54: =Control!$C$19 -> 0.31349133 | AP54: =Control!$C$19 -> 0.31349133 | AQ54: =IFERROR((AQ15+AQ53)/AQ$15,"") -> 0.31349133 | AR54: =Control!$D$19 -> 0.31349133 | AS54: =Control!$D$19 -> 0.31349133 | AT54: =Control!$D$19 -> 0.31349133 | AU54: =Control!$D$19 -> 0.31349133 | AV54: =IFERROR((AV15+AV53)/AV$15,"") -> 0.31349133 | AW54: =Control!$E$19 -> 0.31349133 | AX54: =Control!$E$19 -> 0.31349133 | AY54: =Control!$E$19 -> 0.31349133 | AZ54: =Control!$E$19 -> 0.31349133 | BA54: =IFERROR((BA15+BA53)/BA$15,"") -> 0.31349133 | BB54: =Control!$F$19 -> 0.31349133 | BC54: =Control!$F$19 -> 0.31349133 | BD54: =Control!$F$19 -> 0.31349133 | BE54: =Control!$F$19 -> 0.31349133 | BF54: =IFERROR((BF15+BF53)/BF$15,"") -> 0.31349133
C57: SG&A and Other (cash) | I57: ='Inputs (2)'!D6 -> -37.007 | J57: ='Inputs (2)'!E6 -> -72.009 | K57: ='Inputs (2)'!F6 -> -98.542 | L57: ='Inputs (2)'!G6 -> -5.338 | M57: ='Inputs (2)'!H6 -> -212.896 | N57: ='Inputs (2)'!I6 -> -134.703 | O57: ='Inputs (2)'!J6 -> -172.018 | P57: ='Inputs (2)'!K6 -> 37.062 | ... AI57: ='Inputs (2)'!AD6 -> -106.914 | AJ57: =-AJ15*AJ58 -> -200.18286 | AK57: =-AK15*AK58 -> -215.14189 | AL57: =SUM(AH57:AK57) -> -1176.4078 | AM57: =-AM15*AM58 -> -173.98959 | AN57: =-AN15*AN58 -> -172.91233 | AO57: =-AO15*AO58 -> -229.26578 | AP57: =-AP15*AP58 -> -246.39809 | AQ57: =SUM(AM57:AP57) -> -822.56579 | AR57: =-AR15*AR58 -> -198.39716 | AS57: =-AS15*AS58 -> -197.16878 | AT57: =-AT15*AT58 -> -261.42759 | AU57: =-AU15*AU58 -> -280.96325 | AV57: =SUM(AR57:AU57) -> -937.95678 | AW57: =-AW15*AW58 -> -225.23668 | AX57: =-AX15*AX58 -> -223.84213 | AY57: =-AY15*AY58 -> -296.79398 | AZ57: =-AZ15*AZ58 -> -318.97245 | BA57: =SUM(AW57:AZ57) -> -1064.8452 | BB57: =-BB15*BB58 -> -254.58091 | BC57: =-BC15*BC58 -> -253.00467 | BD57: =-BD15*BD58 -> -335.46083 | BE57: =-BE15*BE58 -> -360.52875 | BF57: =SUM(BB57:BE57) -> -1203.5752
C58: % SG&A and Other Margin | I58: =IFERROR(-(I57/I$15),"") -> 0.067023332 | J58: =IFERROR(-(J57/J$15),"") -> 0.12391758 | K58: =IFERROR(-(K57/K$15),"") -> 0.15992041 | L58: =IFERROR(-(L57/L$15),"") -> 0.0069567439 | M58: =IFERROR(-(M57/M$15),"") -> 0.084591233 | N58: =IFERROR(-(N57/N$15),"") -> 0.11761804 | O58: =IFERROR(-(O57/O$15),"") -> 0.12773725 | P58: =IFERROR(-(P57/P$15),"") -> -0.024083421 | ... AI58: =IFERROR(-(AI57/AI$15),"") -> 0.034990684 | AJ58: =Control!$B$20 -> 0.049411891 | AK58: =Control!$B$20 -> 0.049411891 | AL58: =IFERROR(-(AL57/AL$15),"") -> 0.08093401 | AM58: =Control!$C$20 -> 0.049411891 | AN58: =Control!$C$20 -> 0.049411891 | AO58: =Control!$C$20 -> 0.049411891 | AP58: =Control!$C$20 -> 0.049411891 | AQ58: =IFERROR(-(AQ57/AQ$15),"") -> 0.049411891 | AR58: =Control!$D$20 -> 0.049411891 | AS58: =Control!$D$20 -> 0.049411891 | AT58: =Control!$D$20 -> 0.049411891 | AU58: =Control!$D$20 -> 0.049411891 | AV58: =IFERROR(-(AV57/AV$15),"") -> 0.049411891 | AW58: =Control!$E$20 -> 0.049411891 | AX58: =Control!$E$20 -> 0.049411891 | AY58: =Control!$E$20 -> 0.049411891 | AZ58: =Control!$E$20 -> 0.049411891 | BA58: =IFERROR(-(BA57/BA$15),"") -> 0.049411891 | BB58: =Control!$F$20 -> 0.049411891 | BC58: =Control!$F$20 -> 0.049411891 | BD58: =Control!$F$20 -> 0.049411891 | BE58: =Control!$F$20 -> 0.049411891 | BF58: =IFERROR(-(BF57/BF$15),"") -> 0.049411891
C60: Com Vendas
C61: Gerais & Administrativas
C62: Outras Receitas (Despesas) Operacionais, Líquidas
C64: Com Vendas (%)
C65: Gerais & Administrativas (%)
C66: Outras Receitas (Despesas) Operacionais, Líquidas (%)
C68: EBITDA | I68: =SUM(I15,I53,I57) -> 370.107 | J68: =SUM(J15,J53,J57) -> 238.192 | K68: =SUM(K15,K53,K57) -> 852.098 | L68: =SUM(L15,L53,L57) -> 319.047 | M68: =SUM(I68:L68) -> 1779.444 | N68: =SUM(N15,N53,N57) -> 304.652 | O68: =SUM(O15,O53,O57) -> 289.486 | P68: =SUM(P15,P53,P57) -> 503.239 | Q68: =SUM(Q15,Q53,Q57) -> 760.783 | R68: =SUM(N68:Q68) -> 1858.16 | S68: =SUM(S15,S53,S57) -> 451.882 | T68: =SUM(T15,T53,T57) -> 457.91 | U68: =SUM(U15,U53,U57) -> 350.08 | V68: =SUM(V15,V53,V57) -> 418.005 | W68: =SUM(S68:V68) -> 1677.877 | X68: =SUM(X15,X53,X57) -> 599.644 | Y68: =SUM(Y15,Y53,Y57) -> 398.07 | Z68: =SUM(Z15,Z53,Z57) -> 633.579 | AA68: =SUM(AA15,AA53,AA57) -> 209.178 | AB68: =SUM(X68:AA68) -> 1840.471 | AC68: =SUM(AC15,AC53,AC57) -> 1377.508 | AD68: =SUM(AD15,AD53,AD57) -> 517.013 | AE68: =SUM(AE15,AE53,AE57) -> 664.324 | AF68: =SUM(AF15,AF53,AF57) -> 1474.895 | AG68: =SUM(AC68:AF68) -> 4033.74 | AH68: =SUM(AH15,AH53,AH57) -> 300.116 | AI68: =SUM(AI15,AI53,AI57) -> 810.767 | AJ68: =SUM(AJ15,AJ53,AJ57) -> 1069.8675 | AK68: =SUM(AK15,AK53,AK57) -> 1149.8153 | AL68: =SUM(AH68:AK68) -> 3330.5659 | AM68: =SUM(AM15,AM53,AM57) -> 929.87887 | AN68: =SUM(AN15,AN53,AN57) -> 924.12152 | AO68: =SUM(AO15,AO53,AO57) -> 1225.2998 | AP68: =SUM(AP15,AP53,AP57) -> 1316.8625 | AQ68: =SUM(AM68:AP68) -> 4396.1627 | AR68: =SUM(AR15,AR53,AR57) -> 1060.3239 | AS68: =SUM(AS15,AS53,AS57) -> 1053.7589 | AT68: =SUM(AT15,AT53,AT57) -> 1397.187 | AU68: =SUM(AU15,AU53,AU57) -> 1501.5944 | AV68: =SUM(AR68:AU68) -> 5012.8642 | AW68: =SUM(AW15,AW53,AW57) -> 1203.7664 | AX68: =SUM(AX15,AX53,AX57) -> 1196.3133 | AY68: =SUM(AY15,AY53,AY57) -> 1586.201 | AZ68: =SUM(AZ15,AZ53,AZ57) -> 1704.7327 | BA68: =SUM(AW68:AZ68) -> 5691.0134 | BB68: =SUM(BB15,BB53,BB57) -> 1360.5953 | BC68: =SUM(BC15,BC53,BC57) -> 1352.1711 | BD68: =SUM(BD15,BD53,BD57) -> 1792.854 | BE68: =SUM(BE15,BE53,BE57) -> 1926.8283 | BF68: =SUM(BB68:BE68) -> 6432.4487
C69: D&A | I69: ='Inputs (2)'!D7 -> -132.593 | J69: ='Inputs (2)'!E7 -> -131.573 | K69: ='Inputs (2)'!F7 -> -145.397 | L69: ='Inputs (2)'!G7 -> -149.432 | M69: ='Inputs (2)'!H7 -> -558.995 | N69: ='Inputs (2)'!I7 -> -157.304 | O69: ='Inputs (2)'!J7 -> -161.19 | P69: ='Inputs (2)'!K7 -> -161.353 | ... AI69: ='Inputs (2)'!AD7 -> -465.443 | AJ69: =-AJ70*AJ15 -> -605.92957 | AK69: =-AK70*AK15 -> -651.20876 | AL69: =SUM(AH69:AK69) -> -2189.4123 | AM69: =-AM70*AM15 -> -526.64567 | AN69: =-AN70*AN15 -> -523.38494 | AO69: =-AO70*AO15 -> -693.96009 | AP69: =-AP70*AP15 -> -745.81753 | AQ69: =SUM(AM69:AP69) -> -2489.8082 | AR69: =-AR70*AR15 -> -600.52446 | AS69: =-AS70*AS15 -> -596.80631 | AT69: =-AT70*AT15 -> -791.31005 | AU69: =-AU70*AU15 -> -850.44213 | AV69: =SUM(AR69:AU69) -> -2839.083 | AW69: =-AW70*AW15 -> -681.76448 | AX69: =-AX70*AX15 -> -677.54333 | AY69: =-AY70*AY15 -> -898.35987 | AZ69: =-AZ70*AZ15 -> -965.49146 | BA69: =SUM(AW69:AZ69) -> -3223.1591 | BB69: =-BB70*BB15 -> -770.58597 | BC69: =-BC70*BC15 -> -765.81488 | BD69: =-BD70*BD15 -> -1015.3998 | BE69: =-BE70*BE15 -> -1091.2774 | BF69: =SUM(BB69:BE69) -> -3643.078
C70: % of Revenue | I70: =IFERROR(-I69/I15,"") -> 0.24013902 | J70: =IFERROR(-J69/J15,"") -> 0.22641902 | K70: =IFERROR(-K69/K15,"") -> 0.23595978 | L70: =IFERROR(-L69/L15,"") -> 0.19474712 | N70: =IFERROR(-N69/N15,"") -> 0.13735246 | O70: =IFERROR(-O69/O15,"") -> 0.11969658 | P70: =IFERROR(-P69/P15,"") -> 0.1048495 | Q70: =IFERROR(-Q69/Q15,"") -> 0.079404428 | S70: =IFERROR(-S69/S15,"") -> 0.11900022 | T70: =IFERROR(-T69/T15,"") -> 0.11806236 | U70: =IFERROR(-U69/U15,"") -> 0.10429364 | V70: =IFERROR(-V69/V15,"") -> 0.099570817 | X70: =IFERROR(-X69/X15,"") -> 0.11905353 | Y70: =IFERROR(-Y69/Y15,"") -> 0.12080797 | Z70: =IFERROR(-Z69/Z15,"") -> 0.089230402 | AA70: =IFERROR(-AA69/AA15,"") -> 0.059705976 | AC70: =IFERROR(-AC69/AC15,"") -> 0.15519952 | AD70: =IFERROR(-AD69/AD15,"") -> 0.18081503 | AE70: =IFERROR(-AE69/AE15,"") -> 0.13160914 | AF70: =IFERROR(-AF69/AF15,"") -> 0.12559207 | AH70: =IFERROR(-AH69/AH15,"") -> 0.15183792 | AI70: =IFERROR(-AI69/AI15,"") -> 0.15232962 | AJ70: =Control!$B$21 -> 0.14956388 | AK70: =Control!$B$21 -> 0.14956388 | AM70: =Control!$C$21 -> 0.14956388 | AN70: =Control!$C$21 -> 0.14956388 | AO70: =Control!$C$21 -> 0.14956388 | AP70: =Control!$C$21 -> 0.14956388 | AR70: =Control!$D$21 -> 0.14956388 | AS70: =Control!$D$21 -> 0.14956388 | AT70: =Control!$D$21 -> 0.14956388 | AU70: =Control!$D$21 -> 0.14956388 | AW70: =Control!$E$21 -> 0.14956388 | AX70: =Control!$E$21 -> 0.14956388 | AY70: =Control!$E$21 -> 0.14956388 | AZ70: =Control!$E$21 -> 0.14956388 | BB70: =Control!$F$21 -> 0.14956388 | BC70: =Control!$F$21 -> 0.14956388 | BD70: =Control!$F$21 -> 0.14956388 | BE70: =Control!$F$21 -> 0.14956388
C72: Operating Profit - EBIT | I72: =SUM(I68,I69) -> 237.514 | J72: =SUM(J68,J69) -> 106.619 | K72: =SUM(K68,K69) -> 706.701 | L72: =SUM(L68,L69) -> 169.615 | M72: =SUM(I72:L72) -> 1220.449 | N72: =SUM(N68,N69) -> 147.348 | O72: =SUM(O68,O69) -> 128.296 | P72: =SUM(P68,P69) -> 341.886 | Q72: =SUM(Q68,Q69) -> 642.876 | R72: =SUM(N72:Q72) -> 1260.406 | S72: =SUM(S68,S69) -> 283.555 | T72: =SUM(T68,T69) -> 288.244 | U72: =SUM(U68,U69) -> 180.437 | V72: =SUM(V68,V69) -> 248.366 | W72: =SUM(S72:V72) -> 1000.602 | X72: =SUM(X68,X69) -> 433.263 | Y72: =SUM(Y68,Y69) -> 222.893 | Z72: =SUM(Z68,Z69) -> 450.968 | AA72: =SUM(AA68,AA69) -> 20.157 | AB72: =SUM(X72:AA72) -> 1127.281 | AC72: =SUM(AC68,AC69) -> 919.312 | AD72: =SUM(AD68,AD69) -> -4.734 | AE72: =SUM(AE68,AE69) -> 198.771 | AF72: =SUM(AF68,AF69) -> 997.428 | AG72: =SUM(AC72:AF72) -> 2110.777 | AH72: =SUM(AH68,AH69) -> -166.715 | AI72: =SUM(AI68,AI69) -> 345.324 | AJ72: =SUM(AJ68,AJ69) -> 463.93796 | AK72: =SUM(AK68,AK69) -> 498.60657 | AL72: =SUM(AL68,AL69) -> 1141.1535 | AM72: =SUM(AM68,AM69) -> 403.2332 | AN72: =SUM(AN68,AN69) -> 400.73658 | AO72: =SUM(AO68,AO69) -> 531.33969 | ... BF72: =SUM(BF68,BF69) -> 2789.3707
C73: Interest Expense | I73: ='Inputs (2)'!D8 -> -164.756 | J73: ='Inputs (2)'!E8 -> -211.669 | K73: ='Inputs (2)'!F8 -> -193.237 | L73: ='Inputs (2)'!G8 -> -238.999 | M73: ='Inputs (2)'!H8 -> -808.661 | N73: ='Inputs (2)'!I8 -> -250.51 | O73: ='Inputs (2)'!J8 -> -291.34 | P73: ='Inputs (2)'!K8 -> -165.812 | ... AI73: ='Inputs (2)'!AD8 -> -1018.168 | AJ73: =IF(Control!$E$9="","",-AI91*Control!$E$9/4) -> -806.72427 | AK73: =IF(Control!$E$9="","",-AJ91*Control!$E$9/4) -> -806.72427 | AL73: =SUM(AH73:AK73) -> -3499.0975 | AM73: =IF(Control!$E$9="","",-AL91*Control!$E$9/4) -> -806.72427 | AN73: =IF(Control!$E$9="","",-AM91*Control!$E$9/4) -> -806.72427 | AO73: =IF(Control!$E$9="","",-AN91*Control!$E$9/4) -> -806.72427 | AP73: =IF(Control!$E$9="","",-AO91*Control!$E$9/4) -> -806.72427 | AQ73: =SUM(AM73:AP73) -> -3226.8971 | AR73: =IF(Control!$E$9="","",-AQ91*Control!$E$9/4) -> -806.72427 | AS73: =IF(Control!$E$9="","",-AR91*Control!$E$9/4) -> -806.72427 | AT73: =IF(Control!$E$9="","",-AS91*Control!$E$9/4) -> -806.72427 | AU73: =IF(Control!$E$9="","",-AT91*Control!$E$9/4) -> -806.72427 | AV73: =SUM(AR73:AU73) -> -3226.8971 | AW73: =IF(Control!$E$9="","",-AV91*Control!$E$9/4) -> -806.72427 | AX73: =IF(Control!$E$9="","",-AW91*Control!$E$9/4) -> -806.72427 | AY73: =IF(Control!$E$9="","",-AX91*Control!$E$9/4) -> -806.72427 | AZ73: =IF(Control!$E$9="","",-AY91*Control!$E$9/4) -> -806.72427 | BA73: =SUM(AW73:AZ73) -> -3226.8971 | BB73: =IF(Control!$E$9="","",-BA91*Control!$E$9/4) -> -806.72427 | BC73: =IF(Control!$E$9="","",-BB91*Control!$E$9/4) -> -806.72427 | BD73: =IF(Control!$E$9="","",-BC91*Control!$E$9/4) -> -806.72427 | BE73: =IF(Control!$E$9="","",-BD91*Control!$E$9/4) -> -806.72427 | BF73: =SUM(BB73:BE73) -> -3226.8971
C74: % of Debt | I74: =IFERROR(-I73/SUM(I211+I216),"") -> 0.04385953 | J74: =IFERROR(-J73/SUM(J211+J216),"") -> 0.055902056 | K74: =IFERROR(-K73/SUM(K211+K216),"") -> 0.04470623 | L74: =IFERROR(-L73/SUM(L211+L216),"") -> 0.050733473 | N74: =IFERROR(-N73/SUM(N211+N216),"") -> 0.051883632 | O74: =IFERROR(-O73/SUM(O211+O216),"") -> 0.052158881 | P74: =IFERROR(-P73/SUM(P211+P216),"") -> 0.028943644 | Q74: =IFERROR(-Q73/SUM(Q211+Q216),"") -> 0.080438687 | S74: =IFERROR(-S73/SUM(S211+S216),"") -> 0.044444644 | T74: =IFERROR(-T73/SUM(T211+T216),"") -> 0.074489298 | U74: =IFERROR(-U73/SUM(U211+U216),"") -> 0.031667194 | V74: =IFERROR(-V73/SUM(V211+V216),"") -> 0.03385227 | X74: =IFERROR(-X73/SUM(X211+X216),"") -> 0.039986288 | Y74: =IFERROR(-Y73/SUM(Y211+Y216),"") -> 0.031017004 | Z74: =IFERROR(-Z73/SUM(Z211+Z216),"") -> 0.029344026 | AA74: =IFERROR(-AA73/SUM(AA211+AA216),"") -> 0.026537364 | AC74: =IFERROR(-AC73/SUM(AC211+AC216),"") -> 0.0388121 | AD74: =IFERROR(-AD73/SUM(AD211+AD216),"") -> 0.035883829 | AE74: =IFERROR(-AE73/SUM(AE211+AE216),"") -> 0.035030962 | AF74: =IFERROR(-AF73/SUM(AF211+AF216),"") -> 0.031963619 | AH74: =IFERROR(-AH73/SUM(AH211+AH216),"") -> 0.036616383 | AI74: =IFERROR(-AI73/SUM(AI211+AI216),"") -> 0.043341914 | AJ74: =IFERROR(Control!$E$9,0) -> 0.13736426 | AK74: =IFERROR(Control!$E$9,0) -> 0.13736426 | AM74: =IFERROR(Control!$E$9,0) -> 0.13736426 | AN74: =IFERROR(Control!$E$9,0) -> 0.13736426 | AO74: =IFERROR(Control!$E$9,0) -> 0.13736426 | AP74: =IFERROR(Control!$E$9,0) -> 0.13736426 | AR74: =IFERROR(Control!$E$9,0) -> 0.13736426 | AS74: =IFERROR(Control!$E$9,0) -> 0.13736426 | AT74: =IFERROR(Control!$E$9,0) -> 0.13736426 | AU74: =IFERROR(Control!$E$9,0) -> 0.13736426 | AW74: =IFERROR(Control!$E$9,0) -> 0.13736426 | AX74: =IFERROR(Control!$E$9,0) -> 0.13736426 | AY74: =IFERROR(Control!$E$9,0) -> 0.13736426 | AZ74: =IFERROR(Control!$E$9,0) -> 0.13736426 | BB74: =IFERROR(Control!$E$9,0) -> 0.13736426 | BC74: =IFERROR(Control!$E$9,0) -> 0.13736426 | BD74: =IFERROR(Control!$E$9,0) -> 0.13736426 | BE74: =IFERROR(Control!$E$9,0) -> 0.13736426
C75: %CDI
C78: RECEITA FINANCEIRA
C79: DESPESA FINANCEIRA
C80: OUTROS
C82: Cash and equivalents (inc. investment securities)
C83: Interest on cash
C84: Average interest rate
C85: % CDI
C87: Current portion of long-term debt | I87: =I211 -> 113.698 | J87: =J211 -> 126.835 | K87: =K211 -> 112.867 | L87: =L211 -> 208.959 | M87: =M211 -> 208.959 | N87: =N211 -> 204.389 | O87: =O211 -> 226.936 | P87: =P211 -> 236.588 | ... BF87: =BF211 -> 1922.546
C88: Short term debt (Revolving credit facility) | I88: =I212 -> 0 | J88: =J212 -> 0 | K88: =K212 -> 0 | L88: =L212 -> 0 | M88: =M212 -> 0 | N88: =N212 -> 0 | O88: =O212 -> 0 | P88: =P212 -> 0 | ... BF88: =BF212 -> 0
C89: Long term debt | I89: =I216 -> 3642.749 | J89: =J216 -> 3659.591 | K89: =K216 -> 4209.506 | L89: =L216 -> 4501.915 | M89: =M216 -> 4501.915 | N89: =N216 -> 4623.916 | O89: =O216 -> 5358.69 | P89: =P216 -> 5492.2 | ... BF89: =BF216 -> 21568.987
C90: Convertible debt | I90: =I237 -> 0 | J90: =J237 -> 0 | K90: =K237 -> 0 | L90: =L237 -> 0 | M90: =M237 -> 0 | N90: =N237 -> 0 | O90: =O237 -> 0 | P90: =P237 -> 0 | ... BF90: =BF237 -> 0
C91: Total debt | I91: =SUM(I87:I90) -> 3756.447 | J91: =SUM(J87:J90) -> 3786.426 | K91: =SUM(K87:K90) -> 4322.373 | L91: =SUM(L87:L90) -> 4710.874 | M91: =SUM(M87:M90) -> 4710.874 | N91: =SUM(N87:N90) -> 4828.305 | O91: =SUM(O87:O90) -> 5585.626 | P91: =SUM(P87:P90) -> 5728.788 | ... BF91: =SUM(BF87:BF90) -> 23491.533
C92: Interest expense
C93: Average interest rate
C95: Stake
C96: PRE
C97: CDI+
C99: Spread
C100: PRE
C101: CDI+
C103: RECEITAS FINANCEIRAS - Rendimentos de aplicações financeiras
C104: RECEITAS FINANCEIRAS - Variação cambial ativa
C105: RECEITAS FINANCEIRAS - Atualização de contas a pagar por aquisição de empresas
C106: RECEITAS FINANCEIRAS - Resultado positivo com instrumentos derivativos
... C120: CHECK [EX IFRS-16]
C122: Nonoperating Income / (Loss) | I122: ='Inputs (2)'!D9 -> 13.753 | J122: ='Inputs (2)'!E9 -> 11.716 | K122: ='Inputs (2)'!F9 -> 41.663 | L122: ='Inputs (2)'!G9 -> 33.412 | M122: ='Inputs (2)'!H9 -> 100.544 | N122: ='Inputs (2)'!I9 -> 86.074 | O122: ='Inputs (2)'!J9 -> 103.888 | P122: ='Inputs (2)'!K9 -> 112.759 | ... AI122: ='Inputs (2)'!AD9 -> 286.022 | AJ122: =AJ15*Control!$B$23 -> 350.71981 | AK122: =AK15*Control!$B$23 -> 376.92798 | AL122: =SUM(AH122:AK122) -> 1291.3198 | AM122: =AM15*Control!$C$23 -> 304.82927 | AN122: =AN15*Control!$C$23 -> 302.94192 | AO122: =AO15*Control!$C$23 -> 401.673 | AP122: =AP15*Control!$C$23 -> 431.68875 | AQ122: =SUM(AM122:AP122) -> 1441.1329 | AR122: =AR15*Control!$D$23 -> 347.59126 | AS122: =AS15*Control!$D$23 -> 345.43915 | AT122: =AT15*Control!$D$23 -> 458.02041 | AU122: =AU15*Control!$D$23 -> 492.24682 | AV122: =SUM(AR122:AU122) -> 1643.2976 | AW122: =AW15*Control!$E$23 -> 394.61403 | AX122: =AX15*Control!$E$23 -> 392.17077 | AY122: =AY15*Control!$E$23 -> 519.98222 | AZ122: =AZ15*Control!$E$23 -> 558.83884 | BA122: =SUM(AW122:AZ122) -> 1865.6059 | BB122: =BB15*Control!$F$23 -> 446.02504 | BC122: =BC15*Control!$F$23 -> 443.26348 | BD122: =BD15*Control!$F$23 -> 587.72643 | BE122: =BE15*Control!$F$23 -> 631.64536 | BF122: =SUM(BB122:BE122) -> 2108.6603
C124: Resultado Não Recorrente
C125: Plano de Opção de Compra de Ações
C126: Baixa Imobilizado
C129: Pretax Income - EBT | I129: =SUM(I72,I73,I122) -> 86.511 | J129: =SUM(J72,J73,J122) -> -93.334 | K129: =SUM(K72,K73,K122) -> 555.127 | L129: =SUM(L72,L73,L122) -> -35.972 | M129: =SUM(I129:L129) -> 512.332 | N129: =SUM(N72,N73,N122) -> -17.088 | O129: =SUM(O72,O73,O122) -> -59.156 | P129: =SUM(P72,P73,P122) -> 288.833 | Q129: =SUM(Q72,Q73,Q122) -> 2710.092 | R129: =SUM(N129:Q129) -> 2922.681 | S129: =SUM(S72,S73,S122) -> 266.368 | T129: =SUM(T72,T73,T122) -> 263.793 | U129: =SUM(U72,U73,U122) -> 60.309 | V129: =SUM(V72,V73,V122) -> 172.125 | W129: =SUM(S129:V129) -> 762.595 | X129: =SUM(X72,X73,X122) -> 324.284 | Y129: =SUM(Y72,Y73,Y122) -> 86.841 | Z129: =SUM(Z72,Z73,Z122) -> 348.343 | AA129: =SUM(AA72,AA73,AA122) -> -393.479 | AB129: =SUM(X129:AA129) -> 365.989 | AC129: =SUM(AC72,AC73,AC122) -> 187.235 | AD129: =SUM(AD72,AD73,AD122) -> -649.261 | AE129: =SUM(AE72,AE73,AE122) -> -426.519 | AF129: =SUM(AF72,AF73,AF122) -> 565.384 | AG129: =SUM(AC129:AF129) -> -323.161 | AH129: =SUM(AH72,AH73,AH122) -> -756.546 | AI129: =SUM(AI72,AI73,AI122) -> -386.822 | AJ129: =SUM(AJ72,AJ73,AJ122:AJ127) -> 7.9334947 | AK129: =SUM(AK72,AK73,AK122:AK127) -> 68.810283 | AL129: =SUM(AH129:AK129) -> -1066.6242 | AM129: =SUM(AM72,AM73,AM122:AM127) -> -98.6618 | AN129: =SUM(AN72,AN73,AN122:AN127) -> -103.04577 | AO129: =SUM(AO72,AO73,AO122:AO127) -> 126.28842 | AP129: =SUM(AP72,AP73,AP122:AP127) -> 196.0095 | AQ129: =SUM(AM129:AP129) -> 120.59035 | AR129: =SUM(AR72,AR73,AR122:AR127) -> 0.6664613 | AS129: =SUM(AS72,AS73,AS122:AS127) -> -4.3325028 | AT129: =SUM(AT72,AT73,AT122:AT127) -> 257.1731 | AU129: =SUM(AU72,AU73,AU122:AU127) -> 336.67477 | AV129: =SUM(AR129:AU129) -> 590.18183 | AW129: =SUM(AW72,AW73,AW122:AW127) -> 109.89171 | AX129: =SUM(AX72,AX73,AX122:AX127) -> 104.21648 | AY129: =SUM(AY72,AY73,AY122:AY127) -> 401.09902 | AZ129: =SUM(AZ72,AZ73,AZ122:AZ127) -> 491.35583 | BA129: =SUM(AW129:AZ129) -> 1106.563 | BB129: =SUM(BB72,BB73,BB122:BB127) -> 229.31007 | BC129: =SUM(BC72,BC73,BC122:BC127) -> 222.89546 | BD129: =SUM(BD72,BD73,BD122:BD127) -> 558.45639 | BE129: =SUM(BE72,BE73,BE122:BE127) -> 660.47201 | BF129: =SUM(BB129:BE129) -> 1671.1339
C130: Taxes | I130: ='Inputs (2)'!D10 -> -46.947 | J130: ='Inputs (2)'!E10 -> 7.108 | K130: ='Inputs (2)'!F10 -> -238.601 | L130: ='Inputs (2)'!G10 -> 16.235 | M130: ='Inputs (2)'!H10 -> -262.205 | N130: ='Inputs (2)'!I10 -> -14.548 | O130: ='Inputs (2)'!J10 -> 2.189 | P130: ='Inputs (2)'!K10 -> -111.046 | ... AI130: ='Inputs (2)'!AD10 -> -31.833 | AJ130: =-AJ129*AJ131 -> -2.1574172 | AK130: =-AK129*AK131 -> -18.712118 | AL130: =SUM(AH130:AK130) -> 30.750465 | AM130: =-AM129*AM131 -> 26.829874 | AN130: =-AN129*AN131 -> 28.022042 | AO130: =-AO129*AO131 -> -34.342597 | AP130: =-AP129*AP131 -> -53.302394 | AQ130: =SUM(AM130:AP130) -> -32.793075 | AR130: =-AR129*AR131 -> -0.18123603 | AS130: =-AS129*AS131 -> 1.1781713 | AT130: =-AT129*AT131 -> -69.93509 | AU130: =-AU129*AU131 -> -91.554601 | AV130: =SUM(AR130:AU130) -> -160.49276 | AW130: =-AW129*AW131 -> -29.883712 | AX130: =-AX129*AX131 -> -28.340402 | AY130: =-AY129*AY131 -> -109.07399 | AZ130: =-AZ129*AZ131 -> -133.61823 | BA130: =SUM(AW130:AZ130) -> -300.91633 | BB130: =-BB129*BB131 -> -62.358079 | BC130: =-BC129*BC131 -> -60.613704 | BD130: =-BD129*BD131 -> -151.86541 | BE130: =-BE129*BE131 -> -179.60731 | BF130: =SUM(BB130:BE130) -> -454.4445
C131: % ETR | I131: =IFERROR(-I130/I129,"") -> 0.54267087 | J131: =IFERROR(-J130/J129,"") -> 0.076156599 | K131: =IFERROR(-K130/K129,"") -> 0.42981336 | L131: =IFERROR(-L130/L129,"") -> 0.45132325 | M131: =IFERROR(-M130/M129,"") -> 0.51178728 | N131: =IFERROR(-N130/N129,"") -> -0.85135768 | O131: =IFERROR(-O130/O129,"") -> 0.037003854 | P131: =IFERROR(-P130/P129,"") -> 0.38446438 | ... AI131: =IFERROR(-AI130/AI129,"") -> -0.082293665 | AJ131: =Control!$B$22 -> 0.27193781 | AK131: =Control!$B$22 -> 0.27193781 | AL131: =IFERROR(-AL130/AL129,"") -> 0.028829708 | AM131: =Control!$C$22 -> 0.27193781 | AN131: =Control!$C$22 -> 0.27193781 | AO131: =Control!$C$22 -> 0.27193781 | AP131: =Control!$C$22 -> 0.27193781 | AQ131: =IFERROR(-AQ130/AQ129,"") -> 0.27193781 | AR131: =Control!$D$22 -> 0.27193781 | AS131: =Control!$D$22 -> 0.27193781 | AT131: =Control!$D$22 -> 0.27193781 | AU131: =Control!$D$22 -> 0.27193781 | AV131: =IFERROR(-AV130/AV129,"") -> 0.27193781 | AW131: =Control!$E$22 -> 0.27193781 | AX131: =Control!$E$22 -> 0.27193781 | AY131: =Control!$E$22 -> 0.27193781 | AZ131: =Control!$E$22 -> 0.27193781 | BA131: =IFERROR(-BA130/BA129,"") -> 0.27193781 | BB131: =Control!$F$22 -> 0.27193781 | BC131: =Control!$F$22 -> 0.27193781 | BD131: =Control!$F$22 -> 0.27193781 | BE131: =Control!$F$22 -> 0.27193781 | BF131: =IFERROR(-BF130/BF129,"") -> 0.27193781
C134: Equity in Income of Affiliates, after tax (enter as +) | I134: ='Inputs (2)'!D11 -> 0 | J134: ='Inputs (2)'!E11 -> 0 | K134: ='Inputs (2)'!F11 -> 0 | L134: ='Inputs (2)'!G11 -> 0 | M134: ='Inputs (2)'!H11 -> 0 | N134: ='Inputs (2)'!I11 -> 29.051 | O134: ='Inputs (2)'!J11 -> 54.94 | P134: ='Inputs (2)'!K11 -> 52.3 | ... AI134: ='Inputs (2)'!AD11 -> 39.594 | AJ134: =AVERAGE(AE134,AF134,AH134,AI134) -> 57.38075 | AK134: =AJ134 -> 57.38075 | AL134: =SUM(AH134:AK134) -> 225.8425 | AM134: =AK134 -> 57.38075 | AN134: =AM134 -> 57.38075 | AO134: =AN134 -> 57.38075 | AP134: =AO134 -> 57.38075 | AQ134: =SUM(AM134:AP134) -> 229.523 | AR134: =AP134 -> 57.38075 | AS134: =AR134 -> 57.38075 | AT134: =AS134 -> 57.38075 | AU134: =AT134 -> 57.38075 | AV134: =SUM(AR134:AU134) -> 229.523 | AW134: =AU134 -> 57.38075 | AX134: =AW134 -> 57.38075 | AY134: =AX134 -> 57.38075 | AZ134: =AY134 -> 57.38075 | BA134: =SUM(AW134:AZ134) -> 229.523 | BB134: =AZ134 -> 57.38075 | BC134: =BB134 -> 57.38075 | BD134: =BC134 -> 57.38075 | BE134: =BD134 -> 57.38075 | BF134: =SUM(BB134:BE134) -> 229.523
C135: Minority Interest Expense, after tax (enter as - ) | I135: ='Inputs (2)'!D12 -> -29.436 | J135: ='Inputs (2)'!E12 -> 15.169 | K135: ='Inputs (2)'!F12 -> -234.281 | L135: ='Inputs (2)'!G12 -> 34.187 | M135: ='Inputs (2)'!H12 -> -214.361 | N135: ='Inputs (2)'!I12 -> -4.214 | O135: ='Inputs (2)'!J12 -> 0 | P135: ='Inputs (2)'!K12 -> 0 | ... AI135: ='Inputs (2)'!AD12 -> -31.886 | AJ135: =AVERAGE(AE135,AF135,AH135,AI135) -> -14.93425 | AK135: =AJ135 -> -14.93425 | AL135: =SUM(AH135:AK135) -> -81.4865 | AM135: =AK135 -> -14.93425 | AN135: =AM135 -> -14.93425 | AO135: =AN135 -> -14.93425 | AP135: =AO135 -> -14.93425 | AQ135: =SUM(AM135:AP135) -> -59.737 | AR135: =AP135 -> -14.93425 | AS135: =AR135 -> -14.93425 | AT135: =AS135 -> -14.93425 | AU135: =AT135 -> -14.93425 | AV135: =SUM(AR135:AU135) -> -59.737 | AW135: =AU135 -> -14.93425 | AX135: =AW135 -> -14.93425 | AY135: =AX135 -> -14.93425 | AZ135: =AY135 -> -14.93425 | BA135: =SUM(AW135:AZ135) -> -59.737 | BB135: =AZ135 -> -14.93425 | BC135: =BB135 -> -14.93425 | BD135: =BC135 -> -14.93425 | BE135: =BD135 -> -14.93425 | BF135: =SUM(BB135:BE135) -> -59.737
C136: Net Income | I136: =SUM(I129,I130,I134,I135) -> 10.128 | J136: =SUM(J129,J130,J134,J135) -> -71.057 | K136: =SUM(K129,K130,K134,K135) -> 82.245 | L136: =SUM(L129,L130,L134,L135) -> 14.45 | M136: =SUM(I136:L136) -> 35.766 | N136: =SUM(N129,N130,N134,N135) -> -6.799 | O136: =SUM(O129,O130,O134,O135) -> -2.027 | P136: =SUM(P129,P130,P134,P135) -> 230.087 | Q136: =SUM(Q129,Q130,Q134,Q135) -> 2453.139 | R136: =SUM(N136:Q136) -> 2674.4 | S136: =SUM(S129,S130,S134,S135) -> 229.952 | T136: =SUM(T129,T130,T134,T135) -> 182.882 | U136: =SUM(U129,U130,U134,U135) -> -838.116 | V136: =SUM(V129,V130,V134,V135) -> 107.593 | W136: =SUM(S136:V136) -> -317.689 | X136: =SUM(X129,X130,X134,X135) -> 253.618 | Y136: =SUM(Y129,Y130,Y134,Y135) -> 91.089 | Z136: =SUM(Z129,Z130,Z134,Z135) -> 270.83 | AA136: =SUM(AA129,AA130,AA134,AA135) -> -364.599 | AB136: =SUM(X136:AA136) -> 250.938 | AC136: =SUM(AC129,AC130,AC134,AC135) -> 8.496 | AD136: =SUM(AD129,AD130,AD134,AD135) -> -615.39 | AE136: =SUM(AE129,AE130,AE134,AE135) -> -397.034 | AF136: =SUM(AF129,AF130,AF134,AF135) -> 339.896 | AG136: =SUM(AC136:AF136) -> -664.032 | AH136: =SUM(AH129,AH130,AH134,AH135) -> -621.338 | AI136: =SUM(AI129,AI130,AI134,AI135) -> -410.947 | AJ136: =SUM(AJ129,AJ130,AJ134,AJ135) -> 48.222577 | AK136: =SUM(AK129,AK130,AK134,AK135) -> 92.544665 | AL136: =SUM(AH136:AK136) -> -891.51776 | AM136: =SUM(AM129,AM130,AM134,AM135) -> -29.385426 | AN136: =SUM(AN129,AN130,AN134,AN135) -> -32.57723 | AO136: =SUM(AO129,AO130,AO134,AO135) -> 134.39232 | AP136: =SUM(AP129,AP130,AP134,AP135) -> 185.1536 | AQ136: =SUM(AM136:AP136) -> 257.58327 | AR136: =SUM(AR129,AR130,AR134,AR135) -> 42.931725 | AS136: =SUM(AS129,AS130,AS134,AS135) -> 39.292169 | AT136: =SUM(AT129,AT130,AT134,AT135) -> 229.68451 | AU136: =SUM(AU129,AU130,AU134,AU135) -> 287.56667 | AV136: =SUM(AR136:AU136) -> 599.47507 | AW136: =SUM(AW129,AW130,AW134,AW135) -> 122.4545 | AX136: =SUM(AX129,AX130,AX134,AX135) -> 118.32258 | AY136: =SUM(AY129,AY130,AY134,AY135) -> 334.47153 | AZ136: =SUM(AZ129,AZ130,AZ134,AZ135) -> 400.1841 | BA136: =SUM(AW136:AZ136) -> 975.43271 | BB136: =SUM(BB129,BB130,BB134,BB135) -> 209.39849 | BC136: =SUM(BC129,BC130,BC134,BC135) -> 204.72826 | BD136: =SUM(BD129,BD130,BD134,BD135) -> 449.03748 | BE136: =SUM(BE129,BE130,BE134,BE135) -> 523.31119 | BF136: =SUM(BB136:BE136) -> 1386.4754
C137: Common Dividends | I137: ='Inputs (2)'!D13 -> -3.475 | J137: ='Inputs (2)'!E13 -> -352.302 | K137: ='Inputs (2)'!F13 -> -146.582 | L137: ='Inputs (2)'!G13 -> -0.003 | M137: ='Inputs (2)'!H13 -> -502.362 | N137: ='Inputs (2)'!I13 -> 0 | O137: ='Inputs (2)'!J13 -> -99.991 | P137: ='Inputs (2)'!K13 -> 0 | ... AI137: ='Inputs (2)'!AD13 -> 0.148 | AJ137: =-MAX(0,AJ136)*Control!$E$15 -> 0 | AK137: =-MAX(0,AK136)*Control!$E$15 -> 0 | AL137: =SUM(AH137:AK137) -> -42.818 | AM137: =-MAX(0,AM136)*Control!$E$15 -> 0 | AN137: =-MAX(0,AN136)*Control!$E$15 -> 0 | AO137: =-MAX(0,AO136)*Control!$E$15 -> 0 | AP137: =-MAX(0,AP136)*Control!$E$15 -> 0 | AQ137: =SUM(AM137:AP137) -> 0 | AR137: =-MAX(0,AR136)*Control!$E$15 -> 0 | AS137: =-MAX(0,AS136)*Control!$E$15 -> 0 | AT137: =-MAX(0,AT136)*Control!$E$15 -> 0 | AU137: =-MAX(0,AU136)*Control!$E$15 -> 0 | AV137: =SUM(AR137:AU137) -> 0 | AW137: =-MAX(0,AW136)*Control!$E$15 -> 0 | AX137: =-MAX(0,AX136)*Control!$E$15 -> 0 | AY137: =-MAX(0,AY136)*Control!$E$15 -> 0 | AZ137: =-MAX(0,AZ136)*Control!$E$15 -> 0 | BA137: =SUM(AW137:AZ137) -> 0 | BB137: =-MAX(0,BB136)*Control!$E$15 -> 0 | BC137: =-MAX(0,BC136)*Control!$E$15 -> 0 | BD137: =-MAX(0,BD136)*Control!$E$15 -> 0 | BE137: =-MAX(0,BE136)*Control!$E$15 -> 0 | BF137: =SUM(BB137:BE137) -> 0
...

Sheet Valuation
C3: Discounted Cash Flow Model
C4: All figures in millions, except per share data
C7: Ticker | D7: =IF(Control!B4="","",Control!B4) -> AURE3 | F7: Last close | G7: =IF(Control!E4="","",Control!E4)
C8: Operating scenario: | D8: =IF(Control!B10=1,"Bull Case",IF(Control!B10=2,"Base Case","Bear Case")) -> Base Case
C9: Last fiscal year end date: | D9: =IF(Control!B12="","",DATE(YEAR(Control!B12)-1,12,31)) -> 46022
C10: Valuation / deal date: | D10: =IF(Control!B12="","",Control!B12) -> 46287
C11: Stub year fraction: | D11: =IF(Control!B12="","",Control!B13) -> 0.2739726
C12: Weighted average cost of capital: | D12: =IF(Control!E12="","",Control!E12)
C14: Historicals | G14: Projected Annual Forecast
G15: Granular
D16: 2023 | E16: 2024 | F16: 2025 | G16: 2026 | H16: 2027 | I16: 2028 | J16: 2029 | K16: 2030
D17: 45291 | E17: 45657 | F17: 46022 | G17: 46387 | H17: 46752 | I17: 47118 | J17: 47483 | K17: 47848
C18: Net Revenues | D18: =Model!W15 -> 6181.89 | E18: =Model!AB15 -> 8059.951 | F18: =Model!AG15 -> 13176.952 | G18: =Model!AL15 -> 14535.394 | H18: =Model!AQ15 -> 16647.122 | I18: =Model!AV15 -> 18982.41 | J18: =Model!BA15 -> 21550.384 | K18: =Model!BF15 -> 24358.007
D19: ="" | E19: =IFERROR(IF(D18=0,"",E18/D18-1),"") -> 0.30380046 | F19: =IFERROR(IF(E18=0,"",F18/E18-1),"") -> 0.63486751 | G19: =IF(F18=0,"",G18/F18-1) -> 0.10309231 | H19: =IF(G18=0,"",H18/G18-1) -> 0.14528178 | I19: =IF(H18=0,"",I18/H18-1) -> 0.14028178 | J19: =IF(I18=0,"",J18/I18-1) -> 0.13528178 | K19: =IF(J18=0,"",K18/J18-1) -> 0.13028178
C20: EBITDA | D20: =Model!W68 -> 1677.877 | E20: =Model!AB68 -> 1840.471 | F20: =Model!AG68 -> 4033.74 | G20: =Model!AL68 -> 3330.5659 | H20: =Model!AQ68 -> 4396.1627 | I20: =Model!AV68 -> 5012.8642 | J20: =Model!BA68 -> 5691.0134 | K20: =Model!BF68 -> 6432.4487
D21: =IFERROR(IF(D18=0,"",D20/D18),"") -> 0.27141813 | E21: =IFERROR(IF(E18=0,"",E20/E18),"") -> 0.22834767 | F21: =IF(F18=0,"",F20/F18) -> 0.30612087 | G21: =IF(G18=0,"",G20/G18) -> 0.22913488 | H21: =IF(H18=0,"",H20/H18) -> 0.26407944 | I21: =IF(I18=0,"",I20/I18) -> 0.26407944 | J21: =IF(J18=0,"",J20/J18) -> 0.26407944 | K21: =IF(K18=0,"",K20/K18) -> 0.26407944
C22: EBIT | D22: =Model!W72 -> 1000.602 | E22: =Model!AB72 -> 1127.281 | F22: =Model!AG72 -> 2110.777 | G22: =Model!AL72 -> 1141.1535 | H22: =Model!AQ72 -> 1906.3545 | I22: =Model!AV72 -> 2173.7813 | J22: =Model!BA72 -> 2467.8543 | K22: =Model!BF72 -> 2789.3707
D23: =IFERROR(IF(D18=0,"",D22/D18),"") -> 0.16186021 | E23: =IFERROR(IF(E18=0,"",E22/E18),"") -> 0.13986202 | F23: =IF(F18=0,"",F22/F18) -> 0.16018704 | G23: =IF(G18=0,"",G22/G18) -> 0.078508604 | H23: =IF(H18=0,"",H22/H18) -> 0.11451556 | I23: =IF(I18=0,"",I22/I18) -> 0.11451556 | J23: =IF(J18=0,"",J22/J18) -> 0.11451556 | K23: =IF(K18=0,"",K22/K18) -> 0.11451556
C24: Tax rate (ETR limitada a 0%-100%) | D24: =Model!W348 -> 1 | E24: =Model!AB348 -> 0.70631631 | F24: =Model!AG348 -> 0 | G24: =Model!AL348 -> 0.028829708 | H24: =Model!AQ348 -> 0.27193781 | I24: =Model!AV348 -> 0.27193781 | J24: =Model!BA348 -> 0.27193781 | K24: =Model!BF348 -> 0.27193781
C25: NOPLAT | D25: =D22*(1-D24) -> 0 | E25: =E22*(1-E24) -> 331.06404 | F25: =F22*(1-F24) -> 2110.777 | G25: =G22*(1-G24) -> 1108.2544 | H25: =H22*(1-H24) -> 1387.9446 | I25: =I22*(1-I24) -> 1582.648 | J25: =J22*(1-J24) -> 1796.7514 | K25: =K22*(1-K24) -> 2030.8353
C26: Depreciation & Amortization | D26: =-Model!W69 -> 677.275 | E26: =-Model!AB69 -> 713.19 | F26: =-Model!AG69 -> 1922.963 | G26: =-Model!AL69 -> 2189.4123 | H26: =-Model!AQ69 -> 2489.8082 | I26: =-Model!AV69 -> 2839.083 | J26: =-Model!BA69 -> 3223.1591 | K26: =-Model!BF69 -> 3643.078
C27: Cash from working capital | D27: =Model!W278 -> -293.626 | E27: =Model!AB278 -> 1438.917 | F27: =Model!AG278 -> -29.755 | G27: =Model!AL278 -> 296.46761 | H27: =Model!AQ278 -> 240.77765 | I27: =Model!AV278 -> 426.35372 | J27: =Model!BA278 -> 720.96512 | K27: =Model!BF278 -> 1177.3935
C28: Accounts receivable | D28: =Model!W279 -> -61.616 | E28: =Model!AB279 -> -813.391 | F28: =Model!AG279 -> -219.547 | G28: =Model!AL279 -> -283.65549 | H28: =Model!AQ279 -> -289.99252 | I28: =Model!AV279 -> -320.69284 | J28: =Model!BA279 -> -352.64642 | K28: =Model!BF279 -> -385.55605
C29: Inventories | D29: =Model!W280 -> 0 | E29: =Model!AB280 -> 0 | F29: =Model!AG280 -> 0 | G29: =Model!AL280 -> 0 | H29: =Model!AQ280 -> 0 | I29: =Model!AV280 -> 0 | J29: =Model!BA280 -> 0 | K29: =Model!BF280 -> 0
C30: Deferred income taxes (assets) | D30: =Model!W281 -> 302.042 | E30: =Model!AB281 -> 526.679 | F30: =Model!AG281 -> 229.378 | G30: =Model!AL281 -> -55.156 | H30: =Model!AQ281 -> 0 | I30: =Model!AV281 -> 0 | J30: =Model!BA281 -> 0 | K30: =Model!BF281 -> 0
C31: Prepaid expenses | D31: =Model!W282 -> 0 | E31: =Model!AB282 -> 0 | F31: =Model!AG282 -> 0 | G31: =Model!AL282 -> 0 | H31: =Model!AQ282 -> 0 | I31: =Model!AV282 -> 0 | J31: =Model!BA282 -> 0 | K31: =Model!BF282 -> 0
C32: Other current assets | D32: =Model!W283 -> 399.339 | E32: =Model!AB283 -> -421.758 | F32: =Model!AG283 -> 76.478 | G32: =Model!AL283 -> 283.41 | H32: =Model!AQ283 -> 0 | I32: =Model!AV283 -> 0 | J32: =Model!BA283 -> 0 | K32: =Model!BF283 -> 0
C33: Accounts payable | D33: =Model!W284 -> 23.302 | E33: =Model!AB284 -> 733.189 | F33: =Model!AG284 -> 156.474 | G33: =Model!AL284 -> 163.3747 | H33: =Model!AQ284 -> 236.135 | I33: =Model!AV284 -> 261.13364 | J33: =Model!BA284 -> 287.1528 | K33: =Model!BF284 -> 313.95044
C34: Accrued expenses | D34: =Model!W285 -> 32.513 | E34: =Model!AB285 -> 17.909 | F34: =Model!AG285 -> 1.412 | G34: =Model!AL285 -> 1.1611315 | H34: =Model!AQ285 -> 85.992157 | I34: =Model!AV285 -> 141.81844 | J34: =Model!BA285 -> 229.53568 | K34: =Model!BF285 -> 364.53262
C35: Taxes payable | D35: =Model!W286 -> -30.833 | E35: =Model!AB286 -> 73.433 | F35: =Model!AG286 -> 13.253 | G35: =Model!AL286 -> 126.27527 | H35: =Model!AQ286 -> 208.64301 | I35: =Model!AV286 -> 344.09448 | J35: =Model!BA286 -> 556.92307 | K35: =Model!BF286 -> 884.46653
C36: Other current liabilities | D36: =Model!W287 -> -952.575 | E36: =Model!AB287 -> 621.338 | F36: =Model!AG287 -> -158.319 | G36: =Model!AL287 -> 251.612 | H36: =Model!AQ287 -> 0 | I36: =Model!AV287 -> 0 | J36: =Model!BA287 -> 0 | K36: =Model!BF287 -> 0
C37: Deferred tax (liabilities) | D37: =Model!W288 -> -5.798 | E37: =Model!AB288 -> 701.518 | F37: =Model!AG288 -> -128.884 | G37: =Model!AL288 -> -190.554 | H37: =Model!AQ288 -> 0 | I37: =Model!AV288 -> 0 | J37: =Model!BA288 -> 0 | K37: =Model!BF288 -> 0
C38: Other non-current assets | D38: =(Model!W188-Model!R188)*-1 -> 3895.154 | E38: =(Model!AB188-Model!W188)*-1 -> 434.419 | F38: =(Model!AG188-Model!AB188)*-1 -> 72.158 | G38: =(Model!AL188-Model!AG188)*-1 -> -9.665 | H38: =(Model!AQ188-Model!AL188)*-1 -> 0 | I38: =(Model!AV188-Model!AQ188)*-1 -> 0 | J38: =(Model!BA188-Model!AV188)*-1 -> 0 | K38: =(Model!BF188-Model!BA188)*-1 -> 0
C39: Other non-current liabilities | D39: =Model!W239-Model!R239 -> -14.862 | E39: =Model!AB239-Model!W239 -> -1298.964 | F39: =Model!AG239-Model!AB239 -> -672.798 | G39: =Model!AL239-Model!AG239 -> 276.673 | H39: =Model!AQ239-Model!AL239 -> 0 | I39: =Model!AV239-Model!AQ239 -> 0 | J39: =Model!BA239-Model!AV239 -> 0 | K39: =Model!BF239-Model!BA239 -> 0
C40: Capital expenditures | D40: =Model!W294 -> -2129.587 | E40: =Model!AB294 -> -15067.639 | F40: =Model!AG294 -> -1149.414 | G40: =Model!AL294 -> -1250.7996 | H40: =Model!AQ294 -> -1441.8357 | I40: =Model!AV294 -> -1644.0989 | J40: =Model!BA294 -> -1866.5156 | K40: =Model!BF294 -> -2109.6885
C41: Capital expenditures [IFRS16 - implied lease payments] | D41: =0 -> 0 | E41: =0 -> 0 | F41: =0 -> 0 | G41: =0 -> 0 | H41: =0 -> 0 | I41: =0 -> 0 | J41: =0 -> 0 | K41: =0 -> 0
C42: Purchase of intangible assets | D42: =0 -> 0 | E42: =0 -> 0 | F42: =0 -> 0 | G42: =0 -> 0 | H42: =0 -> 0 | I42: =0 -> 0 | J42: =0 -> 0 | K42: =0 -> 0
C44: Net Investments | D44: =SUM(D27,D40:D42,D26) -> -1745.938 | E44: =SUM(E27,E40:E42,E26) -> -12915.532 | F44: =SUM(F27,F40:F42,F26) -> 743.794 | G44: =SUM(G27,G40:G42,G26) -> 1235.0803 | H44: =SUM(H27,H40:H42,H26) -> 1288.7502 | I44: =SUM(I27,I40:I42,I26) -> 1621.3377 | J44: =SUM(J27,J40:J42,J26) -> 2077.6087 | K44: =SUM(K27,K40:K42,K26) -> 2710.7831
C46: Invested Capital | D46: =Model!V349 -> 14198.996 | E46: =Model!AA349 -> 33642.616 | F46: =Model!AF349 -> 33227.159 | G46: =Model!AK349 -> 31280.451 | H46: =Model!AP349 -> 29991.7 | I46: =Model!AU349 -> 28370.363 | J46: =Model!AZ349 -> 26292.754 | K46: =Model!BE349 -> 23581.971
C47: Invested Capital (ex Goodwill) | D47: =Model!V350 -> 14198.996 | E47: =Model!AA350 -> 33642.616 | F47: =Model!AF350 -> 33227.159 | G47: =Model!AK350 -> 31280.451 | H47: =Model!AP350 -> 29991.7 | I47: =Model!AU350 -> 28370.363 | J47: =Model!AZ350 -> 26292.754 | K47: =Model!BE350 -> 23581.971
C48: Invested Capital / Net Revenues | D48: =IFERROR(IF(D18=0,"",D46/D18),"") -> 2.2968697 | E48: =IFERROR(IF(E18=0,"",E46/E18),"") -> 4.1740472 | F48: =IF(F18=0,"",F46/F18) -> 2.5216119 | G48: =IF(G18=0,"",G46/G18) -> 2.1520194 | H48: =IF(H18=0,"",H46/H18) -> 1.8016147 | I48: =IF(I18=0,"",I46/I18) -> 1.4945606 | J48: =IF(J18=0,"",J46/J18) -> 1.2200596 | K48: =IF(K18=0,"",K46/K18) -> 0.96814043
C50: ROIC | D50: =IF(D46=0,"",D25/D46) -> 0 | E50: =IF(E46=0,"",E25/E46) -> 0.0098406154 | F50: =IF(F46=0,"",F25/F46) -> 0.063525654 | G50: =IF(G46=0,"",G25/G46) -> 0.035429618 | H50: =IF(H46=0,"",H25/H46) -> 0.046277623 | I50: =IF(I46=0,"",I25/I46) -> 0.055785256 | J50: =IF(J46=0,"",J25/J46) -> 0.06833637 | K50: =IF(K46=0,"",K25/K46) -> 0.086118134
C51: Capital Turnover | D51: =IF(D46=0,"",D18/D46) -> 0.43537515 | E51: =IF(E46=0,"",E18/E46) -> 0.23957563 | F51: =IF(F46=0,"",F18/F46) -> 0.39657173 | G51: =IF(G46=0,"",G18/G46) -> 0.46467983 | H51: =IF(H46=0,"",H18/H46) -> 0.55505763 | I51: =IF(I46=0,"",I18/I46) -> 0.66909297 | J51: =IF(J46=0,"",J18/J46) -> 0.81963207 | K51: =IF(K46=0,"",K18/K46) -> 1.032908
C53: Unlevered free cash flows = FCFF | D53: =D25+D44 -> -1745.938 | E53: =E25+E44 -> -12584.468 | F53: =F25+F44 -> 2854.571 | G53: =G25+G44 -> 2343.3347 | H53: =H25+H44 -> 2676.6948 | I53: =I25+I44 -> 3203.9857 | J53: =J25+J44 -> 3874.3601 | K53: =K25+K44 -> 4741.6184
C54: Discount factor | G54: =IF(Control!E12="","",1/(1+Control!E12)^Control!B13) | H54: =IF(G54="","",G54/(1+Control!E12)) | I54: =IF(H54="","",H54/(1+Control!E12)) | J54: =IF(I54="","",I54/(1+Control!E12)) | K54: =IF(J54="","",J54/(1+Control!E12))
C55: Midyear adjustment factor | G55: =IF(Control!E12="","",(1+Control!E12)^0.5) | H55: =G55 | I55: =H55 | J55: =I55 | K55: =J55
C56: Present value of free cash flows | G56: =IF(G54="","",G53*G54*G55) | H56: =IF(H54="","",H53*H54*H55) | I56: =IF(I54="","",I53*I54*I55) | J56: =IF(J54="","",J53*J54*J55) | K56: =IF(K54="","",K53*K54*K55)
C57: Sum of present values of FCFs | G57: =IF(COUNT(G56:K56)=0,"",SUM(G56:K56))
D59: =IF(Control!B9="","",Control!B9) -> 47848 | H59: =IF(Control!B7="","",Control!B7) -> 46203
C60: Terminal value | E60: Equity value calculations | I60: Shares Outstanding Worksheet
C62: Key value driver method | E62: Enterprise value | H62: =D80 | I62: Basic Shares Outanding :
C63: g | D63: =IF(Control!E13="","",Control!E13) | E63: Calculation of net debt: | I63: Current Share Price:
C64: RONIC | D64: =K50 -> 0.086118134 | E64: Current portion of long-term debt | H64: =IFERROR(INDEX(Model!$I$211:$BF$211,1,MATCH(Control!$B$7,Model!$I$5:$BF$5,0)),"") -> 1922.546 | I64: Options / Warrants Data
C65: NOPLAT (t+1) | D65: =IF(D63="","",K25*(1+D63)) | E65: Short term debt | H65: =IFERROR(INDEX(Model!$I$212:$BF$212,1,MATCH(Control!$B$7,Model!$I$5:$BF$5,0)),"") -> 0 | J65: # of options | K65: $ strike
C66: Terminal value | D66: =IF(OR(Control!E12="",D64="",D64<=D63,Control!E12<=D63),"",(D65*(1-D63/D64))/(Control!E12-D63)) | E66: Long term debt | H66: =IFERROR(INDEX(Model!$I$216:$BF$216,1,MATCH(Control!$B$7,Model!$I$5:$BF$5,0)),"") -> 21568.987 | I66: Batch 1
C67: Midyear adjusted terminal value | D67: =IF(D66="","",D66*K55) | E67: Convertible debt | H67: =IFERROR(INDEX(Model!$I$237:$BF$237,1,MATCH(Control!$B$7,Model!$I$5:$BF$5,0)),"") -> 0 | I67: Batch 2
C68: Present value of terminal value | D68: =IF(D67="","",D67*K54) | E68: Minority interest | H68: =IFERROR(INDEX(Model!$I$247:$BF$247,1,MATCH(Control!$B$7,Model!$I$5:$BF$5,0)),"") -> 1245.517 | I68: Batch 3
C69: Enterprise value | D69: =IF(OR(D68="",G57=""),"",D68+G57) | E69: Convertible preferred stock | H69: =IFERROR(INDEX(Model!$I$252:$BF$252,1,MATCH(Control!$B$7,Model!$I$5:$BF$5,0)),"") -> 0 | I69: Batch 4
E70: Short term operating leases | H70: =IFERROR(INDEX(Model!$I$213:$BF$213,1,MATCH(Control!$B$7,Model!$I$5:$BF$5,0)),"") -> 13.608 | I70: Batch 5
C71: Exit multiple method | E71: Long term operating leases | H71: =IFERROR(INDEX(Model!$I$234:$BF$234,1,MATCH(Control!$B$7,Model!$I$5:$BF$5,0)),"") -> 149.083 | I71: Batch 6
C72: Exit EV / EBITDA multiple | D72: =IF(Control!E14="","",Control!E14) | E72: Less: Excess cash | H72: =IFERROR(-INDEX(Model!$I$143:$BF$143,1,MATCH(Control!$B$7,Model!$I$5:$BF$5,0)),"") -> -3638.808 | K72: Total in-the-$ options:
C73: LTM EBITDA at end of projection | D73: =K20 -> 6432.4487 | E73: Less: Equity investments | H73: =IFERROR(-INDEX(Model!$I$160:$BF$160,1,MATCH(Control!$B$7,Model!$I$5:$BF$5,0)),"") -> -2043.198 | K73: Total $ proceeds:
C74: Terminal value | D74: =IF(OR(D72="",D73=""),"",D73*D72) | E74: Net debt | H74: =IFERROR(SUM(H64:H73),"") -> 19217.735 | K74: Total shares repurchased:
C75: Present value of terminal value | D75: =IF(OR(D74="",K54="",K55=""),"",D74*K54*K55) | E75: Equity value | H75: =IFERROR(IF(H62="","",H62-H74),"") | K75: Basic shares outstanding
C76: Enterprise value | D76: =IF(OR(D75="",G57=""),"",G57+D75) | E76: Shares outstanding | H76: =IF(Control!E5="","",Control!E5) | K76: New shares from options:
E77: Equity value / share | H77: =IFERROR(IF(OR(H75="",H76="",H76=0),"",H75/H76),"") | K77: New shares from convert. pref. stock:
C78: Select a terminal value method | K78: New shares from convertible debt:
C79: Perpetual growth = 1 / Exit multiple = 2 | D79: =Control!B11 -> 1 | K79: Total Shares Outstanding:
C80: Enterprise value | D80: =IF(D79=1,D69,D76)
C81: Terminal value as percent of total value | D81: =IFERROR(IF(D79=1,D68/D69,D75/D76),"")
C83: Analysis of WACC
C85: Cost of debt | F85: Capital structure
C86: Cost of debt | D86: =IF(Control!E9="","",Control!E9) -> 0.13736426 | G86: Current capital structure | I86: Target capital structure
C87: Marginal tax rate | D87: =IF(Control!E10="","",Control!E10) | G87: Market value | H87: % Weight | I87: override | J87: % Weight
C88: Cost of debt after tax shield | D88: =IF(OR(D86="",D87=""),"",D86*(1-D87)) | F88: Net debt | G88: =IFERROR(H74,"") -> 19217.735 | H88: =IFERROR(debt/totalcap,"") -> 1 | J88: =IFERROR(IF(I88,I88,H88),"") -> 1
F89: Equity | G89: =L63*L79 -> 0 | H89: =IFERROR(1-H88,"") -> 0 | J89: =IFERROR(1-debt_weight,"") -> 0
C90: Cost of equity | F90: Total | G90: =IFERROR(SUM(G88:G89),"") -> 19217.735
C91: Risk-Free Rate (rf) | D91: =IF(Control!E6="","",Control!E6)
C92: Market Risk Premium (rm-rf) | D92: =IF(Control!E7="","",Control!E7) | F92: Weighted average cost of capital
C93: Raw (observed) beta | D93: =IF(Control!E8="","",Control!E8) | F93: Weighted average cost of capital: | J93: =IF(Control!E12="","",Control!E12)
C94: Cost of equity using relevered industry beta | D94: =IF(COUNT(D91:D93)<3,"",D91+D93*D92)
C96: Industry beta calculation
C97: Comps | D97: Raw beta | E97: Share price | F97: Shares | G97: Market cap. | H97: Debt | I97: D / E | J97: Tax rate | K97: Unl. Beta
C98: =ticker -> AURE3
C99: TICKER 2
C100: TICKER 3
C101: TICKER 4

Sheet Control
A1: CONTROL & ASSUMPTIONS – BASE MODEL
A3: Company | B3: Auren Energia S.A. | D3: Valuation assumptions
A4: Ticker | B4: AURE3 | D4: Last close (R$/share)
A5: Currency | D5: Shares outstanding (mm)
A6: Model unit | B6: R$ milhões | D6: Risk-free rate
A7: Last actual period | B7: 46203 | D7: Market risk premium
A8: Quarterly forecast through | B8: 47118 | D8: Beta
A9: Forecast end | B9: 47848 | D9: Pre-tax cost of debt | E9: =IFERROR(-Model!AG73/AVERAGE(Model!AB91,Model!AG91),"") -> 0.13736426
A10: Scenario (1 Bull / 2 Base / 3 Bear) | B10: 2 | D10: Marginal tax rate
A11: Terminal method (1 Perpetuity / 2 Exit) | B11: 1 | D11: Target debt weight
A12: Valuation date | B12: 46287 | D12: WACC | E12: =IF(COUNT(E6:E11)<6,"",E11*E9*(1-E10)+(1-E11)*(E6+E8*E7))
A13: Stub year fraction | B13: =IFERROR((DATE(YEAR(B12),12,31)-B12)/365,"") -> 0.2739726 | D13: Terminal growth
D14: Exit EV/EBITDA
D15: Dividend payout
A17: Forecast drivers | B17: 2026E | C17: 2027E | D17: 2028E | E17: 2029E | F17: 2030E
A18: Revenue growth | B18: =IFERROR(AVERAGE(Model!AC16:AF16,Model!AH16:AI16),"") -> 0.14528178 | C18: =IF(B18="","",B18) -> 0.14528178 | D18: =IF(C18="","",MAX(0,C18-0.5%)) -> 0.14028178 | E18: =IF(D18="","",MAX(0,D18-0.5%)) -> 0.13528178 | F18: =IF(E18="","",MAX(0,E18-0.5%)) -> 0.13028178
A19: Gross margin | B19: =IFERROR(AVERAGE(Model!AC54:AF54,Model!AH54:AI54),"") -> 0.31349133 | C19: =IF(B19="","",B19) -> 0.31349133 | D19: =IF(C19="","",C19) -> 0.31349133 | E19: =IF(D19="","",D19) -> 0.31349133 | F19: =IF(E19="","",E19) -> 0.31349133
A20: SG&A / Revenue | B20: =IFERROR(AVERAGE(Model!AC58:AF58,Model!AH58:AI58),"") -> 0.049411891 | C20: =IF(B20="","",B20) -> 0.049411891 | D20: =IF(C20="","",C20) -> 0.049411891 | E20: =IF(D20="","",D20) -> 0.049411891 | F20: =IF(E20="","",E20) -> 0.049411891
A21: D&A / Revenue | B21: =IFERROR(AVERAGE(Model!AC70:AF70,Model!AH70:AI70),"") -> 0.14956388 | C21: =IF(B21="","",B21) -> 0.14956388 | D21: =IF(C21="","",C21) -> 0.14956388 | E21: =IF(D21="","",D21) -> 0.14956388 | F21: =IF(E21="","",E21) -> 0.14956388
A22: Effective tax rate | B22: =IFERROR(AVERAGE(Model!AC131:AF131,Model!AH131:AI131),"") -> 0.27193781 | C22: =IF(B22="","",B22) -> 0.27193781 | D22: =IF(C22="","",C22) -> 0.27193781 | E22: =IF(D22="","",D22) -> 0.27193781 | F22: =IF(E22="","",E22) -> 0.27193781
A23: Financial income / Revenue | B23: =IFERROR(AVERAGE(Model!AC122:AF122,Model!AH122:AI122)/AVERAGE(Model!AC15:AF15,Model!AH15:AI15),"") -> 0.086569494 | C23: =IF(B23="","",B23) -> 0.086569494 | D23: =IF(C23="","",C23) -> 0.086569494 | E23: =IF(D23="","",D23) -> 0.086569494 | F23: =IF(E23="","",E23) -> 0.086569494
A24: Capex / Revenue | B24: =IFERROR(-AVERAGE(Model!AC294:AF294,Model!AH294:AI294)/AVERAGE(Model!AC15:AF15,Model!AH15:AI15),"") -> 0.086611706 | C24: =IF(B24="","",B24) -> 0.086611706 | D24: =IF(C24="","",C24) -> 0.086611706 | E24: =IF(D24="","",D24) -> 0.086611706 | F24: =IF(E24="","",E24) -> 0.086611706
A25: DSO | B25: =IFERROR(AVERAGE(Model!AC145:AF145,Model!AH145:AI145),"") -> 42.176446 | C25: =IF(B25="","",B25) -> 42.176446 | D25: =IF(C25="","",C25) -> 42.176446 | E25: =IF(D25="","",D25) -> 42.176446 | F25: =IF(E25="","",E25) -> 42.176446
A26: DIO | B26: =IFERROR(AVERAGE(Model!AC149:AF149,Model!AH149:AI149),"") -> 0 | C26: =IF(B26="","",B26) -> 0 | D26: =IF(C26="","",C26) -> 0 | E26: =IF(D26="","",D26) -> 0 | F26: =IF(E26="","",E26) -> 0
A27: DPO | B27: =IFERROR(AVERAGE(Model!AC198:AF198,Model!AH198:AI198),"") -> 50.0262 | C27: =IF(B27="","",B27) -> 50.0262 | D27: =IF(C27="","",C27) -> 50.0262 | E27: =IF(D27="","",D27) -> 50.0262 | F27: =IF(E27="","",E27) -> 50.0262
A29: Model status
A30: Source
A31: Unit flow | B31: R$ mil → R$ milhões via Inputs (2)
A32: Historical coverage | B32: =IF(B7="","","1Q21–"&ROUNDUP(MONTH(B7)/3,0)&"Q"&RIGHT(YEAR(B7),2)) -> 1Q21–2Q26
A33: Valuation readiness | B33: =IF(OR(B3="",B4=""),"PENDING COMPANY SETUP",IF(OR(E4="",E5="",E12=""),"PENDING MARKET INPUTS","READY")) -> PENDING MARKET INPUTS
