Workbook
Name beta_observed: Valuation!$D$93
Name beta_observed_unlevered: #REF!
Name beta_unlev_comps: #REF!
Name cirkbreak: #REF!
Name costdebtfirm: #REF!
Name costequity: #REF!
Name Debt: #REF!
Name debt_weight: #REF!
Name last_close: Valuation!$G$7
Name Market_Equity: #REF!
Name midyear: #REF!
Name Net_Debt: #REF!
Name range: #REF!
Name Stub_year_fraction: #REF!
Name ticker: Valuation!$D$7
Name Useful_Life_of_Depreciable_PP_E: "PPElife"
Name beta_observed: #REF!
Name ticker: #REF!
Name costdebtfirm: Valuation!$D$86
Name costequity: Valuation!$D$94
Name debt: Valuation!$G$88
Name debt_weight: Valuation!$J$88
Name g: Valuation!$D$63
Name market_equity: Valuation!$G$89
Name noplat_t1: Valuation!$D$65
Name relevered_beta: Valuation!$M$102
Name risk_free_rate: Valuation!$D$91
Name risk_premium: Valuation!$D$92
Name ronic: Valuation!$D$64
Name stub_year_fraction: Valuation!$D$11
Name totalcap: Valuation!$G$90
Name wacc: Valuation!$D$12
Name scenario: Valuation!$E$8

Sheet Inputs
A1: Fator p/ milhões: | B1: 1 | D1: SIMPAR (SIMH3) - fonte: Planilha de Fundamentos 2T26 do RI (ri.simpar.com.br > Fundamentos e Planilhas): abas Consolidado (DRE e Balanco trimestrais), Fluxo de caixa (acumulado no ano) e abas das controladas. Moeda: BRL. Brutos JA EM R$ MILHOES (fator 1).
J2: Trimestre na fonte | K2: 1T20 | L2: 2T20 | M2: 3T20 | N2: 4T20 | O2: 1T21 | P2: 2T21 | Q2: 3T21 | R2: 4T21 | S2: 1T22 | T2: 2T22 | U2: 3T22 | V2: 4T22 | W2: 1T23 | X2: 2T23 | Y2: 3T23 | Z2: 4T23 | AA2: 1T24 | AB2: 2T24 | AC2: 3T24 | AD2: 4T24 | AE2: 1T25 | AF2: 2T25 | AG2: 3T25 | AH2: 4T25 | AI2: 1T26 | AJ2: 2T26
A4: COD1 | B4: SINAL1 | C4: COD2 | D4: SINAL2 | E4: COD3 | F4: SINAL3 | G4: UNID | H4: Conta (PT) / origem | I4: Account (EN) | J4: ORIGEM | K4: 1Q20 | L4: 2Q20 | M4: 3Q20 | N4: 4Q20 | O4: 1Q21 | P4: 2Q21 | Q4: 3Q21 | R4: 4Q21 | S4: 1Q22 | T4: 2Q22 | U4: 3Q22 | V4: 4Q22 | W4: 1Q23 | X4: 2Q23 | Y4: 3Q23 | Z4: 4Q23 | AA4: 1Q24 | AB4: 2Q24 | AC4: 3Q24 | AD4: 4Q24 | AE4: 1Q25 | AF4: 2Q25 | AG4: 3Q25 | AH4: 4Q25 | AI4: 1Q26 | AJ4: 2Q26
H5: DRE - TRIMESTRE ISOLADO (aba Consolidado, linhas 4-54; R$ milhoes). 1T20 e 4T20 = colunas "2" da planilha: desconsideram o impairment da Movida do 1T20 (nota 2)
A6: 1 | B6: 1 | G6: moeda | H6: (=) Receita Líquida (Consolidado l.10) | J6: fonte | K6: 2356.8923 | L6: 2197.2248 | M6: 2603.0449 | N6: 2649.895 | O6: 2620.1057 | P6: 3149.0663 | Q6: 3958.28 | R6: 4138.767 | S6: 4530.197 | T6: 5387.1474 | U6: 6823.3505 | V6: 7341.1863 | W6: 7440.0438 | X6: 7563.6362 | Y6: 8318.109 | Z6: 8521.824 | AA6: 9066.5964 | AB6: 10227.19 | AC6: 10790.491 | AD6: 10653.809 | AE6: 10244.635 | AF6: 10340.786 | AG6: 11100.933 | AH6: 11119.492 | AI6: 10924.298 | AJ6: 11248.662
A7: 2 | B7: 1 | G7: moeda | H7: Custo de Serviços (Consolidado l.16) (inclui D&A, devolvida abaixo) | J7: fonte | K7: -1038.6836 | L7: -1028.1092 | M7: -1326.0076 | N7: -1630.8336 | O7: -1481.367 | P7: -1652.8268 | Q7: -2035.8914 | R7: -2134.4488 | S7: -2223.278 | T7: -2629.6072 | U7: -3516.1967 | V7: -3955.4359 | W7: -3874.9459 | X7: -4188.9999 | Y7: -4564.5525 | Z7: -5529.0473 | AA7: -4888.5124 | AB7: -5508.3774 | AC7: -5804.7913 | AD7: -6204.2261 | AE7: -5624.734 | AF7: -5675.8107 | AG7: -6069.728 | AH7: -6291.5956 | AI7: -6029.2018 | AJ7: -6368.1225
A8: 2 | B8: 1 | G8: moeda | H8: Custo de Construção (Consolidado l.17) | J8: fonte | K8: 0 | L8: 0 | M8: 0 | N8: 0 | O8: 0 | P8: 0 | Q8: 0 | R8: 0 | S8: 0 | T8: 0 | U8: 0 | V8: 0 | W8: -14.312977 | X8: -10.787482 | Y8: -57.521267 | Z8: -92.885161 | AA8: -118.30826 | AB8: -223.03071 | AC8: -167.6488 | AD8: -209.1667 | AE8: -20.009113 | AF8: -15.237781 | AG8: -39.488761 | AH8: -61.195852 | AI8: -49.969726 | AJ8: -89.118339
A9: 2 | B9: 1 | G9: moeda | H9: Custo de Venda de Ativos (Consolidado l.18) (custo dos seminovos/ativos vendidos - valor contabil) | J9: fonte | K9: -606.92471 | L9: -775.58343 | M9: -736.84785 | N9: -498.74537 | O9: -311.05654 | P9: -519.4787 | Q9: -658.81809 | R9: -588.42666 | S9: -730.09 | T9: -958.129 | U9: -1234.134 | V9: -1243.8387 | W9: -1417.2688 | X9: -1213.5616 | Y9: -1473.4792 | Z9: -1262.398 | AA9: -1616.1813 | AB9: -1917.7287 | AC9: -2118.765 | AD9: -1533.9042 | AE9: -1905.2994 | AF9: -1872.9852 | AG9: -2103.3696 | AH9: -1814.6505 | AI9: -1897.7609 | AJ9: -1610.1056
A10: 3 | B10: 1 | G10: moeda | H10: Despesas Administrativas e Comerciais (Consolidado l.24) | J10: fonte | K10: -220.47711 | L10: -196.51759 | M10: -237.70136 | N10: -306.95917 | O10: -279.24788 | P10: -315.34856 | Q10: -414.17026 | R10: -429.99557 | S10: -459.752 | T10: -536.422 | U10: -641.04493 | V10: -772.00509 | W10: -711.21981 | X10: -723.50546 | Y10: -717.06489 | Z10: -1069.583 | AA10: -796.74091 | AB10: -861.08988 | AC10: -885.70228 | AD10: -907.57643 | AE10: -854.19454 | AF10: -925.89818 | AG10: -973.75871 | AH10: -992.8547 | AI10: -1000.3594 | AJ10: -1044.9958
A11: 3 | B11: 1 | G11: moeda | H11: Despesas Tributárias (Consolidado l.25) | J11: fonte | K11: -3.7134487 | L11: -1.4303652 | M11: -3.7997666 | N11: -4.7581916 | O11: -3.876756 | P11: -3.862527 | Q11: -5.4167488 | R11: -4.2346844 | S11: 0 | T11: 0 | U11: 0 | V11: 0 | W11: 0 | X11: 0 | Y11: -73.854294 | Z11: 13.099838 | AA11: -17.386277 | AB11: -16.999831 | AC11: -21.902204 | AD11: -24.58519 | AE11: -16.930686 | AF11: -16.821631 | AG11: -25.056971 | AH11: -20.919126 | AI11: -22.08476 | AJ11: -25.307738
A12: 3 | B12: 1 | G12: moeda | H12: Outras Receitas (Despesas) Operacionais (Consolidado l.26) (inclui equivalencia patrimonial) | J12: fonte | K12: -201.08978 | L12: 2.9401183 | M12: -1.4278036 | N12: 217.27628 | O12: -27.902485 | P12: 66.025884 | Q12: 45.698271 | R12: 18.977329 | S12: 18.474 | T12: 23.76 | U12: -3.9688666 | V12: -103.39559 | W12: -105.19163 | X12: 161.32539 | Y12: -63.773406 | Z12: 10.584691 | AA12: -90.301822 | AB12: -0.59738857 | AC12: -89.59461 | AD12: -133.70918 | AE12: -73.859858 | AF12: -30.33766 | AG12: -154.72258 | AH12: 929.81234 | AI12: -152.60911 | AJ12: -12.683275
A13: 6 | B13: 1 | G13: moeda | H13: Receitas Financeiras (Consolidado l.33) | J13: fonte | K13: 202.50764 | L13: 257.41068 | M13: 105.50668 | N13: 114.00069 | O13: 225.14892 | P13: 10.13128 | Q13: 210.23048 | R13: 290.85133 | S13: 345.152 | T13: 283.463 | U13: 246.492 | V13: 353.93468 | W13: 338.376 | X13: 183.206 | Y13: 316.416 | Z13: 299.504 | AA13: 367.50281 | AB13: 382.482 | AC13: 432.02735 | AD13: 484.81983 | AE13: 455.02286 | AF13: 516.74414 | AG13: 567.399 | AH13: 540.99036 | AI13: 611.519 | AJ13: 693.054
A14: 5 | B14: 1 | G14: moeda | H14: Despesa Financeiras (Consolidado l.34) | J14: fonte | K14: -372.69144 | L14: -154.39356 | M14: -261.248 | N14: -265.86925 | O14: -454.95787 | P14: -191.11211 | Q14: -526.93389 | R14: -780.95114 | S14: -1017.218 | T14: -1246.042 | U14: -1499.372 | V14: -1595.8405 | W14: -1648.827 | X14: -1664.541 | Y14: -1877.077 | Z14: -1840.783 | AA14: -1808.7842 | AB14: -1862.3567 | AC14: -1990.9005 | AD14: -2181.3582 | AE14: -2235.645 | AF14: -2445.21 | AG14: -2633.139 | AH14: -2646.005 | AI14: -2595.69 | AJ14: -2958.432
A15: 7 | B15: 1 | G15: moeda | H15: Impostos e contribuições sobre o lucro (Consolidado l.37) | J15: fonte | K15: -32.636457 | L15: -144.96427 | M15: -45.564212 | N15: -59.110733 | O15: -115.67799 | P15: -150.76209 | Q15: -173.62383 | R15: -143.94408 | S15: -134.962 | T15: -111.208 | U15: -64.128 | V15: 263.61971 | W15: 70.277896 | X15: -6.8864771 | Y15: 82.158321 | Z15: 231.65526 | AA15: -16.365505 | AB15: -79.027014 | AC15: -41.456355 | AD15: -178.77276 | AE15: 33.112948 | AF15: 76.221045 | AG15: 83.71827 | AH15: -239.26192 | AI15: 58.796699 | AJ15: 40.521435
A16: 6 | B16: 1 | G16: moeda | H16: (-) Prejuízo após os tributos de operações descontinuadas (Consolidado l.41) (operacoes descontinuadas -> cod 6, nao operacional) | J16: fonte | K16: 0 | L16: -19.787 | M16: -8.752 | N16: 0 | O16: 0 | P16: 0 | Q16: 0 | R16: 0 | S16: 0 | T16: 0 | U16: 0 | V16: 0 | W16: 0 | X16: 0 | Y16: 0 | Z16: 0 | AA16: -8.8055272 | AB16: 1.3839526 | AC16: 1.1765506 | AD16: 11.006811 | AE16: 9.5006091 | AF16: 5.6261114 | AG16: 8.7014613 | AH16: -40.983601 | AI16: -21.214936 | AJ16: -24.593788
G17: moeda | H17: (=) Lucro líquido do exercício (l.43) - memoria | J17: memoria | K17: 83.183425 | L17: 136.79017 | M17: 87.203023 | N17: 214.89566 | O17: 171.16807 | P17: 391.83268 | Q17: 399.3545 | R17: 366.59475 | S17: 328.523 | T17: 212.9622 | U17: 110.998 | V17: 288.22496 | W17: 76.931625 | X17: 99.885652 | Y17: -110.63922 | Z17: -718.02862 | AA17: 72.713039 | AB17: 141.84856 | AC17: 102.93343 | AD17: -223.66346 | AE17: 11.598454 | AF17: -42.923824 | AG17: -238.51153 | AH17: 482.82833 | AI17: -174.27665 | AJ17: -151.1218
G18: moeda | H18: (=) Lucro líquido do Controladores (l.46) - memoria | J18: memoria | K18: 54.4 | L18: 155.40027 | M18: 73.166 | N18: 138.96464 | O18: 94.243 | P18: 267.247 | Q18: 245.763 | R18: 215.002 | S18: 191.676 | T18: 101.977 | U18: 18.501 | V18: 169.929 | W18: 6.189 | X18: 12.329 | Y18: -136.515 | Z18: -377.224 | AA18: -13.055231 | AB18: 49.299835 | AC18: 10.84225 | AD18: -245.24247 | AE18: -50.953 | AF18: -96.291 | AG18: -246.193 | AH18: 432.908 | AI18: -179.59733 | AJ18: -189.46967
G19: moeda | H19: EBIT (l.28) - memoria | J19: memoria | K19: 286.00368 | L19: 198.52431 | M19: 297.26056 | N19: 425.87495 | O19: 516.65502 | P19: 723.57559 | Q19: 889.68174 | R19: 1000.6386 | S19: 1135.551 | T19: 1286.7492 | U19: 1428.006 | V19: 1266.5111 | W19: 1317.1047 | X19: 1588.1071 | Y19: 1367.8635 | Z19: 591.59512 | AA19: 1539.1654 | AB19: 1699.3663 | AC19: 1702.0863 | AD19: 1640.6408 | AE19: 1749.607 | AF19: 1803.6949 | AG19: 1734.8087 | AH19: 2868.0885 | AI19: 1772.3126 | AJ19: 2098.3286
G20: moeda | H20: EBITDA (l.49, como divulgado) - memoria | J20: memoria | K20: 561.68639 | L20: 470.43411 | M20: 587.5119 | N20: 699.98255 | O20: 733.70402 | P20: 965.00987 | Q20: 1165.5211 | R20: 1325.431 | S20: 1513.044 | T20: 1702.957 | U20: 1938.0713 | V20: 1849.022 | W20: 1963.8645 | X20: 2267.4931 | Y20: 2084.9445 | Z20: 1652.321 | AA20: 2361.1452 | AB20: 2597.0095 | AC20: 2699.2809 | AD20: 2614.9432 | AE20: 2802.0203 | AF20: 2922.6358 | AG20: 2906.8707 | AH20: 4066.0581 | AI20: 3012.2391 | AJ20: 3351.8827
G21: moeda | H21: EBITDA-A (l.53; EBITDA + custo de venda de ativos) - memoria | J21: memoria | K21: 1168.6111 | L21: 1246.0175 | M21: 1324.3598 | N21: 1198.7279 | O21: 1044.7606 | P21: 1484.4886 | Q21: 1824.3392 | R21: 1913.8577 | S21: 2243.134 | T21: 2661.086 | U21: 3172.2053 | V21: 3092.8606 | W21: 3381.1333 | X21: 3481.0547 | Y21: 3558.4237 | Z21: 2914.7189 | AA21: 3977.3265 | AB21: 4514.7382 | AC21: 4818.0459 | AD21: 4148.8474 | AE21: 4707.3197 | AF21: 4795.621 | AG21: 5010.2404 | AH21: 5880.7087 | AI21: 4910 | AJ21: 4961.9883
H22: DFC - ACUMULADO NO ANO (aba Fluxo de caixa; R$ milhoes). ATENCAO: colunas de periodos diferentes vem de documentos com reapresentacoes (ex.: 9M20 < 6M20 em dividendos)
G23: moeda | H23: Dividendos e JCP pagos (DFC l.59, acum.) | J23: memoria | K23: -41.585 | L23: -55.41 | M23: -33.956 | N23: -48.856 | O23: -23.249 | P23: -83.506 | Q23: -113.606 | R23: -226.573 | S23: -125.184 | T23: -546.665 | U23: -595.858 | V23: -415.184 | W23: -125.974 | X23: -235.098 | Y23: -257.782 | Z23: -481.563 | AA23: 0 | AB23: 0 | AC23: -112.087 | AD23: -157.178 | AE23: -40.884 | AF23: -230.635 | AG23: -236.437 | AH23: -229.051 | AI23: 0 | AJ23: -168.72
G24: moeda | H24: Depreciacao, amortizacao e impairment (DFC l.8, acum.) - memoria | J24: memoria | K24: 471.075 | L24: 742.986 | M24: 1033.238 | N24: 1257.202 | O24: 217.049 | P24: 458.483 | Q24: 734.322 | R24: 1059.114 | S24: 377.493 | T24: 793.699 | U24: 1303.765 | V24: 1895.775 | W24: 646.761 | X24: 1326.146 | Y24: 2043.227 | Z24: 3481.049 | AA24: 813.581 | AB24: 1858.994 | AC24: 2914.121 | AD24: 4010.493 | AE24: 1070.425 | AF24: 2322.567 | AG24: 3646.428 | AH24: 4882.131 | AI24: 1340.958 | AJ24: 1291.856
G25: moeda | H25: Compra de imobilizado operacional para locacao (DFC l.32, acum.) - memoria | J25: memoria | K25: -1245.249 | L25: -2036.648 | M25: -3175.716 | N25: -4460.52 | O25: -1766.086 | P25: -3980.548 | Q25: -7316.132 | R25: -10084.996 | S25: -3561.009 | T25: -7501.827 | U25: -12980.307 | V25: -15080.412 | W25: -3703.141 | X25: -6491.819 | Y25: -9095.136 | Z25: -10477.54 | AA25: -4241.138 | AB25: -8468.889 | AC25: -11831.202 | AD25: -14859.243 | AE25: -2614.813 | AF25: -6178.595 | AG25: -8977.631 | AH25: -12997.609 | AI25: -1809.101 | AJ25: -4642.176
H26: DERIVADAS (formula nesta aba)
A27: 4 | B27: -1 | C27: 2 | D27: 1 | G27: moeda | H27: D&A = EBITDA - EBIT divulgados (l.49 - l.28). COD1=4 lanca; COD2=2 devolve ao custo (depreciacao da frota esta no custo) | J27: derivada | K27: =K20-K19 -> 275.68271 | L27: =L20-L19 -> 271.9098 | M27: =M20-M19 -> 290.25134 | N27: =N20-N19 -> 274.10759 | O27: =O20-O19 -> 217.049 | P27: =P20-P19 -> 241.43428 | Q27: =Q20-Q19 -> 275.83937 | R27: =R20-R19 -> 324.79236 | ... AJ27: =AJ20-AJ19 -> 1253.5541
A28: 9 | B28: 1 | G28: moeda | H28: Participacao de nao controladores = lucro dos controladores - lucro total (l.46 - l.43; negativo quando os minoritarios tem lucro) | J28: derivada | K28: =K18-K17 -> -28.783425 | L28: =L18-L17 -> 18.610103 | M28: =M18-M17 -> -14.037023 | N28: =N18-N17 -> -75.931013 | O28: =O18-O17 -> -76.925074 | P28: =P18-P17 -> -124.58568 | Q28: =Q18-Q17 -> -153.5915 | R28: =R18-R17 -> -151.59275 | ... AJ28: =AJ18-AJ17 -> -38.347865
A29: 44 | B29: 1 | G29: moeda | H29: Lucro liquido dos controladores (l.46) - COD 44 alimenta o check IS do Model (linha 4) | J29: derivada | K29: =K18 -> 54.4 | L29: =L18 -> 155.40027 | M29: =M18 -> 73.166 | N29: =N18 -> 138.96464 | O29: =O18 -> 94.243 | P29: =P18 -> 267.247 | Q29: =Q18 -> 245.763 | R29: =R18 -> 215.002 | ... AJ29: =AJ18 -> -189.46967
A30: 10 | B30: 1 | G30: moeda | H30: Dividendos e JCP pagos (DFC trimestralizado; trimestres com reapresentacao podem sair positivos) | J30: derivada | K30: =N(K23) -> -41.585 | L30: =N(L23)-N(K23) -> -13.825 | M30: =N(M23)-N(L23) -> 21.454 | N30: =N(N23)-N(M23) -> -14.9 | O30: =N(O23) -> -23.249 | P30: =N(P23)-N(O23) -> -60.257 | Q30: =N(Q23)-N(P23) -> -30.1 | R30: =N(R23)-N(Q23) -> -112.967 | S30: =N(S23) -> -125.184 | T30: =N(T23)-N(S23) -> -421.481 | U30: =N(U23)-N(T23) -> -49.193 | V30: =N(V23)-N(U23) -> 180.674 | W30: =N(W23) -> -125.974 | X30: =N(X23)-N(W23) -> -109.124 | Y30: =N(Y23)-N(X23) -> -22.684 | Z30: =N(Z23)-N(Y23) -> -223.781 | AA30: =N(AA23) -> 0 | AB30: =N(AB23)-N(AA23) -> 0 | AC30: =N(AC23)-N(AB23) -> -112.087 | AD30: =N(AD23)-N(AC23) -> -45.091 | AE30: =N(AE23) -> -40.884 | AF30: =N(AF23)-N(AE23) -> -189.751 | AG30: =N(AG23)-N(AF23) -> -5.802 | AH30: =N(AH23)-N(AG23) -> 7.386 | AI30: =N(AI23) -> 0 | AJ30: =N(AJ23)-N(AI23) -> -168.72
G31: moeda | H31: Capex de frota (DFC trimestralizado) - memoria | J31: derivada | K31: =N(K25) -> -1245.249 | L31: =N(L25)-N(K25) -> -791.399 | M31: =N(M25)-N(L25) -> -1139.068 | N31: =N(N25)-N(M25) -> -1284.804 | O31: =N(O25) -> -1766.086 | P31: =N(P25)-N(O25) -> -2214.462 | Q31: =N(Q25)-N(P25) -> -3335.584 | R31: =N(R25)-N(Q25) -> -2768.864 | S31: =N(S25) -> -3561.009 | T31: =N(T25)-N(S25) -> -3940.818 | U31: =N(U25)-N(T25) -> -5478.48 | V31: =N(V25)-N(U25) -> -2100.105 | W31: =N(W25) -> -3703.141 | X31: =N(X25)-N(W25) -> -2788.678 | Y31: =N(Y25)-N(X25) -> -2603.317 | Z31: =N(Z25)-N(Y25) -> -1382.404 | AA31: =N(AA25) -> -4241.138 | AB31: =N(AB25)-N(AA25) -> -4227.751 | AC31: =N(AC25)-N(AB25) -> -3362.313 | AD31: =N(AD25)-N(AC25) -> -3028.041 | AE31: =N(AE25) -> -2614.813 | AF31: =N(AF25)-N(AE25) -> -3563.782 | AG31: =N(AG25)-N(AF25) -> -2799.036 | AH31: =N(AH25)-N(AG25) -> -4019.978 | AI31: =N(AI25) -> -1809.101 | AJ31: =N(AJ25)-N(AI25) -> -2833.075
H32: BALANCO (aba Consolidado, linhas 64-181; R$ milhoes, fim de trimestre)
A33: 11 | B33: 1 | G33: moeda | H33: A: Caixa e equivalentes de caixa (l.67) | J33: fonte | K33: 580.58739 | L33: 753.93436 | M33: 641.479 | N33: 409.60138 | O33: 1726.239 | P33: 3301.653 | Q33: 5168.084 | R33: 1029.384 | S33: 2552.381 | T33: 2530.055 | U33: 1884.29 | V33: 1718.025 | W33: 2623.6717 | X33: 1586.5072 | Y33: 1636.2833 | Z33: 1345.475 | AA33: 1553.012 | AB33: 2098.1617 | AC33: 1868.1544 | AD33: 1885.4154 | AE33: 1730.6384 | AF33: 2214.5866 | AG33: 3105.4519 | AH33: 2953.811 | AI33: 3477.9485 | AJ33: 3441.5673
A34: 11 | B34: 1 | G34: moeda | H34: A: Títulos e valores mobiliários (l.68) | J34: fonte | K34: 5935.2547 | L34: 7483.9905 | M34: 7128.441 | N34: 7918.78 | O34: 9102.152 | P34: 8800.845 | Q34: 11475.516 | R34: 17622.841 | S34: 12143.677 | T34: 12483.413 | U34: 13473.979 | V34: 11024.128 | W34: 7154.9991 | X34: 6184.3166 | Y34: 6324.0083 | Z34: 9600.8353 | AA34: 11216.067 | AB34: 9927.8475 | AC34: 12137.606 | AD34: 11288.479 | AE34: 11594.217 | AF34: 10123.046 | AG34: 9369.5804 | AH34: 11074.648 | AI34: 11703.556 | AJ34: 10442.73
A35: 16 | B35: 1 | G35: moeda | H35: A: Instrumentos financeiros derivativos (l.69) | J35: fonte | K35: 30.0589 | L35: 30.921311 | M35: 82.1 | N35: 80.38 | O35: 20.33803 | P35: 0.116 | Q35: 0.147 | R35: 0.147 | S35: 0.147 | T35: 0.079 | U35: 7.605 | V35: 0.086 | W35: 0.0820253 | X35: 0.04496455 | Y35: 2.7251504 | Z35: 29.180997 | AA35: 31.840035 | AB35: 248.27592 | AC35: 272.11148 | AD35: 1033.6062 | AE35: 521.73347 | AF35: 157.77192 | AG35: 156.77727 | AH35: 147.06728 | AI35: 116.73912 | AJ35: 84.271308
A36: 12 | B36: 1 | G36: moeda | H36: A: Contas a receber (l.70) | J36: fonte | K36: 1591.8635 | L36: 1627.089 | M36: 1741.4563 | N36: 1934.4459 | O36: 2151.3927 | P36: 2430.89 | Q36: 2779.127 | R36: 3260.329 | S36: 3702.988 | T36: 3976.906 | U36: 4223.848 | V36: 4433.345 | W36: 4794.6021 | X36: 5221.9683 | Y36: 5708.6408 | Z36: 5106.6802 | AA36: 5418.7127 | AB36: 5801.9812 | AC36: 6344.7848 | AD36: 6051.441 | AE36: 6817.3601 | AF36: 7493.7022 | AG36: 7771.081 | AH36: 7614.7977 | AI36: 7759.6153 | AJ36: 8715.7413
A37: 13 | B37: 1 | G37: moeda | H37: A: Estoques (l.71) | J37: fonte | K37: 308.24344 | L37: 292.12009 | M37: 235.56131 | N37: 213.01693 | O37: 255.36257 | P37: 378.575 | Q37: 378.18 | R37: 525.95 | S37: 596.625 | T37: 775.164 | U37: 1166.831 | V37: 1694.32 | W37: 1774.0662 | X37: 2010.4287 | Y37: 2549.5825 | Z37: 2890.5094 | AA37: 2876.0548 | AB37: 2973.7873 | AC37: 3204.8421 | AD37: 3180.4208 | AE37: 3017.7035 | AF37: 3009.3821 | AG37: 2814.7036 | AH37: 2827.6063 | AI37: 2524.4447 | AJ37: 2670.2405
A38: 16 | B38: 1 | G38: moeda | H38: A: Tributos a recuperar (l.72) | J38: fonte | K38: 122.99103 | L38: 97.706754 | M38: 115.61314 | N38: 160.48997 | O38: 150.9978 | P38: 114.452 | Q38: 162.229 | R38: 325.496 | S38: 377.863 | T38: 446.778 | U38: 496.207 | V38: 361.125 | W38: 325.88766 | X38: 388.85872 | Y38: 431.68915 | Z38: 499.76457 | AA38: 525.30188 | AB38: 538.20681 | AC38: 499.48772 | AD38: 461.80213 | AE38: 445.81045 | AF38: 606.92628 | AG38: 547.308 | AH38: 506.63815 | AI38: 585.23837 | AJ38: 446.31355
A39: 16 | B39: 1 | G39: moeda | H39: A: Imposto de renda e contribuição social a recuperar (l.73) | J39: fonte | K39: 217.93655 | L39: 372.23178 | M39: 372.73579 | N39: 298.45131 | O39: 214.99823 | P39: 268.861 | Q39: 283.454 | R39: 227.643 | S39: 277.368 | T39: 389.085 | U39: 508.702 | V39: 577.912 | W39: 563.13959 | X39: 623.51458 | Y39: 683.05489 | Z39: 855.07584 | AA39: 821.74362 | AB39: 854.26953 | AC39: 822.08008 | AD39: 937.23422 | AE39: 1086.4658 | AF39: 1227.8204 | AG39: 1224.878 | AH39: 1091.0048 | AI39: 1100.7377 | AJ39: 1189.6287
A40: 15 | B40: 1 | G40: moeda | H40: A: Despesas antecipadas (l.74) | J40: fonte | K40: 140.32446 | L40: 110.5702 | M40: 90.579392 | N40: 58.314227 | O40: 154.82687 | P40: 145.481 | Q40: 115.248 | R40: 67.977 | S40: 219.519 | T40: 189.826 | U40: 176.358 | V40: 98.457 | W40: 205.01664 | X40: 348.50864 | Y40: 264.29539 | Z40: 127.72711 | AA40: 393.75851 | AB40: 415.55977 | AC40: 320.16497 | AD40: 165.44256 | AE40: 537.14427 | AF40: 508.51692 | AG40: 346.88826 | AH40: 211.97374 | AI40: 581.06858 | AJ40: 475.81639
A41: 16 | B41: 1 | G41: moeda | H41: A: Dividendos a receber (l.75) | J41: fonte | K41: 0 | L41: 0 | M41: 0.02337902 | N41: 0 | O41: 0 | P41: 0 | Q41: 0 | R41: 0 | S41: 0 | T41: 0.28 | U41: 0.572 | V41: 0 | W41: 0.32206496 | X41: 1e-08 | Y41: -5e-08 | Z41: -5e-08 | AA41: 0.58519963 | AB41: 0.58519964 | AC41: 0.58519969 | AD41: 0.74816063 | AE41: 0.16296194 | AF41: 0.43468422 | AG41: 0.43464383 | AH41: 0.4346845 | AI41: 3.3446438 | AJ41: 0.58093421
A42: 16 | B42: 1 | G42: moeda | H42: A: Ativo imobilizado disponibilizado para venda (l.76) (frota desmobilizada para venda) | J42: fonte | K42: 633.57521 | L42: 684.01637 | M42: 314.7331 | N42: 320.87883 | O42: 359.34465 | P42: 508.655 | Q42: 459.638 | R42: 431.962 | S42: 757.035 | T42: 851.292 | U42: 1218.401 | V42: 1527.738 | W42: 1320.499 | X42: 1262.9172 | Y42: 1515.0643 | Z42: 1262.2403 | AA42: 1642.618 | AB42: 1931.5978 | AC42: 1992.7722 | AD42: 1575.6142 | AE42: 2188.2198 | AF42: 2405.4218 | AG42: 2024.0543 | AH42: 1337.6633 | AI42: 1542.3472 | AJ42: 1575.5158
A43: 16 | B43: 1 | G43: moeda | H43: A: Adiantamento de Terceiros (l.77) | J43: fonte | K43: 70.840052 | L43: 40.545099 | M43: 43.784999 | N43: 43.689136 | O43: 45.776 | P43: 52.81 | Q43: 72.564 | R43: 69.14 | S43: 59.008 | T43: 75.926 | U43: 134.897 | V43: 111.317 | W43: 107.18445 | X43: 225.4188 | Y43: 349.27026 | Z43: 380.19028 | AA43: 387.1204 | AB43: 377.00344 | AC43: 360.7451 | AD43: 404.14144 | AE43: 313.22812 | AF43: 364.40968 | AG43: 387.65598 | AH43: 513.72333 | AI43: 512.43217 | AJ43: 479.71124
A44: 16 | B44: 1 | G44: moeda | H44: A: Adiantamento a terceiros - Intergrupo (l.78) | J44: fonte | K44: 0 | L44: 0 | M44: 0 | N44: 0 | O44: 0 | P44: 0 | Q44: 0 | R44: 0 | S44: 69.144 | T44: 105.091 | U44: 0 | V44: 0 | W44: 0 | X44: 0 | Y44: 0 | Z44: 0.04961745 | AA44: 0 | AB44: 0 | AC44: 0 | AD44: 0 | AE44: 0.79189683 | AF44: 0.59835376 | AG44: 0.81500159 | AH44: 0 | AI44: -50.778949 | AJ44: -23.984469
... A117: 40 | B117: 1 | G117: moeda | H117: PL: Outros ajustes patrimoniais reflexos de controladas (l.178) | J117: fonte | K117: 286.76 | L117: 376.82141 | M117: -118.919 | N117: -120.471 | O117: -158.278 | P117: -113.68 | Q117: -226.171 | R117: -269.203 | S117: -440.692 | T117: -717.596 | U117: 0 | V117: -721.574 | W117: 3.5597244 | X117: 3.5597244 | Y117: -97.444276 | Z117: 25.628118 | AA117: -30.43085 | AB117: -66.011774 | AC117: -17.889584 | AD117: 0.20780122 | AE117: -4.5191064 | AF117: 563.49859 | AG117: 651.52011 | AH117: 874.54394 | AI117: 793.66738 | AJ117: 775.32692
H118: BALANCO - totais divulgados (memoria)
G119: moeda | H119: Total do ativo (l.116) | J119: memoria | K119: 21556.885 | L119: 22603.402 | M119: 22774.199 | N119: 25562.25 | O119: 31959.714 | P119: 33773.128 | Q119: 41082.055 | R119: 47968.194 | S119: 47543.699 | T119: 52956.699 | U119: 59006.238 | V119: 61659.514 | W119: 59367.331 | X119: 60059.526 | Y119: 62697.615 | Z119: 70140.839 | AA119: 74190.125 | AB119: 76293.225 | AC119: 80107.523 | AD119: 83152.865 | AE119: 81029.261 | AF119: 81414.237 | AG119: 81263.335 | AH119: 86702.213 | AI119: 87178.624 | AJ119: 91594.776
G120: moeda | H120: Total do passivo e PL (l.181) | J120: memoria | K120: 21556.883 | L120: 22603.402 | M120: 22774.194 | N120: 25562.248 | O120: 31959.715 | P120: 33773.127 | Q120: 41082.055 | R120: 47968.194 | S120: 47543.699 | T120: 52956.699 | U120: 59006.238 | V120: 61659.514 | W120: 59367.299 | X120: 60059.524 | Y120: 62697.614 | Z120: 70140.84 | AA120: 74190.125 | AB120: 76293.224 | AC120: 80107.519 | AD120: 83152.881 | AE120: 81029.282 | AF120: 81414.253 | AG120: 81263.301 | AH120: 86702.214 | AI120: 87178.624 | AJ120: 91594.776
G121: moeda | H121: Divida liquida (l.208, conceito da Cia) - memoria | J121: memoria | K121: 8012.7312 | L121: 8497.6937 | M121: 7624.0095 | N121: 8470.6049 | O121: 9494.9313 | P121: 10782.323 | Q121: 12482.595 | R121: 15479.61 | S121: 18005.872 | T121: 21998.237 | U121: 24496.265 | V121: 26040.934 | W121: 28454.065 | X121: 31465.992 | Y121: 31605.173 | Z121: 31745.27 | AA121: 33536.479 | AB121: 36221.215 | AC121: 37861.419 | AD121: 39880.033 | AE121: 41337.646 | AF121: 42537.963 | AG121: 41627.909 | AH121: 40561.902 | AI121: 41796.451 | AJ121: 41288.431
H122: CHECKS (devem ser 0)
G123: moeda | H123: CHECK: receita + custos + despesas op. + resultado financeiro + IR + descontinuadas - lucro liquido total | J123: derivada | K123: =ROUND(K6+K7+K8+K9+K10+K11+K12+K13+K14+K15+K16-K17,1) -> 0 | L123: =ROUND(L6+L7+L8+L9+L10+L11+L12+L13+L14+L15+L16-L17,1) -> 0 | M123: =ROUND(M6+M7+M8+M9+M10+M11+M12+M13+M14+M15+M16-M17,1) -> 0 | N123: =ROUND(N6+N7+N8+N9+N10+N11+N12+N13+N14+N15+N16-N17,1) -> 0 | O123: =ROUND(O6+O7+O8+O9+O10+O11+O12+O13+O14+O15+O16-O17,1) -> 0 | P123: =ROUND(P6+P7+P8+P9+P10+P11+P12+P13+P14+P15+P16-P17,1) -> 0 | Q123: =ROUND(Q6+Q7+Q8+Q9+Q10+Q11+Q12+Q13+Q14+Q15+Q16-Q17,1) -> 0 | R123: =ROUND(R6+R7+R8+R9+R10+R11+R12+R13+R14+R15+R16-R17,1) -> 0 | ... AJ123: =ROUND(AJ6+AJ7+AJ8+AJ9+AJ10+AJ11+AJ12+AJ13+AJ14+AJ15+AJ16-AJ17,1) -> 0
G124: moeda | H124: CHECK: contas de ativo - ativo total | J124: derivada | K124: =ROUND(K33+K34+K35+K36+K37+K38+K39+K40+K41+K42+K43+K44+K45+K46+K47+K48+K49+K50+K51+K52+K53+K54+K55+K56+K57+K58+K59+K60+K61+K62+K63+K64+K65-K119,1) -> 0 | L124: =ROUND(L33+L34+L35+L36+L37+L38+L39+L40+L41+L42+L43+L44+L45+L46+L47+L48+L49+L50+L51+L52+L53+L54+L55+L56+L57+L58+L59+L60+L61+L62+L63+L64+L65-L119,1) -> 0 | M124: =ROUND(M33+M34+M35+M36+M37+M38+M39+M40+M41+M42+M43+M44+M45+M46+M47+M48+M49+M50+M51+M52+M53+M54+M55+M56+M57+M58+M59+M60+M61+M62+M63+M64+M65-M119,1) -> 0 | N124: =ROUND(N33+N34+N35+N36+N37+N38+N39+N40+N41+N42+N43+N44+N45+N46+N47+N48+N49+N50+N51+N52+N53+N54+N55+N56+N57+N58+N59+N60+N61+N62+N63+N64+N65-N119,1) -> 0 | O124: =ROUND(O33+O34+O35+O36+O37+O38+O39+O40+O41+O42+O43+O44+O45+O46+O47+O48+O49+O50+O51+O52+O53+O54+O55+O56+O57+O58+O59+O60+O61+O62+O63+O64+O65-O119,1) -> 0 | P124: =ROUND(P33+P34+P35+P36+P37+P38+P39+P40+P41+P42+P43+P44+P45+P46+P47+P48+P49+P50+P51+P52+P53+P54+P55+P56+P57+P58+P59+P60+P61+P62+P63+P64+P65-P119,1) -> 0 | Q124: =ROUND(Q33+Q34+Q35+Q36+Q37+Q38+Q39+Q40+Q41+Q42+Q43+Q44+Q45+Q46+Q47+Q48+Q49+Q50+Q51+Q52+Q53+Q54+Q55+Q56+Q57+Q58+Q59+Q60+Q61+Q62+Q63+Q64+Q65-Q119,1) -> 0 | R124: =ROUND(R33+R34+R35+R36+R37+R38+R39+R40+R41+R42+R43+R44+R45+R46+R47+R48+R49+R50+R51+R52+R53+R54+R55+R56+R57+R58+R59+R60+R61+R62+R63+R64+R65-R119,1) -> 0 | ... AJ124: =ROUND(AJ33+AJ34+AJ35+AJ36+AJ37+AJ38+AJ39+AJ40+AJ41+AJ42+AJ43+AJ44+AJ45+AJ46+AJ47+AJ48+AJ49+AJ50+AJ51+AJ52+AJ53+AJ54+AJ55+AJ56+AJ57+AJ58+AJ59+AJ60+AJ61+AJ62+AJ63+AJ64+AJ65-AJ119,1) -> 0
G125: moeda | H125: CHECK: passivo + PL - passivo total | J125: derivada | K125: =ROUND(K66+K67+K68+K69+K70+K71+K72+K73+K74+K75+K76+K77+K78+K79+K80+K81+K82+K83+K84+K85+K86+K87+K88+K89+K90+K91+K92+K93+K94+K95+K96+K97+K98+K99+K100+K101+K102+K103+K104+K105+K106+K107+K108+K109+K110+K111+K112+K113+K114+K115+K116+K117-K120,1) -> 0 | L125: =ROUND(L66+L67+L68+L69+L70+L71+L72+L73+L74+L75+L76+L77+L78+L79+L80+L81+L82+L83+L84+L85+L86+L87+L88+L89+L90+L91+L92+L93+L94+L95+L96+L97+L98+L99+L100+L101+L102+L103+L104+L105+L106+L107+L108+L109+L110+L111+L112+L113+L114+L115+L116+L117-L120,1) -> 0 | M125: =ROUND(M66+M67+M68+M69+M70+M71+M72+M73+M74+M75+M76+M77+M78+M79+M80+M81+M82+M83+M84+M85+M86+M87+M88+M89+M90+M91+M92+M93+M94+M95+M96+M97+M98+M99+M100+M101+M102+M103+M104+M105+M106+M107+M108+M109+M110+M111+M112+M113+M114+M115+M116+M117-M120,1) -> 0 | N125: =ROUND(N66+N67+N68+N69+N70+N71+N72+N73+N74+N75+N76+N77+N78+N79+N80+N81+N82+N83+N84+N85+N86+N87+N88+N89+N90+N91+N92+N93+N94+N95+N96+N97+N98+N99+N100+N101+N102+N103+N104+N105+N106+N107+N108+N109+N110+N111+N112+N113+N114+N115+N116+N117-N120,1) -> 0 | O125: =ROUND(O66+O67+O68+O69+O70+O71+O72+O73+O74+O75+O76+O77+O78+O79+O80+O81+O82+O83+O84+O85+O86+O87+O88+O89+O90+O91+O92+O93+O94+O95+O96+O97+O98+O99+O100+O101+O102+O103+O104+O105+O106+O107+O108+O109+O110+O111+O112+O113+O114+O115+O116+O117-O120,1) -> 0 | P125: =ROUND(P66+P67+P68+P69+P70+P71+P72+P73+P74+P75+P76+P77+P78+P79+P80+P81+P82+P83+P84+P85+P86+P87+P88+P89+P90+P91+P92+P93+P94+P95+P96+P97+P98+P99+P100+P101+P102+P103+P104+P105+P106+P107+P108+P109+P110+P111+P112+P113+P114+P115+P116+P117-P120,1) -> 0 | Q125: =ROUND(Q66+Q67+Q68+Q69+Q70+Q71+Q72+Q73+Q74+Q75+Q76+Q77+Q78+Q79+Q80+Q81+Q82+Q83+Q84+Q85+Q86+Q87+Q88+Q89+Q90+Q91+Q92+Q93+Q94+Q95+Q96+Q97+Q98+Q99+Q100+Q101+Q102+Q103+Q104+Q105+Q106+Q107+Q108+Q109+Q110+Q111+Q112+Q113+Q114+Q115+Q116+Q117-Q120,1) -> 0 | R125: =ROUND(R66+R67+R68+R69+R70+R71+R72+R73+R74+R75+R76+R77+R78+R79+R80+R81+R82+R83+R84+R85+R86+R87+R88+R89+R90+R91+R92+R93+R94+R95+R96+R97+R98+R99+R100+R101+R102+R103+R104+R105+R106+R107+R108+R109+R110+R111+R112+R113+R114+R115+R116+R117-R120,1) -> 0 | ... AJ125: =ROUND(AJ66+AJ67+AJ68+AJ69+AJ70+AJ71+AJ72+AJ73+AJ74+AJ75+AJ76+AJ77+AJ78+AJ79+AJ80+AJ81+AJ82+AJ83+AJ84+AJ85+AJ86+AJ87+AJ88+AJ89+AJ90+AJ91+AJ92+AJ93+AJ94+AJ95+AJ96+AJ97+AJ98+AJ99+AJ100+AJ101+AJ102+AJ103+AJ104+AJ105+AJ106+AJ107+AJ108+AJ109+AJ110+AJ111+AJ112+AJ113+AJ114+AJ115+AJ116+AJ117-AJ120,1) -> 0
H126: [vazio] cod 8 Equity in affiliates: dentro de "Outras receitas (despesas) operacionais" na planilha
H127: [vazio] cod 20 Goodwill: dentro do intangivel
H128: [vazio] cod 28 Revolver: sem linha propria
H129: [vazio] cod 32 Convertible debt: inexistente
H130: [vazio] cod 36 Convertible Preferred Stock: inexistente
H132: DRIVERS DE RECEITA (codigos 45+): receita por natureza e por controlada (R$ milhoes, UNID moeda, fator 1) e KPIs operacionais (UNID un) da Planilha de Fundamentos.
A133: 45 | B133: 1 | G133: moeda | H133: Receita liquida de vendas e prestacao de servicos (Consolidado l.11) | J133: fonte | K133: 1710.2773 | L133: 1331.1136 | M133: 1812.4828 | N133: 2092.2813 | O133: 2228.9893 | P133: 2434.4397 | Q133: 3035.233 | R133: 3306.956 | S133: 3513.118 | T133: 4128.0414 | U133: 5325.2895 | V133: 5865.3716 | W133: 5777.4338 | X133: 6044.1637 | Y133: 6692.1315 | Z133: 7086.9051 | AA133: 7163.3457 | AB133: 7938.0944 | AC133: 8358.2245 | AD133: 8796.8193 | AE133: 8189.7475 | AF133: 8295.8503 | AG133: 8958.1003 | AH133: 9041.6002 | AI133: 8877.85 | AJ133: 9488.0486
A134: 46 | B134: 1 | G134: moeda | H134: Receita liquida de construcao (Consolidado l.12; concessoes - ICPC 01) | J134: fonte | K134: 0 | L134: 0 | M134: 0 | N134: 0 | O134: 0 | P134: 0 | Q134: 0 | R134: 0 | S134: 0 | T134: 0 | U134: 0 | V134: 0 | W134: 14.312977 | X134: 10.787482 | Y134: 57.521542 | Z134: 92.884887 | AA134: 118.30826 | AB134: 223.03071 | AC134: 167.6489 | AD134: 209.1667 | AE134: 20.009113 | AF134: 15.237781 | AG134: 39.488761 | AH134: 61.195852 | AI134: 49.969726 | AJ134: 89.118339
A135: 47 | B135: 1 | G135: moeda | H135: Receita liquida de renovacao de frota / venda de ativos (Consolidado l.13) | J135: fonte | K135: 646.61535 | L135: 866.11079 | M135: 790.5619 | N135: 557.61395 | O135: 391.11638 | P135: 714.62662 | Q135: 923.047 | R135: 831.811 | S135: 1017.079 | T135: 1259.106 | U135: 1498.061 | V135: 1475.8147 | W135: 1648.297 | X135: 1508.685 | Y135: 1568.456 | Z135: 1342.034 | AA135: 1784.9425 | AB135: 2066.065 | AC135: 2264.6172 | AD135: 1647.8227 | AE135: 2034.878 | AF135: 2029.698 | AG135: 2103.3444 | AH135: 2016.6959 | AI135: 1996.4786 | AJ135: 1671.4949
A136: 48 | B136: 1 | G136: moeda | H136: Receita liquida - JSL (aba JSL l.23) | J136: fonte | K136: 693.77792 | L136: 581.6444 | M136: 733.23156 | N136: 818.15111 | O136: 868.17128 | P136: 922.36676 | Q136: 1177.7676 | R136: 1327.7631 | S136: 1296.4594 | T136: 1438.6826 | U136: 1624.8181 | V136: 1662.4452 | W136: 1563.5778 | X136: 1839.5752 | Y136: 2010.1251 | Z136: 2161.3661 | AA136: 2070.3405 | AB136: 2142.5947 | AC136: 2352.356 | AD136: 2490.9668 | AE136: 2319.9344 | AF136: 2381.7586 | AG136: 2484.8932 | AH136: 2454.022 | AI136: 2372.7115 | AJ136: 2498.854
A137: 49 | B137: 1 | G137: moeda | H137: Receita liquida de servicos - JSL (aba JSL l.24) | J137: fonte | K137: 656.29898 | L137: 550.21168 | M137: 660.67811 | N137: 789.14901 | O137: 853.24253 | P137: 902.46296 | Q137: 1150.1477 | R137: 1306.8653 | S137: 1267.6136 | T137: 1372.7187 | U137: 1570.7923 | V137: 1607.6705 | W137: 1505.4569 | X137: 1779.1681 | Y137: 1942.8758 | Z137: 2071.4733 | AA137: 1993.4498 | AB137: 2073.1724 | AC137: 2284.4237 | AD137: 2411.3388 | AE137: 2229.4554 | AF137: 2274.3119 | AG137: 2369.647 | AH137: 2354.7274 | AI137: 2272.7645 | AJ137: 2409.504
A138: 50 | B138: 1 | G138: moeda | H138: Receita liquida - Movida (aba Movida l.15) | J138: fonte | K138: 1011.166 | L138: 1047.824 | M138: 1035.5683 | N138: 990.70076 | O138: 804.889 | P138: 1211.4988 | Q138: 1575.241 | R138: 1740.9938 | S138: 1905.6571 | T138: 2230.9922 | U138: 2536.8641 | V138: 2626.6328 | W138: 2703.2063 | X138: 2479.1443 | Y138: 2666.2199 | Z138: 2493.4442 | AA138: 3021.6459 | AB138: 3435.6036 | AC138: 3775.8637 | AD138: 3248.157 | AE138: 3568.2305 | AF138: 3679.0056 | AG138: 3765.8428 | AH138: 3658.9752 | AI138: 3780.645 | AJ138: 3765.8302
A139: 51 | B139: 1 | G139: moeda | H139: Receita liquida de servicos - Movida (aba Movida l.16) | J139: fonte | K139: 451.96694 | L139: 298.74775 | M139: 394.70364 | N139: 499.98813 | O139: 530.34866 | P139: 538.01874 | Q139: 730.62053 | R139: 931.87856 | S139: 931.89505 | T139: 1002.3577 | U139: 1126.4365 | V139: 1222.2256 | W139: 1239.7417 | X139: 1233.7808 | Y139: 1297.3177 | Z139: 1339.6205 | AA139: 1495.1983 | AB139: 1608.0605 | AC139: 1744.7243 | AD139: 1791.0569 | AE139: 1878.9041 | AF139: 1892.632 | AG139: 2010.8116 | AH139: 2096.3941 | AI139: 2205.6165 | AJ139: 2295.3346
A140: 52 | B140: 1 | G140: moeda | H140: Receita liquida - Vamos locacao + industria. 1T23+: aba VAMOS - Income Statement l.21 (SIMPAR); 1T20-4T22: Planilha de Fundamentos ANTIGA da Vamos (com concessionarias, ate 3T24), aba VAMOS DRE_BP l.65 (locacoes) + l.130 (customizacao/industria) | J140: fonte | K140: 204.44394 | L140: 197.51018 | M140: 223.01141 | N140: 253.47815 | O140: 265.74583 | P140: 273.97073 | Q140: 303.68842 | R140: 328.26959 | S140: 366.98904 | T140: 461.85636 | U140: 590.21934 | V140: 715.33438 | W140: 945.32265 | X140: 912.72497 | Y140: 984.45925 | Z140: 705.9099 | AA140: 1077.929 | AB140: 1207.0999 | AC140: 1221.0947 | AD140: 1193.1883 | AE140: 1332.0158 | AF140: 1411.6659 | AG140: 1529.0072 | AH140: 1483.023 | AI140: 1620.2898 | AJ140: 1564.3052
A141: 53 | B141: 1 | G141: moeda | H141: Receita liquida de servicos de locacao - Vamos (1T23+: l.23 SIMPAR; 1T20-4T22: planilha antiga Vamos l.66) | J141: fonte | K141: 145.67905 | L141: 160.08128 | M141: 162.03618 | N141: 182.84635 | O141: 199.18428 | P141: 225.10853 | Q141: 250.8327 | R141: 278.68327 | S141: 306.15902 | T141: 383.46407 | U141: 435.80484 | V141: 511.04703 | W141: 595.69433 | X141: 656.33667 | Y141: 700.141 | Z141: 773.89296 | AA141: 838.378 | AB141: 921.71 | AC141: 927.638 | AD141: 962.05572 | AE141: 960.61334 | AF141: 1002.1301 | AG141: 1038.6915 | AH141: 1071.5831 | AI141: 1054.3815 | AJ141: 1087.8768
A142: 54 | B142: 1 | G142: moeda | H142: Receita liquida - Concessionarias da Vamos (1T20-4T22; planilha antiga Vamos l.97; a partir de 2023 dentro da Automob) | J142: fonte | K142: 104.18079 | L142: 138.39691 | M142: 252.03969 | N142: 194.24778 | O142: 278.3634 | P142: 412.5211 | Q142: 526.5801 | R142: 478.95954 | S142: 578.19047 | T142: 736.84008 | U142: 787.92102 | V142: 676.10242
A143: 55 | B143: 1 | G143: moeda | H143: Receita liquida - Automob (aba Automob - Site l.29; desde 1T23) | J143: fonte | W143: 2137.91 | X143: 2204.25 | Y143: 2483.79 | Z143: 2695.64 | AA143: 2681.5219 | AB143: 3050.0894 | AC143: 3110.2451 | AD143: 3144.698 | AE143: 2907.8834 | AF143: 3087.3326 | AG143: 3465.4924 | AH143: 3354.6902 | AI143: 3126.4926 | AJ143: 3455.1114
A144: 56 | B144: 1 | G144: moeda | H144: Receita liquida - CS Brasil (aba CS Brasil l.22) | J144: fonte | K144: 211.80971 | L144: 183.71003 | M144: 209.5146 | N144: 240.77521 | O144: 253.15965 | P144: 280.22126 | Q144: 175.24414 | R144: 125.00165 | S144: 120.59228 | T144: 135.57766 | U144: 185.37971 | V144: 275.84895 | W144: 175.43203 | X144: 176.42615 | Y144: 176.48227 | Z144: 153.20969 | AA144: 143.81807 | AB144: 153.54271 | AC144: 151.23505 | AD144: 144.91785 | AE144: 146.34649 | AF144: 183.87346 | AG144: 186.5506 | AH144: 173.98258 | AI144: 138.33868 | AJ144: 230.74953
A145: 57 | B145: 1 | G145: moeda | H145: Receita liquida - CS Infra (aba CS Infra l.10; desde 1T22; a partir de 2025 sem a Ciclus Rio, vendida) | J145: fonte | S145: 98.582541 | T145: 99.051924 | U145: 101.15181 | V145: 102.3592 | W145: 146.70616 | X145: 156.59407 | Y145: 215.89663 | Z145: 238.41846 | AA145: 146.55116 | AB145: 275.77706 | AC145: 215.81665 | AD145: 279.3834 | AE145: 42.04555 | AF145: 42.089978 | AG145: 71.743179 | AH145: 134.13563 | AI145: 122.33628 | AJ145: 175.85169
A146: 58 | B146: 1 | G146: moeda | H146: Receita liquida - BBC (aba BBC l.10) | J146: fonte | K146: 11.548736 | L146: 10.602368 | M146: 11.702788 | N146: 11.572117 | O146: 10.284299 | P146: 10.141096 | Q146: 10.644288 | R146: 12.196996 | S146: 15.518837 | T146: 17.604299 | U146: 19.517645 | V146: 24.912927 | W146: 2.6902153 | X146: 3.7626075 | Y146: 3.730961 | Z146: 3.8575961 | AA146: 1.9037001 | AB146: 2.0294727 | AC146: 2.4250426 | AD146: 2.9018413 | AE146: 1.8172851 | AF146: 1.9923675 | AG146: 1.8515601 | AH146: 1.5317548 | AI146: 1.4756487 | AJ146: 1.5251402
A147: 59 | B147: 1 | G147: un | H147: Movida RAC - frota final (carros; Movida - Operational data l.8) | J147: fonte | K147: 78220 | L147: 66025 | M147: 67978 | N147: 71219 | O147: 70213 | P147: 78453 | Q147: 79888 | R147: 90671 | S147: 96572 | T147: 100403 | U147: 104987 | V147: 111632 | W147: 98373 | X147: 91632 | Y147: 94273 | Z147: 113150 | AA147: 110091 | AB147: 108716 | AC147: 110182 | AD147: 121942 | AE147: 113257 | AF147: 120133 | AG147: 115498 | AH147: 130634 | AI147: 125307 | AJ147: 139785
A148: 60 | B148: 1 | G148: un | H148: Movida RAC - numero de diarias (mil; l.16) | J148: fonte | K148: 4419.568 | L148: 3462.499 | M148: 4330.12 | N148: 4822.77 | O148: 5067.042 | P148: 4618.39 | Q148: 5143.355 | R148: 5281.203 | S148: 5224.573 | T148: 5677.49 | U148: 5888.846 | V148: 6111.338 | W148: 6218.754 | X148: 5837.236 | Y148: 5819.624 | Z148: 5945.636 | AA148: 6414.484 | AB148: 6200.041 | AC148: 6004.671 | AD148: 5958.805 | AE148: 6026.629 | AF148: 6070.355 | AG148: 6084.784 | AH148: 6688.82 | AI148: 7085.3151 | AJ148: 7412.787
A149: 61 | B149: 1 | G149: un | H149: Movida RAC - taxa de ocupacao (l.17) | J149: fonte | K149: 0.752 | L149: 0.729 | M149: 0.827 | N149: 0.844 | O149: 0.793 | P149: 0.796 | Q149: 0.829 | R149: 0.808 | S149: 0.761 | T149: 0.793 | U149: 0.772 | V149: 0.766 | W149: 0.784 | X149: 0.783 | Y149: 0.811 | Z149: 0.82 | AA149: 0.802 | AB149: 0.781 | AC149: 0.781 | AD149: 0.749 | AE149: 0.717 | AF149: 0.741 | AG149: 0.718 | AH149: 0.75846991 | AI149: 0.77283417 | AJ149: 0.76208042
A150: 62 | B150: 1 | G150: un | H150: Movida RAC - diaria media (R$; l.18) | J150: fonte | K150: 83.427 | L150: 59.514 | M150: 70.337 | N150: 84.379 | O150: 81.742 | P150: 84.087 | Q150: 96.404 | R150: 118.614 | S150: 118.61 | T150: 115.745 | U150: 128.557 | V150: 127.297 | W150: 126.002 | X150: 123.362 | Y150: 124.524 | Z150: 126.1 | AA150: 130.299 | AB150: 134.541 | AC150: 142.036 | AD150: 150.723 | AE150: 158.045 | AF150: 154.171 | AG150: 159.266 | AH150: 160.58786 | AI150: 168.45183 | AJ150: 164.72559
A151: 63 | B151: 1 | G151: un | H151: Movida GTF - frota final (carros; l.21) | J151: fonte | K151: 40889 | L151: 39673 | M151: 40731 | N151: 47244 | O151: 52395 | P151: 55776 | Q151: 88379 | R151: 96303 | S151: 95370 | T151: 106498 | U151: 107728 | V151: 112352 | W151: 114617 | X151: 113678 | Y151: 119574 | Z151: 130781 | AA151: 135628 | AB151: 137648 | AC151: 137405 | AD151: 146543 | AE151: 143794 | AF151: 142296 | AG151: 143449 | AH151: 144207 | AI151: 141949 | AJ151: 145882
A152: 64 | B152: 1 | G152: un | H152: Movida GTF - ticket medio mensal (R$; l.26) | J152: fonte | K152: 1353.649 | L152: 1390.284 | M152: 1241.48 | N152: 1196.553 | O152: 1372.319 | P152: 1446.677 | Q152: 1556.347 | R152: 1554.954 | S152: 1656.1 | T152: 1785.39 | U152: 1811.553 | V152: 1924.074 | W152: 2040.898 | X152: 2110.268 | Y152: 2191.255 | Z152: 2275.453 | AA152: 2380.167 | AB152: 2582.26 | AC152: 2695.784 | AD152: 2780.174 | AE152: 2855.385 | AF152: 2948.728 | AG152: 3025.387 | AH152: 3123.2874 | AI152: 3162.0203 | AJ152: 3288.9568
A153: 65 | B153: 1 | G153: un | H153: Movida - carros vendidos (seminovos; l.29) | J153: fonte | K153: 14127 | L153: 18465 | M153: 14321 | N153: 9869 | O153: 5356 | P153: 12462 | Q153: 14509 | R153: 12472 | S153: 15225 | T153: 18474 | U153: 20023 | V153: 18697 | W153: 19610 | X153: 18806 | Y153: 20503 | Z153: 17253 | AA153: 23249 | AB153: 27954 | AC153: 30572 | AD153: 21916 | AE153: 24784 | AF153: 25917 | AG153: 24472 | AH153: 22172 | AI153: 20620 | AJ153: 19414
A154: 66 | B154: 1 | G154: un | H154: Movida - preco medio do carro vendido (R$; l.32) | J154: fonte | K154: 40161.535 | L154: 40614.688 | M154: 45289.77 | N154: 50153.014 | O154: 51893.918 | P154: 54575.562 | Q154: 58732.576 | R154: 65422.791 | S154: 64467.473 | T154: 66619.727 | U154: 70866.812 | V154: 75437.883 | W154: 75131.641 | X154: 67009.986 | Y154: 67718.251 | Z154: 68176.185 | AA154: 66942.505 | AB154: 66598.725 | AC154: 67728.675 | AD154: 68181.225 | AE154: 69546.779 | AF154: 70398.095 | AG154: 73431.672 | AH154: 72269.744 | AI154: 77823.729 | AJ154: 77252.184
A155: 67 | B155: 1 | G155: un | H155: Vamos - frota de locacao final (ativos; 1T21+: VAMOS - Operational Data l.21 da SIMPAR; 2020: planilha antiga Vamos, VAMOS Operational Data l.20) | J155: fonte | K155: 13529 | L155: 13785 | M155: 14015 | N155: 15128 | O155: 16025 | P155: 18395 | Q155: 20384 | R155: 23627 | S155: 26859 | T155: 33940 | U155: 38561 | V155: 43829 | W155: 45055 | X155: 45279 | Y155: 45161 | Z155: 45727 | AA155: 49515 | AB155: 50384 | AC155: 51090 | AD155: 51604 | AE155: 52593 | AF155: 52544 | AG155: 52047 | AH155: 51953 | AI155: 50980 | AJ155: 51256
H156: Notas: (i) Vamos 1T20-4T22 vem da Planilha de Fundamentos ANTIGA da Vamos (ri.grupovamos.com.br, versao com concessionarias ate 3T24): locacao + industria, e as concessionarias da Vamos em linha propria. No 1T23 a serie SIMPAR (945,3) supera locacao + industria da planilha antiga (887,5) pelas reclassificacoes da cisao. A Automob (desde 1T23) e maior que as concessionarias da Vamos: inclui as demais concessionarias do grupo, que ate 4T22 ficam no residual. (ii) Receitas por controlada como divulgadas (JSL, Automob e CS Brasil ajustados, nota do release); a diferenca para o consolidado = holding, eliminacoes e ajustes.
H193: CONVENCOES
H194: Linhas de origem: 5 a 156. As formulas da Inputs (2) varrem as linhas 5 a 190; as linhas 157 a 190 estao livres para novas contas.
H195: Periodos: colunas K a AJ (1Q20 a 2Q26 = 1T20 a 2T26).
H196: Brutos ja em R$ milhoes (como na planilha da Cia): fator da celula B1 = 1.
H197: ORIGEM: fonte = copiado da planilha; memoria = como divulgado, sem codigo; derivada = formula nesta aba.
H198: Codigos 45 a 67: drivers de receita (memoria); alimentam o bloco logo abaixo da receita liquida no Model.

Sheet Inputs (2)
A1: =COUNTIF($B$3:$B$1048576,$B$1) -> 1 | B1: =MAX($B$3:$B$1048576) -> 67
D2: 1Q21 | E2: 2Q21 | F2: 3Q21 | G2: 4Q21 | H2: 2021 | I2: 1Q22 | J2: 2Q22 | K2: 3Q22 | L2: 4Q22 | M2: 2022 | N2: 1Q23 | O2: 2Q23 | P2: 3Q23 | Q2: 4Q23 | R2: 2023 | S2: 1Q24 | T2: 2Q24 | U2: 3Q24 | V2: 4Q24 | W2: 2024 | X2: 1Q25 | Y2: 2Q25 | Z2: 3Q25 | AA2: 4Q25 | AB2: 2025 | AC2: 1Q26 | AD2: 2Q26 | AE2: 3Q26 | AF2: 4Q26 | AG2: 2026 | AH2: 1Q20 | AI2: 2Q20 | AJ2: 3Q20 | AK2: 4Q20 | AL2: 2020 | AN2: Sem dado na fonte: 3Q26, 4Q26 e 2026 (rotulo em cinza). 2020 fica nas colunas AH-AL.
B4: 1 | C4: Net Revenues | D4: =IF(ISNA(MATCH(D$2,Inputs!$K$4:$AJ$4,0)),NA(),IF(SUMPRODUCT((Inputs!$A$5:$A$190=$B4)*ISNUMBER(INDEX(Inputs!$K$5:$AJ$190,0,MATCH(D$2,Inputs!$K$4:$AJ$4,0))))+SUMPRODUCT((Inputs!$C$5:$C$190=$B4)*ISNUMBER(INDEX(Inputs!$K$5:$AJ$190,0,MATCH(D$2,Inputs!$K$4:$AJ$4,0))))+SUMPRODUCT((Inputs!$E$5:$E$190=$B4)*ISNUMBER(INDEX(Inputs!$K$5:$AJ$190,0,MATCH(D$2,Inputs!$K$4:$AJ$4,0))))=0,NA(),SUMPRODUCT((Inputs!$A$5:$A$190=$B4)*Inputs!$B$5:$B$190*(((Inputs!$G$5:$G$190="moeda")+(Inputs!$G$5:$G$190="acoes"))*Inputs!$B$1+((Inputs!$G$5:$G$190<>"moeda")*(Inputs!$G$5:$G$190<>"acoes")))*INDEX(Inputs!$K$5:$AJ$190,0,MATCH(D$2,Inputs!$K$4:$AJ$4,0)))+SUMPRODUCT((Inputs!$C$5:$C$190=$B4)*Inputs!$D$5:$D$190*(((Inputs!$G$5:$G$190="moeda")+(Inputs!$G$5:$G$190="acoes"))*Inputs!$B$1+((Inputs!$G$5:$G$190<>"moeda")*(Inputs!$G$5:$G$190<>"acoes")))*INDEX(Inputs!$K$5:$AJ$190,0,MATCH(D$2,Inputs!$K$4:$AJ$4,0)))+SUMPRODUCT((Inputs!$E$5:$E$190=$B4)*Inputs!$F$5:$F$190*(((Inputs!$G$5:$G$190="moeda")+(Inputs!$G$5:$G$190="acoes"))*Inputs!$B$1+((Inputs!$G$5:$G$190<>"moeda")*(Inputs!$G$5:$G$190<>"acoes")))*INDEX(Inputs!$K$5:$AJ$190,0,MATCH(D$2,Inputs!$K$4:$AJ$4,0))))) -> 2620.1057 | E4: =IF(ISNA(MATCH(E$2,Inputs!$K$4:$AJ$4,0)),NA(),IF(SUMPRODUCT((Inputs!$A$5:$A$190=$B4)*ISNUMBER(INDEX(Inputs!$K$5:$AJ$190,0,MATCH(E$2,Inputs!$K$4:$AJ$4,0))))+SUMPRODUCT((Inputs!$C$5:$C$190=$B4)*ISNUMBER(INDEX(Inputs!$K$5:$AJ$190,0,MATCH(E$2,Inputs!$K$4:$AJ$4,0))))+SUMPRODUCT((Inputs!$E$5:$E$190=$B4)*ISNUMBER(INDEX(Inputs!$K$5:$AJ$190,0,MATCH(E$2,Inputs!$K$4:$AJ$4,0))))=0,NA(),SUMPRODUCT((Inputs!$A$5:$A$190=$B4)*Inputs!$B$5:$B$190*(((Inputs!$G$5:$G$190="moeda")+(Inputs!$G$5:$G$190="acoes"))*Inputs!$B$1+((Inputs!$G$5:$G$190<>"moeda")*(Inputs!$G$5:$G$190<>"acoes")))*INDEX(Inputs!$K$5:$AJ$190,0,MATCH(E$2,Inputs!$K$4:$AJ$4,0)))+SUMPRODUCT((Inputs!$C$5:$C$190=$B4)*Inputs!$D$5:$D$190*(((Inputs!$G$5:$G$190="moeda")+(Inputs!$G$5:$G$190="acoes"))*Inputs!$B$1+((Inputs!$G$5:$G$190<>"moeda")*(Inputs!$G$5:$G$190<>"acoes")))*INDEX(Inputs!$K$5:$AJ$190,0,MATCH(E$2,Inputs!$K$4:$AJ$4,0)))+SUMPRODUCT((Inputs!$E$5:$E$190=$B4)*Inputs!$F$5:$F$190*(((Inputs!$G$5:$G$190="moeda")+(Inputs!$G$5:$G$190="acoes"))*Inputs!$B$1+((Inputs!$G$5:$G$190<>"moeda")*(Inputs!$G$5:$G$190<>"acoes")))*INDEX(Inputs!$K$5:$AJ$190,0,MATCH(E$2,Inputs!$K$4:$AJ$4,0))))) -> 3149.0663 | F4: =IF(ISNA(MATCH(F$2,Inputs!$K$4:$AJ$4,0)),NA(),IF(SUMPRODUCT((Inputs!$A$5:$A$190=$B4)*ISNUMBER(INDEX(Inputs!$K$5:$AJ$190,0,MATCH(F$2,Inputs!$K$4:$AJ$4,0))))+SUMPRODUCT((Inputs!$C$5:$C$190=$B4)*ISNUMBER(INDEX(Inputs!$K$5:$AJ$190,0,MATCH(F$2,Inputs!$K$4:$AJ$4,0))))+SUMPRODUCT((Inputs!$E$5:$E$190=$B4)*ISNUMBER(INDEX(Inputs!$K$5:$AJ$190,0,MATCH(F$2,Inputs!$K$4:$AJ$4,0))))=0,NA(),SUMPRODUCT((Inputs!$A$5:$A$190=$B4)*Inputs!$B$5:$B$190*(((Inputs!$G$5:$G$190="moeda")+(Inputs!$G$5:$G$190="acoes"))*Inputs!$B$1+((Inputs!$G$5:$G$190<>"moeda")*(Inputs!$G$5:$G$190<>"acoes")))*INDEX(Inputs!$K$5:$AJ$190,0,MATCH(F$2,Inputs!$K$4:$AJ$4,0)))+SUMPRODUCT((Inputs!$C$5:$C$190=$B4)*Inputs!$D$5:$D$190*(((Inputs!$G$5:$G$190="moeda")+(Inputs!$G$5:$G$190="acoes"))*Inputs!$B$1+((Inputs!$G$5:$G$190<>"moeda")*(Inputs!$G$5:$G$190<>"acoes")))*INDEX(Inputs!$K$5:$AJ$190,0,MATCH(F$2,Inputs!$K$4:$AJ$4,0)))+SUMPRODUCT((Inputs!$E$5:$E$190=$B4)*Inputs!$F$5:$F$190*(((Inputs!$G$5:$G$190="moeda")+(Inputs!$G$5:$G$190="acoes"))*Inputs!$B$1+((Inputs!$G$5:$G$190<>"moeda")*(Inputs!$G$5:$G$190<>"acoes")))*INDEX(Inputs!$K$5:$AJ$190,0,MATCH(F$2,Inputs!$K$4:$AJ$4,0))))) -> 3958.28 | G4: =IF(ISNA(MATCH(G$2,Inputs!$K$4:$AJ$4,0)),NA(),IF(SUMPRODUCT((Inputs!$A$5:$A$190=$B4)*ISNUMBER(INDEX(Inputs!$K$5:$AJ$190,0,MATCH(G$2,Inputs!$K$4:$AJ$4,0))))+SUMPRODUCT((Inputs!$C$5:$C$190=$B4)*ISNUMBER(INDEX(Inputs!$K$5:$AJ$190,0,MATCH(G$2,Inputs!$K$4:$AJ$4,0))))+SUMPRODUCT((Inputs!$E$5:$E$190=$B4)*ISNUMBER(INDEX(Inputs!$K$5:$AJ$190,0,MATCH(G$2,Inputs!$K$4:$AJ$4,0))))=0,NA(),SUMPRODUCT((Inputs!$A$5:$A$190=$B4)*Inputs!$B$5:$B$190*(((Inputs!$G$5:$G$190="moeda")+(Inputs!$G$5:$G$190="acoes"))*Inputs!$B$1+((Inputs!$G$5:$G$190<>"moeda")*(Inputs!$G$5:$G$190<>"acoes")))*INDEX(Inputs!$K$5:$AJ$190,0,MATCH(G$2,Inputs!$K$4:$AJ$4,0)))+SUMPRODUCT((Inputs!$C$5:$C$190=$B4)*Inputs!$D$5:$D$190*(((Inputs!$G$5:$G$190="moeda")+(Inputs!$G$5:$G$190="acoes"))*Inputs!$B$1+((Inputs!$G$5:$G$190<>"moeda")*(Inputs!$G$5:$G$190<>"acoes")))*INDEX(Inputs!$K$5:$AJ$190,0,MATCH(G$2,Inputs!$K$4:$AJ$4,0)))+SUMPRODUCT((Inputs!$E$5:$E$190=$B4)*Inputs!$F$5:$F$190*(((Inputs!$G$5:$G$190="moeda")+(Inputs!$G$5:$G$190="acoes"))*Inputs!$B$1+((Inputs!$G$5:$G$190<>"moeda")*(Inputs!$G$5:$G$190<>"acoes")))*INDEX(Inputs!$K$5:$AJ$190,0,MATCH(G$2,Inputs!$K$4:$AJ$4,0))))) -> 4138.767 | H4: =SUM(D4:G4) -> 13866.219 | I4: =IF(ISNA(MATCH(I$2,Inputs!$K$4:$AJ$4,0)),NA(),IF(SUMPRODUCT((Inputs!$A$5:$A$190=$B4)*ISNUMBER(INDEX(Inputs!$K$5:$AJ$190,0,MATCH(I$2,Inputs!$K$4:$AJ$4,0))))+SUMPRODUCT((Inputs!$C$5:$C$190=$B4)*ISNUMBER(INDEX(Inputs!$K$5:$AJ$190,0,MATCH(I$2,Inputs!$K$4:$AJ$4,0))))+SUMPRODUCT((Inputs!$E$5:$E$190=$B4)*ISNUMBER(INDEX(Inputs!$K$5:$AJ$190,0,MATCH(I$2,Inputs!$K$4:$AJ$4,0))))=0,NA(),SUMPRODUCT((Inputs!$A$5:$A$190=$B4)*Inputs!$B$5:$B$190*(((Inputs!$G$5:$G$190="moeda")+(Inputs!$G$5:$G$190="acoes"))*Inputs!$B$1+((Inputs!$G$5:$G$190<>"moeda")*(Inputs!$G$5:$G$190<>"acoes")))*INDEX(Inputs!$K$5:$AJ$190,0,MATCH(I$2,Inputs!$K$4:$AJ$4,0)))+SUMPRODUCT((Inputs!$C$5:$C$190=$B4)*Inputs!$D$5:$D$190*(((Inputs!$G$5:$G$190="moeda")+(Inputs!$G$5:$G$190="acoes"))*Inputs!$B$1+((Inputs!$G$5:$G$190<>"moeda")*(Inputs!$G$5:$G$190<>"acoes")))*INDEX(Inputs!$K$5:$AJ$190,0,MATCH(I$2,Inputs!$K$4:$AJ$4,0)))+SUMPRODUCT((Inputs!$E$5:$E$190=$B4)*Inputs!$F$5:$F$190*(((Inputs!$G$5:$G$190="moeda")+(Inputs!$G$5:$G$190="acoes"))*Inputs!$B$1+((Inputs!$G$5:$G$190<>"moeda")*(Inputs!$G$5:$G$190<>"acoes")))*INDEX(Inputs!$K$5:$AJ$190,0,MATCH(I$2,Inputs!$K$4:$AJ$4,0))))) -> 4530.197 | J4: =IF(ISNA(MATCH(J$2,Inputs!$K$4:$AJ$4,0)),NA(),IF(SUMPRODUCT((Inputs!$A$5:$A$190=$B4)*ISNUMBER(INDEX(Inputs!$K$5:$AJ$190,0,MATCH(J$2,Inputs!$K$4:$AJ$4,0))))+SUMPRODUCT((Inputs!$C$5:$C$190=$B4)*ISNUMBER(INDEX(Inputs!$K$5:$AJ$190,0,MATCH(J$2,Inputs!$K$4:$AJ$4,0))))+SUMPRODUCT((Inputs!$E$5:$E$190=$B4)*ISNUMBER(INDEX(Inputs!$K$5:$AJ$190,0,MATCH(J$2,Inputs!$K$4:$AJ$4,0))))=0,NA(),SUMPRODUCT((Inputs!$A$5:$A$190=$B4)*Inputs!$B$5:$B$190*(((Inputs!$G$5:$G$190="moeda")+(Inputs!$G$5:$G$190="acoes"))*Inputs!$B$1+((Inputs!$G$5:$G$190<>"moeda")*(Inputs!$G$5:$G$190<>"acoes")))*INDEX(Inputs!$K$5:$AJ$190,0,MATCH(J$2,Inputs!$K$4:$AJ$4,0)))+SUMPRODUCT((Inputs!$C$5:$C$190=$B4)*Inputs!$D$5:$D$190*(((Inputs!$G$5:$G$190="moeda")+(Inputs!$G$5:$G$190="acoes"))*Inputs!$B$1+((Inputs!$G$5:$G$190<>"moeda")*(Inputs!$G$5:$G$190<>"acoes")))*INDEX(Inputs!$K$5:$AJ$190,0,MATCH(J$2,Inputs!$K$4:$AJ$4,0)))+SUMPRODUCT((Inputs!$E$5:$E$190=$B4)*Inputs!$F$5:$F$190*(((Inputs!$G$5:$G$190="moeda")+(Inputs!$G$5:$G$190="acoes"))*Inputs!$B$1+((Inputs!$G$5:$G$190<>"moeda")*(Inputs!$G$5:$G$190<>"acoes")))*INDEX(Inputs!$K$5:$AJ$190,0,MATCH(J$2,Inputs!$K$4:$AJ$4,0))))) -> 5387.1474 | K4: =IF(ISNA(MATCH(K$2,Inputs!$K$4:$AJ$4,0)),NA(),IF(SUMPRODUCT((Inputs!$A$5:$A$190=$B4)*ISNUMBER(INDEX(Inputs!$K$5:$AJ$190,0,MATCH(K$2,Inputs!$K$4:$AJ$4,0))))+SUMPRODUCT((Inputs!$C$5:$C$190=$B4)*ISNUMBER(INDEX(Inputs!$K$5:$AJ$190,0,MATCH(K$2,Inputs!$K$4:$AJ$4,0))))+SUMPRODUCT((Inputs!$E$5:$E$190=$B4)*ISNUMBER(INDEX(Inputs!$K$5:$AJ$190,0,MATCH(K$2,Inputs!$K$4:$AJ$4,0))))=0,NA(),SUMPRODUCT((Inputs!$A$5:$A$190=$B4)*Inputs!$B$5:$B$190*(((Inputs!$G$5:$G$190="moeda")+(Inputs!$G$5:$G$190="acoes"))*Inputs!$B$1+((Inputs!$G$5:$G$190<>"moeda")*(Inputs!$G$5:$G$190<>"acoes")))*INDEX(Inputs!$K$5:$AJ$190,0,MATCH(K$2,Inputs!$K$4:$AJ$4,0)))+SUMPRODUCT((Inputs!$C$5:$C$190=$B4)*Inputs!$D$5:$D$190*(((Inputs!$G$5:$G$190="moeda")+(Inputs!$G$5:$G$190="acoes"))*Inputs!$B$1+((Inputs!$G$5:$G$190<>"moeda")*(Inputs!$G$5:$G$190<>"acoes")))*INDEX(Inputs!$K$5:$AJ$190,0,MATCH(K$2,Inputs!$K$4:$AJ$4,0)))+SUMPRODUCT((Inputs!$E$5:$E$190=$B4)*Inputs!$F$5:$F$190*(((Inputs!$G$5:$G$190="moeda")+(Inputs!$G$5:$G$190="acoes"))*Inputs!$B$1+((Inputs!$G$5:$G$190<>"moeda")*(Inputs!$G$5:$G$190<>"acoes")))*INDEX(Inputs!$K$5:$AJ$190,0,MATCH(K$2,Inputs!$K$4:$AJ$4,0))))) -> 6823.3505 | L4: =IF(ISNA(MATCH(L$2,Inputs!$K$4:$AJ$4,0)),NA(),IF(SUMPRODUCT((Inputs!$A$5:$A$190=$B4)*ISNUMBER(INDEX(Inputs!$K$5:$AJ$190,0,MATCH(L$2,Inputs!$K$4:$AJ$4,0))))+SUMPRODUCT((Inputs!$C$5:$C$190=$B4)*ISNUMBER(INDEX(Inputs!$K$5:$AJ$190,0,MATCH(L$2,Inputs!$K$4:$AJ$4,0))))+SUMPRODUCT((Inputs!$E$5:$E$190=$B4)*ISNUMBER(INDEX(Inputs!$K$5:$AJ$190,0,MATCH(L$2,Inputs!$K$4:$AJ$4,0))))=0,NA(),SUMPRODUCT((Inputs!$A$5:$A$190=$B4)*Inputs!$B$5:$B$190*(((Inputs!$G$5:$G$190="moeda")+(Inputs!$G$5:$G$190="acoes"))*Inputs!$B$1+((Inputs!$G$5:$G$190<>"moeda")*(Inputs!$G$5:$G$190<>"acoes")))*INDEX(Inputs!$K$5:$AJ$190,0,MATCH(L$2,Inputs!$K$4:$AJ$4,0)))+SUMPRODUCT((Inputs!$C$5:$C$190=$B4)*Inputs!$D$5:$D$190*(((Inputs!$G$5:$G$190="moeda")+(Inputs!$G$5:$G$190="acoes"))*Inputs!$B$1+((Inputs!$G$5:$G$190<>"moeda")*(Inputs!$G$5:$G$190<>"acoes")))*INDEX(Inputs!$K$5:$AJ$190,0,MATCH(L$2,Inputs!$K$4:$AJ$4,0)))+SUMPRODUCT((Inputs!$E$5:$E$190=$B4)*Inputs!$F$5:$F$190*(((Inputs!$G$5:$G$190="moeda")+(Inputs!$G$5:$G$190="acoes"))*Inputs!$B$1+((Inputs!$G$5:$G$190<>"moeda")*(Inputs!$G$5:$G$190<>"acoes")))*INDEX(Inputs!$K$5:$AJ$190,0,MATCH(L$2,Inputs!$K$4:$AJ$4,0))))) -> 7341.1863 | M4: =SUM(I4:L4) -> 24081.881 | N4: =IF(ISNA(MATCH(N$2,Inputs!$K$4:$AJ$4,0)),NA(),IF(SUMPRODUCT((Inputs!$A$5:$A$190=$B4)*ISNUMBER(INDEX(Inputs!$K$5:$AJ$190,0,MATCH(N$2,Inputs!$K$4:$AJ$4,0))))+SUMPRODUCT((Inputs!$C$5:$C$190=$B4)*ISNUMBER(INDEX(Inputs!$K$5:$AJ$190,0,MATCH(N$2,Inputs!$K$4:$AJ$4,0))))+SUMPRODUCT((Inputs!$E$5:$E$190=$B4)*ISNUMBER(INDEX(Inputs!$K$5:$AJ$190,0,MATCH(N$2,Inputs!$K$4:$AJ$4,0))))=0,NA(),SUMPRODUCT((Inputs!$A$5:$A$190=$B4)*Inputs!$B$5:$B$190*(((Inputs!$G$5:$G$190="moeda")+(Inputs!$G$5:$G$190="acoes"))*Inputs!$B$1+((Inputs!$G$5:$G$190<>"moeda")*(Inputs!$G$5:$G$190<>"acoes")))*INDEX(Inputs!$K$5:$AJ$190,0,MATCH(N$2,Inputs!$K$4:$AJ$4,0)))+SUMPRODUCT((Inputs!$C$5:$C$190=$B4)*Inputs!$D$5:$D$190*(((Inputs!$G$5:$G$190="moeda")+(Inputs!$G$5:$G$190="acoes"))*Inputs!$B$1+((Inputs!$G$5:$G$190<>"moeda")*(Inputs!$G$5:$G$190<>"acoes")))*INDEX(Inputs!$K$5:$AJ$190,0,MATCH(N$2,Inputs!$K$4:$AJ$4,0)))+SUMPRODUCT((Inputs!$E$5:$E$190=$B4)*Inputs!$F$5:$F$190*(((Inputs!$G$5:$G$190="moeda")+(Inputs!$G$5:$G$190="acoes"))*Inputs!$B$1+((Inputs!$G$5:$G$190<>"moeda")*(Inputs!$G$5:$G$190<>"acoes")))*INDEX(Inputs!$K$5:$AJ$190,0,MATCH(N$2,Inputs!$K$4:$AJ$4,0))))) -> 7440.0438 | O4: =IF(ISNA(MATCH(O$2,Inputs!$K$4:$AJ$4,0)),NA(),IF(SUMPRODUCT((Inputs!$A$5:$A$190=$B4)*ISNUMBER(INDEX(Inputs!$K$5:$AJ$190,0,MATCH(O$2,Inputs!$K$4:$AJ$4,0))))+SUMPRODUCT((Inputs!$C$5:$C$190=$B4)*ISNUMBER(INDEX(Inputs!$K$5:$AJ$190,0,MATCH(O$2,Inputs!$K$4:$AJ$4,0))))+SUMPRODUCT((Inputs!$E$5:$E$190=$B4)*ISNUMBER(INDEX(Inputs!$K$5:$AJ$190,0,MATCH(O$2,Inputs!$K$4:$AJ$4,0))))=0,NA(),SUMPRODUCT((Inputs!$A$5:$A$190=$B4)*Inputs!$B$5:$B$190*(((Inputs!$G$5:$G$190="moeda")+(Inputs!$G$5:$G$190="acoes"))*Inputs!$B$1+((Inputs!$G$5:$G$190<>"moeda")*(Inputs!$G$5:$G$190<>"acoes")))*INDEX(Inputs!$K$5:$AJ$190,0,MATCH(O$2,Inputs!$K$4:$AJ$4,0)))+SUMPRODUCT((Inputs!$C$5:$C$190=$B4)*Inputs!$D$5:$D$190*(((Inputs!$G$5:$G$190="moeda")+(Inputs!$G$5:$G$190="acoes"))*Inputs!$B$1+((Inputs!$G$5:$G$190<>"moeda")*(Inputs!$G$5:$G$190<>"acoes")))*INDEX(Inputs!$K$5:$AJ$190,0,MATCH(O$2,Inputs!$K$4:$AJ$4,0)))+SUMPRODUCT((Inputs!$E$5:$E$190=$B4)*Inputs!$F$5:$F$190*(((Inputs!$G$5:$G$190="moeda")+(Inputs!$G$5:$G$190="acoes"))*Inputs!$B$1+((Inputs!$G$5:$G$190<>"moeda")*(Inputs!$G$5:$G$190<>"acoes")))*INDEX(Inputs!$K$5:$AJ$190,0,MATCH(O$2,Inputs!$K$4:$AJ$4,0))))) -> 7563.6362 | P4: =IF(ISNA(MATCH(P$2,Inputs!$K$4:$AJ$4,0)),NA(),IF(SUMPRODUCT((Inputs!$A$5:$A$190=$B4)*ISNUMBER(INDEX(Inputs!$K$5:$AJ$190,0,MATCH(P$2,Inputs!$K$4:$AJ$4,0))))+SUMPRODUCT((Inputs!$C$5:$C$190=$B4)*ISNUMBER(INDEX(Inputs!$K$5:$AJ$190,0,MATCH(P$2,Inputs!$K$4:$AJ$4,0))))+SUMPRODUCT((Inputs!$E$5:$E$190=$B4)*ISNUMBER(INDEX(Inputs!$K$5:$AJ$190,0,MATCH(P$2,Inputs!$K$4:$AJ$4,0))))=0,NA(),SUMPRODUCT((Inputs!$A$5:$A$190=$B4)*Inputs!$B$5:$B$190*(((Inputs!$G$5:$G$190="moeda")+(Inputs!$G$5:$G$190="acoes"))*Inputs!$B$1+((Inputs!$G$5:$G$190<>"moeda")*(Inputs!$G$5:$G$190<>"acoes")))*INDEX(Inputs!$K$5:$AJ$190,0,MATCH(P$2,Inputs!$K$4:$AJ$4,0)))+SUMPRODUCT((Inputs!$C$5:$C$190=$B4)*Inputs!$D$5:$D$190*(((Inputs!$G$5:$G$190="moeda")+(Inputs!$G$5:$G$190="acoes"))*Inputs!$B$1+((Inputs!$G$5:$G$190<>"moeda")*(Inputs!$G$5:$G$190<>"acoes")))*INDEX(Inputs!$K$5:$AJ$190,0,MATCH(P$2,Inputs!$K$4:$AJ$4,0)))+SUMPRODUCT((Inputs!$E$5:$E$190=$B4)*Inputs!$F$5:$F$190*(((Inputs!$G$5:$G$190="moeda")+(Inputs!$G$5:$G$190="acoes"))*Inputs!$B$1+((Inputs!$G$5:$G$190<>"moeda")*(Inputs!$G$5:$G$190<>"acoes")))*INDEX(Inputs!$K$5:$AJ$190,0,MATCH(P$2,Inputs!$K$4:$AJ$4,0))))) -> 8318.109 | Q4: =IF(ISNA(MATCH(Q$2,Inputs!$K$4:$AJ$4,0)),NA(),IF(SUMPRODUCT((Inputs!$A$5:$A$190=$B4)*ISNUMBER(INDEX(Inputs!$K$5:$AJ$190,0,MATCH(Q$2,Inputs!$K$4:$AJ$4,0))))+SUMPRODUCT((Inputs!$C$5:$C$190=$B4)*ISNUMBER(INDEX(Inputs!$K$5:$AJ$190,0,MATCH(Q$2,Inputs!$K$4:$AJ$4,0))))+SUMPRODUCT((Inputs!$E$5:$E$190=$B4)*ISNUMBER(INDEX(Inputs!$K$5:$AJ$190,0,MATCH(Q$2,Inputs!$K$4:$AJ$4,0))))=0,NA(),SUMPRODUCT((Inputs!$A$5:$A$190=$B4)*Inputs!$B$5:$B$190*(((Inputs!$G$5:$G$190="moeda")+(Inputs!$G$5:$G$190="acoes"))*Inputs!$B$1+((Inputs!$G$5:$G$190<>"moeda")*(Inputs!$G$5:$G$190<>"acoes")))*INDEX(Inputs!$K$5:$AJ$190,0,MATCH(Q$2,Inputs!$K$4:$AJ$4,0)))+SUMPRODUCT((Inputs!$C$5:$C$190=$B4)*Inputs!$D$5:$D$190*(((Inputs!$G$5:$G$190="moeda")+(Inputs!$G$5:$G$190="acoes"))*Inputs!$B$1+((Inputs!$G$5:$G$190<>"moeda")*(Inputs!$G$5:$G$190<>"acoes")))*INDEX(Inputs!$K$5:$AJ$190,0,MATCH(Q$2,Inputs!$K$4:$AJ$4,0)))+SUMPRODUCT((Inputs!$E$5:$E$190=$B4)*Inputs!$F$5:$F$190*(((Inputs!$G$5:$G$190="moeda")+(Inputs!$G$5:$G$190="acoes"))*Inputs!$B$1+((Inputs!$G$5:$G$190<>"moeda")*(Inputs!$G$5:$G$190<>"acoes")))*INDEX(Inputs!$K$5:$AJ$190,0,MATCH(Q$2,Inputs!$K$4:$AJ$4,0))))) -> 8521.824 | R4: =SUM(N4:Q4) -> 31843.613 | S4: =IF(ISNA(MATCH(S$2,Inputs!$K$4:$AJ$4,0)),NA(),IF(SUMPRODUCT((Inputs!$A$5:$A$190=$B4)*ISNUMBER(INDEX(Inputs!$K$5:$AJ$190,0,MATCH(S$2,Inputs!$K$4:$AJ$4,0))))+SUMPRODUCT((Inputs!$C$5:$C$190=$B4)*ISNUMBER(INDEX(Inputs!$K$5:$AJ$190,0,MATCH(S$2,Inputs!$K$4:$AJ$4,0))))+SUMPRODUCT((Inputs!$E$5:$E$190=$B4)*ISNUMBER(INDEX(Inputs!$K$5:$AJ$190,0,MATCH(S$2,Inputs!$K$4:$AJ$4,0))))=0,NA(),SUMPRODUCT((Inputs!$A$5:$A$190=$B4)*Inputs!$B$5:$B$190*(((Inputs!$G$5:$G$190="moeda")+(Inputs!$G$5:$G$190="acoes"))*Inputs!$B$1+((Inputs!$G$5:$G$190<>"moeda")*(Inputs!$G$5:$G$190<>"acoes")))*INDEX(Inputs!$K$5:$AJ$190,0,MATCH(S$2,Inputs!$K$4:$AJ$4,0)))+SUMPRODUCT((Inputs!$C$5:$C$190=$B4)*Inputs!$D$5:$D$190*(((Inputs!$G$5:$G$190="moeda")+(Inputs!$G$5:$G$190="acoes"))*Inputs!$B$1+((Inputs!$G$5:$G$190<>"moeda")*(Inputs!$G$5:$G$190<>"acoes")))*INDEX(Inputs!$K$5:$AJ$190,0,MATCH(S$2,Inputs!$K$4:$AJ$4,0)))+SUMPRODUCT((Inputs!$E$5:$E$190=$B4)*Inputs!$F$5:$F$190*(((Inputs!$G$5:$G$190="moeda")+(Inputs!$G$5:$G$190="acoes"))*Inputs!$B$1+((Inputs!$G$5:$G$190<>"moeda")*(Inputs!$G$5:$G$190<>"acoes")))*INDEX(Inputs!$K$5:$AJ$190,0,MATCH(S$2,Inputs!$K$4:$AJ$4,0))))) -> 9066.5964 | T4: =IF(ISNA(MATCH(T$2,Inputs!$K$4:$AJ$4,0)),NA(),IF(SUMPRODUCT((Inputs!$A$5:$A$190=$B4)*ISNUMBER(INDEX(Inputs!$K$5:$AJ$190,0,MATCH(T$2,Inputs!$K$4:$AJ$4,0))))+SUMPRODUCT((Inputs!$C$5:$C$190=$B4)*ISNUMBER(INDEX(Inputs!$K$5:$AJ$190,0,MATCH(T$2,Inputs!$K$4:$AJ$4,0))))+SUMPRODUCT((Inputs!$E$5:$E$190=$B4)*ISNUMBER(INDEX(Inputs!$K$5:$AJ$190,0,MATCH(T$2,Inputs!$K$4:$AJ$4,0))))=0,NA(),SUMPRODUCT((Inputs!$A$5:$A$190=$B4)*Inputs!$B$5:$B$190*(((Inputs!$G$5:$G$190="moeda")+(Inputs!$G$5:$G$190="acoes"))*Inputs!$B$1+((Inputs!$G$5:$G$190<>"moeda")*(Inputs!$G$5:$G$190<>"acoes")))*INDEX(Inputs!$K$5:$AJ$190,0,MATCH(T$2,Inputs!$K$4:$AJ$4,0)))+SUMPRODUCT((Inputs!$C$5:$C$190=$B4)*Inputs!$D$5:$D$190*(((Inputs!$G$5:$G$190="moeda")+(Inputs!$G$5:$G$190="acoes"))*Inputs!$B$1+((Inputs!$G$5:$G$190<>"moeda")*(Inputs!$G$5:$G$190<>"acoes")))*INDEX(Inputs!$K$5:$AJ$190,0,MATCH(T$2,Inputs!$K$4:$AJ$4,0)))+SUMPRODUCT((Inputs!$E$5:$E$190=$B4)*Inputs!$F$5:$F$190*(((Inputs!$G$5:$G$190="moeda")+(Inputs!$G$5:$G$190="acoes"))*Inputs!$B$1+((Inputs!$G$5:$G$190<>"moeda")*(Inputs!$G$5:$G$190<>"acoes")))*INDEX(Inputs!$K$5:$AJ$190,0,MATCH(T$2,Inputs!$K$4:$AJ$4,0))))) -> 10227.19 | U4: =IF(ISNA(MATCH(U$2,Inputs!$K$4:$AJ$4,0)),NA(),IF(SUMPRODUCT((Inputs!$A$5:$A$190=$B4)*ISNUMBER(INDEX(Inputs!$K$5:$AJ$190,0,MATCH(U$2,Inputs!$K$4:$AJ$4,0))))+SUMPRODUCT((Inputs!$C$5:$C$190=$B4)*ISNUMBER(INDEX(Inputs!$K$5:$AJ$190,0,MATCH(U$2,Inputs!$K$4:$AJ$4,0))))+SUMPRODUCT((Inputs!$E$5:$E$190=$B4)*ISNUMBER(INDEX(Inputs!$K$5:$AJ$190,0,MATCH(U$2,Inputs!$K$4:$AJ$4,0))))=0,NA(),SUMPRODUCT((Inputs!$A$5:$A$190=$B4)*Inputs!$B$5:$B$190*(((Inputs!$G$5:$G$190="moeda")+(Inputs!$G$5:$G$190="acoes"))*Inputs!$B$1+((Inputs!$G$5:$G$190<>"moeda")*(Inputs!$G$5:$G$190<>"acoes")))*INDEX(Inputs!$K$5:$AJ$190,0,MATCH(U$2,Inputs!$K$4:$AJ$4,0)))+SUMPRODUCT((Inputs!$C$5:$C$190=$B4)*Inputs!$D$5:$D$190*(((Inputs!$G$5:$G$190="moeda")+(Inputs!$G$5:$G$190="acoes"))*Inputs!$B$1+((Inputs!$G$5:$G$190<>"moeda")*(Inputs!$G$5:$G$190<>"acoes")))*INDEX(Inputs!$K$5:$AJ$190,0,MATCH(U$2,Inputs!$K$4:$AJ$4,0)))+SUMPRODUCT((Inputs!$E$5:$E$190=$B4)*Inputs!$F$5:$F$190*(((Inputs!$G$5:$G$190="moeda")+(Inputs!$G$5:$G$190="acoes"))*Inputs!$B$1+((Inputs!$G$5:$G$190<>"moeda")*(Inputs!$G$5:$G$190<>"acoes")))*INDEX(Inputs!$K$5:$AJ$190,0,MATCH(U$2,Inputs!$K$4:$AJ$4,0))))) -> 10790.491 | V4: =IF(ISNA(MATCH(V$2,Inputs!$K$4:$AJ$4,0)),NA(),IF(SUMPRODUCT((Inputs!$A$5:$A$190=$B4)*ISNUMBER(INDEX(Inputs!$K$5:$AJ$190,0,MATCH(V$2,Inputs!$K$4:$AJ$4,0))))+SUMPRODUCT((Inputs!$C$5:$C$190=$B4)*ISNUMBER(INDEX(Inputs!$K$5:$AJ$190,0,MATCH(V$2,Inputs!$K$4:$AJ$4,0))))+SUMPRODUCT((Inputs!$E$5:$E$190=$B4)*ISNUMBER(INDEX(Inputs!$K$5:$AJ$190,0,MATCH(V$2,Inputs!$K$4:$AJ$4,0))))=0,NA(),SUMPRODUCT((Inputs!$A$5:$A$190=$B4)*Inputs!$B$5:$B$190*(((Inputs!$G$5:$G$190="moeda")+(Inputs!$G$5:$G$190="acoes"))*Inputs!$B$1+((Inputs!$G$5:$G$190<>"moeda")*(Inputs!$G$5:$G$190<>"acoes")))*INDEX(Inputs!$K$5:$AJ$190,0,MATCH(V$2,Inputs!$K$4:$AJ$4,0)))+SUMPRODUCT((Inputs!$C$5:$C$190=$B4)*Inputs!$D$5:$D$190*(((Inputs!$G$5:$G$190="moeda")+(Inputs!$G$5:$G$190="acoes"))*Inputs!$B$1+((Inputs!$G$5:$G$190<>"moeda")*(Inputs!$G$5:$G$190<>"acoes")))*INDEX(Inputs!$K$5:$AJ$190,0,MATCH(V$2,Inputs!$K$4:$AJ$4,0)))+SUMPRODUCT((Inputs!$E$5:$E$190=$B4)*Inputs!$F$5:$F$190*(((Inputs!$G$5:$G$190="moeda")+(Inputs!$G$5:$G$190="acoes"))*Inputs!$B$1+((Inputs!$G$5:$G$190<>"moeda")*(Inputs!$G$5:$G$190<>"acoes")))*INDEX(Inputs!$K$5:$AJ$190,0,MATCH(V$2,Inputs!$K$4:$AJ$4,0))))) -> 10653.809 | W4: =SUM(S4:V4) -> 40738.086 | X4: =IF(ISNA(MATCH(X$2,Inputs!$K$4:$AJ$4,0)),NA(),IF(SUMPRODUCT((Inputs!$A$5:$A$190=$B4)*ISNUMBER(INDEX(Inputs!$K$5:$AJ$190,0,MATCH(X$2,Inputs!$K$4:$AJ$4,0))))+SUMPRODUCT((Inputs!$C$5:$C$190=$B4)*ISNUMBER(INDEX(Inputs!$K$5:$AJ$190,0,MATCH(X$2,Inputs!$K$4:$AJ$4,0))))+SUMPRODUCT((Inputs!$E$5:$E$190=$B4)*ISNUMBER(INDEX(Inputs!$K$5:$AJ$190,0,MATCH(X$2,Inputs!$K$4:$AJ$4,0))))=0,NA(),SUMPRODUCT((Inputs!$A$5:$A$190=$B4)*Inputs!$B$5:$B$190*(((Inputs!$G$5:$G$190="moeda")+(Inputs!$G$5:$G$190="acoes"))*Inputs!$B$1+((Inputs!$G$5:$G$190<>"moeda")*(Inputs!$G$5:$G$190<>"acoes")))*INDEX(Inputs!$K$5:$AJ$190,0,MATCH(X$2,Inputs!$K$4:$AJ$4,0)))+SUMPRODUCT((Inputs!$C$5:$C$190=$B4)*Inputs!$D$5:$D$190*(((Inputs!$G$5:$G$190="moeda")+(Inputs!$G$5:$G$190="acoes"))*Inputs!$B$1+((Inputs!$G$5:$G$190<>"moeda")*(Inputs!$G$5:$G$190<>"acoes")))*INDEX(Inputs!$K$5:$AJ$190,0,MATCH(X$2,Inputs!$K$4:$AJ$4,0)))+SUMPRODUCT((Inputs!$E$5:$E$190=$B4)*Inputs!$F$5:$F$190*(((Inputs!$G$5:$G$190="moeda")+(Inputs!$G$5:$G$190="acoes"))*Inputs!$B$1+((Inputs!$G$5:$G$190<>"moeda")*(Inputs!$G$5:$G$190<>"acoes")))*INDEX(Inputs!$K$5:$AJ$190,0,MATCH(X$2,Inputs!$K$4:$AJ$4,0))))) -> 10244.635 | Y4: =IF(ISNA(MATCH(Y$2,Inputs!$K$4:$AJ$4,0)),NA(),IF(SUMPRODUCT((Inputs!$A$5:$A$190=$B4)*ISNUMBER(INDEX(Inputs!$K$5:$AJ$190,0,MATCH(Y$2,Inputs!$K$4:$AJ$4,0))))+SUMPRODUCT((Inputs!$C$5:$C$190=$B4)*ISNUMBER(INDEX(Inputs!$K$5:$AJ$190,0,MATCH(Y$2,Inputs!$K$4:$AJ$4,0))))+SUMPRODUCT((Inputs!$E$5:$E$190=$B4)*ISNUMBER(INDEX(Inputs!$K$5:$AJ$190,0,MATCH(Y$2,Inputs!$K$4:$AJ$4,0))))=0,NA(),SUMPRODUCT((Inputs!$A$5:$A$190=$B4)*Inputs!$B$5:$B$190*(((Inputs!$G$5:$G$190="moeda")+(Inputs!$G$5:$G$190="acoes"))*Inputs!$B$1+((Inputs!$G$5:$G$190<>"moeda")*(Inputs!$G$5:$G$190<>"acoes")))*INDEX(Inputs!$K$5:$AJ$190,0,MATCH(Y$2,Inputs!$K$4:$AJ$4,0)))+SUMPRODUCT((Inputs!$C$5:$C$190=$B4)*Inputs!$D$5:$D$190*(((Inputs!$G$5:$G$190="moeda")+(Inputs!$G$5:$G$190="acoes"))*Inputs!$B$1+((Inputs!$G$5:$G$190<>"moeda")*(Inputs!$G$5:$G$190<>"acoes")))*INDEX(Inputs!$K$5:$AJ$190,0,MATCH(Y$2,Inputs!$K$4:$AJ$4,0)))+SUMPRODUCT((Inputs!$E$5:$E$190=$B4)*Inputs!$F$5:$F$190*(((Inputs!$G$5:$G$190="moeda")+(Inputs!$G$5:$G$190="acoes"))*Inputs!$B$1+((Inputs!$G$5:$G$190<>"moeda")*(Inputs!$G$5:$G$190<>"acoes")))*INDEX(Inputs!$K$5:$AJ$190,0,MATCH(Y$2,Inputs!$K$4:$AJ$4,0))))) -> 10340.786 | Z4: =IF(ISNA(MATCH(Z$2,Inputs!$K$4:$AJ$4,0)),NA(),IF(SUMPRODUCT((Inputs!$A$5:$A$190=$B4)*ISNUMBER(INDEX(Inputs!$K$5:$AJ$190,0,MATCH(Z$2,Inputs!$K$4:$AJ$4,0))))+SUMPRODUCT((Inputs!$C$5:$C$190=$B4)*ISNUMBER(INDEX(Inputs!$K$5:$AJ$190,0,MATCH(Z$2,Inputs!$K$4:$AJ$4,0))))+SUMPRODUCT((Inputs!$E$5:$E$190=$B4)*ISNUMBER(INDEX(Inputs!$K$5:$AJ$190,0,MATCH(Z$2,Inputs!$K$4:$AJ$4,0))))=0,NA(),SUMPRODUCT((Inputs!$A$5:$A$190=$B4)*Inputs!$B$5:$B$190*(((Inputs!$G$5:$G$190="moeda")+(Inputs!$G$5:$G$190="acoes"))*Inputs!$B$1+((Inputs!$G$5:$G$190<>"moeda")*(Inputs!$G$5:$G$190<>"acoes")))*INDEX(Inputs!$K$5:$AJ$190,0,MATCH(Z$2,Inputs!$K$4:$AJ$4,0)))+SUMPRODUCT((Inputs!$C$5:$C$190=$B4)*Inputs!$D$5:$D$190*(((Inputs!$G$5:$G$190="moeda")+(Inputs!$G$5:$G$190="acoes"))*Inputs!$B$1+((Inputs!$G$5:$G$190<>"moeda")*(Inputs!$G$5:$G$190<>"acoes")))*INDEX(Inputs!$K$5:$AJ$190,0,MATCH(Z$2,Inputs!$K$4:$AJ$4,0)))+SUMPRODUCT((Inputs!$E$5:$E$190=$B4)*Inputs!$F$5:$F$190*(((Inputs!$G$5:$G$190="moeda")+(Inputs!$G$5:$G$190="acoes"))*Inputs!$B$1+((Inputs!$G$5:$G$190<>"moeda")*(Inputs!$G$5:$G$190<>"acoes")))*INDEX(Inputs!$K$5:$AJ$190,0,MATCH(Z$2,Inputs!$K$4:$AJ$4,0))))) -> 11100.933 | AA4: =IF(ISNA(MATCH(AA$2,Inputs!$K$4:$AJ$4,0)),NA(),IF(SUMPRODUCT((Inputs!$A$5:$A$190=$B4)*ISNUMBER(INDEX(Inputs!$K$5:$AJ$190,0,MATCH(AA$2,Inputs!$K$4:$AJ$4,0))))+SUMPRODUCT((Inputs!$C$5:$C$190=$B4)*ISNUMBER(INDEX(Inputs!$K$5:$AJ$190,0,MATCH(AA$2,Inputs!$K$4:$AJ$4,0))))+SUMPRODUCT((Inputs!$E$5:$E$190=$B4)*ISNUMBER(INDEX(Inputs!$K$5:$AJ$190,0,MATCH(AA$2,Inputs!$K$4:$AJ$4,0))))=0,NA(),SUMPRODUCT((Inputs!$A$5:$A$190=$B4)*Inputs!$B$5:$B$190*(((Inputs!$G$5:$G$190="moeda")+(Inputs!$G$5:$G$190="acoes"))*Inputs!$B$1+((Inputs!$G$5:$G$190<>"moeda")*(Inputs!$G$5:$G$190<>"acoes")))*INDEX(Inputs!$K$5:$AJ$190,0,MATCH(AA$2,Inputs!$K$4:$AJ$4,0)))+SUMPRODUCT((Inputs!$C$5:$C$190=$B4)*Inputs!$D$5:$D$190*(((Inputs!$G$5:$G$190="moeda")+(Inputs!$G$5:$G$190="acoes"))*Inputs!$B$1+((Inputs!$G$5:$G$190<>"moeda")*(Inputs!$G$5:$G$190<>"acoes")))*INDEX(Inputs!$K$5:$AJ$190,0,MATCH(AA$2,Inputs!$K$4:$AJ$4,0)))+SUMPRODUCT((Inputs!$E$5:$E$190=$B4)*Inputs!$F$5:$F$190*(((Inputs!$G$5:$G$190="moeda")+(Inputs!$G$5:$G$190="acoes"))*Inputs!$B$1+((Inputs!$G$5:$G$190<>"moeda")*(Inputs!$G$5:$G$190<>"acoes")))*INDEX(Inputs!$K$5:$AJ$190,0,MATCH(AA$2,Inputs!$K$4:$AJ$4,0))))) -> 11119.492 | AB4: =SUM(X4:AA4) -> 42805.846 | AC4: =IF(ISNA(MATCH(AC$2,Inputs!$K$4:$AJ$4,0)),NA(),IF(SUMPRODUCT((Inputs!$A$5:$A$190=$B4)*ISNUMBER(INDEX(Inputs!$K$5:$AJ$190,0,MATCH(AC$2,Inputs!$K$4:$AJ$4,0))))+SUMPRODUCT((Inputs!$C$5:$C$190=$B4)*ISNUMBER(INDEX(Inputs!$K$5:$AJ$190,0,MATCH(AC$2,Inputs!$K$4:$AJ$4,0))))+SUMPRODUCT((Inputs!$E$5:$E$190=$B4)*ISNUMBER(INDEX(Inputs!$K$5:$AJ$190,0,MATCH(AC$2,Inputs!$K$4:$AJ$4,0))))=0,NA(),SUMPRODUCT((Inputs!$A$5:$A$190=$B4)*Inputs!$B$5:$B$190*(((Inputs!$G$5:$G$190="moeda")+(Inputs!$G$5:$G$190="acoes"))*Inputs!$B$1+((Inputs!$G$5:$G$190<>"moeda")*(Inputs!$G$5:$G$190<>"acoes")))*INDEX(Inputs!$K$5:$AJ$190,0,MATCH(AC$2,Inputs!$K$4:$AJ$4,0)))+SUMPRODUCT((Inputs!$C$5:$C$190=$B4)*Inputs!$D$5:$D$190*(((Inputs!$G$5:$G$190="moeda")+(Inputs!$G$5:$G$190="acoes"))*Inputs!$B$1+((Inputs!$G$5:$G$190<>"moeda")*(Inputs!$G$5:$G$190<>"acoes")))*INDEX(Inputs!$K$5:$AJ$190,0,MATCH(AC$2,Inputs!$K$4:$AJ$4,0)))+SUMPRODUCT((Inputs!$E$5:$E$190=$B4)*Inputs!$F$5:$F$190*(((Inputs!$G$5:$G$190="moeda")+(Inputs!$G$5:$G$190="acoes"))*Inputs!$B$1+((Inputs!$G$5:$G$190<>"moeda")*(Inputs!$G$5:$G$190<>"acoes")))*INDEX(Inputs!$K$5:$AJ$190,0,MATCH(AC$2,Inputs!$K$4:$AJ$4,0))))) -> 10924.298 | AD4: =IF(ISNA(MATCH(AD$2,Inputs!$K$4:$AJ$4,0)),NA(),IF(SUMPRODUCT((Inputs!$A$5:$A$190=$B4)*ISNUMBER(INDEX(Inputs!$K$5:$AJ$190,0,MATCH(AD$2,Inputs!$K$4:$AJ$4,0))))+SUMPRODUCT((Inputs!$C$5:$C$190=$B4)*ISNUMBER(INDEX(Inputs!$K$5:$AJ$190,0,MATCH(AD$2,Inputs!$K$4:$AJ$4,0))))+SUMPRODUCT((Inputs!$E$5:$E$190=$B4)*ISNUMBER(INDEX(Inputs!$K$5:$AJ$190,0,MATCH(AD$2,Inputs!$K$4:$AJ$4,0))))=0,NA(),SUMPRODUCT((Inputs!$A$5:$A$190=$B4)*Inputs!$B$5:$B$190*(((Inputs!$G$5:$G$190="moeda")+(Inputs!$G$5:$G$190="acoes"))*Inputs!$B$1+((Inputs!$G$5:$G$190<>"moeda")*(Inputs!$G$5:$G$190<>"acoes")))*INDEX(Inputs!$K$5:$AJ$190,0,MATCH(AD$2,Inputs!$K$4:$AJ$4,0)))+SUMPRODUCT((Inputs!$C$5:$C$190=$B4)*Inputs!$D$5:$D$190*(((Inputs!$G$5:$G$190="moeda")+(Inputs!$G$5:$G$190="acoes"))*Inputs!$B$1+((Inputs!$G$5:$G$190<>"moeda")*(Inputs!$G$5:$G$190<>"acoes")))*INDEX(Inputs!$K$5:$AJ$190,0,MATCH(AD$2,Inputs!$K$4:$AJ$4,0)))+SUMPRODUCT((Inputs!$E$5:$E$190=$B4)*Inputs!$F$5:$F$190*(((Inputs!$G$5:$G$190="moeda")+(Inputs!$G$5:$G$190="acoes"))*Inputs!$B$1+((Inputs!$G$5:$G$190<>"moeda")*(Inputs!$G$5:$G$190<>"acoes")))*INDEX(Inputs!$K$5:$AJ$190,0,MATCH(AD$2,Inputs!$K$4:$AJ$4,0))))) -> 11248.662 | AE4: =IF(ISNA(MATCH(AE$2,Inputs!$K$4:$AJ$4,0)),NA(),IF(SUMPRODUCT((Inputs!$A$5:$A$190=$B4)*ISNUMBER(INDEX(Inputs!$K$5:$AJ$190,0,MATCH(AE$2,Inputs!$K$4:$AJ$4,0))))+SUMPRODUCT((Inputs!$C$5:$C$190=$B4)*ISNUMBER(INDEX(Inputs!$K$5:$AJ$190,0,MATCH(AE$2,Inputs!$K$4:$AJ$4,0))))+SUMPRODUCT((Inputs!$E$5:$E$190=$B4)*ISNUMBER(INDEX(Inputs!$K$5:$AJ$190,0,MATCH(AE$2,Inputs!$K$4:$AJ$4,0))))=0,NA(),SUMPRODUCT((Inputs!$A$5:$A$190=$B4)*Inputs!$B$5:$B$190*(((Inputs!$G$5:$G$190="moeda")+(Inputs!$G$5:$G$190="acoes"))*Inputs!$B$1+((Inputs!$G$5:$G$190<>"moeda")*(Inputs!$G$5:$G$190<>"acoes")))*INDEX(Inputs!$K$5:$AJ$190,0,MATCH(AE$2,Inputs!$K$4:$AJ$4,0)))+SUMPRODUCT((Inputs!$C$5:$C$190=$B4)*Inputs!$D$5:$D$190*(((Inputs!$G$5:$G$190="moeda")+(Inputs!$G$5:$G$190="acoes"))*Inputs!$B$1+((Inputs!$G$5:$G$190<>"moeda")*(Inputs!$G$5:$G$190<>"acoes")))*INDEX(Inputs!$K$5:$AJ$190,0,MATCH(AE$2,Inputs!$K$4:$AJ$4,0)))+SUMPRODUCT((Inputs!$E$5:$E$190=$B4)*Inputs!$F$5:$F$190*(((Inputs!$G$5:$G$190="moeda")+(Inputs!$G$5:$G$190="acoes"))*Inputs!$B$1+((Inputs!$G$5:$G$190<>"moeda")*(Inputs!$G$5:$G$190<>"acoes")))*INDEX(Inputs!$K$5:$AJ$190,0,MATCH(AE$2,Inputs!$K$4:$AJ$4,0))))) -> #N/A | AF4: =IF(ISNA(MATCH(AF$2,Inputs!$K$4:$AJ$4,0)),NA(),IF(SUMPRODUCT((Inputs!$A$5:$A$190=$B4)*ISNUMBER(INDEX(Inputs!$K$5:$AJ$190,0,MATCH(AF$2,Inputs!$K$4:$AJ$4,0))))+SUMPRODUCT((Inputs!$C$5:$C$190=$B4)*ISNUMBER(INDEX(Inputs!$K$5:$AJ$190,0,MATCH(AF$2,Inputs!$K$4:$AJ$4,0))))+SUMPRODUCT((Inputs!$E$5:$E$190=$B4)*ISNUMBER(INDEX(Inputs!$K$5:$AJ$190,0,MATCH(AF$2,Inputs!$K$4:$AJ$4,0))))=0,NA(),SUMPRODUCT((Inputs!$A$5:$A$190=$B4)*Inputs!$B$5:$B$190*(((Inputs!$G$5:$G$190="moeda")+(Inputs!$G$5:$G$190="acoes"))*Inputs!$B$1+((Inputs!$G$5:$G$190<>"moeda")*(Inputs!$G$5:$G$190<>"acoes")))*INDEX(Inputs!$K$5:$AJ$190,0,MATCH(AF$2,Inputs!$K$4:$AJ$4,0)))+SUMPRODUCT((Inputs!$C$5:$C$190=$B4)*Inputs!$D$5:$D$190*(((Inputs!$G$5:$G$190="moeda")+(Inputs!$G$5:$G$190="acoes"))*Inputs!$B$1+((Inputs!$G$5:$G$190<>"moeda")*(Inputs!$G$5:$G$190<>"acoes")))*INDEX(Inputs!$K$5:$AJ$190,0,MATCH(AF$2,Inputs!$K$4:$AJ$4,0)))+SUMPRODUCT((Inputs!$E$5:$E$190=$B4)*Inputs!$F$5:$F$190*(((Inputs!$G$5:$G$190="moeda")+(Inputs!$G$5:$G$190="acoes"))*Inputs!$B$1+((Inputs!$G$5:$G$190<>"moeda")*(Inputs!$G$5:$G$190<>"acoes")))*INDEX(Inputs!$K$5:$AJ$190,0,MATCH(AF$2,Inputs!$K$4:$AJ$4,0))))) -> #N/A | AG4: =SUM(AC4:AF4) -> #N/A | AH4: =IF(ISNA(MATCH(AH$2,Inputs!$K$4:$AJ$4,0)),NA(),IF(SUMPRODUCT((Inputs!$A$5:$A$190=$B4)*ISNUMBER(INDEX(Inputs!$K$5:$AJ$190,0,MATCH(AH$2,Inputs!$K$4:$AJ$4,0))))+SUMPRODUCT((Inputs!$C$5:$C$190=$B4)*ISNUMBER(INDEX(Inputs!$K$5:$AJ$190,0,MATCH(AH$2,Inputs!$K$4:$AJ$4,0))))+SUMPRODUCT((Inputs!$E$5:$E$190=$B4)*ISNUMBER(INDEX(Inputs!$K$5:$AJ$190,0,MATCH(AH$2,Inputs!$K$4:$AJ$4,0))))=0,NA(),SUMPRODUCT((Inputs!$A$5:$A$190=$B4)*Inputs!$B$5:$B$190*(((Inputs!$G$5:$G$190="moeda")+(Inputs!$G$5:$G$190="acoes"))*Inputs!$B$1+((Inputs!$G$5:$G$190<>"moeda")*(Inputs!$G$5:$G$190<>"acoes")))*INDEX(Inputs!$K$5:$AJ$190,0,MATCH(AH$2,Inputs!$K$4:$AJ$4,0)))+SUMPRODUCT((Inputs!$C$5:$C$190=$B4)*Inputs!$D$5:$D$190*(((Inputs!$G$5:$G$190="moeda")+(Inputs!$G$5:$G$190="acoes"))*Inputs!$B$1+((Inputs!$G$5:$G$190<>"moeda")*(Inputs!$G$5:$G$190<>"acoes")))*INDEX(Inputs!$K$5:$AJ$190,0,MATCH(AH$2,Inputs!$K$4:$AJ$4,0)))+SUMPRODUCT((Inputs!$E$5:$E$190=$B4)*Inputs!$F$5:$F$190*(((Inputs!$G$5:$G$190="moeda")+(Inputs!$G$5:$G$190="acoes"))*Inputs!$B$1+((Inputs!$G$5:$G$190<>"moeda")*(Inputs!$G$5:$G$190<>"acoes")))*INDEX(Inputs!$K$5:$AJ$190,0,MATCH(AH$2,Inputs!$K$4:$AJ$4,0))))) -> 2356.8923 | AI4: =IF(ISNA(MATCH(AI$2,Inputs!$K$4:$AJ$4,0)),NA(),IF(SUMPRODUCT((Inputs!$A$5:$A$190=$B4)*ISNUMBER(INDEX(Inputs!$K$5:$AJ$190,0,MATCH(AI$2,Inputs!$K$4:$AJ$4,0))))+SUMPRODUCT((Inputs!$C$5:$C$190=$B4)*ISNUMBER(INDEX(Inputs!$K$5:$AJ$190,0,MATCH(AI$2,Inputs!$K$4:$AJ$4,0))))+SUMPRODUCT((Inputs!$E$5:$E$190=$B4)*ISNUMBER(INDEX(Inputs!$K$5:$AJ$190,0,MATCH(AI$2,Inputs!$K$4:$AJ$4,0))))=0,NA(),SUMPRODUCT((Inputs!$A$5:$A$190=$B4)*Inputs!$B$5:$B$190*(((Inputs!$G$5:$G$190="moeda")+(Inputs!$G$5:$G$190="acoes"))*Inputs!$B$1+((Inputs!$G$5:$G$190<>"moeda")*(Inputs!$G$5:$G$190<>"acoes")))*INDEX(Inputs!$K$5:$AJ$190,0,MATCH(AI$2,Inputs!$K$4:$AJ$4,0)))+SUMPRODUCT((Inputs!$C$5:$C$190=$B4)*Inputs!$D$5:$D$190*(((Inputs!$G$5:$G$190="moeda")+(Inputs!$G$5:$G$190="acoes"))*Inputs!$B$1+((Inputs!$G$5:$G$190<>"moeda")*(Inputs!$G$5:$G$190<>"acoes")))*INDEX(Inputs!$K$5:$AJ$190,0,MATCH(AI$2,Inputs!$K$4:$AJ$4,0)))+SUMPRODUCT((Inputs!$E$5:$E$190=$B4)*Inputs!$F$5:$F$190*(((Inputs!$G$5:$G$190="moeda")+(Inputs!$G$5:$G$190="acoes"))*Inputs!$B$1+((Inputs!$G$5:$G$190<>"moeda")*(Inputs!$G$5:$G$190<>"acoes")))*INDEX(Inputs!$K$5:$AJ$190,0,MATCH(AI$2,Inputs!$K$4:$AJ$4,0))))) -> 2197.2248 | AJ4: =IF(ISNA(MATCH(AJ$2,Inputs!$K$4:$AJ$4,0)),NA(),IF(SUMPRODUCT((Inputs!$A$5:$A$190=$B4)*ISNUMBER(INDEX(Inputs!$K$5:$AJ$190,0,MATCH(AJ$2,Inputs!$K$4:$AJ$4,0))))+SUMPRODUCT((Inputs!$C$5:$C$190=$B4)*ISNUMBER(INDEX(Inputs!$K$5:$AJ$190,0,MATCH(AJ$2,Inputs!$K$4:$AJ$4,0))))+SUMPRODUCT((Inputs!$E$5:$E$190=$B4)*ISNUMBER(INDEX(Inputs!$K$5:$AJ$190,0,MATCH(AJ$2,Inputs!$K$4:$AJ$4,0))))=0,NA(),SUMPRODUCT((Inputs!$A$5:$A$190=$B4)*Inputs!$B$5:$B$190*(((Inputs!$G$5:$G$190="moeda")+(Inputs!$G$5:$G$190="acoes"))*Inputs!$B$1+((Inputs!$G$5:$G$190<>"moeda")*(Inputs!$G$5:$G$190<>"acoes")))*INDEX(Inputs!$K$5:$AJ$190,0,MATCH(AJ$2,Inputs!$K$4:$AJ$4,0)))+SUMPRODUCT((Inputs!$C$5:$C$190=$B4)*Inputs!$D$5:$D$190*(((Inputs!$G$5:$G$190="moeda")+(Inputs!$G$5:$G$190="acoes"))*Inputs!$B$1+((Inputs!$G$5:$G$190<>"moeda")*(Inputs!$G$5:$G$190<>"acoes")))*INDEX(Inputs!$K$5:$AJ$190,0,MATCH(AJ$2,Inputs!$K$4:$AJ$4,0)))+SUMPRODUCT((Inputs!$E$5:$E$190=$B4)*Inputs!$F$5:$F$190*(((Inputs!$G$5:$G$190="moeda")+(Inputs!$G$5:$G$190="acoes"))*Inputs!$B$1+((Inputs!$G$5:$G$190<>"moeda")*(Inputs!$G$5:$G$190<>"acoes")))*INDEX(Inputs!$K$5:$AJ$190,0,MATCH(AJ$2,Inputs!$K$4:$AJ$4,0))))) -> 2603.0449 | AK4: =IF(ISNA(MATCH(AK$2,Inputs!$K$4:$AJ$4,0)),NA(),IF(SUMPRODUCT((Inputs!$A$5:$A$190=$B4)*ISNUMBER(INDEX(Inputs!$K$5:$AJ$190,0,MATCH(AK$2,Inputs!$K$4:$AJ$4,0))))+SUMPRODUCT((Inputs!$C$5:$C$190=$B4)*ISNUMBER(INDEX(Inputs!$K$5:$AJ$190,0,MATCH(AK$2,Inputs!$K$4:$AJ$4,0))))+SUMPRODUCT((Inputs!$E$5:$E$190=$B4)*ISNUMBER(INDEX(Inputs!$K$5:$AJ$190,0,MATCH(AK$2,Inputs!$K$4:$AJ$4,0))))=0,NA(),SUMPRODUCT((Inputs!$A$5:$A$190=$B4)*Inputs!$B$5:$B$190*(((Inputs!$G$5:$G$190="moeda")+(Inputs!$G$5:$G$190="acoes"))*Inputs!$B$1+((Inputs!$G$5:$G$190<>"moeda")*(Inputs!$G$5:$G$190<>"acoes")))*INDEX(Inputs!$K$5:$AJ$190,0,MATCH(AK$2,Inputs!$K$4:$AJ$4,0)))+SUMPRODUCT((Inputs!$C$5:$C$190=$B4)*Inputs!$D$5:$D$190*(((Inputs!$G$5:$G$190="moeda")+(Inputs!$G$5:$G$190="acoes"))*Inputs!$B$1+((Inputs!$G$5:$G$190<>"moeda")*(Inputs!$G$5:$G$190<>"acoes")))*INDEX(Inputs!$K$5:$AJ$190,0,MATCH(AK$2,Inputs!$K$4:$AJ$4,0)))+SUMPRODUCT((Inputs!$E$5:$E$190=$B4)*Inputs!$F$5:$F$190*(((Inputs!$G$5:$G$190="moeda")+(Inputs!$G$5:$G$190="acoes"))*Inputs!$B$1+((Inputs!$G$5:$G$190<>"moeda")*(Inputs!$G$5:$G$190<>"acoes")))*INDEX(Inputs!$K$5:$AJ$190,0,MATCH(AK$2,Inputs!$K$4:$AJ$4,0))))) -> 2649.895 | AL4: =SUM(AH4:AK4) -> 9807.057
B5: 2 | C5: COGS (cash) | D5: =IF(ISNA(MATCH(D$2,Inputs!$K$4:$AJ$4,0)),NA(),IF(SUMPRODUCT((Inputs!$A$5:$A$190=$B5)*ISNUMBER(INDEX(Inputs!$K$5:$AJ$190,0,MATCH(D$2,Inputs!$K$4:$AJ$4,0))))+SUMPRODUCT((Inputs!$C$5:$C$190=$B5)*ISNUMBER(INDEX(Inputs!$K$5:$AJ$190,0,MATCH(D$2,Inputs!$K$4:$AJ$4,0))))+SUMPRODUCT((Inputs!$E$5:$E$190=$B5)*ISNUMBER(INDEX(Inputs!$K$5:$AJ$190,0,MATCH(D$2,Inputs!$K$4:$AJ$4,0))))=0,NA(),SUMPRODUCT((Inputs!$A$5:$A$190=$B5)*Inputs!$B$5:$B$190*(((Inputs!$G$5:$G$190="moeda")+(Inputs!$G$5:$G$190="acoes"))*Inputs!$B$1+((Inputs!$G$5:$G$190<>"moeda")*(Inputs!$G$5:$G$190<>"acoes")))*INDEX(Inputs!$K$5:$AJ$190,0,MATCH(D$2,Inputs!$K$4:$AJ$4,0)))+SUMPRODUCT((Inputs!$C$5:$C$190=$B5)*Inputs!$D$5:$D$190*(((Inputs!$G$5:$G$190="moeda")+(Inputs!$G$5:$G$190="acoes"))*Inputs!$B$1+((Inputs!$G$5:$G$190<>"moeda")*(Inputs!$G$5:$G$190<>"acoes")))*INDEX(Inputs!$K$5:$AJ$190,0,MATCH(D$2,Inputs!$K$4:$AJ$4,0)))+SUMPRODUCT((Inputs!$E$5:$E$190=$B5)*Inputs!$F$5:$F$190*(((Inputs!$G$5:$G$190="moeda")+(Inputs!$G$5:$G$190="acoes"))*Inputs!$B$1+((Inputs!$G$5:$G$190<>"moeda")*(Inputs!$G$5:$G$190<>"acoes")))*INDEX(Inputs!$K$5:$AJ$190,0,MATCH(D$2,Inputs!$K$4:$AJ$4,0))))) -> -1575.3745 | E5: =IF(ISNA(MATCH(E$2,Inputs!$K$4:$AJ$4,0)),NA(),IF(SUMPRODUCT((Inputs!$A$5:$A$190=$B5)*ISNUMBER(INDEX(Inputs!$K$5:$AJ$190,0,MATCH(E$2,Inputs!$K$4:$AJ$4,0))))+SUMPRODUCT((Inputs!$C$5:$C$190=$B5)*ISNUMBER(INDEX(Inputs!$K$5:$AJ$190,0,MATCH(E$2,Inputs!$K$4:$AJ$4,0))))+SUMPRODUCT((Inputs!$E$5:$E$190=$B5)*ISNUMBER(INDEX(Inputs!$K$5:$AJ$190,0,MATCH(E$2,Inputs!$K$4:$AJ$4,0))))=0,NA(),SUMPRODUCT((Inputs!$A$5:$A$190=$B5)*Inputs!$B$5:$B$190*(((Inputs!$G$5:$G$190="moeda")+(Inputs!$G$5:$G$190="acoes"))*Inputs!$B$1+((Inputs!$G$5:$G$190<>"moeda")*(Inputs!$G$5:$G$190<>"acoes")))*INDEX(Inputs!$K$5:$AJ$190,0,MATCH(E$2,Inputs!$K$4:$AJ$4,0)))+SUMPRODUCT((Inputs!$C$5:$C$190=$B5)*Inputs!$D$5:$D$190*(((Inputs!$G$5:$G$190="moeda")+(Inputs!$G$5:$G$190="acoes"))*Inputs!$B$1+((Inputs!$G$5:$G$190<>"moeda")*(Inputs!$G$5:$G$190<>"acoes")))*INDEX(Inputs!$K$5:$AJ$190,0,MATCH(E$2,Inputs!$K$4:$AJ$4,0)))+SUMPRODUCT((Inputs!$E$5:$E$190=$B5)*Inputs!$F$5:$F$190*(((Inputs!$G$5:$G$190="moeda")+(Inputs!$G$5:$G$190="acoes"))*Inputs!$B$1+((Inputs!$G$5:$G$190<>"moeda")*(Inputs!$G$5:$G$190<>"acoes")))*INDEX(Inputs!$K$5:$AJ$190,0,MATCH(E$2,Inputs!$K$4:$AJ$4,0))))) -> -1930.8713 | F5: =IF(ISNA(MATCH(F$2,Inputs!$K$4:$AJ$4,0)),NA(),IF(SUMPRODUCT((Inputs!$A$5:$A$190=$B5)*ISNUMBER(INDEX(Inputs!$K$5:$AJ$190,0,MATCH(F$2,Inputs!$K$4:$AJ$4,0))))+SUMPRODUCT((Inputs!$C$5:$C$190=$B5)*ISNUMBER(INDEX(Inputs!$K$5:$AJ$190,0,MATCH(F$2,Inputs!$K$4:$AJ$4,0))))+SUMPRODUCT((Inputs!$E$5:$E$190=$B5)*ISNUMBER(INDEX(Inputs!$K$5:$AJ$190,0,MATCH(F$2,Inputs!$K$4:$AJ$4,0))))=0,NA(),SUMPRODUCT((Inputs!$A$5:$A$190=$B5)*Inputs!$B$5:$B$190*(((Inputs!$G$5:$G$190="moeda")+(Inputs!$G$5:$G$190="acoes"))*Inputs!$B$1+((Inputs!$G$5:$G$190<>"moeda")*(Inputs!$G$5:$G$190<>"acoes")))*INDEX(Inputs!$K$5:$AJ$190,0,MATCH(F$2,Inputs!$K$4:$AJ$4,0)))+SUMPRODUCT((Inputs!$C$5:$C$190=$B5)*Inputs!$D$5:$D$190*(((Inputs!$G$5:$G$190="moeda")+(Inputs!$G$5:$G$190="acoes"))*Inputs!$B$1+((Inputs!$G$5:$G$190<>"moeda")*(Inputs!$G$5:$G$190<>"acoes")))*INDEX(Inputs!$K$5:$AJ$190,0,MATCH(F$2,Inputs!$K$4:$AJ$4,0)))+SUMPRODUCT((Inputs!$E$5:$E$190=$B5)*Inputs!$F$5:$F$190*(((Inputs!$G$5:$G$190="moeda")+(Inputs!$G$5:$G$190="acoes"))*Inputs!$B$1+((Inputs!$G$5:$G$190<>"moeda")*(Inputs!$G$5:$G$190<>"acoes")))*INDEX(Inputs!$K$5:$AJ$190,0,MATCH(F$2,Inputs!$K$4:$AJ$4,0))))) -> -2418.8701 | G5: =IF(ISNA(MATCH(G$2,Inputs!$K$4:$AJ$4,0)),NA(),IF(SUMPRODUCT((Inputs!$A$5:$A$190=$B5)*ISNUMBER(INDEX(Inputs!$K$5:$AJ$190,0,MATCH(G$2,Inputs!$K$4:$AJ$4,0))))+SUMPRODUCT((Inputs!$C$5:$C$190=$B5)*ISNUMBER(INDEX(Inputs!$K$5:$AJ$190,0,MATCH(G$2,Inputs!$K$4:$AJ$4,0))))+SUMPRODUCT((Inputs!$E$5:$E$190=$B5)*ISNUMBER(INDEX(Inputs!$K$5:$AJ$190,0,MATCH(G$2,Inputs!$K$4:$AJ$4,0))))=0,NA(),SUMPRODUCT((Inputs!$A$5:$A$190=$B5)*Inputs!$B$5:$B$190*(((Inputs!$G$5:$G$190="moeda")+(Inputs!$G$5:$G$190="acoes"))*Inputs!$B$1+((Inputs!$G$5:$G$190<>"moeda")*(Inputs!$G$5:$G$190<>"acoes")))*INDEX(Inputs!$K$5:$AJ$190,0,MATCH(G$2,Inputs!$K$4:$AJ$4,0)))+SUMPRODUCT((Inputs!$C$5:$C$190=$B5)*Inputs!$D$5:$D$190*(((Inputs!$G$5:$G$190="moeda")+(Inputs!$G$5:$G$190="acoes"))*Inputs!$B$1+((Inputs!$G$5:$G$190<>"moeda")*(Inputs!$G$5:$G$190<>"acoes")))*INDEX(Inputs!$K$5:$AJ$190,0,MATCH(G$2,Inputs!$K$4:$AJ$4,0)))+SUMPRODUCT((Inputs!$E$5:$E$190=$B5)*Inputs!$F$5:$F$190*(((Inputs!$G$5:$G$190="moeda")+(Inputs!$G$5:$G$190="acoes"))*Inputs!$B$1+((Inputs!$G$5:$G$190<>"moeda")*(Inputs!$G$5:$G$190<>"acoes")))*INDEX(Inputs!$K$5:$AJ$190,0,MATCH(G$2,Inputs!$K$4:$AJ$4,0))))) -> -2398.0831 | H5: =SUM(D5:G5) -> -8323.199 | I5: =IF(ISNA(MATCH(I$2,Inputs!$K$4:$AJ$4,0)),NA(),IF(SUMPRODUCT((Inputs!$A$5:$A$190=$B5)*ISNUMBER(INDEX(Inputs!$K$5:$AJ$190,0,MATCH(I$2,Inputs!$K$4:$AJ$4,0))))+SUMPRODUCT((Inputs!$C$5:$C$190=$B5)*ISNUMBER(INDEX(Inputs!$K$5:$AJ$190,0,MATCH(I$2,Inputs!$K$4:$AJ$4,0))))+SUMPRODUCT((Inputs!$E$5:$E$190=$B5)*ISNUMBER(INDEX(Inputs!$K$5:$AJ$190,0,MATCH(I$2,Inputs!$K$4:$AJ$4,0))))=0,NA(),SUMPRODUCT((Inputs!$A$5:$A$190=$B5)*Inputs!$B$5:$B$190*(((Inputs!$G$5:$G$190="moeda")+(Inputs!$G$5:$G$190="acoes"))*Inputs!$B$1+((Inputs!$G$5:$G$190<>"moeda")*(Inputs!$G$5:$G$190<>"acoes")))*INDEX(Inputs!$K$5:$AJ$190,0,MATCH(I$2,Inputs!$K$4:$AJ$4,0)))+SUMPRODUCT((Inputs!$C$5:$C$190=$B5)*Inputs!$D$5:$D$190*(((Inputs!$G$5:$G$190="moeda")+(Inputs!$G$5:$G$190="acoes"))*Inputs!$B$1+((Inputs!$G$5:$G$190<>"moeda")*(Inputs!$G$5:$G$190<>"acoes")))*INDEX(Inputs!$K$5:$AJ$190,0,MATCH(I$2,Inputs!$K$4:$AJ$4,0)))+SUMPRODUCT((Inputs!$E$5:$E$190=$B5)*Inputs!$F$5:$F$190*(((Inputs!$G$5:$G$190="moeda")+(Inputs!$G$5:$G$190="acoes"))*Inputs!$B$1+((Inputs!$G$5:$G$190<>"moeda")*(Inputs!$G$5:$G$190<>"acoes")))*INDEX(Inputs!$K$5:$AJ$190,0,MATCH(I$2,Inputs!$K$4:$AJ$4,0))))) -> -2575.875 | J5: =IF(ISNA(MATCH(J$2,Inputs!$K$4:$AJ$4,0)),NA(),IF(SUMPRODUCT((Inputs!$A$5:$A$190=$B5)*ISNUMBER(INDEX(Inputs!$K$5:$AJ$190,0,MATCH(J$2,Inputs!$K$4:$AJ$4,0))))+SUMPRODUCT((Inputs!$C$5:$C$190=$B5)*ISNUMBER(INDEX(Inputs!$K$5:$AJ$190,0,MATCH(J$2,Inputs!$K$4:$AJ$4,0))))+SUMPRODUCT((Inputs!$E$5:$E$190=$B5)*ISNUMBER(INDEX(Inputs!$K$5:$AJ$190,0,MATCH(J$2,Inputs!$K$4:$AJ$4,0))))=0,NA(),SUMPRODUCT((Inputs!$A$5:$A$190=$B5)*Inputs!$B$5:$B$190*(((Inputs!$G$5:$G$190="moeda")+(Inputs!$G$5:$G$190="acoes"))*Inputs!$B$1+((Inputs!$G$5:$G$190<>"moeda")*(Inputs!$G$5:$G$190<>"acoes")))*INDEX(Inputs!$K$5:$AJ$190,0,MATCH(J$2,Inputs!$K$4:$AJ$4,0)))+SUMPRODUCT((Inputs!$C$5:$C$190=$B5)*Inputs!$D$5:$D$190*(((Inputs!$G$5:$G$190="moeda")+(Inputs!$G$5:$G$190="acoes"))*Inputs!$B$1+((Inputs!$G$5:$G$190<>"moeda")*(Inputs!$G$5:$G$190<>"acoes")))*INDEX(Inputs!$K$5:$AJ$190,0,MATCH(J$2,Inputs!$K$4:$AJ$4,0)))+SUMPRODUCT((Inputs!$E$5:$E$190=$B5)*Inputs!$F$5:$F$190*(((Inputs!$G$5:$G$190="moeda")+(Inputs!$G$5:$G$190="acoes"))*Inputs!$B$1+((Inputs!$G$5:$G$190<>"moeda")*(Inputs!$G$5:$G$190<>"acoes")))*INDEX(Inputs!$K$5:$AJ$190,0,MATCH(J$2,Inputs!$K$4:$AJ$4,0))))) -> -3171.5284 | K5: =IF(ISNA(MATCH(K$2,Inputs!$K$4:$AJ$4,0)),NA(),IF(SUMPRODUCT((Inputs!$A$5:$A$190=$B5)*ISNUMBER(INDEX(Inputs!$K$5:$AJ$190,0,MATCH(K$2,Inputs!$K$4:$AJ$4,0))))+SUMPRODUCT((Inputs!$C$5:$C$190=$B5)*ISNUMBER(INDEX(Inputs!$K$5:$AJ$190,0,MATCH(K$2,Inputs!$K$4:$AJ$4,0))))+SUMPRODUCT((Inputs!$E$5:$E$190=$B5)*ISNUMBER(INDEX(Inputs!$K$5:$AJ$190,0,MATCH(K$2,Inputs!$K$4:$AJ$4,0))))=0,NA(),SUMPRODUCT((Inputs!$A$5:$A$190=$B5)*Inputs!$B$5:$B$190*(((Inputs!$G$5:$G$190="moeda")+(Inputs!$G$5:$G$190="acoes"))*Inputs!$B$1+((Inputs!$G$5:$G$190<>"moeda")*(Inputs!$G$5:$G$190<>"acoes")))*INDEX(Inputs!$K$5:$AJ$190,0,MATCH(K$2,Inputs!$K$4:$AJ$4,0)))+SUMPRODUCT((Inputs!$C$5:$C$190=$B5)*Inputs!$D$5:$D$190*(((Inputs!$G$5:$G$190="moeda")+(Inputs!$G$5:$G$190="acoes"))*Inputs!$B$1+((Inputs!$G$5:$G$190<>"moeda")*(Inputs!$G$5:$G$190<>"acoes")))*INDEX(Inputs!$K$5:$AJ$190,0,MATCH(K$2,Inputs!$K$4:$AJ$4,0)))+SUMPRODUCT((Inputs!$E$5:$E$190=$B5)*Inputs!$F$5:$F$190*(((Inputs!$G$5:$G$190="moeda")+(Inputs!$G$5:$G$190="acoes"))*Inputs!$B$1+((Inputs!$G$5:$G$190<>"moeda")*(Inputs!$G$5:$G$190<>"acoes")))*INDEX(Inputs!$K$5:$AJ$190,0,MATCH(K$2,Inputs!$K$4:$AJ$4,0))))) -> -4240.2654 | L5: =IF(ISNA(MATCH(L$2,Inputs!$K$4:$AJ$4,0)),NA(),IF(SUMPRODUCT((Inputs!$A$5:$A$190=$B5)*ISNUMBER(INDEX(Inputs!$K$5:$AJ$190,0,MATCH(L$2,Inputs!$K$4:$AJ$4,0))))+SUMPRODUCT((Inputs!$C$5:$C$190=$B5)*ISNUMBER(INDEX(Inputs!$K$5:$AJ$190,0,MATCH(L$2,Inputs!$K$4:$AJ$4,0))))+SUMPRODUCT((Inputs!$E$5:$E$190=$B5)*ISNUMBER(INDEX(Inputs!$K$5:$AJ$190,0,MATCH(L$2,Inputs!$K$4:$AJ$4,0))))=0,NA(),SUMPRODUCT((Inputs!$A$5:$A$190=$B5)*Inputs!$B$5:$B$190*(((Inputs!$G$5:$G$190="moeda")+(Inputs!$G$5:$G$190="acoes"))*Inputs!$B$1+((Inputs!$G$5:$G$190<>"moeda")*(Inputs!$G$5:$G$190<>"acoes")))*INDEX(Inputs!$K$5:$AJ$190,0,MATCH(L$2,Inputs!$K$4:$AJ$4,0)))+SUMPRODUCT((Inputs!$C$5:$C$190=$B5)*Inputs!$D$5:$D$190*(((Inputs!$G$5:$G$190="moeda")+(Inputs!$G$5:$G$190="acoes"))*Inputs!$B$1+((Inputs!$G$5:$G$190<>"moeda")*(Inputs!$G$5:$G$190<>"acoes")))*INDEX(Inputs!$K$5:$AJ$190,0,MATCH(L$2,Inputs!$K$4:$AJ$4,0)))+SUMPRODUCT((Inputs!$E$5:$E$190=$B5)*Inputs!$F$5:$F$190*(((Inputs!$G$5:$G$190="moeda")+(Inputs!$G$5:$G$190="acoes"))*Inputs!$B$1+((Inputs!$G$5:$G$190<>"moeda")*(Inputs!$G$5:$G$190<>"acoes")))*INDEX(Inputs!$K$5:$AJ$190,0,MATCH(L$2,Inputs!$K$4:$AJ$4,0))))) -> -4616.7636 | M5: =SUM(I5:L5) -> -14604.432 | N5: =IF(ISNA(MATCH(N$2,Inputs!$K$4:$AJ$4,0)),NA(),IF(SUMPRODUCT((Inputs!$A$5:$A$190=$B5)*ISNUMBER(INDEX(Inputs!$K$5:$AJ$190,0,MATCH(N$2,Inputs!$K$4:$AJ$4,0))))+SUMPRODUCT((Inputs!$C$5:$C$190=$B5)*ISNUMBER(INDEX(Inputs!$K$5:$AJ$190,0,MATCH(N$2,Inputs!$K$4:$AJ$4,0))))+SUMPRODUCT((Inputs!$E$5:$E$190=$B5)*ISNUMBER(INDEX(Inputs!$K$5:$AJ$190,0,MATCH(N$2,Inputs!$K$4:$AJ$4,0))))=0,NA(),SUMPRODUCT((Inputs!$A$5:$A$190=$B5)*Inputs!$B$5:$B$190*(((Inputs!$G$5:$G$190="moeda")+(Inputs!$G$5:$G$190="acoes"))*Inputs!$B$1+((Inputs!$G$5:$G$190<>"moeda")*(Inputs!$G$5:$G$190<>"acoes")))*INDEX(Inputs!$K$5:$AJ$190,0,MATCH(N$2,Inputs!$K$4:$AJ$4,0)))+SUMPRODUCT((Inputs!$C$5:$C$190=$B5)*Inputs!$D$5:$D$190*(((Inputs!$G$5:$G$190="moeda")+(Inputs!$G$5:$G$190="acoes"))*Inputs!$B$1+((Inputs!$G$5:$G$190<>"moeda")*(Inputs!$G$5:$G$190<>"acoes")))*INDEX(Inputs!$K$5:$AJ$190,0,MATCH(N$2,Inputs!$K$4:$AJ$4,0)))+SUMPRODUCT((Inputs!$E$5:$E$190=$B5)*Inputs!$F$5:$F$190*(((Inputs!$G$5:$G$190="moeda")+(Inputs!$G$5:$G$190="acoes"))*Inputs!$B$1+((Inputs!$G$5:$G$190<>"moeda")*(Inputs!$G$5:$G$190<>"acoes")))*INDEX(Inputs!$K$5:$AJ$190,0,MATCH(N$2,Inputs!$K$4:$AJ$4,0))))) -> -4659.7679 | O5: =IF(ISNA(MATCH(O$2,Inputs!$K$4:$AJ$4,0)),NA(),IF(SUMPRODUCT((Inputs!$A$5:$A$190=$B5)*ISNUMBER(INDEX(Inputs!$K$5:$AJ$190,0,MATCH(O$2,Inputs!$K$4:$AJ$4,0))))+SUMPRODUCT((Inputs!$C$5:$C$190=$B5)*ISNUMBER(INDEX(Inputs!$K$5:$AJ$190,0,MATCH(O$2,Inputs!$K$4:$AJ$4,0))))+SUMPRODUCT((Inputs!$E$5:$E$190=$B5)*ISNUMBER(INDEX(Inputs!$K$5:$AJ$190,0,MATCH(O$2,Inputs!$K$4:$AJ$4,0))))=0,NA(),SUMPRODUCT((Inputs!$A$5:$A$190=$B5)*Inputs!$B$5:$B$190*(((Inputs!$G$5:$G$190="moeda")+(Inputs!$G$5:$G$190="acoes"))*Inputs!$B$1+((Inputs!$G$5:$G$190<>"moeda")*(Inputs!$G$5:$G$190<>"acoes")))*INDEX(Inputs!$K$5:$AJ$190,0,MATCH(O$2,Inputs!$K$4:$AJ$4,0)))+SUMPRODUCT((Inputs!$C$5:$C$190=$B5)*Inputs!$D$5:$D$190*(((Inputs!$G$5:$G$190="moeda")+(Inputs!$G$5:$G$190="acoes"))*Inputs!$B$1+((Inputs!$G$5:$G$190<>"moeda")*(Inputs!$G$5:$G$190<>"acoes")))*INDEX(Inputs!$K$5:$AJ$190,0,MATCH(O$2,Inputs!$K$4:$AJ$4,0)))+SUMPRODUCT((Inputs!$E$5:$E$190=$B5)*Inputs!$F$5:$F$190*(((Inputs!$G$5:$G$190="moeda")+(Inputs!$G$5:$G$190="acoes"))*Inputs!$B$1+((Inputs!$G$5:$G$190<>"moeda")*(Inputs!$G$5:$G$190<>"acoes")))*INDEX(Inputs!$K$5:$AJ$190,0,MATCH(O$2,Inputs!$K$4:$AJ$4,0))))) -> -4733.963 | P5: =IF(ISNA(MATCH(P$2,Inputs!$K$4:$AJ$4,0)),NA(),IF(SUMPRODUCT((Inputs!$A$5:$A$190=$B5)*ISNUMBER(INDEX(Inputs!$K$5:$AJ$190,0,MATCH(P$2,Inputs!$K$4:$AJ$4,0))))+SUMPRODUCT((Inputs!$C$5:$C$190=$B5)*ISNUMBER(INDEX(Inputs!$K$5:$AJ$190,0,MATCH(P$2,Inputs!$K$4:$AJ$4,0))))+SUMPRODUCT((Inputs!$E$5:$E$190=$B5)*ISNUMBER(INDEX(Inputs!$K$5:$AJ$190,0,MATCH(P$2,Inputs!$K$4:$AJ$4,0))))=0,NA(),SUMPRODUCT((Inputs!$A$5:$A$190=$B5)*Inputs!$B$5:$B$190*(((Inputs!$G$5:$G$190="moeda")+(Inputs!$G$5:$G$190="acoes"))*Inputs!$B$1+((Inputs!$G$5:$G$190<>"moeda")*(Inputs!$G$5:$G$190<>"acoes")))*INDEX(Inputs!$K$5:$AJ$190,0,MATCH(P$2,Inputs!$K$4:$AJ$4,0)))+SUMPRODUCT((Inputs!$C$5:$C$190=$B5)*Inputs!$D$5:$D$190*(((Inputs!$G$5:$G$190="moeda")+(Inputs!$G$5:$G$190="acoes"))*Inputs!$B$1+((Inputs!$G$5:$G$190<>"moeda")*(Inputs!$G$5:$G$190<>"acoes")))*INDEX(Inputs!$K$5:$AJ$190,0,MATCH(P$2,Inputs!$K$4:$AJ$4,0)))+SUMPRODUCT((Inputs!$E$5:$E$190=$B5)*Inputs!$F$5:$F$190*(((Inputs!$G$5:$G$190="moeda")+(Inputs!$G$5:$G$190="acoes"))*Inputs!$B$1+((Inputs!$G$5:$G$190<>"moeda")*(Inputs!$G$5:$G$190<>"acoes")))*INDEX(Inputs!$K$5:$AJ$190,0,MATCH(P$2,Inputs!$K$4:$AJ$4,0))))) -> -5378.4719 | Q5: =IF(ISNA(MATCH(Q$2,Inputs!$K$4:$AJ$4,0)),NA(),IF(SUMPRODUCT((Inputs!$A$5:$A$190=$B5)*ISNUMBER(INDEX(Inputs!$K$5:$AJ$190,0,MATCH(Q$2,Inputs!$K$4:$AJ$4,0))))+SUMPRODUCT((Inputs!$C$5:$C$190=$B5)*ISNUMBER(INDEX(Inputs!$K$5:$AJ$190,0,MATCH(Q$2,Inputs!$K$4:$AJ$4,0))))+SUMPRODUCT((Inputs!$E$5:$E$190=$B5)*ISNUMBER(INDEX(Inputs!$K$5:$AJ$190,0,MATCH(Q$2,Inputs!$K$4:$AJ$4,0))))=0,NA(),SUMPRODUCT((Inputs!$A$5:$A$190=$B5)*Inputs!$B$5:$B$190*(((Inputs!$G$5:$G$190="moeda")+(Inputs!$G$5:$G$190="acoes"))*Inputs!$B$1+((Inputs!$G$5:$G$190<>"moeda")*(Inputs!$G$5:$G$190<>"acoes")))*INDEX(Inputs!$K$5:$AJ$190,0,MATCH(Q$2,Inputs!$K$4:$AJ$4,0)))+SUMPRODUCT((Inputs!$C$5:$C$190=$B5)*Inputs!$D$5:$D$190*(((Inputs!$G$5:$G$190="moeda")+(Inputs!$G$5:$G$190="acoes"))*Inputs!$B$1+((Inputs!$G$5:$G$190<>"moeda")*(Inputs!$G$5:$G$190<>"acoes")))*INDEX(Inputs!$K$5:$AJ$190,0,MATCH(Q$2,Inputs!$K$4:$AJ$4,0)))+SUMPRODUCT((Inputs!$E$5:$E$190=$B5)*Inputs!$F$5:$F$190*(((Inputs!$G$5:$G$190="moeda")+(Inputs!$G$5:$G$190="acoes"))*Inputs!$B$1+((Inputs!$G$5:$G$190<>"moeda")*(Inputs!$G$5:$G$190<>"acoes")))*INDEX(Inputs!$K$5:$AJ$190,0,MATCH(Q$2,Inputs!$K$4:$AJ$4,0))))) -> -5823.6046 | R5: =SUM(N5:Q5) -> -20595.807 | S5: =IF(ISNA(MATCH(S$2,Inputs!$K$4:$AJ$4,0)),NA(),IF(SUMPRODUCT((Inputs!$A$5:$A$190=$B5)*ISNUMBER(INDEX(Inputs!$K$5:$AJ$190,0,MATCH(S$2,Inputs!$K$4:$AJ$4,0))))+SUMPRODUCT((Inputs!$C$5:$C$190=$B5)*ISNUMBER(INDEX(Inputs!$K$5:$AJ$190,0,MATCH(S$2,Inputs!$K$4:$AJ$4,0))))+SUMPRODUCT((Inputs!$E$5:$E$190=$B5)*ISNUMBER(INDEX(Inputs!$K$5:$AJ$190,0,MATCH(S$2,Inputs!$K$4:$AJ$4,0))))=0,NA(),SUMPRODUCT((Inputs!$A$5:$A$190=$B5)*Inputs!$B$5:$B$190*(((Inputs!$G$5:$G$190="moeda")+(Inputs!$G$5:$G$190="acoes"))*Inputs!$B$1+((Inputs!$G$5:$G$190<>"moeda")*(Inputs!$G$5:$G$190<>"acoes")))*INDEX(Inputs!$K$5:$AJ$190,0,MATCH(S$2,Inputs!$K$4:$AJ$4,0)))+SUMPRODUCT((Inputs!$C$5:$C$190=$B5)*Inputs!$D$5:$D$190*(((Inputs!$G$5:$G$190="moeda")+(Inputs!$G$5:$G$190="acoes"))*Inputs!$B$1+((Inputs!$G$5:$G$190<>"moeda")*(Inputs!$G$5:$G$190<>"acoes")))*INDEX(Inputs!$K$5:$AJ$190,0,MATCH(S$2,Inputs!$K$4:$AJ$4,0)))+SUMPRODUCT((Inputs!$E$5:$E$190=$B5)*Inputs!$F$5:$F$190*(((Inputs!$G$5:$G$190="moeda")+(Inputs!$G$5:$G$190="acoes"))*Inputs!$B$1+((Inputs!$G$5:$G$190<>"moeda")*(Inputs!$G$5:$G$190<>"acoes")))*INDEX(Inputs!$K$5:$AJ$190,0,MATCH(S$2,Inputs!$K$4:$AJ$4,0))))) -> -5801.0222 | T5: =IF(ISNA(MATCH(T$2,Inputs!$K$4:$AJ$4,0)),NA(),IF(SUMPRODUCT((Inputs!$A$5:$A$190=$B5)*ISNUMBER(INDEX(Inputs!$K$5:$AJ$190,0,MATCH(T$2,Inputs!$K$4:$AJ$4,0))))+SUMPRODUCT((Inputs!$C$5:$C$190=$B5)*ISNUMBER(INDEX(Inputs!$K$5:$AJ$190,0,MATCH(T$2,Inputs!$K$4:$AJ$4,0))))+SUMPRODUCT((Inputs!$E$5:$E$190=$B5)*ISNUMBER(INDEX(Inputs!$K$5:$AJ$190,0,MATCH(T$2,Inputs!$K$4:$AJ$4,0))))=0,NA(),SUMPRODUCT((Inputs!$A$5:$A$190=$B5)*Inputs!$B$5:$B$190*(((Inputs!$G$5:$G$190="moeda")+(Inputs!$G$5:$G$190="acoes"))*Inputs!$B$1+((Inputs!$G$5:$G$190<>"moeda")*(Inputs!$G$5:$G$190<>"acoes")))*INDEX(Inputs!$K$5:$AJ$190,0,MATCH(T$2,Inputs!$K$4:$AJ$4,0)))+SUMPRODUCT((Inputs!$C$5:$C$190=$B5)*Inputs!$D$5:$D$190*(((Inputs!$G$5:$G$190="moeda")+(Inputs!$G$5:$G$190="acoes"))*Inputs!$B$1+((Inputs!$G$5:$G$190<>"moeda")*(Inputs!$G$5:$G$190<>"acoes")))*INDEX(Inputs!$K$5:$AJ$190,0,MATCH(T$2,Inputs!$K$4:$AJ$4,0)))+SUMPRODUCT((Inputs!$E$5:$E$190=$B5)*Inputs!$F$5:$F$190*(((Inputs!$G$5:$G$190="moeda")+(Inputs!$G$5:$G$190="acoes"))*Inputs!$B$1+((Inputs!$G$5:$G$190<>"moeda")*(Inputs!$G$5:$G$190<>"acoes")))*INDEX(Inputs!$K$5:$AJ$190,0,MATCH(T$2,Inputs!$K$4:$AJ$4,0))))) -> -6751.4936 | U5: =IF(ISNA(MATCH(U$2,Inputs!$K$4:$AJ$4,0)),NA(),IF(SUMPRODUCT((Inputs!$A$5:$A$190=$B5)*ISNUMBER(INDEX(Inputs!$K$5:$AJ$190,0,MATCH(U$2,Inputs!$K$4:$AJ$4,0))))+SUMPRODUCT((Inputs!$C$5:$C$190=$B5)*ISNUMBER(INDEX(Inputs!$K$5:$AJ$190,0,MATCH(U$2,Inputs!$K$4:$AJ$4,0))))+SUMPRODUCT((Inputs!$E$5:$E$190=$B5)*ISNUMBER(INDEX(Inputs!$K$5:$AJ$190,0,MATCH(U$2,Inputs!$K$4:$AJ$4,0))))=0,NA(),SUMPRODUCT((Inputs!$A$5:$A$190=$B5)*Inputs!$B$5:$B$190*(((Inputs!$G$5:$G$190="moeda")+(Inputs!$G$5:$G$190="acoes"))*Inputs!$B$1+((Inputs!$G$5:$G$190<>"moeda")*(Inputs!$G$5:$G$190<>"acoes")))*INDEX(Inputs!$K$5:$AJ$190,0,MATCH(U$2,Inputs!$K$4:$AJ$4,0)))+SUMPRODUCT((Inputs!$C$5:$C$190=$B5)*Inputs!$D$5:$D$190*(((Inputs!$G$5:$G$190="moeda")+(Inputs!$G$5:$G$190="acoes"))*Inputs!$B$1+((Inputs!$G$5:$G$190<>"moeda")*(Inputs!$G$5:$G$190<>"acoes")))*INDEX(Inputs!$K$5:$AJ$190,0,MATCH(U$2,Inputs!$K$4:$AJ$4,0)))+SUMPRODUCT((Inputs!$E$5:$E$190=$B5)*Inputs!$F$5:$F$190*(((Inputs!$G$5:$G$190="moeda")+(Inputs!$G$5:$G$190="acoes"))*Inputs!$B$1+((Inputs!$G$5:$G$190<>"moeda")*(Inputs!$G$5:$G$190<>"acoes")))*INDEX(Inputs!$K$5:$AJ$190,0,MATCH(U$2,Inputs!$K$4:$AJ$4,0))))) -> -7094.0107 | V5: =IF(ISNA(MATCH(V$2,Inputs!$K$4:$AJ$4,0)),NA(),IF(SUMPRODUCT((Inputs!$A$5:$A$190=$B5)*ISNUMBER(INDEX(Inputs!$K$5:$AJ$190,0,MATCH(V$2,Inputs!$K$4:$AJ$4,0))))+SUMPRODUCT((Inputs!$C$5:$C$190=$B5)*ISNUMBER(INDEX(Inputs!$K$5:$AJ$190,0,MATCH(V$2,Inputs!$K$4:$AJ$4,0))))+SUMPRODUCT((Inputs!$E$5:$E$190=$B5)*ISNUMBER(INDEX(Inputs!$K$5:$AJ$190,0,MATCH(V$2,Inputs!$K$4:$AJ$4,0))))=0,NA(),SUMPRODUCT((Inputs!$A$5:$A$190=$B5)*Inputs!$B$5:$B$190*(((Inputs!$G$5:$G$190="moeda")+(Inputs!$G$5:$G$190="acoes"))*Inputs!$B$1+((Inputs!$G$5:$G$190<>"moeda")*(Inputs!$G$5:$G$190<>"acoes")))*INDEX(Inputs!$K$5:$AJ$190,0,MATCH(V$2,Inputs!$K$4:$AJ$4,0)))+SUMPRODUCT((Inputs!$C$5:$C$190=$B5)*Inputs!$D$5:$D$190*(((Inputs!$G$5:$G$190="moeda")+(Inputs!$G$5:$G$190="acoes"))*Inputs!$B$1+((Inputs!$G$5:$G$190<>"moeda")*(Inputs!$G$5:$G$190<>"acoes")))*INDEX(Inputs!$K$5:$AJ$190,0,MATCH(V$2,Inputs!$K$4:$AJ$4,0)))+SUMPRODUCT((Inputs!$E$5:$E$190=$B5)*Inputs!$F$5:$F$190*(((Inputs!$G$5:$G$190="moeda")+(Inputs!$G$5:$G$190="acoes"))*Inputs!$B$1+((Inputs!$G$5:$G$190<>"moeda")*(Inputs!$G$5:$G$190<>"acoes")))*INDEX(Inputs!$K$5:$AJ$190,0,MATCH(V$2,Inputs!$K$4:$AJ$4,0))))) -> -6972.9947 | W5: =SUM(S5:V5) -> -26619.521 | X5: =IF(ISNA(MATCH(X$2,Inputs!$K$4:$AJ$4,0)),NA(),IF(SUMPRODUCT((Inputs!$A$5:$A$190=$B5)*ISNUMBER(INDEX(Inputs!$K$5:$AJ$190,0,MATCH(X$2,Inputs!$K$4:$AJ$4,0))))+SUMPRODUCT((Inputs!$C$5:$C$190=$B5)*ISNUMBER(INDEX(Inputs!$K$5:$AJ$190,0,MATCH(X$2,Inputs!$K$4:$AJ$4,0))))+SUMPRODUCT((Inputs!$E$5:$E$190=$B5)*ISNUMBER(INDEX(Inputs!$K$5:$AJ$190,0,MATCH(X$2,Inputs!$K$4:$AJ$4,0))))=0,NA(),SUMPRODUCT((Inputs!$A$5:$A$190=$B5)*Inputs!$B$5:$B$190*(((Inputs!$G$5:$G$190="moeda")+(Inputs!$G$5:$G$190="acoes"))*Inputs!$B$1+((Inputs!$G$5:$G$190<>"moeda")*(Inputs!$G$5:$G$190<>"acoes")))*INDEX(Inputs!$K$5:$AJ$190,0,MATCH(X$2,Inputs!$K$4:$AJ$4,0)))+SUMPRODUCT((Inputs!$C$5:$C$190=$B5)*Inputs!$D$5:$D$190*(((Inputs!$G$5:$G$190="moeda")+(Inputs!$G$5:$G$190="acoes"))*Inputs!$B$1+((Inputs!$G$5:$G$190<>"moeda")*(Inputs!$G$5:$G$190<>"acoes")))*INDEX(Inputs!$K$5:$AJ$190,0,MATCH(X$2,Inputs!$K$4:$AJ$4,0)))+SUMPRODUCT((Inputs!$E$5:$E$190=$B5)*Inputs!$F$5:$F$190*(((Inputs!$G$5:$G$190="moeda")+(Inputs!$G$5:$G$190="acoes"))*Inputs!$B$1+((Inputs!$G$5:$G$190<>"moeda")*(Inputs!$G$5:$G$190<>"acoes")))*INDEX(Inputs!$K$5:$AJ$190,0,MATCH(X$2,Inputs!$K$4:$AJ$4,0))))) -> -6497.6292 | Y5: =IF(ISNA(MATCH(Y$2,Inputs!$K$4:$AJ$4,0)),NA(),IF(SUMPRODUCT((Inputs!$A$5:$A$190=$B5)*ISNUMBER(INDEX(Inputs!$K$5:$AJ$190,0,MATCH(Y$2,Inputs!$K$4:$AJ$4,0))))+SUMPRODUCT((Inputs!$C$5:$C$190=$B5)*ISNUMBER(INDEX(Inputs!$K$5:$AJ$190,0,MATCH(Y$2,Inputs!$K$4:$AJ$4,0))))+SUMPRODUCT((Inputs!$E$5:$E$190=$B5)*ISNUMBER(INDEX(Inputs!$K$5:$AJ$190,0,MATCH(Y$2,Inputs!$K$4:$AJ$4,0))))=0,NA(),SUMPRODUCT((Inputs!$A$5:$A$190=$B5)*Inputs!$B$5:$B$190*(((Inputs!$G$5:$G$190="moeda")+(Inputs!$G$5:$G$190="acoes"))*Inputs!$B$1+((Inputs!$G$5:$G$190<>"moeda")*(Inputs!$G$5:$G$190<>"acoes")))*INDEX(Inputs!$K$5:$AJ$190,0,MATCH(Y$2,Inputs!$K$4:$AJ$4,0)))+SUMPRODUCT((Inputs!$C$5:$C$190=$B5)*Inputs!$D$5:$D$190*(((Inputs!$G$5:$G$190="moeda")+(Inputs!$G$5:$G$190="acoes"))*Inputs!$B$1+((Inputs!$G$5:$G$190<>"moeda")*(Inputs!$G$5:$G$190<>"acoes")))*INDEX(Inputs!$K$5:$AJ$190,0,MATCH(Y$2,Inputs!$K$4:$AJ$4,0)))+SUMPRODUCT((Inputs!$E$5:$E$190=$B5)*Inputs!$F$5:$F$190*(((Inputs!$G$5:$G$190="moeda")+(Inputs!$G$5:$G$190="acoes"))*Inputs!$B$1+((Inputs!$G$5:$G$190<>"moeda")*(Inputs!$G$5:$G$190<>"acoes")))*INDEX(Inputs!$K$5:$AJ$190,0,MATCH(Y$2,Inputs!$K$4:$AJ$4,0))))) -> -6445.0928 | Z5: =IF(ISNA(MATCH(Z$2,Inputs!$K$4:$AJ$4,0)),NA(),IF(SUMPRODUCT((Inputs!$A$5:$A$190=$B5)*ISNUMBER(INDEX(Inputs!$K$5:$AJ$190,0,MATCH(Z$2,Inputs!$K$4:$AJ$4,0))))+SUMPRODUCT((Inputs!$C$5:$C$190=$B5)*ISNUMBER(INDEX(Inputs!$K$5:$AJ$190,0,MATCH(Z$2,Inputs!$K$4:$AJ$4,0))))+SUMPRODUCT((Inputs!$E$5:$E$190=$B5)*ISNUMBER(INDEX(Inputs!$K$5:$AJ$190,0,MATCH(Z$2,Inputs!$K$4:$AJ$4,0))))=0,NA(),SUMPRODUCT((Inputs!$A$5:$A$190=$B5)*Inputs!$B$5:$B$190*(((Inputs!$G$5:$G$190="moeda")+(Inputs!$G$5:$G$190="acoes"))*Inputs!$B$1+((Inputs!$G$5:$G$190<>"moeda")*(Inputs!$G$5:$G$190<>"acoes")))*INDEX(Inputs!$K$5:$AJ$190,0,MATCH(Z$2,Inputs!$K$4:$AJ$4,0)))+SUMPRODUCT((Inputs!$C$5:$C$190=$B5)*Inputs!$D$5:$D$190*(((Inputs!$G$5:$G$190="moeda")+(Inputs!$G$5:$G$190="acoes"))*Inputs!$B$1+((Inputs!$G$5:$G$190<>"moeda")*(Inputs!$G$5:$G$190<>"acoes")))*INDEX(Inputs!$K$5:$AJ$190,0,MATCH(Z$2,Inputs!$K$4:$AJ$4,0)))+SUMPRODUCT((Inputs!$E$5:$E$190=$B5)*Inputs!$F$5:$F$190*(((Inputs!$G$5:$G$190="moeda")+(Inputs!$G$5:$G$190="acoes"))*Inputs!$B$1+((Inputs!$G$5:$G$190<>"moeda")*(Inputs!$G$5:$G$190<>"acoes")))*INDEX(Inputs!$K$5:$AJ$190,0,MATCH(Z$2,Inputs!$K$4:$AJ$4,0))))) -> -7040.5244 | AA5: =IF(ISNA(MATCH(AA$2,Inputs!$K$4:$AJ$4,0)),NA(),IF(SUMPRODUCT((Inputs!$A$5:$A$190=$B5)*ISNUMBER(INDEX(Inputs!$K$5:$AJ$190,0,MATCH(AA$2,Inputs!$K$4:$AJ$4,0))))+SUMPRODUCT((Inputs!$C$5:$C$190=$B5)*ISNUMBER(INDEX(Inputs!$K$5:$AJ$190,0,MATCH(AA$2,Inputs!$K$4:$AJ$4,0))))+SUMPRODUCT((Inputs!$E$5:$E$190=$B5)*ISNUMBER(INDEX(Inputs!$K$5:$AJ$190,0,MATCH(AA$2,Inputs!$K$4:$AJ$4,0))))=0,NA(),SUMPRODUCT((Inputs!$A$5:$A$190=$B5)*Inputs!$B$5:$B$190*(((Inputs!$G$5:$G$190="moeda")+(Inputs!$G$5:$G$190="acoes"))*Inputs!$B$1+((Inputs!$G$5:$G$190<>"moeda")*(Inputs!$G$5:$G$190<>"acoes")))*INDEX(Inputs!$K$5:$AJ$190,0,MATCH(AA$2,Inputs!$K$4:$AJ$4,0)))+SUMPRODUCT((Inputs!$C$5:$C$190=$B5)*Inputs!$D$5:$D$190*(((Inputs!$G$5:$G$190="moeda")+(Inputs!$G$5:$G$190="acoes"))*Inputs!$B$1+((Inputs!$G$5:$G$190<>"moeda")*(Inputs!$G$5:$G$190<>"acoes")))*INDEX(Inputs!$K$5:$AJ$190,0,MATCH(AA$2,Inputs!$K$4:$AJ$4,0)))+SUMPRODUCT((Inputs!$E$5:$E$190=$B5)*Inputs!$F$5:$F$190*(((Inputs!$G$5:$G$190="moeda")+(Inputs!$G$5:$G$190="acoes"))*Inputs!$B$1+((Inputs!$G$5:$G$190<>"moeda")*(Inputs!$G$5:$G$190<>"acoes")))*INDEX(Inputs!$K$5:$AJ$190,0,MATCH(AA$2,Inputs!$K$4:$AJ$4,0))))) -> -6969.4723 | AB5: =SUM(X5:AA5) -> -26952.719 | AC5: =IF(ISNA(MATCH(AC$2,Inputs!$K$4:$AJ$4,0)),NA(),IF(SUMPRODUCT((Inputs!$A$5:$A$190=$B5)*ISNUMBER(INDEX(Inputs!$K$5:$AJ$190,0,MATCH(AC$2,Inputs!$K$4:$AJ$4,0))))+SUMPRODUCT((Inputs!$C$5:$C$190=$B5)*ISNUMBER(INDEX(Inputs!$K$5:$AJ$190,0,MATCH(AC$2,Inputs!$K$4:$AJ$4,0))))+SUMPRODUCT((Inputs!$E$5:$E$190=$B5)*ISNUMBER(INDEX(Inputs!$K$5:$AJ$190,0,MATCH(AC$2,Inputs!$K$4:$AJ$4,0))))=0,NA(),SUMPRODUCT((Inputs!$A$5:$A$190=$B5)*Inputs!$B$5:$B$190*(((Inputs!$G$5:$G$190="moeda")+(Inputs!$G$5:$G$190="acoes"))*Inputs!$B$1+((Inputs!$G$5:$G$190<>"moeda")*(Inputs!$G$5:$G$190<>"acoes")))*INDEX(Inputs!$K$5:$AJ$190,0,MATCH(AC$2,Inputs!$K$4:$AJ$4,0)))+SUMPRODUCT((Inputs!$C$5:$C$190=$B5)*Inputs!$D$5:$D$190*(((Inputs!$G$5:$G$190="moeda")+(Inputs!$G$5:$G$190="acoes"))*Inputs!$B$1+((Inputs!$G$5:$G$190<>"moeda")*(Inputs!$G$5:$G$190<>"acoes")))*INDEX(Inputs!$K$5:$AJ$190,0,MATCH(AC$2,Inputs!$K$4:$AJ$4,0)))+SUMPRODUCT((Inputs!$E$5:$E$190=$B5)*Inputs!$F$5:$F$190*(((Inputs!$G$5:$G$190="moeda")+(Inputs!$G$5:$G$190="acoes"))*Inputs!$B$1+((Inputs!$G$5:$G$190<>"moeda")*(Inputs!$G$5:$G$190<>"acoes")))*INDEX(Inputs!$K$5:$AJ$190,0,MATCH(AC$2,Inputs!$K$4:$AJ$4,0))))) -> -6737.0059 | AD5: =IF(ISNA(MATCH(AD$2,Inputs!$K$4:$AJ$4,0)),NA(),IF(SUMPRODUCT((Inputs!$A$5:$A$190=$B5)*ISNUMBER(INDEX(Inputs!$K$5:$AJ$190,0,MATCH(AD$2,Inputs!$K$4:$AJ$4,0))))+SUMPRODUCT((Inputs!$C$5:$C$190=$B5)*ISNUMBER(INDEX(Inputs!$K$5:$AJ$190,0,MATCH(AD$2,Inputs!$K$4:$AJ$4,0))))+SUMPRODUCT((Inputs!$E$5:$E$190=$B5)*ISNUMBER(INDEX(Inputs!$K$5:$AJ$190,0,MATCH(AD$2,Inputs!$K$4:$AJ$4,0))))=0,NA(),SUMPRODUCT((Inputs!$A$5:$A$190=$B5)*Inputs!$B$5:$B$190*(((Inputs!$G$5:$G$190="moeda")+(Inputs!$G$5:$G$190="acoes"))*Inputs!$B$1+((Inputs!$G$5:$G$190<>"moeda")*(Inputs!$G$5:$G$190<>"acoes")))*INDEX(Inputs!$K$5:$AJ$190,0,MATCH(AD$2,Inputs!$K$4:$AJ$4,0)))+SUMPRODUCT((Inputs!$C$5:$C$190=$B5)*Inputs!$D$5:$D$190*(((Inputs!$G$5:$G$190="moeda")+(Inputs!$G$5:$G$190="acoes"))*Inputs!$B$1+((Inputs!$G$5:$G$190<>"moeda")*(Inputs!$G$5:$G$190<>"acoes")))*INDEX(Inputs!$K$5:$AJ$190,0,MATCH(AD$2,Inputs!$K$4:$AJ$4,0)))+SUMPRODUCT((Inputs!$E$5:$E$190=$B5)*Inputs!$F$5:$F$190*(((Inputs!$G$5:$G$190="moeda")+(Inputs!$G$5:$G$190="acoes"))*Inputs!$B$1+((Inputs!$G$5:$G$190<>"moeda")*(Inputs!$G$5:$G$190<>"acoes")))*INDEX(Inputs!$K$5:$AJ$190,0,MATCH(AD$2,Inputs!$K$4:$AJ$4,0))))) -> -6813.7923 | AE5: =IF(ISNA(MATCH(AE$2,Inputs!$K$4:$AJ$4,0)),NA(),IF(SUMPRODUCT((Inputs!$A$5:$A$190=$B5)*ISNUMBER(INDEX(Inputs!$K$5:$AJ$190,0,MATCH(AE$2,Inputs!$K$4:$AJ$4,0))))+SUMPRODUCT((Inputs!$C$5:$C$190=$B5)*ISNUMBER(INDEX(Inputs!$K$5:$AJ$190,0,MATCH(AE$2,Inputs!$K$4:$AJ$4,0))))+SUMPRODUCT((Inputs!$E$5:$E$190=$B5)*ISNUMBER(INDEX(Inputs!$K$5:$AJ$190,0,MATCH(AE$2,Inputs!$K$4:$AJ$4,0))))=0,NA(),SUMPRODUCT((Inputs!$A$5:$A$190=$B5)*Inputs!$B$5:$B$190*(((Inputs!$G$5:$G$190="moeda")+(Inputs!$G$5:$G$190="acoes"))*Inputs!$B$1+((Inputs!$G$5:$G$190<>"moeda")*(Inputs!$G$5:$G$190<>"acoes")))*INDEX(Inputs!$K$5:$AJ$190,0,MATCH(AE$2,Inputs!$K$4:$AJ$4,0)))+SUMPRODUCT((Inputs!$C$5:$C$190=$B5)*Inputs!$D$5:$D$190*(((Inputs!$G$5:$G$190="moeda")+(Inputs!$G$5:$G$190="acoes"))*Inputs!$B$1+((Inputs!$G$5:$G$190<>"moeda")*(Inputs!$G$5:$G$190<>"acoes")))*INDEX(Inputs!$K$5:$AJ$190,0,MATCH(AE$2,Inputs!$K$4:$AJ$4,0)))+SUMPRODUCT((Inputs!$E$5:$E$190=$B5)*Inputs!$F$5:$F$190*(((Inputs!$G$5:$G$190="moeda")+(Inputs!$G$5:$G$190="acoes"))*Inputs!$B$1+((Inputs!$G$5:$G$190<>"moeda")*(Inputs!$G$5:$G$190<>"acoes")))*INDEX(Inputs!$K$5:$AJ$190,0,MATCH(AE$2,Inputs!$K$4:$AJ$4,0))))) -> #N/A | AF5: =IF(ISNA(MATCH(AF$2,Inputs!$K$4:$AJ$4,0)),NA(),IF(SUMPRODUCT((Inputs!$A$5:$A$190=$B5)*ISNUMBER(INDEX(Inputs!$K$5:$AJ$190,0,MATCH(AF$2,Inputs!$K$4:$AJ$4,0))))+SUMPRODUCT((Inputs!$C$5:$C$190=$B5)*ISNUMBER(INDEX(Inputs!$K$5:$AJ$190,0,MATCH(AF$2,Inputs!$K$4:$AJ$4,0))))+SUMPRODUCT((Inputs!$E$5:$E$190=$B5)*ISNUMBER(INDEX(Inputs!$K$5:$AJ$190,0,MATCH(AF$2,Inputs!$K$4:$AJ$4,0))))=0,NA(),SUMPRODUCT((Inputs!$A$5:$A$190=$B5)*Inputs!$B$5:$B$190*(((Inputs!$G$5:$G$190="moeda")+(Inputs!$G$5:$G$190="acoes"))*Inputs!$B$1+((Inputs!$G$5:$G$190<>"moeda")*(Inputs!$G$5:$G$190<>"acoes")))*INDEX(Inputs!$K$5:$AJ$190,0,MATCH(AF$2,Inputs!$K$4:$AJ$4,0)))+SUMPRODUCT((Inputs!$C$5:$C$190=$B5)*Inputs!$D$5:$D$190*(((Inputs!$G$5:$G$190="moeda")+(Inputs!$G$5:$G$190="acoes"))*Inputs!$B$1+((Inputs!$G$5:$G$190<>"moeda")*(Inputs!$G$5:$G$190<>"acoes")))*INDEX(Inputs!$K$5:$AJ$190,0,MATCH(AF$2,Inputs!$K$4:$AJ$4,0)))+SUMPRODUCT((Inputs!$E$5:$E$190=$B5)*Inputs!$F$5:$F$190*(((Inputs!$G$5:$G$190="moeda")+(Inputs!$G$5:$G$190="acoes"))*Inputs!$B$1+((Inputs!$G$5:$G$190<>"moeda")*(Inputs!$G$5:$G$190<>"acoes")))*INDEX(Inputs!$K$5:$AJ$190,0,MATCH(AF$2,Inputs!$K$4:$AJ$4,0))))) -> #N/A | AG5: =SUM(AC5:AF5) -> #N/A | AH5: =IF(ISNA(MATCH(AH$2,Inputs!$K$4:$AJ$4,0)),NA(),IF(SUMPRODUCT((Inputs!$A$5:$A$190=$B5)*ISNUMBER(INDEX(Inputs!$K$5:$AJ$190,0,MATCH(AH$2,Inputs!$K$4:$AJ$4,0))))+SUMPRODUCT((Inputs!$C$5:$C$190=$B5)*ISNUMBER(INDEX(Inputs!$K$5:$AJ$190,0,MATCH(AH$2,Inputs!$K$4:$AJ$4,0))))+SUMPRODUCT((Inputs!$E$5:$E$190=$B5)*ISNUMBER(INDEX(Inputs!$K$5:$AJ$190,0,MATCH(AH$2,Inputs!$K$4:$AJ$4,0))))=0,NA(),SUMPRODUCT((Inputs!$A$5:$A$190=$B5)*Inputs!$B$5:$B$190*(((Inputs!$G$5:$G$190="moeda")+(Inputs!$G$5:$G$190="acoes"))*Inputs!$B$1+((Inputs!$G$5:$G$190<>"moeda")*(Inputs!$G$5:$G$190<>"acoes")))*INDEX(Inputs!$K$5:$AJ$190,0,MATCH(AH$2,Inputs!$K$4:$AJ$4,0)))+SUMPRODUCT((Inputs!$C$5:$C$190=$B5)*Inputs!$D$5:$D$190*(((Inputs!$G$5:$G$190="moeda")+(Inputs!$G$5:$G$190="acoes"))*Inputs!$B$1+((Inputs!$G$5:$G$190<>"moeda")*(Inputs!$G$5:$G$190<>"acoes")))*INDEX(Inputs!$K$5:$AJ$190,0,MATCH(AH$2,Inputs!$K$4:$AJ$4,0)))+SUMPRODUCT((Inputs!$E$5:$E$190=$B5)*Inputs!$F$5:$F$190*(((Inputs!$G$5:$G$190="moeda")+(Inputs!$G$5:$G$190="acoes"))*Inputs!$B$1+((Inputs!$G$5:$G$190<>"moeda")*(Inputs!$G$5:$G$190<>"acoes")))*INDEX(Inputs!$K$5:$AJ$190,0,MATCH(AH$2,Inputs!$K$4:$AJ$4,0))))) -> -1369.9255 | AI5: =IF(ISNA(MATCH(AI$2,Inputs!$K$4:$AJ$4,0)),NA(),IF(SUMPRODUCT((Inputs!$A$5:$A$190=$B5)*ISNUMBER(INDEX(Inputs!$K$5:$AJ$190,0,MATCH(AI$2,Inputs!$K$4:$AJ$4,0))))+SUMPRODUCT((Inputs!$C$5:$C$190=$B5)*ISNUMBER(INDEX(Inputs!$K$5:$AJ$190,0,MATCH(AI$2,Inputs!$K$4:$AJ$4,0))))+SUMPRODUCT((Inputs!$E$5:$E$190=$B5)*ISNUMBER(INDEX(Inputs!$K$5:$AJ$190,0,MATCH(AI$2,Inputs!$K$4:$AJ$4,0))))=0,NA(),SUMPRODUCT((Inputs!$A$5:$A$190=$B5)*Inputs!$B$5:$B$190*(((Inputs!$G$5:$G$190="moeda")+(Inputs!$G$5:$G$190="acoes"))*Inputs!$B$1+((Inputs!$G$5:$G$190<>"moeda")*(Inputs!$G$5:$G$190<>"acoes")))*INDEX(Inputs!$K$5:$AJ$190,0,MATCH(AI$2,Inputs!$K$4:$AJ$4,0)))+SUMPRODUCT((Inputs!$C$5:$C$190=$B5)*Inputs!$D$5:$D$190*(((Inputs!$G$5:$G$190="moeda")+(Inputs!$G$5:$G$190="acoes"))*Inputs!$B$1+((Inputs!$G$5:$G$190<>"moeda")*(Inputs!$G$5:$G$190<>"acoes")))*INDEX(Inputs!$K$5:$AJ$190,0,MATCH(AI$2,Inputs!$K$4:$AJ$4,0)))+SUMPRODUCT((Inputs!$E$5:$E$190=$B5)*Inputs!$F$5:$F$190*(((Inputs!$G$5:$G$190="moeda")+(Inputs!$G$5:$G$190="acoes"))*Inputs!$B$1+((Inputs!$G$5:$G$190<>"moeda")*(Inputs!$G$5:$G$190<>"acoes")))*INDEX(Inputs!$K$5:$AJ$190,0,MATCH(AI$2,Inputs!$K$4:$AJ$4,0))))) -> -1531.7828 | AJ5: =IF(ISNA(MATCH(AJ$2,Inputs!$K$4:$AJ$4,0)),NA(),IF(SUMPRODUCT((Inputs!$A$5:$A$190=$B5)*ISNUMBER(INDEX(Inputs!$K$5:$AJ$190,0,MATCH(AJ$2,Inputs!$K$4:$AJ$4,0))))+SUMPRODUCT((Inputs!$C$5:$C$190=$B5)*ISNUMBER(INDEX(Inputs!$K$5:$AJ$190,0,MATCH(AJ$2,Inputs!$K$4:$AJ$4,0))))+SUMPRODUCT((Inputs!$E$5:$E$190=$B5)*ISNUMBER(INDEX(Inputs!$K$5:$AJ$190,0,MATCH(AJ$2,Inputs!$K$4:$AJ$4,0))))=0,NA(),SUMPRODUCT((Inputs!$A$5:$A$190=$B5)*Inputs!$B$5:$B$190*(((Inputs!$G$5:$G$190="moeda")+(Inputs!$G$5:$G$190="acoes"))*Inputs!$B$1+((Inputs!$G$5:$G$190<>"moeda")*(Inputs!$G$5:$G$190<>"acoes")))*INDEX(Inputs!$K$5:$AJ$190,0,MATCH(AJ$2,Inputs!$K$4:$AJ$4,0)))+SUMPRODUCT((Inputs!$C$5:$C$190=$B5)*Inputs!$D$5:$D$190*(((Inputs!$G$5:$G$190="moeda")+(Inputs!$G$5:$G$190="acoes"))*Inputs!$B$1+((Inputs!$G$5:$G$190<>"moeda")*(Inputs!$G$5:$G$190<>"acoes")))*INDEX(Inputs!$K$5:$AJ$190,0,MATCH(AJ$2,Inputs!$K$4:$AJ$4,0)))+SUMPRODUCT((Inputs!$E$5:$E$190=$B5)*Inputs!$F$5:$F$190*(((Inputs!$G$5:$G$190="moeda")+(Inputs!$G$5:$G$190="acoes"))*Inputs!$B$1+((Inputs!$G$5:$G$190<>"moeda")*(Inputs!$G$5:$G$190<>"acoes")))*INDEX(Inputs!$K$5:$AJ$190,0,MATCH(AJ$2,Inputs!$K$4:$AJ$4,0))))) -> -1772.6041 | AK5: =IF(ISNA(MATCH(AK$2,Inputs!$K$4:$AJ$4,0)),NA(),IF(SUMPRODUCT((Inputs!$A$5:$A$190=$B5)*ISNUMBER(INDEX(Inputs!$K$5:$AJ$190,0,MATCH(AK$2,Inputs!$K$4:$AJ$4,0))))+SUMPRODUCT((Inputs!$C$5:$C$190=$B5)*ISNUMBER(INDEX(Inputs!$K$5:$AJ$190,0,MATCH(AK$2,Inputs!$K$4:$AJ$4,0))))+SUMPRODUCT((Inputs!$E$5:$E$190=$B5)*ISNUMBER(INDEX(Inputs!$K$5:$AJ$190,0,MATCH(AK$2,Inputs!$K$4:$AJ$4,0))))=0,NA(),SUMPRODUCT((Inputs!$A$5:$A$190=$B5)*Inputs!$B$5:$B$190*(((Inputs!$G$5:$G$190="moeda")+(Inputs!$G$5:$G$190="acoes"))*Inputs!$B$1+((Inputs!$G$5:$G$190<>"moeda")*(Inputs!$G$5:$G$190<>"acoes")))*INDEX(Inputs!$K$5:$AJ$190,0,MATCH(AK$2,Inputs!$K$4:$AJ$4,0)))+SUMPRODUCT((Inputs!$C$5:$C$190=$B5)*Inputs!$D$5:$D$190*(((Inputs!$G$5:$G$190="moeda")+(Inputs!$G$5:$G$190="acoes"))*Inputs!$B$1+((Inputs!$G$5:$G$190<>"moeda")*(Inputs!$G$5:$G$190<>"acoes")))*INDEX(Inputs!$K$5:$AJ$190,0,MATCH(AK$2,Inputs!$K$4:$AJ$4,0)))+SUMPRODUCT((Inputs!$E$5:$E$190=$B5)*Inputs!$F$5:$F$190*(((Inputs!$G$5:$G$190="moeda")+(Inputs!$G$5:$G$190="acoes"))*Inputs!$B$1+((Inputs!$G$5:$G$190<>"moeda")*(Inputs!$G$5:$G$190<>"acoes")))*INDEX(Inputs!$K$5:$AJ$190,0,MATCH(AK$2,Inputs!$K$4:$AJ$4,0))))) -> -1855.4714 | AL5: =SUM(AH5:AK5) -> -6529.7839
B6: 3 | C6: SG&A and Other (cash) | D6: =IF(ISNA(MATCH(D$2,Inputs!$K$4:$AJ$4,0)),NA(),IF(SUMPRODUCT((Inputs!$A$5:$A$190=$B6)*ISNUMBER(INDEX(Inputs!$K$5:$AJ$190,0,MATCH(D$2,Inputs!$K$4:$AJ$4,0))))+SUMPRODUCT((Inputs!$C$5:$C$190=$B6)*ISNUMBER(INDEX(Inputs!$K$5:$AJ$190,0,MATCH(D$2,Inputs!$K$4:$AJ$4,0))))+SUMPRODUCT((Inputs!$E$5:$E$190=$B6)*ISNUMBER(INDEX(Inputs!$K$5:$AJ$190,0,MATCH(D$2,Inputs!$K$4:$AJ$4,0))))=0,NA(),SUMPRODUCT((Inputs!$A$5:$A$190=$B6)*Inputs!$B$5:$B$190*(((Inputs!$G$5:$G$190="moeda")+(Inputs!$G$5:$G$190="acoes"))*Inputs!$B$1+((Inputs!$G$5:$G$190<>"moeda")*(Inputs!$G$5:$G$190<>"acoes")))*INDEX(Inputs!$K$5:$AJ$190,0,MATCH(D$2,Inputs!$K$4:$AJ$4,0)))+SUMPRODUCT((Inputs!$C$5:$C$190=$B6)*Inputs!$D$5:$D$190*(((Inputs!$G$5:$G$190="moeda")+(Inputs!$G$5:$G$190="acoes"))*Inputs!$B$1+((Inputs!$G$5:$G$190<>"moeda")*(Inputs!$G$5:$G$190<>"acoes")))*INDEX(Inputs!$K$5:$AJ$190,0,MATCH(D$2,Inputs!$K$4:$AJ$4,0)))+SUMPRODUCT((Inputs!$E$5:$E$190=$B6)*Inputs!$F$5:$F$190*(((Inputs!$G$5:$G$190="moeda")+(Inputs!$G$5:$G$190="acoes"))*Inputs!$B$1+((Inputs!$G$5:$G$190<>"moeda")*(Inputs!$G$5:$G$190<>"acoes")))*INDEX(Inputs!$K$5:$AJ$190,0,MATCH(D$2,Inputs!$K$4:$AJ$4,0))))) -> -311.02712 | E6: =IF(ISNA(MATCH(E$2,Inputs!$K$4:$AJ$4,0)),NA(),IF(SUMPRODUCT((Inputs!$A$5:$A$190=$B6)*ISNUMBER(INDEX(Inputs!$K$5:$AJ$190,0,MATCH(E$2,Inputs!$K$4:$AJ$4,0))))+SUMPRODUCT((Inputs!$C$5:$C$190=$B6)*ISNUMBER(INDEX(Inputs!$K$5:$AJ$190,0,MATCH(E$2,Inputs!$K$4:$AJ$4,0))))+SUMPRODUCT((Inputs!$E$5:$E$190=$B6)*ISNUMBER(INDEX(Inputs!$K$5:$AJ$190,0,MATCH(E$2,Inputs!$K$4:$AJ$4,0))))=0,NA(),SUMPRODUCT((Inputs!$A$5:$A$190=$B6)*Inputs!$B$5:$B$190*(((Inputs!$G$5:$G$190="moeda")+(Inputs!$G$5:$G$190="acoes"))*Inputs!$B$1+((Inputs!$G$5:$G$190<>"moeda")*(Inputs!$G$5:$G$190<>"acoes")))*INDEX(Inputs!$K$5:$AJ$190,0,MATCH(E$2,Inputs!$K$4:$AJ$4,0)))+SUMPRODUCT((Inputs!$C$5:$C$190=$B6)*Inputs!$D$5:$D$190*(((Inputs!$G$5:$G$190="moeda")+(Inputs!$G$5:$G$190="acoes"))*Inputs!$B$1+((Inputs!$G$5:$G$190<>"moeda")*(Inputs!$G$5:$G$190<>"acoes")))*INDEX(Inputs!$K$5:$AJ$190,0,MATCH(E$2,Inputs!$K$4:$AJ$4,0)))+SUMPRODUCT((Inputs!$E$5:$E$190=$B6)*Inputs!$F$5:$F$190*(((Inputs!$G$5:$G$190="moeda")+(Inputs!$G$5:$G$190="acoes"))*Inputs!$B$1+((Inputs!$G$5:$G$190<>"moeda")*(Inputs!$G$5:$G$190<>"acoes")))*INDEX(Inputs!$K$5:$AJ$190,0,MATCH(E$2,Inputs!$K$4:$AJ$4,0))))) -> -253.18521 | F6: =IF(ISNA(MATCH(F$2,Inputs!$K$4:$AJ$4,0)),NA(),IF(SUMPRODUCT((Inputs!$A$5:$A$190=$B6)*ISNUMBER(INDEX(Inputs!$K$5:$AJ$190,0,MATCH(F$2,Inputs!$K$4:$AJ$4,0))))+SUMPRODUCT((Inputs!$C$5:$C$190=$B6)*ISNUMBER(INDEX(Inputs!$K$5:$AJ$190,0,MATCH(F$2,Inputs!$K$4:$AJ$4,0))))+SUMPRODUCT((Inputs!$E$5:$E$190=$B6)*ISNUMBER(INDEX(Inputs!$K$5:$AJ$190,0,MATCH(F$2,Inputs!$K$4:$AJ$4,0))))=0,NA(),SUMPRODUCT((Inputs!$A$5:$A$190=$B6)*Inputs!$B$5:$B$190*(((Inputs!$G$5:$G$190="moeda")+(Inputs!$G$5:$G$190="acoes"))*Inputs!$B$1+((Inputs!$G$5:$G$190<>"moeda")*(Inputs!$G$5:$G$190<>"acoes")))*INDEX(Inputs!$K$5:$AJ$190,0,MATCH(F$2,Inputs!$K$4:$AJ$4,0)))+SUMPRODUCT((Inputs!$C$5:$C$190=$B6)*Inputs!$D$5:$D$190*(((Inputs!$G$5:$G$190="moeda")+(Inputs!$G$5:$G$190="acoes"))*Inputs!$B$1+((Inputs!$G$5:$G$190<>"moeda")*(Inputs!$G$5:$G$190<>"acoes")))*INDEX(Inputs!$K$5:$AJ$190,0,MATCH(F$2,Inputs!$K$4:$AJ$4,0)))+SUMPRODUCT((Inputs!$E$5:$E$190=$B6)*Inputs!$F$5:$F$190*(((Inputs!$G$5:$G$190="moeda")+(Inputs!$G$5:$G$190="acoes"))*Inputs!$B$1+((Inputs!$G$5:$G$190<>"moeda")*(Inputs!$G$5:$G$190<>"acoes")))*INDEX(Inputs!$K$5:$AJ$190,0,MATCH(F$2,Inputs!$K$4:$AJ$4,0))))) -> -373.88874 | G6: =IF(ISNA(MATCH(G$2,Inputs!$K$4:$AJ$4,0)),NA(),IF(SUMPRODUCT((Inputs!$A$5:$A$190=$B6)*ISNUMBER(INDEX(Inputs!$K$5:$AJ$190,0,MATCH(G$2,Inputs!$K$4:$AJ$4,0))))+SUMPRODUCT((Inputs!$C$5:$C$190=$B6)*ISNUMBER(INDEX(Inputs!$K$5:$AJ$190,0,MATCH(G$2,Inputs!$K$4:$AJ$4,0))))+SUMPRODUCT((Inputs!$E$5:$E$190=$B6)*ISNUMBER(INDEX(Inputs!$K$5:$AJ$190,0,MATCH(G$2,Inputs!$K$4:$AJ$4,0))))=0,NA(),SUMPRODUCT((Inputs!$A$5:$A$190=$B6)*Inputs!$B$5:$B$190*(((Inputs!$G$5:$G$190="moeda")+(Inputs!$G$5:$G$190="acoes"))*Inputs!$B$1+((Inputs!$G$5:$G$190<>"moeda")*(Inputs!$G$5:$G$190<>"acoes")))*INDEX(Inputs!$K$5:$AJ$190,0,MATCH(G$2,Inputs!$K$4:$AJ$4,0)))+SUMPRODUCT((Inputs!$C$5:$C$190=$B6)*Inputs!$D$5:$D$190*(((Inputs!$G$5:$G$190="moeda")+(Inputs!$G$5:$G$190="acoes"))*Inputs!$B$1+((Inputs!$G$5:$G$190<>"moeda")*(Inputs!$G$5:$G$190<>"acoes")))*INDEX(Inputs!$K$5:$AJ$190,0,MATCH(G$2,Inputs!$K$4:$AJ$4,0)))+SUMPRODUCT((Inputs!$E$5:$E$190=$B6)*Inputs!$F$5:$F$190*(((Inputs!$G$5:$G$190="moeda")+(Inputs!$G$5:$G$190="acoes"))*Inputs!$B$1+((Inputs!$G$5:$G$190<>"moeda")*(Inputs!$G$5:$G$190<>"acoes")))*INDEX(Inputs!$K$5:$AJ$190,0,MATCH(G$2,Inputs!$K$4:$AJ$4,0))))) -> -415.25293 | H6: =SUM(D6:G6) -> -1353.354 | I6: =IF(ISNA(MATCH(I$2,Inputs!$K$4:$AJ$4,0)),NA(),IF(SUMPRODUCT((Inputs!$A$5:$A$190=$B6)*ISNUMBER(INDEX(Inputs!$K$5:$AJ$190,0,MATCH(I$2,Inputs!$K$4:$AJ$4,0))))+SUMPRODUCT((Inputs!$C$5:$C$190=$B6)*ISNUMBER(INDEX(Inputs!$K$5:$AJ$190,0,MATCH(I$2,Inputs!$K$4:$AJ$4,0))))+SUMPRODUCT((Inputs!$E$5:$E$190=$B6)*ISNUMBER(INDEX(Inputs!$K$5:$AJ$190,0,MATCH(I$2,Inputs!$K$4:$AJ$4,0))))=0,NA(),SUMPRODUCT((Inputs!$A$5:$A$190=$B6)*Inputs!$B$5:$B$190*(((Inputs!$G$5:$G$190="moeda")+(Inputs!$G$5:$G$190="acoes"))*Inputs!$B$1+((Inputs!$G$5:$G$190<>"moeda")*(Inputs!$G$5:$G$190<>"acoes")))*INDEX(Inputs!$K$5:$AJ$190,0,MATCH(I$2,Inputs!$K$4:$AJ$4,0)))+SUMPRODUCT((Inputs!$C$5:$C$190=$B6)*Inputs!$D$5:$D$190*(((Inputs!$G$5:$G$190="moeda")+(Inputs!$G$5:$G$190="acoes"))*Inputs!$B$1+((Inputs!$G$5:$G$190<>"moeda")*(Inputs!$G$5:$G$190<>"acoes")))*INDEX(Inputs!$K$5:$AJ$190,0,MATCH(I$2,Inputs!$K$4:$AJ$4,0)))+SUMPRODUCT((Inputs!$E$5:$E$190=$B6)*Inputs!$F$5:$F$190*(((Inputs!$G$5:$G$190="moeda")+(Inputs!$G$5:$G$190="acoes"))*Inputs!$B$1+((Inputs!$G$5:$G$190<>"moeda")*(Inputs!$G$5:$G$190<>"acoes")))*INDEX(Inputs!$K$5:$AJ$190,0,MATCH(I$2,Inputs!$K$4:$AJ$4,0))))) -> -441.278 | J6: =IF(ISNA(MATCH(J$2,Inputs!$K$4:$AJ$4,0)),NA(),IF(SUMPRODUCT((Inputs!$A$5:$A$190=$B6)*ISNUMBER(INDEX(Inputs!$K$5:$AJ$190,0,MATCH(J$2,Inputs!$K$4:$AJ$4,0))))+SUMPRODUCT((Inputs!$C$5:$C$190=$B6)*ISNUMBER(INDEX(Inputs!$K$5:$AJ$190,0,MATCH(J$2,Inputs!$K$4:$AJ$4,0))))+SUMPRODUCT((Inputs!$E$5:$E$190=$B6)*ISNUMBER(INDEX(Inputs!$K$5:$AJ$190,0,MATCH(J$2,Inputs!$K$4:$AJ$4,0))))=0,NA(),SUMPRODUCT((Inputs!$A$5:$A$190=$B6)*Inputs!$B$5:$B$190*(((Inputs!$G$5:$G$190="moeda")+(Inputs!$G$5:$G$190="acoes"))*Inputs!$B$1+((Inputs!$G$5:$G$190<>"moeda")*(Inputs!$G$5:$G$190<>"acoes")))*INDEX(Inputs!$K$5:$AJ$190,0,MATCH(J$2,Inputs!$K$4:$AJ$4,0)))+SUMPRODUCT((Inputs!$C$5:$C$190=$B6)*Inputs!$D$5:$D$190*(((Inputs!$G$5:$G$190="moeda")+(Inputs!$G$5:$G$190="acoes"))*Inputs!$B$1+((Inputs!$G$5:$G$190<>"moeda")*(Inputs!$G$5:$G$190<>"acoes")))*INDEX(Inputs!$K$5:$AJ$190,0,MATCH(J$2,Inputs!$K$4:$AJ$4,0)))+SUMPRODUCT((Inputs!$E$5:$E$190=$B6)*Inputs!$F$5:$F$190*(((Inputs!$G$5:$G$190="moeda")+(Inputs!$G$5:$G$190="acoes"))*Inputs!$B$1+((Inputs!$G$5:$G$190<>"moeda")*(Inputs!$G$5:$G$190<>"acoes")))*INDEX(Inputs!$K$5:$AJ$190,0,MATCH(J$2,Inputs!$K$4:$AJ$4,0))))) -> -512.662 | K6: =IF(ISNA(MATCH(K$2,Inputs!$K$4:$AJ$4,0)),NA(),IF(SUMPRODUCT((Inputs!$A$5:$A$190=$B6)*ISNUMBER(INDEX(Inputs!$K$5:$AJ$190,0,MATCH(K$2,Inputs!$K$4:$AJ$4,0))))+SUMPRODUCT((Inputs!$C$5:$C$190=$B6)*ISNUMBER(INDEX(Inputs!$K$5:$AJ$190,0,MATCH(K$2,Inputs!$K$4:$AJ$4,0))))+SUMPRODUCT((Inputs!$E$5:$E$190=$B6)*ISNUMBER(INDEX(Inputs!$K$5:$AJ$190,0,MATCH(K$2,Inputs!$K$4:$AJ$4,0))))=0,NA(),SUMPRODUCT((Inputs!$A$5:$A$190=$B6)*Inputs!$B$5:$B$190*(((Inputs!$G$5:$G$190="moeda")+(Inputs!$G$5:$G$190="acoes"))*Inputs!$B$1+((Inputs!$G$5:$G$190<>"moeda")*(Inputs!$G$5:$G$190<>"acoes")))*INDEX(Inputs!$K$5:$AJ$190,0,MATCH(K$2,Inputs!$K$4:$AJ$4,0)))+SUMPRODUCT((Inputs!$C$5:$C$190=$B6)*Inputs!$D$5:$D$190*(((Inputs!$G$5:$G$190="moeda")+(Inputs!$G$5:$G$190="acoes"))*Inputs!$B$1+((Inputs!$G$5:$G$190<>"moeda")*(Inputs!$G$5:$G$190<>"acoes")))*INDEX(Inputs!$K$5:$AJ$190,0,MATCH(K$2,Inputs!$K$4:$AJ$4,0)))+SUMPRODUCT((Inputs!$E$5:$E$190=$B6)*Inputs!$F$5:$F$190*(((Inputs!$G$5:$G$190="moeda")+(Inputs!$G$5:$G$190="acoes"))*Inputs!$B$1+((Inputs!$G$5:$G$190<>"moeda")*(Inputs!$G$5:$G$190<>"acoes")))*INDEX(Inputs!$K$5:$AJ$190,0,MATCH(K$2,Inputs!$K$4:$AJ$4,0))))) -> -645.0138 | L6: =IF(ISNA(MATCH(L$2,Inputs!$K$4:$AJ$4,0)),NA(),IF(SUMPRODUCT((Inputs!$A$5:$A$190=$B6)*ISNUMBER(INDEX(Inputs!$K$5:$AJ$190,0,MATCH(L$2,Inputs!$K$4:$AJ$4,0))))+SUMPRODUCT((Inputs!$C$5:$C$190=$B6)*ISNUMBER(INDEX(Inputs!$K$5:$AJ$190,0,MATCH(L$2,Inputs!$K$4:$AJ$4,0))))+SUMPRODUCT((Inputs!$E$5:$E$190=$B6)*ISNUMBER(INDEX(Inputs!$K$5:$AJ$190,0,MATCH(L$2,Inputs!$K$4:$AJ$4,0))))=0,NA(),SUMPRODUCT((Inputs!$A$5:$A$190=$B6)*Inputs!$B$5:$B$190*(((Inputs!$G$5:$G$190="moeda")+(Inputs!$G$5:$G$190="acoes"))*Inputs!$B$1+((Inputs!$G$5:$G$190<>"moeda")*(Inputs!$G$5:$G$190<>"acoes")))*INDEX(Inputs!$K$5:$AJ$190,0,MATCH(L$2,Inputs!$K$4:$AJ$4,0)))+SUMPRODUCT((Inputs!$C$5:$C$190=$B6)*Inputs!$D$5:$D$190*(((Inputs!$G$5:$G$190="moeda")+(Inputs!$G$5:$G$190="acoes"))*Inputs!$B$1+((Inputs!$G$5:$G$190<>"moeda")*(Inputs!$G$5:$G$190<>"acoes")))*INDEX(Inputs!$K$5:$AJ$190,0,MATCH(L$2,Inputs!$K$4:$AJ$4,0)))+SUMPRODUCT((Inputs!$E$5:$E$190=$B6)*Inputs!$F$5:$F$190*(((Inputs!$G$5:$G$190="moeda")+(Inputs!$G$5:$G$190="acoes"))*Inputs!$B$1+((Inputs!$G$5:$G$190<>"moeda")*(Inputs!$G$5:$G$190<>"acoes")))*INDEX(Inputs!$K$5:$AJ$190,0,MATCH(L$2,Inputs!$K$4:$AJ$4,0))))) -> -875.40069 | M6: =SUM(I6:L6) -> -2474.3545 | N6: =IF(ISNA(MATCH(N$2,Inputs!$K$4:$AJ$4,0)),NA(),IF(SUMPRODUCT((Inputs!$A$5:$A$190=$B6)*ISNUMBER(INDEX(Inputs!$K$5:$AJ$190,0,MATCH(N$2,Inputs!$K$4:$AJ$4,0))))+SUMPRODUCT((Inputs!$C$5:$C$190=$B6)*ISNUMBER(INDEX(Inputs!$K$5:$AJ$190,0,MATCH(N$2,Inputs!$K$4:$AJ$4,0))))+SUMPRODUCT((Inputs!$E$5:$E$190=$B6)*ISNUMBER(INDEX(Inputs!$K$5:$AJ$190,0,MATCH(N$2,Inputs!$K$4:$AJ$4,0))))=0,NA(),SUMPRODUCT((Inputs!$A$5:$A$190=$B6)*Inputs!$B$5:$B$190*(((Inputs!$G$5:$G$190="moeda")+(Inputs!$G$5:$G$190="acoes"))*Inputs!$B$1+((Inputs!$G$5:$G$190<>"moeda")*(Inputs!$G$5:$G$190<>"acoes")))*INDEX(Inputs!$K$5:$AJ$190,0,MATCH(N$2,Inputs!$K$4:$AJ$4,0)))+SUMPRODUCT((Inputs!$C$5:$C$190=$B6)*Inputs!$D$5:$D$190*(((Inputs!$G$5:$G$190="moeda")+(Inputs!$G$5:$G$190="acoes"))*Inputs!$B$1+((Inputs!$G$5:$G$190<>"moeda")*(Inputs!$G$5:$G$190<>"acoes")))*INDEX(Inputs!$K$5:$AJ$190,0,MATCH(N$2,Inputs!$K$4:$AJ$4,0)))+SUMPRODUCT((Inputs!$E$5:$E$190=$B6)*Inputs!$F$5:$F$190*(((Inputs!$G$5:$G$190="moeda")+(Inputs!$G$5:$G$190="acoes"))*Inputs!$B$1+((Inputs!$G$5:$G$190<>"moeda")*(Inputs!$G$5:$G$190<>"acoes")))*INDEX(Inputs!$K$5:$AJ$190,0,MATCH(N$2,Inputs!$K$4:$AJ$4,0))))) -> -816.41144 | O6: =IF(ISNA(MATCH(O$2,Inputs!$K$4:$AJ$4,0)),NA(),IF(SUMPRODUCT((Inputs!$A$5:$A$190=$B6)*ISNUMBER(INDEX(Inputs!$K$5:$AJ$190,0,MATCH(O$2,Inputs!$K$4:$AJ$4,0))))+SUMPRODUCT((Inputs!$C$5:$C$190=$B6)*ISNUMBER(INDEX(Inputs!$K$5:$AJ$190,0,MATCH(O$2,Inputs!$K$4:$AJ$4,0))))+SUMPRODUCT((Inputs!$E$5:$E$190=$B6)*ISNUMBER(INDEX(Inputs!$K$5:$AJ$190,0,MATCH(O$2,Inputs!$K$4:$AJ$4,0))))=0,NA(),SUMPRODUCT((Inputs!$A$5:$A$190=$B6)*Inputs!$B$5:$B$190*(((Inputs!$G$5:$G$190="moeda")+(Inputs!$G$5:$G$190="acoes"))*Inputs!$B$1+((Inputs!$G$5:$G$190<>"moeda")*(Inputs!$G$5:$G$190<>"acoes")))*INDEX(Inputs!$K$5:$AJ$190,0,MATCH(O$2,Inputs!$K$4:$AJ$4,0)))+SUMPRODUCT((Inputs!$C$5:$C$190=$B6)*Inputs!$D$5:$D$190*(((Inputs!$G$5:$G$190="moeda")+(Inputs!$G$5:$G$190="acoes"))*Inputs!$B$1+((Inputs!$G$5:$G$190<>"moeda")*(Inputs!$G$5:$G$190<>"acoes")))*INDEX(Inputs!$K$5:$AJ$190,0,MATCH(O$2,Inputs!$K$4:$AJ$4,0)))+SUMPRODUCT((Inputs!$E$5:$E$190=$B6)*Inputs!$F$5:$F$190*(((Inputs!$G$5:$G$190="moeda")+(Inputs!$G$5:$G$190="acoes"))*Inputs!$B$1+((Inputs!$G$5:$G$190<>"moeda")*(Inputs!$G$5:$G$190<>"acoes")))*INDEX(Inputs!$K$5:$AJ$190,0,MATCH(O$2,Inputs!$K$4:$AJ$4,0))))) -> -562.18007 | P6: =IF(ISNA(MATCH(P$2,Inputs!$K$4:$AJ$4,0)),NA(),IF(SUMPRODUCT((Inputs!$A$5:$A$190=$B6)*ISNUMBER(INDEX(Inputs!$K$5:$AJ$190,0,MATCH(P$2,Inputs!$K$4:$AJ$4,0))))+SUMPRODUCT((Inputs!$C$5:$C$190=$B6)*ISNUMBER(INDEX(Inputs!$K$5:$AJ$190,0,MATCH(P$2,Inputs!$K$4:$AJ$4,0))))+SUMPRODUCT((Inputs!$E$5:$E$190=$B6)*ISNUMBER(INDEX(Inputs!$K$5:$AJ$190,0,MATCH(P$2,Inputs!$K$4:$AJ$4,0))))=0,NA(),SUMPRODUCT((Inputs!$A$5:$A$190=$B6)*Inputs!$B$5:$B$190*(((Inputs!$G$5:$G$190="moeda")+(Inputs!$G$5:$G$190="acoes"))*Inputs!$B$1+((Inputs!$G$5:$G$190<>"moeda")*(Inputs!$G$5:$G$190<>"acoes")))*INDEX(Inputs!$K$5:$AJ$190,0,MATCH(P$2,Inputs!$K$4:$AJ$4,0)))+SUMPRODUCT((Inputs!$C$5:$C$190=$B6)*Inputs!$D$5:$D$190*(((Inputs!$G$5:$G$190="moeda")+(Inputs!$G$5:$G$190="acoes"))*Inputs!$B$1+((Inputs!$G$5:$G$190<>"moeda")*(Inputs!$G$5:$G$190<>"acoes")))*INDEX(Inputs!$K$5:$AJ$190,0,MATCH(P$2,Inputs!$K$4:$AJ$4,0)))+SUMPRODUCT((Inputs!$E$5:$E$190=$B6)*Inputs!$F$5:$F$190*(((Inputs!$G$5:$G$190="moeda")+(Inputs!$G$5:$G$190="acoes"))*Inputs!$B$1+((Inputs!$G$5:$G$190<>"moeda")*(Inputs!$G$5:$G$190<>"acoes")))*INDEX(Inputs!$K$5:$AJ$190,0,MATCH(P$2,Inputs!$K$4:$AJ$4,0))))) -> -854.69259 | Q6: =IF(ISNA(MATCH(Q$2,Inputs!$K$4:$AJ$4,0)),NA(),IF(SUMPRODUCT((Inputs!$A$5:$A$190=$B6)*ISNUMBER(INDEX(Inputs!$K$5:$AJ$190,0,MATCH(Q$2,Inputs!$K$4:$AJ$4,0))))+SUMPRODUCT((Inputs!$C$5:$C$190=$B6)*ISNUMBER(INDEX(Inputs!$K$5:$AJ$190,0,MATCH(Q$2,Inputs!$K$4:$AJ$4,0))))+SUMPRODUCT((Inputs!$E$5:$E$190=$B6)*ISNUMBER(INDEX(Inputs!$K$5:$AJ$190,0,MATCH(Q$2,Inputs!$K$4:$AJ$4,0))))=0,NA(),SUMPRODUCT((Inputs!$A$5:$A$190=$B6)*Inputs!$B$5:$B$190*(((Inputs!$G$5:$G$190="moeda")+(Inputs!$G$5:$G$190="acoes"))*Inputs!$B$1+((Inputs!$G$5:$G$190<>"moeda")*(Inputs!$G$5:$G$190<>"acoes")))*INDEX(Inputs!$K$5:$AJ$190,0,MATCH(Q$2,Inputs!$K$4:$AJ$4,0)))+SUMPRODUCT((Inputs!$C$5:$C$190=$B6)*Inputs!$D$5:$D$190*(((Inputs!$G$5:$G$190="moeda")+(Inputs!$G$5:$G$190="acoes"))*Inputs!$B$1+((Inputs!$G$5:$G$190<>"moeda")*(Inputs!$G$5:$G$190<>"acoes")))*INDEX(Inputs!$K$5:$AJ$190,0,MATCH(Q$2,Inputs!$K$4:$AJ$4,0)))+SUMPRODUCT((Inputs!$E$5:$E$190=$B6)*Inputs!$F$5:$F$190*(((Inputs!$G$5:$G$190="moeda")+(Inputs!$G$5:$G$190="acoes"))*Inputs!$B$1+((Inputs!$G$5:$G$190<>"moeda")*(Inputs!$G$5:$G$190<>"acoes")))*INDEX(Inputs!$K$5:$AJ$190,0,MATCH(Q$2,Inputs!$K$4:$AJ$4,0))))) -> -1045.8985 | R6: =SUM(N6:Q6) -> -3279.1826 | S6: =IF(ISNA(MATCH(S$2,Inputs!$K$4:$AJ$4,0)),NA(),IF(SUMPRODUCT((Inputs!$A$5:$A$190=$B6)*ISNUMBER(INDEX(Inputs!$K$5:$AJ$190,0,MATCH(S$2,Inputs!$K$4:$AJ$4,0))))+SUMPRODUCT((Inputs!$C$5:$C$190=$B6)*ISNUMBER(INDEX(Inputs!$K$5:$AJ$190,0,MATCH(S$2,Inputs!$K$4:$AJ$4,0))))+SUMPRODUCT((Inputs!$E$5:$E$190=$B6)*ISNUMBER(INDEX(Inputs!$K$5:$AJ$190,0,MATCH(S$2,Inputs!$K$4:$AJ$4,0))))=0,NA(),SUMPRODUCT((Inputs!$A$5:$A$190=$B6)*Inputs!$B$5:$B$190*(((Inputs!$G$5:$G$190="moeda")+(Inputs!$G$5:$G$190="acoes"))*Inputs!$B$1+((Inputs!$G$5:$G$190<>"moeda")*(Inputs!$G$5:$G$190<>"acoes")))*INDEX(Inputs!$K$5:$AJ$190,0,MATCH(S$2,Inputs!$K$4:$AJ$4,0)))+SUMPRODUCT((Inputs!$C$5:$C$190=$B6)*Inputs!$D$5:$D$190*(((Inputs!$G$5:$G$190="moeda")+(Inputs!$G$5:$G$190="acoes"))*Inputs!$B$1+((Inputs!$G$5:$G$190<>"moeda")*(Inputs!$G$5:$G$190<>"acoes")))*INDEX(Inputs!$K$5:$AJ$190,0,MATCH(S$2,Inputs!$K$4:$AJ$4,0)))+SUMPRODUCT((Inputs!$E$5:$E$190=$B6)*Inputs!$F$5:$F$190*(((Inputs!$G$5:$G$190="moeda")+(Inputs!$G$5:$G$190="acoes"))*Inputs!$B$1+((Inputs!$G$5:$G$190<>"moeda")*(Inputs!$G$5:$G$190<>"acoes")))*INDEX(Inputs!$K$5:$AJ$190,0,MATCH(S$2,Inputs!$K$4:$AJ$4,0))))) -> -904.42901 | T6: =IF(ISNA(MATCH(T$2,Inputs!$K$4:$AJ$4,0)),NA(),IF(SUMPRODUCT((Inputs!$A$5:$A$190=$B6)*ISNUMBER(INDEX(Inputs!$K$5:$AJ$190,0,MATCH(T$2,Inputs!$K$4:$AJ$4,0))))+SUMPRODUCT((Inputs!$C$5:$C$190=$B6)*ISNUMBER(INDEX(Inputs!$K$5:$AJ$190,0,MATCH(T$2,Inputs!$K$4:$AJ$4,0))))+SUMPRODUCT((Inputs!$E$5:$E$190=$B6)*ISNUMBER(INDEX(Inputs!$K$5:$AJ$190,0,MATCH(T$2,Inputs!$K$4:$AJ$4,0))))=0,NA(),SUMPRODUCT((Inputs!$A$5:$A$190=$B6)*Inputs!$B$5:$B$190*(((Inputs!$G$5:$G$190="moeda")+(Inputs!$G$5:$G$190="acoes"))*Inputs!$B$1+((Inputs!$G$5:$G$190<>"moeda")*(Inputs!$G$5:$G$190<>"acoes")))*INDEX(Inputs!$K$5:$AJ$190,0,MATCH(T$2,Inputs!$K$4:$AJ$4,0)))+SUMPRODUCT((Inputs!$C$5:$C$190=$B6)*Inputs!$D$5:$D$190*(((Inputs!$G$5:$G$190="moeda")+(Inputs!$G$5:$G$190="acoes"))*Inputs!$B$1+((Inputs!$G$5:$G$190<>"moeda")*(Inputs!$G$5:$G$190<>"acoes")))*INDEX(Inputs!$K$5:$AJ$190,0,MATCH(T$2,Inputs!$K$4:$AJ$4,0)))+SUMPRODUCT((Inputs!$E$5:$E$190=$B6)*Inputs!$F$5:$F$190*(((Inputs!$G$5:$G$190="moeda")+(Inputs!$G$5:$G$190="acoes"))*Inputs!$B$1+((Inputs!$G$5:$G$190<>"moeda")*(Inputs!$G$5:$G$190<>"acoes")))*INDEX(Inputs!$K$5:$AJ$190,0,MATCH(T$2,Inputs!$K$4:$AJ$4,0))))) -> -878.6871 | U6: =IF(ISNA(MATCH(U$2,Inputs!$K$4:$AJ$4,0)),NA(),IF(SUMPRODUCT((Inputs!$A$5:$A$190=$B6)*ISNUMBER(INDEX(Inputs!$K$5:$AJ$190,0,MATCH(U$2,Inputs!$K$4:$AJ$4,0))))+SUMPRODUCT((Inputs!$C$5:$C$190=$B6)*ISNUMBER(INDEX(Inputs!$K$5:$AJ$190,0,MATCH(U$2,Inputs!$K$4:$AJ$4,0))))+SUMPRODUCT((Inputs!$E$5:$E$190=$B6)*ISNUMBER(INDEX(Inputs!$K$5:$AJ$190,0,MATCH(U$2,Inputs!$K$4:$AJ$4,0))))=0,NA(),SUMPRODUCT((Inputs!$A$5:$A$190=$B6)*Inputs!$B$5:$B$190*(((Inputs!$G$5:$G$190="moeda")+(Inputs!$G$5:$G$190="acoes"))*Inputs!$B$1+((Inputs!$G$5:$G$190<>"moeda")*(Inputs!$G$5:$G$190<>"acoes")))*INDEX(Inputs!$K$5:$AJ$190,0,MATCH(U$2,Inputs!$K$4:$AJ$4,0)))+SUMPRODUCT((Inputs!$C$5:$C$190=$B6)*Inputs!$D$5:$D$190*(((Inputs!$G$5:$G$190="moeda")+(Inputs!$G$5:$G$190="acoes"))*Inputs!$B$1+((Inputs!$G$5:$G$190<>"moeda")*(Inputs!$G$5:$G$190<>"acoes")))*INDEX(Inputs!$K$5:$AJ$190,0,MATCH(U$2,Inputs!$K$4:$AJ$4,0)))+SUMPRODUCT((Inputs!$E$5:$E$190=$B6)*Inputs!$F$5:$F$190*(((Inputs!$G$5:$G$190="moeda")+(Inputs!$G$5:$G$190="acoes"))*Inputs!$B$1+((Inputs!$G$5:$G$190<>"moeda")*(Inputs!$G$5:$G$190<>"acoes")))*INDEX(Inputs!$K$5:$AJ$190,0,MATCH(U$2,Inputs!$K$4:$AJ$4,0))))) -> -997.19909 | V6: =IF(ISNA(MATCH(V$2,Inputs!$K$4:$AJ$4,0)),NA(),IF(SUMPRODUCT((Inputs!$A$5:$A$190=$B6)*ISNUMBER(INDEX(Inputs!$K$5:$AJ$190,0,MATCH(V$2,Inputs!$K$4:$AJ$4,0))))+SUMPRODUCT((Inputs!$C$5:$C$190=$B6)*ISNUMBER(INDEX(Inputs!$K$5:$AJ$190,0,MATCH(V$2,Inputs!$K$4:$AJ$4,0))))+SUMPRODUCT((Inputs!$E$5:$E$190=$B6)*ISNUMBER(INDEX(Inputs!$K$5:$AJ$190,0,MATCH(V$2,Inputs!$K$4:$AJ$4,0))))=0,NA(),SUMPRODUCT((Inputs!$A$5:$A$190=$B6)*Inputs!$B$5:$B$190*(((Inputs!$G$5:$G$190="moeda")+(Inputs!$G$5:$G$190="acoes"))*Inputs!$B$1+((Inputs!$G$5:$G$190<>"moeda")*(Inputs!$G$5:$G$190<>"acoes")))*INDEX(Inputs!$K$5:$AJ$190,0,MATCH(V$2,Inputs!$K$4:$AJ$4,0)))+SUMPRODUCT((Inputs!$C$5:$C$190=$B6)*Inputs!$D$5:$D$190*(((Inputs!$G$5:$G$190="moeda")+(Inputs!$G$5:$G$190="acoes"))*Inputs!$B$1+((Inputs!$G$5:$G$190<>"moeda")*(Inputs!$G$5:$G$190<>"acoes")))*INDEX(Inputs!$K$5:$AJ$190,0,MATCH(V$2,Inputs!$K$4:$AJ$4,0)))+SUMPRODUCT((Inputs!$E$5:$E$190=$B6)*Inputs!$F$5:$F$190*(((Inputs!$G$5:$G$190="moeda")+(Inputs!$G$5:$G$190="acoes"))*Inputs!$B$1+((Inputs!$G$5:$G$190<>"moeda")*(Inputs!$G$5:$G$190<>"acoes")))*INDEX(Inputs!$K$5:$AJ$190,0,MATCH(V$2,Inputs!$K$4:$AJ$4,0))))) -> -1065.8708 | W6: =SUM(S6:V6) -> -3846.186 | X6: =IF(ISNA(MATCH(X$2,Inputs!$K$4:$AJ$4,0)),NA(),IF(SUMPRODUCT((Inputs!$A$5:$A$190=$B6)*ISNUMBER(INDEX(Inputs!$K$5:$AJ$190,0,MATCH(X$2,Inputs!$K$4:$AJ$4,0))))+SUMPRODUCT((Inputs!$C$5:$C$190=$B6)*ISNUMBER(INDEX(Inputs!$K$5:$AJ$190,0,MATCH(X$2,Inputs!$K$4:$AJ$4,0))))+SUMPRODUCT((Inputs!$E$5:$E$190=$B6)*ISNUMBER(INDEX(Inputs!$K$5:$AJ$190,0,MATCH(X$2,Inputs!$K$4:$AJ$4,0))))=0,NA(),SUMPRODUCT((Inputs!$A$5:$A$190=$B6)*Inputs!$B$5:$B$190*(((Inputs!$G$5:$G$190="moeda")+(Inputs!$G$5:$G$190="acoes"))*Inputs!$B$1+((Inputs!$G$5:$G$190<>"moeda")*(Inputs!$G$5:$G$190<>"acoes")))*INDEX(Inputs!$K$5:$AJ$190,0,MATCH(X$2,Inputs!$K$4:$AJ$4,0)))+SUMPRODUCT((Inputs!$C$5:$C$190=$B6)*Inputs!$D$5:$D$190*(((Inputs!$G$5:$G$190="moeda")+(Inputs!$G$5:$G$190="acoes"))*Inputs!$B$1+((Inputs!$G$5:$G$190<>"moeda")*(Inputs!$G$5:$G$190<>"acoes")))*INDEX(Inputs!$K$5:$AJ$190,0,MATCH(X$2,Inputs!$K$4:$AJ$4,0)))+SUMPRODUCT((Inputs!$E$5:$E$190=$B6)*Inputs!$F$5:$F$190*(((Inputs!$G$5:$G$190="moeda")+(Inputs!$G$5:$G$190="acoes"))*Inputs!$B$1+((Inputs!$G$5:$G$190<>"moeda")*(Inputs!$G$5:$G$190<>"acoes")))*INDEX(Inputs!$K$5:$AJ$190,0,MATCH(X$2,Inputs!$K$4:$AJ$4,0))))) -> -944.98508 | Y6: =IF(ISNA(MATCH(Y$2,Inputs!$K$4:$AJ$4,0)),NA(),IF(SUMPRODUCT((Inputs!$A$5:$A$190=$B6)*ISNUMBER(INDEX(Inputs!$K$5:$AJ$190,0,MATCH(Y$2,Inputs!$K$4:$AJ$4,0))))+SUMPRODUCT((Inputs!$C$5:$C$190=$B6)*ISNUMBER(INDEX(Inputs!$K$5:$AJ$190,0,MATCH(Y$2,Inputs!$K$4:$AJ$4,0))))+SUMPRODUCT((Inputs!$E$5:$E$190=$B6)*ISNUMBER(INDEX(Inputs!$K$5:$AJ$190,0,MATCH(Y$2,Inputs!$K$4:$AJ$4,0))))=0,NA(),SUMPRODUCT((Inputs!$A$5:$A$190=$B6)*Inputs!$B$5:$B$190*(((Inputs!$G$5:$G$190="moeda")+(Inputs!$G$5:$G$190="acoes"))*Inputs!$B$1+((Inputs!$G$5:$G$190<>"moeda")*(Inputs!$G$5:$G$190<>"acoes")))*INDEX(Inputs!$K$5:$AJ$190,0,MATCH(Y$2,Inputs!$K$4:$AJ$4,0)))+SUMPRODUCT((Inputs!$C$5:$C$190=$B6)*Inputs!$D$5:$D$190*(((Inputs!$G$5:$G$190="moeda")+(Inputs!$G$5:$G$190="acoes"))*Inputs!$B$1+((Inputs!$G$5:$G$190<>"moeda")*(Inputs!$G$5:$G$190<>"acoes")))*INDEX(Inputs!$K$5:$AJ$190,0,MATCH(Y$2,Inputs!$K$4:$AJ$4,0)))+SUMPRODUCT((Inputs!$E$5:$E$190=$B6)*Inputs!$F$5:$F$190*(((Inputs!$G$5:$G$190="moeda")+(Inputs!$G$5:$G$190="acoes"))*Inputs!$B$1+((Inputs!$G$5:$G$190<>"moeda")*(Inputs!$G$5:$G$190<>"acoes")))*INDEX(Inputs!$K$5:$AJ$190,0,MATCH(Y$2,Inputs!$K$4:$AJ$4,0))))) -> -973.05747 | Z6: =IF(ISNA(MATCH(Z$2,Inputs!$K$4:$AJ$4,0)),NA(),IF(SUMPRODUCT((Inputs!$A$5:$A$190=$B6)*ISNUMBER(INDEX(Inputs!$K$5:$AJ$190,0,MATCH(Z$2,Inputs!$K$4:$AJ$4,0))))+SUMPRODUCT((Inputs!$C$5:$C$190=$B6)*ISNUMBER(INDEX(Inputs!$K$5:$AJ$190,0,MATCH(Z$2,Inputs!$K$4:$AJ$4,0))))+SUMPRODUCT((Inputs!$E$5:$E$190=$B6)*ISNUMBER(INDEX(Inputs!$K$5:$AJ$190,0,MATCH(Z$2,Inputs!$K$4:$AJ$4,0))))=0,NA(),SUMPRODUCT((Inputs!$A$5:$A$190=$B6)*Inputs!$B$5:$B$190*(((Inputs!$G$5:$G$190="moeda")+(Inputs!$G$5:$G$190="acoes"))*Inputs!$B$1+((Inputs!$G$5:$G$190<>"moeda")*(Inputs!$G$5:$G$190<>"acoes")))*INDEX(Inputs!$K$5:$AJ$190,0,MATCH(Z$2,Inputs!$K$4:$AJ$4,0)))+SUMPRODUCT((Inputs!$C$5:$C$190=$B6)*Inputs!$D$5:$D$190*(((Inputs!$G$5:$G$190="moeda")+(Inputs!$G$5:$G$190="acoes"))*Inputs!$B$1+((Inputs!$G$5:$G$190<>"moeda")*(Inputs!$G$5:$G$190<>"acoes")))*INDEX(Inputs!$K$5:$AJ$190,0,MATCH(Z$2,Inputs!$K$4:$AJ$4,0)))+SUMPRODUCT((Inputs!$E$5:$E$190=$B6)*Inputs!$F$5:$F$190*(((Inputs!$G$5:$G$190="moeda")+(Inputs!$G$5:$G$190="acoes"))*Inputs!$B$1+((Inputs!$G$5:$G$190<>"moeda")*(Inputs!$G$5:$G$190<>"acoes")))*INDEX(Inputs!$K$5:$AJ$190,0,MATCH(Z$2,Inputs!$K$4:$AJ$4,0))))) -> -1153.5383 | AA6: =IF(ISNA(MATCH(AA$2,Inputs!$K$4:$AJ$4,0)),NA(),IF(SUMPRODUCT((Inputs!$A$5:$A$190=$B6)*ISNUMBER(INDEX(Inputs!$K$5:$AJ$190,0,MATCH(AA$2,Inputs!$K$4:$AJ$4,0))))+SUMPRODUCT((Inputs!$C$5:$C$190=$B6)*ISNUMBER(INDEX(Inputs!$K$5:$AJ$190,0,MATCH(AA$2,Inputs!$K$4:$AJ$4,0))))+SUMPRODUCT((Inputs!$E$5:$E$190=$B6)*ISNUMBER(INDEX(Inputs!$K$5:$AJ$190,0,MATCH(AA$2,Inputs!$K$4:$AJ$4,0))))=0,NA(),SUMPRODUCT((Inputs!$A$5:$A$190=$B6)*Inputs!$B$5:$B$190*(((Inputs!$G$5:$G$190="moeda")+(Inputs!$G$5:$G$190="acoes"))*Inputs!$B$1+((Inputs!$G$5:$G$190<>"moeda")*(Inputs!$G$5:$G$190<>"acoes")))*INDEX(Inputs!$K$5:$AJ$190,0,MATCH(AA$2,Inputs!$K$4:$AJ$4,0)))+SUMPRODUCT((Inputs!$C$5:$C$190=$B6)*Inputs!$D$5:$D$190*(((Inputs!$G$5:$G$190="moeda")+(Inputs!$G$5:$G$190="acoes"))*Inputs!$B$1+((Inputs!$G$5:$G$190<>"moeda")*(Inputs!$G$5:$G$190<>"acoes")))*INDEX(Inputs!$K$5:$AJ$190,0,MATCH(AA$2,Inputs!$K$4:$AJ$4,0)))+SUMPRODUCT((Inputs!$E$5:$E$190=$B6)*Inputs!$F$5:$F$190*(((Inputs!$G$5:$G$190="moeda")+(Inputs!$G$5:$G$190="acoes"))*Inputs!$B$1+((Inputs!$G$5:$G$190<>"moeda")*(Inputs!$G$5:$G$190<>"acoes")))*INDEX(Inputs!$K$5:$AJ$190,0,MATCH(AA$2,Inputs!$K$4:$AJ$4,0))))) -> -83.961485 | AB6: =SUM(X6:AA6) -> -3155.5423 | AC6: =IF(ISNA(MATCH(AC$2,Inputs!$K$4:$AJ$4,0)),NA(),IF(SUMPRODUCT((Inputs!$A$5:$A$190=$B6)*ISNUMBER(INDEX(Inputs!$K$5:$AJ$190,0,MATCH(AC$2,Inputs!$K$4:$AJ$4,0))))+SUMPRODUCT((Inputs!$C$5:$C$190=$B6)*ISNUMBER(INDEX(Inputs!$K$5:$AJ$190,0,MATCH(AC$2,Inputs!$K$4:$AJ$4,0))))+SUMPRODUCT((Inputs!$E$5:$E$190=$B6)*ISNUMBER(INDEX(Inputs!$K$5:$AJ$190,0,MATCH(AC$2,Inputs!$K$4:$AJ$4,0))))=0,NA(),SUMPRODUCT((Inputs!$A$5:$A$190=$B6)*Inputs!$B$5:$B$190*(((Inputs!$G$5:$G$190="moeda")+(Inputs!$G$5:$G$190="acoes"))*Inputs!$B$1+((Inputs!$G$5:$G$190<>"moeda")*(Inputs!$G$5:$G$190<>"acoes")))*INDEX(Inputs!$K$5:$AJ$190,0,MATCH(AC$2,Inputs!$K$4:$AJ$4,0)))+SUMPRODUCT((Inputs!$C$5:$C$190=$B6)*Inputs!$D$5:$D$190*(((Inputs!$G$5:$G$190="moeda")+(Inputs!$G$5:$G$190="acoes"))*Inputs!$B$1+((Inputs!$G$5:$G$190<>"moeda")*(Inputs!$G$5:$G$190<>"acoes")))*INDEX(Inputs!$K$5:$AJ$190,0,MATCH(AC$2,Inputs!$K$4:$AJ$4,0)))+SUMPRODUCT((Inputs!$E$5:$E$190=$B6)*Inputs!$F$5:$F$190*(((Inputs!$G$5:$G$190="moeda")+(Inputs!$G$5:$G$190="acoes"))*Inputs!$B$1+((Inputs!$G$5:$G$190<>"moeda")*(Inputs!$G$5:$G$190<>"acoes")))*INDEX(Inputs!$K$5:$AJ$190,0,MATCH(AC$2,Inputs!$K$4:$AJ$4,0))))) -> -1175.0533 | AD6: =IF(ISNA(MATCH(AD$2,Inputs!$K$4:$AJ$4,0)),NA(),IF(SUMPRODUCT((Inputs!$A$5:$A$190=$B6)*ISNUMBER(INDEX(Inputs!$K$5:$AJ$190,0,MATCH(AD$2,Inputs!$K$4:$AJ$4,0))))+SUMPRODUCT((Inputs!$C$5:$C$190=$B6)*ISNUMBER(INDEX(Inputs!$K$5:$AJ$190,0,MATCH(AD$2,Inputs!$K$4:$AJ$4,0))))+SUMPRODUCT((Inputs!$E$5:$E$190=$B6)*ISNUMBER(INDEX(Inputs!$K$5:$AJ$190,0,MATCH(AD$2,Inputs!$K$4:$AJ$4,0))))=0,NA(),SUMPRODUCT((Inputs!$A$5:$A$190=$B6)*Inputs!$B$5:$B$190*(((Inputs!$G$5:$G$190="moeda")+(Inputs!$G$5:$G$190="acoes"))*Inputs!$B$1+((Inputs!$G$5:$G$190<>"moeda")*(Inputs!$G$5:$G$190<>"acoes")))*INDEX(Inputs!$K$5:$AJ$190,0,MATCH(AD$2,Inputs!$K$4:$AJ$4,0)))+SUMPRODUCT((Inputs!$C$5:$C$190=$B6)*Inputs!$D$5:$D$190*(((Inputs!$G$5:$G$190="moeda")+(Inputs!$G$5:$G$190="acoes"))*Inputs!$B$1+((Inputs!$G$5:$G$190<>"moeda")*(Inputs!$G$5:$G$190<>"acoes")))*INDEX(Inputs!$K$5:$AJ$190,0,MATCH(AD$2,Inputs!$K$4:$AJ$4,0)))+SUMPRODUCT((Inputs!$E$5:$E$190=$B6)*Inputs!$F$5:$F$190*(((Inputs!$G$5:$G$190="moeda")+(Inputs!$G$5:$G$190="acoes"))*Inputs!$B$1+((Inputs!$G$5:$G$190<>"moeda")*(Inputs!$G$5:$G$190<>"acoes")))*INDEX(Inputs!$K$5:$AJ$190,0,MATCH(AD$2,Inputs!$K$4:$AJ$4,0))))) -> -1082.9869 | AE6: =IF(ISNA(MATCH(AE$2,Inputs!$K$4:$AJ$4,0)),NA(),IF(SUMPRODUCT((Inputs!$A$5:$A$190=$B6)*ISNUMBER(INDEX(Inputs!$K$5:$AJ$190,0,MATCH(AE$2,Inputs!$K$4:$AJ$4,0))))+SUMPRODUCT((Inputs!$C$5:$C$190=$B6)*ISNUMBER(INDEX(Inputs!$K$5:$AJ$190,0,MATCH(AE$2,Inputs!$K$4:$AJ$4,0))))+SUMPRODUCT((Inputs!$E$5:$E$190=$B6)*ISNUMBER(INDEX(Inputs!$K$5:$AJ$190,0,MATCH(AE$2,Inputs!$K$4:$AJ$4,0))))=0,NA(),SUMPRODUCT((Inputs!$A$5:$A$190=$B6)*Inputs!$B$5:$B$190*(((Inputs!$G$5:$G$190="moeda")+(Inputs!$G$5:$G$190="acoes"))*Inputs!$B$1+((Inputs!$G$5:$G$190<>"moeda")*(Inputs!$G$5:$G$190<>"acoes")))*INDEX(Inputs!$K$5:$AJ$190,0,MATCH(AE$2,Inputs!$K$4:$AJ$4,0)))+SUMPRODUCT((Inputs!$C$5:$C$190=$B6)*Inputs!$D$5:$D$190*(((Inputs!$G$5:$G$190="moeda")+(Inputs!$G$5:$G$190="acoes"))*Inputs!$B$1+((Inputs!$G$5:$G$190<>"moeda")*(Inputs!$G$5:$G$190<>"acoes")))*INDEX(Inputs!$K$5:$AJ$190,0,MATCH(AE$2,Inputs!$K$4:$AJ$4,0)))+SUMPRODUCT((Inputs!$E$5:$E$190=$B6)*Inputs!$F$5:$F$190*(((Inputs!$G$5:$G$190="moeda")+(Inputs!$G$5:$G$190="acoes"))*Inputs!$B$1+((Inputs!$G$5:$G$190<>"moeda")*(Inputs!$G$5:$G$190<>"acoes")))*INDEX(Inputs!$K$5:$AJ$190,0,MATCH(AE$2,Inputs!$K$4:$AJ$4,0))))) -> #N/A | AF6: =IF(ISNA(MATCH(AF$2,Inputs!$K$4:$AJ$4,0)),NA(),IF(SUMPRODUCT((Inputs!$A$5:$A$190=$B6)*ISNUMBER(INDEX(Inputs!$K$5:$AJ$190,0,MATCH(AF$2,Inputs!$K$4:$AJ$4,0))))+SUMPRODUCT((Inputs!$C$5:$C$190=$B6)*ISNUMBER(INDEX(Inputs!$K$5:$AJ$190,0,MATCH(AF$2,Inputs!$K$4:$AJ$4,0))))+SUMPRODUCT((Inputs!$E$5:$E$190=$B6)*ISNUMBER(INDEX(Inputs!$K$5:$AJ$190,0,MATCH(AF$2,Inputs!$K$4:$AJ$4,0))))=0,NA(),SUMPRODUCT((Inputs!$A$5:$A$190=$B6)*Inputs!$B$5:$B$190*(((Inputs!$G$5:$G$190="moeda")+(Inputs!$G$5:$G$190="acoes"))*Inputs!$B$1+((Inputs!$G$5:$G$190<>"moeda")*(Inputs!$G$5:$G$190<>"acoes")))*INDEX(Inputs!$K$5:$AJ$190,0,MATCH(AF$2,Inputs!$K$4:$AJ$4,0)))+SUMPRODUCT((Inputs!$C$5:$C$190=$B6)*Inputs!$D$5:$D$190*(((Inputs!$G$5:$G$190="moeda")+(Inputs!$G$5:$G$190="acoes"))*Inputs!$B$1+((Inputs!$G$5:$G$190<>"moeda")*(Inputs!$G$5:$G$190<>"acoes")))*INDEX(Inputs!$K$5:$AJ$190,0,MATCH(AF$2,Inputs!$K$4:$AJ$4,0)))+SUMPRODUCT((Inputs!$E$5:$E$190=$B6)*Inputs!$F$5:$F$190*(((Inputs!$G$5:$G$190="moeda")+(Inputs!$G$5:$G$190="acoes"))*Inputs!$B$1+((Inputs!$G$5:$G$190<>"moeda")*(Inputs!$G$5:$G$190<>"acoes")))*INDEX(Inputs!$K$5:$AJ$190,0,MATCH(AF$2,Inputs!$K$4:$AJ$4,0))))) -> #N/A | AG6: =SUM(AC6:AF6) -> #N/A | AH6: =IF(ISNA(MATCH(AH$2,Inputs!$K$4:$AJ$4,0)),NA(),IF(SUMPRODUCT((Inputs!$A$5:$A$190=$B6)*ISNUMBER(INDEX(Inputs!$K$5:$AJ$190,0,MATCH(AH$2,Inputs!$K$4:$AJ$4,0))))+SUMPRODUCT((Inputs!$C$5:$C$190=$B6)*ISNUMBER(INDEX(Inputs!$K$5:$AJ$190,0,MATCH(AH$2,Inputs!$K$4:$AJ$4,0))))+SUMPRODUCT((Inputs!$E$5:$E$190=$B6)*ISNUMBER(INDEX(Inputs!$K$5:$AJ$190,0,MATCH(AH$2,Inputs!$K$4:$AJ$4,0))))=0,NA(),SUMPRODUCT((Inputs!$A$5:$A$190=$B6)*Inputs!$B$5:$B$190*(((Inputs!$G$5:$G$190="moeda")+(Inputs!$G$5:$G$190="acoes"))*Inputs!$B$1+((Inputs!$G$5:$G$190<>"moeda")*(Inputs!$G$5:$G$190<>"acoes")))*INDEX(Inputs!$K$5:$AJ$190,0,MATCH(AH$2,Inputs!$K$4:$AJ$4,0)))+SUMPRODUCT((Inputs!$C$5:$C$190=$B6)*Inputs!$D$5:$D$190*(((Inputs!$G$5:$G$190="moeda")+(Inputs!$G$5:$G$190="acoes"))*Inputs!$B$1+((Inputs!$G$5:$G$190<>"moeda")*(Inputs!$G$5:$G$190<>"acoes")))*INDEX(Inputs!$K$5:$AJ$190,0,MATCH(AH$2,Inputs!$K$4:$AJ$4,0)))+SUMPRODUCT((Inputs!$E$5:$E$190=$B6)*Inputs!$F$5:$F$190*(((Inputs!$G$5:$G$190="moeda")+(Inputs!$G$5:$G$190="acoes"))*Inputs!$B$1+((Inputs!$G$5:$G$190<>"moeda")*(Inputs!$G$5:$G$190<>"acoes")))*INDEX(Inputs!$K$5:$AJ$190,0,MATCH(AH$2,Inputs!$K$4:$AJ$4,0))))) -> -425.28034 | AI6: =IF(ISNA(MATCH(AI$2,Inputs!$K$4:$AJ$4,0)),NA(),IF(SUMPRODUCT((Inputs!$A$5:$A$190=$B6)*ISNUMBER(INDEX(Inputs!$K$5:$AJ$190,0,MATCH(AI$2,Inputs!$K$4:$AJ$4,0))))+SUMPRODUCT((Inputs!$C$5:$C$190=$B6)*ISNUMBER(INDEX(Inputs!$K$5:$AJ$190,0,MATCH(AI$2,Inputs!$K$4:$AJ$4,0))))+SUMPRODUCT((Inputs!$E$5:$E$190=$B6)*ISNUMBER(INDEX(Inputs!$K$5:$AJ$190,0,MATCH(AI$2,Inputs!$K$4:$AJ$4,0))))=0,NA(),SUMPRODUCT((Inputs!$A$5:$A$190=$B6)*Inputs!$B$5:$B$190*(((Inputs!$G$5:$G$190="moeda")+(Inputs!$G$5:$G$190="acoes"))*Inputs!$B$1+((Inputs!$G$5:$G$190<>"moeda")*(Inputs!$G$5:$G$190<>"acoes")))*INDEX(Inputs!$K$5:$AJ$190,0,MATCH(AI$2,Inputs!$K$4:$AJ$4,0)))+SUMPRODUCT((Inputs!$C$5:$C$190=$B6)*Inputs!$D$5:$D$190*(((Inputs!$G$5:$G$190="moeda")+(Inputs!$G$5:$G$190="acoes"))*Inputs!$B$1+((Inputs!$G$5:$G$190<>"moeda")*(Inputs!$G$5:$G$190<>"acoes")))*INDEX(Inputs!$K$5:$AJ$190,0,MATCH(AI$2,Inputs!$K$4:$AJ$4,0)))+SUMPRODUCT((Inputs!$E$5:$E$190=$B6)*Inputs!$F$5:$F$190*(((Inputs!$G$5:$G$190="moeda")+(Inputs!$G$5:$G$190="acoes"))*Inputs!$B$1+((Inputs!$G$5:$G$190<>"moeda")*(Inputs!$G$5:$G$190<>"acoes")))*INDEX(Inputs!$K$5:$AJ$190,0,MATCH(AI$2,Inputs!$K$4:$AJ$4,0))))) -> -195.00783 | AJ6: =IF(ISNA(MATCH(AJ$2,Inputs!$K$4:$AJ$4,0)),NA(),IF(SUMPRODUCT((Inputs!$A$5:$A$190=$B6)*ISNUMBER(INDEX(Inputs!$K$5:$AJ$190,0,MATCH(AJ$2,Inputs!$K$4:$AJ$4,0))))+SUMPRODUCT((Inputs!$C$5:$C$190=$B6)*ISNUMBER(INDEX(Inputs!$K$5:$AJ$190,0,MATCH(AJ$2,Inputs!$K$4:$AJ$4,0))))+SUMPRODUCT((Inputs!$E$5:$E$190=$B6)*ISNUMBER(INDEX(Inputs!$K$5:$AJ$190,0,MATCH(AJ$2,Inputs!$K$4:$AJ$4,0))))=0,NA(),SUMPRODUCT((Inputs!$A$5:$A$190=$B6)*Inputs!$B$5:$B$190*(((Inputs!$G$5:$G$190="moeda")+(Inputs!$G$5:$G$190="acoes"))*Inputs!$B$1+((Inputs!$G$5:$G$190<>"moeda")*(Inputs!$G$5:$G$190<>"acoes")))*INDEX(Inputs!$K$5:$AJ$190,0,MATCH(AJ$2,Inputs!$K$4:$AJ$4,0)))+SUMPRODUCT((Inputs!$C$5:$C$190=$B6)*Inputs!$D$5:$D$190*(((Inputs!$G$5:$G$190="moeda")+(Inputs!$G$5:$G$190="acoes"))*Inputs!$B$1+((Inputs!$G$5:$G$190<>"moeda")*(Inputs!$G$5:$G$190<>"acoes")))*INDEX(Inputs!$K$5:$AJ$190,0,MATCH(AJ$2,Inputs!$K$4:$AJ$4,0)))+SUMPRODUCT((Inputs!$E$5:$E$190=$B6)*Inputs!$F$5:$F$190*(((Inputs!$G$5:$G$190="moeda")+(Inputs!$G$5:$G$190="acoes"))*Inputs!$B$1+((Inputs!$G$5:$G$190<>"moeda")*(Inputs!$G$5:$G$190<>"acoes")))*INDEX(Inputs!$K$5:$AJ$190,0,MATCH(AJ$2,Inputs!$K$4:$AJ$4,0))))) -> -242.92893 | AK6: =IF(ISNA(MATCH(AK$2,Inputs!$K$4:$AJ$4,0)),NA(),IF(SUMPRODUCT((Inputs!$A$5:$A$190=$B6)*ISNUMBER(INDEX(Inputs!$K$5:$AJ$190,0,MATCH(AK$2,Inputs!$K$4:$AJ$4,0))))+SUMPRODUCT((Inputs!$C$5:$C$190=$B6)*ISNUMBER(INDEX(Inputs!$K$5:$AJ$190,0,MATCH(AK$2,Inputs!$K$4:$AJ$4,0))))+SUMPRODUCT((Inputs!$E$5:$E$190=$B6)*ISNUMBER(INDEX(Inputs!$K$5:$AJ$190,0,MATCH(AK$2,Inputs!$K$4:$AJ$4,0))))=0,NA(),SUMPRODUCT((Inputs!$A$5:$A$190=$B6)*Inputs!$B$5:$B$190*(((Inputs!$G$5:$G$190="moeda")+(Inputs!$G$5:$G$190="acoes"))*Inputs!$B$1+((Inputs!$G$5:$G$190<>"moeda")*(Inputs!$G$5:$G$190<>"acoes")))*INDEX(Inputs!$K$5:$AJ$190,0,MATCH(AK$2,Inputs!$K$4:$AJ$4,0)))+SUMPRODUCT((Inputs!$C$5:$C$190=$B6)*Inputs!$D$5:$D$190*(((Inputs!$G$5:$G$190="moeda")+(Inputs!$G$5:$G$190="acoes"))*Inputs!$B$1+((Inputs!$G$5:$G$190<>"moeda")*(Inputs!$G$5:$G$190<>"acoes")))*INDEX(Inputs!$K$5:$AJ$190,0,MATCH(AK$2,Inputs!$K$4:$AJ$4,0)))+SUMPRODUCT((Inputs!$E$5:$E$190=$B6)*Inputs!$F$5:$F$190*(((Inputs!$G$5:$G$190="moeda")+(Inputs!$G$5:$G$190="acoes"))*Inputs!$B$1+((Inputs!$G$5:$G$190<>"moeda")*(Inputs!$G$5:$G$190<>"acoes")))*INDEX(Inputs!$K$5:$AJ$190,0,MATCH(AK$2,Inputs!$K$4:$AJ$4,0))))) -> -94.441084 | AL6: =SUM(AH6:AK6) -> -957.65819
B7: 4 | C7: D&A | D7: =IF(ISNA(MATCH(D$2,Inputs!$K$4:$AJ$4,0)),NA(),IF(SUMPRODUCT((Inputs!$A$5:$A$190=$B7)*ISNUMBER(INDEX(Inputs!$K$5:$AJ$190,0,MATCH(D$2,Inputs!$K$4:$AJ$4,0))))+SUMPRODUCT((Inputs!$C$5:$C$190=$B7)*ISNUMBER(INDEX(Inputs!$K$5:$AJ$190,0,MATCH(D$2,Inputs!$K$4:$AJ$4,0))))+SUMPRODUCT((Inputs!$E$5:$E$190=$B7)*ISNUMBER(INDEX(Inputs!$K$5:$AJ$190,0,MATCH(D$2,Inputs!$K$4:$AJ$4,0))))=0,NA(),SUMPRODUCT((Inputs!$A$5:$A$190=$B7)*Inputs!$B$5:$B$190*(((Inputs!$G$5:$G$190="moeda")+(Inputs!$G$5:$G$190="acoes"))*Inputs!$B$1+((Inputs!$G$5:$G$190<>"moeda")*(Inputs!$G$5:$G$190<>"acoes")))*INDEX(Inputs!$K$5:$AJ$190,0,MATCH(D$2,Inputs!$K$4:$AJ$4,0)))+SUMPRODUCT((Inputs!$C$5:$C$190=$B7)*Inputs!$D$5:$D$190*(((Inputs!$G$5:$G$190="moeda")+(Inputs!$G$5:$G$190="acoes"))*Inputs!$B$1+((Inputs!$G$5:$G$190<>"moeda")*(Inputs!$G$5:$G$190<>"acoes")))*INDEX(Inputs!$K$5:$AJ$190,0,MATCH(D$2,Inputs!$K$4:$AJ$4,0)))+SUMPRODUCT((Inputs!$E$5:$E$190=$B7)*Inputs!$F$5:$F$190*(((Inputs!$G$5:$G$190="moeda")+(Inputs!$G$5:$G$190="acoes"))*Inputs!$B$1+((Inputs!$G$5:$G$190<>"moeda")*(Inputs!$G$5:$G$190<>"acoes")))*INDEX(Inputs!$K$5:$AJ$190,0,MATCH(D$2,Inputs!$K$4:$AJ$4,0))))) -> -217.049 | E7: =IF(ISNA(MATCH(E$2,Inputs!$K$4:$AJ$4,0)),NA(),IF(SUMPRODUCT((Inputs!$A$5:$A$190=$B7)*ISNUMBER(INDEX(Inputs!$K$5:$AJ$190,0,MATCH(E$2,Inputs!$K$4:$AJ$4,0))))+SUMPRODUCT((Inputs!$C$5:$C$190=$B7)*ISNUMBER(INDEX(Inputs!$K$5:$AJ$190,0,MATCH(E$2,Inputs!$K$4:$AJ$4,0))))+SUMPRODUCT((Inputs!$E$5:$E$190=$B7)*ISNUMBER(INDEX(Inputs!$K$5:$AJ$190,0,MATCH(E$2,Inputs!$K$4:$AJ$4,0))))=0,NA(),SUMPRODUCT((Inputs!$A$5:$A$190=$B7)*Inputs!$B$5:$B$190*(((Inputs!$G$5:$G$190="moeda")+(Inputs!$G$5:$G$190="acoes"))*Inputs!$B$1+((Inputs!$G$5:$G$190<>"moeda")*(Inputs!$G$5:$G$190<>"acoes")))*INDEX(Inputs!$K$5:$AJ$190,0,MATCH(E$2,Inputs!$K$4:$AJ$4,0)))+SUMPRODUCT((Inputs!$C$5:$C$190=$B7)*Inputs!$D$5:$D$190*(((Inputs!$G$5:$G$190="moeda")+(Inputs!$G$5:$G$190="acoes"))*Inputs!$B$1+((Inputs!$G$5:$G$190<>"moeda")*(Inputs!$G$5:$G$190<>"acoes")))*INDEX(Inputs!$K$5:$AJ$190,0,MATCH(E$2,Inputs!$K$4:$AJ$4,0)))+SUMPRODUCT((Inputs!$E$5:$E$190=$B7)*Inputs!$F$5:$F$190*(((Inputs!$G$5:$G$190="moeda")+(Inputs!$G$5:$G$190="acoes"))*Inputs!$B$1+((Inputs!$G$5:$G$190<>"moeda")*(Inputs!$G$5:$G$190<>"acoes")))*INDEX(Inputs!$K$5:$AJ$190,0,MATCH(E$2,Inputs!$K$4:$AJ$4,0))))) -> -241.43428 | F7: =IF(ISNA(MATCH(F$2,Inputs!$K$4:$AJ$4,0)),NA(),IF(SUMPRODUCT((Inputs!$A$5:$A$190=$B7)*ISNUMBER(INDEX(Inputs!$K$5:$AJ$190,0,MATCH(F$2,Inputs!$K$4:$AJ$4,0))))+SUMPRODUCT((Inputs!$C$5:$C$190=$B7)*ISNUMBER(INDEX(Inputs!$K$5:$AJ$190,0,MATCH(F$2,Inputs!$K$4:$AJ$4,0))))+SUMPRODUCT((Inputs!$E$5:$E$190=$B7)*ISNUMBER(INDEX(Inputs!$K$5:$AJ$190,0,MATCH(F$2,Inputs!$K$4:$AJ$4,0))))=0,NA(),SUMPRODUCT((Inputs!$A$5:$A$190=$B7)*Inputs!$B$5:$B$190*(((Inputs!$G$5:$G$190="moeda")+(Inputs!$G$5:$G$190="acoes"))*Inputs!$B$1+((Inputs!$G$5:$G$190<>"moeda")*(Inputs!$G$5:$G$190<>"acoes")))*INDEX(Inputs!$K$5:$AJ$190,0,MATCH(F$2,Inputs!$K$4:$AJ$4,0)))+SUMPRODUCT((Inputs!$C$5:$C$190=$B7)*Inputs!$D$5:$D$190*(((Inputs!$G$5:$G$190="moeda")+(Inputs!$G$5:$G$190="acoes"))*Inputs!$B$1+((Inputs!$G$5:$G$190<>"moeda")*(Inputs!$G$5:$G$190<>"acoes")))*INDEX(Inputs!$K$5:$AJ$190,0,MATCH(F$2,Inputs!$K$4:$AJ$4,0)))+SUMPRODUCT((Inputs!$E$5:$E$190=$B7)*Inputs!$F$5:$F$190*(((Inputs!$G$5:$G$190="moeda")+(Inputs!$G$5:$G$190="acoes"))*Inputs!$B$1+((Inputs!$G$5:$G$190<>"moeda")*(Inputs!$G$5:$G$190<>"acoes")))*INDEX(Inputs!$K$5:$AJ$190,0,MATCH(F$2,Inputs!$K$4:$AJ$4,0))))) -> -275.83937 | G7: =IF(ISNA(MATCH(G$2,Inputs!$K$4:$AJ$4,0)),NA(),IF(SUMPRODUCT((Inputs!$A$5:$A$190=$B7)*ISNUMBER(INDEX(Inputs!$K$5:$AJ$190,0,MATCH(G$2,Inputs!$K$4:$AJ$4,0))))+SUMPRODUCT((Inputs!$C$5:$C$190=$B7)*ISNUMBER(INDEX(Inputs!$K$5:$AJ$190,0,MATCH(G$2,Inputs!$K$4:$AJ$4,0))))+SUMPRODUCT((Inputs!$E$5:$E$190=$B7)*ISNUMBER(INDEX(Inputs!$K$5:$AJ$190,0,MATCH(G$2,Inputs!$K$4:$AJ$4,0))))=0,NA(),SUMPRODUCT((Inputs!$A$5:$A$190=$B7)*Inputs!$B$5:$B$190*(((Inputs!$G$5:$G$190="moeda")+(Inputs!$G$5:$G$190="acoes"))*Inputs!$B$1+((Inputs!$G$5:$G$190<>"moeda")*(Inputs!$G$5:$G$190<>"acoes")))*INDEX(Inputs!$K$5:$AJ$190,0,MATCH(G$2,Inputs!$K$4:$AJ$4,0)))+SUMPRODUCT((Inputs!$C$5:$C$190=$B7)*Inputs!$D$5:$D$190*(((Inputs!$G$5:$G$190="moeda")+(Inputs!$G$5:$G$190="acoes"))*Inputs!$B$1+((Inputs!$G$5:$G$190<>"moeda")*(Inputs!$G$5:$G$190<>"acoes")))*INDEX(Inputs!$K$5:$AJ$190,0,MATCH(G$2,Inputs!$K$4:$AJ$4,0)))+SUMPRODUCT((Inputs!$E$5:$E$190=$B7)*Inputs!$F$5:$F$190*(((Inputs!$G$5:$G$190="moeda")+(Inputs!$G$5:$G$190="acoes"))*Inputs!$B$1+((Inputs!$G$5:$G$190<>"moeda")*(Inputs!$G$5:$G$190<>"acoes")))*INDEX(Inputs!$K$5:$AJ$190,0,MATCH(G$2,Inputs!$K$4:$AJ$4,0))))) -> -324.79236 | H7: =SUM(D7:G7) -> -1059.115 | I7: =IF(ISNA(MATCH(I$2,Inputs!$K$4:$AJ$4,0)),NA(),IF(SUMPRODUCT((Inputs!$A$5:$A$190=$B7)*ISNUMBER(INDEX(Inputs!$K$5:$AJ$190,0,MATCH(I$2,Inputs!$K$4:$AJ$4,0))))+SUMPRODUCT((Inputs!$C$5:$C$190=$B7)*ISNUMBER(INDEX(Inputs!$K$5:$AJ$190,0,MATCH(I$2,Inputs!$K$4:$AJ$4,0))))+SUMPRODUCT((Inputs!$E$5:$E$190=$B7)*ISNUMBER(INDEX(Inputs!$K$5:$AJ$190,0,MATCH(I$2,Inputs!$K$4:$AJ$4,0))))=0,NA(),SUMPRODUCT((Inputs!$A$5:$A$190=$B7)*Inputs!$B$5:$B$190*(((Inputs!$G$5:$G$190="moeda")+(Inputs!$G$5:$G$190="acoes"))*Inputs!$B$1+((Inputs!$G$5:$G$190<>"moeda")*(Inputs!$G$5:$G$190<>"acoes")))*INDEX(Inputs!$K$5:$AJ$190,0,MATCH(I$2,Inputs!$K$4:$AJ$4,0)))+SUMPRODUCT((Inputs!$C$5:$C$190=$B7)*Inputs!$D$5:$D$190*(((Inputs!$G$5:$G$190="moeda")+(Inputs!$G$5:$G$190="acoes"))*Inputs!$B$1+((Inputs!$G$5:$G$190<>"moeda")*(Inputs!$G$5:$G$190<>"acoes")))*INDEX(Inputs!$K$5:$AJ$190,0,MATCH(I$2,Inputs!$K$4:$AJ$4,0)))+SUMPRODUCT((Inputs!$E$5:$E$190=$B7)*Inputs!$F$5:$F$190*(((Inputs!$G$5:$G$190="moeda")+(Inputs!$G$5:$G$190="acoes"))*Inputs!$B$1+((Inputs!$G$5:$G$190<>"moeda")*(Inputs!$G$5:$G$190<>"acoes")))*INDEX(Inputs!$K$5:$AJ$190,0,MATCH(I$2,Inputs!$K$4:$AJ$4,0))))) -> -377.493 | J7: =IF(ISNA(MATCH(J$2,Inputs!$K$4:$AJ$4,0)),NA(),IF(SUMPRODUCT((Inputs!$A$5:$A$190=$B7)*ISNUMBER(INDEX(Inputs!$K$5:$AJ$190,0,MATCH(J$2,Inputs!$K$4:$AJ$4,0))))+SUMPRODUCT((Inputs!$C$5:$C$190=$B7)*ISNUMBER(INDEX(Inputs!$K$5:$AJ$190,0,MATCH(J$2,Inputs!$K$4:$AJ$4,0))))+SUMPRODUCT((Inputs!$E$5:$E$190=$B7)*ISNUMBER(INDEX(Inputs!$K$5:$AJ$190,0,MATCH(J$2,Inputs!$K$4:$AJ$4,0))))=0,NA(),SUMPRODUCT((Inputs!$A$5:$A$190=$B7)*Inputs!$B$5:$B$190*(((Inputs!$G$5:$G$190="moeda")+(Inputs!$G$5:$G$190="acoes"))*Inputs!$B$1+((Inputs!$G$5:$G$190<>"moeda")*(Inputs!$G$5:$G$190<>"acoes")))*INDEX(Inputs!$K$5:$AJ$190,0,MATCH(J$2,Inputs!$K$4:$AJ$4,0)))+SUMPRODUCT((Inputs!$C$5:$C$190=$B7)*Inputs!$D$5:$D$190*(((Inputs!$G$5:$G$190="moeda")+(Inputs!$G$5:$G$190="acoes"))*Inputs!$B$1+((Inputs!$G$5:$G$190<>"moeda")*(Inputs!$G$5:$G$190<>"acoes")))*INDEX(Inputs!$K$5:$AJ$190,0,MATCH(J$2,Inputs!$K$4:$AJ$4,0)))+SUMPRODUCT((Inputs!$E$5:$E$190=$B7)*Inputs!$F$5:$F$190*(((Inputs!$G$5:$G$190="moeda")+(Inputs!$G$5:$G$190="acoes"))*Inputs!$B$1+((Inputs!$G$5:$G$190<>"moeda")*(Inputs!$G$5:$G$190<>"acoes")))*INDEX(Inputs!$K$5:$AJ$190,0,MATCH(J$2,Inputs!$K$4:$AJ$4,0))))) -> -416.2078 | K7: =IF(ISNA(MATCH(K$2,Inputs!$K$4:$AJ$4,0)),NA(),IF(SUMPRODUCT((Inputs!$A$5:$A$190=$B7)*ISNUMBER(INDEX(Inputs!$K$5:$AJ$190,0,MATCH(K$2,Inputs!$K$4:$AJ$4,0))))+SUMPRODUCT((Inputs!$C$5:$C$190=$B7)*ISNUMBER(INDEX(Inputs!$K$5:$AJ$190,0,MATCH(K$2,Inputs!$K$4:$AJ$4,0))))+SUMPRODUCT((Inputs!$E$5:$E$190=$B7)*ISNUMBER(INDEX(Inputs!$K$5:$AJ$190,0,MATCH(K$2,Inputs!$K$4:$AJ$4,0))))=0,NA(),SUMPRODUCT((Inputs!$A$5:$A$190=$B7)*Inputs!$B$5:$B$190*(((Inputs!$G$5:$G$190="moeda")+(Inputs!$G$5:$G$190="acoes"))*Inputs!$B$1+((Inputs!$G$5:$G$190<>"moeda")*(Inputs!$G$5:$G$190<>"acoes")))*INDEX(Inputs!$K$5:$AJ$190,0,MATCH(K$2,Inputs!$K$4:$AJ$4,0)))+SUMPRODUCT((Inputs!$C$5:$C$190=$B7)*Inputs!$D$5:$D$190*(((Inputs!$G$5:$G$190="moeda")+(Inputs!$G$5:$G$190="acoes"))*Inputs!$B$1+((Inputs!$G$5:$G$190<>"moeda")*(Inputs!$G$5:$G$190<>"acoes")))*INDEX(Inputs!$K$5:$AJ$190,0,MATCH(K$2,Inputs!$K$4:$AJ$4,0)))+SUMPRODUCT((Inputs!$E$5:$E$190=$B7)*Inputs!$F$5:$F$190*(((Inputs!$G$5:$G$190="moeda")+(Inputs!$G$5:$G$190="acoes"))*Inputs!$B$1+((Inputs!$G$5:$G$190<>"moeda")*(Inputs!$G$5:$G$190<>"acoes")))*INDEX(Inputs!$K$5:$AJ$190,0,MATCH(K$2,Inputs!$K$4:$AJ$4,0))))) -> -510.06531 | L7: =IF(ISNA(MATCH(L$2,Inputs!$K$4:$AJ$4,0)),NA(),IF(SUMPRODUCT((Inputs!$A$5:$A$190=$B7)*ISNUMBER(INDEX(Inputs!$K$5:$AJ$190,0,MATCH(L$2,Inputs!$K$4:$AJ$4,0))))+SUMPRODUCT((Inputs!$C$5:$C$190=$B7)*ISNUMBER(INDEX(Inputs!$K$5:$AJ$190,0,MATCH(L$2,Inputs!$K$4:$AJ$4,0))))+SUMPRODUCT((Inputs!$E$5:$E$190=$B7)*ISNUMBER(INDEX(Inputs!$K$5:$AJ$190,0,MATCH(L$2,Inputs!$K$4:$AJ$4,0))))=0,NA(),SUMPRODUCT((Inputs!$A$5:$A$190=$B7)*Inputs!$B$5:$B$190*(((Inputs!$G$5:$G$190="moeda")+(Inputs!$G$5:$G$190="acoes"))*Inputs!$B$1+((Inputs!$G$5:$G$190<>"moeda")*(Inputs!$G$5:$G$190<>"acoes")))*INDEX(Inputs!$K$5:$AJ$190,0,MATCH(L$2,Inputs!$K$4:$AJ$4,0)))+SUMPRODUCT((Inputs!$C$5:$C$190=$B7)*Inputs!$D$5:$D$190*(((Inputs!$G$5:$G$190="moeda")+(Inputs!$G$5:$G$190="acoes"))*Inputs!$B$1+((Inputs!$G$5:$G$190<>"moeda")*(Inputs!$G$5:$G$190<>"acoes")))*INDEX(Inputs!$K$5:$AJ$190,0,MATCH(L$2,Inputs!$K$4:$AJ$4,0)))+SUMPRODUCT((Inputs!$E$5:$E$190=$B7)*Inputs!$F$5:$F$190*(((Inputs!$G$5:$G$190="moeda")+(Inputs!$G$5:$G$190="acoes"))*Inputs!$B$1+((Inputs!$G$5:$G$190<>"moeda")*(Inputs!$G$5:$G$190<>"acoes")))*INDEX(Inputs!$K$5:$AJ$190,0,MATCH(L$2,Inputs!$K$4:$AJ$4,0))))) -> -582.5109 | M7: =SUM(I7:L7) -> -1886.277 | N7: =IF(ISNA(MATCH(N$2,Inputs!$K$4:$AJ$4,0)),NA(),IF(SUMPRODUCT((Inputs!$A$5:$A$190=$B7)*ISNUMBER(INDEX(Inputs!$K$5:$AJ$190,0,MATCH(N$2,Inputs!$K$4:$AJ$4,0))))+SUMPRODUCT((Inputs!$C$5:$C$190=$B7)*ISNUMBER(INDEX(Inputs!$K$5:$AJ$190,0,MATCH(N$2,Inputs!$K$4:$AJ$4,0))))+SUMPRODUCT((Inputs!$E$5:$E$190=$B7)*ISNUMBER(INDEX(Inputs!$K$5:$AJ$190,0,MATCH(N$2,Inputs!$K$4:$AJ$4,0))))=0,NA(),SUMPRODUCT((Inputs!$A$5:$A$190=$B7)*Inputs!$B$5:$B$190*(((Inputs!$G$5:$G$190="moeda")+(Inputs!$G$5:$G$190="acoes"))*Inputs!$B$1+((Inputs!$G$5:$G$190<>"moeda")*(Inputs!$G$5:$G$190<>"acoes")))*INDEX(Inputs!$K$5:$AJ$190,0,MATCH(N$2,Inputs!$K$4:$AJ$4,0)))+SUMPRODUCT((Inputs!$C$5:$C$190=$B7)*Inputs!$D$5:$D$190*(((Inputs!$G$5:$G$190="moeda")+(Inputs!$G$5:$G$190="acoes"))*Inputs!$B$1+((Inputs!$G$5:$G$190<>"moeda")*(Inputs!$G$5:$G$190<>"acoes")))*INDEX(Inputs!$K$5:$AJ$190,0,MATCH(N$2,Inputs!$K$4:$AJ$4,0)))+SUMPRODUCT((Inputs!$E$5:$E$190=$B7)*Inputs!$F$5:$F$190*(((Inputs!$G$5:$G$190="moeda")+(Inputs!$G$5:$G$190="acoes"))*Inputs!$B$1+((Inputs!$G$5:$G$190<>"moeda")*(Inputs!$G$5:$G$190<>"acoes")))*INDEX(Inputs!$K$5:$AJ$190,0,MATCH(N$2,Inputs!$K$4:$AJ$4,0))))) -> -646.75978 | O7: =IF(ISNA(MATCH(O$2,Inputs!$K$4:$AJ$4,0)),NA(),IF(SUMPRODUCT((Inputs!$A$5:$A$190=$B7)*ISNUMBER(INDEX(Inputs!$K$5:$AJ$190,0,MATCH(O$2,Inputs!$K$4:$AJ$4,0))))+SUMPRODUCT((Inputs!$C$5:$C$190=$B7)*ISNUMBER(INDEX(Inputs!$K$5:$AJ$190,0,MATCH(O$2,Inputs!$K$4:$AJ$4,0))))+SUMPRODUCT((Inputs!$E$5:$E$190=$B7)*ISNUMBER(INDEX(Inputs!$K$5:$AJ$190,0,MATCH(O$2,Inputs!$K$4:$AJ$4,0))))=0,NA(),SUMPRODUCT((Inputs!$A$5:$A$190=$B7)*Inputs!$B$5:$B$190*(((Inputs!$G$5:$G$190="moeda")+(Inputs!$G$5:$G$190="acoes"))*Inputs!$B$1+((Inputs!$G$5:$G$190<>"moeda")*(Inputs!$G$5:$G$190<>"acoes")))*INDEX(Inputs!$K$5:$AJ$190,0,MATCH(O$2,Inputs!$K$4:$AJ$4,0)))+SUMPRODUCT((Inputs!$C$5:$C$190=$B7)*Inputs!$D$5:$D$190*(((Inputs!$G$5:$G$190="moeda")+(Inputs!$G$5:$G$190="acoes"))*Inputs!$B$1+((Inputs!$G$5:$G$190<>"moeda")*(Inputs!$G$5:$G$190<>"acoes")))*INDEX(Inputs!$K$5:$AJ$190,0,MATCH(O$2,Inputs!$K$4:$AJ$4,0)))+SUMPRODUCT((Inputs!$E$5:$E$190=$B7)*Inputs!$F$5:$F$190*(((Inputs!$G$5:$G$190="moeda")+(Inputs!$G$5:$G$190="acoes"))*Inputs!$B$1+((Inputs!$G$5:$G$190<>"moeda")*(Inputs!$G$5:$G$190<>"acoes")))*INDEX(Inputs!$K$5:$AJ$190,0,MATCH(O$2,Inputs!$K$4:$AJ$4,0))))) -> -679.386 | P7: =IF(ISNA(MATCH(P$2,Inputs!$K$4:$AJ$4,0)),NA(),IF(SUMPRODUCT((Inputs!$A$5:$A$190=$B7)*ISNUMBER(INDEX(Inputs!$K$5:$AJ$190,0,MATCH(P$2,Inputs!$K$4:$AJ$4,0))))+SUMPRODUCT((Inputs!$C$5:$C$190=$B7)*ISNUMBER(INDEX(Inputs!$K$5:$AJ$190,0,MATCH(P$2,Inputs!$K$4:$AJ$4,0))))+SUMPRODUCT((Inputs!$E$5:$E$190=$B7)*ISNUMBER(INDEX(Inputs!$K$5:$AJ$190,0,MATCH(P$2,Inputs!$K$4:$AJ$4,0))))=0,NA(),SUMPRODUCT((Inputs!$A$5:$A$190=$B7)*Inputs!$B$5:$B$190*(((Inputs!$G$5:$G$190="moeda")+(Inputs!$G$5:$G$190="acoes"))*Inputs!$B$1+((Inputs!$G$5:$G$190<>"moeda")*(Inputs!$G$5:$G$190<>"acoes")))*INDEX(Inputs!$K$5:$AJ$190,0,MATCH(P$2,Inputs!$K$4:$AJ$4,0)))+SUMPRODUCT((Inputs!$C$5:$C$190=$B7)*Inputs!$D$5:$D$190*(((Inputs!$G$5:$G$190="moeda")+(Inputs!$G$5:$G$190="acoes"))*Inputs!$B$1+((Inputs!$G$5:$G$190<>"moeda")*(Inputs!$G$5:$G$190<>"acoes")))*INDEX(Inputs!$K$5:$AJ$190,0,MATCH(P$2,Inputs!$K$4:$AJ$4,0)))+SUMPRODUCT((Inputs!$E$5:$E$190=$B7)*Inputs!$F$5:$F$190*(((Inputs!$G$5:$G$190="moeda")+(Inputs!$G$5:$G$190="acoes"))*Inputs!$B$1+((Inputs!$G$5:$G$190<>"moeda")*(Inputs!$G$5:$G$190<>"acoes")))*INDEX(Inputs!$K$5:$AJ$190,0,MATCH(P$2,Inputs!$K$4:$AJ$4,0))))) -> -717.08101 | Q7: =IF(ISNA(MATCH(Q$2,Inputs!$K$4:$AJ$4,0)),NA(),IF(SUMPRODUCT((Inputs!$A$5:$A$190=$B7)*ISNUMBER(INDEX(Inputs!$K$5:$AJ$190,0,MATCH(Q$2,Inputs!$K$4:$AJ$4,0))))+SUMPRODUCT((Inputs!$C$5:$C$190=$B7)*ISNUMBER(INDEX(Inputs!$K$5:$AJ$190,0,MATCH(Q$2,Inputs!$K$4:$AJ$4,0))))+SUMPRODUCT((Inputs!$E$5:$E$190=$B7)*ISNUMBER(INDEX(Inputs!$K$5:$AJ$190,0,MATCH(Q$2,Inputs!$K$4:$AJ$4,0))))=0,NA(),SUMPRODUCT((Inputs!$A$5:$A$190=$B7)*Inputs!$B$5:$B$190*(((Inputs!$G$5:$G$190="moeda")+(Inputs!$G$5:$G$190="acoes"))*Inputs!$B$1+((Inputs!$G$5:$G$190<>"moeda")*(Inputs!$G$5:$G$190<>"acoes")))*INDEX(Inputs!$K$5:$AJ$190,0,MATCH(Q$2,Inputs!$K$4:$AJ$4,0)))+SUMPRODUCT((Inputs!$C$5:$C$190=$B7)*Inputs!$D$5:$D$190*(((Inputs!$G$5:$G$190="moeda")+(Inputs!$G$5:$G$190="acoes"))*Inputs!$B$1+((Inputs!$G$5:$G$190<>"moeda")*(Inputs!$G$5:$G$190<>"acoes")))*INDEX(Inputs!$K$5:$AJ$190,0,MATCH(Q$2,Inputs!$K$4:$AJ$4,0)))+SUMPRODUCT((Inputs!$E$5:$E$190=$B7)*Inputs!$F$5:$F$190*(((Inputs!$G$5:$G$190="moeda")+(Inputs!$G$5:$G$190="acoes"))*Inputs!$B$1+((Inputs!$G$5:$G$190<>"moeda")*(Inputs!$G$5:$G$190<>"acoes")))*INDEX(Inputs!$K$5:$AJ$190,0,MATCH(Q$2,Inputs!$K$4:$AJ$4,0))))) -> -1060.7258 | R7: =SUM(N7:Q7) -> -3103.9526 | S7: =IF(ISNA(MATCH(S$2,Inputs!$K$4:$AJ$4,0)),NA(),IF(SUMPRODUCT((Inputs!$A$5:$A$190=$B7)*ISNUMBER(INDEX(Inputs!$K$5:$AJ$190,0,MATCH(S$2,Inputs!$K$4:$AJ$4,0))))+SUMPRODUCT((Inputs!$C$5:$C$190=$B7)*ISNUMBER(INDEX(Inputs!$K$5:$AJ$190,0,MATCH(S$2,Inputs!$K$4:$AJ$4,0))))+SUMPRODUCT((Inputs!$E$5:$E$190=$B7)*ISNUMBER(INDEX(Inputs!$K$5:$AJ$190,0,MATCH(S$2,Inputs!$K$4:$AJ$4,0))))=0,NA(),SUMPRODUCT((Inputs!$A$5:$A$190=$B7)*Inputs!$B$5:$B$190*(((Inputs!$G$5:$G$190="moeda")+(Inputs!$G$5:$G$190="acoes"))*Inputs!$B$1+((Inputs!$G$5:$G$190<>"moeda")*(Inputs!$G$5:$G$190<>"acoes")))*INDEX(Inputs!$K$5:$AJ$190,0,MATCH(S$2,Inputs!$K$4:$AJ$4,0)))+SUMPRODUCT((Inputs!$C$5:$C$190=$B7)*Inputs!$D$5:$D$190*(((Inputs!$G$5:$G$190="moeda")+(Inputs!$G$5:$G$190="acoes"))*Inputs!$B$1+((Inputs!$G$5:$G$190<>"moeda")*(Inputs!$G$5:$G$190<>"acoes")))*INDEX(Inputs!$K$5:$AJ$190,0,MATCH(S$2,Inputs!$K$4:$AJ$4,0)))+SUMPRODUCT((Inputs!$E$5:$E$190=$B7)*Inputs!$F$5:$F$190*(((Inputs!$G$5:$G$190="moeda")+(Inputs!$G$5:$G$190="acoes"))*Inputs!$B$1+((Inputs!$G$5:$G$190<>"moeda")*(Inputs!$G$5:$G$190<>"acoes")))*INDEX(Inputs!$K$5:$AJ$190,0,MATCH(S$2,Inputs!$K$4:$AJ$4,0))))) -> -821.97977 | T7: =IF(ISNA(MATCH(T$2,Inputs!$K$4:$AJ$4,0)),NA(),IF(SUMPRODUCT((Inputs!$A$5:$A$190=$B7)*ISNUMBER(INDEX(Inputs!$K$5:$AJ$190,0,MATCH(T$2,Inputs!$K$4:$AJ$4,0))))+SUMPRODUCT((Inputs!$C$5:$C$190=$B7)*ISNUMBER(INDEX(Inputs!$K$5:$AJ$190,0,MATCH(T$2,Inputs!$K$4:$AJ$4,0))))+SUMPRODUCT((Inputs!$E$5:$E$190=$B7)*ISNUMBER(INDEX(Inputs!$K$5:$AJ$190,0,MATCH(T$2,Inputs!$K$4:$AJ$4,0))))=0,NA(),SUMPRODUCT((Inputs!$A$5:$A$190=$B7)*Inputs!$B$5:$B$190*(((Inputs!$G$5:$G$190="moeda")+(Inputs!$G$5:$G$190="acoes"))*Inputs!$B$1+((Inputs!$G$5:$G$190<>"moeda")*(Inputs!$G$5:$G$190<>"acoes")))*INDEX(Inputs!$K$5:$AJ$190,0,MATCH(T$2,Inputs!$K$4:$AJ$4,0)))+SUMPRODUCT((Inputs!$C$5:$C$190=$B7)*Inputs!$D$5:$D$190*(((Inputs!$G$5:$G$190="moeda")+(Inputs!$G$5:$G$190="acoes"))*Inputs!$B$1+((Inputs!$G$5:$G$190<>"moeda")*(Inputs!$G$5:$G$190<>"acoes")))*INDEX(Inputs!$K$5:$AJ$190,0,MATCH(T$2,Inputs!$K$4:$AJ$4,0)))+SUMPRODUCT((Inputs!$E$5:$E$190=$B7)*Inputs!$F$5:$F$190*(((Inputs!$G$5:$G$190="moeda")+(Inputs!$G$5:$G$190="acoes"))*Inputs!$B$1+((Inputs!$G$5:$G$190<>"moeda")*(Inputs!$G$5:$G$190<>"acoes")))*INDEX(Inputs!$K$5:$AJ$190,0,MATCH(T$2,Inputs!$K$4:$AJ$4,0))))) -> -897.64322 | U7: =IF(ISNA(MATCH(U$2,Inputs!$K$4:$AJ$4,0)),NA(),IF(SUMPRODUCT((Inputs!$A$5:$A$190=$B7)*ISNUMBER(INDEX(Inputs!$K$5:$AJ$190,0,MATCH(U$2,Inputs!$K$4:$AJ$4,0))))+SUMPRODUCT((Inputs!$C$5:$C$190=$B7)*ISNUMBER(INDEX(Inputs!$K$5:$AJ$190,0,MATCH(U$2,Inputs!$K$4:$AJ$4,0))))+SUMPRODUCT((Inputs!$E$5:$E$190=$B7)*ISNUMBER(INDEX(Inputs!$K$5:$AJ$190,0,MATCH(U$2,Inputs!$K$4:$AJ$4,0))))=0,NA(),SUMPRODUCT((Inputs!$A$5:$A$190=$B7)*Inputs!$B$5:$B$190*(((Inputs!$G$5:$G$190="moeda")+(Inputs!$G$5:$G$190="acoes"))*Inputs!$B$1+((Inputs!$G$5:$G$190<>"moeda")*(Inputs!$G$5:$G$190<>"acoes")))*INDEX(Inputs!$K$5:$AJ$190,0,MATCH(U$2,Inputs!$K$4:$AJ$4,0)))+SUMPRODUCT((Inputs!$C$5:$C$190=$B7)*Inputs!$D$5:$D$190*(((Inputs!$G$5:$G$190="moeda")+(Inputs!$G$5:$G$190="acoes"))*Inputs!$B$1+((Inputs!$G$5:$G$190<>"moeda")*(Inputs!$G$5:$G$190<>"acoes")))*INDEX(Inputs!$K$5:$AJ$190,0,MATCH(U$2,Inputs!$K$4:$AJ$4,0)))+SUMPRODUCT((Inputs!$E$5:$E$190=$B7)*Inputs!$F$5:$F$190*(((Inputs!$G$5:$G$190="moeda")+(Inputs!$G$5:$G$190="acoes"))*Inputs!$B$1+((Inputs!$G$5:$G$190<>"moeda")*(Inputs!$G$5:$G$190<>"acoes")))*INDEX(Inputs!$K$5:$AJ$190,0,MATCH(U$2,Inputs!$K$4:$AJ$4,0))))) -> -997.19453 | V7: =IF(ISNA(MATCH(V$2,Inputs!$K$4:$AJ$4,0)),NA(),IF(SUMPRODUCT((Inputs!$A$5:$A$190=$B7)*ISNUMBER(INDEX(Inputs!$K$5:$AJ$190,0,MATCH(V$2,Inputs!$K$4:$AJ$4,0))))+SUMPRODUCT((Inputs!$C$5:$C$190=$B7)*ISNUMBER(INDEX(Inputs!$K$5:$AJ$190,0,MATCH(V$2,Inputs!$K$4:$AJ$4,0))))+SUMPRODUCT((Inputs!$E$5:$E$190=$B7)*ISNUMBER(INDEX(Inputs!$K$5:$AJ$190,0,MATCH(V$2,Inputs!$K$4:$AJ$4,0))))=0,NA(),SUMPRODUCT((Inputs!$A$5:$A$190=$B7)*Inputs!$B$5:$B$190*(((Inputs!$G$5:$G$190="moeda")+(Inputs!$G$5:$G$190="acoes"))*Inputs!$B$1+((Inputs!$G$5:$G$190<>"moeda")*(Inputs!$G$5:$G$190<>"acoes")))*INDEX(Inputs!$K$5:$AJ$190,0,MATCH(V$2,Inputs!$K$4:$AJ$4,0)))+SUMPRODUCT((Inputs!$C$5:$C$190=$B7)*Inputs!$D$5:$D$190*(((Inputs!$G$5:$G$190="moeda")+(Inputs!$G$5:$G$190="acoes"))*Inputs!$B$1+((Inputs!$G$5:$G$190<>"moeda")*(Inputs!$G$5:$G$190<>"acoes")))*INDEX(Inputs!$K$5:$AJ$190,0,MATCH(V$2,Inputs!$K$4:$AJ$4,0)))+SUMPRODUCT((Inputs!$E$5:$E$190=$B7)*Inputs!$F$5:$F$190*(((Inputs!$G$5:$G$190="moeda")+(Inputs!$G$5:$G$190="acoes"))*Inputs!$B$1+((Inputs!$G$5:$G$190<>"moeda")*(Inputs!$G$5:$G$190<>"acoes")))*INDEX(Inputs!$K$5:$AJ$190,0,MATCH(V$2,Inputs!$K$4:$AJ$4,0))))) -> -974.30237 | W7: =SUM(S7:V7) -> -3691.1199 | X7: =IF(ISNA(MATCH(X$2,Inputs!$K$4:$AJ$4,0)),NA(),IF(SUMPRODUCT((Inputs!$A$5:$A$190=$B7)*ISNUMBER(INDEX(Inputs!$K$5:$AJ$190,0,MATCH(X$2,Inputs!$K$4:$AJ$4,0))))+SUMPRODUCT((Inputs!$C$5:$C$190=$B7)*ISNUMBER(INDEX(Inputs!$K$5:$AJ$190,0,MATCH(X$2,Inputs!$K$4:$AJ$4,0))))+SUMPRODUCT((Inputs!$E$5:$E$190=$B7)*ISNUMBER(INDEX(Inputs!$K$5:$AJ$190,0,MATCH(X$2,Inputs!$K$4:$AJ$4,0))))=0,NA(),SUMPRODUCT((Inputs!$A$5:$A$190=$B7)*Inputs!$B$5:$B$190*(((Inputs!$G$5:$G$190="moeda")+(Inputs!$G$5:$G$190="acoes"))*Inputs!$B$1+((Inputs!$G$5:$G$190<>"moeda")*(Inputs!$G$5:$G$190<>"acoes")))*INDEX(Inputs!$K$5:$AJ$190,0,MATCH(X$2,Inputs!$K$4:$AJ$4,0)))+SUMPRODUCT((Inputs!$C$5:$C$190=$B7)*Inputs!$D$5:$D$190*(((Inputs!$G$5:$G$190="moeda")+(Inputs!$G$5:$G$190="acoes"))*Inputs!$B$1+((Inputs!$G$5:$G$190<>"moeda")*(Inputs!$G$5:$G$190<>"acoes")))*INDEX(Inputs!$K$5:$AJ$190,0,MATCH(X$2,Inputs!$K$4:$AJ$4,0)))+SUMPRODUCT((Inputs!$E$5:$E$190=$B7)*Inputs!$F$5:$F$190*(((Inputs!$G$5:$G$190="moeda")+(Inputs!$G$5:$G$190="acoes"))*Inputs!$B$1+((Inputs!$G$5:$G$190<>"moeda")*(Inputs!$G$5:$G$190<>"acoes")))*INDEX(Inputs!$K$5:$AJ$190,0,MATCH(X$2,Inputs!$K$4:$AJ$4,0))))) -> -1052.4133 | Y7: =IF(ISNA(MATCH(Y$2,Inputs!$K$4:$AJ$4,0)),NA(),IF(SUMPRODUCT((Inputs!$A$5:$A$190=$B7)*ISNUMBER(INDEX(Inputs!$K$5:$AJ$190,0,MATCH(Y$2,Inputs!$K$4:$AJ$4,0))))+SUMPRODUCT((Inputs!$C$5:$C$190=$B7)*ISNUMBER(INDEX(Inputs!$K$5:$AJ$190,0,MATCH(Y$2,Inputs!$K$4:$AJ$4,0))))+SUMPRODUCT((Inputs!$E$5:$E$190=$B7)*ISNUMBER(INDEX(Inputs!$K$5:$AJ$190,0,MATCH(Y$2,Inputs!$K$4:$AJ$4,0))))=0,NA(),SUMPRODUCT((Inputs!$A$5:$A$190=$B7)*Inputs!$B$5:$B$190*(((Inputs!$G$5:$G$190="moeda")+(Inputs!$G$5:$G$190="acoes"))*Inputs!$B$1+((Inputs!$G$5:$G$190<>"moeda")*(Inputs!$G$5:$G$190<>"acoes")))*INDEX(Inputs!$K$5:$AJ$190,0,MATCH(Y$2,Inputs!$K$4:$AJ$4,0)))+SUMPRODUCT((Inputs!$C$5:$C$190=$B7)*Inputs!$D$5:$D$190*(((Inputs!$G$5:$G$190="moeda")+(Inputs!$G$5:$G$190="acoes"))*Inputs!$B$1+((Inputs!$G$5:$G$190<>"moeda")*(Inputs!$G$5:$G$190<>"acoes")))*INDEX(Inputs!$K$5:$AJ$190,0,MATCH(Y$2,Inputs!$K$4:$AJ$4,0)))+SUMPRODUCT((Inputs!$E$5:$E$190=$B7)*Inputs!$F$5:$F$190*(((Inputs!$G$5:$G$190="moeda")+(Inputs!$G$5:$G$190="acoes"))*Inputs!$B$1+((Inputs!$G$5:$G$190<>"moeda")*(Inputs!$G$5:$G$190<>"acoes")))*INDEX(Inputs!$K$5:$AJ$190,0,MATCH(Y$2,Inputs!$K$4:$AJ$4,0))))) -> -1118.9409 | Z7: =IF(ISNA(MATCH(Z$2,Inputs!$K$4:$AJ$4,0)),NA(),IF(SUMPRODUCT((Inputs!$A$5:$A$190=$B7)*ISNUMBER(INDEX(Inputs!$K$5:$AJ$190,0,MATCH(Z$2,Inputs!$K$4:$AJ$4,0))))+SUMPRODUCT((Inputs!$C$5:$C$190=$B7)*ISNUMBER(INDEX(Inputs!$K$5:$AJ$190,0,MATCH(Z$2,Inputs!$K$4:$AJ$4,0))))+SUMPRODUCT((Inputs!$E$5:$E$190=$B7)*ISNUMBER(INDEX(Inputs!$K$5:$AJ$190,0,MATCH(Z$2,Inputs!$K$4:$AJ$4,0))))=0,NA(),SUMPRODUCT((Inputs!$A$5:$A$190=$B7)*Inputs!$B$5:$B$190*(((Inputs!$G$5:$G$190="moeda")+(Inputs!$G$5:$G$190="acoes"))*Inputs!$B$1+((Inputs!$G$5:$G$190<>"moeda")*(Inputs!$G$5:$G$190<>"acoes")))*INDEX(Inputs!$K$5:$AJ$190,0,MATCH(Z$2,Inputs!$K$4:$AJ$4,0)))+SUMPRODUCT((Inputs!$C$5:$C$190=$B7)*Inputs!$D$5:$D$190*(((Inputs!$G$5:$G$190="moeda")+(Inputs!$G$5:$G$190="acoes"))*Inputs!$B$1+((Inputs!$G$5:$G$190<>"moeda")*(Inputs!$G$5:$G$190<>"acoes")))*INDEX(Inputs!$K$5:$AJ$190,0,MATCH(Z$2,Inputs!$K$4:$AJ$4,0)))+SUMPRODUCT((Inputs!$E$5:$E$190=$B7)*Inputs!$F$5:$F$190*(((Inputs!$G$5:$G$190="moeda")+(Inputs!$G$5:$G$190="acoes"))*Inputs!$B$1+((Inputs!$G$5:$G$190<>"moeda")*(Inputs!$G$5:$G$190<>"acoes")))*INDEX(Inputs!$K$5:$AJ$190,0,MATCH(Z$2,Inputs!$K$4:$AJ$4,0))))) -> -1172.062 | AA7: =IF(ISNA(MATCH(AA$2,Inputs!$K$4:$AJ$4,0)),NA(),IF(SUMPRODUCT((Inputs!$A$5:$A$190=$B7)*ISNUMBER(INDEX(Inputs!$K$5:$AJ$190,0,MATCH(AA$2,Inputs!$K$4:$AJ$4,0))))+SUMPRODUCT((Inputs!$C$5:$C$190=$B7)*ISNUMBER(INDEX(Inputs!$K$5:$AJ$190,0,MATCH(AA$2,Inputs!$K$4:$AJ$4,0))))+SUMPRODUCT((Inputs!$E$5:$E$190=$B7)*ISNUMBER(INDEX(Inputs!$K$5:$AJ$190,0,MATCH(AA$2,Inputs!$K$4:$AJ$4,0))))=0,NA(),SUMPRODUCT((Inputs!$A$5:$A$190=$B7)*Inputs!$B$5:$B$190*(((Inputs!$G$5:$G$190="moeda")+(Inputs!$G$5:$G$190="acoes"))*Inputs!$B$1+((Inputs!$G$5:$G$190<>"moeda")*(Inputs!$G$5:$G$190<>"acoes")))*INDEX(Inputs!$K$5:$AJ$190,0,MATCH(AA$2,Inputs!$K$4:$AJ$4,0)))+SUMPRODUCT((Inputs!$C$5:$C$190=$B7)*Inputs!$D$5:$D$190*(((Inputs!$G$5:$G$190="moeda")+(Inputs!$G$5:$G$190="acoes"))*Inputs!$B$1+((Inputs!$G$5:$G$190<>"moeda")*(Inputs!$G$5:$G$190<>"acoes")))*INDEX(Inputs!$K$5:$AJ$190,0,MATCH(AA$2,Inputs!$K$4:$AJ$4,0)))+SUMPRODUCT((Inputs!$E$5:$E$190=$B7)*Inputs!$F$5:$F$190*(((Inputs!$G$5:$G$190="moeda")+(Inputs!$G$5:$G$190="acoes"))*Inputs!$B$1+((Inputs!$G$5:$G$190<>"moeda")*(Inputs!$G$5:$G$190<>"acoes")))*INDEX(Inputs!$K$5:$AJ$190,0,MATCH(AA$2,Inputs!$K$4:$AJ$4,0))))) -> -1197.9697 | AB7: =SUM(X7:AA7) -> -4541.3858 | AC7: =IF(ISNA(MATCH(AC$2,Inputs!$K$4:$AJ$4,0)),NA(),IF(SUMPRODUCT((Inputs!$A$5:$A$190=$B7)*ISNUMBER(INDEX(Inputs!$K$5:$AJ$190,0,MATCH(AC$2,Inputs!$K$4:$AJ$4,0))))+SUMPRODUCT((Inputs!$C$5:$C$190=$B7)*ISNUMBER(INDEX(Inputs!$K$5:$AJ$190,0,MATCH(AC$2,Inputs!$K$4:$AJ$4,0))))+SUMPRODUCT((Inputs!$E$5:$E$190=$B7)*ISNUMBER(INDEX(Inputs!$K$5:$AJ$190,0,MATCH(AC$2,Inputs!$K$4:$AJ$4,0))))=0,NA(),SUMPRODUCT((Inputs!$A$5:$A$190=$B7)*Inputs!$B$5:$B$190*(((Inputs!$G$5:$G$190="moeda")+(Inputs!$G$5:$G$190="acoes"))*Inputs!$B$1+((Inputs!$G$5:$G$190<>"moeda")*(Inputs!$G$5:$G$190<>"acoes")))*INDEX(Inputs!$K$5:$AJ$190,0,MATCH(AC$2,Inputs!$K$4:$AJ$4,0)))+SUMPRODUCT((Inputs!$C$5:$C$190=$B7)*Inputs!$D$5:$D$190*(((Inputs!$G$5:$G$190="moeda")+(Inputs!$G$5:$G$190="acoes"))*Inputs!$B$1+((Inputs!$G$5:$G$190<>"moeda")*(Inputs!$G$5:$G$190<>"acoes")))*INDEX(Inputs!$K$5:$AJ$190,0,MATCH(AC$2,Inputs!$K$4:$AJ$4,0)))+SUMPRODUCT((Inputs!$E$5:$E$190=$B7)*Inputs!$F$5:$F$190*(((Inputs!$G$5:$G$190="moeda")+(Inputs!$G$5:$G$190="acoes"))*Inputs!$B$1+((Inputs!$G$5:$G$190<>"moeda")*(Inputs!$G$5:$G$190<>"acoes")))*INDEX(Inputs!$K$5:$AJ$190,0,MATCH(AC$2,Inputs!$K$4:$AJ$4,0))))) -> -1239.9265 | AD7: =IF(ISNA(MATCH(AD$2,Inputs!$K$4:$AJ$4,0)),NA(),IF(SUMPRODUCT((Inputs!$A$5:$A$190=$B7)*ISNUMBER(INDEX(Inputs!$K$5:$AJ$190,0,MATCH(AD$2,Inputs!$K$4:$AJ$4,0))))+SUMPRODUCT((Inputs!$C$5:$C$190=$B7)*ISNUMBER(INDEX(Inputs!$K$5:$AJ$190,0,MATCH(AD$2,Inputs!$K$4:$AJ$4,0))))+SUMPRODUCT((Inputs!$E$5:$E$190=$B7)*ISNUMBER(INDEX(Inputs!$K$5:$AJ$190,0,MATCH(AD$2,Inputs!$K$4:$AJ$4,0))))=0,NA(),SUMPRODUCT((Inputs!$A$5:$A$190=$B7)*Inputs!$B$5:$B$190*(((Inputs!$G$5:$G$190="moeda")+(Inputs!$G$5:$G$190="acoes"))*Inputs!$B$1+((Inputs!$G$5:$G$190<>"moeda")*(Inputs!$G$5:$G$190<>"acoes")))*INDEX(Inputs!$K$5:$AJ$190,0,MATCH(AD$2,Inputs!$K$4:$AJ$4,0)))+SUMPRODUCT((Inputs!$C$5:$C$190=$B7)*Inputs!$D$5:$D$190*(((Inputs!$G$5:$G$190="moeda")+(Inputs!$G$5:$G$190="acoes"))*Inputs!$B$1+((Inputs!$G$5:$G$190<>"moeda")*(Inputs!$G$5:$G$190<>"acoes")))*INDEX(Inputs!$K$5:$AJ$190,0,MATCH(AD$2,Inputs!$K$4:$AJ$4,0)))+SUMPRODUCT((Inputs!$E$5:$E$190=$B7)*Inputs!$F$5:$F$190*(((Inputs!$G$5:$G$190="moeda")+(Inputs!$G$5:$G$190="acoes"))*Inputs!$B$1+((Inputs!$G$5:$G$190<>"moeda")*(Inputs!$G$5:$G$190<>"acoes")))*INDEX(Inputs!$K$5:$AJ$190,0,MATCH(AD$2,Inputs!$K$4:$AJ$4,0))))) -> -1253.5541 | AE7: =IF(ISNA(MATCH(AE$2,Inputs!$K$4:$AJ$4,0)),NA(),IF(SUMPRODUCT((Inputs!$A$5:$A$190=$B7)*ISNUMBER(INDEX(Inputs!$K$5:$AJ$190,0,MATCH(AE$2,Inputs!$K$4:$AJ$4,0))))+SUMPRODUCT((Inputs!$C$5:$C$190=$B7)*ISNUMBER(INDEX(Inputs!$K$5:$AJ$190,0,MATCH(AE$2,Inputs!$K$4:$AJ$4,0))))+SUMPRODUCT((Inputs!$E$5:$E$190=$B7)*ISNUMBER(INDEX(Inputs!$K$5:$AJ$190,0,MATCH(AE$2,Inputs!$K$4:$AJ$4,0))))=0,NA(),SUMPRODUCT((Inputs!$A$5:$A$190=$B7)*Inputs!$B$5:$B$190*(((Inputs!$G$5:$G$190="moeda")+(Inputs!$G$5:$G$190="acoes"))*Inputs!$B$1+((Inputs!$G$5:$G$190<>"moeda")*(Inputs!$G$5:$G$190<>"acoes")))*INDEX(Inputs!$K$5:$AJ$190,0,MATCH(AE$2,Inputs!$K$4:$AJ$4,0)))+SUMPRODUCT((Inputs!$C$5:$C$190=$B7)*Inputs!$D$5:$D$190*(((Inputs!$G$5:$G$190="moeda")+(Inputs!$G$5:$G$190="acoes"))*Inputs!$B$1+((Inputs!$G$5:$G$190<>"moeda")*(Inputs!$G$5:$G$190<>"acoes")))*INDEX(Inputs!$K$5:$AJ$190,0,MATCH(AE$2,Inputs!$K$4:$AJ$4,0)))+SUMPRODUCT((Inputs!$E$5:$E$190=$B7)*Inputs!$F$5:$F$190*(((Inputs!$G$5:$G$190="moeda")+(Inputs!$G$5:$G$190="acoes"))*Inputs!$B$1+((Inputs!$G$5:$G$190<>"moeda")*(Inputs!$G$5:$G$190<>"acoes")))*INDEX(Inputs!$K$5:$AJ$190,0,MATCH(AE$2,Inputs!$K$4:$AJ$4,0))))) -> #N/A | AF7: =IF(ISNA(MATCH(AF$2,Inputs!$K$4:$AJ$4,0)),NA(),IF(SUMPRODUCT((Inputs!$A$5:$A$190=$B7)*ISNUMBER(INDEX(Inputs!$K$5:$AJ$190,0,MATCH(AF$2,Inputs!$K$4:$AJ$4,0))))+SUMPRODUCT((Inputs!$C$5:$C$190=$B7)*ISNUMBER(INDEX(Inputs!$K$5:$AJ$190,0,MATCH(AF$2,Inputs!$K$4:$AJ$4,0))))+SUMPRODUCT((Inputs!$E$5:$E$190=$B7)*ISNUMBER(INDEX(Inputs!$K$5:$AJ$190,0,MATCH(AF$2,Inputs!$K$4:$AJ$4,0))))=0,NA(),SUMPRODUCT((Inputs!$A$5:$A$190=$B7)*Inputs!$B$5:$B$190*(((Inputs!$G$5:$G$190="moeda")+(Inputs!$G$5:$G$190="acoes"))*Inputs!$B$1+((Inputs!$G$5:$G$190<>"moeda")*(Inputs!$G$5:$G$190<>"acoes")))*INDEX(Inputs!$K$5:$AJ$190,0,MATCH(AF$2,Inputs!$K$4:$AJ$4,0)))+SUMPRODUCT((Inputs!$C$5:$C$190=$B7)*Inputs!$D$5:$D$190*(((Inputs!$G$5:$G$190="moeda")+(Inputs!$G$5:$G$190="acoes"))*Inputs!$B$1+((Inputs!$G$5:$G$190<>"moeda")*(Inputs!$G$5:$G$190<>"acoes")))*INDEX(Inputs!$K$5:$AJ$190,0,MATCH(AF$2,Inputs!$K$4:$AJ$4,0)))+SUMPRODUCT((Inputs!$E$5:$E$190=$B7)*Inputs!$F$5:$F$190*(((Inputs!$G$5:$G$190="moeda")+(Inputs!$G$5:$G$190="acoes"))*Inputs!$B$1+((Inputs!$G$5:$G$190<>"moeda")*(Inputs!$G$5:$G$190<>"acoes")))*INDEX(Inputs!$K$5:$AJ$190,0,MATCH(AF$2,Inputs!$K$4:$AJ$4,0))))) -> #N/A | AG7: =SUM(AC7:AF7) -> #N/A | AH7: =IF(ISNA(MATCH(AH$2,Inputs!$K$4:$AJ$4,0)),NA(),IF(SUMPRODUCT((Inputs!$A$5:$A$190=$B7)*ISNUMBER(INDEX(Inputs!$K$5:$AJ$190,0,MATCH(AH$2,Inputs!$K$4:$AJ$4,0))))+SUMPRODUCT((Inputs!$C$5:$C$190=$B7)*ISNUMBER(INDEX(Inputs!$K$5:$AJ$190,0,MATCH(AH$2,Inputs!$K$4:$AJ$4,0))))+SUMPRODUCT((Inputs!$E$5:$E$190=$B7)*ISNUMBER(INDEX(Inputs!$K$5:$AJ$190,0,MATCH(AH$2,Inputs!$K$4:$AJ$4,0))))=0,NA(),SUMPRODUCT((Inputs!$A$5:$A$190=$B7)*Inputs!$B$5:$B$190*(((Inputs!$G$5:$G$190="moeda")+(Inputs!$G$5:$G$190="acoes"))*Inputs!$B$1+((Inputs!$G$5:$G$190<>"moeda")*(Inputs!$G$5:$G$190<>"acoes")))*INDEX(Inputs!$K$5:$AJ$190,0,MATCH(AH$2,Inputs!$K$4:$AJ$4,0)))+SUMPRODUCT((Inputs!$C$5:$C$190=$B7)*Inputs!$D$5:$D$190*(((Inputs!$G$5:$G$190="moeda")+(Inputs!$G$5:$G$190="acoes"))*Inputs!$B$1+((Inputs!$G$5:$G$190<>"moeda")*(Inputs!$G$5:$G$190<>"acoes")))*INDEX(Inputs!$K$5:$AJ$190,0,MATCH(AH$2,Inputs!$K$4:$AJ$4,0)))+SUMPRODUCT((Inputs!$E$5:$E$190=$B7)*Inputs!$F$5:$F$190*(((Inputs!$G$5:$G$190="moeda")+(Inputs!$G$5:$G$190="acoes"))*Inputs!$B$1+((Inputs!$G$5:$G$190<>"moeda")*(Inputs!$G$5:$G$190<>"acoes")))*INDEX(Inputs!$K$5:$AJ$190,0,MATCH(AH$2,Inputs!$K$4:$AJ$4,0))))) -> -275.68271 | AI7: =IF(ISNA(MATCH(AI$2,Inputs!$K$4:$AJ$4,0)),NA(),IF(SUMPRODUCT((Inputs!$A$5:$A$190=$B7)*ISNUMBER(INDEX(Inputs!$K$5:$AJ$190,0,MATCH(AI$2,Inputs!$K$4:$AJ$4,0))))+SUMPRODUCT((Inputs!$C$5:$C$190=$B7)*ISNUMBER(INDEX(Inputs!$K$5:$AJ$190,0,MATCH(AI$2,Inputs!$K$4:$AJ$4,0))))+SUMPRODUCT((Inputs!$E$5:$E$190=$B7)*ISNUMBER(INDEX(Inputs!$K$5:$AJ$190,0,MATCH(AI$2,Inputs!$K$4:$AJ$4,0))))=0,NA(),SUMPRODUCT((Inputs!$A$5:$A$190=$B7)*Inputs!$B$5:$B$190*(((Inputs!$G$5:$G$190="moeda")+(Inputs!$G$5:$G$190="acoes"))*Inputs!$B$1+((Inputs!$G$5:$G$190<>"moeda")*(Inputs!$G$5:$G$190<>"acoes")))*INDEX(Inputs!$K$5:$AJ$190,0,MATCH(AI$2,Inputs!$K$4:$AJ$4,0)))+SUMPRODUCT((Inputs!$C$5:$C$190=$B7)*Inputs!$D$5:$D$190*(((Inputs!$G$5:$G$190="moeda")+(Inputs!$G$5:$G$190="acoes"))*Inputs!$B$1+((Inputs!$G$5:$G$190<>"moeda")*(Inputs!$G$5:$G$190<>"acoes")))*INDEX(Inputs!$K$5:$AJ$190,0,MATCH(AI$2,Inputs!$K$4:$AJ$4,0)))+SUMPRODUCT((Inputs!$E$5:$E$190=$B7)*Inputs!$F$5:$F$190*(((Inputs!$G$5:$G$190="moeda")+(Inputs!$G$5:$G$190="acoes"))*Inputs!$B$1+((Inputs!$G$5:$G$190<>"moeda")*(Inputs!$G$5:$G$190<>"acoes")))*INDEX(Inputs!$K$5:$AJ$190,0,MATCH(AI$2,Inputs!$K$4:$AJ$4,0))))) -> -271.9098 | AJ7: =IF(ISNA(MATCH(AJ$2,Inputs!$K$4:$AJ$4,0)),NA(),IF(SUMPRODUCT((Inputs!$A$5:$A$190=$B7)*ISNUMBER(INDEX(Inputs!$K$5:$AJ$190,0,MATCH(AJ$2,Inputs!$K$4:$AJ$4,0))))+SUMPRODUCT((Inputs!$C$5:$C$190=$B7)*ISNUMBER(INDEX(Inputs!$K$5:$AJ$190,0,MATCH(AJ$2,Inputs!$K$4:$AJ$4,0))))+SUMPRODUCT((Inputs!$E$5:$E$190=$B7)*ISNUMBER(INDEX(Inputs!$K$5:$AJ$190,0,MATCH(AJ$2,Inputs!$K$4:$AJ$4,0))))=0,NA(),SUMPRODUCT((Inputs!$A$5:$A$190=$B7)*Inputs!$B$5:$B$190*(((Inputs!$G$5:$G$190="moeda")+(Inputs!$G$5:$G$190="acoes"))*Inputs!$B$1+((Inputs!$G$5:$G$190<>"moeda")*(Inputs!$G$5:$G$190<>"acoes")))*INDEX(Inputs!$K$5:$AJ$190,0,MATCH(AJ$2,Inputs!$K$4:$AJ$4,0)))+SUMPRODUCT((Inputs!$C$5:$C$190=$B7)*Inputs!$D$5:$D$190*(((Inputs!$G$5:$G$190="moeda")+(Inputs!$G$5:$G$190="acoes"))*Inputs!$B$1+((Inputs!$G$5:$G$190<>"moeda")*(Inputs!$G$5:$G$190<>"acoes")))*INDEX(Inputs!$K$5:$AJ$190,0,MATCH(AJ$2,Inputs!$K$4:$AJ$4,0)))+SUMPRODUCT((Inputs!$E$5:$E$190=$B7)*Inputs!$F$5:$F$190*(((Inputs!$G$5:$G$190="moeda")+(Inputs!$G$5:$G$190="acoes"))*Inputs!$B$1+((Inputs!$G$5:$G$190<>"moeda")*(Inputs!$G$5:$G$190<>"acoes")))*INDEX(Inputs!$K$5:$AJ$190,0,MATCH(AJ$2,Inputs!$K$4:$AJ$4,0))))) -> -290.25134 | AK7: =IF(ISNA(MATCH(AK$2,Inputs!$K$4:$AJ$4,0)),NA(),IF(SUMPRODUCT((Inputs!$A$5:$A$190=$B7)*ISNUMBER(INDEX(Inputs!$K$5:$AJ$190,0,MATCH(AK$2,Inputs!$K$4:$AJ$4,0))))+SUMPRODUCT((Inputs!$C$5:$C$190=$B7)*ISNUMBER(INDEX(Inputs!$K$5:$AJ$190,0,MATCH(AK$2,Inputs!$K$4:$AJ$4,0))))+SUMPRODUCT((Inputs!$E$5:$E$190=$B7)*ISNUMBER(INDEX(Inputs!$K$5:$AJ$190,0,MATCH(AK$2,Inputs!$K$4:$AJ$4,0))))=0,NA(),SUMPRODUCT((Inputs!$A$5:$A$190=$B7)*Inputs!$B$5:$B$190*(((Inputs!$G$5:$G$190="moeda")+(Inputs!$G$5:$G$190="acoes"))*Inputs!$B$1+((Inputs!$G$5:$G$190<>"moeda")*(Inputs!$G$5:$G$190<>"acoes")))*INDEX(Inputs!$K$5:$AJ$190,0,MATCH(AK$2,Inputs!$K$4:$AJ$4,0)))+SUMPRODUCT((Inputs!$C$5:$C$190=$B7)*Inputs!$D$5:$D$190*(((Inputs!$G$5:$G$190="moeda")+(Inputs!$G$5:$G$190="acoes"))*Inputs!$B$1+((Inputs!$G$5:$G$190<>"moeda")*(Inputs!$G$5:$G$190<>"acoes")))*INDEX(Inputs!$K$5:$AJ$190,0,MATCH(AK$2,Inputs!$K$4:$AJ$4,0)))+SUMPRODUCT((Inputs!$E$5:$E$190=$B7)*Inputs!$F$5:$F$190*(((Inputs!$G$5:$G$190="moeda")+(Inputs!$G$5:$G$190="acoes"))*Inputs!$B$1+((Inputs!$G$5:$G$190<>"moeda")*(Inputs!$G$5:$G$190<>"acoes")))*INDEX(Inputs!$K$5:$AJ$190,0,MATCH(AK$2,Inputs!$K$4:$AJ$4,0))))) -> -274.10759 | AL7: =SUM(AH7:AK7) -> -1111.9514
