Workbook

Sheet Inputs
A1: Fator p/ milhões: | B1: 1 | D1: Shell plc (SHEL, CIK 1306965) - fonte: Quarterly Databook Q2 2026 do RI (shell.com/investors). Moeda: USD. Brutos já em USD milhões (fator = 1). Trimestre isolado (a soma dos quatro trimestres fecha o ano, arredondamento de US$ 1 mi). Série da fonte: 1T21 a 2T26. 1T20-4T20 ficam vazios: o databook vigente começa em Q1 2021. IFRS: DRE em etapa única, sem lucro operacional divulgado.
J2: Trimestre | K2: 1Q20 | L2: 2Q20 | M2: 3Q20 | N2: 4Q20 | O2: 1Q21 | P2: 2Q21 | Q2: 3Q21 | R2: 4Q21 | S2: 1Q22 | T2: 2Q22 | U2: 3Q22 | V2: 4Q22 | W2: 1Q23 | X2: 2Q23 | Y2: 3Q23 | Z2: 4Q23 | AA2: 1Q24 | AB2: 2Q24 | AC2: 3Q24 | AD2: 4Q24 | AE2: 1Q25 | AF2: 2Q25 | AG2: 3Q25 | AH2: 4Q25 | AI2: 1Q26 | AJ2: 2Q26
A4: COD1 | B4: SINAL1 | C4: COD2 | D4: SINAL2 | E4: COD3 | F4: SINAL3 | G4: UNID | H4: Conta (PT) / origem | I4: Account (EN) | J4: ORIGEM | K4: 1Q20 | L4: 2Q20 | M4: 3Q20 | N4: 4Q20 | O4: 1Q21 | P4: 2Q21 | Q4: 3Q21 | R4: 4Q21 | S4: 1Q22 | T4: 2Q22 | U4: 3Q22 | V4: 4Q22 | W4: 1Q23 | X4: 2Q23 | Y4: 3Q23 | Z4: 4Q23 | AA4: 1Q24 | AB4: 2Q24 | AC4: 3Q24 | AD4: 4Q24 | AE4: 1Q25 | AF4: 2Q25 | AG4: 3Q25 | AH4: 4Q25 | AI4: 1Q26 | AJ4: 2Q26
H5: DRE - trimestre isolado (USD milhões). Fonte: aba Statement of Income do databook
A6: 1 | B6: 1 | G6: moeda | H6: Receita [Revenue] databook Statement of Income | J6: fonte | O6: 55665 | P6: 60515 | Q6: 60044 | R6: 85280 | S6: 84204 | T6: 100059 | U6: 95749 | V6: 101303 | W6: 86959 | X6: 74578 | Y6: 76350 | Z6: 78732 | AA6: 72478 | AB6: 74463 | AC6: 71089 | AD6: 66281 | AE6: 69234 | AF6: 65406 | AG6: 68153 | AH6: 64093 | AI6: 69691 | AJ6: 94664
A7: 2 | B7: -1 | G7: moeda | H7: Compras / custo da receita (divulgado positivo) [Purchases] | J7: fonte | O7: 34369 | P7: 39717 | Q7: 44260 | R7: 56566 | S7: 55657 | T7: 66658 | U7: 70684 | V7: 65489 | W7: 57502 | X7: 51492 | Y7: 49144 | Z7: 54745 | AA7: 46867 | AB7: 49417 | AC7: 48225 | AD7: 43610 | AE7: 45849 | AF7: 44099 | AG7: 45145 | AH7: 42102 | AI7: 44775 | AJ7: 64530
G8: moeda | H8: Despesas de produção e fabricação [Production and manufacturing expenses] (memória; entram nas despesas operacionais) | J8: memoria | O8: 6808 | P8: 5162 | Q8: 5322 | R8: 6530 | S8: 6029 | T8: 6359 | U8: 5910 | V8: 7220 | W8: 6008 | X8: 6041 | Y8: 6384 | Z8: 6807 | AA8: 5810 | AB8: 5593 | AC8: 6138 | AD8: 5839 | AE8: 5549 | AF8: 4909 | AG8: 5609 | AH8: 5830 | AI8: 5745 | AJ8: 5476
G9: moeda | H9: Despesas de vendas, distribuição e administrativas [Selling, distribution and administrative expenses] | J9: memoria | O9: 2462 | P9: 3107 | Q9: 2892 | R9: 2867 | S9: 3239 | T9: 2924 | U9: 3229 | V9: 3491 | W9: 3051 | X9: 3314 | Y9: 3447 | Z9: 3621 | AA9: 2975 | AB9: 3094 | AC9: 3139 | AD9: 3231 | AE9: 2840 | AF9: 3077 | AG9: 3258 | AH9: 3432 | AI9: 2803 | AJ9: 2911
G10: moeda | H10: P&D [Research and development] | J10: memoria | O10: 166 | P10: 201 | Q10: 145 | R10: 304 | S10: 189 | T10: 264 | U10: 220 | V10: 403 | W10: 253 | X10: 297 | Y10: 267 | Z10: 469 | AA10: 212 | AB10: 263 | AC10: 294 | AD10: 331 | AE10: 185 | AF10: 278 | AG10: 409 | AH10: 298 | AI10: 167 | AJ10: 277
G11: moeda | H11: Exploração [Exploration] | J11: memoria | O11: 285 | P11: 332 | Q11: 526 | R11: 280 | S11: 269 | T11: 370 | U11: 424 | V11: 649 | W11: 404 | X11: 444 | Y11: 436 | Z11: 467 | AA11: 750 | AB11: 496 | AC11: 305 | AD11: 861 | AE11: 210 | AF11: 360 | AG11: 175 | AH11: 391 | AI11: 98 | AJ11: 110
G12: moeda | H12: Lucro operacional DERIVADO = receita − compras − produção − vendas/adm − P&D − exploração − D&A. A Shell não divulga EBIT; JV e outras receitas ficam no não operacional. | J12: memoria | O12: 5679 | P12: 3773 | Q12: 541 | R12: 12288 | S12: 12526 | T12: 23832 | U12: 9158 | V12: 17592 | W12: 13456 | X12: 5118 | Y12: 10761 | Z12: 1402 | AA12: 9983 | AB12: 8045 | AC12: 7072 | AD12: 4889 | AE12: 9160 | AF12: 6013 | AG12: 6950 | AH12: 5459 | AI12: 10360 | AJ12: 15177
A13: 3 | B13: -1 | G13: moeda | H13: Despesas operacionais = receita − custo − lucro operacional (produção, vendas/adm, P&D, exploração, D&A) | J13: derivada | O13: =N(O6)-N(O7)-N(O12) -> 15617 | P13: =N(P6)-N(P7)-N(P12) -> 17025 | Q13: =N(Q6)-N(Q7)-N(Q12) -> 15243 | R13: =N(R6)-N(R7)-N(R12) -> 16426 | S13: =N(S6)-N(S7)-N(S12) -> 16021 | T13: =N(T6)-N(T7)-N(T12) -> 9569 | U13: =N(U6)-N(U7)-N(U12) -> 15907 | V13: =N(V6)-N(V7)-N(V12) -> 18222 | ... AJ13: =N(AJ6)-N(AJ7)-N(AJ12) -> 14957
G14: moeda | H14: Lucro antes do IR [Income/(loss) before taxation] | J14: memoria | O14: 8237 | P14: 4130 | Q14: 1193 | R14: 16269 | S14: 10776 | T14: 26160 | U14: 11435 | V14: 16443 | W14: 14354 | X14: 5348 | Y14: 11291 | Z14: 1635 | AA14: 11044 | AB14: 7404 | AC14: 7270 | AD14: 4205 | AE14: 8959 | AF14: 5975 | AG14: 7924 | AH14: 6898 | AI14: 9328 | AJ14: 15754
A15: 6 | B15: 1 | G15: moeda | H15: Resultado não operacional total = lucro antes do IR − lucro operacional (JV + outras receitas − juros) | J15: derivada | O15: =N(O14)-N(O12) -> 2558 | P15: =N(P14)-N(P12) -> 357 | Q15: =N(Q14)-N(Q12) -> 652 | R15: =N(R14)-N(R12) -> 3981 | S15: =N(S14)-N(S12) -> -1750 | T15: =N(T14)-N(T12) -> 2328 | U15: =N(U14)-N(U12) -> 2277 | V15: =N(V14)-N(V12) -> -1149 | ... AJ15: =N(AJ14)-N(AJ12) -> 577
G16: moeda | H16: Equivalência patrimonial [Share of profit/(loss) of joint ventures and associates] (memória; já está no código 6 via não operacional) | J16: memoria | O16: 995 | P16: 1114 | Q16: 1014 | R16: 975 | S16: -303 | T16: 2031 | U16: 2512 | V16: -268 | W16: 1581 | X16: 629 | Y16: 747 | Z16: 768 | AA16: 1318 | AB16: 898 | AC16: 933 | AD16: -156 | AE16: 615 | AF16: 712 | AG16: 507 | AH16: -215 | AI16: -93 | AJ16: 642
G17: moeda | H17: Juros e outras receitas/(despesas) [Interest and other income/(expenses)] (memória; já está no código 6 via não operacional) | J17: memoria | O17: 2455 | P17: 134 | Q17: 497 | R17: 3968 | S17: -737 | T17: 993 | U17: 498 | V17: 160 | W17: 481 | X17: 813 | Y17: 913 | Z17: 631 | AA17: 907 | AB17: -305 | AC17: 440 | AD17: 683 | AE17: 302 | AF17: 326 | AG17: 1751 | AH17: 2848 | AI17: 535 | AJ17: 1048
A18: 5 | B18: -1 | C18: 6 | D18: 1 | G18: moeda | H18: Despesa de juros (divulgado positivo): COD1=5 lança; COD2=6 devolve ao não operacional, que já a contém [Interest expense] | J18: fonte | O18: 892 | P18: 893 | Q18: 859 | R18: 963 | S18: 711 | T18: 695 | U18: 734 | V18: 1040 | W18: 1165 | X18: 1211 | Y18: 1131 | Z18: 1166 | AA18: 1164 | AB18: 1235 | AC18: 1174 | AD18: 1213 | AE18: 1120 | AF18: 1075 | AG18: 1284 | AH18: 1193 | AI18: 1473 | AJ18: 1114
A19: 7 | B19: -1 | G19: moeda | H19: Imposto de renda (charge positivo / credit negativo) [Taxation charge/(credit)] | J19: fonte | O19: 2453 | P19: 571 | Q19: 1510 | R19: 4665 | S19: 3457 | T19: 7922 | U19: 4587 | V19: 5975 | W19: 5582 | X19: 2195 | Y19: 4115 | Z19: 1099 | AA19: 3604 | AB19: 3754 | AC19: 2879 | AD19: 3164 | AE19: 4083 | AF19: 2332 | AG19: 2504 | AH19: 2718 | AI19: 3570 | AJ19: 4949
A20: 9 | B20: -1 | G20: moeda | H20: Lucro atribuído a não controladores [Income/(loss) attributable to non-controlling interest] | J20: fonte | O20: 124 | P20: 131 | Q20: 130 | R20: 144 | S20: 203 | T20: 198 | U20: 104 | V20: 59 | W20: 64 | X20: 20 | Y20: 132 | Z20: 62 | AA20: 82 | AB20: 133 | AC20: 100 | AD20: 113 | AE20: 95 | AF20: 43 | AG20: 98 | AH20: 46 | AI20: 64 | AJ20: -16
G21: moeda | H21: Lucro líquido atribuído à Shell plc [Income/(loss) attributable to Shell plc shareholders] | J21: memoria | O21: 5660 | P21: 3428 | Q21: -447 | R21: 11461 | S21: 7116 | T21: 18040 | U21: 6743 | V21: 10409 | W21: 8709 | X21: 3134 | Y21: 7044 | Z21: 474 | AA21: 7358 | AB21: 3517 | AC21: 4291 | AD21: 928 | AE21: 4780 | AF21: 3601 | AG21: 5322 | AH21: 4134 | AI21: 5694 | AJ21: 10821
A22: 8 | B22: 1 | G22: moeda | H22: Resultado após IR não classificado: lucro − (LAIR − IR − minoritários); absorve arredondamento de US$ 1 mi | J22: derivada | O22: =N(O21)-(N(O14)-N(O19)-N(O20)) -> 0 | P22: =N(P21)-(N(P14)-N(P19)-N(P20)) -> 0 | Q22: =N(Q21)-(N(Q14)-N(Q19)-N(Q20)) -> 0 | R22: =N(R21)-(N(R14)-N(R19)-N(R20)) -> 1 | S22: =N(S21)-(N(S14)-N(S19)-N(S20)) -> 0 | T22: =N(T21)-(N(T14)-N(T19)-N(T20)) -> 0 | U22: =N(U21)-(N(U14)-N(U19)-N(U20)) -> -1 | V22: =N(V21)-(N(V14)-N(V19)-N(V20)) -> 0 | ... AJ22: =N(AJ21)-(N(AJ14)-N(AJ19)-N(AJ20)) -> 0
A23: 44 | B23: 1 | G23: moeda | H23: Lucro líquido (check IS, código 44) | J23: derivada | O23: =N(O21) -> 5660 | P23: =N(P21) -> 3428 | Q23: =N(Q21) -> -447 | R23: =N(R21) -> 11461 | S23: =N(S21) -> 7116 | T23: =N(T21) -> 18040 | U23: =N(U21) -> 6743 | V23: =N(V21) -> 10409 | ... AJ23: =N(AJ21) -> 10821
H24: DFC - trimestre isolado (USD milhões). Dividendos: databook negativo, lançados em valor absoluto
A25: 4 | B25: -1 | C25: 3 | D25: 1 | G25: moeda | H25: D&A da DRE. COD1=4 lança; COD2=3 devolve às despesas operacionais (a D&A vem em linha própria, não no custo) [Depreciation, depletion and amortisation] | J25: fonte | O25: 5896 | P25: 8223 | Q25: 6358 | R25: 6445 | S25: 6295 | T25: -348 | U25: 6124 | V25: 6459 | W25: 6285 | X25: 7872 | Y25: 5911 | Z25: 11221 | AA25: 5881 | AB25: 7555 | AC25: 5916 | AD25: 7520 | AE25: 5441 | AF25: 6670 | AG25: 6607 | AH25: 6581 | AI25: 5743 | AJ25: 6183
A26: 10 | B26: -1 | G26: moeda | H26: Dividendos pagos aos acionistas da Shell plc (valor absoluto do fluxo) [Cash dividends paid to Shell plc shareholders] | J26: fonte | O26: 1292 | P26: 1310 | Q26: 1812 | R26: 1838 | S26: 1950 | T26: 1851 | U26: 1818 | V26: 1785 | W26: 2029 | X26: 1983 | Y26: 2179 | Z26: 2201 | AA26: 2210 | AB26: 2177 | AC26: 2167 | AD26: 2114 | AE26: 2179 | AF26: 2122 | AG26: 2103 | AH26: 2068 | AI26: 2100 | AJ26: 2164
G27: moeda | H27: CFO [Cash flow from operating activities] memória | J27: memoria | O27: 8294 | P27: 12617 | Q27: 16025 | R27: 8170 | S27: 14815 | T27: 18655 | U27: 12539 | V27: 22404 | W27: 14159 | X27: 15130 | Y27: 12332 | Z27: 12575 | AA27: 13330 | AB27: 13508 | AC27: 14684 | AD27: 13162 | AE27: 9281 | AF27: 11937 | AG27: 12207 | AH27: 9438 | AI27: 6062 | AJ27: 21432
G28: moeda | H28: CFI [Cash flow from investing activities] memória | J28: memoria | O28: -590 | P28: -2946 | Q28: -3804 | R28: 2579 | S28: -4273 | T28: -6207 | U28: -5049 | V28: -6918 | W28: -4238 | X28: -3015 | Y28: -4827 | Z28: -5657 | AA28: -3528 | AB28: -3338 | AC28: -3857 | AD28: -4431 | AE28: -3959 | AF28: -5406 | AG28: -2257 | AH28: -5190 | AI28: -3136 | AJ28: -3908
G29: moeda | H29: CFF [Cash flow from financing activities] memória | J29: memoria | O29: -8420 | P29: -6550 | Q29: -7930 | R29: -11764 | S29: -9019 | T29: -11150 | U29: -9707 | V29: -12078 | W29: -8385 | X29: -9003 | Y29: -9147 | Z29: -11703 | AA29: -8248 | AB29: -11846 | AC29: -7452 | AD29: -10889 | AE29: -9183 | AF29: -10106 | AG29: -9473 | AH29: -7049 | AI29: -9820 | AJ29: -9166
G30: moeda | H30: Capex (valor absoluto) [Capital expenditure] memória | J30: memoria | O30: 3885 | P30: 4232 | Q30: 4648 | R30: 6236 | S30: 4237 | T30: 6677 | U30: 5268 | V30: 6417 | W30: 6161 | X30: 4614 | Y30: 5259 | Z30: 6960 | AA30: 3980 | AB30: 4445 | AC30: 4690 | AD30: 6486 | AE30: 3748 | AF30: 5393 | AG30: 4557 | AH30: 5250 | AI30: 3757 | AJ30: 4031
H31: BALANÇO (USD milhões, saldo no fim do trimestre). IFRS: não circulante primeiro. Arrendamentos dentro de PPE e Debt.
A32: 20 | B32: 1 | G32: moeda | H32: Goodwill | J32: fonte | O32: 14086 | P32: 14019 | Q32: 13858 | R32: 14920 | S32: 15200 | T32: 15810 | U32: 15423 | V32: 16039 | W32: 17651 | X32: 17655 | Y32: 17345 | Z32: 16660 | AA32: 16554 | AB32: 16538 | AC32: 16600 | AD32: 16032 | AE32: 16072 | AF32: 16332 | AG32: 16034 | AH32: 15662 | AI32: 15189 | AJ32: 14969
A33: 21 | B33: 1 | G33: moeda | H33: Outros intangíveis [Other intangible assets] | J33: fonte | O33: 8786 | P33: 8443 | Q33: 8486 | R33: 9773 | S33: 9735 | T33: 9730 | U33: 8939 | V33: 9662 | W33: 9751 | X33: 8642 | Y33: 8288 | Z33: 10253 | AA33: 9999 | AB33: 9387 | AC33: 8188 | AD33: 9480 | AE33: 11365 | AF33: 11338 | AG33: 9546 | AH33: 11010 | AI33: 10873 | AJ33: 10449
A34: 18 | B34: 1 | G34: moeda | H34: Imobilizado (inclui direito de uso IFRS 16) [Property, plant and equipment] | J34: fonte | O34: 208298 | P34: 205272 | Q34: 196261 | R34: 194932 | S34: 193301 | T34: 200122 | U34: 193681 | V34: 198642 | W34: 199209 | X34: 197177 | Y34: 197043 | Z34: 194835 | AA34: 191952 | AB34: 189656 | AC34: 191721 | AD34: 185219 | AE34: 183712 | AF34: 186461 | AG34: 183907 | AH34: 185077 | AI34: 185708 | AJ34: 182300
A35: 17 | B35: 1 | G35: moeda | H35: Investimentos em joint ventures e coligadas | J35: fonte | O35: 22537 | P35: 23248 | Q35: 23724 | R35: 23415 | S35: 23289 | T35: 23264 | U35: 24489 | V35: 23864 | W35: 24843 | X35: 24434 | Y35: 24477 | Z35: 24457 | AA35: 25113 | AB35: 25098 | AC35: 25764 | AD35: 23445 | AE35: 24236 | AF35: 23456 | AG35: 23729 | AH35: 27775 | AI35: 27579 | AJ35: 27997
A36: 22 | B36: 1 | G36: moeda | H36: Investimentos em títulos [Investments in securities] | J36: fonte | O36: 3341 | P36: 3554 | Q36: 3662 | R36: 3797 | S36: 3550 | T36: 3507 | U36: 3491 | V36: 3362 | W36: 3357 | X36: 3431 | Y36: 3329 | Z36: 3246 | AA36: 3033 | AB36: 2972 | AC36: 3062 | AD36: 2255 | AE36: 2284 | AF36: 2225 | AG36: 1592 | AH36: 1557 | AI36: 1554 | AJ36: 1479
A37: 14 | B37: 1 | G37: moeda | H37: IR diferido ativo [Deferred tax, não circulante] | J37: fonte | O37: 13871 | P37: 14392 | Q37: 14542 | R37: 12426 | S37: 11420 | T37: 8575 | U37: 7885 | V37: 7815 | W37: 6716 | X37: 6238 | Y37: 5537 | Z37: 6454 | AA37: 6217 | AB37: 5888 | AC37: 6114 | AD37: 6857 | AE37: 6989 | AF37: 7524 | AG37: 8088 | AH37: 8173 | AI37: 7474 | AJ37: 6606
A38: 22 | B38: 1 | G38: moeda | H38: Ativo de benefícios de aposentadoria [Retirement benefits] | J38: fonte | O38: 5845 | P38: 7941 | Q38: 8009 | R38: 8471 | S38: 9548 | T38: 14973 | U38: 13314 | V38: 10200 | W38: 10330 | X38: 10398 | Y38: 9654 | Z38: 9151 | AA38: 9151 | AB38: 9454 | AC38: 10564 | AD38: 10003 | AE38: 10266 | AF38: 10980 | AG38: 5527 | AH38: 5052 | AI38: 5192 | AJ38: 5306
A39: 22 | B39: 1 | G39: moeda | H39: Contas a receber não circulantes [Trade and other receivables] | J39: fonte | O39: 7396 | P39: 7798 | Q39: 7605 | R39: 7065 | S39: 6218 | T39: 5853 | U39: 5841 | V39: 6920 | W39: 6184 | X39: 6031 | Y39: 6049 | Z39: 6298 | AA39: 6548 | AB39: 6808 | AC39: 6883 | AD39: 6018 | AE39: 7269 | AF39: 7315 | AG39: 7472 | AH39: 8252 | AI39: 7294 | AJ39: 8017
A40: 22 | B40: 1 | G40: moeda | H40: Derivativos ativo não circulante | J40: fonte | O40: 1681 | P40: 1508 | Q40: 1052 | R40: 815 | S40: 705 | T40: 839 | U40: 978 | V40: 582 | W40: 540 | X40: 541 | Y40: 524 | Z40: 801 | AA40: 381 | AB40: 348 | AC40: 498 | AD40: 374 | AE40: 400 | AF40: 692 | AG40: 665 | AH40: 619 | AI40: 573 | AJ40: 558
A41: 13 | B41: 1 | G41: moeda | H41: Estoques [Inventories] | J41: fonte | O41: 22680 | P41: 25097 | Q41: 24596 | R41: 25258 | S41: 30008 | T41: 36087 | U41: 34721 | V41: 31894 | W41: 28579 | X41: 26975 | Y41: 30230 | Z41: 26019 | AA41: 26471 | AB41: 26449 | AC41: 24143 | AD41: 23426 | AE41: 22984 | AF41: 23283 | AG41: 22913 | AH41: 22216 | AI41: 28700 | AJ41: 26639
A42: 12 | B42: 1 | G42: moeda | H42: Contas a receber circulantes [Trade and other receivables] | J42: fonte | O42: 40142 | P42: 43694 | Q42: 46366 | R42: 53208 | S42: 63481 | T42: 66708 | U42: 66699 | V42: 66510 | W42: 61738 | X42: 52383 | Y42: 52077 | Z42: 53273 | AA42: 53178 | AB42: 50619 | AC42: 46782 | AD42: 45860 | AE42: 48247 | AF42: 45570 | AG42: 45287 | AH42: 44597 | AI42: 53891 | AJ42: 52938
A43: 16 | B43: 1 | G43: moeda | H43: Derivativos ativo circulante | J43: fonte | O43: 5752 | P43: 8787 | Q43: 14613 | R43: 11369 | S43: 18708 | T43: 23257 | U43: 23585 | V43: 24437 | W43: 18148 | X43: 15616 | Y43: 14724 | Z43: 15098 | AA43: 12730 | AB43: 11724 | AC43: 10233 | AD43: 9673 | AE43: 8941 | AF43: 9443 | AG43: 9103 | AH43: 9114 | AI43: 11086 | AJ43: 9487
A44: 11 | B44: 1 | G44: moeda | H44: Caixa e equivalentes [Cash and cash equivalents] | J44: fonte | O44: 30985 | P44: 34104 | Q44: 38073 | R44: 36970 | S44: 38360 | T44: 38970 | U44: 35978 | V44: 40246 | W44: 42074 | X44: 45094 | Y44: 43031 | Z44: 38774 | AA44: 39949 | AB44: 38148 | AC44: 42252 | AD44: 39110 | AE44: 35601 | AF44: 32682 | AG44: 33053 | AH44: 30216 | AI44: 23117 | AJ44: 31374
A45: 16 | B45: 1 | G45: moeda | H45: Ativos classificados como mantidos para venda | J45: fonte | Q45: 7922 | R45: 1960 | S45: 1464 | T45: 203 | U45: 2335 | V45: 2851 | W45: 33 | X45: 417 | Y45: 1189 | Z45: 951 | AA45: 762 | AB45: 1692 | AC45: 2144 | AD45: 9857 | AE45: 10881 | AF45: 10619 | AG45: 10819 | AH45: 1030 | AI45: 2367 | AJ45: 2395
A46: 30 | B46: 1 | G46: moeda | H46: Dívida não circulante (inclui arrendamentos) [Debt] | J46: fonte | O46: 87828 | P46: 87034 | Q46: 84705 | R46: 80868 | S46: 79021 | T46: 77220 | U46: 73944 | V46: 74794 | W46: 76098 | X46: 72252 | Y46: 72028 | Z46: 71610 | AA46: 68886 | AB46: 64619 | AC46: 64597 | AD46: 65448 | AE46: 65120 | AF46: 65218 | AG46: 63955 | AH46: 66515 | AI46: 65585 | AJ46: 64534
A47: 34 | B47: 1 | G47: moeda | H47: Fornecedores e outras contas não circulantes | J47: fonte | O47: 2670 | P47: 2885 | Q47: 2224 | R47: 2075 | S47: 2516 | T47: 3829 | U47: 3475 | V47: 3432 | W47: 4215 | X47: 4440 | Y47: 3920 | Z47: 3103 | AA47: 3909 | AB47: 4471 | AC47: 3864 | AD47: 3290 | AE47: 5487 | AF47: 5876 | AG47: 4671 | AH47: 4463 | AI47: 5119 | AJ47: 7290
A48: 34 | B48: 1 | G48: moeda | H48: Derivativos passivo não circulante | J48: fonte | O48: 554 | P48: 385 | Q48: 571 | R48: 887 | S48: 1551 | T48: 3238 | U48: 5110 | V48: 3563 | W48: 3099 | X48: 3080 | Y48: 3257 | Z48: 2301 | AA48: 2338 | AB48: 2438 | AC48: 1749 | AD48: 2185 | AE48: 1565 | AF48: 1037 | AG48: 885 | AH48: 1108 | AI48: 1161 | AJ48: 1069
A49: 33 | B49: 1 | G49: moeda | H49: IR diferido passivo | J49: fonte | O49: 11285 | P49: 11717 | Q49: 12159 | R49: 12547 | S49: 13021 | T49: 16145 | U49: 16893 | V49: 16186 | W49: 16464 | X49: 15955 | Y49: 15891 | Z49: 15347 | AA49: 15179 | AB49: 15293 | AC49: 15487 | AD49: 13505 | AE49: 13257 | AF49: 12921 | AG49: 11955 | AH49: 11983 | AI49: 11884 | AJ49: 11831
A50: 34 | B50: 1 | G50: moeda | H50: Passivo de benefícios de aposentadoria | J50: fonte | O50: 12348 | P50: 12435 | Q50: 11835 | R50: 11325 | S50: 10464 | T50: 8693 | U50: 7475 | V50: 7296 | W50: 7379 | X50: 7491 | Y50: 6837 | Z50: 7549 | AA50: 7101 | AB50: 6701 | AC50: 7110 | AD50: 6752 | AE50: 6756 | AF50: 6983 | AG50: 7632 | AH50: 7136 | AI50: 6876 | AJ50: 6635
A51: 34 | B51: 1 | G51: moeda | H51: Descomissionamento e outras provisões não circulantes | J51: fonte | O51: 27330 | P51: 27657 | Q51: 26361 | R51: 25804 | S51: 25583 | T51: 25798 | U51: 21551 | V51: 23845 | W51: 23691 | X51: 23592 | Y51: 23492 | Z51: 22531 | AA51: 22412 | AB51: 22574 | AC51: 22979 | AD51: 21227 | AE51: 20313 | AF51: 20777 | AG51: 21197 | AH51: 21411 | AI51: 21899 | AJ51: 21758
A52: 27 | B52: 1 | G52: moeda | H52: Dívida circulante (inclui arrendamentos) [Debt] | J52: fonte | O52: 14541 | P52: 13042 | Q52: 10686 | R52: 8218 | S52: 7027 | T52: 6521 | U52: 8046 | V52: 9001 | W52: 9044 | X52: 12114 | Y52: 10119 | Z52: 9931 | AA52: 11046 | AB52: 10849 | AC52: 12015 | AD52: 11630 | AE52: 11391 | AF52: 10457 | AG52: 10022 | AH52: 9128 | AI52: 10060 | AJ52: 8542
A53: 23 | B53: 1 | G53: moeda | H53: Fornecedores e outras contas circulantes | J53: fonte | O53: 49456 | P53: 54948 | Q53: 59722 | R53: 63173 | S53: 71741 | T53: 75445 | U53: 70341 | V53: 79357 | W53: 68857 | X53: 63996 | Y53: 67188 | Z53: 68237 | AA53: 65997 | AB53: 63943 | AC53: 61076 | AD53: 60693 | AE53: 60870 | AF53: 58379 | AG53: 56816 | AH53: 57770 | AI53: 64288 | AJ53: 60742
A54: 26 | B54: 1 | G54: moeda | H54: Derivativos passivo circulante | J54: fonte | O54: 5260 | P54: 10385 | Q54: 26118 | R54: 16311 | S54: 26496 | T54: 28881 | U54: 32011 | V54: 23779 | W54: 15863 | X54: 12513 | Y54: 9444 | Z54: 9529 | AA54: 8919 | AB54: 8138 | AC54: 6775 | AD54: 7391 | AE54: 6371 | AF54: 6451 | AG54: 5924 | AH54: 5664 | AI54: 10324 | AJ54: 7225
A55: 25 | B55: 1 | G55: moeda | H55: Impostos a pagar [Income taxes payable] | J55: fonte | O55: 3372 | P55: 2837 | Q55: 2809 | R55: 3254 | S55: 3752 | T55: 4506 | U55: 4332 | V55: 4869 | W55: 5924 | X55: 4462 | Y55: 4372 | Z55: 3422 | AA55: 3940 | AB55: 4087 | AC55: 4289 | AD55: 4648 | AE55: 4343 | AF55: 3642 | AG55: 3447 | AH55: 3150 | AI55: 3883 | AJ55: 4349
A56: 26 | B56: 1 | G56: moeda | H56: Descomissionamento e outras provisões circulantes | J56: fonte | O56: 3802 | P56: 3290 | Q56: 3139 | R56: 3338 | S56: 3225 | T56: 2943 | U56: 2459 | V56: 2910 | W56: 2989 | X56: 3037 | Y56: 3223 | Z56: 4041 | AA56: 3714 | AB56: 3622 | AC56: 4171 | AD56: 4469 | AE56: 5104 | AF56: 5234 | AG56: 5657 | AH56: 5884 | AI56: 3963 | AJ56: 3935
A57: 26 | B57: 1 | G57: moeda | H57: Passivos associados a ativos mantidos para venda | J57: fonte | Q57: 1758 | R57: 1253 | S57: 1057 | T57: 382 | U57: 1483 | V57: 1395 | W57: 0 | X57: 6 | Y57: 786 | Z57: 307 | AA57: 296 | AB57: 857 | AC57: 1298 | AD57: 6203 | AE57: 8001 | AF57: 7856 | AG57: 7755 | AH57: 820 | AI57: 955 | AJ57: 821
A58: 35 | B58: 1 | G58: moeda | H58: Participação de não controladores (balanço) | J58: fonte | O58: 3239 | P58: 3244 | Q58: 3293 | R58: 3360 | S58: 3535 | T58: 3799 | U58: 3715 | V58: 2125 | W58: 2214 | X58: 1633 | Y58: 1745 | Z58: 1755 | AA58: 1739 | AB58: 1783 | AC58: 1865 | AD58: 1861 | AE58: 1856 | AF58: 1951 | AG58: 1999 | AH58: 928 | AI58: 1018 | AJ58: 995
A59: 41 | B59: 1 | G59: moeda | H59: Patrimônio atribuível aos acionistas da Shell plc (capital, tesouraria e OCI não abertos na face condensada) | J59: fonte | O59: 163714 | P59: 167999 | Q59: 163390 | R59: 171966 | S59: 175998 | T59: 190500 | U59: 186523 | V59: 190472 | W59: 193317 | X59: 190461 | Y59: 191199 | Z59: 186607 | AA59: 186565 | AB59: 185407 | AC59: 187673 | AD59: 178303 | AE59: 178813 | AF59: 181137 | AG59: 175823 | AH59: 174392 | AI59: 173583 | AJ59: 180786
A60: 16 | B60: 1 | G60: moeda | H60: Diferença de arredondamento do ativo (total divulgado − soma das linhas; < US$ 50 mi) | J60: derivada | U60: -1 | W60: 1 | X60: 1 | Y60: 1 | AA60: 1 | AB60: 2 | AC60: 1 | AD60: -2 | AE60: 1 | AG60: 3 | AH60: 1 | AI60: 1 | AJ60: -1
A61: 26 | B61: 1 | G61: moeda | H61: Diferença de arredondamento do passivo + PL (total divulgado − soma das linhas; < US$ 50 mi) | J61: derivada | O61: 1 | P61: -1 | Q61: -1 | T61: -2 | X61: 1 | Y61: -3 | AA61: -2 | AB61: 1 | AC61: 1 | AD61: 2 | AE61: 1 | AF61: 1 | AH61: -1 | AJ61: 1
G62: moeda | H62: [vazio] código 15: Despesas antecipadas: não abertas na face condensada | J62: derivada
G63: moeda | H63: [vazio] código 19: Direito de uso: dentro do imobilizado (IFRS 16) | J63: derivada
G64: moeda | H64: [vazio] código 24: Despesas provisionadas: dentro de fornecedores | J64: derivada
G65: moeda | H65: [vazio] código 28: Revolving: dentro da dívida | J65: derivada
G66: moeda | H66: [vazio] código 29: Arrendamento CP: dentro da dívida circulante | J66: derivada
G67: moeda | H67: [vazio] código 31: Arrendamento LP: dentro da dívida não circulante | J67: derivada
G68: moeda | H68: [vazio] código 32: Dívida conversível: não divulgada | J68: derivada
G69: moeda | H69: [vazio] código 37: Capital + APIC: não aberto (tudo no código 41) | J69: derivada
G70: moeda | H70: [vazio] código 38: Tesouraria: não aberta (tudo no código 41) | J70: derivada
G71: moeda | H71: [vazio] código 39: Outros resultados abrangentes: não abertos (tudo no código 41) | J71: derivada
G72: moeda | H72: [vazio] código 40: Outras contas do PL | J72: derivada
H73: BALANÇO - totais divulgados (memória)
G74: moeda | H74: Total do ativo [Total assets] | J74: memoria | O74: 385400 | P74: 397857 | Q74: 408769 | R74: 404379 | S74: 424987 | T74: 447898 | U74: 437358 | V74: 443024 | W74: 429154 | X74: 415033 | Y74: 413498 | Z74: 406270 | AA74: 402039 | AB74: 394783 | AC74: 394949 | AD74: 387607 | AE74: 389248 | AF74: 387920 | AG74: 377738 | AH74: 370351 | AI74: 380598 | AJ74: 380513
G75: moeda | H75: Total do passivo + PL [Total liabilities and equity] | J75: memoria | O75: 385400 | P75: 397857 | Q75: 408769 | R75: 404379 | S75: 424987 | T75: 447898 | U75: 437358 | V75: 443024 | W75: 429154 | X75: 415033 | Y75: 413498 | Z75: 406270 | AA75: 402039 | AB75: 394783 | AC75: 394949 | AD75: 387607 | AE75: 389248 | AF75: 387920 | AG75: 377738 | AH75: 370351 | AI75: 380598 | AJ75: 380513
H76: CHECKS (devem ser 0)
G77: moeda | H77: CHECK: contas de ativo - ativo total (USD milhões) | J77: derivada | O77: =ROUND(N(O32)+N(O33)+N(O34)+N(O35)+N(O36)+N(O37)+N(O38)+N(O39)+N(O40)+N(O41)+N(O42)+N(O43)+N(O44)+N(O45)+N(O60)-N(O74),1) -> 0 | P77: =ROUND(N(P32)+N(P33)+N(P34)+N(P35)+N(P36)+N(P37)+N(P38)+N(P39)+N(P40)+N(P41)+N(P42)+N(P43)+N(P44)+N(P45)+N(P60)-N(P74),1) -> 0 | Q77: =ROUND(N(Q32)+N(Q33)+N(Q34)+N(Q35)+N(Q36)+N(Q37)+N(Q38)+N(Q39)+N(Q40)+N(Q41)+N(Q42)+N(Q43)+N(Q44)+N(Q45)+N(Q60)-N(Q74),1) -> 0 | R77: =ROUND(N(R32)+N(R33)+N(R34)+N(R35)+N(R36)+N(R37)+N(R38)+N(R39)+N(R40)+N(R41)+N(R42)+N(R43)+N(R44)+N(R45)+N(R60)-N(R74),1) -> 0 | S77: =ROUND(N(S32)+N(S33)+N(S34)+N(S35)+N(S36)+N(S37)+N(S38)+N(S39)+N(S40)+N(S41)+N(S42)+N(S43)+N(S44)+N(S45)+N(S60)-N(S74),1) -> 0 | T77: =ROUND(N(T32)+N(T33)+N(T34)+N(T35)+N(T36)+N(T37)+N(T38)+N(T39)+N(T40)+N(T41)+N(T42)+N(T43)+N(T44)+N(T45)+N(T60)-N(T74),1) -> 0 | U77: =ROUND(N(U32)+N(U33)+N(U34)+N(U35)+N(U36)+N(U37)+N(U38)+N(U39)+N(U40)+N(U41)+N(U42)+N(U43)+N(U44)+N(U45)+N(U60)-N(U74),1) -> 0 | V77: =ROUND(N(V32)+N(V33)+N(V34)+N(V35)+N(V36)+N(V37)+N(V38)+N(V39)+N(V40)+N(V41)+N(V42)+N(V43)+N(V44)+N(V45)+N(V60)-N(V74),1) -> 0 | ... AJ77: =ROUND(N(AJ32)+N(AJ33)+N(AJ34)+N(AJ35)+N(AJ36)+N(AJ37)+N(AJ38)+N(AJ39)+N(AJ40)+N(AJ41)+N(AJ42)+N(AJ43)+N(AJ44)+N(AJ45)+N(AJ60)-N(AJ74),1) -> 0
G78: moeda | H78: CHECK: passivo + PL (contas) - passivo + PL total | J78: derivada | O78: =ROUND(N(O46)+N(O47)+N(O48)+N(O49)+N(O50)+N(O51)+N(O52)+N(O53)+N(O54)+N(O55)+N(O56)+N(O57)+N(O58)+N(O59)+N(O61)-N(O75),1) -> 0 | P78: =ROUND(N(P46)+N(P47)+N(P48)+N(P49)+N(P50)+N(P51)+N(P52)+N(P53)+N(P54)+N(P55)+N(P56)+N(P57)+N(P58)+N(P59)+N(P61)-N(P75),1) -> 0 | Q78: =ROUND(N(Q46)+N(Q47)+N(Q48)+N(Q49)+N(Q50)+N(Q51)+N(Q52)+N(Q53)+N(Q54)+N(Q55)+N(Q56)+N(Q57)+N(Q58)+N(Q59)+N(Q61)-N(Q75),1) -> 0 | R78: =ROUND(N(R46)+N(R47)+N(R48)+N(R49)+N(R50)+N(R51)+N(R52)+N(R53)+N(R54)+N(R55)+N(R56)+N(R57)+N(R58)+N(R59)+N(R61)-N(R75),1) -> 0 | S78: =ROUND(N(S46)+N(S47)+N(S48)+N(S49)+N(S50)+N(S51)+N(S52)+N(S53)+N(S54)+N(S55)+N(S56)+N(S57)+N(S58)+N(S59)+N(S61)-N(S75),1) -> 0 | T78: =ROUND(N(T46)+N(T47)+N(T48)+N(T49)+N(T50)+N(T51)+N(T52)+N(T53)+N(T54)+N(T55)+N(T56)+N(T57)+N(T58)+N(T59)+N(T61)-N(T75),1) -> 0 | U78: =ROUND(N(U46)+N(U47)+N(U48)+N(U49)+N(U50)+N(U51)+N(U52)+N(U53)+N(U54)+N(U55)+N(U56)+N(U57)+N(U58)+N(U59)+N(U61)-N(U75),1) -> 0 | V78: =ROUND(N(V46)+N(V47)+N(V48)+N(V49)+N(V50)+N(V51)+N(V52)+N(V53)+N(V54)+N(V55)+N(V56)+N(V57)+N(V58)+N(V59)+N(V61)-N(V75),1) -> 0 | ... AJ78: =ROUND(N(AJ46)+N(AJ47)+N(AJ48)+N(AJ49)+N(AJ50)+N(AJ51)+N(AJ52)+N(AJ53)+N(AJ54)+N(AJ55)+N(AJ56)+N(AJ57)+N(AJ58)+N(AJ59)+N(AJ61)-N(AJ75),1) -> 0
H79: CHECK: receita - custo - despesas + não operacional - IR - minoritários + outros após IR - lucro (deve ser 0) | J79: derivada | O79: =ROUND(N(O6)-N(O7)-N(O13)+N(O15)-N(O19)-N(O20)+N(O22)-N(O23),1) -> 0 | P79: =ROUND(N(P6)-N(P7)-N(P13)+N(P15)-N(P19)-N(P20)+N(P22)-N(P23),1) -> 0 | Q79: =ROUND(N(Q6)-N(Q7)-N(Q13)+N(Q15)-N(Q19)-N(Q20)+N(Q22)-N(Q23),1) -> 0 | R79: =ROUND(N(R6)-N(R7)-N(R13)+N(R15)-N(R19)-N(R20)+N(R22)-N(R23),1) -> 0 | S79: =ROUND(N(S6)-N(S7)-N(S13)+N(S15)-N(S19)-N(S20)+N(S22)-N(S23),1) -> 0 | T79: =ROUND(N(T6)-N(T7)-N(T13)+N(T15)-N(T19)-N(T20)+N(T22)-N(T23),1) -> 0 | U79: =ROUND(N(U6)-N(U7)-N(U13)+N(U15)-N(U19)-N(U20)+N(U22)-N(U23),1) -> 0 | V79: =ROUND(N(V6)-N(V7)-N(V13)+N(V15)-N(V19)-N(V20)+N(V22)-N(V23),1) -> 0 | ... AJ79: =ROUND(N(AJ6)-N(AJ7)-N(AJ13)+N(AJ15)-N(AJ19)-N(AJ20)+N(AJ22)-N(AJ23),1) -> 0
H80: [vazio] 1T20-4T20: o Quarterly Databook Q2 2026 começa em Q1 2021. Não interpolar.
H81: [vazio] Direito de uso e arrendamentos: a face condensada IFRS junta no imobilizado e na dívida.
H83: DRIVERS DE RECEITA (codigos 45+): receita de terceiros por segmento (Integrated Gas, Upstream, Marketing, Chemicals & Products, Renewables and Energy Solutions) e Adjusted Earnings por segmento — Quarterly Databook Q2 2026 do RI (USD milhões, fator 1).
A84: 45 | B84: 1 | G84: moeda | H84: Integrated Gas - receita de terceiros (USD mi) | J84: fonte | O84: 6022 | P84: 5537 | Q84: 5661 | R84: 12702 | S84: 14074 | T84: 12403 | U84: 14471 | V84: 13802 | W84: 10932 | X84: 7938 | Y84: 8338 | Z84: 10437 | AA84: 9195 | AB84: 9052 | AC84: 9748 | AD84: 9294 | AE84: 9602 | AF84: 9576 | AG84: 9736 | AH84: 9542 | AI84: 7748 | AJ84: 11278
A85: 46 | B85: 1 | G85: moeda | H85: Upstream - receita de terceiros (USD mi) | J85: fonte | O85: 1936 | P85: 2281 | Q85: 2360 | R85: 2605 | S85: 1531 | T85: 2253 | U85: 1623 | V85: 2945 | W85: 2062 | X85: 1533 | Y85: 1617 | Z85: 1263 | AA85: 1759 | AB85: 1590 | AC85: 1605 | AD85: 1652 | AE85: 1510 | AF85: 1193 | AG85: 844 | AH85: 1559 | AI85: 1400 | AJ85: 1800
A86: 47 | B86: 1 | G86: moeda | H86: Marketing - receita de terceiros (USD mi) | J86: fonte | O86: 20111 | P86: 24745 | Q86: 27470 | R86: 29486 | S86: 32406 | T86: 42065 | U86: 39598 | V86: 35371 | W86: 32045 | X86: 31517 | Y86: 35236 | Z86: 31761 | AA86: 30041 | AB86: 32005 | AC86: 30519 | AD86: 27524 | AE86: 27083 | AF86: 28241 | AG86: 29648 | AH86: 26881 | AI86: 30695 | AJ86: 38015
A87: 48 | B87: 1 | G87: moeda | H87: Chemicals & Products - receita de terceiros (USD mi) | J87: fonte | O87: 22356 | P87: 24282 | Q87: 23213 | R87: 28279 | S87: 27150 | T87: 31850 | U87: 30016 | V87: 26525 | W87: 26290 | X87: 23712 | Y87: 22119 | Z87: 24957 | AA87: 23735 | AB87: 24583 | AC87: 22608 | AD87: 19992 | AE87: 21610 | AF87: 18388 | AG87: 19418 | AH87: 17655 | AI87: 19221 | AJ87: 34235
A88: 49 | B88: 1 | G88: moeda | H88: Renewables and Energy Solutions - receita de terceiros (USD mi) | J88: fonte | O88: 5227 | P88: 3658 | Q88: 1330 | R88: 12200 | S88: 9026 | T88: 11477 | U88: 10031 | V88: 22656 | W88: 15619 | X88: 9866 | Y88: 9032 | Z88: 10302 | AA88: 7737 | AB88: 7222 | AC88: 6599 | AD88: 7808 | AE88: 9417 | AF88: 7996 | AG88: 8500 | AH88: 8446 | AI88: 10622 | AJ88: 9338
A89: 50 | B89: 1 | G89: moeda | H89: Integrated Gas - Adjusted Earnings (USD mi) | J89: fonte | O89: 1570 | P89: 1605 | Q89: 1837 | R89: 4036 | S89: 4094 | T89: 3760 | U89: 2321 | V89: 5971 | W89: 4919 | X89: 2500 | Y89: 2530 | Z89: 3968 | AA89: 3680 | AB89: 2675 | AC89: 2871 | AD89: 2165 | AE89: 2483 | AF89: 1737 | AG89: 2143 | AH89: 1661 | AI89: 1819 | AJ89: 2691
A90: 51 | B90: 1 | G90: moeda | H90: Upstream - Adjusted Earnings (USD mi) | J90: fonte | O90: 933 | P90: 2511 | Q90: 1734 | R90: 2838 | S90: 3454 | T90: 4917 | U90: 5903 | V90: 3080 | W90: 2810 | X90: 1699 | Y90: 2236 | Z90: 3060 | AA90: 1933 | AB90: 2336 | AC90: 2443 | AD90: 1682 | AE90: 2337 | AF90: 1732 | AG90: 1804 | AH90: 1570 | AI90: 2377 | AJ90: 3485
A91: 52 | B91: 1 | G91: moeda | H91: Marketing - Adjusted Earnings (USD mi) | J91: fonte | O91: 845 | P91: 982 | Q91: 1171 | R91: 616 | S91: 822 | T91: 637 | U91: 1028 | V91: 418 | W91: 946 | X91: 931 | Y91: 641 | Z91: 794 | AA91: 781 | AB91: 1082 | AC91: 1182 | AD91: 839 | AE91: 900 | AF91: 1199 | AG91: 1316 | AH91: 578 | AI91: 1334 | AJ91: 1329
A92: 53 | B92: 1 | G92: moeda | H92: Chemicals & Products - Adjusted Earnings (USD mi) | J92: fonte | O92: 739 | P92: 962 | Q92: 404 | R92: -135 | S92: 1086 | T92: 2154 | U92: 571 | V92: 782 | W92: 1707 | X92: 419 | Y92: 1463 | Z92: 29 | AA92: 1615 | AB92: 1085 | AC92: 463 | AD92: -229 | AE92: 449 | AF92: 118 | AG92: 550 | AH92: -66 | AI92: 1925 | AJ92: 2877
A93: 54 | B93: 1 | G93: moeda | H93: Renewables and Energy Solutions - Adjusted Earnings (USD mi) | J93: fonte | O93: -102 | P93: -13 | Q93: -171 | R93: 43 | S93: 348 | T93: 730 | U93: 389 | V93: 310 | W93: 395 | X93: 238 | Y93: -52 | Z93: 173 | AA93: 163 | AB93: -187 | AC93: -162 | AD93: -311 | AE93: -42 | AF93: -9 | AG93: 92 | AH93: 131 | AI93: 348 | AJ93: 79
A94: 55 | B94: 1 | G94: moeda | H94: Corporate - Adjusted Earnings (USD mi) | J94: fonte | O94: -666 | P94: -399 | Q94: -732 | R94: -889 | S94: -560 | T94: -644 | U94: -594 | V94: -674 | W94: -1057 | X94: -689 | Y94: -519 | Z94: -609 | AA94: -368 | AB94: -576 | AC94: -643 | AD94: -380 | AE94: -457 | AF94: -463 | AG94: -383 | AH94: -567 | AI94: -908 | AJ94: -617
H95: Notas: receita de terceiros as reported (aba de cada segmento, linha Third-party abaixo de Revenue:). A soma dos cinco segmentos difere da receita do grupo em até US$ 17 mi (1T22); no 2T26 a diferença é de US$ −2 mi. Não interpolar o residual — a Shell não abre essa linha na face de segmentos (Corporate não tem receita de terceiros própria no databook). Intersegmento fica de fora (é eliminado na consolidação). Adjusted Earnings é a abertura de resultado que a Shell usa no release, não EBIT IFRS. Série: 1T21-2T26. 1T20-4T20 vazios: o databook vigente começa em Q1 2021.
H133: CONVENCOES
H134: Linhas de origem: 5 a 95. As formulas da Inputs (2) varrem as linhas 5 a 130; as linhas 96 a 130 estao livres para novas contas.
H135: Periodos: colunas K a AJ = 1Q20 a 2Q26. Primeiro trimestre com dado = 1Q21.
H136: Brutos em USD milhões: fator da célula B1 = 1. UNID = moeda.
H137: ORIGEM: fonte = databook; memoria = como divulgado, sem codigo; derivada = formula nesta aba.
H138: Balanço: PL dos controladores no código 41 (face condensada não abre capital/tesouraria/OCI).
H139: Codigos 45 a 55: drivers de receita (memoria); alimentam o bloco logo abaixo da receita liquida no Model.

Sheet Inputs (2)
A1: =COUNTIF($B$3:$B$1048576,$B$1) -> 1 | B1: =MAX($B$3:$B$1048576) -> 55
D2: 1Q21 | E2: 2Q21 | F2: 3Q21 | G2: 4Q21 | H2: 2021 | I2: 1Q22 | J2: 2Q22 | K2: 3Q22 | L2: 4Q22 | M2: 2022 | N2: 1Q23 | O2: 2Q23 | P2: 3Q23 | Q2: 4Q23 | R2: 2023 | S2: 1Q24 | T2: 2Q24 | U2: 3Q24 | V2: 4Q24 | W2: 2024 | X2: 1Q25 | Y2: 2Q25 | Z2: 3Q25 | AA2: 4Q25 | AB2: 2025 | AC2: 1Q26 | AD2: 2Q26 | AE2: 3Q26 | AF2: 4Q26 | AG2: 2026 | AH2: 1Q20 | AI2: 2Q20 | AJ2: 3Q20 | AK2: 4Q20 | AL2: 2020 | AN2: Sem dado na fonte: 1Q20-4Q20 (databook começa em 1Q21); 3Q26, 4Q26 e 2026 (rotulo em cinza).
B4: 1 | C4: Net Revenues | D4: =IF(ISNA(MATCH(D$2,Inputs!$K$4:$AJ$4,0)),NA(),IF(SUMPRODUCT((Inputs!$A$5:$A$130=$B4)*ISNUMBER(INDEX(Inputs!$K$5:$AJ$130,0,MATCH(D$2,Inputs!$K$4:$AJ$4,0))))+SUMPRODUCT((Inputs!$C$5:$C$130=$B4)*ISNUMBER(INDEX(Inputs!$K$5:$AJ$130,0,MATCH(D$2,Inputs!$K$4:$AJ$4,0))))+SUMPRODUCT((Inputs!$E$5:$E$130=$B4)*ISNUMBER(INDEX(Inputs!$K$5:$AJ$130,0,MATCH(D$2,Inputs!$K$4:$AJ$4,0))))=0,NA(),SUMPRODUCT((Inputs!$A$5:$A$130=$B4)*Inputs!$B$5:$B$130*(((Inputs!$G$5:$G$130="moeda")+(Inputs!$G$5:$G$130="acoes"))*Inputs!$B$1+((Inputs!$G$5:$G$130<>"moeda")*(Inputs!$G$5:$G$130<>"acoes")))*INDEX(Inputs!$K$5:$AJ$130,0,MATCH(D$2,Inputs!$K$4:$AJ$4,0)))+SUMPRODUCT((Inputs!$C$5:$C$130=$B4)*Inputs!$D$5:$D$130*(((Inputs!$G$5:$G$130="moeda")+(Inputs!$G$5:$G$130="acoes"))*Inputs!$B$1+((Inputs!$G$5:$G$130<>"moeda")*(Inputs!$G$5:$G$130<>"acoes")))*INDEX(Inputs!$K$5:$AJ$130,0,MATCH(D$2,Inputs!$K$4:$AJ$4,0)))+SUMPRODUCT((Inputs!$E$5:$E$130=$B4)*Inputs!$F$5:$F$130*(((Inputs!$G$5:$G$130="moeda")+(Inputs!$G$5:$G$130="acoes"))*Inputs!$B$1+((Inputs!$G$5:$G$130<>"moeda")*(Inputs!$G$5:$G$130<>"acoes")))*INDEX(Inputs!$K$5:$AJ$130,0,MATCH(D$2,Inputs!$K$4:$AJ$4,0))))) -> 55665 | E4: =IF(ISNA(MATCH(E$2,Inputs!$K$4:$AJ$4,0)),NA(),IF(SUMPRODUCT((Inputs!$A$5:$A$130=$B4)*ISNUMBER(INDEX(Inputs!$K$5:$AJ$130,0,MATCH(E$2,Inputs!$K$4:$AJ$4,0))))+SUMPRODUCT((Inputs!$C$5:$C$130=$B4)*ISNUMBER(INDEX(Inputs!$K$5:$AJ$130,0,MATCH(E$2,Inputs!$K$4:$AJ$4,0))))+SUMPRODUCT((Inputs!$E$5:$E$130=$B4)*ISNUMBER(INDEX(Inputs!$K$5:$AJ$130,0,MATCH(E$2,Inputs!$K$4:$AJ$4,0))))=0,NA(),SUMPRODUCT((Inputs!$A$5:$A$130=$B4)*Inputs!$B$5:$B$130*(((Inputs!$G$5:$G$130="moeda")+(Inputs!$G$5:$G$130="acoes"))*Inputs!$B$1+((Inputs!$G$5:$G$130<>"moeda")*(Inputs!$G$5:$G$130<>"acoes")))*INDEX(Inputs!$K$5:$AJ$130,0,MATCH(E$2,Inputs!$K$4:$AJ$4,0)))+SUMPRODUCT((Inputs!$C$5:$C$130=$B4)*Inputs!$D$5:$D$130*(((Inputs!$G$5:$G$130="moeda")+(Inputs!$G$5:$G$130="acoes"))*Inputs!$B$1+((Inputs!$G$5:$G$130<>"moeda")*(Inputs!$G$5:$G$130<>"acoes")))*INDEX(Inputs!$K$5:$AJ$130,0,MATCH(E$2,Inputs!$K$4:$AJ$4,0)))+SUMPRODUCT((Inputs!$E$5:$E$130=$B4)*Inputs!$F$5:$F$130*(((Inputs!$G$5:$G$130="moeda")+(Inputs!$G$5:$G$130="acoes"))*Inputs!$B$1+((Inputs!$G$5:$G$130<>"moeda")*(Inputs!$G$5:$G$130<>"acoes")))*INDEX(Inputs!$K$5:$AJ$130,0,MATCH(E$2,Inputs!$K$4:$AJ$4,0))))) -> 60515 | F4: =IF(ISNA(MATCH(F$2,Inputs!$K$4:$AJ$4,0)),NA(),IF(SUMPRODUCT((Inputs!$A$5:$A$130=$B4)*ISNUMBER(INDEX(Inputs!$K$5:$AJ$130,0,MATCH(F$2,Inputs!$K$4:$AJ$4,0))))+SUMPRODUCT((Inputs!$C$5:$C$130=$B4)*ISNUMBER(INDEX(Inputs!$K$5:$AJ$130,0,MATCH(F$2,Inputs!$K$4:$AJ$4,0))))+SUMPRODUCT((Inputs!$E$5:$E$130=$B4)*ISNUMBER(INDEX(Inputs!$K$5:$AJ$130,0,MATCH(F$2,Inputs!$K$4:$AJ$4,0))))=0,NA(),SUMPRODUCT((Inputs!$A$5:$A$130=$B4)*Inputs!$B$5:$B$130*(((Inputs!$G$5:$G$130="moeda")+(Inputs!$G$5:$G$130="acoes"))*Inputs!$B$1+((Inputs!$G$5:$G$130<>"moeda")*(Inputs!$G$5:$G$130<>"acoes")))*INDEX(Inputs!$K$5:$AJ$130,0,MATCH(F$2,Inputs!$K$4:$AJ$4,0)))+SUMPRODUCT((Inputs!$C$5:$C$130=$B4)*Inputs!$D$5:$D$130*(((Inputs!$G$5:$G$130="moeda")+(Inputs!$G$5:$G$130="acoes"))*Inputs!$B$1+((Inputs!$G$5:$G$130<>"moeda")*(Inputs!$G$5:$G$130<>"acoes")))*INDEX(Inputs!$K$5:$AJ$130,0,MATCH(F$2,Inputs!$K$4:$AJ$4,0)))+SUMPRODUCT((Inputs!$E$5:$E$130=$B4)*Inputs!$F$5:$F$130*(((Inputs!$G$5:$G$130="moeda")+(Inputs!$G$5:$G$130="acoes"))*Inputs!$B$1+((Inputs!$G$5:$G$130<>"moeda")*(Inputs!$G$5:$G$130<>"acoes")))*INDEX(Inputs!$K$5:$AJ$130,0,MATCH(F$2,Inputs!$K$4:$AJ$4,0))))) -> 60044 | G4: =IF(ISNA(MATCH(G$2,Inputs!$K$4:$AJ$4,0)),NA(),IF(SUMPRODUCT((Inputs!$A$5:$A$130=$B4)*ISNUMBER(INDEX(Inputs!$K$5:$AJ$130,0,MATCH(G$2,Inputs!$K$4:$AJ$4,0))))+SUMPRODUCT((Inputs!$C$5:$C$130=$B4)*ISNUMBER(INDEX(Inputs!$K$5:$AJ$130,0,MATCH(G$2,Inputs!$K$4:$AJ$4,0))))+SUMPRODUCT((Inputs!$E$5:$E$130=$B4)*ISNUMBER(INDEX(Inputs!$K$5:$AJ$130,0,MATCH(G$2,Inputs!$K$4:$AJ$4,0))))=0,NA(),SUMPRODUCT((Inputs!$A$5:$A$130=$B4)*Inputs!$B$5:$B$130*(((Inputs!$G$5:$G$130="moeda")+(Inputs!$G$5:$G$130="acoes"))*Inputs!$B$1+((Inputs!$G$5:$G$130<>"moeda")*(Inputs!$G$5:$G$130<>"acoes")))*INDEX(Inputs!$K$5:$AJ$130,0,MATCH(G$2,Inputs!$K$4:$AJ$4,0)))+SUMPRODUCT((Inputs!$C$5:$C$130=$B4)*Inputs!$D$5:$D$130*(((Inputs!$G$5:$G$130="moeda")+(Inputs!$G$5:$G$130="acoes"))*Inputs!$B$1+((Inputs!$G$5:$G$130<>"moeda")*(Inputs!$G$5:$G$130<>"acoes")))*INDEX(Inputs!$K$5:$AJ$130,0,MATCH(G$2,Inputs!$K$4:$AJ$4,0)))+SUMPRODUCT((Inputs!$E$5:$E$130=$B4)*Inputs!$F$5:$F$130*(((Inputs!$G$5:$G$130="moeda")+(Inputs!$G$5:$G$130="acoes"))*Inputs!$B$1+((Inputs!$G$5:$G$130<>"moeda")*(Inputs!$G$5:$G$130<>"acoes")))*INDEX(Inputs!$K$5:$AJ$130,0,MATCH(G$2,Inputs!$K$4:$AJ$4,0))))) -> 85280 | H4: =SUM(D4:G4) -> 261504 | I4: =IF(ISNA(MATCH(I$2,Inputs!$K$4:$AJ$4,0)),NA(),IF(SUMPRODUCT((Inputs!$A$5:$A$130=$B4)*ISNUMBER(INDEX(Inputs!$K$5:$AJ$130,0,MATCH(I$2,Inputs!$K$4:$AJ$4,0))))+SUMPRODUCT((Inputs!$C$5:$C$130=$B4)*ISNUMBER(INDEX(Inputs!$K$5:$AJ$130,0,MATCH(I$2,Inputs!$K$4:$AJ$4,0))))+SUMPRODUCT((Inputs!$E$5:$E$130=$B4)*ISNUMBER(INDEX(Inputs!$K$5:$AJ$130,0,MATCH(I$2,Inputs!$K$4:$AJ$4,0))))=0,NA(),SUMPRODUCT((Inputs!$A$5:$A$130=$B4)*Inputs!$B$5:$B$130*(((Inputs!$G$5:$G$130="moeda")+(Inputs!$G$5:$G$130="acoes"))*Inputs!$B$1+((Inputs!$G$5:$G$130<>"moeda")*(Inputs!$G$5:$G$130<>"acoes")))*INDEX(Inputs!$K$5:$AJ$130,0,MATCH(I$2,Inputs!$K$4:$AJ$4,0)))+SUMPRODUCT((Inputs!$C$5:$C$130=$B4)*Inputs!$D$5:$D$130*(((Inputs!$G$5:$G$130="moeda")+(Inputs!$G$5:$G$130="acoes"))*Inputs!$B$1+((Inputs!$G$5:$G$130<>"moeda")*(Inputs!$G$5:$G$130<>"acoes")))*INDEX(Inputs!$K$5:$AJ$130,0,MATCH(I$2,Inputs!$K$4:$AJ$4,0)))+SUMPRODUCT((Inputs!$E$5:$E$130=$B4)*Inputs!$F$5:$F$130*(((Inputs!$G$5:$G$130="moeda")+(Inputs!$G$5:$G$130="acoes"))*Inputs!$B$1+((Inputs!$G$5:$G$130<>"moeda")*(Inputs!$G$5:$G$130<>"acoes")))*INDEX(Inputs!$K$5:$AJ$130,0,MATCH(I$2,Inputs!$K$4:$AJ$4,0))))) -> 84204 | J4: =IF(ISNA(MATCH(J$2,Inputs!$K$4:$AJ$4,0)),NA(),IF(SUMPRODUCT((Inputs!$A$5:$A$130=$B4)*ISNUMBER(INDEX(Inputs!$K$5:$AJ$130,0,MATCH(J$2,Inputs!$K$4:$AJ$4,0))))+SUMPRODUCT((Inputs!$C$5:$C$130=$B4)*ISNUMBER(INDEX(Inputs!$K$5:$AJ$130,0,MATCH(J$2,Inputs!$K$4:$AJ$4,0))))+SUMPRODUCT((Inputs!$E$5:$E$130=$B4)*ISNUMBER(INDEX(Inputs!$K$5:$AJ$130,0,MATCH(J$2,Inputs!$K$4:$AJ$4,0))))=0,NA(),SUMPRODUCT((Inputs!$A$5:$A$130=$B4)*Inputs!$B$5:$B$130*(((Inputs!$G$5:$G$130="moeda")+(Inputs!$G$5:$G$130="acoes"))*Inputs!$B$1+((Inputs!$G$5:$G$130<>"moeda")*(Inputs!$G$5:$G$130<>"acoes")))*INDEX(Inputs!$K$5:$AJ$130,0,MATCH(J$2,Inputs!$K$4:$AJ$4,0)))+SUMPRODUCT((Inputs!$C$5:$C$130=$B4)*Inputs!$D$5:$D$130*(((Inputs!$G$5:$G$130="moeda")+(Inputs!$G$5:$G$130="acoes"))*Inputs!$B$1+((Inputs!$G$5:$G$130<>"moeda")*(Inputs!$G$5:$G$130<>"acoes")))*INDEX(Inputs!$K$5:$AJ$130,0,MATCH(J$2,Inputs!$K$4:$AJ$4,0)))+SUMPRODUCT((Inputs!$E$5:$E$130=$B4)*Inputs!$F$5:$F$130*(((Inputs!$G$5:$G$130="moeda")+(Inputs!$G$5:$G$130="acoes"))*Inputs!$B$1+((Inputs!$G$5:$G$130<>"moeda")*(Inputs!$G$5:$G$130<>"acoes")))*INDEX(Inputs!$K$5:$AJ$130,0,MATCH(J$2,Inputs!$K$4:$AJ$4,0))))) -> 100059 | K4: =IF(ISNA(MATCH(K$2,Inputs!$K$4:$AJ$4,0)),NA(),IF(SUMPRODUCT((Inputs!$A$5:$A$130=$B4)*ISNUMBER(INDEX(Inputs!$K$5:$AJ$130,0,MATCH(K$2,Inputs!$K$4:$AJ$4,0))))+SUMPRODUCT((Inputs!$C$5:$C$130=$B4)*ISNUMBER(INDEX(Inputs!$K$5:$AJ$130,0,MATCH(K$2,Inputs!$K$4:$AJ$4,0))))+SUMPRODUCT((Inputs!$E$5:$E$130=$B4)*ISNUMBER(INDEX(Inputs!$K$5:$AJ$130,0,MATCH(K$2,Inputs!$K$4:$AJ$4,0))))=0,NA(),SUMPRODUCT((Inputs!$A$5:$A$130=$B4)*Inputs!$B$5:$B$130*(((Inputs!$G$5:$G$130="moeda")+(Inputs!$G$5:$G$130="acoes"))*Inputs!$B$1+((Inputs!$G$5:$G$130<>"moeda")*(Inputs!$G$5:$G$130<>"acoes")))*INDEX(Inputs!$K$5:$AJ$130,0,MATCH(K$2,Inputs!$K$4:$AJ$4,0)))+SUMPRODUCT((Inputs!$C$5:$C$130=$B4)*Inputs!$D$5:$D$130*(((Inputs!$G$5:$G$130="moeda")+(Inputs!$G$5:$G$130="acoes"))*Inputs!$B$1+((Inputs!$G$5:$G$130<>"moeda")*(Inputs!$G$5:$G$130<>"acoes")))*INDEX(Inputs!$K$5:$AJ$130,0,MATCH(K$2,Inputs!$K$4:$AJ$4,0)))+SUMPRODUCT((Inputs!$E$5:$E$130=$B4)*Inputs!$F$5:$F$130*(((Inputs!$G$5:$G$130="moeda")+(Inputs!$G$5:$G$130="acoes"))*Inputs!$B$1+((Inputs!$G$5:$G$130<>"moeda")*(Inputs!$G$5:$G$130<>"acoes")))*INDEX(Inputs!$K$5:$AJ$130,0,MATCH(K$2,Inputs!$K$4:$AJ$4,0))))) -> 95749 | L4: =IF(ISNA(MATCH(L$2,Inputs!$K$4:$AJ$4,0)),NA(),IF(SUMPRODUCT((Inputs!$A$5:$A$130=$B4)*ISNUMBER(INDEX(Inputs!$K$5:$AJ$130,0,MATCH(L$2,Inputs!$K$4:$AJ$4,0))))+SUMPRODUCT((Inputs!$C$5:$C$130=$B4)*ISNUMBER(INDEX(Inputs!$K$5:$AJ$130,0,MATCH(L$2,Inputs!$K$4:$AJ$4,0))))+SUMPRODUCT((Inputs!$E$5:$E$130=$B4)*ISNUMBER(INDEX(Inputs!$K$5:$AJ$130,0,MATCH(L$2,Inputs!$K$4:$AJ$4,0))))=0,NA(),SUMPRODUCT((Inputs!$A$5:$A$130=$B4)*Inputs!$B$5:$B$130*(((Inputs!$G$5:$G$130="moeda")+(Inputs!$G$5:$G$130="acoes"))*Inputs!$B$1+((Inputs!$G$5:$G$130<>"moeda")*(Inputs!$G$5:$G$130<>"acoes")))*INDEX(Inputs!$K$5:$AJ$130,0,MATCH(L$2,Inputs!$K$4:$AJ$4,0)))+SUMPRODUCT((Inputs!$C$5:$C$130=$B4)*Inputs!$D$5:$D$130*(((Inputs!$G$5:$G$130="moeda")+(Inputs!$G$5:$G$130="acoes"))*Inputs!$B$1+((Inputs!$G$5:$G$130<>"moeda")*(Inputs!$G$5:$G$130<>"acoes")))*INDEX(Inputs!$K$5:$AJ$130,0,MATCH(L$2,Inputs!$K$4:$AJ$4,0)))+SUMPRODUCT((Inputs!$E$5:$E$130=$B4)*Inputs!$F$5:$F$130*(((Inputs!$G$5:$G$130="moeda")+(Inputs!$G$5:$G$130="acoes"))*Inputs!$B$1+((Inputs!$G$5:$G$130<>"moeda")*(Inputs!$G$5:$G$130<>"acoes")))*INDEX(Inputs!$K$5:$AJ$130,0,MATCH(L$2,Inputs!$K$4:$AJ$4,0))))) -> 101303 | M4: =SUM(I4:L4) -> 381315 | N4: =IF(ISNA(MATCH(N$2,Inputs!$K$4:$AJ$4,0)),NA(),IF(SUMPRODUCT((Inputs!$A$5:$A$130=$B4)*ISNUMBER(INDEX(Inputs!$K$5:$AJ$130,0,MATCH(N$2,Inputs!$K$4:$AJ$4,0))))+SUMPRODUCT((Inputs!$C$5:$C$130=$B4)*ISNUMBER(INDEX(Inputs!$K$5:$AJ$130,0,MATCH(N$2,Inputs!$K$4:$AJ$4,0))))+SUMPRODUCT((Inputs!$E$5:$E$130=$B4)*ISNUMBER(INDEX(Inputs!$K$5:$AJ$130,0,MATCH(N$2,Inputs!$K$4:$AJ$4,0))))=0,NA(),SUMPRODUCT((Inputs!$A$5:$A$130=$B4)*Inputs!$B$5:$B$130*(((Inputs!$G$5:$G$130="moeda")+(Inputs!$G$5:$G$130="acoes"))*Inputs!$B$1+((Inputs!$G$5:$G$130<>"moeda")*(Inputs!$G$5:$G$130<>"acoes")))*INDEX(Inputs!$K$5:$AJ$130,0,MATCH(N$2,Inputs!$K$4:$AJ$4,0)))+SUMPRODUCT((Inputs!$C$5:$C$130=$B4)*Inputs!$D$5:$D$130*(((Inputs!$G$5:$G$130="moeda")+(Inputs!$G$5:$G$130="acoes"))*Inputs!$B$1+((Inputs!$G$5:$G$130<>"moeda")*(Inputs!$G$5:$G$130<>"acoes")))*INDEX(Inputs!$K$5:$AJ$130,0,MATCH(N$2,Inputs!$K$4:$AJ$4,0)))+SUMPRODUCT((Inputs!$E$5:$E$130=$B4)*Inputs!$F$5:$F$130*(((Inputs!$G$5:$G$130="moeda")+(Inputs!$G$5:$G$130="acoes"))*Inputs!$B$1+((Inputs!$G$5:$G$130<>"moeda")*(Inputs!$G$5:$G$130<>"acoes")))*INDEX(Inputs!$K$5:$AJ$130,0,MATCH(N$2,Inputs!$K$4:$AJ$4,0))))) -> 86959 | O4: =IF(ISNA(MATCH(O$2,Inputs!$K$4:$AJ$4,0)),NA(),IF(SUMPRODUCT((Inputs!$A$5:$A$130=$B4)*ISNUMBER(INDEX(Inputs!$K$5:$AJ$130,0,MATCH(O$2,Inputs!$K$4:$AJ$4,0))))+SUMPRODUCT((Inputs!$C$5:$C$130=$B4)*ISNUMBER(INDEX(Inputs!$K$5:$AJ$130,0,MATCH(O$2,Inputs!$K$4:$AJ$4,0))))+SUMPRODUCT((Inputs!$E$5:$E$130=$B4)*ISNUMBER(INDEX(Inputs!$K$5:$AJ$130,0,MATCH(O$2,Inputs!$K$4:$AJ$4,0))))=0,NA(),SUMPRODUCT((Inputs!$A$5:$A$130=$B4)*Inputs!$B$5:$B$130*(((Inputs!$G$5:$G$130="moeda")+(Inputs!$G$5:$G$130="acoes"))*Inputs!$B$1+((Inputs!$G$5:$G$130<>"moeda")*(Inputs!$G$5:$G$130<>"acoes")))*INDEX(Inputs!$K$5:$AJ$130,0,MATCH(O$2,Inputs!$K$4:$AJ$4,0)))+SUMPRODUCT((Inputs!$C$5:$C$130=$B4)*Inputs!$D$5:$D$130*(((Inputs!$G$5:$G$130="moeda")+(Inputs!$G$5:$G$130="acoes"))*Inputs!$B$1+((Inputs!$G$5:$G$130<>"moeda")*(Inputs!$G$5:$G$130<>"acoes")))*INDEX(Inputs!$K$5:$AJ$130,0,MATCH(O$2,Inputs!$K$4:$AJ$4,0)))+SUMPRODUCT((Inputs!$E$5:$E$130=$B4)*Inputs!$F$5:$F$130*(((Inputs!$G$5:$G$130="moeda")+(Inputs!$G$5:$G$130="acoes"))*Inputs!$B$1+((Inputs!$G$5:$G$130<>"moeda")*(Inputs!$G$5:$G$130<>"acoes")))*INDEX(Inputs!$K$5:$AJ$130,0,MATCH(O$2,Inputs!$K$4:$AJ$4,0))))) -> 74578 | P4: =IF(ISNA(MATCH(P$2,Inputs!$K$4:$AJ$4,0)),NA(),IF(SUMPRODUCT((Inputs!$A$5:$A$130=$B4)*ISNUMBER(INDEX(Inputs!$K$5:$AJ$130,0,MATCH(P$2,Inputs!$K$4:$AJ$4,0))))+SUMPRODUCT((Inputs!$C$5:$C$130=$B4)*ISNUMBER(INDEX(Inputs!$K$5:$AJ$130,0,MATCH(P$2,Inputs!$K$4:$AJ$4,0))))+SUMPRODUCT((Inputs!$E$5:$E$130=$B4)*ISNUMBER(INDEX(Inputs!$K$5:$AJ$130,0,MATCH(P$2,Inputs!$K$4:$AJ$4,0))))=0,NA(),SUMPRODUCT((Inputs!$A$5:$A$130=$B4)*Inputs!$B$5:$B$130*(((Inputs!$G$5:$G$130="moeda")+(Inputs!$G$5:$G$130="acoes"))*Inputs!$B$1+((Inputs!$G$5:$G$130<>"moeda")*(Inputs!$G$5:$G$130<>"acoes")))*INDEX(Inputs!$K$5:$AJ$130,0,MATCH(P$2,Inputs!$K$4:$AJ$4,0)))+SUMPRODUCT((Inputs!$C$5:$C$130=$B4)*Inputs!$D$5:$D$130*(((Inputs!$G$5:$G$130="moeda")+(Inputs!$G$5:$G$130="acoes"))*Inputs!$B$1+((Inputs!$G$5:$G$130<>"moeda")*(Inputs!$G$5:$G$130<>"acoes")))*INDEX(Inputs!$K$5:$AJ$130,0,MATCH(P$2,Inputs!$K$4:$AJ$4,0)))+SUMPRODUCT((Inputs!$E$5:$E$130=$B4)*Inputs!$F$5:$F$130*(((Inputs!$G$5:$G$130="moeda")+(Inputs!$G$5:$G$130="acoes"))*Inputs!$B$1+((Inputs!$G$5:$G$130<>"moeda")*(Inputs!$G$5:$G$130<>"acoes")))*INDEX(Inputs!$K$5:$AJ$130,0,MATCH(P$2,Inputs!$K$4:$AJ$4,0))))) -> 76350 | Q4: =IF(ISNA(MATCH(Q$2,Inputs!$K$4:$AJ$4,0)),NA(),IF(SUMPRODUCT((Inputs!$A$5:$A$130=$B4)*ISNUMBER(INDEX(Inputs!$K$5:$AJ$130,0,MATCH(Q$2,Inputs!$K$4:$AJ$4,0))))+SUMPRODUCT((Inputs!$C$5:$C$130=$B4)*ISNUMBER(INDEX(Inputs!$K$5:$AJ$130,0,MATCH(Q$2,Inputs!$K$4:$AJ$4,0))))+SUMPRODUCT((Inputs!$E$5:$E$130=$B4)*ISNUMBER(INDEX(Inputs!$K$5:$AJ$130,0,MATCH(Q$2,Inputs!$K$4:$AJ$4,0))))=0,NA(),SUMPRODUCT((Inputs!$A$5:$A$130=$B4)*Inputs!$B$5:$B$130*(((Inputs!$G$5:$G$130="moeda")+(Inputs!$G$5:$G$130="acoes"))*Inputs!$B$1+((Inputs!$G$5:$G$130<>"moeda")*(Inputs!$G$5:$G$130<>"acoes")))*INDEX(Inputs!$K$5:$AJ$130,0,MATCH(Q$2,Inputs!$K$4:$AJ$4,0)))+SUMPRODUCT((Inputs!$C$5:$C$130=$B4)*Inputs!$D$5:$D$130*(((Inputs!$G$5:$G$130="moeda")+(Inputs!$G$5:$G$130="acoes"))*Inputs!$B$1+((Inputs!$G$5:$G$130<>"moeda")*(Inputs!$G$5:$G$130<>"acoes")))*INDEX(Inputs!$K$5:$AJ$130,0,MATCH(Q$2,Inputs!$K$4:$AJ$4,0)))+SUMPRODUCT((Inputs!$E$5:$E$130=$B4)*Inputs!$F$5:$F$130*(((Inputs!$G$5:$G$130="moeda")+(Inputs!$G$5:$G$130="acoes"))*Inputs!$B$1+((Inputs!$G$5:$G$130<>"moeda")*(Inputs!$G$5:$G$130<>"acoes")))*INDEX(Inputs!$K$5:$AJ$130,0,MATCH(Q$2,Inputs!$K$4:$AJ$4,0))))) -> 78732 | R4: =SUM(N4:Q4) -> 316619 | S4: =IF(ISNA(MATCH(S$2,Inputs!$K$4:$AJ$4,0)),NA(),IF(SUMPRODUCT((Inputs!$A$5:$A$130=$B4)*ISNUMBER(INDEX(Inputs!$K$5:$AJ$130,0,MATCH(S$2,Inputs!$K$4:$AJ$4,0))))+SUMPRODUCT((Inputs!$C$5:$C$130=$B4)*ISNUMBER(INDEX(Inputs!$K$5:$AJ$130,0,MATCH(S$2,Inputs!$K$4:$AJ$4,0))))+SUMPRODUCT((Inputs!$E$5:$E$130=$B4)*ISNUMBER(INDEX(Inputs!$K$5:$AJ$130,0,MATCH(S$2,Inputs!$K$4:$AJ$4,0))))=0,NA(),SUMPRODUCT((Inputs!$A$5:$A$130=$B4)*Inputs!$B$5:$B$130*(((Inputs!$G$5:$G$130="moeda")+(Inputs!$G$5:$G$130="acoes"))*Inputs!$B$1+((Inputs!$G$5:$G$130<>"moeda")*(Inputs!$G$5:$G$130<>"acoes")))*INDEX(Inputs!$K$5:$AJ$130,0,MATCH(S$2,Inputs!$K$4:$AJ$4,0)))+SUMPRODUCT((Inputs!$C$5:$C$130=$B4)*Inputs!$D$5:$D$130*(((Inputs!$G$5:$G$130="moeda")+(Inputs!$G$5:$G$130="acoes"))*Inputs!$B$1+((Inputs!$G$5:$G$130<>"moeda")*(Inputs!$G$5:$G$130<>"acoes")))*INDEX(Inputs!$K$5:$AJ$130,0,MATCH(S$2,Inputs!$K$4:$AJ$4,0)))+SUMPRODUCT((Inputs!$E$5:$E$130=$B4)*Inputs!$F$5:$F$130*(((Inputs!$G$5:$G$130="moeda")+(Inputs!$G$5:$G$130="acoes"))*Inputs!$B$1+((Inputs!$G$5:$G$130<>"moeda")*(Inputs!$G$5:$G$130<>"acoes")))*INDEX(Inputs!$K$5:$AJ$130,0,MATCH(S$2,Inputs!$K$4:$AJ$4,0))))) -> 72478 | T4: =IF(ISNA(MATCH(T$2,Inputs!$K$4:$AJ$4,0)),NA(),IF(SUMPRODUCT((Inputs!$A$5:$A$130=$B4)*ISNUMBER(INDEX(Inputs!$K$5:$AJ$130,0,MATCH(T$2,Inputs!$K$4:$AJ$4,0))))+SUMPRODUCT((Inputs!$C$5:$C$130=$B4)*ISNUMBER(INDEX(Inputs!$K$5:$AJ$130,0,MATCH(T$2,Inputs!$K$4:$AJ$4,0))))+SUMPRODUCT((Inputs!$E$5:$E$130=$B4)*ISNUMBER(INDEX(Inputs!$K$5:$AJ$130,0,MATCH(T$2,Inputs!$K$4:$AJ$4,0))))=0,NA(),SUMPRODUCT((Inputs!$A$5:$A$130=$B4)*Inputs!$B$5:$B$130*(((Inputs!$G$5:$G$130="moeda")+(Inputs!$G$5:$G$130="acoes"))*Inputs!$B$1+((Inputs!$G$5:$G$130<>"moeda")*(Inputs!$G$5:$G$130<>"acoes")))*INDEX(Inputs!$K$5:$AJ$130,0,MATCH(T$2,Inputs!$K$4:$AJ$4,0)))+SUMPRODUCT((Inputs!$C$5:$C$130=$B4)*Inputs!$D$5:$D$130*(((Inputs!$G$5:$G$130="moeda")+(Inputs!$G$5:$G$130="acoes"))*Inputs!$B$1+((Inputs!$G$5:$G$130<>"moeda")*(Inputs!$G$5:$G$130<>"acoes")))*INDEX(Inputs!$K$5:$AJ$130,0,MATCH(T$2,Inputs!$K$4:$AJ$4,0)))+SUMPRODUCT((Inputs!$E$5:$E$130=$B4)*Inputs!$F$5:$F$130*(((Inputs!$G$5:$G$130="moeda")+(Inputs!$G$5:$G$130="acoes"))*Inputs!$B$1+((Inputs!$G$5:$G$130<>"moeda")*(Inputs!$G$5:$G$130<>"acoes")))*INDEX(Inputs!$K$5:$AJ$130,0,MATCH(T$2,Inputs!$K$4:$AJ$4,0))))) -> 74463 | U4: =IF(ISNA(MATCH(U$2,Inputs!$K$4:$AJ$4,0)),NA(),IF(SUMPRODUCT((Inputs!$A$5:$A$130=$B4)*ISNUMBER(INDEX(Inputs!$K$5:$AJ$130,0,MATCH(U$2,Inputs!$K$4:$AJ$4,0))))+SUMPRODUCT((Inputs!$C$5:$C$130=$B4)*ISNUMBER(INDEX(Inputs!$K$5:$AJ$130,0,MATCH(U$2,Inputs!$K$4:$AJ$4,0))))+SUMPRODUCT((Inputs!$E$5:$E$130=$B4)*ISNUMBER(INDEX(Inputs!$K$5:$AJ$130,0,MATCH(U$2,Inputs!$K$4:$AJ$4,0))))=0,NA(),SUMPRODUCT((Inputs!$A$5:$A$130=$B4)*Inputs!$B$5:$B$130*(((Inputs!$G$5:$G$130="moeda")+(Inputs!$G$5:$G$130="acoes"))*Inputs!$B$1+((Inputs!$G$5:$G$130<>"moeda")*(Inputs!$G$5:$G$130<>"acoes")))*INDEX(Inputs!$K$5:$AJ$130,0,MATCH(U$2,Inputs!$K$4:$AJ$4,0)))+SUMPRODUCT((Inputs!$C$5:$C$130=$B4)*Inputs!$D$5:$D$130*(((Inputs!$G$5:$G$130="moeda")+(Inputs!$G$5:$G$130="acoes"))*Inputs!$B$1+((Inputs!$G$5:$G$130<>"moeda")*(Inputs!$G$5:$G$130<>"acoes")))*INDEX(Inputs!$K$5:$AJ$130,0,MATCH(U$2,Inputs!$K$4:$AJ$4,0)))+SUMPRODUCT((Inputs!$E$5:$E$130=$B4)*Inputs!$F$5:$F$130*(((Inputs!$G$5:$G$130="moeda")+(Inputs!$G$5:$G$130="acoes"))*Inputs!$B$1+((Inputs!$G$5:$G$130<>"moeda")*(Inputs!$G$5:$G$130<>"acoes")))*INDEX(Inputs!$K$5:$AJ$130,0,MATCH(U$2,Inputs!$K$4:$AJ$4,0))))) -> 71089 | V4: =IF(ISNA(MATCH(V$2,Inputs!$K$4:$AJ$4,0)),NA(),IF(SUMPRODUCT((Inputs!$A$5:$A$130=$B4)*ISNUMBER(INDEX(Inputs!$K$5:$AJ$130,0,MATCH(V$2,Inputs!$K$4:$AJ$4,0))))+SUMPRODUCT((Inputs!$C$5:$C$130=$B4)*ISNUMBER(INDEX(Inputs!$K$5:$AJ$130,0,MATCH(V$2,Inputs!$K$4:$AJ$4,0))))+SUMPRODUCT((Inputs!$E$5:$E$130=$B4)*ISNUMBER(INDEX(Inputs!$K$5:$AJ$130,0,MATCH(V$2,Inputs!$K$4:$AJ$4,0))))=0,NA(),SUMPRODUCT((Inputs!$A$5:$A$130=$B4)*Inputs!$B$5:$B$130*(((Inputs!$G$5:$G$130="moeda")+(Inputs!$G$5:$G$130="acoes"))*Inputs!$B$1+((Inputs!$G$5:$G$130<>"moeda")*(Inputs!$G$5:$G$130<>"acoes")))*INDEX(Inputs!$K$5:$AJ$130,0,MATCH(V$2,Inputs!$K$4:$AJ$4,0)))+SUMPRODUCT((Inputs!$C$5:$C$130=$B4)*Inputs!$D$5:$D$130*(((Inputs!$G$5:$G$130="moeda")+(Inputs!$G$5:$G$130="acoes"))*Inputs!$B$1+((Inputs!$G$5:$G$130<>"moeda")*(Inputs!$G$5:$G$130<>"acoes")))*INDEX(Inputs!$K$5:$AJ$130,0,MATCH(V$2,Inputs!$K$4:$AJ$4,0)))+SUMPRODUCT((Inputs!$E$5:$E$130=$B4)*Inputs!$F$5:$F$130*(((Inputs!$G$5:$G$130="moeda")+(Inputs!$G$5:$G$130="acoes"))*Inputs!$B$1+((Inputs!$G$5:$G$130<>"moeda")*(Inputs!$G$5:$G$130<>"acoes")))*INDEX(Inputs!$K$5:$AJ$130,0,MATCH(V$2,Inputs!$K$4:$AJ$4,0))))) -> 66281 | W4: =SUM(S4:V4) -> 284311 | X4: =IF(ISNA(MATCH(X$2,Inputs!$K$4:$AJ$4,0)),NA(),IF(SUMPRODUCT((Inputs!$A$5:$A$130=$B4)*ISNUMBER(INDEX(Inputs!$K$5:$AJ$130,0,MATCH(X$2,Inputs!$K$4:$AJ$4,0))))+SUMPRODUCT((Inputs!$C$5:$C$130=$B4)*ISNUMBER(INDEX(Inputs!$K$5:$AJ$130,0,MATCH(X$2,Inputs!$K$4:$AJ$4,0))))+SUMPRODUCT((Inputs!$E$5:$E$130=$B4)*ISNUMBER(INDEX(Inputs!$K$5:$AJ$130,0,MATCH(X$2,Inputs!$K$4:$AJ$4,0))))=0,NA(),SUMPRODUCT((Inputs!$A$5:$A$130=$B4)*Inputs!$B$5:$B$130*(((Inputs!$G$5:$G$130="moeda")+(Inputs!$G$5:$G$130="acoes"))*Inputs!$B$1+((Inputs!$G$5:$G$130<>"moeda")*(Inputs!$G$5:$G$130<>"acoes")))*INDEX(Inputs!$K$5:$AJ$130,0,MATCH(X$2,Inputs!$K$4:$AJ$4,0)))+SUMPRODUCT((Inputs!$C$5:$C$130=$B4)*Inputs!$D$5:$D$130*(((Inputs!$G$5:$G$130="moeda")+(Inputs!$G$5:$G$130="acoes"))*Inputs!$B$1+((Inputs!$G$5:$G$130<>"moeda")*(Inputs!$G$5:$G$130<>"acoes")))*INDEX(Inputs!$K$5:$AJ$130,0,MATCH(X$2,Inputs!$K$4:$AJ$4,0)))+SUMPRODUCT((Inputs!$E$5:$E$130=$B4)*Inputs!$F$5:$F$130*(((Inputs!$G$5:$G$130="moeda")+(Inputs!$G$5:$G$130="acoes"))*Inputs!$B$1+((Inputs!$G$5:$G$130<>"moeda")*(Inputs!$G$5:$G$130<>"acoes")))*INDEX(Inputs!$K$5:$AJ$130,0,MATCH(X$2,Inputs!$K$4:$AJ$4,0))))) -> 69234 | Y4: =IF(ISNA(MATCH(Y$2,Inputs!$K$4:$AJ$4,0)),NA(),IF(SUMPRODUCT((Inputs!$A$5:$A$130=$B4)*ISNUMBER(INDEX(Inputs!$K$5:$AJ$130,0,MATCH(Y$2,Inputs!$K$4:$AJ$4,0))))+SUMPRODUCT((Inputs!$C$5:$C$130=$B4)*ISNUMBER(INDEX(Inputs!$K$5:$AJ$130,0,MATCH(Y$2,Inputs!$K$4:$AJ$4,0))))+SUMPRODUCT((Inputs!$E$5:$E$130=$B4)*ISNUMBER(INDEX(Inputs!$K$5:$AJ$130,0,MATCH(Y$2,Inputs!$K$4:$AJ$4,0))))=0,NA(),SUMPRODUCT((Inputs!$A$5:$A$130=$B4)*Inputs!$B$5:$B$130*(((Inputs!$G$5:$G$130="moeda")+(Inputs!$G$5:$G$130="acoes"))*Inputs!$B$1+((Inputs!$G$5:$G$130<>"moeda")*(Inputs!$G$5:$G$130<>"acoes")))*INDEX(Inputs!$K$5:$AJ$130,0,MATCH(Y$2,Inputs!$K$4:$AJ$4,0)))+SUMPRODUCT((Inputs!$C$5:$C$130=$B4)*Inputs!$D$5:$D$130*(((Inputs!$G$5:$G$130="moeda")+(Inputs!$G$5:$G$130="acoes"))*Inputs!$B$1+((Inputs!$G$5:$G$130<>"moeda")*(Inputs!$G$5:$G$130<>"acoes")))*INDEX(Inputs!$K$5:$AJ$130,0,MATCH(Y$2,Inputs!$K$4:$AJ$4,0)))+SUMPRODUCT((Inputs!$E$5:$E$130=$B4)*Inputs!$F$5:$F$130*(((Inputs!$G$5:$G$130="moeda")+(Inputs!$G$5:$G$130="acoes"))*Inputs!$B$1+((Inputs!$G$5:$G$130<>"moeda")*(Inputs!$G$5:$G$130<>"acoes")))*INDEX(Inputs!$K$5:$AJ$130,0,MATCH(Y$2,Inputs!$K$4:$AJ$4,0))))) -> 65406 | Z4: =IF(ISNA(MATCH(Z$2,Inputs!$K$4:$AJ$4,0)),NA(),IF(SUMPRODUCT((Inputs!$A$5:$A$130=$B4)*ISNUMBER(INDEX(Inputs!$K$5:$AJ$130,0,MATCH(Z$2,Inputs!$K$4:$AJ$4,0))))+SUMPRODUCT((Inputs!$C$5:$C$130=$B4)*ISNUMBER(INDEX(Inputs!$K$5:$AJ$130,0,MATCH(Z$2,Inputs!$K$4:$AJ$4,0))))+SUMPRODUCT((Inputs!$E$5:$E$130=$B4)*ISNUMBER(INDEX(Inputs!$K$5:$AJ$130,0,MATCH(Z$2,Inputs!$K$4:$AJ$4,0))))=0,NA(),SUMPRODUCT((Inputs!$A$5:$A$130=$B4)*Inputs!$B$5:$B$130*(((Inputs!$G$5:$G$130="moeda")+(Inputs!$G$5:$G$130="acoes"))*Inputs!$B$1+((Inputs!$G$5:$G$130<>"moeda")*(Inputs!$G$5:$G$130<>"acoes")))*INDEX(Inputs!$K$5:$AJ$130,0,MATCH(Z$2,Inputs!$K$4:$AJ$4,0)))+SUMPRODUCT((Inputs!$C$5:$C$130=$B4)*Inputs!$D$5:$D$130*(((Inputs!$G$5:$G$130="moeda")+(Inputs!$G$5:$G$130="acoes"))*Inputs!$B$1+((Inputs!$G$5:$G$130<>"moeda")*(Inputs!$G$5:$G$130<>"acoes")))*INDEX(Inputs!$K$5:$AJ$130,0,MATCH(Z$2,Inputs!$K$4:$AJ$4,0)))+SUMPRODUCT((Inputs!$E$5:$E$130=$B4)*Inputs!$F$5:$F$130*(((Inputs!$G$5:$G$130="moeda")+(Inputs!$G$5:$G$130="acoes"))*Inputs!$B$1+((Inputs!$G$5:$G$130<>"moeda")*(Inputs!$G$5:$G$130<>"acoes")))*INDEX(Inputs!$K$5:$AJ$130,0,MATCH(Z$2,Inputs!$K$4:$AJ$4,0))))) -> 68153 | AA4: =IF(ISNA(MATCH(AA$2,Inputs!$K$4:$AJ$4,0)),NA(),IF(SUMPRODUCT((Inputs!$A$5:$A$130=$B4)*ISNUMBER(INDEX(Inputs!$K$5:$AJ$130,0,MATCH(AA$2,Inputs!$K$4:$AJ$4,0))))+SUMPRODUCT((Inputs!$C$5:$C$130=$B4)*ISNUMBER(INDEX(Inputs!$K$5:$AJ$130,0,MATCH(AA$2,Inputs!$K$4:$AJ$4,0))))+SUMPRODUCT((Inputs!$E$5:$E$130=$B4)*ISNUMBER(INDEX(Inputs!$K$5:$AJ$130,0,MATCH(AA$2,Inputs!$K$4:$AJ$4,0))))=0,NA(),SUMPRODUCT((Inputs!$A$5:$A$130=$B4)*Inputs!$B$5:$B$130*(((Inputs!$G$5:$G$130="moeda")+(Inputs!$G$5:$G$130="acoes"))*Inputs!$B$1+((Inputs!$G$5:$G$130<>"moeda")*(Inputs!$G$5:$G$130<>"acoes")))*INDEX(Inputs!$K$5:$AJ$130,0,MATCH(AA$2,Inputs!$K$4:$AJ$4,0)))+SUMPRODUCT((Inputs!$C$5:$C$130=$B4)*Inputs!$D$5:$D$130*(((Inputs!$G$5:$G$130="moeda")+(Inputs!$G$5:$G$130="acoes"))*Inputs!$B$1+((Inputs!$G$5:$G$130<>"moeda")*(Inputs!$G$5:$G$130<>"acoes")))*INDEX(Inputs!$K$5:$AJ$130,0,MATCH(AA$2,Inputs!$K$4:$AJ$4,0)))+SUMPRODUCT((Inputs!$E$5:$E$130=$B4)*Inputs!$F$5:$F$130*(((Inputs!$G$5:$G$130="moeda")+(Inputs!$G$5:$G$130="acoes"))*Inputs!$B$1+((Inputs!$G$5:$G$130<>"moeda")*(Inputs!$G$5:$G$130<>"acoes")))*INDEX(Inputs!$K$5:$AJ$130,0,MATCH(AA$2,Inputs!$K$4:$AJ$4,0))))) -> 64093 | AB4: =SUM(X4:AA4) -> 266886 | AC4: =IF(ISNA(MATCH(AC$2,Inputs!$K$4:$AJ$4,0)),NA(),IF(SUMPRODUCT((Inputs!$A$5:$A$130=$B4)*ISNUMBER(INDEX(Inputs!$K$5:$AJ$130,0,MATCH(AC$2,Inputs!$K$4:$AJ$4,0))))+SUMPRODUCT((Inputs!$C$5:$C$130=$B4)*ISNUMBER(INDEX(Inputs!$K$5:$AJ$130,0,MATCH(AC$2,Inputs!$K$4:$AJ$4,0))))+SUMPRODUCT((Inputs!$E$5:$E$130=$B4)*ISNUMBER(INDEX(Inputs!$K$5:$AJ$130,0,MATCH(AC$2,Inputs!$K$4:$AJ$4,0))))=0,NA(),SUMPRODUCT((Inputs!$A$5:$A$130=$B4)*Inputs!$B$5:$B$130*(((Inputs!$G$5:$G$130="moeda")+(Inputs!$G$5:$G$130="acoes"))*Inputs!$B$1+((Inputs!$G$5:$G$130<>"moeda")*(Inputs!$G$5:$G$130<>"acoes")))*INDEX(Inputs!$K$5:$AJ$130,0,MATCH(AC$2,Inputs!$K$4:$AJ$4,0)))+SUMPRODUCT((Inputs!$C$5:$C$130=$B4)*Inputs!$D$5:$D$130*(((Inputs!$G$5:$G$130="moeda")+(Inputs!$G$5:$G$130="acoes"))*Inputs!$B$1+((Inputs!$G$5:$G$130<>"moeda")*(Inputs!$G$5:$G$130<>"acoes")))*INDEX(Inputs!$K$5:$AJ$130,0,MATCH(AC$2,Inputs!$K$4:$AJ$4,0)))+SUMPRODUCT((Inputs!$E$5:$E$130=$B4)*Inputs!$F$5:$F$130*(((Inputs!$G$5:$G$130="moeda")+(Inputs!$G$5:$G$130="acoes"))*Inputs!$B$1+((Inputs!$G$5:$G$130<>"moeda")*(Inputs!$G$5:$G$130<>"acoes")))*INDEX(Inputs!$K$5:$AJ$130,0,MATCH(AC$2,Inputs!$K$4:$AJ$4,0))))) -> 69691 | AD4: =IF(ISNA(MATCH(AD$2,Inputs!$K$4:$AJ$4,0)),NA(),IF(SUMPRODUCT((Inputs!$A$5:$A$130=$B4)*ISNUMBER(INDEX(Inputs!$K$5:$AJ$130,0,MATCH(AD$2,Inputs!$K$4:$AJ$4,0))))+SUMPRODUCT((Inputs!$C$5:$C$130=$B4)*ISNUMBER(INDEX(Inputs!$K$5:$AJ$130,0,MATCH(AD$2,Inputs!$K$4:$AJ$4,0))))+SUMPRODUCT((Inputs!$E$5:$E$130=$B4)*ISNUMBER(INDEX(Inputs!$K$5:$AJ$130,0,MATCH(AD$2,Inputs!$K$4:$AJ$4,0))))=0,NA(),SUMPRODUCT((Inputs!$A$5:$A$130=$B4)*Inputs!$B$5:$B$130*(((Inputs!$G$5:$G$130="moeda")+(Inputs!$G$5:$G$130="acoes"))*Inputs!$B$1+((Inputs!$G$5:$G$130<>"moeda")*(Inputs!$G$5:$G$130<>"acoes")))*INDEX(Inputs!$K$5:$AJ$130,0,MATCH(AD$2,Inputs!$K$4:$AJ$4,0)))+SUMPRODUCT((Inputs!$C$5:$C$130=$B4)*Inputs!$D$5:$D$130*(((Inputs!$G$5:$G$130="moeda")+(Inputs!$G$5:$G$130="acoes"))*Inputs!$B$1+((Inputs!$G$5:$G$130<>"moeda")*(Inputs!$G$5:$G$130<>"acoes")))*INDEX(Inputs!$K$5:$AJ$130,0,MATCH(AD$2,Inputs!$K$4:$AJ$4,0)))+SUMPRODUCT((Inputs!$E$5:$E$130=$B4)*Inputs!$F$5:$F$130*(((Inputs!$G$5:$G$130="moeda")+(Inputs!$G$5:$G$130="acoes"))*Inputs!$B$1+((Inputs!$G$5:$G$130<>"moeda")*(Inputs!$G$5:$G$130<>"acoes")))*INDEX(Inputs!$K$5:$AJ$130,0,MATCH(AD$2,Inputs!$K$4:$AJ$4,0))))) -> 94664 | AE4: =IF(ISNA(MATCH(AE$2,Inputs!$K$4:$AJ$4,0)),NA(),IF(SUMPRODUCT((Inputs!$A$5:$A$130=$B4)*ISNUMBER(INDEX(Inputs!$K$5:$AJ$130,0,MATCH(AE$2,Inputs!$K$4:$AJ$4,0))))+SUMPRODUCT((Inputs!$C$5:$C$130=$B4)*ISNUMBER(INDEX(Inputs!$K$5:$AJ$130,0,MATCH(AE$2,Inputs!$K$4:$AJ$4,0))))+SUMPRODUCT((Inputs!$E$5:$E$130=$B4)*ISNUMBER(INDEX(Inputs!$K$5:$AJ$130,0,MATCH(AE$2,Inputs!$K$4:$AJ$4,0))))=0,NA(),SUMPRODUCT((Inputs!$A$5:$A$130=$B4)*Inputs!$B$5:$B$130*(((Inputs!$G$5:$G$130="moeda")+(Inputs!$G$5:$G$130="acoes"))*Inputs!$B$1+((Inputs!$G$5:$G$130<>"moeda")*(Inputs!$G$5:$G$130<>"acoes")))*INDEX(Inputs!$K$5:$AJ$130,0,MATCH(AE$2,Inputs!$K$4:$AJ$4,0)))+SUMPRODUCT((Inputs!$C$5:$C$130=$B4)*Inputs!$D$5:$D$130*(((Inputs!$G$5:$G$130="moeda")+(Inputs!$G$5:$G$130="acoes"))*Inputs!$B$1+((Inputs!$G$5:$G$130<>"moeda")*(Inputs!$G$5:$G$130<>"acoes")))*INDEX(Inputs!$K$5:$AJ$130,0,MATCH(AE$2,Inputs!$K$4:$AJ$4,0)))+SUMPRODUCT((Inputs!$E$5:$E$130=$B4)*Inputs!$F$5:$F$130*(((Inputs!$G$5:$G$130="moeda")+(Inputs!$G$5:$G$130="acoes"))*Inputs!$B$1+((Inputs!$G$5:$G$130<>"moeda")*(Inputs!$G$5:$G$130<>"acoes")))*INDEX(Inputs!$K$5:$AJ$130,0,MATCH(AE$2,Inputs!$K$4:$AJ$4,0))))) -> #N/A | AF4: =IF(ISNA(MATCH(AF$2,Inputs!$K$4:$AJ$4,0)),NA(),IF(SUMPRODUCT((Inputs!$A$5:$A$130=$B4)*ISNUMBER(INDEX(Inputs!$K$5:$AJ$130,0,MATCH(AF$2,Inputs!$K$4:$AJ$4,0))))+SUMPRODUCT((Inputs!$C$5:$C$130=$B4)*ISNUMBER(INDEX(Inputs!$K$5:$AJ$130,0,MATCH(AF$2,Inputs!$K$4:$AJ$4,0))))+SUMPRODUCT((Inputs!$E$5:$E$130=$B4)*ISNUMBER(INDEX(Inputs!$K$5:$AJ$130,0,MATCH(AF$2,Inputs!$K$4:$AJ$4,0))))=0,NA(),SUMPRODUCT((Inputs!$A$5:$A$130=$B4)*Inputs!$B$5:$B$130*(((Inputs!$G$5:$G$130="moeda")+(Inputs!$G$5:$G$130="acoes"))*Inputs!$B$1+((Inputs!$G$5:$G$130<>"moeda")*(Inputs!$G$5:$G$130<>"acoes")))*INDEX(Inputs!$K$5:$AJ$130,0,MATCH(AF$2,Inputs!$K$4:$AJ$4,0)))+SUMPRODUCT((Inputs!$C$5:$C$130=$B4)*Inputs!$D$5:$D$130*(((Inputs!$G$5:$G$130="moeda")+(Inputs!$G$5:$G$130="acoes"))*Inputs!$B$1+((Inputs!$G$5:$G$130<>"moeda")*(Inputs!$G$5:$G$130<>"acoes")))*INDEX(Inputs!$K$5:$AJ$130,0,MATCH(AF$2,Inputs!$K$4:$AJ$4,0)))+SUMPRODUCT((Inputs!$E$5:$E$130=$B4)*Inputs!$F$5:$F$130*(((Inputs!$G$5:$G$130="moeda")+(Inputs!$G$5:$G$130="acoes"))*Inputs!$B$1+((Inputs!$G$5:$G$130<>"moeda")*(Inputs!$G$5:$G$130<>"acoes")))*INDEX(Inputs!$K$5:$AJ$130,0,MATCH(AF$2,Inputs!$K$4:$AJ$4,0))))) -> #N/A | AG4: =SUM(AC4:AF4) -> #N/A | AH4: =IF(ISNA(MATCH(AH$2,Inputs!$K$4:$AJ$4,0)),NA(),IF(SUMPRODUCT((Inputs!$A$5:$A$130=$B4)*ISNUMBER(INDEX(Inputs!$K$5:$AJ$130,0,MATCH(AH$2,Inputs!$K$4:$AJ$4,0))))+SUMPRODUCT((Inputs!$C$5:$C$130=$B4)*ISNUMBER(INDEX(Inputs!$K$5:$AJ$130,0,MATCH(AH$2,Inputs!$K$4:$AJ$4,0))))+SUMPRODUCT((Inputs!$E$5:$E$130=$B4)*ISNUMBER(INDEX(Inputs!$K$5:$AJ$130,0,MATCH(AH$2,Inputs!$K$4:$AJ$4,0))))=0,NA(),SUMPRODUCT((Inputs!$A$5:$A$130=$B4)*Inputs!$B$5:$B$130*(((Inputs!$G$5:$G$130="moeda")+(Inputs!$G$5:$G$130="acoes"))*Inputs!$B$1+((Inputs!$G$5:$G$130<>"moeda")*(Inputs!$G$5:$G$130<>"acoes")))*INDEX(Inputs!$K$5:$AJ$130,0,MATCH(AH$2,Inputs!$K$4:$AJ$4,0)))+SUMPRODUCT((Inputs!$C$5:$C$130=$B4)*Inputs!$D$5:$D$130*(((Inputs!$G$5:$G$130="moeda")+(Inputs!$G$5:$G$130="acoes"))*Inputs!$B$1+((Inputs!$G$5:$G$130<>"moeda")*(Inputs!$G$5:$G$130<>"acoes")))*INDEX(Inputs!$K$5:$AJ$130,0,MATCH(AH$2,Inputs!$K$4:$AJ$4,0)))+SUMPRODUCT((Inputs!$E$5:$E$130=$B4)*Inputs!$F$5:$F$130*(((Inputs!$G$5:$G$130="moeda")+(Inputs!$G$5:$G$130="acoes"))*Inputs!$B$1+((Inputs!$G$5:$G$130<>"moeda")*(Inputs!$G$5:$G$130<>"acoes")))*INDEX(Inputs!$K$5:$AJ$130,0,MATCH(AH$2,Inputs!$K$4:$AJ$4,0))))) -> #N/A | AI4: =IF(ISNA(MATCH(AI$2,Inputs!$K$4:$AJ$4,0)),NA(),IF(SUMPRODUCT((Inputs!$A$5:$A$130=$B4)*ISNUMBER(INDEX(Inputs!$K$5:$AJ$130,0,MATCH(AI$2,Inputs!$K$4:$AJ$4,0))))+SUMPRODUCT((Inputs!$C$5:$C$130=$B4)*ISNUMBER(INDEX(Inputs!$K$5:$AJ$130,0,MATCH(AI$2,Inputs!$K$4:$AJ$4,0))))+SUMPRODUCT((Inputs!$E$5:$E$130=$B4)*ISNUMBER(INDEX(Inputs!$K$5:$AJ$130,0,MATCH(AI$2,Inputs!$K$4:$AJ$4,0))))=0,NA(),SUMPRODUCT((Inputs!$A$5:$A$130=$B4)*Inputs!$B$5:$B$130*(((Inputs!$G$5:$G$130="moeda")+(Inputs!$G$5:$G$130="acoes"))*Inputs!$B$1+((Inputs!$G$5:$G$130<>"moeda")*(Inputs!$G$5:$G$130<>"acoes")))*INDEX(Inputs!$K$5:$AJ$130,0,MATCH(AI$2,Inputs!$K$4:$AJ$4,0)))+SUMPRODUCT((Inputs!$C$5:$C$130=$B4)*Inputs!$D$5:$D$130*(((Inputs!$G$5:$G$130="moeda")+(Inputs!$G$5:$G$130="acoes"))*Inputs!$B$1+((Inputs!$G$5:$G$130<>"moeda")*(Inputs!$G$5:$G$130<>"acoes")))*INDEX(Inputs!$K$5:$AJ$130,0,MATCH(AI$2,Inputs!$K$4:$AJ$4,0)))+SUMPRODUCT((Inputs!$E$5:$E$130=$B4)*Inputs!$F$5:$F$130*(((Inputs!$G$5:$G$130="moeda")+(Inputs!$G$5:$G$130="acoes"))*Inputs!$B$1+((Inputs!$G$5:$G$130<>"moeda")*(Inputs!$G$5:$G$130<>"acoes")))*INDEX(Inputs!$K$5:$AJ$130,0,MATCH(AI$2,Inputs!$K$4:$AJ$4,0))))) -> #N/A | AJ4: =IF(ISNA(MATCH(AJ$2,Inputs!$K$4:$AJ$4,0)),NA(),IF(SUMPRODUCT((Inputs!$A$5:$A$130=$B4)*ISNUMBER(INDEX(Inputs!$K$5:$AJ$130,0,MATCH(AJ$2,Inputs!$K$4:$AJ$4,0))))+SUMPRODUCT((Inputs!$C$5:$C$130=$B4)*ISNUMBER(INDEX(Inputs!$K$5:$AJ$130,0,MATCH(AJ$2,Inputs!$K$4:$AJ$4,0))))+SUMPRODUCT((Inputs!$E$5:$E$130=$B4)*ISNUMBER(INDEX(Inputs!$K$5:$AJ$130,0,MATCH(AJ$2,Inputs!$K$4:$AJ$4,0))))=0,NA(),SUMPRODUCT((Inputs!$A$5:$A$130=$B4)*Inputs!$B$5:$B$130*(((Inputs!$G$5:$G$130="moeda")+(Inputs!$G$5:$G$130="acoes"))*Inputs!$B$1+((Inputs!$G$5:$G$130<>"moeda")*(Inputs!$G$5:$G$130<>"acoes")))*INDEX(Inputs!$K$5:$AJ$130,0,MATCH(AJ$2,Inputs!$K$4:$AJ$4,0)))+SUMPRODUCT((Inputs!$C$5:$C$130=$B4)*Inputs!$D$5:$D$130*(((Inputs!$G$5:$G$130="moeda")+(Inputs!$G$5:$G$130="acoes"))*Inputs!$B$1+((Inputs!$G$5:$G$130<>"moeda")*(Inputs!$G$5:$G$130<>"acoes")))*INDEX(Inputs!$K$5:$AJ$130,0,MATCH(AJ$2,Inputs!$K$4:$AJ$4,0)))+SUMPRODUCT((Inputs!$E$5:$E$130=$B4)*Inputs!$F$5:$F$130*(((Inputs!$G$5:$G$130="moeda")+(Inputs!$G$5:$G$130="acoes"))*Inputs!$B$1+((Inputs!$G$5:$G$130<>"moeda")*(Inputs!$G$5:$G$130<>"acoes")))*INDEX(Inputs!$K$5:$AJ$130,0,MATCH(AJ$2,Inputs!$K$4:$AJ$4,0))))) -> #N/A | AK4: =IF(ISNA(MATCH(AK$2,Inputs!$K$4:$AJ$4,0)),NA(),IF(SUMPRODUCT((Inputs!$A$5:$A$130=$B4)*ISNUMBER(INDEX(Inputs!$K$5:$AJ$130,0,MATCH(AK$2,Inputs!$K$4:$AJ$4,0))))+SUMPRODUCT((Inputs!$C$5:$C$130=$B4)*ISNUMBER(INDEX(Inputs!$K$5:$AJ$130,0,MATCH(AK$2,Inputs!$K$4:$AJ$4,0))))+SUMPRODUCT((Inputs!$E$5:$E$130=$B4)*ISNUMBER(INDEX(Inputs!$K$5:$AJ$130,0,MATCH(AK$2,Inputs!$K$4:$AJ$4,0))))=0,NA(),SUMPRODUCT((Inputs!$A$5:$A$130=$B4)*Inputs!$B$5:$B$130*(((Inputs!$G$5:$G$130="moeda")+(Inputs!$G$5:$G$130="acoes"))*Inputs!$B$1+((Inputs!$G$5:$G$130<>"moeda")*(Inputs!$G$5:$G$130<>"acoes")))*INDEX(Inputs!$K$5:$AJ$130,0,MATCH(AK$2,Inputs!$K$4:$AJ$4,0)))+SUMPRODUCT((Inputs!$C$5:$C$130=$B4)*Inputs!$D$5:$D$130*(((Inputs!$G$5:$G$130="moeda")+(Inputs!$G$5:$G$130="acoes"))*Inputs!$B$1+((Inputs!$G$5:$G$130<>"moeda")*(Inputs!$G$5:$G$130<>"acoes")))*INDEX(Inputs!$K$5:$AJ$130,0,MATCH(AK$2,Inputs!$K$4:$AJ$4,0)))+SUMPRODUCT((Inputs!$E$5:$E$130=$B4)*Inputs!$F$5:$F$130*(((Inputs!$G$5:$G$130="moeda")+(Inputs!$G$5:$G$130="acoes"))*Inputs!$B$1+((Inputs!$G$5:$G$130<>"moeda")*(Inputs!$G$5:$G$130<>"acoes")))*INDEX(Inputs!$K$5:$AJ$130,0,MATCH(AK$2,Inputs!$K$4:$AJ$4,0))))) -> #N/A | AL4: =SUM(AH4:AK4) -> #N/A
B5: 2 | C5: COGS (cash) | D5: =IF(ISNA(MATCH(D$2,Inputs!$K$4:$AJ$4,0)),NA(),IF(SUMPRODUCT((Inputs!$A$5:$A$130=$B5)*ISNUMBER(INDEX(Inputs!$K$5:$AJ$130,0,MATCH(D$2,Inputs!$K$4:$AJ$4,0))))+SUMPRODUCT((Inputs!$C$5:$C$130=$B5)*ISNUMBER(INDEX(Inputs!$K$5:$AJ$130,0,MATCH(D$2,Inputs!$K$4:$AJ$4,0))))+SUMPRODUCT((Inputs!$E$5:$E$130=$B5)*ISNUMBER(INDEX(Inputs!$K$5:$AJ$130,0,MATCH(D$2,Inputs!$K$4:$AJ$4,0))))=0,NA(),SUMPRODUCT((Inputs!$A$5:$A$130=$B5)*Inputs!$B$5:$B$130*(((Inputs!$G$5:$G$130="moeda")+(Inputs!$G$5:$G$130="acoes"))*Inputs!$B$1+((Inputs!$G$5:$G$130<>"moeda")*(Inputs!$G$5:$G$130<>"acoes")))*INDEX(Inputs!$K$5:$AJ$130,0,MATCH(D$2,Inputs!$K$4:$AJ$4,0)))+SUMPRODUCT((Inputs!$C$5:$C$130=$B5)*Inputs!$D$5:$D$130*(((Inputs!$G$5:$G$130="moeda")+(Inputs!$G$5:$G$130="acoes"))*Inputs!$B$1+((Inputs!$G$5:$G$130<>"moeda")*(Inputs!$G$5:$G$130<>"acoes")))*INDEX(Inputs!$K$5:$AJ$130,0,MATCH(D$2,Inputs!$K$4:$AJ$4,0)))+SUMPRODUCT((Inputs!$E$5:$E$130=$B5)*Inputs!$F$5:$F$130*(((Inputs!$G$5:$G$130="moeda")+(Inputs!$G$5:$G$130="acoes"))*Inputs!$B$1+((Inputs!$G$5:$G$130<>"moeda")*(Inputs!$G$5:$G$130<>"acoes")))*INDEX(Inputs!$K$5:$AJ$130,0,MATCH(D$2,Inputs!$K$4:$AJ$4,0))))) -> -34369 | E5: =IF(ISNA(MATCH(E$2,Inputs!$K$4:$AJ$4,0)),NA(),IF(SUMPRODUCT((Inputs!$A$5:$A$130=$B5)*ISNUMBER(INDEX(Inputs!$K$5:$AJ$130,0,MATCH(E$2,Inputs!$K$4:$AJ$4,0))))+SUMPRODUCT((Inputs!$C$5:$C$130=$B5)*ISNUMBER(INDEX(Inputs!$K$5:$AJ$130,0,MATCH(E$2,Inputs!$K$4:$AJ$4,0))))+SUMPRODUCT((Inputs!$E$5:$E$130=$B5)*ISNUMBER(INDEX(Inputs!$K$5:$AJ$130,0,MATCH(E$2,Inputs!$K$4:$AJ$4,0))))=0,NA(),SUMPRODUCT((Inputs!$A$5:$A$130=$B5)*Inputs!$B$5:$B$130*(((Inputs!$G$5:$G$130="moeda")+(Inputs!$G$5:$G$130="acoes"))*Inputs!$B$1+((Inputs!$G$5:$G$130<>"moeda")*(Inputs!$G$5:$G$130<>"acoes")))*INDEX(Inputs!$K$5:$AJ$130,0,MATCH(E$2,Inputs!$K$4:$AJ$4,0)))+SUMPRODUCT((Inputs!$C$5:$C$130=$B5)*Inputs!$D$5:$D$130*(((Inputs!$G$5:$G$130="moeda")+(Inputs!$G$5:$G$130="acoes"))*Inputs!$B$1+((Inputs!$G$5:$G$130<>"moeda")*(Inputs!$G$5:$G$130<>"acoes")))*INDEX(Inputs!$K$5:$AJ$130,0,MATCH(E$2,Inputs!$K$4:$AJ$4,0)))+SUMPRODUCT((Inputs!$E$5:$E$130=$B5)*Inputs!$F$5:$F$130*(((Inputs!$G$5:$G$130="moeda")+(Inputs!$G$5:$G$130="acoes"))*Inputs!$B$1+((Inputs!$G$5:$G$130<>"moeda")*(Inputs!$G$5:$G$130<>"acoes")))*INDEX(Inputs!$K$5:$AJ$130,0,MATCH(E$2,Inputs!$K$4:$AJ$4,0))))) -> -39717 | F5: =IF(ISNA(MATCH(F$2,Inputs!$K$4:$AJ$4,0)),NA(),IF(SUMPRODUCT((Inputs!$A$5:$A$130=$B5)*ISNUMBER(INDEX(Inputs!$K$5:$AJ$130,0,MATCH(F$2,Inputs!$K$4:$AJ$4,0))))+SUMPRODUCT((Inputs!$C$5:$C$130=$B5)*ISNUMBER(INDEX(Inputs!$K$5:$AJ$130,0,MATCH(F$2,Inputs!$K$4:$AJ$4,0))))+SUMPRODUCT((Inputs!$E$5:$E$130=$B5)*ISNUMBER(INDEX(Inputs!$K$5:$AJ$130,0,MATCH(F$2,Inputs!$K$4:$AJ$4,0))))=0,NA(),SUMPRODUCT((Inputs!$A$5:$A$130=$B5)*Inputs!$B$5:$B$130*(((Inputs!$G$5:$G$130="moeda")+(Inputs!$G$5:$G$130="acoes"))*Inputs!$B$1+((Inputs!$G$5:$G$130<>"moeda")*(Inputs!$G$5:$G$130<>"acoes")))*INDEX(Inputs!$K$5:$AJ$130,0,MATCH(F$2,Inputs!$K$4:$AJ$4,0)))+SUMPRODUCT((Inputs!$C$5:$C$130=$B5)*Inputs!$D$5:$D$130*(((Inputs!$G$5:$G$130="moeda")+(Inputs!$G$5:$G$130="acoes"))*Inputs!$B$1+((Inputs!$G$5:$G$130<>"moeda")*(Inputs!$G$5:$G$130<>"acoes")))*INDEX(Inputs!$K$5:$AJ$130,0,MATCH(F$2,Inputs!$K$4:$AJ$4,0)))+SUMPRODUCT((Inputs!$E$5:$E$130=$B5)*Inputs!$F$5:$F$130*(((Inputs!$G$5:$G$130="moeda")+(Inputs!$G$5:$G$130="acoes"))*Inputs!$B$1+((Inputs!$G$5:$G$130<>"moeda")*(Inputs!$G$5:$G$130<>"acoes")))*INDEX(Inputs!$K$5:$AJ$130,0,MATCH(F$2,Inputs!$K$4:$AJ$4,0))))) -> -44260 | G5: =IF(ISNA(MATCH(G$2,Inputs!$K$4:$AJ$4,0)),NA(),IF(SUMPRODUCT((Inputs!$A$5:$A$130=$B5)*ISNUMBER(INDEX(Inputs!$K$5:$AJ$130,0,MATCH(G$2,Inputs!$K$4:$AJ$4,0))))+SUMPRODUCT((Inputs!$C$5:$C$130=$B5)*ISNUMBER(INDEX(Inputs!$K$5:$AJ$130,0,MATCH(G$2,Inputs!$K$4:$AJ$4,0))))+SUMPRODUCT((Inputs!$E$5:$E$130=$B5)*ISNUMBER(INDEX(Inputs!$K$5:$AJ$130,0,MATCH(G$2,Inputs!$K$4:$AJ$4,0))))=0,NA(),SUMPRODUCT((Inputs!$A$5:$A$130=$B5)*Inputs!$B$5:$B$130*(((Inputs!$G$5:$G$130="moeda")+(Inputs!$G$5:$G$130="acoes"))*Inputs!$B$1+((Inputs!$G$5:$G$130<>"moeda")*(Inputs!$G$5:$G$130<>"acoes")))*INDEX(Inputs!$K$5:$AJ$130,0,MATCH(G$2,Inputs!$K$4:$AJ$4,0)))+SUMPRODUCT((Inputs!$C$5:$C$130=$B5)*Inputs!$D$5:$D$130*(((Inputs!$G$5:$G$130="moeda")+(Inputs!$G$5:$G$130="acoes"))*Inputs!$B$1+((Inputs!$G$5:$G$130<>"moeda")*(Inputs!$G$5:$G$130<>"acoes")))*INDEX(Inputs!$K$5:$AJ$130,0,MATCH(G$2,Inputs!$K$4:$AJ$4,0)))+SUMPRODUCT((Inputs!$E$5:$E$130=$B5)*Inputs!$F$5:$F$130*(((Inputs!$G$5:$G$130="moeda")+(Inputs!$G$5:$G$130="acoes"))*Inputs!$B$1+((Inputs!$G$5:$G$130<>"moeda")*(Inputs!$G$5:$G$130<>"acoes")))*INDEX(Inputs!$K$5:$AJ$130,0,MATCH(G$2,Inputs!$K$4:$AJ$4,0))))) -> -56566 | H5: =SUM(D5:G5) -> -174912 | I5: =IF(ISNA(MATCH(I$2,Inputs!$K$4:$AJ$4,0)),NA(),IF(SUMPRODUCT((Inputs!$A$5:$A$130=$B5)*ISNUMBER(INDEX(Inputs!$K$5:$AJ$130,0,MATCH(I$2,Inputs!$K$4:$AJ$4,0))))+SUMPRODUCT((Inputs!$C$5:$C$130=$B5)*ISNUMBER(INDEX(Inputs!$K$5:$AJ$130,0,MATCH(I$2,Inputs!$K$4:$AJ$4,0))))+SUMPRODUCT((Inputs!$E$5:$E$130=$B5)*ISNUMBER(INDEX(Inputs!$K$5:$AJ$130,0,MATCH(I$2,Inputs!$K$4:$AJ$4,0))))=0,NA(),SUMPRODUCT((Inputs!$A$5:$A$130=$B5)*Inputs!$B$5:$B$130*(((Inputs!$G$5:$G$130="moeda")+(Inputs!$G$5:$G$130="acoes"))*Inputs!$B$1+((Inputs!$G$5:$G$130<>"moeda")*(Inputs!$G$5:$G$130<>"acoes")))*INDEX(Inputs!$K$5:$AJ$130,0,MATCH(I$2,Inputs!$K$4:$AJ$4,0)))+SUMPRODUCT((Inputs!$C$5:$C$130=$B5)*Inputs!$D$5:$D$130*(((Inputs!$G$5:$G$130="moeda")+(Inputs!$G$5:$G$130="acoes"))*Inputs!$B$1+((Inputs!$G$5:$G$130<>"moeda")*(Inputs!$G$5:$G$130<>"acoes")))*INDEX(Inputs!$K$5:$AJ$130,0,MATCH(I$2,Inputs!$K$4:$AJ$4,0)))+SUMPRODUCT((Inputs!$E$5:$E$130=$B5)*Inputs!$F$5:$F$130*(((Inputs!$G$5:$G$130="moeda")+(Inputs!$G$5:$G$130="acoes"))*Inputs!$B$1+((Inputs!$G$5:$G$130<>"moeda")*(Inputs!$G$5:$G$130<>"acoes")))*INDEX(Inputs!$K$5:$AJ$130,0,MATCH(I$2,Inputs!$K$4:$AJ$4,0))))) -> -55657 | J5: =IF(ISNA(MATCH(J$2,Inputs!$K$4:$AJ$4,0)),NA(),IF(SUMPRODUCT((Inputs!$A$5:$A$130=$B5)*ISNUMBER(INDEX(Inputs!$K$5:$AJ$130,0,MATCH(J$2,Inputs!$K$4:$AJ$4,0))))+SUMPRODUCT((Inputs!$C$5:$C$130=$B5)*ISNUMBER(INDEX(Inputs!$K$5:$AJ$130,0,MATCH(J$2,Inputs!$K$4:$AJ$4,0))))+SUMPRODUCT((Inputs!$E$5:$E$130=$B5)*ISNUMBER(INDEX(Inputs!$K$5:$AJ$130,0,MATCH(J$2,Inputs!$K$4:$AJ$4,0))))=0,NA(),SUMPRODUCT((Inputs!$A$5:$A$130=$B5)*Inputs!$B$5:$B$130*(((Inputs!$G$5:$G$130="moeda")+(Inputs!$G$5:$G$130="acoes"))*Inputs!$B$1+((Inputs!$G$5:$G$130<>"moeda")*(Inputs!$G$5:$G$130<>"acoes")))*INDEX(Inputs!$K$5:$AJ$130,0,MATCH(J$2,Inputs!$K$4:$AJ$4,0)))+SUMPRODUCT((Inputs!$C$5:$C$130=$B5)*Inputs!$D$5:$D$130*(((Inputs!$G$5:$G$130="moeda")+(Inputs!$G$5:$G$130="acoes"))*Inputs!$B$1+((Inputs!$G$5:$G$130<>"moeda")*(Inputs!$G$5:$G$130<>"acoes")))*INDEX(Inputs!$K$5:$AJ$130,0,MATCH(J$2,Inputs!$K$4:$AJ$4,0)))+SUMPRODUCT((Inputs!$E$5:$E$130=$B5)*Inputs!$F$5:$F$130*(((Inputs!$G$5:$G$130="moeda")+(Inputs!$G$5:$G$130="acoes"))*Inputs!$B$1+((Inputs!$G$5:$G$130<>"moeda")*(Inputs!$G$5:$G$130<>"acoes")))*INDEX(Inputs!$K$5:$AJ$130,0,MATCH(J$2,Inputs!$K$4:$AJ$4,0))))) -> -66658 | K5: =IF(ISNA(MATCH(K$2,Inputs!$K$4:$AJ$4,0)),NA(),IF(SUMPRODUCT((Inputs!$A$5:$A$130=$B5)*ISNUMBER(INDEX(Inputs!$K$5:$AJ$130,0,MATCH(K$2,Inputs!$K$4:$AJ$4,0))))+SUMPRODUCT((Inputs!$C$5:$C$130=$B5)*ISNUMBER(INDEX(Inputs!$K$5:$AJ$130,0,MATCH(K$2,Inputs!$K$4:$AJ$4,0))))+SUMPRODUCT((Inputs!$E$5:$E$130=$B5)*ISNUMBER(INDEX(Inputs!$K$5:$AJ$130,0,MATCH(K$2,Inputs!$K$4:$AJ$4,0))))=0,NA(),SUMPRODUCT((Inputs!$A$5:$A$130=$B5)*Inputs!$B$5:$B$130*(((Inputs!$G$5:$G$130="moeda")+(Inputs!$G$5:$G$130="acoes"))*Inputs!$B$1+((Inputs!$G$5:$G$130<>"moeda")*(Inputs!$G$5:$G$130<>"acoes")))*INDEX(Inputs!$K$5:$AJ$130,0,MATCH(K$2,Inputs!$K$4:$AJ$4,0)))+SUMPRODUCT((Inputs!$C$5:$C$130=$B5)*Inputs!$D$5:$D$130*(((Inputs!$G$5:$G$130="moeda")+(Inputs!$G$5:$G$130="acoes"))*Inputs!$B$1+((Inputs!$G$5:$G$130<>"moeda")*(Inputs!$G$5:$G$130<>"acoes")))*INDEX(Inputs!$K$5:$AJ$130,0,MATCH(K$2,Inputs!$K$4:$AJ$4,0)))+SUMPRODUCT((Inputs!$E$5:$E$130=$B5)*Inputs!$F$5:$F$130*(((Inputs!$G$5:$G$130="moeda")+(Inputs!$G$5:$G$130="acoes"))*Inputs!$B$1+((Inputs!$G$5:$G$130<>"moeda")*(Inputs!$G$5:$G$130<>"acoes")))*INDEX(Inputs!$K$5:$AJ$130,0,MATCH(K$2,Inputs!$K$4:$AJ$4,0))))) -> -70684 | L5: =IF(ISNA(MATCH(L$2,Inputs!$K$4:$AJ$4,0)),NA(),IF(SUMPRODUCT((Inputs!$A$5:$A$130=$B5)*ISNUMBER(INDEX(Inputs!$K$5:$AJ$130,0,MATCH(L$2,Inputs!$K$4:$AJ$4,0))))+SUMPRODUCT((Inputs!$C$5:$C$130=$B5)*ISNUMBER(INDEX(Inputs!$K$5:$AJ$130,0,MATCH(L$2,Inputs!$K$4:$AJ$4,0))))+SUMPRODUCT((Inputs!$E$5:$E$130=$B5)*ISNUMBER(INDEX(Inputs!$K$5:$AJ$130,0,MATCH(L$2,Inputs!$K$4:$AJ$4,0))))=0,NA(),SUMPRODUCT((Inputs!$A$5:$A$130=$B5)*Inputs!$B$5:$B$130*(((Inputs!$G$5:$G$130="moeda")+(Inputs!$G$5:$G$130="acoes"))*Inputs!$B$1+((Inputs!$G$5:$G$130<>"moeda")*(Inputs!$G$5:$G$130<>"acoes")))*INDEX(Inputs!$K$5:$AJ$130,0,MATCH(L$2,Inputs!$K$4:$AJ$4,0)))+SUMPRODUCT((Inputs!$C$5:$C$130=$B5)*Inputs!$D$5:$D$130*(((Inputs!$G$5:$G$130="moeda")+(Inputs!$G$5:$G$130="acoes"))*Inputs!$B$1+((Inputs!$G$5:$G$130<>"moeda")*(Inputs!$G$5:$G$130<>"acoes")))*INDEX(Inputs!$K$5:$AJ$130,0,MATCH(L$2,Inputs!$K$4:$AJ$4,0)))+SUMPRODUCT((Inputs!$E$5:$E$130=$B5)*Inputs!$F$5:$F$130*(((Inputs!$G$5:$G$130="moeda")+(Inputs!$G$5:$G$130="acoes"))*Inputs!$B$1+((Inputs!$G$5:$G$130<>"moeda")*(Inputs!$G$5:$G$130<>"acoes")))*INDEX(Inputs!$K$5:$AJ$130,0,MATCH(L$2,Inputs!$K$4:$AJ$4,0))))) -> -65489 | M5: =SUM(I5:L5) -> -258488 | N5: =IF(ISNA(MATCH(N$2,Inputs!$K$4:$AJ$4,0)),NA(),IF(SUMPRODUCT((Inputs!$A$5:$A$130=$B5)*ISNUMBER(INDEX(Inputs!$K$5:$AJ$130,0,MATCH(N$2,Inputs!$K$4:$AJ$4,0))))+SUMPRODUCT((Inputs!$C$5:$C$130=$B5)*ISNUMBER(INDEX(Inputs!$K$5:$AJ$130,0,MATCH(N$2,Inputs!$K$4:$AJ$4,0))))+SUMPRODUCT((Inputs!$E$5:$E$130=$B5)*ISNUMBER(INDEX(Inputs!$K$5:$AJ$130,0,MATCH(N$2,Inputs!$K$4:$AJ$4,0))))=0,NA(),SUMPRODUCT((Inputs!$A$5:$A$130=$B5)*Inputs!$B$5:$B$130*(((Inputs!$G$5:$G$130="moeda")+(Inputs!$G$5:$G$130="acoes"))*Inputs!$B$1+((Inputs!$G$5:$G$130<>"moeda")*(Inputs!$G$5:$G$130<>"acoes")))*INDEX(Inputs!$K$5:$AJ$130,0,MATCH(N$2,Inputs!$K$4:$AJ$4,0)))+SUMPRODUCT((Inputs!$C$5:$C$130=$B5)*Inputs!$D$5:$D$130*(((Inputs!$G$5:$G$130="moeda")+(Inputs!$G$5:$G$130="acoes"))*Inputs!$B$1+((Inputs!$G$5:$G$130<>"moeda")*(Inputs!$G$5:$G$130<>"acoes")))*INDEX(Inputs!$K$5:$AJ$130,0,MATCH(N$2,Inputs!$K$4:$AJ$4,0)))+SUMPRODUCT((Inputs!$E$5:$E$130=$B5)*Inputs!$F$5:$F$130*(((Inputs!$G$5:$G$130="moeda")+(Inputs!$G$5:$G$130="acoes"))*Inputs!$B$1+((Inputs!$G$5:$G$130<>"moeda")*(Inputs!$G$5:$G$130<>"acoes")))*INDEX(Inputs!$K$5:$AJ$130,0,MATCH(N$2,Inputs!$K$4:$AJ$4,0))))) -> -57502 | O5: =IF(ISNA(MATCH(O$2,Inputs!$K$4:$AJ$4,0)),NA(),IF(SUMPRODUCT((Inputs!$A$5:$A$130=$B5)*ISNUMBER(INDEX(Inputs!$K$5:$AJ$130,0,MATCH(O$2,Inputs!$K$4:$AJ$4,0))))+SUMPRODUCT((Inputs!$C$5:$C$130=$B5)*ISNUMBER(INDEX(Inputs!$K$5:$AJ$130,0,MATCH(O$2,Inputs!$K$4:$AJ$4,0))))+SUMPRODUCT((Inputs!$E$5:$E$130=$B5)*ISNUMBER(INDEX(Inputs!$K$5:$AJ$130,0,MATCH(O$2,Inputs!$K$4:$AJ$4,0))))=0,NA(),SUMPRODUCT((Inputs!$A$5:$A$130=$B5)*Inputs!$B$5:$B$130*(((Inputs!$G$5:$G$130="moeda")+(Inputs!$G$5:$G$130="acoes"))*Inputs!$B$1+((Inputs!$G$5:$G$130<>"moeda")*(Inputs!$G$5:$G$130<>"acoes")))*INDEX(Inputs!$K$5:$AJ$130,0,MATCH(O$2,Inputs!$K$4:$AJ$4,0)))+SUMPRODUCT((Inputs!$C$5:$C$130=$B5)*Inputs!$D$5:$D$130*(((Inputs!$G$5:$G$130="moeda")+(Inputs!$G$5:$G$130="acoes"))*Inputs!$B$1+((Inputs!$G$5:$G$130<>"moeda")*(Inputs!$G$5:$G$130<>"acoes")))*INDEX(Inputs!$K$5:$AJ$130,0,MATCH(O$2,Inputs!$K$4:$AJ$4,0)))+SUMPRODUCT((Inputs!$E$5:$E$130=$B5)*Inputs!$F$5:$F$130*(((Inputs!$G$5:$G$130="moeda")+(Inputs!$G$5:$G$130="acoes"))*Inputs!$B$1+((Inputs!$G$5:$G$130<>"moeda")*(Inputs!$G$5:$G$130<>"acoes")))*INDEX(Inputs!$K$5:$AJ$130,0,MATCH(O$2,Inputs!$K$4:$AJ$4,0))))) -> -51492 | P5: =IF(ISNA(MATCH(P$2,Inputs!$K$4:$AJ$4,0)),NA(),IF(SUMPRODUCT((Inputs!$A$5:$A$130=$B5)*ISNUMBER(INDEX(Inputs!$K$5:$AJ$130,0,MATCH(P$2,Inputs!$K$4:$AJ$4,0))))+SUMPRODUCT((Inputs!$C$5:$C$130=$B5)*ISNUMBER(INDEX(Inputs!$K$5:$AJ$130,0,MATCH(P$2,Inputs!$K$4:$AJ$4,0))))+SUMPRODUCT((Inputs!$E$5:$E$130=$B5)*ISNUMBER(INDEX(Inputs!$K$5:$AJ$130,0,MATCH(P$2,Inputs!$K$4:$AJ$4,0))))=0,NA(),SUMPRODUCT((Inputs!$A$5:$A$130=$B5)*Inputs!$B$5:$B$130*(((Inputs!$G$5:$G$130="moeda")+(Inputs!$G$5:$G$130="acoes"))*Inputs!$B$1+((Inputs!$G$5:$G$130<>"moeda")*(Inputs!$G$5:$G$130<>"acoes")))*INDEX(Inputs!$K$5:$AJ$130,0,MATCH(P$2,Inputs!$K$4:$AJ$4,0)))+SUMPRODUCT((Inputs!$C$5:$C$130=$B5)*Inputs!$D$5:$D$130*(((Inputs!$G$5:$G$130="moeda")+(Inputs!$G$5:$G$130="acoes"))*Inputs!$B$1+((Inputs!$G$5:$G$130<>"moeda")*(Inputs!$G$5:$G$130<>"acoes")))*INDEX(Inputs!$K$5:$AJ$130,0,MATCH(P$2,Inputs!$K$4:$AJ$4,0)))+SUMPRODUCT((Inputs!$E$5:$E$130=$B5)*Inputs!$F$5:$F$130*(((Inputs!$G$5:$G$130="moeda")+(Inputs!$G$5:$G$130="acoes"))*Inputs!$B$1+((Inputs!$G$5:$G$130<>"moeda")*(Inputs!$G$5:$G$130<>"acoes")))*INDEX(Inputs!$K$5:$AJ$130,0,MATCH(P$2,Inputs!$K$4:$AJ$4,0))))) -> -49144 | Q5: =IF(ISNA(MATCH(Q$2,Inputs!$K$4:$AJ$4,0)),NA(),IF(SUMPRODUCT((Inputs!$A$5:$A$130=$B5)*ISNUMBER(INDEX(Inputs!$K$5:$AJ$130,0,MATCH(Q$2,Inputs!$K$4:$AJ$4,0))))+SUMPRODUCT((Inputs!$C$5:$C$130=$B5)*ISNUMBER(INDEX(Inputs!$K$5:$AJ$130,0,MATCH(Q$2,Inputs!$K$4:$AJ$4,0))))+SUMPRODUCT((Inputs!$E$5:$E$130=$B5)*ISNUMBER(INDEX(Inputs!$K$5:$AJ$130,0,MATCH(Q$2,Inputs!$K$4:$AJ$4,0))))=0,NA(),SUMPRODUCT((Inputs!$A$5:$A$130=$B5)*Inputs!$B$5:$B$130*(((Inputs!$G$5:$G$130="moeda")+(Inputs!$G$5:$G$130="acoes"))*Inputs!$B$1+((Inputs!$G$5:$G$130<>"moeda")*(Inputs!$G$5:$G$130<>"acoes")))*INDEX(Inputs!$K$5:$AJ$130,0,MATCH(Q$2,Inputs!$K$4:$AJ$4,0)))+SUMPRODUCT((Inputs!$C$5:$C$130=$B5)*Inputs!$D$5:$D$130*(((Inputs!$G$5:$G$130="moeda")+(Inputs!$G$5:$G$130="acoes"))*Inputs!$B$1+((Inputs!$G$5:$G$130<>"moeda")*(Inputs!$G$5:$G$130<>"acoes")))*INDEX(Inputs!$K$5:$AJ$130,0,MATCH(Q$2,Inputs!$K$4:$AJ$4,0)))+SUMPRODUCT((Inputs!$E$5:$E$130=$B5)*Inputs!$F$5:$F$130*(((Inputs!$G$5:$G$130="moeda")+(Inputs!$G$5:$G$130="acoes"))*Inputs!$B$1+((Inputs!$G$5:$G$130<>"moeda")*(Inputs!$G$5:$G$130<>"acoes")))*INDEX(Inputs!$K$5:$AJ$130,0,MATCH(Q$2,Inputs!$K$4:$AJ$4,0))))) -> -54745 | R5: =SUM(N5:Q5) -> -212883 | S5: =IF(ISNA(MATCH(S$2,Inputs!$K$4:$AJ$4,0)),NA(),IF(SUMPRODUCT((Inputs!$A$5:$A$130=$B5)*ISNUMBER(INDEX(Inputs!$K$5:$AJ$130,0,MATCH(S$2,Inputs!$K$4:$AJ$4,0))))+SUMPRODUCT((Inputs!$C$5:$C$130=$B5)*ISNUMBER(INDEX(Inputs!$K$5:$AJ$130,0,MATCH(S$2,Inputs!$K$4:$AJ$4,0))))+SUMPRODUCT((Inputs!$E$5:$E$130=$B5)*ISNUMBER(INDEX(Inputs!$K$5:$AJ$130,0,MATCH(S$2,Inputs!$K$4:$AJ$4,0))))=0,NA(),SUMPRODUCT((Inputs!$A$5:$A$130=$B5)*Inputs!$B$5:$B$130*(((Inputs!$G$5:$G$130="moeda")+(Inputs!$G$5:$G$130="acoes"))*Inputs!$B$1+((Inputs!$G$5:$G$130<>"moeda")*(Inputs!$G$5:$G$130<>"acoes")))*INDEX(Inputs!$K$5:$AJ$130,0,MATCH(S$2,Inputs!$K$4:$AJ$4,0)))+SUMPRODUCT((Inputs!$C$5:$C$130=$B5)*Inputs!$D$5:$D$130*(((Inputs!$G$5:$G$130="moeda")+(Inputs!$G$5:$G$130="acoes"))*Inputs!$B$1+((Inputs!$G$5:$G$130<>"moeda")*(Inputs!$G$5:$G$130<>"acoes")))*INDEX(Inputs!$K$5:$AJ$130,0,MATCH(S$2,Inputs!$K$4:$AJ$4,0)))+SUMPRODUCT((Inputs!$E$5:$E$130=$B5)*Inputs!$F$5:$F$130*(((Inputs!$G$5:$G$130="moeda")+(Inputs!$G$5:$G$130="acoes"))*Inputs!$B$1+((Inputs!$G$5:$G$130<>"moeda")*(Inputs!$G$5:$G$130<>"acoes")))*INDEX(Inputs!$K$5:$AJ$130,0,MATCH(S$2,Inputs!$K$4:$AJ$4,0))))) -> -46867 | T5: =IF(ISNA(MATCH(T$2,Inputs!$K$4:$AJ$4,0)),NA(),IF(SUMPRODUCT((Inputs!$A$5:$A$130=$B5)*ISNUMBER(INDEX(Inputs!$K$5:$AJ$130,0,MATCH(T$2,Inputs!$K$4:$AJ$4,0))))+SUMPRODUCT((Inputs!$C$5:$C$130=$B5)*ISNUMBER(INDEX(Inputs!$K$5:$AJ$130,0,MATCH(T$2,Inputs!$K$4:$AJ$4,0))))+SUMPRODUCT((Inputs!$E$5:$E$130=$B5)*ISNUMBER(INDEX(Inputs!$K$5:$AJ$130,0,MATCH(T$2,Inputs!$K$4:$AJ$4,0))))=0,NA(),SUMPRODUCT((Inputs!$A$5:$A$130=$B5)*Inputs!$B$5:$B$130*(((Inputs!$G$5:$G$130="moeda")+(Inputs!$G$5:$G$130="acoes"))*Inputs!$B$1+((Inputs!$G$5:$G$130<>"moeda")*(Inputs!$G$5:$G$130<>"acoes")))*INDEX(Inputs!$K$5:$AJ$130,0,MATCH(T$2,Inputs!$K$4:$AJ$4,0)))+SUMPRODUCT((Inputs!$C$5:$C$130=$B5)*Inputs!$D$5:$D$130*(((Inputs!$G$5:$G$130="moeda")+(Inputs!$G$5:$G$130="acoes"))*Inputs!$B$1+((Inputs!$G$5:$G$130<>"moeda")*(Inputs!$G$5:$G$130<>"acoes")))*INDEX(Inputs!$K$5:$AJ$130,0,MATCH(T$2,Inputs!$K$4:$AJ$4,0)))+SUMPRODUCT((Inputs!$E$5:$E$130=$B5)*Inputs!$F$5:$F$130*(((Inputs!$G$5:$G$130="moeda")+(Inputs!$G$5:$G$130="acoes"))*Inputs!$B$1+((Inputs!$G$5:$G$130<>"moeda")*(Inputs!$G$5:$G$130<>"acoes")))*INDEX(Inputs!$K$5:$AJ$130,0,MATCH(T$2,Inputs!$K$4:$AJ$4,0))))) -> -49417 | U5: =IF(ISNA(MATCH(U$2,Inputs!$K$4:$AJ$4,0)),NA(),IF(SUMPRODUCT((Inputs!$A$5:$A$130=$B5)*ISNUMBER(INDEX(Inputs!$K$5:$AJ$130,0,MATCH(U$2,Inputs!$K$4:$AJ$4,0))))+SUMPRODUCT((Inputs!$C$5:$C$130=$B5)*ISNUMBER(INDEX(Inputs!$K$5:$AJ$130,0,MATCH(U$2,Inputs!$K$4:$AJ$4,0))))+SUMPRODUCT((Inputs!$E$5:$E$130=$B5)*ISNUMBER(INDEX(Inputs!$K$5:$AJ$130,0,MATCH(U$2,Inputs!$K$4:$AJ$4,0))))=0,NA(),SUMPRODUCT((Inputs!$A$5:$A$130=$B5)*Inputs!$B$5:$B$130*(((Inputs!$G$5:$G$130="moeda")+(Inputs!$G$5:$G$130="acoes"))*Inputs!$B$1+((Inputs!$G$5:$G$130<>"moeda")*(Inputs!$G$5:$G$130<>"acoes")))*INDEX(Inputs!$K$5:$AJ$130,0,MATCH(U$2,Inputs!$K$4:$AJ$4,0)))+SUMPRODUCT((Inputs!$C$5:$C$130=$B5)*Inputs!$D$5:$D$130*(((Inputs!$G$5:$G$130="moeda")+(Inputs!$G$5:$G$130="acoes"))*Inputs!$B$1+((Inputs!$G$5:$G$130<>"moeda")*(Inputs!$G$5:$G$130<>"acoes")))*INDEX(Inputs!$K$5:$AJ$130,0,MATCH(U$2,Inputs!$K$4:$AJ$4,0)))+SUMPRODUCT((Inputs!$E$5:$E$130=$B5)*Inputs!$F$5:$F$130*(((Inputs!$G$5:$G$130="moeda")+(Inputs!$G$5:$G$130="acoes"))*Inputs!$B$1+((Inputs!$G$5:$G$130<>"moeda")*(Inputs!$G$5:$G$130<>"acoes")))*INDEX(Inputs!$K$5:$AJ$130,0,MATCH(U$2,Inputs!$K$4:$AJ$4,0))))) -> -48225 | V5: =IF(ISNA(MATCH(V$2,Inputs!$K$4:$AJ$4,0)),NA(),IF(SUMPRODUCT((Inputs!$A$5:$A$130=$B5)*ISNUMBER(INDEX(Inputs!$K$5:$AJ$130,0,MATCH(V$2,Inputs!$K$4:$AJ$4,0))))+SUMPRODUCT((Inputs!$C$5:$C$130=$B5)*ISNUMBER(INDEX(Inputs!$K$5:$AJ$130,0,MATCH(V$2,Inputs!$K$4:$AJ$4,0))))+SUMPRODUCT((Inputs!$E$5:$E$130=$B5)*ISNUMBER(INDEX(Inputs!$K$5:$AJ$130,0,MATCH(V$2,Inputs!$K$4:$AJ$4,0))))=0,NA(),SUMPRODUCT((Inputs!$A$5:$A$130=$B5)*Inputs!$B$5:$B$130*(((Inputs!$G$5:$G$130="moeda")+(Inputs!$G$5:$G$130="acoes"))*Inputs!$B$1+((Inputs!$G$5:$G$130<>"moeda")*(Inputs!$G$5:$G$130<>"acoes")))*INDEX(Inputs!$K$5:$AJ$130,0,MATCH(V$2,Inputs!$K$4:$AJ$4,0)))+SUMPRODUCT((Inputs!$C$5:$C$130=$B5)*Inputs!$D$5:$D$130*(((Inputs!$G$5:$G$130="moeda")+(Inputs!$G$5:$G$130="acoes"))*Inputs!$B$1+((Inputs!$G$5:$G$130<>"moeda")*(Inputs!$G$5:$G$130<>"acoes")))*INDEX(Inputs!$K$5:$AJ$130,0,MATCH(V$2,Inputs!$K$4:$AJ$4,0)))+SUMPRODUCT((Inputs!$E$5:$E$130=$B5)*Inputs!$F$5:$F$130*(((Inputs!$G$5:$G$130="moeda")+(Inputs!$G$5:$G$130="acoes"))*Inputs!$B$1+((Inputs!$G$5:$G$130<>"moeda")*(Inputs!$G$5:$G$130<>"acoes")))*INDEX(Inputs!$K$5:$AJ$130,0,MATCH(V$2,Inputs!$K$4:$AJ$4,0))))) -> -43610 | W5: =SUM(S5:V5) -> -188119 | X5: =IF(ISNA(MATCH(X$2,Inputs!$K$4:$AJ$4,0)),NA(),IF(SUMPRODUCT((Inputs!$A$5:$A$130=$B5)*ISNUMBER(INDEX(Inputs!$K$5:$AJ$130,0,MATCH(X$2,Inputs!$K$4:$AJ$4,0))))+SUMPRODUCT((Inputs!$C$5:$C$130=$B5)*ISNUMBER(INDEX(Inputs!$K$5:$AJ$130,0,MATCH(X$2,Inputs!$K$4:$AJ$4,0))))+SUMPRODUCT((Inputs!$E$5:$E$130=$B5)*ISNUMBER(INDEX(Inputs!$K$5:$AJ$130,0,MATCH(X$2,Inputs!$K$4:$AJ$4,0))))=0,NA(),SUMPRODUCT((Inputs!$A$5:$A$130=$B5)*Inputs!$B$5:$B$130*(((Inputs!$G$5:$G$130="moeda")+(Inputs!$G$5:$G$130="acoes"))*Inputs!$B$1+((Inputs!$G$5:$G$130<>"moeda")*(Inputs!$G$5:$G$130<>"acoes")))*INDEX(Inputs!$K$5:$AJ$130,0,MATCH(X$2,Inputs!$K$4:$AJ$4,0)))+SUMPRODUCT((Inputs!$C$5:$C$130=$B5)*Inputs!$D$5:$D$130*(((Inputs!$G$5:$G$130="moeda")+(Inputs!$G$5:$G$130="acoes"))*Inputs!$B$1+((Inputs!$G$5:$G$130<>"moeda")*(Inputs!$G$5:$G$130<>"acoes")))*INDEX(Inputs!$K$5:$AJ$130,0,MATCH(X$2,Inputs!$K$4:$AJ$4,0)))+SUMPRODUCT((Inputs!$E$5:$E$130=$B5)*Inputs!$F$5:$F$130*(((Inputs!$G$5:$G$130="moeda")+(Inputs!$G$5:$G$130="acoes"))*Inputs!$B$1+((Inputs!$G$5:$G$130<>"moeda")*(Inputs!$G$5:$G$130<>"acoes")))*INDEX(Inputs!$K$5:$AJ$130,0,MATCH(X$2,Inputs!$K$4:$AJ$4,0))))) -> -45849 | Y5: =IF(ISNA(MATCH(Y$2,Inputs!$K$4:$AJ$4,0)),NA(),IF(SUMPRODUCT((Inputs!$A$5:$A$130=$B5)*ISNUMBER(INDEX(Inputs!$K$5:$AJ$130,0,MATCH(Y$2,Inputs!$K$4:$AJ$4,0))))+SUMPRODUCT((Inputs!$C$5:$C$130=$B5)*ISNUMBER(INDEX(Inputs!$K$5:$AJ$130,0,MATCH(Y$2,Inputs!$K$4:$AJ$4,0))))+SUMPRODUCT((Inputs!$E$5:$E$130=$B5)*ISNUMBER(INDEX(Inputs!$K$5:$AJ$130,0,MATCH(Y$2,Inputs!$K$4:$AJ$4,0))))=0,NA(),SUMPRODUCT((Inputs!$A$5:$A$130=$B5)*Inputs!$B$5:$B$130*(((Inputs!$G$5:$G$130="moeda")+(Inputs!$G$5:$G$130="acoes"))*Inputs!$B$1+((Inputs!$G$5:$G$130<>"moeda")*(Inputs!$G$5:$G$130<>"acoes")))*INDEX(Inputs!$K$5:$AJ$130,0,MATCH(Y$2,Inputs!$K$4:$AJ$4,0)))+SUMPRODUCT((Inputs!$C$5:$C$130=$B5)*Inputs!$D$5:$D$130*(((Inputs!$G$5:$G$130="moeda")+(Inputs!$G$5:$G$130="acoes"))*Inputs!$B$1+((Inputs!$G$5:$G$130<>"moeda")*(Inputs!$G$5:$G$130<>"acoes")))*INDEX(Inputs!$K$5:$AJ$130,0,MATCH(Y$2,Inputs!$K$4:$AJ$4,0)))+SUMPRODUCT((Inputs!$E$5:$E$130=$B5)*Inputs!$F$5:$F$130*(((Inputs!$G$5:$G$130="moeda")+(Inputs!$G$5:$G$130="acoes"))*Inputs!$B$1+((Inputs!$G$5:$G$130<>"moeda")*(Inputs!$G$5:$G$130<>"acoes")))*INDEX(Inputs!$K$5:$AJ$130,0,MATCH(Y$2,Inputs!$K$4:$AJ$4,0))))) -> -44099 | Z5: =IF(ISNA(MATCH(Z$2,Inputs!$K$4:$AJ$4,0)),NA(),IF(SUMPRODUCT((Inputs!$A$5:$A$130=$B5)*ISNUMBER(INDEX(Inputs!$K$5:$AJ$130,0,MATCH(Z$2,Inputs!$K$4:$AJ$4,0))))+SUMPRODUCT((Inputs!$C$5:$C$130=$B5)*ISNUMBER(INDEX(Inputs!$K$5:$AJ$130,0,MATCH(Z$2,Inputs!$K$4:$AJ$4,0))))+SUMPRODUCT((Inputs!$E$5:$E$130=$B5)*ISNUMBER(INDEX(Inputs!$K$5:$AJ$130,0,MATCH(Z$2,Inputs!$K$4:$AJ$4,0))))=0,NA(),SUMPRODUCT((Inputs!$A$5:$A$130=$B5)*Inputs!$B$5:$B$130*(((Inputs!$G$5:$G$130="moeda")+(Inputs!$G$5:$G$130="acoes"))*Inputs!$B$1+((Inputs!$G$5:$G$130<>"moeda")*(Inputs!$G$5:$G$130<>"acoes")))*INDEX(Inputs!$K$5:$AJ$130,0,MATCH(Z$2,Inputs!$K$4:$AJ$4,0)))+SUMPRODUCT((Inputs!$C$5:$C$130=$B5)*Inputs!$D$5:$D$130*(((Inputs!$G$5:$G$130="moeda")+(Inputs!$G$5:$G$130="acoes"))*Inputs!$B$1+((Inputs!$G$5:$G$130<>"moeda")*(Inputs!$G$5:$G$130<>"acoes")))*INDEX(Inputs!$K$5:$AJ$130,0,MATCH(Z$2,Inputs!$K$4:$AJ$4,0)))+SUMPRODUCT((Inputs!$E$5:$E$130=$B5)*Inputs!$F$5:$F$130*(((Inputs!$G$5:$G$130="moeda")+(Inputs!$G$5:$G$130="acoes"))*Inputs!$B$1+((Inputs!$G$5:$G$130<>"moeda")*(Inputs!$G$5:$G$130<>"acoes")))*INDEX(Inputs!$K$5:$AJ$130,0,MATCH(Z$2,Inputs!$K$4:$AJ$4,0))))) -> -45145 | AA5: =IF(ISNA(MATCH(AA$2,Inputs!$K$4:$AJ$4,0)),NA(),IF(SUMPRODUCT((Inputs!$A$5:$A$130=$B5)*ISNUMBER(INDEX(Inputs!$K$5:$AJ$130,0,MATCH(AA$2,Inputs!$K$4:$AJ$4,0))))+SUMPRODUCT((Inputs!$C$5:$C$130=$B5)*ISNUMBER(INDEX(Inputs!$K$5:$AJ$130,0,MATCH(AA$2,Inputs!$K$4:$AJ$4,0))))+SUMPRODUCT((Inputs!$E$5:$E$130=$B5)*ISNUMBER(INDEX(Inputs!$K$5:$AJ$130,0,MATCH(AA$2,Inputs!$K$4:$AJ$4,0))))=0,NA(),SUMPRODUCT((Inputs!$A$5:$A$130=$B5)*Inputs!$B$5:$B$130*(((Inputs!$G$5:$G$130="moeda")+(Inputs!$G$5:$G$130="acoes"))*Inputs!$B$1+((Inputs!$G$5:$G$130<>"moeda")*(Inputs!$G$5:$G$130<>"acoes")))*INDEX(Inputs!$K$5:$AJ$130,0,MATCH(AA$2,Inputs!$K$4:$AJ$4,0)))+SUMPRODUCT((Inputs!$C$5:$C$130=$B5)*Inputs!$D$5:$D$130*(((Inputs!$G$5:$G$130="moeda")+(Inputs!$G$5:$G$130="acoes"))*Inputs!$B$1+((Inputs!$G$5:$G$130<>"moeda")*(Inputs!$G$5:$G$130<>"acoes")))*INDEX(Inputs!$K$5:$AJ$130,0,MATCH(AA$2,Inputs!$K$4:$AJ$4,0)))+SUMPRODUCT((Inputs!$E$5:$E$130=$B5)*Inputs!$F$5:$F$130*(((Inputs!$G$5:$G$130="moeda")+(Inputs!$G$5:$G$130="acoes"))*Inputs!$B$1+((Inputs!$G$5:$G$130<>"moeda")*(Inputs!$G$5:$G$130<>"acoes")))*INDEX(Inputs!$K$5:$AJ$130,0,MATCH(AA$2,Inputs!$K$4:$AJ$4,0))))) -> -42102 | AB5: =SUM(X5:AA5) -> -177195 | AC5: =IF(ISNA(MATCH(AC$2,Inputs!$K$4:$AJ$4,0)),NA(),IF(SUMPRODUCT((Inputs!$A$5:$A$130=$B5)*ISNUMBER(INDEX(Inputs!$K$5:$AJ$130,0,MATCH(AC$2,Inputs!$K$4:$AJ$4,0))))+SUMPRODUCT((Inputs!$C$5:$C$130=$B5)*ISNUMBER(INDEX(Inputs!$K$5:$AJ$130,0,MATCH(AC$2,Inputs!$K$4:$AJ$4,0))))+SUMPRODUCT((Inputs!$E$5:$E$130=$B5)*ISNUMBER(INDEX(Inputs!$K$5:$AJ$130,0,MATCH(AC$2,Inputs!$K$4:$AJ$4,0))))=0,NA(),SUMPRODUCT((Inputs!$A$5:$A$130=$B5)*Inputs!$B$5:$B$130*(((Inputs!$G$5:$G$130="moeda")+(Inputs!$G$5:$G$130="acoes"))*Inputs!$B$1+((Inputs!$G$5:$G$130<>"moeda")*(Inputs!$G$5:$G$130<>"acoes")))*INDEX(Inputs!$K$5:$AJ$130,0,MATCH(AC$2,Inputs!$K$4:$AJ$4,0)))+SUMPRODUCT((Inputs!$C$5:$C$130=$B5)*Inputs!$D$5:$D$130*(((Inputs!$G$5:$G$130="moeda")+(Inputs!$G$5:$G$130="acoes"))*Inputs!$B$1+((Inputs!$G$5:$G$130<>"moeda")*(Inputs!$G$5:$G$130<>"acoes")))*INDEX(Inputs!$K$5:$AJ$130,0,MATCH(AC$2,Inputs!$K$4:$AJ$4,0)))+SUMPRODUCT((Inputs!$E$5:$E$130=$B5)*Inputs!$F$5:$F$130*(((Inputs!$G$5:$G$130="moeda")+(Inputs!$G$5:$G$130="acoes"))*Inputs!$B$1+((Inputs!$G$5:$G$130<>"moeda")*(Inputs!$G$5:$G$130<>"acoes")))*INDEX(Inputs!$K$5:$AJ$130,0,MATCH(AC$2,Inputs!$K$4:$AJ$4,0))))) -> -44775 | AD5: =IF(ISNA(MATCH(AD$2,Inputs!$K$4:$AJ$4,0)),NA(),IF(SUMPRODUCT((Inputs!$A$5:$A$130=$B5)*ISNUMBER(INDEX(Inputs!$K$5:$AJ$130,0,MATCH(AD$2,Inputs!$K$4:$AJ$4,0))))+SUMPRODUCT((Inputs!$C$5:$C$130=$B5)*ISNUMBER(INDEX(Inputs!$K$5:$AJ$130,0,MATCH(AD$2,Inputs!$K$4:$AJ$4,0))))+SUMPRODUCT((Inputs!$E$5:$E$130=$B5)*ISNUMBER(INDEX(Inputs!$K$5:$AJ$130,0,MATCH(AD$2,Inputs!$K$4:$AJ$4,0))))=0,NA(),SUMPRODUCT((Inputs!$A$5:$A$130=$B5)*Inputs!$B$5:$B$130*(((Inputs!$G$5:$G$130="moeda")+(Inputs!$G$5:$G$130="acoes"))*Inputs!$B$1+((Inputs!$G$5:$G$130<>"moeda")*(Inputs!$G$5:$G$130<>"acoes")))*INDEX(Inputs!$K$5:$AJ$130,0,MATCH(AD$2,Inputs!$K$4:$AJ$4,0)))+SUMPRODUCT((Inputs!$C$5:$C$130=$B5)*Inputs!$D$5:$D$130*(((Inputs!$G$5:$G$130="moeda")+(Inputs!$G$5:$G$130="acoes"))*Inputs!$B$1+((Inputs!$G$5:$G$130<>"moeda")*(Inputs!$G$5:$G$130<>"acoes")))*INDEX(Inputs!$K$5:$AJ$130,0,MATCH(AD$2,Inputs!$K$4:$AJ$4,0)))+SUMPRODUCT((Inputs!$E$5:$E$130=$B5)*Inputs!$F$5:$F$130*(((Inputs!$G$5:$G$130="moeda")+(Inputs!$G$5:$G$130="acoes"))*Inputs!$B$1+((Inputs!$G$5:$G$130<>"moeda")*(Inputs!$G$5:$G$130<>"acoes")))*INDEX(Inputs!$K$5:$AJ$130,0,MATCH(AD$2,Inputs!$K$4:$AJ$4,0))))) -> -64530 | AE5: =IF(ISNA(MATCH(AE$2,Inputs!$K$4:$AJ$4,0)),NA(),IF(SUMPRODUCT((Inputs!$A$5:$A$130=$B5)*ISNUMBER(INDEX(Inputs!$K$5:$AJ$130,0,MATCH(AE$2,Inputs!$K$4:$AJ$4,0))))+SUMPRODUCT((Inputs!$C$5:$C$130=$B5)*ISNUMBER(INDEX(Inputs!$K$5:$AJ$130,0,MATCH(AE$2,Inputs!$K$4:$AJ$4,0))))+SUMPRODUCT((Inputs!$E$5:$E$130=$B5)*ISNUMBER(INDEX(Inputs!$K$5:$AJ$130,0,MATCH(AE$2,Inputs!$K$4:$AJ$4,0))))=0,NA(),SUMPRODUCT((Inputs!$A$5:$A$130=$B5)*Inputs!$B$5:$B$130*(((Inputs!$G$5:$G$130="moeda")+(Inputs!$G$5:$G$130="acoes"))*Inputs!$B$1+((Inputs!$G$5:$G$130<>"moeda")*(Inputs!$G$5:$G$130<>"acoes")))*INDEX(Inputs!$K$5:$AJ$130,0,MATCH(AE$2,Inputs!$K$4:$AJ$4,0)))+SUMPRODUCT((Inputs!$C$5:$C$130=$B5)*Inputs!$D$5:$D$130*(((Inputs!$G$5:$G$130="moeda")+(Inputs!$G$5:$G$130="acoes"))*Inputs!$B$1+((Inputs!$G$5:$G$130<>"moeda")*(Inputs!$G$5:$G$130<>"acoes")))*INDEX(Inputs!$K$5:$AJ$130,0,MATCH(AE$2,Inputs!$K$4:$AJ$4,0)))+SUMPRODUCT((Inputs!$E$5:$E$130=$B5)*Inputs!$F$5:$F$130*(((Inputs!$G$5:$G$130="moeda")+(Inputs!$G$5:$G$130="acoes"))*Inputs!$B$1+((Inputs!$G$5:$G$130<>"moeda")*(Inputs!$G$5:$G$130<>"acoes")))*INDEX(Inputs!$K$5:$AJ$130,0,MATCH(AE$2,Inputs!$K$4:$AJ$4,0))))) -> #N/A | AF5: =IF(ISNA(MATCH(AF$2,Inputs!$K$4:$AJ$4,0)),NA(),IF(SUMPRODUCT((Inputs!$A$5:$A$130=$B5)*ISNUMBER(INDEX(Inputs!$K$5:$AJ$130,0,MATCH(AF$2,Inputs!$K$4:$AJ$4,0))))+SUMPRODUCT((Inputs!$C$5:$C$130=$B5)*ISNUMBER(INDEX(Inputs!$K$5:$AJ$130,0,MATCH(AF$2,Inputs!$K$4:$AJ$4,0))))+SUMPRODUCT((Inputs!$E$5:$E$130=$B5)*ISNUMBER(INDEX(Inputs!$K$5:$AJ$130,0,MATCH(AF$2,Inputs!$K$4:$AJ$4,0))))=0,NA(),SUMPRODUCT((Inputs!$A$5:$A$130=$B5)*Inputs!$B$5:$B$130*(((Inputs!$G$5:$G$130="moeda")+(Inputs!$G$5:$G$130="acoes"))*Inputs!$B$1+((Inputs!$G$5:$G$130<>"moeda")*(Inputs!$G$5:$G$130<>"acoes")))*INDEX(Inputs!$K$5:$AJ$130,0,MATCH(AF$2,Inputs!$K$4:$AJ$4,0)))+SUMPRODUCT((Inputs!$C$5:$C$130=$B5)*Inputs!$D$5:$D$130*(((Inputs!$G$5:$G$130="moeda")+(Inputs!$G$5:$G$130="acoes"))*Inputs!$B$1+((Inputs!$G$5:$G$130<>"moeda")*(Inputs!$G$5:$G$130<>"acoes")))*INDEX(Inputs!$K$5:$AJ$130,0,MATCH(AF$2,Inputs!$K$4:$AJ$4,0)))+SUMPRODUCT((Inputs!$E$5:$E$130=$B5)*Inputs!$F$5:$F$130*(((Inputs!$G$5:$G$130="moeda")+(Inputs!$G$5:$G$130="acoes"))*Inputs!$B$1+((Inputs!$G$5:$G$130<>"moeda")*(Inputs!$G$5:$G$130<>"acoes")))*INDEX(Inputs!$K$5:$AJ$130,0,MATCH(AF$2,Inputs!$K$4:$AJ$4,0))))) -> #N/A | AG5: =SUM(AC5:AF5) -> #N/A | AH5: =IF(ISNA(MATCH(AH$2,Inputs!$K$4:$AJ$4,0)),NA(),IF(SUMPRODUCT((Inputs!$A$5:$A$130=$B5)*ISNUMBER(INDEX(Inputs!$K$5:$AJ$130,0,MATCH(AH$2,Inputs!$K$4:$AJ$4,0))))+SUMPRODUCT((Inputs!$C$5:$C$130=$B5)*ISNUMBER(INDEX(Inputs!$K$5:$AJ$130,0,MATCH(AH$2,Inputs!$K$4:$AJ$4,0))))+SUMPRODUCT((Inputs!$E$5:$E$130=$B5)*ISNUMBER(INDEX(Inputs!$K$5:$AJ$130,0,MATCH(AH$2,Inputs!$K$4:$AJ$4,0))))=0,NA(),SUMPRODUCT((Inputs!$A$5:$A$130=$B5)*Inputs!$B$5:$B$130*(((Inputs!$G$5:$G$130="moeda")+(Inputs!$G$5:$G$130="acoes"))*Inputs!$B$1+((Inputs!$G$5:$G$130<>"moeda")*(Inputs!$G$5:$G$130<>"acoes")))*INDEX(Inputs!$K$5:$AJ$130,0,MATCH(AH$2,Inputs!$K$4:$AJ$4,0)))+SUMPRODUCT((Inputs!$C$5:$C$130=$B5)*Inputs!$D$5:$D$130*(((Inputs!$G$5:$G$130="moeda")+(Inputs!$G$5:$G$130="acoes"))*Inputs!$B$1+((Inputs!$G$5:$G$130<>"moeda")*(Inputs!$G$5:$G$130<>"acoes")))*INDEX(Inputs!$K$5:$AJ$130,0,MATCH(AH$2,Inputs!$K$4:$AJ$4,0)))+SUMPRODUCT((Inputs!$E$5:$E$130=$B5)*Inputs!$F$5:$F$130*(((Inputs!$G$5:$G$130="moeda")+(Inputs!$G$5:$G$130="acoes"))*Inputs!$B$1+((Inputs!$G$5:$G$130<>"moeda")*(Inputs!$G$5:$G$130<>"acoes")))*INDEX(Inputs!$K$5:$AJ$130,0,MATCH(AH$2,Inputs!$K$4:$AJ$4,0))))) -> #N/A | AI5: =IF(ISNA(MATCH(AI$2,Inputs!$K$4:$AJ$4,0)),NA(),IF(SUMPRODUCT((Inputs!$A$5:$A$130=$B5)*ISNUMBER(INDEX(Inputs!$K$5:$AJ$130,0,MATCH(AI$2,Inputs!$K$4:$AJ$4,0))))+SUMPRODUCT((Inputs!$C$5:$C$130=$B5)*ISNUMBER(INDEX(Inputs!$K$5:$AJ$130,0,MATCH(AI$2,Inputs!$K$4:$AJ$4,0))))+SUMPRODUCT((Inputs!$E$5:$E$130=$B5)*ISNUMBER(INDEX(Inputs!$K$5:$AJ$130,0,MATCH(AI$2,Inputs!$K$4:$AJ$4,0))))=0,NA(),SUMPRODUCT((Inputs!$A$5:$A$130=$B5)*Inputs!$B$5:$B$130*(((Inputs!$G$5:$G$130="moeda")+(Inputs!$G$5:$G$130="acoes"))*Inputs!$B$1+((Inputs!$G$5:$G$130<>"moeda")*(Inputs!$G$5:$G$130<>"acoes")))*INDEX(Inputs!$K$5:$AJ$130,0,MATCH(AI$2,Inputs!$K$4:$AJ$4,0)))+SUMPRODUCT((Inputs!$C$5:$C$130=$B5)*Inputs!$D$5:$D$130*(((Inputs!$G$5:$G$130="moeda")+(Inputs!$G$5:$G$130="acoes"))*Inputs!$B$1+((Inputs!$G$5:$G$130<>"moeda")*(Inputs!$G$5:$G$130<>"acoes")))*INDEX(Inputs!$K$5:$AJ$130,0,MATCH(AI$2,Inputs!$K$4:$AJ$4,0)))+SUMPRODUCT((Inputs!$E$5:$E$130=$B5)*Inputs!$F$5:$F$130*(((Inputs!$G$5:$G$130="moeda")+(Inputs!$G$5:$G$130="acoes"))*Inputs!$B$1+((Inputs!$G$5:$G$130<>"moeda")*(Inputs!$G$5:$G$130<>"acoes")))*INDEX(Inputs!$K$5:$AJ$130,0,MATCH(AI$2,Inputs!$K$4:$AJ$4,0))))) -> #N/A | AJ5: =IF(ISNA(MATCH(AJ$2,Inputs!$K$4:$AJ$4,0)),NA(),IF(SUMPRODUCT((Inputs!$A$5:$A$130=$B5)*ISNUMBER(INDEX(Inputs!$K$5:$AJ$130,0,MATCH(AJ$2,Inputs!$K$4:$AJ$4,0))))+SUMPRODUCT((Inputs!$C$5:$C$130=$B5)*ISNUMBER(INDEX(Inputs!$K$5:$AJ$130,0,MATCH(AJ$2,Inputs!$K$4:$AJ$4,0))))+SUMPRODUCT((Inputs!$E$5:$E$130=$B5)*ISNUMBER(INDEX(Inputs!$K$5:$AJ$130,0,MATCH(AJ$2,Inputs!$K$4:$AJ$4,0))))=0,NA(),SUMPRODUCT((Inputs!$A$5:$A$130=$B5)*Inputs!$B$5:$B$130*(((Inputs!$G$5:$G$130="moeda")+(Inputs!$G$5:$G$130="acoes"))*Inputs!$B$1+((Inputs!$G$5:$G$130<>"moeda")*(Inputs!$G$5:$G$130<>"acoes")))*INDEX(Inputs!$K$5:$AJ$130,0,MATCH(AJ$2,Inputs!$K$4:$AJ$4,0)))+SUMPRODUCT((Inputs!$C$5:$C$130=$B5)*Inputs!$D$5:$D$130*(((Inputs!$G$5:$G$130="moeda")+(Inputs!$G$5:$G$130="acoes"))*Inputs!$B$1+((Inputs!$G$5:$G$130<>"moeda")*(Inputs!$G$5:$G$130<>"acoes")))*INDEX(Inputs!$K$5:$AJ$130,0,MATCH(AJ$2,Inputs!$K$4:$AJ$4,0)))+SUMPRODUCT((Inputs!$E$5:$E$130=$B5)*Inputs!$F$5:$F$130*(((Inputs!$G$5:$G$130="moeda")+(Inputs!$G$5:$G$130="acoes"))*Inputs!$B$1+((Inputs!$G$5:$G$130<>"moeda")*(Inputs!$G$5:$G$130<>"acoes")))*INDEX(Inputs!$K$5:$AJ$130,0,MATCH(AJ$2,Inputs!$K$4:$AJ$4,0))))) -> #N/A | AK5: =IF(ISNA(MATCH(AK$2,Inputs!$K$4:$AJ$4,0)),NA(),IF(SUMPRODUCT((Inputs!$A$5:$A$130=$B5)*ISNUMBER(INDEX(Inputs!$K$5:$AJ$130,0,MATCH(AK$2,Inputs!$K$4:$AJ$4,0))))+SUMPRODUCT((Inputs!$C$5:$C$130=$B5)*ISNUMBER(INDEX(Inputs!$K$5:$AJ$130,0,MATCH(AK$2,Inputs!$K$4:$AJ$4,0))))+SUMPRODUCT((Inputs!$E$5:$E$130=$B5)*ISNUMBER(INDEX(Inputs!$K$5:$AJ$130,0,MATCH(AK$2,Inputs!$K$4:$AJ$4,0))))=0,NA(),SUMPRODUCT((Inputs!$A$5:$A$130=$B5)*Inputs!$B$5:$B$130*(((Inputs!$G$5:$G$130="moeda")+(Inputs!$G$5:$G$130="acoes"))*Inputs!$B$1+((Inputs!$G$5:$G$130<>"moeda")*(Inputs!$G$5:$G$130<>"acoes")))*INDEX(Inputs!$K$5:$AJ$130,0,MATCH(AK$2,Inputs!$K$4:$AJ$4,0)))+SUMPRODUCT((Inputs!$C$5:$C$130=$B5)*Inputs!$D$5:$D$130*(((Inputs!$G$5:$G$130="moeda")+(Inputs!$G$5:$G$130="acoes"))*Inputs!$B$1+((Inputs!$G$5:$G$130<>"moeda")*(Inputs!$G$5:$G$130<>"acoes")))*INDEX(Inputs!$K$5:$AJ$130,0,MATCH(AK$2,Inputs!$K$4:$AJ$4,0)))+SUMPRODUCT((Inputs!$E$5:$E$130=$B5)*Inputs!$F$5:$F$130*(((Inputs!$G$5:$G$130="moeda")+(Inputs!$G$5:$G$130="acoes"))*Inputs!$B$1+((Inputs!$G$5:$G$130<>"moeda")*(Inputs!$G$5:$G$130<>"acoes")))*INDEX(Inputs!$K$5:$AJ$130,0,MATCH(AK$2,Inputs!$K$4:$AJ$4,0))))) -> #N/A | AL5: =SUM(AH5:AK5) -> #N/A
B6: 3 | C6: SG&A and Other (cash) | D6: =IF(ISNA(MATCH(D$2,Inputs!$K$4:$AJ$4,0)),NA(),IF(SUMPRODUCT((Inputs!$A$5:$A$130=$B6)*ISNUMBER(INDEX(Inputs!$K$5:$AJ$130,0,MATCH(D$2,Inputs!$K$4:$AJ$4,0))))+SUMPRODUCT((Inputs!$C$5:$C$130=$B6)*ISNUMBER(INDEX(Inputs!$K$5:$AJ$130,0,MATCH(D$2,Inputs!$K$4:$AJ$4,0))))+SUMPRODUCT((Inputs!$E$5:$E$130=$B6)*ISNUMBER(INDEX(Inputs!$K$5:$AJ$130,0,MATCH(D$2,Inputs!$K$4:$AJ$4,0))))=0,NA(),SUMPRODUCT((Inputs!$A$5:$A$130=$B6)*Inputs!$B$5:$B$130*(((Inputs!$G$5:$G$130="moeda")+(Inputs!$G$5:$G$130="acoes"))*Inputs!$B$1+((Inputs!$G$5:$G$130<>"moeda")*(Inputs!$G$5:$G$130<>"acoes")))*INDEX(Inputs!$K$5:$AJ$130,0,MATCH(D$2,Inputs!$K$4:$AJ$4,0)))+SUMPRODUCT((Inputs!$C$5:$C$130=$B6)*Inputs!$D$5:$D$130*(((Inputs!$G$5:$G$130="moeda")+(Inputs!$G$5:$G$130="acoes"))*Inputs!$B$1+((Inputs!$G$5:$G$130<>"moeda")*(Inputs!$G$5:$G$130<>"acoes")))*INDEX(Inputs!$K$5:$AJ$130,0,MATCH(D$2,Inputs!$K$4:$AJ$4,0)))+SUMPRODUCT((Inputs!$E$5:$E$130=$B6)*Inputs!$F$5:$F$130*(((Inputs!$G$5:$G$130="moeda")+(Inputs!$G$5:$G$130="acoes"))*Inputs!$B$1+((Inputs!$G$5:$G$130<>"moeda")*(Inputs!$G$5:$G$130<>"acoes")))*INDEX(Inputs!$K$5:$AJ$130,0,MATCH(D$2,Inputs!$K$4:$AJ$4,0))))) -> -9721 | E6: =IF(ISNA(MATCH(E$2,Inputs!$K$4:$AJ$4,0)),NA(),IF(SUMPRODUCT((Inputs!$A$5:$A$130=$B6)*ISNUMBER(INDEX(Inputs!$K$5:$AJ$130,0,MATCH(E$2,Inputs!$K$4:$AJ$4,0))))+SUMPRODUCT((Inputs!$C$5:$C$130=$B6)*ISNUMBER(INDEX(Inputs!$K$5:$AJ$130,0,MATCH(E$2,Inputs!$K$4:$AJ$4,0))))+SUMPRODUCT((Inputs!$E$5:$E$130=$B6)*ISNUMBER(INDEX(Inputs!$K$5:$AJ$130,0,MATCH(E$2,Inputs!$K$4:$AJ$4,0))))=0,NA(),SUMPRODUCT((Inputs!$A$5:$A$130=$B6)*Inputs!$B$5:$B$130*(((Inputs!$G$5:$G$130="moeda")+(Inputs!$G$5:$G$130="acoes"))*Inputs!$B$1+((Inputs!$G$5:$G$130<>"moeda")*(Inputs!$G$5:$G$130<>"acoes")))*INDEX(Inputs!$K$5:$AJ$130,0,MATCH(E$2,Inputs!$K$4:$AJ$4,0)))+SUMPRODUCT((Inputs!$C$5:$C$130=$B6)*Inputs!$D$5:$D$130*(((Inputs!$G$5:$G$130="moeda")+(Inputs!$G$5:$G$130="acoes"))*Inputs!$B$1+((Inputs!$G$5:$G$130<>"moeda")*(Inputs!$G$5:$G$130<>"acoes")))*INDEX(Inputs!$K$5:$AJ$130,0,MATCH(E$2,Inputs!$K$4:$AJ$4,0)))+SUMPRODUCT((Inputs!$E$5:$E$130=$B6)*Inputs!$F$5:$F$130*(((Inputs!$G$5:$G$130="moeda")+(Inputs!$G$5:$G$130="acoes"))*Inputs!$B$1+((Inputs!$G$5:$G$130<>"moeda")*(Inputs!$G$5:$G$130<>"acoes")))*INDEX(Inputs!$K$5:$AJ$130,0,MATCH(E$2,Inputs!$K$4:$AJ$4,0))))) -> -8802 | F6: =IF(ISNA(MATCH(F$2,Inputs!$K$4:$AJ$4,0)),NA(),IF(SUMPRODUCT((Inputs!$A$5:$A$130=$B6)*ISNUMBER(INDEX(Inputs!$K$5:$AJ$130,0,MATCH(F$2,Inputs!$K$4:$AJ$4,0))))+SUMPRODUCT((Inputs!$C$5:$C$130=$B6)*ISNUMBER(INDEX(Inputs!$K$5:$AJ$130,0,MATCH(F$2,Inputs!$K$4:$AJ$4,0))))+SUMPRODUCT((Inputs!$E$5:$E$130=$B6)*ISNUMBER(INDEX(Inputs!$K$5:$AJ$130,0,MATCH(F$2,Inputs!$K$4:$AJ$4,0))))=0,NA(),SUMPRODUCT((Inputs!$A$5:$A$130=$B6)*Inputs!$B$5:$B$130*(((Inputs!$G$5:$G$130="moeda")+(Inputs!$G$5:$G$130="acoes"))*Inputs!$B$1+((Inputs!$G$5:$G$130<>"moeda")*(Inputs!$G$5:$G$130<>"acoes")))*INDEX(Inputs!$K$5:$AJ$130,0,MATCH(F$2,Inputs!$K$4:$AJ$4,0)))+SUMPRODUCT((Inputs!$C$5:$C$130=$B6)*Inputs!$D$5:$D$130*(((Inputs!$G$5:$G$130="moeda")+(Inputs!$G$5:$G$130="acoes"))*Inputs!$B$1+((Inputs!$G$5:$G$130<>"moeda")*(Inputs!$G$5:$G$130<>"acoes")))*INDEX(Inputs!$K$5:$AJ$130,0,MATCH(F$2,Inputs!$K$4:$AJ$4,0)))+SUMPRODUCT((Inputs!$E$5:$E$130=$B6)*Inputs!$F$5:$F$130*(((Inputs!$G$5:$G$130="moeda")+(Inputs!$G$5:$G$130="acoes"))*Inputs!$B$1+((Inputs!$G$5:$G$130<>"moeda")*(Inputs!$G$5:$G$130<>"acoes")))*INDEX(Inputs!$K$5:$AJ$130,0,MATCH(F$2,Inputs!$K$4:$AJ$4,0))))) -> -8885 | G6: =IF(ISNA(MATCH(G$2,Inputs!$K$4:$AJ$4,0)),NA(),IF(SUMPRODUCT((Inputs!$A$5:$A$130=$B6)*ISNUMBER(INDEX(Inputs!$K$5:$AJ$130,0,MATCH(G$2,Inputs!$K$4:$AJ$4,0))))+SUMPRODUCT((Inputs!$C$5:$C$130=$B6)*ISNUMBER(INDEX(Inputs!$K$5:$AJ$130,0,MATCH(G$2,Inputs!$K$4:$AJ$4,0))))+SUMPRODUCT((Inputs!$E$5:$E$130=$B6)*ISNUMBER(INDEX(Inputs!$K$5:$AJ$130,0,MATCH(G$2,Inputs!$K$4:$AJ$4,0))))=0,NA(),SUMPRODUCT((Inputs!$A$5:$A$130=$B6)*Inputs!$B$5:$B$130*(((Inputs!$G$5:$G$130="moeda")+(Inputs!$G$5:$G$130="acoes"))*Inputs!$B$1+((Inputs!$G$5:$G$130<>"moeda")*(Inputs!$G$5:$G$130<>"acoes")))*INDEX(Inputs!$K$5:$AJ$130,0,MATCH(G$2,Inputs!$K$4:$AJ$4,0)))+SUMPRODUCT((Inputs!$C$5:$C$130=$B6)*Inputs!$D$5:$D$130*(((Inputs!$G$5:$G$130="moeda")+(Inputs!$G$5:$G$130="acoes"))*Inputs!$B$1+((Inputs!$G$5:$G$130<>"moeda")*(Inputs!$G$5:$G$130<>"acoes")))*INDEX(Inputs!$K$5:$AJ$130,0,MATCH(G$2,Inputs!$K$4:$AJ$4,0)))+SUMPRODUCT((Inputs!$E$5:$E$130=$B6)*Inputs!$F$5:$F$130*(((Inputs!$G$5:$G$130="moeda")+(Inputs!$G$5:$G$130="acoes"))*Inputs!$B$1+((Inputs!$G$5:$G$130<>"moeda")*(Inputs!$G$5:$G$130<>"acoes")))*INDEX(Inputs!$K$5:$AJ$130,0,MATCH(G$2,Inputs!$K$4:$AJ$4,0))))) -> -9981 | H6: =SUM(D6:G6) -> -37389 | I6: =IF(ISNA(MATCH(I$2,Inputs!$K$4:$AJ$4,0)),NA(),IF(SUMPRODUCT((Inputs!$A$5:$A$130=$B6)*ISNUMBER(INDEX(Inputs!$K$5:$AJ$130,0,MATCH(I$2,Inputs!$K$4:$AJ$4,0))))+SUMPRODUCT((Inputs!$C$5:$C$130=$B6)*ISNUMBER(INDEX(Inputs!$K$5:$AJ$130,0,MATCH(I$2,Inputs!$K$4:$AJ$4,0))))+SUMPRODUCT((Inputs!$E$5:$E$130=$B6)*ISNUMBER(INDEX(Inputs!$K$5:$AJ$130,0,MATCH(I$2,Inputs!$K$4:$AJ$4,0))))=0,NA(),SUMPRODUCT((Inputs!$A$5:$A$130=$B6)*Inputs!$B$5:$B$130*(((Inputs!$G$5:$G$130="moeda")+(Inputs!$G$5:$G$130="acoes"))*Inputs!$B$1+((Inputs!$G$5:$G$130<>"moeda")*(Inputs!$G$5:$G$130<>"acoes")))*INDEX(Inputs!$K$5:$AJ$130,0,MATCH(I$2,Inputs!$K$4:$AJ$4,0)))+SUMPRODUCT((Inputs!$C$5:$C$130=$B6)*Inputs!$D$5:$D$130*(((Inputs!$G$5:$G$130="moeda")+(Inputs!$G$5:$G$130="acoes"))*Inputs!$B$1+((Inputs!$G$5:$G$130<>"moeda")*(Inputs!$G$5:$G$130<>"acoes")))*INDEX(Inputs!$K$5:$AJ$130,0,MATCH(I$2,Inputs!$K$4:$AJ$4,0)))+SUMPRODUCT((Inputs!$E$5:$E$130=$B6)*Inputs!$F$5:$F$130*(((Inputs!$G$5:$G$130="moeda")+(Inputs!$G$5:$G$130="acoes"))*Inputs!$B$1+((Inputs!$G$5:$G$130<>"moeda")*(Inputs!$G$5:$G$130<>"acoes")))*INDEX(Inputs!$K$5:$AJ$130,0,MATCH(I$2,Inputs!$K$4:$AJ$4,0))))) -> -9726 | J6: =IF(ISNA(MATCH(J$2,Inputs!$K$4:$AJ$4,0)),NA(),IF(SUMPRODUCT((Inputs!$A$5:$A$130=$B6)*ISNUMBER(INDEX(Inputs!$K$5:$AJ$130,0,MATCH(J$2,Inputs!$K$4:$AJ$4,0))))+SUMPRODUCT((Inputs!$C$5:$C$130=$B6)*ISNUMBER(INDEX(Inputs!$K$5:$AJ$130,0,MATCH(J$2,Inputs!$K$4:$AJ$4,0))))+SUMPRODUCT((Inputs!$E$5:$E$130=$B6)*ISNUMBER(INDEX(Inputs!$K$5:$AJ$130,0,MATCH(J$2,Inputs!$K$4:$AJ$4,0))))=0,NA(),SUMPRODUCT((Inputs!$A$5:$A$130=$B6)*Inputs!$B$5:$B$130*(((Inputs!$G$5:$G$130="moeda")+(Inputs!$G$5:$G$130="acoes"))*Inputs!$B$1+((Inputs!$G$5:$G$130<>"moeda")*(Inputs!$G$5:$G$130<>"acoes")))*INDEX(Inputs!$K$5:$AJ$130,0,MATCH(J$2,Inputs!$K$4:$AJ$4,0)))+SUMPRODUCT((Inputs!$C$5:$C$130=$B6)*Inputs!$D$5:$D$130*(((Inputs!$G$5:$G$130="moeda")+(Inputs!$G$5:$G$130="acoes"))*Inputs!$B$1+((Inputs!$G$5:$G$130<>"moeda")*(Inputs!$G$5:$G$130<>"acoes")))*INDEX(Inputs!$K$5:$AJ$130,0,MATCH(J$2,Inputs!$K$4:$AJ$4,0)))+SUMPRODUCT((Inputs!$E$5:$E$130=$B6)*Inputs!$F$5:$F$130*(((Inputs!$G$5:$G$130="moeda")+(Inputs!$G$5:$G$130="acoes"))*Inputs!$B$1+((Inputs!$G$5:$G$130<>"moeda")*(Inputs!$G$5:$G$130<>"acoes")))*INDEX(Inputs!$K$5:$AJ$130,0,MATCH(J$2,Inputs!$K$4:$AJ$4,0))))) -> -9917 | K6: =IF(ISNA(MATCH(K$2,Inputs!$K$4:$AJ$4,0)),NA(),IF(SUMPRODUCT((Inputs!$A$5:$A$130=$B6)*ISNUMBER(INDEX(Inputs!$K$5:$AJ$130,0,MATCH(K$2,Inputs!$K$4:$AJ$4,0))))+SUMPRODUCT((Inputs!$C$5:$C$130=$B6)*ISNUMBER(INDEX(Inputs!$K$5:$AJ$130,0,MATCH(K$2,Inputs!$K$4:$AJ$4,0))))+SUMPRODUCT((Inputs!$E$5:$E$130=$B6)*ISNUMBER(INDEX(Inputs!$K$5:$AJ$130,0,MATCH(K$2,Inputs!$K$4:$AJ$4,0))))=0,NA(),SUMPRODUCT((Inputs!$A$5:$A$130=$B6)*Inputs!$B$5:$B$130*(((Inputs!$G$5:$G$130="moeda")+(Inputs!$G$5:$G$130="acoes"))*Inputs!$B$1+((Inputs!$G$5:$G$130<>"moeda")*(Inputs!$G$5:$G$130<>"acoes")))*INDEX(Inputs!$K$5:$AJ$130,0,MATCH(K$2,Inputs!$K$4:$AJ$4,0)))+SUMPRODUCT((Inputs!$C$5:$C$130=$B6)*Inputs!$D$5:$D$130*(((Inputs!$G$5:$G$130="moeda")+(Inputs!$G$5:$G$130="acoes"))*Inputs!$B$1+((Inputs!$G$5:$G$130<>"moeda")*(Inputs!$G$5:$G$130<>"acoes")))*INDEX(Inputs!$K$5:$AJ$130,0,MATCH(K$2,Inputs!$K$4:$AJ$4,0)))+SUMPRODUCT((Inputs!$E$5:$E$130=$B6)*Inputs!$F$5:$F$130*(((Inputs!$G$5:$G$130="moeda")+(Inputs!$G$5:$G$130="acoes"))*Inputs!$B$1+((Inputs!$G$5:$G$130<>"moeda")*(Inputs!$G$5:$G$130<>"acoes")))*INDEX(Inputs!$K$5:$AJ$130,0,MATCH(K$2,Inputs!$K$4:$AJ$4,0))))) -> -9783 | L6: =IF(ISNA(MATCH(L$2,Inputs!$K$4:$AJ$4,0)),NA(),IF(SUMPRODUCT((Inputs!$A$5:$A$130=$B6)*ISNUMBER(INDEX(Inputs!$K$5:$AJ$130,0,MATCH(L$2,Inputs!$K$4:$AJ$4,0))))+SUMPRODUCT((Inputs!$C$5:$C$130=$B6)*ISNUMBER(INDEX(Inputs!$K$5:$AJ$130,0,MATCH(L$2,Inputs!$K$4:$AJ$4,0))))+SUMPRODUCT((Inputs!$E$5:$E$130=$B6)*ISNUMBER(INDEX(Inputs!$K$5:$AJ$130,0,MATCH(L$2,Inputs!$K$4:$AJ$4,0))))=0,NA(),SUMPRODUCT((Inputs!$A$5:$A$130=$B6)*Inputs!$B$5:$B$130*(((Inputs!$G$5:$G$130="moeda")+(Inputs!$G$5:$G$130="acoes"))*Inputs!$B$1+((Inputs!$G$5:$G$130<>"moeda")*(Inputs!$G$5:$G$130<>"acoes")))*INDEX(Inputs!$K$5:$AJ$130,0,MATCH(L$2,Inputs!$K$4:$AJ$4,0)))+SUMPRODUCT((Inputs!$C$5:$C$130=$B6)*Inputs!$D$5:$D$130*(((Inputs!$G$5:$G$130="moeda")+(Inputs!$G$5:$G$130="acoes"))*Inputs!$B$1+((Inputs!$G$5:$G$130<>"moeda")*(Inputs!$G$5:$G$130<>"acoes")))*INDEX(Inputs!$K$5:$AJ$130,0,MATCH(L$2,Inputs!$K$4:$AJ$4,0)))+SUMPRODUCT((Inputs!$E$5:$E$130=$B6)*Inputs!$F$5:$F$130*(((Inputs!$G$5:$G$130="moeda")+(Inputs!$G$5:$G$130="acoes"))*Inputs!$B$1+((Inputs!$G$5:$G$130<>"moeda")*(Inputs!$G$5:$G$130<>"acoes")))*INDEX(Inputs!$K$5:$AJ$130,0,MATCH(L$2,Inputs!$K$4:$AJ$4,0))))) -> -11763 | M6: =SUM(I6:L6) -> -41189 | N6: =IF(ISNA(MATCH(N$2,Inputs!$K$4:$AJ$4,0)),NA(),IF(SUMPRODUCT((Inputs!$A$5:$A$130=$B6)*ISNUMBER(INDEX(Inputs!$K$5:$AJ$130,0,MATCH(N$2,Inputs!$K$4:$AJ$4,0))))+SUMPRODUCT((Inputs!$C$5:$C$130=$B6)*ISNUMBER(INDEX(Inputs!$K$5:$AJ$130,0,MATCH(N$2,Inputs!$K$4:$AJ$4,0))))+SUMPRODUCT((Inputs!$E$5:$E$130=$B6)*ISNUMBER(INDEX(Inputs!$K$5:$AJ$130,0,MATCH(N$2,Inputs!$K$4:$AJ$4,0))))=0,NA(),SUMPRODUCT((Inputs!$A$5:$A$130=$B6)*Inputs!$B$5:$B$130*(((Inputs!$G$5:$G$130="moeda")+(Inputs!$G$5:$G$130="acoes"))*Inputs!$B$1+((Inputs!$G$5:$G$130<>"moeda")*(Inputs!$G$5:$G$130<>"acoes")))*INDEX(Inputs!$K$5:$AJ$130,0,MATCH(N$2,Inputs!$K$4:$AJ$4,0)))+SUMPRODUCT((Inputs!$C$5:$C$130=$B6)*Inputs!$D$5:$D$130*(((Inputs!$G$5:$G$130="moeda")+(Inputs!$G$5:$G$130="acoes"))*Inputs!$B$1+((Inputs!$G$5:$G$130<>"moeda")*(Inputs!$G$5:$G$130<>"acoes")))*INDEX(Inputs!$K$5:$AJ$130,0,MATCH(N$2,Inputs!$K$4:$AJ$4,0)))+SUMPRODUCT((Inputs!$E$5:$E$130=$B6)*Inputs!$F$5:$F$130*(((Inputs!$G$5:$G$130="moeda")+(Inputs!$G$5:$G$130="acoes"))*Inputs!$B$1+((Inputs!$G$5:$G$130<>"moeda")*(Inputs!$G$5:$G$130<>"acoes")))*INDEX(Inputs!$K$5:$AJ$130,0,MATCH(N$2,Inputs!$K$4:$AJ$4,0))))) -> -9716 | O6: =IF(ISNA(MATCH(O$2,Inputs!$K$4:$AJ$4,0)),NA(),IF(SUMPRODUCT((Inputs!$A$5:$A$130=$B6)*ISNUMBER(INDEX(Inputs!$K$5:$AJ$130,0,MATCH(O$2,Inputs!$K$4:$AJ$4,0))))+SUMPRODUCT((Inputs!$C$5:$C$130=$B6)*ISNUMBER(INDEX(Inputs!$K$5:$AJ$130,0,MATCH(O$2,Inputs!$K$4:$AJ$4,0))))+SUMPRODUCT((Inputs!$E$5:$E$130=$B6)*ISNUMBER(INDEX(Inputs!$K$5:$AJ$130,0,MATCH(O$2,Inputs!$K$4:$AJ$4,0))))=0,NA(),SUMPRODUCT((Inputs!$A$5:$A$130=$B6)*Inputs!$B$5:$B$130*(((Inputs!$G$5:$G$130="moeda")+(Inputs!$G$5:$G$130="acoes"))*Inputs!$B$1+((Inputs!$G$5:$G$130<>"moeda")*(Inputs!$G$5:$G$130<>"acoes")))*INDEX(Inputs!$K$5:$AJ$130,0,MATCH(O$2,Inputs!$K$4:$AJ$4,0)))+SUMPRODUCT((Inputs!$C$5:$C$130=$B6)*Inputs!$D$5:$D$130*(((Inputs!$G$5:$G$130="moeda")+(Inputs!$G$5:$G$130="acoes"))*Inputs!$B$1+((Inputs!$G$5:$G$130<>"moeda")*(Inputs!$G$5:$G$130<>"acoes")))*INDEX(Inputs!$K$5:$AJ$130,0,MATCH(O$2,Inputs!$K$4:$AJ$4,0)))+SUMPRODUCT((Inputs!$E$5:$E$130=$B6)*Inputs!$F$5:$F$130*(((Inputs!$G$5:$G$130="moeda")+(Inputs!$G$5:$G$130="acoes"))*Inputs!$B$1+((Inputs!$G$5:$G$130<>"moeda")*(Inputs!$G$5:$G$130<>"acoes")))*INDEX(Inputs!$K$5:$AJ$130,0,MATCH(O$2,Inputs!$K$4:$AJ$4,0))))) -> -10096 | P6: =IF(ISNA(MATCH(P$2,Inputs!$K$4:$AJ$4,0)),NA(),IF(SUMPRODUCT((Inputs!$A$5:$A$130=$B6)*ISNUMBER(INDEX(Inputs!$K$5:$AJ$130,0,MATCH(P$2,Inputs!$K$4:$AJ$4,0))))+SUMPRODUCT((Inputs!$C$5:$C$130=$B6)*ISNUMBER(INDEX(Inputs!$K$5:$AJ$130,0,MATCH(P$2,Inputs!$K$4:$AJ$4,0))))+SUMPRODUCT((Inputs!$E$5:$E$130=$B6)*ISNUMBER(INDEX(Inputs!$K$5:$AJ$130,0,MATCH(P$2,Inputs!$K$4:$AJ$4,0))))=0,NA(),SUMPRODUCT((Inputs!$A$5:$A$130=$B6)*Inputs!$B$5:$B$130*(((Inputs!$G$5:$G$130="moeda")+(Inputs!$G$5:$G$130="acoes"))*Inputs!$B$1+((Inputs!$G$5:$G$130<>"moeda")*(Inputs!$G$5:$G$130<>"acoes")))*INDEX(Inputs!$K$5:$AJ$130,0,MATCH(P$2,Inputs!$K$4:$AJ$4,0)))+SUMPRODUCT((Inputs!$C$5:$C$130=$B6)*Inputs!$D$5:$D$130*(((Inputs!$G$5:$G$130="moeda")+(Inputs!$G$5:$G$130="acoes"))*Inputs!$B$1+((Inputs!$G$5:$G$130<>"moeda")*(Inputs!$G$5:$G$130<>"acoes")))*INDEX(Inputs!$K$5:$AJ$130,0,MATCH(P$2,Inputs!$K$4:$AJ$4,0)))+SUMPRODUCT((Inputs!$E$5:$E$130=$B6)*Inputs!$F$5:$F$130*(((Inputs!$G$5:$G$130="moeda")+(Inputs!$G$5:$G$130="acoes"))*Inputs!$B$1+((Inputs!$G$5:$G$130<>"moeda")*(Inputs!$G$5:$G$130<>"acoes")))*INDEX(Inputs!$K$5:$AJ$130,0,MATCH(P$2,Inputs!$K$4:$AJ$4,0))))) -> -10534 | Q6: =IF(ISNA(MATCH(Q$2,Inputs!$K$4:$AJ$4,0)),NA(),IF(SUMPRODUCT((Inputs!$A$5:$A$130=$B6)*ISNUMBER(INDEX(Inputs!$K$5:$AJ$130,0,MATCH(Q$2,Inputs!$K$4:$AJ$4,0))))+SUMPRODUCT((Inputs!$C$5:$C$130=$B6)*ISNUMBER(INDEX(Inputs!$K$5:$AJ$130,0,MATCH(Q$2,Inputs!$K$4:$AJ$4,0))))+SUMPRODUCT((Inputs!$E$5:$E$130=$B6)*ISNUMBER(INDEX(Inputs!$K$5:$AJ$130,0,MATCH(Q$2,Inputs!$K$4:$AJ$4,0))))=0,NA(),SUMPRODUCT((Inputs!$A$5:$A$130=$B6)*Inputs!$B$5:$B$130*(((Inputs!$G$5:$G$130="moeda")+(Inputs!$G$5:$G$130="acoes"))*Inputs!$B$1+((Inputs!$G$5:$G$130<>"moeda")*(Inputs!$G$5:$G$130<>"acoes")))*INDEX(Inputs!$K$5:$AJ$130,0,MATCH(Q$2,Inputs!$K$4:$AJ$4,0)))+SUMPRODUCT((Inputs!$C$5:$C$130=$B6)*Inputs!$D$5:$D$130*(((Inputs!$G$5:$G$130="moeda")+(Inputs!$G$5:$G$130="acoes"))*Inputs!$B$1+((Inputs!$G$5:$G$130<>"moeda")*(Inputs!$G$5:$G$130<>"acoes")))*INDEX(Inputs!$K$5:$AJ$130,0,MATCH(Q$2,Inputs!$K$4:$AJ$4,0)))+SUMPRODUCT((Inputs!$E$5:$E$130=$B6)*Inputs!$F$5:$F$130*(((Inputs!$G$5:$G$130="moeda")+(Inputs!$G$5:$G$130="acoes"))*Inputs!$B$1+((Inputs!$G$5:$G$130<>"moeda")*(Inputs!$G$5:$G$130<>"acoes")))*INDEX(Inputs!$K$5:$AJ$130,0,MATCH(Q$2,Inputs!$K$4:$AJ$4,0))))) -> -11364 | R6: =SUM(N6:Q6) -> -41710 | S6: =IF(ISNA(MATCH(S$2,Inputs!$K$4:$AJ$4,0)),NA(),IF(SUMPRODUCT((Inputs!$A$5:$A$130=$B6)*ISNUMBER(INDEX(Inputs!$K$5:$AJ$130,0,MATCH(S$2,Inputs!$K$4:$AJ$4,0))))+SUMPRODUCT((Inputs!$C$5:$C$130=$B6)*ISNUMBER(INDEX(Inputs!$K$5:$AJ$130,0,MATCH(S$2,Inputs!$K$4:$AJ$4,0))))+SUMPRODUCT((Inputs!$E$5:$E$130=$B6)*ISNUMBER(INDEX(Inputs!$K$5:$AJ$130,0,MATCH(S$2,Inputs!$K$4:$AJ$4,0))))=0,NA(),SUMPRODUCT((Inputs!$A$5:$A$130=$B6)*Inputs!$B$5:$B$130*(((Inputs!$G$5:$G$130="moeda")+(Inputs!$G$5:$G$130="acoes"))*Inputs!$B$1+((Inputs!$G$5:$G$130<>"moeda")*(Inputs!$G$5:$G$130<>"acoes")))*INDEX(Inputs!$K$5:$AJ$130,0,MATCH(S$2,Inputs!$K$4:$AJ$4,0)))+SUMPRODUCT((Inputs!$C$5:$C$130=$B6)*Inputs!$D$5:$D$130*(((Inputs!$G$5:$G$130="moeda")+(Inputs!$G$5:$G$130="acoes"))*Inputs!$B$1+((Inputs!$G$5:$G$130<>"moeda")*(Inputs!$G$5:$G$130<>"acoes")))*INDEX(Inputs!$K$5:$AJ$130,0,MATCH(S$2,Inputs!$K$4:$AJ$4,0)))+SUMPRODUCT((Inputs!$E$5:$E$130=$B6)*Inputs!$F$5:$F$130*(((Inputs!$G$5:$G$130="moeda")+(Inputs!$G$5:$G$130="acoes"))*Inputs!$B$1+((Inputs!$G$5:$G$130<>"moeda")*(Inputs!$G$5:$G$130<>"acoes")))*INDEX(Inputs!$K$5:$AJ$130,0,MATCH(S$2,Inputs!$K$4:$AJ$4,0))))) -> -9747 | T6: =IF(ISNA(MATCH(T$2,Inputs!$K$4:$AJ$4,0)),NA(),IF(SUMPRODUCT((Inputs!$A$5:$A$130=$B6)*ISNUMBER(INDEX(Inputs!$K$5:$AJ$130,0,MATCH(T$2,Inputs!$K$4:$AJ$4,0))))+SUMPRODUCT((Inputs!$C$5:$C$130=$B6)*ISNUMBER(INDEX(Inputs!$K$5:$AJ$130,0,MATCH(T$2,Inputs!$K$4:$AJ$4,0))))+SUMPRODUCT((Inputs!$E$5:$E$130=$B6)*ISNUMBER(INDEX(Inputs!$K$5:$AJ$130,0,MATCH(T$2,Inputs!$K$4:$AJ$4,0))))=0,NA(),SUMPRODUCT((Inputs!$A$5:$A$130=$B6)*Inputs!$B$5:$B$130*(((Inputs!$G$5:$G$130="moeda")+(Inputs!$G$5:$G$130="acoes"))*Inputs!$B$1+((Inputs!$G$5:$G$130<>"moeda")*(Inputs!$G$5:$G$130<>"acoes")))*INDEX(Inputs!$K$5:$AJ$130,0,MATCH(T$2,Inputs!$K$4:$AJ$4,0)))+SUMPRODUCT((Inputs!$C$5:$C$130=$B6)*Inputs!$D$5:$D$130*(((Inputs!$G$5:$G$130="moeda")+(Inputs!$G$5:$G$130="acoes"))*Inputs!$B$1+((Inputs!$G$5:$G$130<>"moeda")*(Inputs!$G$5:$G$130<>"acoes")))*INDEX(Inputs!$K$5:$AJ$130,0,MATCH(T$2,Inputs!$K$4:$AJ$4,0)))+SUMPRODUCT((Inputs!$E$5:$E$130=$B6)*Inputs!$F$5:$F$130*(((Inputs!$G$5:$G$130="moeda")+(Inputs!$G$5:$G$130="acoes"))*Inputs!$B$1+((Inputs!$G$5:$G$130<>"moeda")*(Inputs!$G$5:$G$130<>"acoes")))*INDEX(Inputs!$K$5:$AJ$130,0,MATCH(T$2,Inputs!$K$4:$AJ$4,0))))) -> -9446 | U6: =IF(ISNA(MATCH(U$2,Inputs!$K$4:$AJ$4,0)),NA(),IF(SUMPRODUCT((Inputs!$A$5:$A$130=$B6)*ISNUMBER(INDEX(Inputs!$K$5:$AJ$130,0,MATCH(U$2,Inputs!$K$4:$AJ$4,0))))+SUMPRODUCT((Inputs!$C$5:$C$130=$B6)*ISNUMBER(INDEX(Inputs!$K$5:$AJ$130,0,MATCH(U$2,Inputs!$K$4:$AJ$4,0))))+SUMPRODUCT((Inputs!$E$5:$E$130=$B6)*ISNUMBER(INDEX(Inputs!$K$5:$AJ$130,0,MATCH(U$2,Inputs!$K$4:$AJ$4,0))))=0,NA(),SUMPRODUCT((Inputs!$A$5:$A$130=$B6)*Inputs!$B$5:$B$130*(((Inputs!$G$5:$G$130="moeda")+(Inputs!$G$5:$G$130="acoes"))*Inputs!$B$1+((Inputs!$G$5:$G$130<>"moeda")*(Inputs!$G$5:$G$130<>"acoes")))*INDEX(Inputs!$K$5:$AJ$130,0,MATCH(U$2,Inputs!$K$4:$AJ$4,0)))+SUMPRODUCT((Inputs!$C$5:$C$130=$B6)*Inputs!$D$5:$D$130*(((Inputs!$G$5:$G$130="moeda")+(Inputs!$G$5:$G$130="acoes"))*Inputs!$B$1+((Inputs!$G$5:$G$130<>"moeda")*(Inputs!$G$5:$G$130<>"acoes")))*INDEX(Inputs!$K$5:$AJ$130,0,MATCH(U$2,Inputs!$K$4:$AJ$4,0)))+SUMPRODUCT((Inputs!$E$5:$E$130=$B6)*Inputs!$F$5:$F$130*(((Inputs!$G$5:$G$130="moeda")+(Inputs!$G$5:$G$130="acoes"))*Inputs!$B$1+((Inputs!$G$5:$G$130<>"moeda")*(Inputs!$G$5:$G$130<>"acoes")))*INDEX(Inputs!$K$5:$AJ$130,0,MATCH(U$2,Inputs!$K$4:$AJ$4,0))))) -> -9876 | V6: =IF(ISNA(MATCH(V$2,Inputs!$K$4:$AJ$4,0)),NA(),IF(SUMPRODUCT((Inputs!$A$5:$A$130=$B6)*ISNUMBER(INDEX(Inputs!$K$5:$AJ$130,0,MATCH(V$2,Inputs!$K$4:$AJ$4,0))))+SUMPRODUCT((Inputs!$C$5:$C$130=$B6)*ISNUMBER(INDEX(Inputs!$K$5:$AJ$130,0,MATCH(V$2,Inputs!$K$4:$AJ$4,0))))+SUMPRODUCT((Inputs!$E$5:$E$130=$B6)*ISNUMBER(INDEX(Inputs!$K$5:$AJ$130,0,MATCH(V$2,Inputs!$K$4:$AJ$4,0))))=0,NA(),SUMPRODUCT((Inputs!$A$5:$A$130=$B6)*Inputs!$B$5:$B$130*(((Inputs!$G$5:$G$130="moeda")+(Inputs!$G$5:$G$130="acoes"))*Inputs!$B$1+((Inputs!$G$5:$G$130<>"moeda")*(Inputs!$G$5:$G$130<>"acoes")))*INDEX(Inputs!$K$5:$AJ$130,0,MATCH(V$2,Inputs!$K$4:$AJ$4,0)))+SUMPRODUCT((Inputs!$C$5:$C$130=$B6)*Inputs!$D$5:$D$130*(((Inputs!$G$5:$G$130="moeda")+(Inputs!$G$5:$G$130="acoes"))*Inputs!$B$1+((Inputs!$G$5:$G$130<>"moeda")*(Inputs!$G$5:$G$130<>"acoes")))*INDEX(Inputs!$K$5:$AJ$130,0,MATCH(V$2,Inputs!$K$4:$AJ$4,0)))+SUMPRODUCT((Inputs!$E$5:$E$130=$B6)*Inputs!$F$5:$F$130*(((Inputs!$G$5:$G$130="moeda")+(Inputs!$G$5:$G$130="acoes"))*Inputs!$B$1+((Inputs!$G$5:$G$130<>"moeda")*(Inputs!$G$5:$G$130<>"acoes")))*INDEX(Inputs!$K$5:$AJ$130,0,MATCH(V$2,Inputs!$K$4:$AJ$4,0))))) -> -10262 | W6: =SUM(S6:V6) -> -39331 | X6: =IF(ISNA(MATCH(X$2,Inputs!$K$4:$AJ$4,0)),NA(),IF(SUMPRODUCT((Inputs!$A$5:$A$130=$B6)*ISNUMBER(INDEX(Inputs!$K$5:$AJ$130,0,MATCH(X$2,Inputs!$K$4:$AJ$4,0))))+SUMPRODUCT((Inputs!$C$5:$C$130=$B6)*ISNUMBER(INDEX(Inputs!$K$5:$AJ$130,0,MATCH(X$2,Inputs!$K$4:$AJ$4,0))))+SUMPRODUCT((Inputs!$E$5:$E$130=$B6)*ISNUMBER(INDEX(Inputs!$K$5:$AJ$130,0,MATCH(X$2,Inputs!$K$4:$AJ$4,0))))=0,NA(),SUMPRODUCT((Inputs!$A$5:$A$130=$B6)*Inputs!$B$5:$B$130*(((Inputs!$G$5:$G$130="moeda")+(Inputs!$G$5:$G$130="acoes"))*Inputs!$B$1+((Inputs!$G$5:$G$130<>"moeda")*(Inputs!$G$5:$G$130<>"acoes")))*INDEX(Inputs!$K$5:$AJ$130,0,MATCH(X$2,Inputs!$K$4:$AJ$4,0)))+SUMPRODUCT((Inputs!$C$5:$C$130=$B6)*Inputs!$D$5:$D$130*(((Inputs!$G$5:$G$130="moeda")+(Inputs!$G$5:$G$130="acoes"))*Inputs!$B$1+((Inputs!$G$5:$G$130<>"moeda")*(Inputs!$G$5:$G$130<>"acoes")))*INDEX(Inputs!$K$5:$AJ$130,0,MATCH(X$2,Inputs!$K$4:$AJ$4,0)))+SUMPRODUCT((Inputs!$E$5:$E$130=$B6)*Inputs!$F$5:$F$130*(((Inputs!$G$5:$G$130="moeda")+(Inputs!$G$5:$G$130="acoes"))*Inputs!$B$1+((Inputs!$G$5:$G$130<>"moeda")*(Inputs!$G$5:$G$130<>"acoes")))*INDEX(Inputs!$K$5:$AJ$130,0,MATCH(X$2,Inputs!$K$4:$AJ$4,0))))) -> -8784 | Y6: =IF(ISNA(MATCH(Y$2,Inputs!$K$4:$AJ$4,0)),NA(),IF(SUMPRODUCT((Inputs!$A$5:$A$130=$B6)*ISNUMBER(INDEX(Inputs!$K$5:$AJ$130,0,MATCH(Y$2,Inputs!$K$4:$AJ$4,0))))+SUMPRODUCT((Inputs!$C$5:$C$130=$B6)*ISNUMBER(INDEX(Inputs!$K$5:$AJ$130,0,MATCH(Y$2,Inputs!$K$4:$AJ$4,0))))+SUMPRODUCT((Inputs!$E$5:$E$130=$B6)*ISNUMBER(INDEX(Inputs!$K$5:$AJ$130,0,MATCH(Y$2,Inputs!$K$4:$AJ$4,0))))=0,NA(),SUMPRODUCT((Inputs!$A$5:$A$130=$B6)*Inputs!$B$5:$B$130*(((Inputs!$G$5:$G$130="moeda")+(Inputs!$G$5:$G$130="acoes"))*Inputs!$B$1+((Inputs!$G$5:$G$130<>"moeda")*(Inputs!$G$5:$G$130<>"acoes")))*INDEX(Inputs!$K$5:$AJ$130,0,MATCH(Y$2,Inputs!$K$4:$AJ$4,0)))+SUMPRODUCT((Inputs!$C$5:$C$130=$B6)*Inputs!$D$5:$D$130*(((Inputs!$G$5:$G$130="moeda")+(Inputs!$G$5:$G$130="acoes"))*Inputs!$B$1+((Inputs!$G$5:$G$130<>"moeda")*(Inputs!$G$5:$G$130<>"acoes")))*INDEX(Inputs!$K$5:$AJ$130,0,MATCH(Y$2,Inputs!$K$4:$AJ$4,0)))+SUMPRODUCT((Inputs!$E$5:$E$130=$B6)*Inputs!$F$5:$F$130*(((Inputs!$G$5:$G$130="moeda")+(Inputs!$G$5:$G$130="acoes"))*Inputs!$B$1+((Inputs!$G$5:$G$130<>"moeda")*(Inputs!$G$5:$G$130<>"acoes")))*INDEX(Inputs!$K$5:$AJ$130,0,MATCH(Y$2,Inputs!$K$4:$AJ$4,0))))) -> -8624 | Z6: =IF(ISNA(MATCH(Z$2,Inputs!$K$4:$AJ$4,0)),NA(),IF(SUMPRODUCT((Inputs!$A$5:$A$130=$B6)*ISNUMBER(INDEX(Inputs!$K$5:$AJ$130,0,MATCH(Z$2,Inputs!$K$4:$AJ$4,0))))+SUMPRODUCT((Inputs!$C$5:$C$130=$B6)*ISNUMBER(INDEX(Inputs!$K$5:$AJ$130,0,MATCH(Z$2,Inputs!$K$4:$AJ$4,0))))+SUMPRODUCT((Inputs!$E$5:$E$130=$B6)*ISNUMBER(INDEX(Inputs!$K$5:$AJ$130,0,MATCH(Z$2,Inputs!$K$4:$AJ$4,0))))=0,NA(),SUMPRODUCT((Inputs!$A$5:$A$130=$B6)*Inputs!$B$5:$B$130*(((Inputs!$G$5:$G$130="moeda")+(Inputs!$G$5:$G$130="acoes"))*Inputs!$B$1+((Inputs!$G$5:$G$130<>"moeda")*(Inputs!$G$5:$G$130<>"acoes")))*INDEX(Inputs!$K$5:$AJ$130,0,MATCH(Z$2,Inputs!$K$4:$AJ$4,0)))+SUMPRODUCT((Inputs!$C$5:$C$130=$B6)*Inputs!$D$5:$D$130*(((Inputs!$G$5:$G$130="moeda")+(Inputs!$G$5:$G$130="acoes"))*Inputs!$B$1+((Inputs!$G$5:$G$130<>"moeda")*(Inputs!$G$5:$G$130<>"acoes")))*INDEX(Inputs!$K$5:$AJ$130,0,MATCH(Z$2,Inputs!$K$4:$AJ$4,0)))+SUMPRODUCT((Inputs!$E$5:$E$130=$B6)*Inputs!$F$5:$F$130*(((Inputs!$G$5:$G$130="moeda")+(Inputs!$G$5:$G$130="acoes"))*Inputs!$B$1+((Inputs!$G$5:$G$130<>"moeda")*(Inputs!$G$5:$G$130<>"acoes")))*INDEX(Inputs!$K$5:$AJ$130,0,MATCH(Z$2,Inputs!$K$4:$AJ$4,0))))) -> -9451 | AA6: =IF(ISNA(MATCH(AA$2,Inputs!$K$4:$AJ$4,0)),NA(),IF(SUMPRODUCT((Inputs!$A$5:$A$130=$B6)*ISNUMBER(INDEX(Inputs!$K$5:$AJ$130,0,MATCH(AA$2,Inputs!$K$4:$AJ$4,0))))+SUMPRODUCT((Inputs!$C$5:$C$130=$B6)*ISNUMBER(INDEX(Inputs!$K$5:$AJ$130,0,MATCH(AA$2,Inputs!$K$4:$AJ$4,0))))+SUMPRODUCT((Inputs!$E$5:$E$130=$B6)*ISNUMBER(INDEX(Inputs!$K$5:$AJ$130,0,MATCH(AA$2,Inputs!$K$4:$AJ$4,0))))=0,NA(),SUMPRODUCT((Inputs!$A$5:$A$130=$B6)*Inputs!$B$5:$B$130*(((Inputs!$G$5:$G$130="moeda")+(Inputs!$G$5:$G$130="acoes"))*Inputs!$B$1+((Inputs!$G$5:$G$130<>"moeda")*(Inputs!$G$5:$G$130<>"acoes")))*INDEX(Inputs!$K$5:$AJ$130,0,MATCH(AA$2,Inputs!$K$4:$AJ$4,0)))+SUMPRODUCT((Inputs!$C$5:$C$130=$B6)*Inputs!$D$5:$D$130*(((Inputs!$G$5:$G$130="moeda")+(Inputs!$G$5:$G$130="acoes"))*Inputs!$B$1+((Inputs!$G$5:$G$130<>"moeda")*(Inputs!$G$5:$G$130<>"acoes")))*INDEX(Inputs!$K$5:$AJ$130,0,MATCH(AA$2,Inputs!$K$4:$AJ$4,0)))+SUMPRODUCT((Inputs!$E$5:$E$130=$B6)*Inputs!$F$5:$F$130*(((Inputs!$G$5:$G$130="moeda")+(Inputs!$G$5:$G$130="acoes"))*Inputs!$B$1+((Inputs!$G$5:$G$130<>"moeda")*(Inputs!$G$5:$G$130<>"acoes")))*INDEX(Inputs!$K$5:$AJ$130,0,MATCH(AA$2,Inputs!$K$4:$AJ$4,0))))) -> -9951 | AB6: =SUM(X6:AA6) -> -36810 | AC6: =IF(ISNA(MATCH(AC$2,Inputs!$K$4:$AJ$4,0)),NA(),IF(SUMPRODUCT((Inputs!$A$5:$A$130=$B6)*ISNUMBER(INDEX(Inputs!$K$5:$AJ$130,0,MATCH(AC$2,Inputs!$K$4:$AJ$4,0))))+SUMPRODUCT((Inputs!$C$5:$C$130=$B6)*ISNUMBER(INDEX(Inputs!$K$5:$AJ$130,0,MATCH(AC$2,Inputs!$K$4:$AJ$4,0))))+SUMPRODUCT((Inputs!$E$5:$E$130=$B6)*ISNUMBER(INDEX(Inputs!$K$5:$AJ$130,0,MATCH(AC$2,Inputs!$K$4:$AJ$4,0))))=0,NA(),SUMPRODUCT((Inputs!$A$5:$A$130=$B6)*Inputs!$B$5:$B$130*(((Inputs!$G$5:$G$130="moeda")+(Inputs!$G$5:$G$130="acoes"))*Inputs!$B$1+((Inputs!$G$5:$G$130<>"moeda")*(Inputs!$G$5:$G$130<>"acoes")))*INDEX(Inputs!$K$5:$AJ$130,0,MATCH(AC$2,Inputs!$K$4:$AJ$4,0)))+SUMPRODUCT((Inputs!$C$5:$C$130=$B6)*Inputs!$D$5:$D$130*(((Inputs!$G$5:$G$130="moeda")+(Inputs!$G$5:$G$130="acoes"))*Inputs!$B$1+((Inputs!$G$5:$G$130<>"moeda")*(Inputs!$G$5:$G$130<>"acoes")))*INDEX(Inputs!$K$5:$AJ$130,0,MATCH(AC$2,Inputs!$K$4:$AJ$4,0)))+SUMPRODUCT((Inputs!$E$5:$E$130=$B6)*Inputs!$F$5:$F$130*(((Inputs!$G$5:$G$130="moeda")+(Inputs!$G$5:$G$130="acoes"))*Inputs!$B$1+((Inputs!$G$5:$G$130<>"moeda")*(Inputs!$G$5:$G$130<>"acoes")))*INDEX(Inputs!$K$5:$AJ$130,0,MATCH(AC$2,Inputs!$K$4:$AJ$4,0))))) -> -8813 | AD6: =IF(ISNA(MATCH(AD$2,Inputs!$K$4:$AJ$4,0)),NA(),IF(SUMPRODUCT((Inputs!$A$5:$A$130=$B6)*ISNUMBER(INDEX(Inputs!$K$5:$AJ$130,0,MATCH(AD$2,Inputs!$K$4:$AJ$4,0))))+SUMPRODUCT((Inputs!$C$5:$C$130=$B6)*ISNUMBER(INDEX(Inputs!$K$5:$AJ$130,0,MATCH(AD$2,Inputs!$K$4:$AJ$4,0))))+SUMPRODUCT((Inputs!$E$5:$E$130=$B6)*ISNUMBER(INDEX(Inputs!$K$5:$AJ$130,0,MATCH(AD$2,Inputs!$K$4:$AJ$4,0))))=0,NA(),SUMPRODUCT((Inputs!$A$5:$A$130=$B6)*Inputs!$B$5:$B$130*(((Inputs!$G$5:$G$130="moeda")+(Inputs!$G$5:$G$130="acoes"))*Inputs!$B$1+((Inputs!$G$5:$G$130<>"moeda")*(Inputs!$G$5:$G$130<>"acoes")))*INDEX(Inputs!$K$5:$AJ$130,0,MATCH(AD$2,Inputs!$K$4:$AJ$4,0)))+SUMPRODUCT((Inputs!$C$5:$C$130=$B6)*Inputs!$D$5:$D$130*(((Inputs!$G$5:$G$130="moeda")+(Inputs!$G$5:$G$130="acoes"))*Inputs!$B$1+((Inputs!$G$5:$G$130<>"moeda")*(Inputs!$G$5:$G$130<>"acoes")))*INDEX(Inputs!$K$5:$AJ$130,0,MATCH(AD$2,Inputs!$K$4:$AJ$4,0)))+SUMPRODUCT((Inputs!$E$5:$E$130=$B6)*Inputs!$F$5:$F$130*(((Inputs!$G$5:$G$130="moeda")+(Inputs!$G$5:$G$130="acoes"))*Inputs!$B$1+((Inputs!$G$5:$G$130<>"moeda")*(Inputs!$G$5:$G$130<>"acoes")))*INDEX(Inputs!$K$5:$AJ$130,0,MATCH(AD$2,Inputs!$K$4:$AJ$4,0))))) -> -8774 | AE6: =IF(ISNA(MATCH(AE$2,Inputs!$K$4:$AJ$4,0)),NA(),IF(SUMPRODUCT((Inputs!$A$5:$A$130=$B6)*ISNUMBER(INDEX(Inputs!$K$5:$AJ$130,0,MATCH(AE$2,Inputs!$K$4:$AJ$4,0))))+SUMPRODUCT((Inputs!$C$5:$C$130=$B6)*ISNUMBER(INDEX(Inputs!$K$5:$AJ$130,0,MATCH(AE$2,Inputs!$K$4:$AJ$4,0))))+SUMPRODUCT((Inputs!$E$5:$E$130=$B6)*ISNUMBER(INDEX(Inputs!$K$5:$AJ$130,0,MATCH(AE$2,Inputs!$K$4:$AJ$4,0))))=0,NA(),SUMPRODUCT((Inputs!$A$5:$A$130=$B6)*Inputs!$B$5:$B$130*(((Inputs!$G$5:$G$130="moeda")+(Inputs!$G$5:$G$130="acoes"))*Inputs!$B$1+((Inputs!$G$5:$G$130<>"moeda")*(Inputs!$G$5:$G$130<>"acoes")))*INDEX(Inputs!$K$5:$AJ$130,0,MATCH(AE$2,Inputs!$K$4:$AJ$4,0)))+SUMPRODUCT((Inputs!$C$5:$C$130=$B6)*Inputs!$D$5:$D$130*(((Inputs!$G$5:$G$130="moeda")+(Inputs!$G$5:$G$130="acoes"))*Inputs!$B$1+((Inputs!$G$5:$G$130<>"moeda")*(Inputs!$G$5:$G$130<>"acoes")))*INDEX(Inputs!$K$5:$AJ$130,0,MATCH(AE$2,Inputs!$K$4:$AJ$4,0)))+SUMPRODUCT((Inputs!$E$5:$E$130=$B6)*Inputs!$F$5:$F$130*(((Inputs!$G$5:$G$130="moeda")+(Inputs!$G$5:$G$130="acoes"))*Inputs!$B$1+((Inputs!$G$5:$G$130<>"moeda")*(Inputs!$G$5:$G$130<>"acoes")))*INDEX(Inputs!$K$5:$AJ$130,0,MATCH(AE$2,Inputs!$K$4:$AJ$4,0))))) -> #N/A | AF6: =IF(ISNA(MATCH(AF$2,Inputs!$K$4:$AJ$4,0)),NA(),IF(SUMPRODUCT((Inputs!$A$5:$A$130=$B6)*ISNUMBER(INDEX(Inputs!$K$5:$AJ$130,0,MATCH(AF$2,Inputs!$K$4:$AJ$4,0))))+SUMPRODUCT((Inputs!$C$5:$C$130=$B6)*ISNUMBER(INDEX(Inputs!$K$5:$AJ$130,0,MATCH(AF$2,Inputs!$K$4:$AJ$4,0))))+SUMPRODUCT((Inputs!$E$5:$E$130=$B6)*ISNUMBER(INDEX(Inputs!$K$5:$AJ$130,0,MATCH(AF$2,Inputs!$K$4:$AJ$4,0))))=0,NA(),SUMPRODUCT((Inputs!$A$5:$A$130=$B6)*Inputs!$B$5:$B$130*(((Inputs!$G$5:$G$130="moeda")+(Inputs!$G$5:$G$130="acoes"))*Inputs!$B$1+((Inputs!$G$5:$G$130<>"moeda")*(Inputs!$G$5:$G$130<>"acoes")))*INDEX(Inputs!$K$5:$AJ$130,0,MATCH(AF$2,Inputs!$K$4:$AJ$4,0)))+SUMPRODUCT((Inputs!$C$5:$C$130=$B6)*Inputs!$D$5:$D$130*(((Inputs!$G$5:$G$130="moeda")+(Inputs!$G$5:$G$130="acoes"))*Inputs!$B$1+((Inputs!$G$5:$G$130<>"moeda")*(Inputs!$G$5:$G$130<>"acoes")))*INDEX(Inputs!$K$5:$AJ$130,0,MATCH(AF$2,Inputs!$K$4:$AJ$4,0)))+SUMPRODUCT((Inputs!$E$5:$E$130=$B6)*Inputs!$F$5:$F$130*(((Inputs!$G$5:$G$130="moeda")+(Inputs!$G$5:$G$130="acoes"))*Inputs!$B$1+((Inputs!$G$5:$G$130<>"moeda")*(Inputs!$G$5:$G$130<>"acoes")))*INDEX(Inputs!$K$5:$AJ$130,0,MATCH(AF$2,Inputs!$K$4:$AJ$4,0))))) -> #N/A | AG6: =SUM(AC6:AF6) -> #N/A | AH6: =IF(ISNA(MATCH(AH$2,Inputs!$K$4:$AJ$4,0)),NA(),IF(SUMPRODUCT((Inputs!$A$5:$A$130=$B6)*ISNUMBER(INDEX(Inputs!$K$5:$AJ$130,0,MATCH(AH$2,Inputs!$K$4:$AJ$4,0))))+SUMPRODUCT((Inputs!$C$5:$C$130=$B6)*ISNUMBER(INDEX(Inputs!$K$5:$AJ$130,0,MATCH(AH$2,Inputs!$K$4:$AJ$4,0))))+SUMPRODUCT((Inputs!$E$5:$E$130=$B6)*ISNUMBER(INDEX(Inputs!$K$5:$AJ$130,0,MATCH(AH$2,Inputs!$K$4:$AJ$4,0))))=0,NA(),SUMPRODUCT((Inputs!$A$5:$A$130=$B6)*Inputs!$B$5:$B$130*(((Inputs!$G$5:$G$130="moeda")+(Inputs!$G$5:$G$130="acoes"))*Inputs!$B$1+((Inputs!$G$5:$G$130<>"moeda")*(Inputs!$G$5:$G$130<>"acoes")))*INDEX(Inputs!$K$5:$AJ$130,0,MATCH(AH$2,Inputs!$K$4:$AJ$4,0)))+SUMPRODUCT((Inputs!$C$5:$C$130=$B6)*Inputs!$D$5:$D$130*(((Inputs!$G$5:$G$130="moeda")+(Inputs!$G$5:$G$130="acoes"))*Inputs!$B$1+((Inputs!$G$5:$G$130<>"moeda")*(Inputs!$G$5:$G$130<>"acoes")))*INDEX(Inputs!$K$5:$AJ$130,0,MATCH(AH$2,Inputs!$K$4:$AJ$4,0)))+SUMPRODUCT((Inputs!$E$5:$E$130=$B6)*Inputs!$F$5:$F$130*(((Inputs!$G$5:$G$130="moeda")+(Inputs!$G$5:$G$130="acoes"))*Inputs!$B$1+((Inputs!$G$5:$G$130<>"moeda")*(Inputs!$G$5:$G$130<>"acoes")))*INDEX(Inputs!$K$5:$AJ$130,0,MATCH(AH$2,Inputs!$K$4:$AJ$4,0))))) -> #N/A | AI6: =IF(ISNA(MATCH(AI$2,Inputs!$K$4:$AJ$4,0)),NA(),IF(SUMPRODUCT((Inputs!$A$5:$A$130=$B6)*ISNUMBER(INDEX(Inputs!$K$5:$AJ$130,0,MATCH(AI$2,Inputs!$K$4:$AJ$4,0))))+SUMPRODUCT((Inputs!$C$5:$C$130=$B6)*ISNUMBER(INDEX(Inputs!$K$5:$AJ$130,0,MATCH(AI$2,Inputs!$K$4:$AJ$4,0))))+SUMPRODUCT((Inputs!$E$5:$E$130=$B6)*ISNUMBER(INDEX(Inputs!$K$5:$AJ$130,0,MATCH(AI$2,Inputs!$K$4:$AJ$4,0))))=0,NA(),SUMPRODUCT((Inputs!$A$5:$A$130=$B6)*Inputs!$B$5:$B$130*(((Inputs!$G$5:$G$130="moeda")+(Inputs!$G$5:$G$130="acoes"))*Inputs!$B$1+((Inputs!$G$5:$G$130<>"moeda")*(Inputs!$G$5:$G$130<>"acoes")))*INDEX(Inputs!$K$5:$AJ$130,0,MATCH(AI$2,Inputs!$K$4:$AJ$4,0)))+SUMPRODUCT((Inputs!$C$5:$C$130=$B6)*Inputs!$D$5:$D$130*(((Inputs!$G$5:$G$130="moeda")+(Inputs!$G$5:$G$130="acoes"))*Inputs!$B$1+((Inputs!$G$5:$G$130<>"moeda")*(Inputs!$G$5:$G$130<>"acoes")))*INDEX(Inputs!$K$5:$AJ$130,0,MATCH(AI$2,Inputs!$K$4:$AJ$4,0)))+SUMPRODUCT((Inputs!$E$5:$E$130=$B6)*Inputs!$F$5:$F$130*(((Inputs!$G$5:$G$130="moeda")+(Inputs!$G$5:$G$130="acoes"))*Inputs!$B$1+((Inputs!$G$5:$G$130<>"moeda")*(Inputs!$G$5:$G$130<>"acoes")))*INDEX(Inputs!$K$5:$AJ$130,0,MATCH(AI$2,Inputs!$K$4:$AJ$4,0))))) -> #N/A | AJ6: =IF(ISNA(MATCH(AJ$2,Inputs!$K$4:$AJ$4,0)),NA(),IF(SUMPRODUCT((Inputs!$A$5:$A$130=$B6)*ISNUMBER(INDEX(Inputs!$K$5:$AJ$130,0,MATCH(AJ$2,Inputs!$K$4:$AJ$4,0))))+SUMPRODUCT((Inputs!$C$5:$C$130=$B6)*ISNUMBER(INDEX(Inputs!$K$5:$AJ$130,0,MATCH(AJ$2,Inputs!$K$4:$AJ$4,0))))+SUMPRODUCT((Inputs!$E$5:$E$130=$B6)*ISNUMBER(INDEX(Inputs!$K$5:$AJ$130,0,MATCH(AJ$2,Inputs!$K$4:$AJ$4,0))))=0,NA(),SUMPRODUCT((Inputs!$A$5:$A$130=$B6)*Inputs!$B$5:$B$130*(((Inputs!$G$5:$G$130="moeda")+(Inputs!$G$5:$G$130="acoes"))*Inputs!$B$1+((Inputs!$G$5:$G$130<>"moeda")*(Inputs!$G$5:$G$130<>"acoes")))*INDEX(Inputs!$K$5:$AJ$130,0,MATCH(AJ$2,Inputs!$K$4:$AJ$4,0)))+SUMPRODUCT((Inputs!$C$5:$C$130=$B6)*Inputs!$D$5:$D$130*(((Inputs!$G$5:$G$130="moeda")+(Inputs!$G$5:$G$130="acoes"))*Inputs!$B$1+((Inputs!$G$5:$G$130<>"moeda")*(Inputs!$G$5:$G$130<>"acoes")))*INDEX(Inputs!$K$5:$AJ$130,0,MATCH(AJ$2,Inputs!$K$4:$AJ$4,0)))+SUMPRODUCT((Inputs!$E$5:$E$130=$B6)*Inputs!$F$5:$F$130*(((Inputs!$G$5:$G$130="moeda")+(Inputs!$G$5:$G$130="acoes"))*Inputs!$B$1+((Inputs!$G$5:$G$130<>"moeda")*(Inputs!$G$5:$G$130<>"acoes")))*INDEX(Inputs!$K$5:$AJ$130,0,MATCH(AJ$2,Inputs!$K$4:$AJ$4,0))))) -> #N/A | AK6: =IF(ISNA(MATCH(AK$2,Inputs!$K$4:$AJ$4,0)),NA(),IF(SUMPRODUCT((Inputs!$A$5:$A$130=$B6)*ISNUMBER(INDEX(Inputs!$K$5:$AJ$130,0,MATCH(AK$2,Inputs!$K$4:$AJ$4,0))))+SUMPRODUCT((Inputs!$C$5:$C$130=$B6)*ISNUMBER(INDEX(Inputs!$K$5:$AJ$130,0,MATCH(AK$2,Inputs!$K$4:$AJ$4,0))))+SUMPRODUCT((Inputs!$E$5:$E$130=$B6)*ISNUMBER(INDEX(Inputs!$K$5:$AJ$130,0,MATCH(AK$2,Inputs!$K$4:$AJ$4,0))))=0,NA(),SUMPRODUCT((Inputs!$A$5:$A$130=$B6)*Inputs!$B$5:$B$130*(((Inputs!$G$5:$G$130="moeda")+(Inputs!$G$5:$G$130="acoes"))*Inputs!$B$1+((Inputs!$G$5:$G$130<>"moeda")*(Inputs!$G$5:$G$130<>"acoes")))*INDEX(Inputs!$K$5:$AJ$130,0,MATCH(AK$2,Inputs!$K$4:$AJ$4,0)))+SUMPRODUCT((Inputs!$C$5:$C$130=$B6)*Inputs!$D$5:$D$130*(((Inputs!$G$5:$G$130="moeda")+(Inputs!$G$5:$G$130="acoes"))*Inputs!$B$1+((Inputs!$G$5:$G$130<>"moeda")*(Inputs!$G$5:$G$130<>"acoes")))*INDEX(Inputs!$K$5:$AJ$130,0,MATCH(AK$2,Inputs!$K$4:$AJ$4,0)))+SUMPRODUCT((Inputs!$E$5:$E$130=$B6)*Inputs!$F$5:$F$130*(((Inputs!$G$5:$G$130="moeda")+(Inputs!$G$5:$G$130="acoes"))*Inputs!$B$1+((Inputs!$G$5:$G$130<>"moeda")*(Inputs!$G$5:$G$130<>"acoes")))*INDEX(Inputs!$K$5:$AJ$130,0,MATCH(AK$2,Inputs!$K$4:$AJ$4,0))))) -> #N/A | AL6: =SUM(AH6:AK6) -> #N/A
B7: 4 | C7: D&A | D7: =IF(ISNA(MATCH(D$2,Inputs!$K$4:$AJ$4,0)),NA(),IF(SUMPRODUCT((Inputs!$A$5:$A$130=$B7)*ISNUMBER(INDEX(Inputs!$K$5:$AJ$130,0,MATCH(D$2,Inputs!$K$4:$AJ$4,0))))+SUMPRODUCT((Inputs!$C$5:$C$130=$B7)*ISNUMBER(INDEX(Inputs!$K$5:$AJ$130,0,MATCH(D$2,Inputs!$K$4:$AJ$4,0))))+SUMPRODUCT((Inputs!$E$5:$E$130=$B7)*ISNUMBER(INDEX(Inputs!$K$5:$AJ$130,0,MATCH(D$2,Inputs!$K$4:$AJ$4,0))))=0,NA(),SUMPRODUCT((Inputs!$A$5:$A$130=$B7)*Inputs!$B$5:$B$130*(((Inputs!$G$5:$G$130="moeda")+(Inputs!$G$5:$G$130="acoes"))*Inputs!$B$1+((Inputs!$G$5:$G$130<>"moeda")*(Inputs!$G$5:$G$130<>"acoes")))*INDEX(Inputs!$K$5:$AJ$130,0,MATCH(D$2,Inputs!$K$4:$AJ$4,0)))+SUMPRODUCT((Inputs!$C$5:$C$130=$B7)*Inputs!$D$5:$D$130*(((Inputs!$G$5:$G$130="moeda")+(Inputs!$G$5:$G$130="acoes"))*Inputs!$B$1+((Inputs!$G$5:$G$130<>"moeda")*(Inputs!$G$5:$G$130<>"acoes")))*INDEX(Inputs!$K$5:$AJ$130,0,MATCH(D$2,Inputs!$K$4:$AJ$4,0)))+SUMPRODUCT((Inputs!$E$5:$E$130=$B7)*Inputs!$F$5:$F$130*(((Inputs!$G$5:$G$130="moeda")+(Inputs!$G$5:$G$130="acoes"))*Inputs!$B$1+((Inputs!$G$5:$G$130<>"moeda")*(Inputs!$G$5:$G$130<>"acoes")))*INDEX(Inputs!$K$5:$AJ$130,0,MATCH(D$2,Inputs!$K$4:$AJ$4,0))))) -> -5896 | E7: =IF(ISNA(MATCH(E$2,Inputs!$K$4:$AJ$4,0)),NA(),IF(SUMPRODUCT((Inputs!$A$5:$A$130=$B7)*ISNUMBER(INDEX(Inputs!$K$5:$AJ$130,0,MATCH(E$2,Inputs!$K$4:$AJ$4,0))))+SUMPRODUCT((Inputs!$C$5:$C$130=$B7)*ISNUMBER(INDEX(Inputs!$K$5:$AJ$130,0,MATCH(E$2,Inputs!$K$4:$AJ$4,0))))+SUMPRODUCT((Inputs!$E$5:$E$130=$B7)*ISNUMBER(INDEX(Inputs!$K$5:$AJ$130,0,MATCH(E$2,Inputs!$K$4:$AJ$4,0))))=0,NA(),SUMPRODUCT((Inputs!$A$5:$A$130=$B7)*Inputs!$B$5:$B$130*(((Inputs!$G$5:$G$130="moeda")+(Inputs!$G$5:$G$130="acoes"))*Inputs!$B$1+((Inputs!$G$5:$G$130<>"moeda")*(Inputs!$G$5:$G$130<>"acoes")))*INDEX(Inputs!$K$5:$AJ$130,0,MATCH(E$2,Inputs!$K$4:$AJ$4,0)))+SUMPRODUCT((Inputs!$C$5:$C$130=$B7)*Inputs!$D$5:$D$130*(((Inputs!$G$5:$G$130="moeda")+(Inputs!$G$5:$G$130="acoes"))*Inputs!$B$1+((Inputs!$G$5:$G$130<>"moeda")*(Inputs!$G$5:$G$130<>"acoes")))*INDEX(Inputs!$K$5:$AJ$130,0,MATCH(E$2,Inputs!$K$4:$AJ$4,0)))+SUMPRODUCT((Inputs!$E$5:$E$130=$B7)*Inputs!$F$5:$F$130*(((Inputs!$G$5:$G$130="moeda")+(Inputs!$G$5:$G$130="acoes"))*Inputs!$B$1+((Inputs!$G$5:$G$130<>"moeda")*(Inputs!$G$5:$G$130<>"acoes")))*INDEX(Inputs!$K$5:$AJ$130,0,MATCH(E$2,Inputs!$K$4:$AJ$4,0))))) -> -8223 | F7: =IF(ISNA(MATCH(F$2,Inputs!$K$4:$AJ$4,0)),NA(),IF(SUMPRODUCT((Inputs!$A$5:$A$130=$B7)*ISNUMBER(INDEX(Inputs!$K$5:$AJ$130,0,MATCH(F$2,Inputs!$K$4:$AJ$4,0))))+SUMPRODUCT((Inputs!$C$5:$C$130=$B7)*ISNUMBER(INDEX(Inputs!$K$5:$AJ$130,0,MATCH(F$2,Inputs!$K$4:$AJ$4,0))))+SUMPRODUCT((Inputs!$E$5:$E$130=$B7)*ISNUMBER(INDEX(Inputs!$K$5:$AJ$130,0,MATCH(F$2,Inputs!$K$4:$AJ$4,0))))=0,NA(),SUMPRODUCT((Inputs!$A$5:$A$130=$B7)*Inputs!$B$5:$B$130*(((Inputs!$G$5:$G$130="moeda")+(Inputs!$G$5:$G$130="acoes"))*Inputs!$B$1+((Inputs!$G$5:$G$130<>"moeda")*(Inputs!$G$5:$G$130<>"acoes")))*INDEX(Inputs!$K$5:$AJ$130,0,MATCH(F$2,Inputs!$K$4:$AJ$4,0)))+SUMPRODUCT((Inputs!$C$5:$C$130=$B7)*Inputs!$D$5:$D$130*(((Inputs!$G$5:$G$130="moeda")+(Inputs!$G$5:$G$130="acoes"))*Inputs!$B$1+((Inputs!$G$5:$G$130<>"moeda")*(Inputs!$G$5:$G$130<>"acoes")))*INDEX(Inputs!$K$5:$AJ$130,0,MATCH(F$2,Inputs!$K$4:$AJ$4,0)))+SUMPRODUCT((Inputs!$E$5:$E$130=$B7)*Inputs!$F$5:$F$130*(((Inputs!$G$5:$G$130="moeda")+(Inputs!$G$5:$G$130="acoes"))*Inputs!$B$1+((Inputs!$G$5:$G$130<>"moeda")*(Inputs!$G$5:$G$130<>"acoes")))*INDEX(Inputs!$K$5:$AJ$130,0,MATCH(F$2,Inputs!$K$4:$AJ$4,0))))) -> -6358 | G7: =IF(ISNA(MATCH(G$2,Inputs!$K$4:$AJ$4,0)),NA(),IF(SUMPRODUCT((Inputs!$A$5:$A$130=$B7)*ISNUMBER(INDEX(Inputs!$K$5:$AJ$130,0,MATCH(G$2,Inputs!$K$4:$AJ$4,0))))+SUMPRODUCT((Inputs!$C$5:$C$130=$B7)*ISNUMBER(INDEX(Inputs!$K$5:$AJ$130,0,MATCH(G$2,Inputs!$K$4:$AJ$4,0))))+SUMPRODUCT((Inputs!$E$5:$E$130=$B7)*ISNUMBER(INDEX(Inputs!$K$5:$AJ$130,0,MATCH(G$2,Inputs!$K$4:$AJ$4,0))))=0,NA(),SUMPRODUCT((Inputs!$A$5:$A$130=$B7)*Inputs!$B$5:$B$130*(((Inputs!$G$5:$G$130="moeda")+(Inputs!$G$5:$G$130="acoes"))*Inputs!$B$1+((Inputs!$G$5:$G$130<>"moeda")*(Inputs!$G$5:$G$130<>"acoes")))*INDEX(Inputs!$K$5:$AJ$130,0,MATCH(G$2,Inputs!$K$4:$AJ$4,0)))+SUMPRODUCT((Inputs!$C$5:$C$130=$B7)*Inputs!$D$5:$D$130*(((Inputs!$G$5:$G$130="moeda")+(Inputs!$G$5:$G$130="acoes"))*Inputs!$B$1+((Inputs!$G$5:$G$130<>"moeda")*(Inputs!$G$5:$G$130<>"acoes")))*INDEX(Inputs!$K$5:$AJ$130,0,MATCH(G$2,Inputs!$K$4:$AJ$4,0)))+SUMPRODUCT((Inputs!$E$5:$E$130=$B7)*Inputs!$F$5:$F$130*(((Inputs!$G$5:$G$130="moeda")+(Inputs!$G$5:$G$130="acoes"))*Inputs!$B$1+((Inputs!$G$5:$G$130<>"moeda")*(Inputs!$G$5:$G$130<>"acoes")))*INDEX(Inputs!$K$5:$AJ$130,0,MATCH(G$2,Inputs!$K$4:$AJ$4,0))))) -> -6445 | H7: =SUM(D7:G7) -> -26922 | I7: =IF(ISNA(MATCH(I$2,Inputs!$K$4:$AJ$4,0)),NA(),IF(SUMPRODUCT((Inputs!$A$5:$A$130=$B7)*ISNUMBER(INDEX(Inputs!$K$5:$AJ$130,0,MATCH(I$2,Inputs!$K$4:$AJ$4,0))))+SUMPRODUCT((Inputs!$C$5:$C$130=$B7)*ISNUMBER(INDEX(Inputs!$K$5:$AJ$130,0,MATCH(I$2,Inputs!$K$4:$AJ$4,0))))+SUMPRODUCT((Inputs!$E$5:$E$130=$B7)*ISNUMBER(INDEX(Inputs!$K$5:$AJ$130,0,MATCH(I$2,Inputs!$K$4:$AJ$4,0))))=0,NA(),SUMPRODUCT((Inputs!$A$5:$A$130=$B7)*Inputs!$B$5:$B$130*(((Inputs!$G$5:$G$130="moeda")+(Inputs!$G$5:$G$130="acoes"))*Inputs!$B$1+((Inputs!$G$5:$G$130<>"moeda")*(Inputs!$G$5:$G$130<>"acoes")))*INDEX(Inputs!$K$5:$AJ$130,0,MATCH(I$2,Inputs!$K$4:$AJ$4,0)))+SUMPRODUCT((Inputs!$C$5:$C$130=$B7)*Inputs!$D$5:$D$130*(((Inputs!$G$5:$G$130="moeda")+(Inputs!$G$5:$G$130="acoes"))*Inputs!$B$1+((Inputs!$G$5:$G$130<>"moeda")*(Inputs!$G$5:$G$130<>"acoes")))*INDEX(Inputs!$K$5:$AJ$130,0,MATCH(I$2,Inputs!$K$4:$AJ$4,0)))+SUMPRODUCT((Inputs!$E$5:$E$130=$B7)*Inputs!$F$5:$F$130*(((Inputs!$G$5:$G$130="moeda")+(Inputs!$G$5:$G$130="acoes"))*Inputs!$B$1+((Inputs!$G$5:$G$130<>"moeda")*(Inputs!$G$5:$G$130<>"acoes")))*INDEX(Inputs!$K$5:$AJ$130,0,MATCH(I$2,Inputs!$K$4:$AJ$4,0))))) -> -6295 | J7: =IF(ISNA(MATCH(J$2,Inputs!$K$4:$AJ$4,0)),NA(),IF(SUMPRODUCT((Inputs!$A$5:$A$130=$B7)*ISNUMBER(INDEX(Inputs!$K$5:$AJ$130,0,MATCH(J$2,Inputs!$K$4:$AJ$4,0))))+SUMPRODUCT((Inputs!$C$5:$C$130=$B7)*ISNUMBER(INDEX(Inputs!$K$5:$AJ$130,0,MATCH(J$2,Inputs!$K$4:$AJ$4,0))))+SUMPRODUCT((Inputs!$E$5:$E$130=$B7)*ISNUMBER(INDEX(Inputs!$K$5:$AJ$130,0,MATCH(J$2,Inputs!$K$4:$AJ$4,0))))=0,NA(),SUMPRODUCT((Inputs!$A$5:$A$130=$B7)*Inputs!$B$5:$B$130*(((Inputs!$G$5:$G$130="moeda")+(Inputs!$G$5:$G$130="acoes"))*Inputs!$B$1+((Inputs!$G$5:$G$130<>"moeda")*(Inputs!$G$5:$G$130<>"acoes")))*INDEX(Inputs!$K$5:$AJ$130,0,MATCH(J$2,Inputs!$K$4:$AJ$4,0)))+SUMPRODUCT((Inputs!$C$5:$C$130=$B7)*Inputs!$D$5:$D$130*(((Inputs!$G$5:$G$130="moeda")+(Inputs!$G$5:$G$130="acoes"))*Inputs!$B$1+((Inputs!$G$5:$G$130<>"moeda")*(Inputs!$G$5:$G$130<>"acoes")))*INDEX(Inputs!$K$5:$AJ$130,0,MATCH(J$2,Inputs!$K$4:$AJ$4,0)))+SUMPRODUCT((Inputs!$E$5:$E$130=$B7)*Inputs!$F$5:$F$130*(((Inputs!$G$5:$G$130="moeda")+(Inputs!$G$5:$G$130="acoes"))*Inputs!$B$1+((Inputs!$G$5:$G$130<>"moeda")*(Inputs!$G$5:$G$130<>"acoes")))*INDEX(Inputs!$K$5:$AJ$130,0,MATCH(J$2,Inputs!$K$4:$AJ$4,0))))) -> 348 | K7: =IF(ISNA(MATCH(K$2,Inputs!$K$4:$AJ$4,0)),NA(),IF(SUMPRODUCT((Inputs!$A$5:$A$130=$B7)*ISNUMBER(INDEX(Inputs!$K$5:$AJ$130,0,MATCH(K$2,Inputs!$K$4:$AJ$4,0))))+SUMPRODUCT((Inputs!$C$5:$C$130=$B7)*ISNUMBER(INDEX(Inputs!$K$5:$AJ$130,0,MATCH(K$2,Inputs!$K$4:$AJ$4,0))))+SUMPRODUCT((Inputs!$E$5:$E$130=$B7)*ISNUMBER(INDEX(Inputs!$K$5:$AJ$130,0,MATCH(K$2,Inputs!$K$4:$AJ$4,0))))=0,NA(),SUMPRODUCT((Inputs!$A$5:$A$130=$B7)*Inputs!$B$5:$B$130*(((Inputs!$G$5:$G$130="moeda")+(Inputs!$G$5:$G$130="acoes"))*Inputs!$B$1+((Inputs!$G$5:$G$130<>"moeda")*(Inputs!$G$5:$G$130<>"acoes")))*INDEX(Inputs!$K$5:$AJ$130,0,MATCH(K$2,Inputs!$K$4:$AJ$4,0)))+SUMPRODUCT((Inputs!$C$5:$C$130=$B7)*Inputs!$D$5:$D$130*(((Inputs!$G$5:$G$130="moeda")+(Inputs!$G$5:$G$130="acoes"))*Inputs!$B$1+((Inputs!$G$5:$G$130<>"moeda")*(Inputs!$G$5:$G$130<>"acoes")))*INDEX(Inputs!$K$5:$AJ$130,0,MATCH(K$2,Inputs!$K$4:$AJ$4,0)))+SUMPRODUCT((Inputs!$E$5:$E$130=$B7)*Inputs!$F$5:$F$130*(((Inputs!$G$5:$G$130="moeda")+(Inputs!$G$5:$G$130="acoes"))*Inputs!$B$1+((Inputs!$G$5:$G$130<>"moeda")*(Inputs!$G$5:$G$130<>"acoes")))*INDEX(Inputs!$K$5:$AJ$130,0,MATCH(K$2,Inputs!$K$4:$AJ$4,0))))) -> -6124 | L7: =IF(ISNA(MATCH(L$2,Inputs!$K$4:$AJ$4,0)),NA(),IF(SUMPRODUCT((Inputs!$A$5:$A$130=$B7)*ISNUMBER(INDEX(Inputs!$K$5:$AJ$130,0,MATCH(L$2,Inputs!$K$4:$AJ$4,0))))+SUMPRODUCT((Inputs!$C$5:$C$130=$B7)*ISNUMBER(INDEX(Inputs!$K$5:$AJ$130,0,MATCH(L$2,Inputs!$K$4:$AJ$4,0))))+SUMPRODUCT((Inputs!$E$5:$E$130=$B7)*ISNUMBER(INDEX(Inputs!$K$5:$AJ$130,0,MATCH(L$2,Inputs!$K$4:$AJ$4,0))))=0,NA(),SUMPRODUCT((Inputs!$A$5:$A$130=$B7)*Inputs!$B$5:$B$130*(((Inputs!$G$5:$G$130="moeda")+(Inputs!$G$5:$G$130="acoes"))*Inputs!$B$1+((Inputs!$G$5:$G$130<>"moeda")*(Inputs!$G$5:$G$130<>"acoes")))*INDEX(Inputs!$K$5:$AJ$130,0,MATCH(L$2,Inputs!$K$4:$AJ$4,0)))+SUMPRODUCT((Inputs!$C$5:$C$130=$B7)*Inputs!$D$5:$D$130*(((Inputs!$G$5:$G$130="moeda")+(Inputs!$G$5:$G$130="acoes"))*Inputs!$B$1+((Inputs!$G$5:$G$130<>"moeda")*(Inputs!$G$5:$G$130<>"acoes")))*INDEX(Inputs!$K$5:$AJ$130,0,MATCH(L$2,Inputs!$K$4:$AJ$4,0)))+SUMPRODUCT((Inputs!$E$5:$E$130=$B7)*Inputs!$F$5:$F$130*(((Inputs!$G$5:$G$130="moeda")+(Inputs!$G$5:$G$130="acoes"))*Inputs!$B$1+((Inputs!$G$5:$G$130<>"moeda")*(Inputs!$G$5:$G$130<>"acoes")))*INDEX(Inputs!$K$5:$AJ$130,0,MATCH(L$2,Inputs!$K$4:$AJ$4,0))))) -> -6459 | M7: =SUM(I7:L7) -> -18530 | N7: =IF(ISNA(MATCH(N$2,Inputs!$K$4:$AJ$4,0)),NA(),IF(SUMPRODUCT((Inputs!$A$5:$A$130=$B7)*ISNUMBER(INDEX(Inputs!$K$5:$AJ$130,0,MATCH(N$2,Inputs!$K$4:$AJ$4,0))))+SUMPRODUCT((Inputs!$C$5:$C$130=$B7)*ISNUMBER(INDEX(Inputs!$K$5:$AJ$130,0,MATCH(N$2,Inputs!$K$4:$AJ$4,0))))+SUMPRODUCT((Inputs!$E$5:$E$130=$B7)*ISNUMBER(INDEX(Inputs!$K$5:$AJ$130,0,MATCH(N$2,Inputs!$K$4:$AJ$4,0))))=0,NA(),SUMPRODUCT((Inputs!$A$5:$A$130=$B7)*Inputs!$B$5:$B$130*(((Inputs!$G$5:$G$130="moeda")+(Inputs!$G$5:$G$130="acoes"))*Inputs!$B$1+((Inputs!$G$5:$G$130<>"moeda")*(Inputs!$G$5:$G$130<>"acoes")))*INDEX(Inputs!$K$5:$AJ$130,0,MATCH(N$2,Inputs!$K$4:$AJ$4,0)))+SUMPRODUCT((Inputs!$C$5:$C$130=$B7)*Inputs!$D$5:$D$130*(((Inputs!$G$5:$G$130="moeda")+(Inputs!$G$5:$G$130="acoes"))*Inputs!$B$1+((Inputs!$G$5:$G$130<>"moeda")*(Inputs!$G$5:$G$130<>"acoes")))*INDEX(Inputs!$K$5:$AJ$130,0,MATCH(N$2,Inputs!$K$4:$AJ$4,0)))+SUMPRODUCT((Inputs!$E$5:$E$130=$B7)*Inputs!$F$5:$F$130*(((Inputs!$G$5:$G$130="moeda")+(Inputs!$G$5:$G$130="acoes"))*Inputs!$B$1+((Inputs!$G$5:$G$130<>"moeda")*(Inputs!$G$5:$G$130<>"acoes")))*INDEX(Inputs!$K$5:$AJ$130,0,MATCH(N$2,Inputs!$K$4:$AJ$4,0))))) -> -6285 | O7: =IF(ISNA(MATCH(O$2,Inputs!$K$4:$AJ$4,0)),NA(),IF(SUMPRODUCT((Inputs!$A$5:$A$130=$B7)*ISNUMBER(INDEX(Inputs!$K$5:$AJ$130,0,MATCH(O$2,Inputs!$K$4:$AJ$4,0))))+SUMPRODUCT((Inputs!$C$5:$C$130=$B7)*ISNUMBER(INDEX(Inputs!$K$5:$AJ$130,0,MATCH(O$2,Inputs!$K$4:$AJ$4,0))))+SUMPRODUCT((Inputs!$E$5:$E$130=$B7)*ISNUMBER(INDEX(Inputs!$K$5:$AJ$130,0,MATCH(O$2,Inputs!$K$4:$AJ$4,0))))=0,NA(),SUMPRODUCT((Inputs!$A$5:$A$130=$B7)*Inputs!$B$5:$B$130*(((Inputs!$G$5:$G$130="moeda")+(Inputs!$G$5:$G$130="acoes"))*Inputs!$B$1+((Inputs!$G$5:$G$130<>"moeda")*(Inputs!$G$5:$G$130<>"acoes")))*INDEX(Inputs!$K$5:$AJ$130,0,MATCH(O$2,Inputs!$K$4:$AJ$4,0)))+SUMPRODUCT((Inputs!$C$5:$C$130=$B7)*Inputs!$D$5:$D$130*(((Inputs!$G$5:$G$130="moeda")+(Inputs!$G$5:$G$130="acoes"))*Inputs!$B$1+((Inputs!$G$5:$G$130<>"moeda")*(Inputs!$G$5:$G$130<>"acoes")))*INDEX(Inputs!$K$5:$AJ$130,0,MATCH(O$2,Inputs!$K$4:$AJ$4,0)))+SUMPRODUCT((Inputs!$E$5:$E$130=$B7)*Inputs!$F$5:$F$130*(((Inputs!$G$5:$G$130="moeda")+(Inputs!$G$5:$G$130="acoes"))*Inputs!$B$1+((Inputs!$G$5:$G$130<>"moeda")*(Inputs!$G$5:$G$130<>"acoes")))*INDEX(Inputs!$K$5:$AJ$130,0,MATCH(O$2,Inputs!$K$4:$AJ$4,0))))) -> -7872 | P7: =IF(ISNA(MATCH(P$2,Inputs!$K$4:$AJ$4,0)),NA(),IF(SUMPRODUCT((Inputs!$A$5:$A$130=$B7)*ISNUMBER(INDEX(Inputs!$K$5:$AJ$130,0,MATCH(P$2,Inputs!$K$4:$AJ$4,0))))+SUMPRODUCT((Inputs!$C$5:$C$130=$B7)*ISNUMBER(INDEX(Inputs!$K$5:$AJ$130,0,MATCH(P$2,Inputs!$K$4:$AJ$4,0))))+SUMPRODUCT((Inputs!$E$5:$E$130=$B7)*ISNUMBER(INDEX(Inputs!$K$5:$AJ$130,0,MATCH(P$2,Inputs!$K$4:$AJ$4,0))))=0,NA(),SUMPRODUCT((Inputs!$A$5:$A$130=$B7)*Inputs!$B$5:$B$130*(((Inputs!$G$5:$G$130="moeda")+(Inputs!$G$5:$G$130="acoes"))*Inputs!$B$1+((Inputs!$G$5:$G$130<>"moeda")*(Inputs!$G$5:$G$130<>"acoes")))*INDEX(Inputs!$K$5:$AJ$130,0,MATCH(P$2,Inputs!$K$4:$AJ$4,0)))+SUMPRODUCT((Inputs!$C$5:$C$130=$B7)*Inputs!$D$5:$D$130*(((Inputs!$G$5:$G$130="moeda")+(Inputs!$G$5:$G$130="acoes"))*Inputs!$B$1+((Inputs!$G$5:$G$130<>"moeda")*(Inputs!$G$5:$G$130<>"acoes")))*INDEX(Inputs!$K$5:$AJ$130,0,MATCH(P$2,Inputs!$K$4:$AJ$4,0)))+SUMPRODUCT((Inputs!$E$5:$E$130=$B7)*Inputs!$F$5:$F$130*(((Inputs!$G$5:$G$130="moeda")+(Inputs!$G$5:$G$130="acoes"))*Inputs!$B$1+((Inputs!$G$5:$G$130<>"moeda")*(Inputs!$G$5:$G$130<>"acoes")))*INDEX(Inputs!$K$5:$AJ$130,0,MATCH(P$2,Inputs!$K$4:$AJ$4,0))))) -> -5911 | Q7: =IF(ISNA(MATCH(Q$2,Inputs!$K$4:$AJ$4,0)),NA(),IF(SUMPRODUCT((Inputs!$A$5:$A$130=$B7)*ISNUMBER(INDEX(Inputs!$K$5:$AJ$130,0,MATCH(Q$2,Inputs!$K$4:$AJ$4,0))))+SUMPRODUCT((Inputs!$C$5:$C$130=$B7)*ISNUMBER(INDEX(Inputs!$K$5:$AJ$130,0,MATCH(Q$2,Inputs!$K$4:$AJ$4,0))))+SUMPRODUCT((Inputs!$E$5:$E$130=$B7)*ISNUMBER(INDEX(Inputs!$K$5:$AJ$130,0,MATCH(Q$2,Inputs!$K$4:$AJ$4,0))))=0,NA(),SUMPRODUCT((Inputs!$A$5:$A$130=$B7)*Inputs!$B$5:$B$130*(((Inputs!$G$5:$G$130="moeda")+(Inputs!$G$5:$G$130="acoes"))*Inputs!$B$1+((Inputs!$G$5:$G$130<>"moeda")*(Inputs!$G$5:$G$130<>"acoes")))*INDEX(Inputs!$K$5:$AJ$130,0,MATCH(Q$2,Inputs!$K$4:$AJ$4,0)))+SUMPRODUCT((Inputs!$C$5:$C$130=$B7)*Inputs!$D$5:$D$130*(((Inputs!$G$5:$G$130="moeda")+(Inputs!$G$5:$G$130="acoes"))*Inputs!$B$1+((Inputs!$G$5:$G$130<>"moeda")*(Inputs!$G$5:$G$130<>"acoes")))*INDEX(Inputs!$K$5:$AJ$130,0,MATCH(Q$2,Inputs!$K$4:$AJ$4,0)))+SUMPRODUCT((Inputs!$E$5:$E$130=$B7)*Inputs!$F$5:$F$130*(((Inputs!$G$5:$G$130="moeda")+(Inputs!$G$5:$G$130="acoes"))*Inputs!$B$1+((Inputs!$G$5:$G$130<>"moeda")*(Inputs!$G$5:$G$130<>"acoes")))*INDEX(Inputs!$K$5:$AJ$130,0,MATCH(Q$2,Inputs!$K$4:$AJ$4,0))))) -> -11221 | R7: =SUM(N7:Q7) -> -31289 | S7: =IF(ISNA(MATCH(S$2,Inputs!$K$4:$AJ$4,0)),NA(),IF(SUMPRODUCT((Inputs!$A$5:$A$130=$B7)*ISNUMBER(INDEX(Inputs!$K$5:$AJ$130,0,MATCH(S$2,Inputs!$K$4:$AJ$4,0))))+SUMPRODUCT((Inputs!$C$5:$C$130=$B7)*ISNUMBER(INDEX(Inputs!$K$5:$AJ$130,0,MATCH(S$2,Inputs!$K$4:$AJ$4,0))))+SUMPRODUCT((Inputs!$E$5:$E$130=$B7)*ISNUMBER(INDEX(Inputs!$K$5:$AJ$130,0,MATCH(S$2,Inputs!$K$4:$AJ$4,0))))=0,NA(),SUMPRODUCT((Inputs!$A$5:$A$130=$B7)*Inputs!$B$5:$B$130*(((Inputs!$G$5:$G$130="moeda")+(Inputs!$G$5:$G$130="acoes"))*Inputs!$B$1+((Inputs!$G$5:$G$130<>"moeda")*(Inputs!$G$5:$G$130<>"acoes")))*INDEX(Inputs!$K$5:$AJ$130,0,MATCH(S$2,Inputs!$K$4:$AJ$4,0)))+SUMPRODUCT((Inputs!$C$5:$C$130=$B7)*Inputs!$D$5:$D$130*(((Inputs!$G$5:$G$130="moeda")+(Inputs!$G$5:$G$130="acoes"))*Inputs!$B$1+((Inputs!$G$5:$G$130<>"moeda")*(Inputs!$G$5:$G$130<>"acoes")))*INDEX(Inputs!$K$5:$AJ$130,0,MATCH(S$2,Inputs!$K$4:$AJ$4,0)))+SUMPRODUCT((Inputs!$E$5:$E$130=$B7)*Inputs!$F$5:$F$130*(((Inputs!$G$5:$G$130="moeda")+(Inputs!$G$5:$G$130="acoes"))*Inputs!$B$1+((Inputs!$G$5:$G$130<>"moeda")*(Inputs!$G$5:$G$130<>"acoes")))*INDEX(Inputs!$K$5:$AJ$130,0,MATCH(S$2,Inputs!$K$4:$AJ$4,0))))) -> -5881 | T7: =IF(ISNA(MATCH(T$2,Inputs!$K$4:$AJ$4,0)),NA(),IF(SUMPRODUCT((Inputs!$A$5:$A$130=$B7)*ISNUMBER(INDEX(Inputs!$K$5:$AJ$130,0,MATCH(T$2,Inputs!$K$4:$AJ$4,0))))+SUMPRODUCT((Inputs!$C$5:$C$130=$B7)*ISNUMBER(INDEX(Inputs!$K$5:$AJ$130,0,MATCH(T$2,Inputs!$K$4:$AJ$4,0))))+SUMPRODUCT((Inputs!$E$5:$E$130=$B7)*ISNUMBER(INDEX(Inputs!$K$5:$AJ$130,0,MATCH(T$2,Inputs!$K$4:$AJ$4,0))))=0,NA(),SUMPRODUCT((Inputs!$A$5:$A$130=$B7)*Inputs!$B$5:$B$130*(((Inputs!$G$5:$G$130="moeda")+(Inputs!$G$5:$G$130="acoes"))*Inputs!$B$1+((Inputs!$G$5:$G$130<>"moeda")*(Inputs!$G$5:$G$130<>"acoes")))*INDEX(Inputs!$K$5:$AJ$130,0,MATCH(T$2,Inputs!$K$4:$AJ$4,0)))+SUMPRODUCT((Inputs!$C$5:$C$130=$B7)*Inputs!$D$5:$D$130*(((Inputs!$G$5:$G$130="moeda")+(Inputs!$G$5:$G$130="acoes"))*Inputs!$B$1+((Inputs!$G$5:$G$130<>"moeda")*(Inputs!$G$5:$G$130<>"acoes")))*INDEX(Inputs!$K$5:$AJ$130,0,MATCH(T$2,Inputs!$K$4:$AJ$4,0)))+SUMPRODUCT((Inputs!$E$5:$E$130=$B7)*Inputs!$F$5:$F$130*(((Inputs!$G$5:$G$130="moeda")+(Inputs!$G$5:$G$130="acoes"))*Inputs!$B$1+((Inputs!$G$5:$G$130<>"moeda")*(Inputs!$G$5:$G$130<>"acoes")))*INDEX(Inputs!$K$5:$AJ$130,0,MATCH(T$2,Inputs!$K$4:$AJ$4,0))))) -> -7555 | U7: =IF(ISNA(MATCH(U$2,Inputs!$K$4:$AJ$4,0)),NA(),IF(SUMPRODUCT((Inputs!$A$5:$A$130=$B7)*ISNUMBER(INDEX(Inputs!$K$5:$AJ$130,0,MATCH(U$2,Inputs!$K$4:$AJ$4,0))))+SUMPRODUCT((Inputs!$C$5:$C$130=$B7)*ISNUMBER(INDEX(Inputs!$K$5:$AJ$130,0,MATCH(U$2,Inputs!$K$4:$AJ$4,0))))+SUMPRODUCT((Inputs!$E$5:$E$130=$B7)*ISNUMBER(INDEX(Inputs!$K$5:$AJ$130,0,MATCH(U$2,Inputs!$K$4:$AJ$4,0))))=0,NA(),SUMPRODUCT((Inputs!$A$5:$A$130=$B7)*Inputs!$B$5:$B$130*(((Inputs!$G$5:$G$130="moeda")+(Inputs!$G$5:$G$130="acoes"))*Inputs!$B$1+((Inputs!$G$5:$G$130<>"moeda")*(Inputs!$G$5:$G$130<>"acoes")))*INDEX(Inputs!$K$5:$AJ$130,0,MATCH(U$2,Inputs!$K$4:$AJ$4,0)))+SUMPRODUCT((Inputs!$C$5:$C$130=$B7)*Inputs!$D$5:$D$130*(((Inputs!$G$5:$G$130="moeda")+(Inputs!$G$5:$G$130="acoes"))*Inputs!$B$1+((Inputs!$G$5:$G$130<>"moeda")*(Inputs!$G$5:$G$130<>"acoes")))*INDEX(Inputs!$K$5:$AJ$130,0,MATCH(U$2,Inputs!$K$4:$AJ$4,0)))+SUMPRODUCT((Inputs!$E$5:$E$130=$B7)*Inputs!$F$5:$F$130*(((Inputs!$G$5:$G$130="moeda")+(Inputs!$G$5:$G$130="acoes"))*Inputs!$B$1+((Inputs!$G$5:$G$130<>"moeda")*(Inputs!$G$5:$G$130<>"acoes")))*INDEX(Inputs!$K$5:$AJ$130,0,MATCH(U$2,Inputs!$K$4:$AJ$4,0))))) -> -5916 | V7: =IF(ISNA(MATCH(V$2,Inputs!$K$4:$AJ$4,0)),NA(),IF(SUMPRODUCT((Inputs!$A$5:$A$130=$B7)*ISNUMBER(INDEX(Inputs!$K$5:$AJ$130,0,MATCH(V$2,Inputs!$K$4:$AJ$4,0))))+SUMPRODUCT((Inputs!$C$5:$C$130=$B7)*ISNUMBER(INDEX(Inputs!$K$5:$AJ$130,0,MATCH(V$2,Inputs!$K$4:$AJ$4,0))))+SUMPRODUCT((Inputs!$E$5:$E$130=$B7)*ISNUMBER(INDEX(Inputs!$K$5:$AJ$130,0,MATCH(V$2,Inputs!$K$4:$AJ$4,0))))=0,NA(),SUMPRODUCT((Inputs!$A$5:$A$130=$B7)*Inputs!$B$5:$B$130*(((Inputs!$G$5:$G$130="moeda")+(Inputs!$G$5:$G$130="acoes"))*Inputs!$B$1+((Inputs!$G$5:$G$130<>"moeda")*(Inputs!$G$5:$G$130<>"acoes")))*INDEX(Inputs!$K$5:$AJ$130,0,MATCH(V$2,Inputs!$K$4:$AJ$4,0)))+SUMPRODUCT((Inputs!$C$5:$C$130=$B7)*Inputs!$D$5:$D$130*(((Inputs!$G$5:$G$130="moeda")+(Inputs!$G$5:$G$130="acoes"))*Inputs!$B$1+((Inputs!$G$5:$G$130<>"moeda")*(Inputs!$G$5:$G$130<>"acoes")))*INDEX(Inputs!$K$5:$AJ$130,0,MATCH(V$2,Inputs!$K$4:$AJ$4,0)))+SUMPRODUCT((Inputs!$E$5:$E$130=$B7)*Inputs!$F$5:$F$130*(((Inputs!$G$5:$G$130="moeda")+(Inputs!$G$5:$G$130="acoes"))*Inputs!$B$1+((Inputs!$G$5:$G$130<>"moeda")*(Inputs!$G$5:$G$130<>"acoes")))*INDEX(Inputs!$K$5:$AJ$130,0,MATCH(V$2,Inputs!$K$4:$AJ$4,0))))) -> -7520 | W7: =SUM(S7:V7) -> -26872 | X7: =IF(ISNA(MATCH(X$2,Inputs!$K$4:$AJ$4,0)),NA(),IF(SUMPRODUCT((Inputs!$A$5:$A$130=$B7)*ISNUMBER(INDEX(Inputs!$K$5:$AJ$130,0,MATCH(X$2,Inputs!$K$4:$AJ$4,0))))+SUMPRODUCT((Inputs!$C$5:$C$130=$B7)*ISNUMBER(INDEX(Inputs!$K$5:$AJ$130,0,MATCH(X$2,Inputs!$K$4:$AJ$4,0))))+SUMPRODUCT((Inputs!$E$5:$E$130=$B7)*ISNUMBER(INDEX(Inputs!$K$5:$AJ$130,0,MATCH(X$2,Inputs!$K$4:$AJ$4,0))))=0,NA(),SUMPRODUCT((Inputs!$A$5:$A$130=$B7)*Inputs!$B$5:$B$130*(((Inputs!$G$5:$G$130="moeda")+(Inputs!$G$5:$G$130="acoes"))*Inputs!$B$1+((Inputs!$G$5:$G$130<>"moeda")*(Inputs!$G$5:$G$130<>"acoes")))*INDEX(Inputs!$K$5:$AJ$130,0,MATCH(X$2,Inputs!$K$4:$AJ$4,0)))+SUMPRODUCT((Inputs!$C$5:$C$130=$B7)*Inputs!$D$5:$D$130*(((Inputs!$G$5:$G$130="moeda")+(Inputs!$G$5:$G$130="acoes"))*Inputs!$B$1+((Inputs!$G$5:$G$130<>"moeda")*(Inputs!$G$5:$G$130<>"acoes")))*INDEX(Inputs!$K$5:$AJ$130,0,MATCH(X$2,Inputs!$K$4:$AJ$4,0)))+SUMPRODUCT((Inputs!$E$5:$E$130=$B7)*Inputs!$F$5:$F$130*(((Inputs!$G$5:$G$130="moeda")+(Inputs!$G$5:$G$130="acoes"))*Inputs!$B$1+((Inputs!$G$5:$G$130<>"moeda")*(Inputs!$G$5:$G$130<>"acoes")))*INDEX(Inputs!$K$5:$AJ$130,0,MATCH(X$2,Inputs!$K$4:$AJ$4,0))))) -> -5441 | Y7: =IF(ISNA(MATCH(Y$2,Inputs!$K$4:$AJ$4,0)),NA(),IF(SUMPRODUCT((Inputs!$A$5:$A$130=$B7)*ISNUMBER(INDEX(Inputs!$K$5:$AJ$130,0,MATCH(Y$2,Inputs!$K$4:$AJ$4,0))))+SUMPRODUCT((Inputs!$C$5:$C$130=$B7)*ISNUMBER(INDEX(Inputs!$K$5:$AJ$130,0,MATCH(Y$2,Inputs!$K$4:$AJ$4,0))))+SUMPRODUCT((Inputs!$E$5:$E$130=$B7)*ISNUMBER(INDEX(Inputs!$K$5:$AJ$130,0,MATCH(Y$2,Inputs!$K$4:$AJ$4,0))))=0,NA(),SUMPRODUCT((Inputs!$A$5:$A$130=$B7)*Inputs!$B$5:$B$130*(((Inputs!$G$5:$G$130="moeda")+(Inputs!$G$5:$G$130="acoes"))*Inputs!$B$1+((Inputs!$G$5:$G$130<>"moeda")*(Inputs!$G$5:$G$130<>"acoes")))*INDEX(Inputs!$K$5:$AJ$130,0,MATCH(Y$2,Inputs!$K$4:$AJ$4,0)))+SUMPRODUCT((Inputs!$C$5:$C$130=$B7)*Inputs!$D$5:$D$130*(((Inputs!$G$5:$G$130="moeda")+(Inputs!$G$5:$G$130="acoes"))*Inputs!$B$1+((Inputs!$G$5:$G$130<>"moeda")*(Inputs!$G$5:$G$130<>"acoes")))*INDEX(Inputs!$K$5:$AJ$130,0,MATCH(Y$2,Inputs!$K$4:$AJ$4,0)))+SUMPRODUCT((Inputs!$E$5:$E$130=$B7)*Inputs!$F$5:$F$130*(((Inputs!$G$5:$G$130="moeda")+(Inputs!$G$5:$G$130="acoes"))*Inputs!$B$1+((Inputs!$G$5:$G$130<>"moeda")*(Inputs!$G$5:$G$130<>"acoes")))*INDEX(Inputs!$K$5:$AJ$130,0,MATCH(Y$2,Inputs!$K$4:$AJ$4,0))))) -> -6670 | Z7: =IF(ISNA(MATCH(Z$2,Inputs!$K$4:$AJ$4,0)),NA(),IF(SUMPRODUCT((Inputs!$A$5:$A$130=$B7)*ISNUMBER(INDEX(Inputs!$K$5:$AJ$130,0,MATCH(Z$2,Inputs!$K$4:$AJ$4,0))))+SUMPRODUCT((Inputs!$C$5:$C$130=$B7)*ISNUMBER(INDEX(Inputs!$K$5:$AJ$130,0,MATCH(Z$2,Inputs!$K$4:$AJ$4,0))))+SUMPRODUCT((Inputs!$E$5:$E$130=$B7)*ISNUMBER(INDEX(Inputs!$K$5:$AJ$130,0,MATCH(Z$2,Inputs!$K$4:$AJ$4,0))))=0,NA(),SUMPRODUCT((Inputs!$A$5:$A$130=$B7)*Inputs!$B$5:$B$130*(((Inputs!$G$5:$G$130="moeda")+(Inputs!$G$5:$G$130="acoes"))*Inputs!$B$1+((Inputs!$G$5:$G$130<>"moeda")*(Inputs!$G$5:$G$130<>"acoes")))*INDEX(Inputs!$K$5:$AJ$130,0,MATCH(Z$2,Inputs!$K$4:$AJ$4,0)))+SUMPRODUCT((Inputs!$C$5:$C$130=$B7)*Inputs!$D$5:$D$130*(((Inputs!$G$5:$G$130="moeda")+(Inputs!$G$5:$G$130="acoes"))*Inputs!$B$1+((Inputs!$G$5:$G$130<>"moeda")*(Inputs!$G$5:$G$130<>"acoes")))*INDEX(Inputs!$K$5:$AJ$130,0,MATCH(Z$2,Inputs!$K$4:$AJ$4,0)))+SUMPRODUCT((Inputs!$E$5:$E$130=$B7)*Inputs!$F$5:$F$130*(((Inputs!$G$5:$G$130="moeda")+(Inputs!$G$5:$G$130="acoes"))*Inputs!$B$1+((Inputs!$G$5:$G$130<>"moeda")*(Inputs!$G$5:$G$130<>"acoes")))*INDEX(Inputs!$K$5:$AJ$130,0,MATCH(Z$2,Inputs!$K$4:$AJ$4,0))))) -> -6607 | AA7: =IF(ISNA(MATCH(AA$2,Inputs!$K$4:$AJ$4,0)),NA(),IF(SUMPRODUCT((Inputs!$A$5:$A$130=$B7)*ISNUMBER(INDEX(Inputs!$K$5:$AJ$130,0,MATCH(AA$2,Inputs!$K$4:$AJ$4,0))))+SUMPRODUCT((Inputs!$C$5:$C$130=$B7)*ISNUMBER(INDEX(Inputs!$K$5:$AJ$130,0,MATCH(AA$2,Inputs!$K$4:$AJ$4,0))))+SUMPRODUCT((Inputs!$E$5:$E$130=$B7)*ISNUMBER(INDEX(Inputs!$K$5:$AJ$130,0,MATCH(AA$2,Inputs!$K$4:$AJ$4,0))))=0,NA(),SUMPRODUCT((Inputs!$A$5:$A$130=$B7)*Inputs!$B$5:$B$130*(((Inputs!$G$5:$G$130="moeda")+(Inputs!$G$5:$G$130="acoes"))*Inputs!$B$1+((Inputs!$G$5:$G$130<>"moeda")*(Inputs!$G$5:$G$130<>"acoes")))*INDEX(Inputs!$K$5:$AJ$130,0,MATCH(AA$2,Inputs!$K$4:$AJ$4,0)))+SUMPRODUCT((Inputs!$C$5:$C$130=$B7)*Inputs!$D$5:$D$130*(((Inputs!$G$5:$G$130="moeda")+(Inputs!$G$5:$G$130="acoes"))*Inputs!$B$1+((Inputs!$G$5:$G$130<>"moeda")*(Inputs!$G$5:$G$130<>"acoes")))*INDEX(Inputs!$K$5:$AJ$130,0,MATCH(AA$2,Inputs!$K$4:$AJ$4,0)))+SUMPRODUCT((Inputs!$E$5:$E$130=$B7)*Inputs!$F$5:$F$130*(((Inputs!$G$5:$G$130="moeda")+(Inputs!$G$5:$G$130="acoes"))*Inputs!$B$1+((Inputs!$G$5:$G$130<>"moeda")*(Inputs!$G$5:$G$130<>"acoes")))*INDEX(Inputs!$K$5:$AJ$130,0,MATCH(AA$2,Inputs!$K$4:$AJ$4,0))))) -> -6581 | AB7: =SUM(X7:AA7) -> -25299 | AC7: =IF(ISNA(MATCH(AC$2,Inputs!$K$4:$AJ$4,0)),NA(),IF(SUMPRODUCT((Inputs!$A$5:$A$130=$B7)*ISNUMBER(INDEX(Inputs!$K$5:$AJ$130,0,MATCH(AC$2,Inputs!$K$4:$AJ$4,0))))+SUMPRODUCT((Inputs!$C$5:$C$130=$B7)*ISNUMBER(INDEX(Inputs!$K$5:$AJ$130,0,MATCH(AC$2,Inputs!$K$4:$AJ$4,0))))+SUMPRODUCT((Inputs!$E$5:$E$130=$B7)*ISNUMBER(INDEX(Inputs!$K$5:$AJ$130,0,MATCH(AC$2,Inputs!$K$4:$AJ$4,0))))=0,NA(),SUMPRODUCT((Inputs!$A$5:$A$130=$B7)*Inputs!$B$5:$B$130*(((Inputs!$G$5:$G$130="moeda")+(Inputs!$G$5:$G$130="acoes"))*Inputs!$B$1+((Inputs!$G$5:$G$130<>"moeda")*(Inputs!$G$5:$G$130<>"acoes")))*INDEX(Inputs!$K$5:$AJ$130,0,MATCH(AC$2,Inputs!$K$4:$AJ$4,0)))+SUMPRODUCT((Inputs!$C$5:$C$130=$B7)*Inputs!$D$5:$D$130*(((Inputs!$G$5:$G$130="moeda")+(Inputs!$G$5:$G$130="acoes"))*Inputs!$B$1+((Inputs!$G$5:$G$130<>"moeda")*(Inputs!$G$5:$G$130<>"acoes")))*INDEX(Inputs!$K$5:$AJ$130,0,MATCH(AC$2,Inputs!$K$4:$AJ$4,0)))+SUMPRODUCT((Inputs!$E$5:$E$130=$B7)*Inputs!$F$5:$F$130*(((Inputs!$G$5:$G$130="moeda")+(Inputs!$G$5:$G$130="acoes"))*Inputs!$B$1+((Inputs!$G$5:$G$130<>"moeda")*(Inputs!$G$5:$G$130<>"acoes")))*INDEX(Inputs!$K$5:$AJ$130,0,MATCH(AC$2,Inputs!$K$4:$AJ$4,0))))) -> -5743 | AD7: =IF(ISNA(MATCH(AD$2,Inputs!$K$4:$AJ$4,0)),NA(),IF(SUMPRODUCT((Inputs!$A$5:$A$130=$B7)*ISNUMBER(INDEX(Inputs!$K$5:$AJ$130,0,MATCH(AD$2,Inputs!$K$4:$AJ$4,0))))+SUMPRODUCT((Inputs!$C$5:$C$130=$B7)*ISNUMBER(INDEX(Inputs!$K$5:$AJ$130,0,MATCH(AD$2,Inputs!$K$4:$AJ$4,0))))+SUMPRODUCT((Inputs!$E$5:$E$130=$B7)*ISNUMBER(INDEX(Inputs!$K$5:$AJ$130,0,MATCH(AD$2,Inputs!$K$4:$AJ$4,0))))=0,NA(),SUMPRODUCT((Inputs!$A$5:$A$130=$B7)*Inputs!$B$5:$B$130*(((Inputs!$G$5:$G$130="moeda")+(Inputs!$G$5:$G$130="acoes"))*Inputs!$B$1+((Inputs!$G$5:$G$130<>"moeda")*(Inputs!$G$5:$G$130<>"acoes")))*INDEX(Inputs!$K$5:$AJ$130,0,MATCH(AD$2,Inputs!$K$4:$AJ$4,0)))+SUMPRODUCT((Inputs!$C$5:$C$130=$B7)*Inputs!$D$5:$D$130*(((Inputs!$G$5:$G$130="moeda")+(Inputs!$G$5:$G$130="acoes"))*Inputs!$B$1+((Inputs!$G$5:$G$130<>"moeda")*(Inputs!$G$5:$G$130<>"acoes")))*INDEX(Inputs!$K$5:$AJ$130,0,MATCH(AD$2,Inputs!$K$4:$AJ$4,0)))+SUMPRODUCT((Inputs!$E$5:$E$130=$B7)*Inputs!$F$5:$F$130*(((Inputs!$G$5:$G$130="moeda")+(Inputs!$G$5:$G$130="acoes"))*Inputs!$B$1+((Inputs!$G$5:$G$130<>"moeda")*(Inputs!$G$5:$G$130<>"acoes")))*INDEX(Inputs!$K$5:$AJ$130,0,MATCH(AD$2,Inputs!$K$4:$AJ$4,0))))) -> -6183 | AE7: =IF(ISNA(MATCH(AE$2,Inputs!$K$4:$AJ$4,0)),NA(),IF(SUMPRODUCT((Inputs!$A$5:$A$130=$B7)*ISNUMBER(INDEX(Inputs!$K$5:$AJ$130,0,MATCH(AE$2,Inputs!$K$4:$AJ$4,0))))+SUMPRODUCT((Inputs!$C$5:$C$130=$B7)*ISNUMBER(INDEX(Inputs!$K$5:$AJ$130,0,MATCH(AE$2,Inputs!$K$4:$AJ$4,0))))+SUMPRODUCT((Inputs!$E$5:$E$130=$B7)*ISNUMBER(INDEX(Inputs!$K$5:$AJ$130,0,MATCH(AE$2,Inputs!$K$4:$AJ$4,0))))=0,NA(),SUMPRODUCT((Inputs!$A$5:$A$130=$B7)*Inputs!$B$5:$B$130*(((Inputs!$G$5:$G$130="moeda")+(Inputs!$G$5:$G$130="acoes"))*Inputs!$B$1+((Inputs!$G$5:$G$130<>"moeda")*(Inputs!$G$5:$G$130<>"acoes")))*INDEX(Inputs!$K$5:$AJ$130,0,MATCH(AE$2,Inputs!$K$4:$AJ$4,0)))+SUMPRODUCT((Inputs!$C$5:$C$130=$B7)*Inputs!$D$5:$D$130*(((Inputs!$G$5:$G$130="moeda")+(Inputs!$G$5:$G$130="acoes"))*Inputs!$B$1+((Inputs!$G$5:$G$130<>"moeda")*(Inputs!$G$5:$G$130<>"acoes")))*INDEX(Inputs!$K$5:$AJ$130,0,MATCH(AE$2,Inputs!$K$4:$AJ$4,0)))+SUMPRODUCT((Inputs!$E$5:$E$130=$B7)*Inputs!$F$5:$F$130*(((Inputs!$G$5:$G$130="moeda")+(Inputs!$G$5:$G$130="acoes"))*Inputs!$B$1+((Inputs!$G$5:$G$130<>"moeda")*(Inputs!$G$5:$G$130<>"acoes")))*INDEX(Inputs!$K$5:$AJ$130,0,MATCH(AE$2,Inputs!$K$4:$AJ$4,0))))) -> #N/A | AF7: =IF(ISNA(MATCH(AF$2,Inputs!$K$4:$AJ$4,0)),NA(),IF(SUMPRODUCT((Inputs!$A$5:$A$130=$B7)*ISNUMBER(INDEX(Inputs!$K$5:$AJ$130,0,MATCH(AF$2,Inputs!$K$4:$AJ$4,0))))+SUMPRODUCT((Inputs!$C$5:$C$130=$B7)*ISNUMBER(INDEX(Inputs!$K$5:$AJ$130,0,MATCH(AF$2,Inputs!$K$4:$AJ$4,0))))+SUMPRODUCT((Inputs!$E$5:$E$130=$B7)*ISNUMBER(INDEX(Inputs!$K$5:$AJ$130,0,MATCH(AF$2,Inputs!$K$4:$AJ$4,0))))=0,NA(),SUMPRODUCT((Inputs!$A$5:$A$130=$B7)*Inputs!$B$5:$B$130*(((Inputs!$G$5:$G$130="moeda")+(Inputs!$G$5:$G$130="acoes"))*Inputs!$B$1+((Inputs!$G$5:$G$130<>"moeda")*(Inputs!$G$5:$G$130<>"acoes")))*INDEX(Inputs!$K$5:$AJ$130,0,MATCH(AF$2,Inputs!$K$4:$AJ$4,0)))+SUMPRODUCT((Inputs!$C$5:$C$130=$B7)*Inputs!$D$5:$D$130*(((Inputs!$G$5:$G$130="moeda")+(Inputs!$G$5:$G$130="acoes"))*Inputs!$B$1+((Inputs!$G$5:$G$130<>"moeda")*(Inputs!$G$5:$G$130<>"acoes")))*INDEX(Inputs!$K$5:$AJ$130,0,MATCH(AF$2,Inputs!$K$4:$AJ$4,0)))+SUMPRODUCT((Inputs!$E$5:$E$130=$B7)*Inputs!$F$5:$F$130*(((Inputs!$G$5:$G$130="moeda")+(Inputs!$G$5:$G$130="acoes"))*Inputs!$B$1+((Inputs!$G$5:$G$130<>"moeda")*(Inputs!$G$5:$G$130<>"acoes")))*INDEX(Inputs!$K$5:$AJ$130,0,MATCH(AF$2,Inputs!$K$4:$AJ$4,0))))) -> #N/A | AG7: =SUM(AC7:AF7) -> #N/A | AH7: =IF(ISNA(MATCH(AH$2,Inputs!$K$4:$AJ$4,0)),NA(),IF(SUMPRODUCT((Inputs!$A$5:$A$130=$B7)*ISNUMBER(INDEX(Inputs!$K$5:$AJ$130,0,MATCH(AH$2,Inputs!$K$4:$AJ$4,0))))+SUMPRODUCT((Inputs!$C$5:$C$130=$B7)*ISNUMBER(INDEX(Inputs!$K$5:$AJ$130,0,MATCH(AH$2,Inputs!$K$4:$AJ$4,0))))+SUMPRODUCT((Inputs!$E$5:$E$130=$B7)*ISNUMBER(INDEX(Inputs!$K$5:$AJ$130,0,MATCH(AH$2,Inputs!$K$4:$AJ$4,0))))=0,NA(),SUMPRODUCT((Inputs!$A$5:$A$130=$B7)*Inputs!$B$5:$B$130*(((Inputs!$G$5:$G$130="moeda")+(Inputs!$G$5:$G$130="acoes"))*Inputs!$B$1+((Inputs!$G$5:$G$130<>"moeda")*(Inputs!$G$5:$G$130<>"acoes")))*INDEX(Inputs!$K$5:$AJ$130,0,MATCH(AH$2,Inputs!$K$4:$AJ$4,0)))+SUMPRODUCT((Inputs!$C$5:$C$130=$B7)*Inputs!$D$5:$D$130*(((Inputs!$G$5:$G$130="moeda")+(Inputs!$G$5:$G$130="acoes"))*Inputs!$B$1+((Inputs!$G$5:$G$130<>"moeda")*(Inputs!$G$5:$G$130<>"acoes")))*INDEX(Inputs!$K$5:$AJ$130,0,MATCH(AH$2,Inputs!$K$4:$AJ$4,0)))+SUMPRODUCT((Inputs!$E$5:$E$130=$B7)*Inputs!$F$5:$F$130*(((Inputs!$G$5:$G$130="moeda")+(Inputs!$G$5:$G$130="acoes"))*Inputs!$B$1+((Inputs!$G$5:$G$130<>"moeda")*(Inputs!$G$5:$G$130<>"acoes")))*INDEX(Inputs!$K$5:$AJ$130,0,MATCH(AH$2,Inputs!$K$4:$AJ$4,0))))) -> #N/A | AI7: =IF(ISNA(MATCH(AI$2,Inputs!$K$4:$AJ$4,0)),NA(),IF(SUMPRODUCT((Inputs!$A$5:$A$130=$B7)*ISNUMBER(INDEX(Inputs!$K$5:$AJ$130,0,MATCH(AI$2,Inputs!$K$4:$AJ$4,0))))+SUMPRODUCT((Inputs!$C$5:$C$130=$B7)*ISNUMBER(INDEX(Inputs!$K$5:$AJ$130,0,MATCH(AI$2,Inputs!$K$4:$AJ$4,0))))+SUMPRODUCT((Inputs!$E$5:$E$130=$B7)*ISNUMBER(INDEX(Inputs!$K$5:$AJ$130,0,MATCH(AI$2,Inputs!$K$4:$AJ$4,0))))=0,NA(),SUMPRODUCT((Inputs!$A$5:$A$130=$B7)*Inputs!$B$5:$B$130*(((Inputs!$G$5:$G$130="moeda")+(Inputs!$G$5:$G$130="acoes"))*Inputs!$B$1+((Inputs!$G$5:$G$130<>"moeda")*(Inputs!$G$5:$G$130<>"acoes")))*INDEX(Inputs!$K$5:$AJ$130,0,MATCH(AI$2,Inputs!$K$4:$AJ$4,0)))+SUMPRODUCT((Inputs!$C$5:$C$130=$B7)*Inputs!$D$5:$D$130*(((Inputs!$G$5:$G$130="moeda")+(Inputs!$G$5:$G$130="acoes"))*Inputs!$B$1+((Inputs!$G$5:$G$130<>"moeda")*(Inputs!$G$5:$G$130<>"acoes")))*INDEX(Inputs!$K$5:$AJ$130,0,MATCH(AI$2,Inputs!$K$4:$AJ$4,0)))+SUMPRODUCT((Inputs!$E$5:$E$130=$B7)*Inputs!$F$5:$F$130*(((Inputs!$G$5:$G$130="moeda")+(Inputs!$G$5:$G$130="acoes"))*Inputs!$B$1+((Inputs!$G$5:$G$130<>"moeda")*(Inputs!$G$5:$G$130<>"acoes")))*INDEX(Inputs!$K$5:$AJ$130,0,MATCH(AI$2,Inputs!$K$4:$AJ$4,0))))) -> #N/A | AJ7: =IF(ISNA(MATCH(AJ$2,Inputs!$K$4:$AJ$4,0)),NA(),IF(SUMPRODUCT((Inputs!$A$5:$A$130=$B7)*ISNUMBER(INDEX(Inputs!$K$5:$AJ$130,0,MATCH(AJ$2,Inputs!$K$4:$AJ$4,0))))+SUMPRODUCT((Inputs!$C$5:$C$130=$B7)*ISNUMBER(INDEX(Inputs!$K$5:$AJ$130,0,MATCH(AJ$2,Inputs!$K$4:$AJ$4,0))))+SUMPRODUCT((Inputs!$E$5:$E$130=$B7)*ISNUMBER(INDEX(Inputs!$K$5:$AJ$130,0,MATCH(AJ$2,Inputs!$K$4:$AJ$4,0))))=0,NA(),SUMPRODUCT((Inputs!$A$5:$A$130=$B7)*Inputs!$B$5:$B$130*(((Inputs!$G$5:$G$130="moeda")+(Inputs!$G$5:$G$130="acoes"))*Inputs!$B$1+((Inputs!$G$5:$G$130<>"moeda")*(Inputs!$G$5:$G$130<>"acoes")))*INDEX(Inputs!$K$5:$AJ$130,0,MATCH(AJ$2,Inputs!$K$4:$AJ$4,0)))+SUMPRODUCT((Inputs!$C$5:$C$130=$B7)*Inputs!$D$5:$D$130*(((Inputs!$G$5:$G$130="moeda")+(Inputs!$G$5:$G$130="acoes"))*Inputs!$B$1+((Inputs!$G$5:$G$130<>"moeda")*(Inputs!$G$5:$G$130<>"acoes")))*INDEX(Inputs!$K$5:$AJ$130,0,MATCH(AJ$2,Inputs!$K$4:$AJ$4,0)))+SUMPRODUCT((Inputs!$E$5:$E$130=$B7)*Inputs!$F$5:$F$130*(((Inputs!$G$5:$G$130="moeda")+(Inputs!$G$5:$G$130="acoes"))*Inputs!$B$1+((Inputs!$G$5:$G$130<>"moeda")*(Inputs!$G$5:$G$130<>"acoes")))*INDEX(Inputs!$K$5:$AJ$130,0,MATCH(AJ$2,Inputs!$K$4:$AJ$4,0))))) -> #N/A | AK7: =IF(ISNA(MATCH(AK$2,Inputs!$K$4:$AJ$4,0)),NA(),IF(SUMPRODUCT((Inputs!$A$5:$A$130=$B7)*ISNUMBER(INDEX(Inputs!$K$5:$AJ$130,0,MATCH(AK$2,Inputs!$K$4:$AJ$4,0))))+SUMPRODUCT((Inputs!$C$5:$C$130=$B7)*ISNUMBER(INDEX(Inputs!$K$5:$AJ$130,0,MATCH(AK$2,Inputs!$K$4:$AJ$4,0))))+SUMPRODUCT((Inputs!$E$5:$E$130=$B7)*ISNUMBER(INDEX(Inputs!$K$5:$AJ$130,0,MATCH(AK$2,Inputs!$K$4:$AJ$4,0))))=0,NA(),SUMPRODUCT((Inputs!$A$5:$A$130=$B7)*Inputs!$B$5:$B$130*(((Inputs!$G$5:$G$130="moeda")+(Inputs!$G$5:$G$130="acoes"))*Inputs!$B$1+((Inputs!$G$5:$G$130<>"moeda")*(Inputs!$G$5:$G$130<>"acoes")))*INDEX(Inputs!$K$5:$AJ$130,0,MATCH(AK$2,Inputs!$K$4:$AJ$4,0)))+SUMPRODUCT((Inputs!$C$5:$C$130=$B7)*Inputs!$D$5:$D$130*(((Inputs!$G$5:$G$130="moeda")+(Inputs!$G$5:$G$130="acoes"))*Inputs!$B$1+((Inputs!$G$5:$G$130<>"moeda")*(Inputs!$G$5:$G$130<>"acoes")))*INDEX(Inputs!$K$5:$AJ$130,0,MATCH(AK$2,Inputs!$K$4:$AJ$4,0)))+SUMPRODUCT((Inputs!$E$5:$E$130=$B7)*Inputs!$F$5:$F$130*(((Inputs!$G$5:$G$130="moeda")+(Inputs!$G$5:$G$130="acoes"))*Inputs!$B$1+((Inputs!$G$5:$G$130<>"moeda")*(Inputs!$G$5:$G$130<>"acoes")))*INDEX(Inputs!$K$5:$AJ$130,0,MATCH(AK$2,Inputs!$K$4:$AJ$4,0))))) -> #N/A | AL7: =SUM(AH7:AK7) -> #N/A
B8: 5 | C8: Interest Expense | D8: =IF(ISNA(MATCH(D$2,Inputs!$K$4:$AJ$4,0)),NA(),IF(SUMPRODUCT((Inputs!$A$5:$A$130=$B8)*ISNUMBER(INDEX(Inputs!$K$5:$AJ$130,0,MATCH(D$2,Inputs!$K$4:$AJ$4,0))))+SUMPRODUCT((Inputs!$C$5:$C$130=$B8)*ISNUMBER(INDEX(Inputs!$K$5:$AJ$130,0,MATCH(D$2,Inputs!$K$4:$AJ$4,0))))+SUMPRODUCT((Inputs!$E$5:$E$130=$B8)*ISNUMBER(INDEX(Inputs!$K$5:$AJ$130,0,MATCH(D$2,Inputs!$K$4:$AJ$4,0))))=0,NA(),SUMPRODUCT((Inputs!$A$5:$A$130=$B8)*Inputs!$B$5:$B$130*(((Inputs!$G$5:$G$130="moeda")+(Inputs!$G$5:$G$130="acoes"))*Inputs!$B$1+((Inputs!$G$5:$G$130<>"moeda")*(Inputs!$G$5:$G$130<>"acoes")))*INDEX(Inputs!$K$5:$AJ$130,0,MATCH(D$2,Inputs!$K$4:$AJ$4,0)))+SUMPRODUCT((Inputs!$C$5:$C$130=$B8)*Inputs!$D$5:$D$130*(((Inputs!$G$5:$G$130="moeda")+(Inputs!$G$5:$G$130="acoes"))*Inputs!$B$1+((Inputs!$G$5:$G$130<>"moeda")*(Inputs!$G$5:$G$130<>"acoes")))*INDEX(Inputs!$K$5:$AJ$130,0,MATCH(D$2,Inputs!$K$4:$AJ$4,0)))+SUMPRODUCT((Inputs!$E$5:$E$130=$B8)*Inputs!$F$5:$F$130*(((Inputs!$G$5:$G$130="moeda")+(Inputs!$G$5:$G$130="acoes"))*Inputs!$B$1+((Inputs!$G$5:$G$130<>"moeda")*(Inputs!$G$5:$G$130<>"acoes")))*INDEX(Inputs!$K$5:$AJ$130,0,MATCH(D$2,Inputs!$K$4:$AJ$4,0))))) -> -892 | E8: =IF(ISNA(MATCH(E$2,Inputs!$K$4:$AJ$4,0)),NA(),IF(SUMPRODUCT((Inputs!$A$5:$A$130=$B8)*ISNUMBER(INDEX(Inputs!$K$5:$AJ$130,0,MATCH(E$2,Inputs!$K$4:$AJ$4,0))))+SUMPRODUCT((Inputs!$C$5:$C$130=$B8)*ISNUMBER(INDEX(Inputs!$K$5:$AJ$130,0,MATCH(E$2,Inputs!$K$4:$AJ$4,0))))+SUMPRODUCT((Inputs!$E$5:$E$130=$B8)*ISNUMBER(INDEX(Inputs!$K$5:$AJ$130,0,MATCH(E$2,Inputs!$K$4:$AJ$4,0))))=0,NA(),SUMPRODUCT((Inputs!$A$5:$A$130=$B8)*Inputs!$B$5:$B$130*(((Inputs!$G$5:$G$130="moeda")+(Inputs!$G$5:$G$130="acoes"))*Inputs!$B$1+((Inputs!$G$5:$G$130<>"moeda")*(Inputs!$G$5:$G$130<>"acoes")))*INDEX(Inputs!$K$5:$AJ$130,0,MATCH(E$2,Inputs!$K$4:$AJ$4,0)))+SUMPRODUCT((Inputs!$C$5:$C$130=$B8)*Inputs!$D$5:$D$130*(((Inputs!$G$5:$G$130="moeda")+(Inputs!$G$5:$G$130="acoes"))*Inputs!$B$1+((Inputs!$G$5:$G$130<>"moeda")*(Inputs!$G$5:$G$130<>"acoes")))*INDEX(Inputs!$K$5:$AJ$130,0,MATCH(E$2,Inputs!$K$4:$AJ$4,0)))+SUMPRODUCT((Inputs!$E$5:$E$130=$B8)*Inputs!$F$5:$F$130*(((Inputs!$G$5:$G$130="moeda")+(Inputs!$G$5:$G$130="acoes"))*Inputs!$B$1+((Inputs!$G$5:$G$130<>"moeda")*(Inputs!$G$5:$G$130<>"acoes")))*INDEX(Inputs!$K$5:$AJ$130,0,MATCH(E$2,Inputs!$K$4:$AJ$4,0))))) -> -893 | F8: =IF(ISNA(MATCH(F$2,Inputs!$K$4:$AJ$4,0)),NA(),IF(SUMPRODUCT((Inputs!$A$5:$A$130=$B8)*ISNUMBER(INDEX(Inputs!$K$5:$AJ$130,0,MATCH(F$2,Inputs!$K$4:$AJ$4,0))))+SUMPRODUCT((Inputs!$C$5:$C$130=$B8)*ISNUMBER(INDEX(Inputs!$K$5:$AJ$130,0,MATCH(F$2,Inputs!$K$4:$AJ$4,0))))+SUMPRODUCT((Inputs!$E$5:$E$130=$B8)*ISNUMBER(INDEX(Inputs!$K$5:$AJ$130,0,MATCH(F$2,Inputs!$K$4:$AJ$4,0))))=0,NA(),SUMPRODUCT((Inputs!$A$5:$A$130=$B8)*Inputs!$B$5:$B$130*(((Inputs!$G$5:$G$130="moeda")+(Inputs!$G$5:$G$130="acoes"))*Inputs!$B$1+((Inputs!$G$5:$G$130<>"moeda")*(Inputs!$G$5:$G$130<>"acoes")))*INDEX(Inputs!$K$5:$AJ$130,0,MATCH(F$2,Inputs!$K$4:$AJ$4,0)))+SUMPRODUCT((Inputs!$C$5:$C$130=$B8)*Inputs!$D$5:$D$130*(((Inputs!$G$5:$G$130="moeda")+(Inputs!$G$5:$G$130="acoes"))*Inputs!$B$1+((Inputs!$G$5:$G$130<>"moeda")*(Inputs!$G$5:$G$130<>"acoes")))*INDEX(Inputs!$K$5:$AJ$130,0,MATCH(F$2,Inputs!$K$4:$AJ$4,0)))+SUMPRODUCT((Inputs!$E$5:$E$130=$B8)*Inputs!$F$5:$F$130*(((Inputs!$G$5:$G$130="moeda")+(Inputs!$G$5:$G$130="acoes"))*Inputs!$B$1+((Inputs!$G$5:$G$130<>"moeda")*(Inputs!$G$5:$G$130<>"acoes")))*INDEX(Inputs!$K$5:$AJ$130,0,MATCH(F$2,Inputs!$K$4:$AJ$4,0))))) -> -859 | G8: =IF(ISNA(MATCH(G$2,Inputs!$K$4:$AJ$4,0)),NA(),IF(SUMPRODUCT((Inputs!$A$5:$A$130=$B8)*ISNUMBER(INDEX(Inputs!$K$5:$AJ$130,0,MATCH(G$2,Inputs!$K$4:$AJ$4,0))))+SUMPRODUCT((Inputs!$C$5:$C$130=$B8)*ISNUMBER(INDEX(Inputs!$K$5:$AJ$130,0,MATCH(G$2,Inputs!$K$4:$AJ$4,0))))+SUMPRODUCT((Inputs!$E$5:$E$130=$B8)*ISNUMBER(INDEX(Inputs!$K$5:$AJ$130,0,MATCH(G$2,Inputs!$K$4:$AJ$4,0))))=0,NA(),SUMPRODUCT((Inputs!$A$5:$A$130=$B8)*Inputs!$B$5:$B$130*(((Inputs!$G$5:$G$130="moeda")+(Inputs!$G$5:$G$130="acoes"))*Inputs!$B$1+((Inputs!$G$5:$G$130<>"moeda")*(Inputs!$G$5:$G$130<>"acoes")))*INDEX(Inputs!$K$5:$AJ$130,0,MATCH(G$2,Inputs!$K$4:$AJ$4,0)))+SUMPRODUCT((Inputs!$C$5:$C$130=$B8)*Inputs!$D$5:$D$130*(((Inputs!$G$5:$G$130="moeda")+(Inputs!$G$5:$G$130="acoes"))*Inputs!$B$1+((Inputs!$G$5:$G$130<>"moeda")*(Inputs!$G$5:$G$130<>"acoes")))*INDEX(Inputs!$K$5:$AJ$130,0,MATCH(G$2,Inputs!$K$4:$AJ$4,0)))+SUMPRODUCT((Inputs!$E$5:$E$130=$B8)*Inputs!$F$5:$F$130*(((Inputs!$G$5:$G$130="moeda")+(Inputs!$G$5:$G$130="acoes"))*Inputs!$B$1+((Inputs!$G$5:$G$130<>"moeda")*(Inputs!$G$5:$G$130<>"acoes")))*INDEX(Inputs!$K$5:$AJ$130,0,MATCH(G$2,Inputs!$K$4:$AJ$4,0))))) -> -963 | H8: =SUM(D8:G8) -> -3607 | I8: =IF(ISNA(MATCH(I$2,Inputs!$K$4:$AJ$4,0)),NA(),IF(SUMPRODUCT((Inputs!$A$5:$A$130=$B8)*ISNUMBER(INDEX(Inputs!$K$5:$AJ$130,0,MATCH(I$2,Inputs!$K$4:$AJ$4,0))))+SUMPRODUCT((Inputs!$C$5:$C$130=$B8)*ISNUMBER(INDEX(Inputs!$K$5:$AJ$130,0,MATCH(I$2,Inputs!$K$4:$AJ$4,0))))+SUMPRODUCT((Inputs!$E$5:$E$130=$B8)*ISNUMBER(INDEX(Inputs!$K$5:$AJ$130,0,MATCH(I$2,Inputs!$K$4:$AJ$4,0))))=0,NA(),SUMPRODUCT((Inputs!$A$5:$A$130=$B8)*Inputs!$B$5:$B$130*(((Inputs!$G$5:$G$130="moeda")+(Inputs!$G$5:$G$130="acoes"))*Inputs!$B$1+((Inputs!$G$5:$G$130<>"moeda")*(Inputs!$G$5:$G$130<>"acoes")))*INDEX(Inputs!$K$5:$AJ$130,0,MATCH(I$2,Inputs!$K$4:$AJ$4,0)))+SUMPRODUCT((Inputs!$C$5:$C$130=$B8)*Inputs!$D$5:$D$130*(((Inputs!$G$5:$G$130="moeda")+(Inputs!$G$5:$G$130="acoes"))*Inputs!$B$1+((Inputs!$G$5:$G$130<>"moeda")*(Inputs!$G$5:$G$130<>"acoes")))*INDEX(Inputs!$K$5:$AJ$130,0,MATCH(I$2,Inputs!$K$4:$AJ$4,0)))+SUMPRODUCT((Inputs!$E$5:$E$130=$B8)*Inputs!$F$5:$F$130*(((Inputs!$G$5:$G$130="moeda")+(Inputs!$G$5:$G$130="acoes"))*Inputs!$B$1+((Inputs!$G$5:$G$130<>"moeda")*(Inputs!$G$5:$G$130<>"acoes")))*INDEX(Inputs!$K$5:$AJ$130,0,MATCH(I$2,Inputs!$K$4:$AJ$4,0))))) -> -711 | J8: =IF(ISNA(MATCH(J$2,Inputs!$K$4:$AJ$4,0)),NA(),IF(SUMPRODUCT((Inputs!$A$5:$A$130=$B8)*ISNUMBER(INDEX(Inputs!$K$5:$AJ$130,0,MATCH(J$2,Inputs!$K$4:$AJ$4,0))))+SUMPRODUCT((Inputs!$C$5:$C$130=$B8)*ISNUMBER(INDEX(Inputs!$K$5:$AJ$130,0,MATCH(J$2,Inputs!$K$4:$AJ$4,0))))+SUMPRODUCT((Inputs!$E$5:$E$130=$B8)*ISNUMBER(INDEX(Inputs!$K$5:$AJ$130,0,MATCH(J$2,Inputs!$K$4:$AJ$4,0))))=0,NA(),SUMPRODUCT((Inputs!$A$5:$A$130=$B8)*Inputs!$B$5:$B$130*(((Inputs!$G$5:$G$130="moeda")+(Inputs!$G$5:$G$130="acoes"))*Inputs!$B$1+((Inputs!$G$5:$G$130<>"moeda")*(Inputs!$G$5:$G$130<>"acoes")))*INDEX(Inputs!$K$5:$AJ$130,0,MATCH(J$2,Inputs!$K$4:$AJ$4,0)))+SUMPRODUCT((Inputs!$C$5:$C$130=$B8)*Inputs!$D$5:$D$130*(((Inputs!$G$5:$G$130="moeda")+(Inputs!$G$5:$G$130="acoes"))*Inputs!$B$1+((Inputs!$G$5:$G$130<>"moeda")*(Inputs!$G$5:$G$130<>"acoes")))*INDEX(Inputs!$K$5:$AJ$130,0,MATCH(J$2,Inputs!$K$4:$AJ$4,0)))+SUMPRODUCT((Inputs!$E$5:$E$130=$B8)*Inputs!$F$5:$F$130*(((Inputs!$G$5:$G$130="moeda")+(Inputs!$G$5:$G$130="acoes"))*Inputs!$B$1+((Inputs!$G$5:$G$130<>"moeda")*(Inputs!$G$5:$G$130<>"acoes")))*INDEX(Inputs!$K$5:$AJ$130,0,MATCH(J$2,Inputs!$K$4:$AJ$4,0))))) -> -695 | K8: =IF(ISNA(MATCH(K$2,Inputs!$K$4:$AJ$4,0)),NA(),IF(SUMPRODUCT((Inputs!$A$5:$A$130=$B8)*ISNUMBER(INDEX(Inputs!$K$5:$AJ$130,0,MATCH(K$2,Inputs!$K$4:$AJ$4,0))))+SUMPRODUCT((Inputs!$C$5:$C$130=$B8)*ISNUMBER(INDEX(Inputs!$K$5:$AJ$130,0,MATCH(K$2,Inputs!$K$4:$AJ$4,0))))+SUMPRODUCT((Inputs!$E$5:$E$130=$B8)*ISNUMBER(INDEX(Inputs!$K$5:$AJ$130,0,MATCH(K$2,Inputs!$K$4:$AJ$4,0))))=0,NA(),SUMPRODUCT((Inputs!$A$5:$A$130=$B8)*Inputs!$B$5:$B$130*(((Inputs!$G$5:$G$130="moeda")+(Inputs!$G$5:$G$130="acoes"))*Inputs!$B$1+((Inputs!$G$5:$G$130<>"moeda")*(Inputs!$G$5:$G$130<>"acoes")))*INDEX(Inputs!$K$5:$AJ$130,0,MATCH(K$2,Inputs!$K$4:$AJ$4,0)))+SUMPRODUCT((Inputs!$C$5:$C$130=$B8)*Inputs!$D$5:$D$130*(((Inputs!$G$5:$G$130="moeda")+(Inputs!$G$5:$G$130="acoes"))*Inputs!$B$1+((Inputs!$G$5:$G$130<>"moeda")*(Inputs!$G$5:$G$130<>"acoes")))*INDEX(Inputs!$K$5:$AJ$130,0,MATCH(K$2,Inputs!$K$4:$AJ$4,0)))+SUMPRODUCT((Inputs!$E$5:$E$130=$B8)*Inputs!$F$5:$F$130*(((Inputs!$G$5:$G$130="moeda")+(Inputs!$G$5:$G$130="acoes"))*Inputs!$B$1+((Inputs!$G$5:$G$130<>"moeda")*(Inputs!$G$5:$G$130<>"acoes")))*INDEX(Inputs!$K$5:$AJ$130,0,MATCH(K$2,Inputs!$K$4:$AJ$4,0))))) -> -734 | L8: =IF(ISNA(MATCH(L$2,Inputs!$K$4:$AJ$4,0)),NA(),IF(SUMPRODUCT((Inputs!$A$5:$A$130=$B8)*ISNUMBER(INDEX(Inputs!$K$5:$AJ$130,0,MATCH(L$2,Inputs!$K$4:$AJ$4,0))))+SUMPRODUCT((Inputs!$C$5:$C$130=$B8)*ISNUMBER(INDEX(Inputs!$K$5:$AJ$130,0,MATCH(L$2,Inputs!$K$4:$AJ$4,0))))+SUMPRODUCT((Inputs!$E$5:$E$130=$B8)*ISNUMBER(INDEX(Inputs!$K$5:$AJ$130,0,MATCH(L$2,Inputs!$K$4:$AJ$4,0))))=0,NA(),SUMPRODUCT((Inputs!$A$5:$A$130=$B8)*Inputs!$B$5:$B$130*(((Inputs!$G$5:$G$130="moeda")+(Inputs!$G$5:$G$130="acoes"))*Inputs!$B$1+((Inputs!$G$5:$G$130<>"moeda")*(Inputs!$G$5:$G$130<>"acoes")))*INDEX(Inputs!$K$5:$AJ$130,0,MATCH(L$2,Inputs!$K$4:$AJ$4,0)))+SUMPRODUCT((Inputs!$C$5:$C$130=$B8)*Inputs!$D$5:$D$130*(((Inputs!$G$5:$G$130="moeda")+(Inputs!$G$5:$G$130="acoes"))*Inputs!$B$1+((Inputs!$G$5:$G$130<>"moeda")*(Inputs!$G$5:$G$130<>"acoes")))*INDEX(Inputs!$K$5:$AJ$130,0,MATCH(L$2,Inputs!$K$4:$AJ$4,0)))+SUMPRODUCT((Inputs!$E$5:$E$130=$B8)*Inputs!$F$5:$F$130*(((Inputs!$G$5:$G$130="moeda")+(Inputs!$G$5:$G$130="acoes"))*Inputs!$B$1+((Inputs!$G$5:$G$130<>"moeda")*(Inputs!$G$5:$G$130<>"acoes")))*INDEX(Inputs!$K$5:$AJ$130,0,MATCH(L$2,Inputs!$K$4:$AJ$4,0))))) -> -1040 | M8: =SUM(I8:L8) -> -3180 | N8: =IF(ISNA(MATCH(N$2,Inputs!$K$4:$AJ$4,0)),NA(),IF(SUMPRODUCT((Inputs!$A$5:$A$130=$B8)*ISNUMBER(INDEX(Inputs!$K$5:$AJ$130,0,MATCH(N$2,Inputs!$K$4:$AJ$4,0))))+SUMPRODUCT((Inputs!$C$5:$C$130=$B8)*ISNUMBER(INDEX(Inputs!$K$5:$AJ$130,0,MATCH(N$2,Inputs!$K$4:$AJ$4,0))))+SUMPRODUCT((Inputs!$E$5:$E$130=$B8)*ISNUMBER(INDEX(Inputs!$K$5:$AJ$130,0,MATCH(N$2,Inputs!$K$4:$AJ$4,0))))=0,NA(),SUMPRODUCT((Inputs!$A$5:$A$130=$B8)*Inputs!$B$5:$B$130*(((Inputs!$G$5:$G$130="moeda")+(Inputs!$G$5:$G$130="acoes"))*Inputs!$B$1+((Inputs!$G$5:$G$130<>"moeda")*(Inputs!$G$5:$G$130<>"acoes")))*INDEX(Inputs!$K$5:$AJ$130,0,MATCH(N$2,Inputs!$K$4:$AJ$4,0)))+SUMPRODUCT((Inputs!$C$5:$C$130=$B8)*Inputs!$D$5:$D$130*(((Inputs!$G$5:$G$130="moeda")+(Inputs!$G$5:$G$130="acoes"))*Inputs!$B$1+((Inputs!$G$5:$G$130<>"moeda")*(Inputs!$G$5:$G$130<>"acoes")))*INDEX(Inputs!$K$5:$AJ$130,0,MATCH(N$2,Inputs!$K$4:$AJ$4,0)))+SUMPRODUCT((Inputs!$E$5:$E$130=$B8)*Inputs!$F$5:$F$130*(((Inputs!$G$5:$G$130="moeda")+(Inputs!$G$5:$G$130="acoes"))*Inputs!$B$1+((Inputs!$G$5:$G$130<>"moeda")*(Inputs!$G$5:$G$130<>"acoes")))*INDEX(Inputs!$K$5:$AJ$130,0,MATCH(N$2,Inputs!$K$4:$AJ$4,0))))) -> -1165 | O8: =IF(ISNA(MATCH(O$2,Inputs!$K$4:$AJ$4,0)),NA(),IF(SUMPRODUCT((Inputs!$A$5:$A$130=$B8)*ISNUMBER(INDEX(Inputs!$K$5:$AJ$130,0,MATCH(O$2,Inputs!$K$4:$AJ$4,0))))+SUMPRODUCT((Inputs!$C$5:$C$130=$B8)*ISNUMBER(INDEX(Inputs!$K$5:$AJ$130,0,MATCH(O$2,Inputs!$K$4:$AJ$4,0))))+SUMPRODUCT((Inputs!$E$5:$E$130=$B8)*ISNUMBER(INDEX(Inputs!$K$5:$AJ$130,0,MATCH(O$2,Inputs!$K$4:$AJ$4,0))))=0,NA(),SUMPRODUCT((Inputs!$A$5:$A$130=$B8)*Inputs!$B$5:$B$130*(((Inputs!$G$5:$G$130="moeda")+(Inputs!$G$5:$G$130="acoes"))*Inputs!$B$1+((Inputs!$G$5:$G$130<>"moeda")*(Inputs!$G$5:$G$130<>"acoes")))*INDEX(Inputs!$K$5:$AJ$130,0,MATCH(O$2,Inputs!$K$4:$AJ$4,0)))+SUMPRODUCT((Inputs!$C$5:$C$130=$B8)*Inputs!$D$5:$D$130*(((Inputs!$G$5:$G$130="moeda")+(Inputs!$G$5:$G$130="acoes"))*Inputs!$B$1+((Inputs!$G$5:$G$130<>"moeda")*(Inputs!$G$5:$G$130<>"acoes")))*INDEX(Inputs!$K$5:$AJ$130,0,MATCH(O$2,Inputs!$K$4:$AJ$4,0)))+SUMPRODUCT((Inputs!$E$5:$E$130=$B8)*Inputs!$F$5:$F$130*(((Inputs!$G$5:$G$130="moeda")+(Inputs!$G$5:$G$130="acoes"))*Inputs!$B$1+((Inputs!$G$5:$G$130<>"moeda")*(Inputs!$G$5:$G$130<>"acoes")))*INDEX(Inputs!$K$5:$AJ$130,0,MATCH(O$2,Inputs!$K$4:$AJ$4,0))))) -> -1211 | P8: =IF(ISNA(MATCH(P$2,Inputs!$K$4:$AJ$4,0)),NA(),IF(SUMPRODUCT((Inputs!$A$5:$A$130=$B8)*ISNUMBER(INDEX(Inputs!$K$5:$AJ$130,0,MATCH(P$2,Inputs!$K$4:$AJ$4,0))))+SUMPRODUCT((Inputs!$C$5:$C$130=$B8)*ISNUMBER(INDEX(Inputs!$K$5:$AJ$130,0,MATCH(P$2,Inputs!$K$4:$AJ$4,0))))+SUMPRODUCT((Inputs!$E$5:$E$130=$B8)*ISNUMBER(INDEX(Inputs!$K$5:$AJ$130,0,MATCH(P$2,Inputs!$K$4:$AJ$4,0))))=0,NA(),SUMPRODUCT((Inputs!$A$5:$A$130=$B8)*Inputs!$B$5:$B$130*(((Inputs!$G$5:$G$130="moeda")+(Inputs!$G$5:$G$130="acoes"))*Inputs!$B$1+((Inputs!$G$5:$G$130<>"moeda")*(Inputs!$G$5:$G$130<>"acoes")))*INDEX(Inputs!$K$5:$AJ$130,0,MATCH(P$2,Inputs!$K$4:$AJ$4,0)))+SUMPRODUCT((Inputs!$C$5:$C$130=$B8)*Inputs!$D$5:$D$130*(((Inputs!$G$5:$G$130="moeda")+(Inputs!$G$5:$G$130="acoes"))*Inputs!$B$1+((Inputs!$G$5:$G$130<>"moeda")*(Inputs!$G$5:$G$130<>"acoes")))*INDEX(Inputs!$K$5:$AJ$130,0,MATCH(P$2,Inputs!$K$4:$AJ$4,0)))+SUMPRODUCT((Inputs!$E$5:$E$130=$B8)*Inputs!$F$5:$F$130*(((Inputs!$G$5:$G$130="moeda")+(Inputs!$G$5:$G$130="acoes"))*Inputs!$B$1+((Inputs!$G$5:$G$130<>"moeda")*(Inputs!$G$5:$G$130<>"acoes")))*INDEX(Inputs!$K$5:$AJ$130,0,MATCH(P$2,Inputs!$K$4:$AJ$4,0))))) -> -1131 | Q8: =IF(ISNA(MATCH(Q$2,Inputs!$K$4:$AJ$4,0)),NA(),IF(SUMPRODUCT((Inputs!$A$5:$A$130=$B8)*ISNUMBER(INDEX(Inputs!$K$5:$AJ$130,0,MATCH(Q$2,Inputs!$K$4:$AJ$4,0))))+SUMPRODUCT((Inputs!$C$5:$C$130=$B8)*ISNUMBER(INDEX(Inputs!$K$5:$AJ$130,0,MATCH(Q$2,Inputs!$K$4:$AJ$4,0))))+SUMPRODUCT((Inputs!$E$5:$E$130=$B8)*ISNUMBER(INDEX(Inputs!$K$5:$AJ$130,0,MATCH(Q$2,Inputs!$K$4:$AJ$4,0))))=0,NA(),SUMPRODUCT((Inputs!$A$5:$A$130=$B8)*Inputs!$B$5:$B$130*(((Inputs!$G$5:$G$130="moeda")+(Inputs!$G$5:$G$130="acoes"))*Inputs!$B$1+((Inputs!$G$5:$G$130<>"moeda")*(Inputs!$G$5:$G$130<>"acoes")))*INDEX(Inputs!$K$5:$AJ$130,0,MATCH(Q$2,Inputs!$K$4:$AJ$4,0)))+SUMPRODUCT((Inputs!$C$5:$C$130=$B8)*Inputs!$D$5:$D$130*(((Inputs!$G$5:$G$130="moeda")+(Inputs!$G$5:$G$130="acoes"))*Inputs!$B$1+((Inputs!$G$5:$G$130<>"moeda")*(Inputs!$G$5:$G$130<>"acoes")))*INDEX(Inputs!$K$5:$AJ$130,0,MATCH(Q$2,Inputs!$K$4:$AJ$4,0)))+SUMPRODUCT((Inputs!$E$5:$E$130=$B8)*Inputs!$F$5:$F$130*(((Inputs!$G$5:$G$130="moeda")+(Inputs!$G$5:$G$130="acoes"))*Inputs!$B$1+((Inputs!$G$5:$G$130<>"moeda")*(Inputs!$G$5:$G$130<>"acoes")))*INDEX(Inputs!$K$5:$AJ$130,0,MATCH(Q$2,Inputs!$K$4:$AJ$4,0))))) -> -1166 | R8: =SUM(N8:Q8) -> -4673 | S8: =IF(ISNA(MATCH(S$2,Inputs!$K$4:$AJ$4,0)),NA(),IF(SUMPRODUCT((Inputs!$A$5:$A$130=$B8)*ISNUMBER(INDEX(Inputs!$K$5:$AJ$130,0,MATCH(S$2,Inputs!$K$4:$AJ$4,0))))+SUMPRODUCT((Inputs!$C$5:$C$130=$B8)*ISNUMBER(INDEX(Inputs!$K$5:$AJ$130,0,MATCH(S$2,Inputs!$K$4:$AJ$4,0))))+SUMPRODUCT((Inputs!$E$5:$E$130=$B8)*ISNUMBER(INDEX(Inputs!$K$5:$AJ$130,0,MATCH(S$2,Inputs!$K$4:$AJ$4,0))))=0,NA(),SUMPRODUCT((Inputs!$A$5:$A$130=$B8)*Inputs!$B$5:$B$130*(((Inputs!$G$5:$G$130="moeda")+(Inputs!$G$5:$G$130="acoes"))*Inputs!$B$1+((Inputs!$G$5:$G$130<>"moeda")*(Inputs!$G$5:$G$130<>"acoes")))*INDEX(Inputs!$K$5:$AJ$130,0,MATCH(S$2,Inputs!$K$4:$AJ$4,0)))+SUMPRODUCT((Inputs!$C$5:$C$130=$B8)*Inputs!$D$5:$D$130*(((Inputs!$G$5:$G$130="moeda")+(Inputs!$G$5:$G$130="acoes"))*Inputs!$B$1+((Inputs!$G$5:$G$130<>"moeda")*(Inputs!$G$5:$G$130<>"acoes")))*INDEX(Inputs!$K$5:$AJ$130,0,MATCH(S$2,Inputs!$K$4:$AJ$4,0)))+SUMPRODUCT((Inputs!$E$5:$E$130=$B8)*Inputs!$F$5:$F$130*(((Inputs!$G$5:$G$130="moeda")+(Inputs!$G$5:$G$130="acoes"))*Inputs!$B$1+((Inputs!$G$5:$G$130<>"moeda")*(Inputs!$G$5:$G$130<>"acoes")))*INDEX(Inputs!$K$5:$AJ$130,0,MATCH(S$2,Inputs!$K$4:$AJ$4,0))))) -> -1164 | T8: =IF(ISNA(MATCH(T$2,Inputs!$K$4:$AJ$4,0)),NA(),IF(SUMPRODUCT((Inputs!$A$5:$A$130=$B8)*ISNUMBER(INDEX(Inputs!$K$5:$AJ$130,0,MATCH(T$2,Inputs!$K$4:$AJ$4,0))))+SUMPRODUCT((Inputs!$C$5:$C$130=$B8)*ISNUMBER(INDEX(Inputs!$K$5:$AJ$130,0,MATCH(T$2,Inputs!$K$4:$AJ$4,0))))+SUMPRODUCT((Inputs!$E$5:$E$130=$B8)*ISNUMBER(INDEX(Inputs!$K$5:$AJ$130,0,MATCH(T$2,Inputs!$K$4:$AJ$4,0))))=0,NA(),SUMPRODUCT((Inputs!$A$5:$A$130=$B8)*Inputs!$B$5:$B$130*(((Inputs!$G$5:$G$130="moeda")+(Inputs!$G$5:$G$130="acoes"))*Inputs!$B$1+((Inputs!$G$5:$G$130<>"moeda")*(Inputs!$G$5:$G$130<>"acoes")))*INDEX(Inputs!$K$5:$AJ$130,0,MATCH(T$2,Inputs!$K$4:$AJ$4,0)))+SUMPRODUCT((Inputs!$C$5:$C$130=$B8)*Inputs!$D$5:$D$130*(((Inputs!$G$5:$G$130="moeda")+(Inputs!$G$5:$G$130="acoes"))*Inputs!$B$1+((Inputs!$G$5:$G$130<>"moeda")*(Inputs!$G$5:$G$130<>"acoes")))*INDEX(Inputs!$K$5:$AJ$130,0,MATCH(T$2,Inputs!$K$4:$AJ$4,0)))+SUMPRODUCT((Inputs!$E$5:$E$130=$B8)*Inputs!$F$5:$F$130*(((Inputs!$G$5:$G$130="moeda")+(Inputs!$G$5:$G$130="acoes"))*Inputs!$B$1+((Inputs!$G$5:$G$130<>"moeda")*(Inputs!$G$5:$G$130<>"acoes")))*INDEX(Inputs!$K$5:$AJ$130,0,MATCH(T$2,Inputs!$K$4:$AJ$4,0))))) -> -1235 | U8: =IF(ISNA(MATCH(U$2,Inputs!$K$4:$AJ$4,0)),NA(),IF(SUMPRODUCT((Inputs!$A$5:$A$130=$B8)*ISNUMBER(INDEX(Inputs!$K$5:$AJ$130,0,MATCH(U$2,Inputs!$K$4:$AJ$4,0))))+SUMPRODUCT((Inputs!$C$5:$C$130=$B8)*ISNUMBER(INDEX(Inputs!$K$5:$AJ$130,0,MATCH(U$2,Inputs!$K$4:$AJ$4,0))))+SUMPRODUCT((Inputs!$E$5:$E$130=$B8)*ISNUMBER(INDEX(Inputs!$K$5:$AJ$130,0,MATCH(U$2,Inputs!$K$4:$AJ$4,0))))=0,NA(),SUMPRODUCT((Inputs!$A$5:$A$130=$B8)*Inputs!$B$5:$B$130*(((Inputs!$G$5:$G$130="moeda")+(Inputs!$G$5:$G$130="acoes"))*Inputs!$B$1+((Inputs!$G$5:$G$130<>"moeda")*(Inputs!$G$5:$G$130<>"acoes")))*INDEX(Inputs!$K$5:$AJ$130,0,MATCH(U$2,Inputs!$K$4:$AJ$4,0)))+SUMPRODUCT((Inputs!$C$5:$C$130=$B8)*Inputs!$D$5:$D$130*(((Inputs!$G$5:$G$130="moeda")+(Inputs!$G$5:$G$130="acoes"))*Inputs!$B$1+((Inputs!$G$5:$G$130<>"moeda")*(Inputs!$G$5:$G$130<>"acoes")))*INDEX(Inputs!$K$5:$AJ$130,0,MATCH(U$2,Inputs!$K$4:$AJ$4,0)))+SUMPRODUCT((Inputs!$E$5:$E$130=$B8)*Inputs!$F$5:$F$130*(((Inputs!$G$5:$G$130="moeda")+(Inputs!$G$5:$G$130="acoes"))*Inputs!$B$1+((Inputs!$G$5:$G$130<>"moeda")*(Inputs!$G$5:$G$130<>"acoes")))*INDEX(Inputs!$K$5:$AJ$130,0,MATCH(U$2,Inputs!$K$4:$AJ$4,0))))) -> -1174 | V8: =IF(ISNA(MATCH(V$2,Inputs!$K$4:$AJ$4,0)),NA(),IF(SUMPRODUCT((Inputs!$A$5:$A$130=$B8)*ISNUMBER(INDEX(Inputs!$K$5:$AJ$130,0,MATCH(V$2,Inputs!$K$4:$AJ$4,0))))+SUMPRODUCT((Inputs!$C$5:$C$130=$B8)*ISNUMBER(INDEX(Inputs!$K$5:$AJ$130,0,MATCH(V$2,Inputs!$K$4:$AJ$4,0))))+SUMPRODUCT((Inputs!$E$5:$E$130=$B8)*ISNUMBER(INDEX(Inputs!$K$5:$AJ$130,0,MATCH(V$2,Inputs!$K$4:$AJ$4,0))))=0,NA(),SUMPRODUCT((Inputs!$A$5:$A$130=$B8)*Inputs!$B$5:$B$130*(((Inputs!$G$5:$G$130="moeda")+(Inputs!$G$5:$G$130="acoes"))*Inputs!$B$1+((Inputs!$G$5:$G$130<>"moeda")*(Inputs!$G$5:$G$130<>"acoes")))*INDEX(Inputs!$K$5:$AJ$130,0,MATCH(V$2,Inputs!$K$4:$AJ$4,0)))+SUMPRODUCT((Inputs!$C$5:$C$130=$B8)*Inputs!$D$5:$D$130*(((Inputs!$G$5:$G$130="moeda")+(Inputs!$G$5:$G$130="acoes"))*Inputs!$B$1+((Inputs!$G$5:$G$130<>"moeda")*(Inputs!$G$5:$G$130<>"acoes")))*INDEX(Inputs!$K$5:$AJ$130,0,MATCH(V$2,Inputs!$K$4:$AJ$4,0)))+SUMPRODUCT((Inputs!$E$5:$E$130=$B8)*Inputs!$F$5:$F$130*(((Inputs!$G$5:$G$130="moeda")+(Inputs!$G$5:$G$130="acoes"))*Inputs!$B$1+((Inputs!$G$5:$G$130<>"moeda")*(Inputs!$G$5:$G$130<>"acoes")))*INDEX(Inputs!$K$5:$AJ$130,0,MATCH(V$2,Inputs!$K$4:$AJ$4,0))))) -> -1213 | W8: =SUM(S8:V8) -> -4786 | X8: =IF(ISNA(MATCH(X$2,Inputs!$K$4:$AJ$4,0)),NA(),IF(SUMPRODUCT((Inputs!$A$5:$A$130=$B8)*ISNUMBER(INDEX(Inputs!$K$5:$AJ$130,0,MATCH(X$2,Inputs!$K$4:$AJ$4,0))))+SUMPRODUCT((Inputs!$C$5:$C$130=$B8)*ISNUMBER(INDEX(Inputs!$K$5:$AJ$130,0,MATCH(X$2,Inputs!$K$4:$AJ$4,0))))+SUMPRODUCT((Inputs!$E$5:$E$130=$B8)*ISNUMBER(INDEX(Inputs!$K$5:$AJ$130,0,MATCH(X$2,Inputs!$K$4:$AJ$4,0))))=0,NA(),SUMPRODUCT((Inputs!$A$5:$A$130=$B8)*Inputs!$B$5:$B$130*(((Inputs!$G$5:$G$130="moeda")+(Inputs!$G$5:$G$130="acoes"))*Inputs!$B$1+((Inputs!$G$5:$G$130<>"moeda")*(Inputs!$G$5:$G$130<>"acoes")))*INDEX(Inputs!$K$5:$AJ$130,0,MATCH(X$2,Inputs!$K$4:$AJ$4,0)))+SUMPRODUCT((Inputs!$C$5:$C$130=$B8)*Inputs!$D$5:$D$130*(((Inputs!$G$5:$G$130="moeda")+(Inputs!$G$5:$G$130="acoes"))*Inputs!$B$1+((Inputs!$G$5:$G$130<>"moeda")*(Inputs!$G$5:$G$130<>"acoes")))*INDEX(Inputs!$K$5:$AJ$130,0,MATCH(X$2,Inputs!$K$4:$AJ$4,0)))+SUMPRODUCT((Inputs!$E$5:$E$130=$B8)*Inputs!$F$5:$F$130*(((Inputs!$G$5:$G$130="moeda")+(Inputs!$G$5:$G$130="acoes"))*Inputs!$B$1+((Inputs!$G$5:$G$130<>"moeda")*(Inputs!$G$5:$G$130<>"acoes")))*INDEX(Inputs!$K$5:$AJ$130,0,MATCH(X$2,Inputs!$K$4:$AJ$4,0))))) -> -1120 | Y8: =IF(ISNA(MATCH(Y$2,Inputs!$K$4:$AJ$4,0)),NA(),IF(SUMPRODUCT((Inputs!$A$5:$A$130=$B8)*ISNUMBER(INDEX(Inputs!$K$5:$AJ$130,0,MATCH(Y$2,Inputs!$K$4:$AJ$4,0))))+SUMPRODUCT((Inputs!$C$5:$C$130=$B8)*ISNUMBER(INDEX(Inputs!$K$5:$AJ$130,0,MATCH(Y$2,Inputs!$K$4:$AJ$4,0))))+SUMPRODUCT((Inputs!$E$5:$E$130=$B8)*ISNUMBER(INDEX(Inputs!$K$5:$AJ$130,0,MATCH(Y$2,Inputs!$K$4:$AJ$4,0))))=0,NA(),SUMPRODUCT((Inputs!$A$5:$A$130=$B8)*Inputs!$B$5:$B$130*(((Inputs!$G$5:$G$130="moeda")+(Inputs!$G$5:$G$130="acoes"))*Inputs!$B$1+((Inputs!$G$5:$G$130<>"moeda")*(Inputs!$G$5:$G$130<>"acoes")))*INDEX(Inputs!$K$5:$AJ$130,0,MATCH(Y$2,Inputs!$K$4:$AJ$4,0)))+SUMPRODUCT((Inputs!$C$5:$C$130=$B8)*Inputs!$D$5:$D$130*(((Inputs!$G$5:$G$130="moeda")+(Inputs!$G$5:$G$130="acoes"))*Inputs!$B$1+((Inputs!$G$5:$G$130<>"moeda")*(Inputs!$G$5:$G$130<>"acoes")))*INDEX(Inputs!$K$5:$AJ$130,0,MATCH(Y$2,Inputs!$K$4:$AJ$4,0)))+SUMPRODUCT((Inputs!$E$5:$E$130=$B8)*Inputs!$F$5:$F$130*(((Inputs!$G$5:$G$130="moeda")+(Inputs!$G$5:$G$130="acoes"))*Inputs!$B$1+((Inputs!$G$5:$G$130<>"moeda")*(Inputs!$G$5:$G$130<>"acoes")))*INDEX(Inputs!$K$5:$AJ$130,0,MATCH(Y$2,Inputs!$K$4:$AJ$4,0))))) -> -1075 | Z8: =IF(ISNA(MATCH(Z$2,Inputs!$K$4:$AJ$4,0)),NA(),IF(SUMPRODUCT((Inputs!$A$5:$A$130=$B8)*ISNUMBER(INDEX(Inputs!$K$5:$AJ$130,0,MATCH(Z$2,Inputs!$K$4:$AJ$4,0))))+SUMPRODUCT((Inputs!$C$5:$C$130=$B8)*ISNUMBER(INDEX(Inputs!$K$5:$AJ$130,0,MATCH(Z$2,Inputs!$K$4:$AJ$4,0))))+SUMPRODUCT((Inputs!$E$5:$E$130=$B8)*ISNUMBER(INDEX(Inputs!$K$5:$AJ$130,0,MATCH(Z$2,Inputs!$K$4:$AJ$4,0))))=0,NA(),SUMPRODUCT((Inputs!$A$5:$A$130=$B8)*Inputs!$B$5:$B$130*(((Inputs!$G$5:$G$130="moeda")+(Inputs!$G$5:$G$130="acoes"))*Inputs!$B$1+((Inputs!$G$5:$G$130<>"moeda")*(Inputs!$G$5:$G$130<>"acoes")))*INDEX(Inputs!$K$5:$AJ$130,0,MATCH(Z$2,Inputs!$K$4:$AJ$4,0)))+SUMPRODUCT((Inputs!$C$5:$C$130=$B8)*Inputs!$D$5:$D$130*(((Inputs!$G$5:$G$130="moeda")+(Inputs!$G$5:$G$130="acoes"))*Inputs!$B$1+((Inputs!$G$5:$G$130<>"moeda")*(Inputs!$G$5:$G$130<>"acoes")))*INDEX(Inputs!$K$5:$AJ$130,0,MATCH(Z$2,Inputs!$K$4:$AJ$4,0)))+SUMPRODUCT((Inputs!$E$5:$E$130=$B8)*Inputs!$F$5:$F$130*(((Inputs!$G$5:$G$130="moeda")+(Inputs!$G$5:$G$130="acoes"))*Inputs!$B$1+((Inputs!$G$5:$G$130<>"moeda")*(Inputs!$G$5:$G$130<>"acoes")))*INDEX(Inputs!$K$5:$AJ$130,0,MATCH(Z$2,Inputs!$K$4:$AJ$4,0))))) -> -1284 | AA8: =IF(ISNA(MATCH(AA$2,Inputs!$K$4:$AJ$4,0)),NA(),IF(SUMPRODUCT((Inputs!$A$5:$A$130=$B8)*ISNUMBER(INDEX(Inputs!$K$5:$AJ$130,0,MATCH(AA$2,Inputs!$K$4:$AJ$4,0))))+SUMPRODUCT((Inputs!$C$5:$C$130=$B8)*ISNUMBER(INDEX(Inputs!$K$5:$AJ$130,0,MATCH(AA$2,Inputs!$K$4:$AJ$4,0))))+SUMPRODUCT((Inputs!$E$5:$E$130=$B8)*ISNUMBER(INDEX(Inputs!$K$5:$AJ$130,0,MATCH(AA$2,Inputs!$K$4:$AJ$4,0))))=0,NA(),SUMPRODUCT((Inputs!$A$5:$A$130=$B8)*Inputs!$B$5:$B$130*(((Inputs!$G$5:$G$130="moeda")+(Inputs!$G$5:$G$130="acoes"))*Inputs!$B$1+((Inputs!$G$5:$G$130<>"moeda")*(Inputs!$G$5:$G$130<>"acoes")))*INDEX(Inputs!$K$5:$AJ$130,0,MATCH(AA$2,Inputs!$K$4:$AJ$4,0)))+SUMPRODUCT((Inputs!$C$5:$C$130=$B8)*Inputs!$D$5:$D$130*(((Inputs!$G$5:$G$130="moeda")+(Inputs!$G$5:$G$130="acoes"))*Inputs!$B$1+((Inputs!$G$5:$G$130<>"moeda")*(Inputs!$G$5:$G$130<>"acoes")))*INDEX(Inputs!$K$5:$AJ$130,0,MATCH(AA$2,Inputs!$K$4:$AJ$4,0)))+SUMPRODUCT((Inputs!$E$5:$E$130=$B8)*Inputs!$F$5:$F$130*(((Inputs!$G$5:$G$130="moeda")+(Inputs!$G$5:$G$130="acoes"))*Inputs!$B$1+((Inputs!$G$5:$G$130<>"moeda")*(Inputs!$G$5:$G$130<>"acoes")))*INDEX(Inputs!$K$5:$AJ$130,0,MATCH(AA$2,Inputs!$K$4:$AJ$4,0))))) -> -1193 | AB8: =SUM(X8:AA8) -> -4672 | AC8: =IF(ISNA(MATCH(AC$2,Inputs!$K$4:$AJ$4,0)),NA(),IF(SUMPRODUCT((Inputs!$A$5:$A$130=$B8)*ISNUMBER(INDEX(Inputs!$K$5:$AJ$130,0,MATCH(AC$2,Inputs!$K$4:$AJ$4,0))))+SUMPRODUCT((Inputs!$C$5:$C$130=$B8)*ISNUMBER(INDEX(Inputs!$K$5:$AJ$130,0,MATCH(AC$2,Inputs!$K$4:$AJ$4,0))))+SUMPRODUCT((Inputs!$E$5:$E$130=$B8)*ISNUMBER(INDEX(Inputs!$K$5:$AJ$130,0,MATCH(AC$2,Inputs!$K$4:$AJ$4,0))))=0,NA(),SUMPRODUCT((Inputs!$A$5:$A$130=$B8)*Inputs!$B$5:$B$130*(((Inputs!$G$5:$G$130="moeda")+(Inputs!$G$5:$G$130="acoes"))*Inputs!$B$1+((Inputs!$G$5:$G$130<>"moeda")*(Inputs!$G$5:$G$130<>"acoes")))*INDEX(Inputs!$K$5:$AJ$130,0,MATCH(AC$2,Inputs!$K$4:$AJ$4,0)))+SUMPRODUCT((Inputs!$C$5:$C$130=$B8)*Inputs!$D$5:$D$130*(((Inputs!$G$5:$G$130="moeda")+(Inputs!$G$5:$G$130="acoes"))*Inputs!$B$1+((Inputs!$G$5:$G$130<>"moeda")*(Inputs!$G$5:$G$130<>"acoes")))*INDEX(Inputs!$K$5:$AJ$130,0,MATCH(AC$2,Inputs!$K$4:$AJ$4,0)))+SUMPRODUCT((Inputs!$E$5:$E$130=$B8)*Inputs!$F$5:$F$130*(((Inputs!$G$5:$G$130="moeda")+(Inputs!$G$5:$G$130="acoes"))*Inputs!$B$1+((Inputs!$G$5:$G$130<>"moeda")*(Inputs!$G$5:$G$130<>"acoes")))*INDEX(Inputs!$K$5:$AJ$130,0,MATCH(AC$2,Inputs!$K$4:$AJ$4,0))))) -> -1473 | AD8: =IF(ISNA(MATCH(AD$2,Inputs!$K$4:$AJ$4,0)),NA(),IF(SUMPRODUCT((Inputs!$A$5:$A$130=$B8)*ISNUMBER(INDEX(Inputs!$K$5:$AJ$130,0,MATCH(AD$2,Inputs!$K$4:$AJ$4,0))))+SUMPRODUCT((Inputs!$C$5:$C$130=$B8)*ISNUMBER(INDEX(Inputs!$K$5:$AJ$130,0,MATCH(AD$2,Inputs!$K$4:$AJ$4,0))))+SUMPRODUCT((Inputs!$E$5:$E$130=$B8)*ISNUMBER(INDEX(Inputs!$K$5:$AJ$130,0,MATCH(AD$2,Inputs!$K$4:$AJ$4,0))))=0,NA(),SUMPRODUCT((Inputs!$A$5:$A$130=$B8)*Inputs!$B$5:$B$130*(((Inputs!$G$5:$G$130="moeda")+(Inputs!$G$5:$G$130="acoes"))*Inputs!$B$1+((Inputs!$G$5:$G$130<>"moeda")*(Inputs!$G$5:$G$130<>"acoes")))*INDEX(Inputs!$K$5:$AJ$130,0,MATCH(AD$2,Inputs!$K$4:$AJ$4,0)))+SUMPRODUCT((Inputs!$C$5:$C$130=$B8)*Inputs!$D$5:$D$130*(((Inputs!$G$5:$G$130="moeda")+(Inputs!$G$5:$G$130="acoes"))*Inputs!$B$1+((Inputs!$G$5:$G$130<>"moeda")*(Inputs!$G$5:$G$130<>"acoes")))*INDEX(Inputs!$K$5:$AJ$130,0,MATCH(AD$2,Inputs!$K$4:$AJ$4,0)))+SUMPRODUCT((Inputs!$E$5:$E$130=$B8)*Inputs!$F$5:$F$130*(((Inputs!$G$5:$G$130="moeda")+(Inputs!$G$5:$G$130="acoes"))*Inputs!$B$1+((Inputs!$G$5:$G$130<>"moeda")*(Inputs!$G$5:$G$130<>"acoes")))*INDEX(Inputs!$K$5:$AJ$130,0,MATCH(AD$2,Inputs!$K$4:$AJ$4,0))))) -> -1114 | AE8: =IF(ISNA(MATCH(AE$2,Inputs!$K$4:$AJ$4,0)),NA(),IF(SUMPRODUCT((Inputs!$A$5:$A$130=$B8)*ISNUMBER(INDEX(Inputs!$K$5:$AJ$130,0,MATCH(AE$2,Inputs!$K$4:$AJ$4,0))))+SUMPRODUCT((Inputs!$C$5:$C$130=$B8)*ISNUMBER(INDEX(Inputs!$K$5:$AJ$130,0,MATCH(AE$2,Inputs!$K$4:$AJ$4,0))))+SUMPRODUCT((Inputs!$E$5:$E$130=$B8)*ISNUMBER(INDEX(Inputs!$K$5:$AJ$130,0,MATCH(AE$2,Inputs!$K$4:$AJ$4,0))))=0,NA(),SUMPRODUCT((Inputs!$A$5:$A$130=$B8)*Inputs!$B$5:$B$130*(((Inputs!$G$5:$G$130="moeda")+(Inputs!$G$5:$G$130="acoes"))*Inputs!$B$1+((Inputs!$G$5:$G$130<>"moeda")*(Inputs!$G$5:$G$130<>"acoes")))*INDEX(Inputs!$K$5:$AJ$130,0,MATCH(AE$2,Inputs!$K$4:$AJ$4,0)))+SUMPRODUCT((Inputs!$C$5:$C$130=$B8)*Inputs!$D$5:$D$130*(((Inputs!$G$5:$G$130="moeda")+(Inputs!$G$5:$G$130="acoes"))*Inputs!$B$1+((Inputs!$G$5:$G$130<>"moeda")*(Inputs!$G$5:$G$130<>"acoes")))*INDEX(Inputs!$K$5:$AJ$130,0,MATCH(AE$2,Inputs!$K$4:$AJ$4,0)))+SUMPRODUCT((Inputs!$E$5:$E$130=$B8)*Inputs!$F$5:$F$130*(((Inputs!$G$5:$G$130="moeda")+(Inputs!$G$5:$G$130="acoes"))*Inputs!$B$1+((Inputs!$G$5:$G$130<>"moeda")*(Inputs!$G$5:$G$130<>"acoes")))*INDEX(Inputs!$K$5:$AJ$130,0,MATCH(AE$2,Inputs!$K$4:$AJ$4,0))))) -> #N/A | AF8: =IF(ISNA(MATCH(AF$2,Inputs!$K$4:$AJ$4,0)),NA(),IF(SUMPRODUCT((Inputs!$A$5:$A$130=$B8)*ISNUMBER(INDEX(Inputs!$K$5:$AJ$130,0,MATCH(AF$2,Inputs!$K$4:$AJ$4,0))))+SUMPRODUCT((Inputs!$C$5:$C$130=$B8)*ISNUMBER(INDEX(Inputs!$K$5:$AJ$130,0,MATCH(AF$2,Inputs!$K$4:$AJ$4,0))))+SUMPRODUCT((Inputs!$E$5:$E$130=$B8)*ISNUMBER(INDEX(Inputs!$K$5:$AJ$130,0,MATCH(AF$2,Inputs!$K$4:$AJ$4,0))))=0,NA(),SUMPRODUCT((Inputs!$A$5:$A$130=$B8)*Inputs!$B$5:$B$130*(((Inputs!$G$5:$G$130="moeda")+(Inputs!$G$5:$G$130="acoes"))*Inputs!$B$1+((Inputs!$G$5:$G$130<>"moeda")*(Inputs!$G$5:$G$130<>"acoes")))*INDEX(Inputs!$K$5:$AJ$130,0,MATCH(AF$2,Inputs!$K$4:$AJ$4,0)))+SUMPRODUCT((Inputs!$C$5:$C$130=$B8)*Inputs!$D$5:$D$130*(((Inputs!$G$5:$G$130="moeda")+(Inputs!$G$5:$G$130="acoes"))*Inputs!$B$1+((Inputs!$G$5:$G$130<>"moeda")*(Inputs!$G$5:$G$130<>"acoes")))*INDEX(Inputs!$K$5:$AJ$130,0,MATCH(AF$2,Inputs!$K$4:$AJ$4,0)))+SUMPRODUCT((Inputs!$E$5:$E$130=$B8)*Inputs!$F$5:$F$130*(((Inputs!$G$5:$G$130="moeda")+(Inputs!$G$5:$G$130="acoes"))*Inputs!$B$1+((Inputs!$G$5:$G$130<>"moeda")*(Inputs!$G$5:$G$130<>"acoes")))*INDEX(Inputs!$K$5:$AJ$130,0,MATCH(AF$2,Inputs!$K$4:$AJ$4,0))))) -> #N/A | AG8: =SUM(AC8:AF8) -> #N/A | AH8: =IF(ISNA(MATCH(AH$2,Inputs!$K$4:$AJ$4,0)),NA(),IF(SUMPRODUCT((Inputs!$A$5:$A$130=$B8)*ISNUMBER(INDEX(Inputs!$K$5:$AJ$130,0,MATCH(AH$2,Inputs!$K$4:$AJ$4,0))))+SUMPRODUCT((Inputs!$C$5:$C$130=$B8)*ISNUMBER(INDEX(Inputs!$K$5:$AJ$130,0,MATCH(AH$2,Inputs!$K$4:$AJ$4,0))))+SUMPRODUCT((Inputs!$E$5:$E$130=$B8)*ISNUMBER(INDEX(Inputs!$K$5:$AJ$130,0,MATCH(AH$2,Inputs!$K$4:$AJ$4,0))))=0,NA(),SUMPRODUCT((Inputs!$A$5:$A$130=$B8)*Inputs!$B$5:$B$130*(((Inputs!$G$5:$G$130="moeda")+(Inputs!$G$5:$G$130="acoes"))*Inputs!$B$1+((Inputs!$G$5:$G$130<>"moeda")*(Inputs!$G$5:$G$130<>"acoes")))*INDEX(Inputs!$K$5:$AJ$130,0,MATCH(AH$2,Inputs!$K$4:$AJ$4,0)))+SUMPRODUCT((Inputs!$C$5:$C$130=$B8)*Inputs!$D$5:$D$130*(((Inputs!$G$5:$G$130="moeda")+(Inputs!$G$5:$G$130="acoes"))*Inputs!$B$1+((Inputs!$G$5:$G$130<>"moeda")*(Inputs!$G$5:$G$130<>"acoes")))*INDEX(Inputs!$K$5:$AJ$130,0,MATCH(AH$2,Inputs!$K$4:$AJ$4,0)))+SUMPRODUCT((Inputs!$E$5:$E$130=$B8)*Inputs!$F$5:$F$130*(((Inputs!$G$5:$G$130="moeda")+(Inputs!$G$5:$G$130="acoes"))*Inputs!$B$1+((Inputs!$G$5:$G$130<>"moeda")*(Inputs!$G$5:$G$130<>"acoes")))*INDEX(Inputs!$K$5:$AJ$130,0,MATCH(AH$2,Inputs!$K$4:$AJ$4,0))))) -> #N/A | AI8: =IF(ISNA(MATCH(AI$2,Inputs!$K$4:$AJ$4,0)),NA(),IF(SUMPRODUCT((Inputs!$A$5:$A$130=$B8)*ISNUMBER(INDEX(Inputs!$K$5:$AJ$130,0,MATCH(AI$2,Inputs!$K$4:$AJ$4,0))))+SUMPRODUCT((Inputs!$C$5:$C$130=$B8)*ISNUMBER(INDEX(Inputs!$K$5:$AJ$130,0,MATCH(AI$2,Inputs!$K$4:$AJ$4,0))))+SUMPRODUCT((Inputs!$E$5:$E$130=$B8)*ISNUMBER(INDEX(Inputs!$K$5:$AJ$130,0,MATCH(AI$2,Inputs!$K$4:$AJ$4,0))))=0,NA(),SUMPRODUCT((Inputs!$A$5:$A$130=$B8)*Inputs!$B$5:$B$130*(((Inputs!$G$5:$G$130="moeda")+(Inputs!$G$5:$G$130="acoes"))*Inputs!$B$1+((Inputs!$G$5:$G$130<>"moeda")*(Inputs!$G$5:$G$130<>"acoes")))*INDEX(Inputs!$K$5:$AJ$130,0,MATCH(AI$2,Inputs!$K$4:$AJ$4,0)))+SUMPRODUCT((Inputs!$C$5:$C$130=$B8)*Inputs!$D$5:$D$130*(((Inputs!$G$5:$G$130="moeda")+(Inputs!$G$5:$G$130="acoes"))*Inputs!$B$1+((Inputs!$G$5:$G$130<>"moeda")*(Inputs!$G$5:$G$130<>"acoes")))*INDEX(Inputs!$K$5:$AJ$130,0,MATCH(AI$2,Inputs!$K$4:$AJ$4,0)))+SUMPRODUCT((Inputs!$E$5:$E$130=$B8)*Inputs!$F$5:$F$130*(((Inputs!$G$5:$G$130="moeda")+(Inputs!$G$5:$G$130="acoes"))*Inputs!$B$1+((Inputs!$G$5:$G$130<>"moeda")*(Inputs!$G$5:$G$130<>"acoes")))*INDEX(Inputs!$K$5:$AJ$130,0,MATCH(AI$2,Inputs!$K$4:$AJ$4,0))))) -> #N/A | AJ8: =IF(ISNA(MATCH(AJ$2,Inputs!$K$4:$AJ$4,0)),NA(),IF(SUMPRODUCT((Inputs!$A$5:$A$130=$B8)*ISNUMBER(INDEX(Inputs!$K$5:$AJ$130,0,MATCH(AJ$2,Inputs!$K$4:$AJ$4,0))))+SUMPRODUCT((Inputs!$C$5:$C$130=$B8)*ISNUMBER(INDEX(Inputs!$K$5:$AJ$130,0,MATCH(AJ$2,Inputs!$K$4:$AJ$4,0))))+SUMPRODUCT((Inputs!$E$5:$E$130=$B8)*ISNUMBER(INDEX(Inputs!$K$5:$AJ$130,0,MATCH(AJ$2,Inputs!$K$4:$AJ$4,0))))=0,NA(),SUMPRODUCT((Inputs!$A$5:$A$130=$B8)*Inputs!$B$5:$B$130*(((Inputs!$G$5:$G$130="moeda")+(Inputs!$G$5:$G$130="acoes"))*Inputs!$B$1+((Inputs!$G$5:$G$130<>"moeda")*(Inputs!$G$5:$G$130<>"acoes")))*INDEX(Inputs!$K$5:$AJ$130,0,MATCH(AJ$2,Inputs!$K$4:$AJ$4,0)))+SUMPRODUCT((Inputs!$C$5:$C$130=$B8)*Inputs!$D$5:$D$130*(((Inputs!$G$5:$G$130="moeda")+(Inputs!$G$5:$G$130="acoes"))*Inputs!$B$1+((Inputs!$G$5:$G$130<>"moeda")*(Inputs!$G$5:$G$130<>"acoes")))*INDEX(Inputs!$K$5:$AJ$130,0,MATCH(AJ$2,Inputs!$K$4:$AJ$4,0)))+SUMPRODUCT((Inputs!$E$5:$E$130=$B8)*Inputs!$F$5:$F$130*(((Inputs!$G$5:$G$130="moeda")+(Inputs!$G$5:$G$130="acoes"))*Inputs!$B$1+((Inputs!$G$5:$G$130<>"moeda")*(Inputs!$G$5:$G$130<>"acoes")))*INDEX(Inputs!$K$5:$AJ$130,0,MATCH(AJ$2,Inputs!$K$4:$AJ$4,0))))) -> #N/A | AK8: =IF(ISNA(MATCH(AK$2,Inputs!$K$4:$AJ$4,0)),NA(),IF(SUMPRODUCT((Inputs!$A$5:$A$130=$B8)*ISNUMBER(INDEX(Inputs!$K$5:$AJ$130,0,MATCH(AK$2,Inputs!$K$4:$AJ$4,0))))+SUMPRODUCT((Inputs!$C$5:$C$130=$B8)*ISNUMBER(INDEX(Inputs!$K$5:$AJ$130,0,MATCH(AK$2,Inputs!$K$4:$AJ$4,0))))+SUMPRODUCT((Inputs!$E$5:$E$130=$B8)*ISNUMBER(INDEX(Inputs!$K$5:$AJ$130,0,MATCH(AK$2,Inputs!$K$4:$AJ$4,0))))=0,NA(),SUMPRODUCT((Inputs!$A$5:$A$130=$B8)*Inputs!$B$5:$B$130*(((Inputs!$G$5:$G$130="moeda")+(Inputs!$G$5:$G$130="acoes"))*Inputs!$B$1+((Inputs!$G$5:$G$130<>"moeda")*(Inputs!$G$5:$G$130<>"acoes")))*INDEX(Inputs!$K$5:$AJ$130,0,MATCH(AK$2,Inputs!$K$4:$AJ$4,0)))+SUMPRODUCT((Inputs!$C$5:$C$130=$B8)*Inputs!$D$5:$D$130*(((Inputs!$G$5:$G$130="moeda")+(Inputs!$G$5:$G$130="acoes"))*Inputs!$B$1+((Inputs!$G$5:$G$130<>"moeda")*(Inputs!$G$5:$G$130<>"acoes")))*INDEX(Inputs!$K$5:$AJ$130,0,MATCH(AK$2,Inputs!$K$4:$AJ$4,0)))+SUMPRODUCT((Inputs!$E$5:$E$130=$B8)*Inputs!$F$5:$F$130*(((Inputs!$G$5:$G$130="moeda")+(Inputs!$G$5:$G$130="acoes"))*Inputs!$B$1+((Inputs!$G$5:$G$130<>"moeda")*(Inputs!$G$5:$G$130<>"acoes")))*INDEX(Inputs!$K$5:$AJ$130,0,MATCH(AK$2,Inputs!$K$4:$AJ$4,0))))) -> #N/A | AL8: =SUM(AH8:AK8) -> #N/A
