Workbook
Name beta_observed: Valuation!$D$93
Name beta_observed_unlevered: #REF!
Name beta_unlev_comps: #REF!
Name cirkbreak: #REF!
Name costdebtfirm: #REF!
Name costequity: #REF!
Name Debt: #REF!
Name debt_weight: #REF!
Name last_close: Valuation!$G$7
Name Market_Equity: #REF!
Name midyear: #REF!
Name Net_Debt: #REF!
Name range: #REF!
Name Stub_year_fraction: #REF!
Name ticker: Valuation!$D$7
Name Useful_Life_of_Depreciable_PP_E: "PPElife"
Name beta_observed: #REF!
Name ticker: #REF!
Name costdebtfirm: Valuation!$D$86
Name costequity: Valuation!$D$94
Name debt: Valuation!$G$88
Name debt_weight: Valuation!$J$88
Name g: Valuation!$D$63
Name market_equity: Valuation!$G$89
Name noplat_t1: Valuation!$D$65
Name relevered_beta: Valuation!$M$102
Name risk_free_rate: Valuation!$D$91
Name risk_premium: Valuation!$D$92
Name ronic: Valuation!$D$64
Name stub_year_fraction: Valuation!$D$11
Name totalcap: Valuation!$G$90
Name wacc: Valuation!$D$12
Name scenario: Valuation!$E$8

Sheet Inputs
A1: Fator p/ milhões: | B1: 0.001 | D1: Cury Construtora (CURY3) - fonte: Planilha Fundamentos do RI (abas Resultados Operacionais, Demonstracoes do Resultado, BP Ativo, BP Passivo, Fluxo de Caixa). Moeda: BRL. Brutos em R$ mil. Consolidado. DRE e DFC trimestrais isolados (soma = ano, conferido).
J2: Trimestre na fonte | K2: 1T20 | L2: 2T20 | M2: 3T20 | N2: 4T20 | O2: 1T21 | P2: 2T21 | Q2: 3T21 | R2: 4T21 | S2: 1T22 | T2: 2T22 | U2: 3T22 | V2: 4T22 | W2: 1T23 | X2: 2T23 | Y2: 3T23 | Z2: 4T23 | AA2: 1T24 | AB2: 2T24 | AC2: 3T24 | AD2: 4T24 | AE2: 1T25 | AF2: 2T25 | AG2: 3T25 | AH2: 4T25 | AI2: 1T26 | AJ2: 2T26
A4: COD1 | B4: SINAL1 | C4: COD2 | D4: SINAL2 | E4: COD3 | F4: SINAL3 | G4: UNID | H4: Conta (PT) / origem | I4: Account (EN) | J4: ORIGEM | K4: 1Q20 | L4: 2Q20 | M4: 3Q20 | N4: 4Q20 | O4: 1Q21 | P4: 2Q21 | Q4: 3Q21 | R4: 4Q21 | S4: 1Q22 | T4: 2Q22 | U4: 3Q22 | V4: 4Q22 | W4: 1Q23 | X4: 2Q23 | Y4: 3Q23 | Z4: 4Q23 | AA4: 1Q24 | AB4: 2Q24 | AC4: 3Q24 | AD4: 4Q24 | AE4: 1Q25 | AF4: 2Q25 | AG4: 3Q25 | AH4: 4Q25 | AI4: 1Q26 | AJ4: 2Q26
H5: DRE - TRIMESTRE ISOLADO (aba Demonstracoes do Resultado; R$ mil)
A6: 1 | B6: 1 | G6: moeda | H6: Receita liquida (DRE l.4) | J6: fonte | K6: 227321 | L6: 246204 | M6: 325898 | N6: 345259 | O6: 339286 | P6: 451337 | Q6: 456449.58 | R6: 491223 | S6: 447374 | T6: 602783 | U6: 626659 | V6: 580478 | W6: 594956 | X6: 727746 | Y6: 751874 | Z6: 811596 | AA6: 837382 | AB6: 998085 | AC6: 1055872 | AD6: 1034971 | AE6: 1216184 | AF6: 1346599 | AG6: 1416926 | AH6: 1419715 | AI6: 1612571 | AJ6: 1690594
A7: 2 | B7: 1 | G7: moeda | H7: Custo das vendas e servicos (DRE l.5; inclui juros capitalizados apropriados ao custo) | J7: fonte | K7: -149181 | L7: -159137 | M7: -202541 | N7: -205433 | O7: -218944 | P7: -288421 | Q7: -281477.74 | R7: -304781 | S7: -281465 | T7: -387286 | U7: -392916 | V7: -358735 | W7: -371794 | X7: -453192 | Y7: -467971 | Z7: -497862 | AA7: -520773 | AB7: -615554 | AC7: -646426 | AD7: -630617 | AE7: -741296 | AF7: -813823 | AG7: -850699 | AH7: -847019 | AI7: -982915 | AJ7: -1022232
A8: 3 | B8: 1 | G8: moeda | H8: Despesas com vendas (DRE l.10; inclui depreciacao de estandes, devolvida abaixo) | J8: fonte | K8: -22046 | L8: -26343 | M8: -27428 | N8: -26987 | O8: -30360 | P8: -38953 | Q8: -47900 | R8: -46959 | S8: -44417 | T8: -53835 | U8: -59384 | V8: -54552 | W8: -62031 | X8: -66728 | Y8: -80995 | Z8: -75476 | AA8: -76092 | AB8: -97945.737 | AC8: -113852 | AD8: -103983 | AE8: -106236 | AF8: -124746.99 | AG8: -134823 | AH8: -129085 | AI8: -119070 | AJ8: -166790
A9: 3 | B9: 1 | G9: moeda | H9: Despesas gerais e administrativas (DRE l.11) | J9: fonte | K9: -28376 | L9: -14508 | M9: -25631 | N9: -28377 | O9: -20615 | P9: -24043 | Q9: -31170 | R9: -26689 | S9: -22810 | T9: -34143 | U9: -49409 | V9: -30206 | W9: -33375 | X9: -42088 | Y9: -54245 | Z9: -36075 | AA9: -41298 | AB9: -62203 | AC9: -68034 | AD9: -52894 | AE9: -50355 | AF9: -64401.683 | AG9: -66007 | AH9: -58575 | AI9: -64932 | AJ9: -78364
A10: 3 | B10: 1 | G10: moeda | H10: Outros resultados operacionais (DRE l.12) | J10: fonte | K10: -3179 | L10: 2365 | M10: -3304 | N10: -1914 | O10: -6524 | P10: -10905 | Q10: -8910 | R10: 23796 | S10: -19298 | T10: -15382 | U10: -11456 | V10: -12938 | W10: -12810 | X10: -18568 | Y10: -12803 | Z10: -19866 | AA10: -21345 | AB10: -23250 | AC10: -19747 | AD10: -21156 | AE10: -39738 | AF10: -30493.826 | AG10: -39204 | AH10: -42251 | AI10: -44791 | AJ10: -45797
A11: 8 | B11: 1 | G11: moeda | H11: Equivalencia patrimonial (DRE l.14) | J11: fonte | K11: 791 | L11: 195 | M11: 336 | N11: 1038 | O11: 1138 | P11: 1726 | Q11: -950 | R11: -991 | S11: -311 | T11: -141 | U11: 976 | V11: -145 | W11: -110 | X11: 696 | Y11: -295 | Z11: 1356 | AA11: 1299 | AB11: 2807 | AC11: 3389 | AD11: 1044 | AE11: 688 | AF11: 1091.0762 | AG11: 2474 | AH11: 3137 | AI11: 2282 | AJ11: 1014
A12: 5 | B12: 1 | G12: moeda | H12: Despesas financeiras (DRE l.18) | J12: fonte | K12: -4959 | L12: -5719 | M12: -6639 | N12: -6166 | O12: -7256 | P12: -9300 | Q12: -11430 | R12: -21731 | S12: -17062 | T12: -22214 | U12: -22860 | V12: -26332 | W12: -25672 | X12: -26026 | Y12: -23214 | Z12: -25215 | AA12: -24806 | AB12: -31099 | AC12: -39673 | AD12: -41587 | AE12: -51332 | AF12: -50846.244 | AG12: -56062 | AH12: -59596 | AI12: -59802 | AJ12: -70288
A13: 6 | B13: 1 | G13: moeda | H13: Receitas financeiras (DRE l.19) | J13: fonte | K13: 2784 | L13: 2827 | M13: 5428 | N13: 3634 | O13: 2222 | P13: 3924 | Q13: 10360 | R13: 8485 | S13: 12977 | T13: 17605 | U13: 18795 | V13: 14654 | W13: 20228 | X13: 20425 | Y13: 19668 | Z13: 25895 | AA13: 19889 | AB13: 25350 | AC13: 32060 | AD13: 28782 | AE13: 36752 | AF13: 35218.012 | AG13: 47368 | AH13: 50684 | AI13: 49093 | AJ13: 48168
A14: 7 | B14: 1 | G14: moeda | H14: IR e CS diferido (DRE l.23) | J14: fonte | K14: -666 | L14: 186 | M14: -1002 | N14: -82 | O14: -1492 | P14: -2193 | Q14: -842 | R14: 89 | S14: -2130 | T14: -2124 | U14: -1635 | V14: 81 | W14: -1627 | X14: -2289 | Y14: -800 | Z14: 133 | AA14: -2957 | AB14: -951 | AC14: -1562 | AD14: 2237 | AE14: -8693 | AF14: -2894 | AG14: 260 | AH14: 136 | AI14: -4003 | AJ14: -3011
A15: 7 | B15: 1 | G15: moeda | H15: IR e CS corrente (DRE l.24) | J15: fonte | K15: -7071 | L15: -5058 | M15: -5901 | N15: -6620 | O15: -5387 | P15: -6221 | Q15: -9490 | R15: -10799 | S15: -9507 | T15: -12324 | U15: -13899 | V15: -15026 | W15: -13709 | X15: -15906 | Y15: -18328 | Z15: -19892 | AA15: -17229 | AB15: -19957 | AC15: -21440 | AD15: -27925 | AE15: -22310 | AF15: -28545 | AG15: -37023 | AH15: -39957 | AI15: -37247 | AJ15: -42103
G16: moeda | H16: Lucro liquido do exercicio - 100% (DRE l.26) - memoria | J16: memoria | K16: 15418 | L16: 41012 | M16: 59216 | N16: 74352 | O16: 52068 | P16: 76951 | Q16: 74639.49 | R16: 111644 | S16: 63351 | T16: 92939 | U16: 94871 | V16: 97279 | W16: 94056 | X16: 124070 | Y16: 112891 | Z16: 164594 | AA16: 154070 | AB16: 175282 | AC16: 180588 | AD16: 188872 | AE16: 233664 | AF16: 267157 | AG16: 283210 | AH16: 297189 | AI16: 351186 | AJ16: 311191
A17: 9 | B17: -1 | G17: moeda | H17: Parcela do lucro atribuida aos nao controladores (DRE l.29; positiva na fonte -> COD 9 com sinal -1) | J17: fonte | K17: 8918 | L17: 4023 | M17: 9861 | N17: 6384 | O17: 2075 | P17: -1652 | Q17: 7241.7259 | R17: 7891 | S17: 1448 | T17: 6614 | U17: 4999 | V17: 5494 | W17: 2207 | X17: 2697 | Y17: 4671 | Z17: 4271 | AA17: 12829 | AB17: 3035 | AC17: 10017 | AD17: 23088 | AE17: 20189 | AF17: 30426.4 | AG17: 27957 | AH17: 27112 | AI17: 48319 | AJ17: 40740
A18: 44 | B18: 1 | G18: moeda | H18: Lucro liquido atribuido aos acionistas da controladora - %Cury (DRE l.30). COD 44 alimenta o check IS do Model (linha 4) | J18: fonte | K18: 6500 | L18: 36989 | M18: 49355 | N18: 67968 | O18: 49993 | P18: 78603 | Q18: 67397.764 | R18: 103753 | S18: 61903 | T18: 86325 | U18: 89872 | V18: 91785 | W18: 91849 | X18: 121373 | Y18: 108220 | Z18: 160323 | AA18: 141241 | AB18: 172247 | AC18: 170571 | AD18: 165784 | AE18: 213475 | AF18: 236730.6 | AG18: 255253 | AH18: 270077 | AI18: 302867 | AJ18: 270451
G19: moeda | H19: EBIT - lucro antes do resultado financeiro (DRE l.16) - memoria | J19: memoria | K19: 25330 | L19: 48776 | M19: 67330 | N19: 83586 | O19: 63981 | P19: 90741 | Q19: 86041.841 | R19: 135600 | S19: 79073 | T19: 111996 | U19: 114470 | V19: 123902 | W19: 114836 | X19: 147866 | Y19: 135565 | Z19: 183673 | AA19: 179173 | AB19: 201938.5 | AC19: 211203 | AD19: 227365 | AE19: 279247 | AF19: 314224 | AG19: 328667 | AH19: 345922 | AI19: 403145 | AJ19: 378425
G20: moeda | H20: EBITDA (DRE l.34, como divulgado) - memoria | J20: memoria | K20: 28255 | L20: 49083 | M20: 67695 | N20: 83849.71 | O20: 64315.653 | P20: 91096.058 | Q20: 86417.801 | R20: 135977.74 | S20: 79997.387 | T20: 117700 | U20: 120185 | V20: 130204 | W20: 121057.08 | X20: 154166 | Y20: 141905.89 | Z20: 190683.02 | AA20: 186290 | AB20: 208950.08 | AC20: 219394.2 | AD20: 236176.19 | AE20: 287780 | AF20: 322978 | AG20: 337188 | AH20: 354992 | AI20: 411494 | AJ20: 386976
G21: moeda | H21: EBITDA ajustado (DRE l.36; soma juros capitalizados) - memoria | J21: memoria | K21: 29620 | L21: 50769 | M21: 68104 | N21: 84604.71 | O21: 64437.653 | P21: 91238.058 | Q21: 86926.401 | R21: 136539.14 | S21: 80604.387 | T21: 118450.94 | U21: 121285.06 | V21: 131030 | W21: 122355.92 | X21: 155581.16 | Y21: 143394.89 | Z21: 192444.02 | AA21: 188146.01 | AB21: 211076 | AC21: 221434.3 | AD21: 238513.69 | AE21: 289491 | AF21: 326435.39 | AG21: 340249 | AH21: 359319 | AI21: 415737 | AJ21: 392251
G22: moeda | H22: Depreciacao e amortizacao (DRE l.33) - memoria | J22: memoria | K22: 2925 | L22: 307 | M22: 365 | N22: 265 | O22: 334.74295 | P22: 355.0585 | Q22: 370.45284 | R22: 378 | S22: 5875 | T22: 5704 | U22: 5715 | V22: 6302 | W22: 6221.0827 | X22: 6300 | Y22: 6340.8939 | Z22: 7010.0235 | AA22: 7117 | AB22: 7009 | AC22: 8191.3272 | AD22: 8811.1873 | AE22: 8533 | AF22: 8754 | AG22: 8521 | AH22: 9070 | AI22: 8349 | AJ22: 8551
H23: DFC - TRIMESTRE ISOLADO (aba Fluxo de Caixa; R$ mil)
A24: 10 | B24: 1 | G24: moeda | H24: Dividendos pagos a acionistas (DFC l.55; ja negativo na fonte) | J24: fonte | K24: 0 | L24: 0 | M24: 0 | N24: -170000 | O24: 0 | P24: 0 | Q24: -115000 | R24: -50000 | S24: 0 | T24: 0 | U24: -150000 | V24: 0 | W24: -60000 | X24: -18348 | Y24: 0 | Z24: -250000 | AA24: 0 | AB24: -118537 | AC24: -265000 | AD24: -100000 | AE24: -175000 | AF24: -154338 | AG24: 0 | AH24: -1023000 | AI24: 0 | AJ24: -270000
G25: moeda | H25: Imobilizado (DFC l.45) - capex - memoria | J25: memoria | K25: -3482 | L25: -3535 | M25: -5230 | N25: -5452 | O25: -10124 | P25: -8154 | Q25: -7054 | R25: -6369 | S25: -3970 | T25: -3383 | U25: 800 | V25: -12210 | W25: -13870 | X25: -8152 | Y25: -6189 | Z25: -7971 | AA25: -9128 | AB25: -7072 | AC25: -10833 | AD25: -10607 | AE25: -8816 | AF25: -7259 | AG25: -8645 | AH25: -9760 | AI25: -13519 | AJ25: -13320
G26: moeda | H26: Fluxo de caixa liquido das atividades operacionais (DFC l.39) - memoria | J26: memoria | K26: 4520.7146 | L26: 67057.593 | M26: 55153.829 | N26: 51347.864 | O26: 14590 | P26: 78624 | Q26: 78369 | R26: 210711 | S26: 27317 | T26: 94261 | U26: 70903 | V26: 154885 | W26: 19409 | X26: 106372 | Y26: 137791 | Z26: 154885 | AA26: 24438 | AB26: 173094 | AC26: 114104 | AD26: 167927.6 | AE26: 57863 | AF26: 105845 | AG26: 271006 | AH26: 312332 | AI26: 81925 | AJ26: 149981
H27: DERIVADAS (formula nesta aba)
A28: 4 | B28: -1 | C28: 3 | D28: 1 | G28: moeda | H28: D&A = EBITDA divulgado - EBIT (DRE l.34 - l.16), para o EBITDA do modelo ser o da Cia. Bate com a D&A da l.33 exceto 1T22 (EBITDA divulgado R$ 80,0 mi = EBIT 79,1 + 0,9; l.33 traz 5,9). COD1=4 lanca; COD2=3 devolve as despesas operacionais | J28: derivada | K28: =K20-K19 -> 2925 | L28: =L20-L19 -> 307 | M28: =M20-M19 -> 365 | N28: =N20-N19 -> 263.71006 | O28: =O20-O19 -> 334.65271 | P28: =P20-P19 -> 355.0585 | Q28: =Q20-Q19 -> 375.96036 | R28: =R20-R19 -> 377.74207 | ... AJ28: =AJ20-AJ19 -> 8551
H29: BALANCO (abas BP Ativo e BP Passivo; R$ mil, fim de trimestre)
A30: 11 | B30: 1 | G30: moeda | H30: Ativo: Caixa e equivalentes (l.6) | J30: fonte | K30: 254528 | L30: 358082 | M30: 529672 | N30: 291125 | O30: 329971 | P30: 390596 | Q30: 414633 | R30: 375963 | S30: 360921 | T30: 454074 | U30: 394522 | V30: 562264 | W30: 470159 | X30: 556696 | Y30: 730072 | Z30: 643630 | AA30: 647595 | AB30: 889522 | AC30: 760259 | AD30: 975224 | AE30: 1031724 | AF30: 1035262 | AG30: 1287134 | AH30: 1355394 | AI30: 1397709 | AJ30: 1375239
A31: 11 | B31: 1 | G31: moeda | H31: Ativo: Títulos e valores mobiliários (l.7) | J31: fonte | K31: 71000 | L31: 67765 | M31: 80177 | N31: 139773 | O31: 106673 | P31: 101391 | Q31: 140294 | R31: 218524 | S31: 241647 | T31: 225903 | U31: 240386 | V31: 227162 | W31: 259664 | X31: 278694 | Y31: 379003 | Z31: 348639 | AA31: 364073 | AB31: 668498 | AC31: 664956 | AD31: 441012 | AE31: 512082 | AF31: 495613 | AG31: 486069 | AH31: 435543 | AI31: 359601 | AJ31: 258467
A32: 12 | B32: 1 | G32: moeda | H32: Ativo: Contas a receber de clientes (l.8) | J32: fonte | K32: 448111 | L32: 528330 | M32: 647241 | N32: 627243 | O32: 770187 | P32: 835343 | Q32: 700282 | R32: 731349 | S32: 996524 | T32: 1004386 | U32: 879561.98 | V32: 681536 | W32: 677724 | X32: 678261 | Y32: 489221 | Z32: 481218 | AA32: 649909 | AB32: 494497 | AC32: 371958 | AD32: 345783 | AE32: 602208 | AF32: 552497 | AG32: 475943.34 | AH32: 286215 | AI32: 536930 | AJ32: 580014
A33: 13 | B33: 1 | G33: moeda | H33: Ativo: Imóveis a comercializar (l.9) | J33: fonte | K33: 210689 | L33: 190026 | M33: 226704 | N33: 270277 | O33: 382697 | P33: 320995 | Q33: 338886 | R33: 486666 | S33: 454883 | T33: 420684 | U33: 477113 | V33: 534993 | W33: 675394 | X33: 602449 | Y33: 626691 | Z33: 641546 | AA33: 683171 | AB33: 699423 | AC33: 683894 | AD33: 808203 | AE33: 742802 | AF33: 744049 | AG33: 960833 | AH33: 919547 | AI33: 1180633 | AJ33: 1185612
A34: 15 | B34: 1 | G34: moeda | H34: Ativo: Adiantamentos a fornecedores (l.10) | J34: fonte | K34: 11718 | L34: 9125 | M34: 8463 | N34: 7748 | O34: 7755 | P34: 5560 | Q34: 9083 | R34: 6611 | S34: 6676 | T34: 6582 | U34: 8343 | V34: 7297 | W34: 7108 | X34: 9562 | Y34: 11558 | Z34: 13547 | AA34: 9839 | AB34: 26070 | AC34: 15022 | AD34: 17033 | AE34: 15238 | AF34: 8316 | AG34: 9581 | AH34: 11708 | AI34: 10253 | AJ34: 9152
A35: 16 | B35: 1 | G35: moeda | H35: Ativo: Outros créditos (l.11) | J35: fonte | K35: 34332 | L35: 36889 | M35: 42749 | N35: 16345 | O35: 15478 | P35: 19254 | Q35: 24330 | R35: 27836 | S35: 30305 | T35: 36248 | U35: 43329 | V35: 50270 | W35: 58214 | X35: 63169 | Y35: 79675 | Z35: 84228 | AA35: 92050 | AB35: 115011 | AC35: 132338 | AD35: 138882 | AE35: 144504 | AF35: 170013 | AG35: 187277 | AH35: 203465 | AI35: 206713 | AJ35: 230579
A36: 12 | B36: 1 | G36: moeda | H36: Ativo: Contas a receber de clientes (l.14) -> cod 12: contas a receber total (CP + LP), padrao de incorporadora; para separar, trocar para cod 22 | J36: fonte | K36: 157343 | L36: 157343 | M36: 183813 | N36: 172079 | O36: 167826 | P36: 213781 | Q36: 406000 | R36: 546316 | S36: 634055 | T36: 552406 | U36: 520139.02 | V36: 497726 | W36: 372912 | X36: 407428 | Y36: 591170 | Z36: 609583 | AA36: 635299 | AB36: 884755 | AC36: 1082272 | AD36: 1091454 | AE36: 1294500 | AF36: 1581210 | AG36: 1722834.7 | AH36: 1871728 | AI36: 2012450 | AJ36: 2142326
A37: 13 | B37: 1 | G37: moeda | H37: Ativo: Imóveis a comercializar (l.15) -> cod 13: imoveis a comercializar total (CP + LP); para separar, trocar para cod 22 | J37: fonte | K37: 0 | L37: 0 | M37: 0 | N37: 25981 | O37: 36788 | P37: 44683 | Q37: 42742 | R37: 46042 | S37: 45908 | T37: 49903 | U37: 51027 | V37: 69096 | W37: 37104 | X37: 55154 | Y37: 62334 | Z37: 76002 | AA37: 128214 | AB37: 66628 | AC37: 107723 | AD37: 384925 | AE37: 392141 | AF37: 439808 | AG37: 356022 | AH37: 429102 | AI37: 340955 | AJ37: 344507
A38: 22 | B38: 1 | G38: moeda | H38: Ativo: Valores a receber entre partes relacionadas (l.16) | J38: fonte | K38: 41381 | L38: 41232 | M38: 32688 | N38: 12206 | O38: 12223 | P38: 4771 | Q38: 4788 | R38: 4321 | S38: 4445 | T38: 4724 | U38: 4355 | V38: 5073 | W38: 4990 | X38: 9220 | Y38: 9055 | Z38: 12877 | AA38: 17035 | AB38: 20868 | AC38: 18436 | AD38: 19811 | AE38: 15765 | AF38: 19451 | AG38: 12336 | AH38: 11893 | AI38: 17865 | AJ38: 18291
A39: 22 | B39: 1 | G39: moeda | H39: Ativo: Outros créditos (l.17) | J39: fonte | K39: 3640 | L39: 3725 | M39: 4441 | N39: 40318 | O39: 39751 | P39: 40488 | Q39: 40920 | R39: 35863 | S39: 36988 | T39: 38934 | U39: 39513 | V39: 37485 | W39: 38625 | X39: 40822 | Y39: 40775 | Z39: 37440 | AA39: 40040 | AB39: 36529 | AC39: 37791 | AD39: 33123 | AE39: 37748 | AF39: 56629 | AG39: 52251 | AH39: 47276 | AI39: 48248 | AJ39: 52709
A40: 17 | B40: 1 | G40: moeda | H40: Ativo: Investimentos (l.18) | J40: fonte | K40: 18857 | L40: 24778 | M40: 25680 | N40: 26948 | O40: 28737 | P40: 32139 | Q40: 29674 | R40: 29770 | S40: 30764 | T40: 33604 | U40: 36393 | V40: 34316 | W40: 32327 | X40: 33598 | Y40: 29692 | Z40: 40875 | AA40: 40803 | AB40: 44707 | AC40: 42837 | AD40: 42244 | AE40: 40372 | AF40: 40727 | AG40: 41203 | AH40: 41321 | AI40: 37757 | AJ40: 30471
A41: 18 | B41: 1 | G41: moeda | H41: Ativo: Imobilizado (l.19) | J41: fonte | K41: 12276 | L41: 12871 | M41: 13604 | N41: 14669 | O41: 20211 | P41: 23569 | Q41: 25579 | R41: 25765 | S41: 24330 | T41: 22509 | U41: 22203 | V41: 22931 | W41: 31101 | X41: 33293 | Y41: 33278 | Z41: 34596 | AA41: 36855 | AB41: 37163 | AC41: 39806 | AD41: 41601 | AE41: 41884 | AF41: 40389 | AG41: 40513 | AH41: 41203 | AI41: 46373 | AJ41: 51142
... A68: 35 | B68: 1 | G68: moeda | H68: Passivo/PL: Participação dos sócios não controladores (l.35) | J68: fonte | K68: 155510 | L68: 162668 | M68: 170936 | N68: 152923 | O68: 154258 | P68: 150132 | Q68: 148534 | R68: 147230 | S68: 144035 | T68: 147818 | U68: 134033 | V68: 126011 | W68: 126067 | X68: 137528 | Y68: 132985 | Z68: 132015 | AA68: 152236 | AB68: 139517 | AC68: 149296 | AD68: 214069 | AE68: 227539 | AF68: 248326 | AG68: 256908 | AH68: 280348 | AI68: 347397 | AJ68: 393817
H69: BALANCO - totais divulgados (memoria)
G70: moeda | H70: Total do ativo (BP Ativo l.23) | J70: memoria | K70: 1263875 | L70: 1430166 | M70: 1795232 | N70: 1644712 | O70: 1918297 | P70: 2032570 | Q70: 2177211 | R70: 2597922 | S70: 2933909 | T70: 2917631 | U70: 2784853 | V70: 2798431 | W70: 2733836 | X70: 2836650 | Y70: 3150612 | Z70: 3092023 | AA70: 3412477 | AB70: 3983671 | AC70: 3957292 | AD70: 4339295 | AE70: 4870968 | AF70: 5183964 | AG70: 5631997 | AH70: 5654395 | AI70: 6195487 | AJ70: 6278509
G71: moeda | H71: Total do passivo e PL (BP Passivo l.36) | J71: memoria | K71: 1263875 | L71: 1430166 | M71: 1795232 | N71: 1644712 | O71: 1918297 | P71: 2032570 | Q71: 2177211 | R71: 2597922 | S71: 2933909 | T71: 2917631 | U71: 2784853 | V71: 2798431 | W71: 2733836 | X71: 2836650 | Y71: 3150612 | Z71: 3092023 | AA71: 3412477 | AB71: 3983671 | AC71: 3957292 | AD71: 4339295 | AE71: 4870968 | AF71: 5183964 | AG71: 5631997 | AH71: 5654395 | AI71: 6195487 | AJ71: 6278509
H72: CHECKS (devem ser 0)
G73: moeda | H73: CHECK: receita + custo + despesas op. + equivalencia + resultado financeiro + IR - lucro liquido 100% (arredondamento da fonte: ate R$ 1 mil) | J73: derivada | K73: =ROUND(K6+K7+K8+K9+K10+K11+K12+K13+K14+K15-K16,0) -> 0 | L73: =ROUND(L6+L7+L8+L9+L10+L11+L12+L13+L14+L15-L16,0) -> 0 | M73: =ROUND(M6+M7+M8+M9+M10+M11+M12+M13+M14+M15-M16,0) -> 0 | N73: =ROUND(N6+N7+N8+N9+N10+N11+N12+N13+N14+N15-N16,0) -> 0 | O73: =ROUND(O6+O7+O8+O9+O10+O11+O12+O13+O14+O15-O16,0) -> 0 | P73: =ROUND(P6+P7+P8+P9+P10+P11+P12+P13+P14+P15-P16,0) -> 0 | Q73: =ROUND(Q6+Q7+Q8+Q9+Q10+Q11+Q12+Q13+Q14+Q15-Q16,0) -> 0 | R73: =ROUND(R6+R7+R8+R9+R10+R11+R12+R13+R14+R15-R16,0) -> -1 | ... AJ73: =ROUND(AJ6+AJ7+AJ8+AJ9+AJ10+AJ11+AJ12+AJ13+AJ14+AJ15-AJ16,0) -> 0
G74: moeda | H74: CHECK: contas de ativo - ativo total | J74: derivada | K74: =ROUND(K30+K31+K32+K33+K34+K35+K36+K37+K38+K39+K40+K41+K42+K43-K70,0) -> 0 | L74: =ROUND(L30+L31+L32+L33+L34+L35+L36+L37+L38+L39+L40+L41+L42+L43-L70,0) -> 0 | M74: =ROUND(M30+M31+M32+M33+M34+M35+M36+M37+M38+M39+M40+M41+M42+M43-M70,0) -> 0 | N74: =ROUND(N30+N31+N32+N33+N34+N35+N36+N37+N38+N39+N40+N41+N42+N43-N70,0) -> 0 | O74: =ROUND(O30+O31+O32+O33+O34+O35+O36+O37+O38+O39+O40+O41+O42+O43-O70,0) -> 0 | P74: =ROUND(P30+P31+P32+P33+P34+P35+P36+P37+P38+P39+P40+P41+P42+P43-P70,0) -> 0 | Q74: =ROUND(Q30+Q31+Q32+Q33+Q34+Q35+Q36+Q37+Q38+Q39+Q40+Q41+Q42+Q43-Q70,0) -> 0 | R74: =ROUND(R30+R31+R32+R33+R34+R35+R36+R37+R38+R39+R40+R41+R42+R43-R70,0) -> 0 | ... AJ74: =ROUND(AJ30+AJ31+AJ32+AJ33+AJ34+AJ35+AJ36+AJ37+AJ38+AJ39+AJ40+AJ41+AJ42+AJ43-AJ70,0) -> 0
G75: moeda | H75: CHECK: passivo + PL - passivo total | J75: derivada | K75: =ROUND(K44+K45+K46+K47+K48+K49+K50+K51+K52+K53+K54+K55+K56+K57+K58+K59+K60+K61+K62+K63+K64+K65+K66+K67+K68-K71,0) -> 0 | L75: =ROUND(L44+L45+L46+L47+L48+L49+L50+L51+L52+L53+L54+L55+L56+L57+L58+L59+L60+L61+L62+L63+L64+L65+L66+L67+L68-L71,0) -> 0 | M75: =ROUND(M44+M45+M46+M47+M48+M49+M50+M51+M52+M53+M54+M55+M56+M57+M58+M59+M60+M61+M62+M63+M64+M65+M66+M67+M68-M71,0) -> 0 | N75: =ROUND(N44+N45+N46+N47+N48+N49+N50+N51+N52+N53+N54+N55+N56+N57+N58+N59+N60+N61+N62+N63+N64+N65+N66+N67+N68-N71,0) -> 0 | O75: =ROUND(O44+O45+O46+O47+O48+O49+O50+O51+O52+O53+O54+O55+O56+O57+O58+O59+O60+O61+O62+O63+O64+O65+O66+O67+O68-O71,0) -> 0 | P75: =ROUND(P44+P45+P46+P47+P48+P49+P50+P51+P52+P53+P54+P55+P56+P57+P58+P59+P60+P61+P62+P63+P64+P65+P66+P67+P68-P71,0) -> 0 | Q75: =ROUND(Q44+Q45+Q46+Q47+Q48+Q49+Q50+Q51+Q52+Q53+Q54+Q55+Q56+Q57+Q58+Q59+Q60+Q61+Q62+Q63+Q64+Q65+Q66+Q67+Q68-Q71,0) -> 0 | R75: =ROUND(R44+R45+R46+R47+R48+R49+R50+R51+R52+R53+R54+R55+R56+R57+R58+R59+R60+R61+R62+R63+R64+R65+R66+R67+R68-R71,0) -> 0 | ... AJ75: =ROUND(AJ44+AJ45+AJ46+AJ47+AJ48+AJ49+AJ50+AJ51+AJ52+AJ53+AJ54+AJ55+AJ56+AJ57+AJ58+AJ59+AJ60+AJ61+AJ62+AJ63+AJ64+AJ65+AJ66+AJ67+AJ68-AJ71,0) -> 0
H76: [vazio] cod 14 Deferred income taxes (ativo): sem linha propria
H77: [vazio] cod 19 Right-of-use: sem linha propria
H78: [vazio] cod 20 Goodwill: inexistente
H79: [vazio] cod 28 Revolver: sem linha propria (emprestimos CP no cod 27)
H80: [vazio] cod 29 Leases CP: sem linha propria
H81: [vazio] cod 31 Leases LP: sem linha propria
H82: [vazio] cod 32 Convertible debt: inexistente
H83: [vazio] cod 36 Convertible Preferred Stock: inexistente
H84: [vazio] cod 39 ORA: sem linha propria
H85: [vazio] cod 40 Other equity: sem linha propria
H86: Nota: NI do Model = lucro %Cury (atribuido a controladora); nao controladores (SPEs com socios) no cod 9. Juros de financiamento a producao sao capitalizados no custo (EBITDA ajustado da Cia soma esses juros de volta; fica como memoria).
H88: DRIVERS DE RECEITA (codigos 45+): abas Resultados Operacionais e Demonstracoes do Resultado (REF). UNID "moeda" = R$ mil com fator; "un" = sem fator (unidades, %, landbank ja em R$ milhoes).
A89: 45 | B89: 1 | G89: moeda | H89: Lancamentos - VGV 100% (R$ mil; Res. Operacionais l.7) | J89: fonte | K89: 157587.25 | L89: 311528.14 | M89: 396910.12 | N89: 674753.8 | O89: 590494.84 | P89: 686188.67 | Q89: 720223.75 | R89: 788101.23 | S89: 781150 | T89: 1056318 | U89: 919146.34 | V89: 556159.09 | W89: 1419980.9 | X89: 1222565.2 | Y89: 941717.11 | Z89: 856606.65 | AA89: 1884338 | AB89: 1734686.9 | AC89: 1560697 | AD89: 1399837 | AE89: 2783509 | AF89: 2225285.6 | AG89: 1986377.6 | AH89: 1289513.8 | AI89: 2646758.1 | AJ89: 2256889.2
A90: 46 | B90: 1 | G90: moeda | H90: Lancamentos - VGV parte Cury (R$ mil; l.8) | J90: fonte | K90: 72471.069 | L90: 311528.14 | M90: 367288.62 | N90: 625442.98 | O90: 472469.29 | P90: 650171.57 | Q90: 633172.7 | R90: 719679.33 | S90: 781150 | T90: 1056318 | U90: 876846.34 | V90: 556159.09 | W90: 1419980.9 | X90: 1137966.3 | Y90: 805577.11 | Z90: 856606.65 | AA90: 1499854.8 | AB90: 1676918.6 | AC90: 1503046 | AD90: 1060952 | AE90: 2666305 | AF90: 1960487.7 | AG90: 1733913.9 | AH90: 1179132.2 | AI90: 2268903.9 | AJ90: 1943927.9
A91: 47 | B91: 1 | G91: un | H91: Lancamentos - unidades (l.10) | J91: fonte | K91: 903 | L91: 1830 | M91: 2061 | N91: 3439 | O91: 2957 | P91: 3244 | Q91: 3163 | R91: 3275 | S91: 3240 | T91: 3548 | U91: 3650 | V91: 2147 | W91: 5095 | X91: 3799 | Y91: 3658 | Z91: 3123 | AA91: 5959 | AB91: 5588 | AC91: 5157 | AD91: 4061 | AE91: 9132 | AF91: 6588 | AG91: 6813 | AH91: 3833 | AI91: 8001 | AJ91: 6549
A92: 48 | B92: 1 | G92: un | H92: Lancamentos - numero de empreendimentos (l.6) | J92: fonte | K92: 2 | L92: 4 | M92: 5 | N92: 6 | O92: 6 | P92: 7 | Q92: 6 | R92: 7 | S92: 5 | T92: 7 | U92: 6 | V92: 5 | W92: 8 | X92: 8 | Y92: 7 | Z92: 6 | AA92: 10 | AB92: 8 | AC92: 9 | AD92: 7 | AE92: 14 | AF92: 9 | AG92: 9 | AH92: 5 | AI92: 10 | AJ92: 11
A93: 49 | B93: 1 | G93: moeda | H93: Vendas brutas - VGV 100% (R$ mil; l.22) | J93: fonte | K93: 279330.05 | L93: 333769.85 | M93: 467432.94 | N93: 448160.53 | O93: 633518.59 | P93: 736468.39 | Q93: 748701.79 | R93: 671693.78 | S93: 812740.16 | T93: 987420.74 | U93: 967263.3 | V93: 835511.12 | W93: 1164037 | X93: 1342268.7 | Y93: 1154323.1 | Z93: 1025134.1 | AA93: 1679488.9 | AB93: 1926220.5 | AC93: 1590241.7 | AD93: 1531003 | AE93: 2225417.1 | AF93: 2498004.8 | AG93: 2051878.2 | AH93: 1714072.9 | AI93: 2533872.3 | AJ93: 2216669.7
A94: 50 | B94: 1 | G94: moeda | H94: Distratos - VGV (R$ mil; l.23; positivo na fonte) | J94: fonte | K94: 40452.262 | L94: 41687.639 | M94: 57087.342 | N94: 43555.616 | O94: 43145.266 | P94: 53890.715 | Q94: 66331.284 | R94: 60327.683 | S94: 59374.042 | T94: 89935.358 | U94: 81430.701 | V94: 82449.072 | W94: 85145.044 | X94: 148317.92 | Y94: 181679.17 | Z94: 120462.53 | AA94: 127353.6 | AB94: 176980.56 | AC94: 153090 | AD94: 107255 | AE94: 119838.23 | AF94: 236641.66 | AG94: 224841.95 | AH94: 157737.23 | AI94: 229252.62 | AJ94: 171161.96
A95: 51 | B95: 1 | G95: moeda | H95: Vendas liquidas - VGV 100% (R$ mil; l.24) | J95: fonte | K95: 238877.79 | L95: 292082.21 | M95: 410345.6 | N95: 404604.91 | O95: 590373.33 | P95: 682578 | Q95: 682370.51 | R95: 611366.1 | S95: 753366.12 | T95: 897485.38 | U95: 885832.6 | V95: 753062.05 | W95: 1078892 | X95: 1193950.8 | Y95: 972643.95 | Z95: 904671.59 | AA95: 1552135.3 | AB95: 1749239.9 | AC95: 1437151.2 | AD95: 1423748 | AE95: 2105578.9 | AF95: 2261363.2 | AG95: 1827036.2 | AH95: 1556335.7 | AI95: 2304619.7 | AJ95: 2045507.7
A96: 52 | B96: 1 | G96: moeda | H96: Vendas liquidas - parte Cury (R$ mil; l.27) | J96: fonte | K96: 173740.31 | L96: 248207.36 | M96: 363318.77 | N96: 370036.63 | O96: 526078.98 | P96: 618279.07 | Q96: 639576.98 | R96: 565420.45 | S96: 707012.39 | T96: 844809.7 | U96: 836735.12 | V96: 719681.96 | W96: 1061205.9 | X96: 1132517 | Y96: 873639.21 | Z96: 850285.46 | AA96: 1327315.3 | AB96: 1635318.6 | AC96: 1359583.3 | AD96: 1177287 | AE96: 1919242 | AF96: 2007235.9 | AG96: 1630209 | AH96: 1434724.9 | AI96: 1893602.8 | AJ96: 1748768.2
A97: 53 | B97: 1 | G97: un | H97: Unidades vendidas liquidas (l.35) | J97: fonte | K97: 1280 | L97: 1622 | M97: 2131 | N97: 2068 | O97: 2874 | P97: 3253 | Q97: 3080 | R97: 2667 | S97: 3264 | T97: 3734 | U97: 3465 | V97: 3073 | W97: 4014 | X97: 4292.47 | Y97: 3496 | Z97: 3215 | AA97: 5321 | AB97: 5769 | AC97: 4688 | AD97: 4464 | AE97: 6790 | AF97: 7712 | AG97: 6117 | AH97: 4956 | AI97: 7058 | AJ97: 6137
A98: 54 | B98: 1 | G98: un | H98: VSO liquido trimestral (l.29) | J98: fonte | K98: 0.34255281 | L98: 0.38024016 | M98: 0.46454225 | N98: 0.35100526 | O98: 0.43534825 | P98: 0.468 | Q98: 0.45205051 | R98: 0.37951686 | S98: 0.41375165 | T98: 0.41629432 | U98: 0.40313083 | V98: 0.41 | W98: 0.43402358 | X98: 0.45393769 | Y98: 0.40373932 | Z98: 0.3885 | AA98: 0.47870612 | AB98: 0.50526083 | AC98: 0.438513 | AD98: 0.4371 | AE98: 0.45411877 | AF98: 0.47516751 | AG98: 0.40553573 | AH98: 0.39275059 | AI98: 0.4510198 | AJ98: 0.40474897
A99: 55 | B99: 1 | G99: un | H99: VSO liquido UDM (l.30) | J99: fonte | K99: 0.69293619 | L99: 0.70198402 | M99: 0.72874141 | N99: 0.643 | O99: 0.68912645 | P99: 0.72867715 | Q99: 0.74047213 | R99: 0.72 | S99: 0.719 | T99: 0.701 | U99: 0.706 | V99: 0.753 | W99: 0.72 | X99: 0.731 | Y99: 0.736 | Z99: 0.74456499 | AA99: 0.73228994 | AB99: 0.75146774 | AC99: 0.75409795 | AD99: 0.7707 | AE99: 0.72733239 | AF99: 0.74317962 | AG99: 0.73987735 | AH99: 0.76307893 | AI99: 0.73916323 | AJ99: 0.71994711
A100: 56 | B100: 1 | G100: moeda | H100: Repasses - VGV repassado (R$ mil; l.40) | J100: fonte | K100: 250691.58 | L100: 220252.02 | M100: 384044.42 | N100: 344439 | O100: 296903.32 | P100: 540584 | Q100: 723118.13 | R100: 470010.73 | S100: 532336.59 | T100: 728501.12 | U100: 860054.43 | V100: 662004.39 | W100: 578900.07 | X100: 1228870.2 | Y100: 866063.57 | Z100: 857120.81 | AA100: 886489.76 | AB100: 1438166 | AC100: 1437600 | AD100: 927749 | AE100: 1122907.6 | AF100: 2149317.1 | AG100: 1487163.2 | AH100: 1492328.3 | AI100: 1339829.3 | AJ100: 2014958.7
... A109: 65 | B109: 1 | G109: moeda | H109: (-) Custo orcado das unidades vendidas a apropriar (R$ mil; DRE l.41) | J109: fonte | K109: -416158.21 | L109: -409404.42 | M109: -451569.29 | N109: -475106.14 | O109: -608580.97 | P109: -735781 | Q109: -872072 | R109: -949761 | S109: -1101334 | T109: -1227464 | U109: -1343940 | V109: -1426532 | W109: -1691437 | X109: -1885672 | Y109: -1996732 | Z109: -2032161 | AA109: -2404100 | AB109: -2769753 | AC109: -2950257 | AD109: -3150416 | AE109: -3656268 | AF109: -4123959 | AG109: -4355125 | AH109: -4420540 | AI109: -4834308 | AJ109: -4988360
H110: Nota: a aba Resultados Operacionais ja traz a previa operacional do 3T26 (coluna BA); ela fica fora da grade (ultimo trimestre com DRE/BP = 2T26).
H143: CONVENCOES
H144: Linhas de origem: 5 a 110. As formulas da Inputs (2) varrem as linhas 5 a 140; as linhas 111 a 140 estao livres para novas contas.
H145: Periodos: colunas K a AJ (1Q20 a 2Q26 = 1T20 a 2T26).
H146: Brutos em R$ mil, como na fonte. A Inputs (2) multiplica pelo fator da celula B1 (0,001) e entrega R$ milhoes.
H147: ORIGEM: fonte = copiado da planilha; memoria = como divulgado, sem codigo; derivada = formula nesta aba.
H148: Codigos 45 a 65: drivers de receita (memoria); alimentam o bloco logo abaixo da receita liquida no Model.

Sheet Inputs (2)
A1: =COUNTIF($B$3:$B$1048576,$B$1) -> 1 | B1: =MAX($B$3:$B$1048576) -> 65
D2: 1Q21 | E2: 2Q21 | F2: 3Q21 | G2: 4Q21 | H2: 2021 | I2: 1Q22 | J2: 2Q22 | K2: 3Q22 | L2: 4Q22 | M2: 2022 | N2: 1Q23 | O2: 2Q23 | P2: 3Q23 | Q2: 4Q23 | R2: 2023 | S2: 1Q24 | T2: 2Q24 | U2: 3Q24 | V2: 4Q24 | W2: 2024 | X2: 1Q25 | Y2: 2Q25 | Z2: 3Q25 | AA2: 4Q25 | AB2: 2025 | AC2: 1Q26 | AD2: 2Q26 | AE2: 3Q26 | AF2: 4Q26 | AG2: 2026 | AH2: 1Q20 | AI2: 2Q20 | AJ2: 3Q20 | AK2: 4Q20 | AL2: 2020 | AN2: Sem dado na fonte: 3Q26, 4Q26 e 2026 (rotulo em cinza). 2020 fica nas colunas AH-AL.
B4: 1 | C4: Net Revenues | D4: =IF(ISNA(MATCH(D$2,Inputs!$K$4:$AJ$4,0)),NA(),IF(SUMPRODUCT((Inputs!$A$5:$A$140=$B4)*ISNUMBER(INDEX(Inputs!$K$5:$AJ$140,0,MATCH(D$2,Inputs!$K$4:$AJ$4,0))))+SUMPRODUCT((Inputs!$C$5:$C$140=$B4)*ISNUMBER(INDEX(Inputs!$K$5:$AJ$140,0,MATCH(D$2,Inputs!$K$4:$AJ$4,0))))+SUMPRODUCT((Inputs!$E$5:$E$140=$B4)*ISNUMBER(INDEX(Inputs!$K$5:$AJ$140,0,MATCH(D$2,Inputs!$K$4:$AJ$4,0))))=0,NA(),SUMPRODUCT((Inputs!$A$5:$A$140=$B4)*Inputs!$B$5:$B$140*(((Inputs!$G$5:$G$140="moeda")+(Inputs!$G$5:$G$140="acoes"))*Inputs!$B$1+((Inputs!$G$5:$G$140<>"moeda")*(Inputs!$G$5:$G$140<>"acoes")))*INDEX(Inputs!$K$5:$AJ$140,0,MATCH(D$2,Inputs!$K$4:$AJ$4,0)))+SUMPRODUCT((Inputs!$C$5:$C$140=$B4)*Inputs!$D$5:$D$140*(((Inputs!$G$5:$G$140="moeda")+(Inputs!$G$5:$G$140="acoes"))*Inputs!$B$1+((Inputs!$G$5:$G$140<>"moeda")*(Inputs!$G$5:$G$140<>"acoes")))*INDEX(Inputs!$K$5:$AJ$140,0,MATCH(D$2,Inputs!$K$4:$AJ$4,0)))+SUMPRODUCT((Inputs!$E$5:$E$140=$B4)*Inputs!$F$5:$F$140*(((Inputs!$G$5:$G$140="moeda")+(Inputs!$G$5:$G$140="acoes"))*Inputs!$B$1+((Inputs!$G$5:$G$140<>"moeda")*(Inputs!$G$5:$G$140<>"acoes")))*INDEX(Inputs!$K$5:$AJ$140,0,MATCH(D$2,Inputs!$K$4:$AJ$4,0))))) -> 339.286 | E4: =IF(ISNA(MATCH(E$2,Inputs!$K$4:$AJ$4,0)),NA(),IF(SUMPRODUCT((Inputs!$A$5:$A$140=$B4)*ISNUMBER(INDEX(Inputs!$K$5:$AJ$140,0,MATCH(E$2,Inputs!$K$4:$AJ$4,0))))+SUMPRODUCT((Inputs!$C$5:$C$140=$B4)*ISNUMBER(INDEX(Inputs!$K$5:$AJ$140,0,MATCH(E$2,Inputs!$K$4:$AJ$4,0))))+SUMPRODUCT((Inputs!$E$5:$E$140=$B4)*ISNUMBER(INDEX(Inputs!$K$5:$AJ$140,0,MATCH(E$2,Inputs!$K$4:$AJ$4,0))))=0,NA(),SUMPRODUCT((Inputs!$A$5:$A$140=$B4)*Inputs!$B$5:$B$140*(((Inputs!$G$5:$G$140="moeda")+(Inputs!$G$5:$G$140="acoes"))*Inputs!$B$1+((Inputs!$G$5:$G$140<>"moeda")*(Inputs!$G$5:$G$140<>"acoes")))*INDEX(Inputs!$K$5:$AJ$140,0,MATCH(E$2,Inputs!$K$4:$AJ$4,0)))+SUMPRODUCT((Inputs!$C$5:$C$140=$B4)*Inputs!$D$5:$D$140*(((Inputs!$G$5:$G$140="moeda")+(Inputs!$G$5:$G$140="acoes"))*Inputs!$B$1+((Inputs!$G$5:$G$140<>"moeda")*(Inputs!$G$5:$G$140<>"acoes")))*INDEX(Inputs!$K$5:$AJ$140,0,MATCH(E$2,Inputs!$K$4:$AJ$4,0)))+SUMPRODUCT((Inputs!$E$5:$E$140=$B4)*Inputs!$F$5:$F$140*(((Inputs!$G$5:$G$140="moeda")+(Inputs!$G$5:$G$140="acoes"))*Inputs!$B$1+((Inputs!$G$5:$G$140<>"moeda")*(Inputs!$G$5:$G$140<>"acoes")))*INDEX(Inputs!$K$5:$AJ$140,0,MATCH(E$2,Inputs!$K$4:$AJ$4,0))))) -> 451.337 | F4: =IF(ISNA(MATCH(F$2,Inputs!$K$4:$AJ$4,0)),NA(),IF(SUMPRODUCT((Inputs!$A$5:$A$140=$B4)*ISNUMBER(INDEX(Inputs!$K$5:$AJ$140,0,MATCH(F$2,Inputs!$K$4:$AJ$4,0))))+SUMPRODUCT((Inputs!$C$5:$C$140=$B4)*ISNUMBER(INDEX(Inputs!$K$5:$AJ$140,0,MATCH(F$2,Inputs!$K$4:$AJ$4,0))))+SUMPRODUCT((Inputs!$E$5:$E$140=$B4)*ISNUMBER(INDEX(Inputs!$K$5:$AJ$140,0,MATCH(F$2,Inputs!$K$4:$AJ$4,0))))=0,NA(),SUMPRODUCT((Inputs!$A$5:$A$140=$B4)*Inputs!$B$5:$B$140*(((Inputs!$G$5:$G$140="moeda")+(Inputs!$G$5:$G$140="acoes"))*Inputs!$B$1+((Inputs!$G$5:$G$140<>"moeda")*(Inputs!$G$5:$G$140<>"acoes")))*INDEX(Inputs!$K$5:$AJ$140,0,MATCH(F$2,Inputs!$K$4:$AJ$4,0)))+SUMPRODUCT((Inputs!$C$5:$C$140=$B4)*Inputs!$D$5:$D$140*(((Inputs!$G$5:$G$140="moeda")+(Inputs!$G$5:$G$140="acoes"))*Inputs!$B$1+((Inputs!$G$5:$G$140<>"moeda")*(Inputs!$G$5:$G$140<>"acoes")))*INDEX(Inputs!$K$5:$AJ$140,0,MATCH(F$2,Inputs!$K$4:$AJ$4,0)))+SUMPRODUCT((Inputs!$E$5:$E$140=$B4)*Inputs!$F$5:$F$140*(((Inputs!$G$5:$G$140="moeda")+(Inputs!$G$5:$G$140="acoes"))*Inputs!$B$1+((Inputs!$G$5:$G$140<>"moeda")*(Inputs!$G$5:$G$140<>"acoes")))*INDEX(Inputs!$K$5:$AJ$140,0,MATCH(F$2,Inputs!$K$4:$AJ$4,0))))) -> 456.44958 | G4: =IF(ISNA(MATCH(G$2,Inputs!$K$4:$AJ$4,0)),NA(),IF(SUMPRODUCT((Inputs!$A$5:$A$140=$B4)*ISNUMBER(INDEX(Inputs!$K$5:$AJ$140,0,MATCH(G$2,Inputs!$K$4:$AJ$4,0))))+SUMPRODUCT((Inputs!$C$5:$C$140=$B4)*ISNUMBER(INDEX(Inputs!$K$5:$AJ$140,0,MATCH(G$2,Inputs!$K$4:$AJ$4,0))))+SUMPRODUCT((Inputs!$E$5:$E$140=$B4)*ISNUMBER(INDEX(Inputs!$K$5:$AJ$140,0,MATCH(G$2,Inputs!$K$4:$AJ$4,0))))=0,NA(),SUMPRODUCT((Inputs!$A$5:$A$140=$B4)*Inputs!$B$5:$B$140*(((Inputs!$G$5:$G$140="moeda")+(Inputs!$G$5:$G$140="acoes"))*Inputs!$B$1+((Inputs!$G$5:$G$140<>"moeda")*(Inputs!$G$5:$G$140<>"acoes")))*INDEX(Inputs!$K$5:$AJ$140,0,MATCH(G$2,Inputs!$K$4:$AJ$4,0)))+SUMPRODUCT((Inputs!$C$5:$C$140=$B4)*Inputs!$D$5:$D$140*(((Inputs!$G$5:$G$140="moeda")+(Inputs!$G$5:$G$140="acoes"))*Inputs!$B$1+((Inputs!$G$5:$G$140<>"moeda")*(Inputs!$G$5:$G$140<>"acoes")))*INDEX(Inputs!$K$5:$AJ$140,0,MATCH(G$2,Inputs!$K$4:$AJ$4,0)))+SUMPRODUCT((Inputs!$E$5:$E$140=$B4)*Inputs!$F$5:$F$140*(((Inputs!$G$5:$G$140="moeda")+(Inputs!$G$5:$G$140="acoes"))*Inputs!$B$1+((Inputs!$G$5:$G$140<>"moeda")*(Inputs!$G$5:$G$140<>"acoes")))*INDEX(Inputs!$K$5:$AJ$140,0,MATCH(G$2,Inputs!$K$4:$AJ$4,0))))) -> 491.223 | H4: =SUM(D4:G4) -> 1738.2956 | I4: =IF(ISNA(MATCH(I$2,Inputs!$K$4:$AJ$4,0)),NA(),IF(SUMPRODUCT((Inputs!$A$5:$A$140=$B4)*ISNUMBER(INDEX(Inputs!$K$5:$AJ$140,0,MATCH(I$2,Inputs!$K$4:$AJ$4,0))))+SUMPRODUCT((Inputs!$C$5:$C$140=$B4)*ISNUMBER(INDEX(Inputs!$K$5:$AJ$140,0,MATCH(I$2,Inputs!$K$4:$AJ$4,0))))+SUMPRODUCT((Inputs!$E$5:$E$140=$B4)*ISNUMBER(INDEX(Inputs!$K$5:$AJ$140,0,MATCH(I$2,Inputs!$K$4:$AJ$4,0))))=0,NA(),SUMPRODUCT((Inputs!$A$5:$A$140=$B4)*Inputs!$B$5:$B$140*(((Inputs!$G$5:$G$140="moeda")+(Inputs!$G$5:$G$140="acoes"))*Inputs!$B$1+((Inputs!$G$5:$G$140<>"moeda")*(Inputs!$G$5:$G$140<>"acoes")))*INDEX(Inputs!$K$5:$AJ$140,0,MATCH(I$2,Inputs!$K$4:$AJ$4,0)))+SUMPRODUCT((Inputs!$C$5:$C$140=$B4)*Inputs!$D$5:$D$140*(((Inputs!$G$5:$G$140="moeda")+(Inputs!$G$5:$G$140="acoes"))*Inputs!$B$1+((Inputs!$G$5:$G$140<>"moeda")*(Inputs!$G$5:$G$140<>"acoes")))*INDEX(Inputs!$K$5:$AJ$140,0,MATCH(I$2,Inputs!$K$4:$AJ$4,0)))+SUMPRODUCT((Inputs!$E$5:$E$140=$B4)*Inputs!$F$5:$F$140*(((Inputs!$G$5:$G$140="moeda")+(Inputs!$G$5:$G$140="acoes"))*Inputs!$B$1+((Inputs!$G$5:$G$140<>"moeda")*(Inputs!$G$5:$G$140<>"acoes")))*INDEX(Inputs!$K$5:$AJ$140,0,MATCH(I$2,Inputs!$K$4:$AJ$4,0))))) -> 447.374 | J4: =IF(ISNA(MATCH(J$2,Inputs!$K$4:$AJ$4,0)),NA(),IF(SUMPRODUCT((Inputs!$A$5:$A$140=$B4)*ISNUMBER(INDEX(Inputs!$K$5:$AJ$140,0,MATCH(J$2,Inputs!$K$4:$AJ$4,0))))+SUMPRODUCT((Inputs!$C$5:$C$140=$B4)*ISNUMBER(INDEX(Inputs!$K$5:$AJ$140,0,MATCH(J$2,Inputs!$K$4:$AJ$4,0))))+SUMPRODUCT((Inputs!$E$5:$E$140=$B4)*ISNUMBER(INDEX(Inputs!$K$5:$AJ$140,0,MATCH(J$2,Inputs!$K$4:$AJ$4,0))))=0,NA(),SUMPRODUCT((Inputs!$A$5:$A$140=$B4)*Inputs!$B$5:$B$140*(((Inputs!$G$5:$G$140="moeda")+(Inputs!$G$5:$G$140="acoes"))*Inputs!$B$1+((Inputs!$G$5:$G$140<>"moeda")*(Inputs!$G$5:$G$140<>"acoes")))*INDEX(Inputs!$K$5:$AJ$140,0,MATCH(J$2,Inputs!$K$4:$AJ$4,0)))+SUMPRODUCT((Inputs!$C$5:$C$140=$B4)*Inputs!$D$5:$D$140*(((Inputs!$G$5:$G$140="moeda")+(Inputs!$G$5:$G$140="acoes"))*Inputs!$B$1+((Inputs!$G$5:$G$140<>"moeda")*(Inputs!$G$5:$G$140<>"acoes")))*INDEX(Inputs!$K$5:$AJ$140,0,MATCH(J$2,Inputs!$K$4:$AJ$4,0)))+SUMPRODUCT((Inputs!$E$5:$E$140=$B4)*Inputs!$F$5:$F$140*(((Inputs!$G$5:$G$140="moeda")+(Inputs!$G$5:$G$140="acoes"))*Inputs!$B$1+((Inputs!$G$5:$G$140<>"moeda")*(Inputs!$G$5:$G$140<>"acoes")))*INDEX(Inputs!$K$5:$AJ$140,0,MATCH(J$2,Inputs!$K$4:$AJ$4,0))))) -> 602.783 | K4: =IF(ISNA(MATCH(K$2,Inputs!$K$4:$AJ$4,0)),NA(),IF(SUMPRODUCT((Inputs!$A$5:$A$140=$B4)*ISNUMBER(INDEX(Inputs!$K$5:$AJ$140,0,MATCH(K$2,Inputs!$K$4:$AJ$4,0))))+SUMPRODUCT((Inputs!$C$5:$C$140=$B4)*ISNUMBER(INDEX(Inputs!$K$5:$AJ$140,0,MATCH(K$2,Inputs!$K$4:$AJ$4,0))))+SUMPRODUCT((Inputs!$E$5:$E$140=$B4)*ISNUMBER(INDEX(Inputs!$K$5:$AJ$140,0,MATCH(K$2,Inputs!$K$4:$AJ$4,0))))=0,NA(),SUMPRODUCT((Inputs!$A$5:$A$140=$B4)*Inputs!$B$5:$B$140*(((Inputs!$G$5:$G$140="moeda")+(Inputs!$G$5:$G$140="acoes"))*Inputs!$B$1+((Inputs!$G$5:$G$140<>"moeda")*(Inputs!$G$5:$G$140<>"acoes")))*INDEX(Inputs!$K$5:$AJ$140,0,MATCH(K$2,Inputs!$K$4:$AJ$4,0)))+SUMPRODUCT((Inputs!$C$5:$C$140=$B4)*Inputs!$D$5:$D$140*(((Inputs!$G$5:$G$140="moeda")+(Inputs!$G$5:$G$140="acoes"))*Inputs!$B$1+((Inputs!$G$5:$G$140<>"moeda")*(Inputs!$G$5:$G$140<>"acoes")))*INDEX(Inputs!$K$5:$AJ$140,0,MATCH(K$2,Inputs!$K$4:$AJ$4,0)))+SUMPRODUCT((Inputs!$E$5:$E$140=$B4)*Inputs!$F$5:$F$140*(((Inputs!$G$5:$G$140="moeda")+(Inputs!$G$5:$G$140="acoes"))*Inputs!$B$1+((Inputs!$G$5:$G$140<>"moeda")*(Inputs!$G$5:$G$140<>"acoes")))*INDEX(Inputs!$K$5:$AJ$140,0,MATCH(K$2,Inputs!$K$4:$AJ$4,0))))) -> 626.659 | L4: =IF(ISNA(MATCH(L$2,Inputs!$K$4:$AJ$4,0)),NA(),IF(SUMPRODUCT((Inputs!$A$5:$A$140=$B4)*ISNUMBER(INDEX(Inputs!$K$5:$AJ$140,0,MATCH(L$2,Inputs!$K$4:$AJ$4,0))))+SUMPRODUCT((Inputs!$C$5:$C$140=$B4)*ISNUMBER(INDEX(Inputs!$K$5:$AJ$140,0,MATCH(L$2,Inputs!$K$4:$AJ$4,0))))+SUMPRODUCT((Inputs!$E$5:$E$140=$B4)*ISNUMBER(INDEX(Inputs!$K$5:$AJ$140,0,MATCH(L$2,Inputs!$K$4:$AJ$4,0))))=0,NA(),SUMPRODUCT((Inputs!$A$5:$A$140=$B4)*Inputs!$B$5:$B$140*(((Inputs!$G$5:$G$140="moeda")+(Inputs!$G$5:$G$140="acoes"))*Inputs!$B$1+((Inputs!$G$5:$G$140<>"moeda")*(Inputs!$G$5:$G$140<>"acoes")))*INDEX(Inputs!$K$5:$AJ$140,0,MATCH(L$2,Inputs!$K$4:$AJ$4,0)))+SUMPRODUCT((Inputs!$C$5:$C$140=$B4)*Inputs!$D$5:$D$140*(((Inputs!$G$5:$G$140="moeda")+(Inputs!$G$5:$G$140="acoes"))*Inputs!$B$1+((Inputs!$G$5:$G$140<>"moeda")*(Inputs!$G$5:$G$140<>"acoes")))*INDEX(Inputs!$K$5:$AJ$140,0,MATCH(L$2,Inputs!$K$4:$AJ$4,0)))+SUMPRODUCT((Inputs!$E$5:$E$140=$B4)*Inputs!$F$5:$F$140*(((Inputs!$G$5:$G$140="moeda")+(Inputs!$G$5:$G$140="acoes"))*Inputs!$B$1+((Inputs!$G$5:$G$140<>"moeda")*(Inputs!$G$5:$G$140<>"acoes")))*INDEX(Inputs!$K$5:$AJ$140,0,MATCH(L$2,Inputs!$K$4:$AJ$4,0))))) -> 580.478 | M4: =SUM(I4:L4) -> 2257.294 | N4: =IF(ISNA(MATCH(N$2,Inputs!$K$4:$AJ$4,0)),NA(),IF(SUMPRODUCT((Inputs!$A$5:$A$140=$B4)*ISNUMBER(INDEX(Inputs!$K$5:$AJ$140,0,MATCH(N$2,Inputs!$K$4:$AJ$4,0))))+SUMPRODUCT((Inputs!$C$5:$C$140=$B4)*ISNUMBER(INDEX(Inputs!$K$5:$AJ$140,0,MATCH(N$2,Inputs!$K$4:$AJ$4,0))))+SUMPRODUCT((Inputs!$E$5:$E$140=$B4)*ISNUMBER(INDEX(Inputs!$K$5:$AJ$140,0,MATCH(N$2,Inputs!$K$4:$AJ$4,0))))=0,NA(),SUMPRODUCT((Inputs!$A$5:$A$140=$B4)*Inputs!$B$5:$B$140*(((Inputs!$G$5:$G$140="moeda")+(Inputs!$G$5:$G$140="acoes"))*Inputs!$B$1+((Inputs!$G$5:$G$140<>"moeda")*(Inputs!$G$5:$G$140<>"acoes")))*INDEX(Inputs!$K$5:$AJ$140,0,MATCH(N$2,Inputs!$K$4:$AJ$4,0)))+SUMPRODUCT((Inputs!$C$5:$C$140=$B4)*Inputs!$D$5:$D$140*(((Inputs!$G$5:$G$140="moeda")+(Inputs!$G$5:$G$140="acoes"))*Inputs!$B$1+((Inputs!$G$5:$G$140<>"moeda")*(Inputs!$G$5:$G$140<>"acoes")))*INDEX(Inputs!$K$5:$AJ$140,0,MATCH(N$2,Inputs!$K$4:$AJ$4,0)))+SUMPRODUCT((Inputs!$E$5:$E$140=$B4)*Inputs!$F$5:$F$140*(((Inputs!$G$5:$G$140="moeda")+(Inputs!$G$5:$G$140="acoes"))*Inputs!$B$1+((Inputs!$G$5:$G$140<>"moeda")*(Inputs!$G$5:$G$140<>"acoes")))*INDEX(Inputs!$K$5:$AJ$140,0,MATCH(N$2,Inputs!$K$4:$AJ$4,0))))) -> 594.956 | O4: =IF(ISNA(MATCH(O$2,Inputs!$K$4:$AJ$4,0)),NA(),IF(SUMPRODUCT((Inputs!$A$5:$A$140=$B4)*ISNUMBER(INDEX(Inputs!$K$5:$AJ$140,0,MATCH(O$2,Inputs!$K$4:$AJ$4,0))))+SUMPRODUCT((Inputs!$C$5:$C$140=$B4)*ISNUMBER(INDEX(Inputs!$K$5:$AJ$140,0,MATCH(O$2,Inputs!$K$4:$AJ$4,0))))+SUMPRODUCT((Inputs!$E$5:$E$140=$B4)*ISNUMBER(INDEX(Inputs!$K$5:$AJ$140,0,MATCH(O$2,Inputs!$K$4:$AJ$4,0))))=0,NA(),SUMPRODUCT((Inputs!$A$5:$A$140=$B4)*Inputs!$B$5:$B$140*(((Inputs!$G$5:$G$140="moeda")+(Inputs!$G$5:$G$140="acoes"))*Inputs!$B$1+((Inputs!$G$5:$G$140<>"moeda")*(Inputs!$G$5:$G$140<>"acoes")))*INDEX(Inputs!$K$5:$AJ$140,0,MATCH(O$2,Inputs!$K$4:$AJ$4,0)))+SUMPRODUCT((Inputs!$C$5:$C$140=$B4)*Inputs!$D$5:$D$140*(((Inputs!$G$5:$G$140="moeda")+(Inputs!$G$5:$G$140="acoes"))*Inputs!$B$1+((Inputs!$G$5:$G$140<>"moeda")*(Inputs!$G$5:$G$140<>"acoes")))*INDEX(Inputs!$K$5:$AJ$140,0,MATCH(O$2,Inputs!$K$4:$AJ$4,0)))+SUMPRODUCT((Inputs!$E$5:$E$140=$B4)*Inputs!$F$5:$F$140*(((Inputs!$G$5:$G$140="moeda")+(Inputs!$G$5:$G$140="acoes"))*Inputs!$B$1+((Inputs!$G$5:$G$140<>"moeda")*(Inputs!$G$5:$G$140<>"acoes")))*INDEX(Inputs!$K$5:$AJ$140,0,MATCH(O$2,Inputs!$K$4:$AJ$4,0))))) -> 727.746 | P4: =IF(ISNA(MATCH(P$2,Inputs!$K$4:$AJ$4,0)),NA(),IF(SUMPRODUCT((Inputs!$A$5:$A$140=$B4)*ISNUMBER(INDEX(Inputs!$K$5:$AJ$140,0,MATCH(P$2,Inputs!$K$4:$AJ$4,0))))+SUMPRODUCT((Inputs!$C$5:$C$140=$B4)*ISNUMBER(INDEX(Inputs!$K$5:$AJ$140,0,MATCH(P$2,Inputs!$K$4:$AJ$4,0))))+SUMPRODUCT((Inputs!$E$5:$E$140=$B4)*ISNUMBER(INDEX(Inputs!$K$5:$AJ$140,0,MATCH(P$2,Inputs!$K$4:$AJ$4,0))))=0,NA(),SUMPRODUCT((Inputs!$A$5:$A$140=$B4)*Inputs!$B$5:$B$140*(((Inputs!$G$5:$G$140="moeda")+(Inputs!$G$5:$G$140="acoes"))*Inputs!$B$1+((Inputs!$G$5:$G$140<>"moeda")*(Inputs!$G$5:$G$140<>"acoes")))*INDEX(Inputs!$K$5:$AJ$140,0,MATCH(P$2,Inputs!$K$4:$AJ$4,0)))+SUMPRODUCT((Inputs!$C$5:$C$140=$B4)*Inputs!$D$5:$D$140*(((Inputs!$G$5:$G$140="moeda")+(Inputs!$G$5:$G$140="acoes"))*Inputs!$B$1+((Inputs!$G$5:$G$140<>"moeda")*(Inputs!$G$5:$G$140<>"acoes")))*INDEX(Inputs!$K$5:$AJ$140,0,MATCH(P$2,Inputs!$K$4:$AJ$4,0)))+SUMPRODUCT((Inputs!$E$5:$E$140=$B4)*Inputs!$F$5:$F$140*(((Inputs!$G$5:$G$140="moeda")+(Inputs!$G$5:$G$140="acoes"))*Inputs!$B$1+((Inputs!$G$5:$G$140<>"moeda")*(Inputs!$G$5:$G$140<>"acoes")))*INDEX(Inputs!$K$5:$AJ$140,0,MATCH(P$2,Inputs!$K$4:$AJ$4,0))))) -> 751.874 | Q4: =IF(ISNA(MATCH(Q$2,Inputs!$K$4:$AJ$4,0)),NA(),IF(SUMPRODUCT((Inputs!$A$5:$A$140=$B4)*ISNUMBER(INDEX(Inputs!$K$5:$AJ$140,0,MATCH(Q$2,Inputs!$K$4:$AJ$4,0))))+SUMPRODUCT((Inputs!$C$5:$C$140=$B4)*ISNUMBER(INDEX(Inputs!$K$5:$AJ$140,0,MATCH(Q$2,Inputs!$K$4:$AJ$4,0))))+SUMPRODUCT((Inputs!$E$5:$E$140=$B4)*ISNUMBER(INDEX(Inputs!$K$5:$AJ$140,0,MATCH(Q$2,Inputs!$K$4:$AJ$4,0))))=0,NA(),SUMPRODUCT((Inputs!$A$5:$A$140=$B4)*Inputs!$B$5:$B$140*(((Inputs!$G$5:$G$140="moeda")+(Inputs!$G$5:$G$140="acoes"))*Inputs!$B$1+((Inputs!$G$5:$G$140<>"moeda")*(Inputs!$G$5:$G$140<>"acoes")))*INDEX(Inputs!$K$5:$AJ$140,0,MATCH(Q$2,Inputs!$K$4:$AJ$4,0)))+SUMPRODUCT((Inputs!$C$5:$C$140=$B4)*Inputs!$D$5:$D$140*(((Inputs!$G$5:$G$140="moeda")+(Inputs!$G$5:$G$140="acoes"))*Inputs!$B$1+((Inputs!$G$5:$G$140<>"moeda")*(Inputs!$G$5:$G$140<>"acoes")))*INDEX(Inputs!$K$5:$AJ$140,0,MATCH(Q$2,Inputs!$K$4:$AJ$4,0)))+SUMPRODUCT((Inputs!$E$5:$E$140=$B4)*Inputs!$F$5:$F$140*(((Inputs!$G$5:$G$140="moeda")+(Inputs!$G$5:$G$140="acoes"))*Inputs!$B$1+((Inputs!$G$5:$G$140<>"moeda")*(Inputs!$G$5:$G$140<>"acoes")))*INDEX(Inputs!$K$5:$AJ$140,0,MATCH(Q$2,Inputs!$K$4:$AJ$4,0))))) -> 811.596 | R4: =SUM(N4:Q4) -> 2886.172 | S4: =IF(ISNA(MATCH(S$2,Inputs!$K$4:$AJ$4,0)),NA(),IF(SUMPRODUCT((Inputs!$A$5:$A$140=$B4)*ISNUMBER(INDEX(Inputs!$K$5:$AJ$140,0,MATCH(S$2,Inputs!$K$4:$AJ$4,0))))+SUMPRODUCT((Inputs!$C$5:$C$140=$B4)*ISNUMBER(INDEX(Inputs!$K$5:$AJ$140,0,MATCH(S$2,Inputs!$K$4:$AJ$4,0))))+SUMPRODUCT((Inputs!$E$5:$E$140=$B4)*ISNUMBER(INDEX(Inputs!$K$5:$AJ$140,0,MATCH(S$2,Inputs!$K$4:$AJ$4,0))))=0,NA(),SUMPRODUCT((Inputs!$A$5:$A$140=$B4)*Inputs!$B$5:$B$140*(((Inputs!$G$5:$G$140="moeda")+(Inputs!$G$5:$G$140="acoes"))*Inputs!$B$1+((Inputs!$G$5:$G$140<>"moeda")*(Inputs!$G$5:$G$140<>"acoes")))*INDEX(Inputs!$K$5:$AJ$140,0,MATCH(S$2,Inputs!$K$4:$AJ$4,0)))+SUMPRODUCT((Inputs!$C$5:$C$140=$B4)*Inputs!$D$5:$D$140*(((Inputs!$G$5:$G$140="moeda")+(Inputs!$G$5:$G$140="acoes"))*Inputs!$B$1+((Inputs!$G$5:$G$140<>"moeda")*(Inputs!$G$5:$G$140<>"acoes")))*INDEX(Inputs!$K$5:$AJ$140,0,MATCH(S$2,Inputs!$K$4:$AJ$4,0)))+SUMPRODUCT((Inputs!$E$5:$E$140=$B4)*Inputs!$F$5:$F$140*(((Inputs!$G$5:$G$140="moeda")+(Inputs!$G$5:$G$140="acoes"))*Inputs!$B$1+((Inputs!$G$5:$G$140<>"moeda")*(Inputs!$G$5:$G$140<>"acoes")))*INDEX(Inputs!$K$5:$AJ$140,0,MATCH(S$2,Inputs!$K$4:$AJ$4,0))))) -> 837.382 | T4: =IF(ISNA(MATCH(T$2,Inputs!$K$4:$AJ$4,0)),NA(),IF(SUMPRODUCT((Inputs!$A$5:$A$140=$B4)*ISNUMBER(INDEX(Inputs!$K$5:$AJ$140,0,MATCH(T$2,Inputs!$K$4:$AJ$4,0))))+SUMPRODUCT((Inputs!$C$5:$C$140=$B4)*ISNUMBER(INDEX(Inputs!$K$5:$AJ$140,0,MATCH(T$2,Inputs!$K$4:$AJ$4,0))))+SUMPRODUCT((Inputs!$E$5:$E$140=$B4)*ISNUMBER(INDEX(Inputs!$K$5:$AJ$140,0,MATCH(T$2,Inputs!$K$4:$AJ$4,0))))=0,NA(),SUMPRODUCT((Inputs!$A$5:$A$140=$B4)*Inputs!$B$5:$B$140*(((Inputs!$G$5:$G$140="moeda")+(Inputs!$G$5:$G$140="acoes"))*Inputs!$B$1+((Inputs!$G$5:$G$140<>"moeda")*(Inputs!$G$5:$G$140<>"acoes")))*INDEX(Inputs!$K$5:$AJ$140,0,MATCH(T$2,Inputs!$K$4:$AJ$4,0)))+SUMPRODUCT((Inputs!$C$5:$C$140=$B4)*Inputs!$D$5:$D$140*(((Inputs!$G$5:$G$140="moeda")+(Inputs!$G$5:$G$140="acoes"))*Inputs!$B$1+((Inputs!$G$5:$G$140<>"moeda")*(Inputs!$G$5:$G$140<>"acoes")))*INDEX(Inputs!$K$5:$AJ$140,0,MATCH(T$2,Inputs!$K$4:$AJ$4,0)))+SUMPRODUCT((Inputs!$E$5:$E$140=$B4)*Inputs!$F$5:$F$140*(((Inputs!$G$5:$G$140="moeda")+(Inputs!$G$5:$G$140="acoes"))*Inputs!$B$1+((Inputs!$G$5:$G$140<>"moeda")*(Inputs!$G$5:$G$140<>"acoes")))*INDEX(Inputs!$K$5:$AJ$140,0,MATCH(T$2,Inputs!$K$4:$AJ$4,0))))) -> 998.085 | U4: =IF(ISNA(MATCH(U$2,Inputs!$K$4:$AJ$4,0)),NA(),IF(SUMPRODUCT((Inputs!$A$5:$A$140=$B4)*ISNUMBER(INDEX(Inputs!$K$5:$AJ$140,0,MATCH(U$2,Inputs!$K$4:$AJ$4,0))))+SUMPRODUCT((Inputs!$C$5:$C$140=$B4)*ISNUMBER(INDEX(Inputs!$K$5:$AJ$140,0,MATCH(U$2,Inputs!$K$4:$AJ$4,0))))+SUMPRODUCT((Inputs!$E$5:$E$140=$B4)*ISNUMBER(INDEX(Inputs!$K$5:$AJ$140,0,MATCH(U$2,Inputs!$K$4:$AJ$4,0))))=0,NA(),SUMPRODUCT((Inputs!$A$5:$A$140=$B4)*Inputs!$B$5:$B$140*(((Inputs!$G$5:$G$140="moeda")+(Inputs!$G$5:$G$140="acoes"))*Inputs!$B$1+((Inputs!$G$5:$G$140<>"moeda")*(Inputs!$G$5:$G$140<>"acoes")))*INDEX(Inputs!$K$5:$AJ$140,0,MATCH(U$2,Inputs!$K$4:$AJ$4,0)))+SUMPRODUCT((Inputs!$C$5:$C$140=$B4)*Inputs!$D$5:$D$140*(((Inputs!$G$5:$G$140="moeda")+(Inputs!$G$5:$G$140="acoes"))*Inputs!$B$1+((Inputs!$G$5:$G$140<>"moeda")*(Inputs!$G$5:$G$140<>"acoes")))*INDEX(Inputs!$K$5:$AJ$140,0,MATCH(U$2,Inputs!$K$4:$AJ$4,0)))+SUMPRODUCT((Inputs!$E$5:$E$140=$B4)*Inputs!$F$5:$F$140*(((Inputs!$G$5:$G$140="moeda")+(Inputs!$G$5:$G$140="acoes"))*Inputs!$B$1+((Inputs!$G$5:$G$140<>"moeda")*(Inputs!$G$5:$G$140<>"acoes")))*INDEX(Inputs!$K$5:$AJ$140,0,MATCH(U$2,Inputs!$K$4:$AJ$4,0))))) -> 1055.872 | V4: =IF(ISNA(MATCH(V$2,Inputs!$K$4:$AJ$4,0)),NA(),IF(SUMPRODUCT((Inputs!$A$5:$A$140=$B4)*ISNUMBER(INDEX(Inputs!$K$5:$AJ$140,0,MATCH(V$2,Inputs!$K$4:$AJ$4,0))))+SUMPRODUCT((Inputs!$C$5:$C$140=$B4)*ISNUMBER(INDEX(Inputs!$K$5:$AJ$140,0,MATCH(V$2,Inputs!$K$4:$AJ$4,0))))+SUMPRODUCT((Inputs!$E$5:$E$140=$B4)*ISNUMBER(INDEX(Inputs!$K$5:$AJ$140,0,MATCH(V$2,Inputs!$K$4:$AJ$4,0))))=0,NA(),SUMPRODUCT((Inputs!$A$5:$A$140=$B4)*Inputs!$B$5:$B$140*(((Inputs!$G$5:$G$140="moeda")+(Inputs!$G$5:$G$140="acoes"))*Inputs!$B$1+((Inputs!$G$5:$G$140<>"moeda")*(Inputs!$G$5:$G$140<>"acoes")))*INDEX(Inputs!$K$5:$AJ$140,0,MATCH(V$2,Inputs!$K$4:$AJ$4,0)))+SUMPRODUCT((Inputs!$C$5:$C$140=$B4)*Inputs!$D$5:$D$140*(((Inputs!$G$5:$G$140="moeda")+(Inputs!$G$5:$G$140="acoes"))*Inputs!$B$1+((Inputs!$G$5:$G$140<>"moeda")*(Inputs!$G$5:$G$140<>"acoes")))*INDEX(Inputs!$K$5:$AJ$140,0,MATCH(V$2,Inputs!$K$4:$AJ$4,0)))+SUMPRODUCT((Inputs!$E$5:$E$140=$B4)*Inputs!$F$5:$F$140*(((Inputs!$G$5:$G$140="moeda")+(Inputs!$G$5:$G$140="acoes"))*Inputs!$B$1+((Inputs!$G$5:$G$140<>"moeda")*(Inputs!$G$5:$G$140<>"acoes")))*INDEX(Inputs!$K$5:$AJ$140,0,MATCH(V$2,Inputs!$K$4:$AJ$4,0))))) -> 1034.971 | W4: =SUM(S4:V4) -> 3926.31 | X4: =IF(ISNA(MATCH(X$2,Inputs!$K$4:$AJ$4,0)),NA(),IF(SUMPRODUCT((Inputs!$A$5:$A$140=$B4)*ISNUMBER(INDEX(Inputs!$K$5:$AJ$140,0,MATCH(X$2,Inputs!$K$4:$AJ$4,0))))+SUMPRODUCT((Inputs!$C$5:$C$140=$B4)*ISNUMBER(INDEX(Inputs!$K$5:$AJ$140,0,MATCH(X$2,Inputs!$K$4:$AJ$4,0))))+SUMPRODUCT((Inputs!$E$5:$E$140=$B4)*ISNUMBER(INDEX(Inputs!$K$5:$AJ$140,0,MATCH(X$2,Inputs!$K$4:$AJ$4,0))))=0,NA(),SUMPRODUCT((Inputs!$A$5:$A$140=$B4)*Inputs!$B$5:$B$140*(((Inputs!$G$5:$G$140="moeda")+(Inputs!$G$5:$G$140="acoes"))*Inputs!$B$1+((Inputs!$G$5:$G$140<>"moeda")*(Inputs!$G$5:$G$140<>"acoes")))*INDEX(Inputs!$K$5:$AJ$140,0,MATCH(X$2,Inputs!$K$4:$AJ$4,0)))+SUMPRODUCT((Inputs!$C$5:$C$140=$B4)*Inputs!$D$5:$D$140*(((Inputs!$G$5:$G$140="moeda")+(Inputs!$G$5:$G$140="acoes"))*Inputs!$B$1+((Inputs!$G$5:$G$140<>"moeda")*(Inputs!$G$5:$G$140<>"acoes")))*INDEX(Inputs!$K$5:$AJ$140,0,MATCH(X$2,Inputs!$K$4:$AJ$4,0)))+SUMPRODUCT((Inputs!$E$5:$E$140=$B4)*Inputs!$F$5:$F$140*(((Inputs!$G$5:$G$140="moeda")+(Inputs!$G$5:$G$140="acoes"))*Inputs!$B$1+((Inputs!$G$5:$G$140<>"moeda")*(Inputs!$G$5:$G$140<>"acoes")))*INDEX(Inputs!$K$5:$AJ$140,0,MATCH(X$2,Inputs!$K$4:$AJ$4,0))))) -> 1216.184 | Y4: =IF(ISNA(MATCH(Y$2,Inputs!$K$4:$AJ$4,0)),NA(),IF(SUMPRODUCT((Inputs!$A$5:$A$140=$B4)*ISNUMBER(INDEX(Inputs!$K$5:$AJ$140,0,MATCH(Y$2,Inputs!$K$4:$AJ$4,0))))+SUMPRODUCT((Inputs!$C$5:$C$140=$B4)*ISNUMBER(INDEX(Inputs!$K$5:$AJ$140,0,MATCH(Y$2,Inputs!$K$4:$AJ$4,0))))+SUMPRODUCT((Inputs!$E$5:$E$140=$B4)*ISNUMBER(INDEX(Inputs!$K$5:$AJ$140,0,MATCH(Y$2,Inputs!$K$4:$AJ$4,0))))=0,NA(),SUMPRODUCT((Inputs!$A$5:$A$140=$B4)*Inputs!$B$5:$B$140*(((Inputs!$G$5:$G$140="moeda")+(Inputs!$G$5:$G$140="acoes"))*Inputs!$B$1+((Inputs!$G$5:$G$140<>"moeda")*(Inputs!$G$5:$G$140<>"acoes")))*INDEX(Inputs!$K$5:$AJ$140,0,MATCH(Y$2,Inputs!$K$4:$AJ$4,0)))+SUMPRODUCT((Inputs!$C$5:$C$140=$B4)*Inputs!$D$5:$D$140*(((Inputs!$G$5:$G$140="moeda")+(Inputs!$G$5:$G$140="acoes"))*Inputs!$B$1+((Inputs!$G$5:$G$140<>"moeda")*(Inputs!$G$5:$G$140<>"acoes")))*INDEX(Inputs!$K$5:$AJ$140,0,MATCH(Y$2,Inputs!$K$4:$AJ$4,0)))+SUMPRODUCT((Inputs!$E$5:$E$140=$B4)*Inputs!$F$5:$F$140*(((Inputs!$G$5:$G$140="moeda")+(Inputs!$G$5:$G$140="acoes"))*Inputs!$B$1+((Inputs!$G$5:$G$140<>"moeda")*(Inputs!$G$5:$G$140<>"acoes")))*INDEX(Inputs!$K$5:$AJ$140,0,MATCH(Y$2,Inputs!$K$4:$AJ$4,0))))) -> 1346.599 | Z4: =IF(ISNA(MATCH(Z$2,Inputs!$K$4:$AJ$4,0)),NA(),IF(SUMPRODUCT((Inputs!$A$5:$A$140=$B4)*ISNUMBER(INDEX(Inputs!$K$5:$AJ$140,0,MATCH(Z$2,Inputs!$K$4:$AJ$4,0))))+SUMPRODUCT((Inputs!$C$5:$C$140=$B4)*ISNUMBER(INDEX(Inputs!$K$5:$AJ$140,0,MATCH(Z$2,Inputs!$K$4:$AJ$4,0))))+SUMPRODUCT((Inputs!$E$5:$E$140=$B4)*ISNUMBER(INDEX(Inputs!$K$5:$AJ$140,0,MATCH(Z$2,Inputs!$K$4:$AJ$4,0))))=0,NA(),SUMPRODUCT((Inputs!$A$5:$A$140=$B4)*Inputs!$B$5:$B$140*(((Inputs!$G$5:$G$140="moeda")+(Inputs!$G$5:$G$140="acoes"))*Inputs!$B$1+((Inputs!$G$5:$G$140<>"moeda")*(Inputs!$G$5:$G$140<>"acoes")))*INDEX(Inputs!$K$5:$AJ$140,0,MATCH(Z$2,Inputs!$K$4:$AJ$4,0)))+SUMPRODUCT((Inputs!$C$5:$C$140=$B4)*Inputs!$D$5:$D$140*(((Inputs!$G$5:$G$140="moeda")+(Inputs!$G$5:$G$140="acoes"))*Inputs!$B$1+((Inputs!$G$5:$G$140<>"moeda")*(Inputs!$G$5:$G$140<>"acoes")))*INDEX(Inputs!$K$5:$AJ$140,0,MATCH(Z$2,Inputs!$K$4:$AJ$4,0)))+SUMPRODUCT((Inputs!$E$5:$E$140=$B4)*Inputs!$F$5:$F$140*(((Inputs!$G$5:$G$140="moeda")+(Inputs!$G$5:$G$140="acoes"))*Inputs!$B$1+((Inputs!$G$5:$G$140<>"moeda")*(Inputs!$G$5:$G$140<>"acoes")))*INDEX(Inputs!$K$5:$AJ$140,0,MATCH(Z$2,Inputs!$K$4:$AJ$4,0))))) -> 1416.926 | AA4: =IF(ISNA(MATCH(AA$2,Inputs!$K$4:$AJ$4,0)),NA(),IF(SUMPRODUCT((Inputs!$A$5:$A$140=$B4)*ISNUMBER(INDEX(Inputs!$K$5:$AJ$140,0,MATCH(AA$2,Inputs!$K$4:$AJ$4,0))))+SUMPRODUCT((Inputs!$C$5:$C$140=$B4)*ISNUMBER(INDEX(Inputs!$K$5:$AJ$140,0,MATCH(AA$2,Inputs!$K$4:$AJ$4,0))))+SUMPRODUCT((Inputs!$E$5:$E$140=$B4)*ISNUMBER(INDEX(Inputs!$K$5:$AJ$140,0,MATCH(AA$2,Inputs!$K$4:$AJ$4,0))))=0,NA(),SUMPRODUCT((Inputs!$A$5:$A$140=$B4)*Inputs!$B$5:$B$140*(((Inputs!$G$5:$G$140="moeda")+(Inputs!$G$5:$G$140="acoes"))*Inputs!$B$1+((Inputs!$G$5:$G$140<>"moeda")*(Inputs!$G$5:$G$140<>"acoes")))*INDEX(Inputs!$K$5:$AJ$140,0,MATCH(AA$2,Inputs!$K$4:$AJ$4,0)))+SUMPRODUCT((Inputs!$C$5:$C$140=$B4)*Inputs!$D$5:$D$140*(((Inputs!$G$5:$G$140="moeda")+(Inputs!$G$5:$G$140="acoes"))*Inputs!$B$1+((Inputs!$G$5:$G$140<>"moeda")*(Inputs!$G$5:$G$140<>"acoes")))*INDEX(Inputs!$K$5:$AJ$140,0,MATCH(AA$2,Inputs!$K$4:$AJ$4,0)))+SUMPRODUCT((Inputs!$E$5:$E$140=$B4)*Inputs!$F$5:$F$140*(((Inputs!$G$5:$G$140="moeda")+(Inputs!$G$5:$G$140="acoes"))*Inputs!$B$1+((Inputs!$G$5:$G$140<>"moeda")*(Inputs!$G$5:$G$140<>"acoes")))*INDEX(Inputs!$K$5:$AJ$140,0,MATCH(AA$2,Inputs!$K$4:$AJ$4,0))))) -> 1419.715 | AB4: =SUM(X4:AA4) -> 5399.424 | AC4: =IF(ISNA(MATCH(AC$2,Inputs!$K$4:$AJ$4,0)),NA(),IF(SUMPRODUCT((Inputs!$A$5:$A$140=$B4)*ISNUMBER(INDEX(Inputs!$K$5:$AJ$140,0,MATCH(AC$2,Inputs!$K$4:$AJ$4,0))))+SUMPRODUCT((Inputs!$C$5:$C$140=$B4)*ISNUMBER(INDEX(Inputs!$K$5:$AJ$140,0,MATCH(AC$2,Inputs!$K$4:$AJ$4,0))))+SUMPRODUCT((Inputs!$E$5:$E$140=$B4)*ISNUMBER(INDEX(Inputs!$K$5:$AJ$140,0,MATCH(AC$2,Inputs!$K$4:$AJ$4,0))))=0,NA(),SUMPRODUCT((Inputs!$A$5:$A$140=$B4)*Inputs!$B$5:$B$140*(((Inputs!$G$5:$G$140="moeda")+(Inputs!$G$5:$G$140="acoes"))*Inputs!$B$1+((Inputs!$G$5:$G$140<>"moeda")*(Inputs!$G$5:$G$140<>"acoes")))*INDEX(Inputs!$K$5:$AJ$140,0,MATCH(AC$2,Inputs!$K$4:$AJ$4,0)))+SUMPRODUCT((Inputs!$C$5:$C$140=$B4)*Inputs!$D$5:$D$140*(((Inputs!$G$5:$G$140="moeda")+(Inputs!$G$5:$G$140="acoes"))*Inputs!$B$1+((Inputs!$G$5:$G$140<>"moeda")*(Inputs!$G$5:$G$140<>"acoes")))*INDEX(Inputs!$K$5:$AJ$140,0,MATCH(AC$2,Inputs!$K$4:$AJ$4,0)))+SUMPRODUCT((Inputs!$E$5:$E$140=$B4)*Inputs!$F$5:$F$140*(((Inputs!$G$5:$G$140="moeda")+(Inputs!$G$5:$G$140="acoes"))*Inputs!$B$1+((Inputs!$G$5:$G$140<>"moeda")*(Inputs!$G$5:$G$140<>"acoes")))*INDEX(Inputs!$K$5:$AJ$140,0,MATCH(AC$2,Inputs!$K$4:$AJ$4,0))))) -> 1612.571 | AD4: =IF(ISNA(MATCH(AD$2,Inputs!$K$4:$AJ$4,0)),NA(),IF(SUMPRODUCT((Inputs!$A$5:$A$140=$B4)*ISNUMBER(INDEX(Inputs!$K$5:$AJ$140,0,MATCH(AD$2,Inputs!$K$4:$AJ$4,0))))+SUMPRODUCT((Inputs!$C$5:$C$140=$B4)*ISNUMBER(INDEX(Inputs!$K$5:$AJ$140,0,MATCH(AD$2,Inputs!$K$4:$AJ$4,0))))+SUMPRODUCT((Inputs!$E$5:$E$140=$B4)*ISNUMBER(INDEX(Inputs!$K$5:$AJ$140,0,MATCH(AD$2,Inputs!$K$4:$AJ$4,0))))=0,NA(),SUMPRODUCT((Inputs!$A$5:$A$140=$B4)*Inputs!$B$5:$B$140*(((Inputs!$G$5:$G$140="moeda")+(Inputs!$G$5:$G$140="acoes"))*Inputs!$B$1+((Inputs!$G$5:$G$140<>"moeda")*(Inputs!$G$5:$G$140<>"acoes")))*INDEX(Inputs!$K$5:$AJ$140,0,MATCH(AD$2,Inputs!$K$4:$AJ$4,0)))+SUMPRODUCT((Inputs!$C$5:$C$140=$B4)*Inputs!$D$5:$D$140*(((Inputs!$G$5:$G$140="moeda")+(Inputs!$G$5:$G$140="acoes"))*Inputs!$B$1+((Inputs!$G$5:$G$140<>"moeda")*(Inputs!$G$5:$G$140<>"acoes")))*INDEX(Inputs!$K$5:$AJ$140,0,MATCH(AD$2,Inputs!$K$4:$AJ$4,0)))+SUMPRODUCT((Inputs!$E$5:$E$140=$B4)*Inputs!$F$5:$F$140*(((Inputs!$G$5:$G$140="moeda")+(Inputs!$G$5:$G$140="acoes"))*Inputs!$B$1+((Inputs!$G$5:$G$140<>"moeda")*(Inputs!$G$5:$G$140<>"acoes")))*INDEX(Inputs!$K$5:$AJ$140,0,MATCH(AD$2,Inputs!$K$4:$AJ$4,0))))) -> 1690.594 | AE4: =IF(ISNA(MATCH(AE$2,Inputs!$K$4:$AJ$4,0)),NA(),IF(SUMPRODUCT((Inputs!$A$5:$A$140=$B4)*ISNUMBER(INDEX(Inputs!$K$5:$AJ$140,0,MATCH(AE$2,Inputs!$K$4:$AJ$4,0))))+SUMPRODUCT((Inputs!$C$5:$C$140=$B4)*ISNUMBER(INDEX(Inputs!$K$5:$AJ$140,0,MATCH(AE$2,Inputs!$K$4:$AJ$4,0))))+SUMPRODUCT((Inputs!$E$5:$E$140=$B4)*ISNUMBER(INDEX(Inputs!$K$5:$AJ$140,0,MATCH(AE$2,Inputs!$K$4:$AJ$4,0))))=0,NA(),SUMPRODUCT((Inputs!$A$5:$A$140=$B4)*Inputs!$B$5:$B$140*(((Inputs!$G$5:$G$140="moeda")+(Inputs!$G$5:$G$140="acoes"))*Inputs!$B$1+((Inputs!$G$5:$G$140<>"moeda")*(Inputs!$G$5:$G$140<>"acoes")))*INDEX(Inputs!$K$5:$AJ$140,0,MATCH(AE$2,Inputs!$K$4:$AJ$4,0)))+SUMPRODUCT((Inputs!$C$5:$C$140=$B4)*Inputs!$D$5:$D$140*(((Inputs!$G$5:$G$140="moeda")+(Inputs!$G$5:$G$140="acoes"))*Inputs!$B$1+((Inputs!$G$5:$G$140<>"moeda")*(Inputs!$G$5:$G$140<>"acoes")))*INDEX(Inputs!$K$5:$AJ$140,0,MATCH(AE$2,Inputs!$K$4:$AJ$4,0)))+SUMPRODUCT((Inputs!$E$5:$E$140=$B4)*Inputs!$F$5:$F$140*(((Inputs!$G$5:$G$140="moeda")+(Inputs!$G$5:$G$140="acoes"))*Inputs!$B$1+((Inputs!$G$5:$G$140<>"moeda")*(Inputs!$G$5:$G$140<>"acoes")))*INDEX(Inputs!$K$5:$AJ$140,0,MATCH(AE$2,Inputs!$K$4:$AJ$4,0))))) -> #N/A | AF4: =IF(ISNA(MATCH(AF$2,Inputs!$K$4:$AJ$4,0)),NA(),IF(SUMPRODUCT((Inputs!$A$5:$A$140=$B4)*ISNUMBER(INDEX(Inputs!$K$5:$AJ$140,0,MATCH(AF$2,Inputs!$K$4:$AJ$4,0))))+SUMPRODUCT((Inputs!$C$5:$C$140=$B4)*ISNUMBER(INDEX(Inputs!$K$5:$AJ$140,0,MATCH(AF$2,Inputs!$K$4:$AJ$4,0))))+SUMPRODUCT((Inputs!$E$5:$E$140=$B4)*ISNUMBER(INDEX(Inputs!$K$5:$AJ$140,0,MATCH(AF$2,Inputs!$K$4:$AJ$4,0))))=0,NA(),SUMPRODUCT((Inputs!$A$5:$A$140=$B4)*Inputs!$B$5:$B$140*(((Inputs!$G$5:$G$140="moeda")+(Inputs!$G$5:$G$140="acoes"))*Inputs!$B$1+((Inputs!$G$5:$G$140<>"moeda")*(Inputs!$G$5:$G$140<>"acoes")))*INDEX(Inputs!$K$5:$AJ$140,0,MATCH(AF$2,Inputs!$K$4:$AJ$4,0)))+SUMPRODUCT((Inputs!$C$5:$C$140=$B4)*Inputs!$D$5:$D$140*(((Inputs!$G$5:$G$140="moeda")+(Inputs!$G$5:$G$140="acoes"))*Inputs!$B$1+((Inputs!$G$5:$G$140<>"moeda")*(Inputs!$G$5:$G$140<>"acoes")))*INDEX(Inputs!$K$5:$AJ$140,0,MATCH(AF$2,Inputs!$K$4:$AJ$4,0)))+SUMPRODUCT((Inputs!$E$5:$E$140=$B4)*Inputs!$F$5:$F$140*(((Inputs!$G$5:$G$140="moeda")+(Inputs!$G$5:$G$140="acoes"))*Inputs!$B$1+((Inputs!$G$5:$G$140<>"moeda")*(Inputs!$G$5:$G$140<>"acoes")))*INDEX(Inputs!$K$5:$AJ$140,0,MATCH(AF$2,Inputs!$K$4:$AJ$4,0))))) -> #N/A | AG4: =SUM(AC4:AF4) -> #N/A | AH4: =IF(ISNA(MATCH(AH$2,Inputs!$K$4:$AJ$4,0)),NA(),IF(SUMPRODUCT((Inputs!$A$5:$A$140=$B4)*ISNUMBER(INDEX(Inputs!$K$5:$AJ$140,0,MATCH(AH$2,Inputs!$K$4:$AJ$4,0))))+SUMPRODUCT((Inputs!$C$5:$C$140=$B4)*ISNUMBER(INDEX(Inputs!$K$5:$AJ$140,0,MATCH(AH$2,Inputs!$K$4:$AJ$4,0))))+SUMPRODUCT((Inputs!$E$5:$E$140=$B4)*ISNUMBER(INDEX(Inputs!$K$5:$AJ$140,0,MATCH(AH$2,Inputs!$K$4:$AJ$4,0))))=0,NA(),SUMPRODUCT((Inputs!$A$5:$A$140=$B4)*Inputs!$B$5:$B$140*(((Inputs!$G$5:$G$140="moeda")+(Inputs!$G$5:$G$140="acoes"))*Inputs!$B$1+((Inputs!$G$5:$G$140<>"moeda")*(Inputs!$G$5:$G$140<>"acoes")))*INDEX(Inputs!$K$5:$AJ$140,0,MATCH(AH$2,Inputs!$K$4:$AJ$4,0)))+SUMPRODUCT((Inputs!$C$5:$C$140=$B4)*Inputs!$D$5:$D$140*(((Inputs!$G$5:$G$140="moeda")+(Inputs!$G$5:$G$140="acoes"))*Inputs!$B$1+((Inputs!$G$5:$G$140<>"moeda")*(Inputs!$G$5:$G$140<>"acoes")))*INDEX(Inputs!$K$5:$AJ$140,0,MATCH(AH$2,Inputs!$K$4:$AJ$4,0)))+SUMPRODUCT((Inputs!$E$5:$E$140=$B4)*Inputs!$F$5:$F$140*(((Inputs!$G$5:$G$140="moeda")+(Inputs!$G$5:$G$140="acoes"))*Inputs!$B$1+((Inputs!$G$5:$G$140<>"moeda")*(Inputs!$G$5:$G$140<>"acoes")))*INDEX(Inputs!$K$5:$AJ$140,0,MATCH(AH$2,Inputs!$K$4:$AJ$4,0))))) -> 227.321 | AI4: =IF(ISNA(MATCH(AI$2,Inputs!$K$4:$AJ$4,0)),NA(),IF(SUMPRODUCT((Inputs!$A$5:$A$140=$B4)*ISNUMBER(INDEX(Inputs!$K$5:$AJ$140,0,MATCH(AI$2,Inputs!$K$4:$AJ$4,0))))+SUMPRODUCT((Inputs!$C$5:$C$140=$B4)*ISNUMBER(INDEX(Inputs!$K$5:$AJ$140,0,MATCH(AI$2,Inputs!$K$4:$AJ$4,0))))+SUMPRODUCT((Inputs!$E$5:$E$140=$B4)*ISNUMBER(INDEX(Inputs!$K$5:$AJ$140,0,MATCH(AI$2,Inputs!$K$4:$AJ$4,0))))=0,NA(),SUMPRODUCT((Inputs!$A$5:$A$140=$B4)*Inputs!$B$5:$B$140*(((Inputs!$G$5:$G$140="moeda")+(Inputs!$G$5:$G$140="acoes"))*Inputs!$B$1+((Inputs!$G$5:$G$140<>"moeda")*(Inputs!$G$5:$G$140<>"acoes")))*INDEX(Inputs!$K$5:$AJ$140,0,MATCH(AI$2,Inputs!$K$4:$AJ$4,0)))+SUMPRODUCT((Inputs!$C$5:$C$140=$B4)*Inputs!$D$5:$D$140*(((Inputs!$G$5:$G$140="moeda")+(Inputs!$G$5:$G$140="acoes"))*Inputs!$B$1+((Inputs!$G$5:$G$140<>"moeda")*(Inputs!$G$5:$G$140<>"acoes")))*INDEX(Inputs!$K$5:$AJ$140,0,MATCH(AI$2,Inputs!$K$4:$AJ$4,0)))+SUMPRODUCT((Inputs!$E$5:$E$140=$B4)*Inputs!$F$5:$F$140*(((Inputs!$G$5:$G$140="moeda")+(Inputs!$G$5:$G$140="acoes"))*Inputs!$B$1+((Inputs!$G$5:$G$140<>"moeda")*(Inputs!$G$5:$G$140<>"acoes")))*INDEX(Inputs!$K$5:$AJ$140,0,MATCH(AI$2,Inputs!$K$4:$AJ$4,0))))) -> 246.204 | AJ4: =IF(ISNA(MATCH(AJ$2,Inputs!$K$4:$AJ$4,0)),NA(),IF(SUMPRODUCT((Inputs!$A$5:$A$140=$B4)*ISNUMBER(INDEX(Inputs!$K$5:$AJ$140,0,MATCH(AJ$2,Inputs!$K$4:$AJ$4,0))))+SUMPRODUCT((Inputs!$C$5:$C$140=$B4)*ISNUMBER(INDEX(Inputs!$K$5:$AJ$140,0,MATCH(AJ$2,Inputs!$K$4:$AJ$4,0))))+SUMPRODUCT((Inputs!$E$5:$E$140=$B4)*ISNUMBER(INDEX(Inputs!$K$5:$AJ$140,0,MATCH(AJ$2,Inputs!$K$4:$AJ$4,0))))=0,NA(),SUMPRODUCT((Inputs!$A$5:$A$140=$B4)*Inputs!$B$5:$B$140*(((Inputs!$G$5:$G$140="moeda")+(Inputs!$G$5:$G$140="acoes"))*Inputs!$B$1+((Inputs!$G$5:$G$140<>"moeda")*(Inputs!$G$5:$G$140<>"acoes")))*INDEX(Inputs!$K$5:$AJ$140,0,MATCH(AJ$2,Inputs!$K$4:$AJ$4,0)))+SUMPRODUCT((Inputs!$C$5:$C$140=$B4)*Inputs!$D$5:$D$140*(((Inputs!$G$5:$G$140="moeda")+(Inputs!$G$5:$G$140="acoes"))*Inputs!$B$1+((Inputs!$G$5:$G$140<>"moeda")*(Inputs!$G$5:$G$140<>"acoes")))*INDEX(Inputs!$K$5:$AJ$140,0,MATCH(AJ$2,Inputs!$K$4:$AJ$4,0)))+SUMPRODUCT((Inputs!$E$5:$E$140=$B4)*Inputs!$F$5:$F$140*(((Inputs!$G$5:$G$140="moeda")+(Inputs!$G$5:$G$140="acoes"))*Inputs!$B$1+((Inputs!$G$5:$G$140<>"moeda")*(Inputs!$G$5:$G$140<>"acoes")))*INDEX(Inputs!$K$5:$AJ$140,0,MATCH(AJ$2,Inputs!$K$4:$AJ$4,0))))) -> 325.898 | AK4: =IF(ISNA(MATCH(AK$2,Inputs!$K$4:$AJ$4,0)),NA(),IF(SUMPRODUCT((Inputs!$A$5:$A$140=$B4)*ISNUMBER(INDEX(Inputs!$K$5:$AJ$140,0,MATCH(AK$2,Inputs!$K$4:$AJ$4,0))))+SUMPRODUCT((Inputs!$C$5:$C$140=$B4)*ISNUMBER(INDEX(Inputs!$K$5:$AJ$140,0,MATCH(AK$2,Inputs!$K$4:$AJ$4,0))))+SUMPRODUCT((Inputs!$E$5:$E$140=$B4)*ISNUMBER(INDEX(Inputs!$K$5:$AJ$140,0,MATCH(AK$2,Inputs!$K$4:$AJ$4,0))))=0,NA(),SUMPRODUCT((Inputs!$A$5:$A$140=$B4)*Inputs!$B$5:$B$140*(((Inputs!$G$5:$G$140="moeda")+(Inputs!$G$5:$G$140="acoes"))*Inputs!$B$1+((Inputs!$G$5:$G$140<>"moeda")*(Inputs!$G$5:$G$140<>"acoes")))*INDEX(Inputs!$K$5:$AJ$140,0,MATCH(AK$2,Inputs!$K$4:$AJ$4,0)))+SUMPRODUCT((Inputs!$C$5:$C$140=$B4)*Inputs!$D$5:$D$140*(((Inputs!$G$5:$G$140="moeda")+(Inputs!$G$5:$G$140="acoes"))*Inputs!$B$1+((Inputs!$G$5:$G$140<>"moeda")*(Inputs!$G$5:$G$140<>"acoes")))*INDEX(Inputs!$K$5:$AJ$140,0,MATCH(AK$2,Inputs!$K$4:$AJ$4,0)))+SUMPRODUCT((Inputs!$E$5:$E$140=$B4)*Inputs!$F$5:$F$140*(((Inputs!$G$5:$G$140="moeda")+(Inputs!$G$5:$G$140="acoes"))*Inputs!$B$1+((Inputs!$G$5:$G$140<>"moeda")*(Inputs!$G$5:$G$140<>"acoes")))*INDEX(Inputs!$K$5:$AJ$140,0,MATCH(AK$2,Inputs!$K$4:$AJ$4,0))))) -> 345.259 | AL4: =SUM(AH4:AK4) -> 1144.682
B5: 2 | C5: COGS (cash) | D5: =IF(ISNA(MATCH(D$2,Inputs!$K$4:$AJ$4,0)),NA(),IF(SUMPRODUCT((Inputs!$A$5:$A$140=$B5)*ISNUMBER(INDEX(Inputs!$K$5:$AJ$140,0,MATCH(D$2,Inputs!$K$4:$AJ$4,0))))+SUMPRODUCT((Inputs!$C$5:$C$140=$B5)*ISNUMBER(INDEX(Inputs!$K$5:$AJ$140,0,MATCH(D$2,Inputs!$K$4:$AJ$4,0))))+SUMPRODUCT((Inputs!$E$5:$E$140=$B5)*ISNUMBER(INDEX(Inputs!$K$5:$AJ$140,0,MATCH(D$2,Inputs!$K$4:$AJ$4,0))))=0,NA(),SUMPRODUCT((Inputs!$A$5:$A$140=$B5)*Inputs!$B$5:$B$140*(((Inputs!$G$5:$G$140="moeda")+(Inputs!$G$5:$G$140="acoes"))*Inputs!$B$1+((Inputs!$G$5:$G$140<>"moeda")*(Inputs!$G$5:$G$140<>"acoes")))*INDEX(Inputs!$K$5:$AJ$140,0,MATCH(D$2,Inputs!$K$4:$AJ$4,0)))+SUMPRODUCT((Inputs!$C$5:$C$140=$B5)*Inputs!$D$5:$D$140*(((Inputs!$G$5:$G$140="moeda")+(Inputs!$G$5:$G$140="acoes"))*Inputs!$B$1+((Inputs!$G$5:$G$140<>"moeda")*(Inputs!$G$5:$G$140<>"acoes")))*INDEX(Inputs!$K$5:$AJ$140,0,MATCH(D$2,Inputs!$K$4:$AJ$4,0)))+SUMPRODUCT((Inputs!$E$5:$E$140=$B5)*Inputs!$F$5:$F$140*(((Inputs!$G$5:$G$140="moeda")+(Inputs!$G$5:$G$140="acoes"))*Inputs!$B$1+((Inputs!$G$5:$G$140<>"moeda")*(Inputs!$G$5:$G$140<>"acoes")))*INDEX(Inputs!$K$5:$AJ$140,0,MATCH(D$2,Inputs!$K$4:$AJ$4,0))))) -> -218.944 | E5: =IF(ISNA(MATCH(E$2,Inputs!$K$4:$AJ$4,0)),NA(),IF(SUMPRODUCT((Inputs!$A$5:$A$140=$B5)*ISNUMBER(INDEX(Inputs!$K$5:$AJ$140,0,MATCH(E$2,Inputs!$K$4:$AJ$4,0))))+SUMPRODUCT((Inputs!$C$5:$C$140=$B5)*ISNUMBER(INDEX(Inputs!$K$5:$AJ$140,0,MATCH(E$2,Inputs!$K$4:$AJ$4,0))))+SUMPRODUCT((Inputs!$E$5:$E$140=$B5)*ISNUMBER(INDEX(Inputs!$K$5:$AJ$140,0,MATCH(E$2,Inputs!$K$4:$AJ$4,0))))=0,NA(),SUMPRODUCT((Inputs!$A$5:$A$140=$B5)*Inputs!$B$5:$B$140*(((Inputs!$G$5:$G$140="moeda")+(Inputs!$G$5:$G$140="acoes"))*Inputs!$B$1+((Inputs!$G$5:$G$140<>"moeda")*(Inputs!$G$5:$G$140<>"acoes")))*INDEX(Inputs!$K$5:$AJ$140,0,MATCH(E$2,Inputs!$K$4:$AJ$4,0)))+SUMPRODUCT((Inputs!$C$5:$C$140=$B5)*Inputs!$D$5:$D$140*(((Inputs!$G$5:$G$140="moeda")+(Inputs!$G$5:$G$140="acoes"))*Inputs!$B$1+((Inputs!$G$5:$G$140<>"moeda")*(Inputs!$G$5:$G$140<>"acoes")))*INDEX(Inputs!$K$5:$AJ$140,0,MATCH(E$2,Inputs!$K$4:$AJ$4,0)))+SUMPRODUCT((Inputs!$E$5:$E$140=$B5)*Inputs!$F$5:$F$140*(((Inputs!$G$5:$G$140="moeda")+(Inputs!$G$5:$G$140="acoes"))*Inputs!$B$1+((Inputs!$G$5:$G$140<>"moeda")*(Inputs!$G$5:$G$140<>"acoes")))*INDEX(Inputs!$K$5:$AJ$140,0,MATCH(E$2,Inputs!$K$4:$AJ$4,0))))) -> -288.421 | F5: =IF(ISNA(MATCH(F$2,Inputs!$K$4:$AJ$4,0)),NA(),IF(SUMPRODUCT((Inputs!$A$5:$A$140=$B5)*ISNUMBER(INDEX(Inputs!$K$5:$AJ$140,0,MATCH(F$2,Inputs!$K$4:$AJ$4,0))))+SUMPRODUCT((Inputs!$C$5:$C$140=$B5)*ISNUMBER(INDEX(Inputs!$K$5:$AJ$140,0,MATCH(F$2,Inputs!$K$4:$AJ$4,0))))+SUMPRODUCT((Inputs!$E$5:$E$140=$B5)*ISNUMBER(INDEX(Inputs!$K$5:$AJ$140,0,MATCH(F$2,Inputs!$K$4:$AJ$4,0))))=0,NA(),SUMPRODUCT((Inputs!$A$5:$A$140=$B5)*Inputs!$B$5:$B$140*(((Inputs!$G$5:$G$140="moeda")+(Inputs!$G$5:$G$140="acoes"))*Inputs!$B$1+((Inputs!$G$5:$G$140<>"moeda")*(Inputs!$G$5:$G$140<>"acoes")))*INDEX(Inputs!$K$5:$AJ$140,0,MATCH(F$2,Inputs!$K$4:$AJ$4,0)))+SUMPRODUCT((Inputs!$C$5:$C$140=$B5)*Inputs!$D$5:$D$140*(((Inputs!$G$5:$G$140="moeda")+(Inputs!$G$5:$G$140="acoes"))*Inputs!$B$1+((Inputs!$G$5:$G$140<>"moeda")*(Inputs!$G$5:$G$140<>"acoes")))*INDEX(Inputs!$K$5:$AJ$140,0,MATCH(F$2,Inputs!$K$4:$AJ$4,0)))+SUMPRODUCT((Inputs!$E$5:$E$140=$B5)*Inputs!$F$5:$F$140*(((Inputs!$G$5:$G$140="moeda")+(Inputs!$G$5:$G$140="acoes"))*Inputs!$B$1+((Inputs!$G$5:$G$140<>"moeda")*(Inputs!$G$5:$G$140<>"acoes")))*INDEX(Inputs!$K$5:$AJ$140,0,MATCH(F$2,Inputs!$K$4:$AJ$4,0))))) -> -281.47774 | G5: =IF(ISNA(MATCH(G$2,Inputs!$K$4:$AJ$4,0)),NA(),IF(SUMPRODUCT((Inputs!$A$5:$A$140=$B5)*ISNUMBER(INDEX(Inputs!$K$5:$AJ$140,0,MATCH(G$2,Inputs!$K$4:$AJ$4,0))))+SUMPRODUCT((Inputs!$C$5:$C$140=$B5)*ISNUMBER(INDEX(Inputs!$K$5:$AJ$140,0,MATCH(G$2,Inputs!$K$4:$AJ$4,0))))+SUMPRODUCT((Inputs!$E$5:$E$140=$B5)*ISNUMBER(INDEX(Inputs!$K$5:$AJ$140,0,MATCH(G$2,Inputs!$K$4:$AJ$4,0))))=0,NA(),SUMPRODUCT((Inputs!$A$5:$A$140=$B5)*Inputs!$B$5:$B$140*(((Inputs!$G$5:$G$140="moeda")+(Inputs!$G$5:$G$140="acoes"))*Inputs!$B$1+((Inputs!$G$5:$G$140<>"moeda")*(Inputs!$G$5:$G$140<>"acoes")))*INDEX(Inputs!$K$5:$AJ$140,0,MATCH(G$2,Inputs!$K$4:$AJ$4,0)))+SUMPRODUCT((Inputs!$C$5:$C$140=$B5)*Inputs!$D$5:$D$140*(((Inputs!$G$5:$G$140="moeda")+(Inputs!$G$5:$G$140="acoes"))*Inputs!$B$1+((Inputs!$G$5:$G$140<>"moeda")*(Inputs!$G$5:$G$140<>"acoes")))*INDEX(Inputs!$K$5:$AJ$140,0,MATCH(G$2,Inputs!$K$4:$AJ$4,0)))+SUMPRODUCT((Inputs!$E$5:$E$140=$B5)*Inputs!$F$5:$F$140*(((Inputs!$G$5:$G$140="moeda")+(Inputs!$G$5:$G$140="acoes"))*Inputs!$B$1+((Inputs!$G$5:$G$140<>"moeda")*(Inputs!$G$5:$G$140<>"acoes")))*INDEX(Inputs!$K$5:$AJ$140,0,MATCH(G$2,Inputs!$K$4:$AJ$4,0))))) -> -304.781 | H5: =SUM(D5:G5) -> -1093.6237 | I5: =IF(ISNA(MATCH(I$2,Inputs!$K$4:$AJ$4,0)),NA(),IF(SUMPRODUCT((Inputs!$A$5:$A$140=$B5)*ISNUMBER(INDEX(Inputs!$K$5:$AJ$140,0,MATCH(I$2,Inputs!$K$4:$AJ$4,0))))+SUMPRODUCT((Inputs!$C$5:$C$140=$B5)*ISNUMBER(INDEX(Inputs!$K$5:$AJ$140,0,MATCH(I$2,Inputs!$K$4:$AJ$4,0))))+SUMPRODUCT((Inputs!$E$5:$E$140=$B5)*ISNUMBER(INDEX(Inputs!$K$5:$AJ$140,0,MATCH(I$2,Inputs!$K$4:$AJ$4,0))))=0,NA(),SUMPRODUCT((Inputs!$A$5:$A$140=$B5)*Inputs!$B$5:$B$140*(((Inputs!$G$5:$G$140="moeda")+(Inputs!$G$5:$G$140="acoes"))*Inputs!$B$1+((Inputs!$G$5:$G$140<>"moeda")*(Inputs!$G$5:$G$140<>"acoes")))*INDEX(Inputs!$K$5:$AJ$140,0,MATCH(I$2,Inputs!$K$4:$AJ$4,0)))+SUMPRODUCT((Inputs!$C$5:$C$140=$B5)*Inputs!$D$5:$D$140*(((Inputs!$G$5:$G$140="moeda")+(Inputs!$G$5:$G$140="acoes"))*Inputs!$B$1+((Inputs!$G$5:$G$140<>"moeda")*(Inputs!$G$5:$G$140<>"acoes")))*INDEX(Inputs!$K$5:$AJ$140,0,MATCH(I$2,Inputs!$K$4:$AJ$4,0)))+SUMPRODUCT((Inputs!$E$5:$E$140=$B5)*Inputs!$F$5:$F$140*(((Inputs!$G$5:$G$140="moeda")+(Inputs!$G$5:$G$140="acoes"))*Inputs!$B$1+((Inputs!$G$5:$G$140<>"moeda")*(Inputs!$G$5:$G$140<>"acoes")))*INDEX(Inputs!$K$5:$AJ$140,0,MATCH(I$2,Inputs!$K$4:$AJ$4,0))))) -> -281.465 | J5: =IF(ISNA(MATCH(J$2,Inputs!$K$4:$AJ$4,0)),NA(),IF(SUMPRODUCT((Inputs!$A$5:$A$140=$B5)*ISNUMBER(INDEX(Inputs!$K$5:$AJ$140,0,MATCH(J$2,Inputs!$K$4:$AJ$4,0))))+SUMPRODUCT((Inputs!$C$5:$C$140=$B5)*ISNUMBER(INDEX(Inputs!$K$5:$AJ$140,0,MATCH(J$2,Inputs!$K$4:$AJ$4,0))))+SUMPRODUCT((Inputs!$E$5:$E$140=$B5)*ISNUMBER(INDEX(Inputs!$K$5:$AJ$140,0,MATCH(J$2,Inputs!$K$4:$AJ$4,0))))=0,NA(),SUMPRODUCT((Inputs!$A$5:$A$140=$B5)*Inputs!$B$5:$B$140*(((Inputs!$G$5:$G$140="moeda")+(Inputs!$G$5:$G$140="acoes"))*Inputs!$B$1+((Inputs!$G$5:$G$140<>"moeda")*(Inputs!$G$5:$G$140<>"acoes")))*INDEX(Inputs!$K$5:$AJ$140,0,MATCH(J$2,Inputs!$K$4:$AJ$4,0)))+SUMPRODUCT((Inputs!$C$5:$C$140=$B5)*Inputs!$D$5:$D$140*(((Inputs!$G$5:$G$140="moeda")+(Inputs!$G$5:$G$140="acoes"))*Inputs!$B$1+((Inputs!$G$5:$G$140<>"moeda")*(Inputs!$G$5:$G$140<>"acoes")))*INDEX(Inputs!$K$5:$AJ$140,0,MATCH(J$2,Inputs!$K$4:$AJ$4,0)))+SUMPRODUCT((Inputs!$E$5:$E$140=$B5)*Inputs!$F$5:$F$140*(((Inputs!$G$5:$G$140="moeda")+(Inputs!$G$5:$G$140="acoes"))*Inputs!$B$1+((Inputs!$G$5:$G$140<>"moeda")*(Inputs!$G$5:$G$140<>"acoes")))*INDEX(Inputs!$K$5:$AJ$140,0,MATCH(J$2,Inputs!$K$4:$AJ$4,0))))) -> -387.286 | K5: =IF(ISNA(MATCH(K$2,Inputs!$K$4:$AJ$4,0)),NA(),IF(SUMPRODUCT((Inputs!$A$5:$A$140=$B5)*ISNUMBER(INDEX(Inputs!$K$5:$AJ$140,0,MATCH(K$2,Inputs!$K$4:$AJ$4,0))))+SUMPRODUCT((Inputs!$C$5:$C$140=$B5)*ISNUMBER(INDEX(Inputs!$K$5:$AJ$140,0,MATCH(K$2,Inputs!$K$4:$AJ$4,0))))+SUMPRODUCT((Inputs!$E$5:$E$140=$B5)*ISNUMBER(INDEX(Inputs!$K$5:$AJ$140,0,MATCH(K$2,Inputs!$K$4:$AJ$4,0))))=0,NA(),SUMPRODUCT((Inputs!$A$5:$A$140=$B5)*Inputs!$B$5:$B$140*(((Inputs!$G$5:$G$140="moeda")+(Inputs!$G$5:$G$140="acoes"))*Inputs!$B$1+((Inputs!$G$5:$G$140<>"moeda")*(Inputs!$G$5:$G$140<>"acoes")))*INDEX(Inputs!$K$5:$AJ$140,0,MATCH(K$2,Inputs!$K$4:$AJ$4,0)))+SUMPRODUCT((Inputs!$C$5:$C$140=$B5)*Inputs!$D$5:$D$140*(((Inputs!$G$5:$G$140="moeda")+(Inputs!$G$5:$G$140="acoes"))*Inputs!$B$1+((Inputs!$G$5:$G$140<>"moeda")*(Inputs!$G$5:$G$140<>"acoes")))*INDEX(Inputs!$K$5:$AJ$140,0,MATCH(K$2,Inputs!$K$4:$AJ$4,0)))+SUMPRODUCT((Inputs!$E$5:$E$140=$B5)*Inputs!$F$5:$F$140*(((Inputs!$G$5:$G$140="moeda")+(Inputs!$G$5:$G$140="acoes"))*Inputs!$B$1+((Inputs!$G$5:$G$140<>"moeda")*(Inputs!$G$5:$G$140<>"acoes")))*INDEX(Inputs!$K$5:$AJ$140,0,MATCH(K$2,Inputs!$K$4:$AJ$4,0))))) -> -392.916 | L5: =IF(ISNA(MATCH(L$2,Inputs!$K$4:$AJ$4,0)),NA(),IF(SUMPRODUCT((Inputs!$A$5:$A$140=$B5)*ISNUMBER(INDEX(Inputs!$K$5:$AJ$140,0,MATCH(L$2,Inputs!$K$4:$AJ$4,0))))+SUMPRODUCT((Inputs!$C$5:$C$140=$B5)*ISNUMBER(INDEX(Inputs!$K$5:$AJ$140,0,MATCH(L$2,Inputs!$K$4:$AJ$4,0))))+SUMPRODUCT((Inputs!$E$5:$E$140=$B5)*ISNUMBER(INDEX(Inputs!$K$5:$AJ$140,0,MATCH(L$2,Inputs!$K$4:$AJ$4,0))))=0,NA(),SUMPRODUCT((Inputs!$A$5:$A$140=$B5)*Inputs!$B$5:$B$140*(((Inputs!$G$5:$G$140="moeda")+(Inputs!$G$5:$G$140="acoes"))*Inputs!$B$1+((Inputs!$G$5:$G$140<>"moeda")*(Inputs!$G$5:$G$140<>"acoes")))*INDEX(Inputs!$K$5:$AJ$140,0,MATCH(L$2,Inputs!$K$4:$AJ$4,0)))+SUMPRODUCT((Inputs!$C$5:$C$140=$B5)*Inputs!$D$5:$D$140*(((Inputs!$G$5:$G$140="moeda")+(Inputs!$G$5:$G$140="acoes"))*Inputs!$B$1+((Inputs!$G$5:$G$140<>"moeda")*(Inputs!$G$5:$G$140<>"acoes")))*INDEX(Inputs!$K$5:$AJ$140,0,MATCH(L$2,Inputs!$K$4:$AJ$4,0)))+SUMPRODUCT((Inputs!$E$5:$E$140=$B5)*Inputs!$F$5:$F$140*(((Inputs!$G$5:$G$140="moeda")+(Inputs!$G$5:$G$140="acoes"))*Inputs!$B$1+((Inputs!$G$5:$G$140<>"moeda")*(Inputs!$G$5:$G$140<>"acoes")))*INDEX(Inputs!$K$5:$AJ$140,0,MATCH(L$2,Inputs!$K$4:$AJ$4,0))))) -> -358.735 | M5: =SUM(I5:L5) -> -1420.402 | N5: =IF(ISNA(MATCH(N$2,Inputs!$K$4:$AJ$4,0)),NA(),IF(SUMPRODUCT((Inputs!$A$5:$A$140=$B5)*ISNUMBER(INDEX(Inputs!$K$5:$AJ$140,0,MATCH(N$2,Inputs!$K$4:$AJ$4,0))))+SUMPRODUCT((Inputs!$C$5:$C$140=$B5)*ISNUMBER(INDEX(Inputs!$K$5:$AJ$140,0,MATCH(N$2,Inputs!$K$4:$AJ$4,0))))+SUMPRODUCT((Inputs!$E$5:$E$140=$B5)*ISNUMBER(INDEX(Inputs!$K$5:$AJ$140,0,MATCH(N$2,Inputs!$K$4:$AJ$4,0))))=0,NA(),SUMPRODUCT((Inputs!$A$5:$A$140=$B5)*Inputs!$B$5:$B$140*(((Inputs!$G$5:$G$140="moeda")+(Inputs!$G$5:$G$140="acoes"))*Inputs!$B$1+((Inputs!$G$5:$G$140<>"moeda")*(Inputs!$G$5:$G$140<>"acoes")))*INDEX(Inputs!$K$5:$AJ$140,0,MATCH(N$2,Inputs!$K$4:$AJ$4,0)))+SUMPRODUCT((Inputs!$C$5:$C$140=$B5)*Inputs!$D$5:$D$140*(((Inputs!$G$5:$G$140="moeda")+(Inputs!$G$5:$G$140="acoes"))*Inputs!$B$1+((Inputs!$G$5:$G$140<>"moeda")*(Inputs!$G$5:$G$140<>"acoes")))*INDEX(Inputs!$K$5:$AJ$140,0,MATCH(N$2,Inputs!$K$4:$AJ$4,0)))+SUMPRODUCT((Inputs!$E$5:$E$140=$B5)*Inputs!$F$5:$F$140*(((Inputs!$G$5:$G$140="moeda")+(Inputs!$G$5:$G$140="acoes"))*Inputs!$B$1+((Inputs!$G$5:$G$140<>"moeda")*(Inputs!$G$5:$G$140<>"acoes")))*INDEX(Inputs!$K$5:$AJ$140,0,MATCH(N$2,Inputs!$K$4:$AJ$4,0))))) -> -371.794 | O5: =IF(ISNA(MATCH(O$2,Inputs!$K$4:$AJ$4,0)),NA(),IF(SUMPRODUCT((Inputs!$A$5:$A$140=$B5)*ISNUMBER(INDEX(Inputs!$K$5:$AJ$140,0,MATCH(O$2,Inputs!$K$4:$AJ$4,0))))+SUMPRODUCT((Inputs!$C$5:$C$140=$B5)*ISNUMBER(INDEX(Inputs!$K$5:$AJ$140,0,MATCH(O$2,Inputs!$K$4:$AJ$4,0))))+SUMPRODUCT((Inputs!$E$5:$E$140=$B5)*ISNUMBER(INDEX(Inputs!$K$5:$AJ$140,0,MATCH(O$2,Inputs!$K$4:$AJ$4,0))))=0,NA(),SUMPRODUCT((Inputs!$A$5:$A$140=$B5)*Inputs!$B$5:$B$140*(((Inputs!$G$5:$G$140="moeda")+(Inputs!$G$5:$G$140="acoes"))*Inputs!$B$1+((Inputs!$G$5:$G$140<>"moeda")*(Inputs!$G$5:$G$140<>"acoes")))*INDEX(Inputs!$K$5:$AJ$140,0,MATCH(O$2,Inputs!$K$4:$AJ$4,0)))+SUMPRODUCT((Inputs!$C$5:$C$140=$B5)*Inputs!$D$5:$D$140*(((Inputs!$G$5:$G$140="moeda")+(Inputs!$G$5:$G$140="acoes"))*Inputs!$B$1+((Inputs!$G$5:$G$140<>"moeda")*(Inputs!$G$5:$G$140<>"acoes")))*INDEX(Inputs!$K$5:$AJ$140,0,MATCH(O$2,Inputs!$K$4:$AJ$4,0)))+SUMPRODUCT((Inputs!$E$5:$E$140=$B5)*Inputs!$F$5:$F$140*(((Inputs!$G$5:$G$140="moeda")+(Inputs!$G$5:$G$140="acoes"))*Inputs!$B$1+((Inputs!$G$5:$G$140<>"moeda")*(Inputs!$G$5:$G$140<>"acoes")))*INDEX(Inputs!$K$5:$AJ$140,0,MATCH(O$2,Inputs!$K$4:$AJ$4,0))))) -> -453.192 | P5: =IF(ISNA(MATCH(P$2,Inputs!$K$4:$AJ$4,0)),NA(),IF(SUMPRODUCT((Inputs!$A$5:$A$140=$B5)*ISNUMBER(INDEX(Inputs!$K$5:$AJ$140,0,MATCH(P$2,Inputs!$K$4:$AJ$4,0))))+SUMPRODUCT((Inputs!$C$5:$C$140=$B5)*ISNUMBER(INDEX(Inputs!$K$5:$AJ$140,0,MATCH(P$2,Inputs!$K$4:$AJ$4,0))))+SUMPRODUCT((Inputs!$E$5:$E$140=$B5)*ISNUMBER(INDEX(Inputs!$K$5:$AJ$140,0,MATCH(P$2,Inputs!$K$4:$AJ$4,0))))=0,NA(),SUMPRODUCT((Inputs!$A$5:$A$140=$B5)*Inputs!$B$5:$B$140*(((Inputs!$G$5:$G$140="moeda")+(Inputs!$G$5:$G$140="acoes"))*Inputs!$B$1+((Inputs!$G$5:$G$140<>"moeda")*(Inputs!$G$5:$G$140<>"acoes")))*INDEX(Inputs!$K$5:$AJ$140,0,MATCH(P$2,Inputs!$K$4:$AJ$4,0)))+SUMPRODUCT((Inputs!$C$5:$C$140=$B5)*Inputs!$D$5:$D$140*(((Inputs!$G$5:$G$140="moeda")+(Inputs!$G$5:$G$140="acoes"))*Inputs!$B$1+((Inputs!$G$5:$G$140<>"moeda")*(Inputs!$G$5:$G$140<>"acoes")))*INDEX(Inputs!$K$5:$AJ$140,0,MATCH(P$2,Inputs!$K$4:$AJ$4,0)))+SUMPRODUCT((Inputs!$E$5:$E$140=$B5)*Inputs!$F$5:$F$140*(((Inputs!$G$5:$G$140="moeda")+(Inputs!$G$5:$G$140="acoes"))*Inputs!$B$1+((Inputs!$G$5:$G$140<>"moeda")*(Inputs!$G$5:$G$140<>"acoes")))*INDEX(Inputs!$K$5:$AJ$140,0,MATCH(P$2,Inputs!$K$4:$AJ$4,0))))) -> -467.971 | Q5: =IF(ISNA(MATCH(Q$2,Inputs!$K$4:$AJ$4,0)),NA(),IF(SUMPRODUCT((Inputs!$A$5:$A$140=$B5)*ISNUMBER(INDEX(Inputs!$K$5:$AJ$140,0,MATCH(Q$2,Inputs!$K$4:$AJ$4,0))))+SUMPRODUCT((Inputs!$C$5:$C$140=$B5)*ISNUMBER(INDEX(Inputs!$K$5:$AJ$140,0,MATCH(Q$2,Inputs!$K$4:$AJ$4,0))))+SUMPRODUCT((Inputs!$E$5:$E$140=$B5)*ISNUMBER(INDEX(Inputs!$K$5:$AJ$140,0,MATCH(Q$2,Inputs!$K$4:$AJ$4,0))))=0,NA(),SUMPRODUCT((Inputs!$A$5:$A$140=$B5)*Inputs!$B$5:$B$140*(((Inputs!$G$5:$G$140="moeda")+(Inputs!$G$5:$G$140="acoes"))*Inputs!$B$1+((Inputs!$G$5:$G$140<>"moeda")*(Inputs!$G$5:$G$140<>"acoes")))*INDEX(Inputs!$K$5:$AJ$140,0,MATCH(Q$2,Inputs!$K$4:$AJ$4,0)))+SUMPRODUCT((Inputs!$C$5:$C$140=$B5)*Inputs!$D$5:$D$140*(((Inputs!$G$5:$G$140="moeda")+(Inputs!$G$5:$G$140="acoes"))*Inputs!$B$1+((Inputs!$G$5:$G$140<>"moeda")*(Inputs!$G$5:$G$140<>"acoes")))*INDEX(Inputs!$K$5:$AJ$140,0,MATCH(Q$2,Inputs!$K$4:$AJ$4,0)))+SUMPRODUCT((Inputs!$E$5:$E$140=$B5)*Inputs!$F$5:$F$140*(((Inputs!$G$5:$G$140="moeda")+(Inputs!$G$5:$G$140="acoes"))*Inputs!$B$1+((Inputs!$G$5:$G$140<>"moeda")*(Inputs!$G$5:$G$140<>"acoes")))*INDEX(Inputs!$K$5:$AJ$140,0,MATCH(Q$2,Inputs!$K$4:$AJ$4,0))))) -> -497.862 | R5: =SUM(N5:Q5) -> -1790.819 | S5: =IF(ISNA(MATCH(S$2,Inputs!$K$4:$AJ$4,0)),NA(),IF(SUMPRODUCT((Inputs!$A$5:$A$140=$B5)*ISNUMBER(INDEX(Inputs!$K$5:$AJ$140,0,MATCH(S$2,Inputs!$K$4:$AJ$4,0))))+SUMPRODUCT((Inputs!$C$5:$C$140=$B5)*ISNUMBER(INDEX(Inputs!$K$5:$AJ$140,0,MATCH(S$2,Inputs!$K$4:$AJ$4,0))))+SUMPRODUCT((Inputs!$E$5:$E$140=$B5)*ISNUMBER(INDEX(Inputs!$K$5:$AJ$140,0,MATCH(S$2,Inputs!$K$4:$AJ$4,0))))=0,NA(),SUMPRODUCT((Inputs!$A$5:$A$140=$B5)*Inputs!$B$5:$B$140*(((Inputs!$G$5:$G$140="moeda")+(Inputs!$G$5:$G$140="acoes"))*Inputs!$B$1+((Inputs!$G$5:$G$140<>"moeda")*(Inputs!$G$5:$G$140<>"acoes")))*INDEX(Inputs!$K$5:$AJ$140,0,MATCH(S$2,Inputs!$K$4:$AJ$4,0)))+SUMPRODUCT((Inputs!$C$5:$C$140=$B5)*Inputs!$D$5:$D$140*(((Inputs!$G$5:$G$140="moeda")+(Inputs!$G$5:$G$140="acoes"))*Inputs!$B$1+((Inputs!$G$5:$G$140<>"moeda")*(Inputs!$G$5:$G$140<>"acoes")))*INDEX(Inputs!$K$5:$AJ$140,0,MATCH(S$2,Inputs!$K$4:$AJ$4,0)))+SUMPRODUCT((Inputs!$E$5:$E$140=$B5)*Inputs!$F$5:$F$140*(((Inputs!$G$5:$G$140="moeda")+(Inputs!$G$5:$G$140="acoes"))*Inputs!$B$1+((Inputs!$G$5:$G$140<>"moeda")*(Inputs!$G$5:$G$140<>"acoes")))*INDEX(Inputs!$K$5:$AJ$140,0,MATCH(S$2,Inputs!$K$4:$AJ$4,0))))) -> -520.773 | T5: =IF(ISNA(MATCH(T$2,Inputs!$K$4:$AJ$4,0)),NA(),IF(SUMPRODUCT((Inputs!$A$5:$A$140=$B5)*ISNUMBER(INDEX(Inputs!$K$5:$AJ$140,0,MATCH(T$2,Inputs!$K$4:$AJ$4,0))))+SUMPRODUCT((Inputs!$C$5:$C$140=$B5)*ISNUMBER(INDEX(Inputs!$K$5:$AJ$140,0,MATCH(T$2,Inputs!$K$4:$AJ$4,0))))+SUMPRODUCT((Inputs!$E$5:$E$140=$B5)*ISNUMBER(INDEX(Inputs!$K$5:$AJ$140,0,MATCH(T$2,Inputs!$K$4:$AJ$4,0))))=0,NA(),SUMPRODUCT((Inputs!$A$5:$A$140=$B5)*Inputs!$B$5:$B$140*(((Inputs!$G$5:$G$140="moeda")+(Inputs!$G$5:$G$140="acoes"))*Inputs!$B$1+((Inputs!$G$5:$G$140<>"moeda")*(Inputs!$G$5:$G$140<>"acoes")))*INDEX(Inputs!$K$5:$AJ$140,0,MATCH(T$2,Inputs!$K$4:$AJ$4,0)))+SUMPRODUCT((Inputs!$C$5:$C$140=$B5)*Inputs!$D$5:$D$140*(((Inputs!$G$5:$G$140="moeda")+(Inputs!$G$5:$G$140="acoes"))*Inputs!$B$1+((Inputs!$G$5:$G$140<>"moeda")*(Inputs!$G$5:$G$140<>"acoes")))*INDEX(Inputs!$K$5:$AJ$140,0,MATCH(T$2,Inputs!$K$4:$AJ$4,0)))+SUMPRODUCT((Inputs!$E$5:$E$140=$B5)*Inputs!$F$5:$F$140*(((Inputs!$G$5:$G$140="moeda")+(Inputs!$G$5:$G$140="acoes"))*Inputs!$B$1+((Inputs!$G$5:$G$140<>"moeda")*(Inputs!$G$5:$G$140<>"acoes")))*INDEX(Inputs!$K$5:$AJ$140,0,MATCH(T$2,Inputs!$K$4:$AJ$4,0))))) -> -615.554 | U5: =IF(ISNA(MATCH(U$2,Inputs!$K$4:$AJ$4,0)),NA(),IF(SUMPRODUCT((Inputs!$A$5:$A$140=$B5)*ISNUMBER(INDEX(Inputs!$K$5:$AJ$140,0,MATCH(U$2,Inputs!$K$4:$AJ$4,0))))+SUMPRODUCT((Inputs!$C$5:$C$140=$B5)*ISNUMBER(INDEX(Inputs!$K$5:$AJ$140,0,MATCH(U$2,Inputs!$K$4:$AJ$4,0))))+SUMPRODUCT((Inputs!$E$5:$E$140=$B5)*ISNUMBER(INDEX(Inputs!$K$5:$AJ$140,0,MATCH(U$2,Inputs!$K$4:$AJ$4,0))))=0,NA(),SUMPRODUCT((Inputs!$A$5:$A$140=$B5)*Inputs!$B$5:$B$140*(((Inputs!$G$5:$G$140="moeda")+(Inputs!$G$5:$G$140="acoes"))*Inputs!$B$1+((Inputs!$G$5:$G$140<>"moeda")*(Inputs!$G$5:$G$140<>"acoes")))*INDEX(Inputs!$K$5:$AJ$140,0,MATCH(U$2,Inputs!$K$4:$AJ$4,0)))+SUMPRODUCT((Inputs!$C$5:$C$140=$B5)*Inputs!$D$5:$D$140*(((Inputs!$G$5:$G$140="moeda")+(Inputs!$G$5:$G$140="acoes"))*Inputs!$B$1+((Inputs!$G$5:$G$140<>"moeda")*(Inputs!$G$5:$G$140<>"acoes")))*INDEX(Inputs!$K$5:$AJ$140,0,MATCH(U$2,Inputs!$K$4:$AJ$4,0)))+SUMPRODUCT((Inputs!$E$5:$E$140=$B5)*Inputs!$F$5:$F$140*(((Inputs!$G$5:$G$140="moeda")+(Inputs!$G$5:$G$140="acoes"))*Inputs!$B$1+((Inputs!$G$5:$G$140<>"moeda")*(Inputs!$G$5:$G$140<>"acoes")))*INDEX(Inputs!$K$5:$AJ$140,0,MATCH(U$2,Inputs!$K$4:$AJ$4,0))))) -> -646.426 | V5: =IF(ISNA(MATCH(V$2,Inputs!$K$4:$AJ$4,0)),NA(),IF(SUMPRODUCT((Inputs!$A$5:$A$140=$B5)*ISNUMBER(INDEX(Inputs!$K$5:$AJ$140,0,MATCH(V$2,Inputs!$K$4:$AJ$4,0))))+SUMPRODUCT((Inputs!$C$5:$C$140=$B5)*ISNUMBER(INDEX(Inputs!$K$5:$AJ$140,0,MATCH(V$2,Inputs!$K$4:$AJ$4,0))))+SUMPRODUCT((Inputs!$E$5:$E$140=$B5)*ISNUMBER(INDEX(Inputs!$K$5:$AJ$140,0,MATCH(V$2,Inputs!$K$4:$AJ$4,0))))=0,NA(),SUMPRODUCT((Inputs!$A$5:$A$140=$B5)*Inputs!$B$5:$B$140*(((Inputs!$G$5:$G$140="moeda")+(Inputs!$G$5:$G$140="acoes"))*Inputs!$B$1+((Inputs!$G$5:$G$140<>"moeda")*(Inputs!$G$5:$G$140<>"acoes")))*INDEX(Inputs!$K$5:$AJ$140,0,MATCH(V$2,Inputs!$K$4:$AJ$4,0)))+SUMPRODUCT((Inputs!$C$5:$C$140=$B5)*Inputs!$D$5:$D$140*(((Inputs!$G$5:$G$140="moeda")+(Inputs!$G$5:$G$140="acoes"))*Inputs!$B$1+((Inputs!$G$5:$G$140<>"moeda")*(Inputs!$G$5:$G$140<>"acoes")))*INDEX(Inputs!$K$5:$AJ$140,0,MATCH(V$2,Inputs!$K$4:$AJ$4,0)))+SUMPRODUCT((Inputs!$E$5:$E$140=$B5)*Inputs!$F$5:$F$140*(((Inputs!$G$5:$G$140="moeda")+(Inputs!$G$5:$G$140="acoes"))*Inputs!$B$1+((Inputs!$G$5:$G$140<>"moeda")*(Inputs!$G$5:$G$140<>"acoes")))*INDEX(Inputs!$K$5:$AJ$140,0,MATCH(V$2,Inputs!$K$4:$AJ$4,0))))) -> -630.617 | W5: =SUM(S5:V5) -> -2413.37 | X5: =IF(ISNA(MATCH(X$2,Inputs!$K$4:$AJ$4,0)),NA(),IF(SUMPRODUCT((Inputs!$A$5:$A$140=$B5)*ISNUMBER(INDEX(Inputs!$K$5:$AJ$140,0,MATCH(X$2,Inputs!$K$4:$AJ$4,0))))+SUMPRODUCT((Inputs!$C$5:$C$140=$B5)*ISNUMBER(INDEX(Inputs!$K$5:$AJ$140,0,MATCH(X$2,Inputs!$K$4:$AJ$4,0))))+SUMPRODUCT((Inputs!$E$5:$E$140=$B5)*ISNUMBER(INDEX(Inputs!$K$5:$AJ$140,0,MATCH(X$2,Inputs!$K$4:$AJ$4,0))))=0,NA(),SUMPRODUCT((Inputs!$A$5:$A$140=$B5)*Inputs!$B$5:$B$140*(((Inputs!$G$5:$G$140="moeda")+(Inputs!$G$5:$G$140="acoes"))*Inputs!$B$1+((Inputs!$G$5:$G$140<>"moeda")*(Inputs!$G$5:$G$140<>"acoes")))*INDEX(Inputs!$K$5:$AJ$140,0,MATCH(X$2,Inputs!$K$4:$AJ$4,0)))+SUMPRODUCT((Inputs!$C$5:$C$140=$B5)*Inputs!$D$5:$D$140*(((Inputs!$G$5:$G$140="moeda")+(Inputs!$G$5:$G$140="acoes"))*Inputs!$B$1+((Inputs!$G$5:$G$140<>"moeda")*(Inputs!$G$5:$G$140<>"acoes")))*INDEX(Inputs!$K$5:$AJ$140,0,MATCH(X$2,Inputs!$K$4:$AJ$4,0)))+SUMPRODUCT((Inputs!$E$5:$E$140=$B5)*Inputs!$F$5:$F$140*(((Inputs!$G$5:$G$140="moeda")+(Inputs!$G$5:$G$140="acoes"))*Inputs!$B$1+((Inputs!$G$5:$G$140<>"moeda")*(Inputs!$G$5:$G$140<>"acoes")))*INDEX(Inputs!$K$5:$AJ$140,0,MATCH(X$2,Inputs!$K$4:$AJ$4,0))))) -> -741.296 | Y5: =IF(ISNA(MATCH(Y$2,Inputs!$K$4:$AJ$4,0)),NA(),IF(SUMPRODUCT((Inputs!$A$5:$A$140=$B5)*ISNUMBER(INDEX(Inputs!$K$5:$AJ$140,0,MATCH(Y$2,Inputs!$K$4:$AJ$4,0))))+SUMPRODUCT((Inputs!$C$5:$C$140=$B5)*ISNUMBER(INDEX(Inputs!$K$5:$AJ$140,0,MATCH(Y$2,Inputs!$K$4:$AJ$4,0))))+SUMPRODUCT((Inputs!$E$5:$E$140=$B5)*ISNUMBER(INDEX(Inputs!$K$5:$AJ$140,0,MATCH(Y$2,Inputs!$K$4:$AJ$4,0))))=0,NA(),SUMPRODUCT((Inputs!$A$5:$A$140=$B5)*Inputs!$B$5:$B$140*(((Inputs!$G$5:$G$140="moeda")+(Inputs!$G$5:$G$140="acoes"))*Inputs!$B$1+((Inputs!$G$5:$G$140<>"moeda")*(Inputs!$G$5:$G$140<>"acoes")))*INDEX(Inputs!$K$5:$AJ$140,0,MATCH(Y$2,Inputs!$K$4:$AJ$4,0)))+SUMPRODUCT((Inputs!$C$5:$C$140=$B5)*Inputs!$D$5:$D$140*(((Inputs!$G$5:$G$140="moeda")+(Inputs!$G$5:$G$140="acoes"))*Inputs!$B$1+((Inputs!$G$5:$G$140<>"moeda")*(Inputs!$G$5:$G$140<>"acoes")))*INDEX(Inputs!$K$5:$AJ$140,0,MATCH(Y$2,Inputs!$K$4:$AJ$4,0)))+SUMPRODUCT((Inputs!$E$5:$E$140=$B5)*Inputs!$F$5:$F$140*(((Inputs!$G$5:$G$140="moeda")+(Inputs!$G$5:$G$140="acoes"))*Inputs!$B$1+((Inputs!$G$5:$G$140<>"moeda")*(Inputs!$G$5:$G$140<>"acoes")))*INDEX(Inputs!$K$5:$AJ$140,0,MATCH(Y$2,Inputs!$K$4:$AJ$4,0))))) -> -813.823 | Z5: =IF(ISNA(MATCH(Z$2,Inputs!$K$4:$AJ$4,0)),NA(),IF(SUMPRODUCT((Inputs!$A$5:$A$140=$B5)*ISNUMBER(INDEX(Inputs!$K$5:$AJ$140,0,MATCH(Z$2,Inputs!$K$4:$AJ$4,0))))+SUMPRODUCT((Inputs!$C$5:$C$140=$B5)*ISNUMBER(INDEX(Inputs!$K$5:$AJ$140,0,MATCH(Z$2,Inputs!$K$4:$AJ$4,0))))+SUMPRODUCT((Inputs!$E$5:$E$140=$B5)*ISNUMBER(INDEX(Inputs!$K$5:$AJ$140,0,MATCH(Z$2,Inputs!$K$4:$AJ$4,0))))=0,NA(),SUMPRODUCT((Inputs!$A$5:$A$140=$B5)*Inputs!$B$5:$B$140*(((Inputs!$G$5:$G$140="moeda")+(Inputs!$G$5:$G$140="acoes"))*Inputs!$B$1+((Inputs!$G$5:$G$140<>"moeda")*(Inputs!$G$5:$G$140<>"acoes")))*INDEX(Inputs!$K$5:$AJ$140,0,MATCH(Z$2,Inputs!$K$4:$AJ$4,0)))+SUMPRODUCT((Inputs!$C$5:$C$140=$B5)*Inputs!$D$5:$D$140*(((Inputs!$G$5:$G$140="moeda")+(Inputs!$G$5:$G$140="acoes"))*Inputs!$B$1+((Inputs!$G$5:$G$140<>"moeda")*(Inputs!$G$5:$G$140<>"acoes")))*INDEX(Inputs!$K$5:$AJ$140,0,MATCH(Z$2,Inputs!$K$4:$AJ$4,0)))+SUMPRODUCT((Inputs!$E$5:$E$140=$B5)*Inputs!$F$5:$F$140*(((Inputs!$G$5:$G$140="moeda")+(Inputs!$G$5:$G$140="acoes"))*Inputs!$B$1+((Inputs!$G$5:$G$140<>"moeda")*(Inputs!$G$5:$G$140<>"acoes")))*INDEX(Inputs!$K$5:$AJ$140,0,MATCH(Z$2,Inputs!$K$4:$AJ$4,0))))) -> -850.699 | AA5: =IF(ISNA(MATCH(AA$2,Inputs!$K$4:$AJ$4,0)),NA(),IF(SUMPRODUCT((Inputs!$A$5:$A$140=$B5)*ISNUMBER(INDEX(Inputs!$K$5:$AJ$140,0,MATCH(AA$2,Inputs!$K$4:$AJ$4,0))))+SUMPRODUCT((Inputs!$C$5:$C$140=$B5)*ISNUMBER(INDEX(Inputs!$K$5:$AJ$140,0,MATCH(AA$2,Inputs!$K$4:$AJ$4,0))))+SUMPRODUCT((Inputs!$E$5:$E$140=$B5)*ISNUMBER(INDEX(Inputs!$K$5:$AJ$140,0,MATCH(AA$2,Inputs!$K$4:$AJ$4,0))))=0,NA(),SUMPRODUCT((Inputs!$A$5:$A$140=$B5)*Inputs!$B$5:$B$140*(((Inputs!$G$5:$G$140="moeda")+(Inputs!$G$5:$G$140="acoes"))*Inputs!$B$1+((Inputs!$G$5:$G$140<>"moeda")*(Inputs!$G$5:$G$140<>"acoes")))*INDEX(Inputs!$K$5:$AJ$140,0,MATCH(AA$2,Inputs!$K$4:$AJ$4,0)))+SUMPRODUCT((Inputs!$C$5:$C$140=$B5)*Inputs!$D$5:$D$140*(((Inputs!$G$5:$G$140="moeda")+(Inputs!$G$5:$G$140="acoes"))*Inputs!$B$1+((Inputs!$G$5:$G$140<>"moeda")*(Inputs!$G$5:$G$140<>"acoes")))*INDEX(Inputs!$K$5:$AJ$140,0,MATCH(AA$2,Inputs!$K$4:$AJ$4,0)))+SUMPRODUCT((Inputs!$E$5:$E$140=$B5)*Inputs!$F$5:$F$140*(((Inputs!$G$5:$G$140="moeda")+(Inputs!$G$5:$G$140="acoes"))*Inputs!$B$1+((Inputs!$G$5:$G$140<>"moeda")*(Inputs!$G$5:$G$140<>"acoes")))*INDEX(Inputs!$K$5:$AJ$140,0,MATCH(AA$2,Inputs!$K$4:$AJ$4,0))))) -> -847.019 | AB5: =SUM(X5:AA5) -> -3252.837 | AC5: =IF(ISNA(MATCH(AC$2,Inputs!$K$4:$AJ$4,0)),NA(),IF(SUMPRODUCT((Inputs!$A$5:$A$140=$B5)*ISNUMBER(INDEX(Inputs!$K$5:$AJ$140,0,MATCH(AC$2,Inputs!$K$4:$AJ$4,0))))+SUMPRODUCT((Inputs!$C$5:$C$140=$B5)*ISNUMBER(INDEX(Inputs!$K$5:$AJ$140,0,MATCH(AC$2,Inputs!$K$4:$AJ$4,0))))+SUMPRODUCT((Inputs!$E$5:$E$140=$B5)*ISNUMBER(INDEX(Inputs!$K$5:$AJ$140,0,MATCH(AC$2,Inputs!$K$4:$AJ$4,0))))=0,NA(),SUMPRODUCT((Inputs!$A$5:$A$140=$B5)*Inputs!$B$5:$B$140*(((Inputs!$G$5:$G$140="moeda")+(Inputs!$G$5:$G$140="acoes"))*Inputs!$B$1+((Inputs!$G$5:$G$140<>"moeda")*(Inputs!$G$5:$G$140<>"acoes")))*INDEX(Inputs!$K$5:$AJ$140,0,MATCH(AC$2,Inputs!$K$4:$AJ$4,0)))+SUMPRODUCT((Inputs!$C$5:$C$140=$B5)*Inputs!$D$5:$D$140*(((Inputs!$G$5:$G$140="moeda")+(Inputs!$G$5:$G$140="acoes"))*Inputs!$B$1+((Inputs!$G$5:$G$140<>"moeda")*(Inputs!$G$5:$G$140<>"acoes")))*INDEX(Inputs!$K$5:$AJ$140,0,MATCH(AC$2,Inputs!$K$4:$AJ$4,0)))+SUMPRODUCT((Inputs!$E$5:$E$140=$B5)*Inputs!$F$5:$F$140*(((Inputs!$G$5:$G$140="moeda")+(Inputs!$G$5:$G$140="acoes"))*Inputs!$B$1+((Inputs!$G$5:$G$140<>"moeda")*(Inputs!$G$5:$G$140<>"acoes")))*INDEX(Inputs!$K$5:$AJ$140,0,MATCH(AC$2,Inputs!$K$4:$AJ$4,0))))) -> -982.915 | AD5: =IF(ISNA(MATCH(AD$2,Inputs!$K$4:$AJ$4,0)),NA(),IF(SUMPRODUCT((Inputs!$A$5:$A$140=$B5)*ISNUMBER(INDEX(Inputs!$K$5:$AJ$140,0,MATCH(AD$2,Inputs!$K$4:$AJ$4,0))))+SUMPRODUCT((Inputs!$C$5:$C$140=$B5)*ISNUMBER(INDEX(Inputs!$K$5:$AJ$140,0,MATCH(AD$2,Inputs!$K$4:$AJ$4,0))))+SUMPRODUCT((Inputs!$E$5:$E$140=$B5)*ISNUMBER(INDEX(Inputs!$K$5:$AJ$140,0,MATCH(AD$2,Inputs!$K$4:$AJ$4,0))))=0,NA(),SUMPRODUCT((Inputs!$A$5:$A$140=$B5)*Inputs!$B$5:$B$140*(((Inputs!$G$5:$G$140="moeda")+(Inputs!$G$5:$G$140="acoes"))*Inputs!$B$1+((Inputs!$G$5:$G$140<>"moeda")*(Inputs!$G$5:$G$140<>"acoes")))*INDEX(Inputs!$K$5:$AJ$140,0,MATCH(AD$2,Inputs!$K$4:$AJ$4,0)))+SUMPRODUCT((Inputs!$C$5:$C$140=$B5)*Inputs!$D$5:$D$140*(((Inputs!$G$5:$G$140="moeda")+(Inputs!$G$5:$G$140="acoes"))*Inputs!$B$1+((Inputs!$G$5:$G$140<>"moeda")*(Inputs!$G$5:$G$140<>"acoes")))*INDEX(Inputs!$K$5:$AJ$140,0,MATCH(AD$2,Inputs!$K$4:$AJ$4,0)))+SUMPRODUCT((Inputs!$E$5:$E$140=$B5)*Inputs!$F$5:$F$140*(((Inputs!$G$5:$G$140="moeda")+(Inputs!$G$5:$G$140="acoes"))*Inputs!$B$1+((Inputs!$G$5:$G$140<>"moeda")*(Inputs!$G$5:$G$140<>"acoes")))*INDEX(Inputs!$K$5:$AJ$140,0,MATCH(AD$2,Inputs!$K$4:$AJ$4,0))))) -> -1022.232 | AE5: =IF(ISNA(MATCH(AE$2,Inputs!$K$4:$AJ$4,0)),NA(),IF(SUMPRODUCT((Inputs!$A$5:$A$140=$B5)*ISNUMBER(INDEX(Inputs!$K$5:$AJ$140,0,MATCH(AE$2,Inputs!$K$4:$AJ$4,0))))+SUMPRODUCT((Inputs!$C$5:$C$140=$B5)*ISNUMBER(INDEX(Inputs!$K$5:$AJ$140,0,MATCH(AE$2,Inputs!$K$4:$AJ$4,0))))+SUMPRODUCT((Inputs!$E$5:$E$140=$B5)*ISNUMBER(INDEX(Inputs!$K$5:$AJ$140,0,MATCH(AE$2,Inputs!$K$4:$AJ$4,0))))=0,NA(),SUMPRODUCT((Inputs!$A$5:$A$140=$B5)*Inputs!$B$5:$B$140*(((Inputs!$G$5:$G$140="moeda")+(Inputs!$G$5:$G$140="acoes"))*Inputs!$B$1+((Inputs!$G$5:$G$140<>"moeda")*(Inputs!$G$5:$G$140<>"acoes")))*INDEX(Inputs!$K$5:$AJ$140,0,MATCH(AE$2,Inputs!$K$4:$AJ$4,0)))+SUMPRODUCT((Inputs!$C$5:$C$140=$B5)*Inputs!$D$5:$D$140*(((Inputs!$G$5:$G$140="moeda")+(Inputs!$G$5:$G$140="acoes"))*Inputs!$B$1+((Inputs!$G$5:$G$140<>"moeda")*(Inputs!$G$5:$G$140<>"acoes")))*INDEX(Inputs!$K$5:$AJ$140,0,MATCH(AE$2,Inputs!$K$4:$AJ$4,0)))+SUMPRODUCT((Inputs!$E$5:$E$140=$B5)*Inputs!$F$5:$F$140*(((Inputs!$G$5:$G$140="moeda")+(Inputs!$G$5:$G$140="acoes"))*Inputs!$B$1+((Inputs!$G$5:$G$140<>"moeda")*(Inputs!$G$5:$G$140<>"acoes")))*INDEX(Inputs!$K$5:$AJ$140,0,MATCH(AE$2,Inputs!$K$4:$AJ$4,0))))) -> #N/A | AF5: =IF(ISNA(MATCH(AF$2,Inputs!$K$4:$AJ$4,0)),NA(),IF(SUMPRODUCT((Inputs!$A$5:$A$140=$B5)*ISNUMBER(INDEX(Inputs!$K$5:$AJ$140,0,MATCH(AF$2,Inputs!$K$4:$AJ$4,0))))+SUMPRODUCT((Inputs!$C$5:$C$140=$B5)*ISNUMBER(INDEX(Inputs!$K$5:$AJ$140,0,MATCH(AF$2,Inputs!$K$4:$AJ$4,0))))+SUMPRODUCT((Inputs!$E$5:$E$140=$B5)*ISNUMBER(INDEX(Inputs!$K$5:$AJ$140,0,MATCH(AF$2,Inputs!$K$4:$AJ$4,0))))=0,NA(),SUMPRODUCT((Inputs!$A$5:$A$140=$B5)*Inputs!$B$5:$B$140*(((Inputs!$G$5:$G$140="moeda")+(Inputs!$G$5:$G$140="acoes"))*Inputs!$B$1+((Inputs!$G$5:$G$140<>"moeda")*(Inputs!$G$5:$G$140<>"acoes")))*INDEX(Inputs!$K$5:$AJ$140,0,MATCH(AF$2,Inputs!$K$4:$AJ$4,0)))+SUMPRODUCT((Inputs!$C$5:$C$140=$B5)*Inputs!$D$5:$D$140*(((Inputs!$G$5:$G$140="moeda")+(Inputs!$G$5:$G$140="acoes"))*Inputs!$B$1+((Inputs!$G$5:$G$140<>"moeda")*(Inputs!$G$5:$G$140<>"acoes")))*INDEX(Inputs!$K$5:$AJ$140,0,MATCH(AF$2,Inputs!$K$4:$AJ$4,0)))+SUMPRODUCT((Inputs!$E$5:$E$140=$B5)*Inputs!$F$5:$F$140*(((Inputs!$G$5:$G$140="moeda")+(Inputs!$G$5:$G$140="acoes"))*Inputs!$B$1+((Inputs!$G$5:$G$140<>"moeda")*(Inputs!$G$5:$G$140<>"acoes")))*INDEX(Inputs!$K$5:$AJ$140,0,MATCH(AF$2,Inputs!$K$4:$AJ$4,0))))) -> #N/A | AG5: =SUM(AC5:AF5) -> #N/A | AH5: =IF(ISNA(MATCH(AH$2,Inputs!$K$4:$AJ$4,0)),NA(),IF(SUMPRODUCT((Inputs!$A$5:$A$140=$B5)*ISNUMBER(INDEX(Inputs!$K$5:$AJ$140,0,MATCH(AH$2,Inputs!$K$4:$AJ$4,0))))+SUMPRODUCT((Inputs!$C$5:$C$140=$B5)*ISNUMBER(INDEX(Inputs!$K$5:$AJ$140,0,MATCH(AH$2,Inputs!$K$4:$AJ$4,0))))+SUMPRODUCT((Inputs!$E$5:$E$140=$B5)*ISNUMBER(INDEX(Inputs!$K$5:$AJ$140,0,MATCH(AH$2,Inputs!$K$4:$AJ$4,0))))=0,NA(),SUMPRODUCT((Inputs!$A$5:$A$140=$B5)*Inputs!$B$5:$B$140*(((Inputs!$G$5:$G$140="moeda")+(Inputs!$G$5:$G$140="acoes"))*Inputs!$B$1+((Inputs!$G$5:$G$140<>"moeda")*(Inputs!$G$5:$G$140<>"acoes")))*INDEX(Inputs!$K$5:$AJ$140,0,MATCH(AH$2,Inputs!$K$4:$AJ$4,0)))+SUMPRODUCT((Inputs!$C$5:$C$140=$B5)*Inputs!$D$5:$D$140*(((Inputs!$G$5:$G$140="moeda")+(Inputs!$G$5:$G$140="acoes"))*Inputs!$B$1+((Inputs!$G$5:$G$140<>"moeda")*(Inputs!$G$5:$G$140<>"acoes")))*INDEX(Inputs!$K$5:$AJ$140,0,MATCH(AH$2,Inputs!$K$4:$AJ$4,0)))+SUMPRODUCT((Inputs!$E$5:$E$140=$B5)*Inputs!$F$5:$F$140*(((Inputs!$G$5:$G$140="moeda")+(Inputs!$G$5:$G$140="acoes"))*Inputs!$B$1+((Inputs!$G$5:$G$140<>"moeda")*(Inputs!$G$5:$G$140<>"acoes")))*INDEX(Inputs!$K$5:$AJ$140,0,MATCH(AH$2,Inputs!$K$4:$AJ$4,0))))) -> -149.181 | AI5: =IF(ISNA(MATCH(AI$2,Inputs!$K$4:$AJ$4,0)),NA(),IF(SUMPRODUCT((Inputs!$A$5:$A$140=$B5)*ISNUMBER(INDEX(Inputs!$K$5:$AJ$140,0,MATCH(AI$2,Inputs!$K$4:$AJ$4,0))))+SUMPRODUCT((Inputs!$C$5:$C$140=$B5)*ISNUMBER(INDEX(Inputs!$K$5:$AJ$140,0,MATCH(AI$2,Inputs!$K$4:$AJ$4,0))))+SUMPRODUCT((Inputs!$E$5:$E$140=$B5)*ISNUMBER(INDEX(Inputs!$K$5:$AJ$140,0,MATCH(AI$2,Inputs!$K$4:$AJ$4,0))))=0,NA(),SUMPRODUCT((Inputs!$A$5:$A$140=$B5)*Inputs!$B$5:$B$140*(((Inputs!$G$5:$G$140="moeda")+(Inputs!$G$5:$G$140="acoes"))*Inputs!$B$1+((Inputs!$G$5:$G$140<>"moeda")*(Inputs!$G$5:$G$140<>"acoes")))*INDEX(Inputs!$K$5:$AJ$140,0,MATCH(AI$2,Inputs!$K$4:$AJ$4,0)))+SUMPRODUCT((Inputs!$C$5:$C$140=$B5)*Inputs!$D$5:$D$140*(((Inputs!$G$5:$G$140="moeda")+(Inputs!$G$5:$G$140="acoes"))*Inputs!$B$1+((Inputs!$G$5:$G$140<>"moeda")*(Inputs!$G$5:$G$140<>"acoes")))*INDEX(Inputs!$K$5:$AJ$140,0,MATCH(AI$2,Inputs!$K$4:$AJ$4,0)))+SUMPRODUCT((Inputs!$E$5:$E$140=$B5)*Inputs!$F$5:$F$140*(((Inputs!$G$5:$G$140="moeda")+(Inputs!$G$5:$G$140="acoes"))*Inputs!$B$1+((Inputs!$G$5:$G$140<>"moeda")*(Inputs!$G$5:$G$140<>"acoes")))*INDEX(Inputs!$K$5:$AJ$140,0,MATCH(AI$2,Inputs!$K$4:$AJ$4,0))))) -> -159.137 | AJ5: =IF(ISNA(MATCH(AJ$2,Inputs!$K$4:$AJ$4,0)),NA(),IF(SUMPRODUCT((Inputs!$A$5:$A$140=$B5)*ISNUMBER(INDEX(Inputs!$K$5:$AJ$140,0,MATCH(AJ$2,Inputs!$K$4:$AJ$4,0))))+SUMPRODUCT((Inputs!$C$5:$C$140=$B5)*ISNUMBER(INDEX(Inputs!$K$5:$AJ$140,0,MATCH(AJ$2,Inputs!$K$4:$AJ$4,0))))+SUMPRODUCT((Inputs!$E$5:$E$140=$B5)*ISNUMBER(INDEX(Inputs!$K$5:$AJ$140,0,MATCH(AJ$2,Inputs!$K$4:$AJ$4,0))))=0,NA(),SUMPRODUCT((Inputs!$A$5:$A$140=$B5)*Inputs!$B$5:$B$140*(((Inputs!$G$5:$G$140="moeda")+(Inputs!$G$5:$G$140="acoes"))*Inputs!$B$1+((Inputs!$G$5:$G$140<>"moeda")*(Inputs!$G$5:$G$140<>"acoes")))*INDEX(Inputs!$K$5:$AJ$140,0,MATCH(AJ$2,Inputs!$K$4:$AJ$4,0)))+SUMPRODUCT((Inputs!$C$5:$C$140=$B5)*Inputs!$D$5:$D$140*(((Inputs!$G$5:$G$140="moeda")+(Inputs!$G$5:$G$140="acoes"))*Inputs!$B$1+((Inputs!$G$5:$G$140<>"moeda")*(Inputs!$G$5:$G$140<>"acoes")))*INDEX(Inputs!$K$5:$AJ$140,0,MATCH(AJ$2,Inputs!$K$4:$AJ$4,0)))+SUMPRODUCT((Inputs!$E$5:$E$140=$B5)*Inputs!$F$5:$F$140*(((Inputs!$G$5:$G$140="moeda")+(Inputs!$G$5:$G$140="acoes"))*Inputs!$B$1+((Inputs!$G$5:$G$140<>"moeda")*(Inputs!$G$5:$G$140<>"acoes")))*INDEX(Inputs!$K$5:$AJ$140,0,MATCH(AJ$2,Inputs!$K$4:$AJ$4,0))))) -> -202.541 | AK5: =IF(ISNA(MATCH(AK$2,Inputs!$K$4:$AJ$4,0)),NA(),IF(SUMPRODUCT((Inputs!$A$5:$A$140=$B5)*ISNUMBER(INDEX(Inputs!$K$5:$AJ$140,0,MATCH(AK$2,Inputs!$K$4:$AJ$4,0))))+SUMPRODUCT((Inputs!$C$5:$C$140=$B5)*ISNUMBER(INDEX(Inputs!$K$5:$AJ$140,0,MATCH(AK$2,Inputs!$K$4:$AJ$4,0))))+SUMPRODUCT((Inputs!$E$5:$E$140=$B5)*ISNUMBER(INDEX(Inputs!$K$5:$AJ$140,0,MATCH(AK$2,Inputs!$K$4:$AJ$4,0))))=0,NA(),SUMPRODUCT((Inputs!$A$5:$A$140=$B5)*Inputs!$B$5:$B$140*(((Inputs!$G$5:$G$140="moeda")+(Inputs!$G$5:$G$140="acoes"))*Inputs!$B$1+((Inputs!$G$5:$G$140<>"moeda")*(Inputs!$G$5:$G$140<>"acoes")))*INDEX(Inputs!$K$5:$AJ$140,0,MATCH(AK$2,Inputs!$K$4:$AJ$4,0)))+SUMPRODUCT((Inputs!$C$5:$C$140=$B5)*Inputs!$D$5:$D$140*(((Inputs!$G$5:$G$140="moeda")+(Inputs!$G$5:$G$140="acoes"))*Inputs!$B$1+((Inputs!$G$5:$G$140<>"moeda")*(Inputs!$G$5:$G$140<>"acoes")))*INDEX(Inputs!$K$5:$AJ$140,0,MATCH(AK$2,Inputs!$K$4:$AJ$4,0)))+SUMPRODUCT((Inputs!$E$5:$E$140=$B5)*Inputs!$F$5:$F$140*(((Inputs!$G$5:$G$140="moeda")+(Inputs!$G$5:$G$140="acoes"))*Inputs!$B$1+((Inputs!$G$5:$G$140<>"moeda")*(Inputs!$G$5:$G$140<>"acoes")))*INDEX(Inputs!$K$5:$AJ$140,0,MATCH(AK$2,Inputs!$K$4:$AJ$4,0))))) -> -205.433 | AL5: =SUM(AH5:AK5) -> -716.292
B6: 3 | C6: SG&A and Other (cash) | D6: =IF(ISNA(MATCH(D$2,Inputs!$K$4:$AJ$4,0)),NA(),IF(SUMPRODUCT((Inputs!$A$5:$A$140=$B6)*ISNUMBER(INDEX(Inputs!$K$5:$AJ$140,0,MATCH(D$2,Inputs!$K$4:$AJ$4,0))))+SUMPRODUCT((Inputs!$C$5:$C$140=$B6)*ISNUMBER(INDEX(Inputs!$K$5:$AJ$140,0,MATCH(D$2,Inputs!$K$4:$AJ$4,0))))+SUMPRODUCT((Inputs!$E$5:$E$140=$B6)*ISNUMBER(INDEX(Inputs!$K$5:$AJ$140,0,MATCH(D$2,Inputs!$K$4:$AJ$4,0))))=0,NA(),SUMPRODUCT((Inputs!$A$5:$A$140=$B6)*Inputs!$B$5:$B$140*(((Inputs!$G$5:$G$140="moeda")+(Inputs!$G$5:$G$140="acoes"))*Inputs!$B$1+((Inputs!$G$5:$G$140<>"moeda")*(Inputs!$G$5:$G$140<>"acoes")))*INDEX(Inputs!$K$5:$AJ$140,0,MATCH(D$2,Inputs!$K$4:$AJ$4,0)))+SUMPRODUCT((Inputs!$C$5:$C$140=$B6)*Inputs!$D$5:$D$140*(((Inputs!$G$5:$G$140="moeda")+(Inputs!$G$5:$G$140="acoes"))*Inputs!$B$1+((Inputs!$G$5:$G$140<>"moeda")*(Inputs!$G$5:$G$140<>"acoes")))*INDEX(Inputs!$K$5:$AJ$140,0,MATCH(D$2,Inputs!$K$4:$AJ$4,0)))+SUMPRODUCT((Inputs!$E$5:$E$140=$B6)*Inputs!$F$5:$F$140*(((Inputs!$G$5:$G$140="moeda")+(Inputs!$G$5:$G$140="acoes"))*Inputs!$B$1+((Inputs!$G$5:$G$140<>"moeda")*(Inputs!$G$5:$G$140<>"acoes")))*INDEX(Inputs!$K$5:$AJ$140,0,MATCH(D$2,Inputs!$K$4:$AJ$4,0))))) -> -57.164347 | E6: =IF(ISNA(MATCH(E$2,Inputs!$K$4:$AJ$4,0)),NA(),IF(SUMPRODUCT((Inputs!$A$5:$A$140=$B6)*ISNUMBER(INDEX(Inputs!$K$5:$AJ$140,0,MATCH(E$2,Inputs!$K$4:$AJ$4,0))))+SUMPRODUCT((Inputs!$C$5:$C$140=$B6)*ISNUMBER(INDEX(Inputs!$K$5:$AJ$140,0,MATCH(E$2,Inputs!$K$4:$AJ$4,0))))+SUMPRODUCT((Inputs!$E$5:$E$140=$B6)*ISNUMBER(INDEX(Inputs!$K$5:$AJ$140,0,MATCH(E$2,Inputs!$K$4:$AJ$4,0))))=0,NA(),SUMPRODUCT((Inputs!$A$5:$A$140=$B6)*Inputs!$B$5:$B$140*(((Inputs!$G$5:$G$140="moeda")+(Inputs!$G$5:$G$140="acoes"))*Inputs!$B$1+((Inputs!$G$5:$G$140<>"moeda")*(Inputs!$G$5:$G$140<>"acoes")))*INDEX(Inputs!$K$5:$AJ$140,0,MATCH(E$2,Inputs!$K$4:$AJ$4,0)))+SUMPRODUCT((Inputs!$C$5:$C$140=$B6)*Inputs!$D$5:$D$140*(((Inputs!$G$5:$G$140="moeda")+(Inputs!$G$5:$G$140="acoes"))*Inputs!$B$1+((Inputs!$G$5:$G$140<>"moeda")*(Inputs!$G$5:$G$140<>"acoes")))*INDEX(Inputs!$K$5:$AJ$140,0,MATCH(E$2,Inputs!$K$4:$AJ$4,0)))+SUMPRODUCT((Inputs!$E$5:$E$140=$B6)*Inputs!$F$5:$F$140*(((Inputs!$G$5:$G$140="moeda")+(Inputs!$G$5:$G$140="acoes"))*Inputs!$B$1+((Inputs!$G$5:$G$140<>"moeda")*(Inputs!$G$5:$G$140<>"acoes")))*INDEX(Inputs!$K$5:$AJ$140,0,MATCH(E$2,Inputs!$K$4:$AJ$4,0))))) -> -73.545941 | F6: =IF(ISNA(MATCH(F$2,Inputs!$K$4:$AJ$4,0)),NA(),IF(SUMPRODUCT((Inputs!$A$5:$A$140=$B6)*ISNUMBER(INDEX(Inputs!$K$5:$AJ$140,0,MATCH(F$2,Inputs!$K$4:$AJ$4,0))))+SUMPRODUCT((Inputs!$C$5:$C$140=$B6)*ISNUMBER(INDEX(Inputs!$K$5:$AJ$140,0,MATCH(F$2,Inputs!$K$4:$AJ$4,0))))+SUMPRODUCT((Inputs!$E$5:$E$140=$B6)*ISNUMBER(INDEX(Inputs!$K$5:$AJ$140,0,MATCH(F$2,Inputs!$K$4:$AJ$4,0))))=0,NA(),SUMPRODUCT((Inputs!$A$5:$A$140=$B6)*Inputs!$B$5:$B$140*(((Inputs!$G$5:$G$140="moeda")+(Inputs!$G$5:$G$140="acoes"))*Inputs!$B$1+((Inputs!$G$5:$G$140<>"moeda")*(Inputs!$G$5:$G$140<>"acoes")))*INDEX(Inputs!$K$5:$AJ$140,0,MATCH(F$2,Inputs!$K$4:$AJ$4,0)))+SUMPRODUCT((Inputs!$C$5:$C$140=$B6)*Inputs!$D$5:$D$140*(((Inputs!$G$5:$G$140="moeda")+(Inputs!$G$5:$G$140="acoes"))*Inputs!$B$1+((Inputs!$G$5:$G$140<>"moeda")*(Inputs!$G$5:$G$140<>"acoes")))*INDEX(Inputs!$K$5:$AJ$140,0,MATCH(F$2,Inputs!$K$4:$AJ$4,0)))+SUMPRODUCT((Inputs!$E$5:$E$140=$B6)*Inputs!$F$5:$F$140*(((Inputs!$G$5:$G$140="moeda")+(Inputs!$G$5:$G$140="acoes"))*Inputs!$B$1+((Inputs!$G$5:$G$140<>"moeda")*(Inputs!$G$5:$G$140<>"acoes")))*INDEX(Inputs!$K$5:$AJ$140,0,MATCH(F$2,Inputs!$K$4:$AJ$4,0))))) -> -87.60404 | G6: =IF(ISNA(MATCH(G$2,Inputs!$K$4:$AJ$4,0)),NA(),IF(SUMPRODUCT((Inputs!$A$5:$A$140=$B6)*ISNUMBER(INDEX(Inputs!$K$5:$AJ$140,0,MATCH(G$2,Inputs!$K$4:$AJ$4,0))))+SUMPRODUCT((Inputs!$C$5:$C$140=$B6)*ISNUMBER(INDEX(Inputs!$K$5:$AJ$140,0,MATCH(G$2,Inputs!$K$4:$AJ$4,0))))+SUMPRODUCT((Inputs!$E$5:$E$140=$B6)*ISNUMBER(INDEX(Inputs!$K$5:$AJ$140,0,MATCH(G$2,Inputs!$K$4:$AJ$4,0))))=0,NA(),SUMPRODUCT((Inputs!$A$5:$A$140=$B6)*Inputs!$B$5:$B$140*(((Inputs!$G$5:$G$140="moeda")+(Inputs!$G$5:$G$140="acoes"))*Inputs!$B$1+((Inputs!$G$5:$G$140<>"moeda")*(Inputs!$G$5:$G$140<>"acoes")))*INDEX(Inputs!$K$5:$AJ$140,0,MATCH(G$2,Inputs!$K$4:$AJ$4,0)))+SUMPRODUCT((Inputs!$C$5:$C$140=$B6)*Inputs!$D$5:$D$140*(((Inputs!$G$5:$G$140="moeda")+(Inputs!$G$5:$G$140="acoes"))*Inputs!$B$1+((Inputs!$G$5:$G$140<>"moeda")*(Inputs!$G$5:$G$140<>"acoes")))*INDEX(Inputs!$K$5:$AJ$140,0,MATCH(G$2,Inputs!$K$4:$AJ$4,0)))+SUMPRODUCT((Inputs!$E$5:$E$140=$B6)*Inputs!$F$5:$F$140*(((Inputs!$G$5:$G$140="moeda")+(Inputs!$G$5:$G$140="acoes"))*Inputs!$B$1+((Inputs!$G$5:$G$140<>"moeda")*(Inputs!$G$5:$G$140<>"acoes")))*INDEX(Inputs!$K$5:$AJ$140,0,MATCH(G$2,Inputs!$K$4:$AJ$4,0))))) -> -49.474258 | H6: =SUM(D6:G6) -> -267.78859 | I6: =IF(ISNA(MATCH(I$2,Inputs!$K$4:$AJ$4,0)),NA(),IF(SUMPRODUCT((Inputs!$A$5:$A$140=$B6)*ISNUMBER(INDEX(Inputs!$K$5:$AJ$140,0,MATCH(I$2,Inputs!$K$4:$AJ$4,0))))+SUMPRODUCT((Inputs!$C$5:$C$140=$B6)*ISNUMBER(INDEX(Inputs!$K$5:$AJ$140,0,MATCH(I$2,Inputs!$K$4:$AJ$4,0))))+SUMPRODUCT((Inputs!$E$5:$E$140=$B6)*ISNUMBER(INDEX(Inputs!$K$5:$AJ$140,0,MATCH(I$2,Inputs!$K$4:$AJ$4,0))))=0,NA(),SUMPRODUCT((Inputs!$A$5:$A$140=$B6)*Inputs!$B$5:$B$140*(((Inputs!$G$5:$G$140="moeda")+(Inputs!$G$5:$G$140="acoes"))*Inputs!$B$1+((Inputs!$G$5:$G$140<>"moeda")*(Inputs!$G$5:$G$140<>"acoes")))*INDEX(Inputs!$K$5:$AJ$140,0,MATCH(I$2,Inputs!$K$4:$AJ$4,0)))+SUMPRODUCT((Inputs!$C$5:$C$140=$B6)*Inputs!$D$5:$D$140*(((Inputs!$G$5:$G$140="moeda")+(Inputs!$G$5:$G$140="acoes"))*Inputs!$B$1+((Inputs!$G$5:$G$140<>"moeda")*(Inputs!$G$5:$G$140<>"acoes")))*INDEX(Inputs!$K$5:$AJ$140,0,MATCH(I$2,Inputs!$K$4:$AJ$4,0)))+SUMPRODUCT((Inputs!$E$5:$E$140=$B6)*Inputs!$F$5:$F$140*(((Inputs!$G$5:$G$140="moeda")+(Inputs!$G$5:$G$140="acoes"))*Inputs!$B$1+((Inputs!$G$5:$G$140<>"moeda")*(Inputs!$G$5:$G$140<>"acoes")))*INDEX(Inputs!$K$5:$AJ$140,0,MATCH(I$2,Inputs!$K$4:$AJ$4,0))))) -> -85.600613 | J6: =IF(ISNA(MATCH(J$2,Inputs!$K$4:$AJ$4,0)),NA(),IF(SUMPRODUCT((Inputs!$A$5:$A$140=$B6)*ISNUMBER(INDEX(Inputs!$K$5:$AJ$140,0,MATCH(J$2,Inputs!$K$4:$AJ$4,0))))+SUMPRODUCT((Inputs!$C$5:$C$140=$B6)*ISNUMBER(INDEX(Inputs!$K$5:$AJ$140,0,MATCH(J$2,Inputs!$K$4:$AJ$4,0))))+SUMPRODUCT((Inputs!$E$5:$E$140=$B6)*ISNUMBER(INDEX(Inputs!$K$5:$AJ$140,0,MATCH(J$2,Inputs!$K$4:$AJ$4,0))))=0,NA(),SUMPRODUCT((Inputs!$A$5:$A$140=$B6)*Inputs!$B$5:$B$140*(((Inputs!$G$5:$G$140="moeda")+(Inputs!$G$5:$G$140="acoes"))*Inputs!$B$1+((Inputs!$G$5:$G$140<>"moeda")*(Inputs!$G$5:$G$140<>"acoes")))*INDEX(Inputs!$K$5:$AJ$140,0,MATCH(J$2,Inputs!$K$4:$AJ$4,0)))+SUMPRODUCT((Inputs!$C$5:$C$140=$B6)*Inputs!$D$5:$D$140*(((Inputs!$G$5:$G$140="moeda")+(Inputs!$G$5:$G$140="acoes"))*Inputs!$B$1+((Inputs!$G$5:$G$140<>"moeda")*(Inputs!$G$5:$G$140<>"acoes")))*INDEX(Inputs!$K$5:$AJ$140,0,MATCH(J$2,Inputs!$K$4:$AJ$4,0)))+SUMPRODUCT((Inputs!$E$5:$E$140=$B6)*Inputs!$F$5:$F$140*(((Inputs!$G$5:$G$140="moeda")+(Inputs!$G$5:$G$140="acoes"))*Inputs!$B$1+((Inputs!$G$5:$G$140<>"moeda")*(Inputs!$G$5:$G$140<>"acoes")))*INDEX(Inputs!$K$5:$AJ$140,0,MATCH(J$2,Inputs!$K$4:$AJ$4,0))))) -> -97.656 | K6: =IF(ISNA(MATCH(K$2,Inputs!$K$4:$AJ$4,0)),NA(),IF(SUMPRODUCT((Inputs!$A$5:$A$140=$B6)*ISNUMBER(INDEX(Inputs!$K$5:$AJ$140,0,MATCH(K$2,Inputs!$K$4:$AJ$4,0))))+SUMPRODUCT((Inputs!$C$5:$C$140=$B6)*ISNUMBER(INDEX(Inputs!$K$5:$AJ$140,0,MATCH(K$2,Inputs!$K$4:$AJ$4,0))))+SUMPRODUCT((Inputs!$E$5:$E$140=$B6)*ISNUMBER(INDEX(Inputs!$K$5:$AJ$140,0,MATCH(K$2,Inputs!$K$4:$AJ$4,0))))=0,NA(),SUMPRODUCT((Inputs!$A$5:$A$140=$B6)*Inputs!$B$5:$B$140*(((Inputs!$G$5:$G$140="moeda")+(Inputs!$G$5:$G$140="acoes"))*Inputs!$B$1+((Inputs!$G$5:$G$140<>"moeda")*(Inputs!$G$5:$G$140<>"acoes")))*INDEX(Inputs!$K$5:$AJ$140,0,MATCH(K$2,Inputs!$K$4:$AJ$4,0)))+SUMPRODUCT((Inputs!$C$5:$C$140=$B6)*Inputs!$D$5:$D$140*(((Inputs!$G$5:$G$140="moeda")+(Inputs!$G$5:$G$140="acoes"))*Inputs!$B$1+((Inputs!$G$5:$G$140<>"moeda")*(Inputs!$G$5:$G$140<>"acoes")))*INDEX(Inputs!$K$5:$AJ$140,0,MATCH(K$2,Inputs!$K$4:$AJ$4,0)))+SUMPRODUCT((Inputs!$E$5:$E$140=$B6)*Inputs!$F$5:$F$140*(((Inputs!$G$5:$G$140="moeda")+(Inputs!$G$5:$G$140="acoes"))*Inputs!$B$1+((Inputs!$G$5:$G$140<>"moeda")*(Inputs!$G$5:$G$140<>"acoes")))*INDEX(Inputs!$K$5:$AJ$140,0,MATCH(K$2,Inputs!$K$4:$AJ$4,0))))) -> -114.534 | L6: =IF(ISNA(MATCH(L$2,Inputs!$K$4:$AJ$4,0)),NA(),IF(SUMPRODUCT((Inputs!$A$5:$A$140=$B6)*ISNUMBER(INDEX(Inputs!$K$5:$AJ$140,0,MATCH(L$2,Inputs!$K$4:$AJ$4,0))))+SUMPRODUCT((Inputs!$C$5:$C$140=$B6)*ISNUMBER(INDEX(Inputs!$K$5:$AJ$140,0,MATCH(L$2,Inputs!$K$4:$AJ$4,0))))+SUMPRODUCT((Inputs!$E$5:$E$140=$B6)*ISNUMBER(INDEX(Inputs!$K$5:$AJ$140,0,MATCH(L$2,Inputs!$K$4:$AJ$4,0))))=0,NA(),SUMPRODUCT((Inputs!$A$5:$A$140=$B6)*Inputs!$B$5:$B$140*(((Inputs!$G$5:$G$140="moeda")+(Inputs!$G$5:$G$140="acoes"))*Inputs!$B$1+((Inputs!$G$5:$G$140<>"moeda")*(Inputs!$G$5:$G$140<>"acoes")))*INDEX(Inputs!$K$5:$AJ$140,0,MATCH(L$2,Inputs!$K$4:$AJ$4,0)))+SUMPRODUCT((Inputs!$C$5:$C$140=$B6)*Inputs!$D$5:$D$140*(((Inputs!$G$5:$G$140="moeda")+(Inputs!$G$5:$G$140="acoes"))*Inputs!$B$1+((Inputs!$G$5:$G$140<>"moeda")*(Inputs!$G$5:$G$140<>"acoes")))*INDEX(Inputs!$K$5:$AJ$140,0,MATCH(L$2,Inputs!$K$4:$AJ$4,0)))+SUMPRODUCT((Inputs!$E$5:$E$140=$B6)*Inputs!$F$5:$F$140*(((Inputs!$G$5:$G$140="moeda")+(Inputs!$G$5:$G$140="acoes"))*Inputs!$B$1+((Inputs!$G$5:$G$140<>"moeda")*(Inputs!$G$5:$G$140<>"acoes")))*INDEX(Inputs!$K$5:$AJ$140,0,MATCH(L$2,Inputs!$K$4:$AJ$4,0))))) -> -91.394 | M6: =SUM(I6:L6) -> -389.18461 | N6: =IF(ISNA(MATCH(N$2,Inputs!$K$4:$AJ$4,0)),NA(),IF(SUMPRODUCT((Inputs!$A$5:$A$140=$B6)*ISNUMBER(INDEX(Inputs!$K$5:$AJ$140,0,MATCH(N$2,Inputs!$K$4:$AJ$4,0))))+SUMPRODUCT((Inputs!$C$5:$C$140=$B6)*ISNUMBER(INDEX(Inputs!$K$5:$AJ$140,0,MATCH(N$2,Inputs!$K$4:$AJ$4,0))))+SUMPRODUCT((Inputs!$E$5:$E$140=$B6)*ISNUMBER(INDEX(Inputs!$K$5:$AJ$140,0,MATCH(N$2,Inputs!$K$4:$AJ$4,0))))=0,NA(),SUMPRODUCT((Inputs!$A$5:$A$140=$B6)*Inputs!$B$5:$B$140*(((Inputs!$G$5:$G$140="moeda")+(Inputs!$G$5:$G$140="acoes"))*Inputs!$B$1+((Inputs!$G$5:$G$140<>"moeda")*(Inputs!$G$5:$G$140<>"acoes")))*INDEX(Inputs!$K$5:$AJ$140,0,MATCH(N$2,Inputs!$K$4:$AJ$4,0)))+SUMPRODUCT((Inputs!$C$5:$C$140=$B6)*Inputs!$D$5:$D$140*(((Inputs!$G$5:$G$140="moeda")+(Inputs!$G$5:$G$140="acoes"))*Inputs!$B$1+((Inputs!$G$5:$G$140<>"moeda")*(Inputs!$G$5:$G$140<>"acoes")))*INDEX(Inputs!$K$5:$AJ$140,0,MATCH(N$2,Inputs!$K$4:$AJ$4,0)))+SUMPRODUCT((Inputs!$E$5:$E$140=$B6)*Inputs!$F$5:$F$140*(((Inputs!$G$5:$G$140="moeda")+(Inputs!$G$5:$G$140="acoes"))*Inputs!$B$1+((Inputs!$G$5:$G$140<>"moeda")*(Inputs!$G$5:$G$140<>"acoes")))*INDEX(Inputs!$K$5:$AJ$140,0,MATCH(N$2,Inputs!$K$4:$AJ$4,0))))) -> -101.99492 | O6: =IF(ISNA(MATCH(O$2,Inputs!$K$4:$AJ$4,0)),NA(),IF(SUMPRODUCT((Inputs!$A$5:$A$140=$B6)*ISNUMBER(INDEX(Inputs!$K$5:$AJ$140,0,MATCH(O$2,Inputs!$K$4:$AJ$4,0))))+SUMPRODUCT((Inputs!$C$5:$C$140=$B6)*ISNUMBER(INDEX(Inputs!$K$5:$AJ$140,0,MATCH(O$2,Inputs!$K$4:$AJ$4,0))))+SUMPRODUCT((Inputs!$E$5:$E$140=$B6)*ISNUMBER(INDEX(Inputs!$K$5:$AJ$140,0,MATCH(O$2,Inputs!$K$4:$AJ$4,0))))=0,NA(),SUMPRODUCT((Inputs!$A$5:$A$140=$B6)*Inputs!$B$5:$B$140*(((Inputs!$G$5:$G$140="moeda")+(Inputs!$G$5:$G$140="acoes"))*Inputs!$B$1+((Inputs!$G$5:$G$140<>"moeda")*(Inputs!$G$5:$G$140<>"acoes")))*INDEX(Inputs!$K$5:$AJ$140,0,MATCH(O$2,Inputs!$K$4:$AJ$4,0)))+SUMPRODUCT((Inputs!$C$5:$C$140=$B6)*Inputs!$D$5:$D$140*(((Inputs!$G$5:$G$140="moeda")+(Inputs!$G$5:$G$140="acoes"))*Inputs!$B$1+((Inputs!$G$5:$G$140<>"moeda")*(Inputs!$G$5:$G$140<>"acoes")))*INDEX(Inputs!$K$5:$AJ$140,0,MATCH(O$2,Inputs!$K$4:$AJ$4,0)))+SUMPRODUCT((Inputs!$E$5:$E$140=$B6)*Inputs!$F$5:$F$140*(((Inputs!$G$5:$G$140="moeda")+(Inputs!$G$5:$G$140="acoes"))*Inputs!$B$1+((Inputs!$G$5:$G$140<>"moeda")*(Inputs!$G$5:$G$140<>"acoes")))*INDEX(Inputs!$K$5:$AJ$140,0,MATCH(O$2,Inputs!$K$4:$AJ$4,0))))) -> -121.084 | P6: =IF(ISNA(MATCH(P$2,Inputs!$K$4:$AJ$4,0)),NA(),IF(SUMPRODUCT((Inputs!$A$5:$A$140=$B6)*ISNUMBER(INDEX(Inputs!$K$5:$AJ$140,0,MATCH(P$2,Inputs!$K$4:$AJ$4,0))))+SUMPRODUCT((Inputs!$C$5:$C$140=$B6)*ISNUMBER(INDEX(Inputs!$K$5:$AJ$140,0,MATCH(P$2,Inputs!$K$4:$AJ$4,0))))+SUMPRODUCT((Inputs!$E$5:$E$140=$B6)*ISNUMBER(INDEX(Inputs!$K$5:$AJ$140,0,MATCH(P$2,Inputs!$K$4:$AJ$4,0))))=0,NA(),SUMPRODUCT((Inputs!$A$5:$A$140=$B6)*Inputs!$B$5:$B$140*(((Inputs!$G$5:$G$140="moeda")+(Inputs!$G$5:$G$140="acoes"))*Inputs!$B$1+((Inputs!$G$5:$G$140<>"moeda")*(Inputs!$G$5:$G$140<>"acoes")))*INDEX(Inputs!$K$5:$AJ$140,0,MATCH(P$2,Inputs!$K$4:$AJ$4,0)))+SUMPRODUCT((Inputs!$C$5:$C$140=$B6)*Inputs!$D$5:$D$140*(((Inputs!$G$5:$G$140="moeda")+(Inputs!$G$5:$G$140="acoes"))*Inputs!$B$1+((Inputs!$G$5:$G$140<>"moeda")*(Inputs!$G$5:$G$140<>"acoes")))*INDEX(Inputs!$K$5:$AJ$140,0,MATCH(P$2,Inputs!$K$4:$AJ$4,0)))+SUMPRODUCT((Inputs!$E$5:$E$140=$B6)*Inputs!$F$5:$F$140*(((Inputs!$G$5:$G$140="moeda")+(Inputs!$G$5:$G$140="acoes"))*Inputs!$B$1+((Inputs!$G$5:$G$140<>"moeda")*(Inputs!$G$5:$G$140<>"acoes")))*INDEX(Inputs!$K$5:$AJ$140,0,MATCH(P$2,Inputs!$K$4:$AJ$4,0))))) -> -141.70211 | Q6: =IF(ISNA(MATCH(Q$2,Inputs!$K$4:$AJ$4,0)),NA(),IF(SUMPRODUCT((Inputs!$A$5:$A$140=$B6)*ISNUMBER(INDEX(Inputs!$K$5:$AJ$140,0,MATCH(Q$2,Inputs!$K$4:$AJ$4,0))))+SUMPRODUCT((Inputs!$C$5:$C$140=$B6)*ISNUMBER(INDEX(Inputs!$K$5:$AJ$140,0,MATCH(Q$2,Inputs!$K$4:$AJ$4,0))))+SUMPRODUCT((Inputs!$E$5:$E$140=$B6)*ISNUMBER(INDEX(Inputs!$K$5:$AJ$140,0,MATCH(Q$2,Inputs!$K$4:$AJ$4,0))))=0,NA(),SUMPRODUCT((Inputs!$A$5:$A$140=$B6)*Inputs!$B$5:$B$140*(((Inputs!$G$5:$G$140="moeda")+(Inputs!$G$5:$G$140="acoes"))*Inputs!$B$1+((Inputs!$G$5:$G$140<>"moeda")*(Inputs!$G$5:$G$140<>"acoes")))*INDEX(Inputs!$K$5:$AJ$140,0,MATCH(Q$2,Inputs!$K$4:$AJ$4,0)))+SUMPRODUCT((Inputs!$C$5:$C$140=$B6)*Inputs!$D$5:$D$140*(((Inputs!$G$5:$G$140="moeda")+(Inputs!$G$5:$G$140="acoes"))*Inputs!$B$1+((Inputs!$G$5:$G$140<>"moeda")*(Inputs!$G$5:$G$140<>"acoes")))*INDEX(Inputs!$K$5:$AJ$140,0,MATCH(Q$2,Inputs!$K$4:$AJ$4,0)))+SUMPRODUCT((Inputs!$E$5:$E$140=$B6)*Inputs!$F$5:$F$140*(((Inputs!$G$5:$G$140="moeda")+(Inputs!$G$5:$G$140="acoes"))*Inputs!$B$1+((Inputs!$G$5:$G$140<>"moeda")*(Inputs!$G$5:$G$140<>"acoes")))*INDEX(Inputs!$K$5:$AJ$140,0,MATCH(Q$2,Inputs!$K$4:$AJ$4,0))))) -> -124.40698 | R6: =SUM(N6:Q6) -> -489.188 | S6: =IF(ISNA(MATCH(S$2,Inputs!$K$4:$AJ$4,0)),NA(),IF(SUMPRODUCT((Inputs!$A$5:$A$140=$B6)*ISNUMBER(INDEX(Inputs!$K$5:$AJ$140,0,MATCH(S$2,Inputs!$K$4:$AJ$4,0))))+SUMPRODUCT((Inputs!$C$5:$C$140=$B6)*ISNUMBER(INDEX(Inputs!$K$5:$AJ$140,0,MATCH(S$2,Inputs!$K$4:$AJ$4,0))))+SUMPRODUCT((Inputs!$E$5:$E$140=$B6)*ISNUMBER(INDEX(Inputs!$K$5:$AJ$140,0,MATCH(S$2,Inputs!$K$4:$AJ$4,0))))=0,NA(),SUMPRODUCT((Inputs!$A$5:$A$140=$B6)*Inputs!$B$5:$B$140*(((Inputs!$G$5:$G$140="moeda")+(Inputs!$G$5:$G$140="acoes"))*Inputs!$B$1+((Inputs!$G$5:$G$140<>"moeda")*(Inputs!$G$5:$G$140<>"acoes")))*INDEX(Inputs!$K$5:$AJ$140,0,MATCH(S$2,Inputs!$K$4:$AJ$4,0)))+SUMPRODUCT((Inputs!$C$5:$C$140=$B6)*Inputs!$D$5:$D$140*(((Inputs!$G$5:$G$140="moeda")+(Inputs!$G$5:$G$140="acoes"))*Inputs!$B$1+((Inputs!$G$5:$G$140<>"moeda")*(Inputs!$G$5:$G$140<>"acoes")))*INDEX(Inputs!$K$5:$AJ$140,0,MATCH(S$2,Inputs!$K$4:$AJ$4,0)))+SUMPRODUCT((Inputs!$E$5:$E$140=$B6)*Inputs!$F$5:$F$140*(((Inputs!$G$5:$G$140="moeda")+(Inputs!$G$5:$G$140="acoes"))*Inputs!$B$1+((Inputs!$G$5:$G$140<>"moeda")*(Inputs!$G$5:$G$140<>"acoes")))*INDEX(Inputs!$K$5:$AJ$140,0,MATCH(S$2,Inputs!$K$4:$AJ$4,0))))) -> -131.618 | T6: =IF(ISNA(MATCH(T$2,Inputs!$K$4:$AJ$4,0)),NA(),IF(SUMPRODUCT((Inputs!$A$5:$A$140=$B6)*ISNUMBER(INDEX(Inputs!$K$5:$AJ$140,0,MATCH(T$2,Inputs!$K$4:$AJ$4,0))))+SUMPRODUCT((Inputs!$C$5:$C$140=$B6)*ISNUMBER(INDEX(Inputs!$K$5:$AJ$140,0,MATCH(T$2,Inputs!$K$4:$AJ$4,0))))+SUMPRODUCT((Inputs!$E$5:$E$140=$B6)*ISNUMBER(INDEX(Inputs!$K$5:$AJ$140,0,MATCH(T$2,Inputs!$K$4:$AJ$4,0))))=0,NA(),SUMPRODUCT((Inputs!$A$5:$A$140=$B6)*Inputs!$B$5:$B$140*(((Inputs!$G$5:$G$140="moeda")+(Inputs!$G$5:$G$140="acoes"))*Inputs!$B$1+((Inputs!$G$5:$G$140<>"moeda")*(Inputs!$G$5:$G$140<>"acoes")))*INDEX(Inputs!$K$5:$AJ$140,0,MATCH(T$2,Inputs!$K$4:$AJ$4,0)))+SUMPRODUCT((Inputs!$C$5:$C$140=$B6)*Inputs!$D$5:$D$140*(((Inputs!$G$5:$G$140="moeda")+(Inputs!$G$5:$G$140="acoes"))*Inputs!$B$1+((Inputs!$G$5:$G$140<>"moeda")*(Inputs!$G$5:$G$140<>"acoes")))*INDEX(Inputs!$K$5:$AJ$140,0,MATCH(T$2,Inputs!$K$4:$AJ$4,0)))+SUMPRODUCT((Inputs!$E$5:$E$140=$B6)*Inputs!$F$5:$F$140*(((Inputs!$G$5:$G$140="moeda")+(Inputs!$G$5:$G$140="acoes"))*Inputs!$B$1+((Inputs!$G$5:$G$140<>"moeda")*(Inputs!$G$5:$G$140<>"acoes")))*INDEX(Inputs!$K$5:$AJ$140,0,MATCH(T$2,Inputs!$K$4:$AJ$4,0))))) -> -176.38716 | U6: =IF(ISNA(MATCH(U$2,Inputs!$K$4:$AJ$4,0)),NA(),IF(SUMPRODUCT((Inputs!$A$5:$A$140=$B6)*ISNUMBER(INDEX(Inputs!$K$5:$AJ$140,0,MATCH(U$2,Inputs!$K$4:$AJ$4,0))))+SUMPRODUCT((Inputs!$C$5:$C$140=$B6)*ISNUMBER(INDEX(Inputs!$K$5:$AJ$140,0,MATCH(U$2,Inputs!$K$4:$AJ$4,0))))+SUMPRODUCT((Inputs!$E$5:$E$140=$B6)*ISNUMBER(INDEX(Inputs!$K$5:$AJ$140,0,MATCH(U$2,Inputs!$K$4:$AJ$4,0))))=0,NA(),SUMPRODUCT((Inputs!$A$5:$A$140=$B6)*Inputs!$B$5:$B$140*(((Inputs!$G$5:$G$140="moeda")+(Inputs!$G$5:$G$140="acoes"))*Inputs!$B$1+((Inputs!$G$5:$G$140<>"moeda")*(Inputs!$G$5:$G$140<>"acoes")))*INDEX(Inputs!$K$5:$AJ$140,0,MATCH(U$2,Inputs!$K$4:$AJ$4,0)))+SUMPRODUCT((Inputs!$C$5:$C$140=$B6)*Inputs!$D$5:$D$140*(((Inputs!$G$5:$G$140="moeda")+(Inputs!$G$5:$G$140="acoes"))*Inputs!$B$1+((Inputs!$G$5:$G$140<>"moeda")*(Inputs!$G$5:$G$140<>"acoes")))*INDEX(Inputs!$K$5:$AJ$140,0,MATCH(U$2,Inputs!$K$4:$AJ$4,0)))+SUMPRODUCT((Inputs!$E$5:$E$140=$B6)*Inputs!$F$5:$F$140*(((Inputs!$G$5:$G$140="moeda")+(Inputs!$G$5:$G$140="acoes"))*Inputs!$B$1+((Inputs!$G$5:$G$140<>"moeda")*(Inputs!$G$5:$G$140<>"acoes")))*INDEX(Inputs!$K$5:$AJ$140,0,MATCH(U$2,Inputs!$K$4:$AJ$4,0))))) -> -193.4418 | V6: =IF(ISNA(MATCH(V$2,Inputs!$K$4:$AJ$4,0)),NA(),IF(SUMPRODUCT((Inputs!$A$5:$A$140=$B6)*ISNUMBER(INDEX(Inputs!$K$5:$AJ$140,0,MATCH(V$2,Inputs!$K$4:$AJ$4,0))))+SUMPRODUCT((Inputs!$C$5:$C$140=$B6)*ISNUMBER(INDEX(Inputs!$K$5:$AJ$140,0,MATCH(V$2,Inputs!$K$4:$AJ$4,0))))+SUMPRODUCT((Inputs!$E$5:$E$140=$B6)*ISNUMBER(INDEX(Inputs!$K$5:$AJ$140,0,MATCH(V$2,Inputs!$K$4:$AJ$4,0))))=0,NA(),SUMPRODUCT((Inputs!$A$5:$A$140=$B6)*Inputs!$B$5:$B$140*(((Inputs!$G$5:$G$140="moeda")+(Inputs!$G$5:$G$140="acoes"))*Inputs!$B$1+((Inputs!$G$5:$G$140<>"moeda")*(Inputs!$G$5:$G$140<>"acoes")))*INDEX(Inputs!$K$5:$AJ$140,0,MATCH(V$2,Inputs!$K$4:$AJ$4,0)))+SUMPRODUCT((Inputs!$C$5:$C$140=$B6)*Inputs!$D$5:$D$140*(((Inputs!$G$5:$G$140="moeda")+(Inputs!$G$5:$G$140="acoes"))*Inputs!$B$1+((Inputs!$G$5:$G$140<>"moeda")*(Inputs!$G$5:$G$140<>"acoes")))*INDEX(Inputs!$K$5:$AJ$140,0,MATCH(V$2,Inputs!$K$4:$AJ$4,0)))+SUMPRODUCT((Inputs!$E$5:$E$140=$B6)*Inputs!$F$5:$F$140*(((Inputs!$G$5:$G$140="moeda")+(Inputs!$G$5:$G$140="acoes"))*Inputs!$B$1+((Inputs!$G$5:$G$140<>"moeda")*(Inputs!$G$5:$G$140<>"acoes")))*INDEX(Inputs!$K$5:$AJ$140,0,MATCH(V$2,Inputs!$K$4:$AJ$4,0))))) -> -169.22181 | W6: =SUM(S6:V6) -> -670.66877 | X6: =IF(ISNA(MATCH(X$2,Inputs!$K$4:$AJ$4,0)),NA(),IF(SUMPRODUCT((Inputs!$A$5:$A$140=$B6)*ISNUMBER(INDEX(Inputs!$K$5:$AJ$140,0,MATCH(X$2,Inputs!$K$4:$AJ$4,0))))+SUMPRODUCT((Inputs!$C$5:$C$140=$B6)*ISNUMBER(INDEX(Inputs!$K$5:$AJ$140,0,MATCH(X$2,Inputs!$K$4:$AJ$4,0))))+SUMPRODUCT((Inputs!$E$5:$E$140=$B6)*ISNUMBER(INDEX(Inputs!$K$5:$AJ$140,0,MATCH(X$2,Inputs!$K$4:$AJ$4,0))))=0,NA(),SUMPRODUCT((Inputs!$A$5:$A$140=$B6)*Inputs!$B$5:$B$140*(((Inputs!$G$5:$G$140="moeda")+(Inputs!$G$5:$G$140="acoes"))*Inputs!$B$1+((Inputs!$G$5:$G$140<>"moeda")*(Inputs!$G$5:$G$140<>"acoes")))*INDEX(Inputs!$K$5:$AJ$140,0,MATCH(X$2,Inputs!$K$4:$AJ$4,0)))+SUMPRODUCT((Inputs!$C$5:$C$140=$B6)*Inputs!$D$5:$D$140*(((Inputs!$G$5:$G$140="moeda")+(Inputs!$G$5:$G$140="acoes"))*Inputs!$B$1+((Inputs!$G$5:$G$140<>"moeda")*(Inputs!$G$5:$G$140<>"acoes")))*INDEX(Inputs!$K$5:$AJ$140,0,MATCH(X$2,Inputs!$K$4:$AJ$4,0)))+SUMPRODUCT((Inputs!$E$5:$E$140=$B6)*Inputs!$F$5:$F$140*(((Inputs!$G$5:$G$140="moeda")+(Inputs!$G$5:$G$140="acoes"))*Inputs!$B$1+((Inputs!$G$5:$G$140<>"moeda")*(Inputs!$G$5:$G$140<>"acoes")))*INDEX(Inputs!$K$5:$AJ$140,0,MATCH(X$2,Inputs!$K$4:$AJ$4,0))))) -> -187.796 | Y6: =IF(ISNA(MATCH(Y$2,Inputs!$K$4:$AJ$4,0)),NA(),IF(SUMPRODUCT((Inputs!$A$5:$A$140=$B6)*ISNUMBER(INDEX(Inputs!$K$5:$AJ$140,0,MATCH(Y$2,Inputs!$K$4:$AJ$4,0))))+SUMPRODUCT((Inputs!$C$5:$C$140=$B6)*ISNUMBER(INDEX(Inputs!$K$5:$AJ$140,0,MATCH(Y$2,Inputs!$K$4:$AJ$4,0))))+SUMPRODUCT((Inputs!$E$5:$E$140=$B6)*ISNUMBER(INDEX(Inputs!$K$5:$AJ$140,0,MATCH(Y$2,Inputs!$K$4:$AJ$4,0))))=0,NA(),SUMPRODUCT((Inputs!$A$5:$A$140=$B6)*Inputs!$B$5:$B$140*(((Inputs!$G$5:$G$140="moeda")+(Inputs!$G$5:$G$140="acoes"))*Inputs!$B$1+((Inputs!$G$5:$G$140<>"moeda")*(Inputs!$G$5:$G$140<>"acoes")))*INDEX(Inputs!$K$5:$AJ$140,0,MATCH(Y$2,Inputs!$K$4:$AJ$4,0)))+SUMPRODUCT((Inputs!$C$5:$C$140=$B6)*Inputs!$D$5:$D$140*(((Inputs!$G$5:$G$140="moeda")+(Inputs!$G$5:$G$140="acoes"))*Inputs!$B$1+((Inputs!$G$5:$G$140<>"moeda")*(Inputs!$G$5:$G$140<>"acoes")))*INDEX(Inputs!$K$5:$AJ$140,0,MATCH(Y$2,Inputs!$K$4:$AJ$4,0)))+SUMPRODUCT((Inputs!$E$5:$E$140=$B6)*Inputs!$F$5:$F$140*(((Inputs!$G$5:$G$140="moeda")+(Inputs!$G$5:$G$140="acoes"))*Inputs!$B$1+((Inputs!$G$5:$G$140<>"moeda")*(Inputs!$G$5:$G$140<>"acoes")))*INDEX(Inputs!$K$5:$AJ$140,0,MATCH(Y$2,Inputs!$K$4:$AJ$4,0))))) -> -210.8885 | Z6: =IF(ISNA(MATCH(Z$2,Inputs!$K$4:$AJ$4,0)),NA(),IF(SUMPRODUCT((Inputs!$A$5:$A$140=$B6)*ISNUMBER(INDEX(Inputs!$K$5:$AJ$140,0,MATCH(Z$2,Inputs!$K$4:$AJ$4,0))))+SUMPRODUCT((Inputs!$C$5:$C$140=$B6)*ISNUMBER(INDEX(Inputs!$K$5:$AJ$140,0,MATCH(Z$2,Inputs!$K$4:$AJ$4,0))))+SUMPRODUCT((Inputs!$E$5:$E$140=$B6)*ISNUMBER(INDEX(Inputs!$K$5:$AJ$140,0,MATCH(Z$2,Inputs!$K$4:$AJ$4,0))))=0,NA(),SUMPRODUCT((Inputs!$A$5:$A$140=$B6)*Inputs!$B$5:$B$140*(((Inputs!$G$5:$G$140="moeda")+(Inputs!$G$5:$G$140="acoes"))*Inputs!$B$1+((Inputs!$G$5:$G$140<>"moeda")*(Inputs!$G$5:$G$140<>"acoes")))*INDEX(Inputs!$K$5:$AJ$140,0,MATCH(Z$2,Inputs!$K$4:$AJ$4,0)))+SUMPRODUCT((Inputs!$C$5:$C$140=$B6)*Inputs!$D$5:$D$140*(((Inputs!$G$5:$G$140="moeda")+(Inputs!$G$5:$G$140="acoes"))*Inputs!$B$1+((Inputs!$G$5:$G$140<>"moeda")*(Inputs!$G$5:$G$140<>"acoes")))*INDEX(Inputs!$K$5:$AJ$140,0,MATCH(Z$2,Inputs!$K$4:$AJ$4,0)))+SUMPRODUCT((Inputs!$E$5:$E$140=$B6)*Inputs!$F$5:$F$140*(((Inputs!$G$5:$G$140="moeda")+(Inputs!$G$5:$G$140="acoes"))*Inputs!$B$1+((Inputs!$G$5:$G$140<>"moeda")*(Inputs!$G$5:$G$140<>"acoes")))*INDEX(Inputs!$K$5:$AJ$140,0,MATCH(Z$2,Inputs!$K$4:$AJ$4,0))))) -> -231.513 | AA6: =IF(ISNA(MATCH(AA$2,Inputs!$K$4:$AJ$4,0)),NA(),IF(SUMPRODUCT((Inputs!$A$5:$A$140=$B6)*ISNUMBER(INDEX(Inputs!$K$5:$AJ$140,0,MATCH(AA$2,Inputs!$K$4:$AJ$4,0))))+SUMPRODUCT((Inputs!$C$5:$C$140=$B6)*ISNUMBER(INDEX(Inputs!$K$5:$AJ$140,0,MATCH(AA$2,Inputs!$K$4:$AJ$4,0))))+SUMPRODUCT((Inputs!$E$5:$E$140=$B6)*ISNUMBER(INDEX(Inputs!$K$5:$AJ$140,0,MATCH(AA$2,Inputs!$K$4:$AJ$4,0))))=0,NA(),SUMPRODUCT((Inputs!$A$5:$A$140=$B6)*Inputs!$B$5:$B$140*(((Inputs!$G$5:$G$140="moeda")+(Inputs!$G$5:$G$140="acoes"))*Inputs!$B$1+((Inputs!$G$5:$G$140<>"moeda")*(Inputs!$G$5:$G$140<>"acoes")))*INDEX(Inputs!$K$5:$AJ$140,0,MATCH(AA$2,Inputs!$K$4:$AJ$4,0)))+SUMPRODUCT((Inputs!$C$5:$C$140=$B6)*Inputs!$D$5:$D$140*(((Inputs!$G$5:$G$140="moeda")+(Inputs!$G$5:$G$140="acoes"))*Inputs!$B$1+((Inputs!$G$5:$G$140<>"moeda")*(Inputs!$G$5:$G$140<>"acoes")))*INDEX(Inputs!$K$5:$AJ$140,0,MATCH(AA$2,Inputs!$K$4:$AJ$4,0)))+SUMPRODUCT((Inputs!$E$5:$E$140=$B6)*Inputs!$F$5:$F$140*(((Inputs!$G$5:$G$140="moeda")+(Inputs!$G$5:$G$140="acoes"))*Inputs!$B$1+((Inputs!$G$5:$G$140<>"moeda")*(Inputs!$G$5:$G$140<>"acoes")))*INDEX(Inputs!$K$5:$AJ$140,0,MATCH(AA$2,Inputs!$K$4:$AJ$4,0))))) -> -220.841 | AB6: =SUM(X6:AA6) -> -851.0385 | AC6: =IF(ISNA(MATCH(AC$2,Inputs!$K$4:$AJ$4,0)),NA(),IF(SUMPRODUCT((Inputs!$A$5:$A$140=$B6)*ISNUMBER(INDEX(Inputs!$K$5:$AJ$140,0,MATCH(AC$2,Inputs!$K$4:$AJ$4,0))))+SUMPRODUCT((Inputs!$C$5:$C$140=$B6)*ISNUMBER(INDEX(Inputs!$K$5:$AJ$140,0,MATCH(AC$2,Inputs!$K$4:$AJ$4,0))))+SUMPRODUCT((Inputs!$E$5:$E$140=$B6)*ISNUMBER(INDEX(Inputs!$K$5:$AJ$140,0,MATCH(AC$2,Inputs!$K$4:$AJ$4,0))))=0,NA(),SUMPRODUCT((Inputs!$A$5:$A$140=$B6)*Inputs!$B$5:$B$140*(((Inputs!$G$5:$G$140="moeda")+(Inputs!$G$5:$G$140="acoes"))*Inputs!$B$1+((Inputs!$G$5:$G$140<>"moeda")*(Inputs!$G$5:$G$140<>"acoes")))*INDEX(Inputs!$K$5:$AJ$140,0,MATCH(AC$2,Inputs!$K$4:$AJ$4,0)))+SUMPRODUCT((Inputs!$C$5:$C$140=$B6)*Inputs!$D$5:$D$140*(((Inputs!$G$5:$G$140="moeda")+(Inputs!$G$5:$G$140="acoes"))*Inputs!$B$1+((Inputs!$G$5:$G$140<>"moeda")*(Inputs!$G$5:$G$140<>"acoes")))*INDEX(Inputs!$K$5:$AJ$140,0,MATCH(AC$2,Inputs!$K$4:$AJ$4,0)))+SUMPRODUCT((Inputs!$E$5:$E$140=$B6)*Inputs!$F$5:$F$140*(((Inputs!$G$5:$G$140="moeda")+(Inputs!$G$5:$G$140="acoes"))*Inputs!$B$1+((Inputs!$G$5:$G$140<>"moeda")*(Inputs!$G$5:$G$140<>"acoes")))*INDEX(Inputs!$K$5:$AJ$140,0,MATCH(AC$2,Inputs!$K$4:$AJ$4,0))))) -> -220.444 | AD6: =IF(ISNA(MATCH(AD$2,Inputs!$K$4:$AJ$4,0)),NA(),IF(SUMPRODUCT((Inputs!$A$5:$A$140=$B6)*ISNUMBER(INDEX(Inputs!$K$5:$AJ$140,0,MATCH(AD$2,Inputs!$K$4:$AJ$4,0))))+SUMPRODUCT((Inputs!$C$5:$C$140=$B6)*ISNUMBER(INDEX(Inputs!$K$5:$AJ$140,0,MATCH(AD$2,Inputs!$K$4:$AJ$4,0))))+SUMPRODUCT((Inputs!$E$5:$E$140=$B6)*ISNUMBER(INDEX(Inputs!$K$5:$AJ$140,0,MATCH(AD$2,Inputs!$K$4:$AJ$4,0))))=0,NA(),SUMPRODUCT((Inputs!$A$5:$A$140=$B6)*Inputs!$B$5:$B$140*(((Inputs!$G$5:$G$140="moeda")+(Inputs!$G$5:$G$140="acoes"))*Inputs!$B$1+((Inputs!$G$5:$G$140<>"moeda")*(Inputs!$G$5:$G$140<>"acoes")))*INDEX(Inputs!$K$5:$AJ$140,0,MATCH(AD$2,Inputs!$K$4:$AJ$4,0)))+SUMPRODUCT((Inputs!$C$5:$C$140=$B6)*Inputs!$D$5:$D$140*(((Inputs!$G$5:$G$140="moeda")+(Inputs!$G$5:$G$140="acoes"))*Inputs!$B$1+((Inputs!$G$5:$G$140<>"moeda")*(Inputs!$G$5:$G$140<>"acoes")))*INDEX(Inputs!$K$5:$AJ$140,0,MATCH(AD$2,Inputs!$K$4:$AJ$4,0)))+SUMPRODUCT((Inputs!$E$5:$E$140=$B6)*Inputs!$F$5:$F$140*(((Inputs!$G$5:$G$140="moeda")+(Inputs!$G$5:$G$140="acoes"))*Inputs!$B$1+((Inputs!$G$5:$G$140<>"moeda")*(Inputs!$G$5:$G$140<>"acoes")))*INDEX(Inputs!$K$5:$AJ$140,0,MATCH(AD$2,Inputs!$K$4:$AJ$4,0))))) -> -282.4 | AE6: =IF(ISNA(MATCH(AE$2,Inputs!$K$4:$AJ$4,0)),NA(),IF(SUMPRODUCT((Inputs!$A$5:$A$140=$B6)*ISNUMBER(INDEX(Inputs!$K$5:$AJ$140,0,MATCH(AE$2,Inputs!$K$4:$AJ$4,0))))+SUMPRODUCT((Inputs!$C$5:$C$140=$B6)*ISNUMBER(INDEX(Inputs!$K$5:$AJ$140,0,MATCH(AE$2,Inputs!$K$4:$AJ$4,0))))+SUMPRODUCT((Inputs!$E$5:$E$140=$B6)*ISNUMBER(INDEX(Inputs!$K$5:$AJ$140,0,MATCH(AE$2,Inputs!$K$4:$AJ$4,0))))=0,NA(),SUMPRODUCT((Inputs!$A$5:$A$140=$B6)*Inputs!$B$5:$B$140*(((Inputs!$G$5:$G$140="moeda")+(Inputs!$G$5:$G$140="acoes"))*Inputs!$B$1+((Inputs!$G$5:$G$140<>"moeda")*(Inputs!$G$5:$G$140<>"acoes")))*INDEX(Inputs!$K$5:$AJ$140,0,MATCH(AE$2,Inputs!$K$4:$AJ$4,0)))+SUMPRODUCT((Inputs!$C$5:$C$140=$B6)*Inputs!$D$5:$D$140*(((Inputs!$G$5:$G$140="moeda")+(Inputs!$G$5:$G$140="acoes"))*Inputs!$B$1+((Inputs!$G$5:$G$140<>"moeda")*(Inputs!$G$5:$G$140<>"acoes")))*INDEX(Inputs!$K$5:$AJ$140,0,MATCH(AE$2,Inputs!$K$4:$AJ$4,0)))+SUMPRODUCT((Inputs!$E$5:$E$140=$B6)*Inputs!$F$5:$F$140*(((Inputs!$G$5:$G$140="moeda")+(Inputs!$G$5:$G$140="acoes"))*Inputs!$B$1+((Inputs!$G$5:$G$140<>"moeda")*(Inputs!$G$5:$G$140<>"acoes")))*INDEX(Inputs!$K$5:$AJ$140,0,MATCH(AE$2,Inputs!$K$4:$AJ$4,0))))) -> #N/A | AF6: =IF(ISNA(MATCH(AF$2,Inputs!$K$4:$AJ$4,0)),NA(),IF(SUMPRODUCT((Inputs!$A$5:$A$140=$B6)*ISNUMBER(INDEX(Inputs!$K$5:$AJ$140,0,MATCH(AF$2,Inputs!$K$4:$AJ$4,0))))+SUMPRODUCT((Inputs!$C$5:$C$140=$B6)*ISNUMBER(INDEX(Inputs!$K$5:$AJ$140,0,MATCH(AF$2,Inputs!$K$4:$AJ$4,0))))+SUMPRODUCT((Inputs!$E$5:$E$140=$B6)*ISNUMBER(INDEX(Inputs!$K$5:$AJ$140,0,MATCH(AF$2,Inputs!$K$4:$AJ$4,0))))=0,NA(),SUMPRODUCT((Inputs!$A$5:$A$140=$B6)*Inputs!$B$5:$B$140*(((Inputs!$G$5:$G$140="moeda")+(Inputs!$G$5:$G$140="acoes"))*Inputs!$B$1+((Inputs!$G$5:$G$140<>"moeda")*(Inputs!$G$5:$G$140<>"acoes")))*INDEX(Inputs!$K$5:$AJ$140,0,MATCH(AF$2,Inputs!$K$4:$AJ$4,0)))+SUMPRODUCT((Inputs!$C$5:$C$140=$B6)*Inputs!$D$5:$D$140*(((Inputs!$G$5:$G$140="moeda")+(Inputs!$G$5:$G$140="acoes"))*Inputs!$B$1+((Inputs!$G$5:$G$140<>"moeda")*(Inputs!$G$5:$G$140<>"acoes")))*INDEX(Inputs!$K$5:$AJ$140,0,MATCH(AF$2,Inputs!$K$4:$AJ$4,0)))+SUMPRODUCT((Inputs!$E$5:$E$140=$B6)*Inputs!$F$5:$F$140*(((Inputs!$G$5:$G$140="moeda")+(Inputs!$G$5:$G$140="acoes"))*Inputs!$B$1+((Inputs!$G$5:$G$140<>"moeda")*(Inputs!$G$5:$G$140<>"acoes")))*INDEX(Inputs!$K$5:$AJ$140,0,MATCH(AF$2,Inputs!$K$4:$AJ$4,0))))) -> #N/A | AG6: =SUM(AC6:AF6) -> #N/A | AH6: =IF(ISNA(MATCH(AH$2,Inputs!$K$4:$AJ$4,0)),NA(),IF(SUMPRODUCT((Inputs!$A$5:$A$140=$B6)*ISNUMBER(INDEX(Inputs!$K$5:$AJ$140,0,MATCH(AH$2,Inputs!$K$4:$AJ$4,0))))+SUMPRODUCT((Inputs!$C$5:$C$140=$B6)*ISNUMBER(INDEX(Inputs!$K$5:$AJ$140,0,MATCH(AH$2,Inputs!$K$4:$AJ$4,0))))+SUMPRODUCT((Inputs!$E$5:$E$140=$B6)*ISNUMBER(INDEX(Inputs!$K$5:$AJ$140,0,MATCH(AH$2,Inputs!$K$4:$AJ$4,0))))=0,NA(),SUMPRODUCT((Inputs!$A$5:$A$140=$B6)*Inputs!$B$5:$B$140*(((Inputs!$G$5:$G$140="moeda")+(Inputs!$G$5:$G$140="acoes"))*Inputs!$B$1+((Inputs!$G$5:$G$140<>"moeda")*(Inputs!$G$5:$G$140<>"acoes")))*INDEX(Inputs!$K$5:$AJ$140,0,MATCH(AH$2,Inputs!$K$4:$AJ$4,0)))+SUMPRODUCT((Inputs!$C$5:$C$140=$B6)*Inputs!$D$5:$D$140*(((Inputs!$G$5:$G$140="moeda")+(Inputs!$G$5:$G$140="acoes"))*Inputs!$B$1+((Inputs!$G$5:$G$140<>"moeda")*(Inputs!$G$5:$G$140<>"acoes")))*INDEX(Inputs!$K$5:$AJ$140,0,MATCH(AH$2,Inputs!$K$4:$AJ$4,0)))+SUMPRODUCT((Inputs!$E$5:$E$140=$B6)*Inputs!$F$5:$F$140*(((Inputs!$G$5:$G$140="moeda")+(Inputs!$G$5:$G$140="acoes"))*Inputs!$B$1+((Inputs!$G$5:$G$140<>"moeda")*(Inputs!$G$5:$G$140<>"acoes")))*INDEX(Inputs!$K$5:$AJ$140,0,MATCH(AH$2,Inputs!$K$4:$AJ$4,0))))) -> -50.676 | AI6: =IF(ISNA(MATCH(AI$2,Inputs!$K$4:$AJ$4,0)),NA(),IF(SUMPRODUCT((Inputs!$A$5:$A$140=$B6)*ISNUMBER(INDEX(Inputs!$K$5:$AJ$140,0,MATCH(AI$2,Inputs!$K$4:$AJ$4,0))))+SUMPRODUCT((Inputs!$C$5:$C$140=$B6)*ISNUMBER(INDEX(Inputs!$K$5:$AJ$140,0,MATCH(AI$2,Inputs!$K$4:$AJ$4,0))))+SUMPRODUCT((Inputs!$E$5:$E$140=$B6)*ISNUMBER(INDEX(Inputs!$K$5:$AJ$140,0,MATCH(AI$2,Inputs!$K$4:$AJ$4,0))))=0,NA(),SUMPRODUCT((Inputs!$A$5:$A$140=$B6)*Inputs!$B$5:$B$140*(((Inputs!$G$5:$G$140="moeda")+(Inputs!$G$5:$G$140="acoes"))*Inputs!$B$1+((Inputs!$G$5:$G$140<>"moeda")*(Inputs!$G$5:$G$140<>"acoes")))*INDEX(Inputs!$K$5:$AJ$140,0,MATCH(AI$2,Inputs!$K$4:$AJ$4,0)))+SUMPRODUCT((Inputs!$C$5:$C$140=$B6)*Inputs!$D$5:$D$140*(((Inputs!$G$5:$G$140="moeda")+(Inputs!$G$5:$G$140="acoes"))*Inputs!$B$1+((Inputs!$G$5:$G$140<>"moeda")*(Inputs!$G$5:$G$140<>"acoes")))*INDEX(Inputs!$K$5:$AJ$140,0,MATCH(AI$2,Inputs!$K$4:$AJ$4,0)))+SUMPRODUCT((Inputs!$E$5:$E$140=$B6)*Inputs!$F$5:$F$140*(((Inputs!$G$5:$G$140="moeda")+(Inputs!$G$5:$G$140="acoes"))*Inputs!$B$1+((Inputs!$G$5:$G$140<>"moeda")*(Inputs!$G$5:$G$140<>"acoes")))*INDEX(Inputs!$K$5:$AJ$140,0,MATCH(AI$2,Inputs!$K$4:$AJ$4,0))))) -> -38.179 | AJ6: =IF(ISNA(MATCH(AJ$2,Inputs!$K$4:$AJ$4,0)),NA(),IF(SUMPRODUCT((Inputs!$A$5:$A$140=$B6)*ISNUMBER(INDEX(Inputs!$K$5:$AJ$140,0,MATCH(AJ$2,Inputs!$K$4:$AJ$4,0))))+SUMPRODUCT((Inputs!$C$5:$C$140=$B6)*ISNUMBER(INDEX(Inputs!$K$5:$AJ$140,0,MATCH(AJ$2,Inputs!$K$4:$AJ$4,0))))+SUMPRODUCT((Inputs!$E$5:$E$140=$B6)*ISNUMBER(INDEX(Inputs!$K$5:$AJ$140,0,MATCH(AJ$2,Inputs!$K$4:$AJ$4,0))))=0,NA(),SUMPRODUCT((Inputs!$A$5:$A$140=$B6)*Inputs!$B$5:$B$140*(((Inputs!$G$5:$G$140="moeda")+(Inputs!$G$5:$G$140="acoes"))*Inputs!$B$1+((Inputs!$G$5:$G$140<>"moeda")*(Inputs!$G$5:$G$140<>"acoes")))*INDEX(Inputs!$K$5:$AJ$140,0,MATCH(AJ$2,Inputs!$K$4:$AJ$4,0)))+SUMPRODUCT((Inputs!$C$5:$C$140=$B6)*Inputs!$D$5:$D$140*(((Inputs!$G$5:$G$140="moeda")+(Inputs!$G$5:$G$140="acoes"))*Inputs!$B$1+((Inputs!$G$5:$G$140<>"moeda")*(Inputs!$G$5:$G$140<>"acoes")))*INDEX(Inputs!$K$5:$AJ$140,0,MATCH(AJ$2,Inputs!$K$4:$AJ$4,0)))+SUMPRODUCT((Inputs!$E$5:$E$140=$B6)*Inputs!$F$5:$F$140*(((Inputs!$G$5:$G$140="moeda")+(Inputs!$G$5:$G$140="acoes"))*Inputs!$B$1+((Inputs!$G$5:$G$140<>"moeda")*(Inputs!$G$5:$G$140<>"acoes")))*INDEX(Inputs!$K$5:$AJ$140,0,MATCH(AJ$2,Inputs!$K$4:$AJ$4,0))))) -> -55.998 | AK6: =IF(ISNA(MATCH(AK$2,Inputs!$K$4:$AJ$4,0)),NA(),IF(SUMPRODUCT((Inputs!$A$5:$A$140=$B6)*ISNUMBER(INDEX(Inputs!$K$5:$AJ$140,0,MATCH(AK$2,Inputs!$K$4:$AJ$4,0))))+SUMPRODUCT((Inputs!$C$5:$C$140=$B6)*ISNUMBER(INDEX(Inputs!$K$5:$AJ$140,0,MATCH(AK$2,Inputs!$K$4:$AJ$4,0))))+SUMPRODUCT((Inputs!$E$5:$E$140=$B6)*ISNUMBER(INDEX(Inputs!$K$5:$AJ$140,0,MATCH(AK$2,Inputs!$K$4:$AJ$4,0))))=0,NA(),SUMPRODUCT((Inputs!$A$5:$A$140=$B6)*Inputs!$B$5:$B$140*(((Inputs!$G$5:$G$140="moeda")+(Inputs!$G$5:$G$140="acoes"))*Inputs!$B$1+((Inputs!$G$5:$G$140<>"moeda")*(Inputs!$G$5:$G$140<>"acoes")))*INDEX(Inputs!$K$5:$AJ$140,0,MATCH(AK$2,Inputs!$K$4:$AJ$4,0)))+SUMPRODUCT((Inputs!$C$5:$C$140=$B6)*Inputs!$D$5:$D$140*(((Inputs!$G$5:$G$140="moeda")+(Inputs!$G$5:$G$140="acoes"))*Inputs!$B$1+((Inputs!$G$5:$G$140<>"moeda")*(Inputs!$G$5:$G$140<>"acoes")))*INDEX(Inputs!$K$5:$AJ$140,0,MATCH(AK$2,Inputs!$K$4:$AJ$4,0)))+SUMPRODUCT((Inputs!$E$5:$E$140=$B6)*Inputs!$F$5:$F$140*(((Inputs!$G$5:$G$140="moeda")+(Inputs!$G$5:$G$140="acoes"))*Inputs!$B$1+((Inputs!$G$5:$G$140<>"moeda")*(Inputs!$G$5:$G$140<>"acoes")))*INDEX(Inputs!$K$5:$AJ$140,0,MATCH(AK$2,Inputs!$K$4:$AJ$4,0))))) -> -57.01429 | AL6: =SUM(AH6:AK6) -> -201.86729
B7: 4 | C7: D&A | D7: =IF(ISNA(MATCH(D$2,Inputs!$K$4:$AJ$4,0)),NA(),IF(SUMPRODUCT((Inputs!$A$5:$A$140=$B7)*ISNUMBER(INDEX(Inputs!$K$5:$AJ$140,0,MATCH(D$2,Inputs!$K$4:$AJ$4,0))))+SUMPRODUCT((Inputs!$C$5:$C$140=$B7)*ISNUMBER(INDEX(Inputs!$K$5:$AJ$140,0,MATCH(D$2,Inputs!$K$4:$AJ$4,0))))+SUMPRODUCT((Inputs!$E$5:$E$140=$B7)*ISNUMBER(INDEX(Inputs!$K$5:$AJ$140,0,MATCH(D$2,Inputs!$K$4:$AJ$4,0))))=0,NA(),SUMPRODUCT((Inputs!$A$5:$A$140=$B7)*Inputs!$B$5:$B$140*(((Inputs!$G$5:$G$140="moeda")+(Inputs!$G$5:$G$140="acoes"))*Inputs!$B$1+((Inputs!$G$5:$G$140<>"moeda")*(Inputs!$G$5:$G$140<>"acoes")))*INDEX(Inputs!$K$5:$AJ$140,0,MATCH(D$2,Inputs!$K$4:$AJ$4,0)))+SUMPRODUCT((Inputs!$C$5:$C$140=$B7)*Inputs!$D$5:$D$140*(((Inputs!$G$5:$G$140="moeda")+(Inputs!$G$5:$G$140="acoes"))*Inputs!$B$1+((Inputs!$G$5:$G$140<>"moeda")*(Inputs!$G$5:$G$140<>"acoes")))*INDEX(Inputs!$K$5:$AJ$140,0,MATCH(D$2,Inputs!$K$4:$AJ$4,0)))+SUMPRODUCT((Inputs!$E$5:$E$140=$B7)*Inputs!$F$5:$F$140*(((Inputs!$G$5:$G$140="moeda")+(Inputs!$G$5:$G$140="acoes"))*Inputs!$B$1+((Inputs!$G$5:$G$140<>"moeda")*(Inputs!$G$5:$G$140<>"acoes")))*INDEX(Inputs!$K$5:$AJ$140,0,MATCH(D$2,Inputs!$K$4:$AJ$4,0))))) -> -0.33465271 | E7: =IF(ISNA(MATCH(E$2,Inputs!$K$4:$AJ$4,0)),NA(),IF(SUMPRODUCT((Inputs!$A$5:$A$140=$B7)*ISNUMBER(INDEX(Inputs!$K$5:$AJ$140,0,MATCH(E$2,Inputs!$K$4:$AJ$4,0))))+SUMPRODUCT((Inputs!$C$5:$C$140=$B7)*ISNUMBER(INDEX(Inputs!$K$5:$AJ$140,0,MATCH(E$2,Inputs!$K$4:$AJ$4,0))))+SUMPRODUCT((Inputs!$E$5:$E$140=$B7)*ISNUMBER(INDEX(Inputs!$K$5:$AJ$140,0,MATCH(E$2,Inputs!$K$4:$AJ$4,0))))=0,NA(),SUMPRODUCT((Inputs!$A$5:$A$140=$B7)*Inputs!$B$5:$B$140*(((Inputs!$G$5:$G$140="moeda")+(Inputs!$G$5:$G$140="acoes"))*Inputs!$B$1+((Inputs!$G$5:$G$140<>"moeda")*(Inputs!$G$5:$G$140<>"acoes")))*INDEX(Inputs!$K$5:$AJ$140,0,MATCH(E$2,Inputs!$K$4:$AJ$4,0)))+SUMPRODUCT((Inputs!$C$5:$C$140=$B7)*Inputs!$D$5:$D$140*(((Inputs!$G$5:$G$140="moeda")+(Inputs!$G$5:$G$140="acoes"))*Inputs!$B$1+((Inputs!$G$5:$G$140<>"moeda")*(Inputs!$G$5:$G$140<>"acoes")))*INDEX(Inputs!$K$5:$AJ$140,0,MATCH(E$2,Inputs!$K$4:$AJ$4,0)))+SUMPRODUCT((Inputs!$E$5:$E$140=$B7)*Inputs!$F$5:$F$140*(((Inputs!$G$5:$G$140="moeda")+(Inputs!$G$5:$G$140="acoes"))*Inputs!$B$1+((Inputs!$G$5:$G$140<>"moeda")*(Inputs!$G$5:$G$140<>"acoes")))*INDEX(Inputs!$K$5:$AJ$140,0,MATCH(E$2,Inputs!$K$4:$AJ$4,0))))) -> -0.3550585 | F7: =IF(ISNA(MATCH(F$2,Inputs!$K$4:$AJ$4,0)),NA(),IF(SUMPRODUCT((Inputs!$A$5:$A$140=$B7)*ISNUMBER(INDEX(Inputs!$K$5:$AJ$140,0,MATCH(F$2,Inputs!$K$4:$AJ$4,0))))+SUMPRODUCT((Inputs!$C$5:$C$140=$B7)*ISNUMBER(INDEX(Inputs!$K$5:$AJ$140,0,MATCH(F$2,Inputs!$K$4:$AJ$4,0))))+SUMPRODUCT((Inputs!$E$5:$E$140=$B7)*ISNUMBER(INDEX(Inputs!$K$5:$AJ$140,0,MATCH(F$2,Inputs!$K$4:$AJ$4,0))))=0,NA(),SUMPRODUCT((Inputs!$A$5:$A$140=$B7)*Inputs!$B$5:$B$140*(((Inputs!$G$5:$G$140="moeda")+(Inputs!$G$5:$G$140="acoes"))*Inputs!$B$1+((Inputs!$G$5:$G$140<>"moeda")*(Inputs!$G$5:$G$140<>"acoes")))*INDEX(Inputs!$K$5:$AJ$140,0,MATCH(F$2,Inputs!$K$4:$AJ$4,0)))+SUMPRODUCT((Inputs!$C$5:$C$140=$B7)*Inputs!$D$5:$D$140*(((Inputs!$G$5:$G$140="moeda")+(Inputs!$G$5:$G$140="acoes"))*Inputs!$B$1+((Inputs!$G$5:$G$140<>"moeda")*(Inputs!$G$5:$G$140<>"acoes")))*INDEX(Inputs!$K$5:$AJ$140,0,MATCH(F$2,Inputs!$K$4:$AJ$4,0)))+SUMPRODUCT((Inputs!$E$5:$E$140=$B7)*Inputs!$F$5:$F$140*(((Inputs!$G$5:$G$140="moeda")+(Inputs!$G$5:$G$140="acoes"))*Inputs!$B$1+((Inputs!$G$5:$G$140<>"moeda")*(Inputs!$G$5:$G$140<>"acoes")))*INDEX(Inputs!$K$5:$AJ$140,0,MATCH(F$2,Inputs!$K$4:$AJ$4,0))))) -> -0.37596036 | G7: =IF(ISNA(MATCH(G$2,Inputs!$K$4:$AJ$4,0)),NA(),IF(SUMPRODUCT((Inputs!$A$5:$A$140=$B7)*ISNUMBER(INDEX(Inputs!$K$5:$AJ$140,0,MATCH(G$2,Inputs!$K$4:$AJ$4,0))))+SUMPRODUCT((Inputs!$C$5:$C$140=$B7)*ISNUMBER(INDEX(Inputs!$K$5:$AJ$140,0,MATCH(G$2,Inputs!$K$4:$AJ$4,0))))+SUMPRODUCT((Inputs!$E$5:$E$140=$B7)*ISNUMBER(INDEX(Inputs!$K$5:$AJ$140,0,MATCH(G$2,Inputs!$K$4:$AJ$4,0))))=0,NA(),SUMPRODUCT((Inputs!$A$5:$A$140=$B7)*Inputs!$B$5:$B$140*(((Inputs!$G$5:$G$140="moeda")+(Inputs!$G$5:$G$140="acoes"))*Inputs!$B$1+((Inputs!$G$5:$G$140<>"moeda")*(Inputs!$G$5:$G$140<>"acoes")))*INDEX(Inputs!$K$5:$AJ$140,0,MATCH(G$2,Inputs!$K$4:$AJ$4,0)))+SUMPRODUCT((Inputs!$C$5:$C$140=$B7)*Inputs!$D$5:$D$140*(((Inputs!$G$5:$G$140="moeda")+(Inputs!$G$5:$G$140="acoes"))*Inputs!$B$1+((Inputs!$G$5:$G$140<>"moeda")*(Inputs!$G$5:$G$140<>"acoes")))*INDEX(Inputs!$K$5:$AJ$140,0,MATCH(G$2,Inputs!$K$4:$AJ$4,0)))+SUMPRODUCT((Inputs!$E$5:$E$140=$B7)*Inputs!$F$5:$F$140*(((Inputs!$G$5:$G$140="moeda")+(Inputs!$G$5:$G$140="acoes"))*Inputs!$B$1+((Inputs!$G$5:$G$140<>"moeda")*(Inputs!$G$5:$G$140<>"acoes")))*INDEX(Inputs!$K$5:$AJ$140,0,MATCH(G$2,Inputs!$K$4:$AJ$4,0))))) -> -0.37774207 | H7: =SUM(D7:G7) -> -1.4434136 | I7: =IF(ISNA(MATCH(I$2,Inputs!$K$4:$AJ$4,0)),NA(),IF(SUMPRODUCT((Inputs!$A$5:$A$140=$B7)*ISNUMBER(INDEX(Inputs!$K$5:$AJ$140,0,MATCH(I$2,Inputs!$K$4:$AJ$4,0))))+SUMPRODUCT((Inputs!$C$5:$C$140=$B7)*ISNUMBER(INDEX(Inputs!$K$5:$AJ$140,0,MATCH(I$2,Inputs!$K$4:$AJ$4,0))))+SUMPRODUCT((Inputs!$E$5:$E$140=$B7)*ISNUMBER(INDEX(Inputs!$K$5:$AJ$140,0,MATCH(I$2,Inputs!$K$4:$AJ$4,0))))=0,NA(),SUMPRODUCT((Inputs!$A$5:$A$140=$B7)*Inputs!$B$5:$B$140*(((Inputs!$G$5:$G$140="moeda")+(Inputs!$G$5:$G$140="acoes"))*Inputs!$B$1+((Inputs!$G$5:$G$140<>"moeda")*(Inputs!$G$5:$G$140<>"acoes")))*INDEX(Inputs!$K$5:$AJ$140,0,MATCH(I$2,Inputs!$K$4:$AJ$4,0)))+SUMPRODUCT((Inputs!$C$5:$C$140=$B7)*Inputs!$D$5:$D$140*(((Inputs!$G$5:$G$140="moeda")+(Inputs!$G$5:$G$140="acoes"))*Inputs!$B$1+((Inputs!$G$5:$G$140<>"moeda")*(Inputs!$G$5:$G$140<>"acoes")))*INDEX(Inputs!$K$5:$AJ$140,0,MATCH(I$2,Inputs!$K$4:$AJ$4,0)))+SUMPRODUCT((Inputs!$E$5:$E$140=$B7)*Inputs!$F$5:$F$140*(((Inputs!$G$5:$G$140="moeda")+(Inputs!$G$5:$G$140="acoes"))*Inputs!$B$1+((Inputs!$G$5:$G$140<>"moeda")*(Inputs!$G$5:$G$140<>"acoes")))*INDEX(Inputs!$K$5:$AJ$140,0,MATCH(I$2,Inputs!$K$4:$AJ$4,0))))) -> -0.92438681 | J7: =IF(ISNA(MATCH(J$2,Inputs!$K$4:$AJ$4,0)),NA(),IF(SUMPRODUCT((Inputs!$A$5:$A$140=$B7)*ISNUMBER(INDEX(Inputs!$K$5:$AJ$140,0,MATCH(J$2,Inputs!$K$4:$AJ$4,0))))+SUMPRODUCT((Inputs!$C$5:$C$140=$B7)*ISNUMBER(INDEX(Inputs!$K$5:$AJ$140,0,MATCH(J$2,Inputs!$K$4:$AJ$4,0))))+SUMPRODUCT((Inputs!$E$5:$E$140=$B7)*ISNUMBER(INDEX(Inputs!$K$5:$AJ$140,0,MATCH(J$2,Inputs!$K$4:$AJ$4,0))))=0,NA(),SUMPRODUCT((Inputs!$A$5:$A$140=$B7)*Inputs!$B$5:$B$140*(((Inputs!$G$5:$G$140="moeda")+(Inputs!$G$5:$G$140="acoes"))*Inputs!$B$1+((Inputs!$G$5:$G$140<>"moeda")*(Inputs!$G$5:$G$140<>"acoes")))*INDEX(Inputs!$K$5:$AJ$140,0,MATCH(J$2,Inputs!$K$4:$AJ$4,0)))+SUMPRODUCT((Inputs!$C$5:$C$140=$B7)*Inputs!$D$5:$D$140*(((Inputs!$G$5:$G$140="moeda")+(Inputs!$G$5:$G$140="acoes"))*Inputs!$B$1+((Inputs!$G$5:$G$140<>"moeda")*(Inputs!$G$5:$G$140<>"acoes")))*INDEX(Inputs!$K$5:$AJ$140,0,MATCH(J$2,Inputs!$K$4:$AJ$4,0)))+SUMPRODUCT((Inputs!$E$5:$E$140=$B7)*Inputs!$F$5:$F$140*(((Inputs!$G$5:$G$140="moeda")+(Inputs!$G$5:$G$140="acoes"))*Inputs!$B$1+((Inputs!$G$5:$G$140<>"moeda")*(Inputs!$G$5:$G$140<>"acoes")))*INDEX(Inputs!$K$5:$AJ$140,0,MATCH(J$2,Inputs!$K$4:$AJ$4,0))))) -> -5.704 | K7: =IF(ISNA(MATCH(K$2,Inputs!$K$4:$AJ$4,0)),NA(),IF(SUMPRODUCT((Inputs!$A$5:$A$140=$B7)*ISNUMBER(INDEX(Inputs!$K$5:$AJ$140,0,MATCH(K$2,Inputs!$K$4:$AJ$4,0))))+SUMPRODUCT((Inputs!$C$5:$C$140=$B7)*ISNUMBER(INDEX(Inputs!$K$5:$AJ$140,0,MATCH(K$2,Inputs!$K$4:$AJ$4,0))))+SUMPRODUCT((Inputs!$E$5:$E$140=$B7)*ISNUMBER(INDEX(Inputs!$K$5:$AJ$140,0,MATCH(K$2,Inputs!$K$4:$AJ$4,0))))=0,NA(),SUMPRODUCT((Inputs!$A$5:$A$140=$B7)*Inputs!$B$5:$B$140*(((Inputs!$G$5:$G$140="moeda")+(Inputs!$G$5:$G$140="acoes"))*Inputs!$B$1+((Inputs!$G$5:$G$140<>"moeda")*(Inputs!$G$5:$G$140<>"acoes")))*INDEX(Inputs!$K$5:$AJ$140,0,MATCH(K$2,Inputs!$K$4:$AJ$4,0)))+SUMPRODUCT((Inputs!$C$5:$C$140=$B7)*Inputs!$D$5:$D$140*(((Inputs!$G$5:$G$140="moeda")+(Inputs!$G$5:$G$140="acoes"))*Inputs!$B$1+((Inputs!$G$5:$G$140<>"moeda")*(Inputs!$G$5:$G$140<>"acoes")))*INDEX(Inputs!$K$5:$AJ$140,0,MATCH(K$2,Inputs!$K$4:$AJ$4,0)))+SUMPRODUCT((Inputs!$E$5:$E$140=$B7)*Inputs!$F$5:$F$140*(((Inputs!$G$5:$G$140="moeda")+(Inputs!$G$5:$G$140="acoes"))*Inputs!$B$1+((Inputs!$G$5:$G$140<>"moeda")*(Inputs!$G$5:$G$140<>"acoes")))*INDEX(Inputs!$K$5:$AJ$140,0,MATCH(K$2,Inputs!$K$4:$AJ$4,0))))) -> -5.715 | L7: =IF(ISNA(MATCH(L$2,Inputs!$K$4:$AJ$4,0)),NA(),IF(SUMPRODUCT((Inputs!$A$5:$A$140=$B7)*ISNUMBER(INDEX(Inputs!$K$5:$AJ$140,0,MATCH(L$2,Inputs!$K$4:$AJ$4,0))))+SUMPRODUCT((Inputs!$C$5:$C$140=$B7)*ISNUMBER(INDEX(Inputs!$K$5:$AJ$140,0,MATCH(L$2,Inputs!$K$4:$AJ$4,0))))+SUMPRODUCT((Inputs!$E$5:$E$140=$B7)*ISNUMBER(INDEX(Inputs!$K$5:$AJ$140,0,MATCH(L$2,Inputs!$K$4:$AJ$4,0))))=0,NA(),SUMPRODUCT((Inputs!$A$5:$A$140=$B7)*Inputs!$B$5:$B$140*(((Inputs!$G$5:$G$140="moeda")+(Inputs!$G$5:$G$140="acoes"))*Inputs!$B$1+((Inputs!$G$5:$G$140<>"moeda")*(Inputs!$G$5:$G$140<>"acoes")))*INDEX(Inputs!$K$5:$AJ$140,0,MATCH(L$2,Inputs!$K$4:$AJ$4,0)))+SUMPRODUCT((Inputs!$C$5:$C$140=$B7)*Inputs!$D$5:$D$140*(((Inputs!$G$5:$G$140="moeda")+(Inputs!$G$5:$G$140="acoes"))*Inputs!$B$1+((Inputs!$G$5:$G$140<>"moeda")*(Inputs!$G$5:$G$140<>"acoes")))*INDEX(Inputs!$K$5:$AJ$140,0,MATCH(L$2,Inputs!$K$4:$AJ$4,0)))+SUMPRODUCT((Inputs!$E$5:$E$140=$B7)*Inputs!$F$5:$F$140*(((Inputs!$G$5:$G$140="moeda")+(Inputs!$G$5:$G$140="acoes"))*Inputs!$B$1+((Inputs!$G$5:$G$140<>"moeda")*(Inputs!$G$5:$G$140<>"acoes")))*INDEX(Inputs!$K$5:$AJ$140,0,MATCH(L$2,Inputs!$K$4:$AJ$4,0))))) -> -6.302 | M7: =SUM(I7:L7) -> -18.645387 | N7: =IF(ISNA(MATCH(N$2,Inputs!$K$4:$AJ$4,0)),NA(),IF(SUMPRODUCT((Inputs!$A$5:$A$140=$B7)*ISNUMBER(INDEX(Inputs!$K$5:$AJ$140,0,MATCH(N$2,Inputs!$K$4:$AJ$4,0))))+SUMPRODUCT((Inputs!$C$5:$C$140=$B7)*ISNUMBER(INDEX(Inputs!$K$5:$AJ$140,0,MATCH(N$2,Inputs!$K$4:$AJ$4,0))))+SUMPRODUCT((Inputs!$E$5:$E$140=$B7)*ISNUMBER(INDEX(Inputs!$K$5:$AJ$140,0,MATCH(N$2,Inputs!$K$4:$AJ$4,0))))=0,NA(),SUMPRODUCT((Inputs!$A$5:$A$140=$B7)*Inputs!$B$5:$B$140*(((Inputs!$G$5:$G$140="moeda")+(Inputs!$G$5:$G$140="acoes"))*Inputs!$B$1+((Inputs!$G$5:$G$140<>"moeda")*(Inputs!$G$5:$G$140<>"acoes")))*INDEX(Inputs!$K$5:$AJ$140,0,MATCH(N$2,Inputs!$K$4:$AJ$4,0)))+SUMPRODUCT((Inputs!$C$5:$C$140=$B7)*Inputs!$D$5:$D$140*(((Inputs!$G$5:$G$140="moeda")+(Inputs!$G$5:$G$140="acoes"))*Inputs!$B$1+((Inputs!$G$5:$G$140<>"moeda")*(Inputs!$G$5:$G$140<>"acoes")))*INDEX(Inputs!$K$5:$AJ$140,0,MATCH(N$2,Inputs!$K$4:$AJ$4,0)))+SUMPRODUCT((Inputs!$E$5:$E$140=$B7)*Inputs!$F$5:$F$140*(((Inputs!$G$5:$G$140="moeda")+(Inputs!$G$5:$G$140="acoes"))*Inputs!$B$1+((Inputs!$G$5:$G$140<>"moeda")*(Inputs!$G$5:$G$140<>"acoes")))*INDEX(Inputs!$K$5:$AJ$140,0,MATCH(N$2,Inputs!$K$4:$AJ$4,0))))) -> -6.2210827 | O7: =IF(ISNA(MATCH(O$2,Inputs!$K$4:$AJ$4,0)),NA(),IF(SUMPRODUCT((Inputs!$A$5:$A$140=$B7)*ISNUMBER(INDEX(Inputs!$K$5:$AJ$140,0,MATCH(O$2,Inputs!$K$4:$AJ$4,0))))+SUMPRODUCT((Inputs!$C$5:$C$140=$B7)*ISNUMBER(INDEX(Inputs!$K$5:$AJ$140,0,MATCH(O$2,Inputs!$K$4:$AJ$4,0))))+SUMPRODUCT((Inputs!$E$5:$E$140=$B7)*ISNUMBER(INDEX(Inputs!$K$5:$AJ$140,0,MATCH(O$2,Inputs!$K$4:$AJ$4,0))))=0,NA(),SUMPRODUCT((Inputs!$A$5:$A$140=$B7)*Inputs!$B$5:$B$140*(((Inputs!$G$5:$G$140="moeda")+(Inputs!$G$5:$G$140="acoes"))*Inputs!$B$1+((Inputs!$G$5:$G$140<>"moeda")*(Inputs!$G$5:$G$140<>"acoes")))*INDEX(Inputs!$K$5:$AJ$140,0,MATCH(O$2,Inputs!$K$4:$AJ$4,0)))+SUMPRODUCT((Inputs!$C$5:$C$140=$B7)*Inputs!$D$5:$D$140*(((Inputs!$G$5:$G$140="moeda")+(Inputs!$G$5:$G$140="acoes"))*Inputs!$B$1+((Inputs!$G$5:$G$140<>"moeda")*(Inputs!$G$5:$G$140<>"acoes")))*INDEX(Inputs!$K$5:$AJ$140,0,MATCH(O$2,Inputs!$K$4:$AJ$4,0)))+SUMPRODUCT((Inputs!$E$5:$E$140=$B7)*Inputs!$F$5:$F$140*(((Inputs!$G$5:$G$140="moeda")+(Inputs!$G$5:$G$140="acoes"))*Inputs!$B$1+((Inputs!$G$5:$G$140<>"moeda")*(Inputs!$G$5:$G$140<>"acoes")))*INDEX(Inputs!$K$5:$AJ$140,0,MATCH(O$2,Inputs!$K$4:$AJ$4,0))))) -> -6.3 | P7: =IF(ISNA(MATCH(P$2,Inputs!$K$4:$AJ$4,0)),NA(),IF(SUMPRODUCT((Inputs!$A$5:$A$140=$B7)*ISNUMBER(INDEX(Inputs!$K$5:$AJ$140,0,MATCH(P$2,Inputs!$K$4:$AJ$4,0))))+SUMPRODUCT((Inputs!$C$5:$C$140=$B7)*ISNUMBER(INDEX(Inputs!$K$5:$AJ$140,0,MATCH(P$2,Inputs!$K$4:$AJ$4,0))))+SUMPRODUCT((Inputs!$E$5:$E$140=$B7)*ISNUMBER(INDEX(Inputs!$K$5:$AJ$140,0,MATCH(P$2,Inputs!$K$4:$AJ$4,0))))=0,NA(),SUMPRODUCT((Inputs!$A$5:$A$140=$B7)*Inputs!$B$5:$B$140*(((Inputs!$G$5:$G$140="moeda")+(Inputs!$G$5:$G$140="acoes"))*Inputs!$B$1+((Inputs!$G$5:$G$140<>"moeda")*(Inputs!$G$5:$G$140<>"acoes")))*INDEX(Inputs!$K$5:$AJ$140,0,MATCH(P$2,Inputs!$K$4:$AJ$4,0)))+SUMPRODUCT((Inputs!$C$5:$C$140=$B7)*Inputs!$D$5:$D$140*(((Inputs!$G$5:$G$140="moeda")+(Inputs!$G$5:$G$140="acoes"))*Inputs!$B$1+((Inputs!$G$5:$G$140<>"moeda")*(Inputs!$G$5:$G$140<>"acoes")))*INDEX(Inputs!$K$5:$AJ$140,0,MATCH(P$2,Inputs!$K$4:$AJ$4,0)))+SUMPRODUCT((Inputs!$E$5:$E$140=$B7)*Inputs!$F$5:$F$140*(((Inputs!$G$5:$G$140="moeda")+(Inputs!$G$5:$G$140="acoes"))*Inputs!$B$1+((Inputs!$G$5:$G$140<>"moeda")*(Inputs!$G$5:$G$140<>"acoes")))*INDEX(Inputs!$K$5:$AJ$140,0,MATCH(P$2,Inputs!$K$4:$AJ$4,0))))) -> -6.3408938 | Q7: =IF(ISNA(MATCH(Q$2,Inputs!$K$4:$AJ$4,0)),NA(),IF(SUMPRODUCT((Inputs!$A$5:$A$140=$B7)*ISNUMBER(INDEX(Inputs!$K$5:$AJ$140,0,MATCH(Q$2,Inputs!$K$4:$AJ$4,0))))+SUMPRODUCT((Inputs!$C$5:$C$140=$B7)*ISNUMBER(INDEX(Inputs!$K$5:$AJ$140,0,MATCH(Q$2,Inputs!$K$4:$AJ$4,0))))+SUMPRODUCT((Inputs!$E$5:$E$140=$B7)*ISNUMBER(INDEX(Inputs!$K$5:$AJ$140,0,MATCH(Q$2,Inputs!$K$4:$AJ$4,0))))=0,NA(),SUMPRODUCT((Inputs!$A$5:$A$140=$B7)*Inputs!$B$5:$B$140*(((Inputs!$G$5:$G$140="moeda")+(Inputs!$G$5:$G$140="acoes"))*Inputs!$B$1+((Inputs!$G$5:$G$140<>"moeda")*(Inputs!$G$5:$G$140<>"acoes")))*INDEX(Inputs!$K$5:$AJ$140,0,MATCH(Q$2,Inputs!$K$4:$AJ$4,0)))+SUMPRODUCT((Inputs!$C$5:$C$140=$B7)*Inputs!$D$5:$D$140*(((Inputs!$G$5:$G$140="moeda")+(Inputs!$G$5:$G$140="acoes"))*Inputs!$B$1+((Inputs!$G$5:$G$140<>"moeda")*(Inputs!$G$5:$G$140<>"acoes")))*INDEX(Inputs!$K$5:$AJ$140,0,MATCH(Q$2,Inputs!$K$4:$AJ$4,0)))+SUMPRODUCT((Inputs!$E$5:$E$140=$B7)*Inputs!$F$5:$F$140*(((Inputs!$G$5:$G$140="moeda")+(Inputs!$G$5:$G$140="acoes"))*Inputs!$B$1+((Inputs!$G$5:$G$140<>"moeda")*(Inputs!$G$5:$G$140<>"acoes")))*INDEX(Inputs!$K$5:$AJ$140,0,MATCH(Q$2,Inputs!$K$4:$AJ$4,0))))) -> -7.0100235 | R7: =SUM(N7:Q7) -> -25.872 | S7: =IF(ISNA(MATCH(S$2,Inputs!$K$4:$AJ$4,0)),NA(),IF(SUMPRODUCT((Inputs!$A$5:$A$140=$B7)*ISNUMBER(INDEX(Inputs!$K$5:$AJ$140,0,MATCH(S$2,Inputs!$K$4:$AJ$4,0))))+SUMPRODUCT((Inputs!$C$5:$C$140=$B7)*ISNUMBER(INDEX(Inputs!$K$5:$AJ$140,0,MATCH(S$2,Inputs!$K$4:$AJ$4,0))))+SUMPRODUCT((Inputs!$E$5:$E$140=$B7)*ISNUMBER(INDEX(Inputs!$K$5:$AJ$140,0,MATCH(S$2,Inputs!$K$4:$AJ$4,0))))=0,NA(),SUMPRODUCT((Inputs!$A$5:$A$140=$B7)*Inputs!$B$5:$B$140*(((Inputs!$G$5:$G$140="moeda")+(Inputs!$G$5:$G$140="acoes"))*Inputs!$B$1+((Inputs!$G$5:$G$140<>"moeda")*(Inputs!$G$5:$G$140<>"acoes")))*INDEX(Inputs!$K$5:$AJ$140,0,MATCH(S$2,Inputs!$K$4:$AJ$4,0)))+SUMPRODUCT((Inputs!$C$5:$C$140=$B7)*Inputs!$D$5:$D$140*(((Inputs!$G$5:$G$140="moeda")+(Inputs!$G$5:$G$140="acoes"))*Inputs!$B$1+((Inputs!$G$5:$G$140<>"moeda")*(Inputs!$G$5:$G$140<>"acoes")))*INDEX(Inputs!$K$5:$AJ$140,0,MATCH(S$2,Inputs!$K$4:$AJ$4,0)))+SUMPRODUCT((Inputs!$E$5:$E$140=$B7)*Inputs!$F$5:$F$140*(((Inputs!$G$5:$G$140="moeda")+(Inputs!$G$5:$G$140="acoes"))*Inputs!$B$1+((Inputs!$G$5:$G$140<>"moeda")*(Inputs!$G$5:$G$140<>"acoes")))*INDEX(Inputs!$K$5:$AJ$140,0,MATCH(S$2,Inputs!$K$4:$AJ$4,0))))) -> -7.117 | T7: =IF(ISNA(MATCH(T$2,Inputs!$K$4:$AJ$4,0)),NA(),IF(SUMPRODUCT((Inputs!$A$5:$A$140=$B7)*ISNUMBER(INDEX(Inputs!$K$5:$AJ$140,0,MATCH(T$2,Inputs!$K$4:$AJ$4,0))))+SUMPRODUCT((Inputs!$C$5:$C$140=$B7)*ISNUMBER(INDEX(Inputs!$K$5:$AJ$140,0,MATCH(T$2,Inputs!$K$4:$AJ$4,0))))+SUMPRODUCT((Inputs!$E$5:$E$140=$B7)*ISNUMBER(INDEX(Inputs!$K$5:$AJ$140,0,MATCH(T$2,Inputs!$K$4:$AJ$4,0))))=0,NA(),SUMPRODUCT((Inputs!$A$5:$A$140=$B7)*Inputs!$B$5:$B$140*(((Inputs!$G$5:$G$140="moeda")+(Inputs!$G$5:$G$140="acoes"))*Inputs!$B$1+((Inputs!$G$5:$G$140<>"moeda")*(Inputs!$G$5:$G$140<>"acoes")))*INDEX(Inputs!$K$5:$AJ$140,0,MATCH(T$2,Inputs!$K$4:$AJ$4,0)))+SUMPRODUCT((Inputs!$C$5:$C$140=$B7)*Inputs!$D$5:$D$140*(((Inputs!$G$5:$G$140="moeda")+(Inputs!$G$5:$G$140="acoes"))*Inputs!$B$1+((Inputs!$G$5:$G$140<>"moeda")*(Inputs!$G$5:$G$140<>"acoes")))*INDEX(Inputs!$K$5:$AJ$140,0,MATCH(T$2,Inputs!$K$4:$AJ$4,0)))+SUMPRODUCT((Inputs!$E$5:$E$140=$B7)*Inputs!$F$5:$F$140*(((Inputs!$G$5:$G$140="moeda")+(Inputs!$G$5:$G$140="acoes"))*Inputs!$B$1+((Inputs!$G$5:$G$140<>"moeda")*(Inputs!$G$5:$G$140<>"acoes")))*INDEX(Inputs!$K$5:$AJ$140,0,MATCH(T$2,Inputs!$K$4:$AJ$4,0))))) -> -7.0115768 | U7: =IF(ISNA(MATCH(U$2,Inputs!$K$4:$AJ$4,0)),NA(),IF(SUMPRODUCT((Inputs!$A$5:$A$140=$B7)*ISNUMBER(INDEX(Inputs!$K$5:$AJ$140,0,MATCH(U$2,Inputs!$K$4:$AJ$4,0))))+SUMPRODUCT((Inputs!$C$5:$C$140=$B7)*ISNUMBER(INDEX(Inputs!$K$5:$AJ$140,0,MATCH(U$2,Inputs!$K$4:$AJ$4,0))))+SUMPRODUCT((Inputs!$E$5:$E$140=$B7)*ISNUMBER(INDEX(Inputs!$K$5:$AJ$140,0,MATCH(U$2,Inputs!$K$4:$AJ$4,0))))=0,NA(),SUMPRODUCT((Inputs!$A$5:$A$140=$B7)*Inputs!$B$5:$B$140*(((Inputs!$G$5:$G$140="moeda")+(Inputs!$G$5:$G$140="acoes"))*Inputs!$B$1+((Inputs!$G$5:$G$140<>"moeda")*(Inputs!$G$5:$G$140<>"acoes")))*INDEX(Inputs!$K$5:$AJ$140,0,MATCH(U$2,Inputs!$K$4:$AJ$4,0)))+SUMPRODUCT((Inputs!$C$5:$C$140=$B7)*Inputs!$D$5:$D$140*(((Inputs!$G$5:$G$140="moeda")+(Inputs!$G$5:$G$140="acoes"))*Inputs!$B$1+((Inputs!$G$5:$G$140<>"moeda")*(Inputs!$G$5:$G$140<>"acoes")))*INDEX(Inputs!$K$5:$AJ$140,0,MATCH(U$2,Inputs!$K$4:$AJ$4,0)))+SUMPRODUCT((Inputs!$E$5:$E$140=$B7)*Inputs!$F$5:$F$140*(((Inputs!$G$5:$G$140="moeda")+(Inputs!$G$5:$G$140="acoes"))*Inputs!$B$1+((Inputs!$G$5:$G$140<>"moeda")*(Inputs!$G$5:$G$140<>"acoes")))*INDEX(Inputs!$K$5:$AJ$140,0,MATCH(U$2,Inputs!$K$4:$AJ$4,0))))) -> -8.1911989 | V7: =IF(ISNA(MATCH(V$2,Inputs!$K$4:$AJ$4,0)),NA(),IF(SUMPRODUCT((Inputs!$A$5:$A$140=$B7)*ISNUMBER(INDEX(Inputs!$K$5:$AJ$140,0,MATCH(V$2,Inputs!$K$4:$AJ$4,0))))+SUMPRODUCT((Inputs!$C$5:$C$140=$B7)*ISNUMBER(INDEX(Inputs!$K$5:$AJ$140,0,MATCH(V$2,Inputs!$K$4:$AJ$4,0))))+SUMPRODUCT((Inputs!$E$5:$E$140=$B7)*ISNUMBER(INDEX(Inputs!$K$5:$AJ$140,0,MATCH(V$2,Inputs!$K$4:$AJ$4,0))))=0,NA(),SUMPRODUCT((Inputs!$A$5:$A$140=$B7)*Inputs!$B$5:$B$140*(((Inputs!$G$5:$G$140="moeda")+(Inputs!$G$5:$G$140="acoes"))*Inputs!$B$1+((Inputs!$G$5:$G$140<>"moeda")*(Inputs!$G$5:$G$140<>"acoes")))*INDEX(Inputs!$K$5:$AJ$140,0,MATCH(V$2,Inputs!$K$4:$AJ$4,0)))+SUMPRODUCT((Inputs!$C$5:$C$140=$B7)*Inputs!$D$5:$D$140*(((Inputs!$G$5:$G$140="moeda")+(Inputs!$G$5:$G$140="acoes"))*Inputs!$B$1+((Inputs!$G$5:$G$140<>"moeda")*(Inputs!$G$5:$G$140<>"acoes")))*INDEX(Inputs!$K$5:$AJ$140,0,MATCH(V$2,Inputs!$K$4:$AJ$4,0)))+SUMPRODUCT((Inputs!$E$5:$E$140=$B7)*Inputs!$F$5:$F$140*(((Inputs!$G$5:$G$140="moeda")+(Inputs!$G$5:$G$140="acoes"))*Inputs!$B$1+((Inputs!$G$5:$G$140<>"moeda")*(Inputs!$G$5:$G$140<>"acoes")))*INDEX(Inputs!$K$5:$AJ$140,0,MATCH(V$2,Inputs!$K$4:$AJ$4,0))))) -> -8.8111873 | W7: =SUM(S7:V7) -> -31.130963 | X7: =IF(ISNA(MATCH(X$2,Inputs!$K$4:$AJ$4,0)),NA(),IF(SUMPRODUCT((Inputs!$A$5:$A$140=$B7)*ISNUMBER(INDEX(Inputs!$K$5:$AJ$140,0,MATCH(X$2,Inputs!$K$4:$AJ$4,0))))+SUMPRODUCT((Inputs!$C$5:$C$140=$B7)*ISNUMBER(INDEX(Inputs!$K$5:$AJ$140,0,MATCH(X$2,Inputs!$K$4:$AJ$4,0))))+SUMPRODUCT((Inputs!$E$5:$E$140=$B7)*ISNUMBER(INDEX(Inputs!$K$5:$AJ$140,0,MATCH(X$2,Inputs!$K$4:$AJ$4,0))))=0,NA(),SUMPRODUCT((Inputs!$A$5:$A$140=$B7)*Inputs!$B$5:$B$140*(((Inputs!$G$5:$G$140="moeda")+(Inputs!$G$5:$G$140="acoes"))*Inputs!$B$1+((Inputs!$G$5:$G$140<>"moeda")*(Inputs!$G$5:$G$140<>"acoes")))*INDEX(Inputs!$K$5:$AJ$140,0,MATCH(X$2,Inputs!$K$4:$AJ$4,0)))+SUMPRODUCT((Inputs!$C$5:$C$140=$B7)*Inputs!$D$5:$D$140*(((Inputs!$G$5:$G$140="moeda")+(Inputs!$G$5:$G$140="acoes"))*Inputs!$B$1+((Inputs!$G$5:$G$140<>"moeda")*(Inputs!$G$5:$G$140<>"acoes")))*INDEX(Inputs!$K$5:$AJ$140,0,MATCH(X$2,Inputs!$K$4:$AJ$4,0)))+SUMPRODUCT((Inputs!$E$5:$E$140=$B7)*Inputs!$F$5:$F$140*(((Inputs!$G$5:$G$140="moeda")+(Inputs!$G$5:$G$140="acoes"))*Inputs!$B$1+((Inputs!$G$5:$G$140<>"moeda")*(Inputs!$G$5:$G$140<>"acoes")))*INDEX(Inputs!$K$5:$AJ$140,0,MATCH(X$2,Inputs!$K$4:$AJ$4,0))))) -> -8.533 | Y7: =IF(ISNA(MATCH(Y$2,Inputs!$K$4:$AJ$4,0)),NA(),IF(SUMPRODUCT((Inputs!$A$5:$A$140=$B7)*ISNUMBER(INDEX(Inputs!$K$5:$AJ$140,0,MATCH(Y$2,Inputs!$K$4:$AJ$4,0))))+SUMPRODUCT((Inputs!$C$5:$C$140=$B7)*ISNUMBER(INDEX(Inputs!$K$5:$AJ$140,0,MATCH(Y$2,Inputs!$K$4:$AJ$4,0))))+SUMPRODUCT((Inputs!$E$5:$E$140=$B7)*ISNUMBER(INDEX(Inputs!$K$5:$AJ$140,0,MATCH(Y$2,Inputs!$K$4:$AJ$4,0))))=0,NA(),SUMPRODUCT((Inputs!$A$5:$A$140=$B7)*Inputs!$B$5:$B$140*(((Inputs!$G$5:$G$140="moeda")+(Inputs!$G$5:$G$140="acoes"))*Inputs!$B$1+((Inputs!$G$5:$G$140<>"moeda")*(Inputs!$G$5:$G$140<>"acoes")))*INDEX(Inputs!$K$5:$AJ$140,0,MATCH(Y$2,Inputs!$K$4:$AJ$4,0)))+SUMPRODUCT((Inputs!$C$5:$C$140=$B7)*Inputs!$D$5:$D$140*(((Inputs!$G$5:$G$140="moeda")+(Inputs!$G$5:$G$140="acoes"))*Inputs!$B$1+((Inputs!$G$5:$G$140<>"moeda")*(Inputs!$G$5:$G$140<>"acoes")))*INDEX(Inputs!$K$5:$AJ$140,0,MATCH(Y$2,Inputs!$K$4:$AJ$4,0)))+SUMPRODUCT((Inputs!$E$5:$E$140=$B7)*Inputs!$F$5:$F$140*(((Inputs!$G$5:$G$140="moeda")+(Inputs!$G$5:$G$140="acoes"))*Inputs!$B$1+((Inputs!$G$5:$G$140<>"moeda")*(Inputs!$G$5:$G$140<>"acoes")))*INDEX(Inputs!$K$5:$AJ$140,0,MATCH(Y$2,Inputs!$K$4:$AJ$4,0))))) -> -8.754 | Z7: =IF(ISNA(MATCH(Z$2,Inputs!$K$4:$AJ$4,0)),NA(),IF(SUMPRODUCT((Inputs!$A$5:$A$140=$B7)*ISNUMBER(INDEX(Inputs!$K$5:$AJ$140,0,MATCH(Z$2,Inputs!$K$4:$AJ$4,0))))+SUMPRODUCT((Inputs!$C$5:$C$140=$B7)*ISNUMBER(INDEX(Inputs!$K$5:$AJ$140,0,MATCH(Z$2,Inputs!$K$4:$AJ$4,0))))+SUMPRODUCT((Inputs!$E$5:$E$140=$B7)*ISNUMBER(INDEX(Inputs!$K$5:$AJ$140,0,MATCH(Z$2,Inputs!$K$4:$AJ$4,0))))=0,NA(),SUMPRODUCT((Inputs!$A$5:$A$140=$B7)*Inputs!$B$5:$B$140*(((Inputs!$G$5:$G$140="moeda")+(Inputs!$G$5:$G$140="acoes"))*Inputs!$B$1+((Inputs!$G$5:$G$140<>"moeda")*(Inputs!$G$5:$G$140<>"acoes")))*INDEX(Inputs!$K$5:$AJ$140,0,MATCH(Z$2,Inputs!$K$4:$AJ$4,0)))+SUMPRODUCT((Inputs!$C$5:$C$140=$B7)*Inputs!$D$5:$D$140*(((Inputs!$G$5:$G$140="moeda")+(Inputs!$G$5:$G$140="acoes"))*Inputs!$B$1+((Inputs!$G$5:$G$140<>"moeda")*(Inputs!$G$5:$G$140<>"acoes")))*INDEX(Inputs!$K$5:$AJ$140,0,MATCH(Z$2,Inputs!$K$4:$AJ$4,0)))+SUMPRODUCT((Inputs!$E$5:$E$140=$B7)*Inputs!$F$5:$F$140*(((Inputs!$G$5:$G$140="moeda")+(Inputs!$G$5:$G$140="acoes"))*Inputs!$B$1+((Inputs!$G$5:$G$140<>"moeda")*(Inputs!$G$5:$G$140<>"acoes")))*INDEX(Inputs!$K$5:$AJ$140,0,MATCH(Z$2,Inputs!$K$4:$AJ$4,0))))) -> -8.521 | AA7: =IF(ISNA(MATCH(AA$2,Inputs!$K$4:$AJ$4,0)),NA(),IF(SUMPRODUCT((Inputs!$A$5:$A$140=$B7)*ISNUMBER(INDEX(Inputs!$K$5:$AJ$140,0,MATCH(AA$2,Inputs!$K$4:$AJ$4,0))))+SUMPRODUCT((Inputs!$C$5:$C$140=$B7)*ISNUMBER(INDEX(Inputs!$K$5:$AJ$140,0,MATCH(AA$2,Inputs!$K$4:$AJ$4,0))))+SUMPRODUCT((Inputs!$E$5:$E$140=$B7)*ISNUMBER(INDEX(Inputs!$K$5:$AJ$140,0,MATCH(AA$2,Inputs!$K$4:$AJ$4,0))))=0,NA(),SUMPRODUCT((Inputs!$A$5:$A$140=$B7)*Inputs!$B$5:$B$140*(((Inputs!$G$5:$G$140="moeda")+(Inputs!$G$5:$G$140="acoes"))*Inputs!$B$1+((Inputs!$G$5:$G$140<>"moeda")*(Inputs!$G$5:$G$140<>"acoes")))*INDEX(Inputs!$K$5:$AJ$140,0,MATCH(AA$2,Inputs!$K$4:$AJ$4,0)))+SUMPRODUCT((Inputs!$C$5:$C$140=$B7)*Inputs!$D$5:$D$140*(((Inputs!$G$5:$G$140="moeda")+(Inputs!$G$5:$G$140="acoes"))*Inputs!$B$1+((Inputs!$G$5:$G$140<>"moeda")*(Inputs!$G$5:$G$140<>"acoes")))*INDEX(Inputs!$K$5:$AJ$140,0,MATCH(AA$2,Inputs!$K$4:$AJ$4,0)))+SUMPRODUCT((Inputs!$E$5:$E$140=$B7)*Inputs!$F$5:$F$140*(((Inputs!$G$5:$G$140="moeda")+(Inputs!$G$5:$G$140="acoes"))*Inputs!$B$1+((Inputs!$G$5:$G$140<>"moeda")*(Inputs!$G$5:$G$140<>"acoes")))*INDEX(Inputs!$K$5:$AJ$140,0,MATCH(AA$2,Inputs!$K$4:$AJ$4,0))))) -> -9.07 | AB7: =SUM(X7:AA7) -> -34.878 | AC7: =IF(ISNA(MATCH(AC$2,Inputs!$K$4:$AJ$4,0)),NA(),IF(SUMPRODUCT((Inputs!$A$5:$A$140=$B7)*ISNUMBER(INDEX(Inputs!$K$5:$AJ$140,0,MATCH(AC$2,Inputs!$K$4:$AJ$4,0))))+SUMPRODUCT((Inputs!$C$5:$C$140=$B7)*ISNUMBER(INDEX(Inputs!$K$5:$AJ$140,0,MATCH(AC$2,Inputs!$K$4:$AJ$4,0))))+SUMPRODUCT((Inputs!$E$5:$E$140=$B7)*ISNUMBER(INDEX(Inputs!$K$5:$AJ$140,0,MATCH(AC$2,Inputs!$K$4:$AJ$4,0))))=0,NA(),SUMPRODUCT((Inputs!$A$5:$A$140=$B7)*Inputs!$B$5:$B$140*(((Inputs!$G$5:$G$140="moeda")+(Inputs!$G$5:$G$140="acoes"))*Inputs!$B$1+((Inputs!$G$5:$G$140<>"moeda")*(Inputs!$G$5:$G$140<>"acoes")))*INDEX(Inputs!$K$5:$AJ$140,0,MATCH(AC$2,Inputs!$K$4:$AJ$4,0)))+SUMPRODUCT((Inputs!$C$5:$C$140=$B7)*Inputs!$D$5:$D$140*(((Inputs!$G$5:$G$140="moeda")+(Inputs!$G$5:$G$140="acoes"))*Inputs!$B$1+((Inputs!$G$5:$G$140<>"moeda")*(Inputs!$G$5:$G$140<>"acoes")))*INDEX(Inputs!$K$5:$AJ$140,0,MATCH(AC$2,Inputs!$K$4:$AJ$4,0)))+SUMPRODUCT((Inputs!$E$5:$E$140=$B7)*Inputs!$F$5:$F$140*(((Inputs!$G$5:$G$140="moeda")+(Inputs!$G$5:$G$140="acoes"))*Inputs!$B$1+((Inputs!$G$5:$G$140<>"moeda")*(Inputs!$G$5:$G$140<>"acoes")))*INDEX(Inputs!$K$5:$AJ$140,0,MATCH(AC$2,Inputs!$K$4:$AJ$4,0))))) -> -8.349 | AD7: =IF(ISNA(MATCH(AD$2,Inputs!$K$4:$AJ$4,0)),NA(),IF(SUMPRODUCT((Inputs!$A$5:$A$140=$B7)*ISNUMBER(INDEX(Inputs!$K$5:$AJ$140,0,MATCH(AD$2,Inputs!$K$4:$AJ$4,0))))+SUMPRODUCT((Inputs!$C$5:$C$140=$B7)*ISNUMBER(INDEX(Inputs!$K$5:$AJ$140,0,MATCH(AD$2,Inputs!$K$4:$AJ$4,0))))+SUMPRODUCT((Inputs!$E$5:$E$140=$B7)*ISNUMBER(INDEX(Inputs!$K$5:$AJ$140,0,MATCH(AD$2,Inputs!$K$4:$AJ$4,0))))=0,NA(),SUMPRODUCT((Inputs!$A$5:$A$140=$B7)*Inputs!$B$5:$B$140*(((Inputs!$G$5:$G$140="moeda")+(Inputs!$G$5:$G$140="acoes"))*Inputs!$B$1+((Inputs!$G$5:$G$140<>"moeda")*(Inputs!$G$5:$G$140<>"acoes")))*INDEX(Inputs!$K$5:$AJ$140,0,MATCH(AD$2,Inputs!$K$4:$AJ$4,0)))+SUMPRODUCT((Inputs!$C$5:$C$140=$B7)*Inputs!$D$5:$D$140*(((Inputs!$G$5:$G$140="moeda")+(Inputs!$G$5:$G$140="acoes"))*Inputs!$B$1+((Inputs!$G$5:$G$140<>"moeda")*(Inputs!$G$5:$G$140<>"acoes")))*INDEX(Inputs!$K$5:$AJ$140,0,MATCH(AD$2,Inputs!$K$4:$AJ$4,0)))+SUMPRODUCT((Inputs!$E$5:$E$140=$B7)*Inputs!$F$5:$F$140*(((Inputs!$G$5:$G$140="moeda")+(Inputs!$G$5:$G$140="acoes"))*Inputs!$B$1+((Inputs!$G$5:$G$140<>"moeda")*(Inputs!$G$5:$G$140<>"acoes")))*INDEX(Inputs!$K$5:$AJ$140,0,MATCH(AD$2,Inputs!$K$4:$AJ$4,0))))) -> -8.551 | AE7: =IF(ISNA(MATCH(AE$2,Inputs!$K$4:$AJ$4,0)),NA(),IF(SUMPRODUCT((Inputs!$A$5:$A$140=$B7)*ISNUMBER(INDEX(Inputs!$K$5:$AJ$140,0,MATCH(AE$2,Inputs!$K$4:$AJ$4,0))))+SUMPRODUCT((Inputs!$C$5:$C$140=$B7)*ISNUMBER(INDEX(Inputs!$K$5:$AJ$140,0,MATCH(AE$2,Inputs!$K$4:$AJ$4,0))))+SUMPRODUCT((Inputs!$E$5:$E$140=$B7)*ISNUMBER(INDEX(Inputs!$K$5:$AJ$140,0,MATCH(AE$2,Inputs!$K$4:$AJ$4,0))))=0,NA(),SUMPRODUCT((Inputs!$A$5:$A$140=$B7)*Inputs!$B$5:$B$140*(((Inputs!$G$5:$G$140="moeda")+(Inputs!$G$5:$G$140="acoes"))*Inputs!$B$1+((Inputs!$G$5:$G$140<>"moeda")*(Inputs!$G$5:$G$140<>"acoes")))*INDEX(Inputs!$K$5:$AJ$140,0,MATCH(AE$2,Inputs!$K$4:$AJ$4,0)))+SUMPRODUCT((Inputs!$C$5:$C$140=$B7)*Inputs!$D$5:$D$140*(((Inputs!$G$5:$G$140="moeda")+(Inputs!$G$5:$G$140="acoes"))*Inputs!$B$1+((Inputs!$G$5:$G$140<>"moeda")*(Inputs!$G$5:$G$140<>"acoes")))*INDEX(Inputs!$K$5:$AJ$140,0,MATCH(AE$2,Inputs!$K$4:$AJ$4,0)))+SUMPRODUCT((Inputs!$E$5:$E$140=$B7)*Inputs!$F$5:$F$140*(((Inputs!$G$5:$G$140="moeda")+(Inputs!$G$5:$G$140="acoes"))*Inputs!$B$1+((Inputs!$G$5:$G$140<>"moeda")*(Inputs!$G$5:$G$140<>"acoes")))*INDEX(Inputs!$K$5:$AJ$140,0,MATCH(AE$2,Inputs!$K$4:$AJ$4,0))))) -> #N/A | AF7: =IF(ISNA(MATCH(AF$2,Inputs!$K$4:$AJ$4,0)),NA(),IF(SUMPRODUCT((Inputs!$A$5:$A$140=$B7)*ISNUMBER(INDEX(Inputs!$K$5:$AJ$140,0,MATCH(AF$2,Inputs!$K$4:$AJ$4,0))))+SUMPRODUCT((Inputs!$C$5:$C$140=$B7)*ISNUMBER(INDEX(Inputs!$K$5:$AJ$140,0,MATCH(AF$2,Inputs!$K$4:$AJ$4,0))))+SUMPRODUCT((Inputs!$E$5:$E$140=$B7)*ISNUMBER(INDEX(Inputs!$K$5:$AJ$140,0,MATCH(AF$2,Inputs!$K$4:$AJ$4,0))))=0,NA(),SUMPRODUCT((Inputs!$A$5:$A$140=$B7)*Inputs!$B$5:$B$140*(((Inputs!$G$5:$G$140="moeda")+(Inputs!$G$5:$G$140="acoes"))*Inputs!$B$1+((Inputs!$G$5:$G$140<>"moeda")*(Inputs!$G$5:$G$140<>"acoes")))*INDEX(Inputs!$K$5:$AJ$140,0,MATCH(AF$2,Inputs!$K$4:$AJ$4,0)))+SUMPRODUCT((Inputs!$C$5:$C$140=$B7)*Inputs!$D$5:$D$140*(((Inputs!$G$5:$G$140="moeda")+(Inputs!$G$5:$G$140="acoes"))*Inputs!$B$1+((Inputs!$G$5:$G$140<>"moeda")*(Inputs!$G$5:$G$140<>"acoes")))*INDEX(Inputs!$K$5:$AJ$140,0,MATCH(AF$2,Inputs!$K$4:$AJ$4,0)))+SUMPRODUCT((Inputs!$E$5:$E$140=$B7)*Inputs!$F$5:$F$140*(((Inputs!$G$5:$G$140="moeda")+(Inputs!$G$5:$G$140="acoes"))*Inputs!$B$1+((Inputs!$G$5:$G$140<>"moeda")*(Inputs!$G$5:$G$140<>"acoes")))*INDEX(Inputs!$K$5:$AJ$140,0,MATCH(AF$2,Inputs!$K$4:$AJ$4,0))))) -> #N/A | AG7: =SUM(AC7:AF7) -> #N/A | AH7: =IF(ISNA(MATCH(AH$2,Inputs!$K$4:$AJ$4,0)),NA(),IF(SUMPRODUCT((Inputs!$A$5:$A$140=$B7)*ISNUMBER(INDEX(Inputs!$K$5:$AJ$140,0,MATCH(AH$2,Inputs!$K$4:$AJ$4,0))))+SUMPRODUCT((Inputs!$C$5:$C$140=$B7)*ISNUMBER(INDEX(Inputs!$K$5:$AJ$140,0,MATCH(AH$2,Inputs!$K$4:$AJ$4,0))))+SUMPRODUCT((Inputs!$E$5:$E$140=$B7)*ISNUMBER(INDEX(Inputs!$K$5:$AJ$140,0,MATCH(AH$2,Inputs!$K$4:$AJ$4,0))))=0,NA(),SUMPRODUCT((Inputs!$A$5:$A$140=$B7)*Inputs!$B$5:$B$140*(((Inputs!$G$5:$G$140="moeda")+(Inputs!$G$5:$G$140="acoes"))*Inputs!$B$1+((Inputs!$G$5:$G$140<>"moeda")*(Inputs!$G$5:$G$140<>"acoes")))*INDEX(Inputs!$K$5:$AJ$140,0,MATCH(AH$2,Inputs!$K$4:$AJ$4,0)))+SUMPRODUCT((Inputs!$C$5:$C$140=$B7)*Inputs!$D$5:$D$140*(((Inputs!$G$5:$G$140="moeda")+(Inputs!$G$5:$G$140="acoes"))*Inputs!$B$1+((Inputs!$G$5:$G$140<>"moeda")*(Inputs!$G$5:$G$140<>"acoes")))*INDEX(Inputs!$K$5:$AJ$140,0,MATCH(AH$2,Inputs!$K$4:$AJ$4,0)))+SUMPRODUCT((Inputs!$E$5:$E$140=$B7)*Inputs!$F$5:$F$140*(((Inputs!$G$5:$G$140="moeda")+(Inputs!$G$5:$G$140="acoes"))*Inputs!$B$1+((Inputs!$G$5:$G$140<>"moeda")*(Inputs!$G$5:$G$140<>"acoes")))*INDEX(Inputs!$K$5:$AJ$140,0,MATCH(AH$2,Inputs!$K$4:$AJ$4,0))))) -> -2.925 | AI7: =IF(ISNA(MATCH(AI$2,Inputs!$K$4:$AJ$4,0)),NA(),IF(SUMPRODUCT((Inputs!$A$5:$A$140=$B7)*ISNUMBER(INDEX(Inputs!$K$5:$AJ$140,0,MATCH(AI$2,Inputs!$K$4:$AJ$4,0))))+SUMPRODUCT((Inputs!$C$5:$C$140=$B7)*ISNUMBER(INDEX(Inputs!$K$5:$AJ$140,0,MATCH(AI$2,Inputs!$K$4:$AJ$4,0))))+SUMPRODUCT((Inputs!$E$5:$E$140=$B7)*ISNUMBER(INDEX(Inputs!$K$5:$AJ$140,0,MATCH(AI$2,Inputs!$K$4:$AJ$4,0))))=0,NA(),SUMPRODUCT((Inputs!$A$5:$A$140=$B7)*Inputs!$B$5:$B$140*(((Inputs!$G$5:$G$140="moeda")+(Inputs!$G$5:$G$140="acoes"))*Inputs!$B$1+((Inputs!$G$5:$G$140<>"moeda")*(Inputs!$G$5:$G$140<>"acoes")))*INDEX(Inputs!$K$5:$AJ$140,0,MATCH(AI$2,Inputs!$K$4:$AJ$4,0)))+SUMPRODUCT((Inputs!$C$5:$C$140=$B7)*Inputs!$D$5:$D$140*(((Inputs!$G$5:$G$140="moeda")+(Inputs!$G$5:$G$140="acoes"))*Inputs!$B$1+((Inputs!$G$5:$G$140<>"moeda")*(Inputs!$G$5:$G$140<>"acoes")))*INDEX(Inputs!$K$5:$AJ$140,0,MATCH(AI$2,Inputs!$K$4:$AJ$4,0)))+SUMPRODUCT((Inputs!$E$5:$E$140=$B7)*Inputs!$F$5:$F$140*(((Inputs!$G$5:$G$140="moeda")+(Inputs!$G$5:$G$140="acoes"))*Inputs!$B$1+((Inputs!$G$5:$G$140<>"moeda")*(Inputs!$G$5:$G$140<>"acoes")))*INDEX(Inputs!$K$5:$AJ$140,0,MATCH(AI$2,Inputs!$K$4:$AJ$4,0))))) -> -0.307 | AJ7: =IF(ISNA(MATCH(AJ$2,Inputs!$K$4:$AJ$4,0)),NA(),IF(SUMPRODUCT((Inputs!$A$5:$A$140=$B7)*ISNUMBER(INDEX(Inputs!$K$5:$AJ$140,0,MATCH(AJ$2,Inputs!$K$4:$AJ$4,0))))+SUMPRODUCT((Inputs!$C$5:$C$140=$B7)*ISNUMBER(INDEX(Inputs!$K$5:$AJ$140,0,MATCH(AJ$2,Inputs!$K$4:$AJ$4,0))))+SUMPRODUCT((Inputs!$E$5:$E$140=$B7)*ISNUMBER(INDEX(Inputs!$K$5:$AJ$140,0,MATCH(AJ$2,Inputs!$K$4:$AJ$4,0))))=0,NA(),SUMPRODUCT((Inputs!$A$5:$A$140=$B7)*Inputs!$B$5:$B$140*(((Inputs!$G$5:$G$140="moeda")+(Inputs!$G$5:$G$140="acoes"))*Inputs!$B$1+((Inputs!$G$5:$G$140<>"moeda")*(Inputs!$G$5:$G$140<>"acoes")))*INDEX(Inputs!$K$5:$AJ$140,0,MATCH(AJ$2,Inputs!$K$4:$AJ$4,0)))+SUMPRODUCT((Inputs!$C$5:$C$140=$B7)*Inputs!$D$5:$D$140*(((Inputs!$G$5:$G$140="moeda")+(Inputs!$G$5:$G$140="acoes"))*Inputs!$B$1+((Inputs!$G$5:$G$140<>"moeda")*(Inputs!$G$5:$G$140<>"acoes")))*INDEX(Inputs!$K$5:$AJ$140,0,MATCH(AJ$2,Inputs!$K$4:$AJ$4,0)))+SUMPRODUCT((Inputs!$E$5:$E$140=$B7)*Inputs!$F$5:$F$140*(((Inputs!$G$5:$G$140="moeda")+(Inputs!$G$5:$G$140="acoes"))*Inputs!$B$1+((Inputs!$G$5:$G$140<>"moeda")*(Inputs!$G$5:$G$140<>"acoes")))*INDEX(Inputs!$K$5:$AJ$140,0,MATCH(AJ$2,Inputs!$K$4:$AJ$4,0))))) -> -0.365 | AK7: =IF(ISNA(MATCH(AK$2,Inputs!$K$4:$AJ$4,0)),NA(),IF(SUMPRODUCT((Inputs!$A$5:$A$140=$B7)*ISNUMBER(INDEX(Inputs!$K$5:$AJ$140,0,MATCH(AK$2,Inputs!$K$4:$AJ$4,0))))+SUMPRODUCT((Inputs!$C$5:$C$140=$B7)*ISNUMBER(INDEX(Inputs!$K$5:$AJ$140,0,MATCH(AK$2,Inputs!$K$4:$AJ$4,0))))+SUMPRODUCT((Inputs!$E$5:$E$140=$B7)*ISNUMBER(INDEX(Inputs!$K$5:$AJ$140,0,MATCH(AK$2,Inputs!$K$4:$AJ$4,0))))=0,NA(),SUMPRODUCT((Inputs!$A$5:$A$140=$B7)*Inputs!$B$5:$B$140*(((Inputs!$G$5:$G$140="moeda")+(Inputs!$G$5:$G$140="acoes"))*Inputs!$B$1+((Inputs!$G$5:$G$140<>"moeda")*(Inputs!$G$5:$G$140<>"acoes")))*INDEX(Inputs!$K$5:$AJ$140,0,MATCH(AK$2,Inputs!$K$4:$AJ$4,0)))+SUMPRODUCT((Inputs!$C$5:$C$140=$B7)*Inputs!$D$5:$D$140*(((Inputs!$G$5:$G$140="moeda")+(Inputs!$G$5:$G$140="acoes"))*Inputs!$B$1+((Inputs!$G$5:$G$140<>"moeda")*(Inputs!$G$5:$G$140<>"acoes")))*INDEX(Inputs!$K$5:$AJ$140,0,MATCH(AK$2,Inputs!$K$4:$AJ$4,0)))+SUMPRODUCT((Inputs!$E$5:$E$140=$B7)*Inputs!$F$5:$F$140*(((Inputs!$G$5:$G$140="moeda")+(Inputs!$G$5:$G$140="acoes"))*Inputs!$B$1+((Inputs!$G$5:$G$140<>"moeda")*(Inputs!$G$5:$G$140<>"acoes")))*INDEX(Inputs!$K$5:$AJ$140,0,MATCH(AK$2,Inputs!$K$4:$AJ$4,0))))) -> -0.26371006 | AL7: =SUM(AH7:AK7) -> -3.8607101
B8: 5 | C8: Interest Expense | D8: =IF(ISNA(MATCH(D$2,Inputs!$K$4:$AJ$4,0)),NA(),IF(SUMPRODUCT((Inputs!$A$5:$A$140=$B8)*ISNUMBER(INDEX(Inputs!$K$5:$AJ$140,0,MATCH(D$2,Inputs!$K$4:$AJ$4,0))))+SUMPRODUCT((Inputs!$C$5:$C$140=$B8)*ISNUMBER(INDEX(Inputs!$K$5:$AJ$140,0,MATCH(D$2,Inputs!$K$4:$AJ$4,0))))+SUMPRODUCT((Inputs!$E$5:$E$140=$B8)*ISNUMBER(INDEX(Inputs!$K$5:$AJ$140,0,MATCH(D$2,Inputs!$K$4:$AJ$4,0))))=0,NA(),SUMPRODUCT((Inputs!$A$5:$A$140=$B8)*Inputs!$B$5:$B$140*(((Inputs!$G$5:$G$140="moeda")+(Inputs!$G$5:$G$140="acoes"))*Inputs!$B$1+((Inputs!$G$5:$G$140<>"moeda")*(Inputs!$G$5:$G$140<>"acoes")))*INDEX(Inputs!$K$5:$AJ$140,0,MATCH(D$2,Inputs!$K$4:$AJ$4,0)))+SUMPRODUCT((Inputs!$C$5:$C$140=$B8)*Inputs!$D$5:$D$140*(((Inputs!$G$5:$G$140="moeda")+(Inputs!$G$5:$G$140="acoes"))*Inputs!$B$1+((Inputs!$G$5:$G$140<>"moeda")*(Inputs!$G$5:$G$140<>"acoes")))*INDEX(Inputs!$K$5:$AJ$140,0,MATCH(D$2,Inputs!$K$4:$AJ$4,0)))+SUMPRODUCT((Inputs!$E$5:$E$140=$B8)*Inputs!$F$5:$F$140*(((Inputs!$G$5:$G$140="moeda")+(Inputs!$G$5:$G$140="acoes"))*Inputs!$B$1+((Inputs!$G$5:$G$140<>"moeda")*(Inputs!$G$5:$G$140<>"acoes")))*INDEX(Inputs!$K$5:$AJ$140,0,MATCH(D$2,Inputs!$K$4:$AJ$4,0))))) -> -7.256 | E8: =IF(ISNA(MATCH(E$2,Inputs!$K$4:$AJ$4,0)),NA(),IF(SUMPRODUCT((Inputs!$A$5:$A$140=$B8)*ISNUMBER(INDEX(Inputs!$K$5:$AJ$140,0,MATCH(E$2,Inputs!$K$4:$AJ$4,0))))+SUMPRODUCT((Inputs!$C$5:$C$140=$B8)*ISNUMBER(INDEX(Inputs!$K$5:$AJ$140,0,MATCH(E$2,Inputs!$K$4:$AJ$4,0))))+SUMPRODUCT((Inputs!$E$5:$E$140=$B8)*ISNUMBER(INDEX(Inputs!$K$5:$AJ$140,0,MATCH(E$2,Inputs!$K$4:$AJ$4,0))))=0,NA(),SUMPRODUCT((Inputs!$A$5:$A$140=$B8)*Inputs!$B$5:$B$140*(((Inputs!$G$5:$G$140="moeda")+(Inputs!$G$5:$G$140="acoes"))*Inputs!$B$1+((Inputs!$G$5:$G$140<>"moeda")*(Inputs!$G$5:$G$140<>"acoes")))*INDEX(Inputs!$K$5:$AJ$140,0,MATCH(E$2,Inputs!$K$4:$AJ$4,0)))+SUMPRODUCT((Inputs!$C$5:$C$140=$B8)*Inputs!$D$5:$D$140*(((Inputs!$G$5:$G$140="moeda")+(Inputs!$G$5:$G$140="acoes"))*Inputs!$B$1+((Inputs!$G$5:$G$140<>"moeda")*(Inputs!$G$5:$G$140<>"acoes")))*INDEX(Inputs!$K$5:$AJ$140,0,MATCH(E$2,Inputs!$K$4:$AJ$4,0)))+SUMPRODUCT((Inputs!$E$5:$E$140=$B8)*Inputs!$F$5:$F$140*(((Inputs!$G$5:$G$140="moeda")+(Inputs!$G$5:$G$140="acoes"))*Inputs!$B$1+((Inputs!$G$5:$G$140<>"moeda")*(Inputs!$G$5:$G$140<>"acoes")))*INDEX(Inputs!$K$5:$AJ$140,0,MATCH(E$2,Inputs!$K$4:$AJ$4,0))))) -> -9.3 | F8: =IF(ISNA(MATCH(F$2,Inputs!$K$4:$AJ$4,0)),NA(),IF(SUMPRODUCT((Inputs!$A$5:$A$140=$B8)*ISNUMBER(INDEX(Inputs!$K$5:$AJ$140,0,MATCH(F$2,Inputs!$K$4:$AJ$4,0))))+SUMPRODUCT((Inputs!$C$5:$C$140=$B8)*ISNUMBER(INDEX(Inputs!$K$5:$AJ$140,0,MATCH(F$2,Inputs!$K$4:$AJ$4,0))))+SUMPRODUCT((Inputs!$E$5:$E$140=$B8)*ISNUMBER(INDEX(Inputs!$K$5:$AJ$140,0,MATCH(F$2,Inputs!$K$4:$AJ$4,0))))=0,NA(),SUMPRODUCT((Inputs!$A$5:$A$140=$B8)*Inputs!$B$5:$B$140*(((Inputs!$G$5:$G$140="moeda")+(Inputs!$G$5:$G$140="acoes"))*Inputs!$B$1+((Inputs!$G$5:$G$140<>"moeda")*(Inputs!$G$5:$G$140<>"acoes")))*INDEX(Inputs!$K$5:$AJ$140,0,MATCH(F$2,Inputs!$K$4:$AJ$4,0)))+SUMPRODUCT((Inputs!$C$5:$C$140=$B8)*Inputs!$D$5:$D$140*(((Inputs!$G$5:$G$140="moeda")+(Inputs!$G$5:$G$140="acoes"))*Inputs!$B$1+((Inputs!$G$5:$G$140<>"moeda")*(Inputs!$G$5:$G$140<>"acoes")))*INDEX(Inputs!$K$5:$AJ$140,0,MATCH(F$2,Inputs!$K$4:$AJ$4,0)))+SUMPRODUCT((Inputs!$E$5:$E$140=$B8)*Inputs!$F$5:$F$140*(((Inputs!$G$5:$G$140="moeda")+(Inputs!$G$5:$G$140="acoes"))*Inputs!$B$1+((Inputs!$G$5:$G$140<>"moeda")*(Inputs!$G$5:$G$140<>"acoes")))*INDEX(Inputs!$K$5:$AJ$140,0,MATCH(F$2,Inputs!$K$4:$AJ$4,0))))) -> -11.43 | G8: =IF(ISNA(MATCH(G$2,Inputs!$K$4:$AJ$4,0)),NA(),IF(SUMPRODUCT((Inputs!$A$5:$A$140=$B8)*ISNUMBER(INDEX(Inputs!$K$5:$AJ$140,0,MATCH(G$2,Inputs!$K$4:$AJ$4,0))))+SUMPRODUCT((Inputs!$C$5:$C$140=$B8)*ISNUMBER(INDEX(Inputs!$K$5:$AJ$140,0,MATCH(G$2,Inputs!$K$4:$AJ$4,0))))+SUMPRODUCT((Inputs!$E$5:$E$140=$B8)*ISNUMBER(INDEX(Inputs!$K$5:$AJ$140,0,MATCH(G$2,Inputs!$K$4:$AJ$4,0))))=0,NA(),SUMPRODUCT((Inputs!$A$5:$A$140=$B8)*Inputs!$B$5:$B$140*(((Inputs!$G$5:$G$140="moeda")+(Inputs!$G$5:$G$140="acoes"))*Inputs!$B$1+((Inputs!$G$5:$G$140<>"moeda")*(Inputs!$G$5:$G$140<>"acoes")))*INDEX(Inputs!$K$5:$AJ$140,0,MATCH(G$2,Inputs!$K$4:$AJ$4,0)))+SUMPRODUCT((Inputs!$C$5:$C$140=$B8)*Inputs!$D$5:$D$140*(((Inputs!$G$5:$G$140="moeda")+(Inputs!$G$5:$G$140="acoes"))*Inputs!$B$1+((Inputs!$G$5:$G$140<>"moeda")*(Inputs!$G$5:$G$140<>"acoes")))*INDEX(Inputs!$K$5:$AJ$140,0,MATCH(G$2,Inputs!$K$4:$AJ$4,0)))+SUMPRODUCT((Inputs!$E$5:$E$140=$B8)*Inputs!$F$5:$F$140*(((Inputs!$G$5:$G$140="moeda")+(Inputs!$G$5:$G$140="acoes"))*Inputs!$B$1+((Inputs!$G$5:$G$140<>"moeda")*(Inputs!$G$5:$G$140<>"acoes")))*INDEX(Inputs!$K$5:$AJ$140,0,MATCH(G$2,Inputs!$K$4:$AJ$4,0))))) -> -21.731 | H8: =SUM(D8:G8) -> -49.717 | I8: =IF(ISNA(MATCH(I$2,Inputs!$K$4:$AJ$4,0)),NA(),IF(SUMPRODUCT((Inputs!$A$5:$A$140=$B8)*ISNUMBER(INDEX(Inputs!$K$5:$AJ$140,0,MATCH(I$2,Inputs!$K$4:$AJ$4,0))))+SUMPRODUCT((Inputs!$C$5:$C$140=$B8)*ISNUMBER(INDEX(Inputs!$K$5:$AJ$140,0,MATCH(I$2,Inputs!$K$4:$AJ$4,0))))+SUMPRODUCT((Inputs!$E$5:$E$140=$B8)*ISNUMBER(INDEX(Inputs!$K$5:$AJ$140,0,MATCH(I$2,Inputs!$K$4:$AJ$4,0))))=0,NA(),SUMPRODUCT((Inputs!$A$5:$A$140=$B8)*Inputs!$B$5:$B$140*(((Inputs!$G$5:$G$140="moeda")+(Inputs!$G$5:$G$140="acoes"))*Inputs!$B$1+((Inputs!$G$5:$G$140<>"moeda")*(Inputs!$G$5:$G$140<>"acoes")))*INDEX(Inputs!$K$5:$AJ$140,0,MATCH(I$2,Inputs!$K$4:$AJ$4,0)))+SUMPRODUCT((Inputs!$C$5:$C$140=$B8)*Inputs!$D$5:$D$140*(((Inputs!$G$5:$G$140="moeda")+(Inputs!$G$5:$G$140="acoes"))*Inputs!$B$1+((Inputs!$G$5:$G$140<>"moeda")*(Inputs!$G$5:$G$140<>"acoes")))*INDEX(Inputs!$K$5:$AJ$140,0,MATCH(I$2,Inputs!$K$4:$AJ$4,0)))+SUMPRODUCT((Inputs!$E$5:$E$140=$B8)*Inputs!$F$5:$F$140*(((Inputs!$G$5:$G$140="moeda")+(Inputs!$G$5:$G$140="acoes"))*Inputs!$B$1+((Inputs!$G$5:$G$140<>"moeda")*(Inputs!$G$5:$G$140<>"acoes")))*INDEX(Inputs!$K$5:$AJ$140,0,MATCH(I$2,Inputs!$K$4:$AJ$4,0))))) -> -17.062 | J8: =IF(ISNA(MATCH(J$2,Inputs!$K$4:$AJ$4,0)),NA(),IF(SUMPRODUCT((Inputs!$A$5:$A$140=$B8)*ISNUMBER(INDEX(Inputs!$K$5:$AJ$140,0,MATCH(J$2,Inputs!$K$4:$AJ$4,0))))+SUMPRODUCT((Inputs!$C$5:$C$140=$B8)*ISNUMBER(INDEX(Inputs!$K$5:$AJ$140,0,MATCH(J$2,Inputs!$K$4:$AJ$4,0))))+SUMPRODUCT((Inputs!$E$5:$E$140=$B8)*ISNUMBER(INDEX(Inputs!$K$5:$AJ$140,0,MATCH(J$2,Inputs!$K$4:$AJ$4,0))))=0,NA(),SUMPRODUCT((Inputs!$A$5:$A$140=$B8)*Inputs!$B$5:$B$140*(((Inputs!$G$5:$G$140="moeda")+(Inputs!$G$5:$G$140="acoes"))*Inputs!$B$1+((Inputs!$G$5:$G$140<>"moeda")*(Inputs!$G$5:$G$140<>"acoes")))*INDEX(Inputs!$K$5:$AJ$140,0,MATCH(J$2,Inputs!$K$4:$AJ$4,0)))+SUMPRODUCT((Inputs!$C$5:$C$140=$B8)*Inputs!$D$5:$D$140*(((Inputs!$G$5:$G$140="moeda")+(Inputs!$G$5:$G$140="acoes"))*Inputs!$B$1+((Inputs!$G$5:$G$140<>"moeda")*(Inputs!$G$5:$G$140<>"acoes")))*INDEX(Inputs!$K$5:$AJ$140,0,MATCH(J$2,Inputs!$K$4:$AJ$4,0)))+SUMPRODUCT((Inputs!$E$5:$E$140=$B8)*Inputs!$F$5:$F$140*(((Inputs!$G$5:$G$140="moeda")+(Inputs!$G$5:$G$140="acoes"))*Inputs!$B$1+((Inputs!$G$5:$G$140<>"moeda")*(Inputs!$G$5:$G$140<>"acoes")))*INDEX(Inputs!$K$5:$AJ$140,0,MATCH(J$2,Inputs!$K$4:$AJ$4,0))))) -> -22.214 | K8: =IF(ISNA(MATCH(K$2,Inputs!$K$4:$AJ$4,0)),NA(),IF(SUMPRODUCT((Inputs!$A$5:$A$140=$B8)*ISNUMBER(INDEX(Inputs!$K$5:$AJ$140,0,MATCH(K$2,Inputs!$K$4:$AJ$4,0))))+SUMPRODUCT((Inputs!$C$5:$C$140=$B8)*ISNUMBER(INDEX(Inputs!$K$5:$AJ$140,0,MATCH(K$2,Inputs!$K$4:$AJ$4,0))))+SUMPRODUCT((Inputs!$E$5:$E$140=$B8)*ISNUMBER(INDEX(Inputs!$K$5:$AJ$140,0,MATCH(K$2,Inputs!$K$4:$AJ$4,0))))=0,NA(),SUMPRODUCT((Inputs!$A$5:$A$140=$B8)*Inputs!$B$5:$B$140*(((Inputs!$G$5:$G$140="moeda")+(Inputs!$G$5:$G$140="acoes"))*Inputs!$B$1+((Inputs!$G$5:$G$140<>"moeda")*(Inputs!$G$5:$G$140<>"acoes")))*INDEX(Inputs!$K$5:$AJ$140,0,MATCH(K$2,Inputs!$K$4:$AJ$4,0)))+SUMPRODUCT((Inputs!$C$5:$C$140=$B8)*Inputs!$D$5:$D$140*(((Inputs!$G$5:$G$140="moeda")+(Inputs!$G$5:$G$140="acoes"))*Inputs!$B$1+((Inputs!$G$5:$G$140<>"moeda")*(Inputs!$G$5:$G$140<>"acoes")))*INDEX(Inputs!$K$5:$AJ$140,0,MATCH(K$2,Inputs!$K$4:$AJ$4,0)))+SUMPRODUCT((Inputs!$E$5:$E$140=$B8)*Inputs!$F$5:$F$140*(((Inputs!$G$5:$G$140="moeda")+(Inputs!$G$5:$G$140="acoes"))*Inputs!$B$1+((Inputs!$G$5:$G$140<>"moeda")*(Inputs!$G$5:$G$140<>"acoes")))*INDEX(Inputs!$K$5:$AJ$140,0,MATCH(K$2,Inputs!$K$4:$AJ$4,0))))) -> -22.86 | L8: =IF(ISNA(MATCH(L$2,Inputs!$K$4:$AJ$4,0)),NA(),IF(SUMPRODUCT((Inputs!$A$5:$A$140=$B8)*ISNUMBER(INDEX(Inputs!$K$5:$AJ$140,0,MATCH(L$2,Inputs!$K$4:$AJ$4,0))))+SUMPRODUCT((Inputs!$C$5:$C$140=$B8)*ISNUMBER(INDEX(Inputs!$K$5:$AJ$140,0,MATCH(L$2,Inputs!$K$4:$AJ$4,0))))+SUMPRODUCT((Inputs!$E$5:$E$140=$B8)*ISNUMBER(INDEX(Inputs!$K$5:$AJ$140,0,MATCH(L$2,Inputs!$K$4:$AJ$4,0))))=0,NA(),SUMPRODUCT((Inputs!$A$5:$A$140=$B8)*Inputs!$B$5:$B$140*(((Inputs!$G$5:$G$140="moeda")+(Inputs!$G$5:$G$140="acoes"))*Inputs!$B$1+((Inputs!$G$5:$G$140<>"moeda")*(Inputs!$G$5:$G$140<>"acoes")))*INDEX(Inputs!$K$5:$AJ$140,0,MATCH(L$2,Inputs!$K$4:$AJ$4,0)))+SUMPRODUCT((Inputs!$C$5:$C$140=$B8)*Inputs!$D$5:$D$140*(((Inputs!$G$5:$G$140="moeda")+(Inputs!$G$5:$G$140="acoes"))*Inputs!$B$1+((Inputs!$G$5:$G$140<>"moeda")*(Inputs!$G$5:$G$140<>"acoes")))*INDEX(Inputs!$K$5:$AJ$140,0,MATCH(L$2,Inputs!$K$4:$AJ$4,0)))+SUMPRODUCT((Inputs!$E$5:$E$140=$B8)*Inputs!$F$5:$F$140*(((Inputs!$G$5:$G$140="moeda")+(Inputs!$G$5:$G$140="acoes"))*Inputs!$B$1+((Inputs!$G$5:$G$140<>"moeda")*(Inputs!$G$5:$G$140<>"acoes")))*INDEX(Inputs!$K$5:$AJ$140,0,MATCH(L$2,Inputs!$K$4:$AJ$4,0))))) -> -26.332 | M8: =SUM(I8:L8) -> -88.468 | N8: =IF(ISNA(MATCH(N$2,Inputs!$K$4:$AJ$4,0)),NA(),IF(SUMPRODUCT((Inputs!$A$5:$A$140=$B8)*ISNUMBER(INDEX(Inputs!$K$5:$AJ$140,0,MATCH(N$2,Inputs!$K$4:$AJ$4,0))))+SUMPRODUCT((Inputs!$C$5:$C$140=$B8)*ISNUMBER(INDEX(Inputs!$K$5:$AJ$140,0,MATCH(N$2,Inputs!$K$4:$AJ$4,0))))+SUMPRODUCT((Inputs!$E$5:$E$140=$B8)*ISNUMBER(INDEX(Inputs!$K$5:$AJ$140,0,MATCH(N$2,Inputs!$K$4:$AJ$4,0))))=0,NA(),SUMPRODUCT((Inputs!$A$5:$A$140=$B8)*Inputs!$B$5:$B$140*(((Inputs!$G$5:$G$140="moeda")+(Inputs!$G$5:$G$140="acoes"))*Inputs!$B$1+((Inputs!$G$5:$G$140<>"moeda")*(Inputs!$G$5:$G$140<>"acoes")))*INDEX(Inputs!$K$5:$AJ$140,0,MATCH(N$2,Inputs!$K$4:$AJ$4,0)))+SUMPRODUCT((Inputs!$C$5:$C$140=$B8)*Inputs!$D$5:$D$140*(((Inputs!$G$5:$G$140="moeda")+(Inputs!$G$5:$G$140="acoes"))*Inputs!$B$1+((Inputs!$G$5:$G$140<>"moeda")*(Inputs!$G$5:$G$140<>"acoes")))*INDEX(Inputs!$K$5:$AJ$140,0,MATCH(N$2,Inputs!$K$4:$AJ$4,0)))+SUMPRODUCT((Inputs!$E$5:$E$140=$B8)*Inputs!$F$5:$F$140*(((Inputs!$G$5:$G$140="moeda")+(Inputs!$G$5:$G$140="acoes"))*Inputs!$B$1+((Inputs!$G$5:$G$140<>"moeda")*(Inputs!$G$5:$G$140<>"acoes")))*INDEX(Inputs!$K$5:$AJ$140,0,MATCH(N$2,Inputs!$K$4:$AJ$4,0))))) -> -25.672 | O8: =IF(ISNA(MATCH(O$2,Inputs!$K$4:$AJ$4,0)),NA(),IF(SUMPRODUCT((Inputs!$A$5:$A$140=$B8)*ISNUMBER(INDEX(Inputs!$K$5:$AJ$140,0,MATCH(O$2,Inputs!$K$4:$AJ$4,0))))+SUMPRODUCT((Inputs!$C$5:$C$140=$B8)*ISNUMBER(INDEX(Inputs!$K$5:$AJ$140,0,MATCH(O$2,Inputs!$K$4:$AJ$4,0))))+SUMPRODUCT((Inputs!$E$5:$E$140=$B8)*ISNUMBER(INDEX(Inputs!$K$5:$AJ$140,0,MATCH(O$2,Inputs!$K$4:$AJ$4,0))))=0,NA(),SUMPRODUCT((Inputs!$A$5:$A$140=$B8)*Inputs!$B$5:$B$140*(((Inputs!$G$5:$G$140="moeda")+(Inputs!$G$5:$G$140="acoes"))*Inputs!$B$1+((Inputs!$G$5:$G$140<>"moeda")*(Inputs!$G$5:$G$140<>"acoes")))*INDEX(Inputs!$K$5:$AJ$140,0,MATCH(O$2,Inputs!$K$4:$AJ$4,0)))+SUMPRODUCT((Inputs!$C$5:$C$140=$B8)*Inputs!$D$5:$D$140*(((Inputs!$G$5:$G$140="moeda")+(Inputs!$G$5:$G$140="acoes"))*Inputs!$B$1+((Inputs!$G$5:$G$140<>"moeda")*(Inputs!$G$5:$G$140<>"acoes")))*INDEX(Inputs!$K$5:$AJ$140,0,MATCH(O$2,Inputs!$K$4:$AJ$4,0)))+SUMPRODUCT((Inputs!$E$5:$E$140=$B8)*Inputs!$F$5:$F$140*(((Inputs!$G$5:$G$140="moeda")+(Inputs!$G$5:$G$140="acoes"))*Inputs!$B$1+((Inputs!$G$5:$G$140<>"moeda")*(Inputs!$G$5:$G$140<>"acoes")))*INDEX(Inputs!$K$5:$AJ$140,0,MATCH(O$2,Inputs!$K$4:$AJ$4,0))))) -> -26.026 | P8: =IF(ISNA(MATCH(P$2,Inputs!$K$4:$AJ$4,0)),NA(),IF(SUMPRODUCT((Inputs!$A$5:$A$140=$B8)*ISNUMBER(INDEX(Inputs!$K$5:$AJ$140,0,MATCH(P$2,Inputs!$K$4:$AJ$4,0))))+SUMPRODUCT((Inputs!$C$5:$C$140=$B8)*ISNUMBER(INDEX(Inputs!$K$5:$AJ$140,0,MATCH(P$2,Inputs!$K$4:$AJ$4,0))))+SUMPRODUCT((Inputs!$E$5:$E$140=$B8)*ISNUMBER(INDEX(Inputs!$K$5:$AJ$140,0,MATCH(P$2,Inputs!$K$4:$AJ$4,0))))=0,NA(),SUMPRODUCT((Inputs!$A$5:$A$140=$B8)*Inputs!$B$5:$B$140*(((Inputs!$G$5:$G$140="moeda")+(Inputs!$G$5:$G$140="acoes"))*Inputs!$B$1+((Inputs!$G$5:$G$140<>"moeda")*(Inputs!$G$5:$G$140<>"acoes")))*INDEX(Inputs!$K$5:$AJ$140,0,MATCH(P$2,Inputs!$K$4:$AJ$4,0)))+SUMPRODUCT((Inputs!$C$5:$C$140=$B8)*Inputs!$D$5:$D$140*(((Inputs!$G$5:$G$140="moeda")+(Inputs!$G$5:$G$140="acoes"))*Inputs!$B$1+((Inputs!$G$5:$G$140<>"moeda")*(Inputs!$G$5:$G$140<>"acoes")))*INDEX(Inputs!$K$5:$AJ$140,0,MATCH(P$2,Inputs!$K$4:$AJ$4,0)))+SUMPRODUCT((Inputs!$E$5:$E$140=$B8)*Inputs!$F$5:$F$140*(((Inputs!$G$5:$G$140="moeda")+(Inputs!$G$5:$G$140="acoes"))*Inputs!$B$1+((Inputs!$G$5:$G$140<>"moeda")*(Inputs!$G$5:$G$140<>"acoes")))*INDEX(Inputs!$K$5:$AJ$140,0,MATCH(P$2,Inputs!$K$4:$AJ$4,0))))) -> -23.214 | Q8: =IF(ISNA(MATCH(Q$2,Inputs!$K$4:$AJ$4,0)),NA(),IF(SUMPRODUCT((Inputs!$A$5:$A$140=$B8)*ISNUMBER(INDEX(Inputs!$K$5:$AJ$140,0,MATCH(Q$2,Inputs!$K$4:$AJ$4,0))))+SUMPRODUCT((Inputs!$C$5:$C$140=$B8)*ISNUMBER(INDEX(Inputs!$K$5:$AJ$140,0,MATCH(Q$2,Inputs!$K$4:$AJ$4,0))))+SUMPRODUCT((Inputs!$E$5:$E$140=$B8)*ISNUMBER(INDEX(Inputs!$K$5:$AJ$140,0,MATCH(Q$2,Inputs!$K$4:$AJ$4,0))))=0,NA(),SUMPRODUCT((Inputs!$A$5:$A$140=$B8)*Inputs!$B$5:$B$140*(((Inputs!$G$5:$G$140="moeda")+(Inputs!$G$5:$G$140="acoes"))*Inputs!$B$1+((Inputs!$G$5:$G$140<>"moeda")*(Inputs!$G$5:$G$140<>"acoes")))*INDEX(Inputs!$K$5:$AJ$140,0,MATCH(Q$2,Inputs!$K$4:$AJ$4,0)))+SUMPRODUCT((Inputs!$C$5:$C$140=$B8)*Inputs!$D$5:$D$140*(((Inputs!$G$5:$G$140="moeda")+(Inputs!$G$5:$G$140="acoes"))*Inputs!$B$1+((Inputs!$G$5:$G$140<>"moeda")*(Inputs!$G$5:$G$140<>"acoes")))*INDEX(Inputs!$K$5:$AJ$140,0,MATCH(Q$2,Inputs!$K$4:$AJ$4,0)))+SUMPRODUCT((Inputs!$E$5:$E$140=$B8)*Inputs!$F$5:$F$140*(((Inputs!$G$5:$G$140="moeda")+(Inputs!$G$5:$G$140="acoes"))*Inputs!$B$1+((Inputs!$G$5:$G$140<>"moeda")*(Inputs!$G$5:$G$140<>"acoes")))*INDEX(Inputs!$K$5:$AJ$140,0,MATCH(Q$2,Inputs!$K$4:$AJ$4,0))))) -> -25.215 | R8: =SUM(N8:Q8) -> -100.127 | S8: =IF(ISNA(MATCH(S$2,Inputs!$K$4:$AJ$4,0)),NA(),IF(SUMPRODUCT((Inputs!$A$5:$A$140=$B8)*ISNUMBER(INDEX(Inputs!$K$5:$AJ$140,0,MATCH(S$2,Inputs!$K$4:$AJ$4,0))))+SUMPRODUCT((Inputs!$C$5:$C$140=$B8)*ISNUMBER(INDEX(Inputs!$K$5:$AJ$140,0,MATCH(S$2,Inputs!$K$4:$AJ$4,0))))+SUMPRODUCT((Inputs!$E$5:$E$140=$B8)*ISNUMBER(INDEX(Inputs!$K$5:$AJ$140,0,MATCH(S$2,Inputs!$K$4:$AJ$4,0))))=0,NA(),SUMPRODUCT((Inputs!$A$5:$A$140=$B8)*Inputs!$B$5:$B$140*(((Inputs!$G$5:$G$140="moeda")+(Inputs!$G$5:$G$140="acoes"))*Inputs!$B$1+((Inputs!$G$5:$G$140<>"moeda")*(Inputs!$G$5:$G$140<>"acoes")))*INDEX(Inputs!$K$5:$AJ$140,0,MATCH(S$2,Inputs!$K$4:$AJ$4,0)))+SUMPRODUCT((Inputs!$C$5:$C$140=$B8)*Inputs!$D$5:$D$140*(((Inputs!$G$5:$G$140="moeda")+(Inputs!$G$5:$G$140="acoes"))*Inputs!$B$1+((Inputs!$G$5:$G$140<>"moeda")*(Inputs!$G$5:$G$140<>"acoes")))*INDEX(Inputs!$K$5:$AJ$140,0,MATCH(S$2,Inputs!$K$4:$AJ$4,0)))+SUMPRODUCT((Inputs!$E$5:$E$140=$B8)*Inputs!$F$5:$F$140*(((Inputs!$G$5:$G$140="moeda")+(Inputs!$G$5:$G$140="acoes"))*Inputs!$B$1+((Inputs!$G$5:$G$140<>"moeda")*(Inputs!$G$5:$G$140<>"acoes")))*INDEX(Inputs!$K$5:$AJ$140,0,MATCH(S$2,Inputs!$K$4:$AJ$4,0))))) -> -24.806 | T8: =IF(ISNA(MATCH(T$2,Inputs!$K$4:$AJ$4,0)),NA(),IF(SUMPRODUCT((Inputs!$A$5:$A$140=$B8)*ISNUMBER(INDEX(Inputs!$K$5:$AJ$140,0,MATCH(T$2,Inputs!$K$4:$AJ$4,0))))+SUMPRODUCT((Inputs!$C$5:$C$140=$B8)*ISNUMBER(INDEX(Inputs!$K$5:$AJ$140,0,MATCH(T$2,Inputs!$K$4:$AJ$4,0))))+SUMPRODUCT((Inputs!$E$5:$E$140=$B8)*ISNUMBER(INDEX(Inputs!$K$5:$AJ$140,0,MATCH(T$2,Inputs!$K$4:$AJ$4,0))))=0,NA(),SUMPRODUCT((Inputs!$A$5:$A$140=$B8)*Inputs!$B$5:$B$140*(((Inputs!$G$5:$G$140="moeda")+(Inputs!$G$5:$G$140="acoes"))*Inputs!$B$1+((Inputs!$G$5:$G$140<>"moeda")*(Inputs!$G$5:$G$140<>"acoes")))*INDEX(Inputs!$K$5:$AJ$140,0,MATCH(T$2,Inputs!$K$4:$AJ$4,0)))+SUMPRODUCT((Inputs!$C$5:$C$140=$B8)*Inputs!$D$5:$D$140*(((Inputs!$G$5:$G$140="moeda")+(Inputs!$G$5:$G$140="acoes"))*Inputs!$B$1+((Inputs!$G$5:$G$140<>"moeda")*(Inputs!$G$5:$G$140<>"acoes")))*INDEX(Inputs!$K$5:$AJ$140,0,MATCH(T$2,Inputs!$K$4:$AJ$4,0)))+SUMPRODUCT((Inputs!$E$5:$E$140=$B8)*Inputs!$F$5:$F$140*(((Inputs!$G$5:$G$140="moeda")+(Inputs!$G$5:$G$140="acoes"))*Inputs!$B$1+((Inputs!$G$5:$G$140<>"moeda")*(Inputs!$G$5:$G$140<>"acoes")))*INDEX(Inputs!$K$5:$AJ$140,0,MATCH(T$2,Inputs!$K$4:$AJ$4,0))))) -> -31.099 | U8: =IF(ISNA(MATCH(U$2,Inputs!$K$4:$AJ$4,0)),NA(),IF(SUMPRODUCT((Inputs!$A$5:$A$140=$B8)*ISNUMBER(INDEX(Inputs!$K$5:$AJ$140,0,MATCH(U$2,Inputs!$K$4:$AJ$4,0))))+SUMPRODUCT((Inputs!$C$5:$C$140=$B8)*ISNUMBER(INDEX(Inputs!$K$5:$AJ$140,0,MATCH(U$2,Inputs!$K$4:$AJ$4,0))))+SUMPRODUCT((Inputs!$E$5:$E$140=$B8)*ISNUMBER(INDEX(Inputs!$K$5:$AJ$140,0,MATCH(U$2,Inputs!$K$4:$AJ$4,0))))=0,NA(),SUMPRODUCT((Inputs!$A$5:$A$140=$B8)*Inputs!$B$5:$B$140*(((Inputs!$G$5:$G$140="moeda")+(Inputs!$G$5:$G$140="acoes"))*Inputs!$B$1+((Inputs!$G$5:$G$140<>"moeda")*(Inputs!$G$5:$G$140<>"acoes")))*INDEX(Inputs!$K$5:$AJ$140,0,MATCH(U$2,Inputs!$K$4:$AJ$4,0)))+SUMPRODUCT((Inputs!$C$5:$C$140=$B8)*Inputs!$D$5:$D$140*(((Inputs!$G$5:$G$140="moeda")+(Inputs!$G$5:$G$140="acoes"))*Inputs!$B$1+((Inputs!$G$5:$G$140<>"moeda")*(Inputs!$G$5:$G$140<>"acoes")))*INDEX(Inputs!$K$5:$AJ$140,0,MATCH(U$2,Inputs!$K$4:$AJ$4,0)))+SUMPRODUCT((Inputs!$E$5:$E$140=$B8)*Inputs!$F$5:$F$140*(((Inputs!$G$5:$G$140="moeda")+(Inputs!$G$5:$G$140="acoes"))*Inputs!$B$1+((Inputs!$G$5:$G$140<>"moeda")*(Inputs!$G$5:$G$140<>"acoes")))*INDEX(Inputs!$K$5:$AJ$140,0,MATCH(U$2,Inputs!$K$4:$AJ$4,0))))) -> -39.673 | V8: =IF(ISNA(MATCH(V$2,Inputs!$K$4:$AJ$4,0)),NA(),IF(SUMPRODUCT((Inputs!$A$5:$A$140=$B8)*ISNUMBER(INDEX(Inputs!$K$5:$AJ$140,0,MATCH(V$2,Inputs!$K$4:$AJ$4,0))))+SUMPRODUCT((Inputs!$C$5:$C$140=$B8)*ISNUMBER(INDEX(Inputs!$K$5:$AJ$140,0,MATCH(V$2,Inputs!$K$4:$AJ$4,0))))+SUMPRODUCT((Inputs!$E$5:$E$140=$B8)*ISNUMBER(INDEX(Inputs!$K$5:$AJ$140,0,MATCH(V$2,Inputs!$K$4:$AJ$4,0))))=0,NA(),SUMPRODUCT((Inputs!$A$5:$A$140=$B8)*Inputs!$B$5:$B$140*(((Inputs!$G$5:$G$140="moeda")+(Inputs!$G$5:$G$140="acoes"))*Inputs!$B$1+((Inputs!$G$5:$G$140<>"moeda")*(Inputs!$G$5:$G$140<>"acoes")))*INDEX(Inputs!$K$5:$AJ$140,0,MATCH(V$2,Inputs!$K$4:$AJ$4,0)))+SUMPRODUCT((Inputs!$C$5:$C$140=$B8)*Inputs!$D$5:$D$140*(((Inputs!$G$5:$G$140="moeda")+(Inputs!$G$5:$G$140="acoes"))*Inputs!$B$1+((Inputs!$G$5:$G$140<>"moeda")*(Inputs!$G$5:$G$140<>"acoes")))*INDEX(Inputs!$K$5:$AJ$140,0,MATCH(V$2,Inputs!$K$4:$AJ$4,0)))+SUMPRODUCT((Inputs!$E$5:$E$140=$B8)*Inputs!$F$5:$F$140*(((Inputs!$G$5:$G$140="moeda")+(Inputs!$G$5:$G$140="acoes"))*Inputs!$B$1+((Inputs!$G$5:$G$140<>"moeda")*(Inputs!$G$5:$G$140<>"acoes")))*INDEX(Inputs!$K$5:$AJ$140,0,MATCH(V$2,Inputs!$K$4:$AJ$4,0))))) -> -41.587 | W8: =SUM(S8:V8) -> -137.165 | X8: =IF(ISNA(MATCH(X$2,Inputs!$K$4:$AJ$4,0)),NA(),IF(SUMPRODUCT((Inputs!$A$5:$A$140=$B8)*ISNUMBER(INDEX(Inputs!$K$5:$AJ$140,0,MATCH(X$2,Inputs!$K$4:$AJ$4,0))))+SUMPRODUCT((Inputs!$C$5:$C$140=$B8)*ISNUMBER(INDEX(Inputs!$K$5:$AJ$140,0,MATCH(X$2,Inputs!$K$4:$AJ$4,0))))+SUMPRODUCT((Inputs!$E$5:$E$140=$B8)*ISNUMBER(INDEX(Inputs!$K$5:$AJ$140,0,MATCH(X$2,Inputs!$K$4:$AJ$4,0))))=0,NA(),SUMPRODUCT((Inputs!$A$5:$A$140=$B8)*Inputs!$B$5:$B$140*(((Inputs!$G$5:$G$140="moeda")+(Inputs!$G$5:$G$140="acoes"))*Inputs!$B$1+((Inputs!$G$5:$G$140<>"moeda")*(Inputs!$G$5:$G$140<>"acoes")))*INDEX(Inputs!$K$5:$AJ$140,0,MATCH(X$2,Inputs!$K$4:$AJ$4,0)))+SUMPRODUCT((Inputs!$C$5:$C$140=$B8)*Inputs!$D$5:$D$140*(((Inputs!$G$5:$G$140="moeda")+(Inputs!$G$5:$G$140="acoes"))*Inputs!$B$1+((Inputs!$G$5:$G$140<>"moeda")*(Inputs!$G$5:$G$140<>"acoes")))*INDEX(Inputs!$K$5:$AJ$140,0,MATCH(X$2,Inputs!$K$4:$AJ$4,0)))+SUMPRODUCT((Inputs!$E$5:$E$140=$B8)*Inputs!$F$5:$F$140*(((Inputs!$G$5:$G$140="moeda")+(Inputs!$G$5:$G$140="acoes"))*Inputs!$B$1+((Inputs!$G$5:$G$140<>"moeda")*(Inputs!$G$5:$G$140<>"acoes")))*INDEX(Inputs!$K$5:$AJ$140,0,MATCH(X$2,Inputs!$K$4:$AJ$4,0))))) -> -51.332 | Y8: =IF(ISNA(MATCH(Y$2,Inputs!$K$4:$AJ$4,0)),NA(),IF(SUMPRODUCT((Inputs!$A$5:$A$140=$B8)*ISNUMBER(INDEX(Inputs!$K$5:$AJ$140,0,MATCH(Y$2,Inputs!$K$4:$AJ$4,0))))+SUMPRODUCT((Inputs!$C$5:$C$140=$B8)*ISNUMBER(INDEX(Inputs!$K$5:$AJ$140,0,MATCH(Y$2,Inputs!$K$4:$AJ$4,0))))+SUMPRODUCT((Inputs!$E$5:$E$140=$B8)*ISNUMBER(INDEX(Inputs!$K$5:$AJ$140,0,MATCH(Y$2,Inputs!$K$4:$AJ$4,0))))=0,NA(),SUMPRODUCT((Inputs!$A$5:$A$140=$B8)*Inputs!$B$5:$B$140*(((Inputs!$G$5:$G$140="moeda")+(Inputs!$G$5:$G$140="acoes"))*Inputs!$B$1+((Inputs!$G$5:$G$140<>"moeda")*(Inputs!$G$5:$G$140<>"acoes")))*INDEX(Inputs!$K$5:$AJ$140,0,MATCH(Y$2,Inputs!$K$4:$AJ$4,0)))+SUMPRODUCT((Inputs!$C$5:$C$140=$B8)*Inputs!$D$5:$D$140*(((Inputs!$G$5:$G$140="moeda")+(Inputs!$G$5:$G$140="acoes"))*Inputs!$B$1+((Inputs!$G$5:$G$140<>"moeda")*(Inputs!$G$5:$G$140<>"acoes")))*INDEX(Inputs!$K$5:$AJ$140,0,MATCH(Y$2,Inputs!$K$4:$AJ$4,0)))+SUMPRODUCT((Inputs!$E$5:$E$140=$B8)*Inputs!$F$5:$F$140*(((Inputs!$G$5:$G$140="moeda")+(Inputs!$G$5:$G$140="acoes"))*Inputs!$B$1+((Inputs!$G$5:$G$140<>"moeda")*(Inputs!$G$5:$G$140<>"acoes")))*INDEX(Inputs!$K$5:$AJ$140,0,MATCH(Y$2,Inputs!$K$4:$AJ$4,0))))) -> -50.846244 | Z8: =IF(ISNA(MATCH(Z$2,Inputs!$K$4:$AJ$4,0)),NA(),IF(SUMPRODUCT((Inputs!$A$5:$A$140=$B8)*ISNUMBER(INDEX(Inputs!$K$5:$AJ$140,0,MATCH(Z$2,Inputs!$K$4:$AJ$4,0))))+SUMPRODUCT((Inputs!$C$5:$C$140=$B8)*ISNUMBER(INDEX(Inputs!$K$5:$AJ$140,0,MATCH(Z$2,Inputs!$K$4:$AJ$4,0))))+SUMPRODUCT((Inputs!$E$5:$E$140=$B8)*ISNUMBER(INDEX(Inputs!$K$5:$AJ$140,0,MATCH(Z$2,Inputs!$K$4:$AJ$4,0))))=0,NA(),SUMPRODUCT((Inputs!$A$5:$A$140=$B8)*Inputs!$B$5:$B$140*(((Inputs!$G$5:$G$140="moeda")+(Inputs!$G$5:$G$140="acoes"))*Inputs!$B$1+((Inputs!$G$5:$G$140<>"moeda")*(Inputs!$G$5:$G$140<>"acoes")))*INDEX(Inputs!$K$5:$AJ$140,0,MATCH(Z$2,Inputs!$K$4:$AJ$4,0)))+SUMPRODUCT((Inputs!$C$5:$C$140=$B8)*Inputs!$D$5:$D$140*(((Inputs!$G$5:$G$140="moeda")+(Inputs!$G$5:$G$140="acoes"))*Inputs!$B$1+((Inputs!$G$5:$G$140<>"moeda")*(Inputs!$G$5:$G$140<>"acoes")))*INDEX(Inputs!$K$5:$AJ$140,0,MATCH(Z$2,Inputs!$K$4:$AJ$4,0)))+SUMPRODUCT((Inputs!$E$5:$E$140=$B8)*Inputs!$F$5:$F$140*(((Inputs!$G$5:$G$140="moeda")+(Inputs!$G$5:$G$140="acoes"))*Inputs!$B$1+((Inputs!$G$5:$G$140<>"moeda")*(Inputs!$G$5:$G$140<>"acoes")))*INDEX(Inputs!$K$5:$AJ$140,0,MATCH(Z$2,Inputs!$K$4:$AJ$4,0))))) -> -56.062 | AA8: =IF(ISNA(MATCH(AA$2,Inputs!$K$4:$AJ$4,0)),NA(),IF(SUMPRODUCT((Inputs!$A$5:$A$140=$B8)*ISNUMBER(INDEX(Inputs!$K$5:$AJ$140,0,MATCH(AA$2,Inputs!$K$4:$AJ$4,0))))+SUMPRODUCT((Inputs!$C$5:$C$140=$B8)*ISNUMBER(INDEX(Inputs!$K$5:$AJ$140,0,MATCH(AA$2,Inputs!$K$4:$AJ$4,0))))+SUMPRODUCT((Inputs!$E$5:$E$140=$B8)*ISNUMBER(INDEX(Inputs!$K$5:$AJ$140,0,MATCH(AA$2,Inputs!$K$4:$AJ$4,0))))=0,NA(),SUMPRODUCT((Inputs!$A$5:$A$140=$B8)*Inputs!$B$5:$B$140*(((Inputs!$G$5:$G$140="moeda")+(Inputs!$G$5:$G$140="acoes"))*Inputs!$B$1+((Inputs!$G$5:$G$140<>"moeda")*(Inputs!$G$5:$G$140<>"acoes")))*INDEX(Inputs!$K$5:$AJ$140,0,MATCH(AA$2,Inputs!$K$4:$AJ$4,0)))+SUMPRODUCT((Inputs!$C$5:$C$140=$B8)*Inputs!$D$5:$D$140*(((Inputs!$G$5:$G$140="moeda")+(Inputs!$G$5:$G$140="acoes"))*Inputs!$B$1+((Inputs!$G$5:$G$140<>"moeda")*(Inputs!$G$5:$G$140<>"acoes")))*INDEX(Inputs!$K$5:$AJ$140,0,MATCH(AA$2,Inputs!$K$4:$AJ$4,0)))+SUMPRODUCT((Inputs!$E$5:$E$140=$B8)*Inputs!$F$5:$F$140*(((Inputs!$G$5:$G$140="moeda")+(Inputs!$G$5:$G$140="acoes"))*Inputs!$B$1+((Inputs!$G$5:$G$140<>"moeda")*(Inputs!$G$5:$G$140<>"acoes")))*INDEX(Inputs!$K$5:$AJ$140,0,MATCH(AA$2,Inputs!$K$4:$AJ$4,0))))) -> -59.596 | AB8: =SUM(X8:AA8) -> -217.83624 | AC8: =IF(ISNA(MATCH(AC$2,Inputs!$K$4:$AJ$4,0)),NA(),IF(SUMPRODUCT((Inputs!$A$5:$A$140=$B8)*ISNUMBER(INDEX(Inputs!$K$5:$AJ$140,0,MATCH(AC$2,Inputs!$K$4:$AJ$4,0))))+SUMPRODUCT((Inputs!$C$5:$C$140=$B8)*ISNUMBER(INDEX(Inputs!$K$5:$AJ$140,0,MATCH(AC$2,Inputs!$K$4:$AJ$4,0))))+SUMPRODUCT((Inputs!$E$5:$E$140=$B8)*ISNUMBER(INDEX(Inputs!$K$5:$AJ$140,0,MATCH(AC$2,Inputs!$K$4:$AJ$4,0))))=0,NA(),SUMPRODUCT((Inputs!$A$5:$A$140=$B8)*Inputs!$B$5:$B$140*(((Inputs!$G$5:$G$140="moeda")+(Inputs!$G$5:$G$140="acoes"))*Inputs!$B$1+((Inputs!$G$5:$G$140<>"moeda")*(Inputs!$G$5:$G$140<>"acoes")))*INDEX(Inputs!$K$5:$AJ$140,0,MATCH(AC$2,Inputs!$K$4:$AJ$4,0)))+SUMPRODUCT((Inputs!$C$5:$C$140=$B8)*Inputs!$D$5:$D$140*(((Inputs!$G$5:$G$140="moeda")+(Inputs!$G$5:$G$140="acoes"))*Inputs!$B$1+((Inputs!$G$5:$G$140<>"moeda")*(Inputs!$G$5:$G$140<>"acoes")))*INDEX(Inputs!$K$5:$AJ$140,0,MATCH(AC$2,Inputs!$K$4:$AJ$4,0)))+SUMPRODUCT((Inputs!$E$5:$E$140=$B8)*Inputs!$F$5:$F$140*(((Inputs!$G$5:$G$140="moeda")+(Inputs!$G$5:$G$140="acoes"))*Inputs!$B$1+((Inputs!$G$5:$G$140<>"moeda")*(Inputs!$G$5:$G$140<>"acoes")))*INDEX(Inputs!$K$5:$AJ$140,0,MATCH(AC$2,Inputs!$K$4:$AJ$4,0))))) -> -59.802 | AD8: =IF(ISNA(MATCH(AD$2,Inputs!$K$4:$AJ$4,0)),NA(),IF(SUMPRODUCT((Inputs!$A$5:$A$140=$B8)*ISNUMBER(INDEX(Inputs!$K$5:$AJ$140,0,MATCH(AD$2,Inputs!$K$4:$AJ$4,0))))+SUMPRODUCT((Inputs!$C$5:$C$140=$B8)*ISNUMBER(INDEX(Inputs!$K$5:$AJ$140,0,MATCH(AD$2,Inputs!$K$4:$AJ$4,0))))+SUMPRODUCT((Inputs!$E$5:$E$140=$B8)*ISNUMBER(INDEX(Inputs!$K$5:$AJ$140,0,MATCH(AD$2,Inputs!$K$4:$AJ$4,0))))=0,NA(),SUMPRODUCT((Inputs!$A$5:$A$140=$B8)*Inputs!$B$5:$B$140*(((Inputs!$G$5:$G$140="moeda")+(Inputs!$G$5:$G$140="acoes"))*Inputs!$B$1+((Inputs!$G$5:$G$140<>"moeda")*(Inputs!$G$5:$G$140<>"acoes")))*INDEX(Inputs!$K$5:$AJ$140,0,MATCH(AD$2,Inputs!$K$4:$AJ$4,0)))+SUMPRODUCT((Inputs!$C$5:$C$140=$B8)*Inputs!$D$5:$D$140*(((Inputs!$G$5:$G$140="moeda")+(Inputs!$G$5:$G$140="acoes"))*Inputs!$B$1+((Inputs!$G$5:$G$140<>"moeda")*(Inputs!$G$5:$G$140<>"acoes")))*INDEX(Inputs!$K$5:$AJ$140,0,MATCH(AD$2,Inputs!$K$4:$AJ$4,0)))+SUMPRODUCT((Inputs!$E$5:$E$140=$B8)*Inputs!$F$5:$F$140*(((Inputs!$G$5:$G$140="moeda")+(Inputs!$G$5:$G$140="acoes"))*Inputs!$B$1+((Inputs!$G$5:$G$140<>"moeda")*(Inputs!$G$5:$G$140<>"acoes")))*INDEX(Inputs!$K$5:$AJ$140,0,MATCH(AD$2,Inputs!$K$4:$AJ$4,0))))) -> -70.288 | AE8: =IF(ISNA(MATCH(AE$2,Inputs!$K$4:$AJ$4,0)),NA(),IF(SUMPRODUCT((Inputs!$A$5:$A$140=$B8)*ISNUMBER(INDEX(Inputs!$K$5:$AJ$140,0,MATCH(AE$2,Inputs!$K$4:$AJ$4,0))))+SUMPRODUCT((Inputs!$C$5:$C$140=$B8)*ISNUMBER(INDEX(Inputs!$K$5:$AJ$140,0,MATCH(AE$2,Inputs!$K$4:$AJ$4,0))))+SUMPRODUCT((Inputs!$E$5:$E$140=$B8)*ISNUMBER(INDEX(Inputs!$K$5:$AJ$140,0,MATCH(AE$2,Inputs!$K$4:$AJ$4,0))))=0,NA(),SUMPRODUCT((Inputs!$A$5:$A$140=$B8)*Inputs!$B$5:$B$140*(((Inputs!$G$5:$G$140="moeda")+(Inputs!$G$5:$G$140="acoes"))*Inputs!$B$1+((Inputs!$G$5:$G$140<>"moeda")*(Inputs!$G$5:$G$140<>"acoes")))*INDEX(Inputs!$K$5:$AJ$140,0,MATCH(AE$2,Inputs!$K$4:$AJ$4,0)))+SUMPRODUCT((Inputs!$C$5:$C$140=$B8)*Inputs!$D$5:$D$140*(((Inputs!$G$5:$G$140="moeda")+(Inputs!$G$5:$G$140="acoes"))*Inputs!$B$1+((Inputs!$G$5:$G$140<>"moeda")*(Inputs!$G$5:$G$140<>"acoes")))*INDEX(Inputs!$K$5:$AJ$140,0,MATCH(AE$2,Inputs!$K$4:$AJ$4,0)))+SUMPRODUCT((Inputs!$E$5:$E$140=$B8)*Inputs!$F$5:$F$140*(((Inputs!$G$5:$G$140="moeda")+(Inputs!$G$5:$G$140="acoes"))*Inputs!$B$1+((Inputs!$G$5:$G$140<>"moeda")*(Inputs!$G$5:$G$140<>"acoes")))*INDEX(Inputs!$K$5:$AJ$140,0,MATCH(AE$2,Inputs!$K$4:$AJ$4,0))))) -> #N/A | AF8: =IF(ISNA(MATCH(AF$2,Inputs!$K$4:$AJ$4,0)),NA(),IF(SUMPRODUCT((Inputs!$A$5:$A$140=$B8)*ISNUMBER(INDEX(Inputs!$K$5:$AJ$140,0,MATCH(AF$2,Inputs!$K$4:$AJ$4,0))))+SUMPRODUCT((Inputs!$C$5:$C$140=$B8)*ISNUMBER(INDEX(Inputs!$K$5:$AJ$140,0,MATCH(AF$2,Inputs!$K$4:$AJ$4,0))))+SUMPRODUCT((Inputs!$E$5:$E$140=$B8)*ISNUMBER(INDEX(Inputs!$K$5:$AJ$140,0,MATCH(AF$2,Inputs!$K$4:$AJ$4,0))))=0,NA(),SUMPRODUCT((Inputs!$A$5:$A$140=$B8)*Inputs!$B$5:$B$140*(((Inputs!$G$5:$G$140="moeda")+(Inputs!$G$5:$G$140="acoes"))*Inputs!$B$1+((Inputs!$G$5:$G$140<>"moeda")*(Inputs!$G$5:$G$140<>"acoes")))*INDEX(Inputs!$K$5:$AJ$140,0,MATCH(AF$2,Inputs!$K$4:$AJ$4,0)))+SUMPRODUCT((Inputs!$C$5:$C$140=$B8)*Inputs!$D$5:$D$140*(((Inputs!$G$5:$G$140="moeda")+(Inputs!$G$5:$G$140="acoes"))*Inputs!$B$1+((Inputs!$G$5:$G$140<>"moeda")*(Inputs!$G$5:$G$140<>"acoes")))*INDEX(Inputs!$K$5:$AJ$140,0,MATCH(AF$2,Inputs!$K$4:$AJ$4,0)))+SUMPRODUCT((Inputs!$E$5:$E$140=$B8)*Inputs!$F$5:$F$140*(((Inputs!$G$5:$G$140="moeda")+(Inputs!$G$5:$G$140="acoes"))*Inputs!$B$1+((Inputs!$G$5:$G$140<>"moeda")*(Inputs!$G$5:$G$140<>"acoes")))*INDEX(Inputs!$K$5:$AJ$140,0,MATCH(AF$2,Inputs!$K$4:$AJ$4,0))))) -> #N/A | AG8: =SUM(AC8:AF8) -> #N/A | AH8: =IF(ISNA(MATCH(AH$2,Inputs!$K$4:$AJ$4,0)),NA(),IF(SUMPRODUCT((Inputs!$A$5:$A$140=$B8)*ISNUMBER(INDEX(Inputs!$K$5:$AJ$140,0,MATCH(AH$2,Inputs!$K$4:$AJ$4,0))))+SUMPRODUCT((Inputs!$C$5:$C$140=$B8)*ISNUMBER(INDEX(Inputs!$K$5:$AJ$140,0,MATCH(AH$2,Inputs!$K$4:$AJ$4,0))))+SUMPRODUCT((Inputs!$E$5:$E$140=$B8)*ISNUMBER(INDEX(Inputs!$K$5:$AJ$140,0,MATCH(AH$2,Inputs!$K$4:$AJ$4,0))))=0,NA(),SUMPRODUCT((Inputs!$A$5:$A$140=$B8)*Inputs!$B$5:$B$140*(((Inputs!$G$5:$G$140="moeda")+(Inputs!$G$5:$G$140="acoes"))*Inputs!$B$1+((Inputs!$G$5:$G$140<>"moeda")*(Inputs!$G$5:$G$140<>"acoes")))*INDEX(Inputs!$K$5:$AJ$140,0,MATCH(AH$2,Inputs!$K$4:$AJ$4,0)))+SUMPRODUCT((Inputs!$C$5:$C$140=$B8)*Inputs!$D$5:$D$140*(((Inputs!$G$5:$G$140="moeda")+(Inputs!$G$5:$G$140="acoes"))*Inputs!$B$1+((Inputs!$G$5:$G$140<>"moeda")*(Inputs!$G$5:$G$140<>"acoes")))*INDEX(Inputs!$K$5:$AJ$140,0,MATCH(AH$2,Inputs!$K$4:$AJ$4,0)))+SUMPRODUCT((Inputs!$E$5:$E$140=$B8)*Inputs!$F$5:$F$140*(((Inputs!$G$5:$G$140="moeda")+(Inputs!$G$5:$G$140="acoes"))*Inputs!$B$1+((Inputs!$G$5:$G$140<>"moeda")*(Inputs!$G$5:$G$140<>"acoes")))*INDEX(Inputs!$K$5:$AJ$140,0,MATCH(AH$2,Inputs!$K$4:$AJ$4,0))))) -> -4.959 | AI8: =IF(ISNA(MATCH(AI$2,Inputs!$K$4:$AJ$4,0)),NA(),IF(SUMPRODUCT((Inputs!$A$5:$A$140=$B8)*ISNUMBER(INDEX(Inputs!$K$5:$AJ$140,0,MATCH(AI$2,Inputs!$K$4:$AJ$4,0))))+SUMPRODUCT((Inputs!$C$5:$C$140=$B8)*ISNUMBER(INDEX(Inputs!$K$5:$AJ$140,0,MATCH(AI$2,Inputs!$K$4:$AJ$4,0))))+SUMPRODUCT((Inputs!$E$5:$E$140=$B8)*ISNUMBER(INDEX(Inputs!$K$5:$AJ$140,0,MATCH(AI$2,Inputs!$K$4:$AJ$4,0))))=0,NA(),SUMPRODUCT((Inputs!$A$5:$A$140=$B8)*Inputs!$B$5:$B$140*(((Inputs!$G$5:$G$140="moeda")+(Inputs!$G$5:$G$140="acoes"))*Inputs!$B$1+((Inputs!$G$5:$G$140<>"moeda")*(Inputs!$G$5:$G$140<>"acoes")))*INDEX(Inputs!$K$5:$AJ$140,0,MATCH(AI$2,Inputs!$K$4:$AJ$4,0)))+SUMPRODUCT((Inputs!$C$5:$C$140=$B8)*Inputs!$D$5:$D$140*(((Inputs!$G$5:$G$140="moeda")+(Inputs!$G$5:$G$140="acoes"))*Inputs!$B$1+((Inputs!$G$5:$G$140<>"moeda")*(Inputs!$G$5:$G$140<>"acoes")))*INDEX(Inputs!$K$5:$AJ$140,0,MATCH(AI$2,Inputs!$K$4:$AJ$4,0)))+SUMPRODUCT((Inputs!$E$5:$E$140=$B8)*Inputs!$F$5:$F$140*(((Inputs!$G$5:$G$140="moeda")+(Inputs!$G$5:$G$140="acoes"))*Inputs!$B$1+((Inputs!$G$5:$G$140<>"moeda")*(Inputs!$G$5:$G$140<>"acoes")))*INDEX(Inputs!$K$5:$AJ$140,0,MATCH(AI$2,Inputs!$K$4:$AJ$4,0))))) -> -5.719 | AJ8: =IF(ISNA(MATCH(AJ$2,Inputs!$K$4:$AJ$4,0)),NA(),IF(SUMPRODUCT((Inputs!$A$5:$A$140=$B8)*ISNUMBER(INDEX(Inputs!$K$5:$AJ$140,0,MATCH(AJ$2,Inputs!$K$4:$AJ$4,0))))+SUMPRODUCT((Inputs!$C$5:$C$140=$B8)*ISNUMBER(INDEX(Inputs!$K$5:$AJ$140,0,MATCH(AJ$2,Inputs!$K$4:$AJ$4,0))))+SUMPRODUCT((Inputs!$E$5:$E$140=$B8)*ISNUMBER(INDEX(Inputs!$K$5:$AJ$140,0,MATCH(AJ$2,Inputs!$K$4:$AJ$4,0))))=0,NA(),SUMPRODUCT((Inputs!$A$5:$A$140=$B8)*Inputs!$B$5:$B$140*(((Inputs!$G$5:$G$140="moeda")+(Inputs!$G$5:$G$140="acoes"))*Inputs!$B$1+((Inputs!$G$5:$G$140<>"moeda")*(Inputs!$G$5:$G$140<>"acoes")))*INDEX(Inputs!$K$5:$AJ$140,0,MATCH(AJ$2,Inputs!$K$4:$AJ$4,0)))+SUMPRODUCT((Inputs!$C$5:$C$140=$B8)*Inputs!$D$5:$D$140*(((Inputs!$G$5:$G$140="moeda")+(Inputs!$G$5:$G$140="acoes"))*Inputs!$B$1+((Inputs!$G$5:$G$140<>"moeda")*(Inputs!$G$5:$G$140<>"acoes")))*INDEX(Inputs!$K$5:$AJ$140,0,MATCH(AJ$2,Inputs!$K$4:$AJ$4,0)))+SUMPRODUCT((Inputs!$E$5:$E$140=$B8)*Inputs!$F$5:$F$140*(((Inputs!$G$5:$G$140="moeda")+(Inputs!$G$5:$G$140="acoes"))*Inputs!$B$1+((Inputs!$G$5:$G$140<>"moeda")*(Inputs!$G$5:$G$140<>"acoes")))*INDEX(Inputs!$K$5:$AJ$140,0,MATCH(AJ$2,Inputs!$K$4:$AJ$4,0))))) -> -6.639 | AK8: =IF(ISNA(MATCH(AK$2,Inputs!$K$4:$AJ$4,0)),NA(),IF(SUMPRODUCT((Inputs!$A$5:$A$140=$B8)*ISNUMBER(INDEX(Inputs!$K$5:$AJ$140,0,MATCH(AK$2,Inputs!$K$4:$AJ$4,0))))+SUMPRODUCT((Inputs!$C$5:$C$140=$B8)*ISNUMBER(INDEX(Inputs!$K$5:$AJ$140,0,MATCH(AK$2,Inputs!$K$4:$AJ$4,0))))+SUMPRODUCT((Inputs!$E$5:$E$140=$B8)*ISNUMBER(INDEX(Inputs!$K$5:$AJ$140,0,MATCH(AK$2,Inputs!$K$4:$AJ$4,0))))=0,NA(),SUMPRODUCT((Inputs!$A$5:$A$140=$B8)*Inputs!$B$5:$B$140*(((Inputs!$G$5:$G$140="moeda")+(Inputs!$G$5:$G$140="acoes"))*Inputs!$B$1+((Inputs!$G$5:$G$140<>"moeda")*(Inputs!$G$5:$G$140<>"acoes")))*INDEX(Inputs!$K$5:$AJ$140,0,MATCH(AK$2,Inputs!$K$4:$AJ$4,0)))+SUMPRODUCT((Inputs!$C$5:$C$140=$B8)*Inputs!$D$5:$D$140*(((Inputs!$G$5:$G$140="moeda")+(Inputs!$G$5:$G$140="acoes"))*Inputs!$B$1+((Inputs!$G$5:$G$140<>"moeda")*(Inputs!$G$5:$G$140<>"acoes")))*INDEX(Inputs!$K$5:$AJ$140,0,MATCH(AK$2,Inputs!$K$4:$AJ$4,0)))+SUMPRODUCT((Inputs!$E$5:$E$140=$B8)*Inputs!$F$5:$F$140*(((Inputs!$G$5:$G$140="moeda")+(Inputs!$G$5:$G$140="acoes"))*Inputs!$B$1+((Inputs!$G$5:$G$140<>"moeda")*(Inputs!$G$5:$G$140<>"acoes")))*INDEX(Inputs!$K$5:$AJ$140,0,MATCH(AK$2,Inputs!$K$4:$AJ$4,0))))) -> -6.166 | AL8: =SUM(AH8:AK8) -> -23.483
