Workbook
Name beta_observed: #REF!
Name beta_observed: Valuation!$D$93
Name costdebtfirm: Valuation!$D$86
Name costequity: Valuation!$D$94
Name debt: Valuation!$G$88
Name debt_weight: Valuation!$J$88
Name g: Valuation!$D$63
Name last_close: Valuation!$G$7
Name market_equity: Valuation!$G$89
Name noplat_t1: Valuation!$D$65
Name relevered_beta: Valuation!$M$102
Name risk_free_rate: Valuation!$D$91
Name risk_premium: Valuation!$D$92
Name ronic: Valuation!$D$64
Name stub_year_fraction: Valuation!$D$11
Name ticker: #REF!
Name ticker: Valuation!$D$7
Name totalcap: Valuation!$G$90
Name Useful_Life_of_Depreciable_PP_E: "PPElife"
Name wacc: Valuation!$D$12

Sheet Inputs
A1: Base histórica normalizada (R$ mil)
A2: Fonte / conta original | B2: Código | C2: Conta padronizada | D2: 1Q21 | E2: 2Q21 | F2: 3Q21 | G2: 4Q21 | H2: 2021 | I2: 1Q22 | J2: 2Q22 | K2: 3Q22 | L2: 4Q22 | M2: 2022 | N2: 1Q23 | O2: 2Q23 | P2: 3Q23 | Q2: 4Q23 | R2: 2023 | S2: 1Q24 | T2: 2Q24 | U2: 3Q24 | V2: 4Q24 | W2: 2024 | X2: 1Q25 | Y2: 2Q25 | Z2: 3Q25 | AA2: 4Q25 | AB2: 2025 | AC2: 1Q26 | AD2: 2Q26 | AE2: 3Q26 | AF2: 4Q26 | AG2: 2026
A3: Fonte: preencher com planilha de fundamentos e/ou RI | C3: Unidade original: R$ mil
B4: 1 | C4: Net Revenues
B5: 2 | C5: COGS (cash)
B6: 3 | C6: SG&A and Other (cash)
B7: 4 | C7: D&A
B8: 5 | C8: Interest Expense
B9: 6 | C9: Nonoperating Income / (Loss)
B10: 7 | C10: Taxes
B11: 8 | C11: Equity in Income of Affiliates, after tax (enter as +)
B12: 9 | C12: Minority Interest Expense, after tax (enter as - )
B13: 10 | C13: Common Dividends
B14: 11 | C14: Cash and equivalents (inc. investment securities)
B15: 12 | C15: Accounts receivable
... B44: 41 | C44: Retained earnings

Sheet Inputs (2)
A1: =IF(Control!B3="","EMPRESA",Control!B3) -> EMPRESA | B1: Código | C1: Conta padronizada | D1: 2021 | E1: 2021 | F1: 2021 | G1: 2021 | H1: 2021 | I1: 2022 | J1: 2022 | K1: 2022 | L1: 2022 | M1: 2022 | N1: 2023 | O1: 2023 | P1: 2023 | Q1: 2023 | R1: 2023 | S1: 2024 | T1: 2024 | U1: 2024 | V1: 2024 | W1: 2024 | X1: 2025 | Y1: 2025 | Z1: 2025 | AA1: 2025 | AB1: 2025 | AC1: 2026 | AD1: 2026 | AE1: 2026 | AF1: 2026 | AG1: 2026
A2: R$ milhões | C2: Período | D2: 1Q21 | E2: 2Q21 | F2: 3Q21 | G2: 4Q21 | H2: 2021 | I2: 1Q22 | J2: 2Q22 | K2: 3Q22 | L2: 4Q22 | M2: 2022 | N2: 1Q23 | O2: 2Q23 | P2: 3Q23 | Q2: 4Q23 | R2: 2023 | S2: 1Q24 | T2: 2Q24 | U2: 3Q24 | V2: 4Q24 | W2: 2024 | X2: 1Q25 | Y2: 2Q25 | Z2: 3Q25 | AA2: 4Q25 | AB2: 2025 | AC2: 1Q26 | AD2: 2Q26 | AE2: 3Q26 | AF2: 4Q26 | AG2: 2026
A3: Actual flag | C3: 0 = sem dados / 1 = realizado | D3: 0 | E3: 0 | F3: 0 | G3: 0 | H3: 0 | I3: 0 | J3: 0 | K3: 0 | L3: 0 | M3: 0 | N3: 0 | O3: 0 | P3: 0 | Q3: 0 | R3: 0 | S3: 0 | T3: 0 | U3: 0 | V3: 0 | W3: 0 | X3: 0 | Y3: 0 | Z3: 0 | AA3: 0 | AB3: 0 | AC3: 0 | AD3: 0 | AE3: 0 | AF3: 0 | AG3: 0
B4: 1 | C4: Net Revenues | D4: =IF(D$3=0,"",SUMIFS(INDEX(Inputs!$D$4:$AG$100,0,MATCH(D$2,Inputs!$D$2:$AG$2,0)),Inputs!$B$4:$B$100,$B4)/1000) | E4: =IF(E$3=0,"",SUMIFS(INDEX(Inputs!$D$4:$AG$100,0,MATCH(E$2,Inputs!$D$2:$AG$2,0)),Inputs!$B$4:$B$100,$B4)/1000) | F4: =IF(F$3=0,"",SUMIFS(INDEX(Inputs!$D$4:$AG$100,0,MATCH(F$2,Inputs!$D$2:$AG$2,0)),Inputs!$B$4:$B$100,$B4)/1000) | G4: =IF(G$3=0,"",SUMIFS(INDEX(Inputs!$D$4:$AG$100,0,MATCH(G$2,Inputs!$D$2:$AG$2,0)),Inputs!$B$4:$B$100,$B4)/1000) | H4: =IF(COUNT(D4:G4)=4,SUM(D4:G4),"") | I4: =IF(I$3=0,"",SUMIFS(INDEX(Inputs!$D$4:$AG$100,0,MATCH(I$2,Inputs!$D$2:$AG$2,0)),Inputs!$B$4:$B$100,$B4)/1000) | J4: =IF(J$3=0,"",SUMIFS(INDEX(Inputs!$D$4:$AG$100,0,MATCH(J$2,Inputs!$D$2:$AG$2,0)),Inputs!$B$4:$B$100,$B4)/1000) | K4: =IF(K$3=0,"",SUMIFS(INDEX(Inputs!$D$4:$AG$100,0,MATCH(K$2,Inputs!$D$2:$AG$2,0)),Inputs!$B$4:$B$100,$B4)/1000) | L4: =IF(L$3=0,"",SUMIFS(INDEX(Inputs!$D$4:$AG$100,0,MATCH(L$2,Inputs!$D$2:$AG$2,0)),Inputs!$B$4:$B$100,$B4)/1000) | M4: =IF(COUNT(I4:L4)=4,SUM(I4:L4),"") | N4: =IF(N$3=0,"",SUMIFS(INDEX(Inputs!$D$4:$AG$100,0,MATCH(N$2,Inputs!$D$2:$AG$2,0)),Inputs!$B$4:$B$100,$B4)/1000) | O4: =IF(O$3=0,"",SUMIFS(INDEX(Inputs!$D$4:$AG$100,0,MATCH(O$2,Inputs!$D$2:$AG$2,0)),Inputs!$B$4:$B$100,$B4)/1000) | P4: =IF(P$3=0,"",SUMIFS(INDEX(Inputs!$D$4:$AG$100,0,MATCH(P$2,Inputs!$D$2:$AG$2,0)),Inputs!$B$4:$B$100,$B4)/1000) | Q4: =IF(Q$3=0,"",SUMIFS(INDEX(Inputs!$D$4:$AG$100,0,MATCH(Q$2,Inputs!$D$2:$AG$2,0)),Inputs!$B$4:$B$100,$B4)/1000) | R4: =IF(COUNT(N4:Q4)=4,SUM(N4:Q4),"") | S4: =IF(S$3=0,"",SUMIFS(INDEX(Inputs!$D$4:$AG$100,0,MATCH(S$2,Inputs!$D$2:$AG$2,0)),Inputs!$B$4:$B$100,$B4)/1000) | T4: =IF(T$3=0,"",SUMIFS(INDEX(Inputs!$D$4:$AG$100,0,MATCH(T$2,Inputs!$D$2:$AG$2,0)),Inputs!$B$4:$B$100,$B4)/1000) | U4: =IF(U$3=0,"",SUMIFS(INDEX(Inputs!$D$4:$AG$100,0,MATCH(U$2,Inputs!$D$2:$AG$2,0)),Inputs!$B$4:$B$100,$B4)/1000) | V4: =IF(V$3=0,"",SUMIFS(INDEX(Inputs!$D$4:$AG$100,0,MATCH(V$2,Inputs!$D$2:$AG$2,0)),Inputs!$B$4:$B$100,$B4)/1000) | W4: =IF(COUNT(S4:V4)=4,SUM(S4:V4),"") | X4: =IF(X$3=0,"",SUMIFS(INDEX(Inputs!$D$4:$AG$100,0,MATCH(X$2,Inputs!$D$2:$AG$2,0)),Inputs!$B$4:$B$100,$B4)/1000) | Y4: =IF(Y$3=0,"",SUMIFS(INDEX(Inputs!$D$4:$AG$100,0,MATCH(Y$2,Inputs!$D$2:$AG$2,0)),Inputs!$B$4:$B$100,$B4)/1000) | Z4: =IF(Z$3=0,"",SUMIFS(INDEX(Inputs!$D$4:$AG$100,0,MATCH(Z$2,Inputs!$D$2:$AG$2,0)),Inputs!$B$4:$B$100,$B4)/1000) | AA4: =IF(AA$3=0,"",SUMIFS(INDEX(Inputs!$D$4:$AG$100,0,MATCH(AA$2,Inputs!$D$2:$AG$2,0)),Inputs!$B$4:$B$100,$B4)/1000) | AB4: =IF(COUNT(X4:AA4)=4,SUM(X4:AA4),"") | AC4: =IF(AC$3=0,"",SUMIFS(INDEX(Inputs!$D$4:$AG$100,0,MATCH(AC$2,Inputs!$D$2:$AG$2,0)),Inputs!$B$4:$B$100,$B4)/1000) | AD4: =IF(AD$3=0,"",SUMIFS(INDEX(Inputs!$D$4:$AG$100,0,MATCH(AD$2,Inputs!$D$2:$AG$2,0)),Inputs!$B$4:$B$100,$B4)/1000) | AE4: =IF(AE$3=0,"",SUMIFS(INDEX(Inputs!$D$4:$AG$100,0,MATCH(AE$2,Inputs!$D$2:$AG$2,0)),Inputs!$B$4:$B$100,$B4)/1000) | AF4: =IF(AF$3=0,"",SUMIFS(INDEX(Inputs!$D$4:$AG$100,0,MATCH(AF$2,Inputs!$D$2:$AG$2,0)),Inputs!$B$4:$B$100,$B4)/1000) | AG4: =IF(COUNT(AC4:AF4)=4,SUM(AC4:AF4),"")
B5: 2 | C5: COGS (cash) | D5: =IF(D$3=0,"",SUMIFS(INDEX(Inputs!$D$4:$AG$100,0,MATCH(D$2,Inputs!$D$2:$AG$2,0)),Inputs!$B$4:$B$100,$B5)/1000) | E5: =IF(E$3=0,"",SUMIFS(INDEX(Inputs!$D$4:$AG$100,0,MATCH(E$2,Inputs!$D$2:$AG$2,0)),Inputs!$B$4:$B$100,$B5)/1000) | F5: =IF(F$3=0,"",SUMIFS(INDEX(Inputs!$D$4:$AG$100,0,MATCH(F$2,Inputs!$D$2:$AG$2,0)),Inputs!$B$4:$B$100,$B5)/1000) | G5: =IF(G$3=0,"",SUMIFS(INDEX(Inputs!$D$4:$AG$100,0,MATCH(G$2,Inputs!$D$2:$AG$2,0)),Inputs!$B$4:$B$100,$B5)/1000) | H5: =IF(COUNT(D5:G5)=4,SUM(D5:G5),"") | I5: =IF(I$3=0,"",SUMIFS(INDEX(Inputs!$D$4:$AG$100,0,MATCH(I$2,Inputs!$D$2:$AG$2,0)),Inputs!$B$4:$B$100,$B5)/1000) | J5: =IF(J$3=0,"",SUMIFS(INDEX(Inputs!$D$4:$AG$100,0,MATCH(J$2,Inputs!$D$2:$AG$2,0)),Inputs!$B$4:$B$100,$B5)/1000) | K5: =IF(K$3=0,"",SUMIFS(INDEX(Inputs!$D$4:$AG$100,0,MATCH(K$2,Inputs!$D$2:$AG$2,0)),Inputs!$B$4:$B$100,$B5)/1000) | L5: =IF(L$3=0,"",SUMIFS(INDEX(Inputs!$D$4:$AG$100,0,MATCH(L$2,Inputs!$D$2:$AG$2,0)),Inputs!$B$4:$B$100,$B5)/1000) | M5: =IF(COUNT(I5:L5)=4,SUM(I5:L5),"") | N5: =IF(N$3=0,"",SUMIFS(INDEX(Inputs!$D$4:$AG$100,0,MATCH(N$2,Inputs!$D$2:$AG$2,0)),Inputs!$B$4:$B$100,$B5)/1000) | O5: =IF(O$3=0,"",SUMIFS(INDEX(Inputs!$D$4:$AG$100,0,MATCH(O$2,Inputs!$D$2:$AG$2,0)),Inputs!$B$4:$B$100,$B5)/1000) | P5: =IF(P$3=0,"",SUMIFS(INDEX(Inputs!$D$4:$AG$100,0,MATCH(P$2,Inputs!$D$2:$AG$2,0)),Inputs!$B$4:$B$100,$B5)/1000) | Q5: =IF(Q$3=0,"",SUMIFS(INDEX(Inputs!$D$4:$AG$100,0,MATCH(Q$2,Inputs!$D$2:$AG$2,0)),Inputs!$B$4:$B$100,$B5)/1000) | R5: =IF(COUNT(N5:Q5)=4,SUM(N5:Q5),"") | S5: =IF(S$3=0,"",SUMIFS(INDEX(Inputs!$D$4:$AG$100,0,MATCH(S$2,Inputs!$D$2:$AG$2,0)),Inputs!$B$4:$B$100,$B5)/1000) | T5: =IF(T$3=0,"",SUMIFS(INDEX(Inputs!$D$4:$AG$100,0,MATCH(T$2,Inputs!$D$2:$AG$2,0)),Inputs!$B$4:$B$100,$B5)/1000) | U5: =IF(U$3=0,"",SUMIFS(INDEX(Inputs!$D$4:$AG$100,0,MATCH(U$2,Inputs!$D$2:$AG$2,0)),Inputs!$B$4:$B$100,$B5)/1000) | V5: =IF(V$3=0,"",SUMIFS(INDEX(Inputs!$D$4:$AG$100,0,MATCH(V$2,Inputs!$D$2:$AG$2,0)),Inputs!$B$4:$B$100,$B5)/1000) | W5: =IF(COUNT(S5:V5)=4,SUM(S5:V5),"") | X5: =IF(X$3=0,"",SUMIFS(INDEX(Inputs!$D$4:$AG$100,0,MATCH(X$2,Inputs!$D$2:$AG$2,0)),Inputs!$B$4:$B$100,$B5)/1000) | Y5: =IF(Y$3=0,"",SUMIFS(INDEX(Inputs!$D$4:$AG$100,0,MATCH(Y$2,Inputs!$D$2:$AG$2,0)),Inputs!$B$4:$B$100,$B5)/1000) | Z5: =IF(Z$3=0,"",SUMIFS(INDEX(Inputs!$D$4:$AG$100,0,MATCH(Z$2,Inputs!$D$2:$AG$2,0)),Inputs!$B$4:$B$100,$B5)/1000) | AA5: =IF(AA$3=0,"",SUMIFS(INDEX(Inputs!$D$4:$AG$100,0,MATCH(AA$2,Inputs!$D$2:$AG$2,0)),Inputs!$B$4:$B$100,$B5)/1000) | AB5: =IF(COUNT(X5:AA5)=4,SUM(X5:AA5),"") | AC5: =IF(AC$3=0,"",SUMIFS(INDEX(Inputs!$D$4:$AG$100,0,MATCH(AC$2,Inputs!$D$2:$AG$2,0)),Inputs!$B$4:$B$100,$B5)/1000) | AD5: =IF(AD$3=0,"",SUMIFS(INDEX(Inputs!$D$4:$AG$100,0,MATCH(AD$2,Inputs!$D$2:$AG$2,0)),Inputs!$B$4:$B$100,$B5)/1000) | AE5: =IF(AE$3=0,"",SUMIFS(INDEX(Inputs!$D$4:$AG$100,0,MATCH(AE$2,Inputs!$D$2:$AG$2,0)),Inputs!$B$4:$B$100,$B5)/1000) | AF5: =IF(AF$3=0,"",SUMIFS(INDEX(Inputs!$D$4:$AG$100,0,MATCH(AF$2,Inputs!$D$2:$AG$2,0)),Inputs!$B$4:$B$100,$B5)/1000) | AG5: =IF(COUNT(AC5:AF5)=4,SUM(AC5:AF5),"")
B6: 3 | C6: SG&A and Other (cash) | D6: =IF(D$3=0,"",SUMIFS(INDEX(Inputs!$D$4:$AG$100,0,MATCH(D$2,Inputs!$D$2:$AG$2,0)),Inputs!$B$4:$B$100,$B6)/1000) | E6: =IF(E$3=0,"",SUMIFS(INDEX(Inputs!$D$4:$AG$100,0,MATCH(E$2,Inputs!$D$2:$AG$2,0)),Inputs!$B$4:$B$100,$B6)/1000) | F6: =IF(F$3=0,"",SUMIFS(INDEX(Inputs!$D$4:$AG$100,0,MATCH(F$2,Inputs!$D$2:$AG$2,0)),Inputs!$B$4:$B$100,$B6)/1000) | G6: =IF(G$3=0,"",SUMIFS(INDEX(Inputs!$D$4:$AG$100,0,MATCH(G$2,Inputs!$D$2:$AG$2,0)),Inputs!$B$4:$B$100,$B6)/1000) | H6: =IF(COUNT(D6:G6)=4,SUM(D6:G6),"") | I6: =IF(I$3=0,"",SUMIFS(INDEX(Inputs!$D$4:$AG$100,0,MATCH(I$2,Inputs!$D$2:$AG$2,0)),Inputs!$B$4:$B$100,$B6)/1000) | J6: =IF(J$3=0,"",SUMIFS(INDEX(Inputs!$D$4:$AG$100,0,MATCH(J$2,Inputs!$D$2:$AG$2,0)),Inputs!$B$4:$B$100,$B6)/1000) | K6: =IF(K$3=0,"",SUMIFS(INDEX(Inputs!$D$4:$AG$100,0,MATCH(K$2,Inputs!$D$2:$AG$2,0)),Inputs!$B$4:$B$100,$B6)/1000) | L6: =IF(L$3=0,"",SUMIFS(INDEX(Inputs!$D$4:$AG$100,0,MATCH(L$2,Inputs!$D$2:$AG$2,0)),Inputs!$B$4:$B$100,$B6)/1000) | M6: =IF(COUNT(I6:L6)=4,SUM(I6:L6),"") | N6: =IF(N$3=0,"",SUMIFS(INDEX(Inputs!$D$4:$AG$100,0,MATCH(N$2,Inputs!$D$2:$AG$2,0)),Inputs!$B$4:$B$100,$B6)/1000) | O6: =IF(O$3=0,"",SUMIFS(INDEX(Inputs!$D$4:$AG$100,0,MATCH(O$2,Inputs!$D$2:$AG$2,0)),Inputs!$B$4:$B$100,$B6)/1000) | P6: =IF(P$3=0,"",SUMIFS(INDEX(Inputs!$D$4:$AG$100,0,MATCH(P$2,Inputs!$D$2:$AG$2,0)),Inputs!$B$4:$B$100,$B6)/1000) | Q6: =IF(Q$3=0,"",SUMIFS(INDEX(Inputs!$D$4:$AG$100,0,MATCH(Q$2,Inputs!$D$2:$AG$2,0)),Inputs!$B$4:$B$100,$B6)/1000) | R6: =IF(COUNT(N6:Q6)=4,SUM(N6:Q6),"") | S6: =IF(S$3=0,"",SUMIFS(INDEX(Inputs!$D$4:$AG$100,0,MATCH(S$2,Inputs!$D$2:$AG$2,0)),Inputs!$B$4:$B$100,$B6)/1000) | T6: =IF(T$3=0,"",SUMIFS(INDEX(Inputs!$D$4:$AG$100,0,MATCH(T$2,Inputs!$D$2:$AG$2,0)),Inputs!$B$4:$B$100,$B6)/1000) | U6: =IF(U$3=0,"",SUMIFS(INDEX(Inputs!$D$4:$AG$100,0,MATCH(U$2,Inputs!$D$2:$AG$2,0)),Inputs!$B$4:$B$100,$B6)/1000) | V6: =IF(V$3=0,"",SUMIFS(INDEX(Inputs!$D$4:$AG$100,0,MATCH(V$2,Inputs!$D$2:$AG$2,0)),Inputs!$B$4:$B$100,$B6)/1000) | W6: =IF(COUNT(S6:V6)=4,SUM(S6:V6),"") | X6: =IF(X$3=0,"",SUMIFS(INDEX(Inputs!$D$4:$AG$100,0,MATCH(X$2,Inputs!$D$2:$AG$2,0)),Inputs!$B$4:$B$100,$B6)/1000) | Y6: =IF(Y$3=0,"",SUMIFS(INDEX(Inputs!$D$4:$AG$100,0,MATCH(Y$2,Inputs!$D$2:$AG$2,0)),Inputs!$B$4:$B$100,$B6)/1000) | Z6: =IF(Z$3=0,"",SUMIFS(INDEX(Inputs!$D$4:$AG$100,0,MATCH(Z$2,Inputs!$D$2:$AG$2,0)),Inputs!$B$4:$B$100,$B6)/1000) | AA6: =IF(AA$3=0,"",SUMIFS(INDEX(Inputs!$D$4:$AG$100,0,MATCH(AA$2,Inputs!$D$2:$AG$2,0)),Inputs!$B$4:$B$100,$B6)/1000) | AB6: =IF(COUNT(X6:AA6)=4,SUM(X6:AA6),"") | AC6: =IF(AC$3=0,"",SUMIFS(INDEX(Inputs!$D$4:$AG$100,0,MATCH(AC$2,Inputs!$D$2:$AG$2,0)),Inputs!$B$4:$B$100,$B6)/1000) | AD6: =IF(AD$3=0,"",SUMIFS(INDEX(Inputs!$D$4:$AG$100,0,MATCH(AD$2,Inputs!$D$2:$AG$2,0)),Inputs!$B$4:$B$100,$B6)/1000) | AE6: =IF(AE$3=0,"",SUMIFS(INDEX(Inputs!$D$4:$AG$100,0,MATCH(AE$2,Inputs!$D$2:$AG$2,0)),Inputs!$B$4:$B$100,$B6)/1000) | AF6: =IF(AF$3=0,"",SUMIFS(INDEX(Inputs!$D$4:$AG$100,0,MATCH(AF$2,Inputs!$D$2:$AG$2,0)),Inputs!$B$4:$B$100,$B6)/1000) | AG6: =IF(COUNT(AC6:AF6)=4,SUM(AC6:AF6),"")
B7: 4 | C7: D&A | D7: =IF(D$3=0,"",SUMIFS(INDEX(Inputs!$D$4:$AG$100,0,MATCH(D$2,Inputs!$D$2:$AG$2,0)),Inputs!$B$4:$B$100,$B7)/1000) | E7: =IF(E$3=0,"",SUMIFS(INDEX(Inputs!$D$4:$AG$100,0,MATCH(E$2,Inputs!$D$2:$AG$2,0)),Inputs!$B$4:$B$100,$B7)/1000) | F7: =IF(F$3=0,"",SUMIFS(INDEX(Inputs!$D$4:$AG$100,0,MATCH(F$2,Inputs!$D$2:$AG$2,0)),Inputs!$B$4:$B$100,$B7)/1000) | G7: =IF(G$3=0,"",SUMIFS(INDEX(Inputs!$D$4:$AG$100,0,MATCH(G$2,Inputs!$D$2:$AG$2,0)),Inputs!$B$4:$B$100,$B7)/1000) | H7: =IF(COUNT(D7:G7)=4,SUM(D7:G7),"") | I7: =IF(I$3=0,"",SUMIFS(INDEX(Inputs!$D$4:$AG$100,0,MATCH(I$2,Inputs!$D$2:$AG$2,0)),Inputs!$B$4:$B$100,$B7)/1000) | J7: =IF(J$3=0,"",SUMIFS(INDEX(Inputs!$D$4:$AG$100,0,MATCH(J$2,Inputs!$D$2:$AG$2,0)),Inputs!$B$4:$B$100,$B7)/1000) | K7: =IF(K$3=0,"",SUMIFS(INDEX(Inputs!$D$4:$AG$100,0,MATCH(K$2,Inputs!$D$2:$AG$2,0)),Inputs!$B$4:$B$100,$B7)/1000) | L7: =IF(L$3=0,"",SUMIFS(INDEX(Inputs!$D$4:$AG$100,0,MATCH(L$2,Inputs!$D$2:$AG$2,0)),Inputs!$B$4:$B$100,$B7)/1000) | M7: =IF(COUNT(I7:L7)=4,SUM(I7:L7),"") | N7: =IF(N$3=0,"",SUMIFS(INDEX(Inputs!$D$4:$AG$100,0,MATCH(N$2,Inputs!$D$2:$AG$2,0)),Inputs!$B$4:$B$100,$B7)/1000) | O7: =IF(O$3=0,"",SUMIFS(INDEX(Inputs!$D$4:$AG$100,0,MATCH(O$2,Inputs!$D$2:$AG$2,0)),Inputs!$B$4:$B$100,$B7)/1000) | P7: =IF(P$3=0,"",SUMIFS(INDEX(Inputs!$D$4:$AG$100,0,MATCH(P$2,Inputs!$D$2:$AG$2,0)),Inputs!$B$4:$B$100,$B7)/1000) | Q7: =IF(Q$3=0,"",SUMIFS(INDEX(Inputs!$D$4:$AG$100,0,MATCH(Q$2,Inputs!$D$2:$AG$2,0)),Inputs!$B$4:$B$100,$B7)/1000) | R7: =IF(COUNT(N7:Q7)=4,SUM(N7:Q7),"") | S7: =IF(S$3=0,"",SUMIFS(INDEX(Inputs!$D$4:$AG$100,0,MATCH(S$2,Inputs!$D$2:$AG$2,0)),Inputs!$B$4:$B$100,$B7)/1000) | T7: =IF(T$3=0,"",SUMIFS(INDEX(Inputs!$D$4:$AG$100,0,MATCH(T$2,Inputs!$D$2:$AG$2,0)),Inputs!$B$4:$B$100,$B7)/1000) | U7: =IF(U$3=0,"",SUMIFS(INDEX(Inputs!$D$4:$AG$100,0,MATCH(U$2,Inputs!$D$2:$AG$2,0)),Inputs!$B$4:$B$100,$B7)/1000) | V7: =IF(V$3=0,"",SUMIFS(INDEX(Inputs!$D$4:$AG$100,0,MATCH(V$2,Inputs!$D$2:$AG$2,0)),Inputs!$B$4:$B$100,$B7)/1000) | W7: =IF(COUNT(S7:V7)=4,SUM(S7:V7),"") | X7: =IF(X$3=0,"",SUMIFS(INDEX(Inputs!$D$4:$AG$100,0,MATCH(X$2,Inputs!$D$2:$AG$2,0)),Inputs!$B$4:$B$100,$B7)/1000) | Y7: =IF(Y$3=0,"",SUMIFS(INDEX(Inputs!$D$4:$AG$100,0,MATCH(Y$2,Inputs!$D$2:$AG$2,0)),Inputs!$B$4:$B$100,$B7)/1000) | Z7: =IF(Z$3=0,"",SUMIFS(INDEX(Inputs!$D$4:$AG$100,0,MATCH(Z$2,Inputs!$D$2:$AG$2,0)),Inputs!$B$4:$B$100,$B7)/1000) | AA7: =IF(AA$3=0,"",SUMIFS(INDEX(Inputs!$D$4:$AG$100,0,MATCH(AA$2,Inputs!$D$2:$AG$2,0)),Inputs!$B$4:$B$100,$B7)/1000) | AB7: =IF(COUNT(X7:AA7)=4,SUM(X7:AA7),"") | AC7: =IF(AC$3=0,"",SUMIFS(INDEX(Inputs!$D$4:$AG$100,0,MATCH(AC$2,Inputs!$D$2:$AG$2,0)),Inputs!$B$4:$B$100,$B7)/1000) | AD7: =IF(AD$3=0,"",SUMIFS(INDEX(Inputs!$D$4:$AG$100,0,MATCH(AD$2,Inputs!$D$2:$AG$2,0)),Inputs!$B$4:$B$100,$B7)/1000) | AE7: =IF(AE$3=0,"",SUMIFS(INDEX(Inputs!$D$4:$AG$100,0,MATCH(AE$2,Inputs!$D$2:$AG$2,0)),Inputs!$B$4:$B$100,$B7)/1000) | AF7: =IF(AF$3=0,"",SUMIFS(INDEX(Inputs!$D$4:$AG$100,0,MATCH(AF$2,Inputs!$D$2:$AG$2,0)),Inputs!$B$4:$B$100,$B7)/1000) | AG7: =IF(COUNT(AC7:AF7)=4,SUM(AC7:AF7),"")
B8: 5 | C8: Interest Expense | D8: =IF(D$3=0,"",SUMIFS(INDEX(Inputs!$D$4:$AG$100,0,MATCH(D$2,Inputs!$D$2:$AG$2,0)),Inputs!$B$4:$B$100,$B8)/1000) | E8: =IF(E$3=0,"",SUMIFS(INDEX(Inputs!$D$4:$AG$100,0,MATCH(E$2,Inputs!$D$2:$AG$2,0)),Inputs!$B$4:$B$100,$B8)/1000) | F8: =IF(F$3=0,"",SUMIFS(INDEX(Inputs!$D$4:$AG$100,0,MATCH(F$2,Inputs!$D$2:$AG$2,0)),Inputs!$B$4:$B$100,$B8)/1000) | G8: =IF(G$3=0,"",SUMIFS(INDEX(Inputs!$D$4:$AG$100,0,MATCH(G$2,Inputs!$D$2:$AG$2,0)),Inputs!$B$4:$B$100,$B8)/1000) | H8: =IF(COUNT(D8:G8)=4,SUM(D8:G8),"") | I8: =IF(I$3=0,"",SUMIFS(INDEX(Inputs!$D$4:$AG$100,0,MATCH(I$2,Inputs!$D$2:$AG$2,0)),Inputs!$B$4:$B$100,$B8)/1000) | J8: =IF(J$3=0,"",SUMIFS(INDEX(Inputs!$D$4:$AG$100,0,MATCH(J$2,Inputs!$D$2:$AG$2,0)),Inputs!$B$4:$B$100,$B8)/1000) | K8: =IF(K$3=0,"",SUMIFS(INDEX(Inputs!$D$4:$AG$100,0,MATCH(K$2,Inputs!$D$2:$AG$2,0)),Inputs!$B$4:$B$100,$B8)/1000) | L8: =IF(L$3=0,"",SUMIFS(INDEX(Inputs!$D$4:$AG$100,0,MATCH(L$2,Inputs!$D$2:$AG$2,0)),Inputs!$B$4:$B$100,$B8)/1000) | M8: =IF(COUNT(I8:L8)=4,SUM(I8:L8),"") | N8: =IF(N$3=0,"",SUMIFS(INDEX(Inputs!$D$4:$AG$100,0,MATCH(N$2,Inputs!$D$2:$AG$2,0)),Inputs!$B$4:$B$100,$B8)/1000) | O8: =IF(O$3=0,"",SUMIFS(INDEX(Inputs!$D$4:$AG$100,0,MATCH(O$2,Inputs!$D$2:$AG$2,0)),Inputs!$B$4:$B$100,$B8)/1000) | P8: =IF(P$3=0,"",SUMIFS(INDEX(Inputs!$D$4:$AG$100,0,MATCH(P$2,Inputs!$D$2:$AG$2,0)),Inputs!$B$4:$B$100,$B8)/1000) | Q8: =IF(Q$3=0,"",SUMIFS(INDEX(Inputs!$D$4:$AG$100,0,MATCH(Q$2,Inputs!$D$2:$AG$2,0)),Inputs!$B$4:$B$100,$B8)/1000) | R8: =IF(COUNT(N8:Q8)=4,SUM(N8:Q8),"") | S8: =IF(S$3=0,"",SUMIFS(INDEX(Inputs!$D$4:$AG$100,0,MATCH(S$2,Inputs!$D$2:$AG$2,0)),Inputs!$B$4:$B$100,$B8)/1000) | T8: =IF(T$3=0,"",SUMIFS(INDEX(Inputs!$D$4:$AG$100,0,MATCH(T$2,Inputs!$D$2:$AG$2,0)),Inputs!$B$4:$B$100,$B8)/1000) | U8: =IF(U$3=0,"",SUMIFS(INDEX(Inputs!$D$4:$AG$100,0,MATCH(U$2,Inputs!$D$2:$AG$2,0)),Inputs!$B$4:$B$100,$B8)/1000) | V8: =IF(V$3=0,"",SUMIFS(INDEX(Inputs!$D$4:$AG$100,0,MATCH(V$2,Inputs!$D$2:$AG$2,0)),Inputs!$B$4:$B$100,$B8)/1000) | W8: =IF(COUNT(S8:V8)=4,SUM(S8:V8),"") | X8: =IF(X$3=0,"",SUMIFS(INDEX(Inputs!$D$4:$AG$100,0,MATCH(X$2,Inputs!$D$2:$AG$2,0)),Inputs!$B$4:$B$100,$B8)/1000) | Y8: =IF(Y$3=0,"",SUMIFS(INDEX(Inputs!$D$4:$AG$100,0,MATCH(Y$2,Inputs!$D$2:$AG$2,0)),Inputs!$B$4:$B$100,$B8)/1000) | Z8: =IF(Z$3=0,"",SUMIFS(INDEX(Inputs!$D$4:$AG$100,0,MATCH(Z$2,Inputs!$D$2:$AG$2,0)),Inputs!$B$4:$B$100,$B8)/1000) | AA8: =IF(AA$3=0,"",SUMIFS(INDEX(Inputs!$D$4:$AG$100,0,MATCH(AA$2,Inputs!$D$2:$AG$2,0)),Inputs!$B$4:$B$100,$B8)/1000) | AB8: =IF(COUNT(X8:AA8)=4,SUM(X8:AA8),"") | AC8: =IF(AC$3=0,"",SUMIFS(INDEX(Inputs!$D$4:$AG$100,0,MATCH(AC$2,Inputs!$D$2:$AG$2,0)),Inputs!$B$4:$B$100,$B8)/1000) | AD8: =IF(AD$3=0,"",SUMIFS(INDEX(Inputs!$D$4:$AG$100,0,MATCH(AD$2,Inputs!$D$2:$AG$2,0)),Inputs!$B$4:$B$100,$B8)/1000) | AE8: =IF(AE$3=0,"",SUMIFS(INDEX(Inputs!$D$4:$AG$100,0,MATCH(AE$2,Inputs!$D$2:$AG$2,0)),Inputs!$B$4:$B$100,$B8)/1000) | AF8: =IF(AF$3=0,"",SUMIFS(INDEX(Inputs!$D$4:$AG$100,0,MATCH(AF$2,Inputs!$D$2:$AG$2,0)),Inputs!$B$4:$B$100,$B8)/1000) | AG8: =IF(COUNT(AC8:AF8)=4,SUM(AC8:AF8),"")
B9: 6 | C9: Nonoperating Income / (Loss) | D9: =IF(D$3=0,"",SUMIFS(INDEX(Inputs!$D$4:$AG$100,0,MATCH(D$2,Inputs!$D$2:$AG$2,0)),Inputs!$B$4:$B$100,$B9)/1000) | E9: =IF(E$3=0,"",SUMIFS(INDEX(Inputs!$D$4:$AG$100,0,MATCH(E$2,Inputs!$D$2:$AG$2,0)),Inputs!$B$4:$B$100,$B9)/1000) | F9: =IF(F$3=0,"",SUMIFS(INDEX(Inputs!$D$4:$AG$100,0,MATCH(F$2,Inputs!$D$2:$AG$2,0)),Inputs!$B$4:$B$100,$B9)/1000) | G9: =IF(G$3=0,"",SUMIFS(INDEX(Inputs!$D$4:$AG$100,0,MATCH(G$2,Inputs!$D$2:$AG$2,0)),Inputs!$B$4:$B$100,$B9)/1000) | H9: =IF(COUNT(D9:G9)=4,SUM(D9:G9),"") | I9: =IF(I$3=0,"",SUMIFS(INDEX(Inputs!$D$4:$AG$100,0,MATCH(I$2,Inputs!$D$2:$AG$2,0)),Inputs!$B$4:$B$100,$B9)/1000) | J9: =IF(J$3=0,"",SUMIFS(INDEX(Inputs!$D$4:$AG$100,0,MATCH(J$2,Inputs!$D$2:$AG$2,0)),Inputs!$B$4:$B$100,$B9)/1000) | K9: =IF(K$3=0,"",SUMIFS(INDEX(Inputs!$D$4:$AG$100,0,MATCH(K$2,Inputs!$D$2:$AG$2,0)),Inputs!$B$4:$B$100,$B9)/1000) | L9: =IF(L$3=0,"",SUMIFS(INDEX(Inputs!$D$4:$AG$100,0,MATCH(L$2,Inputs!$D$2:$AG$2,0)),Inputs!$B$4:$B$100,$B9)/1000) | M9: =IF(COUNT(I9:L9)=4,SUM(I9:L9),"") | N9: =IF(N$3=0,"",SUMIFS(INDEX(Inputs!$D$4:$AG$100,0,MATCH(N$2,Inputs!$D$2:$AG$2,0)),Inputs!$B$4:$B$100,$B9)/1000) | O9: =IF(O$3=0,"",SUMIFS(INDEX(Inputs!$D$4:$AG$100,0,MATCH(O$2,Inputs!$D$2:$AG$2,0)),Inputs!$B$4:$B$100,$B9)/1000) | P9: =IF(P$3=0,"",SUMIFS(INDEX(Inputs!$D$4:$AG$100,0,MATCH(P$2,Inputs!$D$2:$AG$2,0)),Inputs!$B$4:$B$100,$B9)/1000) | Q9: =IF(Q$3=0,"",SUMIFS(INDEX(Inputs!$D$4:$AG$100,0,MATCH(Q$2,Inputs!$D$2:$AG$2,0)),Inputs!$B$4:$B$100,$B9)/1000) | R9: =IF(COUNT(N9:Q9)=4,SUM(N9:Q9),"") | S9: =IF(S$3=0,"",SUMIFS(INDEX(Inputs!$D$4:$AG$100,0,MATCH(S$2,Inputs!$D$2:$AG$2,0)),Inputs!$B$4:$B$100,$B9)/1000) | T9: =IF(T$3=0,"",SUMIFS(INDEX(Inputs!$D$4:$AG$100,0,MATCH(T$2,Inputs!$D$2:$AG$2,0)),Inputs!$B$4:$B$100,$B9)/1000) | U9: =IF(U$3=0,"",SUMIFS(INDEX(Inputs!$D$4:$AG$100,0,MATCH(U$2,Inputs!$D$2:$AG$2,0)),Inputs!$B$4:$B$100,$B9)/1000) | V9: =IF(V$3=0,"",SUMIFS(INDEX(Inputs!$D$4:$AG$100,0,MATCH(V$2,Inputs!$D$2:$AG$2,0)),Inputs!$B$4:$B$100,$B9)/1000) | W9: =IF(COUNT(S9:V9)=4,SUM(S9:V9),"") | X9: =IF(X$3=0,"",SUMIFS(INDEX(Inputs!$D$4:$AG$100,0,MATCH(X$2,Inputs!$D$2:$AG$2,0)),Inputs!$B$4:$B$100,$B9)/1000) | Y9: =IF(Y$3=0,"",SUMIFS(INDEX(Inputs!$D$4:$AG$100,0,MATCH(Y$2,Inputs!$D$2:$AG$2,0)),Inputs!$B$4:$B$100,$B9)/1000) | Z9: =IF(Z$3=0,"",SUMIFS(INDEX(Inputs!$D$4:$AG$100,0,MATCH(Z$2,Inputs!$D$2:$AG$2,0)),Inputs!$B$4:$B$100,$B9)/1000) | AA9: =IF(AA$3=0,"",SUMIFS(INDEX(Inputs!$D$4:$AG$100,0,MATCH(AA$2,Inputs!$D$2:$AG$2,0)),Inputs!$B$4:$B$100,$B9)/1000) | AB9: =IF(COUNT(X9:AA9)=4,SUM(X9:AA9),"") | AC9: =IF(AC$3=0,"",SUMIFS(INDEX(Inputs!$D$4:$AG$100,0,MATCH(AC$2,Inputs!$D$2:$AG$2,0)),Inputs!$B$4:$B$100,$B9)/1000) | AD9: =IF(AD$3=0,"",SUMIFS(INDEX(Inputs!$D$4:$AG$100,0,MATCH(AD$2,Inputs!$D$2:$AG$2,0)),Inputs!$B$4:$B$100,$B9)/1000) | AE9: =IF(AE$3=0,"",SUMIFS(INDEX(Inputs!$D$4:$AG$100,0,MATCH(AE$2,Inputs!$D$2:$AG$2,0)),Inputs!$B$4:$B$100,$B9)/1000) | AF9: =IF(AF$3=0,"",SUMIFS(INDEX(Inputs!$D$4:$AG$100,0,MATCH(AF$2,Inputs!$D$2:$AG$2,0)),Inputs!$B$4:$B$100,$B9)/1000) | AG9: =IF(COUNT(AC9:AF9)=4,SUM(AC9:AF9),"")
B10: 7 | C10: Taxes | D10: =IF(D$3=0,"",SUMIFS(INDEX(Inputs!$D$4:$AG$100,0,MATCH(D$2,Inputs!$D$2:$AG$2,0)),Inputs!$B$4:$B$100,$B10)/1000) | E10: =IF(E$3=0,"",SUMIFS(INDEX(Inputs!$D$4:$AG$100,0,MATCH(E$2,Inputs!$D$2:$AG$2,0)),Inputs!$B$4:$B$100,$B10)/1000) | F10: =IF(F$3=0,"",SUMIFS(INDEX(Inputs!$D$4:$AG$100,0,MATCH(F$2,Inputs!$D$2:$AG$2,0)),Inputs!$B$4:$B$100,$B10)/1000) | G10: =IF(G$3=0,"",SUMIFS(INDEX(Inputs!$D$4:$AG$100,0,MATCH(G$2,Inputs!$D$2:$AG$2,0)),Inputs!$B$4:$B$100,$B10)/1000) | H10: =IF(COUNT(D10:G10)=4,SUM(D10:G10),"") | I10: =IF(I$3=0,"",SUMIFS(INDEX(Inputs!$D$4:$AG$100,0,MATCH(I$2,Inputs!$D$2:$AG$2,0)),Inputs!$B$4:$B$100,$B10)/1000) | J10: =IF(J$3=0,"",SUMIFS(INDEX(Inputs!$D$4:$AG$100,0,MATCH(J$2,Inputs!$D$2:$AG$2,0)),Inputs!$B$4:$B$100,$B10)/1000) | K10: =IF(K$3=0,"",SUMIFS(INDEX(Inputs!$D$4:$AG$100,0,MATCH(K$2,Inputs!$D$2:$AG$2,0)),Inputs!$B$4:$B$100,$B10)/1000) | L10: =IF(L$3=0,"",SUMIFS(INDEX(Inputs!$D$4:$AG$100,0,MATCH(L$2,Inputs!$D$2:$AG$2,0)),Inputs!$B$4:$B$100,$B10)/1000) | M10: =IF(COUNT(I10:L10)=4,SUM(I10:L10),"") | N10: =IF(N$3=0,"",SUMIFS(INDEX(Inputs!$D$4:$AG$100,0,MATCH(N$2,Inputs!$D$2:$AG$2,0)),Inputs!$B$4:$B$100,$B10)/1000) | O10: =IF(O$3=0,"",SUMIFS(INDEX(Inputs!$D$4:$AG$100,0,MATCH(O$2,Inputs!$D$2:$AG$2,0)),Inputs!$B$4:$B$100,$B10)/1000) | P10: =IF(P$3=0,"",SUMIFS(INDEX(Inputs!$D$4:$AG$100,0,MATCH(P$2,Inputs!$D$2:$AG$2,0)),Inputs!$B$4:$B$100,$B10)/1000) | Q10: =IF(Q$3=0,"",SUMIFS(INDEX(Inputs!$D$4:$AG$100,0,MATCH(Q$2,Inputs!$D$2:$AG$2,0)),Inputs!$B$4:$B$100,$B10)/1000) | R10: =IF(COUNT(N10:Q10)=4,SUM(N10:Q10),"") | S10: =IF(S$3=0,"",SUMIFS(INDEX(Inputs!$D$4:$AG$100,0,MATCH(S$2,Inputs!$D$2:$AG$2,0)),Inputs!$B$4:$B$100,$B10)/1000) | T10: =IF(T$3=0,"",SUMIFS(INDEX(Inputs!$D$4:$AG$100,0,MATCH(T$2,Inputs!$D$2:$AG$2,0)),Inputs!$B$4:$B$100,$B10)/1000) | U10: =IF(U$3=0,"",SUMIFS(INDEX(Inputs!$D$4:$AG$100,0,MATCH(U$2,Inputs!$D$2:$AG$2,0)),Inputs!$B$4:$B$100,$B10)/1000) | V10: =IF(V$3=0,"",SUMIFS(INDEX(Inputs!$D$4:$AG$100,0,MATCH(V$2,Inputs!$D$2:$AG$2,0)),Inputs!$B$4:$B$100,$B10)/1000) | W10: =IF(COUNT(S10:V10)=4,SUM(S10:V10),"") | X10: =IF(X$3=0,"",SUMIFS(INDEX(Inputs!$D$4:$AG$100,0,MATCH(X$2,Inputs!$D$2:$AG$2,0)),Inputs!$B$4:$B$100,$B10)/1000) | Y10: =IF(Y$3=0,"",SUMIFS(INDEX(Inputs!$D$4:$AG$100,0,MATCH(Y$2,Inputs!$D$2:$AG$2,0)),Inputs!$B$4:$B$100,$B10)/1000) | Z10: =IF(Z$3=0,"",SUMIFS(INDEX(Inputs!$D$4:$AG$100,0,MATCH(Z$2,Inputs!$D$2:$AG$2,0)),Inputs!$B$4:$B$100,$B10)/1000) | AA10: =IF(AA$3=0,"",SUMIFS(INDEX(Inputs!$D$4:$AG$100,0,MATCH(AA$2,Inputs!$D$2:$AG$2,0)),Inputs!$B$4:$B$100,$B10)/1000) | AB10: =IF(COUNT(X10:AA10)=4,SUM(X10:AA10),"") | AC10: =IF(AC$3=0,"",SUMIFS(INDEX(Inputs!$D$4:$AG$100,0,MATCH(AC$2,Inputs!$D$2:$AG$2,0)),Inputs!$B$4:$B$100,$B10)/1000) | AD10: =IF(AD$3=0,"",SUMIFS(INDEX(Inputs!$D$4:$AG$100,0,MATCH(AD$2,Inputs!$D$2:$AG$2,0)),Inputs!$B$4:$B$100,$B10)/1000) | AE10: =IF(AE$3=0,"",SUMIFS(INDEX(Inputs!$D$4:$AG$100,0,MATCH(AE$2,Inputs!$D$2:$AG$2,0)),Inputs!$B$4:$B$100,$B10)/1000) | AF10: =IF(AF$3=0,"",SUMIFS(INDEX(Inputs!$D$4:$AG$100,0,MATCH(AF$2,Inputs!$D$2:$AG$2,0)),Inputs!$B$4:$B$100,$B10)/1000) | AG10: =IF(COUNT(AC10:AF10)=4,SUM(AC10:AF10),"")
B11: 8 | C11: Equity in Income of Affiliates, after tax (enter as +) | D11: =IF(D$3=0,"",SUMIFS(INDEX(Inputs!$D$4:$AG$100,0,MATCH(D$2,Inputs!$D$2:$AG$2,0)),Inputs!$B$4:$B$100,$B11)/1000) | E11: =IF(E$3=0,"",SUMIFS(INDEX(Inputs!$D$4:$AG$100,0,MATCH(E$2,Inputs!$D$2:$AG$2,0)),Inputs!$B$4:$B$100,$B11)/1000) | F11: =IF(F$3=0,"",SUMIFS(INDEX(Inputs!$D$4:$AG$100,0,MATCH(F$2,Inputs!$D$2:$AG$2,0)),Inputs!$B$4:$B$100,$B11)/1000) | G11: =IF(G$3=0,"",SUMIFS(INDEX(Inputs!$D$4:$AG$100,0,MATCH(G$2,Inputs!$D$2:$AG$2,0)),Inputs!$B$4:$B$100,$B11)/1000) | H11: =IF(COUNT(D11:G11)=4,SUM(D11:G11),"") | I11: =IF(I$3=0,"",SUMIFS(INDEX(Inputs!$D$4:$AG$100,0,MATCH(I$2,Inputs!$D$2:$AG$2,0)),Inputs!$B$4:$B$100,$B11)/1000) | J11: =IF(J$3=0,"",SUMIFS(INDEX(Inputs!$D$4:$AG$100,0,MATCH(J$2,Inputs!$D$2:$AG$2,0)),Inputs!$B$4:$B$100,$B11)/1000) | K11: =IF(K$3=0,"",SUMIFS(INDEX(Inputs!$D$4:$AG$100,0,MATCH(K$2,Inputs!$D$2:$AG$2,0)),Inputs!$B$4:$B$100,$B11)/1000) | L11: =IF(L$3=0,"",SUMIFS(INDEX(Inputs!$D$4:$AG$100,0,MATCH(L$2,Inputs!$D$2:$AG$2,0)),Inputs!$B$4:$B$100,$B11)/1000) | M11: =IF(COUNT(I11:L11)=4,SUM(I11:L11),"") | N11: =IF(N$3=0,"",SUMIFS(INDEX(Inputs!$D$4:$AG$100,0,MATCH(N$2,Inputs!$D$2:$AG$2,0)),Inputs!$B$4:$B$100,$B11)/1000) | O11: =IF(O$3=0,"",SUMIFS(INDEX(Inputs!$D$4:$AG$100,0,MATCH(O$2,Inputs!$D$2:$AG$2,0)),Inputs!$B$4:$B$100,$B11)/1000) | P11: =IF(P$3=0,"",SUMIFS(INDEX(Inputs!$D$4:$AG$100,0,MATCH(P$2,Inputs!$D$2:$AG$2,0)),Inputs!$B$4:$B$100,$B11)/1000) | Q11: =IF(Q$3=0,"",SUMIFS(INDEX(Inputs!$D$4:$AG$100,0,MATCH(Q$2,Inputs!$D$2:$AG$2,0)),Inputs!$B$4:$B$100,$B11)/1000) | R11: =IF(COUNT(N11:Q11)=4,SUM(N11:Q11),"") | S11: =IF(S$3=0,"",SUMIFS(INDEX(Inputs!$D$4:$AG$100,0,MATCH(S$2,Inputs!$D$2:$AG$2,0)),Inputs!$B$4:$B$100,$B11)/1000) | T11: =IF(T$3=0,"",SUMIFS(INDEX(Inputs!$D$4:$AG$100,0,MATCH(T$2,Inputs!$D$2:$AG$2,0)),Inputs!$B$4:$B$100,$B11)/1000) | U11: =IF(U$3=0,"",SUMIFS(INDEX(Inputs!$D$4:$AG$100,0,MATCH(U$2,Inputs!$D$2:$AG$2,0)),Inputs!$B$4:$B$100,$B11)/1000) | V11: =IF(V$3=0,"",SUMIFS(INDEX(Inputs!$D$4:$AG$100,0,MATCH(V$2,Inputs!$D$2:$AG$2,0)),Inputs!$B$4:$B$100,$B11)/1000) | W11: =IF(COUNT(S11:V11)=4,SUM(S11:V11),"") | X11: =IF(X$3=0,"",SUMIFS(INDEX(Inputs!$D$4:$AG$100,0,MATCH(X$2,Inputs!$D$2:$AG$2,0)),Inputs!$B$4:$B$100,$B11)/1000) | Y11: =IF(Y$3=0,"",SUMIFS(INDEX(Inputs!$D$4:$AG$100,0,MATCH(Y$2,Inputs!$D$2:$AG$2,0)),Inputs!$B$4:$B$100,$B11)/1000) | Z11: =IF(Z$3=0,"",SUMIFS(INDEX(Inputs!$D$4:$AG$100,0,MATCH(Z$2,Inputs!$D$2:$AG$2,0)),Inputs!$B$4:$B$100,$B11)/1000) | AA11: =IF(AA$3=0,"",SUMIFS(INDEX(Inputs!$D$4:$AG$100,0,MATCH(AA$2,Inputs!$D$2:$AG$2,0)),Inputs!$B$4:$B$100,$B11)/1000) | AB11: =IF(COUNT(X11:AA11)=4,SUM(X11:AA11),"") | AC11: =IF(AC$3=0,"",SUMIFS(INDEX(Inputs!$D$4:$AG$100,0,MATCH(AC$2,Inputs!$D$2:$AG$2,0)),Inputs!$B$4:$B$100,$B11)/1000) | AD11: =IF(AD$3=0,"",SUMIFS(INDEX(Inputs!$D$4:$AG$100,0,MATCH(AD$2,Inputs!$D$2:$AG$2,0)),Inputs!$B$4:$B$100,$B11)/1000) | AE11: =IF(AE$3=0,"",SUMIFS(INDEX(Inputs!$D$4:$AG$100,0,MATCH(AE$2,Inputs!$D$2:$AG$2,0)),Inputs!$B$4:$B$100,$B11)/1000) | AF11: =IF(AF$3=0,"",SUMIFS(INDEX(Inputs!$D$4:$AG$100,0,MATCH(AF$2,Inputs!$D$2:$AG$2,0)),Inputs!$B$4:$B$100,$B11)/1000) | AG11: =IF(COUNT(AC11:AF11)=4,SUM(AC11:AF11),"")
B12: 9 | C12: Minority Interest Expense, after tax (enter as - ) | D12: =IF(D$3=0,"",SUMIFS(INDEX(Inputs!$D$4:$AG$100,0,MATCH(D$2,Inputs!$D$2:$AG$2,0)),Inputs!$B$4:$B$100,$B12)/1000) | E12: =IF(E$3=0,"",SUMIFS(INDEX(Inputs!$D$4:$AG$100,0,MATCH(E$2,Inputs!$D$2:$AG$2,0)),Inputs!$B$4:$B$100,$B12)/1000) | F12: =IF(F$3=0,"",SUMIFS(INDEX(Inputs!$D$4:$AG$100,0,MATCH(F$2,Inputs!$D$2:$AG$2,0)),Inputs!$B$4:$B$100,$B12)/1000) | G12: =IF(G$3=0,"",SUMIFS(INDEX(Inputs!$D$4:$AG$100,0,MATCH(G$2,Inputs!$D$2:$AG$2,0)),Inputs!$B$4:$B$100,$B12)/1000) | H12: =IF(COUNT(D12:G12)=4,SUM(D12:G12),"") | I12: =IF(I$3=0,"",SUMIFS(INDEX(Inputs!$D$4:$AG$100,0,MATCH(I$2,Inputs!$D$2:$AG$2,0)),Inputs!$B$4:$B$100,$B12)/1000) | J12: =IF(J$3=0,"",SUMIFS(INDEX(Inputs!$D$4:$AG$100,0,MATCH(J$2,Inputs!$D$2:$AG$2,0)),Inputs!$B$4:$B$100,$B12)/1000) | K12: =IF(K$3=0,"",SUMIFS(INDEX(Inputs!$D$4:$AG$100,0,MATCH(K$2,Inputs!$D$2:$AG$2,0)),Inputs!$B$4:$B$100,$B12)/1000) | L12: =IF(L$3=0,"",SUMIFS(INDEX(Inputs!$D$4:$AG$100,0,MATCH(L$2,Inputs!$D$2:$AG$2,0)),Inputs!$B$4:$B$100,$B12)/1000) | M12: =IF(COUNT(I12:L12)=4,SUM(I12:L12),"") | N12: =IF(N$3=0,"",SUMIFS(INDEX(Inputs!$D$4:$AG$100,0,MATCH(N$2,Inputs!$D$2:$AG$2,0)),Inputs!$B$4:$B$100,$B12)/1000) | O12: =IF(O$3=0,"",SUMIFS(INDEX(Inputs!$D$4:$AG$100,0,MATCH(O$2,Inputs!$D$2:$AG$2,0)),Inputs!$B$4:$B$100,$B12)/1000) | P12: =IF(P$3=0,"",SUMIFS(INDEX(Inputs!$D$4:$AG$100,0,MATCH(P$2,Inputs!$D$2:$AG$2,0)),Inputs!$B$4:$B$100,$B12)/1000) | Q12: =IF(Q$3=0,"",SUMIFS(INDEX(Inputs!$D$4:$AG$100,0,MATCH(Q$2,Inputs!$D$2:$AG$2,0)),Inputs!$B$4:$B$100,$B12)/1000) | R12: =IF(COUNT(N12:Q12)=4,SUM(N12:Q12),"") | S12: =IF(S$3=0,"",SUMIFS(INDEX(Inputs!$D$4:$AG$100,0,MATCH(S$2,Inputs!$D$2:$AG$2,0)),Inputs!$B$4:$B$100,$B12)/1000) | T12: =IF(T$3=0,"",SUMIFS(INDEX(Inputs!$D$4:$AG$100,0,MATCH(T$2,Inputs!$D$2:$AG$2,0)),Inputs!$B$4:$B$100,$B12)/1000) | U12: =IF(U$3=0,"",SUMIFS(INDEX(Inputs!$D$4:$AG$100,0,MATCH(U$2,Inputs!$D$2:$AG$2,0)),Inputs!$B$4:$B$100,$B12)/1000) | V12: =IF(V$3=0,"",SUMIFS(INDEX(Inputs!$D$4:$AG$100,0,MATCH(V$2,Inputs!$D$2:$AG$2,0)),Inputs!$B$4:$B$100,$B12)/1000) | W12: =IF(COUNT(S12:V12)=4,SUM(S12:V12),"") | X12: =IF(X$3=0,"",SUMIFS(INDEX(Inputs!$D$4:$AG$100,0,MATCH(X$2,Inputs!$D$2:$AG$2,0)),Inputs!$B$4:$B$100,$B12)/1000) | Y12: =IF(Y$3=0,"",SUMIFS(INDEX(Inputs!$D$4:$AG$100,0,MATCH(Y$2,Inputs!$D$2:$AG$2,0)),Inputs!$B$4:$B$100,$B12)/1000) | Z12: =IF(Z$3=0,"",SUMIFS(INDEX(Inputs!$D$4:$AG$100,0,MATCH(Z$2,Inputs!$D$2:$AG$2,0)),Inputs!$B$4:$B$100,$B12)/1000) | AA12: =IF(AA$3=0,"",SUMIFS(INDEX(Inputs!$D$4:$AG$100,0,MATCH(AA$2,Inputs!$D$2:$AG$2,0)),Inputs!$B$4:$B$100,$B12)/1000) | AB12: =IF(COUNT(X12:AA12)=4,SUM(X12:AA12),"") | AC12: =IF(AC$3=0,"",SUMIFS(INDEX(Inputs!$D$4:$AG$100,0,MATCH(AC$2,Inputs!$D$2:$AG$2,0)),Inputs!$B$4:$B$100,$B12)/1000) | AD12: =IF(AD$3=0,"",SUMIFS(INDEX(Inputs!$D$4:$AG$100,0,MATCH(AD$2,Inputs!$D$2:$AG$2,0)),Inputs!$B$4:$B$100,$B12)/1000) | AE12: =IF(AE$3=0,"",SUMIFS(INDEX(Inputs!$D$4:$AG$100,0,MATCH(AE$2,Inputs!$D$2:$AG$2,0)),Inputs!$B$4:$B$100,$B12)/1000) | AF12: =IF(AF$3=0,"",SUMIFS(INDEX(Inputs!$D$4:$AG$100,0,MATCH(AF$2,Inputs!$D$2:$AG$2,0)),Inputs!$B$4:$B$100,$B12)/1000) | AG12: =IF(COUNT(AC12:AF12)=4,SUM(AC12:AF12),"")
B13: 10 | C13: Common Dividends | D13: =IF(D$3=0,"",SUMIFS(INDEX(Inputs!$D$4:$AG$100,0,MATCH(D$2,Inputs!$D$2:$AG$2,0)),Inputs!$B$4:$B$100,$B13)/1000) | E13: =IF(E$3=0,"",SUMIFS(INDEX(Inputs!$D$4:$AG$100,0,MATCH(E$2,Inputs!$D$2:$AG$2,0)),Inputs!$B$4:$B$100,$B13)/1000) | F13: =IF(F$3=0,"",SUMIFS(INDEX(Inputs!$D$4:$AG$100,0,MATCH(F$2,Inputs!$D$2:$AG$2,0)),Inputs!$B$4:$B$100,$B13)/1000) | G13: =IF(G$3=0,"",SUMIFS(INDEX(Inputs!$D$4:$AG$100,0,MATCH(G$2,Inputs!$D$2:$AG$2,0)),Inputs!$B$4:$B$100,$B13)/1000) | H13: =IF(COUNT(D13:G13)=4,SUM(D13:G13),"") | I13: =IF(I$3=0,"",SUMIFS(INDEX(Inputs!$D$4:$AG$100,0,MATCH(I$2,Inputs!$D$2:$AG$2,0)),Inputs!$B$4:$B$100,$B13)/1000) | J13: =IF(J$3=0,"",SUMIFS(INDEX(Inputs!$D$4:$AG$100,0,MATCH(J$2,Inputs!$D$2:$AG$2,0)),Inputs!$B$4:$B$100,$B13)/1000) | K13: =IF(K$3=0,"",SUMIFS(INDEX(Inputs!$D$4:$AG$100,0,MATCH(K$2,Inputs!$D$2:$AG$2,0)),Inputs!$B$4:$B$100,$B13)/1000) | L13: =IF(L$3=0,"",SUMIFS(INDEX(Inputs!$D$4:$AG$100,0,MATCH(L$2,Inputs!$D$2:$AG$2,0)),Inputs!$B$4:$B$100,$B13)/1000) | M13: =IF(COUNT(I13:L13)=4,SUM(I13:L13),"") | N13: =IF(N$3=0,"",SUMIFS(INDEX(Inputs!$D$4:$AG$100,0,MATCH(N$2,Inputs!$D$2:$AG$2,0)),Inputs!$B$4:$B$100,$B13)/1000) | O13: =IF(O$3=0,"",SUMIFS(INDEX(Inputs!$D$4:$AG$100,0,MATCH(O$2,Inputs!$D$2:$AG$2,0)),Inputs!$B$4:$B$100,$B13)/1000) | P13: =IF(P$3=0,"",SUMIFS(INDEX(Inputs!$D$4:$AG$100,0,MATCH(P$2,Inputs!$D$2:$AG$2,0)),Inputs!$B$4:$B$100,$B13)/1000) | Q13: =IF(Q$3=0,"",SUMIFS(INDEX(Inputs!$D$4:$AG$100,0,MATCH(Q$2,Inputs!$D$2:$AG$2,0)),Inputs!$B$4:$B$100,$B13)/1000) | R13: =IF(COUNT(N13:Q13)=4,SUM(N13:Q13),"") | S13: =IF(S$3=0,"",SUMIFS(INDEX(Inputs!$D$4:$AG$100,0,MATCH(S$2,Inputs!$D$2:$AG$2,0)),Inputs!$B$4:$B$100,$B13)/1000) | T13: =IF(T$3=0,"",SUMIFS(INDEX(Inputs!$D$4:$AG$100,0,MATCH(T$2,Inputs!$D$2:$AG$2,0)),Inputs!$B$4:$B$100,$B13)/1000) | U13: =IF(U$3=0,"",SUMIFS(INDEX(Inputs!$D$4:$AG$100,0,MATCH(U$2,Inputs!$D$2:$AG$2,0)),Inputs!$B$4:$B$100,$B13)/1000) | V13: =IF(V$3=0,"",SUMIFS(INDEX(Inputs!$D$4:$AG$100,0,MATCH(V$2,Inputs!$D$2:$AG$2,0)),Inputs!$B$4:$B$100,$B13)/1000) | W13: =IF(COUNT(S13:V13)=4,SUM(S13:V13),"") | X13: =IF(X$3=0,"",SUMIFS(INDEX(Inputs!$D$4:$AG$100,0,MATCH(X$2,Inputs!$D$2:$AG$2,0)),Inputs!$B$4:$B$100,$B13)/1000) | Y13: =IF(Y$3=0,"",SUMIFS(INDEX(Inputs!$D$4:$AG$100,0,MATCH(Y$2,Inputs!$D$2:$AG$2,0)),Inputs!$B$4:$B$100,$B13)/1000) | Z13: =IF(Z$3=0,"",SUMIFS(INDEX(Inputs!$D$4:$AG$100,0,MATCH(Z$2,Inputs!$D$2:$AG$2,0)),Inputs!$B$4:$B$100,$B13)/1000) | AA13: =IF(AA$3=0,"",SUMIFS(INDEX(Inputs!$D$4:$AG$100,0,MATCH(AA$2,Inputs!$D$2:$AG$2,0)),Inputs!$B$4:$B$100,$B13)/1000) | AB13: =IF(COUNT(X13:AA13)=4,SUM(X13:AA13),"") | AC13: =IF(AC$3=0,"",SUMIFS(INDEX(Inputs!$D$4:$AG$100,0,MATCH(AC$2,Inputs!$D$2:$AG$2,0)),Inputs!$B$4:$B$100,$B13)/1000) | AD13: =IF(AD$3=0,"",SUMIFS(INDEX(Inputs!$D$4:$AG$100,0,MATCH(AD$2,Inputs!$D$2:$AG$2,0)),Inputs!$B$4:$B$100,$B13)/1000) | AE13: =IF(AE$3=0,"",SUMIFS(INDEX(Inputs!$D$4:$AG$100,0,MATCH(AE$2,Inputs!$D$2:$AG$2,0)),Inputs!$B$4:$B$100,$B13)/1000) | AF13: =IF(AF$3=0,"",SUMIFS(INDEX(Inputs!$D$4:$AG$100,0,MATCH(AF$2,Inputs!$D$2:$AG$2,0)),Inputs!$B$4:$B$100,$B13)/1000) | AG13: =IF(COUNT(AC13:AF13)=4,SUM(AC13:AF13),"")
B15: 11 | C15: Cash and equivalents (inc. investment securities) | D15: =IF(D$3=0,"",SUMIFS(INDEX(Inputs!$D$4:$AG$100,0,MATCH(D$2,Inputs!$D$2:$AG$2,0)),Inputs!$B$4:$B$100,$B15)/1000) | E15: =IF(E$3=0,"",SUMIFS(INDEX(Inputs!$D$4:$AG$100,0,MATCH(E$2,Inputs!$D$2:$AG$2,0)),Inputs!$B$4:$B$100,$B15)/1000) | F15: =IF(F$3=0,"",SUMIFS(INDEX(Inputs!$D$4:$AG$100,0,MATCH(F$2,Inputs!$D$2:$AG$2,0)),Inputs!$B$4:$B$100,$B15)/1000) | G15: =IF(G$3=0,"",SUMIFS(INDEX(Inputs!$D$4:$AG$100,0,MATCH(G$2,Inputs!$D$2:$AG$2,0)),Inputs!$B$4:$B$100,$B15)/1000) | H15: =IF(G15="","",G15) | I15: =IF(I$3=0,"",SUMIFS(INDEX(Inputs!$D$4:$AG$100,0,MATCH(I$2,Inputs!$D$2:$AG$2,0)),Inputs!$B$4:$B$100,$B15)/1000) | J15: =IF(J$3=0,"",SUMIFS(INDEX(Inputs!$D$4:$AG$100,0,MATCH(J$2,Inputs!$D$2:$AG$2,0)),Inputs!$B$4:$B$100,$B15)/1000) | K15: =IF(K$3=0,"",SUMIFS(INDEX(Inputs!$D$4:$AG$100,0,MATCH(K$2,Inputs!$D$2:$AG$2,0)),Inputs!$B$4:$B$100,$B15)/1000) | L15: =IF(L$3=0,"",SUMIFS(INDEX(Inputs!$D$4:$AG$100,0,MATCH(L$2,Inputs!$D$2:$AG$2,0)),Inputs!$B$4:$B$100,$B15)/1000) | M15: =IF(L15="","",L15) | N15: =IF(N$3=0,"",SUMIFS(INDEX(Inputs!$D$4:$AG$100,0,MATCH(N$2,Inputs!$D$2:$AG$2,0)),Inputs!$B$4:$B$100,$B15)/1000) | O15: =IF(O$3=0,"",SUMIFS(INDEX(Inputs!$D$4:$AG$100,0,MATCH(O$2,Inputs!$D$2:$AG$2,0)),Inputs!$B$4:$B$100,$B15)/1000) | P15: =IF(P$3=0,"",SUMIFS(INDEX(Inputs!$D$4:$AG$100,0,MATCH(P$2,Inputs!$D$2:$AG$2,0)),Inputs!$B$4:$B$100,$B15)/1000) | Q15: =IF(Q$3=0,"",SUMIFS(INDEX(Inputs!$D$4:$AG$100,0,MATCH(Q$2,Inputs!$D$2:$AG$2,0)),Inputs!$B$4:$B$100,$B15)/1000) | R15: =IF(Q15="","",Q15) | S15: =IF(S$3=0,"",SUMIFS(INDEX(Inputs!$D$4:$AG$100,0,MATCH(S$2,Inputs!$D$2:$AG$2,0)),Inputs!$B$4:$B$100,$B15)/1000) | T15: =IF(T$3=0,"",SUMIFS(INDEX(Inputs!$D$4:$AG$100,0,MATCH(T$2,Inputs!$D$2:$AG$2,0)),Inputs!$B$4:$B$100,$B15)/1000) | U15: =IF(U$3=0,"",SUMIFS(INDEX(Inputs!$D$4:$AG$100,0,MATCH(U$2,Inputs!$D$2:$AG$2,0)),Inputs!$B$4:$B$100,$B15)/1000) | V15: =IF(V$3=0,"",SUMIFS(INDEX(Inputs!$D$4:$AG$100,0,MATCH(V$2,Inputs!$D$2:$AG$2,0)),Inputs!$B$4:$B$100,$B15)/1000) | W15: =IF(V15="","",V15) | X15: =IF(X$3=0,"",SUMIFS(INDEX(Inputs!$D$4:$AG$100,0,MATCH(X$2,Inputs!$D$2:$AG$2,0)),Inputs!$B$4:$B$100,$B15)/1000) | Y15: =IF(Y$3=0,"",SUMIFS(INDEX(Inputs!$D$4:$AG$100,0,MATCH(Y$2,Inputs!$D$2:$AG$2,0)),Inputs!$B$4:$B$100,$B15)/1000) | Z15: =IF(Z$3=0,"",SUMIFS(INDEX(Inputs!$D$4:$AG$100,0,MATCH(Z$2,Inputs!$D$2:$AG$2,0)),Inputs!$B$4:$B$100,$B15)/1000) | AA15: =IF(AA$3=0,"",SUMIFS(INDEX(Inputs!$D$4:$AG$100,0,MATCH(AA$2,Inputs!$D$2:$AG$2,0)),Inputs!$B$4:$B$100,$B15)/1000) | AB15: =IF(AA15="","",AA15) | AC15: =IF(AC$3=0,"",SUMIFS(INDEX(Inputs!$D$4:$AG$100,0,MATCH(AC$2,Inputs!$D$2:$AG$2,0)),Inputs!$B$4:$B$100,$B15)/1000) | AD15: =IF(AD$3=0,"",SUMIFS(INDEX(Inputs!$D$4:$AG$100,0,MATCH(AD$2,Inputs!$D$2:$AG$2,0)),Inputs!$B$4:$B$100,$B15)/1000) | AE15: =IF(AE$3=0,"",SUMIFS(INDEX(Inputs!$D$4:$AG$100,0,MATCH(AE$2,Inputs!$D$2:$AG$2,0)),Inputs!$B$4:$B$100,$B15)/1000) | AF15: =IF(AF$3=0,"",SUMIFS(INDEX(Inputs!$D$4:$AG$100,0,MATCH(AF$2,Inputs!$D$2:$AG$2,0)),Inputs!$B$4:$B$100,$B15)/1000) | AG15: =IF(AF15="","",AF15)
B16: 12 | C16: Accounts receivable | D16: =IF(D$3=0,"",SUMIFS(INDEX(Inputs!$D$4:$AG$100,0,MATCH(D$2,Inputs!$D$2:$AG$2,0)),Inputs!$B$4:$B$100,$B16)/1000) | E16: =IF(E$3=0,"",SUMIFS(INDEX(Inputs!$D$4:$AG$100,0,MATCH(E$2,Inputs!$D$2:$AG$2,0)),Inputs!$B$4:$B$100,$B16)/1000) | F16: =IF(F$3=0,"",SUMIFS(INDEX(Inputs!$D$4:$AG$100,0,MATCH(F$2,Inputs!$D$2:$AG$2,0)),Inputs!$B$4:$B$100,$B16)/1000) | G16: =IF(G$3=0,"",SUMIFS(INDEX(Inputs!$D$4:$AG$100,0,MATCH(G$2,Inputs!$D$2:$AG$2,0)),Inputs!$B$4:$B$100,$B16)/1000) | H16: =IF(G16="","",G16) | I16: =IF(I$3=0,"",SUMIFS(INDEX(Inputs!$D$4:$AG$100,0,MATCH(I$2,Inputs!$D$2:$AG$2,0)),Inputs!$B$4:$B$100,$B16)/1000) | J16: =IF(J$3=0,"",SUMIFS(INDEX(Inputs!$D$4:$AG$100,0,MATCH(J$2,Inputs!$D$2:$AG$2,0)),Inputs!$B$4:$B$100,$B16)/1000) | K16: =IF(K$3=0,"",SUMIFS(INDEX(Inputs!$D$4:$AG$100,0,MATCH(K$2,Inputs!$D$2:$AG$2,0)),Inputs!$B$4:$B$100,$B16)/1000) | L16: =IF(L$3=0,"",SUMIFS(INDEX(Inputs!$D$4:$AG$100,0,MATCH(L$2,Inputs!$D$2:$AG$2,0)),Inputs!$B$4:$B$100,$B16)/1000) | M16: =IF(L16="","",L16) | N16: =IF(N$3=0,"",SUMIFS(INDEX(Inputs!$D$4:$AG$100,0,MATCH(N$2,Inputs!$D$2:$AG$2,0)),Inputs!$B$4:$B$100,$B16)/1000) | O16: =IF(O$3=0,"",SUMIFS(INDEX(Inputs!$D$4:$AG$100,0,MATCH(O$2,Inputs!$D$2:$AG$2,0)),Inputs!$B$4:$B$100,$B16)/1000) | P16: =IF(P$3=0,"",SUMIFS(INDEX(Inputs!$D$4:$AG$100,0,MATCH(P$2,Inputs!$D$2:$AG$2,0)),Inputs!$B$4:$B$100,$B16)/1000) | Q16: =IF(Q$3=0,"",SUMIFS(INDEX(Inputs!$D$4:$AG$100,0,MATCH(Q$2,Inputs!$D$2:$AG$2,0)),Inputs!$B$4:$B$100,$B16)/1000) | R16: =IF(Q16="","",Q16) | S16: =IF(S$3=0,"",SUMIFS(INDEX(Inputs!$D$4:$AG$100,0,MATCH(S$2,Inputs!$D$2:$AG$2,0)),Inputs!$B$4:$B$100,$B16)/1000) | T16: =IF(T$3=0,"",SUMIFS(INDEX(Inputs!$D$4:$AG$100,0,MATCH(T$2,Inputs!$D$2:$AG$2,0)),Inputs!$B$4:$B$100,$B16)/1000) | U16: =IF(U$3=0,"",SUMIFS(INDEX(Inputs!$D$4:$AG$100,0,MATCH(U$2,Inputs!$D$2:$AG$2,0)),Inputs!$B$4:$B$100,$B16)/1000) | V16: =IF(V$3=0,"",SUMIFS(INDEX(Inputs!$D$4:$AG$100,0,MATCH(V$2,Inputs!$D$2:$AG$2,0)),Inputs!$B$4:$B$100,$B16)/1000) | W16: =IF(V16="","",V16) | X16: =IF(X$3=0,"",SUMIFS(INDEX(Inputs!$D$4:$AG$100,0,MATCH(X$2,Inputs!$D$2:$AG$2,0)),Inputs!$B$4:$B$100,$B16)/1000) | Y16: =IF(Y$3=0,"",SUMIFS(INDEX(Inputs!$D$4:$AG$100,0,MATCH(Y$2,Inputs!$D$2:$AG$2,0)),Inputs!$B$4:$B$100,$B16)/1000) | Z16: =IF(Z$3=0,"",SUMIFS(INDEX(Inputs!$D$4:$AG$100,0,MATCH(Z$2,Inputs!$D$2:$AG$2,0)),Inputs!$B$4:$B$100,$B16)/1000) | AA16: =IF(AA$3=0,"",SUMIFS(INDEX(Inputs!$D$4:$AG$100,0,MATCH(AA$2,Inputs!$D$2:$AG$2,0)),Inputs!$B$4:$B$100,$B16)/1000) | AB16: =IF(AA16="","",AA16) | AC16: =IF(AC$3=0,"",SUMIFS(INDEX(Inputs!$D$4:$AG$100,0,MATCH(AC$2,Inputs!$D$2:$AG$2,0)),Inputs!$B$4:$B$100,$B16)/1000) | AD16: =IF(AD$3=0,"",SUMIFS(INDEX(Inputs!$D$4:$AG$100,0,MATCH(AD$2,Inputs!$D$2:$AG$2,0)),Inputs!$B$4:$B$100,$B16)/1000) | AE16: =IF(AE$3=0,"",SUMIFS(INDEX(Inputs!$D$4:$AG$100,0,MATCH(AE$2,Inputs!$D$2:$AG$2,0)),Inputs!$B$4:$B$100,$B16)/1000) | AF16: =IF(AF$3=0,"",SUMIFS(INDEX(Inputs!$D$4:$AG$100,0,MATCH(AF$2,Inputs!$D$2:$AG$2,0)),Inputs!$B$4:$B$100,$B16)/1000) | AG16: =IF(AF16="","",AF16)
B17: 13 | C17: Inventories | D17: =IF(D$3=0,"",SUMIFS(INDEX(Inputs!$D$4:$AG$100,0,MATCH(D$2,Inputs!$D$2:$AG$2,0)),Inputs!$B$4:$B$100,$B17)/1000) | E17: =IF(E$3=0,"",SUMIFS(INDEX(Inputs!$D$4:$AG$100,0,MATCH(E$2,Inputs!$D$2:$AG$2,0)),Inputs!$B$4:$B$100,$B17)/1000) | F17: =IF(F$3=0,"",SUMIFS(INDEX(Inputs!$D$4:$AG$100,0,MATCH(F$2,Inputs!$D$2:$AG$2,0)),Inputs!$B$4:$B$100,$B17)/1000) | G17: =IF(G$3=0,"",SUMIFS(INDEX(Inputs!$D$4:$AG$100,0,MATCH(G$2,Inputs!$D$2:$AG$2,0)),Inputs!$B$4:$B$100,$B17)/1000) | H17: =IF(G17="","",G17) | I17: =IF(I$3=0,"",SUMIFS(INDEX(Inputs!$D$4:$AG$100,0,MATCH(I$2,Inputs!$D$2:$AG$2,0)),Inputs!$B$4:$B$100,$B17)/1000) | J17: =IF(J$3=0,"",SUMIFS(INDEX(Inputs!$D$4:$AG$100,0,MATCH(J$2,Inputs!$D$2:$AG$2,0)),Inputs!$B$4:$B$100,$B17)/1000) | K17: =IF(K$3=0,"",SUMIFS(INDEX(Inputs!$D$4:$AG$100,0,MATCH(K$2,Inputs!$D$2:$AG$2,0)),Inputs!$B$4:$B$100,$B17)/1000) | L17: =IF(L$3=0,"",SUMIFS(INDEX(Inputs!$D$4:$AG$100,0,MATCH(L$2,Inputs!$D$2:$AG$2,0)),Inputs!$B$4:$B$100,$B17)/1000) | M17: =IF(L17="","",L17) | N17: =IF(N$3=0,"",SUMIFS(INDEX(Inputs!$D$4:$AG$100,0,MATCH(N$2,Inputs!$D$2:$AG$2,0)),Inputs!$B$4:$B$100,$B17)/1000) | O17: =IF(O$3=0,"",SUMIFS(INDEX(Inputs!$D$4:$AG$100,0,MATCH(O$2,Inputs!$D$2:$AG$2,0)),Inputs!$B$4:$B$100,$B17)/1000) | P17: =IF(P$3=0,"",SUMIFS(INDEX(Inputs!$D$4:$AG$100,0,MATCH(P$2,Inputs!$D$2:$AG$2,0)),Inputs!$B$4:$B$100,$B17)/1000) | Q17: =IF(Q$3=0,"",SUMIFS(INDEX(Inputs!$D$4:$AG$100,0,MATCH(Q$2,Inputs!$D$2:$AG$2,0)),Inputs!$B$4:$B$100,$B17)/1000) | R17: =IF(Q17="","",Q17) | S17: =IF(S$3=0,"",SUMIFS(INDEX(Inputs!$D$4:$AG$100,0,MATCH(S$2,Inputs!$D$2:$AG$2,0)),Inputs!$B$4:$B$100,$B17)/1000) | T17: =IF(T$3=0,"",SUMIFS(INDEX(Inputs!$D$4:$AG$100,0,MATCH(T$2,Inputs!$D$2:$AG$2,0)),Inputs!$B$4:$B$100,$B17)/1000) | U17: =IF(U$3=0,"",SUMIFS(INDEX(Inputs!$D$4:$AG$100,0,MATCH(U$2,Inputs!$D$2:$AG$2,0)),Inputs!$B$4:$B$100,$B17)/1000) | V17: =IF(V$3=0,"",SUMIFS(INDEX(Inputs!$D$4:$AG$100,0,MATCH(V$2,Inputs!$D$2:$AG$2,0)),Inputs!$B$4:$B$100,$B17)/1000) | W17: =IF(V17="","",V17) | X17: =IF(X$3=0,"",SUMIFS(INDEX(Inputs!$D$4:$AG$100,0,MATCH(X$2,Inputs!$D$2:$AG$2,0)),Inputs!$B$4:$B$100,$B17)/1000) | Y17: =IF(Y$3=0,"",SUMIFS(INDEX(Inputs!$D$4:$AG$100,0,MATCH(Y$2,Inputs!$D$2:$AG$2,0)),Inputs!$B$4:$B$100,$B17)/1000) | Z17: =IF(Z$3=0,"",SUMIFS(INDEX(Inputs!$D$4:$AG$100,0,MATCH(Z$2,Inputs!$D$2:$AG$2,0)),Inputs!$B$4:$B$100,$B17)/1000) | AA17: =IF(AA$3=0,"",SUMIFS(INDEX(Inputs!$D$4:$AG$100,0,MATCH(AA$2,Inputs!$D$2:$AG$2,0)),Inputs!$B$4:$B$100,$B17)/1000) | AB17: =IF(AA17="","",AA17) | AC17: =IF(AC$3=0,"",SUMIFS(INDEX(Inputs!$D$4:$AG$100,0,MATCH(AC$2,Inputs!$D$2:$AG$2,0)),Inputs!$B$4:$B$100,$B17)/1000) | AD17: =IF(AD$3=0,"",SUMIFS(INDEX(Inputs!$D$4:$AG$100,0,MATCH(AD$2,Inputs!$D$2:$AG$2,0)),Inputs!$B$4:$B$100,$B17)/1000) | AE17: =IF(AE$3=0,"",SUMIFS(INDEX(Inputs!$D$4:$AG$100,0,MATCH(AE$2,Inputs!$D$2:$AG$2,0)),Inputs!$B$4:$B$100,$B17)/1000) | AF17: =IF(AF$3=0,"",SUMIFS(INDEX(Inputs!$D$4:$AG$100,0,MATCH(AF$2,Inputs!$D$2:$AG$2,0)),Inputs!$B$4:$B$100,$B17)/1000) | AG17: =IF(AF17="","",AF17)
B18: 14 | C18: Deferred income taxes | D18: =IF(D$3=0,"",SUMIFS(INDEX(Inputs!$D$4:$AG$100,0,MATCH(D$2,Inputs!$D$2:$AG$2,0)),Inputs!$B$4:$B$100,$B18)/1000) | E18: =IF(E$3=0,"",SUMIFS(INDEX(Inputs!$D$4:$AG$100,0,MATCH(E$2,Inputs!$D$2:$AG$2,0)),Inputs!$B$4:$B$100,$B18)/1000) | F18: =IF(F$3=0,"",SUMIFS(INDEX(Inputs!$D$4:$AG$100,0,MATCH(F$2,Inputs!$D$2:$AG$2,0)),Inputs!$B$4:$B$100,$B18)/1000) | G18: =IF(G$3=0,"",SUMIFS(INDEX(Inputs!$D$4:$AG$100,0,MATCH(G$2,Inputs!$D$2:$AG$2,0)),Inputs!$B$4:$B$100,$B18)/1000) | H18: =IF(G18="","",G18) | I18: =IF(I$3=0,"",SUMIFS(INDEX(Inputs!$D$4:$AG$100,0,MATCH(I$2,Inputs!$D$2:$AG$2,0)),Inputs!$B$4:$B$100,$B18)/1000) | J18: =IF(J$3=0,"",SUMIFS(INDEX(Inputs!$D$4:$AG$100,0,MATCH(J$2,Inputs!$D$2:$AG$2,0)),Inputs!$B$4:$B$100,$B18)/1000) | K18: =IF(K$3=0,"",SUMIFS(INDEX(Inputs!$D$4:$AG$100,0,MATCH(K$2,Inputs!$D$2:$AG$2,0)),Inputs!$B$4:$B$100,$B18)/1000) | L18: =IF(L$3=0,"",SUMIFS(INDEX(Inputs!$D$4:$AG$100,0,MATCH(L$2,Inputs!$D$2:$AG$2,0)),Inputs!$B$4:$B$100,$B18)/1000) | M18: =IF(L18="","",L18) | N18: =IF(N$3=0,"",SUMIFS(INDEX(Inputs!$D$4:$AG$100,0,MATCH(N$2,Inputs!$D$2:$AG$2,0)),Inputs!$B$4:$B$100,$B18)/1000) | O18: =IF(O$3=0,"",SUMIFS(INDEX(Inputs!$D$4:$AG$100,0,MATCH(O$2,Inputs!$D$2:$AG$2,0)),Inputs!$B$4:$B$100,$B18)/1000) | P18: =IF(P$3=0,"",SUMIFS(INDEX(Inputs!$D$4:$AG$100,0,MATCH(P$2,Inputs!$D$2:$AG$2,0)),Inputs!$B$4:$B$100,$B18)/1000) | Q18: =IF(Q$3=0,"",SUMIFS(INDEX(Inputs!$D$4:$AG$100,0,MATCH(Q$2,Inputs!$D$2:$AG$2,0)),Inputs!$B$4:$B$100,$B18)/1000) | R18: =IF(Q18="","",Q18) | S18: =IF(S$3=0,"",SUMIFS(INDEX(Inputs!$D$4:$AG$100,0,MATCH(S$2,Inputs!$D$2:$AG$2,0)),Inputs!$B$4:$B$100,$B18)/1000) | T18: =IF(T$3=0,"",SUMIFS(INDEX(Inputs!$D$4:$AG$100,0,MATCH(T$2,Inputs!$D$2:$AG$2,0)),Inputs!$B$4:$B$100,$B18)/1000) | U18: =IF(U$3=0,"",SUMIFS(INDEX(Inputs!$D$4:$AG$100,0,MATCH(U$2,Inputs!$D$2:$AG$2,0)),Inputs!$B$4:$B$100,$B18)/1000) | V18: =IF(V$3=0,"",SUMIFS(INDEX(Inputs!$D$4:$AG$100,0,MATCH(V$2,Inputs!$D$2:$AG$2,0)),Inputs!$B$4:$B$100,$B18)/1000) | W18: =IF(V18="","",V18) | X18: =IF(X$3=0,"",SUMIFS(INDEX(Inputs!$D$4:$AG$100,0,MATCH(X$2,Inputs!$D$2:$AG$2,0)),Inputs!$B$4:$B$100,$B18)/1000) | Y18: =IF(Y$3=0,"",SUMIFS(INDEX(Inputs!$D$4:$AG$100,0,MATCH(Y$2,Inputs!$D$2:$AG$2,0)),Inputs!$B$4:$B$100,$B18)/1000) | Z18: =IF(Z$3=0,"",SUMIFS(INDEX(Inputs!$D$4:$AG$100,0,MATCH(Z$2,Inputs!$D$2:$AG$2,0)),Inputs!$B$4:$B$100,$B18)/1000) | AA18: =IF(AA$3=0,"",SUMIFS(INDEX(Inputs!$D$4:$AG$100,0,MATCH(AA$2,Inputs!$D$2:$AG$2,0)),Inputs!$B$4:$B$100,$B18)/1000) | AB18: =IF(AA18="","",AA18) | AC18: =IF(AC$3=0,"",SUMIFS(INDEX(Inputs!$D$4:$AG$100,0,MATCH(AC$2,Inputs!$D$2:$AG$2,0)),Inputs!$B$4:$B$100,$B18)/1000) | AD18: =IF(AD$3=0,"",SUMIFS(INDEX(Inputs!$D$4:$AG$100,0,MATCH(AD$2,Inputs!$D$2:$AG$2,0)),Inputs!$B$4:$B$100,$B18)/1000) | AE18: =IF(AE$3=0,"",SUMIFS(INDEX(Inputs!$D$4:$AG$100,0,MATCH(AE$2,Inputs!$D$2:$AG$2,0)),Inputs!$B$4:$B$100,$B18)/1000) | AF18: =IF(AF$3=0,"",SUMIFS(INDEX(Inputs!$D$4:$AG$100,0,MATCH(AF$2,Inputs!$D$2:$AG$2,0)),Inputs!$B$4:$B$100,$B18)/1000) | AG18: =IF(AF18="","",AF18)
B19: 15 | C19: Prepaid expenses | D19: =IF(D$3=0,"",SUMIFS(INDEX(Inputs!$D$4:$AG$100,0,MATCH(D$2,Inputs!$D$2:$AG$2,0)),Inputs!$B$4:$B$100,$B19)/1000) | E19: =IF(E$3=0,"",SUMIFS(INDEX(Inputs!$D$4:$AG$100,0,MATCH(E$2,Inputs!$D$2:$AG$2,0)),Inputs!$B$4:$B$100,$B19)/1000) | F19: =IF(F$3=0,"",SUMIFS(INDEX(Inputs!$D$4:$AG$100,0,MATCH(F$2,Inputs!$D$2:$AG$2,0)),Inputs!$B$4:$B$100,$B19)/1000) | G19: =IF(G$3=0,"",SUMIFS(INDEX(Inputs!$D$4:$AG$100,0,MATCH(G$2,Inputs!$D$2:$AG$2,0)),Inputs!$B$4:$B$100,$B19)/1000) | H19: =IF(G19="","",G19) | I19: =IF(I$3=0,"",SUMIFS(INDEX(Inputs!$D$4:$AG$100,0,MATCH(I$2,Inputs!$D$2:$AG$2,0)),Inputs!$B$4:$B$100,$B19)/1000) | J19: =IF(J$3=0,"",SUMIFS(INDEX(Inputs!$D$4:$AG$100,0,MATCH(J$2,Inputs!$D$2:$AG$2,0)),Inputs!$B$4:$B$100,$B19)/1000) | K19: =IF(K$3=0,"",SUMIFS(INDEX(Inputs!$D$4:$AG$100,0,MATCH(K$2,Inputs!$D$2:$AG$2,0)),Inputs!$B$4:$B$100,$B19)/1000) | L19: =IF(L$3=0,"",SUMIFS(INDEX(Inputs!$D$4:$AG$100,0,MATCH(L$2,Inputs!$D$2:$AG$2,0)),Inputs!$B$4:$B$100,$B19)/1000) | M19: =IF(L19="","",L19) | N19: =IF(N$3=0,"",SUMIFS(INDEX(Inputs!$D$4:$AG$100,0,MATCH(N$2,Inputs!$D$2:$AG$2,0)),Inputs!$B$4:$B$100,$B19)/1000) | O19: =IF(O$3=0,"",SUMIFS(INDEX(Inputs!$D$4:$AG$100,0,MATCH(O$2,Inputs!$D$2:$AG$2,0)),Inputs!$B$4:$B$100,$B19)/1000) | P19: =IF(P$3=0,"",SUMIFS(INDEX(Inputs!$D$4:$AG$100,0,MATCH(P$2,Inputs!$D$2:$AG$2,0)),Inputs!$B$4:$B$100,$B19)/1000) | Q19: =IF(Q$3=0,"",SUMIFS(INDEX(Inputs!$D$4:$AG$100,0,MATCH(Q$2,Inputs!$D$2:$AG$2,0)),Inputs!$B$4:$B$100,$B19)/1000) | R19: =IF(Q19="","",Q19) | S19: =IF(S$3=0,"",SUMIFS(INDEX(Inputs!$D$4:$AG$100,0,MATCH(S$2,Inputs!$D$2:$AG$2,0)),Inputs!$B$4:$B$100,$B19)/1000) | T19: =IF(T$3=0,"",SUMIFS(INDEX(Inputs!$D$4:$AG$100,0,MATCH(T$2,Inputs!$D$2:$AG$2,0)),Inputs!$B$4:$B$100,$B19)/1000) | U19: =IF(U$3=0,"",SUMIFS(INDEX(Inputs!$D$4:$AG$100,0,MATCH(U$2,Inputs!$D$2:$AG$2,0)),Inputs!$B$4:$B$100,$B19)/1000) | V19: =IF(V$3=0,"",SUMIFS(INDEX(Inputs!$D$4:$AG$100,0,MATCH(V$2,Inputs!$D$2:$AG$2,0)),Inputs!$B$4:$B$100,$B19)/1000) | W19: =IF(V19="","",V19) | X19: =IF(X$3=0,"",SUMIFS(INDEX(Inputs!$D$4:$AG$100,0,MATCH(X$2,Inputs!$D$2:$AG$2,0)),Inputs!$B$4:$B$100,$B19)/1000) | Y19: =IF(Y$3=0,"",SUMIFS(INDEX(Inputs!$D$4:$AG$100,0,MATCH(Y$2,Inputs!$D$2:$AG$2,0)),Inputs!$B$4:$B$100,$B19)/1000) | Z19: =IF(Z$3=0,"",SUMIFS(INDEX(Inputs!$D$4:$AG$100,0,MATCH(Z$2,Inputs!$D$2:$AG$2,0)),Inputs!$B$4:$B$100,$B19)/1000) | AA19: =IF(AA$3=0,"",SUMIFS(INDEX(Inputs!$D$4:$AG$100,0,MATCH(AA$2,Inputs!$D$2:$AG$2,0)),Inputs!$B$4:$B$100,$B19)/1000) | AB19: =IF(AA19="","",AA19) | AC19: =IF(AC$3=0,"",SUMIFS(INDEX(Inputs!$D$4:$AG$100,0,MATCH(AC$2,Inputs!$D$2:$AG$2,0)),Inputs!$B$4:$B$100,$B19)/1000) | AD19: =IF(AD$3=0,"",SUMIFS(INDEX(Inputs!$D$4:$AG$100,0,MATCH(AD$2,Inputs!$D$2:$AG$2,0)),Inputs!$B$4:$B$100,$B19)/1000) | AE19: =IF(AE$3=0,"",SUMIFS(INDEX(Inputs!$D$4:$AG$100,0,MATCH(AE$2,Inputs!$D$2:$AG$2,0)),Inputs!$B$4:$B$100,$B19)/1000) | AF19: =IF(AF$3=0,"",SUMIFS(INDEX(Inputs!$D$4:$AG$100,0,MATCH(AF$2,Inputs!$D$2:$AG$2,0)),Inputs!$B$4:$B$100,$B19)/1000) | AG19: =IF(AF19="","",AF19)
B20: 16 | C20: Other current assets | D20: =IF(D$3=0,"",SUMIFS(INDEX(Inputs!$D$4:$AG$100,0,MATCH(D$2,Inputs!$D$2:$AG$2,0)),Inputs!$B$4:$B$100,$B20)/1000) | E20: =IF(E$3=0,"",SUMIFS(INDEX(Inputs!$D$4:$AG$100,0,MATCH(E$2,Inputs!$D$2:$AG$2,0)),Inputs!$B$4:$B$100,$B20)/1000) | F20: =IF(F$3=0,"",SUMIFS(INDEX(Inputs!$D$4:$AG$100,0,MATCH(F$2,Inputs!$D$2:$AG$2,0)),Inputs!$B$4:$B$100,$B20)/1000) | G20: =IF(G$3=0,"",SUMIFS(INDEX(Inputs!$D$4:$AG$100,0,MATCH(G$2,Inputs!$D$2:$AG$2,0)),Inputs!$B$4:$B$100,$B20)/1000) | H20: =IF(G20="","",G20) | I20: =IF(I$3=0,"",SUMIFS(INDEX(Inputs!$D$4:$AG$100,0,MATCH(I$2,Inputs!$D$2:$AG$2,0)),Inputs!$B$4:$B$100,$B20)/1000) | J20: =IF(J$3=0,"",SUMIFS(INDEX(Inputs!$D$4:$AG$100,0,MATCH(J$2,Inputs!$D$2:$AG$2,0)),Inputs!$B$4:$B$100,$B20)/1000) | K20: =IF(K$3=0,"",SUMIFS(INDEX(Inputs!$D$4:$AG$100,0,MATCH(K$2,Inputs!$D$2:$AG$2,0)),Inputs!$B$4:$B$100,$B20)/1000) | L20: =IF(L$3=0,"",SUMIFS(INDEX(Inputs!$D$4:$AG$100,0,MATCH(L$2,Inputs!$D$2:$AG$2,0)),Inputs!$B$4:$B$100,$B20)/1000) | M20: =IF(L20="","",L20) | N20: =IF(N$3=0,"",SUMIFS(INDEX(Inputs!$D$4:$AG$100,0,MATCH(N$2,Inputs!$D$2:$AG$2,0)),Inputs!$B$4:$B$100,$B20)/1000) | O20: =IF(O$3=0,"",SUMIFS(INDEX(Inputs!$D$4:$AG$100,0,MATCH(O$2,Inputs!$D$2:$AG$2,0)),Inputs!$B$4:$B$100,$B20)/1000) | P20: =IF(P$3=0,"",SUMIFS(INDEX(Inputs!$D$4:$AG$100,0,MATCH(P$2,Inputs!$D$2:$AG$2,0)),Inputs!$B$4:$B$100,$B20)/1000) | Q20: =IF(Q$3=0,"",SUMIFS(INDEX(Inputs!$D$4:$AG$100,0,MATCH(Q$2,Inputs!$D$2:$AG$2,0)),Inputs!$B$4:$B$100,$B20)/1000) | R20: =IF(Q20="","",Q20) | S20: =IF(S$3=0,"",SUMIFS(INDEX(Inputs!$D$4:$AG$100,0,MATCH(S$2,Inputs!$D$2:$AG$2,0)),Inputs!$B$4:$B$100,$B20)/1000) | T20: =IF(T$3=0,"",SUMIFS(INDEX(Inputs!$D$4:$AG$100,0,MATCH(T$2,Inputs!$D$2:$AG$2,0)),Inputs!$B$4:$B$100,$B20)/1000) | U20: =IF(U$3=0,"",SUMIFS(INDEX(Inputs!$D$4:$AG$100,0,MATCH(U$2,Inputs!$D$2:$AG$2,0)),Inputs!$B$4:$B$100,$B20)/1000) | V20: =IF(V$3=0,"",SUMIFS(INDEX(Inputs!$D$4:$AG$100,0,MATCH(V$2,Inputs!$D$2:$AG$2,0)),Inputs!$B$4:$B$100,$B20)/1000) | W20: =IF(V20="","",V20) | X20: =IF(X$3=0,"",SUMIFS(INDEX(Inputs!$D$4:$AG$100,0,MATCH(X$2,Inputs!$D$2:$AG$2,0)),Inputs!$B$4:$B$100,$B20)/1000) | Y20: =IF(Y$3=0,"",SUMIFS(INDEX(Inputs!$D$4:$AG$100,0,MATCH(Y$2,Inputs!$D$2:$AG$2,0)),Inputs!$B$4:$B$100,$B20)/1000) | Z20: =IF(Z$3=0,"",SUMIFS(INDEX(Inputs!$D$4:$AG$100,0,MATCH(Z$2,Inputs!$D$2:$AG$2,0)),Inputs!$B$4:$B$100,$B20)/1000) | AA20: =IF(AA$3=0,"",SUMIFS(INDEX(Inputs!$D$4:$AG$100,0,MATCH(AA$2,Inputs!$D$2:$AG$2,0)),Inputs!$B$4:$B$100,$B20)/1000) | AB20: =IF(AA20="","",AA20) | AC20: =IF(AC$3=0,"",SUMIFS(INDEX(Inputs!$D$4:$AG$100,0,MATCH(AC$2,Inputs!$D$2:$AG$2,0)),Inputs!$B$4:$B$100,$B20)/1000) | AD20: =IF(AD$3=0,"",SUMIFS(INDEX(Inputs!$D$4:$AG$100,0,MATCH(AD$2,Inputs!$D$2:$AG$2,0)),Inputs!$B$4:$B$100,$B20)/1000) | AE20: =IF(AE$3=0,"",SUMIFS(INDEX(Inputs!$D$4:$AG$100,0,MATCH(AE$2,Inputs!$D$2:$AG$2,0)),Inputs!$B$4:$B$100,$B20)/1000) | AF20: =IF(AF$3=0,"",SUMIFS(INDEX(Inputs!$D$4:$AG$100,0,MATCH(AF$2,Inputs!$D$2:$AG$2,0)),Inputs!$B$4:$B$100,$B20)/1000) | AG20: =IF(AF20="","",AF20)
B21: 17 | C21: Equity in affiliates | D21: =IF(D$3=0,"",SUMIFS(INDEX(Inputs!$D$4:$AG$100,0,MATCH(D$2,Inputs!$D$2:$AG$2,0)),Inputs!$B$4:$B$100,$B21)/1000) | E21: =IF(E$3=0,"",SUMIFS(INDEX(Inputs!$D$4:$AG$100,0,MATCH(E$2,Inputs!$D$2:$AG$2,0)),Inputs!$B$4:$B$100,$B21)/1000) | F21: =IF(F$3=0,"",SUMIFS(INDEX(Inputs!$D$4:$AG$100,0,MATCH(F$2,Inputs!$D$2:$AG$2,0)),Inputs!$B$4:$B$100,$B21)/1000) | G21: =IF(G$3=0,"",SUMIFS(INDEX(Inputs!$D$4:$AG$100,0,MATCH(G$2,Inputs!$D$2:$AG$2,0)),Inputs!$B$4:$B$100,$B21)/1000) | H21: =IF(G21="","",G21) | I21: =IF(I$3=0,"",SUMIFS(INDEX(Inputs!$D$4:$AG$100,0,MATCH(I$2,Inputs!$D$2:$AG$2,0)),Inputs!$B$4:$B$100,$B21)/1000) | J21: =IF(J$3=0,"",SUMIFS(INDEX(Inputs!$D$4:$AG$100,0,MATCH(J$2,Inputs!$D$2:$AG$2,0)),Inputs!$B$4:$B$100,$B21)/1000) | K21: =IF(K$3=0,"",SUMIFS(INDEX(Inputs!$D$4:$AG$100,0,MATCH(K$2,Inputs!$D$2:$AG$2,0)),Inputs!$B$4:$B$100,$B21)/1000) | L21: =IF(L$3=0,"",SUMIFS(INDEX(Inputs!$D$4:$AG$100,0,MATCH(L$2,Inputs!$D$2:$AG$2,0)),Inputs!$B$4:$B$100,$B21)/1000) | M21: =IF(L21="","",L21) | N21: =IF(N$3=0,"",SUMIFS(INDEX(Inputs!$D$4:$AG$100,0,MATCH(N$2,Inputs!$D$2:$AG$2,0)),Inputs!$B$4:$B$100,$B21)/1000) | O21: =IF(O$3=0,"",SUMIFS(INDEX(Inputs!$D$4:$AG$100,0,MATCH(O$2,Inputs!$D$2:$AG$2,0)),Inputs!$B$4:$B$100,$B21)/1000) | P21: =IF(P$3=0,"",SUMIFS(INDEX(Inputs!$D$4:$AG$100,0,MATCH(P$2,Inputs!$D$2:$AG$2,0)),Inputs!$B$4:$B$100,$B21)/1000) | Q21: =IF(Q$3=0,"",SUMIFS(INDEX(Inputs!$D$4:$AG$100,0,MATCH(Q$2,Inputs!$D$2:$AG$2,0)),Inputs!$B$4:$B$100,$B21)/1000) | R21: =IF(Q21="","",Q21) | S21: =IF(S$3=0,"",SUMIFS(INDEX(Inputs!$D$4:$AG$100,0,MATCH(S$2,Inputs!$D$2:$AG$2,0)),Inputs!$B$4:$B$100,$B21)/1000) | T21: =IF(T$3=0,"",SUMIFS(INDEX(Inputs!$D$4:$AG$100,0,MATCH(T$2,Inputs!$D$2:$AG$2,0)),Inputs!$B$4:$B$100,$B21)/1000) | U21: =IF(U$3=0,"",SUMIFS(INDEX(Inputs!$D$4:$AG$100,0,MATCH(U$2,Inputs!$D$2:$AG$2,0)),Inputs!$B$4:$B$100,$B21)/1000) | V21: =IF(V$3=0,"",SUMIFS(INDEX(Inputs!$D$4:$AG$100,0,MATCH(V$2,Inputs!$D$2:$AG$2,0)),Inputs!$B$4:$B$100,$B21)/1000) | W21: =IF(V21="","",V21) | X21: =IF(X$3=0,"",SUMIFS(INDEX(Inputs!$D$4:$AG$100,0,MATCH(X$2,Inputs!$D$2:$AG$2,0)),Inputs!$B$4:$B$100,$B21)/1000) | Y21: =IF(Y$3=0,"",SUMIFS(INDEX(Inputs!$D$4:$AG$100,0,MATCH(Y$2,Inputs!$D$2:$AG$2,0)),Inputs!$B$4:$B$100,$B21)/1000) | Z21: =IF(Z$3=0,"",SUMIFS(INDEX(Inputs!$D$4:$AG$100,0,MATCH(Z$2,Inputs!$D$2:$AG$2,0)),Inputs!$B$4:$B$100,$B21)/1000) | AA21: =IF(AA$3=0,"",SUMIFS(INDEX(Inputs!$D$4:$AG$100,0,MATCH(AA$2,Inputs!$D$2:$AG$2,0)),Inputs!$B$4:$B$100,$B21)/1000) | AB21: =IF(AA21="","",AA21) | AC21: =IF(AC$3=0,"",SUMIFS(INDEX(Inputs!$D$4:$AG$100,0,MATCH(AC$2,Inputs!$D$2:$AG$2,0)),Inputs!$B$4:$B$100,$B21)/1000) | AD21: =IF(AD$3=0,"",SUMIFS(INDEX(Inputs!$D$4:$AG$100,0,MATCH(AD$2,Inputs!$D$2:$AG$2,0)),Inputs!$B$4:$B$100,$B21)/1000) | AE21: =IF(AE$3=0,"",SUMIFS(INDEX(Inputs!$D$4:$AG$100,0,MATCH(AE$2,Inputs!$D$2:$AG$2,0)),Inputs!$B$4:$B$100,$B21)/1000) | AF21: =IF(AF$3=0,"",SUMIFS(INDEX(Inputs!$D$4:$AG$100,0,MATCH(AF$2,Inputs!$D$2:$AG$2,0)),Inputs!$B$4:$B$100,$B21)/1000) | AG21: =IF(AF21="","",AF21)
B22: 18 | C22: PP&E | D22: =IF(D$3=0,"",SUMIFS(INDEX(Inputs!$D$4:$AG$100,0,MATCH(D$2,Inputs!$D$2:$AG$2,0)),Inputs!$B$4:$B$100,$B22)/1000) | E22: =IF(E$3=0,"",SUMIFS(INDEX(Inputs!$D$4:$AG$100,0,MATCH(E$2,Inputs!$D$2:$AG$2,0)),Inputs!$B$4:$B$100,$B22)/1000) | F22: =IF(F$3=0,"",SUMIFS(INDEX(Inputs!$D$4:$AG$100,0,MATCH(F$2,Inputs!$D$2:$AG$2,0)),Inputs!$B$4:$B$100,$B22)/1000) | G22: =IF(G$3=0,"",SUMIFS(INDEX(Inputs!$D$4:$AG$100,0,MATCH(G$2,Inputs!$D$2:$AG$2,0)),Inputs!$B$4:$B$100,$B22)/1000) | H22: =IF(G22="","",G22) | I22: =IF(I$3=0,"",SUMIFS(INDEX(Inputs!$D$4:$AG$100,0,MATCH(I$2,Inputs!$D$2:$AG$2,0)),Inputs!$B$4:$B$100,$B22)/1000) | J22: =IF(J$3=0,"",SUMIFS(INDEX(Inputs!$D$4:$AG$100,0,MATCH(J$2,Inputs!$D$2:$AG$2,0)),Inputs!$B$4:$B$100,$B22)/1000) | K22: =IF(K$3=0,"",SUMIFS(INDEX(Inputs!$D$4:$AG$100,0,MATCH(K$2,Inputs!$D$2:$AG$2,0)),Inputs!$B$4:$B$100,$B22)/1000) | L22: =IF(L$3=0,"",SUMIFS(INDEX(Inputs!$D$4:$AG$100,0,MATCH(L$2,Inputs!$D$2:$AG$2,0)),Inputs!$B$4:$B$100,$B22)/1000) | M22: =IF(L22="","",L22) | N22: =IF(N$3=0,"",SUMIFS(INDEX(Inputs!$D$4:$AG$100,0,MATCH(N$2,Inputs!$D$2:$AG$2,0)),Inputs!$B$4:$B$100,$B22)/1000) | O22: =IF(O$3=0,"",SUMIFS(INDEX(Inputs!$D$4:$AG$100,0,MATCH(O$2,Inputs!$D$2:$AG$2,0)),Inputs!$B$4:$B$100,$B22)/1000) | P22: =IF(P$3=0,"",SUMIFS(INDEX(Inputs!$D$4:$AG$100,0,MATCH(P$2,Inputs!$D$2:$AG$2,0)),Inputs!$B$4:$B$100,$B22)/1000) | Q22: =IF(Q$3=0,"",SUMIFS(INDEX(Inputs!$D$4:$AG$100,0,MATCH(Q$2,Inputs!$D$2:$AG$2,0)),Inputs!$B$4:$B$100,$B22)/1000) | R22: =IF(Q22="","",Q22) | S22: =IF(S$3=0,"",SUMIFS(INDEX(Inputs!$D$4:$AG$100,0,MATCH(S$2,Inputs!$D$2:$AG$2,0)),Inputs!$B$4:$B$100,$B22)/1000) | T22: =IF(T$3=0,"",SUMIFS(INDEX(Inputs!$D$4:$AG$100,0,MATCH(T$2,Inputs!$D$2:$AG$2,0)),Inputs!$B$4:$B$100,$B22)/1000) | U22: =IF(U$3=0,"",SUMIFS(INDEX(Inputs!$D$4:$AG$100,0,MATCH(U$2,Inputs!$D$2:$AG$2,0)),Inputs!$B$4:$B$100,$B22)/1000) | V22: =IF(V$3=0,"",SUMIFS(INDEX(Inputs!$D$4:$AG$100,0,MATCH(V$2,Inputs!$D$2:$AG$2,0)),Inputs!$B$4:$B$100,$B22)/1000) | W22: =IF(V22="","",V22) | X22: =IF(X$3=0,"",SUMIFS(INDEX(Inputs!$D$4:$AG$100,0,MATCH(X$2,Inputs!$D$2:$AG$2,0)),Inputs!$B$4:$B$100,$B22)/1000) | Y22: =IF(Y$3=0,"",SUMIFS(INDEX(Inputs!$D$4:$AG$100,0,MATCH(Y$2,Inputs!$D$2:$AG$2,0)),Inputs!$B$4:$B$100,$B22)/1000) | Z22: =IF(Z$3=0,"",SUMIFS(INDEX(Inputs!$D$4:$AG$100,0,MATCH(Z$2,Inputs!$D$2:$AG$2,0)),Inputs!$B$4:$B$100,$B22)/1000) | AA22: =IF(AA$3=0,"",SUMIFS(INDEX(Inputs!$D$4:$AG$100,0,MATCH(AA$2,Inputs!$D$2:$AG$2,0)),Inputs!$B$4:$B$100,$B22)/1000) | AB22: =IF(AA22="","",AA22) | AC22: =IF(AC$3=0,"",SUMIFS(INDEX(Inputs!$D$4:$AG$100,0,MATCH(AC$2,Inputs!$D$2:$AG$2,0)),Inputs!$B$4:$B$100,$B22)/1000) | AD22: =IF(AD$3=0,"",SUMIFS(INDEX(Inputs!$D$4:$AG$100,0,MATCH(AD$2,Inputs!$D$2:$AG$2,0)),Inputs!$B$4:$B$100,$B22)/1000) | AE22: =IF(AE$3=0,"",SUMIFS(INDEX(Inputs!$D$4:$AG$100,0,MATCH(AE$2,Inputs!$D$2:$AG$2,0)),Inputs!$B$4:$B$100,$B22)/1000) | AF22: =IF(AF$3=0,"",SUMIFS(INDEX(Inputs!$D$4:$AG$100,0,MATCH(AF$2,Inputs!$D$2:$AG$2,0)),Inputs!$B$4:$B$100,$B22)/1000) | AG22: =IF(AF22="","",AF22)
B23: 19 | C23: Right-of-use-assets | D23: =IF(D$3=0,"",SUMIFS(INDEX(Inputs!$D$4:$AG$100,0,MATCH(D$2,Inputs!$D$2:$AG$2,0)),Inputs!$B$4:$B$100,$B23)/1000) | E23: =IF(E$3=0,"",SUMIFS(INDEX(Inputs!$D$4:$AG$100,0,MATCH(E$2,Inputs!$D$2:$AG$2,0)),Inputs!$B$4:$B$100,$B23)/1000) | F23: =IF(F$3=0,"",SUMIFS(INDEX(Inputs!$D$4:$AG$100,0,MATCH(F$2,Inputs!$D$2:$AG$2,0)),Inputs!$B$4:$B$100,$B23)/1000) | G23: =IF(G$3=0,"",SUMIFS(INDEX(Inputs!$D$4:$AG$100,0,MATCH(G$2,Inputs!$D$2:$AG$2,0)),Inputs!$B$4:$B$100,$B23)/1000) | H23: =IF(G23="","",G23) | I23: =IF(I$3=0,"",SUMIFS(INDEX(Inputs!$D$4:$AG$100,0,MATCH(I$2,Inputs!$D$2:$AG$2,0)),Inputs!$B$4:$B$100,$B23)/1000) | J23: =IF(J$3=0,"",SUMIFS(INDEX(Inputs!$D$4:$AG$100,0,MATCH(J$2,Inputs!$D$2:$AG$2,0)),Inputs!$B$4:$B$100,$B23)/1000) | K23: =IF(K$3=0,"",SUMIFS(INDEX(Inputs!$D$4:$AG$100,0,MATCH(K$2,Inputs!$D$2:$AG$2,0)),Inputs!$B$4:$B$100,$B23)/1000) | L23: =IF(L$3=0,"",SUMIFS(INDEX(Inputs!$D$4:$AG$100,0,MATCH(L$2,Inputs!$D$2:$AG$2,0)),Inputs!$B$4:$B$100,$B23)/1000) | M23: =IF(L23="","",L23) | N23: =IF(N$3=0,"",SUMIFS(INDEX(Inputs!$D$4:$AG$100,0,MATCH(N$2,Inputs!$D$2:$AG$2,0)),Inputs!$B$4:$B$100,$B23)/1000) | O23: =IF(O$3=0,"",SUMIFS(INDEX(Inputs!$D$4:$AG$100,0,MATCH(O$2,Inputs!$D$2:$AG$2,0)),Inputs!$B$4:$B$100,$B23)/1000) | P23: =IF(P$3=0,"",SUMIFS(INDEX(Inputs!$D$4:$AG$100,0,MATCH(P$2,Inputs!$D$2:$AG$2,0)),Inputs!$B$4:$B$100,$B23)/1000) | Q23: =IF(Q$3=0,"",SUMIFS(INDEX(Inputs!$D$4:$AG$100,0,MATCH(Q$2,Inputs!$D$2:$AG$2,0)),Inputs!$B$4:$B$100,$B23)/1000) | R23: =IF(Q23="","",Q23) | S23: =IF(S$3=0,"",SUMIFS(INDEX(Inputs!$D$4:$AG$100,0,MATCH(S$2,Inputs!$D$2:$AG$2,0)),Inputs!$B$4:$B$100,$B23)/1000) | T23: =IF(T$3=0,"",SUMIFS(INDEX(Inputs!$D$4:$AG$100,0,MATCH(T$2,Inputs!$D$2:$AG$2,0)),Inputs!$B$4:$B$100,$B23)/1000) | U23: =IF(U$3=0,"",SUMIFS(INDEX(Inputs!$D$4:$AG$100,0,MATCH(U$2,Inputs!$D$2:$AG$2,0)),Inputs!$B$4:$B$100,$B23)/1000) | V23: =IF(V$3=0,"",SUMIFS(INDEX(Inputs!$D$4:$AG$100,0,MATCH(V$2,Inputs!$D$2:$AG$2,0)),Inputs!$B$4:$B$100,$B23)/1000) | W23: =IF(V23="","",V23) | X23: =IF(X$3=0,"",SUMIFS(INDEX(Inputs!$D$4:$AG$100,0,MATCH(X$2,Inputs!$D$2:$AG$2,0)),Inputs!$B$4:$B$100,$B23)/1000) | Y23: =IF(Y$3=0,"",SUMIFS(INDEX(Inputs!$D$4:$AG$100,0,MATCH(Y$2,Inputs!$D$2:$AG$2,0)),Inputs!$B$4:$B$100,$B23)/1000) | Z23: =IF(Z$3=0,"",SUMIFS(INDEX(Inputs!$D$4:$AG$100,0,MATCH(Z$2,Inputs!$D$2:$AG$2,0)),Inputs!$B$4:$B$100,$B23)/1000) | AA23: =IF(AA$3=0,"",SUMIFS(INDEX(Inputs!$D$4:$AG$100,0,MATCH(AA$2,Inputs!$D$2:$AG$2,0)),Inputs!$B$4:$B$100,$B23)/1000) | AB23: =IF(AA23="","",AA23) | AC23: =IF(AC$3=0,"",SUMIFS(INDEX(Inputs!$D$4:$AG$100,0,MATCH(AC$2,Inputs!$D$2:$AG$2,0)),Inputs!$B$4:$B$100,$B23)/1000) | AD23: =IF(AD$3=0,"",SUMIFS(INDEX(Inputs!$D$4:$AG$100,0,MATCH(AD$2,Inputs!$D$2:$AG$2,0)),Inputs!$B$4:$B$100,$B23)/1000) | AE23: =IF(AE$3=0,"",SUMIFS(INDEX(Inputs!$D$4:$AG$100,0,MATCH(AE$2,Inputs!$D$2:$AG$2,0)),Inputs!$B$4:$B$100,$B23)/1000) | AF23: =IF(AF$3=0,"",SUMIFS(INDEX(Inputs!$D$4:$AG$100,0,MATCH(AF$2,Inputs!$D$2:$AG$2,0)),Inputs!$B$4:$B$100,$B23)/1000) | AG23: =IF(AF23="","",AF23)
B24: 20 | C24: Goodwill | D24: =IF(D$3=0,"",SUMIFS(INDEX(Inputs!$D$4:$AG$100,0,MATCH(D$2,Inputs!$D$2:$AG$2,0)),Inputs!$B$4:$B$100,$B24)/1000) | E24: =IF(E$3=0,"",SUMIFS(INDEX(Inputs!$D$4:$AG$100,0,MATCH(E$2,Inputs!$D$2:$AG$2,0)),Inputs!$B$4:$B$100,$B24)/1000) | F24: =IF(F$3=0,"",SUMIFS(INDEX(Inputs!$D$4:$AG$100,0,MATCH(F$2,Inputs!$D$2:$AG$2,0)),Inputs!$B$4:$B$100,$B24)/1000) | G24: =IF(G$3=0,"",SUMIFS(INDEX(Inputs!$D$4:$AG$100,0,MATCH(G$2,Inputs!$D$2:$AG$2,0)),Inputs!$B$4:$B$100,$B24)/1000) | H24: =IF(G24="","",G24) | I24: =IF(I$3=0,"",SUMIFS(INDEX(Inputs!$D$4:$AG$100,0,MATCH(I$2,Inputs!$D$2:$AG$2,0)),Inputs!$B$4:$B$100,$B24)/1000) | J24: =IF(J$3=0,"",SUMIFS(INDEX(Inputs!$D$4:$AG$100,0,MATCH(J$2,Inputs!$D$2:$AG$2,0)),Inputs!$B$4:$B$100,$B24)/1000) | K24: =IF(K$3=0,"",SUMIFS(INDEX(Inputs!$D$4:$AG$100,0,MATCH(K$2,Inputs!$D$2:$AG$2,0)),Inputs!$B$4:$B$100,$B24)/1000) | L24: =IF(L$3=0,"",SUMIFS(INDEX(Inputs!$D$4:$AG$100,0,MATCH(L$2,Inputs!$D$2:$AG$2,0)),Inputs!$B$4:$B$100,$B24)/1000) | M24: =IF(L24="","",L24) | N24: =IF(N$3=0,"",SUMIFS(INDEX(Inputs!$D$4:$AG$100,0,MATCH(N$2,Inputs!$D$2:$AG$2,0)),Inputs!$B$4:$B$100,$B24)/1000) | O24: =IF(O$3=0,"",SUMIFS(INDEX(Inputs!$D$4:$AG$100,0,MATCH(O$2,Inputs!$D$2:$AG$2,0)),Inputs!$B$4:$B$100,$B24)/1000) | P24: =IF(P$3=0,"",SUMIFS(INDEX(Inputs!$D$4:$AG$100,0,MATCH(P$2,Inputs!$D$2:$AG$2,0)),Inputs!$B$4:$B$100,$B24)/1000) | Q24: =IF(Q$3=0,"",SUMIFS(INDEX(Inputs!$D$4:$AG$100,0,MATCH(Q$2,Inputs!$D$2:$AG$2,0)),Inputs!$B$4:$B$100,$B24)/1000) | R24: =IF(Q24="","",Q24) | S24: =IF(S$3=0,"",SUMIFS(INDEX(Inputs!$D$4:$AG$100,0,MATCH(S$2,Inputs!$D$2:$AG$2,0)),Inputs!$B$4:$B$100,$B24)/1000) | T24: =IF(T$3=0,"",SUMIFS(INDEX(Inputs!$D$4:$AG$100,0,MATCH(T$2,Inputs!$D$2:$AG$2,0)),Inputs!$B$4:$B$100,$B24)/1000) | U24: =IF(U$3=0,"",SUMIFS(INDEX(Inputs!$D$4:$AG$100,0,MATCH(U$2,Inputs!$D$2:$AG$2,0)),Inputs!$B$4:$B$100,$B24)/1000) | V24: =IF(V$3=0,"",SUMIFS(INDEX(Inputs!$D$4:$AG$100,0,MATCH(V$2,Inputs!$D$2:$AG$2,0)),Inputs!$B$4:$B$100,$B24)/1000) | W24: =IF(V24="","",V24) | X24: =IF(X$3=0,"",SUMIFS(INDEX(Inputs!$D$4:$AG$100,0,MATCH(X$2,Inputs!$D$2:$AG$2,0)),Inputs!$B$4:$B$100,$B24)/1000) | Y24: =IF(Y$3=0,"",SUMIFS(INDEX(Inputs!$D$4:$AG$100,0,MATCH(Y$2,Inputs!$D$2:$AG$2,0)),Inputs!$B$4:$B$100,$B24)/1000) | Z24: =IF(Z$3=0,"",SUMIFS(INDEX(Inputs!$D$4:$AG$100,0,MATCH(Z$2,Inputs!$D$2:$AG$2,0)),Inputs!$B$4:$B$100,$B24)/1000) | AA24: =IF(AA$3=0,"",SUMIFS(INDEX(Inputs!$D$4:$AG$100,0,MATCH(AA$2,Inputs!$D$2:$AG$2,0)),Inputs!$B$4:$B$100,$B24)/1000) | AB24: =IF(AA24="","",AA24) | AC24: =IF(AC$3=0,"",SUMIFS(INDEX(Inputs!$D$4:$AG$100,0,MATCH(AC$2,Inputs!$D$2:$AG$2,0)),Inputs!$B$4:$B$100,$B24)/1000) | AD24: =IF(AD$3=0,"",SUMIFS(INDEX(Inputs!$D$4:$AG$100,0,MATCH(AD$2,Inputs!$D$2:$AG$2,0)),Inputs!$B$4:$B$100,$B24)/1000) | AE24: =IF(AE$3=0,"",SUMIFS(INDEX(Inputs!$D$4:$AG$100,0,MATCH(AE$2,Inputs!$D$2:$AG$2,0)),Inputs!$B$4:$B$100,$B24)/1000) | AF24: =IF(AF$3=0,"",SUMIFS(INDEX(Inputs!$D$4:$AG$100,0,MATCH(AF$2,Inputs!$D$2:$AG$2,0)),Inputs!$B$4:$B$100,$B24)/1000) | AG24: =IF(AF24="","",AF24)
B25: 21 | C25: Intangibles | D25: =IF(D$3=0,"",SUMIFS(INDEX(Inputs!$D$4:$AG$100,0,MATCH(D$2,Inputs!$D$2:$AG$2,0)),Inputs!$B$4:$B$100,$B25)/1000) | E25: =IF(E$3=0,"",SUMIFS(INDEX(Inputs!$D$4:$AG$100,0,MATCH(E$2,Inputs!$D$2:$AG$2,0)),Inputs!$B$4:$B$100,$B25)/1000) | F25: =IF(F$3=0,"",SUMIFS(INDEX(Inputs!$D$4:$AG$100,0,MATCH(F$2,Inputs!$D$2:$AG$2,0)),Inputs!$B$4:$B$100,$B25)/1000) | G25: =IF(G$3=0,"",SUMIFS(INDEX(Inputs!$D$4:$AG$100,0,MATCH(G$2,Inputs!$D$2:$AG$2,0)),Inputs!$B$4:$B$100,$B25)/1000) | H25: =IF(G25="","",G25) | I25: =IF(I$3=0,"",SUMIFS(INDEX(Inputs!$D$4:$AG$100,0,MATCH(I$2,Inputs!$D$2:$AG$2,0)),Inputs!$B$4:$B$100,$B25)/1000) | J25: =IF(J$3=0,"",SUMIFS(INDEX(Inputs!$D$4:$AG$100,0,MATCH(J$2,Inputs!$D$2:$AG$2,0)),Inputs!$B$4:$B$100,$B25)/1000) | K25: =IF(K$3=0,"",SUMIFS(INDEX(Inputs!$D$4:$AG$100,0,MATCH(K$2,Inputs!$D$2:$AG$2,0)),Inputs!$B$4:$B$100,$B25)/1000) | L25: =IF(L$3=0,"",SUMIFS(INDEX(Inputs!$D$4:$AG$100,0,MATCH(L$2,Inputs!$D$2:$AG$2,0)),Inputs!$B$4:$B$100,$B25)/1000) | M25: =IF(L25="","",L25) | N25: =IF(N$3=0,"",SUMIFS(INDEX(Inputs!$D$4:$AG$100,0,MATCH(N$2,Inputs!$D$2:$AG$2,0)),Inputs!$B$4:$B$100,$B25)/1000) | O25: =IF(O$3=0,"",SUMIFS(INDEX(Inputs!$D$4:$AG$100,0,MATCH(O$2,Inputs!$D$2:$AG$2,0)),Inputs!$B$4:$B$100,$B25)/1000) | P25: =IF(P$3=0,"",SUMIFS(INDEX(Inputs!$D$4:$AG$100,0,MATCH(P$2,Inputs!$D$2:$AG$2,0)),Inputs!$B$4:$B$100,$B25)/1000) | Q25: =IF(Q$3=0,"",SUMIFS(INDEX(Inputs!$D$4:$AG$100,0,MATCH(Q$2,Inputs!$D$2:$AG$2,0)),Inputs!$B$4:$B$100,$B25)/1000) | R25: =IF(Q25="","",Q25) | S25: =IF(S$3=0,"",SUMIFS(INDEX(Inputs!$D$4:$AG$100,0,MATCH(S$2,Inputs!$D$2:$AG$2,0)),Inputs!$B$4:$B$100,$B25)/1000) | T25: =IF(T$3=0,"",SUMIFS(INDEX(Inputs!$D$4:$AG$100,0,MATCH(T$2,Inputs!$D$2:$AG$2,0)),Inputs!$B$4:$B$100,$B25)/1000) | U25: =IF(U$3=0,"",SUMIFS(INDEX(Inputs!$D$4:$AG$100,0,MATCH(U$2,Inputs!$D$2:$AG$2,0)),Inputs!$B$4:$B$100,$B25)/1000) | V25: =IF(V$3=0,"",SUMIFS(INDEX(Inputs!$D$4:$AG$100,0,MATCH(V$2,Inputs!$D$2:$AG$2,0)),Inputs!$B$4:$B$100,$B25)/1000) | W25: =IF(V25="","",V25) | X25: =IF(X$3=0,"",SUMIFS(INDEX(Inputs!$D$4:$AG$100,0,MATCH(X$2,Inputs!$D$2:$AG$2,0)),Inputs!$B$4:$B$100,$B25)/1000) | Y25: =IF(Y$3=0,"",SUMIFS(INDEX(Inputs!$D$4:$AG$100,0,MATCH(Y$2,Inputs!$D$2:$AG$2,0)),Inputs!$B$4:$B$100,$B25)/1000) | Z25: =IF(Z$3=0,"",SUMIFS(INDEX(Inputs!$D$4:$AG$100,0,MATCH(Z$2,Inputs!$D$2:$AG$2,0)),Inputs!$B$4:$B$100,$B25)/1000) | AA25: =IF(AA$3=0,"",SUMIFS(INDEX(Inputs!$D$4:$AG$100,0,MATCH(AA$2,Inputs!$D$2:$AG$2,0)),Inputs!$B$4:$B$100,$B25)/1000) | AB25: =IF(AA25="","",AA25) | AC25: =IF(AC$3=0,"",SUMIFS(INDEX(Inputs!$D$4:$AG$100,0,MATCH(AC$2,Inputs!$D$2:$AG$2,0)),Inputs!$B$4:$B$100,$B25)/1000) | AD25: =IF(AD$3=0,"",SUMIFS(INDEX(Inputs!$D$4:$AG$100,0,MATCH(AD$2,Inputs!$D$2:$AG$2,0)),Inputs!$B$4:$B$100,$B25)/1000) | AE25: =IF(AE$3=0,"",SUMIFS(INDEX(Inputs!$D$4:$AG$100,0,MATCH(AE$2,Inputs!$D$2:$AG$2,0)),Inputs!$B$4:$B$100,$B25)/1000) | AF25: =IF(AF$3=0,"",SUMIFS(INDEX(Inputs!$D$4:$AG$100,0,MATCH(AF$2,Inputs!$D$2:$AG$2,0)),Inputs!$B$4:$B$100,$B25)/1000) | AG25: =IF(AF25="","",AF25)
B26: 22 | C26: Other non-current assets | D26: =IF(D$3=0,"",SUMIFS(INDEX(Inputs!$D$4:$AG$100,0,MATCH(D$2,Inputs!$D$2:$AG$2,0)),Inputs!$B$4:$B$100,$B26)/1000) | E26: =IF(E$3=0,"",SUMIFS(INDEX(Inputs!$D$4:$AG$100,0,MATCH(E$2,Inputs!$D$2:$AG$2,0)),Inputs!$B$4:$B$100,$B26)/1000) | F26: =IF(F$3=0,"",SUMIFS(INDEX(Inputs!$D$4:$AG$100,0,MATCH(F$2,Inputs!$D$2:$AG$2,0)),Inputs!$B$4:$B$100,$B26)/1000) | G26: =IF(G$3=0,"",SUMIFS(INDEX(Inputs!$D$4:$AG$100,0,MATCH(G$2,Inputs!$D$2:$AG$2,0)),Inputs!$B$4:$B$100,$B26)/1000) | H26: =IF(G26="","",G26) | I26: =IF(I$3=0,"",SUMIFS(INDEX(Inputs!$D$4:$AG$100,0,MATCH(I$2,Inputs!$D$2:$AG$2,0)),Inputs!$B$4:$B$100,$B26)/1000) | J26: =IF(J$3=0,"",SUMIFS(INDEX(Inputs!$D$4:$AG$100,0,MATCH(J$2,Inputs!$D$2:$AG$2,0)),Inputs!$B$4:$B$100,$B26)/1000) | K26: =IF(K$3=0,"",SUMIFS(INDEX(Inputs!$D$4:$AG$100,0,MATCH(K$2,Inputs!$D$2:$AG$2,0)),Inputs!$B$4:$B$100,$B26)/1000) | L26: =IF(L$3=0,"",SUMIFS(INDEX(Inputs!$D$4:$AG$100,0,MATCH(L$2,Inputs!$D$2:$AG$2,0)),Inputs!$B$4:$B$100,$B26)/1000) | M26: =IF(L26="","",L26) | N26: =IF(N$3=0,"",SUMIFS(INDEX(Inputs!$D$4:$AG$100,0,MATCH(N$2,Inputs!$D$2:$AG$2,0)),Inputs!$B$4:$B$100,$B26)/1000) | O26: =IF(O$3=0,"",SUMIFS(INDEX(Inputs!$D$4:$AG$100,0,MATCH(O$2,Inputs!$D$2:$AG$2,0)),Inputs!$B$4:$B$100,$B26)/1000) | P26: =IF(P$3=0,"",SUMIFS(INDEX(Inputs!$D$4:$AG$100,0,MATCH(P$2,Inputs!$D$2:$AG$2,0)),Inputs!$B$4:$B$100,$B26)/1000) | Q26: =IF(Q$3=0,"",SUMIFS(INDEX(Inputs!$D$4:$AG$100,0,MATCH(Q$2,Inputs!$D$2:$AG$2,0)),Inputs!$B$4:$B$100,$B26)/1000) | R26: =IF(Q26="","",Q26) | S26: =IF(S$3=0,"",SUMIFS(INDEX(Inputs!$D$4:$AG$100,0,MATCH(S$2,Inputs!$D$2:$AG$2,0)),Inputs!$B$4:$B$100,$B26)/1000) | T26: =IF(T$3=0,"",SUMIFS(INDEX(Inputs!$D$4:$AG$100,0,MATCH(T$2,Inputs!$D$2:$AG$2,0)),Inputs!$B$4:$B$100,$B26)/1000) | U26: =IF(U$3=0,"",SUMIFS(INDEX(Inputs!$D$4:$AG$100,0,MATCH(U$2,Inputs!$D$2:$AG$2,0)),Inputs!$B$4:$B$100,$B26)/1000) | V26: =IF(V$3=0,"",SUMIFS(INDEX(Inputs!$D$4:$AG$100,0,MATCH(V$2,Inputs!$D$2:$AG$2,0)),Inputs!$B$4:$B$100,$B26)/1000) | W26: =IF(V26="","",V26) | X26: =IF(X$3=0,"",SUMIFS(INDEX(Inputs!$D$4:$AG$100,0,MATCH(X$2,Inputs!$D$2:$AG$2,0)),Inputs!$B$4:$B$100,$B26)/1000) | Y26: =IF(Y$3=0,"",SUMIFS(INDEX(Inputs!$D$4:$AG$100,0,MATCH(Y$2,Inputs!$D$2:$AG$2,0)),Inputs!$B$4:$B$100,$B26)/1000) | Z26: =IF(Z$3=0,"",SUMIFS(INDEX(Inputs!$D$4:$AG$100,0,MATCH(Z$2,Inputs!$D$2:$AG$2,0)),Inputs!$B$4:$B$100,$B26)/1000) | AA26: =IF(AA$3=0,"",SUMIFS(INDEX(Inputs!$D$4:$AG$100,0,MATCH(AA$2,Inputs!$D$2:$AG$2,0)),Inputs!$B$4:$B$100,$B26)/1000) | AB26: =IF(AA26="","",AA26) | AC26: =IF(AC$3=0,"",SUMIFS(INDEX(Inputs!$D$4:$AG$100,0,MATCH(AC$2,Inputs!$D$2:$AG$2,0)),Inputs!$B$4:$B$100,$B26)/1000) | AD26: =IF(AD$3=0,"",SUMIFS(INDEX(Inputs!$D$4:$AG$100,0,MATCH(AD$2,Inputs!$D$2:$AG$2,0)),Inputs!$B$4:$B$100,$B26)/1000) | AE26: =IF(AE$3=0,"",SUMIFS(INDEX(Inputs!$D$4:$AG$100,0,MATCH(AE$2,Inputs!$D$2:$AG$2,0)),Inputs!$B$4:$B$100,$B26)/1000) | AF26: =IF(AF$3=0,"",SUMIFS(INDEX(Inputs!$D$4:$AG$100,0,MATCH(AF$2,Inputs!$D$2:$AG$2,0)),Inputs!$B$4:$B$100,$B26)/1000) | AG26: =IF(AF26="","",AF26)
... B47: 41 | C47: Retained earnings | D47: =IF(D$3=0,"",SUMIFS(INDEX(Inputs!$D$4:$AG$100,0,MATCH(D$2,Inputs!$D$2:$AG$2,0)),Inputs!$B$4:$B$100,$B47)/1000) | E47: =IF(E$3=0,"",SUMIFS(INDEX(Inputs!$D$4:$AG$100,0,MATCH(E$2,Inputs!$D$2:$AG$2,0)),Inputs!$B$4:$B$100,$B47)/1000) | F47: =IF(F$3=0,"",SUMIFS(INDEX(Inputs!$D$4:$AG$100,0,MATCH(F$2,Inputs!$D$2:$AG$2,0)),Inputs!$B$4:$B$100,$B47)/1000) | G47: =IF(G$3=0,"",SUMIFS(INDEX(Inputs!$D$4:$AG$100,0,MATCH(G$2,Inputs!$D$2:$AG$2,0)),Inputs!$B$4:$B$100,$B47)/1000) | H47: =IF(G47="","",G47) | I47: =IF(I$3=0,"",SUMIFS(INDEX(Inputs!$D$4:$AG$100,0,MATCH(I$2,Inputs!$D$2:$AG$2,0)),Inputs!$B$4:$B$100,$B47)/1000) | J47: =IF(J$3=0,"",SUMIFS(INDEX(Inputs!$D$4:$AG$100,0,MATCH(J$2,Inputs!$D$2:$AG$2,0)),Inputs!$B$4:$B$100,$B47)/1000) | K47: =IF(K$3=0,"",SUMIFS(INDEX(Inputs!$D$4:$AG$100,0,MATCH(K$2,Inputs!$D$2:$AG$2,0)),Inputs!$B$4:$B$100,$B47)/1000) | L47: =IF(L$3=0,"",SUMIFS(INDEX(Inputs!$D$4:$AG$100,0,MATCH(L$2,Inputs!$D$2:$AG$2,0)),Inputs!$B$4:$B$100,$B47)/1000) | M47: =IF(L47="","",L47) | N47: =IF(N$3=0,"",SUMIFS(INDEX(Inputs!$D$4:$AG$100,0,MATCH(N$2,Inputs!$D$2:$AG$2,0)),Inputs!$B$4:$B$100,$B47)/1000) | O47: =IF(O$3=0,"",SUMIFS(INDEX(Inputs!$D$4:$AG$100,0,MATCH(O$2,Inputs!$D$2:$AG$2,0)),Inputs!$B$4:$B$100,$B47)/1000) | P47: =IF(P$3=0,"",SUMIFS(INDEX(Inputs!$D$4:$AG$100,0,MATCH(P$2,Inputs!$D$2:$AG$2,0)),Inputs!$B$4:$B$100,$B47)/1000) | Q47: =IF(Q$3=0,"",SUMIFS(INDEX(Inputs!$D$4:$AG$100,0,MATCH(Q$2,Inputs!$D$2:$AG$2,0)),Inputs!$B$4:$B$100,$B47)/1000) | R47: =IF(Q47="","",Q47) | S47: =IF(S$3=0,"",SUMIFS(INDEX(Inputs!$D$4:$AG$100,0,MATCH(S$2,Inputs!$D$2:$AG$2,0)),Inputs!$B$4:$B$100,$B47)/1000) | T47: =IF(T$3=0,"",SUMIFS(INDEX(Inputs!$D$4:$AG$100,0,MATCH(T$2,Inputs!$D$2:$AG$2,0)),Inputs!$B$4:$B$100,$B47)/1000) | U47: =IF(U$3=0,"",SUMIFS(INDEX(Inputs!$D$4:$AG$100,0,MATCH(U$2,Inputs!$D$2:$AG$2,0)),Inputs!$B$4:$B$100,$B47)/1000) | V47: =IF(V$3=0,"",SUMIFS(INDEX(Inputs!$D$4:$AG$100,0,MATCH(V$2,Inputs!$D$2:$AG$2,0)),Inputs!$B$4:$B$100,$B47)/1000) | W47: =IF(V47="","",V47) | X47: =IF(X$3=0,"",SUMIFS(INDEX(Inputs!$D$4:$AG$100,0,MATCH(X$2,Inputs!$D$2:$AG$2,0)),Inputs!$B$4:$B$100,$B47)/1000) | Y47: =IF(Y$3=0,"",SUMIFS(INDEX(Inputs!$D$4:$AG$100,0,MATCH(Y$2,Inputs!$D$2:$AG$2,0)),Inputs!$B$4:$B$100,$B47)/1000) | Z47: =IF(Z$3=0,"",SUMIFS(INDEX(Inputs!$D$4:$AG$100,0,MATCH(Z$2,Inputs!$D$2:$AG$2,0)),Inputs!$B$4:$B$100,$B47)/1000) | AA47: =IF(AA$3=0,"",SUMIFS(INDEX(Inputs!$D$4:$AG$100,0,MATCH(AA$2,Inputs!$D$2:$AG$2,0)),Inputs!$B$4:$B$100,$B47)/1000) | AB47: =IF(AA47="","",AA47) | AC47: =IF(AC$3=0,"",SUMIFS(INDEX(Inputs!$D$4:$AG$100,0,MATCH(AC$2,Inputs!$D$2:$AG$2,0)),Inputs!$B$4:$B$100,$B47)/1000) | AD47: =IF(AD$3=0,"",SUMIFS(INDEX(Inputs!$D$4:$AG$100,0,MATCH(AD$2,Inputs!$D$2:$AG$2,0)),Inputs!$B$4:$B$100,$B47)/1000) | AE47: =IF(AE$3=0,"",SUMIFS(INDEX(Inputs!$D$4:$AG$100,0,MATCH(AE$2,Inputs!$D$2:$AG$2,0)),Inputs!$B$4:$B$100,$B47)/1000) | AF47: =IF(AF$3=0,"",SUMIFS(INDEX(Inputs!$D$4:$AG$100,0,MATCH(AF$2,Inputs!$D$2:$AG$2,0)),Inputs!$B$4:$B$100,$B47)/1000) | AG47: =IF(AF47="","",AF47)

Sheet Model
C1: CHECKS | I1: =IF(I2="","",SUM(I2,I3)) | J1: =IF(J2="","",SUM(J2,J3)) | K1: =IF(K2="","",SUM(K2,K3)) | L1: =IF(L2="","",SUM(L2,L3)) | M1: =IF(M2="","",SUM(M2,M3)) -> 0 | N1: =IF(N2="","",SUM(N2,N3)) | O1: =IF(O2="","",SUM(O2,O3)) | P1: =IF(P2="","",SUM(P2,P3)) | ... BF1: =IF(BF2="","",SUM(BF2,BF3))
C2: BS | I2: =IF(COUNT(I163,I239)<2,"",ABS(I163-I239)) | J2: =IF(COUNT(J163,J239)<2,"",ABS(J163-J239)) | K2: =IF(COUNT(K163,K239)<2,"",ABS(K163-K239)) | L2: =IF(COUNT(L163,L239)<2,"",ABS(L163-L239)) | M2: =IF(COUNT(M163,M239)<2,"",ABS(M163-M239)) -> 0 | N2: =IF(COUNT(N163,N239)<2,"",ABS(N163-N239)) | O2: =IF(COUNT(O163,O239)<2,"",ABS(O163-O239)) | P2: =IF(COUNT(P163,P239)<2,"",ABS(P163-P239)) | ... BF2: =IF(COUNT(BF163,BF239)<2,"",ABS(BF163-BF239))
C3: IS | M3: =ABS(M103-M4) -> 0 | R3: =ABS(R103-R4) -> 0 | W3: =ABS(W103-W4) -> 0 | AB3: =ABS(AB103-AB4) -> 0 | AG3: =ABS(AG103-AG4) -> 0 | AH3: =ABS(AH103-AH4) -> 0 | AI3: =ABS(AI103-AI4) -> 0 | AJ3: =ABS(AJ103-AJ4) -> #VALUE! | AK3: =ABS(AK103-AK4) -> #VALUE! | AL3: =ABS(AL103-AL4) -> #VALUE! | AM3: =ABS(AM103-AM4) -> #VALUE! | AN3: =ABS(AN103-AN4) -> #VALUE! | ... BF3: =ABS(BF103-BF4) -> #VALUE!
B5: 45930 | I5: 44286 | J5: =DATE(YEAR(I5),MONTH(I5)+3,DAY(I5)-1) -> 44377 | K5: =DATE(YEAR(J5),MONTH(J5)+3,DAY(J5)) -> 44469 | L5: =DATE(YEAR(K5),MONTH(K5)+3,DAY(K5)+1) -> 44561 | M5: =L5 -> 44561 | N5: =DATE(YEAR(M5),MONTH(M5)+3,DAY(M5)) -> 44651 | O5: =DATE(YEAR(N5),MONTH(N5)+3,DAY(N5)-1) -> 44742 | P5: =DATE(YEAR(O5),MONTH(O5)+3,DAY(O5)) -> 44834 | Q5: =DATE(YEAR(P5),MONTH(P5)+3,DAY(P5)+1) -> 44926 | R5: =Q5 -> 44926 | S5: =DATE(YEAR(R5),MONTH(R5)+3,DAY(R5)) -> 45016 | T5: =DATE(YEAR(S5),MONTH(S5)+3,DAY(S5))-1 -> 45107 | U5: =DATE(YEAR(T5),MONTH(T5)+3,DAY(T5)) -> 45199 | V5: =DATE(YEAR(U5),MONTH(U5)+3,DAY(U5))+1 -> 45291 | W5: =V5 -> 45291 | X5: =DATE(YEAR(W5),MONTH(W5)+3,DAY(W5)) -> 45382 | Y5: =DATE(YEAR(X5),MONTH(X5)+3,DAY(X5))-1 -> 45473 | Z5: =DATE(YEAR(Y5),MONTH(Y5)+3,DAY(Y5)) -> 45565 | AA5: =DATE(YEAR(Z5),MONTH(Z5)+3,DAY(Z5))+1 -> 45657 | AB5: =AA5 -> 45657 | AC5: =DATE(YEAR(AB5),MONTH(AB5)+3,DAY(AB5)) -> 45747 | AD5: =DATE(YEAR(AC5),MONTH(AC5)+3,DAY(AC5))-1 -> 45838 | AE5: =DATE(YEAR(AD5),MONTH(AD5)+3,DAY(AD5)) -> 45930 | AF5: =DATE(YEAR(AE5),MONTH(AE5)+3,DAY(AE5))+1 -> 46022 | AG5: =AF5 -> 46022 | AH5: =DATE(YEAR(AG5),MONTH(AG5)+3,DAY(AG5)) -> 46112 | AI5: =DATE(YEAR(AH5),MONTH(AH5)+3,DAY(AH5))-1 -> 46203 | AJ5: =DATE(YEAR(AI5),MONTH(AI5)+3,DAY(AI5)) -> 46295 | AK5: =DATE(YEAR(AJ5),MONTH(AJ5)+3,DAY(AJ5))+1 -> 46387 | AL5: =AK5 -> 46387 | AM5: =DATE(YEAR(AL5),MONTH(AL5)+3,DAY(AL5)) -> 46477 | AN5: =DATE(YEAR(AM5),MONTH(AM5)+3,DAY(AM5))-1 -> 46568 | AO5: =DATE(YEAR(AN5),MONTH(AN5)+3,DAY(AN5)) -> 46660 | AP5: =DATE(YEAR(AO5),MONTH(AO5)+3,DAY(AO5))+1 -> 46752 | AQ5: =AP5 -> 46752 | AR5: =DATE(YEAR(AQ5),MONTH(AQ5)+3,DAY(AQ5)) -> 46843 | AS5: =DATE(YEAR(AR5),MONTH(AR5)+3,DAY(AR5))-1 -> 46934 | AT5: =DATE(YEAR(AS5),MONTH(AS5)+3,DAY(AS5)) -> 47026 | AU5: =DATE(YEAR(AT5),MONTH(AT5)+3,DAY(AT5))+1 -> 47118 | AV5: =AU5 -> 47118 | AW5: =DATE(YEAR(AV5),MONTH(AV5)+3,DAY(AV5)) -> 47208 | AX5: =DATE(YEAR(AW5),MONTH(AW5)+3,DAY(AW5))-1 -> 47299 | AY5: =DATE(YEAR(AX5),MONTH(AX5)+3,DAY(AX5)) -> 47391 | AZ5: =DATE(YEAR(AY5),MONTH(AY5)+3,DAY(AY5))+1 -> 47483 | BA5: =AZ5 -> 47483 | BB5: =DATE(YEAR(BA5),MONTH(BA5)+3,DAY(BA5)) -> 47573 | BC5: =DATE(YEAR(BB5),MONTH(BB5)+3,DAY(BB5))-1 -> 47664 | BD5: =DATE(YEAR(BC5),MONTH(BC5)+3,DAY(BC5)) -> 47756 | BE5: =DATE(YEAR(BD5),MONTH(BD5)+3,DAY(BD5))+1 -> 47848 | BF5: =BE5 -> 47848
I6: =YEAR(I5) -> 2021 | J6: =YEAR(J5) -> 2021 | K6: =YEAR(K5) -> 2021 | L6: =YEAR(L5) -> 2021 | M6: =YEAR(M5) -> 2021 | N6: =YEAR(N5) -> 2022 | O6: =YEAR(O5) -> 2022 | P6: =YEAR(P5) -> 2022 | ... BF6: =YEAR(BF5) -> 2030
H7: 2020 | I7: ="1Q"&RIGHT(I6,2) -> 1Q21 | J7: ="2Q"&RIGHT(J6,2) -> 2Q21 | K7: ="3Q"&RIGHT(K6,2) -> 3Q21 | L7: ="4Q"&RIGHT(L6,2) -> 4Q21 | M7: =H7+1 -> 2021 | N7: ="1Q"&RIGHT(N6,2) -> 1Q22 | O7: ="2Q"&RIGHT(O6,2) -> 2Q22 | P7: ="3Q"&RIGHT(P6,2) -> 3Q22 | Q7: ="4Q"&RIGHT(Q6,2) -> 4Q22 | R7: =M7+1 -> 2022 | S7: ="1Q"&RIGHT(S6,2) -> 1Q23 | T7: ="2Q"&RIGHT(T6,2) -> 2Q23 | U7: ="3Q"&RIGHT(U6,2) -> 3Q23 | V7: ="4Q"&RIGHT(V6,2) -> 4Q23 | W7: =R7+1 -> 2023 | X7: ="1Q"&RIGHT(X6,2) -> 1Q24 | Y7: ="2Q"&RIGHT(Y6,2) -> 2Q24 | Z7: ="3Q"&RIGHT(Z6,2) -> 3Q24 | AA7: ="4Q"&RIGHT(AA6,2) -> 4Q24 | AB7: =W7+1 -> 2024 | AC7: ="1Q"&RIGHT(AC6,2) -> 1Q25 | AD7: ="2Q"&RIGHT(AD6,2) -> 2Q25 | AE7: ="3Q"&RIGHT(AE6,2) -> 3Q25 | AF7: ="4Q"&RIGHT(AF6,2) -> 4Q25 | AG7: =AB7+1 -> 2025 | AH7: ="1Q"&RIGHT(AH6,2) -> 1Q26 | AI7: ="2Q"&RIGHT(AI6,2) -> 2Q26 | AJ7: ="3Q"&RIGHT(AJ6,2) -> 3Q26 | AK7: ="4Q"&RIGHT(AK6,2) -> 4Q26 | AL7: =AG7+1 -> 2026 | AM7: ="1Q"&RIGHT(AM6,2) -> 1Q27 | AN7: ="2Q"&RIGHT(AN6,2) -> 2Q27 | AO7: ="3Q"&RIGHT(AO6,2) -> 3Q27 | AP7: ="4Q"&RIGHT(AP6,2) -> 4Q27 | AQ7: =AL7+1 -> 2027 | AR7: ="1Q"&RIGHT(AR6,2) -> 1Q28 | AS7: ="2Q"&RIGHT(AS6,2) -> 2Q28 | AT7: ="3Q"&RIGHT(AT6,2) -> 3Q28 | AU7: ="4Q"&RIGHT(AU6,2) -> 4Q28 | AV7: =AQ7+1 -> 2028 | AW7: ="1Q"&RIGHT(AW6,2) -> 1Q29 | AX7: ="2Q"&RIGHT(AX6,2) -> 2Q29 | AY7: ="3Q"&RIGHT(AY6,2) -> 3Q29 | AZ7: ="4Q"&RIGHT(AZ6,2) -> 4Q29 | BA7: =AV7+1 -> 2029 | BB7: ="1Q"&RIGHT(BB6,2) -> 1Q30 | BC7: ="2Q"&RIGHT(BC6,2) -> 2Q30 | BD7: ="3Q"&RIGHT(BD6,2) -> 3Q30 | BE7: ="4Q"&RIGHT(BE6,2) -> 4Q30 | BF7: =BA7+1 -> 2030
C8: IPCA | M8: 0.1006 | R8: 0.0579 | W8: 0.0468 | AB8: 0.0483 | AG8: 0.0468
C9: GDP BRAZIL | M9: 0.046
C10: CDI | M10: 0.0442 | R10: 0.1239 | W10: 0.1304 | AB10: 0.1064 | AG10: 0.1464
C13: Income Statement | I13: =I7 -> 1Q21 | J13: =J7 -> 2Q21 | K13: =K7 -> 3Q21 | L13: =L7 -> 4Q21 | M13: =M7 -> 2021 | N13: =N7 -> 1Q22 | O13: =O7 -> 2Q22 | P13: =P7 -> 3Q22 | ... BF13: =BF7 -> 2030
C15: Net Revenues | I15: ='Inputs (2)'!D4 | J15: ='Inputs (2)'!E4 | K15: ='Inputs (2)'!F4 | L15: ='Inputs (2)'!G4 | M15: ='Inputs (2)'!H4 | N15: ='Inputs (2)'!I4 | O15: ='Inputs (2)'!J4 | P15: ='Inputs (2)'!K4 | ... AI15: ='Inputs (2)'!AD4 | AJ15: =AE15*(1+AJ16) -> #VALUE! | AK15: =AF15*(1+AK16) -> #VALUE! | AL15: =SUM(AH15:AK15) -> #VALUE! | AM15: =AH15*(1+AM16) -> #VALUE! | AN15: =AI15*(1+AN16) -> #VALUE! | AO15: =AJ15*(1+AO16) -> #VALUE! | AP15: =AK15*(1+AP16) -> #VALUE! | AQ15: =SUM(AM15:AP15) -> #VALUE! | AR15: =AM15*(1+AR16) -> #VALUE! | AS15: =AN15*(1+AS16) -> #VALUE! | AT15: =AO15*(1+AT16) -> #VALUE! | AU15: =AP15*(1+AU16) -> #VALUE! | AV15: =SUM(AR15:AU15) -> #VALUE! | AW15: =AR15*(1+AW16) -> #VALUE! | AX15: =AS15*(1+AX16) -> #VALUE! | AY15: =AT15*(1+AY16) -> #VALUE! | AZ15: =AU15*(1+AZ16) -> #VALUE! | BA15: =SUM(AW15:AZ15) -> #VALUE! | BB15: =AW15*(1+BB16) -> #VALUE! | BC15: =AX15*(1+BC16) -> #VALUE! | BD15: =AY15*(1+BD16) -> #VALUE! | BE15: =AZ15*(1+BE16) -> #VALUE! | BF15: =SUM(BB15:BE15) -> #VALUE!
C16: % YoY | N16: =IFERROR(N15/I15-1,"") | O16: =IFERROR(O15/J15-1,"") | P16: =IFERROR(P15/K15-1,"") | Q16: =IFERROR(Q15/L15-1,"") | R16: =IFERROR(R15/M15-1,"") | S16: =IFERROR(S15/N15-1,"") | T16: =IFERROR(T15/O15-1,"") | U16: =IFERROR(U15/P15-1,"") | ... AE16: =IFERROR(AE15/Z15-1,"") | AG16: =IFERROR(AG15/AB15-1,"") | AJ16: =Control!$B$18 | AK16: =Control!$B$18 | AL16: =IFERROR(AL15/AG15-1,"") | AM16: =Control!$C$18 | AN16: =Control!$C$18 | AO16: =Control!$C$18 | AP16: =Control!$C$18 | AQ16: =IFERROR(AQ15/AL15-1,"") | AR16: =Control!$D$18 | AS16: =Control!$D$18 | AT16: =Control!$D$18 | AU16: =Control!$D$18 | AV16: =IFERROR(AV15/AQ15-1,"") | AW16: =Control!$E$18 | AX16: =Control!$E$18 | AY16: =Control!$E$18 | AZ16: =Control!$E$18 | BA16: =IFERROR(BA15/AV15-1,"") | BB16: =Control!$F$18 | BC16: =Control!$F$18 | BD16: =Control!$F$18 | BE16: =Control!$F$18 | BF16: =IFERROR(BF15/BA15-1,"")
C17: Check Receita
C20: COGS (cash) | I20: ='Inputs (2)'!D5 | J20: ='Inputs (2)'!E5 | K20: ='Inputs (2)'!F5 | L20: ='Inputs (2)'!G5 | M20: ='Inputs (2)'!H5 | N20: ='Inputs (2)'!I5 | O20: ='Inputs (2)'!J5 | P20: ='Inputs (2)'!K5 | ... AI20: ='Inputs (2)'!AD5 | AJ20: =-(1-AJ21)*AJ15 -> #VALUE! | AK20: =-(1-AK21)*AK15 -> #VALUE! | AL20: =SUM(AH20:AK20) -> #VALUE! | AM20: =-(1-AM21)*AM15 -> #VALUE! | AN20: =-(1-AN21)*AN15 -> #VALUE! | AO20: =-(1-AO21)*AO15 -> #VALUE! | AP20: =-(1-AP21)*AP15 -> #VALUE! | AQ20: =SUM(AM20:AP20) -> #VALUE! | AR20: =-(1-AR21)*AR15 -> #VALUE! | AS20: =-(1-AS21)*AS15 -> #VALUE! | AT20: =-(1-AT21)*AT15 -> #VALUE! | AU20: =-(1-AU21)*AU15 -> #VALUE! | AV20: =SUM(AR20:AU20) -> #VALUE! | AW20: =-(1-AW21)*AW15 -> #VALUE! | AX20: =-(1-AX21)*AX15 -> #VALUE! | AY20: =-(1-AY21)*AY15 -> #VALUE! | AZ20: =-(1-AZ21)*AZ15 -> #VALUE! | BA20: =SUM(AW20:AZ20) -> #VALUE! | BB20: =-(1-BB21)*BB15 -> #VALUE! | BC20: =-(1-BC21)*BC15 -> #VALUE! | BD20: =-(1-BD21)*BD15 -> #VALUE! | BE20: =-(1-BE21)*BE15 -> #VALUE! | BF20: =SUM(BB20:BE20) -> #VALUE!
C21: % Gross Margin | I21: =IFERROR((I15+I20)/I$15,"") | J21: =IFERROR((J15+J20)/J$15,"") | K21: =IFERROR((K15+K20)/K$15,"") | L21: =IFERROR((L15+L20)/L$15,"") | M21: =IFERROR((M15+M20)/M$15,"") | N21: =IFERROR((N15+N20)/N$15,"") | O21: =IFERROR((O15+O20)/O$15,"") | P21: =IFERROR((P15+P20)/P$15,"") | ... AE21: =IFERROR((AE15+AE20)/AE$15,"") | AG21: =IFERROR((AG15+AG20)/AG$15,"") | AJ21: =Control!$B$19 | AK21: =Control!$B$19 | AL21: =IFERROR((AL15+AL20)/AL$15,"") | AM21: =Control!$C$19 | AN21: =Control!$C$19 | AO21: =Control!$C$19 | AP21: =Control!$C$19 | AQ21: =IFERROR((AQ15+AQ20)/AQ$15,"") | AR21: =Control!$D$19 | AS21: =Control!$D$19 | AT21: =Control!$D$19 | AU21: =Control!$D$19 | AV21: =IFERROR((AV15+AV20)/AV$15,"") | AW21: =Control!$E$19 | AX21: =Control!$E$19 | AY21: =Control!$E$19 | AZ21: =Control!$E$19 | BA21: =IFERROR((BA15+BA20)/BA$15,"") | BB21: =Control!$F$19 | BC21: =Control!$F$19 | BD21: =Control!$F$19 | BE21: =Control!$F$19 | BF21: =IFERROR((BF15+BF20)/BF$15,"")
C24: SG&A and Other (cash) | I24: ='Inputs (2)'!D6 | J24: ='Inputs (2)'!E6 | K24: ='Inputs (2)'!F6 | L24: ='Inputs (2)'!G6 | M24: ='Inputs (2)'!H6 | N24: ='Inputs (2)'!I6 | O24: ='Inputs (2)'!J6 | P24: ='Inputs (2)'!K6 | ... AI24: ='Inputs (2)'!AD6 | AJ24: =-AJ15*AJ25 -> #VALUE! | AK24: =-AK15*AK25 -> #VALUE! | AL24: =SUM(AH24:AK24) -> #VALUE! | AM24: =-AM15*AM25 -> #VALUE! | AN24: =-AN15*AN25 -> #VALUE! | AO24: =-AO15*AO25 -> #VALUE! | AP24: =-AP15*AP25 -> #VALUE! | AQ24: =SUM(AM24:AP24) -> #VALUE! | AR24: =-AR15*AR25 -> #VALUE! | AS24: =-AS15*AS25 -> #VALUE! | AT24: =-AT15*AT25 -> #VALUE! | AU24: =-AU15*AU25 -> #VALUE! | AV24: =SUM(AR24:AU24) -> #VALUE! | AW24: =-AW15*AW25 -> #VALUE! | AX24: =-AX15*AX25 -> #VALUE! | AY24: =-AY15*AY25 -> #VALUE! | AZ24: =-AZ15*AZ25 -> #VALUE! | BA24: =SUM(AW24:AZ24) -> #VALUE! | BB24: =-BB15*BB25 -> #VALUE! | BC24: =-BC15*BC25 -> #VALUE! | BD24: =-BD15*BD25 -> #VALUE! | BE24: =-BE15*BE25 -> #VALUE! | BF24: =SUM(BB24:BE24) -> #VALUE!
C25: % SG&A and Other Margin | I25: =IFERROR(-(I24/I$15),"") | J25: =IFERROR(-(J24/J$15),"") | K25: =IFERROR(-(K24/K$15),"") | L25: =IFERROR(-(L24/L$15),"") | M25: =IFERROR(-(M24/M$15),"") | N25: =IFERROR(-(N24/N$15),"") | O25: =IFERROR(-(O24/O$15),"") | P25: =IFERROR(-(P24/P$15),"") | ... AE25: =IFERROR(-(AE24/AE$15),"") | AG25: =IFERROR(-(AG24/AG$15),"") | AJ25: =Control!$B$20 | AK25: =Control!$B$20 | AL25: =IFERROR(-(AL24/AL$15),"") | AM25: =Control!$C$20 | AN25: =Control!$C$20 | AO25: =Control!$C$20 | AP25: =Control!$C$20 | AQ25: =IFERROR(-(AQ24/AQ$15),"") | AR25: =Control!$D$20 | AS25: =Control!$D$20 | AT25: =Control!$D$20 | AU25: =Control!$D$20 | AV25: =IFERROR(-(AV24/AV$15),"") | AW25: =Control!$E$20 | AX25: =Control!$E$20 | AY25: =Control!$E$20 | AZ25: =Control!$E$20 | BA25: =IFERROR(-(BA24/BA$15),"") | BB25: =Control!$F$20 | BC25: =Control!$F$20 | BD25: =Control!$F$20 | BE25: =Control!$F$20 | BF25: =IFERROR(-(BF24/BF$15),"")
C27: Com Vendas
C28: Gerais & Administrativas
C29: Outras Receitas (Despesas) Operacionais, Líquidas
C31: Com Vendas (%)
C32: Gerais & Administrativas (%)
C33: Outras Receitas (Despesas) Operacionais, Líquidas (%)
C35: EBITDA | I35: =SUM(I15,I20,I24) -> 0 | J35: =SUM(J15,J20,J24) -> 0 | K35: =SUM(K15,K20,K24) -> 0 | L35: =SUM(L15,L20,L24) -> 0 | M35: =SUM(I35:L35) -> 0 | N35: =SUM(N15,N20,N24) -> 0 | O35: =SUM(O15,O20,O24) -> 0 | P35: =SUM(P15,P20,P24) -> 0 | Q35: =SUM(Q15,Q20,Q24) -> 0 | R35: =SUM(N35:Q35) -> 0 | S35: =SUM(S15,S20,S24) -> 0 | T35: =SUM(T15,T20,T24) -> 0 | U35: =SUM(U15,U20,U24) -> 0 | V35: =SUM(V15,V20,V24) -> 0 | W35: =SUM(S35:V35) -> 0 | X35: =SUM(X15,X20,X24) -> 0 | Y35: =SUM(Y15,Y20,Y24) -> 0 | Z35: =SUM(Z15,Z20,Z24) -> 0 | AA35: =SUM(AA15,AA20,AA24) -> 0 | AB35: =SUM(X35:AA35) -> 0 | AC35: =SUM(AC15,AC20,AC24) -> 0 | AD35: =SUM(AD15,AD20,AD24) -> 0 | AE35: =SUM(AE15,AE20,AE24) -> 0 | AF35: =SUM(AF15,AF20,AF24) -> 0 | AG35: =SUM(AC35:AF35) -> 0 | AH35: =SUM(AH15,AH20,AH24) -> 0 | AI35: =SUM(AI15,AI20,AI24) -> 0 | AJ35: =SUM(AJ15,AJ20,AJ24) -> #VALUE! | AK35: =SUM(AK15,AK20,AK24) -> #VALUE! | AL35: =SUM(AH35:AK35) -> #VALUE! | AM35: =SUM(AM15,AM20,AM24) -> #VALUE! | AN35: =SUM(AN15,AN20,AN24) -> #VALUE! | AO35: =SUM(AO15,AO20,AO24) -> #VALUE! | AP35: =SUM(AP15,AP20,AP24) -> #VALUE! | AQ35: =SUM(AM35:AP35) -> #VALUE! | AR35: =SUM(AR15,AR20,AR24) -> #VALUE! | AS35: =SUM(AS15,AS20,AS24) -> #VALUE! | AT35: =SUM(AT15,AT20,AT24) -> #VALUE! | AU35: =SUM(AU15,AU20,AU24) -> #VALUE! | AV35: =SUM(AR35:AU35) -> #VALUE! | AW35: =SUM(AW15,AW20,AW24) -> #VALUE! | AX35: =SUM(AX15,AX20,AX24) -> #VALUE! | AY35: =SUM(AY15,AY20,AY24) -> #VALUE! | AZ35: =SUM(AZ15,AZ20,AZ24) -> #VALUE! | BA35: =SUM(AW35:AZ35) -> #VALUE! | BB35: =SUM(BB15,BB20,BB24) -> #VALUE! | BC35: =SUM(BC15,BC20,BC24) -> #VALUE! | BD35: =SUM(BD15,BD20,BD24) -> #VALUE! | BE35: =SUM(BE15,BE20,BE24) -> #VALUE! | BF35: =SUM(BB35:BE35) -> #VALUE!
C36: D&A | I36: ='Inputs (2)'!D7 | J36: ='Inputs (2)'!E7 | K36: ='Inputs (2)'!F7 | L36: ='Inputs (2)'!G7 | M36: ='Inputs (2)'!H7 | N36: ='Inputs (2)'!I7 | O36: ='Inputs (2)'!J7 | P36: ='Inputs (2)'!K7 | ... AI36: ='Inputs (2)'!AD7 | AJ36: =-AJ37*AJ15 -> #VALUE! | AK36: =-AK37*AK15 -> #VALUE! | AL36: =SUM(AH36:AK36) -> #VALUE! | AM36: =-AM37*AM15 -> #VALUE! | AN36: =-AN37*AN15 -> #VALUE! | AO36: =-AO37*AO15 -> #VALUE! | AP36: =-AP37*AP15 -> #VALUE! | AQ36: =SUM(AM36:AP36) -> #VALUE! | AR36: =-AR37*AR15 -> #VALUE! | AS36: =-AS37*AS15 -> #VALUE! | AT36: =-AT37*AT15 -> #VALUE! | AU36: =-AU37*AU15 -> #VALUE! | AV36: =SUM(AR36:AU36) -> #VALUE! | AW36: =-AW37*AW15 -> #VALUE! | AX36: =-AX37*AX15 -> #VALUE! | AY36: =-AY37*AY15 -> #VALUE! | AZ36: =-AZ37*AZ15 -> #VALUE! | BA36: =SUM(AW36:AZ36) -> #VALUE! | BB36: =-BB37*BB15 -> #VALUE! | BC36: =-BC37*BC15 -> #VALUE! | BD36: =-BD37*BD15 -> #VALUE! | BE36: =-BE37*BE15 -> #VALUE! | BF36: =SUM(BB36:BE36) -> #VALUE!
C37: % of Revenue | I37: =IFERROR(-I36/I15,"") | J37: =IFERROR(-J36/J15,"") | K37: =IFERROR(-K36/K15,"") | L37: =IFERROR(-L36/L15,"") | N37: =IFERROR(-N36/N15,"") | O37: =IFERROR(-O36/O15,"") | P37: =IFERROR(-P36/P15,"") | Q37: =IFERROR(-Q36/Q15,"") | S37: =IFERROR(-S36/S15,"") | T37: =IFERROR(-T36/T15,"") | U37: =IFERROR(-U36/U15,"") | V37: =IFERROR(-V36/V15,"") | X37: =IFERROR(-X36/X15,"") | Y37: =IFERROR(-Y36/Y15,"") | Z37: =IFERROR(-Z36/Z15,"") | AA37: =IFERROR(-AA36/AA15,"") | AC37: =IFERROR(-AC36/AC15,"") | AD37: =IFERROR(-AD36/AD15,"") | AE37: =IFERROR(-AE36/AE15,"") | AJ37: =Control!$B$21 | AK37: =Control!$B$21 | AM37: =Control!$C$21 | AN37: =Control!$C$21 | AO37: =Control!$C$21 | AP37: =Control!$C$21 | AR37: =Control!$D$21 | AS37: =Control!$D$21 | AT37: =Control!$D$21 | AU37: =Control!$D$21 | AW37: =Control!$E$21 | AX37: =Control!$E$21 | AY37: =Control!$E$21 | AZ37: =Control!$E$21 | BB37: =Control!$F$21 | BC37: =Control!$F$21 | BD37: =Control!$F$21 | BE37: =Control!$F$21
C39: Operating Profit - EBIT | I39: =SUM(I35,I36) -> 0 | J39: =SUM(J35,J36) -> 0 | K39: =SUM(K35,K36) -> 0 | L39: =SUM(L35,L36) -> 0 | M39: =SUM(I39:L39) -> 0 | N39: =SUM(N35,N36) -> 0 | O39: =SUM(O35,O36) -> 0 | P39: =SUM(P35,P36) -> 0 | Q39: =SUM(Q35,Q36) -> 0 | R39: =SUM(N39:Q39) -> 0 | S39: =SUM(S35,S36) -> 0 | T39: =SUM(T35,T36) -> 0 | U39: =SUM(U35,U36) -> 0 | V39: =SUM(V35,V36) -> 0 | W39: =SUM(S39:V39) -> 0 | X39: =SUM(X35,X36) -> 0 | Y39: =SUM(Y35,Y36) -> 0 | Z39: =SUM(Z35,Z36) -> 0 | AA39: =SUM(AA35,AA36) -> 0 | AB39: =SUM(X39:AA39) -> 0 | AC39: =SUM(AC35,AC36) -> 0 | AD39: =SUM(AD35,AD36) -> 0 | AE39: =SUM(AE35,AE36) -> 0 | AF39: =SUM(AF35,AF36) -> 0 | AG39: =SUM(AC39:AF39) -> 0 | AH39: =SUM(AH35,AH36) -> 0 | AI39: =SUM(AI35,AI36) -> 0 | AJ39: =SUM(AJ35,AJ36) -> #VALUE! | AK39: =SUM(AK35,AK36) -> #VALUE! | AL39: =SUM(AL35,AL36) -> #VALUE! | AM39: =SUM(AM35,AM36) -> #VALUE! | AN39: =SUM(AN35,AN36) -> #VALUE! | AO39: =SUM(AO35,AO36) -> #VALUE! | ... BF39: =SUM(BF35,BF36) -> #VALUE!
C40: Interest Expense | I40: ='Inputs (2)'!D8 | J40: ='Inputs (2)'!E8 | K40: ='Inputs (2)'!F8 | L40: ='Inputs (2)'!G8 | M40: ='Inputs (2)'!H8 | N40: ='Inputs (2)'!I8 | O40: ='Inputs (2)'!J8 | P40: ='Inputs (2)'!K8 | ... AI40: ='Inputs (2)'!AD8 | AJ40: =IF(Control!$E$9="","",-AI58*Control!$E$9/4) | AK40: =IF(Control!$E$9="","",-AJ58*Control!$E$9/4) | AL40: =SUM(AH40:AK40) -> 0 | AM40: =IF(Control!$E$9="","",-AL58*Control!$E$9/4) | AN40: =IF(Control!$E$9="","",-AM58*Control!$E$9/4) | AO40: =IF(Control!$E$9="","",-AN58*Control!$E$9/4) | AP40: =IF(Control!$E$9="","",-AO58*Control!$E$9/4) | AQ40: =SUM(AM40:AP40) -> 0 | AR40: =IF(Control!$E$9="","",-AQ58*Control!$E$9/4) | AS40: =IF(Control!$E$9="","",-AR58*Control!$E$9/4) | AT40: =IF(Control!$E$9="","",-AS58*Control!$E$9/4) | AU40: =IF(Control!$E$9="","",-AT58*Control!$E$9/4) | AV40: =SUM(AR40:AU40) -> 0 | AW40: =IF(Control!$E$9="","",-AV58*Control!$E$9/4) | AX40: =IF(Control!$E$9="","",-AW58*Control!$E$9/4) | AY40: =IF(Control!$E$9="","",-AX58*Control!$E$9/4) | AZ40: =IF(Control!$E$9="","",-AY58*Control!$E$9/4) | BA40: =SUM(AW40:AZ40) -> 0 | BB40: =IF(Control!$E$9="","",-BA58*Control!$E$9/4) | BC40: =IF(Control!$E$9="","",-BB58*Control!$E$9/4) | BD40: =IF(Control!$E$9="","",-BC58*Control!$E$9/4) | BE40: =IF(Control!$E$9="","",-BD58*Control!$E$9/4) | BF40: =SUM(BB40:BE40) -> 0
C41: % of Debt | I41: =IFERROR(-I40/SUM(I178+I183),"") | J41: =IFERROR(-J40/SUM(J178+J183),"") | K41: =IFERROR(-K40/SUM(K178+K183),"") | L41: =IFERROR(-L40/SUM(L178+L183),"") | N41: =IFERROR(-N40/SUM(N178+N183),"") | O41: =IFERROR(-O40/SUM(O178+O183),"") | P41: =IFERROR(-P40/SUM(P178+P183),"") | Q41: =IFERROR(-Q40/SUM(Q178+Q183),"") | S41: =IFERROR(-S40/SUM(S178+S183),"") | T41: =IFERROR(-T40/SUM(T178+T183),"") | U41: =IFERROR(-U40/SUM(U178+U183),"") | V41: =IFERROR(-V40/SUM(V178+V183),"") | X41: =IFERROR(-X40/SUM(X178+X183),"") | Y41: =IFERROR(-Y40/SUM(Y178+Y183),"") | Z41: =IFERROR(-Z40/SUM(Z178+Z183),"") | AA41: =IFERROR(-AA40/SUM(AA178+AA183),"") | AC41: =IFERROR(-AC40/SUM(AC178+AC183),"") | AD41: =IFERROR(-AD40/SUM(AD178+AD183),"") | AE41: =IFERROR(-AE40/SUM(AE178+AE183),"") | AJ41: =IFERROR(Control!$E$9,0) | AK41: =IFERROR(Control!$E$9,0) | AM41: =IFERROR(Control!$E$9,0) | AN41: =IFERROR(Control!$E$9,0) | AO41: =IFERROR(Control!$E$9,0) | AP41: =IFERROR(Control!$E$9,0) | AR41: =IFERROR(Control!$E$9,0) | AS41: =IFERROR(Control!$E$9,0) | AT41: =IFERROR(Control!$E$9,0) | AU41: =IFERROR(Control!$E$9,0) | AW41: =IFERROR(Control!$E$9,0) | AX41: =IFERROR(Control!$E$9,0) | AY41: =IFERROR(Control!$E$9,0) | AZ41: =IFERROR(Control!$E$9,0) | BB41: =IFERROR(Control!$E$9,0) | BC41: =IFERROR(Control!$E$9,0) | BD41: =IFERROR(Control!$E$9,0) | BE41: =IFERROR(Control!$E$9,0)
C42: %CDI
C45: RECEITA FINANCEIRA
C46: DESPESA FINANCEIRA
C47: OUTROS
C49: Cash and equivalents (inc. investment securities)
C50: Interest on cash
C51: Average interest rate
C52: % CDI
C54: Current portion of long-term debt
C55: Short term debt (Revolving credit facility)
C56: Long term debt
C57: Convertible debt
... C87: CHECK [EX IFRS-16]
C89: Nonoperating Income / (Loss) | I89: ='Inputs (2)'!D9 | J89: ='Inputs (2)'!E9 | K89: ='Inputs (2)'!F9 | L89: ='Inputs (2)'!G9 | M89: ='Inputs (2)'!H9 | N89: ='Inputs (2)'!I9 | O89: ='Inputs (2)'!J9 | P89: ='Inputs (2)'!K9 | ... AI89: ='Inputs (2)'!AD9 | AJ89: =AJ15*Control!$B$23 -> #VALUE! | AK89: =AK15*Control!$B$23 -> #VALUE! | AL89: =SUM(AH89:AK89) -> #VALUE! | AM89: =AM15*Control!$C$23 -> #VALUE! | AN89: =AN15*Control!$C$23 -> #VALUE! | AO89: =AO15*Control!$C$23 -> #VALUE! | AP89: =AP15*Control!$C$23 -> #VALUE! | AQ89: =SUM(AM89:AP89) -> #VALUE! | AR89: =AR15*Control!$D$23 -> #VALUE! | AS89: =AS15*Control!$D$23 -> #VALUE! | AT89: =AT15*Control!$D$23 -> #VALUE! | AU89: =AU15*Control!$D$23 -> #VALUE! | AV89: =SUM(AR89:AU89) -> #VALUE! | AW89: =AW15*Control!$E$23 -> #VALUE! | AX89: =AX15*Control!$E$23 -> #VALUE! | AY89: =AY15*Control!$E$23 -> #VALUE! | AZ89: =AZ15*Control!$E$23 -> #VALUE! | BA89: =SUM(AW89:AZ89) -> #VALUE! | BB89: =BB15*Control!$F$23 -> #VALUE! | BC89: =BC15*Control!$F$23 -> #VALUE! | BD89: =BD15*Control!$F$23 -> #VALUE! | BE89: =BE15*Control!$F$23 -> #VALUE! | BF89: =SUM(BB89:BE89) -> #VALUE!
C91: Resultado Não Recorrente
C92: Plano de Opção de Compra de Ações
C93: Baixa Imobilizado
C96: Pretax Income - EBT | I96: =SUM(I39,I40,I89) -> 0 | J96: =SUM(J39,J40,J89) -> 0 | K96: =SUM(K39,K40,K89) -> 0 | L96: =SUM(L39,L40,L89) -> 0 | M96: =SUM(I96:L96) -> 0 | N96: =SUM(N39,N40,N89) -> 0 | O96: =SUM(O39,O40,O89) -> 0 | P96: =SUM(P39,P40,P89) -> 0 | Q96: =SUM(Q39,Q40,Q89) -> 0 | R96: =SUM(N96:Q96) -> 0 | S96: =SUM(S39,S40,S89) -> 0 | T96: =SUM(T39,T40,T89) -> 0 | U96: =SUM(U39,U40,U89) -> 0 | V96: =SUM(V39,V40,V89) -> 0 | W96: =SUM(S96:V96) -> 0 | X96: =SUM(X39,X40,X89) -> 0 | Y96: =SUM(Y39,Y40,Y89) -> 0 | Z96: =SUM(Z39,Z40,Z89) -> 0 | AA96: =SUM(AA39,AA40,AA89) -> 0 | AB96: =SUM(X96:AA96) -> 0 | AC96: =SUM(AC39,AC40,AC89) -> 0 | AD96: =SUM(AD39,AD40,AD89) -> 0 | AE96: =SUM(AE39,AE40,AE89) -> 0 | AF96: =SUM(AF39,AF40,AF89) -> 0 | AG96: =SUM(AC96:AF96) -> 0 | AH96: =SUM(AH39,AH40,AH89) -> 0 | AI96: =SUM(AI39,AI40,AI89) -> 0 | AJ96: =SUM(AJ39,AJ40,AJ89:AJ94) -> #VALUE! | AK96: =SUM(AK39,AK40,AK89:AK94) -> #VALUE! | AL96: =SUM(AH96:AK96) -> #VALUE! | AM96: =SUM(AM39,AM40,AM89:AM94) -> #VALUE! | AN96: =SUM(AN39,AN40,AN89:AN94) -> #VALUE! | AO96: =SUM(AO39,AO40,AO89:AO94) -> #VALUE! | AP96: =SUM(AP39,AP40,AP89:AP94) -> #VALUE! | AQ96: =SUM(AM96:AP96) -> #VALUE! | AR96: =SUM(AR39,AR40,AR89:AR94) -> #VALUE! | AS96: =SUM(AS39,AS40,AS89:AS94) -> #VALUE! | AT96: =SUM(AT39,AT40,AT89:AT94) -> #VALUE! | AU96: =SUM(AU39,AU40,AU89:AU94) -> #VALUE! | AV96: =SUM(AR96:AU96) -> #VALUE! | AW96: =SUM(AW39,AW40,AW89:AW94) -> #VALUE! | AX96: =SUM(AX39,AX40,AX89:AX94) -> #VALUE! | AY96: =SUM(AY39,AY40,AY89:AY94) -> #VALUE! | AZ96: =SUM(AZ39,AZ40,AZ89:AZ94) -> #VALUE! | BA96: =SUM(AW96:AZ96) -> #VALUE! | BB96: =SUM(BB39,BB40,BB89:BB94) -> #VALUE! | BC96: =SUM(BC39,BC40,BC89:BC94) -> #VALUE! | BD96: =SUM(BD39,BD40,BD89:BD94) -> #VALUE! | BE96: =SUM(BE39,BE40,BE89:BE94) -> #VALUE! | BF96: =SUM(BB96:BE96) -> #VALUE!
C97: Taxes | I97: ='Inputs (2)'!D10 | J97: ='Inputs (2)'!E10 | K97: ='Inputs (2)'!F10 | L97: ='Inputs (2)'!G10 | M97: ='Inputs (2)'!H10 | N97: ='Inputs (2)'!I10 | O97: ='Inputs (2)'!J10 | P97: ='Inputs (2)'!K10 | ... AI97: ='Inputs (2)'!AD10 | AJ97: =-AJ96*AJ98 -> #VALUE! | AK97: =-AK96*AK98 -> #VALUE! | AL97: =SUM(AH97:AK97) -> #VALUE! | AM97: =-AM96*AM98 -> #VALUE! | AN97: =-AN96*AN98 -> #VALUE! | AO97: =-AO96*AO98 -> #VALUE! | AP97: =-AP96*AP98 -> #VALUE! | AQ97: =SUM(AM97:AP97) -> #VALUE! | AR97: =-AR96*AR98 -> #VALUE! | AS97: =-AS96*AS98 -> #VALUE! | AT97: =-AT96*AT98 -> #VALUE! | AU97: =-AU96*AU98 -> #VALUE! | AV97: =SUM(AR97:AU97) -> #VALUE! | AW97: =-AW96*AW98 -> #VALUE! | AX97: =-AX96*AX98 -> #VALUE! | AY97: =-AY96*AY98 -> #VALUE! | AZ97: =-AZ96*AZ98 -> #VALUE! | BA97: =SUM(AW97:AZ97) -> #VALUE! | BB97: =-BB96*BB98 -> #VALUE! | BC97: =-BC96*BC98 -> #VALUE! | BD97: =-BD96*BD98 -> #VALUE! | BE97: =-BE96*BE98 -> #VALUE! | BF97: =SUM(BB97:BE97) -> #VALUE!
C98: % ETR | I98: =IFERROR(-I97/I96,"") | J98: =IFERROR(-J97/J96,"") | K98: =IFERROR(-K97/K96,"") | L98: =IFERROR(-L97/L96,"") | M98: =IFERROR(-M97/M96,"") | N98: =IFERROR(-N97/N96,"") | O98: =IFERROR(-O97/O96,"") | P98: =IFERROR(-P97/P96,"") | ... AE98: =IFERROR(-AE97/AE96,"") | AG98: =IFERROR(-AG97/AG96,"") | AJ98: =Control!$B$22 | AK98: =Control!$B$22 | AL98: =IFERROR(-AL97/AL96,"") | AM98: =Control!$C$22 | AN98: =Control!$C$22 | AO98: =Control!$C$22 | AP98: =Control!$C$22 | AQ98: =IFERROR(-AQ97/AQ96,"") | AR98: =Control!$D$22 | AS98: =Control!$D$22 | AT98: =Control!$D$22 | AU98: =Control!$D$22 | AV98: =IFERROR(-AV97/AV96,"") | AW98: =Control!$E$22 | AX98: =Control!$E$22 | AY98: =Control!$E$22 | AZ98: =Control!$E$22 | BA98: =IFERROR(-BA97/BA96,"") | BB98: =Control!$F$22 | BC98: =Control!$F$22 | BD98: =Control!$F$22 | BE98: =Control!$F$22 | BF98: =IFERROR(-BF97/BF96,"")
C101: Equity in Income of Affiliates, after tax (enter as +) | I101: ='Inputs (2)'!D11 | J101: ='Inputs (2)'!E11 | K101: ='Inputs (2)'!F11 | L101: ='Inputs (2)'!G11 | M101: ='Inputs (2)'!H11 | N101: ='Inputs (2)'!I11 | O101: ='Inputs (2)'!J11 | P101: ='Inputs (2)'!K11 | ... AI101: ='Inputs (2)'!AD11 | AJ101: =0 -> 0 | AK101: =0 -> 0 | AL101: =SUM(AH101:AK101) -> 0 | AM101: =0 -> 0 | AN101: =0 -> 0 | AO101: =0 -> 0 | AP101: =0 -> 0 | AQ101: =SUM(AM101:AP101) -> 0 | AR101: =0 -> 0 | AS101: =0 -> 0 | AT101: =0 -> 0 | AU101: =0 -> 0 | AV101: =SUM(AR101:AU101) -> 0 | AW101: =0 -> 0 | AX101: =0 -> 0 | AY101: =0 -> 0 | AZ101: =0 -> 0 | BA101: =SUM(AW101:AZ101) -> 0 | BB101: =0 -> 0 | BC101: =0 -> 0 | BD101: =0 -> 0 | BE101: =0 -> 0 | BF101: =SUM(BB101:BE101) -> 0
C102: Minority Interest Expense, after tax (enter as - ) | I102: ='Inputs (2)'!D12 | J102: ='Inputs (2)'!E12 | K102: ='Inputs (2)'!F12 | L102: ='Inputs (2)'!G12 | M102: ='Inputs (2)'!H12 | N102: ='Inputs (2)'!I12 | O102: ='Inputs (2)'!J12 | P102: ='Inputs (2)'!K12 | ... AI102: ='Inputs (2)'!AD12 | AJ102: =0 -> 0 | AK102: =0 -> 0 | AL102: =SUM(AH102:AK102) -> 0 | AM102: =0 -> 0 | AN102: =0 -> 0 | AO102: =0 -> 0 | AP102: =0 -> 0 | AQ102: =SUM(AM102:AP102) -> 0 | AR102: =0 -> 0 | AS102: =0 -> 0 | AT102: =0 -> 0 | AU102: =0 -> 0 | AV102: =SUM(AR102:AU102) -> 0 | AW102: =0 -> 0 | AX102: =0 -> 0 | AY102: =0 -> 0 | AZ102: =0 -> 0 | BA102: =SUM(AW102:AZ102) -> 0 | BB102: =0 -> 0 | BC102: =0 -> 0 | BD102: =0 -> 0 | BE102: =0 -> 0 | BF102: =SUM(BB102:BE102) -> 0
C103: Net Income | I103: =SUM(I96,I97,I101,I102) -> 0 | J103: =SUM(J96,J97,J101,J102) -> 0 | K103: =SUM(K96,K97,K101,K102) -> 0 | L103: =SUM(L96,L97,L101,L102) -> 0 | M103: =SUM(I103:L103) -> 0 | N103: =SUM(N96,N97,N101,N102) -> 0 | O103: =SUM(O96,O97,O101,O102) -> 0 | P103: =SUM(P96,P97,P101,P102) -> 0 | Q103: =SUM(Q96,Q97,Q101,Q102) -> 0 | R103: =SUM(N103:Q103) -> 0 | S103: =SUM(S96,S97,S101,S102) -> 0 | T103: =SUM(T96,T97,T101,T102) -> 0 | U103: =SUM(U96,U97,U101,U102) -> 0 | V103: =SUM(V96,V97,V101,V102) -> 0 | W103: =SUM(S103:V103) -> 0 | X103: =SUM(X96,X97,X101,X102) -> 0 | Y103: =SUM(Y96,Y97,Y101,Y102) -> 0 | Z103: =SUM(Z96,Z97,Z101,Z102) -> 0 | AA103: =SUM(AA96,AA97,AA101,AA102) -> 0 | AB103: =SUM(X103:AA103) -> 0 | AC103: =SUM(AC96,AC97,AC101,AC102) -> 0 | AD103: =SUM(AD96,AD97,AD101,AD102) -> 0 | AE103: =SUM(AE96,AE97,AE101,AE102) -> 0 | AF103: =SUM(AF96,AF97,AF101,AF102) -> 0 | AG103: =SUM(AC103:AF103) -> 0 | AH103: =SUM(AH96,AH97,AH101,AH102) -> 0 | AI103: =SUM(AI96,AI97,AI101,AI102) -> 0 | AJ103: =SUM(AJ96,AJ97,AJ101,AJ102) -> #VALUE! | AK103: =SUM(AK96,AK97,AK101,AK102) -> #VALUE! | AL103: =SUM(AH103:AK103) -> #VALUE! | AM103: =SUM(AM96,AM97,AM101,AM102) -> #VALUE! | AN103: =SUM(AN96,AN97,AN101,AN102) -> #VALUE! | AO103: =SUM(AO96,AO97,AO101,AO102) -> #VALUE! | AP103: =SUM(AP96,AP97,AP101,AP102) -> #VALUE! | AQ103: =SUM(AM103:AP103) -> #VALUE! | AR103: =SUM(AR96,AR97,AR101,AR102) -> #VALUE! | AS103: =SUM(AS96,AS97,AS101,AS102) -> #VALUE! | AT103: =SUM(AT96,AT97,AT101,AT102) -> #VALUE! | AU103: =SUM(AU96,AU97,AU101,AU102) -> #VALUE! | AV103: =SUM(AR103:AU103) -> #VALUE! | AW103: =SUM(AW96,AW97,AW101,AW102) -> #VALUE! | AX103: =SUM(AX96,AX97,AX101,AX102) -> #VALUE! | AY103: =SUM(AY96,AY97,AY101,AY102) -> #VALUE! | AZ103: =SUM(AZ96,AZ97,AZ101,AZ102) -> #VALUE! | BA103: =SUM(AW103:AZ103) -> #VALUE! | BB103: =SUM(BB96,BB97,BB101,BB102) -> #VALUE! | BC103: =SUM(BC96,BC97,BC101,BC102) -> #VALUE! | BD103: =SUM(BD96,BD97,BD101,BD102) -> #VALUE! | BE103: =SUM(BE96,BE97,BE101,BE102) -> #VALUE! | BF103: =SUM(BB103:BE103) -> #VALUE!
C104: Common Dividends | I104: ='Inputs (2)'!D13 | J104: ='Inputs (2)'!E13 | K104: ='Inputs (2)'!F13 | L104: ='Inputs (2)'!G13 | M104: ='Inputs (2)'!H13 | N104: ='Inputs (2)'!I13 | O104: ='Inputs (2)'!J13 | P104: ='Inputs (2)'!K13 | ... AI104: ='Inputs (2)'!AD13 | AJ104: =-MAX(0,AJ103)*Control!$E$15 -> #VALUE! | AK104: =-MAX(0,AK103)*Control!$E$15 -> #VALUE! | AL104: =SUM(AH104:AK104) -> #VALUE! | AM104: =-MAX(0,AM103)*Control!$E$15 -> #VALUE! | AN104: =-MAX(0,AN103)*Control!$E$15 -> #VALUE! | AO104: =-MAX(0,AO103)*Control!$E$15 -> #VALUE! | AP104: =-MAX(0,AP103)*Control!$E$15 -> #VALUE! | AQ104: =SUM(AM104:AP104) -> #VALUE! | AR104: =-MAX(0,AR103)*Control!$E$15 -> #VALUE! | AS104: =-MAX(0,AS103)*Control!$E$15 -> #VALUE! | AT104: =-MAX(0,AT103)*Control!$E$15 -> #VALUE! | AU104: =-MAX(0,AU103)*Control!$E$15 -> #VALUE! | AV104: =SUM(AR104:AU104) -> #VALUE! | AW104: =-MAX(0,AW103)*Control!$E$15 -> #VALUE! | AX104: =-MAX(0,AX103)*Control!$E$15 -> #VALUE! | AY104: =-MAX(0,AY103)*Control!$E$15 -> #VALUE! | AZ104: =-MAX(0,AZ103)*Control!$E$15 -> #VALUE! | BA104: =SUM(AW104:AZ104) -> #VALUE! | BB104: =-MAX(0,BB103)*Control!$E$15 -> #VALUE! | BC104: =-MAX(0,BC103)*Control!$E$15 -> #VALUE! | BD104: =-MAX(0,BD103)*Control!$E$15 -> #VALUE! | BE104: =-MAX(0,BE103)*Control!$E$15 -> #VALUE! | BF104: =SUM(BB104:BE104) -> #VALUE!
C105: % DVD Payout | I105: =IF(I103=0,"",-I104/I103) | J105: =IF(J103=0,"",-J104/J103) | K105: =IF(K103=0,"",-K104/K103) | L105: =IF(L103=0,"",-L104/L103) | M105: =IF(M103=0,"",-M104/M103) | N105: =IF(N103=0,"",-N104/N103) | O105: =IF(O103=0,"",-O104/O103) | P105: =IF(P103=0,"",-P104/P103) | ... BF105: =IF(BF103=0,"",-BF104/BF103) -> #VALUE!
C108: Balance Sheet | I108: =I13 -> 1Q21 | J108: =J13 -> 2Q21 | K108: =K13 -> 3Q21 | L108: =L13 -> 4Q21 | M108: =M13 -> 2021 | N108: =N13 -> 1Q22 | O108: =O13 -> 2Q22 | P108: =P13 -> 3Q22 | ... BF108: =BF13 -> 2030
C110: Cash and equivalents (inc. investment securities) | I110: ='Inputs (2)'!D15 | J110: ='Inputs (2)'!E15 | K110: ='Inputs (2)'!F15 | L110: ='Inputs (2)'!G15 | M110: ='Inputs (2)'!H15 | N110: ='Inputs (2)'!I15 | O110: ='Inputs (2)'!J15 | P110: ='Inputs (2)'!K15 | ... AI110: ='Inputs (2)'!AD15 | AJ110: =AJ239-SUM(AJ111,AJ115,AJ119,AJ120,AJ121,AJ127,AJ132,AJ142,AJ145,AJ146,AJ155) -> #VALUE! | AK110: =AK239-SUM(AK111,AK115,AK119,AK120,AK121,AK127,AK132,AK142,AK145,AK146,AK155) -> #VALUE! | AL110: =AK110 -> #VALUE! | AM110: =AM239-SUM(AM111,AM115,AM119,AM120,AM121,AM127,AM132,AM142,AM145,AM146,AM155) -> #VALUE! | AN110: =AN239-SUM(AN111,AN115,AN119,AN120,AN121,AN127,AN132,AN142,AN145,AN146,AN155) -> #VALUE! | AO110: =AO239-SUM(AO111,AO115,AO119,AO120,AO121,AO127,AO132,AO142,AO145,AO146,AO155) -> #VALUE! | AP110: =AP239-SUM(AP111,AP115,AP119,AP120,AP121,AP127,AP132,AP142,AP145,AP146,AP155) -> #VALUE! | AQ110: =AP110 -> #VALUE! | AR110: =AR239-SUM(AR111,AR115,AR119,AR120,AR121,AR127,AR132,AR142,AR145,AR146,AR155) -> #VALUE! | AS110: =AS239-SUM(AS111,AS115,AS119,AS120,AS121,AS127,AS132,AS142,AS145,AS146,AS155) -> #VALUE! | AT110: =AT239-SUM(AT111,AT115,AT119,AT120,AT121,AT127,AT132,AT142,AT145,AT146,AT155) -> #VALUE! | AU110: =AU239-SUM(AU111,AU115,AU119,AU120,AU121,AU127,AU132,AU142,AU145,AU146,AU155) -> #VALUE! | AV110: =AU110 -> #VALUE! | AW110: =AW239-SUM(AW111,AW115,AW119,AW120,AW121,AW127,AW132,AW142,AW145,AW146,AW155) -> #VALUE! | AX110: =AX239-SUM(AX111,AX115,AX119,AX120,AX121,AX127,AX132,AX142,AX145,AX146,AX155) -> #VALUE! | AY110: =AY239-SUM(AY111,AY115,AY119,AY120,AY121,AY127,AY132,AY142,AY145,AY146,AY155) -> #VALUE! | AZ110: =AZ239-SUM(AZ111,AZ115,AZ119,AZ120,AZ121,AZ127,AZ132,AZ142,AZ145,AZ146,AZ155) -> #VALUE! | BA110: =AZ110 -> #VALUE! | BB110: =BB239-SUM(BB111,BB115,BB119,BB120,BB121,BB127,BB132,BB142,BB145,BB146,BB155) -> #VALUE! | BC110: =BC239-SUM(BC111,BC115,BC119,BC120,BC121,BC127,BC132,BC142,BC145,BC146,BC155) -> #VALUE! | BD110: =BD239-SUM(BD111,BD115,BD119,BD120,BD121,BD127,BD132,BD142,BD145,BD146,BD155) -> #VALUE! | BE110: =BE239-SUM(BE111,BE115,BE119,BE120,BE121,BE127,BE132,BE142,BE145,BE146,BE155) -> #VALUE! | BF110: =BE110 -> #VALUE!
C111: Accounts receivable | I111: ='Inputs (2)'!D16 | J111: ='Inputs (2)'!E16 | K111: ='Inputs (2)'!F16 | L111: ='Inputs (2)'!G16 | M111: ='Inputs (2)'!H16 | N111: ='Inputs (2)'!I16 | O111: ='Inputs (2)'!J16 | P111: ='Inputs (2)'!K16 | ... AI111: ='Inputs (2)'!AD16 | AJ111: =(AJ112/(AJ$5-AI$5))*AJ$15 -> #VALUE! | AK111: =(AK112/(AK$5-AJ$5))*AK$15 -> #VALUE! | AL111: =AK111 -> #VALUE! | AM111: =(AM112/(AM$5-AL$5))*AM$15 -> #VALUE! | AN111: =(AN112/(AN$5-AM$5))*AN$15 -> #VALUE! | AO111: =(AO112/(AO$5-AN$5))*AO$15 -> #VALUE! | AP111: =(AP112/(AP$5-AO$5))*AP$15 -> #VALUE! | AQ111: =AP111 -> #VALUE! | AR111: =(AR112/(AR$5-AQ$5))*AR$15 -> #VALUE! | AS111: =(AS112/(AS$5-AR$5))*AS$15 -> #VALUE! | AT111: =(AT112/(AT$5-AS$5))*AT$15 -> #VALUE! | AU111: =(AU112/(AU$5-AT$5))*AU$15 -> #VALUE! | AV111: =AU111 -> #VALUE! | AW111: =(AW112/(AW$5-AV$5))*AW$15 -> #VALUE! | AX111: =(AX112/(AX$5-AW$5))*AX$15 -> #VALUE! | AY111: =(AY112/(AY$5-AX$5))*AY$15 -> #VALUE! | AZ111: =(AZ112/(AZ$5-AY$5))*AZ$15 -> #VALUE! | BA111: =AZ111 -> #VALUE! | BB111: =(BB112/(BB$5-BA$5))*BB$15 -> #VALUE! | BC111: =(BC112/(BC$5-BB$5))*BC$15 -> #VALUE! | BD111: =(BD112/(BD$5-BC$5))*BD$15 -> #VALUE! | BE111: =(BE112/(BE$5-BD$5))*BE$15 -> #VALUE! | BF111: =BE111 -> #VALUE!
C112: DSO | I112: =IFERROR((I111/I$15)*(I$5-H$5),"") | J112: =IFERROR((J111/J$15)*(J$5-I$5),"") | K112: =IFERROR((K111/K$15)*(K$5-J$5),"") | L112: =IFERROR((L111/L$15)*(L$5-K$5),"") | N112: =IFERROR((N111/N$15)*(N$5-M$5),"") | O112: =IFERROR((O111/O$15)*(O$5-N$5),"") | P112: =IFERROR((P111/P$15)*(P$5-O$5),"") | Q112: =IFERROR((Q111/Q$15)*(Q$5-P$5),"") | S112: =IFERROR((S111/S$15)*(S$5-R$5),"") | T112: =IFERROR((T111/T$15)*(T$5-S$5),"") | U112: =IFERROR((U111/U$15)*(U$5-T$5),"") | V112: =IFERROR((V111/V$15)*(V$5-U$5),"") | X112: =IFERROR((X111/X$15)*(X$5-W$5),"") | Y112: =IFERROR((Y111/Y$15)*(Y$5-X$5),"") | Z112: =IFERROR((Z111/Z$15)*(Z$5-Y$5),"") | AA112: =IFERROR((AA111/AA$15)*(AA$5-Z$5),"") | AC112: =IFERROR((AC111/AC$15)*(AC$5-AB$5),"") | AD112: =IFERROR((AD111/AD$15)*(AD$5-AC$5),"") | AE112: =IFERROR((AE111/AE$15)*(AE$5-AD$5),"") | AJ112: =Control!$B$25 | AK112: =Control!$B$25 | AM112: =Control!$C$25 | AN112: =Control!$C$25 | AO112: =Control!$C$25 | AP112: =Control!$C$25 | AR112: =Control!$D$25 | AS112: =Control!$D$25 | AT112: =Control!$D$25 | AU112: =Control!$D$25 | AW112: =Control!$E$25 | AX112: =Control!$E$25 | AY112: =Control!$E$25 | AZ112: =Control!$E$25 | BB112: =Control!$F$25 | BC112: =Control!$F$25 | BD112: =Control!$F$25 | BE112: =Control!$F$25
C115: Inventories | I115: ='Inputs (2)'!D17 | J115: ='Inputs (2)'!E17 | K115: ='Inputs (2)'!F17 | L115: ='Inputs (2)'!G17 | M115: ='Inputs (2)'!H17 | N115: ='Inputs (2)'!I17 | O115: ='Inputs (2)'!J17 | P115: ='Inputs (2)'!K17 | ... AI115: ='Inputs (2)'!AD17 | AJ115: =(AJ116/(AJ$5-AI$5))*-AJ$20 -> #VALUE! | AK115: =(AK116/(AK$5-AJ$5))*-AK$20 -> #VALUE! | AL115: =AK115 -> #VALUE! | AM115: =(AM116/(AM$5-AL$5))*-AM$20 -> #VALUE! | AN115: =(AN116/(AN$5-AM$5))*-AN$20 -> #VALUE! | AO115: =(AO116/(AO$5-AN$5))*-AO$20 -> #VALUE! | AP115: =(AP116/(AP$5-AO$5))*-AP$20 -> #VALUE! | AQ115: =AP115 -> #VALUE! | AR115: =(AR116/(AR$5-AQ$5))*-AR$20 -> #VALUE! | AS115: =(AS116/(AS$5-AR$5))*-AS$20 -> #VALUE! | AT115: =(AT116/(AT$5-AS$5))*-AT$20 -> #VALUE! | AU115: =(AU116/(AU$5-AT$5))*-AU$20 -> #VALUE! | AV115: =AU115 -> #VALUE! | AW115: =(AW116/(AW$5-AV$5))*-AW$20 -> #VALUE! | AX115: =(AX116/(AX$5-AW$5))*-AX$20 -> #VALUE! | AY115: =(AY116/(AY$5-AX$5))*-AY$20 -> #VALUE! | AZ115: =(AZ116/(AZ$5-AY$5))*-AZ$20 -> #VALUE! | BA115: =AZ115 -> #VALUE! | BB115: =(BB116/(BB$5-BA$5))*-BB$20 -> #VALUE! | BC115: =(BC116/(BC$5-BB$5))*-BC$20 -> #VALUE! | BD115: =(BD116/(BD$5-BC$5))*-BD$20 -> #VALUE! | BE115: =(BE116/(BE$5-BD$5))*-BE$20 -> #VALUE! | BF115: =BE115 -> #VALUE!
C116: DIO | I116: =IFERROR(((I115/I$20)*(I$5-H$5))*-1,"") | J116: =IFERROR(((J115/J$20)*(J$5-I$5))*-1,"") | K116: =IFERROR(((K115/K$20)*(K$5-J$5))*-1,"") | L116: =IFERROR(((L115/L$20)*(L$5-K$5))*-1,"") | N116: =IFERROR(((N115/N$20)*(N$5-M$5))*-1,"") | O116: =IFERROR(((O115/O$20)*(O$5-N$5))*-1,"") | P116: =IFERROR(((P115/P$20)*(P$5-O$5))*-1,"") | Q116: =IFERROR(((Q115/Q$20)*(Q$5-P$5))*-1,"") | S116: =IFERROR(((S115/S$20)*(S$5-R$5))*-1,"") | T116: =IFERROR(((T115/T$20)*(T$5-S$5))*-1,"") | U116: =IFERROR(((U115/U$20)*(U$5-T$5))*-1,"") | V116: =IFERROR(((V115/V$20)*(V$5-U$5))*-1,"") | X116: =IFERROR(((X115/X$20)*(X$5-W$5))*-1,"") | Y116: =IFERROR(((Y115/Y$20)*(Y$5-X$5))*-1,"") | Z116: =IFERROR(((Z115/Z$20)*(Z$5-Y$5))*-1,"") | AA116: =IFERROR(((AA115/AA$20)*(AA$5-Z$5))*-1,"") | AC116: =IFERROR(((AC115/AC$20)*(AC$5-AB$5))*-1,"") | AD116: =IFERROR(((AD115/AD$20)*(AD$5-AC$5))*-1,"") | AE116: =IFERROR(((AE115/AE$20)*(AE$5-AD$5))*-1,"") | AJ116: =Control!$B$26 | AK116: =Control!$B$26 | AM116: =Control!$C$26 | AN116: =Control!$C$26 | AO116: =Control!$C$26 | AP116: =Control!$C$26 | AR116: =Control!$D$26 | AS116: =Control!$D$26 | AT116: =Control!$D$26 | AU116: =Control!$D$26 | AW116: =Control!$E$26 | AX116: =Control!$E$26 | AY116: =Control!$E$26 | AZ116: =Control!$E$26 | BB116: =Control!$F$26 | BC116: =Control!$F$26 | BD116: =Control!$F$26 | BE116: =Control!$F$26
C119: Deferred income taxes | I119: ='Inputs (2)'!D18 | J119: ='Inputs (2)'!E18 | K119: ='Inputs (2)'!F18 | L119: ='Inputs (2)'!G18 | M119: ='Inputs (2)'!H18 | N119: ='Inputs (2)'!I18 | O119: ='Inputs (2)'!J18 | P119: ='Inputs (2)'!K18 | ... AI119: ='Inputs (2)'!AD18 | AJ119: =AI119 | AK119: =AJ119 | AL119: =AK119 | AM119: =AL119 | AN119: =AM119 | AO119: =AN119 | AP119: =AO119 | AQ119: =AP119 | ... BF119: =BE119
C120: Prepaid expenses | I120: ='Inputs (2)'!D19 | J120: ='Inputs (2)'!E19 | K120: ='Inputs (2)'!F19 | L120: ='Inputs (2)'!G19 | M120: ='Inputs (2)'!H19 | N120: ='Inputs (2)'!I19 | O120: ='Inputs (2)'!J19 | P120: ='Inputs (2)'!K19 | ... AI120: ='Inputs (2)'!AD19 | AJ120: =AI120 | AK120: =AJ120 | AL120: =AK120 | AM120: =AL120 | AN120: =AM120 | AO120: =AN120 | AP120: =AO120 | AQ120: =AP120 | ... BF120: =BE120
C121: Other current assets | I121: ='Inputs (2)'!D20 | J121: ='Inputs (2)'!E20 | K121: ='Inputs (2)'!F20 | L121: ='Inputs (2)'!G20 | M121: ='Inputs (2)'!H20 | N121: ='Inputs (2)'!I20 | O121: ='Inputs (2)'!J20 | P121: ='Inputs (2)'!K20 | ... AI121: ='Inputs (2)'!AD20 | AJ121: =AI121 | AK121: =AJ121 | AL121: =AK121 | AM121: =AL121 | AN121: =AM121 | AO121: =AN121 | AP121: =AO121 | AQ121: =AP121 | ... BF121: =BE121
C122: %(Var.) | I122: ="" | J122: =IFERROR(IF(I121=0,"",J121/I121-1),"") | K122: =IFERROR(IF(J121=0,"",K121/J121-1),"") | L122: =IFERROR(IF(K121=0,"",L121/K121-1),"") | M122: =IFERROR(IF(L121=0,"",M121/L121-1),"") | N122: =IFERROR(IF(M121=0,"",N121/M121-1),"") | O122: =IFERROR(IF(N121=0,"",O121/N121-1),"") | P122: =IFERROR(IF(O121=0,"",P121/O121-1),"") | Q122: =IFERROR(IF(P121=0,"",Q121/P121-1),"") | ... BF122: =IFERROR(IF(BE121=0,"",BF121/BE121-1),"")
C124: Impostos e Contribuições a Recuperar | AG124: =AF124 -> 0 | AH124: =IFERROR(AG124*AH15/AG15,"") | AI124: =IFERROR(AH124*AI15/AH15,"") | AJ124: =IFERROR(AI124*AJ15/AI15,"") | AK124: =IFERROR(AJ124*AK15/AJ15,"") | AL124: =IFERROR(AK124,"")
C125: Outros Créditos | AG125: =AF125 -> 0 | AH125: =AG125 -> 0 | AI125: =AH125 -> 0 | AJ125: =AI125 -> 0 | AK125: =AJ125 -> 0 | AL125: =AK125 -> 0
C127: Equity in affiliates | I127: ='Inputs (2)'!D21 | J127: ='Inputs (2)'!E21 | K127: ='Inputs (2)'!F21 | L127: ='Inputs (2)'!G21 | M127: ='Inputs (2)'!H21 | N127: ='Inputs (2)'!I21 | O127: ='Inputs (2)'!J21 | P127: ='Inputs (2)'!K21 | ... AI127: ='Inputs (2)'!AD21 | AJ127: =AI127+AJ101 -> #VALUE! | AK127: =AJ127+AK101 -> #VALUE! | AL127: =AK127 -> #VALUE! | AM127: =AL127+AM101 -> #VALUE! | AN127: =AM127+AN101 -> #VALUE! | AO127: =AN127+AO101 -> #VALUE! | AP127: =AO127+AP101 -> #VALUE! | AQ127: =AP127 -> #VALUE! | AR127: =AQ127+AR101 -> #VALUE! | AS127: =AR127+AS101 -> #VALUE! | AT127: =AS127+AT101 -> #VALUE! | AU127: =AT127+AU101 -> #VALUE! | AV127: =AU127 -> #VALUE! | AW127: =AV127+AW101 -> #VALUE! | AX127: =AW127+AX101 -> #VALUE! | AY127: =AX127+AY101 -> #VALUE! | AZ127: =AY127+AZ101 -> #VALUE! | BA127: =AZ127 -> #VALUE! | BB127: =BA127+BB101 -> #VALUE! | BC127: =BB127+BC101 -> #VALUE! | BD127: =BC127+BD101 -> #VALUE! | BE127: =BD127+BE101 -> #VALUE! | BF127: =BE127 -> #VALUE!
C129: Equity in Income - % YoY | N129: =IF(I101=0,0,N101/I101-1) -> #VALUE! | O129: =IF(J101=0,0,O101/J101-1) -> #VALUE! | P129: =IF(K101=0,0,P101/K101-1) -> #VALUE! | Q129: =IF(L101=0,0,Q101/L101-1) -> #VALUE! | S129: =IF(N101=0,0,S101/N101-1) -> #VALUE! | T129: =IF(O101=0,0,T101/O101-1) -> #VALUE! | U129: =IF(P101=0,0,U101/P101-1) -> #VALUE! | V129: =IF(Q101=0,0,V101/Q101-1) -> #VALUE! | X129: =IF(S101=0,0,X101/S101-1) -> #VALUE! | Y129: =IF(T101=0,0,Y101/T101-1) -> #VALUE! | Z129: =IF(U101=0,0,Z101/U101-1) -> #VALUE! | AA129: =IF(V101=0,0,AA101/V101-1) -> #VALUE! | AC129: =IF(X101=0,0,AC101/X101-1) -> #VALUE! | AD129: =IF(Y101=0,0,AD101/Y101-1) -> #VALUE! | AE129: =IF(Z101=0,0,AE101/Z101-1) -> #VALUE! | AF129: =IF(AA101=0,0,AF101/AA101-1) -> #VALUE!
C130: Dividends (enter as -)
C132: PP&E | I132: ='Inputs (2)'!D22 | J132: ='Inputs (2)'!E22 | K132: ='Inputs (2)'!F22 | L132: ='Inputs (2)'!G22 | M132: ='Inputs (2)'!H22 | N132: ='Inputs (2)'!I22 | O132: ='Inputs (2)'!J22 | P132: ='Inputs (2)'!K22 | ... AI132: ='Inputs (2)'!AD22 | AJ132: =AJ137 -> #VALUE! | AK132: =AK137 -> #VALUE! | AL132: =AK132 -> #VALUE! | AM132: =AM137 -> #VALUE! | AN132: =AN137 -> #VALUE! | AO132: =AO137 -> #VALUE! | AP132: =AP137 -> #VALUE! | AQ132: =AP132 -> #VALUE! | AR132: =AR137 -> #VALUE! | AS132: =AS137 -> #VALUE! | AT132: =AT137 -> #VALUE! | AU132: =AU137 -> #VALUE! | AV132: =AU132 -> #VALUE! | AW132: =AW137 -> #VALUE! | AX132: =AX137 -> #VALUE! | AY132: =AY137 -> #VALUE! | AZ132: =AZ137 -> #VALUE! | BA132: =AZ132 -> #VALUE! | BB132: =BB137 -> #VALUE! | BC132: =BC137 -> #VALUE! | BD132: =BD137 -> #VALUE! | BE132: =BE137 -> #VALUE! | BF132: =BE132 -> #VALUE!
C134: Capital expenditures | J134: =J132-I132-J36 -> #VALUE! | K134: =K132-J132-K36 -> #VALUE! | L134: =L132-K132-L36 -> #VALUE! | N134: =N132-M132-N36 -> #VALUE! | O134: =O132-N132-O36 -> #VALUE! | P134: =P132-O132-P36 -> #VALUE! | Q134: =Q132-P132-Q36 -> #VALUE! | S134: =S132-R132-S36 -> #VALUE! | T134: =T132-S132-T36 -> #VALUE! | U134: =U132-T132-U36 -> #VALUE! | V134: =V132-U132-V36 -> #VALUE! | X134: =X132-W132-X36 -> #VALUE! | Y134: =Y132-X132-Y36 -> #VALUE! | Z134: =Z132-Y132-Z36 -> #VALUE! | AA134: =AA132-Z132-AA36 -> #VALUE! | AC134: =AC132-AB132-AC36 -> #VALUE! | AD134: =AD132-AC132-AD36 -> #VALUE! | AE134: =AE132-AD132-AE36 -> #VALUE! | AG134: =SUM(AC134:AF134) -> #VALUE! | AJ134: =AJ15*Control!$B$24 -> #VALUE! | AK134: =AK15*Control!$B$24 -> #VALUE! | AM134: =AM15*Control!$C$24 -> #VALUE! | AN134: =AN15*Control!$C$24 -> #VALUE! | AO134: =AO15*Control!$C$24 -> #VALUE! | AP134: =AP15*Control!$C$24 -> #VALUE! | AR134: =AR15*Control!$D$24 -> #VALUE! | AS134: =AS15*Control!$D$24 -> #VALUE! | AT134: =AT15*Control!$D$24 -> #VALUE! | AU134: =AU15*Control!$D$24 -> #VALUE! | AW134: =AW15*Control!$E$24 -> #VALUE! | AX134: =AX15*Control!$E$24 -> #VALUE! | AY134: =AY15*Control!$E$24 -> #VALUE! | AZ134: =AZ15*Control!$E$24 -> #VALUE! | BB134: =BB15*Control!$F$24 -> #VALUE! | BC134: =BC15*Control!$F$24 -> #VALUE! | BD134: =BD15*Control!$F$24 -> #VALUE! | BE134: =BE15*Control!$F$24 -> #VALUE!
C135: Recurring asset sales (enter as -) | M135: =SUM(I135:L135) -> 0 | R135: =SUM(N135:Q135) -> 0 | W135: =SUM(S135:V135) -> 0 | AB135: =SUM(X135:AA135) -> 0 | AJ135: =0 -> 0 | AK135: =0 -> 0 | AM135: =0 -> 0 | AN135: =0 -> 0 | AO135: =0 -> 0 | AP135: =0 -> 0 | AR135: =0 -> 0 | AS135: =0 -> 0 | AT135: =0 -> 0 | AU135: =0 -> 0 | AW135: =0 -> 0 | AX135: =0 -> 0 | AY135: =0 -> 0 | AZ135: =0 -> 0 | BB135: =0 -> 0 | BC135: =0 -> 0 | BD135: =0 -> 0 | BE135: =0 -> 0
C136: Depreciation | I136: =I36 | J136: =J36 | K136: =K36 | L136: =L36 | N136: =N36 | O136: =O36 | P136: =P36 | Q136: =Q36 | S136: =S36 | T136: =T36 | U136: =U36 | V136: =V36 | X136: =X36 | Y136: =Y36 | Z136: =Z36 | AA136: =AA36 | AC136: =AC36 | AD136: =AD36 | AE136: =AE36 | AF136: =AF36 | AH136: =AH36 | AI136: =AI36 | AJ136: =AJ36 -> #VALUE! | AK136: =AK36 -> #VALUE! | AM136: =AM36 -> #VALUE! | AN136: =AN36 -> #VALUE! | AO136: =AO36 -> #VALUE! | AP136: =AP36 -> #VALUE! | AR136: =AR36 -> #VALUE! | AS136: =AS36 -> #VALUE! | AT136: =AT36 -> #VALUE! | AU136: =AU36 -> #VALUE! | AW136: =AW36 -> #VALUE! | AX136: =AX36 -> #VALUE! | AY136: =AY36 -> #VALUE! | AZ136: =AZ36 -> #VALUE! | BB136: =BB36 -> #VALUE! | BC136: =BC36 -> #VALUE! | BD136: =BD36 -> #VALUE! | BE136: =BE36 -> #VALUE!
C137: PP&E | I137: =I132 | J137: =J132 | K137: =K132 | L137: =L132 | N137: =N132 | O137: =O132 | P137: =P132 | Q137: =Q132 | S137: =S132 | T137: =T132 | U137: =U132 | V137: =V132 | X137: =X132 | Y137: =Y132 | Z137: =Z132 | AA137: =Y137+SUM(AA134:AA136) -> #VALUE! | AC137: =AC132 | AD137: =AD132 | AE137: =AE132 | AF137: =AE137+SUM(AF134:AF136) -> #VALUE! | AH137: =AF137+SUM(AH134:AH136) -> #VALUE! | AI137: =AH137+SUM(AI134:AI136) -> #VALUE! | AJ137: =AI137+SUM(AJ134:AJ136) -> #VALUE! | AK137: =AJ137+SUM(AK134:AK136) -> #VALUE! | AM137: =AK137+SUM(AM134:AM136) -> #VALUE! | AN137: =AM137+SUM(AN134:AN136) -> #VALUE! | AO137: =AN137+SUM(AO134:AO136) -> #VALUE! | AP137: =AO137+SUM(AP134:AP136) -> #VALUE! | AR137: =AP137+SUM(AR134:AR136) -> #VALUE! | AS137: =AR137+SUM(AS134:AS136) -> #VALUE! | AT137: =AS137+SUM(AT134:AT136) -> #VALUE! | AU137: =AT137+SUM(AU134:AU136) -> #VALUE! | AW137: =AU137+SUM(AW134:AW136) -> #VALUE! | AX137: =AW137+SUM(AX134:AX136) -> #VALUE! | AY137: =AX137+SUM(AY134:AY136) -> #VALUE! | AZ137: =AY137+SUM(AZ134:AZ136) -> #VALUE! | BB137: =AZ137+SUM(BB134:BB136) -> #VALUE! | BC137: =BB137+SUM(BC134:BC136) -> #VALUE! | BD137: =BC137+SUM(BD134:BD136) -> #VALUE! | BE137: =BD137+SUM(BE134:BE136) -> #VALUE!
AJ138: =IF(AJ15=0,"",AJ134/AJ15) -> #VALUE! | AK138: =IF(AK15=0,"",AK134/AK15) -> #VALUE! | AM138: =IF(AM15=0,"",AM134/AM15) -> #VALUE! | AN138: =IF(AN15=0,"",AN134/AN15) -> #VALUE! | AO138: =IF(AO15=0,"",AO134/AO15) -> #VALUE! | AP138: =IF(AP15=0,"",AP134/AP15) -> #VALUE! | AR138: =IF(AR15=0,"",AR134/AR15) -> #VALUE! | AS138: =IF(AS15=0,"",AS134/AS15) -> #VALUE! | AT138: =IF(AT15=0,"",AT134/AT15) -> #VALUE! | AU138: =IF(AU15=0,"",AU134/AU15) -> #VALUE! | AW138: =IF(AW15=0,"",AW134/AW15) -> #VALUE! | AX138: =IF(AX15=0,"",AX134/AX15) -> #VALUE! | AY138: =IF(AY15=0,"",AY134/AY15) -> #VALUE! | AZ138: =IF(AZ15=0,"",AZ134/AZ15) -> #VALUE! | BB138: =IF(BB15=0,"",BB134/BB15) -> #VALUE! | BC138: =IF(BC15=0,"",BC134/BC15) -> #VALUE! | BD138: =IF(BD15=0,"",BD134/BD15) -> #VALUE! | BE138: =IF(BE15=0,"",BE134/BE15) -> #VALUE!
C139: Capital expenditures (% Net Revenues) | AF139: =IFERROR(AF134/AF15,"") | AG139: =IFERROR(AG134/AG15,"") | AH139: =IFERROR(AH134/AH15,"") | AI139: =IFERROR(AI134/AI15,"") | AJ139: =IFERROR(AJ134/AJ15,"") | AK139: =IFERROR(AK134/AK15,"") | AL139: =IFERROR(AL134/AL15,"") | AM139: =IFERROR(AM134/AM15,"") | ... BF139: =IFERROR(BF134/BF15,"")
C142: Right-of-use-assets | I142: ='Inputs (2)'!D23 | J142: ='Inputs (2)'!E23 | K142: ='Inputs (2)'!F23 | L142: ='Inputs (2)'!G23 | M142: ='Inputs (2)'!H23 | N142: ='Inputs (2)'!I23 | O142: ='Inputs (2)'!J23 | P142: ='Inputs (2)'!K23 | ... AI142: ='Inputs (2)'!AD23 | AJ142: =AI142 | AK142: =AJ142 | AL142: =AK142 | AM142: =AL142 | AN142: =AM142 | AO142: =AN142 | AP142: =AO142 | AQ142: =AP142 | ... BF142: =BE142
C143: %(Var.) | I143: ="" | J143: =IFERROR(IF(I142=0,"",J142/I142-1),"") | K143: =IFERROR(IF(J142=0,"",K142/J142-1),"") | L143: =IFERROR(IF(K142=0,"",L142/K142-1),"") | M143: =IFERROR(IF(L142=0,"",M142/L142-1),"") | N143: =IFERROR(IF(M142=0,"",N142/M142-1),"") | O143: =IFERROR(IF(N142=0,"",O142/N142-1),"") | P143: =IFERROR(IF(O142=0,"",P142/O142-1),"") | Q143: =IFERROR(IF(P142=0,"",Q142/P142-1),"") | ... BF143: =IFERROR(IF(BE142=0,"",BF142/BE142-1),"")
C145: Goodwill | I145: ='Inputs (2)'!D24 | J145: ='Inputs (2)'!E24 | K145: ='Inputs (2)'!F24 | L145: ='Inputs (2)'!G24 | M145: ='Inputs (2)'!H24 | N145: ='Inputs (2)'!I24 | O145: ='Inputs (2)'!J24 | P145: ='Inputs (2)'!K24 | ... AI145: ='Inputs (2)'!AD24 | AJ145: =AI145 | AK145: =AJ145 | AL145: =AK145 | AM145: =AL145 | AN145: =AM145 | AO145: =AN145 | AP145: =AO145 | AQ145: =AP145 | ... BF145: =BE145
C146: Intangibles | I146: ='Inputs (2)'!D25 | J146: ='Inputs (2)'!E25 | K146: ='Inputs (2)'!F25 | L146: ='Inputs (2)'!G25 | M146: ='Inputs (2)'!H25 | N146: ='Inputs (2)'!I25 | O146: ='Inputs (2)'!J25 | P146: ='Inputs (2)'!K25 | ... AI146: ='Inputs (2)'!AD25 | AJ146: =AI146 | AK146: =AJ146 | AL146: =AK146 | AM146: =AL146 | AN146: =AM146 | AO146: =AN146 | AP146: =AO146 | AQ146: =AP146 | ... BF146: =BE146
C148: Purchase of intangible assets | I148: =I146-H146-I50 -> #VALUE! | J148: =J146-I146-J50 -> #VALUE! | K148: =K146-J146-K50 -> #VALUE! | L148: =L146-K146-L50 -> #VALUE! | N148: =N146-M146-N50 -> #VALUE! | O148: =O146-N146-O50 -> #VALUE! | P148: =P146-O146-P50 -> #VALUE! | Q148: =Q146-P146-Q50 -> #VALUE! | S148: =S146-R146-S50 -> #VALUE! | T148: =T146-S146-T50 -> #VALUE! | U148: =U146-T146-U50 -> #VALUE! | V148: =V146-U146-V50 -> #VALUE! | X148: =X146-W146-X50 -> #VALUE! | Y148: =Y146-X146-Y50 -> #VALUE! | Z148: =Z146-Y146-Z50 -> #VALUE! | AA148: =AA146-Z146-AA50 -> #VALUE! | AC148: =AC146-AB146-AC50 -> #VALUE! | AD148: =AD146-AC146-AD50 -> #VALUE! | AE148: =AE146-AD146-AE50 -> #VALUE!
C149: Amortization (enter as -) | I149: =I49 -> 0 | J149: =J49 -> 0 | K149: =K49 -> 0 | L149: =L49 -> 0 | N149: =N49 -> 0 | O149: =O49 -> 0 | P149: =P49 -> 0 | Q149: =Q49 -> 0 | S149: =S49 -> 0 | T149: =T49 -> 0 | U149: =U49 -> 0 | V149: =V49 -> 0 | X149: =X49 -> 0 | Y149: =Y49 -> 0 | Z149: =Z49 -> 0 | AA149: =AA49 -> 0 | AC149: =AC49 -> 0 | AD149: =AD49 -> 0 | AE149: =AE49 -> 0 | AH149: =AH49 -> 0
C150: Intangibles | I150: =I145 | J150: =J145 | K150: =K145 | L150: =L145 | N150: =N145 | O150: =O145 | P150: =P145 | Q150: =Q145 | S150: =S145 | T150: =T145 | U150: =U145 | V150: =V145 | X150: =X145 | Y150: =Y145 | Z150: =Z145 | AA150: =AA145 | AC150: =AC145 | AD150: =AD145 | AE150: =AE145 | AH150: =AG150+SUM(AH147:AH149) -> 0 | AI150: =AG150+SUM(AI148:AI149) -> 0 | AJ150: =AJ146 | AK150: =AK146 | AM150: =AM146 | AN150: =AN146 | AO150: =AO146 | AP150: =AP146 | AR150: =AR146 | AS150: =AS146 | AT150: =AT146 | AU150: =AU146 | AW150: =AW146 | AX150: =AX146 | AY150: =AY146 | AZ150: =AZ146 | BB150: =BB146 | BC150: =BC146 | BD150: =BD146 | BE150: =BE146
C152: Definir % do D&A No PPE and Intagibles
C155: Other non-current assets | I155: ='Inputs (2)'!D26 | J155: ='Inputs (2)'!E26 | K155: ='Inputs (2)'!F26 | L155: ='Inputs (2)'!G26 | M155: ='Inputs (2)'!H26 | N155: ='Inputs (2)'!I26 | O155: ='Inputs (2)'!J26 | P155: ='Inputs (2)'!K26 | ... AI155: ='Inputs (2)'!AD26 | AJ155: =AI155 | AK155: =AJ155 | AL155: =AK155 | AM155: =AL155 | AN155: =AM155 | AO155: =AN155 | AP155: =AO155 | AQ155: =AP155 | ... BF155: =BE155
C156: %(Var.) | I156: ="" | J156: =IF(I155=0,"",J155/I155-1) -> #VALUE! | K156: =IF(J155=0,"",K155/J155-1) -> #VALUE! | L156: =IF(K155=0,"",L155/K155-1) -> #VALUE! | M156: =IF(L155=0,"",M155/L155-1) -> #VALUE! | N156: =IF(M155=0,"",N155/M155-1) -> #VALUE! | O156: =IF(N155=0,"",O155/N155-1) -> #VALUE! | P156: =IF(O155=0,"",P155/O155-1) -> #VALUE! | Q156: =IF(P155=0,"",Q155/P155-1) -> #VALUE! | ... BF156: =IF(BE155=0,"",BF155/BE155-1) -> #VALUE!
C158: Outros Créditos - LP
C159: Impostos e Contribuições a Recuperar
C160: Imposto de Renda e Contribuição Social Diferidos
C163: Total Assets | I163: =SUM(I110,I111,I115,I119,I120,I121,I127,I132,I142,I145,I146,I155) -> 0 | J163: =SUM(J110,J111,J115,J119,J120,J121,J127,J132,J142,J145,J146,J155) -> 0 | K163: =SUM(K110,K111,K115,K119,K120,K121,K127,K132,K142,K145,K146,K155) -> 0 | L163: =SUM(L110,L111,L115,L119,L120,L121,L127,L132,L142,L145,L146,L155) -> 0 | M163: =SUM(M110,M111,M115,M119,M120,M121,M127,M132,M142,M145,M146,M155) -> 0 | N163: =SUM(N110,N111,N115,N119,N120,N121,N127,N132,N142,N145,N146,N155) -> 0 | O163: =SUM(O110,O111,O115,O119,O120,O121,O127,O132,O142,O145,O146,O155) -> 0 | P163: =SUM(P110,P111,P115,P119,P120,P121,P127,P132,P142,P145,P146,P155) -> 0 | ... BF163: =SUM(BF110,BF111,BF115,BF119,BF120,BF121,BF127,BF132,BF142,BF145,BF146,BF155) -> #VALUE!
C164: Accounts payable | I164: ='Inputs (2)'!D28 | J164: ='Inputs (2)'!E28 | K164: ='Inputs (2)'!F28 | L164: ='Inputs (2)'!G28 | M164: ='Inputs (2)'!H28 | N164: ='Inputs (2)'!I28 | O164: ='Inputs (2)'!J28 | P164: ='Inputs (2)'!K28 | ... AI164: ='Inputs (2)'!AD28 | AJ164: =(AJ165/(AJ$5-AI$5))*-AJ$20 -> #VALUE! | AK164: =(AK165/(AK$5-AJ$5))*-AK$20 -> #VALUE! | AL164: =AK164 -> #VALUE! | AM164: =(AM165/(AM$5-AL$5))*-AM$20 -> #VALUE! | AN164: =(AN165/(AN$5-AM$5))*-AN$20 -> #VALUE! | AO164: =(AO165/(AO$5-AN$5))*-AO$20 -> #VALUE! | AP164: =(AP165/(AP$5-AO$5))*-AP$20 -> #VALUE! | AQ164: =AP164 -> #VALUE! | AR164: =(AR165/(AR$5-AQ$5))*-AR$20 -> #VALUE! | AS164: =(AS165/(AS$5-AR$5))*-AS$20 -> #VALUE! | AT164: =(AT165/(AT$5-AS$5))*-AT$20 -> #VALUE! | AU164: =(AU165/(AU$5-AT$5))*-AU$20 -> #VALUE! | AV164: =AU164 -> #VALUE! | AW164: =(AW165/(AW$5-AV$5))*-AW$20 -> #VALUE! | AX164: =(AX165/(AX$5-AW$5))*-AX$20 -> #VALUE! | AY164: =(AY165/(AY$5-AX$5))*-AY$20 -> #VALUE! | AZ164: =(AZ165/(AZ$5-AY$5))*-AZ$20 -> #VALUE! | BA164: =AZ164 -> #VALUE! | BB164: =(BB165/(BB$5-BA$5))*-BB$20 -> #VALUE! | BC164: =(BC165/(BC$5-BB$5))*-BC$20 -> #VALUE! | BD164: =(BD165/(BD$5-BC$5))*-BD$20 -> #VALUE! | BE164: =(BE165/(BE$5-BD$5))*-BE$20 -> #VALUE! | BF164: =BE164 -> #VALUE!
C165: DPO | I165: =IFERROR(-(I164/I$20)*(I$5-H$5),"") | J165: =IFERROR(-(J164/J$20)*(J$5-I$5),"") | K165: =IFERROR(-(K164/K$20)*(K$5-J$5),"") | L165: =IFERROR(-(L164/L$20)*(L$5-K$5),"") | N165: =IFERROR(-(N164/N$20)*(N$5-M$5),"") | O165: =IFERROR(-(O164/O$20)*(O$5-N$5),"") | P165: =IFERROR(-(P164/P$20)*(P$5-O$5),"") | Q165: =IFERROR(-(Q164/Q$20)*(Q$5-P$5),"") | S165: =IFERROR(-(S164/S$20)*(S$5-R$5),"") | T165: =IFERROR(-(T164/T$20)*(T$5-S$5),"") | U165: =IFERROR(-(U164/U$20)*(U$5-T$5),"") | V165: =IFERROR(-(V164/V$20)*(V$5-U$5),"") | X165: =IFERROR(-(X164/X$20)*(X$5-W$5),"") | Y165: =IFERROR(-(Y164/Y$20)*(Y$5-X$5),"") | Z165: =IFERROR(-(Z164/Z$20)*(Z$5-Y$5),"") | AA165: =IFERROR(-(AA164/AA$20)*(AA$5-Z$5),"") | AC165: =IFERROR(-(AC164/AC$20)*(AC$5-AB$5),"") | AD165: =IFERROR(-(AD164/AD$20)*(AD$5-AC$5),"") | AE165: =IFERROR(-(AE164/AE$20)*(AE$5-AD$5),"") | AJ165: =Control!$B$27 | AK165: =Control!$B$27 | AM165: =Control!$C$27 | AN165: =Control!$C$27 | AO165: =Control!$C$27 | AP165: =Control!$C$27 | AR165: =Control!$D$27 | AS165: =Control!$D$27 | AT165: =Control!$D$27 | AU165: =Control!$D$27 | AW165: =Control!$E$27 | AX165: =Control!$E$27 | AY165: =Control!$E$27 | AZ165: =Control!$E$27 | BB165: =Control!$F$27 | BC165: =Control!$F$27 | BD165: =Control!$F$27 | BE165: =Control!$F$27
C168: Accrued expenses | I168: ='Inputs (2)'!D29 | J168: ='Inputs (2)'!E29 | K168: ='Inputs (2)'!F29 | L168: ='Inputs (2)'!G29 | M168: ='Inputs (2)'!H29 | N168: ='Inputs (2)'!I29 | O168: ='Inputs (2)'!J29 | P168: ='Inputs (2)'!K29 | ... AI168: ='Inputs (2)'!AD29 | AJ168: =AI168*(1+AJ16) -> #VALUE! | AK168: =AJ168*(1+AK16) -> #VALUE! | AL168: =AK168 -> #VALUE! | AM168: =AL168*(1+AM16) -> #VALUE! | AN168: =AM168*(1+AN16) -> #VALUE! | AO168: =AN168*(1+AO16) -> #VALUE! | AP168: =AO168*(1+AP16) -> #VALUE! | AQ168: =AP168 -> #VALUE! | AR168: =AQ168*(1+AR16) -> #VALUE! | AS168: =AR168*(1+AS16) -> #VALUE! | AT168: =AS168*(1+AT16) -> #VALUE! | AU168: =AT168*(1+AU16) -> #VALUE! | AV168: =AU168 -> #VALUE! | AW168: =AV168*(1+AW16) -> #VALUE! | AX168: =AW168*(1+AX16) -> #VALUE! | AY168: =AX168*(1+AY16) -> #VALUE! | AZ168: =AY168*(1+AZ16) -> #VALUE! | BA168: =AZ168 -> #VALUE! | BB168: =BA168*(1+BB16) -> #VALUE! | BC168: =BB168*(1+BC16) -> #VALUE! | BD168: =BC168*(1+BD16) -> #VALUE! | BE168: =BD168*(1+BE16) -> #VALUE! | BF168: =BE168 -> #VALUE!
C169: %(Var.) | I169: ="" | J169: =IFERROR(IF(I168=0,"",J168/I168-1),"") | K169: =IFERROR(IF(J168=0,"",K168/J168-1),"") | L169: =IFERROR(IF(K168=0,"",L168/K168-1),"") | M169: =IF(L168=0,"",M168/L168-1) -> #VALUE! | N169: =IFERROR(IF(M168=0,"",N168/M168-1),"") | O169: =IFERROR(IF(N168=0,"",O168/N168-1),"") | P169: =IFERROR(IF(O168=0,"",P168/O168-1),"") | Q169: =IFERROR(IF(P168=0,"",Q168/P168-1),"") | R169: =IF(Q168=0,"",R168/Q168-1) -> #VALUE! | S169: =IFERROR(IF(R168=0,"",S168/R168-1),"") | T169: =IFERROR(IF(S168=0,"",T168/S168-1),"") | U169: =IFERROR(IF(T168=0,"",U168/T168-1),"") | V169: =IFERROR(IF(U168=0,"",V168/U168-1),"") | W169: =IF(V168=0,"",W168/V168-1) -> #VALUE! | X169: =IFERROR(IF(W168=0,"",X168/W168-1),"") | Y169: =IFERROR(IF(X168=0,"",Y168/X168-1),"") | Z169: =IFERROR(IF(Y168=0,"",Z168/Y168-1),"") | AA169: =IFERROR(IF(Z168=0,"",AA168/Z168-1),"") | AB169: =IF(AA168=0,"",AB168/AA168-1) -> #VALUE! | AC169: =IFERROR(IF(AB168=0,"",AC168/AB168-1),"") | AD169: =IFERROR(IF(AC168=0,"",AD168/AC168-1),"") | AE169: =IFERROR(IF(AD168=0,"",AE168/AD168-1),"") | AF169: =IFERROR(IF(AE168=0,"",AF168/AE168-1),"") | AG169: =IF(AF168=0,"",AG168/AF168-1) -> #VALUE! | AH169: =IFERROR(IF(AG168=0,"",AH168/AG168-1),"") | AI169: =IFERROR(IF(AH168=0,"",AI168/AH168-1),"") | AJ169: =IFERROR(IF(AI168=0,"",AJ168/AI168-1),"") | AK169: =IF(AJ168=0,"",AK168/AJ168-1) -> #VALUE! | AL169: =IF(AK168=0,"",AL168/AK168-1) -> #VALUE! | AM169: =IF(AL168=0,"",AM168/AL168-1) -> #VALUE! | AN169: =IF(AM168=0,"",AN168/AM168-1) -> #VALUE! | AO169: =IF(AN168=0,"",AO168/AN168-1) -> #VALUE! | AP169: =IF(AO168=0,"",AP168/AO168-1) -> #VALUE! | AQ169: =IF(AP168=0,"",AQ168/AP168-1) -> #VALUE! | AR169: =IF(AQ168=0,"",AR168/AQ168-1) -> #VALUE! | ... BF169: =IF(BE168=0,"",BF168/BE168-1) -> #VALUE!
C170: Taxes payable | I170: ='Inputs (2)'!D30 | J170: ='Inputs (2)'!E30 | K170: ='Inputs (2)'!F30 | L170: ='Inputs (2)'!G30 | M170: ='Inputs (2)'!H30 | N170: ='Inputs (2)'!I30 | O170: ='Inputs (2)'!J30 | P170: ='Inputs (2)'!K30 | ... AI170: ='Inputs (2)'!AD30 | AJ170: =AI170*(1+AJ16) -> #VALUE! | AK170: =AJ170*(1+AK16) -> #VALUE! | AL170: =AK170 -> #VALUE! | AM170: =AL170*(1+AM16) -> #VALUE! | AN170: =AM170*(1+AN16) -> #VALUE! | AO170: =AN170*(1+AO16) -> #VALUE! | AP170: =AO170*(1+AP16) -> #VALUE! | AQ170: =AP170 -> #VALUE! | AR170: =AQ170*(1+AR16) -> #VALUE! | AS170: =AR170*(1+AS16) -> #VALUE! | AT170: =AS170*(1+AT16) -> #VALUE! | AU170: =AT170*(1+AU16) -> #VALUE! | AV170: =AU170 -> #VALUE! | AW170: =AV170*(1+AW16) -> #VALUE! | AX170: =AW170*(1+AX16) -> #VALUE! | AY170: =AX170*(1+AY16) -> #VALUE! | AZ170: =AY170*(1+AZ16) -> #VALUE! | BA170: =AZ170 -> #VALUE! | BB170: =BA170*(1+BB16) -> #VALUE! | BC170: =BB170*(1+BC16) -> #VALUE! | BD170: =BC170*(1+BD16) -> #VALUE! | BE170: =BD170*(1+BE16) -> #VALUE! | BF170: =BE170 -> #VALUE!
C171: Other current liabilities (non-debt) | I171: ='Inputs (2)'!D31 | J171: ='Inputs (2)'!E31 | K171: ='Inputs (2)'!F31 | L171: ='Inputs (2)'!G31 | M171: ='Inputs (2)'!H31 | N171: ='Inputs (2)'!I31 | O171: ='Inputs (2)'!J31 | P171: ='Inputs (2)'!K31 | ... AI171: ='Inputs (2)'!AD31 | AJ171: =AI171 | AK171: =AJ171 | AL171: =AK171 | AM171: =AL171 | AN171: =AM171 | AO171: =AN171 | AP171: =AO171 | AQ171: =AP171 | ... BF171: =BE171
C172: %(Var.) | I172: ="" | J172: =IFERROR(IF(I171=0,"",J171/I171-1),"") | K172: =IFERROR(IF(J171=0,"",K171/J171-1),"") | L172: =IFERROR(IF(K171=0,"",L171/K171-1),"") | M172: =IF(L171=0,"",M171/L171-1) -> #VALUE! | N172: =IFERROR(IF(M171=0,"",N171/M171-1),"") | O172: =IFERROR(IF(N171=0,"",O171/N171-1),"") | P172: =IFERROR(IF(O171=0,"",P171/O171-1),"") | Q172: =IFERROR(IF(P171=0,"",Q171/P171-1),"") | R172: =IF(Q171=0,"",R171/Q171-1) -> #VALUE! | S172: =IFERROR(IF(R171=0,"",S171/R171-1),"") | T172: =IFERROR(IF(S171=0,"",T171/S171-1),"") | U172: =IFERROR(IF(T171=0,"",U171/T171-1),"") | V172: =IFERROR(IF(U171=0,"",V171/U171-1),"") | W172: =IF(V171=0,"",W171/V171-1) -> #VALUE! | X172: =IFERROR(IF(W171=0,"",X171/W171-1),"") | Y172: =IFERROR(IF(X171=0,"",Y171/X171-1),"") | Z172: =IFERROR(IF(Y171=0,"",Z171/Y171-1),"") | AA172: =IFERROR(IF(Z171=0,"",AA171/Z171-1),"") | AB172: =IF(AA171=0,"",AB171/AA171-1) -> #VALUE! | AC172: =IFERROR(IF(AB171=0,"",AC171/AB171-1),"") | AD172: =IFERROR(IF(AC171=0,"",AD171/AC171-1),"") | AE172: =IFERROR(IF(AD171=0,"",AE171/AD171-1),"") | AF172: =IFERROR(IF(AE171=0,"",AF171/AE171-1),"") | AG172: =IF(AF171=0,"",AG171/AF171-1) -> #VALUE! | AH172: =IFERROR(IF(AG171=0,"",AH171/AG171-1),"") | AI172: =IFERROR(IF(AH171=0,"",AI171/AH171-1),"") | AJ172: =IFERROR(IF(AI171=0,"",AJ171/AI171-1),"") | AK172: =IFERROR(IF(AJ171=0,"",AK171/AJ171-1),"") | AL172: =IFERROR(IF(AK171=0,"",AL171/AK171-1),"") | AM172: =IFERROR(IF(AL171=0,"",AM171/AL171-1),"") | AN172: =IFERROR(IF(AM171=0,"",AN171/AM171-1),"") | AO172: =IFERROR(IF(AN171=0,"",AO171/AN171-1),"") | ... BF172: =IFERROR(IF(BE171=0,"",BF171/BE171-1),"")
C174: Dividendos a Pagar
C175: Contas a pagar pela aquisição de controladas
C176: Outros
...

Sheet Valuation
C3: Discounted Cash Flow Model
C4: All figures in millions, except per share data
C7: Ticker | D7: =IF(Control!B4="","",Control!B4) | F7: Last close | G7: =IF(Control!E4="","",Control!E4)
C8: Operating scenario: | D8: =IF(Control!B10=1,"Bull Case",IF(Control!B10=2,"Base Case","Bear Case")) -> Base Case
C9: Last fiscal year end date: | D9: =IF(Control!B12="","",DATE(YEAR(Control!B12)-1,12,31))
C10: Valuation / deal date: | D10: =IF(Control!B12="","",Control!B12)
C11: Stub year fraction: | D11: =IF(Control!B12="","",Control!B13)
C12: Weighted average cost of capital: | D12: =IF(Control!E12="","",Control!E12)
C14: Historicals | G14: Projected Annual Forecast
G15: Granular
D16: 2023 | E16: 2024 | F16: 2025 | G16: 2026 | H16: 2027 | I16: 2028 | J16: 2029 | K16: 2030
D17: 45291 | E17: 45657 | F17: 46022 | G17: 46387 | H17: 46752 | I17: 47118 | J17: 47483 | K17: 47848
C18: Net Revenues | D18: =Model!W15 | E18: =Model!AB15 | F18: =Model!AG15 | G18: =Model!AL15 -> #VALUE! | H18: =Model!AQ15 -> #VALUE! | I18: =Model!AV15 -> #VALUE! | J18: =Model!BA15 -> #VALUE! | K18: =Model!BF15 -> #VALUE!
D19: ="" | E19: =IFERROR(IF(D18=0,"",E18/D18-1),"") | F19: =IFERROR(IF(E18=0,"",F18/E18-1),"") | G19: =IF(F18=0,"",G18/F18-1) -> #VALUE! | H19: =IF(G18=0,"",H18/G18-1) -> #VALUE! | I19: =IF(H18=0,"",I18/H18-1) -> #VALUE! | J19: =IF(I18=0,"",J18/I18-1) -> #VALUE! | K19: =IF(J18=0,"",K18/J18-1) -> #VALUE!
C20: EBITDA | D20: =Model!W35 -> 0 | E20: =Model!AB35 -> 0 | F20: =Model!AG35 -> 0 | G20: =Model!AL35 -> #VALUE! | H20: =Model!AQ35 -> #VALUE! | I20: =Model!AV35 -> #VALUE! | J20: =Model!BA35 -> #VALUE! | K20: =Model!BF35 -> #VALUE!
D21: =IFERROR(IF(D18=0,"",D20/D18),"") | E21: =IFERROR(IF(E18=0,"",E20/E18),"") | F21: =IF(F18=0,"",F20/F18) -> #VALUE! | G21: =IF(G18=0,"",G20/G18) -> #VALUE! | H21: =IF(H18=0,"",H20/H18) -> #VALUE! | I21: =IF(I18=0,"",I20/I18) -> #VALUE! | J21: =IF(J18=0,"",J20/J18) -> #VALUE! | K21: =IF(K18=0,"",K20/K18) -> #VALUE!
C22: EBIT | D22: =Model!W39 -> 0 | E22: =Model!AB39 -> 0 | F22: =Model!AG39 -> 0 | G22: =Model!AL39 -> #VALUE! | H22: =Model!AQ39 -> #VALUE! | I22: =Model!AV39 -> #VALUE! | J22: =Model!BA39 -> #VALUE! | K22: =Model!BF39 -> #VALUE!
D23: =IFERROR(IF(D18=0,"",D22/D18),"") | E23: =IFERROR(IF(E18=0,"",E22/E18),"") | F23: =IF(F18=0,"",F22/F18) -> #VALUE! | G23: =IF(G18=0,"",G22/G18) -> #VALUE! | H23: =IF(H18=0,"",H22/H18) -> #VALUE! | I23: =IF(I18=0,"",I22/I18) -> #VALUE! | J23: =IF(J18=0,"",J22/J18) -> #VALUE! | K23: =IF(K18=0,"",K22/K18) -> #VALUE!
C24: Tax rate | D24: =Model!W98 | E24: =Model!AB98 | F24: =Model!AG98 | G24: =Model!AL98 | H24: =Model!AQ98 | I24: =Model!AV98 | J24: =Model!BA98 | K24: =Model!BF98
C25: NOPLAT | D25: =D22*(1-D24) -> #VALUE! | E25: =E22*(1-E24) -> #VALUE! | F25: =F22*(1-F24) -> #VALUE! | G25: =G22*(1-G24) -> #VALUE! | H25: =H22*(1-H24) -> #VALUE! | I25: =I22*(1-I24) -> #VALUE! | J25: =J22*(1-J24) -> #VALUE! | K25: =K22*(1-K24) -> #VALUE!
C26: Depreciation & Amortization | D26: =-Model!W36 -> #VALUE! | E26: =-Model!AB36 -> #VALUE! | F26: =-Model!AG36 -> #VALUE! | G26: =-Model!AL36 -> #VALUE! | H26: =-Model!AQ36 -> #VALUE! | I26: =-Model!AV36 -> #VALUE! | J26: =-Model!BA36 -> #VALUE! | K26: =-Model!BF36 -> #VALUE!
C27: Cash from working capital | D27: =Model!W245 -> #VALUE! | E27: =Model!AB245 -> #VALUE! | F27: =Model!AG245 -> #VALUE! | G27: =Model!AL245 -> #VALUE! | H27: =Model!AQ245 -> #VALUE! | I27: =Model!AV245 -> #VALUE! | J27: =Model!BA245 -> #VALUE! | K27: =Model!BF245 -> #VALUE!
C28: Accounts receivable | D28: =Model!W246 -> #VALUE! | E28: =Model!AB246 -> #VALUE! | F28: =Model!AG246 -> #VALUE! | G28: =Model!AL246 -> #VALUE! | H28: =Model!AQ246 -> #VALUE! | I28: =Model!AV246 -> #VALUE! | J28: =Model!BA246 -> #VALUE! | K28: =Model!BF246 -> #VALUE!
C29: Inventories | D29: =Model!W247 -> #VALUE! | E29: =Model!AB247 -> #VALUE! | F29: =Model!AG247 -> #VALUE! | G29: =Model!AL247 -> #VALUE! | H29: =Model!AQ247 -> #VALUE! | I29: =Model!AV247 -> #VALUE! | J29: =Model!BA247 -> #VALUE! | K29: =Model!BF247 -> #VALUE!
C30: Deferred income taxes (assets) | D30: =Model!W248 -> #VALUE! | E30: =Model!AB248 -> #VALUE! | F30: =Model!AG248 -> #VALUE! | G30: =Model!AL248 -> #VALUE! | H30: =Model!AQ248 -> #VALUE! | I30: =Model!AV248 -> #VALUE! | J30: =Model!BA248 -> #VALUE! | K30: =Model!BF248 -> #VALUE!
C31: Prepaid expenses | D31: =Model!W249 -> #VALUE! | E31: =Model!AB249 -> #VALUE! | F31: =Model!AG249 -> #VALUE! | G31: =Model!AL249 -> #VALUE! | H31: =Model!AQ249 -> #VALUE! | I31: =Model!AV249 -> #VALUE! | J31: =Model!BA249 -> #VALUE! | K31: =Model!BF249 -> #VALUE!
C32: Other current assets | D32: =Model!W250 -> #VALUE! | E32: =Model!AB250 -> #VALUE! | F32: =Model!AG250 -> #VALUE! | G32: =Model!AL250 -> #VALUE! | H32: =Model!AQ250 -> #VALUE! | I32: =Model!AV250 -> #VALUE! | J32: =Model!BA250 -> #VALUE! | K32: =Model!BF250 -> #VALUE!
C33: Accounts payable | D33: =Model!W251 -> #VALUE! | E33: =Model!AB251 -> #VALUE! | F33: =Model!AG251 -> #VALUE! | G33: =Model!AL251 -> #VALUE! | H33: =Model!AQ251 -> #VALUE! | I33: =Model!AV251 -> #VALUE! | J33: =Model!BA251 -> #VALUE! | K33: =Model!BF251 -> #VALUE!
C34: Accrued expenses | D34: =Model!W252 -> #VALUE! | E34: =Model!AB252 -> #VALUE! | F34: =Model!AG252 -> #VALUE! | G34: =Model!AL252 -> #VALUE! | H34: =Model!AQ252 -> #VALUE! | I34: =Model!AV252 -> #VALUE! | J34: =Model!BA252 -> #VALUE! | K34: =Model!BF252 -> #VALUE!
C35: Taxes payable | D35: =Model!W253 -> #VALUE! | E35: =Model!AB253 -> #VALUE! | F35: =Model!AG253 -> #VALUE! | G35: =Model!AL253 -> #VALUE! | H35: =Model!AQ253 -> #VALUE! | I35: =Model!AV253 -> #VALUE! | J35: =Model!BA253 -> #VALUE! | K35: =Model!BF253 -> #VALUE!
C36: Other current liabilities | D36: =Model!W254 -> #VALUE! | E36: =Model!AB254 -> #VALUE! | F36: =Model!AG254 -> #VALUE! | G36: =Model!AL254 -> #VALUE! | H36: =Model!AQ254 -> #VALUE! | I36: =Model!AV254 -> #VALUE! | J36: =Model!BA254 -> #VALUE! | K36: =Model!BF254 -> #VALUE!
C37: Deferred tax (liabilities) | D37: =Model!W255 -> #VALUE! | E37: =Model!AB255 -> #VALUE! | F37: =Model!AG255 -> #VALUE! | G37: =Model!AL255 -> #VALUE! | H37: =Model!AQ255 -> #VALUE! | I37: =Model!AV255 -> #VALUE! | J37: =Model!BA255 -> #VALUE! | K37: =Model!BF255 -> #VALUE!
C38: Other non-current assets | D38: =(Model!W155-Model!R155)*-1 -> #VALUE! | E38: =(Model!AB155-Model!W155)*-1 -> #VALUE! | F38: =(Model!AG155-Model!AB155)*-1 -> #VALUE! | G38: =(Model!AL155-Model!AG155)*-1 -> #VALUE! | H38: =(Model!AQ155-Model!AL155)*-1 -> #VALUE! | I38: =(Model!AV155-Model!AQ155)*-1 -> #VALUE! | J38: =(Model!BA155-Model!AV155)*-1 -> #VALUE! | K38: =(Model!BF155-Model!BA155)*-1 -> #VALUE!
C39: Other non-current liabilities | D39: =Model!W206-Model!R206 -> #VALUE! | E39: =Model!AB206-Model!W206 -> #VALUE! | F39: =Model!AG206-Model!AB206 -> #VALUE! | G39: =Model!AL206-Model!AG206 -> #VALUE! | H39: =Model!AQ206-Model!AL206 -> #VALUE! | I39: =Model!AV206-Model!AQ206 -> #VALUE! | J39: =Model!BA206-Model!AV206 -> #VALUE! | K39: =Model!BF206-Model!BA206 -> #VALUE!
C40: Capital expenditures | D40: =Model!W261 -> #VALUE! | E40: =Model!AB261 -> #VALUE! | F40: =Model!AG261 -> #VALUE! | G40: =Model!AL261 -> #VALUE! | H40: =Model!AQ261 -> #VALUE! | I40: =Model!AV261 -> #VALUE! | J40: =Model!BA261 -> #VALUE! | K40: =Model!BF261 -> #VALUE!
C41: Capital expenditures [IFRS16 - implied lease payments] | D41: =0 -> 0 | E41: =0 -> 0 | F41: =0 -> 0 | G41: =0 -> 0 | H41: =0 -> 0 | I41: =0 -> 0 | J41: =0 -> 0 | K41: =0 -> 0
C42: Purchase of intangible assets | D42: =0 -> 0 | E42: =0 -> 0 | F42: =0 -> 0 | G42: =0 -> 0 | H42: =0 -> 0 | I42: =0 -> 0 | J42: =0 -> 0 | K42: =0 -> 0
C44: Net Investments | D44: =SUM(D27,D40:D42,D26) -> #VALUE! | E44: =SUM(E27,E40:E42,E26) -> #VALUE! | F44: =SUM(F27,F40:F42,F26) -> #VALUE! | G44: =SUM(G27,G40:G42,G26) -> #VALUE! | H44: =SUM(H27,H40:H42,H26) -> #VALUE! | I44: =SUM(I27,I40:I42,I26) -> #VALUE! | J44: =SUM(J27,J40:J42,J26) -> #VALUE! | K44: =SUM(K27,K40:K42,K26) -> #VALUE!
C46: Invested Capital | D46: =Model!W316 -> 0 | E46: =Model!AB316 -> 0 | F46: =Model!AG316 -> 0 | G46: =Model!AL316 -> 0 | H46: =Model!AQ316 -> 0 | I46: =Model!AV316 -> 0 | J46: =Model!BA316 -> 0 | K46: =Model!BF316 -> 0
C47: Invested Capital (ex Goodwill) | D47: =Model!W317 -> 0 | E47: =Model!AB317 -> 0 | F47: =Model!AG317 -> 0 | G47: =Model!AL317 -> 0 | H47: =Model!AQ317 -> 0 | I47: =Model!AV317 -> 0 | J47: =Model!BA317 -> 0 | K47: =Model!BF317 -> 0
C48: Invested Capital / Net Revenues | D48: =IFERROR(IF(D18=0,"",D46/D18),"") | E48: =IFERROR(IF(E18=0,"",E46/E18),"") | F48: =IF(F18=0,"",F46/F18) -> #VALUE! | G48: =IF(G18=0,"",G46/G18) -> #VALUE! | H48: =IF(H18=0,"",H46/H18) -> #VALUE! | I48: =IF(I18=0,"",I46/I18) -> #VALUE! | J48: =IF(J18=0,"",J46/J18) -> #VALUE! | K48: =IF(K18=0,"",K46/K18) -> #VALUE!
C50: ROIC | D50: =IF(D46=0,"",D25/D46) | E50: =IF(E46=0,"",E25/E46) | F50: =IF(F46=0,"",F25/F46) | G50: =IF(G46=0,"",G25/G46) | H50: =IF(H46=0,"",H25/H46) | I50: =IF(I46=0,"",I25/I46) | J50: =IF(J46=0,"",J25/J46) | K50: =IF(K46=0,"",K25/K46)
C51: Capital Turnover | D51: =IF(D46=0,"",D18/D46) | E51: =IF(E46=0,"",E18/E46) | F51: =IF(F46=0,"",F18/F46) | G51: =IF(G46=0,"",G18/G46) | H51: =IF(H46=0,"",H18/H46) | I51: =IF(I46=0,"",I18/I46) | J51: =IF(J46=0,"",J18/J46) | K51: =IF(K46=0,"",K18/K46)
C53: Unlevered free cash flows = FCFF | D53: =D25+D44 -> #VALUE! | E53: =E25+E44 -> #VALUE! | F53: =F25+F44 -> #VALUE! | G53: =G25+G44 -> #VALUE! | H53: =H25+H44 -> #VALUE! | I53: =I25+I44 -> #VALUE! | J53: =J25+J44 -> #VALUE! | K53: =K25+K44 -> #VALUE!
C54: Discount factor | G54: =IF(Control!E12="","",1/(1+Control!E12)^Control!B13) | H54: =IF(G54="","",G54/(1+Control!E12)) | I54: =IF(H54="","",H54/(1+Control!E12)) | J54: =IF(I54="","",I54/(1+Control!E12)) | K54: =IF(J54="","",J54/(1+Control!E12))
C55: Midyear adjustment factor | G55: =IF(Control!E12="","",(1+Control!E12)^0.5) | H55: =G55 | I55: =H55 | J55: =I55 | K55: =J55
C56: Present value of free cash flows | G56: =IF(G54="","",G53*G54*G55) | H56: =IF(H54="","",H53*H54*H55) | I56: =IF(I54="","",I53*I54*I55) | J56: =IF(J54="","",J53*J54*J55) | K56: =IF(K54="","",K53*K54*K55)
C57: Sum of present values of FCFs | G57: =IF(COUNT(G56:K56)=0,"",SUM(G56:K56))
D59: =IF(Control!B9="","",Control!B9) -> 47848 | H59: =IF(Control!B7="","",Control!B7)
C60: Terminal value | E60: Equity value calculations | I60: Shares Outstanding Worksheet
C62: Key value driver method | E62: Enterprise value | H62: =D80 | I62: Basic Shares Outanding :
C63: g | D63: =IF(Control!E13="","",Control!E13) | E63: Calculation of net debt: | I63: Current Share Price:
C64: RONIC | D64: =K50 | E64: Current portion of long-term debt | H64: =IFERROR(INDEX(Model!$I$178:$BF$178,1,MATCH(Control!$B$7,Model!$I$5:$BF$5,0)),"") | I64: Options / Warrants Data
C65: NOPLAT (t+1) | D65: =K25*(1+D63) -> #VALUE! | E65: Short term debt | H65: =IFERROR(INDEX(Model!$I$179:$BF$179,1,MATCH(Control!$B$7,Model!$I$5:$BF$5,0)),"") | J65: # of options | K65: $ strike
C66: Terminal value | D66: =IF(OR(Control!E12="",D64="",D64<=D63,Control!E12<=D63),"",(D65*(1-D63/D64))/(Control!E12-D63)) | E66: Long term debt | H66: =IFERROR(INDEX(Model!$I$183:$BF$183,1,MATCH(Control!$B$7,Model!$I$5:$BF$5,0)),"") | I66: Batch 1
C67: Midyear adjusted terminal value | D67: =IF(D66="","",D66*K55) | E67: Convertible debt | H67: =IFERROR(INDEX(Model!$I$204:$BF$204,1,MATCH(Control!$B$7,Model!$I$5:$BF$5,0)),"") | I67: Batch 2
C68: Present value of terminal value | D68: =IF(D67="","",D67*K54) | E68: Minority interest | H68: =IFERROR(INDEX(Model!$I$214:$BF$214,1,MATCH(Control!$B$7,Model!$I$5:$BF$5,0)),"") | I68: Batch 3
C69: Enterprise value | D69: =IF(OR(D68="",G57=""),"",D68+G57) | E69: Convertible preferred stock | H69: =IFERROR(INDEX(Model!$I$219:$BF$219,1,MATCH(Control!$B$7,Model!$I$5:$BF$5,0)),"") | I69: Batch 4
E70: Short term operating leases | H70: =IFERROR(INDEX(Model!$I$180:$BF$180,1,MATCH(Control!$B$7,Model!$I$5:$BF$5,0)),"") | I70: Batch 5
C71: Exit multiple method | E71: Long term operating leases | H71: =IFERROR(INDEX(Model!$I$201:$BF$201,1,MATCH(Control!$B$7,Model!$I$5:$BF$5,0)),"") | I71: Batch 6
C72: Exit EV / EBITDA multiple | D72: =IF(Control!E14="","",Control!E14) | E72: Less: Excess cash | H72: =IFERROR(-INDEX(Model!$I$110:$BF$110,1,MATCH(Control!$B$7,Model!$I$5:$BF$5,0)),"") | K72: Total in-the-$ options:
C73: LTM EBITDA at end of projection | D73: =K20 -> #VALUE! | E73: Less: Equity investments | H73: =IFERROR(-INDEX(Model!$I$127:$BF$127,1,MATCH(Control!$B$7,Model!$I$5:$BF$5,0)),"") | K73: Total $ proceeds:
C74: Terminal value | D74: =IF(OR(D72="",D73=""),"",D73*D72) -> #VALUE! | E74: Net debt | H74: =IFERROR(SUM(H64:H73),"") -> 0 | K74: Total shares repurchased:
C75: Present value of terminal value | D75: =IF(OR(D74="",K54="",K55=""),"",D74*K54*K55) -> #VALUE! | E75: Equity value | H75: =IFERROR(IF(H62="","",H62-H74),"") | K75: Basic shares outstanding
C76: Enterprise value | D76: =IF(OR(D75="",G57=""),"",G57+D75) -> #VALUE! | E76: Shares outstanding | H76: =IF(Control!E5="","",Control!E5) | K76: New shares from options:
E77: Equity value / share | H77: =IFERROR(IF(OR(H75="",H76="",H76=0),"",H75/H76),"") | K77: New shares from convert. pref. stock:
C78: Select a terminal value method | K78: New shares from convertible debt:
C79: Perpetual growth = 1 / Exit multiple = 2 | D79: =Control!B11 -> 1 | K79: Total Shares Outstanding:
C80: Enterprise value | D80: =IF(D79=1,D69,D76)
C81: Terminal value as percent of total value | D81: =IFERROR(IF(D79=1,D68/D69,D75/D76),"")
C83: Analysis of WACC
C85: Cost of debt | F85: Capital structure
C86: Cost of debt | D86: =IF(Control!E9="","",Control!E9) | G86: Current capital structure | I86: Target capital structure
C87: Marginal tax rate | D87: =IF(Control!E10="","",Control!E10) | G87: Market value | H87: % Weight | I87: override | J87: % Weight
C88: Cost of debt after tax shield | D88: =IF(D86="","",D86*(1-D87)) | F88: Net debt | G88: =IFERROR(H74,"") -> 0 | H88: =IFERROR(debt/totalcap,"") | J88: =IFERROR(IF(I88,I88,H88),"")
F89: Equity | G89: =L63*L79 -> 0 | H89: =IFERROR(1-H88,"") | J89: =IFERROR(1-debt_weight,"")
C90: Cost of equity | F90: Total | G90: =IFERROR(SUM(G88:G89),"") -> 0
C91: Risk-Free Rate (rf) | D91: =IF(Control!E6="","",Control!E6)
C92: Market Risk Premium (rm-rf) | D92: =IF(Control!E7="","",Control!E7) | F92: Weighted average cost of capital
C93: Raw (observed) beta | D93: =IF(Control!E8="","",Control!E8) | F93: Weighted average cost of capital: | J93: =IF(Control!E12="","",Control!E12)
C94: Cost of equity using relevered industry beta | D94: =IF(COUNT(D91:D93)<3,"",D91+D93*D92)
C96: Industry beta calculation
C97: Comps | D97: Raw beta | E97: Share price | F97: Shares | G97: Market cap. | H97: Debt | I97: D / E | J97: Tax rate | K97: Unl. Beta
C98: =ticker
C99: TICKER 2
C100: TICKER 3
C101: TICKER 4

Sheet Control
A1: CONTROL & ASSUMPTIONS – BASE MODEL
A3: Company | D3: Valuation assumptions
A4: Ticker | D4: Last close (R$/share)
A5: Currency | D5: Shares outstanding (mm)
A6: Model unit | B6: R$ milhões | D6: Risk-free rate
A7: Last actual period | D7: Market risk premium
A8: Quarterly forecast through | B8: 47118 | D8: Beta
A9: Forecast end | B9: 47848 | D9: Pre-tax cost of debt | E9: =IFERROR(-Model!AG40/AVERAGE(Model!AB58,Model!AG58),"")
A10: Scenario (1 Bull / 2 Base / 3 Bear) | B10: 2 | D10: Marginal tax rate
A11: Terminal method (1 Perpetuity / 2 Exit) | B11: 1 | D11: Target debt weight
A12: Valuation date | D12: WACC | E12: =IF(COUNT(E6:E11)<6,"",E11*E9*(1-E10)+(1-E11)*(E6+E8*E7))
A13: Stub year fraction | B13: =IFERROR((DATE(YEAR(B12),12,31)-B12)/365,"") -> 1.0027397 | D13: Terminal growth
D14: Exit EV/EBITDA
D15: Dividend payout
A17: Forecast drivers | B17: 2026E | C17: 2027E | D17: 2028E | E17: 2029E | F17: 2030E
A18: Revenue growth | B18: =IFERROR(AVERAGE(Model!AC16:AF16,Model!AH16:AI16),"") | C18: =IF(B18="","",B18) | D18: =IF(C18="","",MAX(0,C18-0.5%)) | E18: =IF(D18="","",MAX(0,D18-0.5%)) | F18: =IF(E18="","",MAX(0,E18-0.5%))
A19: Gross margin | B19: =IFERROR(AVERAGE(Model!AC21:AF21,Model!AH21:AI21),"") | C19: =IF(B19="","",B19) | D19: =IF(C19="","",C19) | E19: =IF(D19="","",D19) | F19: =IF(E19="","",E19)
A20: SG&A / Revenue | B20: =IFERROR(AVERAGE(Model!AC25:AF25,Model!AH25:AI25),"") | C20: =IF(B20="","",B20) | D20: =IF(C20="","",C20) | E20: =IF(D20="","",D20) | F20: =IF(E20="","",E20)
A21: D&A / Revenue | B21: =IFERROR(AVERAGE(Model!AC37:AF37,Model!AH37:AI37),"") | C21: =IF(B21="","",B21) | D21: =IF(C21="","",C21) | E21: =IF(D21="","",D21) | F21: =IF(E21="","",E21)
A22: Effective tax rate | B22: =IFERROR(AVERAGE(Model!AC98:AF98,Model!AH98:AI98),"") | C22: =IF(B22="","",B22) | D22: =IF(C22="","",C22) | E22: =IF(D22="","",D22) | F22: =IF(E22="","",E22)
A23: Financial income / Revenue | B23: =IFERROR(AVERAGE(Model!AC89:AF89,Model!AH89:AI89)/AVERAGE(Model!AC15:AF15,Model!AH15:AI15),"") | C23: =IF(B23="","",B23) | D23: =IF(C23="","",C23) | E23: =IF(D23="","",D23) | F23: =IF(E23="","",E23)
A24: Capex / Revenue | B24: =IFERROR(-AVERAGE(Model!AC261:AF261,Model!AH261:AI261)/AVERAGE(Model!AC15:AF15,Model!AH15:AI15),"") | C24: =IF(B24="","",B24) | D24: =IF(C24="","",C24) | E24: =IF(D24="","",D24) | F24: =IF(E24="","",E24)
A25: DSO | B25: =IFERROR(AVERAGE(Model!AC112:AF112,Model!AH112:AI112),"") | C25: =IF(B25="","",B25) | D25: =IF(C25="","",C25) | E25: =IF(D25="","",D25) | F25: =IF(E25="","",E25)
A26: DIO | B26: =IFERROR(AVERAGE(Model!AC116:AF116,Model!AH116:AI116),"") | C26: =IF(B26="","",B26) | D26: =IF(C26="","",C26) | E26: =IF(D26="","",D26) | F26: =IF(E26="","",E26)
A27: DPO | B27: =IFERROR(AVERAGE(Model!AC165:AF165,Model!AH165:AI165),"") | C27: =IF(B27="","",B27) | D27: =IF(C27="","",C27) | E27: =IF(D27="","",D27) | F27: =IF(E27="","",E27)
A29: Model status
A30: Source
A31: Unit flow | B31: R$ mil → R$ milhões via Inputs (2)
A32: Historical coverage | B32: =IF(B7="","","1Q21–"&ROUNDUP(MONTH(B7)/3,0)&"Q"&RIGHT(YEAR(B7),2))
A33: Valuation readiness | B33: =IF(OR(B3="",B4=""),"PENDING COMPANY SETUP",IF(OR(E4="",E5="",E12=""),"PENDING MARKET INPUTS","READY")) -> PENDING COMPANY SETUP
