Workbook
Name beta_observed: Valuation!$D$93
Name last_close: Valuation!$G$7
Name ticker: Valuation!$D$7
Name Useful_Life_of_Depreciable_PP_E: "PPElife"
Name beta_observed: #REF!
Name ticker: #REF!
Name costdebtfirm: Valuation!$D$86
Name costequity: Valuation!$D$94
Name debt: Valuation!$G$88
Name debt_weight: Valuation!$J$88
Name g: Valuation!$D$63
Name market_equity: Valuation!$G$89
Name noplat_t1: Valuation!$D$65
Name relevered_beta: Valuation!$M$102
Name risk_free_rate: Valuation!$D$91
Name risk_premium: Valuation!$D$92
Name ronic: Valuation!$D$64
Name stub_year_fraction: Valuation!$D$11
Name totalcap: Valuation!$G$90
Name wacc: Valuation!$D$12

Sheet Inputs
A1: Base histórica normalizada (US$ mil) — convertida da máscara anterior; linhas de origem auditáveis
A2: Fonte / conta original | B2: Código | C2: Conta padronizada | D2: 1Q21 | E2: 2Q21 | F2: 3Q21 | G2: 4Q21 | H2: 2021 | I2: 1Q22 | J2: 2Q22 | K2: 3Q22 | L2: 4Q22 | M2: 2022 | N2: 1Q23 | O2: 2Q23 | P2: 3Q23 | Q2: 4Q23 | R2: 2023 | S2: 1Q24 | T2: 2Q24 | U2: 3Q24 | V2: 4Q24 | W2: 2024 | X2: 1Q25 | Y2: 2Q25 | Z2: 3Q25 | AA2: 4Q25 | AB2: 2025 | AC2: 1Q26 | AD2: 2Q26 | AE2: 3Q26 | AF2: 4Q26 | AG2: 2026
A3: Fonte: ver coluna A de cada linha | C3: Unidade: US$ mil (monetário); demais unidades × 1.000
A4: DRE - trimestre isolado (USD). Brutos SEC XBRL; linhas "derivada" são fórmulas nesta aba | C4: [linha bruta, sem código; lançada nas linhas abaixo]
A5: Receita [us-gaap:Revenues] · fonte · unid. moeda | B5: 1 | C5: Net Revenues | D5: 59147000 | E5: 67742000 | F5: 73786000 | G5: 84965000 | I5: 90500000 | J5: 115681000 | K5: 112070000 | L5: 95429000 | N5: 86564000 | O5: 82914000 | P5: 90760000 | Q5: 84344000 | S5: 83083000 | T5: 93060000 | U5: 90016000 | V5: 83426000 | X5: 83130000 | Y5: 81506000 | Z5: 85294000 | AA5: 82308000 | AC5: 85138000 | AD5: 116017000
A6: Custo da receita (divulgado positivo) [us-gaap:CrudeOilAndProductPurchases] · fonte · unid. moeda | C6: [linha bruta, sem código; lançada nas linhas abaixo] | D6: 32601000 | E6: 37329000 | F6: 39745000 | G6: 45489000 | I6: 52388000 | J6: 65613000 | K6: 60197000 | L6: 50761000 | N6: 46003000 | O6: 47598000 | P6: 53076000 | Q6: 46352000 | S6: 47601000 | T6: 54199000 | U6: 51261000 | V6: 46393000 | X6: 46788000 | Y6: 45327000 | Z6: 47928000 | AA6: 44205000 | AC6: 51802000 | AD6: 67801000
A7: (lançamento) código 2, sinal -1 sobre a linha bruta 6: Custo da receita (divulgado positivo) [us-gaap:CrudeOilAndProductPurchases] | B7: 2 | C7: COGS (cash) | D7: =IF(D6="","",-1*D6) -> -32601000 | E7: =IF(E6="","",-1*E6) -> -37329000 | F7: =IF(F6="","",-1*F6) -> -39745000 | G7: =IF(G6="","",-1*G6) -> -45489000 | I7: =IF(I6="","",-1*I6) -> -52388000 | J7: =IF(J6="","",-1*J6) -> -65613000 | K7: =IF(K6="","",-1*K6) -> -60197000 | L7: =IF(L6="","",-1*L6) -> -50761000 | N7: =IF(N6="","",-1*N6) -> -46003000 | O7: =IF(O6="","",-1*O6) -> -47598000 | P7: =IF(P6="","",-1*P6) -> -53076000 | Q7: =IF(Q6="","",-1*Q6) -> -46352000 | S7: =IF(S6="","",-1*S6) -> -47601000 | T7: =IF(T6="","",-1*T6) -> -54199000 | U7: =IF(U6="","",-1*U6) -> -51261000 | V7: =IF(V6="","",-1*V6) -> -46393000 | X7: =IF(X6="","",-1*X6) -> -46788000 | Y7: =IF(Y6="","",-1*Y6) -> -45327000 | Z7: =IF(Z6="","",-1*Z6) -> -47928000 | AA7: =IF(AA6="","",-1*AA6) -> -44205000 | AC7: =IF(AC6="","",-1*AC6) -> -51802000 | AD7: =IF(AD6="","",-1*AD6) -> -67801000
A8: Lucro operacional DERIVADO = receita - custos e despesas totais [us-gaap:CostsAndExpenses] + despesa de juros (a companhia não divulga lucro operacional) · memoria · unid. moeda | C8: [linha bruta, sem código; lançada nas linhas abaixo] | D8: 3850000 | E8: 6561000 | F8: 9820000 | G8: 11950000 | I8: 8744000 | J8: 25127000 | K8: 25631000 | L8: 19049000 | N8: 16962000 | O8: 11905000 | P8: 13868000 | Q8: 10897000 | S8: 12590000 | T8: 13936000 | U8: 13233000 | V8: 10110000 | X8: 11805000 | Y8: 10850000 | Z8: 11022000 | AA8: 8194000 | AC8: 7262000 | AD8: 19651000
A9: Despesas operacionais = receita - custo - lucro operacional (P&D + SG&A + outras operacionais) · derivada · unid. moeda | C9: [linha bruta, sem código; lançada nas linhas abaixo] | D9: =N(D5)-N(D6)-N(D8) -> 22696000 | E9: =N(E5)-N(E6)-N(E8) -> 23852000 | F9: =N(F5)-N(F6)-N(F8) -> 24221000 | G9: =N(G5)-N(G6)-N(G8) -> 27526000 | I9: =N(I5)-N(I6)-N(I8) -> 29368000 | J9: =N(J5)-N(J6)-N(J8) -> 24941000 | K9: =N(K5)-N(K6)-N(K8) -> 26242000 | L9: =N(L5)-N(L6)-N(L8) -> 25619000 | N9: =N(N5)-N(N6)-N(N8) -> 23599000 | O9: =N(O5)-N(O6)-N(O8) -> 23411000 | P9: =N(P5)-N(P6)-N(P8) -> 23816000 | Q9: =N(Q5)-N(Q6)-N(Q8) -> 27095000 | S9: =N(S5)-N(S6)-N(S8) -> 22892000 | T9: =N(T5)-N(T6)-N(T8) -> 24925000 | U9: =N(U5)-N(U6)-N(U8) -> 25522000 | V9: =N(V5)-N(V6)-N(V8) -> 26923000 | X9: =N(X5)-N(X6)-N(X8) -> 24537000 | Y9: =N(Y5)-N(Y6)-N(Y8) -> 25329000 | Z9: =N(Z5)-N(Z6)-N(Z8) -> 26344000 | AA9: =N(AA5)-N(AA6)-N(AA8) -> 29909000 | AC9: =N(AC5)-N(AC6)-N(AC8) -> 26074000 | AD9: =N(AD5)-N(AD6)-N(AD8) -> 28565000
A10: (lançamento) código 3, sinal -1 sobre a linha bruta 9: Despesas operacionais = receita - custo - lucro operacional (P&D + SG&A + outras operacion | B10: 3 | C10: SG&A and Other (cash) | D10: =IF(D9="","",-1*D9) -> -22696000 | E10: =IF(E9="","",-1*E9) -> -23852000 | F10: =IF(F9="","",-1*F9) -> -24221000 | G10: =IF(G9="","",-1*G9) -> -27526000 | I10: =IF(I9="","",-1*I9) -> -29368000 | J10: =IF(J9="","",-1*J9) -> -24941000 | K10: =IF(K9="","",-1*K9) -> -26242000 | L10: =IF(L9="","",-1*L9) -> -25619000 | N10: =IF(N9="","",-1*N9) -> -23599000 | O10: =IF(O9="","",-1*O9) -> -23411000 | P10: =IF(P9="","",-1*P9) -> -23816000 | Q10: =IF(Q9="","",-1*Q9) -> -27095000 | S10: =IF(S9="","",-1*S9) -> -22892000 | T10: =IF(T9="","",-1*T9) -> -24925000 | U10: =IF(U9="","",-1*U9) -> -25522000 | V10: =IF(V9="","",-1*V9) -> -26923000 | X10: =IF(X9="","",-1*X9) -> -24537000 | Y10: =IF(Y9="","",-1*Y9) -> -25329000 | Z10: =IF(Z9="","",-1*Z9) -> -26344000 | AA10: =IF(AA9="","",-1*AA9) -> -29909000 | AC10: =IF(AC9="","",-1*AC9) -> -26074000 | AD10: =IF(AD9="","",-1*AD9) -> -28565000
A11: Lucro antes do IR [us-gaap:IncomeLossFromContinuingOperationsBeforeIncomeTaxesExtraordi] · memoria · unid. moeda | C11: [linha bruta, sem código; lançada nas linhas abaixo] | D11: 3592000 | E11: 6307000 | F11: 9606000 | G11: 11729000 | I11: 8556000 | J11: 24933000 | K11: 25422000 | L11: 18842000 | N11: 16803000 | O11: 11656000 | P11: 13699000 | Q11: 10625000 | S11: 12369000 | T11: 13665000 | U11: 13026000 | V11: 9813000 | X11: 11600000 | Y11: 10705000 | Z11: 10932000 | AA11: 8031000 | AC11: 6967000 | AD11: 19424000
A12: Resultado não operacional total = lucro antes do IR - lucro operacional · derivada · unid. moeda | B12: 6 | C12: Nonoperating Income / (Loss) | D12: =N(D11)-N(D8) -> -258000 | E12: =N(E11)-N(E8) -> -254000 | F12: =N(F11)-N(F8) -> -214000 | G12: =N(G11)-N(G8) -> -221000 | I12: =N(I11)-N(I8) -> -188000 | J12: =N(J11)-N(J8) -> -194000 | K12: =N(K11)-N(K8) -> -209000 | L12: =N(L11)-N(L8) -> -207000 | N12: =N(N11)-N(N8) -> -159000 | O12: =N(O11)-N(O8) -> -249000 | P12: =N(P11)-N(P8) -> -169000 | Q12: =N(Q11)-N(Q8) -> -272000 | S12: =N(S11)-N(S8) -> -221000 | T12: =N(T11)-N(T8) -> -271000 | U12: =N(U11)-N(U8) -> -207000 | V12: =N(V11)-N(V8) -> -297000 | X12: =N(X11)-N(X8) -> -205000 | Y12: =N(Y11)-N(Y8) -> -145000 | Z12: =N(Z11)-N(Z8) -> -90000 | AA12: =N(AA11)-N(AA8) -> -163000 | AC12: =N(AC11)-N(AC8) -> -295000 | AD12: =N(AD11)-N(AD8) -> -227000
A13: Despesa de juros (divulgado positivo): COD1=5 lança; COD2=6 devolve ao não operacional, que já a contém [us-gaap:InterestExpense/InterestExpenseNonoperating] · fonte · unid. moeda | C13: [linha bruta, sem código; lançada nas linhas abaixo] | D13: 258000 | E13: 254000 | F13: 214000 | G13: 221000 | I13: 188000 | J13: 194000 | K13: 209000 | L13: 207000 | N13: 159000 | O13: 249000 | P13: 169000 | Q13: 272000 | S13: 221000 | T13: 271000 | U13: 207000 | V13: 297000 | X13: 205000 | Y13: 145000 | Z13: 90000 | AA13: 163000 | AC13: 295000 | AD13: 227000
A14: (lançamento) código 5, sinal -1 sobre a linha bruta 13: Despesa de juros (divulgado positivo): COD1=5 lança; COD2=6 devolve ao não operacional, qu | B14: 5 | C14: Interest Expense | D14: =IF(D13="","",-1*D13) -> -258000 | E14: =IF(E13="","",-1*E13) -> -254000 | F14: =IF(F13="","",-1*F13) -> -214000 | G14: =IF(G13="","",-1*G13) -> -221000 | I14: =IF(I13="","",-1*I13) -> -188000 | J14: =IF(J13="","",-1*J13) -> -194000 | K14: =IF(K13="","",-1*K13) -> -209000 | L14: =IF(L13="","",-1*L13) -> -207000 | N14: =IF(N13="","",-1*N13) -> -159000 | O14: =IF(O13="","",-1*O13) -> -249000 | P14: =IF(P13="","",-1*P13) -> -169000 | Q14: =IF(Q13="","",-1*Q13) -> -272000 | S14: =IF(S13="","",-1*S13) -> -221000 | T14: =IF(T13="","",-1*T13) -> -271000 | U14: =IF(U13="","",-1*U13) -> -207000 | V14: =IF(V13="","",-1*V13) -> -297000 | X14: =IF(X13="","",-1*X13) -> -205000 | Y14: =IF(Y13="","",-1*Y13) -> -145000 | Z14: =IF(Z13="","",-1*Z13) -> -90000 | AA14: =IF(AA13="","",-1*AA13) -> -163000 | AC14: =IF(AC13="","",-1*AC13) -> -295000 | AD14: =IF(AD13="","",-1*AD13) -> -227000
A15: (lançamento) código 6, sinal +1 sobre a linha bruta 13: Despesa de juros (divulgado positivo): COD1=5 lança; COD2=6 devolve ao não operacional, qu | B15: 6 | C15: Nonoperating Income / (Loss) | D15: =IF(D13="","",D13) -> 258000 | E15: =IF(E13="","",E13) -> 254000 | F15: =IF(F13="","",F13) -> 214000 | G15: =IF(G13="","",G13) -> 221000 | I15: =IF(I13="","",I13) -> 188000 | J15: =IF(J13="","",J13) -> 194000 | K15: =IF(K13="","",K13) -> 209000 | L15: =IF(L13="","",L13) -> 207000 | N15: =IF(N13="","",N13) -> 159000 | O15: =IF(O13="","",O13) -> 249000 | P15: =IF(P13="","",P13) -> 169000 | Q15: =IF(Q13="","",Q13) -> 272000 | S15: =IF(S13="","",S13) -> 221000 | T15: =IF(T13="","",T13) -> 271000 | U15: =IF(U13="","",U13) -> 207000 | V15: =IF(V13="","",V13) -> 297000 | X15: =IF(X13="","",X13) -> 205000 | Y15: =IF(Y13="","",Y13) -> 145000 | Z15: =IF(Z13="","",Z13) -> 90000 | AA15: =IF(AA13="","",AA13) -> 163000 | AC15: =IF(AC13="","",AC13) -> 295000 | AD15: =IF(AD13="","",AD13) -> 227000
A16: Imposto de renda (divulgado positivo) [us-gaap:IncomeTaxExpenseBenefit] · fonte · unid. moeda | C16: [linha bruta, sem código; lançada nas linhas abaixo] | D16: 796000 | E16: 1526000 | F16: 2664000 | G16: 2650000 | I16: 2806000 | J16: 6359000 | K16: 5224000 | L16: 5787000 | N16: 4960000 | O16: 3503000 | P16: 4353000 | Q16: 2613000 | S16: 3803000 | T16: 4094000 | U16: 4055000 | V16: 1858000 | X16: 3567000 | Y16: 3351000 | Z16: 3164000 | AA16: 1422000 | AC16: 2495000 | AD16: 4543000
A17: (lançamento) código 7, sinal -1 sobre a linha bruta 16: Imposto de renda (divulgado positivo) [us-gaap:IncomeTaxExpenseBenefit] | B17: 7 | C17: Taxes | D17: =IF(D16="","",-1*D16) -> -796000 | E17: =IF(E16="","",-1*E16) -> -1526000 | F17: =IF(F16="","",-1*F16) -> -2664000 | G17: =IF(G16="","",-1*G16) -> -2650000 | I17: =IF(I16="","",-1*I16) -> -2806000 | J17: =IF(J16="","",-1*J16) -> -6359000 | K17: =IF(K16="","",-1*K16) -> -5224000 | L17: =IF(L16="","",-1*L16) -> -5787000 | N17: =IF(N16="","",-1*N16) -> -4960000 | O17: =IF(O16="","",-1*O16) -> -3503000 | P17: =IF(P16="","",-1*P16) -> -4353000 | Q17: =IF(Q16="","",-1*Q16) -> -2613000 | S17: =IF(S16="","",-1*S16) -> -3803000 | T17: =IF(T16="","",-1*T16) -> -4094000 | U17: =IF(U16="","",-1*U16) -> -4055000 | V17: =IF(V16="","",-1*V16) -> -1858000 | X17: =IF(X16="","",-1*X16) -> -3567000 | Y17: =IF(Y16="","",-1*Y16) -> -3351000 | Z17: =IF(Z16="","",-1*Z16) -> -3164000 | AA17: =IF(AA16="","",-1*AA16) -> -1422000 | AC17: =IF(AC16="","",-1*AC16) -> -2495000 | AD17: =IF(AD16="","",-1*AD16) -> -4543000
A18: Lucro atribuído a não controladores (divulgado positivo) [us-gaap:NetIncomeLossAttributableToNoncontrollingInterest] · fonte · unid. moeda | C18: [linha bruta, sem código; lançada nas linhas abaixo] | D18: 66000 | E18: 91000 | F18: 192000 | G18: 209000 | I18: 270000 | J18: 724000 | K18: 538000 | L18: 305000 | N18: 413000 | O18: 273000 | P18: 276000 | Q18: 382000 | S18: 346000 | T18: 331000 | U18: 361000 | V18: 345000 | X18: 320000 | Y18: 272000 | Z18: 220000 | AA18: 108000 | AC18: 289000 | AD18: 356000
A19: (lançamento) código 9, sinal -1 sobre a linha bruta 18: Lucro atribuído a não controladores (divulgado positivo) [us-gaap:NetIncomeLossAttributabl | B19: 9 | C19: Minority Interest Expense, after tax (enter as - ) | D19: =IF(D18="","",-1*D18) -> -66000 | E19: =IF(E18="","",-1*E18) -> -91000 | F19: =IF(F18="","",-1*F18) -> -192000 | G19: =IF(G18="","",-1*G18) -> -209000 | I19: =IF(I18="","",-1*I18) -> -270000 | J19: =IF(J18="","",-1*J18) -> -724000 | K19: =IF(K18="","",-1*K18) -> -538000 | L19: =IF(L18="","",-1*L18) -> -305000 | N19: =IF(N18="","",-1*N18) -> -413000 | O19: =IF(O18="","",-1*O18) -> -273000 | P19: =IF(P18="","",-1*P18) -> -276000 | Q19: =IF(Q18="","",-1*Q18) -> -382000 | S19: =IF(S18="","",-1*S18) -> -346000 | T19: =IF(T18="","",-1*T18) -> -331000 | U19: =IF(U18="","",-1*U18) -> -361000 | V19: =IF(V18="","",-1*V18) -> -345000 | X19: =IF(X18="","",-1*X18) -> -320000 | Y19: =IF(Y18="","",-1*Y18) -> -272000 | Z19: =IF(Z18="","",-1*Z18) -> -220000 | AA19: =IF(AA18="","",-1*AA18) -> -108000 | AC19: =IF(AC18="","",-1*AC18) -> -289000 | AD19: =IF(AD18="","",-1*AD18) -> -356000
A20: Lucro líquido atribuído à companhia [us-gaap:NetIncomeLoss] · memoria · unid. moeda | C20: [linha bruta, sem código; lançada nas linhas abaixo] | D20: 2730000 | E20: 4690000 | F20: 6750000 | G20: 8870000 | I20: 5480000 | J20: 17850000 | K20: 19660000 | L20: 12750000 | N20: 11430000 | O20: 7880000 | P20: 9070000 | Q20: 7630000 | S20: 8220000 | T20: 9240000 | U20: 8610000 | V20: 7610000 | X20: 7713000 | Y20: 7082000 | Z20: 7548000 | AA20: 6501000 | AC20: 4183000 | AD20: 14525000
A21: Resultado após IR não classificado acima (equivalência patrimonial, operações descontinuadas): lucro - (LAIR - IR - minoritários); zero quando não há · derivada · unid. moeda | B21: 8 | C21: Equity in Income of Affiliates, after tax (enter as +) | D21: =N(D20)-(N(D11)-N(D16)-N(D18)) -> 0 | E21: =N(E20)-(N(E11)-N(E16)-N(E18)) -> 0 | F21: =N(F20)-(N(F11)-N(F16)-N(F18)) -> 0 | G21: =N(G20)-(N(G11)-N(G16)-N(G18)) -> 0 | I21: =N(I20)-(N(I11)-N(I16)-N(I18)) -> 0 | J21: =N(J20)-(N(J11)-N(J16)-N(J18)) -> 0 | K21: =N(K20)-(N(K11)-N(K16)-N(K18)) -> 0 | L21: =N(L20)-(N(L11)-N(L16)-N(L18)) -> 0 | N21: =N(N20)-(N(N11)-N(N16)-N(N18)) -> 0 | O21: =N(O20)-(N(O11)-N(O16)-N(O18)) -> 0 | P21: =N(P20)-(N(P11)-N(P16)-N(P18)) -> 0 | Q21: =N(Q20)-(N(Q11)-N(Q16)-N(Q18)) -> 0 | S21: =N(S20)-(N(S11)-N(S16)-N(S18)) -> 0 | T21: =N(T20)-(N(T11)-N(T16)-N(T18)) -> 0 | U21: =N(U20)-(N(U11)-N(U16)-N(U18)) -> 0 | V21: =N(V20)-(N(V11)-N(V16)-N(V18)) -> 0 | X21: =N(X20)-(N(X11)-N(X16)-N(X18)) -> 0 | Y21: =N(Y20)-(N(Y11)-N(Y16)-N(Y18)) -> 0 | Z21: =N(Z20)-(N(Z11)-N(Z16)-N(Z18)) -> 0 | AA21: =N(AA20)-(N(AA11)-N(AA16)-N(AA18)) -> 0 | AC21: =N(AC20)-(N(AC11)-N(AC16)-N(AC18)) -> 0 | AD21: =N(AD20)-(N(AD11)-N(AD16)-N(AD18)) -> 0
A22: Lucro líquido (check IS, código 44) · derivada · unid. moeda | B22: 44 | C22: Lucro líquido (check IS, código 44) | D22: =N(D20) -> 2730000 | E22: =N(E20) -> 4690000 | F22: =N(F20) -> 6750000 | G22: =N(G20) -> 8870000 | I22: =N(I20) -> 5480000 | J22: =N(J20) -> 17850000 | K22: =N(K20) -> 19660000 | L22: =N(L20) -> 12750000 | N22: =N(N20) -> 11430000 | O22: =N(O20) -> 7880000 | P22: =N(P20) -> 9070000 | Q22: =N(Q20) -> 7630000 | S22: =N(S20) -> 8220000 | T22: =N(T20) -> 9240000 | U22: =N(U20) -> 8610000 | V22: =N(V20) -> 7610000 | X22: =N(X20) -> 7713000 | Y22: =N(Y20) -> 7082000 | Z22: =N(Z20) -> 7548000 | AA22: =N(AA20) -> 6501000 | AC22: =N(AC20) -> 4183000 | AD22: =N(AD20) -> 14525000
A23: DFC - trimestre isolado (desacumulado na extração) | C23: [linha bruta, sem código; lançada nas linhas abaixo]
A24: D&A (fluxo de caixa). COD1=4 lança (positivo -> -1); COD2=3 devolve às despesas operacionais (a companhia não abre D&A entre custo e despesa) [us-gaap:DepreciationDepletionAndAmortization/DepreciationAmortizationAndImpairment] · fonte · unid. moeda | C24: [linha bruta, sem código; lançada nas linhas abaixo] | D24: 5004000 | E24: 4952000 | F24: 4990000 | G24: 5661000 | I24: 8883000 | J24: 4451000 | K24: 5642000 | L24: 5064000 | N24: 4244000 | O24: 4242000 | P24: 4415000 | Q24: 7740000 | S24: 4812000 | T24: 5787000 | U24: 6258000 | V24: 6585000 | X24: 5702000 | Y24: 6101000 | Z24: 6475000 | AA24: 7715000 | AC24: 6771000 | AD24: 8689000
A25: (lançamento) código 4, sinal -1 sobre a linha bruta 24: D&A (fluxo de caixa). COD1=4 lança (positivo -> -1); COD2=3 devolve às despesas operaciona | B25: 4 | C25: D&A | D25: =IF(D24="","",-1*D24) -> -5004000 | E25: =IF(E24="","",-1*E24) -> -4952000 | F25: =IF(F24="","",-1*F24) -> -4990000 | G25: =IF(G24="","",-1*G24) -> -5661000 | I25: =IF(I24="","",-1*I24) -> -8883000 | J25: =IF(J24="","",-1*J24) -> -4451000 | K25: =IF(K24="","",-1*K24) -> -5642000 | L25: =IF(L24="","",-1*L24) -> -5064000 | N25: =IF(N24="","",-1*N24) -> -4244000 | O25: =IF(O24="","",-1*O24) -> -4242000 | P25: =IF(P24="","",-1*P24) -> -4415000 | Q25: =IF(Q24="","",-1*Q24) -> -7740000 | S25: =IF(S24="","",-1*S24) -> -4812000 | T25: =IF(T24="","",-1*T24) -> -5787000 | U25: =IF(U24="","",-1*U24) -> -6258000 | V25: =IF(V24="","",-1*V24) -> -6585000 | X25: =IF(X24="","",-1*X24) -> -5702000 | Y25: =IF(Y24="","",-1*Y24) -> -6101000 | Z25: =IF(Z24="","",-1*Z24) -> -6475000 | AA25: =IF(AA24="","",-1*AA24) -> -7715000 | AC25: =IF(AC24="","",-1*AC24) -> -6771000 | AD25: =IF(AD24="","",-1*AD24) -> -8689000
A26: (lançamento) código 3, sinal +1 sobre a linha bruta 24: D&A (fluxo de caixa). COD1=4 lança (positivo -> -1); COD2=3 devolve às despesas operaciona | B26: 3 | C26: SG&A and Other (cash) | D26: =IF(D24="","",D24) -> 5004000 | E26: =IF(E24="","",E24) -> 4952000 | F26: =IF(F24="","",F24) -> 4990000 | G26: =IF(G24="","",G24) -> 5661000 | I26: =IF(I24="","",I24) -> 8883000 | J26: =IF(J24="","",J24) -> 4451000 | K26: =IF(K24="","",K24) -> 5642000 | L26: =IF(L24="","",L24) -> 5064000 | N26: =IF(N24="","",N24) -> 4244000 | O26: =IF(O24="","",O24) -> 4242000 | P26: =IF(P24="","",P24) -> 4415000 | Q26: =IF(Q24="","",Q24) -> 7740000 | S26: =IF(S24="","",S24) -> 4812000 | T26: =IF(T24="","",T24) -> 5787000 | U26: =IF(U24="","",U24) -> 6258000 | V26: =IF(V24="","",V24) -> 6585000 | X26: =IF(X24="","",X24) -> 5702000 | Y26: =IF(Y24="","",Y24) -> 6101000 | Z26: =IF(Z24="","",Z24) -> 6475000 | AA26: =IF(AA24="","",AA24) -> 7715000 | AC26: =IF(AC24="","",AC24) -> 6771000 | AD26: =IF(AD24="","",AD24) -> 8689000
A27: Dividendos pagos [us-gaap:PaymentsOfDividends] · fonte · unid. moeda | C27: [linha bruta, sem código; lançada nas linhas abaixo] | D27: 3720000 | E27: 3721000 | F27: 3720000 | G27: 3763000 | I27: 3760000 | J27: 3727000 | K27: 3685000 | L27: 3767000 | N27: 3738000 | O27: 3701000 | P27: 3663000 | Q27: 3839000 | S27: 3808000 | T27: 4285000 | U27: 4240000 | V27: 4371000 | X27: 4335000 | Y27: 4288000 | Z27: 4242000 | AA27: 4366000 | AC27: 4334000 | AD27: 4299000
A28: (lançamento) código 10, sinal -1 sobre a linha bruta 27: Dividendos pagos [us-gaap:PaymentsOfDividends] | B28: 10 | C28: Common Dividends | D28: =IF(D27="","",-1*D27) -> -3720000 | E28: =IF(E27="","",-1*E27) -> -3721000 | F28: =IF(F27="","",-1*F27) -> -3720000 | G28: =IF(G27="","",-1*G27) -> -3763000 | I28: =IF(I27="","",-1*I27) -> -3760000 | J28: =IF(J27="","",-1*J27) -> -3727000 | K28: =IF(K27="","",-1*K27) -> -3685000 | L28: =IF(L27="","",-1*L27) -> -3767000 | N28: =IF(N27="","",-1*N27) -> -3738000 | O28: =IF(O27="","",-1*O27) -> -3701000 | P28: =IF(P27="","",-1*P27) -> -3663000 | Q28: =IF(Q27="","",-1*Q27) -> -3839000 | S28: =IF(S27="","",-1*S27) -> -3808000 | T28: =IF(T27="","",-1*T27) -> -4285000 | U28: =IF(U27="","",-1*U27) -> -4240000 | V28: =IF(V27="","",-1*V27) -> -4371000 | X28: =IF(X27="","",-1*X27) -> -4335000 | Y28: =IF(Y27="","",-1*Y27) -> -4288000 | Z28: =IF(Z27="","",-1*Z27) -> -4242000 | AA28: =IF(AA27="","",-1*AA27) -> -4366000 | AC28: =IF(AC27="","",-1*AC27) -> -4334000 | AD28: =IF(AD27="","",-1*AD27) -> -4299000
A29: BALANÇO DE FACE (USD, saldo no fim do trimestre; cada trimestre lido da instância do próprio 10-Q/10-K) | C29: [linha bruta, sem código; lançada nas linhas abaixo]
A30: CashAndCashEquivalentsAtCarryingValue · fonte · unid. moeda | B30: 11 | C30: Cash and equivalents (inc. investment securities) | D30: 3515000 | E30: 3465000 | F30: 4768000 | G30: 6802000 | I30: 11074000 | J30: 18861000 | K30: 30407000 | L30: 29640000 | N30: 32651000 | O30: 29528000 | P30: 32944000 | Q30: 31539000 | S30: 33320000 | T30: 26460000 | U30: 26926000 | V30: 23029000 | X30: 17036000 | Y30: 14352000 | Z30: 13814000 | AA30: 10681000 | AC30: 8435000 | AD30: 10588000
A31: ReceivablesNetCurrent · fonte · unid. moeda | B31: 12 | C31: Accounts receivable | D31: 24755000 | E31: 28540000 | F31: 29516000 | G31: 32383000 | I31: 42142000 | J31: 48063000 | K31: 42411000 | L31: 41749000 | N31: 38808000 | O31: 35915000 | P31: 41814000 | Q31: 38015000 | S31: 40366000 | T31: 43071000 | U31: 41505000 | V31: 43681000 | X31: 46303000 | Y31: 41792000 | Z31: 45285000 | AA31: 44562000 | AC31: 61783000 | AD31: 60558000
A32: EnergyRelatedInventory · fonte · unid. moeda | B32: 16 | C32: Other current assets | D32: 13740000 | E32: 14711000 | F32: 15087000 | G32: 14519000 | I32: 18074000 | J32: 19580000 | K32: 20078000 | L32: 20434000 | N32: 19458000 | O32: 20006000 | P32: 20052000 | Q32: 20528000 | S32: 18891000 | T32: 19685000 | U32: 19183000 | V32: 19444000 | X32: 20502000 | Y32: 21364000 | Z32: 23174000 | AA32: 22979000 | AC32: 21838000 | AD32: 22363000
A33: InventoryPartsAndComponentsNetOfReserves · fonte · unid. moeda | B33: 16 | C33: Other current assets | D33: 4617000 | E33: 4564000 | F33: 4520000 | G33: 4261000 | I33: 4103000 | J33: 4005000 | K33: 4018000 | L33: 4001000 | N33: 4184000 | O33: 4243000 | P33: 4398000 | Q33: 4592000 | S33: 4600000 | T33: 4818000 | U33: 4692000 | V33: 4080000 | X33: 3976000 | Y33: 4007000 | Z33: 4064000 | AA33: 3323000 | AC33: 3137000 | AD33: 3200000
A34: OtherAssetsCurrent · fonte · unid. moeda | B34: 16 | C34: Other current assets | D34: 1568000 | E34: 1562000 | F34: 1664000 | G34: 1189000 | I34: 1862000 | J34: 2654000 | K34: 2318000 | L34: 1782000 | N34: 2098000 | O34: 2039000 | P34: 1905000 | Q34: 1906000 | S34: 2171000 | T34: 2176000 | U34: 1997000 | V34: 1598000 | X34: 1940000 | Y34: 2234000 | Z34: 2113000 | AA34: 1837000 | AC34: 2594000 | AD34: 4084000
A35: RestrictedCashAndCashEquivalents · fonte · unid. moeda | B35: 16 | C35: Other current assets | D35: 0 | E35: 0 | F35: 0 | G35: 0 | I35: 0 | J35: 0 | K35: 57000 | L35: 0 | N35: 0 | O35: 0 | P35: 0 | Q35: 0 | S35: 0 | T35: 0 | U35: 0 | V35: 0 | X35: 0 | Y35: 0 | Z35: 0 | AA35: 0 | AC35: 0 | AD35: 0
A36: RestrictedCashAndCashEquivalentsAtCarryingValue · fonte · unid. moeda | B36: 16 | C36: Other current assets | D36: 0 | E36: 0 | F36: 0 | G36: 0 | I36: 0 | J36: 0 | K36: 0 | L36: 25000 | N36: 25000 | O36: 29000 | P36: 29000 | Q36: 29000 | S36: 29000 | T36: 28000 | U36: 46000 | V36: 158000 | X36: 1476000 | Y36: 1359000 | Z36: 55000 | AA36: 0 | AC36: 0 | AD36: 0
A37: PropertyPlantAndEquipmentNet · fonte · unid. moeda | B37: 18 | C37: PP&E | D37: 224641000 | E37: 223012000 | F37: 218795000 | G37: 216552000 | I37: 212773000 | J37: 209159000 | K37: 203102000 | L37: 204692000 | N37: 206023000 | O37: 206736000 | P37: 205862000 | Q37: 214940000 | S37: 213723000 | T37: 298283000 | U37: 299543000 | V37: 294318000 | X37: 292646000 | Y37: 295356000 | Z37: 298388000 | AA37: 299373000 | AC37: 298781000 | AD37: 296298000
A38: LongTermInvestmentsAndReceivablesNet · fonte · unid. moeda | B38: 22 | C38: Other non-current assets | D38: 44181000 | E38: 44774000 | F38: 45641000 | G38: 45195000 | I38: 46329000 | J38: 46820000 | K38: 50235000 | L38: 49793000 | N38: 49044000 | O38: 47273000 | P38: 48066000 | Q38: 47630000 | S38: 47608000 | T38: 47948000 | U38: 48869000 | V38: 47200000 | X38: 47853000 | Y38: 46092000 | Z38: 46138000 | AA38: 45317000 | AC38: 46125000 | AD38: 45605000
A39: OtherAssetsNoncurrent · fonte · unid. moeda | B39: 22 | C39: Other non-current assets | D39: 16753000 | E39: 16661000 | F39: 16697000 | G39: 18022000 | I39: 18414000 | J39: 18632000 | K39: 17526000 | L39: 16951000 | N39: 17080000 | O39: 17479000 | P39: 17189000 | Q39: 17138000 | S39: 17210000 | T39: 18238000 | U39: 19155000 | V39: 19967000 | X39: 20176000 | Y39: 21041000 | Z39: 21309000 | AA39: 20908000 | AC39: 21717000 | AD39: 21786000
A40: AccountsPayableAndAccruedLiabilitiesCurrent · fonte · unid. moeda | B40: 23 | C40: Accounts payable | D40: 41017000 | E40: 45780000 | F40: 47257000 | G40: 50766000 | I40: 63501000 | J40: 67958000 | K40: 62550000 | L40: 63197000 | N40: 59935000 | O40: 54404000 | P40: 62257000 | Q40: 58037000 | S40: 59531000 | T40: 60107000 | U40: 60518000 | V40: 61297000 | X40: 63987000 | Y40: 59725000 | Z40: 65382000 | AA40: 60911000 | AC40: 77088000 | AD40: 74491000
A41: AccruedIncomeTaxesCurrent · fonte · unid. moeda | B41: 25 | C41: Taxes payable | D41: 948000 | E41: 1165000 | F41: 1633000 | G41: 1601000 | I41: 3672000 | J41: 4785000 | K41: 5325000 | L41: 5214000 | N41: 4435000 | O41: 3482000 | P41: 4186000 | Q41: 3189000 | S41: 4163000 | T41: 4035000 | U41: 3843000 | V41: 4055000 | X41: 5114000 | Y41: 3017000 | Z41: 3256000 | AA41: 2123000 | AC41: 2759000 | AD41: 4200000
... A69: [vazio] Outras contas do PL: não aparece como linha própria nas demonstrações (zero) · derivada · unid. moeda | B69: 40 | C69: Other equity account | D69: 0 | E69: 0 | F69: 0 | G69: 0 | I69: 0 | J69: 0 | K69: 0 | L69: 0 | N69: 0 | O69: 0 | P69: 0 | Q69: 0 | S69: 0 | T69: 0 | U69: 0 | V69: 0 | X69: 0 | Y69: 0 | Z69: 0 | AA69: 0 | AC69: 0 | AD69: 0
A70: BALANÇO - totais divulgados (memória) | C70: [linha bruta, sem código; lançada nas linhas abaixo]
A71: Total do ativo [us-gaap:Assets] · memoria · unid. moeda | C71: [linha bruta, sem código; lançada nas linhas abaixo] | D71: 333770000 | E71: 337289000 | F71: 336688000 | G71: 338923000 | I71: 354771000 | J71: 367774000 | K71: 370152000 | L71: 369067000 | N71: 369371000 | O71: 363248000 | P71: 372259000 | Q71: 376317000 | S71: 377918000 | T71: 460707000 | U71: 461916000 | V71: 453475000 | X71: 451908000 | Y71: 447597000 | Z71: 454340000 | AA71: 448980000 | AC71: 464410000 | AD71: 464482000
A72: Total do passivo + PL [us-gaap:LiabilitiesAndStockholdersEquity] · memoria · unid. moeda | C72: [linha bruta, sem código; lançada nas linhas abaixo] | D72: 333770000 | E72: 337289000 | F72: 336688000 | G72: 338923000 | I72: 354771000 | J72: 367774000 | K72: 370152000 | L72: 369067000 | N72: 369371000 | O72: 363248000 | P72: 372259000 | Q72: 376317000 | S72: 377918000 | T72: 460707000 | U72: 461916000 | V72: 453475000 | X72: 451908000 | Y72: 447597000 | Z72: 454340000 | AA72: 448980000 | AC72: 464410000 | AD72: 464482000
A73: CHECKS (devem ser 0) | C73: [linha bruta, sem código; lançada nas linhas abaixo]
A74: CHECK: contas de ativo - ativo total (USD, arredondado a 100 mil) · derivada · unid. moeda | C74: [linha bruta, sem código; lançada nas linhas abaixo] | D74: =ROUND(N(D30)+N(D31)+N(D32)+N(D33)+N(D34)+N(D35)+N(D36)+N(D37)+N(D38)+N(D39)-N(D71),-2) -> 0 | E74: =ROUND(N(E30)+N(E31)+N(E32)+N(E33)+N(E34)+N(E35)+N(E36)+N(E37)+N(E38)+N(E39)-N(E71),-2) -> 0 | F74: =ROUND(N(F30)+N(F31)+N(F32)+N(F33)+N(F34)+N(F35)+N(F36)+N(F37)+N(F38)+N(F39)-N(F71),-2) -> 0 | G74: =ROUND(N(G30)+N(G31)+N(G32)+N(G33)+N(G34)+N(G35)+N(G36)+N(G37)+N(G38)+N(G39)-N(G71),-2) -> 0 | I74: =ROUND(N(I30)+N(I31)+N(I32)+N(I33)+N(I34)+N(I35)+N(I36)+N(I37)+N(I38)+N(I39)-N(I71),-2) -> 0 | J74: =ROUND(N(J30)+N(J31)+N(J32)+N(J33)+N(J34)+N(J35)+N(J36)+N(J37)+N(J38)+N(J39)-N(J71),-2) -> 0 | K74: =ROUND(N(K30)+N(K31)+N(K32)+N(K33)+N(K34)+N(K35)+N(K36)+N(K37)+N(K38)+N(K39)-N(K71),-2) -> 0 | L74: =ROUND(N(L30)+N(L31)+N(L32)+N(L33)+N(L34)+N(L35)+N(L36)+N(L37)+N(L38)+N(L39)-N(L71),-2) -> 0 | N74: =ROUND(N(N30)+N(N31)+N(N32)+N(N33)+N(N34)+N(N35)+N(N36)+N(N37)+N(N38)+N(N39)-N(N71),-2) -> 0 | O74: =ROUND(N(O30)+N(O31)+N(O32)+N(O33)+N(O34)+N(O35)+N(O36)+N(O37)+N(O38)+N(O39)-N(O71),-2) -> 0 | P74: =ROUND(N(P30)+N(P31)+N(P32)+N(P33)+N(P34)+N(P35)+N(P36)+N(P37)+N(P38)+N(P39)-N(P71),-2) -> 0 | Q74: =ROUND(N(Q30)+N(Q31)+N(Q32)+N(Q33)+N(Q34)+N(Q35)+N(Q36)+N(Q37)+N(Q38)+N(Q39)-N(Q71),-2) -> 0 | S74: =ROUND(N(S30)+N(S31)+N(S32)+N(S33)+N(S34)+N(S35)+N(S36)+N(S37)+N(S38)+N(S39)-N(S71),-2) -> 0 | T74: =ROUND(N(T30)+N(T31)+N(T32)+N(T33)+N(T34)+N(T35)+N(T36)+N(T37)+N(T38)+N(T39)-N(T71),-2) -> 0 | U74: =ROUND(N(U30)+N(U31)+N(U32)+N(U33)+N(U34)+N(U35)+N(U36)+N(U37)+N(U38)+N(U39)-N(U71),-2) -> 0 | V74: =ROUND(N(V30)+N(V31)+N(V32)+N(V33)+N(V34)+N(V35)+N(V36)+N(V37)+N(V38)+N(V39)-N(V71),-2) -> 0 | X74: =ROUND(N(X30)+N(X31)+N(X32)+N(X33)+N(X34)+N(X35)+N(X36)+N(X37)+N(X38)+N(X39)-N(X71),-2) -> 0 | Y74: =ROUND(N(Y30)+N(Y31)+N(Y32)+N(Y33)+N(Y34)+N(Y35)+N(Y36)+N(Y37)+N(Y38)+N(Y39)-N(Y71),-2) -> 0 | Z74: =ROUND(N(Z30)+N(Z31)+N(Z32)+N(Z33)+N(Z34)+N(Z35)+N(Z36)+N(Z37)+N(Z38)+N(Z39)-N(Z71),-2) -> 0 | AA74: =ROUND(N(AA30)+N(AA31)+N(AA32)+N(AA33)+N(AA34)+N(AA35)+N(AA36)+N(AA37)+N(AA38)+N(AA39)-N(AA71),-2) -> 0 | AC74: =ROUND(N(AC30)+N(AC31)+N(AC32)+N(AC33)+N(AC34)+N(AC35)+N(AC36)+N(AC37)+N(AC38)+N(AC39)-N(AC71),-2) -> 0 | AD74: =ROUND(N(AD30)+N(AD31)+N(AD32)+N(AD33)+N(AD34)+N(AD35)+N(AD36)+N(AD37)+N(AD38)+N(AD39)-N(AD71),-2) -> 0
A75: CHECK: passivo + PL (contas) - passivo + PL total · derivada · unid. moeda | C75: [linha bruta, sem código; lançada nas linhas abaixo] | D75: =ROUND(N(D40)+N(D41)+N(D42)+N(D43)+N(D44)+N(D45)+N(D46)+N(D47)+N(D48)+N(D49)+N(D50)+N(D51)+N(D52)+N(D53)+N(D54)+N(D55)-N(D72),-2) -> 0 | E75: =ROUND(N(E40)+N(E41)+N(E42)+N(E43)+N(E44)+N(E45)+N(E46)+N(E47)+N(E48)+N(E49)+N(E50)+N(E51)+N(E52)+N(E53)+N(E54)+N(E55)-N(E72),-2) -> 0 | F75: =ROUND(N(F40)+N(F41)+N(F42)+N(F43)+N(F44)+N(F45)+N(F46)+N(F47)+N(F48)+N(F49)+N(F50)+N(F51)+N(F52)+N(F53)+N(F54)+N(F55)-N(F72),-2) -> 0 | G75: =ROUND(N(G40)+N(G41)+N(G42)+N(G43)+N(G44)+N(G45)+N(G46)+N(G47)+N(G48)+N(G49)+N(G50)+N(G51)+N(G52)+N(G53)+N(G54)+N(G55)-N(G72),-2) -> 0 | I75: =ROUND(N(I40)+N(I41)+N(I42)+N(I43)+N(I44)+N(I45)+N(I46)+N(I47)+N(I48)+N(I49)+N(I50)+N(I51)+N(I52)+N(I53)+N(I54)+N(I55)-N(I72),-2) -> 0 | J75: =ROUND(N(J40)+N(J41)+N(J42)+N(J43)+N(J44)+N(J45)+N(J46)+N(J47)+N(J48)+N(J49)+N(J50)+N(J51)+N(J52)+N(J53)+N(J54)+N(J55)-N(J72),-2) -> 0 | K75: =ROUND(N(K40)+N(K41)+N(K42)+N(K43)+N(K44)+N(K45)+N(K46)+N(K47)+N(K48)+N(K49)+N(K50)+N(K51)+N(K52)+N(K53)+N(K54)+N(K55)-N(K72),-2) -> 0 | L75: =ROUND(N(L40)+N(L41)+N(L42)+N(L43)+N(L44)+N(L45)+N(L46)+N(L47)+N(L48)+N(L49)+N(L50)+N(L51)+N(L52)+N(L53)+N(L54)+N(L55)-N(L72),-2) -> 0 | N75: =ROUND(N(N40)+N(N41)+N(N42)+N(N43)+N(N44)+N(N45)+N(N46)+N(N47)+N(N48)+N(N49)+N(N50)+N(N51)+N(N52)+N(N53)+N(N54)+N(N55)-N(N72),-2) -> 0 | O75: =ROUND(N(O40)+N(O41)+N(O42)+N(O43)+N(O44)+N(O45)+N(O46)+N(O47)+N(O48)+N(O49)+N(O50)+N(O51)+N(O52)+N(O53)+N(O54)+N(O55)-N(O72),-2) -> 0 | P75: =ROUND(N(P40)+N(P41)+N(P42)+N(P43)+N(P44)+N(P45)+N(P46)+N(P47)+N(P48)+N(P49)+N(P50)+N(P51)+N(P52)+N(P53)+N(P54)+N(P55)-N(P72),-2) -> 0 | Q75: =ROUND(N(Q40)+N(Q41)+N(Q42)+N(Q43)+N(Q44)+N(Q45)+N(Q46)+N(Q47)+N(Q48)+N(Q49)+N(Q50)+N(Q51)+N(Q52)+N(Q53)+N(Q54)+N(Q55)-N(Q72),-2) -> 0 | S75: =ROUND(N(S40)+N(S41)+N(S42)+N(S43)+N(S44)+N(S45)+N(S46)+N(S47)+N(S48)+N(S49)+N(S50)+N(S51)+N(S52)+N(S53)+N(S54)+N(S55)-N(S72),-2) -> 0 | T75: =ROUND(N(T40)+N(T41)+N(T42)+N(T43)+N(T44)+N(T45)+N(T46)+N(T47)+N(T48)+N(T49)+N(T50)+N(T51)+N(T52)+N(T53)+N(T54)+N(T55)-N(T72),-2) -> 0 | U75: =ROUND(N(U40)+N(U41)+N(U42)+N(U43)+N(U44)+N(U45)+N(U46)+N(U47)+N(U48)+N(U49)+N(U50)+N(U51)+N(U52)+N(U53)+N(U54)+N(U55)-N(U72),-2) -> 0 | V75: =ROUND(N(V40)+N(V41)+N(V42)+N(V43)+N(V44)+N(V45)+N(V46)+N(V47)+N(V48)+N(V49)+N(V50)+N(V51)+N(V52)+N(V53)+N(V54)+N(V55)-N(V72),-2) -> 0 | X75: =ROUND(N(X40)+N(X41)+N(X42)+N(X43)+N(X44)+N(X45)+N(X46)+N(X47)+N(X48)+N(X49)+N(X50)+N(X51)+N(X52)+N(X53)+N(X54)+N(X55)-N(X72),-2) -> 0 | Y75: =ROUND(N(Y40)+N(Y41)+N(Y42)+N(Y43)+N(Y44)+N(Y45)+N(Y46)+N(Y47)+N(Y48)+N(Y49)+N(Y50)+N(Y51)+N(Y52)+N(Y53)+N(Y54)+N(Y55)-N(Y72),-2) -> 0 | Z75: =ROUND(N(Z40)+N(Z41)+N(Z42)+N(Z43)+N(Z44)+N(Z45)+N(Z46)+N(Z47)+N(Z48)+N(Z49)+N(Z50)+N(Z51)+N(Z52)+N(Z53)+N(Z54)+N(Z55)-N(Z72),-2) -> 0 | AA75: =ROUND(N(AA40)+N(AA41)+N(AA42)+N(AA43)+N(AA44)+N(AA45)+N(AA46)+N(AA47)+N(AA48)+N(AA49)+N(AA50)+N(AA51)+N(AA52)+N(AA53)+N(AA54)+N(AA55)-N(AA72),-2) -> 0 | AC75: =ROUND(N(AC40)+N(AC41)+N(AC42)+N(AC43)+N(AC44)+N(AC45)+N(AC46)+N(AC47)+N(AC48)+N(AC49)+N(AC50)+N(AC51)+N(AC52)+N(AC53)+N(AC54)+N(AC55)-N(AC72),-2) -> 0 | AD75: =ROUND(N(AD40)+N(AD41)+N(AD42)+N(AD43)+N(AD44)+N(AD45)+N(AD46)+N(AD47)+N(AD48)+N(AD49)+N(AD50)+N(AD51)+N(AD52)+N(AD53)+N(AD54)+N(AD55)-N(AD72),-2) -> 0
A76: CHECK: receita - custo - despesas + não operacional - IR - minoritários + outros após IR - lucro (deve ser 0) · derivada | C76: [linha bruta, sem código; lançada nas linhas abaixo] | D76: =ROUND(N(D5)-N(D6)-N(D9)+N(D12)-N(D16)-N(D18)+N(D21)-N(D22),-2) -> 0 | E76: =ROUND(N(E5)-N(E6)-N(E9)+N(E12)-N(E16)-N(E18)+N(E21)-N(E22),-2) -> 0 | F76: =ROUND(N(F5)-N(F6)-N(F9)+N(F12)-N(F16)-N(F18)+N(F21)-N(F22),-2) -> 0 | G76: =ROUND(N(G5)-N(G6)-N(G9)+N(G12)-N(G16)-N(G18)+N(G21)-N(G22),-2) -> 0 | I76: =ROUND(N(I5)-N(I6)-N(I9)+N(I12)-N(I16)-N(I18)+N(I21)-N(I22),-2) -> 0 | J76: =ROUND(N(J5)-N(J6)-N(J9)+N(J12)-N(J16)-N(J18)+N(J21)-N(J22),-2) -> 0 | K76: =ROUND(N(K5)-N(K6)-N(K9)+N(K12)-N(K16)-N(K18)+N(K21)-N(K22),-2) -> 0 | L76: =ROUND(N(L5)-N(L6)-N(L9)+N(L12)-N(L16)-N(L18)+N(L21)-N(L22),-2) -> 0 | N76: =ROUND(N(N5)-N(N6)-N(N9)+N(N12)-N(N16)-N(N18)+N(N21)-N(N22),-2) -> 0 | O76: =ROUND(N(O5)-N(O6)-N(O9)+N(O12)-N(O16)-N(O18)+N(O21)-N(O22),-2) -> 0 | P76: =ROUND(N(P5)-N(P6)-N(P9)+N(P12)-N(P16)-N(P18)+N(P21)-N(P22),-2) -> 0 | Q76: =ROUND(N(Q5)-N(Q6)-N(Q9)+N(Q12)-N(Q16)-N(Q18)+N(Q21)-N(Q22),-2) -> 0 | S76: =ROUND(N(S5)-N(S6)-N(S9)+N(S12)-N(S16)-N(S18)+N(S21)-N(S22),-2) -> 0 | T76: =ROUND(N(T5)-N(T6)-N(T9)+N(T12)-N(T16)-N(T18)+N(T21)-N(T22),-2) -> 0 | U76: =ROUND(N(U5)-N(U6)-N(U9)+N(U12)-N(U16)-N(U18)+N(U21)-N(U22),-2) -> 0 | V76: =ROUND(N(V5)-N(V6)-N(V9)+N(V12)-N(V16)-N(V18)+N(V21)-N(V22),-2) -> 0 | X76: =ROUND(N(X5)-N(X6)-N(X9)+N(X12)-N(X16)-N(X18)+N(X21)-N(X22),-2) -> 0 | Y76: =ROUND(N(Y5)-N(Y6)-N(Y9)+N(Y12)-N(Y16)-N(Y18)+N(Y21)-N(Y22),-2) -> 0 | Z76: =ROUND(N(Z5)-N(Z6)-N(Z9)+N(Z12)-N(Z16)-N(Z18)+N(Z21)-N(Z22),-2) -> 0 | AA76: =ROUND(N(AA5)-N(AA6)-N(AA9)+N(AA12)-N(AA16)-N(AA18)+N(AA21)-N(AA22),-2) -> 0 | AC76: =ROUND(N(AC5)-N(AC6)-N(AC9)+N(AC12)-N(AC16)-N(AC18)+N(AC21)-N(AC22),-2) -> 0 | AD76: =ROUND(N(AD5)-N(AD6)-N(AD9)+N(AD12)-N(AD16)-N(AD18)+N(AD21)-N(AD22),-2) -> 0
A78: DRIVERS DE RECEITA (codigos 45+): composição da receita (vendas, equivalência, outras) e lucro por segmento (Upstream, Energy Products, Chemical Products, Specialty Products), EUA + exterior - SEC XBRL (USD, fator 0,000001). | C78: [linha bruta, sem código; lançada nas linhas abaixo]
A79: Vendas e outras receitas operacionais (USD) · fonte · unid. moeda | B79: 45 | C79: Vendas e outras receitas operacionais (USD) | I79: 87734000 | J79: 111265000 | K79: 106512000 | L79: 93164000 | N79: 83644000 | O79: 80795000 | P79: 88570000 | Q79: 81688000 | S79: 80411000 | T79: 89986000 | U79: 87792000 | V79: 81058000 | X79: 81058000 | Y79: 79477000 | Z79: 83331000 | AA79: 80039000 | AC79: 83161000 | AD79: 114529000
A80: Receita de equivalência patrimonial (USD) · fonte · unid. moeda | B80: 46 | C80: Receita de equivalência patrimonial (USD) | I80: 2538000 | J80: 3688000 | K80: 4632000 | L80: 605000 | N80: 2381000 | O80: 1382000 | P80: 1457000 | Q80: 1165000 | S80: 1842000 | T80: 1744000 | U80: 1481000 | V80: 1127000 | X80: 1369000 | Y80: 1462000 | Z80: 1267000 | AA80: 966000 | AC80: 1369000 | AD80: 893000
A81: Outras receitas (USD) · fonte · unid. moeda | B81: 47 | C81: Outras receitas (USD) | I81: 228000 | J81: 728000 | K81: 926000 | L81: 1660000 | N81: 539000 | O81: 737000 | P81: 733000 | Q81: 1491000 | S81: 830000 | T81: 1330000 | U81: 743000 | V81: 1241000 | X81: 703000 | Y81: 567000 | Z81: 696000 | AA81: 1303000 | AC81: 608000 | AD81: 595000
A82: Lucro Upstream (EUA + exterior, USD) · fonte · unid. moeda | B82: 48 | C82: Lucro Upstream (EUA + exterior, USD) | D82: 2554000 | E82: 3185000 | F82: 3951000 | I82: 4488000 | J82: 11371000 | K82: 12419000 | L82: 8201000 | N82: 6457000 | O82: 4577000 | P82: 6125000 | Q82: 4149000 | S82: 5660000 | T82: 7074000 | U82: 6158000 | V82: 6498000 | X82: 6756000 | Y82: 5402000 | Z82: 5679000 | AA82: 3517000 | AC82: 5737000 | AD82: 7927000
A83: Lucro Energy Products (USD) · fonte · unid. moeda | B83: 49 | C83: Lucro Energy Products (USD) | I83: -195000 | J83: 5272000 | K83: 5819000 | L83: 4070000 | N83: 4183000 | O83: 2310000 | P83: 2442000 | Q83: 3207000 | S83: 1376000 | T83: 946000 | U83: 1309000 | V83: 402000 | X83: 827000 | Y83: 1366000 | Z83: 1840000 | AA83: 3390000 | AC83: -1262000 | AD83: 5465000
A84: Lucro Chemical Products (USD) · fonte · unid. moeda | B84: 50 | C84: Lucro Chemical Products (USD) | I84: 1406000 | J84: 1075000 | K84: 812000 | L84: 250000 | N84: 371000 | O84: 828000 | P84: 249000 | Q84: 189000 | S84: 785000 | T84: 779000 | U84: 893000 | V84: 120000 | X84: 273000 | Y84: 293000 | Z84: 515000 | AA84: -281000 | AC84: 110000 | AD84: 1131000
A85: Lucro Specialty Products (USD) · fonte · unid. moeda | B85: 51 | C85: Lucro Specialty Products (USD) | I85: 476000 | J85: 417000 | K85: 762000 | L85: 760000 | N85: 774000 | O85: 671000 | P85: 619000 | Q85: 650000 | S85: 761000 | T85: 751000 | U85: 794000 | V85: 746000 | X85: 655000 | Y85: 780000 | Z85: 740000 | AA85: 682000 | AC85: 651000 | AD85: 956000
A86: Corporate e financeiro (USD) · fonte · unid. moeda | B86: 52 | C86: Corporate e financeiro (USD) | D86: -849000 | E86: -588000 | F86: -596000 | I86: -694000 | J86: -286000 | K86: -152000 | L86: -531000 | N86: -355000 | O86: -506000 | P86: -365000 | Q86: -565000 | S86: -362000 | T86: -310000 | U86: -544000 | V86: -156000 | X86: -798000 | Y86: -759000 | Z86: -1226000 | AA86: -807000 | AC86: -1053000 | AD86: -954000
A87: Receita Upstream (USD; desde 4T22) · fonte · unid. moeda | B87: 53 | C87: Receita Upstream (USD; desde 4T22) | S87: 23385000 | T87: 28830000 | U87: 29382000 | V87: 29149000 | X87: 29174000 | Y87: 25700000 | Z87: 27790000 | AA87: 24487000 | AC87: 28824000 | AD87: 35457000
A88: Receita Energy Products (USD; desde 4T22) · fonte · unid. moeda | B88: 54 | C88: Receita Energy Products (USD; desde 4T22) | S88: 77642000 | T88: 82497000 | U88: 78704000 | V88: 72191000 | X88: 71375000 | Y88: 71147000 | Z88: 74990000 | AA88: 74104000 | AC88: 77272000 | AD88: 109543000
A89: Notas: valores dimensionais das instâncias XBRL. A linha "Revenues" da Exxon inclui equivalência patrimonial e outras receitas; o lucro operacional do modelo é receita total - custos totais + juros. Segmentos novos (Energy/Chemical/Specialty Products) a partir do 4T20; Upstream desde sempre. Lucro por segmento = EUA + exterior. | C89: [linha bruta, sem código; lançada nas linhas abaixo]
A91: Linhas de origem: 4 a 89. A Inputs (2) varre as linhas 4 a 150; as linhas 90 a 150 estão livres. Linhas "(lançamento)" aplicam código e sinal sobre a linha bruta indicada (a máscara tem uma só coluna de código).

Sheet Inputs (2)
A1: =IF(Control!B3="","EMPRESA",Control!B3) -> Exxon Mobil Corporation | B1: Código | C1: Conta padronizada | D1: 2021 | E1: 2021 | F1: 2021 | G1: 2021 | H1: 2021 | I1: 2022 | J1: 2022 | K1: 2022 | L1: 2022 | M1: 2022 | N1: 2023 | O1: 2023 | P1: 2023 | Q1: 2023 | R1: 2023 | S1: 2024 | T1: 2024 | U1: 2024 | V1: 2024 | W1: 2024 | X1: 2025 | Y1: 2025 | Z1: 2025 | AA1: 2025 | AB1: 2025 | AC1: 2026 | AD1: 2026 | AE1: 2026 | AF1: 2026 | AG1: 2026
A2: US$ milhões | C2: Período | D2: 1Q21 | E2: 2Q21 | F2: 3Q21 | G2: 4Q21 | H2: 2021 | I2: 1Q22 | J2: 2Q22 | K2: 3Q22 | L2: 4Q22 | M2: 2022 | N2: 1Q23 | O2: 2Q23 | P2: 3Q23 | Q2: 4Q23 | R2: 2023 | S2: 1Q24 | T2: 2Q24 | U2: 3Q24 | V2: 4Q24 | W2: 2024 | X2: 1Q25 | Y2: 2Q25 | Z2: 3Q25 | AA2: 4Q25 | AB2: 2025 | AC2: 1Q26 | AD2: 2Q26 | AE2: 3Q26 | AF2: 4Q26 | AG2: 2026
A3: Actual flag | C3: 0 = sem dados / 1 = realizado | D3: 1 | E3: 1 | F3: 1 | G3: 1 | H3: 1 | I3: 1 | J3: 1 | K3: 1 | L3: 1 | M3: 1 | N3: 1 | O3: 1 | P3: 1 | Q3: 1 | R3: 1 | S3: 1 | T3: 1 | U3: 1 | V3: 1 | W3: 1 | X3: 1 | Y3: 1 | Z3: 1 | AA3: 1 | AB3: 1 | AC3: 1 | AD3: 1 | AE3: 0 | AF3: 0 | AG3: 0
B4: 1 | C4: Net Revenues | D4: =IF(D$3=0,"",SUMIFS(INDEX(Inputs!$D$4:$AG$150,0,MATCH(D$2,Inputs!$D$2:$AG$2,0)),Inputs!$B$4:$B$150,$B4)/1000) -> 59147 | E4: =IF(E$3=0,"",SUMIFS(INDEX(Inputs!$D$4:$AG$150,0,MATCH(E$2,Inputs!$D$2:$AG$2,0)),Inputs!$B$4:$B$150,$B4)/1000) -> 67742 | F4: =IF(F$3=0,"",SUMIFS(INDEX(Inputs!$D$4:$AG$150,0,MATCH(F$2,Inputs!$D$2:$AG$2,0)),Inputs!$B$4:$B$150,$B4)/1000) -> 73786 | G4: =IF(G$3=0,"",SUMIFS(INDEX(Inputs!$D$4:$AG$150,0,MATCH(G$2,Inputs!$D$2:$AG$2,0)),Inputs!$B$4:$B$150,$B4)/1000) -> 84965 | H4: =IF(COUNT(D4:G4)=4,SUM(D4:G4),"") -> 285640 | I4: =IF(I$3=0,"",SUMIFS(INDEX(Inputs!$D$4:$AG$150,0,MATCH(I$2,Inputs!$D$2:$AG$2,0)),Inputs!$B$4:$B$150,$B4)/1000) -> 90500 | J4: =IF(J$3=0,"",SUMIFS(INDEX(Inputs!$D$4:$AG$150,0,MATCH(J$2,Inputs!$D$2:$AG$2,0)),Inputs!$B$4:$B$150,$B4)/1000) -> 115681 | K4: =IF(K$3=0,"",SUMIFS(INDEX(Inputs!$D$4:$AG$150,0,MATCH(K$2,Inputs!$D$2:$AG$2,0)),Inputs!$B$4:$B$150,$B4)/1000) -> 112070 | L4: =IF(L$3=0,"",SUMIFS(INDEX(Inputs!$D$4:$AG$150,0,MATCH(L$2,Inputs!$D$2:$AG$2,0)),Inputs!$B$4:$B$150,$B4)/1000) -> 95429 | M4: =IF(COUNT(I4:L4)=4,SUM(I4:L4),"") -> 413680 | N4: =IF(N$3=0,"",SUMIFS(INDEX(Inputs!$D$4:$AG$150,0,MATCH(N$2,Inputs!$D$2:$AG$2,0)),Inputs!$B$4:$B$150,$B4)/1000) -> 86564 | O4: =IF(O$3=0,"",SUMIFS(INDEX(Inputs!$D$4:$AG$150,0,MATCH(O$2,Inputs!$D$2:$AG$2,0)),Inputs!$B$4:$B$150,$B4)/1000) -> 82914 | P4: =IF(P$3=0,"",SUMIFS(INDEX(Inputs!$D$4:$AG$150,0,MATCH(P$2,Inputs!$D$2:$AG$2,0)),Inputs!$B$4:$B$150,$B4)/1000) -> 90760 | Q4: =IF(Q$3=0,"",SUMIFS(INDEX(Inputs!$D$4:$AG$150,0,MATCH(Q$2,Inputs!$D$2:$AG$2,0)),Inputs!$B$4:$B$150,$B4)/1000) -> 84344 | R4: =IF(COUNT(N4:Q4)=4,SUM(N4:Q4),"") -> 344582 | S4: =IF(S$3=0,"",SUMIFS(INDEX(Inputs!$D$4:$AG$150,0,MATCH(S$2,Inputs!$D$2:$AG$2,0)),Inputs!$B$4:$B$150,$B4)/1000) -> 83083 | T4: =IF(T$3=0,"",SUMIFS(INDEX(Inputs!$D$4:$AG$150,0,MATCH(T$2,Inputs!$D$2:$AG$2,0)),Inputs!$B$4:$B$150,$B4)/1000) -> 93060 | U4: =IF(U$3=0,"",SUMIFS(INDEX(Inputs!$D$4:$AG$150,0,MATCH(U$2,Inputs!$D$2:$AG$2,0)),Inputs!$B$4:$B$150,$B4)/1000) -> 90016 | V4: =IF(V$3=0,"",SUMIFS(INDEX(Inputs!$D$4:$AG$150,0,MATCH(V$2,Inputs!$D$2:$AG$2,0)),Inputs!$B$4:$B$150,$B4)/1000) -> 83426 | W4: =IF(COUNT(S4:V4)=4,SUM(S4:V4),"") -> 349585 | X4: =IF(X$3=0,"",SUMIFS(INDEX(Inputs!$D$4:$AG$150,0,MATCH(X$2,Inputs!$D$2:$AG$2,0)),Inputs!$B$4:$B$150,$B4)/1000) -> 83130 | Y4: =IF(Y$3=0,"",SUMIFS(INDEX(Inputs!$D$4:$AG$150,0,MATCH(Y$2,Inputs!$D$2:$AG$2,0)),Inputs!$B$4:$B$150,$B4)/1000) -> 81506 | Z4: =IF(Z$3=0,"",SUMIFS(INDEX(Inputs!$D$4:$AG$150,0,MATCH(Z$2,Inputs!$D$2:$AG$2,0)),Inputs!$B$4:$B$150,$B4)/1000) -> 85294 | AA4: =IF(AA$3=0,"",SUMIFS(INDEX(Inputs!$D$4:$AG$150,0,MATCH(AA$2,Inputs!$D$2:$AG$2,0)),Inputs!$B$4:$B$150,$B4)/1000) -> 82308 | AB4: =IF(COUNT(X4:AA4)=4,SUM(X4:AA4),"") -> 332238 | AC4: =IF(AC$3=0,"",SUMIFS(INDEX(Inputs!$D$4:$AG$150,0,MATCH(AC$2,Inputs!$D$2:$AG$2,0)),Inputs!$B$4:$B$150,$B4)/1000) -> 85138 | AD4: =IF(AD$3=0,"",SUMIFS(INDEX(Inputs!$D$4:$AG$150,0,MATCH(AD$2,Inputs!$D$2:$AG$2,0)),Inputs!$B$4:$B$150,$B4)/1000) -> 116017 | AE4: =IF(AE$3=0,"",SUMIFS(INDEX(Inputs!$D$4:$AG$150,0,MATCH(AE$2,Inputs!$D$2:$AG$2,0)),Inputs!$B$4:$B$150,$B4)/1000) | AF4: =IF(AF$3=0,"",SUMIFS(INDEX(Inputs!$D$4:$AG$150,0,MATCH(AF$2,Inputs!$D$2:$AG$2,0)),Inputs!$B$4:$B$150,$B4)/1000) | AG4: =IF(COUNT(AC4:AF4)=4,SUM(AC4:AF4),"")
B5: 2 | C5: COGS (cash) | D5: =IF(D$3=0,"",SUMIFS(INDEX(Inputs!$D$4:$AG$150,0,MATCH(D$2,Inputs!$D$2:$AG$2,0)),Inputs!$B$4:$B$150,$B5)/1000) -> -32601 | E5: =IF(E$3=0,"",SUMIFS(INDEX(Inputs!$D$4:$AG$150,0,MATCH(E$2,Inputs!$D$2:$AG$2,0)),Inputs!$B$4:$B$150,$B5)/1000) -> -37329 | F5: =IF(F$3=0,"",SUMIFS(INDEX(Inputs!$D$4:$AG$150,0,MATCH(F$2,Inputs!$D$2:$AG$2,0)),Inputs!$B$4:$B$150,$B5)/1000) -> -39745 | G5: =IF(G$3=0,"",SUMIFS(INDEX(Inputs!$D$4:$AG$150,0,MATCH(G$2,Inputs!$D$2:$AG$2,0)),Inputs!$B$4:$B$150,$B5)/1000) -> -45489 | H5: =IF(COUNT(D5:G5)=4,SUM(D5:G5),"") -> -155164 | I5: =IF(I$3=0,"",SUMIFS(INDEX(Inputs!$D$4:$AG$150,0,MATCH(I$2,Inputs!$D$2:$AG$2,0)),Inputs!$B$4:$B$150,$B5)/1000) -> -52388 | J5: =IF(J$3=0,"",SUMIFS(INDEX(Inputs!$D$4:$AG$150,0,MATCH(J$2,Inputs!$D$2:$AG$2,0)),Inputs!$B$4:$B$150,$B5)/1000) -> -65613 | K5: =IF(K$3=0,"",SUMIFS(INDEX(Inputs!$D$4:$AG$150,0,MATCH(K$2,Inputs!$D$2:$AG$2,0)),Inputs!$B$4:$B$150,$B5)/1000) -> -60197 | L5: =IF(L$3=0,"",SUMIFS(INDEX(Inputs!$D$4:$AG$150,0,MATCH(L$2,Inputs!$D$2:$AG$2,0)),Inputs!$B$4:$B$150,$B5)/1000) -> -50761 | M5: =IF(COUNT(I5:L5)=4,SUM(I5:L5),"") -> -228959 | N5: =IF(N$3=0,"",SUMIFS(INDEX(Inputs!$D$4:$AG$150,0,MATCH(N$2,Inputs!$D$2:$AG$2,0)),Inputs!$B$4:$B$150,$B5)/1000) -> -46003 | O5: =IF(O$3=0,"",SUMIFS(INDEX(Inputs!$D$4:$AG$150,0,MATCH(O$2,Inputs!$D$2:$AG$2,0)),Inputs!$B$4:$B$150,$B5)/1000) -> -47598 | P5: =IF(P$3=0,"",SUMIFS(INDEX(Inputs!$D$4:$AG$150,0,MATCH(P$2,Inputs!$D$2:$AG$2,0)),Inputs!$B$4:$B$150,$B5)/1000) -> -53076 | Q5: =IF(Q$3=0,"",SUMIFS(INDEX(Inputs!$D$4:$AG$150,0,MATCH(Q$2,Inputs!$D$2:$AG$2,0)),Inputs!$B$4:$B$150,$B5)/1000) -> -46352 | R5: =IF(COUNT(N5:Q5)=4,SUM(N5:Q5),"") -> -193029 | S5: =IF(S$3=0,"",SUMIFS(INDEX(Inputs!$D$4:$AG$150,0,MATCH(S$2,Inputs!$D$2:$AG$2,0)),Inputs!$B$4:$B$150,$B5)/1000) -> -47601 | T5: =IF(T$3=0,"",SUMIFS(INDEX(Inputs!$D$4:$AG$150,0,MATCH(T$2,Inputs!$D$2:$AG$2,0)),Inputs!$B$4:$B$150,$B5)/1000) -> -54199 | U5: =IF(U$3=0,"",SUMIFS(INDEX(Inputs!$D$4:$AG$150,0,MATCH(U$2,Inputs!$D$2:$AG$2,0)),Inputs!$B$4:$B$150,$B5)/1000) -> -51261 | V5: =IF(V$3=0,"",SUMIFS(INDEX(Inputs!$D$4:$AG$150,0,MATCH(V$2,Inputs!$D$2:$AG$2,0)),Inputs!$B$4:$B$150,$B5)/1000) -> -46393 | W5: =IF(COUNT(S5:V5)=4,SUM(S5:V5),"") -> -199454 | X5: =IF(X$3=0,"",SUMIFS(INDEX(Inputs!$D$4:$AG$150,0,MATCH(X$2,Inputs!$D$2:$AG$2,0)),Inputs!$B$4:$B$150,$B5)/1000) -> -46788 | Y5: =IF(Y$3=0,"",SUMIFS(INDEX(Inputs!$D$4:$AG$150,0,MATCH(Y$2,Inputs!$D$2:$AG$2,0)),Inputs!$B$4:$B$150,$B5)/1000) -> -45327 | Z5: =IF(Z$3=0,"",SUMIFS(INDEX(Inputs!$D$4:$AG$150,0,MATCH(Z$2,Inputs!$D$2:$AG$2,0)),Inputs!$B$4:$B$150,$B5)/1000) -> -47928 | AA5: =IF(AA$3=0,"",SUMIFS(INDEX(Inputs!$D$4:$AG$150,0,MATCH(AA$2,Inputs!$D$2:$AG$2,0)),Inputs!$B$4:$B$150,$B5)/1000) -> -44205 | AB5: =IF(COUNT(X5:AA5)=4,SUM(X5:AA5),"") -> -184248 | AC5: =IF(AC$3=0,"",SUMIFS(INDEX(Inputs!$D$4:$AG$150,0,MATCH(AC$2,Inputs!$D$2:$AG$2,0)),Inputs!$B$4:$B$150,$B5)/1000) -> -51802 | AD5: =IF(AD$3=0,"",SUMIFS(INDEX(Inputs!$D$4:$AG$150,0,MATCH(AD$2,Inputs!$D$2:$AG$2,0)),Inputs!$B$4:$B$150,$B5)/1000) -> -67801 | AE5: =IF(AE$3=0,"",SUMIFS(INDEX(Inputs!$D$4:$AG$150,0,MATCH(AE$2,Inputs!$D$2:$AG$2,0)),Inputs!$B$4:$B$150,$B5)/1000) | AF5: =IF(AF$3=0,"",SUMIFS(INDEX(Inputs!$D$4:$AG$150,0,MATCH(AF$2,Inputs!$D$2:$AG$2,0)),Inputs!$B$4:$B$150,$B5)/1000) | AG5: =IF(COUNT(AC5:AF5)=4,SUM(AC5:AF5),"")
B6: 3 | C6: SG&A and Other (cash) | D6: =IF(D$3=0,"",SUMIFS(INDEX(Inputs!$D$4:$AG$150,0,MATCH(D$2,Inputs!$D$2:$AG$2,0)),Inputs!$B$4:$B$150,$B6)/1000) -> -17692 | E6: =IF(E$3=0,"",SUMIFS(INDEX(Inputs!$D$4:$AG$150,0,MATCH(E$2,Inputs!$D$2:$AG$2,0)),Inputs!$B$4:$B$150,$B6)/1000) -> -18900 | F6: =IF(F$3=0,"",SUMIFS(INDEX(Inputs!$D$4:$AG$150,0,MATCH(F$2,Inputs!$D$2:$AG$2,0)),Inputs!$B$4:$B$150,$B6)/1000) -> -19231 | G6: =IF(G$3=0,"",SUMIFS(INDEX(Inputs!$D$4:$AG$150,0,MATCH(G$2,Inputs!$D$2:$AG$2,0)),Inputs!$B$4:$B$150,$B6)/1000) -> -21865 | H6: =IF(COUNT(D6:G6)=4,SUM(D6:G6),"") -> -77688 | I6: =IF(I$3=0,"",SUMIFS(INDEX(Inputs!$D$4:$AG$150,0,MATCH(I$2,Inputs!$D$2:$AG$2,0)),Inputs!$B$4:$B$150,$B6)/1000) -> -20485 | J6: =IF(J$3=0,"",SUMIFS(INDEX(Inputs!$D$4:$AG$150,0,MATCH(J$2,Inputs!$D$2:$AG$2,0)),Inputs!$B$4:$B$150,$B6)/1000) -> -20490 | K6: =IF(K$3=0,"",SUMIFS(INDEX(Inputs!$D$4:$AG$150,0,MATCH(K$2,Inputs!$D$2:$AG$2,0)),Inputs!$B$4:$B$150,$B6)/1000) -> -20600 | L6: =IF(L$3=0,"",SUMIFS(INDEX(Inputs!$D$4:$AG$150,0,MATCH(L$2,Inputs!$D$2:$AG$2,0)),Inputs!$B$4:$B$150,$B6)/1000) -> -20555 | M6: =IF(COUNT(I6:L6)=4,SUM(I6:L6),"") -> -82130 | N6: =IF(N$3=0,"",SUMIFS(INDEX(Inputs!$D$4:$AG$150,0,MATCH(N$2,Inputs!$D$2:$AG$2,0)),Inputs!$B$4:$B$150,$B6)/1000) -> -19355 | O6: =IF(O$3=0,"",SUMIFS(INDEX(Inputs!$D$4:$AG$150,0,MATCH(O$2,Inputs!$D$2:$AG$2,0)),Inputs!$B$4:$B$150,$B6)/1000) -> -19169 | P6: =IF(P$3=0,"",SUMIFS(INDEX(Inputs!$D$4:$AG$150,0,MATCH(P$2,Inputs!$D$2:$AG$2,0)),Inputs!$B$4:$B$150,$B6)/1000) -> -19401 | Q6: =IF(Q$3=0,"",SUMIFS(INDEX(Inputs!$D$4:$AG$150,0,MATCH(Q$2,Inputs!$D$2:$AG$2,0)),Inputs!$B$4:$B$150,$B6)/1000) -> -19355 | R6: =IF(COUNT(N6:Q6)=4,SUM(N6:Q6),"") -> -77280 | S6: =IF(S$3=0,"",SUMIFS(INDEX(Inputs!$D$4:$AG$150,0,MATCH(S$2,Inputs!$D$2:$AG$2,0)),Inputs!$B$4:$B$150,$B6)/1000) -> -18080 | T6: =IF(T$3=0,"",SUMIFS(INDEX(Inputs!$D$4:$AG$150,0,MATCH(T$2,Inputs!$D$2:$AG$2,0)),Inputs!$B$4:$B$150,$B6)/1000) -> -19138 | U6: =IF(U$3=0,"",SUMIFS(INDEX(Inputs!$D$4:$AG$150,0,MATCH(U$2,Inputs!$D$2:$AG$2,0)),Inputs!$B$4:$B$150,$B6)/1000) -> -19264 | V6: =IF(V$3=0,"",SUMIFS(INDEX(Inputs!$D$4:$AG$150,0,MATCH(V$2,Inputs!$D$2:$AG$2,0)),Inputs!$B$4:$B$150,$B6)/1000) -> -20338 | W6: =IF(COUNT(S6:V6)=4,SUM(S6:V6),"") -> -76820 | X6: =IF(X$3=0,"",SUMIFS(INDEX(Inputs!$D$4:$AG$150,0,MATCH(X$2,Inputs!$D$2:$AG$2,0)),Inputs!$B$4:$B$150,$B6)/1000) -> -18835 | Y6: =IF(Y$3=0,"",SUMIFS(INDEX(Inputs!$D$4:$AG$150,0,MATCH(Y$2,Inputs!$D$2:$AG$2,0)),Inputs!$B$4:$B$150,$B6)/1000) -> -19228 | Z6: =IF(Z$3=0,"",SUMIFS(INDEX(Inputs!$D$4:$AG$150,0,MATCH(Z$2,Inputs!$D$2:$AG$2,0)),Inputs!$B$4:$B$150,$B6)/1000) -> -19869 | AA6: =IF(AA$3=0,"",SUMIFS(INDEX(Inputs!$D$4:$AG$150,0,MATCH(AA$2,Inputs!$D$2:$AG$2,0)),Inputs!$B$4:$B$150,$B6)/1000) -> -22194 | AB6: =IF(COUNT(X6:AA6)=4,SUM(X6:AA6),"") -> -80126 | AC6: =IF(AC$3=0,"",SUMIFS(INDEX(Inputs!$D$4:$AG$150,0,MATCH(AC$2,Inputs!$D$2:$AG$2,0)),Inputs!$B$4:$B$150,$B6)/1000) -> -19303 | AD6: =IF(AD$3=0,"",SUMIFS(INDEX(Inputs!$D$4:$AG$150,0,MATCH(AD$2,Inputs!$D$2:$AG$2,0)),Inputs!$B$4:$B$150,$B6)/1000) -> -19876 | AE6: =IF(AE$3=0,"",SUMIFS(INDEX(Inputs!$D$4:$AG$150,0,MATCH(AE$2,Inputs!$D$2:$AG$2,0)),Inputs!$B$4:$B$150,$B6)/1000) | AF6: =IF(AF$3=0,"",SUMIFS(INDEX(Inputs!$D$4:$AG$150,0,MATCH(AF$2,Inputs!$D$2:$AG$2,0)),Inputs!$B$4:$B$150,$B6)/1000) | AG6: =IF(COUNT(AC6:AF6)=4,SUM(AC6:AF6),"")
B7: 4 | C7: D&A | D7: =IF(D$3=0,"",SUMIFS(INDEX(Inputs!$D$4:$AG$150,0,MATCH(D$2,Inputs!$D$2:$AG$2,0)),Inputs!$B$4:$B$150,$B7)/1000) -> -5004 | E7: =IF(E$3=0,"",SUMIFS(INDEX(Inputs!$D$4:$AG$150,0,MATCH(E$2,Inputs!$D$2:$AG$2,0)),Inputs!$B$4:$B$150,$B7)/1000) -> -4952 | F7: =IF(F$3=0,"",SUMIFS(INDEX(Inputs!$D$4:$AG$150,0,MATCH(F$2,Inputs!$D$2:$AG$2,0)),Inputs!$B$4:$B$150,$B7)/1000) -> -4990 | G7: =IF(G$3=0,"",SUMIFS(INDEX(Inputs!$D$4:$AG$150,0,MATCH(G$2,Inputs!$D$2:$AG$2,0)),Inputs!$B$4:$B$150,$B7)/1000) -> -5661 | H7: =IF(COUNT(D7:G7)=4,SUM(D7:G7),"") -> -20607 | I7: =IF(I$3=0,"",SUMIFS(INDEX(Inputs!$D$4:$AG$150,0,MATCH(I$2,Inputs!$D$2:$AG$2,0)),Inputs!$B$4:$B$150,$B7)/1000) -> -8883 | J7: =IF(J$3=0,"",SUMIFS(INDEX(Inputs!$D$4:$AG$150,0,MATCH(J$2,Inputs!$D$2:$AG$2,0)),Inputs!$B$4:$B$150,$B7)/1000) -> -4451 | K7: =IF(K$3=0,"",SUMIFS(INDEX(Inputs!$D$4:$AG$150,0,MATCH(K$2,Inputs!$D$2:$AG$2,0)),Inputs!$B$4:$B$150,$B7)/1000) -> -5642 | L7: =IF(L$3=0,"",SUMIFS(INDEX(Inputs!$D$4:$AG$150,0,MATCH(L$2,Inputs!$D$2:$AG$2,0)),Inputs!$B$4:$B$150,$B7)/1000) -> -5064 | M7: =IF(COUNT(I7:L7)=4,SUM(I7:L7),"") -> -24040 | N7: =IF(N$3=0,"",SUMIFS(INDEX(Inputs!$D$4:$AG$150,0,MATCH(N$2,Inputs!$D$2:$AG$2,0)),Inputs!$B$4:$B$150,$B7)/1000) -> -4244 | O7: =IF(O$3=0,"",SUMIFS(INDEX(Inputs!$D$4:$AG$150,0,MATCH(O$2,Inputs!$D$2:$AG$2,0)),Inputs!$B$4:$B$150,$B7)/1000) -> -4242 | P7: =IF(P$3=0,"",SUMIFS(INDEX(Inputs!$D$4:$AG$150,0,MATCH(P$2,Inputs!$D$2:$AG$2,0)),Inputs!$B$4:$B$150,$B7)/1000) -> -4415 | Q7: =IF(Q$3=0,"",SUMIFS(INDEX(Inputs!$D$4:$AG$150,0,MATCH(Q$2,Inputs!$D$2:$AG$2,0)),Inputs!$B$4:$B$150,$B7)/1000) -> -7740 | R7: =IF(COUNT(N7:Q7)=4,SUM(N7:Q7),"") -> -20641 | S7: =IF(S$3=0,"",SUMIFS(INDEX(Inputs!$D$4:$AG$150,0,MATCH(S$2,Inputs!$D$2:$AG$2,0)),Inputs!$B$4:$B$150,$B7)/1000) -> -4812 | T7: =IF(T$3=0,"",SUMIFS(INDEX(Inputs!$D$4:$AG$150,0,MATCH(T$2,Inputs!$D$2:$AG$2,0)),Inputs!$B$4:$B$150,$B7)/1000) -> -5787 | U7: =IF(U$3=0,"",SUMIFS(INDEX(Inputs!$D$4:$AG$150,0,MATCH(U$2,Inputs!$D$2:$AG$2,0)),Inputs!$B$4:$B$150,$B7)/1000) -> -6258 | V7: =IF(V$3=0,"",SUMIFS(INDEX(Inputs!$D$4:$AG$150,0,MATCH(V$2,Inputs!$D$2:$AG$2,0)),Inputs!$B$4:$B$150,$B7)/1000) -> -6585 | W7: =IF(COUNT(S7:V7)=4,SUM(S7:V7),"") -> -23442 | X7: =IF(X$3=0,"",SUMIFS(INDEX(Inputs!$D$4:$AG$150,0,MATCH(X$2,Inputs!$D$2:$AG$2,0)),Inputs!$B$4:$B$150,$B7)/1000) -> -5702 | Y7: =IF(Y$3=0,"",SUMIFS(INDEX(Inputs!$D$4:$AG$150,0,MATCH(Y$2,Inputs!$D$2:$AG$2,0)),Inputs!$B$4:$B$150,$B7)/1000) -> -6101 | Z7: =IF(Z$3=0,"",SUMIFS(INDEX(Inputs!$D$4:$AG$150,0,MATCH(Z$2,Inputs!$D$2:$AG$2,0)),Inputs!$B$4:$B$150,$B7)/1000) -> -6475 | AA7: =IF(AA$3=0,"",SUMIFS(INDEX(Inputs!$D$4:$AG$150,0,MATCH(AA$2,Inputs!$D$2:$AG$2,0)),Inputs!$B$4:$B$150,$B7)/1000) -> -7715 | AB7: =IF(COUNT(X7:AA7)=4,SUM(X7:AA7),"") -> -25993 | AC7: =IF(AC$3=0,"",SUMIFS(INDEX(Inputs!$D$4:$AG$150,0,MATCH(AC$2,Inputs!$D$2:$AG$2,0)),Inputs!$B$4:$B$150,$B7)/1000) -> -6771 | AD7: =IF(AD$3=0,"",SUMIFS(INDEX(Inputs!$D$4:$AG$150,0,MATCH(AD$2,Inputs!$D$2:$AG$2,0)),Inputs!$B$4:$B$150,$B7)/1000) -> -8689 | AE7: =IF(AE$3=0,"",SUMIFS(INDEX(Inputs!$D$4:$AG$150,0,MATCH(AE$2,Inputs!$D$2:$AG$2,0)),Inputs!$B$4:$B$150,$B7)/1000) | AF7: =IF(AF$3=0,"",SUMIFS(INDEX(Inputs!$D$4:$AG$150,0,MATCH(AF$2,Inputs!$D$2:$AG$2,0)),Inputs!$B$4:$B$150,$B7)/1000) | AG7: =IF(COUNT(AC7:AF7)=4,SUM(AC7:AF7),"")
B8: 5 | C8: Interest Expense | D8: =IF(D$3=0,"",SUMIFS(INDEX(Inputs!$D$4:$AG$150,0,MATCH(D$2,Inputs!$D$2:$AG$2,0)),Inputs!$B$4:$B$150,$B8)/1000) -> -258 | E8: =IF(E$3=0,"",SUMIFS(INDEX(Inputs!$D$4:$AG$150,0,MATCH(E$2,Inputs!$D$2:$AG$2,0)),Inputs!$B$4:$B$150,$B8)/1000) -> -254 | F8: =IF(F$3=0,"",SUMIFS(INDEX(Inputs!$D$4:$AG$150,0,MATCH(F$2,Inputs!$D$2:$AG$2,0)),Inputs!$B$4:$B$150,$B8)/1000) -> -214 | G8: =IF(G$3=0,"",SUMIFS(INDEX(Inputs!$D$4:$AG$150,0,MATCH(G$2,Inputs!$D$2:$AG$2,0)),Inputs!$B$4:$B$150,$B8)/1000) -> -221 | H8: =IF(COUNT(D8:G8)=4,SUM(D8:G8),"") -> -947 | I8: =IF(I$3=0,"",SUMIFS(INDEX(Inputs!$D$4:$AG$150,0,MATCH(I$2,Inputs!$D$2:$AG$2,0)),Inputs!$B$4:$B$150,$B8)/1000) -> -188 | J8: =IF(J$3=0,"",SUMIFS(INDEX(Inputs!$D$4:$AG$150,0,MATCH(J$2,Inputs!$D$2:$AG$2,0)),Inputs!$B$4:$B$150,$B8)/1000) -> -194 | K8: =IF(K$3=0,"",SUMIFS(INDEX(Inputs!$D$4:$AG$150,0,MATCH(K$2,Inputs!$D$2:$AG$2,0)),Inputs!$B$4:$B$150,$B8)/1000) -> -209 | L8: =IF(L$3=0,"",SUMIFS(INDEX(Inputs!$D$4:$AG$150,0,MATCH(L$2,Inputs!$D$2:$AG$2,0)),Inputs!$B$4:$B$150,$B8)/1000) -> -207 | M8: =IF(COUNT(I8:L8)=4,SUM(I8:L8),"") -> -798 | N8: =IF(N$3=0,"",SUMIFS(INDEX(Inputs!$D$4:$AG$150,0,MATCH(N$2,Inputs!$D$2:$AG$2,0)),Inputs!$B$4:$B$150,$B8)/1000) -> -159 | O8: =IF(O$3=0,"",SUMIFS(INDEX(Inputs!$D$4:$AG$150,0,MATCH(O$2,Inputs!$D$2:$AG$2,0)),Inputs!$B$4:$B$150,$B8)/1000) -> -249 | P8: =IF(P$3=0,"",SUMIFS(INDEX(Inputs!$D$4:$AG$150,0,MATCH(P$2,Inputs!$D$2:$AG$2,0)),Inputs!$B$4:$B$150,$B8)/1000) -> -169 | Q8: =IF(Q$3=0,"",SUMIFS(INDEX(Inputs!$D$4:$AG$150,0,MATCH(Q$2,Inputs!$D$2:$AG$2,0)),Inputs!$B$4:$B$150,$B8)/1000) -> -272 | R8: =IF(COUNT(N8:Q8)=4,SUM(N8:Q8),"") -> -849 | S8: =IF(S$3=0,"",SUMIFS(INDEX(Inputs!$D$4:$AG$150,0,MATCH(S$2,Inputs!$D$2:$AG$2,0)),Inputs!$B$4:$B$150,$B8)/1000) -> -221 | T8: =IF(T$3=0,"",SUMIFS(INDEX(Inputs!$D$4:$AG$150,0,MATCH(T$2,Inputs!$D$2:$AG$2,0)),Inputs!$B$4:$B$150,$B8)/1000) -> -271 | U8: =IF(U$3=0,"",SUMIFS(INDEX(Inputs!$D$4:$AG$150,0,MATCH(U$2,Inputs!$D$2:$AG$2,0)),Inputs!$B$4:$B$150,$B8)/1000) -> -207 | V8: =IF(V$3=0,"",SUMIFS(INDEX(Inputs!$D$4:$AG$150,0,MATCH(V$2,Inputs!$D$2:$AG$2,0)),Inputs!$B$4:$B$150,$B8)/1000) -> -297 | W8: =IF(COUNT(S8:V8)=4,SUM(S8:V8),"") -> -996 | X8: =IF(X$3=0,"",SUMIFS(INDEX(Inputs!$D$4:$AG$150,0,MATCH(X$2,Inputs!$D$2:$AG$2,0)),Inputs!$B$4:$B$150,$B8)/1000) -> -205 | Y8: =IF(Y$3=0,"",SUMIFS(INDEX(Inputs!$D$4:$AG$150,0,MATCH(Y$2,Inputs!$D$2:$AG$2,0)),Inputs!$B$4:$B$150,$B8)/1000) -> -145 | Z8: =IF(Z$3=0,"",SUMIFS(INDEX(Inputs!$D$4:$AG$150,0,MATCH(Z$2,Inputs!$D$2:$AG$2,0)),Inputs!$B$4:$B$150,$B8)/1000) -> -90 | AA8: =IF(AA$3=0,"",SUMIFS(INDEX(Inputs!$D$4:$AG$150,0,MATCH(AA$2,Inputs!$D$2:$AG$2,0)),Inputs!$B$4:$B$150,$B8)/1000) -> -163 | AB8: =IF(COUNT(X8:AA8)=4,SUM(X8:AA8),"") -> -603 | AC8: =IF(AC$3=0,"",SUMIFS(INDEX(Inputs!$D$4:$AG$150,0,MATCH(AC$2,Inputs!$D$2:$AG$2,0)),Inputs!$B$4:$B$150,$B8)/1000) -> -295 | AD8: =IF(AD$3=0,"",SUMIFS(INDEX(Inputs!$D$4:$AG$150,0,MATCH(AD$2,Inputs!$D$2:$AG$2,0)),Inputs!$B$4:$B$150,$B8)/1000) -> -227 | AE8: =IF(AE$3=0,"",SUMIFS(INDEX(Inputs!$D$4:$AG$150,0,MATCH(AE$2,Inputs!$D$2:$AG$2,0)),Inputs!$B$4:$B$150,$B8)/1000) | AF8: =IF(AF$3=0,"",SUMIFS(INDEX(Inputs!$D$4:$AG$150,0,MATCH(AF$2,Inputs!$D$2:$AG$2,0)),Inputs!$B$4:$B$150,$B8)/1000) | AG8: =IF(COUNT(AC8:AF8)=4,SUM(AC8:AF8),"")
B9: 6 | C9: Nonoperating Income / (Loss) | D9: =IF(D$3=0,"",SUMIFS(INDEX(Inputs!$D$4:$AG$150,0,MATCH(D$2,Inputs!$D$2:$AG$2,0)),Inputs!$B$4:$B$150,$B9)/1000) -> 0 | E9: =IF(E$3=0,"",SUMIFS(INDEX(Inputs!$D$4:$AG$150,0,MATCH(E$2,Inputs!$D$2:$AG$2,0)),Inputs!$B$4:$B$150,$B9)/1000) -> 0 | F9: =IF(F$3=0,"",SUMIFS(INDEX(Inputs!$D$4:$AG$150,0,MATCH(F$2,Inputs!$D$2:$AG$2,0)),Inputs!$B$4:$B$150,$B9)/1000) -> 0 | G9: =IF(G$3=0,"",SUMIFS(INDEX(Inputs!$D$4:$AG$150,0,MATCH(G$2,Inputs!$D$2:$AG$2,0)),Inputs!$B$4:$B$150,$B9)/1000) -> 0 | H9: =IF(COUNT(D9:G9)=4,SUM(D9:G9),"") -> 0 | I9: =IF(I$3=0,"",SUMIFS(INDEX(Inputs!$D$4:$AG$150,0,MATCH(I$2,Inputs!$D$2:$AG$2,0)),Inputs!$B$4:$B$150,$B9)/1000) -> 0 | J9: =IF(J$3=0,"",SUMIFS(INDEX(Inputs!$D$4:$AG$150,0,MATCH(J$2,Inputs!$D$2:$AG$2,0)),Inputs!$B$4:$B$150,$B9)/1000) -> 0 | K9: =IF(K$3=0,"",SUMIFS(INDEX(Inputs!$D$4:$AG$150,0,MATCH(K$2,Inputs!$D$2:$AG$2,0)),Inputs!$B$4:$B$150,$B9)/1000) -> 0 | L9: =IF(L$3=0,"",SUMIFS(INDEX(Inputs!$D$4:$AG$150,0,MATCH(L$2,Inputs!$D$2:$AG$2,0)),Inputs!$B$4:$B$150,$B9)/1000) -> 0 | M9: =IF(COUNT(I9:L9)=4,SUM(I9:L9),"") -> 0 | N9: =IF(N$3=0,"",SUMIFS(INDEX(Inputs!$D$4:$AG$150,0,MATCH(N$2,Inputs!$D$2:$AG$2,0)),Inputs!$B$4:$B$150,$B9)/1000) -> 0 | O9: =IF(O$3=0,"",SUMIFS(INDEX(Inputs!$D$4:$AG$150,0,MATCH(O$2,Inputs!$D$2:$AG$2,0)),Inputs!$B$4:$B$150,$B9)/1000) -> 0 | P9: =IF(P$3=0,"",SUMIFS(INDEX(Inputs!$D$4:$AG$150,0,MATCH(P$2,Inputs!$D$2:$AG$2,0)),Inputs!$B$4:$B$150,$B9)/1000) -> 0 | Q9: =IF(Q$3=0,"",SUMIFS(INDEX(Inputs!$D$4:$AG$150,0,MATCH(Q$2,Inputs!$D$2:$AG$2,0)),Inputs!$B$4:$B$150,$B9)/1000) -> 0 | R9: =IF(COUNT(N9:Q9)=4,SUM(N9:Q9),"") -> 0 | S9: =IF(S$3=0,"",SUMIFS(INDEX(Inputs!$D$4:$AG$150,0,MATCH(S$2,Inputs!$D$2:$AG$2,0)),Inputs!$B$4:$B$150,$B9)/1000) -> 0 | T9: =IF(T$3=0,"",SUMIFS(INDEX(Inputs!$D$4:$AG$150,0,MATCH(T$2,Inputs!$D$2:$AG$2,0)),Inputs!$B$4:$B$150,$B9)/1000) -> 0 | U9: =IF(U$3=0,"",SUMIFS(INDEX(Inputs!$D$4:$AG$150,0,MATCH(U$2,Inputs!$D$2:$AG$2,0)),Inputs!$B$4:$B$150,$B9)/1000) -> 0 | V9: =IF(V$3=0,"",SUMIFS(INDEX(Inputs!$D$4:$AG$150,0,MATCH(V$2,Inputs!$D$2:$AG$2,0)),Inputs!$B$4:$B$150,$B9)/1000) -> 0 | W9: =IF(COUNT(S9:V9)=4,SUM(S9:V9),"") -> 0 | X9: =IF(X$3=0,"",SUMIFS(INDEX(Inputs!$D$4:$AG$150,0,MATCH(X$2,Inputs!$D$2:$AG$2,0)),Inputs!$B$4:$B$150,$B9)/1000) -> 0 | Y9: =IF(Y$3=0,"",SUMIFS(INDEX(Inputs!$D$4:$AG$150,0,MATCH(Y$2,Inputs!$D$2:$AG$2,0)),Inputs!$B$4:$B$150,$B9)/1000) -> 0 | Z9: =IF(Z$3=0,"",SUMIFS(INDEX(Inputs!$D$4:$AG$150,0,MATCH(Z$2,Inputs!$D$2:$AG$2,0)),Inputs!$B$4:$B$150,$B9)/1000) -> 0 | AA9: =IF(AA$3=0,"",SUMIFS(INDEX(Inputs!$D$4:$AG$150,0,MATCH(AA$2,Inputs!$D$2:$AG$2,0)),Inputs!$B$4:$B$150,$B9)/1000) -> 0 | AB9: =IF(COUNT(X9:AA9)=4,SUM(X9:AA9),"") -> 0 | AC9: =IF(AC$3=0,"",SUMIFS(INDEX(Inputs!$D$4:$AG$150,0,MATCH(AC$2,Inputs!$D$2:$AG$2,0)),Inputs!$B$4:$B$150,$B9)/1000) -> 0 | AD9: =IF(AD$3=0,"",SUMIFS(INDEX(Inputs!$D$4:$AG$150,0,MATCH(AD$2,Inputs!$D$2:$AG$2,0)),Inputs!$B$4:$B$150,$B9)/1000) -> 0 | AE9: =IF(AE$3=0,"",SUMIFS(INDEX(Inputs!$D$4:$AG$150,0,MATCH(AE$2,Inputs!$D$2:$AG$2,0)),Inputs!$B$4:$B$150,$B9)/1000) | AF9: =IF(AF$3=0,"",SUMIFS(INDEX(Inputs!$D$4:$AG$150,0,MATCH(AF$2,Inputs!$D$2:$AG$2,0)),Inputs!$B$4:$B$150,$B9)/1000) | AG9: =IF(COUNT(AC9:AF9)=4,SUM(AC9:AF9),"")
B10: 7 | C10: Taxes | D10: =IF(D$3=0,"",SUMIFS(INDEX(Inputs!$D$4:$AG$150,0,MATCH(D$2,Inputs!$D$2:$AG$2,0)),Inputs!$B$4:$B$150,$B10)/1000) -> -796 | E10: =IF(E$3=0,"",SUMIFS(INDEX(Inputs!$D$4:$AG$150,0,MATCH(E$2,Inputs!$D$2:$AG$2,0)),Inputs!$B$4:$B$150,$B10)/1000) -> -1526 | F10: =IF(F$3=0,"",SUMIFS(INDEX(Inputs!$D$4:$AG$150,0,MATCH(F$2,Inputs!$D$2:$AG$2,0)),Inputs!$B$4:$B$150,$B10)/1000) -> -2664 | G10: =IF(G$3=0,"",SUMIFS(INDEX(Inputs!$D$4:$AG$150,0,MATCH(G$2,Inputs!$D$2:$AG$2,0)),Inputs!$B$4:$B$150,$B10)/1000) -> -2650 | H10: =IF(COUNT(D10:G10)=4,SUM(D10:G10),"") -> -7636 | I10: =IF(I$3=0,"",SUMIFS(INDEX(Inputs!$D$4:$AG$150,0,MATCH(I$2,Inputs!$D$2:$AG$2,0)),Inputs!$B$4:$B$150,$B10)/1000) -> -2806 | J10: =IF(J$3=0,"",SUMIFS(INDEX(Inputs!$D$4:$AG$150,0,MATCH(J$2,Inputs!$D$2:$AG$2,0)),Inputs!$B$4:$B$150,$B10)/1000) -> -6359 | K10: =IF(K$3=0,"",SUMIFS(INDEX(Inputs!$D$4:$AG$150,0,MATCH(K$2,Inputs!$D$2:$AG$2,0)),Inputs!$B$4:$B$150,$B10)/1000) -> -5224 | L10: =IF(L$3=0,"",SUMIFS(INDEX(Inputs!$D$4:$AG$150,0,MATCH(L$2,Inputs!$D$2:$AG$2,0)),Inputs!$B$4:$B$150,$B10)/1000) -> -5787 | M10: =IF(COUNT(I10:L10)=4,SUM(I10:L10),"") -> -20176 | N10: =IF(N$3=0,"",SUMIFS(INDEX(Inputs!$D$4:$AG$150,0,MATCH(N$2,Inputs!$D$2:$AG$2,0)),Inputs!$B$4:$B$150,$B10)/1000) -> -4960 | O10: =IF(O$3=0,"",SUMIFS(INDEX(Inputs!$D$4:$AG$150,0,MATCH(O$2,Inputs!$D$2:$AG$2,0)),Inputs!$B$4:$B$150,$B10)/1000) -> -3503 | P10: =IF(P$3=0,"",SUMIFS(INDEX(Inputs!$D$4:$AG$150,0,MATCH(P$2,Inputs!$D$2:$AG$2,0)),Inputs!$B$4:$B$150,$B10)/1000) -> -4353 | Q10: =IF(Q$3=0,"",SUMIFS(INDEX(Inputs!$D$4:$AG$150,0,MATCH(Q$2,Inputs!$D$2:$AG$2,0)),Inputs!$B$4:$B$150,$B10)/1000) -> -2613 | R10: =IF(COUNT(N10:Q10)=4,SUM(N10:Q10),"") -> -15429 | S10: =IF(S$3=0,"",SUMIFS(INDEX(Inputs!$D$4:$AG$150,0,MATCH(S$2,Inputs!$D$2:$AG$2,0)),Inputs!$B$4:$B$150,$B10)/1000) -> -3803 | T10: =IF(T$3=0,"",SUMIFS(INDEX(Inputs!$D$4:$AG$150,0,MATCH(T$2,Inputs!$D$2:$AG$2,0)),Inputs!$B$4:$B$150,$B10)/1000) -> -4094 | U10: =IF(U$3=0,"",SUMIFS(INDEX(Inputs!$D$4:$AG$150,0,MATCH(U$2,Inputs!$D$2:$AG$2,0)),Inputs!$B$4:$B$150,$B10)/1000) -> -4055 | V10: =IF(V$3=0,"",SUMIFS(INDEX(Inputs!$D$4:$AG$150,0,MATCH(V$2,Inputs!$D$2:$AG$2,0)),Inputs!$B$4:$B$150,$B10)/1000) -> -1858 | W10: =IF(COUNT(S10:V10)=4,SUM(S10:V10),"") -> -13810 | X10: =IF(X$3=0,"",SUMIFS(INDEX(Inputs!$D$4:$AG$150,0,MATCH(X$2,Inputs!$D$2:$AG$2,0)),Inputs!$B$4:$B$150,$B10)/1000) -> -3567 | Y10: =IF(Y$3=0,"",SUMIFS(INDEX(Inputs!$D$4:$AG$150,0,MATCH(Y$2,Inputs!$D$2:$AG$2,0)),Inputs!$B$4:$B$150,$B10)/1000) -> -3351 | Z10: =IF(Z$3=0,"",SUMIFS(INDEX(Inputs!$D$4:$AG$150,0,MATCH(Z$2,Inputs!$D$2:$AG$2,0)),Inputs!$B$4:$B$150,$B10)/1000) -> -3164 | AA10: =IF(AA$3=0,"",SUMIFS(INDEX(Inputs!$D$4:$AG$150,0,MATCH(AA$2,Inputs!$D$2:$AG$2,0)),Inputs!$B$4:$B$150,$B10)/1000) -> -1422 | AB10: =IF(COUNT(X10:AA10)=4,SUM(X10:AA10),"") -> -11504 | AC10: =IF(AC$3=0,"",SUMIFS(INDEX(Inputs!$D$4:$AG$150,0,MATCH(AC$2,Inputs!$D$2:$AG$2,0)),Inputs!$B$4:$B$150,$B10)/1000) -> -2495 | AD10: =IF(AD$3=0,"",SUMIFS(INDEX(Inputs!$D$4:$AG$150,0,MATCH(AD$2,Inputs!$D$2:$AG$2,0)),Inputs!$B$4:$B$150,$B10)/1000) -> -4543 | AE10: =IF(AE$3=0,"",SUMIFS(INDEX(Inputs!$D$4:$AG$150,0,MATCH(AE$2,Inputs!$D$2:$AG$2,0)),Inputs!$B$4:$B$150,$B10)/1000) | AF10: =IF(AF$3=0,"",SUMIFS(INDEX(Inputs!$D$4:$AG$150,0,MATCH(AF$2,Inputs!$D$2:$AG$2,0)),Inputs!$B$4:$B$150,$B10)/1000) | AG10: =IF(COUNT(AC10:AF10)=4,SUM(AC10:AF10),"")
B11: 8 | C11: Equity in Income of Affiliates, after tax (enter as +) | D11: =IF(D$3=0,"",SUMIFS(INDEX(Inputs!$D$4:$AG$150,0,MATCH(D$2,Inputs!$D$2:$AG$2,0)),Inputs!$B$4:$B$150,$B11)/1000) -> 0 | E11: =IF(E$3=0,"",SUMIFS(INDEX(Inputs!$D$4:$AG$150,0,MATCH(E$2,Inputs!$D$2:$AG$2,0)),Inputs!$B$4:$B$150,$B11)/1000) -> 0 | F11: =IF(F$3=0,"",SUMIFS(INDEX(Inputs!$D$4:$AG$150,0,MATCH(F$2,Inputs!$D$2:$AG$2,0)),Inputs!$B$4:$B$150,$B11)/1000) -> 0 | G11: =IF(G$3=0,"",SUMIFS(INDEX(Inputs!$D$4:$AG$150,0,MATCH(G$2,Inputs!$D$2:$AG$2,0)),Inputs!$B$4:$B$150,$B11)/1000) -> 0 | H11: =IF(COUNT(D11:G11)=4,SUM(D11:G11),"") -> 0 | I11: =IF(I$3=0,"",SUMIFS(INDEX(Inputs!$D$4:$AG$150,0,MATCH(I$2,Inputs!$D$2:$AG$2,0)),Inputs!$B$4:$B$150,$B11)/1000) -> 0 | J11: =IF(J$3=0,"",SUMIFS(INDEX(Inputs!$D$4:$AG$150,0,MATCH(J$2,Inputs!$D$2:$AG$2,0)),Inputs!$B$4:$B$150,$B11)/1000) -> 0 | K11: =IF(K$3=0,"",SUMIFS(INDEX(Inputs!$D$4:$AG$150,0,MATCH(K$2,Inputs!$D$2:$AG$2,0)),Inputs!$B$4:$B$150,$B11)/1000) -> 0 | L11: =IF(L$3=0,"",SUMIFS(INDEX(Inputs!$D$4:$AG$150,0,MATCH(L$2,Inputs!$D$2:$AG$2,0)),Inputs!$B$4:$B$150,$B11)/1000) -> 0 | M11: =IF(COUNT(I11:L11)=4,SUM(I11:L11),"") -> 0 | N11: =IF(N$3=0,"",SUMIFS(INDEX(Inputs!$D$4:$AG$150,0,MATCH(N$2,Inputs!$D$2:$AG$2,0)),Inputs!$B$4:$B$150,$B11)/1000) -> 0 | O11: =IF(O$3=0,"",SUMIFS(INDEX(Inputs!$D$4:$AG$150,0,MATCH(O$2,Inputs!$D$2:$AG$2,0)),Inputs!$B$4:$B$150,$B11)/1000) -> 0 | P11: =IF(P$3=0,"",SUMIFS(INDEX(Inputs!$D$4:$AG$150,0,MATCH(P$2,Inputs!$D$2:$AG$2,0)),Inputs!$B$4:$B$150,$B11)/1000) -> 0 | Q11: =IF(Q$3=0,"",SUMIFS(INDEX(Inputs!$D$4:$AG$150,0,MATCH(Q$2,Inputs!$D$2:$AG$2,0)),Inputs!$B$4:$B$150,$B11)/1000) -> 0 | R11: =IF(COUNT(N11:Q11)=4,SUM(N11:Q11),"") -> 0 | S11: =IF(S$3=0,"",SUMIFS(INDEX(Inputs!$D$4:$AG$150,0,MATCH(S$2,Inputs!$D$2:$AG$2,0)),Inputs!$B$4:$B$150,$B11)/1000) -> 0 | T11: =IF(T$3=0,"",SUMIFS(INDEX(Inputs!$D$4:$AG$150,0,MATCH(T$2,Inputs!$D$2:$AG$2,0)),Inputs!$B$4:$B$150,$B11)/1000) -> 0 | U11: =IF(U$3=0,"",SUMIFS(INDEX(Inputs!$D$4:$AG$150,0,MATCH(U$2,Inputs!$D$2:$AG$2,0)),Inputs!$B$4:$B$150,$B11)/1000) -> 0 | V11: =IF(V$3=0,"",SUMIFS(INDEX(Inputs!$D$4:$AG$150,0,MATCH(V$2,Inputs!$D$2:$AG$2,0)),Inputs!$B$4:$B$150,$B11)/1000) -> 0 | W11: =IF(COUNT(S11:V11)=4,SUM(S11:V11),"") -> 0 | X11: =IF(X$3=0,"",SUMIFS(INDEX(Inputs!$D$4:$AG$150,0,MATCH(X$2,Inputs!$D$2:$AG$2,0)),Inputs!$B$4:$B$150,$B11)/1000) -> 0 | Y11: =IF(Y$3=0,"",SUMIFS(INDEX(Inputs!$D$4:$AG$150,0,MATCH(Y$2,Inputs!$D$2:$AG$2,0)),Inputs!$B$4:$B$150,$B11)/1000) -> 0 | Z11: =IF(Z$3=0,"",SUMIFS(INDEX(Inputs!$D$4:$AG$150,0,MATCH(Z$2,Inputs!$D$2:$AG$2,0)),Inputs!$B$4:$B$150,$B11)/1000) -> 0 | AA11: =IF(AA$3=0,"",SUMIFS(INDEX(Inputs!$D$4:$AG$150,0,MATCH(AA$2,Inputs!$D$2:$AG$2,0)),Inputs!$B$4:$B$150,$B11)/1000) -> 0 | AB11: =IF(COUNT(X11:AA11)=4,SUM(X11:AA11),"") -> 0 | AC11: =IF(AC$3=0,"",SUMIFS(INDEX(Inputs!$D$4:$AG$150,0,MATCH(AC$2,Inputs!$D$2:$AG$2,0)),Inputs!$B$4:$B$150,$B11)/1000) -> 0 | AD11: =IF(AD$3=0,"",SUMIFS(INDEX(Inputs!$D$4:$AG$150,0,MATCH(AD$2,Inputs!$D$2:$AG$2,0)),Inputs!$B$4:$B$150,$B11)/1000) -> 0 | AE11: =IF(AE$3=0,"",SUMIFS(INDEX(Inputs!$D$4:$AG$150,0,MATCH(AE$2,Inputs!$D$2:$AG$2,0)),Inputs!$B$4:$B$150,$B11)/1000) | AF11: =IF(AF$3=0,"",SUMIFS(INDEX(Inputs!$D$4:$AG$150,0,MATCH(AF$2,Inputs!$D$2:$AG$2,0)),Inputs!$B$4:$B$150,$B11)/1000) | AG11: =IF(COUNT(AC11:AF11)=4,SUM(AC11:AF11),"")
B12: 9 | C12: Minority Interest Expense, after tax (enter as - ) | D12: =IF(D$3=0,"",SUMIFS(INDEX(Inputs!$D$4:$AG$150,0,MATCH(D$2,Inputs!$D$2:$AG$2,0)),Inputs!$B$4:$B$150,$B12)/1000) -> -66 | E12: =IF(E$3=0,"",SUMIFS(INDEX(Inputs!$D$4:$AG$150,0,MATCH(E$2,Inputs!$D$2:$AG$2,0)),Inputs!$B$4:$B$150,$B12)/1000) -> -91 | F12: =IF(F$3=0,"",SUMIFS(INDEX(Inputs!$D$4:$AG$150,0,MATCH(F$2,Inputs!$D$2:$AG$2,0)),Inputs!$B$4:$B$150,$B12)/1000) -> -192 | G12: =IF(G$3=0,"",SUMIFS(INDEX(Inputs!$D$4:$AG$150,0,MATCH(G$2,Inputs!$D$2:$AG$2,0)),Inputs!$B$4:$B$150,$B12)/1000) -> -209 | H12: =IF(COUNT(D12:G12)=4,SUM(D12:G12),"") -> -558 | I12: =IF(I$3=0,"",SUMIFS(INDEX(Inputs!$D$4:$AG$150,0,MATCH(I$2,Inputs!$D$2:$AG$2,0)),Inputs!$B$4:$B$150,$B12)/1000) -> -270 | J12: =IF(J$3=0,"",SUMIFS(INDEX(Inputs!$D$4:$AG$150,0,MATCH(J$2,Inputs!$D$2:$AG$2,0)),Inputs!$B$4:$B$150,$B12)/1000) -> -724 | K12: =IF(K$3=0,"",SUMIFS(INDEX(Inputs!$D$4:$AG$150,0,MATCH(K$2,Inputs!$D$2:$AG$2,0)),Inputs!$B$4:$B$150,$B12)/1000) -> -538 | L12: =IF(L$3=0,"",SUMIFS(INDEX(Inputs!$D$4:$AG$150,0,MATCH(L$2,Inputs!$D$2:$AG$2,0)),Inputs!$B$4:$B$150,$B12)/1000) -> -305 | M12: =IF(COUNT(I12:L12)=4,SUM(I12:L12),"") -> -1837 | N12: =IF(N$3=0,"",SUMIFS(INDEX(Inputs!$D$4:$AG$150,0,MATCH(N$2,Inputs!$D$2:$AG$2,0)),Inputs!$B$4:$B$150,$B12)/1000) -> -413 | O12: =IF(O$3=0,"",SUMIFS(INDEX(Inputs!$D$4:$AG$150,0,MATCH(O$2,Inputs!$D$2:$AG$2,0)),Inputs!$B$4:$B$150,$B12)/1000) -> -273 | P12: =IF(P$3=0,"",SUMIFS(INDEX(Inputs!$D$4:$AG$150,0,MATCH(P$2,Inputs!$D$2:$AG$2,0)),Inputs!$B$4:$B$150,$B12)/1000) -> -276 | Q12: =IF(Q$3=0,"",SUMIFS(INDEX(Inputs!$D$4:$AG$150,0,MATCH(Q$2,Inputs!$D$2:$AG$2,0)),Inputs!$B$4:$B$150,$B12)/1000) -> -382 | R12: =IF(COUNT(N12:Q12)=4,SUM(N12:Q12),"") -> -1344 | S12: =IF(S$3=0,"",SUMIFS(INDEX(Inputs!$D$4:$AG$150,0,MATCH(S$2,Inputs!$D$2:$AG$2,0)),Inputs!$B$4:$B$150,$B12)/1000) -> -346 | T12: =IF(T$3=0,"",SUMIFS(INDEX(Inputs!$D$4:$AG$150,0,MATCH(T$2,Inputs!$D$2:$AG$2,0)),Inputs!$B$4:$B$150,$B12)/1000) -> -331 | U12: =IF(U$3=0,"",SUMIFS(INDEX(Inputs!$D$4:$AG$150,0,MATCH(U$2,Inputs!$D$2:$AG$2,0)),Inputs!$B$4:$B$150,$B12)/1000) -> -361 | V12: =IF(V$3=0,"",SUMIFS(INDEX(Inputs!$D$4:$AG$150,0,MATCH(V$2,Inputs!$D$2:$AG$2,0)),Inputs!$B$4:$B$150,$B12)/1000) -> -345 | W12: =IF(COUNT(S12:V12)=4,SUM(S12:V12),"") -> -1383 | X12: =IF(X$3=0,"",SUMIFS(INDEX(Inputs!$D$4:$AG$150,0,MATCH(X$2,Inputs!$D$2:$AG$2,0)),Inputs!$B$4:$B$150,$B12)/1000) -> -320 | Y12: =IF(Y$3=0,"",SUMIFS(INDEX(Inputs!$D$4:$AG$150,0,MATCH(Y$2,Inputs!$D$2:$AG$2,0)),Inputs!$B$4:$B$150,$B12)/1000) -> -272 | Z12: =IF(Z$3=0,"",SUMIFS(INDEX(Inputs!$D$4:$AG$150,0,MATCH(Z$2,Inputs!$D$2:$AG$2,0)),Inputs!$B$4:$B$150,$B12)/1000) -> -220 | AA12: =IF(AA$3=0,"",SUMIFS(INDEX(Inputs!$D$4:$AG$150,0,MATCH(AA$2,Inputs!$D$2:$AG$2,0)),Inputs!$B$4:$B$150,$B12)/1000) -> -108 | AB12: =IF(COUNT(X12:AA12)=4,SUM(X12:AA12),"") -> -920 | AC12: =IF(AC$3=0,"",SUMIFS(INDEX(Inputs!$D$4:$AG$150,0,MATCH(AC$2,Inputs!$D$2:$AG$2,0)),Inputs!$B$4:$B$150,$B12)/1000) -> -289 | AD12: =IF(AD$3=0,"",SUMIFS(INDEX(Inputs!$D$4:$AG$150,0,MATCH(AD$2,Inputs!$D$2:$AG$2,0)),Inputs!$B$4:$B$150,$B12)/1000) -> -356 | AE12: =IF(AE$3=0,"",SUMIFS(INDEX(Inputs!$D$4:$AG$150,0,MATCH(AE$2,Inputs!$D$2:$AG$2,0)),Inputs!$B$4:$B$150,$B12)/1000) | AF12: =IF(AF$3=0,"",SUMIFS(INDEX(Inputs!$D$4:$AG$150,0,MATCH(AF$2,Inputs!$D$2:$AG$2,0)),Inputs!$B$4:$B$150,$B12)/1000) | AG12: =IF(COUNT(AC12:AF12)=4,SUM(AC12:AF12),"")
B13: 10 | C13: Common Dividends | D13: =IF(D$3=0,"",SUMIFS(INDEX(Inputs!$D$4:$AG$150,0,MATCH(D$2,Inputs!$D$2:$AG$2,0)),Inputs!$B$4:$B$150,$B13)/1000) -> -3720 | E13: =IF(E$3=0,"",SUMIFS(INDEX(Inputs!$D$4:$AG$150,0,MATCH(E$2,Inputs!$D$2:$AG$2,0)),Inputs!$B$4:$B$150,$B13)/1000) -> -3721 | F13: =IF(F$3=0,"",SUMIFS(INDEX(Inputs!$D$4:$AG$150,0,MATCH(F$2,Inputs!$D$2:$AG$2,0)),Inputs!$B$4:$B$150,$B13)/1000) -> -3720 | G13: =IF(G$3=0,"",SUMIFS(INDEX(Inputs!$D$4:$AG$150,0,MATCH(G$2,Inputs!$D$2:$AG$2,0)),Inputs!$B$4:$B$150,$B13)/1000) -> -3763 | H13: =IF(COUNT(D13:G13)=4,SUM(D13:G13),"") -> -14924 | I13: =IF(I$3=0,"",SUMIFS(INDEX(Inputs!$D$4:$AG$150,0,MATCH(I$2,Inputs!$D$2:$AG$2,0)),Inputs!$B$4:$B$150,$B13)/1000) -> -3760 | J13: =IF(J$3=0,"",SUMIFS(INDEX(Inputs!$D$4:$AG$150,0,MATCH(J$2,Inputs!$D$2:$AG$2,0)),Inputs!$B$4:$B$150,$B13)/1000) -> -3727 | K13: =IF(K$3=0,"",SUMIFS(INDEX(Inputs!$D$4:$AG$150,0,MATCH(K$2,Inputs!$D$2:$AG$2,0)),Inputs!$B$4:$B$150,$B13)/1000) -> -3685 | L13: =IF(L$3=0,"",SUMIFS(INDEX(Inputs!$D$4:$AG$150,0,MATCH(L$2,Inputs!$D$2:$AG$2,0)),Inputs!$B$4:$B$150,$B13)/1000) -> -3767 | M13: =IF(COUNT(I13:L13)=4,SUM(I13:L13),"") -> -14939 | N13: =IF(N$3=0,"",SUMIFS(INDEX(Inputs!$D$4:$AG$150,0,MATCH(N$2,Inputs!$D$2:$AG$2,0)),Inputs!$B$4:$B$150,$B13)/1000) -> -3738 | O13: =IF(O$3=0,"",SUMIFS(INDEX(Inputs!$D$4:$AG$150,0,MATCH(O$2,Inputs!$D$2:$AG$2,0)),Inputs!$B$4:$B$150,$B13)/1000) -> -3701 | P13: =IF(P$3=0,"",SUMIFS(INDEX(Inputs!$D$4:$AG$150,0,MATCH(P$2,Inputs!$D$2:$AG$2,0)),Inputs!$B$4:$B$150,$B13)/1000) -> -3663 | Q13: =IF(Q$3=0,"",SUMIFS(INDEX(Inputs!$D$4:$AG$150,0,MATCH(Q$2,Inputs!$D$2:$AG$2,0)),Inputs!$B$4:$B$150,$B13)/1000) -> -3839 | R13: =IF(COUNT(N13:Q13)=4,SUM(N13:Q13),"") -> -14941 | S13: =IF(S$3=0,"",SUMIFS(INDEX(Inputs!$D$4:$AG$150,0,MATCH(S$2,Inputs!$D$2:$AG$2,0)),Inputs!$B$4:$B$150,$B13)/1000) -> -3808 | T13: =IF(T$3=0,"",SUMIFS(INDEX(Inputs!$D$4:$AG$150,0,MATCH(T$2,Inputs!$D$2:$AG$2,0)),Inputs!$B$4:$B$150,$B13)/1000) -> -4285 | U13: =IF(U$3=0,"",SUMIFS(INDEX(Inputs!$D$4:$AG$150,0,MATCH(U$2,Inputs!$D$2:$AG$2,0)),Inputs!$B$4:$B$150,$B13)/1000) -> -4240 | V13: =IF(V$3=0,"",SUMIFS(INDEX(Inputs!$D$4:$AG$150,0,MATCH(V$2,Inputs!$D$2:$AG$2,0)),Inputs!$B$4:$B$150,$B13)/1000) -> -4371 | W13: =IF(COUNT(S13:V13)=4,SUM(S13:V13),"") -> -16704 | X13: =IF(X$3=0,"",SUMIFS(INDEX(Inputs!$D$4:$AG$150,0,MATCH(X$2,Inputs!$D$2:$AG$2,0)),Inputs!$B$4:$B$150,$B13)/1000) -> -4335 | Y13: =IF(Y$3=0,"",SUMIFS(INDEX(Inputs!$D$4:$AG$150,0,MATCH(Y$2,Inputs!$D$2:$AG$2,0)),Inputs!$B$4:$B$150,$B13)/1000) -> -4288 | Z13: =IF(Z$3=0,"",SUMIFS(INDEX(Inputs!$D$4:$AG$150,0,MATCH(Z$2,Inputs!$D$2:$AG$2,0)),Inputs!$B$4:$B$150,$B13)/1000) -> -4242 | AA13: =IF(AA$3=0,"",SUMIFS(INDEX(Inputs!$D$4:$AG$150,0,MATCH(AA$2,Inputs!$D$2:$AG$2,0)),Inputs!$B$4:$B$150,$B13)/1000) -> -4366 | AB13: =IF(COUNT(X13:AA13)=4,SUM(X13:AA13),"") -> -17231 | AC13: =IF(AC$3=0,"",SUMIFS(INDEX(Inputs!$D$4:$AG$150,0,MATCH(AC$2,Inputs!$D$2:$AG$2,0)),Inputs!$B$4:$B$150,$B13)/1000) -> -4334 | AD13: =IF(AD$3=0,"",SUMIFS(INDEX(Inputs!$D$4:$AG$150,0,MATCH(AD$2,Inputs!$D$2:$AG$2,0)),Inputs!$B$4:$B$150,$B13)/1000) -> -4299 | AE13: =IF(AE$3=0,"",SUMIFS(INDEX(Inputs!$D$4:$AG$150,0,MATCH(AE$2,Inputs!$D$2:$AG$2,0)),Inputs!$B$4:$B$150,$B13)/1000) | AF13: =IF(AF$3=0,"",SUMIFS(INDEX(Inputs!$D$4:$AG$150,0,MATCH(AF$2,Inputs!$D$2:$AG$2,0)),Inputs!$B$4:$B$150,$B13)/1000) | AG13: =IF(COUNT(AC13:AF13)=4,SUM(AC13:AF13),"")
B15: 11 | C15: Cash and equivalents (inc. investment securities) | D15: =IF(D$3=0,"",SUMIFS(INDEX(Inputs!$D$4:$AG$150,0,MATCH(D$2,Inputs!$D$2:$AG$2,0)),Inputs!$B$4:$B$150,$B15)/1000) -> 3515 | E15: =IF(E$3=0,"",SUMIFS(INDEX(Inputs!$D$4:$AG$150,0,MATCH(E$2,Inputs!$D$2:$AG$2,0)),Inputs!$B$4:$B$150,$B15)/1000) -> 3465 | F15: =IF(F$3=0,"",SUMIFS(INDEX(Inputs!$D$4:$AG$150,0,MATCH(F$2,Inputs!$D$2:$AG$2,0)),Inputs!$B$4:$B$150,$B15)/1000) -> 4768 | G15: =IF(G$3=0,"",SUMIFS(INDEX(Inputs!$D$4:$AG$150,0,MATCH(G$2,Inputs!$D$2:$AG$2,0)),Inputs!$B$4:$B$150,$B15)/1000) -> 6802 | H15: =IF(G15="","",G15) -> 6802 | I15: =IF(I$3=0,"",SUMIFS(INDEX(Inputs!$D$4:$AG$150,0,MATCH(I$2,Inputs!$D$2:$AG$2,0)),Inputs!$B$4:$B$150,$B15)/1000) -> 11074 | J15: =IF(J$3=0,"",SUMIFS(INDEX(Inputs!$D$4:$AG$150,0,MATCH(J$2,Inputs!$D$2:$AG$2,0)),Inputs!$B$4:$B$150,$B15)/1000) -> 18861 | K15: =IF(K$3=0,"",SUMIFS(INDEX(Inputs!$D$4:$AG$150,0,MATCH(K$2,Inputs!$D$2:$AG$2,0)),Inputs!$B$4:$B$150,$B15)/1000) -> 30407 | L15: =IF(L$3=0,"",SUMIFS(INDEX(Inputs!$D$4:$AG$150,0,MATCH(L$2,Inputs!$D$2:$AG$2,0)),Inputs!$B$4:$B$150,$B15)/1000) -> 29640 | M15: =IF(L15="","",L15) -> 29640 | N15: =IF(N$3=0,"",SUMIFS(INDEX(Inputs!$D$4:$AG$150,0,MATCH(N$2,Inputs!$D$2:$AG$2,0)),Inputs!$B$4:$B$150,$B15)/1000) -> 32651 | O15: =IF(O$3=0,"",SUMIFS(INDEX(Inputs!$D$4:$AG$150,0,MATCH(O$2,Inputs!$D$2:$AG$2,0)),Inputs!$B$4:$B$150,$B15)/1000) -> 29528 | P15: =IF(P$3=0,"",SUMIFS(INDEX(Inputs!$D$4:$AG$150,0,MATCH(P$2,Inputs!$D$2:$AG$2,0)),Inputs!$B$4:$B$150,$B15)/1000) -> 32944 | Q15: =IF(Q$3=0,"",SUMIFS(INDEX(Inputs!$D$4:$AG$150,0,MATCH(Q$2,Inputs!$D$2:$AG$2,0)),Inputs!$B$4:$B$150,$B15)/1000) -> 31539 | R15: =IF(Q15="","",Q15) -> 31539 | S15: =IF(S$3=0,"",SUMIFS(INDEX(Inputs!$D$4:$AG$150,0,MATCH(S$2,Inputs!$D$2:$AG$2,0)),Inputs!$B$4:$B$150,$B15)/1000) -> 33320 | T15: =IF(T$3=0,"",SUMIFS(INDEX(Inputs!$D$4:$AG$150,0,MATCH(T$2,Inputs!$D$2:$AG$2,0)),Inputs!$B$4:$B$150,$B15)/1000) -> 26460 | U15: =IF(U$3=0,"",SUMIFS(INDEX(Inputs!$D$4:$AG$150,0,MATCH(U$2,Inputs!$D$2:$AG$2,0)),Inputs!$B$4:$B$150,$B15)/1000) -> 26926 | V15: =IF(V$3=0,"",SUMIFS(INDEX(Inputs!$D$4:$AG$150,0,MATCH(V$2,Inputs!$D$2:$AG$2,0)),Inputs!$B$4:$B$150,$B15)/1000) -> 23029 | W15: =IF(V15="","",V15) -> 23029 | X15: =IF(X$3=0,"",SUMIFS(INDEX(Inputs!$D$4:$AG$150,0,MATCH(X$2,Inputs!$D$2:$AG$2,0)),Inputs!$B$4:$B$150,$B15)/1000) -> 17036 | Y15: =IF(Y$3=0,"",SUMIFS(INDEX(Inputs!$D$4:$AG$150,0,MATCH(Y$2,Inputs!$D$2:$AG$2,0)),Inputs!$B$4:$B$150,$B15)/1000) -> 14352 | Z15: =IF(Z$3=0,"",SUMIFS(INDEX(Inputs!$D$4:$AG$150,0,MATCH(Z$2,Inputs!$D$2:$AG$2,0)),Inputs!$B$4:$B$150,$B15)/1000) -> 13814 | AA15: =IF(AA$3=0,"",SUMIFS(INDEX(Inputs!$D$4:$AG$150,0,MATCH(AA$2,Inputs!$D$2:$AG$2,0)),Inputs!$B$4:$B$150,$B15)/1000) -> 10681 | AB15: =IF(AA15="","",AA15) -> 10681 | AC15: =IF(AC$3=0,"",SUMIFS(INDEX(Inputs!$D$4:$AG$150,0,MATCH(AC$2,Inputs!$D$2:$AG$2,0)),Inputs!$B$4:$B$150,$B15)/1000) -> 8435 | AD15: =IF(AD$3=0,"",SUMIFS(INDEX(Inputs!$D$4:$AG$150,0,MATCH(AD$2,Inputs!$D$2:$AG$2,0)),Inputs!$B$4:$B$150,$B15)/1000) -> 10588 | AE15: =IF(AE$3=0,"",SUMIFS(INDEX(Inputs!$D$4:$AG$150,0,MATCH(AE$2,Inputs!$D$2:$AG$2,0)),Inputs!$B$4:$B$150,$B15)/1000) | AF15: =IF(AF$3=0,"",SUMIFS(INDEX(Inputs!$D$4:$AG$150,0,MATCH(AF$2,Inputs!$D$2:$AG$2,0)),Inputs!$B$4:$B$150,$B15)/1000) | AG15: =IF(AF15="","",AF15)
B16: 12 | C16: Accounts receivable | D16: =IF(D$3=0,"",SUMIFS(INDEX(Inputs!$D$4:$AG$150,0,MATCH(D$2,Inputs!$D$2:$AG$2,0)),Inputs!$B$4:$B$150,$B16)/1000) -> 24755 | E16: =IF(E$3=0,"",SUMIFS(INDEX(Inputs!$D$4:$AG$150,0,MATCH(E$2,Inputs!$D$2:$AG$2,0)),Inputs!$B$4:$B$150,$B16)/1000) -> 28540 | F16: =IF(F$3=0,"",SUMIFS(INDEX(Inputs!$D$4:$AG$150,0,MATCH(F$2,Inputs!$D$2:$AG$2,0)),Inputs!$B$4:$B$150,$B16)/1000) -> 29516 | G16: =IF(G$3=0,"",SUMIFS(INDEX(Inputs!$D$4:$AG$150,0,MATCH(G$2,Inputs!$D$2:$AG$2,0)),Inputs!$B$4:$B$150,$B16)/1000) -> 32383 | H16: =IF(G16="","",G16) -> 32383 | I16: =IF(I$3=0,"",SUMIFS(INDEX(Inputs!$D$4:$AG$150,0,MATCH(I$2,Inputs!$D$2:$AG$2,0)),Inputs!$B$4:$B$150,$B16)/1000) -> 42142 | J16: =IF(J$3=0,"",SUMIFS(INDEX(Inputs!$D$4:$AG$150,0,MATCH(J$2,Inputs!$D$2:$AG$2,0)),Inputs!$B$4:$B$150,$B16)/1000) -> 48063 | K16: =IF(K$3=0,"",SUMIFS(INDEX(Inputs!$D$4:$AG$150,0,MATCH(K$2,Inputs!$D$2:$AG$2,0)),Inputs!$B$4:$B$150,$B16)/1000) -> 42411 | L16: =IF(L$3=0,"",SUMIFS(INDEX(Inputs!$D$4:$AG$150,0,MATCH(L$2,Inputs!$D$2:$AG$2,0)),Inputs!$B$4:$B$150,$B16)/1000) -> 41749 | M16: =IF(L16="","",L16) -> 41749 | N16: =IF(N$3=0,"",SUMIFS(INDEX(Inputs!$D$4:$AG$150,0,MATCH(N$2,Inputs!$D$2:$AG$2,0)),Inputs!$B$4:$B$150,$B16)/1000) -> 38808 | O16: =IF(O$3=0,"",SUMIFS(INDEX(Inputs!$D$4:$AG$150,0,MATCH(O$2,Inputs!$D$2:$AG$2,0)),Inputs!$B$4:$B$150,$B16)/1000) -> 35915 | P16: =IF(P$3=0,"",SUMIFS(INDEX(Inputs!$D$4:$AG$150,0,MATCH(P$2,Inputs!$D$2:$AG$2,0)),Inputs!$B$4:$B$150,$B16)/1000) -> 41814 | Q16: =IF(Q$3=0,"",SUMIFS(INDEX(Inputs!$D$4:$AG$150,0,MATCH(Q$2,Inputs!$D$2:$AG$2,0)),Inputs!$B$4:$B$150,$B16)/1000) -> 38015 | R16: =IF(Q16="","",Q16) -> 38015 | S16: =IF(S$3=0,"",SUMIFS(INDEX(Inputs!$D$4:$AG$150,0,MATCH(S$2,Inputs!$D$2:$AG$2,0)),Inputs!$B$4:$B$150,$B16)/1000) -> 40366 | T16: =IF(T$3=0,"",SUMIFS(INDEX(Inputs!$D$4:$AG$150,0,MATCH(T$2,Inputs!$D$2:$AG$2,0)),Inputs!$B$4:$B$150,$B16)/1000) -> 43071 | U16: =IF(U$3=0,"",SUMIFS(INDEX(Inputs!$D$4:$AG$150,0,MATCH(U$2,Inputs!$D$2:$AG$2,0)),Inputs!$B$4:$B$150,$B16)/1000) -> 41505 | V16: =IF(V$3=0,"",SUMIFS(INDEX(Inputs!$D$4:$AG$150,0,MATCH(V$2,Inputs!$D$2:$AG$2,0)),Inputs!$B$4:$B$150,$B16)/1000) -> 43681 | W16: =IF(V16="","",V16) -> 43681 | X16: =IF(X$3=0,"",SUMIFS(INDEX(Inputs!$D$4:$AG$150,0,MATCH(X$2,Inputs!$D$2:$AG$2,0)),Inputs!$B$4:$B$150,$B16)/1000) -> 46303 | Y16: =IF(Y$3=0,"",SUMIFS(INDEX(Inputs!$D$4:$AG$150,0,MATCH(Y$2,Inputs!$D$2:$AG$2,0)),Inputs!$B$4:$B$150,$B16)/1000) -> 41792 | Z16: =IF(Z$3=0,"",SUMIFS(INDEX(Inputs!$D$4:$AG$150,0,MATCH(Z$2,Inputs!$D$2:$AG$2,0)),Inputs!$B$4:$B$150,$B16)/1000) -> 45285 | AA16: =IF(AA$3=0,"",SUMIFS(INDEX(Inputs!$D$4:$AG$150,0,MATCH(AA$2,Inputs!$D$2:$AG$2,0)),Inputs!$B$4:$B$150,$B16)/1000) -> 44562 | AB16: =IF(AA16="","",AA16) -> 44562 | AC16: =IF(AC$3=0,"",SUMIFS(INDEX(Inputs!$D$4:$AG$150,0,MATCH(AC$2,Inputs!$D$2:$AG$2,0)),Inputs!$B$4:$B$150,$B16)/1000) -> 61783 | AD16: =IF(AD$3=0,"",SUMIFS(INDEX(Inputs!$D$4:$AG$150,0,MATCH(AD$2,Inputs!$D$2:$AG$2,0)),Inputs!$B$4:$B$150,$B16)/1000) -> 60558 | AE16: =IF(AE$3=0,"",SUMIFS(INDEX(Inputs!$D$4:$AG$150,0,MATCH(AE$2,Inputs!$D$2:$AG$2,0)),Inputs!$B$4:$B$150,$B16)/1000) | AF16: =IF(AF$3=0,"",SUMIFS(INDEX(Inputs!$D$4:$AG$150,0,MATCH(AF$2,Inputs!$D$2:$AG$2,0)),Inputs!$B$4:$B$150,$B16)/1000) | AG16: =IF(AF16="","",AF16)
B17: 13 | C17: Inventories | D17: =IF(D$3=0,"",SUMIFS(INDEX(Inputs!$D$4:$AG$150,0,MATCH(D$2,Inputs!$D$2:$AG$2,0)),Inputs!$B$4:$B$150,$B17)/1000) -> 0 | E17: =IF(E$3=0,"",SUMIFS(INDEX(Inputs!$D$4:$AG$150,0,MATCH(E$2,Inputs!$D$2:$AG$2,0)),Inputs!$B$4:$B$150,$B17)/1000) -> 0 | F17: =IF(F$3=0,"",SUMIFS(INDEX(Inputs!$D$4:$AG$150,0,MATCH(F$2,Inputs!$D$2:$AG$2,0)),Inputs!$B$4:$B$150,$B17)/1000) -> 0 | G17: =IF(G$3=0,"",SUMIFS(INDEX(Inputs!$D$4:$AG$150,0,MATCH(G$2,Inputs!$D$2:$AG$2,0)),Inputs!$B$4:$B$150,$B17)/1000) -> 0 | H17: =IF(G17="","",G17) -> 0 | I17: =IF(I$3=0,"",SUMIFS(INDEX(Inputs!$D$4:$AG$150,0,MATCH(I$2,Inputs!$D$2:$AG$2,0)),Inputs!$B$4:$B$150,$B17)/1000) -> 0 | J17: =IF(J$3=0,"",SUMIFS(INDEX(Inputs!$D$4:$AG$150,0,MATCH(J$2,Inputs!$D$2:$AG$2,0)),Inputs!$B$4:$B$150,$B17)/1000) -> 0 | K17: =IF(K$3=0,"",SUMIFS(INDEX(Inputs!$D$4:$AG$150,0,MATCH(K$2,Inputs!$D$2:$AG$2,0)),Inputs!$B$4:$B$150,$B17)/1000) -> 0 | L17: =IF(L$3=0,"",SUMIFS(INDEX(Inputs!$D$4:$AG$150,0,MATCH(L$2,Inputs!$D$2:$AG$2,0)),Inputs!$B$4:$B$150,$B17)/1000) -> 0 | M17: =IF(L17="","",L17) -> 0 | N17: =IF(N$3=0,"",SUMIFS(INDEX(Inputs!$D$4:$AG$150,0,MATCH(N$2,Inputs!$D$2:$AG$2,0)),Inputs!$B$4:$B$150,$B17)/1000) -> 0 | O17: =IF(O$3=0,"",SUMIFS(INDEX(Inputs!$D$4:$AG$150,0,MATCH(O$2,Inputs!$D$2:$AG$2,0)),Inputs!$B$4:$B$150,$B17)/1000) -> 0 | P17: =IF(P$3=0,"",SUMIFS(INDEX(Inputs!$D$4:$AG$150,0,MATCH(P$2,Inputs!$D$2:$AG$2,0)),Inputs!$B$4:$B$150,$B17)/1000) -> 0 | Q17: =IF(Q$3=0,"",SUMIFS(INDEX(Inputs!$D$4:$AG$150,0,MATCH(Q$2,Inputs!$D$2:$AG$2,0)),Inputs!$B$4:$B$150,$B17)/1000) -> 0 | R17: =IF(Q17="","",Q17) -> 0 | S17: =IF(S$3=0,"",SUMIFS(INDEX(Inputs!$D$4:$AG$150,0,MATCH(S$2,Inputs!$D$2:$AG$2,0)),Inputs!$B$4:$B$150,$B17)/1000) -> 0 | T17: =IF(T$3=0,"",SUMIFS(INDEX(Inputs!$D$4:$AG$150,0,MATCH(T$2,Inputs!$D$2:$AG$2,0)),Inputs!$B$4:$B$150,$B17)/1000) -> 0 | U17: =IF(U$3=0,"",SUMIFS(INDEX(Inputs!$D$4:$AG$150,0,MATCH(U$2,Inputs!$D$2:$AG$2,0)),Inputs!$B$4:$B$150,$B17)/1000) -> 0 | V17: =IF(V$3=0,"",SUMIFS(INDEX(Inputs!$D$4:$AG$150,0,MATCH(V$2,Inputs!$D$2:$AG$2,0)),Inputs!$B$4:$B$150,$B17)/1000) -> 0 | W17: =IF(V17="","",V17) -> 0 | X17: =IF(X$3=0,"",SUMIFS(INDEX(Inputs!$D$4:$AG$150,0,MATCH(X$2,Inputs!$D$2:$AG$2,0)),Inputs!$B$4:$B$150,$B17)/1000) -> 0 | Y17: =IF(Y$3=0,"",SUMIFS(INDEX(Inputs!$D$4:$AG$150,0,MATCH(Y$2,Inputs!$D$2:$AG$2,0)),Inputs!$B$4:$B$150,$B17)/1000) -> 0 | Z17: =IF(Z$3=0,"",SUMIFS(INDEX(Inputs!$D$4:$AG$150,0,MATCH(Z$2,Inputs!$D$2:$AG$2,0)),Inputs!$B$4:$B$150,$B17)/1000) -> 0 | AA17: =IF(AA$3=0,"",SUMIFS(INDEX(Inputs!$D$4:$AG$150,0,MATCH(AA$2,Inputs!$D$2:$AG$2,0)),Inputs!$B$4:$B$150,$B17)/1000) -> 0 | AB17: =IF(AA17="","",AA17) -> 0 | AC17: =IF(AC$3=0,"",SUMIFS(INDEX(Inputs!$D$4:$AG$150,0,MATCH(AC$2,Inputs!$D$2:$AG$2,0)),Inputs!$B$4:$B$150,$B17)/1000) -> 0 | AD17: =IF(AD$3=0,"",SUMIFS(INDEX(Inputs!$D$4:$AG$150,0,MATCH(AD$2,Inputs!$D$2:$AG$2,0)),Inputs!$B$4:$B$150,$B17)/1000) -> 0 | AE17: =IF(AE$3=0,"",SUMIFS(INDEX(Inputs!$D$4:$AG$150,0,MATCH(AE$2,Inputs!$D$2:$AG$2,0)),Inputs!$B$4:$B$150,$B17)/1000) | AF17: =IF(AF$3=0,"",SUMIFS(INDEX(Inputs!$D$4:$AG$150,0,MATCH(AF$2,Inputs!$D$2:$AG$2,0)),Inputs!$B$4:$B$150,$B17)/1000) | AG17: =IF(AF17="","",AF17)
B18: 14 | C18: Deferred income taxes | D18: =IF(D$3=0,"",SUMIFS(INDEX(Inputs!$D$4:$AG$150,0,MATCH(D$2,Inputs!$D$2:$AG$2,0)),Inputs!$B$4:$B$150,$B18)/1000) -> 0 | E18: =IF(E$3=0,"",SUMIFS(INDEX(Inputs!$D$4:$AG$150,0,MATCH(E$2,Inputs!$D$2:$AG$2,0)),Inputs!$B$4:$B$150,$B18)/1000) -> 0 | F18: =IF(F$3=0,"",SUMIFS(INDEX(Inputs!$D$4:$AG$150,0,MATCH(F$2,Inputs!$D$2:$AG$2,0)),Inputs!$B$4:$B$150,$B18)/1000) -> 0 | G18: =IF(G$3=0,"",SUMIFS(INDEX(Inputs!$D$4:$AG$150,0,MATCH(G$2,Inputs!$D$2:$AG$2,0)),Inputs!$B$4:$B$150,$B18)/1000) -> 0 | H18: =IF(G18="","",G18) -> 0 | I18: =IF(I$3=0,"",SUMIFS(INDEX(Inputs!$D$4:$AG$150,0,MATCH(I$2,Inputs!$D$2:$AG$2,0)),Inputs!$B$4:$B$150,$B18)/1000) -> 0 | J18: =IF(J$3=0,"",SUMIFS(INDEX(Inputs!$D$4:$AG$150,0,MATCH(J$2,Inputs!$D$2:$AG$2,0)),Inputs!$B$4:$B$150,$B18)/1000) -> 0 | K18: =IF(K$3=0,"",SUMIFS(INDEX(Inputs!$D$4:$AG$150,0,MATCH(K$2,Inputs!$D$2:$AG$2,0)),Inputs!$B$4:$B$150,$B18)/1000) -> 0 | L18: =IF(L$3=0,"",SUMIFS(INDEX(Inputs!$D$4:$AG$150,0,MATCH(L$2,Inputs!$D$2:$AG$2,0)),Inputs!$B$4:$B$150,$B18)/1000) -> 0 | M18: =IF(L18="","",L18) -> 0 | N18: =IF(N$3=0,"",SUMIFS(INDEX(Inputs!$D$4:$AG$150,0,MATCH(N$2,Inputs!$D$2:$AG$2,0)),Inputs!$B$4:$B$150,$B18)/1000) -> 0 | O18: =IF(O$3=0,"",SUMIFS(INDEX(Inputs!$D$4:$AG$150,0,MATCH(O$2,Inputs!$D$2:$AG$2,0)),Inputs!$B$4:$B$150,$B18)/1000) -> 0 | P18: =IF(P$3=0,"",SUMIFS(INDEX(Inputs!$D$4:$AG$150,0,MATCH(P$2,Inputs!$D$2:$AG$2,0)),Inputs!$B$4:$B$150,$B18)/1000) -> 0 | Q18: =IF(Q$3=0,"",SUMIFS(INDEX(Inputs!$D$4:$AG$150,0,MATCH(Q$2,Inputs!$D$2:$AG$2,0)),Inputs!$B$4:$B$150,$B18)/1000) -> 0 | R18: =IF(Q18="","",Q18) -> 0 | S18: =IF(S$3=0,"",SUMIFS(INDEX(Inputs!$D$4:$AG$150,0,MATCH(S$2,Inputs!$D$2:$AG$2,0)),Inputs!$B$4:$B$150,$B18)/1000) -> 0 | T18: =IF(T$3=0,"",SUMIFS(INDEX(Inputs!$D$4:$AG$150,0,MATCH(T$2,Inputs!$D$2:$AG$2,0)),Inputs!$B$4:$B$150,$B18)/1000) -> 0 | U18: =IF(U$3=0,"",SUMIFS(INDEX(Inputs!$D$4:$AG$150,0,MATCH(U$2,Inputs!$D$2:$AG$2,0)),Inputs!$B$4:$B$150,$B18)/1000) -> 0 | V18: =IF(V$3=0,"",SUMIFS(INDEX(Inputs!$D$4:$AG$150,0,MATCH(V$2,Inputs!$D$2:$AG$2,0)),Inputs!$B$4:$B$150,$B18)/1000) -> 0 | W18: =IF(V18="","",V18) -> 0 | X18: =IF(X$3=0,"",SUMIFS(INDEX(Inputs!$D$4:$AG$150,0,MATCH(X$2,Inputs!$D$2:$AG$2,0)),Inputs!$B$4:$B$150,$B18)/1000) -> 0 | Y18: =IF(Y$3=0,"",SUMIFS(INDEX(Inputs!$D$4:$AG$150,0,MATCH(Y$2,Inputs!$D$2:$AG$2,0)),Inputs!$B$4:$B$150,$B18)/1000) -> 0 | Z18: =IF(Z$3=0,"",SUMIFS(INDEX(Inputs!$D$4:$AG$150,0,MATCH(Z$2,Inputs!$D$2:$AG$2,0)),Inputs!$B$4:$B$150,$B18)/1000) -> 0 | AA18: =IF(AA$3=0,"",SUMIFS(INDEX(Inputs!$D$4:$AG$150,0,MATCH(AA$2,Inputs!$D$2:$AG$2,0)),Inputs!$B$4:$B$150,$B18)/1000) -> 0 | AB18: =IF(AA18="","",AA18) -> 0 | AC18: =IF(AC$3=0,"",SUMIFS(INDEX(Inputs!$D$4:$AG$150,0,MATCH(AC$2,Inputs!$D$2:$AG$2,0)),Inputs!$B$4:$B$150,$B18)/1000) -> 0 | AD18: =IF(AD$3=0,"",SUMIFS(INDEX(Inputs!$D$4:$AG$150,0,MATCH(AD$2,Inputs!$D$2:$AG$2,0)),Inputs!$B$4:$B$150,$B18)/1000) -> 0 | AE18: =IF(AE$3=0,"",SUMIFS(INDEX(Inputs!$D$4:$AG$150,0,MATCH(AE$2,Inputs!$D$2:$AG$2,0)),Inputs!$B$4:$B$150,$B18)/1000) | AF18: =IF(AF$3=0,"",SUMIFS(INDEX(Inputs!$D$4:$AG$150,0,MATCH(AF$2,Inputs!$D$2:$AG$2,0)),Inputs!$B$4:$B$150,$B18)/1000) | AG18: =IF(AF18="","",AF18)
B19: 15 | C19: Prepaid expenses | D19: =IF(D$3=0,"",SUMIFS(INDEX(Inputs!$D$4:$AG$150,0,MATCH(D$2,Inputs!$D$2:$AG$2,0)),Inputs!$B$4:$B$150,$B19)/1000) -> 0 | E19: =IF(E$3=0,"",SUMIFS(INDEX(Inputs!$D$4:$AG$150,0,MATCH(E$2,Inputs!$D$2:$AG$2,0)),Inputs!$B$4:$B$150,$B19)/1000) -> 0 | F19: =IF(F$3=0,"",SUMIFS(INDEX(Inputs!$D$4:$AG$150,0,MATCH(F$2,Inputs!$D$2:$AG$2,0)),Inputs!$B$4:$B$150,$B19)/1000) -> 0 | G19: =IF(G$3=0,"",SUMIFS(INDEX(Inputs!$D$4:$AG$150,0,MATCH(G$2,Inputs!$D$2:$AG$2,0)),Inputs!$B$4:$B$150,$B19)/1000) -> 0 | H19: =IF(G19="","",G19) -> 0 | I19: =IF(I$3=0,"",SUMIFS(INDEX(Inputs!$D$4:$AG$150,0,MATCH(I$2,Inputs!$D$2:$AG$2,0)),Inputs!$B$4:$B$150,$B19)/1000) -> 0 | J19: =IF(J$3=0,"",SUMIFS(INDEX(Inputs!$D$4:$AG$150,0,MATCH(J$2,Inputs!$D$2:$AG$2,0)),Inputs!$B$4:$B$150,$B19)/1000) -> 0 | K19: =IF(K$3=0,"",SUMIFS(INDEX(Inputs!$D$4:$AG$150,0,MATCH(K$2,Inputs!$D$2:$AG$2,0)),Inputs!$B$4:$B$150,$B19)/1000) -> 0 | L19: =IF(L$3=0,"",SUMIFS(INDEX(Inputs!$D$4:$AG$150,0,MATCH(L$2,Inputs!$D$2:$AG$2,0)),Inputs!$B$4:$B$150,$B19)/1000) -> 0 | M19: =IF(L19="","",L19) -> 0 | N19: =IF(N$3=0,"",SUMIFS(INDEX(Inputs!$D$4:$AG$150,0,MATCH(N$2,Inputs!$D$2:$AG$2,0)),Inputs!$B$4:$B$150,$B19)/1000) -> 0 | O19: =IF(O$3=0,"",SUMIFS(INDEX(Inputs!$D$4:$AG$150,0,MATCH(O$2,Inputs!$D$2:$AG$2,0)),Inputs!$B$4:$B$150,$B19)/1000) -> 0 | P19: =IF(P$3=0,"",SUMIFS(INDEX(Inputs!$D$4:$AG$150,0,MATCH(P$2,Inputs!$D$2:$AG$2,0)),Inputs!$B$4:$B$150,$B19)/1000) -> 0 | Q19: =IF(Q$3=0,"",SUMIFS(INDEX(Inputs!$D$4:$AG$150,0,MATCH(Q$2,Inputs!$D$2:$AG$2,0)),Inputs!$B$4:$B$150,$B19)/1000) -> 0 | R19: =IF(Q19="","",Q19) -> 0 | S19: =IF(S$3=0,"",SUMIFS(INDEX(Inputs!$D$4:$AG$150,0,MATCH(S$2,Inputs!$D$2:$AG$2,0)),Inputs!$B$4:$B$150,$B19)/1000) -> 0 | T19: =IF(T$3=0,"",SUMIFS(INDEX(Inputs!$D$4:$AG$150,0,MATCH(T$2,Inputs!$D$2:$AG$2,0)),Inputs!$B$4:$B$150,$B19)/1000) -> 0 | U19: =IF(U$3=0,"",SUMIFS(INDEX(Inputs!$D$4:$AG$150,0,MATCH(U$2,Inputs!$D$2:$AG$2,0)),Inputs!$B$4:$B$150,$B19)/1000) -> 0 | V19: =IF(V$3=0,"",SUMIFS(INDEX(Inputs!$D$4:$AG$150,0,MATCH(V$2,Inputs!$D$2:$AG$2,0)),Inputs!$B$4:$B$150,$B19)/1000) -> 0 | W19: =IF(V19="","",V19) -> 0 | X19: =IF(X$3=0,"",SUMIFS(INDEX(Inputs!$D$4:$AG$150,0,MATCH(X$2,Inputs!$D$2:$AG$2,0)),Inputs!$B$4:$B$150,$B19)/1000) -> 0 | Y19: =IF(Y$3=0,"",SUMIFS(INDEX(Inputs!$D$4:$AG$150,0,MATCH(Y$2,Inputs!$D$2:$AG$2,0)),Inputs!$B$4:$B$150,$B19)/1000) -> 0 | Z19: =IF(Z$3=0,"",SUMIFS(INDEX(Inputs!$D$4:$AG$150,0,MATCH(Z$2,Inputs!$D$2:$AG$2,0)),Inputs!$B$4:$B$150,$B19)/1000) -> 0 | AA19: =IF(AA$3=0,"",SUMIFS(INDEX(Inputs!$D$4:$AG$150,0,MATCH(AA$2,Inputs!$D$2:$AG$2,0)),Inputs!$B$4:$B$150,$B19)/1000) -> 0 | AB19: =IF(AA19="","",AA19) -> 0 | AC19: =IF(AC$3=0,"",SUMIFS(INDEX(Inputs!$D$4:$AG$150,0,MATCH(AC$2,Inputs!$D$2:$AG$2,0)),Inputs!$B$4:$B$150,$B19)/1000) -> 0 | AD19: =IF(AD$3=0,"",SUMIFS(INDEX(Inputs!$D$4:$AG$150,0,MATCH(AD$2,Inputs!$D$2:$AG$2,0)),Inputs!$B$4:$B$150,$B19)/1000) -> 0 | AE19: =IF(AE$3=0,"",SUMIFS(INDEX(Inputs!$D$4:$AG$150,0,MATCH(AE$2,Inputs!$D$2:$AG$2,0)),Inputs!$B$4:$B$150,$B19)/1000) | AF19: =IF(AF$3=0,"",SUMIFS(INDEX(Inputs!$D$4:$AG$150,0,MATCH(AF$2,Inputs!$D$2:$AG$2,0)),Inputs!$B$4:$B$150,$B19)/1000) | AG19: =IF(AF19="","",AF19)
B20: 16 | C20: Other current assets | D20: =IF(D$3=0,"",SUMIFS(INDEX(Inputs!$D$4:$AG$150,0,MATCH(D$2,Inputs!$D$2:$AG$2,0)),Inputs!$B$4:$B$150,$B20)/1000) -> 19925 | E20: =IF(E$3=0,"",SUMIFS(INDEX(Inputs!$D$4:$AG$150,0,MATCH(E$2,Inputs!$D$2:$AG$2,0)),Inputs!$B$4:$B$150,$B20)/1000) -> 20837 | F20: =IF(F$3=0,"",SUMIFS(INDEX(Inputs!$D$4:$AG$150,0,MATCH(F$2,Inputs!$D$2:$AG$2,0)),Inputs!$B$4:$B$150,$B20)/1000) -> 21271 | G20: =IF(G$3=0,"",SUMIFS(INDEX(Inputs!$D$4:$AG$150,0,MATCH(G$2,Inputs!$D$2:$AG$2,0)),Inputs!$B$4:$B$150,$B20)/1000) -> 19969 | H20: =IF(G20="","",G20) -> 19969 | I20: =IF(I$3=0,"",SUMIFS(INDEX(Inputs!$D$4:$AG$150,0,MATCH(I$2,Inputs!$D$2:$AG$2,0)),Inputs!$B$4:$B$150,$B20)/1000) -> 24039 | J20: =IF(J$3=0,"",SUMIFS(INDEX(Inputs!$D$4:$AG$150,0,MATCH(J$2,Inputs!$D$2:$AG$2,0)),Inputs!$B$4:$B$150,$B20)/1000) -> 26239 | K20: =IF(K$3=0,"",SUMIFS(INDEX(Inputs!$D$4:$AG$150,0,MATCH(K$2,Inputs!$D$2:$AG$2,0)),Inputs!$B$4:$B$150,$B20)/1000) -> 26471 | L20: =IF(L$3=0,"",SUMIFS(INDEX(Inputs!$D$4:$AG$150,0,MATCH(L$2,Inputs!$D$2:$AG$2,0)),Inputs!$B$4:$B$150,$B20)/1000) -> 26242 | M20: =IF(L20="","",L20) -> 26242 | N20: =IF(N$3=0,"",SUMIFS(INDEX(Inputs!$D$4:$AG$150,0,MATCH(N$2,Inputs!$D$2:$AG$2,0)),Inputs!$B$4:$B$150,$B20)/1000) -> 25765 | O20: =IF(O$3=0,"",SUMIFS(INDEX(Inputs!$D$4:$AG$150,0,MATCH(O$2,Inputs!$D$2:$AG$2,0)),Inputs!$B$4:$B$150,$B20)/1000) -> 26317 | P20: =IF(P$3=0,"",SUMIFS(INDEX(Inputs!$D$4:$AG$150,0,MATCH(P$2,Inputs!$D$2:$AG$2,0)),Inputs!$B$4:$B$150,$B20)/1000) -> 26384 | Q20: =IF(Q$3=0,"",SUMIFS(INDEX(Inputs!$D$4:$AG$150,0,MATCH(Q$2,Inputs!$D$2:$AG$2,0)),Inputs!$B$4:$B$150,$B20)/1000) -> 27055 | R20: =IF(Q20="","",Q20) -> 27055 | S20: =IF(S$3=0,"",SUMIFS(INDEX(Inputs!$D$4:$AG$150,0,MATCH(S$2,Inputs!$D$2:$AG$2,0)),Inputs!$B$4:$B$150,$B20)/1000) -> 25691 | T20: =IF(T$3=0,"",SUMIFS(INDEX(Inputs!$D$4:$AG$150,0,MATCH(T$2,Inputs!$D$2:$AG$2,0)),Inputs!$B$4:$B$150,$B20)/1000) -> 26707 | U20: =IF(U$3=0,"",SUMIFS(INDEX(Inputs!$D$4:$AG$150,0,MATCH(U$2,Inputs!$D$2:$AG$2,0)),Inputs!$B$4:$B$150,$B20)/1000) -> 25918 | V20: =IF(V$3=0,"",SUMIFS(INDEX(Inputs!$D$4:$AG$150,0,MATCH(V$2,Inputs!$D$2:$AG$2,0)),Inputs!$B$4:$B$150,$B20)/1000) -> 25280 | W20: =IF(V20="","",V20) -> 25280 | X20: =IF(X$3=0,"",SUMIFS(INDEX(Inputs!$D$4:$AG$150,0,MATCH(X$2,Inputs!$D$2:$AG$2,0)),Inputs!$B$4:$B$150,$B20)/1000) -> 27894 | Y20: =IF(Y$3=0,"",SUMIFS(INDEX(Inputs!$D$4:$AG$150,0,MATCH(Y$2,Inputs!$D$2:$AG$2,0)),Inputs!$B$4:$B$150,$B20)/1000) -> 28964 | Z20: =IF(Z$3=0,"",SUMIFS(INDEX(Inputs!$D$4:$AG$150,0,MATCH(Z$2,Inputs!$D$2:$AG$2,0)),Inputs!$B$4:$B$150,$B20)/1000) -> 29406 | AA20: =IF(AA$3=0,"",SUMIFS(INDEX(Inputs!$D$4:$AG$150,0,MATCH(AA$2,Inputs!$D$2:$AG$2,0)),Inputs!$B$4:$B$150,$B20)/1000) -> 28139 | AB20: =IF(AA20="","",AA20) -> 28139 | AC20: =IF(AC$3=0,"",SUMIFS(INDEX(Inputs!$D$4:$AG$150,0,MATCH(AC$2,Inputs!$D$2:$AG$2,0)),Inputs!$B$4:$B$150,$B20)/1000) -> 27569 | AD20: =IF(AD$3=0,"",SUMIFS(INDEX(Inputs!$D$4:$AG$150,0,MATCH(AD$2,Inputs!$D$2:$AG$2,0)),Inputs!$B$4:$B$150,$B20)/1000) -> 29647 | AE20: =IF(AE$3=0,"",SUMIFS(INDEX(Inputs!$D$4:$AG$150,0,MATCH(AE$2,Inputs!$D$2:$AG$2,0)),Inputs!$B$4:$B$150,$B20)/1000) | AF20: =IF(AF$3=0,"",SUMIFS(INDEX(Inputs!$D$4:$AG$150,0,MATCH(AF$2,Inputs!$D$2:$AG$2,0)),Inputs!$B$4:$B$150,$B20)/1000) | AG20: =IF(AF20="","",AF20)
B21: 17 | C21: Equity in affiliates | D21: =IF(D$3=0,"",SUMIFS(INDEX(Inputs!$D$4:$AG$150,0,MATCH(D$2,Inputs!$D$2:$AG$2,0)),Inputs!$B$4:$B$150,$B21)/1000) -> 0 | E21: =IF(E$3=0,"",SUMIFS(INDEX(Inputs!$D$4:$AG$150,0,MATCH(E$2,Inputs!$D$2:$AG$2,0)),Inputs!$B$4:$B$150,$B21)/1000) -> 0 | F21: =IF(F$3=0,"",SUMIFS(INDEX(Inputs!$D$4:$AG$150,0,MATCH(F$2,Inputs!$D$2:$AG$2,0)),Inputs!$B$4:$B$150,$B21)/1000) -> 0 | G21: =IF(G$3=0,"",SUMIFS(INDEX(Inputs!$D$4:$AG$150,0,MATCH(G$2,Inputs!$D$2:$AG$2,0)),Inputs!$B$4:$B$150,$B21)/1000) -> 0 | H21: =IF(G21="","",G21) -> 0 | I21: =IF(I$3=0,"",SUMIFS(INDEX(Inputs!$D$4:$AG$150,0,MATCH(I$2,Inputs!$D$2:$AG$2,0)),Inputs!$B$4:$B$150,$B21)/1000) -> 0 | J21: =IF(J$3=0,"",SUMIFS(INDEX(Inputs!$D$4:$AG$150,0,MATCH(J$2,Inputs!$D$2:$AG$2,0)),Inputs!$B$4:$B$150,$B21)/1000) -> 0 | K21: =IF(K$3=0,"",SUMIFS(INDEX(Inputs!$D$4:$AG$150,0,MATCH(K$2,Inputs!$D$2:$AG$2,0)),Inputs!$B$4:$B$150,$B21)/1000) -> 0 | L21: =IF(L$3=0,"",SUMIFS(INDEX(Inputs!$D$4:$AG$150,0,MATCH(L$2,Inputs!$D$2:$AG$2,0)),Inputs!$B$4:$B$150,$B21)/1000) -> 0 | M21: =IF(L21="","",L21) -> 0 | N21: =IF(N$3=0,"",SUMIFS(INDEX(Inputs!$D$4:$AG$150,0,MATCH(N$2,Inputs!$D$2:$AG$2,0)),Inputs!$B$4:$B$150,$B21)/1000) -> 0 | O21: =IF(O$3=0,"",SUMIFS(INDEX(Inputs!$D$4:$AG$150,0,MATCH(O$2,Inputs!$D$2:$AG$2,0)),Inputs!$B$4:$B$150,$B21)/1000) -> 0 | P21: =IF(P$3=0,"",SUMIFS(INDEX(Inputs!$D$4:$AG$150,0,MATCH(P$2,Inputs!$D$2:$AG$2,0)),Inputs!$B$4:$B$150,$B21)/1000) -> 0 | Q21: =IF(Q$3=0,"",SUMIFS(INDEX(Inputs!$D$4:$AG$150,0,MATCH(Q$2,Inputs!$D$2:$AG$2,0)),Inputs!$B$4:$B$150,$B21)/1000) -> 0 | R21: =IF(Q21="","",Q21) -> 0 | S21: =IF(S$3=0,"",SUMIFS(INDEX(Inputs!$D$4:$AG$150,0,MATCH(S$2,Inputs!$D$2:$AG$2,0)),Inputs!$B$4:$B$150,$B21)/1000) -> 0 | T21: =IF(T$3=0,"",SUMIFS(INDEX(Inputs!$D$4:$AG$150,0,MATCH(T$2,Inputs!$D$2:$AG$2,0)),Inputs!$B$4:$B$150,$B21)/1000) -> 0 | U21: =IF(U$3=0,"",SUMIFS(INDEX(Inputs!$D$4:$AG$150,0,MATCH(U$2,Inputs!$D$2:$AG$2,0)),Inputs!$B$4:$B$150,$B21)/1000) -> 0 | V21: =IF(V$3=0,"",SUMIFS(INDEX(Inputs!$D$4:$AG$150,0,MATCH(V$2,Inputs!$D$2:$AG$2,0)),Inputs!$B$4:$B$150,$B21)/1000) -> 0 | W21: =IF(V21="","",V21) -> 0 | X21: =IF(X$3=0,"",SUMIFS(INDEX(Inputs!$D$4:$AG$150,0,MATCH(X$2,Inputs!$D$2:$AG$2,0)),Inputs!$B$4:$B$150,$B21)/1000) -> 0 | Y21: =IF(Y$3=0,"",SUMIFS(INDEX(Inputs!$D$4:$AG$150,0,MATCH(Y$2,Inputs!$D$2:$AG$2,0)),Inputs!$B$4:$B$150,$B21)/1000) -> 0 | Z21: =IF(Z$3=0,"",SUMIFS(INDEX(Inputs!$D$4:$AG$150,0,MATCH(Z$2,Inputs!$D$2:$AG$2,0)),Inputs!$B$4:$B$150,$B21)/1000) -> 0 | AA21: =IF(AA$3=0,"",SUMIFS(INDEX(Inputs!$D$4:$AG$150,0,MATCH(AA$2,Inputs!$D$2:$AG$2,0)),Inputs!$B$4:$B$150,$B21)/1000) -> 0 | AB21: =IF(AA21="","",AA21) -> 0 | AC21: =IF(AC$3=0,"",SUMIFS(INDEX(Inputs!$D$4:$AG$150,0,MATCH(AC$2,Inputs!$D$2:$AG$2,0)),Inputs!$B$4:$B$150,$B21)/1000) -> 0 | AD21: =IF(AD$3=0,"",SUMIFS(INDEX(Inputs!$D$4:$AG$150,0,MATCH(AD$2,Inputs!$D$2:$AG$2,0)),Inputs!$B$4:$B$150,$B21)/1000) -> 0 | AE21: =IF(AE$3=0,"",SUMIFS(INDEX(Inputs!$D$4:$AG$150,0,MATCH(AE$2,Inputs!$D$2:$AG$2,0)),Inputs!$B$4:$B$150,$B21)/1000) | AF21: =IF(AF$3=0,"",SUMIFS(INDEX(Inputs!$D$4:$AG$150,0,MATCH(AF$2,Inputs!$D$2:$AG$2,0)),Inputs!$B$4:$B$150,$B21)/1000) | AG21: =IF(AF21="","",AF21)
B22: 18 | C22: PP&E | D22: =IF(D$3=0,"",SUMIFS(INDEX(Inputs!$D$4:$AG$150,0,MATCH(D$2,Inputs!$D$2:$AG$2,0)),Inputs!$B$4:$B$150,$B22)/1000) -> 224641 | E22: =IF(E$3=0,"",SUMIFS(INDEX(Inputs!$D$4:$AG$150,0,MATCH(E$2,Inputs!$D$2:$AG$2,0)),Inputs!$B$4:$B$150,$B22)/1000) -> 223012 | F22: =IF(F$3=0,"",SUMIFS(INDEX(Inputs!$D$4:$AG$150,0,MATCH(F$2,Inputs!$D$2:$AG$2,0)),Inputs!$B$4:$B$150,$B22)/1000) -> 218795 | G22: =IF(G$3=0,"",SUMIFS(INDEX(Inputs!$D$4:$AG$150,0,MATCH(G$2,Inputs!$D$2:$AG$2,0)),Inputs!$B$4:$B$150,$B22)/1000) -> 216552 | H22: =IF(G22="","",G22) -> 216552 | I22: =IF(I$3=0,"",SUMIFS(INDEX(Inputs!$D$4:$AG$150,0,MATCH(I$2,Inputs!$D$2:$AG$2,0)),Inputs!$B$4:$B$150,$B22)/1000) -> 212773 | J22: =IF(J$3=0,"",SUMIFS(INDEX(Inputs!$D$4:$AG$150,0,MATCH(J$2,Inputs!$D$2:$AG$2,0)),Inputs!$B$4:$B$150,$B22)/1000) -> 209159 | K22: =IF(K$3=0,"",SUMIFS(INDEX(Inputs!$D$4:$AG$150,0,MATCH(K$2,Inputs!$D$2:$AG$2,0)),Inputs!$B$4:$B$150,$B22)/1000) -> 203102 | L22: =IF(L$3=0,"",SUMIFS(INDEX(Inputs!$D$4:$AG$150,0,MATCH(L$2,Inputs!$D$2:$AG$2,0)),Inputs!$B$4:$B$150,$B22)/1000) -> 204692 | M22: =IF(L22="","",L22) -> 204692 | N22: =IF(N$3=0,"",SUMIFS(INDEX(Inputs!$D$4:$AG$150,0,MATCH(N$2,Inputs!$D$2:$AG$2,0)),Inputs!$B$4:$B$150,$B22)/1000) -> 206023 | O22: =IF(O$3=0,"",SUMIFS(INDEX(Inputs!$D$4:$AG$150,0,MATCH(O$2,Inputs!$D$2:$AG$2,0)),Inputs!$B$4:$B$150,$B22)/1000) -> 206736 | P22: =IF(P$3=0,"",SUMIFS(INDEX(Inputs!$D$4:$AG$150,0,MATCH(P$2,Inputs!$D$2:$AG$2,0)),Inputs!$B$4:$B$150,$B22)/1000) -> 205862 | Q22: =IF(Q$3=0,"",SUMIFS(INDEX(Inputs!$D$4:$AG$150,0,MATCH(Q$2,Inputs!$D$2:$AG$2,0)),Inputs!$B$4:$B$150,$B22)/1000) -> 214940 | R22: =IF(Q22="","",Q22) -> 214940 | S22: =IF(S$3=0,"",SUMIFS(INDEX(Inputs!$D$4:$AG$150,0,MATCH(S$2,Inputs!$D$2:$AG$2,0)),Inputs!$B$4:$B$150,$B22)/1000) -> 213723 | T22: =IF(T$3=0,"",SUMIFS(INDEX(Inputs!$D$4:$AG$150,0,MATCH(T$2,Inputs!$D$2:$AG$2,0)),Inputs!$B$4:$B$150,$B22)/1000) -> 298283 | U22: =IF(U$3=0,"",SUMIFS(INDEX(Inputs!$D$4:$AG$150,0,MATCH(U$2,Inputs!$D$2:$AG$2,0)),Inputs!$B$4:$B$150,$B22)/1000) -> 299543 | V22: =IF(V$3=0,"",SUMIFS(INDEX(Inputs!$D$4:$AG$150,0,MATCH(V$2,Inputs!$D$2:$AG$2,0)),Inputs!$B$4:$B$150,$B22)/1000) -> 294318 | W22: =IF(V22="","",V22) -> 294318 | X22: =IF(X$3=0,"",SUMIFS(INDEX(Inputs!$D$4:$AG$150,0,MATCH(X$2,Inputs!$D$2:$AG$2,0)),Inputs!$B$4:$B$150,$B22)/1000) -> 292646 | Y22: =IF(Y$3=0,"",SUMIFS(INDEX(Inputs!$D$4:$AG$150,0,MATCH(Y$2,Inputs!$D$2:$AG$2,0)),Inputs!$B$4:$B$150,$B22)/1000) -> 295356 | Z22: =IF(Z$3=0,"",SUMIFS(INDEX(Inputs!$D$4:$AG$150,0,MATCH(Z$2,Inputs!$D$2:$AG$2,0)),Inputs!$B$4:$B$150,$B22)/1000) -> 298388 | AA22: =IF(AA$3=0,"",SUMIFS(INDEX(Inputs!$D$4:$AG$150,0,MATCH(AA$2,Inputs!$D$2:$AG$2,0)),Inputs!$B$4:$B$150,$B22)/1000) -> 299373 | AB22: =IF(AA22="","",AA22) -> 299373 | AC22: =IF(AC$3=0,"",SUMIFS(INDEX(Inputs!$D$4:$AG$150,0,MATCH(AC$2,Inputs!$D$2:$AG$2,0)),Inputs!$B$4:$B$150,$B22)/1000) -> 298781 | AD22: =IF(AD$3=0,"",SUMIFS(INDEX(Inputs!$D$4:$AG$150,0,MATCH(AD$2,Inputs!$D$2:$AG$2,0)),Inputs!$B$4:$B$150,$B22)/1000) -> 296298 | AE22: =IF(AE$3=0,"",SUMIFS(INDEX(Inputs!$D$4:$AG$150,0,MATCH(AE$2,Inputs!$D$2:$AG$2,0)),Inputs!$B$4:$B$150,$B22)/1000) | AF22: =IF(AF$3=0,"",SUMIFS(INDEX(Inputs!$D$4:$AG$150,0,MATCH(AF$2,Inputs!$D$2:$AG$2,0)),Inputs!$B$4:$B$150,$B22)/1000) | AG22: =IF(AF22="","",AF22)
B23: 19 | C23: Right-of-use-assets | D23: =IF(D$3=0,"",SUMIFS(INDEX(Inputs!$D$4:$AG$150,0,MATCH(D$2,Inputs!$D$2:$AG$2,0)),Inputs!$B$4:$B$150,$B23)/1000) -> 0 | E23: =IF(E$3=0,"",SUMIFS(INDEX(Inputs!$D$4:$AG$150,0,MATCH(E$2,Inputs!$D$2:$AG$2,0)),Inputs!$B$4:$B$150,$B23)/1000) -> 0 | F23: =IF(F$3=0,"",SUMIFS(INDEX(Inputs!$D$4:$AG$150,0,MATCH(F$2,Inputs!$D$2:$AG$2,0)),Inputs!$B$4:$B$150,$B23)/1000) -> 0 | G23: =IF(G$3=0,"",SUMIFS(INDEX(Inputs!$D$4:$AG$150,0,MATCH(G$2,Inputs!$D$2:$AG$2,0)),Inputs!$B$4:$B$150,$B23)/1000) -> 0 | H23: =IF(G23="","",G23) -> 0 | I23: =IF(I$3=0,"",SUMIFS(INDEX(Inputs!$D$4:$AG$150,0,MATCH(I$2,Inputs!$D$2:$AG$2,0)),Inputs!$B$4:$B$150,$B23)/1000) -> 0 | J23: =IF(J$3=0,"",SUMIFS(INDEX(Inputs!$D$4:$AG$150,0,MATCH(J$2,Inputs!$D$2:$AG$2,0)),Inputs!$B$4:$B$150,$B23)/1000) -> 0 | K23: =IF(K$3=0,"",SUMIFS(INDEX(Inputs!$D$4:$AG$150,0,MATCH(K$2,Inputs!$D$2:$AG$2,0)),Inputs!$B$4:$B$150,$B23)/1000) -> 0 | L23: =IF(L$3=0,"",SUMIFS(INDEX(Inputs!$D$4:$AG$150,0,MATCH(L$2,Inputs!$D$2:$AG$2,0)),Inputs!$B$4:$B$150,$B23)/1000) -> 0 | M23: =IF(L23="","",L23) -> 0 | N23: =IF(N$3=0,"",SUMIFS(INDEX(Inputs!$D$4:$AG$150,0,MATCH(N$2,Inputs!$D$2:$AG$2,0)),Inputs!$B$4:$B$150,$B23)/1000) -> 0 | O23: =IF(O$3=0,"",SUMIFS(INDEX(Inputs!$D$4:$AG$150,0,MATCH(O$2,Inputs!$D$2:$AG$2,0)),Inputs!$B$4:$B$150,$B23)/1000) -> 0 | P23: =IF(P$3=0,"",SUMIFS(INDEX(Inputs!$D$4:$AG$150,0,MATCH(P$2,Inputs!$D$2:$AG$2,0)),Inputs!$B$4:$B$150,$B23)/1000) -> 0 | Q23: =IF(Q$3=0,"",SUMIFS(INDEX(Inputs!$D$4:$AG$150,0,MATCH(Q$2,Inputs!$D$2:$AG$2,0)),Inputs!$B$4:$B$150,$B23)/1000) -> 0 | R23: =IF(Q23="","",Q23) -> 0 | S23: =IF(S$3=0,"",SUMIFS(INDEX(Inputs!$D$4:$AG$150,0,MATCH(S$2,Inputs!$D$2:$AG$2,0)),Inputs!$B$4:$B$150,$B23)/1000) -> 0 | T23: =IF(T$3=0,"",SUMIFS(INDEX(Inputs!$D$4:$AG$150,0,MATCH(T$2,Inputs!$D$2:$AG$2,0)),Inputs!$B$4:$B$150,$B23)/1000) -> 0 | U23: =IF(U$3=0,"",SUMIFS(INDEX(Inputs!$D$4:$AG$150,0,MATCH(U$2,Inputs!$D$2:$AG$2,0)),Inputs!$B$4:$B$150,$B23)/1000) -> 0 | V23: =IF(V$3=0,"",SUMIFS(INDEX(Inputs!$D$4:$AG$150,0,MATCH(V$2,Inputs!$D$2:$AG$2,0)),Inputs!$B$4:$B$150,$B23)/1000) -> 0 | W23: =IF(V23="","",V23) -> 0 | X23: =IF(X$3=0,"",SUMIFS(INDEX(Inputs!$D$4:$AG$150,0,MATCH(X$2,Inputs!$D$2:$AG$2,0)),Inputs!$B$4:$B$150,$B23)/1000) -> 0 | Y23: =IF(Y$3=0,"",SUMIFS(INDEX(Inputs!$D$4:$AG$150,0,MATCH(Y$2,Inputs!$D$2:$AG$2,0)),Inputs!$B$4:$B$150,$B23)/1000) -> 0 | Z23: =IF(Z$3=0,"",SUMIFS(INDEX(Inputs!$D$4:$AG$150,0,MATCH(Z$2,Inputs!$D$2:$AG$2,0)),Inputs!$B$4:$B$150,$B23)/1000) -> 0 | AA23: =IF(AA$3=0,"",SUMIFS(INDEX(Inputs!$D$4:$AG$150,0,MATCH(AA$2,Inputs!$D$2:$AG$2,0)),Inputs!$B$4:$B$150,$B23)/1000) -> 0 | AB23: =IF(AA23="","",AA23) -> 0 | AC23: =IF(AC$3=0,"",SUMIFS(INDEX(Inputs!$D$4:$AG$150,0,MATCH(AC$2,Inputs!$D$2:$AG$2,0)),Inputs!$B$4:$B$150,$B23)/1000) -> 0 | AD23: =IF(AD$3=0,"",SUMIFS(INDEX(Inputs!$D$4:$AG$150,0,MATCH(AD$2,Inputs!$D$2:$AG$2,0)),Inputs!$B$4:$B$150,$B23)/1000) -> 0 | AE23: =IF(AE$3=0,"",SUMIFS(INDEX(Inputs!$D$4:$AG$150,0,MATCH(AE$2,Inputs!$D$2:$AG$2,0)),Inputs!$B$4:$B$150,$B23)/1000) | AF23: =IF(AF$3=0,"",SUMIFS(INDEX(Inputs!$D$4:$AG$150,0,MATCH(AF$2,Inputs!$D$2:$AG$2,0)),Inputs!$B$4:$B$150,$B23)/1000) | AG23: =IF(AF23="","",AF23)
B24: 20 | C24: Goodwill | D24: =IF(D$3=0,"",SUMIFS(INDEX(Inputs!$D$4:$AG$150,0,MATCH(D$2,Inputs!$D$2:$AG$2,0)),Inputs!$B$4:$B$150,$B24)/1000) -> 0 | E24: =IF(E$3=0,"",SUMIFS(INDEX(Inputs!$D$4:$AG$150,0,MATCH(E$2,Inputs!$D$2:$AG$2,0)),Inputs!$B$4:$B$150,$B24)/1000) -> 0 | F24: =IF(F$3=0,"",SUMIFS(INDEX(Inputs!$D$4:$AG$150,0,MATCH(F$2,Inputs!$D$2:$AG$2,0)),Inputs!$B$4:$B$150,$B24)/1000) -> 0 | G24: =IF(G$3=0,"",SUMIFS(INDEX(Inputs!$D$4:$AG$150,0,MATCH(G$2,Inputs!$D$2:$AG$2,0)),Inputs!$B$4:$B$150,$B24)/1000) -> 0 | H24: =IF(G24="","",G24) -> 0 | I24: =IF(I$3=0,"",SUMIFS(INDEX(Inputs!$D$4:$AG$150,0,MATCH(I$2,Inputs!$D$2:$AG$2,0)),Inputs!$B$4:$B$150,$B24)/1000) -> 0 | J24: =IF(J$3=0,"",SUMIFS(INDEX(Inputs!$D$4:$AG$150,0,MATCH(J$2,Inputs!$D$2:$AG$2,0)),Inputs!$B$4:$B$150,$B24)/1000) -> 0 | K24: =IF(K$3=0,"",SUMIFS(INDEX(Inputs!$D$4:$AG$150,0,MATCH(K$2,Inputs!$D$2:$AG$2,0)),Inputs!$B$4:$B$150,$B24)/1000) -> 0 | L24: =IF(L$3=0,"",SUMIFS(INDEX(Inputs!$D$4:$AG$150,0,MATCH(L$2,Inputs!$D$2:$AG$2,0)),Inputs!$B$4:$B$150,$B24)/1000) -> 0 | M24: =IF(L24="","",L24) -> 0 | N24: =IF(N$3=0,"",SUMIFS(INDEX(Inputs!$D$4:$AG$150,0,MATCH(N$2,Inputs!$D$2:$AG$2,0)),Inputs!$B$4:$B$150,$B24)/1000) -> 0 | O24: =IF(O$3=0,"",SUMIFS(INDEX(Inputs!$D$4:$AG$150,0,MATCH(O$2,Inputs!$D$2:$AG$2,0)),Inputs!$B$4:$B$150,$B24)/1000) -> 0 | P24: =IF(P$3=0,"",SUMIFS(INDEX(Inputs!$D$4:$AG$150,0,MATCH(P$2,Inputs!$D$2:$AG$2,0)),Inputs!$B$4:$B$150,$B24)/1000) -> 0 | Q24: =IF(Q$3=0,"",SUMIFS(INDEX(Inputs!$D$4:$AG$150,0,MATCH(Q$2,Inputs!$D$2:$AG$2,0)),Inputs!$B$4:$B$150,$B24)/1000) -> 0 | R24: =IF(Q24="","",Q24) -> 0 | S24: =IF(S$3=0,"",SUMIFS(INDEX(Inputs!$D$4:$AG$150,0,MATCH(S$2,Inputs!$D$2:$AG$2,0)),Inputs!$B$4:$B$150,$B24)/1000) -> 0 | T24: =IF(T$3=0,"",SUMIFS(INDEX(Inputs!$D$4:$AG$150,0,MATCH(T$2,Inputs!$D$2:$AG$2,0)),Inputs!$B$4:$B$150,$B24)/1000) -> 0 | U24: =IF(U$3=0,"",SUMIFS(INDEX(Inputs!$D$4:$AG$150,0,MATCH(U$2,Inputs!$D$2:$AG$2,0)),Inputs!$B$4:$B$150,$B24)/1000) -> 0 | V24: =IF(V$3=0,"",SUMIFS(INDEX(Inputs!$D$4:$AG$150,0,MATCH(V$2,Inputs!$D$2:$AG$2,0)),Inputs!$B$4:$B$150,$B24)/1000) -> 0 | W24: =IF(V24="","",V24) -> 0 | X24: =IF(X$3=0,"",SUMIFS(INDEX(Inputs!$D$4:$AG$150,0,MATCH(X$2,Inputs!$D$2:$AG$2,0)),Inputs!$B$4:$B$150,$B24)/1000) -> 0 | Y24: =IF(Y$3=0,"",SUMIFS(INDEX(Inputs!$D$4:$AG$150,0,MATCH(Y$2,Inputs!$D$2:$AG$2,0)),Inputs!$B$4:$B$150,$B24)/1000) -> 0 | Z24: =IF(Z$3=0,"",SUMIFS(INDEX(Inputs!$D$4:$AG$150,0,MATCH(Z$2,Inputs!$D$2:$AG$2,0)),Inputs!$B$4:$B$150,$B24)/1000) -> 0 | AA24: =IF(AA$3=0,"",SUMIFS(INDEX(Inputs!$D$4:$AG$150,0,MATCH(AA$2,Inputs!$D$2:$AG$2,0)),Inputs!$B$4:$B$150,$B24)/1000) -> 0 | AB24: =IF(AA24="","",AA24) -> 0 | AC24: =IF(AC$3=0,"",SUMIFS(INDEX(Inputs!$D$4:$AG$150,0,MATCH(AC$2,Inputs!$D$2:$AG$2,0)),Inputs!$B$4:$B$150,$B24)/1000) -> 0 | AD24: =IF(AD$3=0,"",SUMIFS(INDEX(Inputs!$D$4:$AG$150,0,MATCH(AD$2,Inputs!$D$2:$AG$2,0)),Inputs!$B$4:$B$150,$B24)/1000) -> 0 | AE24: =IF(AE$3=0,"",SUMIFS(INDEX(Inputs!$D$4:$AG$150,0,MATCH(AE$2,Inputs!$D$2:$AG$2,0)),Inputs!$B$4:$B$150,$B24)/1000) | AF24: =IF(AF$3=0,"",SUMIFS(INDEX(Inputs!$D$4:$AG$150,0,MATCH(AF$2,Inputs!$D$2:$AG$2,0)),Inputs!$B$4:$B$150,$B24)/1000) | AG24: =IF(AF24="","",AF24)
B25: 21 | C25: Intangibles | D25: =IF(D$3=0,"",SUMIFS(INDEX(Inputs!$D$4:$AG$150,0,MATCH(D$2,Inputs!$D$2:$AG$2,0)),Inputs!$B$4:$B$150,$B25)/1000) -> 0 | E25: =IF(E$3=0,"",SUMIFS(INDEX(Inputs!$D$4:$AG$150,0,MATCH(E$2,Inputs!$D$2:$AG$2,0)),Inputs!$B$4:$B$150,$B25)/1000) -> 0 | F25: =IF(F$3=0,"",SUMIFS(INDEX(Inputs!$D$4:$AG$150,0,MATCH(F$2,Inputs!$D$2:$AG$2,0)),Inputs!$B$4:$B$150,$B25)/1000) -> 0 | G25: =IF(G$3=0,"",SUMIFS(INDEX(Inputs!$D$4:$AG$150,0,MATCH(G$2,Inputs!$D$2:$AG$2,0)),Inputs!$B$4:$B$150,$B25)/1000) -> 0 | H25: =IF(G25="","",G25) -> 0 | I25: =IF(I$3=0,"",SUMIFS(INDEX(Inputs!$D$4:$AG$150,0,MATCH(I$2,Inputs!$D$2:$AG$2,0)),Inputs!$B$4:$B$150,$B25)/1000) -> 0 | J25: =IF(J$3=0,"",SUMIFS(INDEX(Inputs!$D$4:$AG$150,0,MATCH(J$2,Inputs!$D$2:$AG$2,0)),Inputs!$B$4:$B$150,$B25)/1000) -> 0 | K25: =IF(K$3=0,"",SUMIFS(INDEX(Inputs!$D$4:$AG$150,0,MATCH(K$2,Inputs!$D$2:$AG$2,0)),Inputs!$B$4:$B$150,$B25)/1000) -> 0 | L25: =IF(L$3=0,"",SUMIFS(INDEX(Inputs!$D$4:$AG$150,0,MATCH(L$2,Inputs!$D$2:$AG$2,0)),Inputs!$B$4:$B$150,$B25)/1000) -> 0 | M25: =IF(L25="","",L25) -> 0 | N25: =IF(N$3=0,"",SUMIFS(INDEX(Inputs!$D$4:$AG$150,0,MATCH(N$2,Inputs!$D$2:$AG$2,0)),Inputs!$B$4:$B$150,$B25)/1000) -> 0 | O25: =IF(O$3=0,"",SUMIFS(INDEX(Inputs!$D$4:$AG$150,0,MATCH(O$2,Inputs!$D$2:$AG$2,0)),Inputs!$B$4:$B$150,$B25)/1000) -> 0 | P25: =IF(P$3=0,"",SUMIFS(INDEX(Inputs!$D$4:$AG$150,0,MATCH(P$2,Inputs!$D$2:$AG$2,0)),Inputs!$B$4:$B$150,$B25)/1000) -> 0 | Q25: =IF(Q$3=0,"",SUMIFS(INDEX(Inputs!$D$4:$AG$150,0,MATCH(Q$2,Inputs!$D$2:$AG$2,0)),Inputs!$B$4:$B$150,$B25)/1000) -> 0 | R25: =IF(Q25="","",Q25) -> 0 | S25: =IF(S$3=0,"",SUMIFS(INDEX(Inputs!$D$4:$AG$150,0,MATCH(S$2,Inputs!$D$2:$AG$2,0)),Inputs!$B$4:$B$150,$B25)/1000) -> 0 | T25: =IF(T$3=0,"",SUMIFS(INDEX(Inputs!$D$4:$AG$150,0,MATCH(T$2,Inputs!$D$2:$AG$2,0)),Inputs!$B$4:$B$150,$B25)/1000) -> 0 | U25: =IF(U$3=0,"",SUMIFS(INDEX(Inputs!$D$4:$AG$150,0,MATCH(U$2,Inputs!$D$2:$AG$2,0)),Inputs!$B$4:$B$150,$B25)/1000) -> 0 | V25: =IF(V$3=0,"",SUMIFS(INDEX(Inputs!$D$4:$AG$150,0,MATCH(V$2,Inputs!$D$2:$AG$2,0)),Inputs!$B$4:$B$150,$B25)/1000) -> 0 | W25: =IF(V25="","",V25) -> 0 | X25: =IF(X$3=0,"",SUMIFS(INDEX(Inputs!$D$4:$AG$150,0,MATCH(X$2,Inputs!$D$2:$AG$2,0)),Inputs!$B$4:$B$150,$B25)/1000) -> 0 | Y25: =IF(Y$3=0,"",SUMIFS(INDEX(Inputs!$D$4:$AG$150,0,MATCH(Y$2,Inputs!$D$2:$AG$2,0)),Inputs!$B$4:$B$150,$B25)/1000) -> 0 | Z25: =IF(Z$3=0,"",SUMIFS(INDEX(Inputs!$D$4:$AG$150,0,MATCH(Z$2,Inputs!$D$2:$AG$2,0)),Inputs!$B$4:$B$150,$B25)/1000) -> 0 | AA25: =IF(AA$3=0,"",SUMIFS(INDEX(Inputs!$D$4:$AG$150,0,MATCH(AA$2,Inputs!$D$2:$AG$2,0)),Inputs!$B$4:$B$150,$B25)/1000) -> 0 | AB25: =IF(AA25="","",AA25) -> 0 | AC25: =IF(AC$3=0,"",SUMIFS(INDEX(Inputs!$D$4:$AG$150,0,MATCH(AC$2,Inputs!$D$2:$AG$2,0)),Inputs!$B$4:$B$150,$B25)/1000) -> 0 | AD25: =IF(AD$3=0,"",SUMIFS(INDEX(Inputs!$D$4:$AG$150,0,MATCH(AD$2,Inputs!$D$2:$AG$2,0)),Inputs!$B$4:$B$150,$B25)/1000) -> 0 | AE25: =IF(AE$3=0,"",SUMIFS(INDEX(Inputs!$D$4:$AG$150,0,MATCH(AE$2,Inputs!$D$2:$AG$2,0)),Inputs!$B$4:$B$150,$B25)/1000) | AF25: =IF(AF$3=0,"",SUMIFS(INDEX(Inputs!$D$4:$AG$150,0,MATCH(AF$2,Inputs!$D$2:$AG$2,0)),Inputs!$B$4:$B$150,$B25)/1000) | AG25: =IF(AF25="","",AF25)
B26: 22 | C26: Other non-current assets | D26: =IF(D$3=0,"",SUMIFS(INDEX(Inputs!$D$4:$AG$150,0,MATCH(D$2,Inputs!$D$2:$AG$2,0)),Inputs!$B$4:$B$150,$B26)/1000) -> 60934 | E26: =IF(E$3=0,"",SUMIFS(INDEX(Inputs!$D$4:$AG$150,0,MATCH(E$2,Inputs!$D$2:$AG$2,0)),Inputs!$B$4:$B$150,$B26)/1000) -> 61435 | F26: =IF(F$3=0,"",SUMIFS(INDEX(Inputs!$D$4:$AG$150,0,MATCH(F$2,Inputs!$D$2:$AG$2,0)),Inputs!$B$4:$B$150,$B26)/1000) -> 62338 | G26: =IF(G$3=0,"",SUMIFS(INDEX(Inputs!$D$4:$AG$150,0,MATCH(G$2,Inputs!$D$2:$AG$2,0)),Inputs!$B$4:$B$150,$B26)/1000) -> 63217 | H26: =IF(G26="","",G26) -> 63217 | I26: =IF(I$3=0,"",SUMIFS(INDEX(Inputs!$D$4:$AG$150,0,MATCH(I$2,Inputs!$D$2:$AG$2,0)),Inputs!$B$4:$B$150,$B26)/1000) -> 64743 | J26: =IF(J$3=0,"",SUMIFS(INDEX(Inputs!$D$4:$AG$150,0,MATCH(J$2,Inputs!$D$2:$AG$2,0)),Inputs!$B$4:$B$150,$B26)/1000) -> 65452 | K26: =IF(K$3=0,"",SUMIFS(INDEX(Inputs!$D$4:$AG$150,0,MATCH(K$2,Inputs!$D$2:$AG$2,0)),Inputs!$B$4:$B$150,$B26)/1000) -> 67761 | L26: =IF(L$3=0,"",SUMIFS(INDEX(Inputs!$D$4:$AG$150,0,MATCH(L$2,Inputs!$D$2:$AG$2,0)),Inputs!$B$4:$B$150,$B26)/1000) -> 66744 | M26: =IF(L26="","",L26) -> 66744 | N26: =IF(N$3=0,"",SUMIFS(INDEX(Inputs!$D$4:$AG$150,0,MATCH(N$2,Inputs!$D$2:$AG$2,0)),Inputs!$B$4:$B$150,$B26)/1000) -> 66124 | O26: =IF(O$3=0,"",SUMIFS(INDEX(Inputs!$D$4:$AG$150,0,MATCH(O$2,Inputs!$D$2:$AG$2,0)),Inputs!$B$4:$B$150,$B26)/1000) -> 64752 | P26: =IF(P$3=0,"",SUMIFS(INDEX(Inputs!$D$4:$AG$150,0,MATCH(P$2,Inputs!$D$2:$AG$2,0)),Inputs!$B$4:$B$150,$B26)/1000) -> 65255 | Q26: =IF(Q$3=0,"",SUMIFS(INDEX(Inputs!$D$4:$AG$150,0,MATCH(Q$2,Inputs!$D$2:$AG$2,0)),Inputs!$B$4:$B$150,$B26)/1000) -> 64768 | R26: =IF(Q26="","",Q26) -> 64768 | S26: =IF(S$3=0,"",SUMIFS(INDEX(Inputs!$D$4:$AG$150,0,MATCH(S$2,Inputs!$D$2:$AG$2,0)),Inputs!$B$4:$B$150,$B26)/1000) -> 64818 | T26: =IF(T$3=0,"",SUMIFS(INDEX(Inputs!$D$4:$AG$150,0,MATCH(T$2,Inputs!$D$2:$AG$2,0)),Inputs!$B$4:$B$150,$B26)/1000) -> 66186 | U26: =IF(U$3=0,"",SUMIFS(INDEX(Inputs!$D$4:$AG$150,0,MATCH(U$2,Inputs!$D$2:$AG$2,0)),Inputs!$B$4:$B$150,$B26)/1000) -> 68024 | V26: =IF(V$3=0,"",SUMIFS(INDEX(Inputs!$D$4:$AG$150,0,MATCH(V$2,Inputs!$D$2:$AG$2,0)),Inputs!$B$4:$B$150,$B26)/1000) -> 67167 | W26: =IF(V26="","",V26) -> 67167 | X26: =IF(X$3=0,"",SUMIFS(INDEX(Inputs!$D$4:$AG$150,0,MATCH(X$2,Inputs!$D$2:$AG$2,0)),Inputs!$B$4:$B$150,$B26)/1000) -> 68029 | Y26: =IF(Y$3=0,"",SUMIFS(INDEX(Inputs!$D$4:$AG$150,0,MATCH(Y$2,Inputs!$D$2:$AG$2,0)),Inputs!$B$4:$B$150,$B26)/1000) -> 67133 | Z26: =IF(Z$3=0,"",SUMIFS(INDEX(Inputs!$D$4:$AG$150,0,MATCH(Z$2,Inputs!$D$2:$AG$2,0)),Inputs!$B$4:$B$150,$B26)/1000) -> 67447 | AA26: =IF(AA$3=0,"",SUMIFS(INDEX(Inputs!$D$4:$AG$150,0,MATCH(AA$2,Inputs!$D$2:$AG$2,0)),Inputs!$B$4:$B$150,$B26)/1000) -> 66225 | AB26: =IF(AA26="","",AA26) -> 66225 | AC26: =IF(AC$3=0,"",SUMIFS(INDEX(Inputs!$D$4:$AG$150,0,MATCH(AC$2,Inputs!$D$2:$AG$2,0)),Inputs!$B$4:$B$150,$B26)/1000) -> 67842 | AD26: =IF(AD$3=0,"",SUMIFS(INDEX(Inputs!$D$4:$AG$150,0,MATCH(AD$2,Inputs!$D$2:$AG$2,0)),Inputs!$B$4:$B$150,$B26)/1000) -> 67391 | AE26: =IF(AE$3=0,"",SUMIFS(INDEX(Inputs!$D$4:$AG$150,0,MATCH(AE$2,Inputs!$D$2:$AG$2,0)),Inputs!$B$4:$B$150,$B26)/1000) | AF26: =IF(AF$3=0,"",SUMIFS(INDEX(Inputs!$D$4:$AG$150,0,MATCH(AF$2,Inputs!$D$2:$AG$2,0)),Inputs!$B$4:$B$150,$B26)/1000) | AG26: =IF(AF26="","",AF26)
... B47: 41 | C47: Retained earnings | D47: =IF(D$3=0,"",SUMIFS(INDEX(Inputs!$D$4:$AG$150,0,MATCH(D$2,Inputs!$D$2:$AG$2,0)),Inputs!$B$4:$B$150,$B47)/1000) -> 382953 | E47: =IF(E$3=0,"",SUMIFS(INDEX(Inputs!$D$4:$AG$150,0,MATCH(E$2,Inputs!$D$2:$AG$2,0)),Inputs!$B$4:$B$150,$B47)/1000) -> 383922 | F47: =IF(F$3=0,"",SUMIFS(INDEX(Inputs!$D$4:$AG$150,0,MATCH(F$2,Inputs!$D$2:$AG$2,0)),Inputs!$B$4:$B$150,$B47)/1000) -> 386952 | G47: =IF(G$3=0,"",SUMIFS(INDEX(Inputs!$D$4:$AG$150,0,MATCH(G$2,Inputs!$D$2:$AG$2,0)),Inputs!$B$4:$B$150,$B47)/1000) -> 392059 | H47: =IF(G47="","",G47) -> 392059 | I47: =IF(I$3=0,"",SUMIFS(INDEX(Inputs!$D$4:$AG$150,0,MATCH(I$2,Inputs!$D$2:$AG$2,0)),Inputs!$B$4:$B$150,$B47)/1000) -> 393779 | J47: =IF(J$3=0,"",SUMIFS(INDEX(Inputs!$D$4:$AG$150,0,MATCH(J$2,Inputs!$D$2:$AG$2,0)),Inputs!$B$4:$B$150,$B47)/1000) -> 407902 | K47: =IF(K$3=0,"",SUMIFS(INDEX(Inputs!$D$4:$AG$150,0,MATCH(K$2,Inputs!$D$2:$AG$2,0)),Inputs!$B$4:$B$150,$B47)/1000) -> 423877 | L47: =IF(L$3=0,"",SUMIFS(INDEX(Inputs!$D$4:$AG$150,0,MATCH(L$2,Inputs!$D$2:$AG$2,0)),Inputs!$B$4:$B$150,$B47)/1000) -> 432860 | M47: =IF(L47="","",L47) -> 432860 | N47: =IF(N$3=0,"",SUMIFS(INDEX(Inputs!$D$4:$AG$150,0,MATCH(N$2,Inputs!$D$2:$AG$2,0)),Inputs!$B$4:$B$150,$B47)/1000) -> 440552 | O47: =IF(O$3=0,"",SUMIFS(INDEX(Inputs!$D$4:$AG$150,0,MATCH(O$2,Inputs!$D$2:$AG$2,0)),Inputs!$B$4:$B$150,$B47)/1000) -> 444731 | P47: =IF(P$3=0,"",SUMIFS(INDEX(Inputs!$D$4:$AG$150,0,MATCH(P$2,Inputs!$D$2:$AG$2,0)),Inputs!$B$4:$B$150,$B47)/1000) -> 450138 | Q47: =IF(Q$3=0,"",SUMIFS(INDEX(Inputs!$D$4:$AG$150,0,MATCH(Q$2,Inputs!$D$2:$AG$2,0)),Inputs!$B$4:$B$150,$B47)/1000) -> 453927 | R47: =IF(Q47="","",Q47) -> 453927 | S47: =IF(S$3=0,"",SUMIFS(INDEX(Inputs!$D$4:$AG$150,0,MATCH(S$2,Inputs!$D$2:$AG$2,0)),Inputs!$B$4:$B$150,$B47)/1000) -> 458339 | T47: =IF(T$3=0,"",SUMIFS(INDEX(Inputs!$D$4:$AG$150,0,MATCH(T$2,Inputs!$D$2:$AG$2,0)),Inputs!$B$4:$B$150,$B47)/1000) -> 463294 | U47: =IF(U$3=0,"",SUMIFS(INDEX(Inputs!$D$4:$AG$150,0,MATCH(U$2,Inputs!$D$2:$AG$2,0)),Inputs!$B$4:$B$150,$B47)/1000) -> 467664 | V47: =IF(V$3=0,"",SUMIFS(INDEX(Inputs!$D$4:$AG$150,0,MATCH(V$2,Inputs!$D$2:$AG$2,0)),Inputs!$B$4:$B$150,$B47)/1000) -> 470903 | W47: =IF(V47="","",V47) -> 470903 | X47: =IF(X$3=0,"",SUMIFS(INDEX(Inputs!$D$4:$AG$150,0,MATCH(X$2,Inputs!$D$2:$AG$2,0)),Inputs!$B$4:$B$150,$B47)/1000) -> 474290 | Y47: =IF(Y$3=0,"",SUMIFS(INDEX(Inputs!$D$4:$AG$150,0,MATCH(Y$2,Inputs!$D$2:$AG$2,0)),Inputs!$B$4:$B$150,$B47)/1000) -> 477061 | Z47: =IF(Z$3=0,"",SUMIFS(INDEX(Inputs!$D$4:$AG$150,0,MATCH(Z$2,Inputs!$D$2:$AG$2,0)),Inputs!$B$4:$B$150,$B47)/1000) -> 480367 | AA47: =IF(AA$3=0,"",SUMIFS(INDEX(Inputs!$D$4:$AG$150,0,MATCH(AA$2,Inputs!$D$2:$AG$2,0)),Inputs!$B$4:$B$150,$B47)/1000) -> 482494 | AB47: =IF(AA47="","",AA47) -> 482494 | AC47: =IF(AC$3=0,"",SUMIFS(INDEX(Inputs!$D$4:$AG$150,0,MATCH(AC$2,Inputs!$D$2:$AG$2,0)),Inputs!$B$4:$B$150,$B47)/1000) -> 482344 | AD47: =IF(AD$3=0,"",SUMIFS(INDEX(Inputs!$D$4:$AG$150,0,MATCH(AD$2,Inputs!$D$2:$AG$2,0)),Inputs!$B$4:$B$150,$B47)/1000) -> 492569 | AE47: =IF(AE$3=0,"",SUMIFS(INDEX(Inputs!$D$4:$AG$150,0,MATCH(AE$2,Inputs!$D$2:$AG$2,0)),Inputs!$B$4:$B$150,$B47)/1000) | AF47: =IF(AF$3=0,"",SUMIFS(INDEX(Inputs!$D$4:$AG$150,0,MATCH(AF$2,Inputs!$D$2:$AG$2,0)),Inputs!$B$4:$B$150,$B47)/1000) | AG47: =IF(AF47="","",AF47)
B50: 44 | C50: Net income reported (lucro líquido reportado) — base do check de DRE [Model linha 4] | D50: =IF(SUMPRODUCT((Inputs!$B$4:$B$150=$B50)*ISNUMBER(INDEX(Inputs!$D$4:$AG$150,0,MATCH(D$2,Inputs!$D$2:$AG$2,0))))=0,"",SUMIFS(INDEX(Inputs!$D$4:$AG$150,0,MATCH(D$2,Inputs!$D$2:$AG$2,0)),Inputs!$B$4:$B$150,$B50)/1000) -> 2730 | E50: =IF(SUMPRODUCT((Inputs!$B$4:$B$150=$B50)*ISNUMBER(INDEX(Inputs!$D$4:$AG$150,0,MATCH(E$2,Inputs!$D$2:$AG$2,0))))=0,"",SUMIFS(INDEX(Inputs!$D$4:$AG$150,0,MATCH(E$2,Inputs!$D$2:$AG$2,0)),Inputs!$B$4:$B$150,$B50)/1000) -> 4690 | F50: =IF(SUMPRODUCT((Inputs!$B$4:$B$150=$B50)*ISNUMBER(INDEX(Inputs!$D$4:$AG$150,0,MATCH(F$2,Inputs!$D$2:$AG$2,0))))=0,"",SUMIFS(INDEX(Inputs!$D$4:$AG$150,0,MATCH(F$2,Inputs!$D$2:$AG$2,0)),Inputs!$B$4:$B$150,$B50)/1000) -> 6750 | G50: =IF(SUMPRODUCT((Inputs!$B$4:$B$150=$B50)*ISNUMBER(INDEX(Inputs!$D$4:$AG$150,0,MATCH(G$2,Inputs!$D$2:$AG$2,0))))=0,"",SUMIFS(INDEX(Inputs!$D$4:$AG$150,0,MATCH(G$2,Inputs!$D$2:$AG$2,0)),Inputs!$B$4:$B$150,$B50)/1000) -> 8870 | H50: =IF(COUNT(D50:G50)=4,SUM(D50:G50),"") -> 23040 | I50: =IF(SUMPRODUCT((Inputs!$B$4:$B$150=$B50)*ISNUMBER(INDEX(Inputs!$D$4:$AG$150,0,MATCH(I$2,Inputs!$D$2:$AG$2,0))))=0,"",SUMIFS(INDEX(Inputs!$D$4:$AG$150,0,MATCH(I$2,Inputs!$D$2:$AG$2,0)),Inputs!$B$4:$B$150,$B50)/1000) -> 5480 | J50: =IF(SUMPRODUCT((Inputs!$B$4:$B$150=$B50)*ISNUMBER(INDEX(Inputs!$D$4:$AG$150,0,MATCH(J$2,Inputs!$D$2:$AG$2,0))))=0,"",SUMIFS(INDEX(Inputs!$D$4:$AG$150,0,MATCH(J$2,Inputs!$D$2:$AG$2,0)),Inputs!$B$4:$B$150,$B50)/1000) -> 17850 | K50: =IF(SUMPRODUCT((Inputs!$B$4:$B$150=$B50)*ISNUMBER(INDEX(Inputs!$D$4:$AG$150,0,MATCH(K$2,Inputs!$D$2:$AG$2,0))))=0,"",SUMIFS(INDEX(Inputs!$D$4:$AG$150,0,MATCH(K$2,Inputs!$D$2:$AG$2,0)),Inputs!$B$4:$B$150,$B50)/1000) -> 19660 | L50: =IF(SUMPRODUCT((Inputs!$B$4:$B$150=$B50)*ISNUMBER(INDEX(Inputs!$D$4:$AG$150,0,MATCH(L$2,Inputs!$D$2:$AG$2,0))))=0,"",SUMIFS(INDEX(Inputs!$D$4:$AG$150,0,MATCH(L$2,Inputs!$D$2:$AG$2,0)),Inputs!$B$4:$B$150,$B50)/1000) -> 12750 | M50: =IF(COUNT(I50:L50)=4,SUM(I50:L50),"") -> 55740 | N50: =IF(SUMPRODUCT((Inputs!$B$4:$B$150=$B50)*ISNUMBER(INDEX(Inputs!$D$4:$AG$150,0,MATCH(N$2,Inputs!$D$2:$AG$2,0))))=0,"",SUMIFS(INDEX(Inputs!$D$4:$AG$150,0,MATCH(N$2,Inputs!$D$2:$AG$2,0)),Inputs!$B$4:$B$150,$B50)/1000) -> 11430 | O50: =IF(SUMPRODUCT((Inputs!$B$4:$B$150=$B50)*ISNUMBER(INDEX(Inputs!$D$4:$AG$150,0,MATCH(O$2,Inputs!$D$2:$AG$2,0))))=0,"",SUMIFS(INDEX(Inputs!$D$4:$AG$150,0,MATCH(O$2,Inputs!$D$2:$AG$2,0)),Inputs!$B$4:$B$150,$B50)/1000) -> 7880 | P50: =IF(SUMPRODUCT((Inputs!$B$4:$B$150=$B50)*ISNUMBER(INDEX(Inputs!$D$4:$AG$150,0,MATCH(P$2,Inputs!$D$2:$AG$2,0))))=0,"",SUMIFS(INDEX(Inputs!$D$4:$AG$150,0,MATCH(P$2,Inputs!$D$2:$AG$2,0)),Inputs!$B$4:$B$150,$B50)/1000) -> 9070 | Q50: =IF(SUMPRODUCT((Inputs!$B$4:$B$150=$B50)*ISNUMBER(INDEX(Inputs!$D$4:$AG$150,0,MATCH(Q$2,Inputs!$D$2:$AG$2,0))))=0,"",SUMIFS(INDEX(Inputs!$D$4:$AG$150,0,MATCH(Q$2,Inputs!$D$2:$AG$2,0)),Inputs!$B$4:$B$150,$B50)/1000) -> 7630 | R50: =IF(COUNT(N50:Q50)=4,SUM(N50:Q50),"") -> 36010 | S50: =IF(SUMPRODUCT((Inputs!$B$4:$B$150=$B50)*ISNUMBER(INDEX(Inputs!$D$4:$AG$150,0,MATCH(S$2,Inputs!$D$2:$AG$2,0))))=0,"",SUMIFS(INDEX(Inputs!$D$4:$AG$150,0,MATCH(S$2,Inputs!$D$2:$AG$2,0)),Inputs!$B$4:$B$150,$B50)/1000) -> 8220 | T50: =IF(SUMPRODUCT((Inputs!$B$4:$B$150=$B50)*ISNUMBER(INDEX(Inputs!$D$4:$AG$150,0,MATCH(T$2,Inputs!$D$2:$AG$2,0))))=0,"",SUMIFS(INDEX(Inputs!$D$4:$AG$150,0,MATCH(T$2,Inputs!$D$2:$AG$2,0)),Inputs!$B$4:$B$150,$B50)/1000) -> 9240 | U50: =IF(SUMPRODUCT((Inputs!$B$4:$B$150=$B50)*ISNUMBER(INDEX(Inputs!$D$4:$AG$150,0,MATCH(U$2,Inputs!$D$2:$AG$2,0))))=0,"",SUMIFS(INDEX(Inputs!$D$4:$AG$150,0,MATCH(U$2,Inputs!$D$2:$AG$2,0)),Inputs!$B$4:$B$150,$B50)/1000) -> 8610 | V50: =IF(SUMPRODUCT((Inputs!$B$4:$B$150=$B50)*ISNUMBER(INDEX(Inputs!$D$4:$AG$150,0,MATCH(V$2,Inputs!$D$2:$AG$2,0))))=0,"",SUMIFS(INDEX(Inputs!$D$4:$AG$150,0,MATCH(V$2,Inputs!$D$2:$AG$2,0)),Inputs!$B$4:$B$150,$B50)/1000) -> 7610 | W50: =IF(COUNT(S50:V50)=4,SUM(S50:V50),"") -> 33680 | X50: =IF(SUMPRODUCT((Inputs!$B$4:$B$150=$B50)*ISNUMBER(INDEX(Inputs!$D$4:$AG$150,0,MATCH(X$2,Inputs!$D$2:$AG$2,0))))=0,"",SUMIFS(INDEX(Inputs!$D$4:$AG$150,0,MATCH(X$2,Inputs!$D$2:$AG$2,0)),Inputs!$B$4:$B$150,$B50)/1000) -> 7713 | Y50: =IF(SUMPRODUCT((Inputs!$B$4:$B$150=$B50)*ISNUMBER(INDEX(Inputs!$D$4:$AG$150,0,MATCH(Y$2,Inputs!$D$2:$AG$2,0))))=0,"",SUMIFS(INDEX(Inputs!$D$4:$AG$150,0,MATCH(Y$2,Inputs!$D$2:$AG$2,0)),Inputs!$B$4:$B$150,$B50)/1000) -> 7082 | Z50: =IF(SUMPRODUCT((Inputs!$B$4:$B$150=$B50)*ISNUMBER(INDEX(Inputs!$D$4:$AG$150,0,MATCH(Z$2,Inputs!$D$2:$AG$2,0))))=0,"",SUMIFS(INDEX(Inputs!$D$4:$AG$150,0,MATCH(Z$2,Inputs!$D$2:$AG$2,0)),Inputs!$B$4:$B$150,$B50)/1000) -> 7548 | AA50: =IF(SUMPRODUCT((Inputs!$B$4:$B$150=$B50)*ISNUMBER(INDEX(Inputs!$D$4:$AG$150,0,MATCH(AA$2,Inputs!$D$2:$AG$2,0))))=0,"",SUMIFS(INDEX(Inputs!$D$4:$AG$150,0,MATCH(AA$2,Inputs!$D$2:$AG$2,0)),Inputs!$B$4:$B$150,$B50)/1000) -> 6501 | AB50: =IF(COUNT(X50:AA50)=4,SUM(X50:AA50),"") -> 28844 | AC50: =IF(SUMPRODUCT((Inputs!$B$4:$B$150=$B50)*ISNUMBER(INDEX(Inputs!$D$4:$AG$150,0,MATCH(AC$2,Inputs!$D$2:$AG$2,0))))=0,"",SUMIFS(INDEX(Inputs!$D$4:$AG$150,0,MATCH(AC$2,Inputs!$D$2:$AG$2,0)),Inputs!$B$4:$B$150,$B50)/1000) -> 4183 | AD50: =IF(SUMPRODUCT((Inputs!$B$4:$B$150=$B50)*ISNUMBER(INDEX(Inputs!$D$4:$AG$150,0,MATCH(AD$2,Inputs!$D$2:$AG$2,0))))=0,"",SUMIFS(INDEX(Inputs!$D$4:$AG$150,0,MATCH(AD$2,Inputs!$D$2:$AG$2,0)),Inputs!$B$4:$B$150,$B50)/1000) -> 14525 | AE50: =IF(SUMPRODUCT((Inputs!$B$4:$B$150=$B50)*ISNUMBER(INDEX(Inputs!$D$4:$AG$150,0,MATCH(AE$2,Inputs!$D$2:$AG$2,0))))=0,"",SUMIFS(INDEX(Inputs!$D$4:$AG$150,0,MATCH(AE$2,Inputs!$D$2:$AG$2,0)),Inputs!$B$4:$B$150,$B50)/1000) | AF50: =IF(SUMPRODUCT((Inputs!$B$4:$B$150=$B50)*ISNUMBER(INDEX(Inputs!$D$4:$AG$150,0,MATCH(AF$2,Inputs!$D$2:$AG$2,0))))=0,"",SUMIFS(INDEX(Inputs!$D$4:$AG$150,0,MATCH(AF$2,Inputs!$D$2:$AG$2,0)),Inputs!$B$4:$B$150,$B50)/1000) | AG50: =IF(COUNT(AC50:AF50)=4,SUM(AC50:AF50),"")
C52: Drivers de receita (memo) - codigos 45+ [Model, bloco abaixo da receita liquida]
B53: 45 | C53: Vendas e outras receitas operacionais (USD) | D53: =IF(SUMPRODUCT((Inputs!$B$4:$B$150=$B53)*ISNUMBER(INDEX(Inputs!$D$4:$AG$150,0,MATCH(D$2,Inputs!$D$2:$AG$2,0))))=0,"",SUMIFS(INDEX(Inputs!$D$4:$AG$150,0,MATCH(D$2,Inputs!$D$2:$AG$2,0)),Inputs!$B$4:$B$150,$B53)/1000) | E53: =IF(SUMPRODUCT((Inputs!$B$4:$B$150=$B53)*ISNUMBER(INDEX(Inputs!$D$4:$AG$150,0,MATCH(E$2,Inputs!$D$2:$AG$2,0))))=0,"",SUMIFS(INDEX(Inputs!$D$4:$AG$150,0,MATCH(E$2,Inputs!$D$2:$AG$2,0)),Inputs!$B$4:$B$150,$B53)/1000) | F53: =IF(SUMPRODUCT((Inputs!$B$4:$B$150=$B53)*ISNUMBER(INDEX(Inputs!$D$4:$AG$150,0,MATCH(F$2,Inputs!$D$2:$AG$2,0))))=0,"",SUMIFS(INDEX(Inputs!$D$4:$AG$150,0,MATCH(F$2,Inputs!$D$2:$AG$2,0)),Inputs!$B$4:$B$150,$B53)/1000) | G53: =IF(SUMPRODUCT((Inputs!$B$4:$B$150=$B53)*ISNUMBER(INDEX(Inputs!$D$4:$AG$150,0,MATCH(G$2,Inputs!$D$2:$AG$2,0))))=0,"",SUMIFS(INDEX(Inputs!$D$4:$AG$150,0,MATCH(G$2,Inputs!$D$2:$AG$2,0)),Inputs!$B$4:$B$150,$B53)/1000) | H53: =IF(COUNT(D53:G53)=4,SUM(D53:G53),"") | I53: =IF(SUMPRODUCT((Inputs!$B$4:$B$150=$B53)*ISNUMBER(INDEX(Inputs!$D$4:$AG$150,0,MATCH(I$2,Inputs!$D$2:$AG$2,0))))=0,"",SUMIFS(INDEX(Inputs!$D$4:$AG$150,0,MATCH(I$2,Inputs!$D$2:$AG$2,0)),Inputs!$B$4:$B$150,$B53)/1000) -> 87734 | J53: =IF(SUMPRODUCT((Inputs!$B$4:$B$150=$B53)*ISNUMBER(INDEX(Inputs!$D$4:$AG$150,0,MATCH(J$2,Inputs!$D$2:$AG$2,0))))=0,"",SUMIFS(INDEX(Inputs!$D$4:$AG$150,0,MATCH(J$2,Inputs!$D$2:$AG$2,0)),Inputs!$B$4:$B$150,$B53)/1000) -> 111265 | K53: =IF(SUMPRODUCT((Inputs!$B$4:$B$150=$B53)*ISNUMBER(INDEX(Inputs!$D$4:$AG$150,0,MATCH(K$2,Inputs!$D$2:$AG$2,0))))=0,"",SUMIFS(INDEX(Inputs!$D$4:$AG$150,0,MATCH(K$2,Inputs!$D$2:$AG$2,0)),Inputs!$B$4:$B$150,$B53)/1000) -> 106512 | L53: =IF(SUMPRODUCT((Inputs!$B$4:$B$150=$B53)*ISNUMBER(INDEX(Inputs!$D$4:$AG$150,0,MATCH(L$2,Inputs!$D$2:$AG$2,0))))=0,"",SUMIFS(INDEX(Inputs!$D$4:$AG$150,0,MATCH(L$2,Inputs!$D$2:$AG$2,0)),Inputs!$B$4:$B$150,$B53)/1000) -> 93164 | M53: =IF(COUNT(I53:L53)=4,SUM(I53:L53),"") -> 398675 | N53: =IF(SUMPRODUCT((Inputs!$B$4:$B$150=$B53)*ISNUMBER(INDEX(Inputs!$D$4:$AG$150,0,MATCH(N$2,Inputs!$D$2:$AG$2,0))))=0,"",SUMIFS(INDEX(Inputs!$D$4:$AG$150,0,MATCH(N$2,Inputs!$D$2:$AG$2,0)),Inputs!$B$4:$B$150,$B53)/1000) -> 83644 | O53: =IF(SUMPRODUCT((Inputs!$B$4:$B$150=$B53)*ISNUMBER(INDEX(Inputs!$D$4:$AG$150,0,MATCH(O$2,Inputs!$D$2:$AG$2,0))))=0,"",SUMIFS(INDEX(Inputs!$D$4:$AG$150,0,MATCH(O$2,Inputs!$D$2:$AG$2,0)),Inputs!$B$4:$B$150,$B53)/1000) -> 80795 | P53: =IF(SUMPRODUCT((Inputs!$B$4:$B$150=$B53)*ISNUMBER(INDEX(Inputs!$D$4:$AG$150,0,MATCH(P$2,Inputs!$D$2:$AG$2,0))))=0,"",SUMIFS(INDEX(Inputs!$D$4:$AG$150,0,MATCH(P$2,Inputs!$D$2:$AG$2,0)),Inputs!$B$4:$B$150,$B53)/1000) -> 88570 | Q53: =IF(SUMPRODUCT((Inputs!$B$4:$B$150=$B53)*ISNUMBER(INDEX(Inputs!$D$4:$AG$150,0,MATCH(Q$2,Inputs!$D$2:$AG$2,0))))=0,"",SUMIFS(INDEX(Inputs!$D$4:$AG$150,0,MATCH(Q$2,Inputs!$D$2:$AG$2,0)),Inputs!$B$4:$B$150,$B53)/1000) -> 81688 | R53: =IF(COUNT(N53:Q53)=4,SUM(N53:Q53),"") -> 334697 | S53: =IF(SUMPRODUCT((Inputs!$B$4:$B$150=$B53)*ISNUMBER(INDEX(Inputs!$D$4:$AG$150,0,MATCH(S$2,Inputs!$D$2:$AG$2,0))))=0,"",SUMIFS(INDEX(Inputs!$D$4:$AG$150,0,MATCH(S$2,Inputs!$D$2:$AG$2,0)),Inputs!$B$4:$B$150,$B53)/1000) -> 80411 | T53: =IF(SUMPRODUCT((Inputs!$B$4:$B$150=$B53)*ISNUMBER(INDEX(Inputs!$D$4:$AG$150,0,MATCH(T$2,Inputs!$D$2:$AG$2,0))))=0,"",SUMIFS(INDEX(Inputs!$D$4:$AG$150,0,MATCH(T$2,Inputs!$D$2:$AG$2,0)),Inputs!$B$4:$B$150,$B53)/1000) -> 89986 | U53: =IF(SUMPRODUCT((Inputs!$B$4:$B$150=$B53)*ISNUMBER(INDEX(Inputs!$D$4:$AG$150,0,MATCH(U$2,Inputs!$D$2:$AG$2,0))))=0,"",SUMIFS(INDEX(Inputs!$D$4:$AG$150,0,MATCH(U$2,Inputs!$D$2:$AG$2,0)),Inputs!$B$4:$B$150,$B53)/1000) -> 87792 | V53: =IF(SUMPRODUCT((Inputs!$B$4:$B$150=$B53)*ISNUMBER(INDEX(Inputs!$D$4:$AG$150,0,MATCH(V$2,Inputs!$D$2:$AG$2,0))))=0,"",SUMIFS(INDEX(Inputs!$D$4:$AG$150,0,MATCH(V$2,Inputs!$D$2:$AG$2,0)),Inputs!$B$4:$B$150,$B53)/1000) -> 81058 | W53: =IF(COUNT(S53:V53)=4,SUM(S53:V53),"") -> 339247 | X53: =IF(SUMPRODUCT((Inputs!$B$4:$B$150=$B53)*ISNUMBER(INDEX(Inputs!$D$4:$AG$150,0,MATCH(X$2,Inputs!$D$2:$AG$2,0))))=0,"",SUMIFS(INDEX(Inputs!$D$4:$AG$150,0,MATCH(X$2,Inputs!$D$2:$AG$2,0)),Inputs!$B$4:$B$150,$B53)/1000) -> 81058 | Y53: =IF(SUMPRODUCT((Inputs!$B$4:$B$150=$B53)*ISNUMBER(INDEX(Inputs!$D$4:$AG$150,0,MATCH(Y$2,Inputs!$D$2:$AG$2,0))))=0,"",SUMIFS(INDEX(Inputs!$D$4:$AG$150,0,MATCH(Y$2,Inputs!$D$2:$AG$2,0)),Inputs!$B$4:$B$150,$B53)/1000) -> 79477 | Z53: =IF(SUMPRODUCT((Inputs!$B$4:$B$150=$B53)*ISNUMBER(INDEX(Inputs!$D$4:$AG$150,0,MATCH(Z$2,Inputs!$D$2:$AG$2,0))))=0,"",SUMIFS(INDEX(Inputs!$D$4:$AG$150,0,MATCH(Z$2,Inputs!$D$2:$AG$2,0)),Inputs!$B$4:$B$150,$B53)/1000) -> 83331 | AA53: =IF(SUMPRODUCT((Inputs!$B$4:$B$150=$B53)*ISNUMBER(INDEX(Inputs!$D$4:$AG$150,0,MATCH(AA$2,Inputs!$D$2:$AG$2,0))))=0,"",SUMIFS(INDEX(Inputs!$D$4:$AG$150,0,MATCH(AA$2,Inputs!$D$2:$AG$2,0)),Inputs!$B$4:$B$150,$B53)/1000) -> 80039 | AB53: =IF(COUNT(X53:AA53)=4,SUM(X53:AA53),"") -> 323905 | AC53: =IF(SUMPRODUCT((Inputs!$B$4:$B$150=$B53)*ISNUMBER(INDEX(Inputs!$D$4:$AG$150,0,MATCH(AC$2,Inputs!$D$2:$AG$2,0))))=0,"",SUMIFS(INDEX(Inputs!$D$4:$AG$150,0,MATCH(AC$2,Inputs!$D$2:$AG$2,0)),Inputs!$B$4:$B$150,$B53)/1000) -> 83161 | AD53: =IF(SUMPRODUCT((Inputs!$B$4:$B$150=$B53)*ISNUMBER(INDEX(Inputs!$D$4:$AG$150,0,MATCH(AD$2,Inputs!$D$2:$AG$2,0))))=0,"",SUMIFS(INDEX(Inputs!$D$4:$AG$150,0,MATCH(AD$2,Inputs!$D$2:$AG$2,0)),Inputs!$B$4:$B$150,$B53)/1000) -> 114529 | AE53: =IF(SUMPRODUCT((Inputs!$B$4:$B$150=$B53)*ISNUMBER(INDEX(Inputs!$D$4:$AG$150,0,MATCH(AE$2,Inputs!$D$2:$AG$2,0))))=0,"",SUMIFS(INDEX(Inputs!$D$4:$AG$150,0,MATCH(AE$2,Inputs!$D$2:$AG$2,0)),Inputs!$B$4:$B$150,$B53)/1000) | AF53: =IF(SUMPRODUCT((Inputs!$B$4:$B$150=$B53)*ISNUMBER(INDEX(Inputs!$D$4:$AG$150,0,MATCH(AF$2,Inputs!$D$2:$AG$2,0))))=0,"",SUMIFS(INDEX(Inputs!$D$4:$AG$150,0,MATCH(AF$2,Inputs!$D$2:$AG$2,0)),Inputs!$B$4:$B$150,$B53)/1000) | AG53: =IF(COUNT(AC53:AF53)=4,SUM(AC53:AF53),"")
B54: 46 | C54: Receita de equivalência patrimonial (USD) | D54: =IF(SUMPRODUCT((Inputs!$B$4:$B$150=$B54)*ISNUMBER(INDEX(Inputs!$D$4:$AG$150,0,MATCH(D$2,Inputs!$D$2:$AG$2,0))))=0,"",SUMIFS(INDEX(Inputs!$D$4:$AG$150,0,MATCH(D$2,Inputs!$D$2:$AG$2,0)),Inputs!$B$4:$B$150,$B54)/1000) | E54: =IF(SUMPRODUCT((Inputs!$B$4:$B$150=$B54)*ISNUMBER(INDEX(Inputs!$D$4:$AG$150,0,MATCH(E$2,Inputs!$D$2:$AG$2,0))))=0,"",SUMIFS(INDEX(Inputs!$D$4:$AG$150,0,MATCH(E$2,Inputs!$D$2:$AG$2,0)),Inputs!$B$4:$B$150,$B54)/1000) | F54: =IF(SUMPRODUCT((Inputs!$B$4:$B$150=$B54)*ISNUMBER(INDEX(Inputs!$D$4:$AG$150,0,MATCH(F$2,Inputs!$D$2:$AG$2,0))))=0,"",SUMIFS(INDEX(Inputs!$D$4:$AG$150,0,MATCH(F$2,Inputs!$D$2:$AG$2,0)),Inputs!$B$4:$B$150,$B54)/1000) | G54: =IF(SUMPRODUCT((Inputs!$B$4:$B$150=$B54)*ISNUMBER(INDEX(Inputs!$D$4:$AG$150,0,MATCH(G$2,Inputs!$D$2:$AG$2,0))))=0,"",SUMIFS(INDEX(Inputs!$D$4:$AG$150,0,MATCH(G$2,Inputs!$D$2:$AG$2,0)),Inputs!$B$4:$B$150,$B54)/1000) | H54: =IF(COUNT(D54:G54)=4,SUM(D54:G54),"") | I54: =IF(SUMPRODUCT((Inputs!$B$4:$B$150=$B54)*ISNUMBER(INDEX(Inputs!$D$4:$AG$150,0,MATCH(I$2,Inputs!$D$2:$AG$2,0))))=0,"",SUMIFS(INDEX(Inputs!$D$4:$AG$150,0,MATCH(I$2,Inputs!$D$2:$AG$2,0)),Inputs!$B$4:$B$150,$B54)/1000) -> 2538 | J54: =IF(SUMPRODUCT((Inputs!$B$4:$B$150=$B54)*ISNUMBER(INDEX(Inputs!$D$4:$AG$150,0,MATCH(J$2,Inputs!$D$2:$AG$2,0))))=0,"",SUMIFS(INDEX(Inputs!$D$4:$AG$150,0,MATCH(J$2,Inputs!$D$2:$AG$2,0)),Inputs!$B$4:$B$150,$B54)/1000) -> 3688 | K54: =IF(SUMPRODUCT((Inputs!$B$4:$B$150=$B54)*ISNUMBER(INDEX(Inputs!$D$4:$AG$150,0,MATCH(K$2,Inputs!$D$2:$AG$2,0))))=0,"",SUMIFS(INDEX(Inputs!$D$4:$AG$150,0,MATCH(K$2,Inputs!$D$2:$AG$2,0)),Inputs!$B$4:$B$150,$B54)/1000) -> 4632 | L54: =IF(SUMPRODUCT((Inputs!$B$4:$B$150=$B54)*ISNUMBER(INDEX(Inputs!$D$4:$AG$150,0,MATCH(L$2,Inputs!$D$2:$AG$2,0))))=0,"",SUMIFS(INDEX(Inputs!$D$4:$AG$150,0,MATCH(L$2,Inputs!$D$2:$AG$2,0)),Inputs!$B$4:$B$150,$B54)/1000) -> 605 | M54: =IF(COUNT(I54:L54)=4,SUM(I54:L54),"") -> 11463 | N54: =IF(SUMPRODUCT((Inputs!$B$4:$B$150=$B54)*ISNUMBER(INDEX(Inputs!$D$4:$AG$150,0,MATCH(N$2,Inputs!$D$2:$AG$2,0))))=0,"",SUMIFS(INDEX(Inputs!$D$4:$AG$150,0,MATCH(N$2,Inputs!$D$2:$AG$2,0)),Inputs!$B$4:$B$150,$B54)/1000) -> 2381 | O54: =IF(SUMPRODUCT((Inputs!$B$4:$B$150=$B54)*ISNUMBER(INDEX(Inputs!$D$4:$AG$150,0,MATCH(O$2,Inputs!$D$2:$AG$2,0))))=0,"",SUMIFS(INDEX(Inputs!$D$4:$AG$150,0,MATCH(O$2,Inputs!$D$2:$AG$2,0)),Inputs!$B$4:$B$150,$B54)/1000) -> 1382 | P54: =IF(SUMPRODUCT((Inputs!$B$4:$B$150=$B54)*ISNUMBER(INDEX(Inputs!$D$4:$AG$150,0,MATCH(P$2,Inputs!$D$2:$AG$2,0))))=0,"",SUMIFS(INDEX(Inputs!$D$4:$AG$150,0,MATCH(P$2,Inputs!$D$2:$AG$2,0)),Inputs!$B$4:$B$150,$B54)/1000) -> 1457 | Q54: =IF(SUMPRODUCT((Inputs!$B$4:$B$150=$B54)*ISNUMBER(INDEX(Inputs!$D$4:$AG$150,0,MATCH(Q$2,Inputs!$D$2:$AG$2,0))))=0,"",SUMIFS(INDEX(Inputs!$D$4:$AG$150,0,MATCH(Q$2,Inputs!$D$2:$AG$2,0)),Inputs!$B$4:$B$150,$B54)/1000) -> 1165 | R54: =IF(COUNT(N54:Q54)=4,SUM(N54:Q54),"") -> 6385 | S54: =IF(SUMPRODUCT((Inputs!$B$4:$B$150=$B54)*ISNUMBER(INDEX(Inputs!$D$4:$AG$150,0,MATCH(S$2,Inputs!$D$2:$AG$2,0))))=0,"",SUMIFS(INDEX(Inputs!$D$4:$AG$150,0,MATCH(S$2,Inputs!$D$2:$AG$2,0)),Inputs!$B$4:$B$150,$B54)/1000) -> 1842 | T54: =IF(SUMPRODUCT((Inputs!$B$4:$B$150=$B54)*ISNUMBER(INDEX(Inputs!$D$4:$AG$150,0,MATCH(T$2,Inputs!$D$2:$AG$2,0))))=0,"",SUMIFS(INDEX(Inputs!$D$4:$AG$150,0,MATCH(T$2,Inputs!$D$2:$AG$2,0)),Inputs!$B$4:$B$150,$B54)/1000) -> 1744 | U54: =IF(SUMPRODUCT((Inputs!$B$4:$B$150=$B54)*ISNUMBER(INDEX(Inputs!$D$4:$AG$150,0,MATCH(U$2,Inputs!$D$2:$AG$2,0))))=0,"",SUMIFS(INDEX(Inputs!$D$4:$AG$150,0,MATCH(U$2,Inputs!$D$2:$AG$2,0)),Inputs!$B$4:$B$150,$B54)/1000) -> 1481 | V54: =IF(SUMPRODUCT((Inputs!$B$4:$B$150=$B54)*ISNUMBER(INDEX(Inputs!$D$4:$AG$150,0,MATCH(V$2,Inputs!$D$2:$AG$2,0))))=0,"",SUMIFS(INDEX(Inputs!$D$4:$AG$150,0,MATCH(V$2,Inputs!$D$2:$AG$2,0)),Inputs!$B$4:$B$150,$B54)/1000) -> 1127 | W54: =IF(COUNT(S54:V54)=4,SUM(S54:V54),"") -> 6194 | X54: =IF(SUMPRODUCT((Inputs!$B$4:$B$150=$B54)*ISNUMBER(INDEX(Inputs!$D$4:$AG$150,0,MATCH(X$2,Inputs!$D$2:$AG$2,0))))=0,"",SUMIFS(INDEX(Inputs!$D$4:$AG$150,0,MATCH(X$2,Inputs!$D$2:$AG$2,0)),Inputs!$B$4:$B$150,$B54)/1000) -> 1369 | Y54: =IF(SUMPRODUCT((Inputs!$B$4:$B$150=$B54)*ISNUMBER(INDEX(Inputs!$D$4:$AG$150,0,MATCH(Y$2,Inputs!$D$2:$AG$2,0))))=0,"",SUMIFS(INDEX(Inputs!$D$4:$AG$150,0,MATCH(Y$2,Inputs!$D$2:$AG$2,0)),Inputs!$B$4:$B$150,$B54)/1000) -> 1462 | Z54: =IF(SUMPRODUCT((Inputs!$B$4:$B$150=$B54)*ISNUMBER(INDEX(Inputs!$D$4:$AG$150,0,MATCH(Z$2,Inputs!$D$2:$AG$2,0))))=0,"",SUMIFS(INDEX(Inputs!$D$4:$AG$150,0,MATCH(Z$2,Inputs!$D$2:$AG$2,0)),Inputs!$B$4:$B$150,$B54)/1000) -> 1267 | AA54: =IF(SUMPRODUCT((Inputs!$B$4:$B$150=$B54)*ISNUMBER(INDEX(Inputs!$D$4:$AG$150,0,MATCH(AA$2,Inputs!$D$2:$AG$2,0))))=0,"",SUMIFS(INDEX(Inputs!$D$4:$AG$150,0,MATCH(AA$2,Inputs!$D$2:$AG$2,0)),Inputs!$B$4:$B$150,$B54)/1000) -> 966 | AB54: =IF(COUNT(X54:AA54)=4,SUM(X54:AA54),"") -> 5064 | AC54: =IF(SUMPRODUCT((Inputs!$B$4:$B$150=$B54)*ISNUMBER(INDEX(Inputs!$D$4:$AG$150,0,MATCH(AC$2,Inputs!$D$2:$AG$2,0))))=0,"",SUMIFS(INDEX(Inputs!$D$4:$AG$150,0,MATCH(AC$2,Inputs!$D$2:$AG$2,0)),Inputs!$B$4:$B$150,$B54)/1000) -> 1369 | AD54: =IF(SUMPRODUCT((Inputs!$B$4:$B$150=$B54)*ISNUMBER(INDEX(Inputs!$D$4:$AG$150,0,MATCH(AD$2,Inputs!$D$2:$AG$2,0))))=0,"",SUMIFS(INDEX(Inputs!$D$4:$AG$150,0,MATCH(AD$2,Inputs!$D$2:$AG$2,0)),Inputs!$B$4:$B$150,$B54)/1000) -> 893 | AE54: =IF(SUMPRODUCT((Inputs!$B$4:$B$150=$B54)*ISNUMBER(INDEX(Inputs!$D$4:$AG$150,0,MATCH(AE$2,Inputs!$D$2:$AG$2,0))))=0,"",SUMIFS(INDEX(Inputs!$D$4:$AG$150,0,MATCH(AE$2,Inputs!$D$2:$AG$2,0)),Inputs!$B$4:$B$150,$B54)/1000) | AF54: =IF(SUMPRODUCT((Inputs!$B$4:$B$150=$B54)*ISNUMBER(INDEX(Inputs!$D$4:$AG$150,0,MATCH(AF$2,Inputs!$D$2:$AG$2,0))))=0,"",SUMIFS(INDEX(Inputs!$D$4:$AG$150,0,MATCH(AF$2,Inputs!$D$2:$AG$2,0)),Inputs!$B$4:$B$150,$B54)/1000) | AG54: =IF(COUNT(AC54:AF54)=4,SUM(AC54:AF54),"")
B55: 47 | C55: Outras receitas (USD) | D55: =IF(SUMPRODUCT((Inputs!$B$4:$B$150=$B55)*ISNUMBER(INDEX(Inputs!$D$4:$AG$150,0,MATCH(D$2,Inputs!$D$2:$AG$2,0))))=0,"",SUMIFS(INDEX(Inputs!$D$4:$AG$150,0,MATCH(D$2,Inputs!$D$2:$AG$2,0)),Inputs!$B$4:$B$150,$B55)/1000) | E55: =IF(SUMPRODUCT((Inputs!$B$4:$B$150=$B55)*ISNUMBER(INDEX(Inputs!$D$4:$AG$150,0,MATCH(E$2,Inputs!$D$2:$AG$2,0))))=0,"",SUMIFS(INDEX(Inputs!$D$4:$AG$150,0,MATCH(E$2,Inputs!$D$2:$AG$2,0)),Inputs!$B$4:$B$150,$B55)/1000) | F55: =IF(SUMPRODUCT((Inputs!$B$4:$B$150=$B55)*ISNUMBER(INDEX(Inputs!$D$4:$AG$150,0,MATCH(F$2,Inputs!$D$2:$AG$2,0))))=0,"",SUMIFS(INDEX(Inputs!$D$4:$AG$150,0,MATCH(F$2,Inputs!$D$2:$AG$2,0)),Inputs!$B$4:$B$150,$B55)/1000) | G55: =IF(SUMPRODUCT((Inputs!$B$4:$B$150=$B55)*ISNUMBER(INDEX(Inputs!$D$4:$AG$150,0,MATCH(G$2,Inputs!$D$2:$AG$2,0))))=0,"",SUMIFS(INDEX(Inputs!$D$4:$AG$150,0,MATCH(G$2,Inputs!$D$2:$AG$2,0)),Inputs!$B$4:$B$150,$B55)/1000) | H55: =IF(COUNT(D55:G55)=4,SUM(D55:G55),"") | I55: =IF(SUMPRODUCT((Inputs!$B$4:$B$150=$B55)*ISNUMBER(INDEX(Inputs!$D$4:$AG$150,0,MATCH(I$2,Inputs!$D$2:$AG$2,0))))=0,"",SUMIFS(INDEX(Inputs!$D$4:$AG$150,0,MATCH(I$2,Inputs!$D$2:$AG$2,0)),Inputs!$B$4:$B$150,$B55)/1000) -> 228 | J55: =IF(SUMPRODUCT((Inputs!$B$4:$B$150=$B55)*ISNUMBER(INDEX(Inputs!$D$4:$AG$150,0,MATCH(J$2,Inputs!$D$2:$AG$2,0))))=0,"",SUMIFS(INDEX(Inputs!$D$4:$AG$150,0,MATCH(J$2,Inputs!$D$2:$AG$2,0)),Inputs!$B$4:$B$150,$B55)/1000) -> 728 | K55: =IF(SUMPRODUCT((Inputs!$B$4:$B$150=$B55)*ISNUMBER(INDEX(Inputs!$D$4:$AG$150,0,MATCH(K$2,Inputs!$D$2:$AG$2,0))))=0,"",SUMIFS(INDEX(Inputs!$D$4:$AG$150,0,MATCH(K$2,Inputs!$D$2:$AG$2,0)),Inputs!$B$4:$B$150,$B55)/1000) -> 926 | L55: =IF(SUMPRODUCT((Inputs!$B$4:$B$150=$B55)*ISNUMBER(INDEX(Inputs!$D$4:$AG$150,0,MATCH(L$2,Inputs!$D$2:$AG$2,0))))=0,"",SUMIFS(INDEX(Inputs!$D$4:$AG$150,0,MATCH(L$2,Inputs!$D$2:$AG$2,0)),Inputs!$B$4:$B$150,$B55)/1000) -> 1660 | M55: =IF(COUNT(I55:L55)=4,SUM(I55:L55),"") -> 3542 | N55: =IF(SUMPRODUCT((Inputs!$B$4:$B$150=$B55)*ISNUMBER(INDEX(Inputs!$D$4:$AG$150,0,MATCH(N$2,Inputs!$D$2:$AG$2,0))))=0,"",SUMIFS(INDEX(Inputs!$D$4:$AG$150,0,MATCH(N$2,Inputs!$D$2:$AG$2,0)),Inputs!$B$4:$B$150,$B55)/1000) -> 539 | O55: =IF(SUMPRODUCT((Inputs!$B$4:$B$150=$B55)*ISNUMBER(INDEX(Inputs!$D$4:$AG$150,0,MATCH(O$2,Inputs!$D$2:$AG$2,0))))=0,"",SUMIFS(INDEX(Inputs!$D$4:$AG$150,0,MATCH(O$2,Inputs!$D$2:$AG$2,0)),Inputs!$B$4:$B$150,$B55)/1000) -> 737 | P55: =IF(SUMPRODUCT((Inputs!$B$4:$B$150=$B55)*ISNUMBER(INDEX(Inputs!$D$4:$AG$150,0,MATCH(P$2,Inputs!$D$2:$AG$2,0))))=0,"",SUMIFS(INDEX(Inputs!$D$4:$AG$150,0,MATCH(P$2,Inputs!$D$2:$AG$2,0)),Inputs!$B$4:$B$150,$B55)/1000) -> 733 | Q55: =IF(SUMPRODUCT((Inputs!$B$4:$B$150=$B55)*ISNUMBER(INDEX(Inputs!$D$4:$AG$150,0,MATCH(Q$2,Inputs!$D$2:$AG$2,0))))=0,"",SUMIFS(INDEX(Inputs!$D$4:$AG$150,0,MATCH(Q$2,Inputs!$D$2:$AG$2,0)),Inputs!$B$4:$B$150,$B55)/1000) -> 1491 | R55: =IF(COUNT(N55:Q55)=4,SUM(N55:Q55),"") -> 3500 | S55: =IF(SUMPRODUCT((Inputs!$B$4:$B$150=$B55)*ISNUMBER(INDEX(Inputs!$D$4:$AG$150,0,MATCH(S$2,Inputs!$D$2:$AG$2,0))))=0,"",SUMIFS(INDEX(Inputs!$D$4:$AG$150,0,MATCH(S$2,Inputs!$D$2:$AG$2,0)),Inputs!$B$4:$B$150,$B55)/1000) -> 830 | T55: =IF(SUMPRODUCT((Inputs!$B$4:$B$150=$B55)*ISNUMBER(INDEX(Inputs!$D$4:$AG$150,0,MATCH(T$2,Inputs!$D$2:$AG$2,0))))=0,"",SUMIFS(INDEX(Inputs!$D$4:$AG$150,0,MATCH(T$2,Inputs!$D$2:$AG$2,0)),Inputs!$B$4:$B$150,$B55)/1000) -> 1330 | U55: =IF(SUMPRODUCT((Inputs!$B$4:$B$150=$B55)*ISNUMBER(INDEX(Inputs!$D$4:$AG$150,0,MATCH(U$2,Inputs!$D$2:$AG$2,0))))=0,"",SUMIFS(INDEX(Inputs!$D$4:$AG$150,0,MATCH(U$2,Inputs!$D$2:$AG$2,0)),Inputs!$B$4:$B$150,$B55)/1000) -> 743 | V55: =IF(SUMPRODUCT((Inputs!$B$4:$B$150=$B55)*ISNUMBER(INDEX(Inputs!$D$4:$AG$150,0,MATCH(V$2,Inputs!$D$2:$AG$2,0))))=0,"",SUMIFS(INDEX(Inputs!$D$4:$AG$150,0,MATCH(V$2,Inputs!$D$2:$AG$2,0)),Inputs!$B$4:$B$150,$B55)/1000) -> 1241 | W55: =IF(COUNT(S55:V55)=4,SUM(S55:V55),"") -> 4144 | X55: =IF(SUMPRODUCT((Inputs!$B$4:$B$150=$B55)*ISNUMBER(INDEX(Inputs!$D$4:$AG$150,0,MATCH(X$2,Inputs!$D$2:$AG$2,0))))=0,"",SUMIFS(INDEX(Inputs!$D$4:$AG$150,0,MATCH(X$2,Inputs!$D$2:$AG$2,0)),Inputs!$B$4:$B$150,$B55)/1000) -> 703 | Y55: =IF(SUMPRODUCT((Inputs!$B$4:$B$150=$B55)*ISNUMBER(INDEX(Inputs!$D$4:$AG$150,0,MATCH(Y$2,Inputs!$D$2:$AG$2,0))))=0,"",SUMIFS(INDEX(Inputs!$D$4:$AG$150,0,MATCH(Y$2,Inputs!$D$2:$AG$2,0)),Inputs!$B$4:$B$150,$B55)/1000) -> 567 | Z55: =IF(SUMPRODUCT((Inputs!$B$4:$B$150=$B55)*ISNUMBER(INDEX(Inputs!$D$4:$AG$150,0,MATCH(Z$2,Inputs!$D$2:$AG$2,0))))=0,"",SUMIFS(INDEX(Inputs!$D$4:$AG$150,0,MATCH(Z$2,Inputs!$D$2:$AG$2,0)),Inputs!$B$4:$B$150,$B55)/1000) -> 696 | AA55: =IF(SUMPRODUCT((Inputs!$B$4:$B$150=$B55)*ISNUMBER(INDEX(Inputs!$D$4:$AG$150,0,MATCH(AA$2,Inputs!$D$2:$AG$2,0))))=0,"",SUMIFS(INDEX(Inputs!$D$4:$AG$150,0,MATCH(AA$2,Inputs!$D$2:$AG$2,0)),Inputs!$B$4:$B$150,$B55)/1000) -> 1303 | AB55: =IF(COUNT(X55:AA55)=4,SUM(X55:AA55),"") -> 3269 | AC55: =IF(SUMPRODUCT((Inputs!$B$4:$B$150=$B55)*ISNUMBER(INDEX(Inputs!$D$4:$AG$150,0,MATCH(AC$2,Inputs!$D$2:$AG$2,0))))=0,"",SUMIFS(INDEX(Inputs!$D$4:$AG$150,0,MATCH(AC$2,Inputs!$D$2:$AG$2,0)),Inputs!$B$4:$B$150,$B55)/1000) -> 608 | AD55: =IF(SUMPRODUCT((Inputs!$B$4:$B$150=$B55)*ISNUMBER(INDEX(Inputs!$D$4:$AG$150,0,MATCH(AD$2,Inputs!$D$2:$AG$2,0))))=0,"",SUMIFS(INDEX(Inputs!$D$4:$AG$150,0,MATCH(AD$2,Inputs!$D$2:$AG$2,0)),Inputs!$B$4:$B$150,$B55)/1000) -> 595 | AE55: =IF(SUMPRODUCT((Inputs!$B$4:$B$150=$B55)*ISNUMBER(INDEX(Inputs!$D$4:$AG$150,0,MATCH(AE$2,Inputs!$D$2:$AG$2,0))))=0,"",SUMIFS(INDEX(Inputs!$D$4:$AG$150,0,MATCH(AE$2,Inputs!$D$2:$AG$2,0)),Inputs!$B$4:$B$150,$B55)/1000) | AF55: =IF(SUMPRODUCT((Inputs!$B$4:$B$150=$B55)*ISNUMBER(INDEX(Inputs!$D$4:$AG$150,0,MATCH(AF$2,Inputs!$D$2:$AG$2,0))))=0,"",SUMIFS(INDEX(Inputs!$D$4:$AG$150,0,MATCH(AF$2,Inputs!$D$2:$AG$2,0)),Inputs!$B$4:$B$150,$B55)/1000) | AG55: =IF(COUNT(AC55:AF55)=4,SUM(AC55:AF55),"")
B56: 48 | C56: Lucro Upstream (EUA + exterior, USD) | D56: =IF(SUMPRODUCT((Inputs!$B$4:$B$150=$B56)*ISNUMBER(INDEX(Inputs!$D$4:$AG$150,0,MATCH(D$2,Inputs!$D$2:$AG$2,0))))=0,"",SUMIFS(INDEX(Inputs!$D$4:$AG$150,0,MATCH(D$2,Inputs!$D$2:$AG$2,0)),Inputs!$B$4:$B$150,$B56)/1000) -> 2554 | E56: =IF(SUMPRODUCT((Inputs!$B$4:$B$150=$B56)*ISNUMBER(INDEX(Inputs!$D$4:$AG$150,0,MATCH(E$2,Inputs!$D$2:$AG$2,0))))=0,"",SUMIFS(INDEX(Inputs!$D$4:$AG$150,0,MATCH(E$2,Inputs!$D$2:$AG$2,0)),Inputs!$B$4:$B$150,$B56)/1000) -> 3185 | F56: =IF(SUMPRODUCT((Inputs!$B$4:$B$150=$B56)*ISNUMBER(INDEX(Inputs!$D$4:$AG$150,0,MATCH(F$2,Inputs!$D$2:$AG$2,0))))=0,"",SUMIFS(INDEX(Inputs!$D$4:$AG$150,0,MATCH(F$2,Inputs!$D$2:$AG$2,0)),Inputs!$B$4:$B$150,$B56)/1000) -> 3951 | G56: =IF(SUMPRODUCT((Inputs!$B$4:$B$150=$B56)*ISNUMBER(INDEX(Inputs!$D$4:$AG$150,0,MATCH(G$2,Inputs!$D$2:$AG$2,0))))=0,"",SUMIFS(INDEX(Inputs!$D$4:$AG$150,0,MATCH(G$2,Inputs!$D$2:$AG$2,0)),Inputs!$B$4:$B$150,$B56)/1000) | H56: =IF(COUNT(D56:G56)=4,SUM(D56:G56),"") | I56: =IF(SUMPRODUCT((Inputs!$B$4:$B$150=$B56)*ISNUMBER(INDEX(Inputs!$D$4:$AG$150,0,MATCH(I$2,Inputs!$D$2:$AG$2,0))))=0,"",SUMIFS(INDEX(Inputs!$D$4:$AG$150,0,MATCH(I$2,Inputs!$D$2:$AG$2,0)),Inputs!$B$4:$B$150,$B56)/1000) -> 4488 | J56: =IF(SUMPRODUCT((Inputs!$B$4:$B$150=$B56)*ISNUMBER(INDEX(Inputs!$D$4:$AG$150,0,MATCH(J$2,Inputs!$D$2:$AG$2,0))))=0,"",SUMIFS(INDEX(Inputs!$D$4:$AG$150,0,MATCH(J$2,Inputs!$D$2:$AG$2,0)),Inputs!$B$4:$B$150,$B56)/1000) -> 11371 | K56: =IF(SUMPRODUCT((Inputs!$B$4:$B$150=$B56)*ISNUMBER(INDEX(Inputs!$D$4:$AG$150,0,MATCH(K$2,Inputs!$D$2:$AG$2,0))))=0,"",SUMIFS(INDEX(Inputs!$D$4:$AG$150,0,MATCH(K$2,Inputs!$D$2:$AG$2,0)),Inputs!$B$4:$B$150,$B56)/1000) -> 12419 | L56: =IF(SUMPRODUCT((Inputs!$B$4:$B$150=$B56)*ISNUMBER(INDEX(Inputs!$D$4:$AG$150,0,MATCH(L$2,Inputs!$D$2:$AG$2,0))))=0,"",SUMIFS(INDEX(Inputs!$D$4:$AG$150,0,MATCH(L$2,Inputs!$D$2:$AG$2,0)),Inputs!$B$4:$B$150,$B56)/1000) -> 8201 | M56: =IF(COUNT(I56:L56)=4,SUM(I56:L56),"") -> 36479 | N56: =IF(SUMPRODUCT((Inputs!$B$4:$B$150=$B56)*ISNUMBER(INDEX(Inputs!$D$4:$AG$150,0,MATCH(N$2,Inputs!$D$2:$AG$2,0))))=0,"",SUMIFS(INDEX(Inputs!$D$4:$AG$150,0,MATCH(N$2,Inputs!$D$2:$AG$2,0)),Inputs!$B$4:$B$150,$B56)/1000) -> 6457 | O56: =IF(SUMPRODUCT((Inputs!$B$4:$B$150=$B56)*ISNUMBER(INDEX(Inputs!$D$4:$AG$150,0,MATCH(O$2,Inputs!$D$2:$AG$2,0))))=0,"",SUMIFS(INDEX(Inputs!$D$4:$AG$150,0,MATCH(O$2,Inputs!$D$2:$AG$2,0)),Inputs!$B$4:$B$150,$B56)/1000) -> 4577 | P56: =IF(SUMPRODUCT((Inputs!$B$4:$B$150=$B56)*ISNUMBER(INDEX(Inputs!$D$4:$AG$150,0,MATCH(P$2,Inputs!$D$2:$AG$2,0))))=0,"",SUMIFS(INDEX(Inputs!$D$4:$AG$150,0,MATCH(P$2,Inputs!$D$2:$AG$2,0)),Inputs!$B$4:$B$150,$B56)/1000) -> 6125 | Q56: =IF(SUMPRODUCT((Inputs!$B$4:$B$150=$B56)*ISNUMBER(INDEX(Inputs!$D$4:$AG$150,0,MATCH(Q$2,Inputs!$D$2:$AG$2,0))))=0,"",SUMIFS(INDEX(Inputs!$D$4:$AG$150,0,MATCH(Q$2,Inputs!$D$2:$AG$2,0)),Inputs!$B$4:$B$150,$B56)/1000) -> 4149 | R56: =IF(COUNT(N56:Q56)=4,SUM(N56:Q56),"") -> 21308 | S56: =IF(SUMPRODUCT((Inputs!$B$4:$B$150=$B56)*ISNUMBER(INDEX(Inputs!$D$4:$AG$150,0,MATCH(S$2,Inputs!$D$2:$AG$2,0))))=0,"",SUMIFS(INDEX(Inputs!$D$4:$AG$150,0,MATCH(S$2,Inputs!$D$2:$AG$2,0)),Inputs!$B$4:$B$150,$B56)/1000) -> 5660 | T56: =IF(SUMPRODUCT((Inputs!$B$4:$B$150=$B56)*ISNUMBER(INDEX(Inputs!$D$4:$AG$150,0,MATCH(T$2,Inputs!$D$2:$AG$2,0))))=0,"",SUMIFS(INDEX(Inputs!$D$4:$AG$150,0,MATCH(T$2,Inputs!$D$2:$AG$2,0)),Inputs!$B$4:$B$150,$B56)/1000) -> 7074 | U56: =IF(SUMPRODUCT((Inputs!$B$4:$B$150=$B56)*ISNUMBER(INDEX(Inputs!$D$4:$AG$150,0,MATCH(U$2,Inputs!$D$2:$AG$2,0))))=0,"",SUMIFS(INDEX(Inputs!$D$4:$AG$150,0,MATCH(U$2,Inputs!$D$2:$AG$2,0)),Inputs!$B$4:$B$150,$B56)/1000) -> 6158 | V56: =IF(SUMPRODUCT((Inputs!$B$4:$B$150=$B56)*ISNUMBER(INDEX(Inputs!$D$4:$AG$150,0,MATCH(V$2,Inputs!$D$2:$AG$2,0))))=0,"",SUMIFS(INDEX(Inputs!$D$4:$AG$150,0,MATCH(V$2,Inputs!$D$2:$AG$2,0)),Inputs!$B$4:$B$150,$B56)/1000) -> 6498 | W56: =IF(COUNT(S56:V56)=4,SUM(S56:V56),"") -> 25390 | X56: =IF(SUMPRODUCT((Inputs!$B$4:$B$150=$B56)*ISNUMBER(INDEX(Inputs!$D$4:$AG$150,0,MATCH(X$2,Inputs!$D$2:$AG$2,0))))=0,"",SUMIFS(INDEX(Inputs!$D$4:$AG$150,0,MATCH(X$2,Inputs!$D$2:$AG$2,0)),Inputs!$B$4:$B$150,$B56)/1000) -> 6756 | Y56: =IF(SUMPRODUCT((Inputs!$B$4:$B$150=$B56)*ISNUMBER(INDEX(Inputs!$D$4:$AG$150,0,MATCH(Y$2,Inputs!$D$2:$AG$2,0))))=0,"",SUMIFS(INDEX(Inputs!$D$4:$AG$150,0,MATCH(Y$2,Inputs!$D$2:$AG$2,0)),Inputs!$B$4:$B$150,$B56)/1000) -> 5402 | Z56: =IF(SUMPRODUCT((Inputs!$B$4:$B$150=$B56)*ISNUMBER(INDEX(Inputs!$D$4:$AG$150,0,MATCH(Z$2,Inputs!$D$2:$AG$2,0))))=0,"",SUMIFS(INDEX(Inputs!$D$4:$AG$150,0,MATCH(Z$2,Inputs!$D$2:$AG$2,0)),Inputs!$B$4:$B$150,$B56)/1000) -> 5679 | AA56: =IF(SUMPRODUCT((Inputs!$B$4:$B$150=$B56)*ISNUMBER(INDEX(Inputs!$D$4:$AG$150,0,MATCH(AA$2,Inputs!$D$2:$AG$2,0))))=0,"",SUMIFS(INDEX(Inputs!$D$4:$AG$150,0,MATCH(AA$2,Inputs!$D$2:$AG$2,0)),Inputs!$B$4:$B$150,$B56)/1000) -> 3517 | AB56: =IF(COUNT(X56:AA56)=4,SUM(X56:AA56),"") -> 21354 | AC56: =IF(SUMPRODUCT((Inputs!$B$4:$B$150=$B56)*ISNUMBER(INDEX(Inputs!$D$4:$AG$150,0,MATCH(AC$2,Inputs!$D$2:$AG$2,0))))=0,"",SUMIFS(INDEX(Inputs!$D$4:$AG$150,0,MATCH(AC$2,Inputs!$D$2:$AG$2,0)),Inputs!$B$4:$B$150,$B56)/1000) -> 5737 | AD56: =IF(SUMPRODUCT((Inputs!$B$4:$B$150=$B56)*ISNUMBER(INDEX(Inputs!$D$4:$AG$150,0,MATCH(AD$2,Inputs!$D$2:$AG$2,0))))=0,"",SUMIFS(INDEX(Inputs!$D$4:$AG$150,0,MATCH(AD$2,Inputs!$D$2:$AG$2,0)),Inputs!$B$4:$B$150,$B56)/1000) -> 7927 | AE56: =IF(SUMPRODUCT((Inputs!$B$4:$B$150=$B56)*ISNUMBER(INDEX(Inputs!$D$4:$AG$150,0,MATCH(AE$2,Inputs!$D$2:$AG$2,0))))=0,"",SUMIFS(INDEX(Inputs!$D$4:$AG$150,0,MATCH(AE$2,Inputs!$D$2:$AG$2,0)),Inputs!$B$4:$B$150,$B56)/1000) | AF56: =IF(SUMPRODUCT((Inputs!$B$4:$B$150=$B56)*ISNUMBER(INDEX(Inputs!$D$4:$AG$150,0,MATCH(AF$2,Inputs!$D$2:$AG$2,0))))=0,"",SUMIFS(INDEX(Inputs!$D$4:$AG$150,0,MATCH(AF$2,Inputs!$D$2:$AG$2,0)),Inputs!$B$4:$B$150,$B56)/1000) | AG56: =IF(COUNT(AC56:AF56)=4,SUM(AC56:AF56),"")
B57: 49 | C57: Lucro Energy Products (USD) | D57: =IF(SUMPRODUCT((Inputs!$B$4:$B$150=$B57)*ISNUMBER(INDEX(Inputs!$D$4:$AG$150,0,MATCH(D$2,Inputs!$D$2:$AG$2,0))))=0,"",SUMIFS(INDEX(Inputs!$D$4:$AG$150,0,MATCH(D$2,Inputs!$D$2:$AG$2,0)),Inputs!$B$4:$B$150,$B57)/1000) | E57: =IF(SUMPRODUCT((Inputs!$B$4:$B$150=$B57)*ISNUMBER(INDEX(Inputs!$D$4:$AG$150,0,MATCH(E$2,Inputs!$D$2:$AG$2,0))))=0,"",SUMIFS(INDEX(Inputs!$D$4:$AG$150,0,MATCH(E$2,Inputs!$D$2:$AG$2,0)),Inputs!$B$4:$B$150,$B57)/1000) | F57: =IF(SUMPRODUCT((Inputs!$B$4:$B$150=$B57)*ISNUMBER(INDEX(Inputs!$D$4:$AG$150,0,MATCH(F$2,Inputs!$D$2:$AG$2,0))))=0,"",SUMIFS(INDEX(Inputs!$D$4:$AG$150,0,MATCH(F$2,Inputs!$D$2:$AG$2,0)),Inputs!$B$4:$B$150,$B57)/1000) | G57: =IF(SUMPRODUCT((Inputs!$B$4:$B$150=$B57)*ISNUMBER(INDEX(Inputs!$D$4:$AG$150,0,MATCH(G$2,Inputs!$D$2:$AG$2,0))))=0,"",SUMIFS(INDEX(Inputs!$D$4:$AG$150,0,MATCH(G$2,Inputs!$D$2:$AG$2,0)),Inputs!$B$4:$B$150,$B57)/1000) | H57: =IF(COUNT(D57:G57)=4,SUM(D57:G57),"") | I57: =IF(SUMPRODUCT((Inputs!$B$4:$B$150=$B57)*ISNUMBER(INDEX(Inputs!$D$4:$AG$150,0,MATCH(I$2,Inputs!$D$2:$AG$2,0))))=0,"",SUMIFS(INDEX(Inputs!$D$4:$AG$150,0,MATCH(I$2,Inputs!$D$2:$AG$2,0)),Inputs!$B$4:$B$150,$B57)/1000) -> -195 | J57: =IF(SUMPRODUCT((Inputs!$B$4:$B$150=$B57)*ISNUMBER(INDEX(Inputs!$D$4:$AG$150,0,MATCH(J$2,Inputs!$D$2:$AG$2,0))))=0,"",SUMIFS(INDEX(Inputs!$D$4:$AG$150,0,MATCH(J$2,Inputs!$D$2:$AG$2,0)),Inputs!$B$4:$B$150,$B57)/1000) -> 5272 | K57: =IF(SUMPRODUCT((Inputs!$B$4:$B$150=$B57)*ISNUMBER(INDEX(Inputs!$D$4:$AG$150,0,MATCH(K$2,Inputs!$D$2:$AG$2,0))))=0,"",SUMIFS(INDEX(Inputs!$D$4:$AG$150,0,MATCH(K$2,Inputs!$D$2:$AG$2,0)),Inputs!$B$4:$B$150,$B57)/1000) -> 5819 | L57: =IF(SUMPRODUCT((Inputs!$B$4:$B$150=$B57)*ISNUMBER(INDEX(Inputs!$D$4:$AG$150,0,MATCH(L$2,Inputs!$D$2:$AG$2,0))))=0,"",SUMIFS(INDEX(Inputs!$D$4:$AG$150,0,MATCH(L$2,Inputs!$D$2:$AG$2,0)),Inputs!$B$4:$B$150,$B57)/1000) -> 4070 | M57: =IF(COUNT(I57:L57)=4,SUM(I57:L57),"") -> 14966 | N57: =IF(SUMPRODUCT((Inputs!$B$4:$B$150=$B57)*ISNUMBER(INDEX(Inputs!$D$4:$AG$150,0,MATCH(N$2,Inputs!$D$2:$AG$2,0))))=0,"",SUMIFS(INDEX(Inputs!$D$4:$AG$150,0,MATCH(N$2,Inputs!$D$2:$AG$2,0)),Inputs!$B$4:$B$150,$B57)/1000) -> 4183 | O57: =IF(SUMPRODUCT((Inputs!$B$4:$B$150=$B57)*ISNUMBER(INDEX(Inputs!$D$4:$AG$150,0,MATCH(O$2,Inputs!$D$2:$AG$2,0))))=0,"",SUMIFS(INDEX(Inputs!$D$4:$AG$150,0,MATCH(O$2,Inputs!$D$2:$AG$2,0)),Inputs!$B$4:$B$150,$B57)/1000) -> 2310 | P57: =IF(SUMPRODUCT((Inputs!$B$4:$B$150=$B57)*ISNUMBER(INDEX(Inputs!$D$4:$AG$150,0,MATCH(P$2,Inputs!$D$2:$AG$2,0))))=0,"",SUMIFS(INDEX(Inputs!$D$4:$AG$150,0,MATCH(P$2,Inputs!$D$2:$AG$2,0)),Inputs!$B$4:$B$150,$B57)/1000) -> 2442 | Q57: =IF(SUMPRODUCT((Inputs!$B$4:$B$150=$B57)*ISNUMBER(INDEX(Inputs!$D$4:$AG$150,0,MATCH(Q$2,Inputs!$D$2:$AG$2,0))))=0,"",SUMIFS(INDEX(Inputs!$D$4:$AG$150,0,MATCH(Q$2,Inputs!$D$2:$AG$2,0)),Inputs!$B$4:$B$150,$B57)/1000) -> 3207 | R57: =IF(COUNT(N57:Q57)=4,SUM(N57:Q57),"") -> 12142 | S57: =IF(SUMPRODUCT((Inputs!$B$4:$B$150=$B57)*ISNUMBER(INDEX(Inputs!$D$4:$AG$150,0,MATCH(S$2,Inputs!$D$2:$AG$2,0))))=0,"",SUMIFS(INDEX(Inputs!$D$4:$AG$150,0,MATCH(S$2,Inputs!$D$2:$AG$2,0)),Inputs!$B$4:$B$150,$B57)/1000) -> 1376 | T57: =IF(SUMPRODUCT((Inputs!$B$4:$B$150=$B57)*ISNUMBER(INDEX(Inputs!$D$4:$AG$150,0,MATCH(T$2,Inputs!$D$2:$AG$2,0))))=0,"",SUMIFS(INDEX(Inputs!$D$4:$AG$150,0,MATCH(T$2,Inputs!$D$2:$AG$2,0)),Inputs!$B$4:$B$150,$B57)/1000) -> 946 | U57: =IF(SUMPRODUCT((Inputs!$B$4:$B$150=$B57)*ISNUMBER(INDEX(Inputs!$D$4:$AG$150,0,MATCH(U$2,Inputs!$D$2:$AG$2,0))))=0,"",SUMIFS(INDEX(Inputs!$D$4:$AG$150,0,MATCH(U$2,Inputs!$D$2:$AG$2,0)),Inputs!$B$4:$B$150,$B57)/1000) -> 1309 | V57: =IF(SUMPRODUCT((Inputs!$B$4:$B$150=$B57)*ISNUMBER(INDEX(Inputs!$D$4:$AG$150,0,MATCH(V$2,Inputs!$D$2:$AG$2,0))))=0,"",SUMIFS(INDEX(Inputs!$D$4:$AG$150,0,MATCH(V$2,Inputs!$D$2:$AG$2,0)),Inputs!$B$4:$B$150,$B57)/1000) -> 402 | W57: =IF(COUNT(S57:V57)=4,SUM(S57:V57),"") -> 4033 | X57: =IF(SUMPRODUCT((Inputs!$B$4:$B$150=$B57)*ISNUMBER(INDEX(Inputs!$D$4:$AG$150,0,MATCH(X$2,Inputs!$D$2:$AG$2,0))))=0,"",SUMIFS(INDEX(Inputs!$D$4:$AG$150,0,MATCH(X$2,Inputs!$D$2:$AG$2,0)),Inputs!$B$4:$B$150,$B57)/1000) -> 827 | Y57: =IF(SUMPRODUCT((Inputs!$B$4:$B$150=$B57)*ISNUMBER(INDEX(Inputs!$D$4:$AG$150,0,MATCH(Y$2,Inputs!$D$2:$AG$2,0))))=0,"",SUMIFS(INDEX(Inputs!$D$4:$AG$150,0,MATCH(Y$2,Inputs!$D$2:$AG$2,0)),Inputs!$B$4:$B$150,$B57)/1000) -> 1366 | Z57: =IF(SUMPRODUCT((Inputs!$B$4:$B$150=$B57)*ISNUMBER(INDEX(Inputs!$D$4:$AG$150,0,MATCH(Z$2,Inputs!$D$2:$AG$2,0))))=0,"",SUMIFS(INDEX(Inputs!$D$4:$AG$150,0,MATCH(Z$2,Inputs!$D$2:$AG$2,0)),Inputs!$B$4:$B$150,$B57)/1000) -> 1840 | AA57: =IF(SUMPRODUCT((Inputs!$B$4:$B$150=$B57)*ISNUMBER(INDEX(Inputs!$D$4:$AG$150,0,MATCH(AA$2,Inputs!$D$2:$AG$2,0))))=0,"",SUMIFS(INDEX(Inputs!$D$4:$AG$150,0,MATCH(AA$2,Inputs!$D$2:$AG$2,0)),Inputs!$B$4:$B$150,$B57)/1000) -> 3390 | AB57: =IF(COUNT(X57:AA57)=4,SUM(X57:AA57),"") -> 7423 | AC57: =IF(SUMPRODUCT((Inputs!$B$4:$B$150=$B57)*ISNUMBER(INDEX(Inputs!$D$4:$AG$150,0,MATCH(AC$2,Inputs!$D$2:$AG$2,0))))=0,"",SUMIFS(INDEX(Inputs!$D$4:$AG$150,0,MATCH(AC$2,Inputs!$D$2:$AG$2,0)),Inputs!$B$4:$B$150,$B57)/1000) -> -1262 | AD57: =IF(SUMPRODUCT((Inputs!$B$4:$B$150=$B57)*ISNUMBER(INDEX(Inputs!$D$4:$AG$150,0,MATCH(AD$2,Inputs!$D$2:$AG$2,0))))=0,"",SUMIFS(INDEX(Inputs!$D$4:$AG$150,0,MATCH(AD$2,Inputs!$D$2:$AG$2,0)),Inputs!$B$4:$B$150,$B57)/1000) -> 5465 | AE57: =IF(SUMPRODUCT((Inputs!$B$4:$B$150=$B57)*ISNUMBER(INDEX(Inputs!$D$4:$AG$150,0,MATCH(AE$2,Inputs!$D$2:$AG$2,0))))=0,"",SUMIFS(INDEX(Inputs!$D$4:$AG$150,0,MATCH(AE$2,Inputs!$D$2:$AG$2,0)),Inputs!$B$4:$B$150,$B57)/1000) | AF57: =IF(SUMPRODUCT((Inputs!$B$4:$B$150=$B57)*ISNUMBER(INDEX(Inputs!$D$4:$AG$150,0,MATCH(AF$2,Inputs!$D$2:$AG$2,0))))=0,"",SUMIFS(INDEX(Inputs!$D$4:$AG$150,0,MATCH(AF$2,Inputs!$D$2:$AG$2,0)),Inputs!$B$4:$B$150,$B57)/1000) | AG57: =IF(COUNT(AC57:AF57)=4,SUM(AC57:AF57),"")
B58: 50 | C58: Lucro Chemical Products (USD) | D58: =IF(SUMPRODUCT((Inputs!$B$4:$B$150=$B58)*ISNUMBER(INDEX(Inputs!$D$4:$AG$150,0,MATCH(D$2,Inputs!$D$2:$AG$2,0))))=0,"",SUMIFS(INDEX(Inputs!$D$4:$AG$150,0,MATCH(D$2,Inputs!$D$2:$AG$2,0)),Inputs!$B$4:$B$150,$B58)/1000) | E58: =IF(SUMPRODUCT((Inputs!$B$4:$B$150=$B58)*ISNUMBER(INDEX(Inputs!$D$4:$AG$150,0,MATCH(E$2,Inputs!$D$2:$AG$2,0))))=0,"",SUMIFS(INDEX(Inputs!$D$4:$AG$150,0,MATCH(E$2,Inputs!$D$2:$AG$2,0)),Inputs!$B$4:$B$150,$B58)/1000) | F58: =IF(SUMPRODUCT((Inputs!$B$4:$B$150=$B58)*ISNUMBER(INDEX(Inputs!$D$4:$AG$150,0,MATCH(F$2,Inputs!$D$2:$AG$2,0))))=0,"",SUMIFS(INDEX(Inputs!$D$4:$AG$150,0,MATCH(F$2,Inputs!$D$2:$AG$2,0)),Inputs!$B$4:$B$150,$B58)/1000) | G58: =IF(SUMPRODUCT((Inputs!$B$4:$B$150=$B58)*ISNUMBER(INDEX(Inputs!$D$4:$AG$150,0,MATCH(G$2,Inputs!$D$2:$AG$2,0))))=0,"",SUMIFS(INDEX(Inputs!$D$4:$AG$150,0,MATCH(G$2,Inputs!$D$2:$AG$2,0)),Inputs!$B$4:$B$150,$B58)/1000) | H58: =IF(COUNT(D58:G58)=4,SUM(D58:G58),"") | I58: =IF(SUMPRODUCT((Inputs!$B$4:$B$150=$B58)*ISNUMBER(INDEX(Inputs!$D$4:$AG$150,0,MATCH(I$2,Inputs!$D$2:$AG$2,0))))=0,"",SUMIFS(INDEX(Inputs!$D$4:$AG$150,0,MATCH(I$2,Inputs!$D$2:$AG$2,0)),Inputs!$B$4:$B$150,$B58)/1000) -> 1406 | J58: =IF(SUMPRODUCT((Inputs!$B$4:$B$150=$B58)*ISNUMBER(INDEX(Inputs!$D$4:$AG$150,0,MATCH(J$2,Inputs!$D$2:$AG$2,0))))=0,"",SUMIFS(INDEX(Inputs!$D$4:$AG$150,0,MATCH(J$2,Inputs!$D$2:$AG$2,0)),Inputs!$B$4:$B$150,$B58)/1000) -> 1075 | K58: =IF(SUMPRODUCT((Inputs!$B$4:$B$150=$B58)*ISNUMBER(INDEX(Inputs!$D$4:$AG$150,0,MATCH(K$2,Inputs!$D$2:$AG$2,0))))=0,"",SUMIFS(INDEX(Inputs!$D$4:$AG$150,0,MATCH(K$2,Inputs!$D$2:$AG$2,0)),Inputs!$B$4:$B$150,$B58)/1000) -> 812 | L58: =IF(SUMPRODUCT((Inputs!$B$4:$B$150=$B58)*ISNUMBER(INDEX(Inputs!$D$4:$AG$150,0,MATCH(L$2,Inputs!$D$2:$AG$2,0))))=0,"",SUMIFS(INDEX(Inputs!$D$4:$AG$150,0,MATCH(L$2,Inputs!$D$2:$AG$2,0)),Inputs!$B$4:$B$150,$B58)/1000) -> 250 | M58: =IF(COUNT(I58:L58)=4,SUM(I58:L58),"") -> 3543 | N58: =IF(SUMPRODUCT((Inputs!$B$4:$B$150=$B58)*ISNUMBER(INDEX(Inputs!$D$4:$AG$150,0,MATCH(N$2,Inputs!$D$2:$AG$2,0))))=0,"",SUMIFS(INDEX(Inputs!$D$4:$AG$150,0,MATCH(N$2,Inputs!$D$2:$AG$2,0)),Inputs!$B$4:$B$150,$B58)/1000) -> 371 | O58: =IF(SUMPRODUCT((Inputs!$B$4:$B$150=$B58)*ISNUMBER(INDEX(Inputs!$D$4:$AG$150,0,MATCH(O$2,Inputs!$D$2:$AG$2,0))))=0,"",SUMIFS(INDEX(Inputs!$D$4:$AG$150,0,MATCH(O$2,Inputs!$D$2:$AG$2,0)),Inputs!$B$4:$B$150,$B58)/1000) -> 828 | P58: =IF(SUMPRODUCT((Inputs!$B$4:$B$150=$B58)*ISNUMBER(INDEX(Inputs!$D$4:$AG$150,0,MATCH(P$2,Inputs!$D$2:$AG$2,0))))=0,"",SUMIFS(INDEX(Inputs!$D$4:$AG$150,0,MATCH(P$2,Inputs!$D$2:$AG$2,0)),Inputs!$B$4:$B$150,$B58)/1000) -> 249 | Q58: =IF(SUMPRODUCT((Inputs!$B$4:$B$150=$B58)*ISNUMBER(INDEX(Inputs!$D$4:$AG$150,0,MATCH(Q$2,Inputs!$D$2:$AG$2,0))))=0,"",SUMIFS(INDEX(Inputs!$D$4:$AG$150,0,MATCH(Q$2,Inputs!$D$2:$AG$2,0)),Inputs!$B$4:$B$150,$B58)/1000) -> 189 | R58: =IF(COUNT(N58:Q58)=4,SUM(N58:Q58),"") -> 1637 | S58: =IF(SUMPRODUCT((Inputs!$B$4:$B$150=$B58)*ISNUMBER(INDEX(Inputs!$D$4:$AG$150,0,MATCH(S$2,Inputs!$D$2:$AG$2,0))))=0,"",SUMIFS(INDEX(Inputs!$D$4:$AG$150,0,MATCH(S$2,Inputs!$D$2:$AG$2,0)),Inputs!$B$4:$B$150,$B58)/1000) -> 785 | T58: =IF(SUMPRODUCT((Inputs!$B$4:$B$150=$B58)*ISNUMBER(INDEX(Inputs!$D$4:$AG$150,0,MATCH(T$2,Inputs!$D$2:$AG$2,0))))=0,"",SUMIFS(INDEX(Inputs!$D$4:$AG$150,0,MATCH(T$2,Inputs!$D$2:$AG$2,0)),Inputs!$B$4:$B$150,$B58)/1000) -> 779 | U58: =IF(SUMPRODUCT((Inputs!$B$4:$B$150=$B58)*ISNUMBER(INDEX(Inputs!$D$4:$AG$150,0,MATCH(U$2,Inputs!$D$2:$AG$2,0))))=0,"",SUMIFS(INDEX(Inputs!$D$4:$AG$150,0,MATCH(U$2,Inputs!$D$2:$AG$2,0)),Inputs!$B$4:$B$150,$B58)/1000) -> 893 | V58: =IF(SUMPRODUCT((Inputs!$B$4:$B$150=$B58)*ISNUMBER(INDEX(Inputs!$D$4:$AG$150,0,MATCH(V$2,Inputs!$D$2:$AG$2,0))))=0,"",SUMIFS(INDEX(Inputs!$D$4:$AG$150,0,MATCH(V$2,Inputs!$D$2:$AG$2,0)),Inputs!$B$4:$B$150,$B58)/1000) -> 120 | W58: =IF(COUNT(S58:V58)=4,SUM(S58:V58),"") -> 2577 | X58: =IF(SUMPRODUCT((Inputs!$B$4:$B$150=$B58)*ISNUMBER(INDEX(Inputs!$D$4:$AG$150,0,MATCH(X$2,Inputs!$D$2:$AG$2,0))))=0,"",SUMIFS(INDEX(Inputs!$D$4:$AG$150,0,MATCH(X$2,Inputs!$D$2:$AG$2,0)),Inputs!$B$4:$B$150,$B58)/1000) -> 273 | Y58: =IF(SUMPRODUCT((Inputs!$B$4:$B$150=$B58)*ISNUMBER(INDEX(Inputs!$D$4:$AG$150,0,MATCH(Y$2,Inputs!$D$2:$AG$2,0))))=0,"",SUMIFS(INDEX(Inputs!$D$4:$AG$150,0,MATCH(Y$2,Inputs!$D$2:$AG$2,0)),Inputs!$B$4:$B$150,$B58)/1000) -> 293 | Z58: =IF(SUMPRODUCT((Inputs!$B$4:$B$150=$B58)*ISNUMBER(INDEX(Inputs!$D$4:$AG$150,0,MATCH(Z$2,Inputs!$D$2:$AG$2,0))))=0,"",SUMIFS(INDEX(Inputs!$D$4:$AG$150,0,MATCH(Z$2,Inputs!$D$2:$AG$2,0)),Inputs!$B$4:$B$150,$B58)/1000) -> 515 | AA58: =IF(SUMPRODUCT((Inputs!$B$4:$B$150=$B58)*ISNUMBER(INDEX(Inputs!$D$4:$AG$150,0,MATCH(AA$2,Inputs!$D$2:$AG$2,0))))=0,"",SUMIFS(INDEX(Inputs!$D$4:$AG$150,0,MATCH(AA$2,Inputs!$D$2:$AG$2,0)),Inputs!$B$4:$B$150,$B58)/1000) -> -281 | AB58: =IF(COUNT(X58:AA58)=4,SUM(X58:AA58),"") -> 800 | AC58: =IF(SUMPRODUCT((Inputs!$B$4:$B$150=$B58)*ISNUMBER(INDEX(Inputs!$D$4:$AG$150,0,MATCH(AC$2,Inputs!$D$2:$AG$2,0))))=0,"",SUMIFS(INDEX(Inputs!$D$4:$AG$150,0,MATCH(AC$2,Inputs!$D$2:$AG$2,0)),Inputs!$B$4:$B$150,$B58)/1000) -> 110 | AD58: =IF(SUMPRODUCT((Inputs!$B$4:$B$150=$B58)*ISNUMBER(INDEX(Inputs!$D$4:$AG$150,0,MATCH(AD$2,Inputs!$D$2:$AG$2,0))))=0,"",SUMIFS(INDEX(Inputs!$D$4:$AG$150,0,MATCH(AD$2,Inputs!$D$2:$AG$2,0)),Inputs!$B$4:$B$150,$B58)/1000) -> 1131 | AE58: =IF(SUMPRODUCT((Inputs!$B$4:$B$150=$B58)*ISNUMBER(INDEX(Inputs!$D$4:$AG$150,0,MATCH(AE$2,Inputs!$D$2:$AG$2,0))))=0,"",SUMIFS(INDEX(Inputs!$D$4:$AG$150,0,MATCH(AE$2,Inputs!$D$2:$AG$2,0)),Inputs!$B$4:$B$150,$B58)/1000) | AF58: =IF(SUMPRODUCT((Inputs!$B$4:$B$150=$B58)*ISNUMBER(INDEX(Inputs!$D$4:$AG$150,0,MATCH(AF$2,Inputs!$D$2:$AG$2,0))))=0,"",SUMIFS(INDEX(Inputs!$D$4:$AG$150,0,MATCH(AF$2,Inputs!$D$2:$AG$2,0)),Inputs!$B$4:$B$150,$B58)/1000) | AG58: =IF(COUNT(AC58:AF58)=4,SUM(AC58:AF58),"")
B59: 51 | C59: Lucro Specialty Products (USD) | D59: =IF(SUMPRODUCT((Inputs!$B$4:$B$150=$B59)*ISNUMBER(INDEX(Inputs!$D$4:$AG$150,0,MATCH(D$2,Inputs!$D$2:$AG$2,0))))=0,"",SUMIFS(INDEX(Inputs!$D$4:$AG$150,0,MATCH(D$2,Inputs!$D$2:$AG$2,0)),Inputs!$B$4:$B$150,$B59)/1000) | E59: =IF(SUMPRODUCT((Inputs!$B$4:$B$150=$B59)*ISNUMBER(INDEX(Inputs!$D$4:$AG$150,0,MATCH(E$2,Inputs!$D$2:$AG$2,0))))=0,"",SUMIFS(INDEX(Inputs!$D$4:$AG$150,0,MATCH(E$2,Inputs!$D$2:$AG$2,0)),Inputs!$B$4:$B$150,$B59)/1000) | F59: =IF(SUMPRODUCT((Inputs!$B$4:$B$150=$B59)*ISNUMBER(INDEX(Inputs!$D$4:$AG$150,0,MATCH(F$2,Inputs!$D$2:$AG$2,0))))=0,"",SUMIFS(INDEX(Inputs!$D$4:$AG$150,0,MATCH(F$2,Inputs!$D$2:$AG$2,0)),Inputs!$B$4:$B$150,$B59)/1000) | G59: =IF(SUMPRODUCT((Inputs!$B$4:$B$150=$B59)*ISNUMBER(INDEX(Inputs!$D$4:$AG$150,0,MATCH(G$2,Inputs!$D$2:$AG$2,0))))=0,"",SUMIFS(INDEX(Inputs!$D$4:$AG$150,0,MATCH(G$2,Inputs!$D$2:$AG$2,0)),Inputs!$B$4:$B$150,$B59)/1000) | H59: =IF(COUNT(D59:G59)=4,SUM(D59:G59),"") | I59: =IF(SUMPRODUCT((Inputs!$B$4:$B$150=$B59)*ISNUMBER(INDEX(Inputs!$D$4:$AG$150,0,MATCH(I$2,Inputs!$D$2:$AG$2,0))))=0,"",SUMIFS(INDEX(Inputs!$D$4:$AG$150,0,MATCH(I$2,Inputs!$D$2:$AG$2,0)),Inputs!$B$4:$B$150,$B59)/1000) -> 476 | J59: =IF(SUMPRODUCT((Inputs!$B$4:$B$150=$B59)*ISNUMBER(INDEX(Inputs!$D$4:$AG$150,0,MATCH(J$2,Inputs!$D$2:$AG$2,0))))=0,"",SUMIFS(INDEX(Inputs!$D$4:$AG$150,0,MATCH(J$2,Inputs!$D$2:$AG$2,0)),Inputs!$B$4:$B$150,$B59)/1000) -> 417 | K59: =IF(SUMPRODUCT((Inputs!$B$4:$B$150=$B59)*ISNUMBER(INDEX(Inputs!$D$4:$AG$150,0,MATCH(K$2,Inputs!$D$2:$AG$2,0))))=0,"",SUMIFS(INDEX(Inputs!$D$4:$AG$150,0,MATCH(K$2,Inputs!$D$2:$AG$2,0)),Inputs!$B$4:$B$150,$B59)/1000) -> 762 | L59: =IF(SUMPRODUCT((Inputs!$B$4:$B$150=$B59)*ISNUMBER(INDEX(Inputs!$D$4:$AG$150,0,MATCH(L$2,Inputs!$D$2:$AG$2,0))))=0,"",SUMIFS(INDEX(Inputs!$D$4:$AG$150,0,MATCH(L$2,Inputs!$D$2:$AG$2,0)),Inputs!$B$4:$B$150,$B59)/1000) -> 760 | M59: =IF(COUNT(I59:L59)=4,SUM(I59:L59),"") -> 2415 | N59: =IF(SUMPRODUCT((Inputs!$B$4:$B$150=$B59)*ISNUMBER(INDEX(Inputs!$D$4:$AG$150,0,MATCH(N$2,Inputs!$D$2:$AG$2,0))))=0,"",SUMIFS(INDEX(Inputs!$D$4:$AG$150,0,MATCH(N$2,Inputs!$D$2:$AG$2,0)),Inputs!$B$4:$B$150,$B59)/1000) -> 774 | O59: =IF(SUMPRODUCT((Inputs!$B$4:$B$150=$B59)*ISNUMBER(INDEX(Inputs!$D$4:$AG$150,0,MATCH(O$2,Inputs!$D$2:$AG$2,0))))=0,"",SUMIFS(INDEX(Inputs!$D$4:$AG$150,0,MATCH(O$2,Inputs!$D$2:$AG$2,0)),Inputs!$B$4:$B$150,$B59)/1000) -> 671 | P59: =IF(SUMPRODUCT((Inputs!$B$4:$B$150=$B59)*ISNUMBER(INDEX(Inputs!$D$4:$AG$150,0,MATCH(P$2,Inputs!$D$2:$AG$2,0))))=0,"",SUMIFS(INDEX(Inputs!$D$4:$AG$150,0,MATCH(P$2,Inputs!$D$2:$AG$2,0)),Inputs!$B$4:$B$150,$B59)/1000) -> 619 | Q59: =IF(SUMPRODUCT((Inputs!$B$4:$B$150=$B59)*ISNUMBER(INDEX(Inputs!$D$4:$AG$150,0,MATCH(Q$2,Inputs!$D$2:$AG$2,0))))=0,"",SUMIFS(INDEX(Inputs!$D$4:$AG$150,0,MATCH(Q$2,Inputs!$D$2:$AG$2,0)),Inputs!$B$4:$B$150,$B59)/1000) -> 650 | R59: =IF(COUNT(N59:Q59)=4,SUM(N59:Q59),"") -> 2714 | S59: =IF(SUMPRODUCT((Inputs!$B$4:$B$150=$B59)*ISNUMBER(INDEX(Inputs!$D$4:$AG$150,0,MATCH(S$2,Inputs!$D$2:$AG$2,0))))=0,"",SUMIFS(INDEX(Inputs!$D$4:$AG$150,0,MATCH(S$2,Inputs!$D$2:$AG$2,0)),Inputs!$B$4:$B$150,$B59)/1000) -> 761 | T59: =IF(SUMPRODUCT((Inputs!$B$4:$B$150=$B59)*ISNUMBER(INDEX(Inputs!$D$4:$AG$150,0,MATCH(T$2,Inputs!$D$2:$AG$2,0))))=0,"",SUMIFS(INDEX(Inputs!$D$4:$AG$150,0,MATCH(T$2,Inputs!$D$2:$AG$2,0)),Inputs!$B$4:$B$150,$B59)/1000) -> 751 | U59: =IF(SUMPRODUCT((Inputs!$B$4:$B$150=$B59)*ISNUMBER(INDEX(Inputs!$D$4:$AG$150,0,MATCH(U$2,Inputs!$D$2:$AG$2,0))))=0,"",SUMIFS(INDEX(Inputs!$D$4:$AG$150,0,MATCH(U$2,Inputs!$D$2:$AG$2,0)),Inputs!$B$4:$B$150,$B59)/1000) -> 794 | V59: =IF(SUMPRODUCT((Inputs!$B$4:$B$150=$B59)*ISNUMBER(INDEX(Inputs!$D$4:$AG$150,0,MATCH(V$2,Inputs!$D$2:$AG$2,0))))=0,"",SUMIFS(INDEX(Inputs!$D$4:$AG$150,0,MATCH(V$2,Inputs!$D$2:$AG$2,0)),Inputs!$B$4:$B$150,$B59)/1000) -> 746 | W59: =IF(COUNT(S59:V59)=4,SUM(S59:V59),"") -> 3052 | X59: =IF(SUMPRODUCT((Inputs!$B$4:$B$150=$B59)*ISNUMBER(INDEX(Inputs!$D$4:$AG$150,0,MATCH(X$2,Inputs!$D$2:$AG$2,0))))=0,"",SUMIFS(INDEX(Inputs!$D$4:$AG$150,0,MATCH(X$2,Inputs!$D$2:$AG$2,0)),Inputs!$B$4:$B$150,$B59)/1000) -> 655 | Y59: =IF(SUMPRODUCT((Inputs!$B$4:$B$150=$B59)*ISNUMBER(INDEX(Inputs!$D$4:$AG$150,0,MATCH(Y$2,Inputs!$D$2:$AG$2,0))))=0,"",SUMIFS(INDEX(Inputs!$D$4:$AG$150,0,MATCH(Y$2,Inputs!$D$2:$AG$2,0)),Inputs!$B$4:$B$150,$B59)/1000) -> 780 | Z59: =IF(SUMPRODUCT((Inputs!$B$4:$B$150=$B59)*ISNUMBER(INDEX(Inputs!$D$4:$AG$150,0,MATCH(Z$2,Inputs!$D$2:$AG$2,0))))=0,"",SUMIFS(INDEX(Inputs!$D$4:$AG$150,0,MATCH(Z$2,Inputs!$D$2:$AG$2,0)),Inputs!$B$4:$B$150,$B59)/1000) -> 740 | AA59: =IF(SUMPRODUCT((Inputs!$B$4:$B$150=$B59)*ISNUMBER(INDEX(Inputs!$D$4:$AG$150,0,MATCH(AA$2,Inputs!$D$2:$AG$2,0))))=0,"",SUMIFS(INDEX(Inputs!$D$4:$AG$150,0,MATCH(AA$2,Inputs!$D$2:$AG$2,0)),Inputs!$B$4:$B$150,$B59)/1000) -> 682 | AB59: =IF(COUNT(X59:AA59)=4,SUM(X59:AA59),"") -> 2857 | AC59: =IF(SUMPRODUCT((Inputs!$B$4:$B$150=$B59)*ISNUMBER(INDEX(Inputs!$D$4:$AG$150,0,MATCH(AC$2,Inputs!$D$2:$AG$2,0))))=0,"",SUMIFS(INDEX(Inputs!$D$4:$AG$150,0,MATCH(AC$2,Inputs!$D$2:$AG$2,0)),Inputs!$B$4:$B$150,$B59)/1000) -> 651 | AD59: =IF(SUMPRODUCT((Inputs!$B$4:$B$150=$B59)*ISNUMBER(INDEX(Inputs!$D$4:$AG$150,0,MATCH(AD$2,Inputs!$D$2:$AG$2,0))))=0,"",SUMIFS(INDEX(Inputs!$D$4:$AG$150,0,MATCH(AD$2,Inputs!$D$2:$AG$2,0)),Inputs!$B$4:$B$150,$B59)/1000) -> 956 | AE59: =IF(SUMPRODUCT((Inputs!$B$4:$B$150=$B59)*ISNUMBER(INDEX(Inputs!$D$4:$AG$150,0,MATCH(AE$2,Inputs!$D$2:$AG$2,0))))=0,"",SUMIFS(INDEX(Inputs!$D$4:$AG$150,0,MATCH(AE$2,Inputs!$D$2:$AG$2,0)),Inputs!$B$4:$B$150,$B59)/1000) | AF59: =IF(SUMPRODUCT((Inputs!$B$4:$B$150=$B59)*ISNUMBER(INDEX(Inputs!$D$4:$AG$150,0,MATCH(AF$2,Inputs!$D$2:$AG$2,0))))=0,"",SUMIFS(INDEX(Inputs!$D$4:$AG$150,0,MATCH(AF$2,Inputs!$D$2:$AG$2,0)),Inputs!$B$4:$B$150,$B59)/1000) | AG59: =IF(COUNT(AC59:AF59)=4,SUM(AC59:AF59),"")
B60: 52 | C60: Corporate e financeiro (USD) | D60: =IF(SUMPRODUCT((Inputs!$B$4:$B$150=$B60)*ISNUMBER(INDEX(Inputs!$D$4:$AG$150,0,MATCH(D$2,Inputs!$D$2:$AG$2,0))))=0,"",SUMIFS(INDEX(Inputs!$D$4:$AG$150,0,MATCH(D$2,Inputs!$D$2:$AG$2,0)),Inputs!$B$4:$B$150,$B60)/1000) -> -849 | E60: =IF(SUMPRODUCT((Inputs!$B$4:$B$150=$B60)*ISNUMBER(INDEX(Inputs!$D$4:$AG$150,0,MATCH(E$2,Inputs!$D$2:$AG$2,0))))=0,"",SUMIFS(INDEX(Inputs!$D$4:$AG$150,0,MATCH(E$2,Inputs!$D$2:$AG$2,0)),Inputs!$B$4:$B$150,$B60)/1000) -> -588 | F60: =IF(SUMPRODUCT((Inputs!$B$4:$B$150=$B60)*ISNUMBER(INDEX(Inputs!$D$4:$AG$150,0,MATCH(F$2,Inputs!$D$2:$AG$2,0))))=0,"",SUMIFS(INDEX(Inputs!$D$4:$AG$150,0,MATCH(F$2,Inputs!$D$2:$AG$2,0)),Inputs!$B$4:$B$150,$B60)/1000) -> -596 | G60: =IF(SUMPRODUCT((Inputs!$B$4:$B$150=$B60)*ISNUMBER(INDEX(Inputs!$D$4:$AG$150,0,MATCH(G$2,Inputs!$D$2:$AG$2,0))))=0,"",SUMIFS(INDEX(Inputs!$D$4:$AG$150,0,MATCH(G$2,Inputs!$D$2:$AG$2,0)),Inputs!$B$4:$B$150,$B60)/1000) | H60: =IF(COUNT(D60:G60)=4,SUM(D60:G60),"") | I60: =IF(SUMPRODUCT((Inputs!$B$4:$B$150=$B60)*ISNUMBER(INDEX(Inputs!$D$4:$AG$150,0,MATCH(I$2,Inputs!$D$2:$AG$2,0))))=0,"",SUMIFS(INDEX(Inputs!$D$4:$AG$150,0,MATCH(I$2,Inputs!$D$2:$AG$2,0)),Inputs!$B$4:$B$150,$B60)/1000) -> -694 | J60: =IF(SUMPRODUCT((Inputs!$B$4:$B$150=$B60)*ISNUMBER(INDEX(Inputs!$D$4:$AG$150,0,MATCH(J$2,Inputs!$D$2:$AG$2,0))))=0,"",SUMIFS(INDEX(Inputs!$D$4:$AG$150,0,MATCH(J$2,Inputs!$D$2:$AG$2,0)),Inputs!$B$4:$B$150,$B60)/1000) -> -286 | K60: =IF(SUMPRODUCT((Inputs!$B$4:$B$150=$B60)*ISNUMBER(INDEX(Inputs!$D$4:$AG$150,0,MATCH(K$2,Inputs!$D$2:$AG$2,0))))=0,"",SUMIFS(INDEX(Inputs!$D$4:$AG$150,0,MATCH(K$2,Inputs!$D$2:$AG$2,0)),Inputs!$B$4:$B$150,$B60)/1000) -> -152 | L60: =IF(SUMPRODUCT((Inputs!$B$4:$B$150=$B60)*ISNUMBER(INDEX(Inputs!$D$4:$AG$150,0,MATCH(L$2,Inputs!$D$2:$AG$2,0))))=0,"",SUMIFS(INDEX(Inputs!$D$4:$AG$150,0,MATCH(L$2,Inputs!$D$2:$AG$2,0)),Inputs!$B$4:$B$150,$B60)/1000) -> -531 | M60: =IF(COUNT(I60:L60)=4,SUM(I60:L60),"") -> -1663 | N60: =IF(SUMPRODUCT((Inputs!$B$4:$B$150=$B60)*ISNUMBER(INDEX(Inputs!$D$4:$AG$150,0,MATCH(N$2,Inputs!$D$2:$AG$2,0))))=0,"",SUMIFS(INDEX(Inputs!$D$4:$AG$150,0,MATCH(N$2,Inputs!$D$2:$AG$2,0)),Inputs!$B$4:$B$150,$B60)/1000) -> -355 | O60: =IF(SUMPRODUCT((Inputs!$B$4:$B$150=$B60)*ISNUMBER(INDEX(Inputs!$D$4:$AG$150,0,MATCH(O$2,Inputs!$D$2:$AG$2,0))))=0,"",SUMIFS(INDEX(Inputs!$D$4:$AG$150,0,MATCH(O$2,Inputs!$D$2:$AG$2,0)),Inputs!$B$4:$B$150,$B60)/1000) -> -506 | P60: =IF(SUMPRODUCT((Inputs!$B$4:$B$150=$B60)*ISNUMBER(INDEX(Inputs!$D$4:$AG$150,0,MATCH(P$2,Inputs!$D$2:$AG$2,0))))=0,"",SUMIFS(INDEX(Inputs!$D$4:$AG$150,0,MATCH(P$2,Inputs!$D$2:$AG$2,0)),Inputs!$B$4:$B$150,$B60)/1000) -> -365 | Q60: =IF(SUMPRODUCT((Inputs!$B$4:$B$150=$B60)*ISNUMBER(INDEX(Inputs!$D$4:$AG$150,0,MATCH(Q$2,Inputs!$D$2:$AG$2,0))))=0,"",SUMIFS(INDEX(Inputs!$D$4:$AG$150,0,MATCH(Q$2,Inputs!$D$2:$AG$2,0)),Inputs!$B$4:$B$150,$B60)/1000) -> -565 | R60: =IF(COUNT(N60:Q60)=4,SUM(N60:Q60),"") -> -1791 | S60: =IF(SUMPRODUCT((Inputs!$B$4:$B$150=$B60)*ISNUMBER(INDEX(Inputs!$D$4:$AG$150,0,MATCH(S$2,Inputs!$D$2:$AG$2,0))))=0,"",SUMIFS(INDEX(Inputs!$D$4:$AG$150,0,MATCH(S$2,Inputs!$D$2:$AG$2,0)),Inputs!$B$4:$B$150,$B60)/1000) -> -362 | T60: =IF(SUMPRODUCT((Inputs!$B$4:$B$150=$B60)*ISNUMBER(INDEX(Inputs!$D$4:$AG$150,0,MATCH(T$2,Inputs!$D$2:$AG$2,0))))=0,"",SUMIFS(INDEX(Inputs!$D$4:$AG$150,0,MATCH(T$2,Inputs!$D$2:$AG$2,0)),Inputs!$B$4:$B$150,$B60)/1000) -> -310 | U60: =IF(SUMPRODUCT((Inputs!$B$4:$B$150=$B60)*ISNUMBER(INDEX(Inputs!$D$4:$AG$150,0,MATCH(U$2,Inputs!$D$2:$AG$2,0))))=0,"",SUMIFS(INDEX(Inputs!$D$4:$AG$150,0,MATCH(U$2,Inputs!$D$2:$AG$2,0)),Inputs!$B$4:$B$150,$B60)/1000) -> -544 | V60: =IF(SUMPRODUCT((Inputs!$B$4:$B$150=$B60)*ISNUMBER(INDEX(Inputs!$D$4:$AG$150,0,MATCH(V$2,Inputs!$D$2:$AG$2,0))))=0,"",SUMIFS(INDEX(Inputs!$D$4:$AG$150,0,MATCH(V$2,Inputs!$D$2:$AG$2,0)),Inputs!$B$4:$B$150,$B60)/1000) -> -156 | W60: =IF(COUNT(S60:V60)=4,SUM(S60:V60),"") -> -1372 | X60: =IF(SUMPRODUCT((Inputs!$B$4:$B$150=$B60)*ISNUMBER(INDEX(Inputs!$D$4:$AG$150,0,MATCH(X$2,Inputs!$D$2:$AG$2,0))))=0,"",SUMIFS(INDEX(Inputs!$D$4:$AG$150,0,MATCH(X$2,Inputs!$D$2:$AG$2,0)),Inputs!$B$4:$B$150,$B60)/1000) -> -798 | Y60: =IF(SUMPRODUCT((Inputs!$B$4:$B$150=$B60)*ISNUMBER(INDEX(Inputs!$D$4:$AG$150,0,MATCH(Y$2,Inputs!$D$2:$AG$2,0))))=0,"",SUMIFS(INDEX(Inputs!$D$4:$AG$150,0,MATCH(Y$2,Inputs!$D$2:$AG$2,0)),Inputs!$B$4:$B$150,$B60)/1000) -> -759 | Z60: =IF(SUMPRODUCT((Inputs!$B$4:$B$150=$B60)*ISNUMBER(INDEX(Inputs!$D$4:$AG$150,0,MATCH(Z$2,Inputs!$D$2:$AG$2,0))))=0,"",SUMIFS(INDEX(Inputs!$D$4:$AG$150,0,MATCH(Z$2,Inputs!$D$2:$AG$2,0)),Inputs!$B$4:$B$150,$B60)/1000) -> -1226 | AA60: =IF(SUMPRODUCT((Inputs!$B$4:$B$150=$B60)*ISNUMBER(INDEX(Inputs!$D$4:$AG$150,0,MATCH(AA$2,Inputs!$D$2:$AG$2,0))))=0,"",SUMIFS(INDEX(Inputs!$D$4:$AG$150,0,MATCH(AA$2,Inputs!$D$2:$AG$2,0)),Inputs!$B$4:$B$150,$B60)/1000) -> -807 | AB60: =IF(COUNT(X60:AA60)=4,SUM(X60:AA60),"") -> -3590 | AC60: =IF(SUMPRODUCT((Inputs!$B$4:$B$150=$B60)*ISNUMBER(INDEX(Inputs!$D$4:$AG$150,0,MATCH(AC$2,Inputs!$D$2:$AG$2,0))))=0,"",SUMIFS(INDEX(Inputs!$D$4:$AG$150,0,MATCH(AC$2,Inputs!$D$2:$AG$2,0)),Inputs!$B$4:$B$150,$B60)/1000) -> -1053 | AD60: =IF(SUMPRODUCT((Inputs!$B$4:$B$150=$B60)*ISNUMBER(INDEX(Inputs!$D$4:$AG$150,0,MATCH(AD$2,Inputs!$D$2:$AG$2,0))))=0,"",SUMIFS(INDEX(Inputs!$D$4:$AG$150,0,MATCH(AD$2,Inputs!$D$2:$AG$2,0)),Inputs!$B$4:$B$150,$B60)/1000) -> -954 | AE60: =IF(SUMPRODUCT((Inputs!$B$4:$B$150=$B60)*ISNUMBER(INDEX(Inputs!$D$4:$AG$150,0,MATCH(AE$2,Inputs!$D$2:$AG$2,0))))=0,"",SUMIFS(INDEX(Inputs!$D$4:$AG$150,0,MATCH(AE$2,Inputs!$D$2:$AG$2,0)),Inputs!$B$4:$B$150,$B60)/1000) | AF60: =IF(SUMPRODUCT((Inputs!$B$4:$B$150=$B60)*ISNUMBER(INDEX(Inputs!$D$4:$AG$150,0,MATCH(AF$2,Inputs!$D$2:$AG$2,0))))=0,"",SUMIFS(INDEX(Inputs!$D$4:$AG$150,0,MATCH(AF$2,Inputs!$D$2:$AG$2,0)),Inputs!$B$4:$B$150,$B60)/1000) | AG60: =IF(COUNT(AC60:AF60)=4,SUM(AC60:AF60),"")
B61: 53 | C61: Receita Upstream (USD; desde 4T22) | D61: =IF(SUMPRODUCT((Inputs!$B$4:$B$150=$B61)*ISNUMBER(INDEX(Inputs!$D$4:$AG$150,0,MATCH(D$2,Inputs!$D$2:$AG$2,0))))=0,"",SUMIFS(INDEX(Inputs!$D$4:$AG$150,0,MATCH(D$2,Inputs!$D$2:$AG$2,0)),Inputs!$B$4:$B$150,$B61)/1000) | E61: =IF(SUMPRODUCT((Inputs!$B$4:$B$150=$B61)*ISNUMBER(INDEX(Inputs!$D$4:$AG$150,0,MATCH(E$2,Inputs!$D$2:$AG$2,0))))=0,"",SUMIFS(INDEX(Inputs!$D$4:$AG$150,0,MATCH(E$2,Inputs!$D$2:$AG$2,0)),Inputs!$B$4:$B$150,$B61)/1000) | F61: =IF(SUMPRODUCT((Inputs!$B$4:$B$150=$B61)*ISNUMBER(INDEX(Inputs!$D$4:$AG$150,0,MATCH(F$2,Inputs!$D$2:$AG$2,0))))=0,"",SUMIFS(INDEX(Inputs!$D$4:$AG$150,0,MATCH(F$2,Inputs!$D$2:$AG$2,0)),Inputs!$B$4:$B$150,$B61)/1000) | G61: =IF(SUMPRODUCT((Inputs!$B$4:$B$150=$B61)*ISNUMBER(INDEX(Inputs!$D$4:$AG$150,0,MATCH(G$2,Inputs!$D$2:$AG$2,0))))=0,"",SUMIFS(INDEX(Inputs!$D$4:$AG$150,0,MATCH(G$2,Inputs!$D$2:$AG$2,0)),Inputs!$B$4:$B$150,$B61)/1000) | H61: =IF(COUNT(D61:G61)=4,SUM(D61:G61),"") | I61: =IF(SUMPRODUCT((Inputs!$B$4:$B$150=$B61)*ISNUMBER(INDEX(Inputs!$D$4:$AG$150,0,MATCH(I$2,Inputs!$D$2:$AG$2,0))))=0,"",SUMIFS(INDEX(Inputs!$D$4:$AG$150,0,MATCH(I$2,Inputs!$D$2:$AG$2,0)),Inputs!$B$4:$B$150,$B61)/1000) | J61: =IF(SUMPRODUCT((Inputs!$B$4:$B$150=$B61)*ISNUMBER(INDEX(Inputs!$D$4:$AG$150,0,MATCH(J$2,Inputs!$D$2:$AG$2,0))))=0,"",SUMIFS(INDEX(Inputs!$D$4:$AG$150,0,MATCH(J$2,Inputs!$D$2:$AG$2,0)),Inputs!$B$4:$B$150,$B61)/1000) | K61: =IF(SUMPRODUCT((Inputs!$B$4:$B$150=$B61)*ISNUMBER(INDEX(Inputs!$D$4:$AG$150,0,MATCH(K$2,Inputs!$D$2:$AG$2,0))))=0,"",SUMIFS(INDEX(Inputs!$D$4:$AG$150,0,MATCH(K$2,Inputs!$D$2:$AG$2,0)),Inputs!$B$4:$B$150,$B61)/1000) | L61: =IF(SUMPRODUCT((Inputs!$B$4:$B$150=$B61)*ISNUMBER(INDEX(Inputs!$D$4:$AG$150,0,MATCH(L$2,Inputs!$D$2:$AG$2,0))))=0,"",SUMIFS(INDEX(Inputs!$D$4:$AG$150,0,MATCH(L$2,Inputs!$D$2:$AG$2,0)),Inputs!$B$4:$B$150,$B61)/1000) | M61: =IF(COUNT(I61:L61)=4,SUM(I61:L61),"") | N61: =IF(SUMPRODUCT((Inputs!$B$4:$B$150=$B61)*ISNUMBER(INDEX(Inputs!$D$4:$AG$150,0,MATCH(N$2,Inputs!$D$2:$AG$2,0))))=0,"",SUMIFS(INDEX(Inputs!$D$4:$AG$150,0,MATCH(N$2,Inputs!$D$2:$AG$2,0)),Inputs!$B$4:$B$150,$B61)/1000) | O61: =IF(SUMPRODUCT((Inputs!$B$4:$B$150=$B61)*ISNUMBER(INDEX(Inputs!$D$4:$AG$150,0,MATCH(O$2,Inputs!$D$2:$AG$2,0))))=0,"",SUMIFS(INDEX(Inputs!$D$4:$AG$150,0,MATCH(O$2,Inputs!$D$2:$AG$2,0)),Inputs!$B$4:$B$150,$B61)/1000) | P61: =IF(SUMPRODUCT((Inputs!$B$4:$B$150=$B61)*ISNUMBER(INDEX(Inputs!$D$4:$AG$150,0,MATCH(P$2,Inputs!$D$2:$AG$2,0))))=0,"",SUMIFS(INDEX(Inputs!$D$4:$AG$150,0,MATCH(P$2,Inputs!$D$2:$AG$2,0)),Inputs!$B$4:$B$150,$B61)/1000) | Q61: =IF(SUMPRODUCT((Inputs!$B$4:$B$150=$B61)*ISNUMBER(INDEX(Inputs!$D$4:$AG$150,0,MATCH(Q$2,Inputs!$D$2:$AG$2,0))))=0,"",SUMIFS(INDEX(Inputs!$D$4:$AG$150,0,MATCH(Q$2,Inputs!$D$2:$AG$2,0)),Inputs!$B$4:$B$150,$B61)/1000) | R61: =IF(COUNT(N61:Q61)=4,SUM(N61:Q61),"") | S61: =IF(SUMPRODUCT((Inputs!$B$4:$B$150=$B61)*ISNUMBER(INDEX(Inputs!$D$4:$AG$150,0,MATCH(S$2,Inputs!$D$2:$AG$2,0))))=0,"",SUMIFS(INDEX(Inputs!$D$4:$AG$150,0,MATCH(S$2,Inputs!$D$2:$AG$2,0)),Inputs!$B$4:$B$150,$B61)/1000) -> 23385 | T61: =IF(SUMPRODUCT((Inputs!$B$4:$B$150=$B61)*ISNUMBER(INDEX(Inputs!$D$4:$AG$150,0,MATCH(T$2,Inputs!$D$2:$AG$2,0))))=0,"",SUMIFS(INDEX(Inputs!$D$4:$AG$150,0,MATCH(T$2,Inputs!$D$2:$AG$2,0)),Inputs!$B$4:$B$150,$B61)/1000) -> 28830 | U61: =IF(SUMPRODUCT((Inputs!$B$4:$B$150=$B61)*ISNUMBER(INDEX(Inputs!$D$4:$AG$150,0,MATCH(U$2,Inputs!$D$2:$AG$2,0))))=0,"",SUMIFS(INDEX(Inputs!$D$4:$AG$150,0,MATCH(U$2,Inputs!$D$2:$AG$2,0)),Inputs!$B$4:$B$150,$B61)/1000) -> 29382 | V61: =IF(SUMPRODUCT((Inputs!$B$4:$B$150=$B61)*ISNUMBER(INDEX(Inputs!$D$4:$AG$150,0,MATCH(V$2,Inputs!$D$2:$AG$2,0))))=0,"",SUMIFS(INDEX(Inputs!$D$4:$AG$150,0,MATCH(V$2,Inputs!$D$2:$AG$2,0)),Inputs!$B$4:$B$150,$B61)/1000) -> 29149 | W61: =IF(COUNT(S61:V61)=4,SUM(S61:V61),"") -> 110746 | X61: =IF(SUMPRODUCT((Inputs!$B$4:$B$150=$B61)*ISNUMBER(INDEX(Inputs!$D$4:$AG$150,0,MATCH(X$2,Inputs!$D$2:$AG$2,0))))=0,"",SUMIFS(INDEX(Inputs!$D$4:$AG$150,0,MATCH(X$2,Inputs!$D$2:$AG$2,0)),Inputs!$B$4:$B$150,$B61)/1000) -> 29174 | Y61: =IF(SUMPRODUCT((Inputs!$B$4:$B$150=$B61)*ISNUMBER(INDEX(Inputs!$D$4:$AG$150,0,MATCH(Y$2,Inputs!$D$2:$AG$2,0))))=0,"",SUMIFS(INDEX(Inputs!$D$4:$AG$150,0,MATCH(Y$2,Inputs!$D$2:$AG$2,0)),Inputs!$B$4:$B$150,$B61)/1000) -> 25700 | Z61: =IF(SUMPRODUCT((Inputs!$B$4:$B$150=$B61)*ISNUMBER(INDEX(Inputs!$D$4:$AG$150,0,MATCH(Z$2,Inputs!$D$2:$AG$2,0))))=0,"",SUMIFS(INDEX(Inputs!$D$4:$AG$150,0,MATCH(Z$2,Inputs!$D$2:$AG$2,0)),Inputs!$B$4:$B$150,$B61)/1000) -> 27790 | AA61: =IF(SUMPRODUCT((Inputs!$B$4:$B$150=$B61)*ISNUMBER(INDEX(Inputs!$D$4:$AG$150,0,MATCH(AA$2,Inputs!$D$2:$AG$2,0))))=0,"",SUMIFS(INDEX(Inputs!$D$4:$AG$150,0,MATCH(AA$2,Inputs!$D$2:$AG$2,0)),Inputs!$B$4:$B$150,$B61)/1000) -> 24487 | AB61: =IF(COUNT(X61:AA61)=4,SUM(X61:AA61),"") -> 107151 | AC61: =IF(SUMPRODUCT((Inputs!$B$4:$B$150=$B61)*ISNUMBER(INDEX(Inputs!$D$4:$AG$150,0,MATCH(AC$2,Inputs!$D$2:$AG$2,0))))=0,"",SUMIFS(INDEX(Inputs!$D$4:$AG$150,0,MATCH(AC$2,Inputs!$D$2:$AG$2,0)),Inputs!$B$4:$B$150,$B61)/1000) -> 28824 | AD61: =IF(SUMPRODUCT((Inputs!$B$4:$B$150=$B61)*ISNUMBER(INDEX(Inputs!$D$4:$AG$150,0,MATCH(AD$2,Inputs!$D$2:$AG$2,0))))=0,"",SUMIFS(INDEX(Inputs!$D$4:$AG$150,0,MATCH(AD$2,Inputs!$D$2:$AG$2,0)),Inputs!$B$4:$B$150,$B61)/1000) -> 35457 | AE61: =IF(SUMPRODUCT((Inputs!$B$4:$B$150=$B61)*ISNUMBER(INDEX(Inputs!$D$4:$AG$150,0,MATCH(AE$2,Inputs!$D$2:$AG$2,0))))=0,"",SUMIFS(INDEX(Inputs!$D$4:$AG$150,0,MATCH(AE$2,Inputs!$D$2:$AG$2,0)),Inputs!$B$4:$B$150,$B61)/1000) | AF61: =IF(SUMPRODUCT((Inputs!$B$4:$B$150=$B61)*ISNUMBER(INDEX(Inputs!$D$4:$AG$150,0,MATCH(AF$2,Inputs!$D$2:$AG$2,0))))=0,"",SUMIFS(INDEX(Inputs!$D$4:$AG$150,0,MATCH(AF$2,Inputs!$D$2:$AG$2,0)),Inputs!$B$4:$B$150,$B61)/1000) | AG61: =IF(COUNT(AC61:AF61)=4,SUM(AC61:AF61),"")
B62: 54 | C62: Receita Energy Products (USD; desde 4T22) | D62: =IF(SUMPRODUCT((Inputs!$B$4:$B$150=$B62)*ISNUMBER(INDEX(Inputs!$D$4:$AG$150,0,MATCH(D$2,Inputs!$D$2:$AG$2,0))))=0,"",SUMIFS(INDEX(Inputs!$D$4:$AG$150,0,MATCH(D$2,Inputs!$D$2:$AG$2,0)),Inputs!$B$4:$B$150,$B62)/1000) | E62: =IF(SUMPRODUCT((Inputs!$B$4:$B$150=$B62)*ISNUMBER(INDEX(Inputs!$D$4:$AG$150,0,MATCH(E$2,Inputs!$D$2:$AG$2,0))))=0,"",SUMIFS(INDEX(Inputs!$D$4:$AG$150,0,MATCH(E$2,Inputs!$D$2:$AG$2,0)),Inputs!$B$4:$B$150,$B62)/1000) | F62: =IF(SUMPRODUCT((Inputs!$B$4:$B$150=$B62)*ISNUMBER(INDEX(Inputs!$D$4:$AG$150,0,MATCH(F$2,Inputs!$D$2:$AG$2,0))))=0,"",SUMIFS(INDEX(Inputs!$D$4:$AG$150,0,MATCH(F$2,Inputs!$D$2:$AG$2,0)),Inputs!$B$4:$B$150,$B62)/1000) | G62: =IF(SUMPRODUCT((Inputs!$B$4:$B$150=$B62)*ISNUMBER(INDEX(Inputs!$D$4:$AG$150,0,MATCH(G$2,Inputs!$D$2:$AG$2,0))))=0,"",SUMIFS(INDEX(Inputs!$D$4:$AG$150,0,MATCH(G$2,Inputs!$D$2:$AG$2,0)),Inputs!$B$4:$B$150,$B62)/1000) | H62: =IF(COUNT(D62:G62)=4,SUM(D62:G62),"") | I62: =IF(SUMPRODUCT((Inputs!$B$4:$B$150=$B62)*ISNUMBER(INDEX(Inputs!$D$4:$AG$150,0,MATCH(I$2,Inputs!$D$2:$AG$2,0))))=0,"",SUMIFS(INDEX(Inputs!$D$4:$AG$150,0,MATCH(I$2,Inputs!$D$2:$AG$2,0)),Inputs!$B$4:$B$150,$B62)/1000) | J62: =IF(SUMPRODUCT((Inputs!$B$4:$B$150=$B62)*ISNUMBER(INDEX(Inputs!$D$4:$AG$150,0,MATCH(J$2,Inputs!$D$2:$AG$2,0))))=0,"",SUMIFS(INDEX(Inputs!$D$4:$AG$150,0,MATCH(J$2,Inputs!$D$2:$AG$2,0)),Inputs!$B$4:$B$150,$B62)/1000) | K62: =IF(SUMPRODUCT((Inputs!$B$4:$B$150=$B62)*ISNUMBER(INDEX(Inputs!$D$4:$AG$150,0,MATCH(K$2,Inputs!$D$2:$AG$2,0))))=0,"",SUMIFS(INDEX(Inputs!$D$4:$AG$150,0,MATCH(K$2,Inputs!$D$2:$AG$2,0)),Inputs!$B$4:$B$150,$B62)/1000) | L62: =IF(SUMPRODUCT((Inputs!$B$4:$B$150=$B62)*ISNUMBER(INDEX(Inputs!$D$4:$AG$150,0,MATCH(L$2,Inputs!$D$2:$AG$2,0))))=0,"",SUMIFS(INDEX(Inputs!$D$4:$AG$150,0,MATCH(L$2,Inputs!$D$2:$AG$2,0)),Inputs!$B$4:$B$150,$B62)/1000) | M62: =IF(COUNT(I62:L62)=4,SUM(I62:L62),"") | N62: =IF(SUMPRODUCT((Inputs!$B$4:$B$150=$B62)*ISNUMBER(INDEX(Inputs!$D$4:$AG$150,0,MATCH(N$2,Inputs!$D$2:$AG$2,0))))=0,"",SUMIFS(INDEX(Inputs!$D$4:$AG$150,0,MATCH(N$2,Inputs!$D$2:$AG$2,0)),Inputs!$B$4:$B$150,$B62)/1000) | O62: =IF(SUMPRODUCT((Inputs!$B$4:$B$150=$B62)*ISNUMBER(INDEX(Inputs!$D$4:$AG$150,0,MATCH(O$2,Inputs!$D$2:$AG$2,0))))=0,"",SUMIFS(INDEX(Inputs!$D$4:$AG$150,0,MATCH(O$2,Inputs!$D$2:$AG$2,0)),Inputs!$B$4:$B$150,$B62)/1000) | P62: =IF(SUMPRODUCT((Inputs!$B$4:$B$150=$B62)*ISNUMBER(INDEX(Inputs!$D$4:$AG$150,0,MATCH(P$2,Inputs!$D$2:$AG$2,0))))=0,"",SUMIFS(INDEX(Inputs!$D$4:$AG$150,0,MATCH(P$2,Inputs!$D$2:$AG$2,0)),Inputs!$B$4:$B$150,$B62)/1000) | Q62: =IF(SUMPRODUCT((Inputs!$B$4:$B$150=$B62)*ISNUMBER(INDEX(Inputs!$D$4:$AG$150,0,MATCH(Q$2,Inputs!$D$2:$AG$2,0))))=0,"",SUMIFS(INDEX(Inputs!$D$4:$AG$150,0,MATCH(Q$2,Inputs!$D$2:$AG$2,0)),Inputs!$B$4:$B$150,$B62)/1000) | R62: =IF(COUNT(N62:Q62)=4,SUM(N62:Q62),"") | S62: =IF(SUMPRODUCT((Inputs!$B$4:$B$150=$B62)*ISNUMBER(INDEX(Inputs!$D$4:$AG$150,0,MATCH(S$2,Inputs!$D$2:$AG$2,0))))=0,"",SUMIFS(INDEX(Inputs!$D$4:$AG$150,0,MATCH(S$2,Inputs!$D$2:$AG$2,0)),Inputs!$B$4:$B$150,$B62)/1000) -> 77642 | T62: =IF(SUMPRODUCT((Inputs!$B$4:$B$150=$B62)*ISNUMBER(INDEX(Inputs!$D$4:$AG$150,0,MATCH(T$2,Inputs!$D$2:$AG$2,0))))=0,"",SUMIFS(INDEX(Inputs!$D$4:$AG$150,0,MATCH(T$2,Inputs!$D$2:$AG$2,0)),Inputs!$B$4:$B$150,$B62)/1000) -> 82497 | U62: =IF(SUMPRODUCT((Inputs!$B$4:$B$150=$B62)*ISNUMBER(INDEX(Inputs!$D$4:$AG$150,0,MATCH(U$2,Inputs!$D$2:$AG$2,0))))=0,"",SUMIFS(INDEX(Inputs!$D$4:$AG$150,0,MATCH(U$2,Inputs!$D$2:$AG$2,0)),Inputs!$B$4:$B$150,$B62)/1000) -> 78704 | V62: =IF(SUMPRODUCT((Inputs!$B$4:$B$150=$B62)*ISNUMBER(INDEX(Inputs!$D$4:$AG$150,0,MATCH(V$2,Inputs!$D$2:$AG$2,0))))=0,"",SUMIFS(INDEX(Inputs!$D$4:$AG$150,0,MATCH(V$2,Inputs!$D$2:$AG$2,0)),Inputs!$B$4:$B$150,$B62)/1000) -> 72191 | W62: =IF(COUNT(S62:V62)=4,SUM(S62:V62),"") -> 311034 | X62: =IF(SUMPRODUCT((Inputs!$B$4:$B$150=$B62)*ISNUMBER(INDEX(Inputs!$D$4:$AG$150,0,MATCH(X$2,Inputs!$D$2:$AG$2,0))))=0,"",SUMIFS(INDEX(Inputs!$D$4:$AG$150,0,MATCH(X$2,Inputs!$D$2:$AG$2,0)),Inputs!$B$4:$B$150,$B62)/1000) -> 71375 | Y62: =IF(SUMPRODUCT((Inputs!$B$4:$B$150=$B62)*ISNUMBER(INDEX(Inputs!$D$4:$AG$150,0,MATCH(Y$2,Inputs!$D$2:$AG$2,0))))=0,"",SUMIFS(INDEX(Inputs!$D$4:$AG$150,0,MATCH(Y$2,Inputs!$D$2:$AG$2,0)),Inputs!$B$4:$B$150,$B62)/1000) -> 71147 | Z62: =IF(SUMPRODUCT((Inputs!$B$4:$B$150=$B62)*ISNUMBER(INDEX(Inputs!$D$4:$AG$150,0,MATCH(Z$2,Inputs!$D$2:$AG$2,0))))=0,"",SUMIFS(INDEX(Inputs!$D$4:$AG$150,0,MATCH(Z$2,Inputs!$D$2:$AG$2,0)),Inputs!$B$4:$B$150,$B62)/1000) -> 74990 | AA62: =IF(SUMPRODUCT((Inputs!$B$4:$B$150=$B62)*ISNUMBER(INDEX(Inputs!$D$4:$AG$150,0,MATCH(AA$2,Inputs!$D$2:$AG$2,0))))=0,"",SUMIFS(INDEX(Inputs!$D$4:$AG$150,0,MATCH(AA$2,Inputs!$D$2:$AG$2,0)),Inputs!$B$4:$B$150,$B62)/1000) -> 74104 | AB62: =IF(COUNT(X62:AA62)=4,SUM(X62:AA62),"") -> 291616 | AC62: =IF(SUMPRODUCT((Inputs!$B$4:$B$150=$B62)*ISNUMBER(INDEX(Inputs!$D$4:$AG$150,0,MATCH(AC$2,Inputs!$D$2:$AG$2,0))))=0,"",SUMIFS(INDEX(Inputs!$D$4:$AG$150,0,MATCH(AC$2,Inputs!$D$2:$AG$2,0)),Inputs!$B$4:$B$150,$B62)/1000) -> 77272 | AD62: =IF(SUMPRODUCT((Inputs!$B$4:$B$150=$B62)*ISNUMBER(INDEX(Inputs!$D$4:$AG$150,0,MATCH(AD$2,Inputs!$D$2:$AG$2,0))))=0,"",SUMIFS(INDEX(Inputs!$D$4:$AG$150,0,MATCH(AD$2,Inputs!$D$2:$AG$2,0)),Inputs!$B$4:$B$150,$B62)/1000) -> 109543 | AE62: =IF(SUMPRODUCT((Inputs!$B$4:$B$150=$B62)*ISNUMBER(INDEX(Inputs!$D$4:$AG$150,0,MATCH(AE$2,Inputs!$D$2:$AG$2,0))))=0,"",SUMIFS(INDEX(Inputs!$D$4:$AG$150,0,MATCH(AE$2,Inputs!$D$2:$AG$2,0)),Inputs!$B$4:$B$150,$B62)/1000) | AF62: =IF(SUMPRODUCT((Inputs!$B$4:$B$150=$B62)*ISNUMBER(INDEX(Inputs!$D$4:$AG$150,0,MATCH(AF$2,Inputs!$D$2:$AG$2,0))))=0,"",SUMIFS(INDEX(Inputs!$D$4:$AG$150,0,MATCH(AF$2,Inputs!$D$2:$AG$2,0)),Inputs!$B$4:$B$150,$B62)/1000) | AG62: =IF(COUNT(AC62:AF62)=4,SUM(AC62:AF62),"")

Sheet Model
C1: CHECKS | I1: =IF(I2="","",SUM(I2,I3)) -> 0 | J1: =IF(J2="","",SUM(J2,J3)) -> 0 | K1: =IF(K2="","",SUM(K2,K3)) -> 0 | L1: =IF(L2="","",SUM(L2,L3)) -> 0 | M1: =IF(M2="","",SUM(M2,M3)) -> 0 | N1: =IF(N2="","",SUM(N2,N3)) -> 0 | O1: =IF(O2="","",SUM(O2,O3)) -> 0 | P1: =IF(P2="","",SUM(P2,P3)) -> 0 | ... BF1: =IF(BF2="","",SUM(BF2,BF3)) -> 39358.61
C2: BS | I2: =IF(COUNT(I183,I259)<2,"",ABS(I183-I259)) -> 0 | J2: =IF(COUNT(J183,J259)<2,"",ABS(J183-J259)) -> 0 | K2: =IF(COUNT(K183,K259)<2,"",ABS(K183-K259)) -> 0 | L2: =IF(COUNT(L183,L259)<2,"",ABS(L183-L259)) -> 0 | M2: =IF(COUNT(M183,M259)<2,"",ABS(M183-M259)) -> 0 | N2: =IF(COUNT(N183,N259)<2,"",ABS(N183-N259)) -> 0 | O2: =IF(COUNT(O183,O259)<2,"",ABS(O183-O259)) -> 0 | P2: =IF(COUNT(P183,P259)<2,"",ABS(P183-P259)) -> 0 | ... BF2: =IF(COUNT(BF183,BF259)<2,"",ABS(BF183-BF259)) -> 0
C3: IS | I3: =IF(COUNT(I123,I4)<2,"",ABS(I123-I4)) -> 0 | J3: =IF(COUNT(J123,J4)<2,"",ABS(J123-J4)) -> 0 | K3: =IF(COUNT(K123,K4)<2,"",ABS(K123-K4)) -> 0 | L3: =IF(COUNT(L123,L4)<2,"",ABS(L123-L4)) -> 0 | M3: =IF(COUNT(M123,M4)<2,"",ABS(M123-M4)) -> 0 | N3: =IF(COUNT(N123,N4)<2,"",ABS(N123-N4)) -> 0 | O3: =IF(COUNT(O123,O4)<2,"",ABS(O123-O4)) -> 0 | P3: =IF(COUNT(P123,P4)<2,"",ABS(P123-P4)) -> 0 | ... AI3: =IF(COUNT(AI123,AI4)<2,"",ABS(AI123-AI4)) -> 0 | AJ3: =ABS(AJ123-AJ4) -> 8100.1234 | AK3: =ABS(AK123-AK4) -> 7816.5516 | AL3: =ABS(AL123-AL4) -> 34624.675 | AM3: =ABS(AM123-AM4) -> 8085.3085 | AN3: =ABS(AN123-AN4) -> 11017.797 | AO3: =ABS(AO123-AO4) -> 8448.5939 | AP3: =ABS(AP123-AP4) -> 8152.8228 | AQ3: =ABS(AQ123-AQ4) -> 35704.523 | ... BF3: =ABS(BF123-BF4) -> 39358.61
C4: Net Income reportado (lucro líquido) — base do check de DRE | I4: =IF(ISNUMBER('Inputs (2)'!D50),'Inputs (2)'!D50,"") -> 2730 | J4: =IF(ISNUMBER('Inputs (2)'!E50),'Inputs (2)'!E50,"") -> 4690 | K4: =IF(ISNUMBER('Inputs (2)'!F50),'Inputs (2)'!F50,"") -> 6750 | L4: =IF(ISNUMBER('Inputs (2)'!G50),'Inputs (2)'!G50,"") -> 8870 | M4: =IF(COUNT(I4:L4)=4,SUM(I4:L4),"") -> 23040 | N4: =IF(ISNUMBER('Inputs (2)'!I50),'Inputs (2)'!I50,"") -> 5480 | O4: =IF(ISNUMBER('Inputs (2)'!J50),'Inputs (2)'!J50,"") -> 17850 | P4: =IF(ISNUMBER('Inputs (2)'!K50),'Inputs (2)'!K50,"") -> 19660 | Q4: =IF(ISNUMBER('Inputs (2)'!L50),'Inputs (2)'!L50,"") -> 12750 | R4: =IF(COUNT(N4:Q4)=4,SUM(N4:Q4),"") -> 55740 | S4: =IF(ISNUMBER('Inputs (2)'!N50),'Inputs (2)'!N50,"") -> 11430 | T4: =IF(ISNUMBER('Inputs (2)'!O50),'Inputs (2)'!O50,"") -> 7880 | U4: =IF(ISNUMBER('Inputs (2)'!P50),'Inputs (2)'!P50,"") -> 9070 | V4: =IF(ISNUMBER('Inputs (2)'!Q50),'Inputs (2)'!Q50,"") -> 7630 | W4: =IF(COUNT(S4:V4)=4,SUM(S4:V4),"") -> 36010 | X4: =IF(ISNUMBER('Inputs (2)'!S50),'Inputs (2)'!S50,"") -> 8220 | Y4: =IF(ISNUMBER('Inputs (2)'!T50),'Inputs (2)'!T50,"") -> 9240 | Z4: =IF(ISNUMBER('Inputs (2)'!U50),'Inputs (2)'!U50,"") -> 8610 | AA4: =IF(ISNUMBER('Inputs (2)'!V50),'Inputs (2)'!V50,"") -> 7610 | AB4: =IF(COUNT(X4:AA4)=4,SUM(X4:AA4),"") -> 33680 | AC4: =IF(ISNUMBER('Inputs (2)'!X50),'Inputs (2)'!X50,"") -> 7713 | AD4: =IF(ISNUMBER('Inputs (2)'!Y50),'Inputs (2)'!Y50,"") -> 7082 | AE4: =IF(ISNUMBER('Inputs (2)'!Z50),'Inputs (2)'!Z50,"") -> 7548 | AF4: =IF(ISNUMBER('Inputs (2)'!AA50),'Inputs (2)'!AA50,"") -> 6501 | AG4: =IF(COUNT(AC4:AF4)=4,SUM(AC4:AF4),"") -> 28844 | AH4: =IF(ISNUMBER('Inputs (2)'!AC50),'Inputs (2)'!AC50,"") -> 4183 | AI4: =IF(ISNUMBER('Inputs (2)'!AD50),'Inputs (2)'!AD50,"") -> 14525
B5: 45930 | H5: 44196 | I5: 44286 | J5: =DATE(YEAR(I5),MONTH(I5)+3,DAY(I5)-1) -> 44377 | K5: =DATE(YEAR(J5),MONTH(J5)+3,DAY(J5)) -> 44469 | L5: =DATE(YEAR(K5),MONTH(K5)+3,DAY(K5)+1) -> 44561 | M5: =L5 -> 44561 | N5: =DATE(YEAR(M5),MONTH(M5)+3,DAY(M5)) -> 44651 | O5: =DATE(YEAR(N5),MONTH(N5)+3,DAY(N5)-1) -> 44742 | P5: =DATE(YEAR(O5),MONTH(O5)+3,DAY(O5)) -> 44834 | Q5: =DATE(YEAR(P5),MONTH(P5)+3,DAY(P5)+1) -> 44926 | R5: =Q5 -> 44926 | S5: =DATE(YEAR(R5),MONTH(R5)+3,DAY(R5)) -> 45016 | T5: =DATE(YEAR(S5),MONTH(S5)+3,DAY(S5))-1 -> 45107 | U5: =DATE(YEAR(T5),MONTH(T5)+3,DAY(T5)) -> 45199 | V5: =DATE(YEAR(U5),MONTH(U5)+3,DAY(U5))+1 -> 45291 | W5: =V5 -> 45291 | X5: =DATE(YEAR(W5),MONTH(W5)+3,DAY(W5)) -> 45382 | Y5: =DATE(YEAR(X5),MONTH(X5)+3,DAY(X5))-1 -> 45473 | Z5: =DATE(YEAR(Y5),MONTH(Y5)+3,DAY(Y5)) -> 45565 | AA5: =DATE(YEAR(Z5),MONTH(Z5)+3,DAY(Z5))+1 -> 45657 | AB5: =AA5 -> 45657 | AC5: =DATE(YEAR(AB5),MONTH(AB5)+3,DAY(AB5)) -> 45747 | AD5: =DATE(YEAR(AC5),MONTH(AC5)+3,DAY(AC5))-1 -> 45838 | AE5: =DATE(YEAR(AD5),MONTH(AD5)+3,DAY(AD5)) -> 45930 | AF5: =DATE(YEAR(AE5),MONTH(AE5)+3,DAY(AE5))+1 -> 46022 | AG5: =AF5 -> 46022 | AH5: =DATE(YEAR(AG5),MONTH(AG5)+3,DAY(AG5)) -> 46112 | AI5: =DATE(YEAR(AH5),MONTH(AH5)+3,DAY(AH5))-1 -> 46203 | AJ5: =DATE(YEAR(AI5),MONTH(AI5)+3,DAY(AI5)) -> 46295 | AK5: =DATE(YEAR(AJ5),MONTH(AJ5)+3,DAY(AJ5))+1 -> 46387 | AL5: =AK5 -> 46387 | AM5: =DATE(YEAR(AL5),MONTH(AL5)+3,DAY(AL5)) -> 46477 | AN5: =DATE(YEAR(AM5),MONTH(AM5)+3,DAY(AM5))-1 -> 46568 | AO5: =DATE(YEAR(AN5),MONTH(AN5)+3,DAY(AN5)) -> 46660 | AP5: =DATE(YEAR(AO5),MONTH(AO5)+3,DAY(AO5))+1 -> 46752 | AQ5: =AP5 -> 46752 | AR5: =DATE(YEAR(AQ5),MONTH(AQ5)+3,DAY(AQ5)) -> 46843 | AS5: =DATE(YEAR(AR5),MONTH(AR5)+3,DAY(AR5))-1 -> 46934 | AT5: =DATE(YEAR(AS5),MONTH(AS5)+3,DAY(AS5)) -> 47026 | AU5: =DATE(YEAR(AT5),MONTH(AT5)+3,DAY(AT5))+1 -> 47118 | AV5: =AU5 -> 47118 | AW5: =DATE(YEAR(AV5),MONTH(AV5)+3,DAY(AV5)) -> 47208 | AX5: =DATE(YEAR(AW5),MONTH(AW5)+3,DAY(AW5))-1 -> 47299 | AY5: =DATE(YEAR(AX5),MONTH(AX5)+3,DAY(AX5)) -> 47391 | AZ5: =DATE(YEAR(AY5),MONTH(AY5)+3,DAY(AY5))+1 -> 47483 | BA5: =AZ5 -> 47483 | BB5: =DATE(YEAR(BA5),MONTH(BA5)+3,DAY(BA5)) -> 47573 | BC5: =DATE(YEAR(BB5),MONTH(BB5)+3,DAY(BB5))-1 -> 47664 | BD5: =DATE(YEAR(BC5),MONTH(BC5)+3,DAY(BC5)) -> 47756 | BE5: =DATE(YEAR(BD5),MONTH(BD5)+3,DAY(BD5))+1 -> 47848 | BF5: =BE5 -> 47848
I6: =YEAR(I5) -> 2021 | J6: =YEAR(J5) -> 2021 | K6: =YEAR(K5) -> 2021 | L6: =YEAR(L5) -> 2021 | M6: =YEAR(M5) -> 2021 | N6: =YEAR(N5) -> 2022 | O6: =YEAR(O5) -> 2022 | P6: =YEAR(P5) -> 2022 | ... BF6: =YEAR(BF5) -> 2030
H7: 2020 | I7: ="1Q"&RIGHT(I6,2) -> 1Q21 | J7: ="2Q"&RIGHT(J6,2) -> 2Q21 | K7: ="3Q"&RIGHT(K6,2) -> 3Q21 | L7: ="4Q"&RIGHT(L6,2) -> 4Q21 | M7: =H7+1 -> 2021 | N7: ="1Q"&RIGHT(N6,2) -> 1Q22 | O7: ="2Q"&RIGHT(O6,2) -> 2Q22 | P7: ="3Q"&RIGHT(P6,2) -> 3Q22 | Q7: ="4Q"&RIGHT(Q6,2) -> 4Q22 | R7: =M7+1 -> 2022 | S7: ="1Q"&RIGHT(S6,2) -> 1Q23 | T7: ="2Q"&RIGHT(T6,2) -> 2Q23 | U7: ="3Q"&RIGHT(U6,2) -> 3Q23 | V7: ="4Q"&RIGHT(V6,2) -> 4Q23 | W7: =R7+1 -> 2023 | X7: ="1Q"&RIGHT(X6,2) -> 1Q24 | Y7: ="2Q"&RIGHT(Y6,2) -> 2Q24 | Z7: ="3Q"&RIGHT(Z6,2) -> 3Q24 | AA7: ="4Q"&RIGHT(AA6,2) -> 4Q24 | AB7: =W7+1 -> 2024 | AC7: ="1Q"&RIGHT(AC6,2) -> 1Q25 | AD7: ="2Q"&RIGHT(AD6,2) -> 2Q25 | AE7: ="3Q"&RIGHT(AE6,2) -> 3Q25 | AF7: ="4Q"&RIGHT(AF6,2) -> 4Q25 | AG7: =AB7+1 -> 2025 | AH7: ="1Q"&RIGHT(AH6,2) -> 1Q26 | AI7: ="2Q"&RIGHT(AI6,2) -> 2Q26 | AJ7: ="3Q"&RIGHT(AJ6,2) -> 3Q26 | AK7: ="4Q"&RIGHT(AK6,2) -> 4Q26 | AL7: =AG7+1 -> 2026 | AM7: ="1Q"&RIGHT(AM6,2) -> 1Q27 | AN7: ="2Q"&RIGHT(AN6,2) -> 2Q27 | AO7: ="3Q"&RIGHT(AO6,2) -> 3Q27 | AP7: ="4Q"&RIGHT(AP6,2) -> 4Q27 | AQ7: =AL7+1 -> 2027 | AR7: ="1Q"&RIGHT(AR6,2) -> 1Q28 | AS7: ="2Q"&RIGHT(AS6,2) -> 2Q28 | AT7: ="3Q"&RIGHT(AT6,2) -> 3Q28 | AU7: ="4Q"&RIGHT(AU6,2) -> 4Q28 | AV7: =AQ7+1 -> 2028 | AW7: ="1Q"&RIGHT(AW6,2) -> 1Q29 | AX7: ="2Q"&RIGHT(AX6,2) -> 2Q29 | AY7: ="3Q"&RIGHT(AY6,2) -> 3Q29 | AZ7: ="4Q"&RIGHT(AZ6,2) -> 4Q29 | BA7: =AV7+1 -> 2029 | BB7: ="1Q"&RIGHT(BB6,2) -> 1Q30 | BC7: ="2Q"&RIGHT(BC6,2) -> 2Q30 | BD7: ="3Q"&RIGHT(BD6,2) -> 3Q30 | BE7: ="4Q"&RIGHT(BE6,2) -> 4Q30 | BF7: =BA7+1 -> 2030
C8: IPCA | M8: 0.1006 | R8: 0.0579 | W8: 0.0468 | AB8: 0.0483 | AG8: 0.0468
C9: GDP BRAZIL | M9: 0.046
C10: CDI | M10: 0.0442 | R10: 0.1239 | W10: 0.1304 | AB10: 0.1064 | AG10: 0.1464
C13: Income Statement | I13: =I7 -> 1Q21 | J13: =J7 -> 2Q21 | K13: =K7 -> 3Q21 | L13: =L7 -> 4Q21 | M13: =M7 -> 2021 | N13: =N7 -> 1Q22 | O13: =O7 -> 2Q22 | P13: =P7 -> 3Q22 | ... BF13: =BF7 -> 2030
C15: Net Revenues | I15: ='Inputs (2)'!D4 -> 59147 | J15: ='Inputs (2)'!E4 -> 67742 | K15: ='Inputs (2)'!F4 -> 73786 | L15: ='Inputs (2)'!G4 -> 84965 | M15: ='Inputs (2)'!H4 -> 285640 | N15: ='Inputs (2)'!I4 -> 90500 | O15: ='Inputs (2)'!J4 -> 115681 | P15: ='Inputs (2)'!K4 -> 112070 | ... AI15: ='Inputs (2)'!AD4 -> 116017 | AJ15: =AE15*(1+AJ16) -> 88963.382 | AK15: =AF15*(1+AK16) -> 85848.923 | AL15: =SUM(AH15:AK15) -> 375967.31 | AM15: =AH15*(1+AM16) -> 88800.671 | AN15: =AI15*(1+AN16) -> 121008.1 | AO15: =AJ15*(1+AO16) -> 92790.623 | AP15: =AK15*(1+AP16) -> 89542.179 | AQ15: =SUM(AM15:AP15) -> 392141.57 | AR15: =AM15*(1+AR16) -> 92176.908 | AS15: =AN15*(1+AS16) -> 125608.87 | AT15: =AO15*(1+AT16) -> 96318.56 | AU15: =AP15*(1+AU16) -> 92946.608 | AV15: =SUM(AR15:AU15) -> 407050.95 | AW15: =AR15*(1+AW16) -> 95220.627 | AX15: =AS15*(1+AX16) -> 129756.53 | AY15: =AT15*(1+AY16) -> 99499.038 | AZ15: =AU15*(1+AZ16) -> 96015.743 | BA15: =SUM(AW15:AZ15) -> 420491.94 | BB15: =AW15*(1+BB16) -> 97888.748 | BC15: =AX15*(1+BC16) -> 133392.36 | BD15: =AY15*(1+BD16) -> 102287.04 | BE15: =AZ15*(1+BE16) -> 98706.143 | BF15: =SUM(BB15:BE15) -> 432274.29
C16: % YoY | N16: =IFERROR(N15/I15-1,"") -> 0.53008606 | O16: =IFERROR(O15/J15-1,"") -> 0.70767028 | P16: =IFERROR(P15/K15-1,"") -> 0.51885181 | Q16: =IFERROR(Q15/L15-1,"") -> 0.12315659 | R16: =IFERROR(R15/M15-1,"") -> 0.44825655 | S16: =IFERROR(S15/N15-1,"") -> -0.043491713 | T16: =IFERROR(T15/O15-1,"") -> -0.28325308 | U16: =IFERROR(U15/P15-1,"") -> -0.19014901 | ... AI16: =IFERROR(AI15/AD15-1,"") -> 0.42341668 | AJ16: =Control!$B$18 -> 0.043020404 | AK16: =Control!$B$18 -> 0.043020404 | AL16: =IFERROR(AL15/AG15-1,"") -> 0.13162042 | AM16: =Control!$C$18 -> 0.043020404 | AN16: =Control!$C$18 -> 0.043020404 | AO16: =Control!$C$18 -> 0.043020404 | AP16: =Control!$C$18 -> 0.043020404 | AQ16: =IFERROR(AQ15/AL15-1,"") -> 0.043020404 | AR16: =Control!$D$18 -> 0.038020404 | AS16: =Control!$D$18 -> 0.038020404 | AT16: =Control!$D$18 -> 0.038020404 | AU16: =Control!$D$18 -> 0.038020404 | AV16: =IFERROR(AV15/AQ15-1,"") -> 0.038020404 | AW16: =Control!$E$18 -> 0.033020404 | AX16: =Control!$E$18 -> 0.033020404 | AY16: =Control!$E$18 -> 0.033020404 | AZ16: =Control!$E$18 -> 0.033020404 | BA16: =IFERROR(BA15/AV15-1,"") -> 0.033020404 | BB16: =Control!$F$18 -> 0.028020404 | BC16: =Control!$F$18 -> 0.028020404 | BD16: =Control!$F$18 -> 0.028020404 | BE16: =Control!$F$18 -> 0.028020404 | BF16: =IFERROR(BF15/BA15-1,"") -> 0.028020404
C17: Check Receita | I17: =IF(ISNUMBER(I23),I23,"") | J17: =IF(ISNUMBER(J23),J23,"") | K17: =IF(ISNUMBER(K23),K23,"") | L17: =IF(ISNUMBER(L23),L23,"") | M17: =IF(ISNUMBER(M23),M23,"") | N17: =IF(ISNUMBER(N23),N23,"") -> 0 | O17: =IF(ISNUMBER(O23),O23,"") -> 0 | P17: =IF(ISNUMBER(P23),P23,"") -> 0 | ... AI17: =IF(ISNUMBER(AI23),AI23,"") -> 0
C18: Composição da receita (USD milhões; a partir do 4T20) | D18: =D7 -> 0 | E18: =E7 -> 0 | F18: =F7 -> 0 | G18: =G7 -> 0 | H18: =H7 -> 2020 | I18: =I7 -> 1Q21 | J18: =J7 -> 2Q21 | K18: =K7 -> 3Q21 | ... AI18: =AI7 -> 2Q26
C19: Vendas e outras receitas operacionais | D19: =IFERROR(INDEX('Inputs (2)'!$D$53:$AL$53,MATCH(D$7&"",'Inputs (2)'!$D$2:$AL$2,0)),"") | E19: =IFERROR(INDEX('Inputs (2)'!$D$53:$AL$53,MATCH(E$7&"",'Inputs (2)'!$D$2:$AL$2,0)),"") | F19: =IFERROR(INDEX('Inputs (2)'!$D$53:$AL$53,MATCH(F$7&"",'Inputs (2)'!$D$2:$AL$2,0)),"") | G19: =IFERROR(INDEX('Inputs (2)'!$D$53:$AL$53,MATCH(G$7&"",'Inputs (2)'!$D$2:$AL$2,0)),"") | H19: =IF(COUNT(D19:G19)=4,SUM(D19:G19),"") | I19: =IFERROR(INDEX('Inputs (2)'!$D$53:$AL$53,MATCH(I$7&"",'Inputs (2)'!$D$2:$AL$2,0)),"") | J19: =IFERROR(INDEX('Inputs (2)'!$D$53:$AL$53,MATCH(J$7&"",'Inputs (2)'!$D$2:$AL$2,0)),"") | K19: =IFERROR(INDEX('Inputs (2)'!$D$53:$AL$53,MATCH(K$7&"",'Inputs (2)'!$D$2:$AL$2,0)),"") | L19: =IFERROR(INDEX('Inputs (2)'!$D$53:$AL$53,MATCH(L$7&"",'Inputs (2)'!$D$2:$AL$2,0)),"") | M19: =IF(COUNT(I19:L19)=4,SUM(I19:L19),"") | N19: =IFERROR(INDEX('Inputs (2)'!$D$53:$AL$53,MATCH(N$7&"",'Inputs (2)'!$D$2:$AL$2,0)),"") -> 87734 | O19: =IFERROR(INDEX('Inputs (2)'!$D$53:$AL$53,MATCH(O$7&"",'Inputs (2)'!$D$2:$AL$2,0)),"") -> 111265 | P19: =IFERROR(INDEX('Inputs (2)'!$D$53:$AL$53,MATCH(P$7&"",'Inputs (2)'!$D$2:$AL$2,0)),"") -> 106512 | Q19: =IFERROR(INDEX('Inputs (2)'!$D$53:$AL$53,MATCH(Q$7&"",'Inputs (2)'!$D$2:$AL$2,0)),"") -> 93164 | R19: =IF(COUNT(N19:Q19)=4,SUM(N19:Q19),"") -> 398675 | S19: =IFERROR(INDEX('Inputs (2)'!$D$53:$AL$53,MATCH(S$7&"",'Inputs (2)'!$D$2:$AL$2,0)),"") -> 83644 | T19: =IFERROR(INDEX('Inputs (2)'!$D$53:$AL$53,MATCH(T$7&"",'Inputs (2)'!$D$2:$AL$2,0)),"") -> 80795 | U19: =IFERROR(INDEX('Inputs (2)'!$D$53:$AL$53,MATCH(U$7&"",'Inputs (2)'!$D$2:$AL$2,0)),"") -> 88570 | V19: =IFERROR(INDEX('Inputs (2)'!$D$53:$AL$53,MATCH(V$7&"",'Inputs (2)'!$D$2:$AL$2,0)),"") -> 81688 | W19: =IF(COUNT(S19:V19)=4,SUM(S19:V19),"") -> 334697 | X19: =IFERROR(INDEX('Inputs (2)'!$D$53:$AL$53,MATCH(X$7&"",'Inputs (2)'!$D$2:$AL$2,0)),"") -> 80411 | Y19: =IFERROR(INDEX('Inputs (2)'!$D$53:$AL$53,MATCH(Y$7&"",'Inputs (2)'!$D$2:$AL$2,0)),"") -> 89986 | Z19: =IFERROR(INDEX('Inputs (2)'!$D$53:$AL$53,MATCH(Z$7&"",'Inputs (2)'!$D$2:$AL$2,0)),"") -> 87792 | AA19: =IFERROR(INDEX('Inputs (2)'!$D$53:$AL$53,MATCH(AA$7&"",'Inputs (2)'!$D$2:$AL$2,0)),"") -> 81058 | AB19: =IF(COUNT(X19:AA19)=4,SUM(X19:AA19),"") -> 339247 | AC19: =IFERROR(INDEX('Inputs (2)'!$D$53:$AL$53,MATCH(AC$7&"",'Inputs (2)'!$D$2:$AL$2,0)),"") -> 81058 | AD19: =IFERROR(INDEX('Inputs (2)'!$D$53:$AL$53,MATCH(AD$7&"",'Inputs (2)'!$D$2:$AL$2,0)),"") -> 79477 | AE19: =IFERROR(INDEX('Inputs (2)'!$D$53:$AL$53,MATCH(AE$7&"",'Inputs (2)'!$D$2:$AL$2,0)),"") -> 83331 | AF19: =IFERROR(INDEX('Inputs (2)'!$D$53:$AL$53,MATCH(AF$7&"",'Inputs (2)'!$D$2:$AL$2,0)),"") -> 80039 | AG19: =IF(COUNT(AC19:AF19)=4,SUM(AC19:AF19),"") -> 323905 | AH19: =IFERROR(INDEX('Inputs (2)'!$D$53:$AL$53,MATCH(AH$7&"",'Inputs (2)'!$D$2:$AL$2,0)),"") -> 83161 | AI19: =IFERROR(INDEX('Inputs (2)'!$D$53:$AL$53,MATCH(AI$7&"",'Inputs (2)'!$D$2:$AL$2,0)),"") -> 114529
C20: Equivalência patrimonial | D20: =IFERROR(INDEX('Inputs (2)'!$D$54:$AL$54,MATCH(D$7&"",'Inputs (2)'!$D$2:$AL$2,0)),"") | E20: =IFERROR(INDEX('Inputs (2)'!$D$54:$AL$54,MATCH(E$7&"",'Inputs (2)'!$D$2:$AL$2,0)),"") | F20: =IFERROR(INDEX('Inputs (2)'!$D$54:$AL$54,MATCH(F$7&"",'Inputs (2)'!$D$2:$AL$2,0)),"") | G20: =IFERROR(INDEX('Inputs (2)'!$D$54:$AL$54,MATCH(G$7&"",'Inputs (2)'!$D$2:$AL$2,0)),"") | H20: =IF(COUNT(D20:G20)=4,SUM(D20:G20),"") | I20: =IFERROR(INDEX('Inputs (2)'!$D$54:$AL$54,MATCH(I$7&"",'Inputs (2)'!$D$2:$AL$2,0)),"") | J20: =IFERROR(INDEX('Inputs (2)'!$D$54:$AL$54,MATCH(J$7&"",'Inputs (2)'!$D$2:$AL$2,0)),"") | K20: =IFERROR(INDEX('Inputs (2)'!$D$54:$AL$54,MATCH(K$7&"",'Inputs (2)'!$D$2:$AL$2,0)),"") | L20: =IFERROR(INDEX('Inputs (2)'!$D$54:$AL$54,MATCH(L$7&"",'Inputs (2)'!$D$2:$AL$2,0)),"") | M20: =IF(COUNT(I20:L20)=4,SUM(I20:L20),"") | N20: =IFERROR(INDEX('Inputs (2)'!$D$54:$AL$54,MATCH(N$7&"",'Inputs (2)'!$D$2:$AL$2,0)),"") -> 2538 | O20: =IFERROR(INDEX('Inputs (2)'!$D$54:$AL$54,MATCH(O$7&"",'Inputs (2)'!$D$2:$AL$2,0)),"") -> 3688 | P20: =IFERROR(INDEX('Inputs (2)'!$D$54:$AL$54,MATCH(P$7&"",'Inputs (2)'!$D$2:$AL$2,0)),"") -> 4632 | Q20: =IFERROR(INDEX('Inputs (2)'!$D$54:$AL$54,MATCH(Q$7&"",'Inputs (2)'!$D$2:$AL$2,0)),"") -> 605 | R20: =IF(COUNT(N20:Q20)=4,SUM(N20:Q20),"") -> 11463 | S20: =IFERROR(INDEX('Inputs (2)'!$D$54:$AL$54,MATCH(S$7&"",'Inputs (2)'!$D$2:$AL$2,0)),"") -> 2381 | T20: =IFERROR(INDEX('Inputs (2)'!$D$54:$AL$54,MATCH(T$7&"",'Inputs (2)'!$D$2:$AL$2,0)),"") -> 1382 | U20: =IFERROR(INDEX('Inputs (2)'!$D$54:$AL$54,MATCH(U$7&"",'Inputs (2)'!$D$2:$AL$2,0)),"") -> 1457 | V20: =IFERROR(INDEX('Inputs (2)'!$D$54:$AL$54,MATCH(V$7&"",'Inputs (2)'!$D$2:$AL$2,0)),"") -> 1165 | W20: =IF(COUNT(S20:V20)=4,SUM(S20:V20),"") -> 6385 | X20: =IFERROR(INDEX('Inputs (2)'!$D$54:$AL$54,MATCH(X$7&"",'Inputs (2)'!$D$2:$AL$2,0)),"") -> 1842 | Y20: =IFERROR(INDEX('Inputs (2)'!$D$54:$AL$54,MATCH(Y$7&"",'Inputs (2)'!$D$2:$AL$2,0)),"") -> 1744 | Z20: =IFERROR(INDEX('Inputs (2)'!$D$54:$AL$54,MATCH(Z$7&"",'Inputs (2)'!$D$2:$AL$2,0)),"") -> 1481 | AA20: =IFERROR(INDEX('Inputs (2)'!$D$54:$AL$54,MATCH(AA$7&"",'Inputs (2)'!$D$2:$AL$2,0)),"") -> 1127 | AB20: =IF(COUNT(X20:AA20)=4,SUM(X20:AA20),"") -> 6194 | AC20: =IFERROR(INDEX('Inputs (2)'!$D$54:$AL$54,MATCH(AC$7&"",'Inputs (2)'!$D$2:$AL$2,0)),"") -> 1369 | AD20: =IFERROR(INDEX('Inputs (2)'!$D$54:$AL$54,MATCH(AD$7&"",'Inputs (2)'!$D$2:$AL$2,0)),"") -> 1462 | AE20: =IFERROR(INDEX('Inputs (2)'!$D$54:$AL$54,MATCH(AE$7&"",'Inputs (2)'!$D$2:$AL$2,0)),"") -> 1267 | AF20: =IFERROR(INDEX('Inputs (2)'!$D$54:$AL$54,MATCH(AF$7&"",'Inputs (2)'!$D$2:$AL$2,0)),"") -> 966 | AG20: =IF(COUNT(AC20:AF20)=4,SUM(AC20:AF20),"") -> 5064 | AH20: =IFERROR(INDEX('Inputs (2)'!$D$54:$AL$54,MATCH(AH$7&"",'Inputs (2)'!$D$2:$AL$2,0)),"") -> 1369 | AI20: =IFERROR(INDEX('Inputs (2)'!$D$54:$AL$54,MATCH(AI$7&"",'Inputs (2)'!$D$2:$AL$2,0)),"") -> 893
C21: Outras receitas | D21: =IFERROR(INDEX('Inputs (2)'!$D$55:$AL$55,MATCH(D$7&"",'Inputs (2)'!$D$2:$AL$2,0)),"") | E21: =IFERROR(INDEX('Inputs (2)'!$D$55:$AL$55,MATCH(E$7&"",'Inputs (2)'!$D$2:$AL$2,0)),"") | F21: =IFERROR(INDEX('Inputs (2)'!$D$55:$AL$55,MATCH(F$7&"",'Inputs (2)'!$D$2:$AL$2,0)),"") | G21: =IFERROR(INDEX('Inputs (2)'!$D$55:$AL$55,MATCH(G$7&"",'Inputs (2)'!$D$2:$AL$2,0)),"") | H21: =IF(COUNT(D21:G21)=4,SUM(D21:G21),"") | I21: =IFERROR(INDEX('Inputs (2)'!$D$55:$AL$55,MATCH(I$7&"",'Inputs (2)'!$D$2:$AL$2,0)),"") | J21: =IFERROR(INDEX('Inputs (2)'!$D$55:$AL$55,MATCH(J$7&"",'Inputs (2)'!$D$2:$AL$2,0)),"") | K21: =IFERROR(INDEX('Inputs (2)'!$D$55:$AL$55,MATCH(K$7&"",'Inputs (2)'!$D$2:$AL$2,0)),"") | L21: =IFERROR(INDEX('Inputs (2)'!$D$55:$AL$55,MATCH(L$7&"",'Inputs (2)'!$D$2:$AL$2,0)),"") | M21: =IF(COUNT(I21:L21)=4,SUM(I21:L21),"") | N21: =IFERROR(INDEX('Inputs (2)'!$D$55:$AL$55,MATCH(N$7&"",'Inputs (2)'!$D$2:$AL$2,0)),"") -> 228 | O21: =IFERROR(INDEX('Inputs (2)'!$D$55:$AL$55,MATCH(O$7&"",'Inputs (2)'!$D$2:$AL$2,0)),"") -> 728 | P21: =IFERROR(INDEX('Inputs (2)'!$D$55:$AL$55,MATCH(P$7&"",'Inputs (2)'!$D$2:$AL$2,0)),"") -> 926 | Q21: =IFERROR(INDEX('Inputs (2)'!$D$55:$AL$55,MATCH(Q$7&"",'Inputs (2)'!$D$2:$AL$2,0)),"") -> 1660 | R21: =IF(COUNT(N21:Q21)=4,SUM(N21:Q21),"") -> 3542 | S21: =IFERROR(INDEX('Inputs (2)'!$D$55:$AL$55,MATCH(S$7&"",'Inputs (2)'!$D$2:$AL$2,0)),"") -> 539 | T21: =IFERROR(INDEX('Inputs (2)'!$D$55:$AL$55,MATCH(T$7&"",'Inputs (2)'!$D$2:$AL$2,0)),"") -> 737 | U21: =IFERROR(INDEX('Inputs (2)'!$D$55:$AL$55,MATCH(U$7&"",'Inputs (2)'!$D$2:$AL$2,0)),"") -> 733 | V21: =IFERROR(INDEX('Inputs (2)'!$D$55:$AL$55,MATCH(V$7&"",'Inputs (2)'!$D$2:$AL$2,0)),"") -> 1491 | W21: =IF(COUNT(S21:V21)=4,SUM(S21:V21),"") -> 3500 | X21: =IFERROR(INDEX('Inputs (2)'!$D$55:$AL$55,MATCH(X$7&"",'Inputs (2)'!$D$2:$AL$2,0)),"") -> 830 | Y21: =IFERROR(INDEX('Inputs (2)'!$D$55:$AL$55,MATCH(Y$7&"",'Inputs (2)'!$D$2:$AL$2,0)),"") -> 1330 | Z21: =IFERROR(INDEX('Inputs (2)'!$D$55:$AL$55,MATCH(Z$7&"",'Inputs (2)'!$D$2:$AL$2,0)),"") -> 743 | AA21: =IFERROR(INDEX('Inputs (2)'!$D$55:$AL$55,MATCH(AA$7&"",'Inputs (2)'!$D$2:$AL$2,0)),"") -> 1241 | AB21: =IF(COUNT(X21:AA21)=4,SUM(X21:AA21),"") -> 4144 | AC21: =IFERROR(INDEX('Inputs (2)'!$D$55:$AL$55,MATCH(AC$7&"",'Inputs (2)'!$D$2:$AL$2,0)),"") -> 703 | AD21: =IFERROR(INDEX('Inputs (2)'!$D$55:$AL$55,MATCH(AD$7&"",'Inputs (2)'!$D$2:$AL$2,0)),"") -> 567 | AE21: =IFERROR(INDEX('Inputs (2)'!$D$55:$AL$55,MATCH(AE$7&"",'Inputs (2)'!$D$2:$AL$2,0)),"") -> 696 | AF21: =IFERROR(INDEX('Inputs (2)'!$D$55:$AL$55,MATCH(AF$7&"",'Inputs (2)'!$D$2:$AL$2,0)),"") -> 1303 | AG21: =IF(COUNT(AC21:AF21)=4,SUM(AC21:AF21),"") -> 3269 | AH21: =IFERROR(INDEX('Inputs (2)'!$D$55:$AL$55,MATCH(AH$7&"",'Inputs (2)'!$D$2:$AL$2,0)),"") -> 608 | AI21: =IFERROR(INDEX('Inputs (2)'!$D$55:$AL$55,MATCH(AI$7&"",'Inputs (2)'!$D$2:$AL$2,0)),"") -> 595
