Workbook
Name beta_observed: Valuation!$D$93
Name beta_observed_unlevered: #REF!
Name beta_unlev_comps: #REF!
Name cirkbreak: #REF!
Name costdebtfirm: #REF!
Name costequity: #REF!
Name Debt: #REF!
Name debt_weight: #REF!
Name last_close: Valuation!$G$7
Name Market_Equity: #REF!
Name midyear: #REF!
Name Net_Debt: #REF!
Name range: #REF!
Name Stub_year_fraction: #REF!
Name ticker: Valuation!$D$7
Name Useful_Life_of_Depreciable_PP_E: "PPElife"
Name beta_observed: #REF!
Name ticker: #REF!
Name costdebtfirm: Valuation!$D$86
Name costequity: Valuation!$D$94
Name debt: Valuation!$G$88
Name debt_weight: Valuation!$J$88
Name g: Valuation!$D$63
Name market_equity: Valuation!$G$89
Name noplat_t1: Valuation!$D$65
Name relevered_beta: Valuation!$M$102
Name risk_free_rate: Valuation!$D$91
Name risk_premium: Valuation!$D$92
Name ronic: Valuation!$D$64
Name stub_year_fraction: Valuation!$D$11
Name totalcap: Valuation!$G$90
Name wacc: Valuation!$D$12
Name scenario: Valuation!$E$8

Sheet Inputs
A1: Fator p/ milhões: | B1: 0.001 | D1: Alupar Investimento S.A. (ALUP11) - fonte: planilha de fundamentos do RI, aba "Consolidado" (IFRS, consolidado). Moeda: BRL. Unidade dos brutos: R$ mil. Fator converte p/ R$ milhoes.
J2: Rotulo na fonte | K2: 1T20 | L2: 2T20 | M2: 3T20 | N2: 4T20 | O2: 1T21 | P2: 2T21 | Q2: 3T21 | R2: 4T21 | S2: 1T22 | T2: 2T22 | U2: 3T22 | V2: 4T22 | W2: 1T23 | X2: 2T23 | Y2: 3T23 | Z2: 4T23 | AA2: 1T24 | AB2: 2T24 | AC2: 3T24 | AD2: 4T24 | AE2: 1T25 | AF2: 2T25 | AG2: 3T25 | AH2: 4T25 | AI2: 1T26 | AJ2: 2T26
A4: COD1 | B4: SINAL1 | C4: COD2 | D4: SINAL2 | E4: COD3 | F4: SINAL3 | G4: UNID | H4: Conta (PT) / origem | I4: Account (EN) | J4: ORIGEM | K4: 1Q20 | L4: 2Q20 | M4: 3Q20 | N4: 4Q20 | O4: 1Q21 | P4: 2Q21 | Q4: 3Q21 | R4: 4Q21 | S4: 1Q22 | T4: 2Q22 | U4: 3Q22 | V4: 4Q22 | W4: 1Q23 | X4: 2Q23 | Y4: 3Q23 | Z4: 4Q23 | AA4: 1Q24 | AB4: 2Q24 | AC4: 3Q24 | AD4: 4Q24 | AE4: 1Q25 | AF4: 2Q25 | AG4: 3Q25 | AH4: 4Q25 | AI4: 1Q26 | AJ4: 2Q26
H5: DRE (R$ mil, trimestre isolado; aba Consolidado IFRS). Receita = componentes da receita bruta + deducoes (subtotal); custos e despesas negativos na fonte
A6: 1 | B6: 1 | G6: moeda | H6: Receita de transmissão de energia (RAP) / Energy Transmission System (l.104) | J6: fonte | K6: 54546 | L6: 78752 | M6: 80994 | N6: 376909 | O6: 94801 | P6: 101892 | Q6: 121340 | R6: 113606 | S6: 132054 | T6: 133093 | U6: 151165 | V6: 150308 | W6: 151077 | X6: 158369 | Y6: 147167 | Z6: 149544 | AA6: 153460 | AB6: 154759 | AC6: 162723 | AD6: 151746 | AE6: 159716 | AF6: 161370 | AG6: 172356 | AH6: 203391 | AI6: 221177 | AJ6: 213113
A7: 1 | B7: 1 | G7: moeda | H7: Suprimento de energia / Energy Supply (l.105) | J7: fonte | K7: 179039 | L7: 119215 | M7: 152402 | N7: 195219 | O7: 181526 | P7: 171678 | Q7: 237412 | R7: 207020 | S7: 185262 | T7: 160392 | U7: 167156 | V7: 182548 | W7: 199097 | X7: 199602 | Y7: 210009 | Z7: 207475 | AA7: 200808 | AB7: 193980 | AC7: 203699 | AD7: 257183 | AE7: 231888 | AF7: 242027 | AG7: 232259 | AH7: 237413 | AI7: 283621 | AJ7: 240198
A8: 1 | B8: 1 | G8: moeda | H8: Remuneração do ativo contratual da concessão / Remuneration of Contractual Assets (l.106) | J8: fonte | K8: 326415 | L8: 217093 | M8: 423869 | N8: 1298898 | O8: 976410 | P8: 1008846 | Q8: 674156 | R8: 881589 | S8: 985322 | T8: 610789 | U8: 401708 | V8: 354639 | W8: 483941 | X8: 397997 | Y8: 395714 | Z8: 395798 | AA8: 398299 | AB8: 401372 | AC8: 428451 | AD8: 407848 | AE8: 417301 | AF8: 418833 | AG8: 442498 | AH8: 468947 | AI8: 426713 | AJ8: 436556
A9: 1 | B9: 1 | G9: moeda | H9: Remuneração do ativo financeiro da concessão / Remuneration of Financial Assets (l.107) | J9: fonte | K9: 0 | L9: 0 | M9: 0 | N9: 0 | O9: 0 | P9: 0 | Q9: 0 | R9: 0 | S9: 0 | T9: 0 | U9: 0 | V9: 0 | W9: 0 | X9: 0 | Y9: 0 | Z9: 0 | AA9: 0 | AB9: 0 | AC9: 0 | AD9: 0 | AE9: 0 | AF9: 0 | AG9: 0 | AH9: 0 | AI9: 0 | AJ9: 0
A10: 1 | B10: 1 | G10: moeda | H10: Correção monetária do ativo contratual / Monetary Update of Contractual Assets (l.108) | J10: fonte | K10: 0 | L10: 0 | M10: 0 | N10: 0 | O10: 0 | P10: 0 | Q10: 0 | R10: 0 | S10: 0 | T10: 334986 | U10: -25281 | V10: 75383 | W10: 191723 | X10: 39452 | Y10: -61721 | Z10: 154100 | AA10: 243913 | AB10: 168422 | AC10: 128826 | AD10: 310931 | AE10: 359799 | AF10: 160033 | AG10: -5485 | AH10: 136574 | AI10: 187379 | AJ10: 482966
A11: 1 | B11: 1 | G11: moeda | H11: Receita de infraestrutura / Infrastructure Revenue (l.109) | J11: fonte | K11: 778224 | L11: 716276 | M11: 980233 | N11: 766981 | O11: 505633 | P11: 190968 | Q11: 245421 | R11: 90901 | S11: 109284 | T11: 48345 | U11: 28371 | V11: 64481 | W11: 77474 | X11: 46838 | Y11: 33037 | Z11: 50753 | AA11: 103932 | AB11: 134115 | AC11: 102852 | AD11: 99966 | AE11: 168103 | AF11: 176178 | AG11: 228238 | AH11: 237882 | AI11: 266965 | AJ11: 419162
A12: 1 | B12: 1 | G12: moeda | H12: Prestação de serviços de garantia / Consultancy and advisory services in the regulatory area (l.110) | J12: fonte | K12: 0 | L12: 0 | M12: 0 | N12: 0 | O12: 0 | P12: 0 | Q12: 0 | R12: 0 | S12: 0 | T12: 0 | U12: 0 | V12: 0 | W12: 0 | X12: 0 | Y12: 0 | Z12: 0 | AA12: 0 | AB12: 0 | AC12: 0 | AD12: 0 | AE12: 0 | AF12: 0 | AG12: 0 | AH12: 0 | AI12: 0 | AJ12: 0
A13: 1 | B13: 1 | G13: moeda | H13: Outras receitas operacionais / O&M Services (l.111) | J13: fonte | K13: 0 | L13: 0 | M13: 0 | N13: 0 | O13: 0 | P13: 0 | Q13: 0 | R13: 0 | S13: 0 | T13: 0 | U13: 0 | V13: 0 | W13: 8251 | X13: -4736 | Y13: 1442 | Z13: 1502 | AA13: 1350 | AB13: 1437 | AC13: 1132 | AD13: 997 | AE13: 12156 | AF13: 135 | AG13: 132 | AH13: 133 | AI13: 4187 | AJ13: 124
A14: 1 | B14: 1 | G14: moeda | H14: Deduções da receita operacional / Deductions from operating revenues (l.113) | J14: fonte | K14: -121297 | L14: -104360 | M14: -146175 | N14: -232488 | O14: -156896 | P14: -136243 | Q14: -110677 | R14: -165175 | S14: -131402 | T14: -119362 | U14: -70460 | V14: -95073 | W14: -107566 | X14: -57366 | Y14: -76691 | Z14: -80901 | AA14: -105227 | AB14: -100393 | AC14: -99116 | AD14: -105361 | AE14: -125232 | AF14: -111436 | AG14: -106645 | AH14: -120681 | AI14: -134407 | AJ14: -164834
A15: 2 | B15: 1 | G15: moeda | H15: Compra de Energia / Energy purchase (l.130) | J15: fonte | K15: -32699 | L15: -26099 | M15: -35062 | N15: -47912 | O15: -26695 | P15: -33948 | Q15: -50791 | R15: -34731 | S15: -12662 | T15: -6806 | U15: -14184 | V15: -8829 | W15: -12730 | X15: -9126 | Y15: -12693 | Z15: -28433 | AA15: -11597 | AB15: -10327 | AC15: -35334 | AD15: -62038 | AE15: -31340 | AF15: -25294 | AG15: -43664 | AH15: -50722 | AI15: -44591 | AJ15: -38203
A16: 2 | B16: 1 | G16: moeda | H16: Custo dos serviços prestados / Cost of Rendered Services (l.131) | J16: fonte | K16: -44865 | L16: -49574 | M16: -53418 | N16: -77825 | O16: -51089 | P16: -56671 | Q16: -72341 | R16: -5524 | S16: -62463 | T16: -72183 | U16: -79556 | V16: -91088 | W16: -78523 | X16: -70345 | Y16: -85709 | Z16: -82765 | AA16: -81490 | AB16: -89146 | AC16: -89797 | AD16: -109700 | AE16: -99565 | AF16: -95678 | AG16: -95957 | AH16: -114899 | AI16: -94540 | AJ16: -106727
A17: 2 | B17: 1 | G17: moeda | H17: Custo de construção / Construction Costs (l.132) | J17: fonte | K17: -500082 | L17: -500547 | M17: -653799 | N17: -549845 | O17: -393249 | P17: -110635 | Q17: -163915 | R17: -265541 | S17: -59664 | T17: -44643 | U17: -37678 | V17: -61157 | W17: -70465 | X17: -57267 | Y17: -63336 | Z17: -78497 | AA17: -75083 | AB17: -80965 | AC17: -121828 | AD17: -155612 | AE17: -164293 | AF17: -161634 | AG17: -106197 | AH17: -170320 | AI17: -269988 | AJ17: -379246
... A31: 9 | B31: 1 | G31: moeda | H31: Participação de acionistas não controladores / Non-controlling interest (l.163) | J31: fonte | K31: -198384 | L31: -125868 | M31: -265868 | N31: -523297 | O31: -337471 | P31: -344143 | Q31: -188716 | R31: -137085 | S31: -307900 | T31: -187923 | U31: -134594 | V31: -114990 | W31: -156618 | X31: -117395 | Y31: -67187 | Z31: -115723 | AA31: -147894 | AB31: -156347 | AC31: -281625 | AD31: -187950 | AE31: -186523 | AF31: -138966 | AG31: -43206 | AH31: -148939 | AI31: -139779 | AJ31: -295846
H32: DRE - subtotais divulgados (memoria)
G33: moeda | H33: Receita operacional bruta / Gross Operating Revenue (l.103) | J33: memoria | K33: 1338224 | L33: 1131336 | M33: 1637498 | N33: 2638007 | O33: 1758370 | P33: 1473384 | Q33: 1278329 | R33: 1293116 | S33: 1411922 | T33: 1287605 | U33: 723119 | V33: 827359 | W33: 1111563 | X33: 837522 | Y33: 725648 | Z33: 959172 | AA33: 1101762 | AB33: 1054085 | AC33: 1027683 | AD33: 1228671 | AE33: 1348963 | AF33: 1158576 | AG33: 1069998 | AH33: 1284340 | AI33: 1390042 | AJ33: 1792119
G34: moeda | H34: Custos / Costs (l.129) | J34: memoria | K34: -604040 | L34: -623099 | M34: -769661 | N34: -702755 | O34: -498916 | P34: -229551 | Q34: -330583 | R34: -340576 | S34: -170289 | T34: -158203 | U34: -166680 | V34: -197481 | W34: -194916 | X34: -171600 | Y34: -201159 | Z34: -230092 | AA34: -209529 | AB34: -222927 | AC34: -291307 | AD34: -371210 | AE34: -334776 | AF34: -326528 | AG34: -291604 | AH34: -385200 | AI34: -460362 | AJ34: -573656
G35: moeda | H35: Lucro antes do resultado financeiro / Income before financial result (l.143) | J35: memoria | K35: 581800 | L35: 372133 | M35: 699950 | N35: 1664671 | O35: 1078685 | P35: 1100133 | Q35: 858378 | R35: 742816 | S35: 1093036 | T35: 836673 | U35: 450425 | V35: 485821 | W35: 776774 | X35: 599764 | Y35: 414163 | Z35: 566994 | AA35: 768929 | AB35: 741690 | AC35: 646938 | AD35: 735079 | AE35: 891274 | AF35: 555102 | AG35: 936989 | AH35: 731154 | AI35: 755987 | AJ35: 1005418
G36: moeda | H36: Despesas financeiras / Financial Expenses (l.145) | J36: memoria | K36: -110320 | L36: -84432 | M36: -104796 | N36: -213505 | O36: -220925 | P36: -220616 | Q36: -312051 | R36: -269776 | S36: -275120 | T36: -409748 | U36: -255871 | V36: -279287 | W36: -354499 | X36: -264197 | Y36: -286255 | Z36: -254432 | AA36: -326855 | AB36: -314151 | AC36: -275474 | AD36: -353327 | AE36: -379058 | AF36: -320431 | AG36: -311305 | AH36: -319449 | AI36: -398261 | AJ36: -367445
G37: moeda | H37: Receitas financeiras / Financial Revenue (l.149) | J37: memoria | K37: 18050 | L37: 15361 | M37: 7682 | N37: 10221 | O37: 10815 | P37: 19481 | Q37: 24304 | R37: 53223 | S37: 49812 | T37: 68796 | U37: 73153 | V37: 62139 | W37: 69850 | X37: 69451 | Y37: 72068 | Z37: 70582 | AA37: 72974 | AB37: 80069 | AC37: 84033 | AD37: 81612 | AE37: 104321 | AF37: 114439 | AG37: 98737 | AH37: 140909 | AI37: 96147 | AJ37: 129420
G38: moeda | H38: Lucro antes da Contribuição social e Imposto de Renda / Income before social contribution and income tax (l.153) | J38: memoria | K38: 489530 | L38: 303062 | M38: 602836 | N38: 1461387 | O38: 868575 | P38: 898998 | Q38: 570631 | R38: 526263 | S38: 867728 | T38: 495721 | U38: 267707 | V38: 268673 | W38: 492125 | X38: 405018 | Y38: 199976 | Z38: 383144 | AA38: 515048 | AB38: 507608 | AC38: 455497 | AD38: 463364 | AE38: 616537 | AF38: 349110 | AG38: 724421 | AH38: 552614 | AI38: 453873 | AJ38: 767393
G39: moeda | H39: Lucro antes da participação de não controladores / Net Income before the non-controlling interest (l.161) | J39: memoria | K39: 377533 | L39: 197977 | M39: 447082 | N39: 1032913 | O39: 660887 | P39: 676488 | Q39: 429032 | R39: 356409 | S39: 738879 | T39: 367931 | U39: 250270 | V39: 306793 | W39: 387328 | X39: 339581 | Y39: 167192 | Z39: 256885 | AA39: 402838 | AB39: 393417 | AC39: 645379 | AD39: 418272 | AE39: 485300 | AF39: 283833 | AG39: 532596 | AH39: 431464 | AI39: 337846 | AJ39: 712472
A40: 44 | B40: 1 | G40: moeda | H40: Lucro Líquido do Exercício / Net Income (l.165) - COD 44 alimenta o check IS do Model (linha 4) | J40: memoria | K40: 179149 | L40: 72109 | M40: 181214 | N40: 509616 | O40: 323416 | P40: 332345 | Q40: 240316 | R40: 219324 | S40: 430979 | T40: 180008 | U40: 115676 | V40: 191803 | W40: 230710 | X40: 222186 | Y40: 100005 | Z40: 141162 | AA40: 254944 | AB40: 237070 | AC40: 363754 | AD40: 230322 | AE40: 298777 | AF40: 144867 | AG40: 489390 | AH40: 282525 | AI40: 198067 | AJ40: 416626
H41: BALANCO (R$ mil, saldo de fim de trimestre). 3T23: bloco do PL realinhado (ver nota na linha do capital social)
A42: 11 | B42: 1 | G42: moeda | H42: Caixa equivalentes de caixa / Cash and Cash Equivalents (l.10) | J42: fonte | K42: 628105 | L42: 606617 | M42: 632296 | N42: 674609 | O42: 523159 | P42: 438465 | Q42: 409127 | R42: 377119 | S42: 449213 | T42: 545253 | U42: 864019 | V42: 850481 | W42: 1073717 | X42: 812592 | Y42: 935306 | Z42: 823209 | AA42: 949533 | AB42: 1172596 | AC42: 1193159 | AD42: 807229 | AE42: 957628 | AF42: 754650 | AG42: 569032 | AH42: 685881 | AI42: 792531 | AJ42: 759240
A43: 11 | B43: 1 | G43: moeda | H43: Investimento de curto prazo / Short-Term Investments (l.11) | J43: fonte | K43: 2791013 | L43: 2154637 | M43: 1727186 | N43: 1405506 | O43: 1365101 | P43: 1247469 | Q43: 1082196 | R43: 1553503 | S43: 1547125 | T43: 1759164 | U43: 1557031 | V43: 1836607 | W43: 1764906 | X43: 1638665 | Y43: 1621571 | Z43: 1852958 | AA43: 1864486 | AB43: 2427255 | AC43: 2142870 | AD43: 2571896 | AE43: 2537074 | AF43: 2789111 | AG43: 2470434 | AH43: 2387700 | AI43: 4262531 | AJ43: 4456479
A44: 11 | B44: 1 | G44: moeda | H44: Títulos e valores mobiliários / Marketable Securities (l.12) | J44: fonte | K44: 2730 | L44: 753 | M44: 2805 | N44: 767 | O44: 3118 | P44: 1390 | Q44: 3292 | R44: 971 | S44: 3843 | T44: 1000 | U44: 3919 | V44: 1304 | W44: 4726 | X44: 144573 | Y44: 159321 | Z44: 155384 | AA44: 176368 | AB44: 157159 | AC44: 173071 | AD44: 165134 | AE44: 183496 | AF44: 152659 | AG44: 184721 | AH44: 155040 | AI44: 191095 | AJ44: 156202
A45: 12 | B45: 1 | G45: moeda | H45: Contas a receber de clientes / Trade Accounts Receivable (l.13) | J45: fonte | K45: 330399 | L45: 328061 | M45: 365380 | N45: 415353 | O45: 338682 | P45: 345885 | Q45: 378626 | R45: 391698 | S45: 363277 | T45: 377686 | U45: 412736 | V45: 448279 | W45: 476539 | X45: 292699 | Y45: 338637 | Z45: 288702 | AA45: 262889 | AB45: 270403 | AC45: 274293 | AD45: 283923 | AE45: 259685 | AF45: 247846 | AG45: 212361 | AH45: 186798 | AI45: 191285 | AJ45: 349127
A46: 16 | B46: 1 | G46: moeda | H46: Partes relacionadas / Related Parties (l.14) | J46: fonte | K46: 175 | L46: 75 | M46: 75 | N46: 75 | O46: 75 | P46: 75 | Q46: 75 | R46: 75 | S46: 75 | T46: 75 | U46: 75 | V46: 75 | W46: 75 | X46: 75 | Y46: 75 | Z46: 75 | AA46: 75 | AB46: 75 | AC46: 75 | AD46: 75 | AE46: 75 | AF46: 75 | AG46: 75 | AH46: 75 | AI46: 75 | AJ46: 75
A47: 16 | B47: 1 | G47: moeda | H47: Impostos a recuperar / Taxes Recoverable (l.15) | J47: fonte | K47: 149911 | L47: 166766 | M47: 172836 | N47: 141160 | O47: 139170 | P47: 81235 | Q47: 85561 | R47: 98802 | S47: 105997 | T47: 117108 | U47: 121285 | V47: 173299 | W47: 171089 | X47: 189566 | Y47: 194828 | Z47: 178974 | AA47: 181205 | AB47: 207146 | AC47: 213207 | AD47: 208344 | AE47: 220975 | AF47: 239885 | AG47: 254571 | AH47: 251346 | AI47: 270761 | AJ47: 345598
A48: 16 | B48: 1 | G48: moeda | H48: Adiantamento a fornecedores / Advance for Suppliers (l.16) | J48: fonte | K48: 16951 | L48: 29556 | M48: 40329 | N48: 79744 | O48: 80879 | P48: 133118 | Q48: 137094 | R48: 171482 | S48: 86932 | T48: 92680 | U48: 86795 | V48: 87668 | W48: 64542 | X48: 64631 | Y48: 65819 | Z48: 50802 | AA48: 51187 | AB48: 42193 | AC48: 41413 | AD48: 44304 | AE48: 35956 | AF48: 47139 | AG48: 85990 | AH48: 135800 | AI48: 172192 | AJ48: 176510
A49: 13 | B49: 1 | G49: moeda | H49: Estoques / Inventories (l.17) | J49: fonte | K49: 9723 | L49: 8082 | M49: 8244 | N49: 7856 | O49: 7969 | P49: 8386 | Q49: 8389 | R49: 8245 | S49: 8368 | T49: 8455 | U49: 8952 | V49: 9201 | W49: 9061 | X49: 9397 | Y49: 17446 | Z49: 10278 | AA49: 9874 | AB49: 9229 | AC49: 9486 | AD49: 9766 | AE49: 10107 | AF49: 9833 | AG49: 9692 | AH49: 10472 | AI49: 10780 | AJ49: 11141
A50: 16 | B50: 1 | G50: moeda | H50: Cauções e depósitos judiciais / Judicial Deposits (l.18) | J50: fonte | K50: 550 | L50: 384 | M50: 384 | N50: 384 | O50: 384 | P50: 384 | Q50: 384 | R50: 384 | S50: 384 | T50: 384 | U50: 384 | V50: 384 | W50: 384 | X50: 384 | Y50: 384 | Z50: 384 | AA50: 384 | AB50: 384 | AC50: 384 | AD50: 120 | AE50: 120 | AF50: 0 | AG50: 0 | AH50: 0 | AI50: 0 | AJ50: 0
A51: 15 | B51: 1 | G51: moeda | H51: Despesas pagas antecipadamente / Prepaid Expenses (l.19) | J51: fonte | K51: 3616 | L51: 1454 | M51: 6391 | N51: 5828 | O51: 4979 | P51: 10437 | Q51: 9944 | R51: 8251 | S51: 7110 | T51: 11678 | U51: 13120 | V51: 13602 | W51: 7204 | X51: 9983 | Y51: 9189 | Z51: 12141 | AA51: 7964 | AB51: 11090 | AC51: 10329 | AD51: 9961 | AE51: 8499 | AF51: 9341 | AG51: 12455 | AH51: 10900 | AI51: 11131 | AJ51: 12761
A52: 16 | B52: 1 | G52: moeda | H52: Ativo financeiro da concessão / Accounts Receivable - Concession Assets (l.20) | J52: fonte | K52: 0 | L52: 0 | M52: 0 | N52: 0 | O52: 0 | P52: 0 | Q52: 0 | R52: 0 | S52: 0 | T52: 0 | U52: 0 | V52: 0 | W52: 0 | X52: 0 | Y52: 0 | Z52: 0 | AA52: 0 | AB52: 0 | AC52: 0 | AD52: 0 | AE52: 0 | AF52: 0 | AG52: 0 | AH52: 0 | AI52: 0 | AJ52: 0
A53: 16 | B53: 1 | G53: moeda | H53: Contas a receber ativo contratual / Accounts Receivable - Contractual Assets (l.21) | J53: fonte | K53: 977687 | L53: 920963 | M53: 1033622 | N53: 1290362 | O53: 1499674 | P53: 1581795 | Q53: 1596466 | R53: 1701139 | S53: 1869931 | T53: 1911593 | U53: 1897690 | V53: 1909364 | W53: 1980098 | X53: 1969683 | Y53: 1976654 | Z53: 1984827 | AA53: 2034340 | AB53: 2062113 | AC53: 2065735 | AD53: 2098105 | AE53: 2148936 | AF53: 2231278 | AG53: 2246629 | AH53: 2254400 | AI53: 2274328 | AJ53: 2359837
... A114: 35 | B114: 1 | G114: moeda | H114: Participação de acionistas não controladores / Non-controlling interest (l.94) | J114: fonte | K114: 2615278 | L114: 2695718 | M114: 2904541 | N114: 3194564 | O114: 3518758 | P114: 3613423 | Q114: 3681275 | R114: 3450486 | S114: 3649408 | T114: 3594617 | U114: 3476338 | V114: 3413556 | W114: 3560059 | X114: 3384892 | Y114: 3320519 | Z114: 3273249 | AA114: 3423454 | AB114: 3448681 | AC114: 3695059 | AD114: 3483372 | AE114: 3664272 | AF114: 3483293 | AG114: 3360623 | AH114: 3412620 | AI114: 3543062 | AJ114: 3738333
H115: BALANCO - totais divulgados (memoria)
G116: moeda | H116: CIRCULANTE / CURRENT (l.9) | J116: memoria | K116: 4967965 | L116: 4288475 | M116: 4060016 | N116: 4084394 | O116: 4024296 | P116: 3909697 | Q116: 3773839 | R116: 4400677 | S116: 4500527 | T116: 4906614 | U116: 5024296 | V116: 5373445 | W116: 5599948 | X116: 5229950 | Y116: 5382282 | Z116: 5419641 | AA116: 5589155 | AB116: 6401270 | AC116: 6175658 | AD116: 6244139 | AE116: 6413485 | AF116: 6556548 | AG116: 6087168 | AH116: 6225834 | AI116: 8297919 | AJ116: 8807375
G117: moeda | H117: NÃO CIRCULANTE / NON CURRENT (l.26) | J117: memoria | K117: 14952515 | L117: 15713153 | M117: 16769395 | N117: 18492116 | O117: 19509671 | P117: 20178150 | Q117: 20728421 | R117: 21345775 | S117: 22060524 | T117: 22289847 | U117: 22359864 | V117: 22560314 | W117: 23014769 | X117: 22882045 | Y117: 22890367 | Z117: 23016440 | AA117: 23306748 | AB117: 23687501 | AC117: 23827339 | AD117: 24444897 | AE117: 24760198 | AF117: 24652051 | AG117: 25390609 | AH117: 25888482 | AI117: 26043883 | AJ117: 26641716
G118: moeda | H118: ATIVO TOTAL / TOTAL ASSETS (l.44) | J118: memoria | K118: 19920480 | L118: 20001628 | M118: 20829411 | N118: 22576510 | O118: 23533967 | P118: 24087847 | Q118: 24502260 | R118: 25746452 | S118: 26561051 | T118: 27196461 | U118: 27384160 | V118: 27933759 | W118: 28614717 | X118: 28111995 | Y118: 28272649 | Z118: 28436081 | AA118: 28895903 | AB118: 30088771 | AC118: 30002997 | AD118: 30689036 | AE118: 31173683 | AF118: 31208599 | AG118: 31477777 | AH118: 32114316 | AI118: 34341802 | AJ118: 35449091
G119: moeda | H119: CIRCULANTE / CURRENT (l.47) | J119: memoria | K119: 2048578 | L119: 1977844 | M119: 1932509 | N119: 2290155 | O119: 2359359 | P119: 2219852 | Q119: 2037251 | R119: 2113639 | S119: 2522328 | T119: 1796435 | U119: 1759471 | V119: 2558195 | W119: 2610544 | X119: 2141952 | Y119: 2842201 | Z119: 3248718 | AA119: 3340417 | AB119: 4017639 | AC119: 3261977 | AD119: 3053989 | AE119: 2985321 | AF119: 3075042 | AG119: 2390073 | AH119: 2544363 | AI119: 2517608 | AJ119: 2774564
G120: moeda | H120: NÃO CIRCULANTE / NON CURRENT (l.65) | J120: memoria | K120: 10050413 | L120: 10016658 | M120: 10490629 | N120: 11341675 | O120: 11564077 | P120: 11882226 | Q120: 12179844 | R120: 13270654 | S120: 13305181 | T120: 14522609 | U120: 14959749 | V120: 15003945 | W120: 15261022 | X120: 15120744 | Y120: 1777277 | Z120: 14558573 | AA120: 14509834 | AB120: 14808364 | AC120: 14931602 | AD120: 15911544 | AE120: 16005114 | AF120: 16206247 | AG120: 16727432 | AH120: 16993439 | AI120: 18994336 | AJ120: 19295645
G121: moeda | H121: Patrimônio líquido + participação de acionistas Não-Controladores / Equity + non-controlling interest (l.96) | J121: memoria | K121: 7821489 | L121: 8007126 | M121: 8406273 | N121: 8944680 | O121: 9610531 | P121: 9985769 | Q121: 10285165 | R121: 10362159 | S121: 10733542 | T121: 10877417 | U121: 10664940 | V121: 10371619 | W121: 10743151 | X121: 10849299 | Y121: 10861978 | Z121: 10628790 | AA121: 11045652 | AB121: 11262768 | AC121: 11809418 | AD121: 11723503 | AE121: 12183248 | AF121: 11927310 | AG121: 12360272 | AH121: 12576514 | AI121: 12829858 | AJ121: 13378882
G122: moeda | H122: PASSIVO TOTAL / TOTAL LIABILITIES AND EQUITY (l.98) | J122: memoria | K122: 19920480 | L122: 20001628 | M122: 20829411 | N122: 22576510 | O122: 23533967 | P122: 24087847 | Q122: 24502260 | R122: 25746452 | S122: 26561051 | T122: 27196461 | U122: 27384160 | V122: 27933759 | W122: 28614717 | X122: 28111995 | Y122: 28272649 | Z122: 28436081 | AA122: 28895903 | AB122: 30088771 | AC122: 30002997 | AD122: 30689036 | AE122: 31173683 | AF122: 31208599 | AG122: 31477777 | AH122: 32114316 | AI122: 34341802 | AJ122: 35449091
H123: CHECKS (devem ser 0)
G124: moeda | H124: CHECK: linhas codificadas 1-9 da DRE - lucro liquido Alupar (atribuivel) | J124: derivada | K124: =K6+K7+K8+K9+K10+K11+K12+K13+K14+K15+K16+K17+K18+K19+K20+K21+K22+K23+K24+K25+K26+K27+K28+K29+K30+K31-K40 -> 0 | L124: =L6+L7+L8+L9+L10+L11+L12+L13+L14+L15+L16+L17+L18+L19+L20+L21+L22+L23+L24+L25+L26+L27+L28+L29+L30+L31-L40 -> 0 | M124: =M6+M7+M8+M9+M10+M11+M12+M13+M14+M15+M16+M17+M18+M19+M20+M21+M22+M23+M24+M25+M26+M27+M28+M29+M30+M31-M40 -> 0 | N124: =N6+N7+N8+N9+N10+N11+N12+N13+N14+N15+N16+N17+N18+N19+N20+N21+N22+N23+N24+N25+N26+N27+N28+N29+N30+N31-N40 -> 0 | O124: =O6+O7+O8+O9+O10+O11+O12+O13+O14+O15+O16+O17+O18+O19+O20+O21+O22+O23+O24+O25+O26+O27+O28+O29+O30+O31-O40 -> 0 | P124: =P6+P7+P8+P9+P10+P11+P12+P13+P14+P15+P16+P17+P18+P19+P20+P21+P22+P23+P24+P25+P26+P27+P28+P29+P30+P31-P40 -> 0 | Q124: =Q6+Q7+Q8+Q9+Q10+Q11+Q12+Q13+Q14+Q15+Q16+Q17+Q18+Q19+Q20+Q21+Q22+Q23+Q24+Q25+Q26+Q27+Q28+Q29+Q30+Q31-Q40 -> 0 | R124: =R6+R7+R8+R9+R10+R11+R12+R13+R14+R15+R16+R17+R18+R19+R20+R21+R22+R23+R24+R25+R26+R27+R28+R29+R30+R31-R40 -> 0 | ... AJ124: =AJ6+AJ7+AJ8+AJ9+AJ10+AJ11+AJ12+AJ13+AJ14+AJ15+AJ16+AJ17+AJ18+AJ19+AJ20+AJ21+AJ22+AJ23+AJ24+AJ25+AJ26+AJ27+AJ28+AJ29+AJ30+AJ31-AJ40 -> 0
G125: moeda | H125: CHECK: ativo (cod 11-22) - ativo total | J125: derivada | K125: =K42+K43+K44+K45+K46+K47+K48+K49+K50+K51+K52+K53+K54+K55+K56+K57+K58+K59+K60+K61+K62+K63+K64+K65+K66+K67+K68+K69+K70+K71+K72-K118 -> 0 | L125: =L42+L43+L44+L45+L46+L47+L48+L49+L50+L51+L52+L53+L54+L55+L56+L57+L58+L59+L60+L61+L62+L63+L64+L65+L66+L67+L68+L69+L70+L71+L72-L118 -> 0 | M125: =M42+M43+M44+M45+M46+M47+M48+M49+M50+M51+M52+M53+M54+M55+M56+M57+M58+M59+M60+M61+M62+M63+M64+M65+M66+M67+M68+M69+M70+M71+M72-M118 -> 0 | N125: =N42+N43+N44+N45+N46+N47+N48+N49+N50+N51+N52+N53+N54+N55+N56+N57+N58+N59+N60+N61+N62+N63+N64+N65+N66+N67+N68+N69+N70+N71+N72-N118 -> 0 | O125: =O42+O43+O44+O45+O46+O47+O48+O49+O50+O51+O52+O53+O54+O55+O56+O57+O58+O59+O60+O61+O62+O63+O64+O65+O66+O67+O68+O69+O70+O71+O72-O118 -> 0 | P125: =P42+P43+P44+P45+P46+P47+P48+P49+P50+P51+P52+P53+P54+P55+P56+P57+P58+P59+P60+P61+P62+P63+P64+P65+P66+P67+P68+P69+P70+P71+P72-P118 -> 0 | Q125: =Q42+Q43+Q44+Q45+Q46+Q47+Q48+Q49+Q50+Q51+Q52+Q53+Q54+Q55+Q56+Q57+Q58+Q59+Q60+Q61+Q62+Q63+Q64+Q65+Q66+Q67+Q68+Q69+Q70+Q71+Q72-Q118 -> 0 | R125: =R42+R43+R44+R45+R46+R47+R48+R49+R50+R51+R52+R53+R54+R55+R56+R57+R58+R59+R60+R61+R62+R63+R64+R65+R66+R67+R68+R69+R70+R71+R72-R118 -> 0 | ... AJ125: =AJ42+AJ43+AJ44+AJ45+AJ46+AJ47+AJ48+AJ49+AJ50+AJ51+AJ52+AJ53+AJ54+AJ55+AJ56+AJ57+AJ58+AJ59+AJ60+AJ61+AJ62+AJ63+AJ64+AJ65+AJ66+AJ67+AJ68+AJ69+AJ70+AJ71+AJ72-AJ118 -> 0
G126: moeda | H126: CHECK: passivo (cod 23-34) + PL (cod 35-41) - passivo total | J126: derivada | K126: =K73+K74+K75+K76+K77+K78+K79+K80+K81+K82+K83+K84+K85+K86+K87+K88+K89+K90+K91+K92+K93+K94+K95+K96+K97+K98+K99+K100+K101+K102+K103+K104+K105+K106+K107+K108+K109+K110+K111+K112+K113+K114-K122 -> 0 | L126: =L73+L74+L75+L76+L77+L78+L79+L80+L81+L82+L83+L84+L85+L86+L87+L88+L89+L90+L91+L92+L93+L94+L95+L96+L97+L98+L99+L100+L101+L102+L103+L104+L105+L106+L107+L108+L109+L110+L111+L112+L113+L114-L122 -> 0 | M126: =M73+M74+M75+M76+M77+M78+M79+M80+M81+M82+M83+M84+M85+M86+M87+M88+M89+M90+M91+M92+M93+M94+M95+M96+M97+M98+M99+M100+M101+M102+M103+M104+M105+M106+M107+M108+M109+M110+M111+M112+M113+M114-M122 -> 0 | N126: =N73+N74+N75+N76+N77+N78+N79+N80+N81+N82+N83+N84+N85+N86+N87+N88+N89+N90+N91+N92+N93+N94+N95+N96+N97+N98+N99+N100+N101+N102+N103+N104+N105+N106+N107+N108+N109+N110+N111+N112+N113+N114-N122 -> 0 | O126: =O73+O74+O75+O76+O77+O78+O79+O80+O81+O82+O83+O84+O85+O86+O87+O88+O89+O90+O91+O92+O93+O94+O95+O96+O97+O98+O99+O100+O101+O102+O103+O104+O105+O106+O107+O108+O109+O110+O111+O112+O113+O114-O122 -> 0 | P126: =P73+P74+P75+P76+P77+P78+P79+P80+P81+P82+P83+P84+P85+P86+P87+P88+P89+P90+P91+P92+P93+P94+P95+P96+P97+P98+P99+P100+P101+P102+P103+P104+P105+P106+P107+P108+P109+P110+P111+P112+P113+P114-P122 -> 0 | Q126: =Q73+Q74+Q75+Q76+Q77+Q78+Q79+Q80+Q81+Q82+Q83+Q84+Q85+Q86+Q87+Q88+Q89+Q90+Q91+Q92+Q93+Q94+Q95+Q96+Q97+Q98+Q99+Q100+Q101+Q102+Q103+Q104+Q105+Q106+Q107+Q108+Q109+Q110+Q111+Q112+Q113+Q114-Q122 -> 0 | R126: =R73+R74+R75+R76+R77+R78+R79+R80+R81+R82+R83+R84+R85+R86+R87+R88+R89+R90+R91+R92+R93+R94+R95+R96+R97+R98+R99+R100+R101+R102+R103+R104+R105+R106+R107+R108+R109+R110+R111+R112+R113+R114-R122 -> 0 | ... AJ126: =AJ73+AJ74+AJ75+AJ76+AJ77+AJ78+AJ79+AJ80+AJ81+AJ82+AJ83+AJ84+AJ85+AJ86+AJ87+AJ88+AJ89+AJ90+AJ91+AJ92+AJ93+AJ94+AJ95+AJ96+AJ97+AJ98+AJ99+AJ100+AJ101+AJ102+AJ103+AJ104+AJ105+AJ106+AJ107+AJ108+AJ109+AJ110+AJ111+AJ112+AJ113+AJ114-AJ122 -> 0
G127: moeda | H127: CHECK: PL (cod 35-41) - PL + minoritarios | J127: derivada | K127: =K107+K108+K109+K110+K111+K112+K113+K114-K121 -> 0 | L127: =L107+L108+L109+L110+L111+L112+L113+L114-L121 -> 0 | M127: =M107+M108+M109+M110+M111+M112+M113+M114-M121 -> 0 | N127: =N107+N108+N109+N110+N111+N112+N113+N114-N121 -> 0 | O127: =O107+O108+O109+O110+O111+O112+O113+O114-O121 -> 0 | P127: =P107+P108+P109+P110+P111+P112+P113+P114-P121 -> 0 | Q127: =Q107+Q108+Q109+Q110+Q111+Q112+Q113+Q114-Q121 -> 0 | R127: =R107+R108+R109+R110+R111+R112+R113+R114-R121 -> 0 | ... AJ127: =AJ107+AJ108+AJ109+AJ110+AJ111+AJ112+AJ113+AJ114-AJ121 -> 0
H128: [vazio] cod 10 Common Dividends: a aba Consolidado nao traz DFC; dividendos pagos nao preenchidos
H129: [vazio] cod 20 Goodwill: nao aberto (dentro do intangivel, cod 21)
H130: [vazio] cod 28 Short term debt (revolving): sem linha propria
H131: [vazio] cod 32 Convertible debt: inexistente
H132: [vazio] cod 36 Convertible Preferred Stock: inexistente
H133: Nota: ativo contratual da concessao (CP e LP) mapeado em outros ativos (16/22); a variacao entra no fluxo de investimento do Model (linha 265). Para tratar como imobilizado, trocar o codigo para 18.
H135: RECEITA LIQUIDA POR SEGMENTO E POR SPE (R$ mil; receita bruta + deducoes de cada aba, a 100%). Codigos 45+ = memoria, nao entram nos codigos 1-41
A136: 45 | B136: 1 | G136: moeda | H136: Transmissao - consolidado do segmento | aba "Consolidado - Transmissao" (so a partir do 1T23) | J136: fonte | W136: 813298 | X136: 601252 | Y136: 454094 | Z136: 686745 | AA136: 811934 | AB136: 774963 | AC136: 743020 | AD136: 890039 | AE136: 1001038 | AF136: 828487 | AG136: 756195 | AH136: 953586 | AI136: 997764 | AJ136: 1414665
A137: 46 | B137: 1 | G137: moeda | H137: Geracao - consolidado do segmento | aba "Consolidado - Geracao" (so a partir do 1T23) | J137: fonte | W137: 191900 | X137: 180105 | Y137: 196063 | Z137: 192716 | AA137: 186343 | AB137: 179835 | AC137: 187835 | AD137: 234921 | AE137: 224332 | AF137: 220415 | AG137: 208737 | AH137: 211600 | AI137: 258765 | AJ137: 212619
H138: Transmissao por SPE (aba de cada SPE)
A139: 47 | B139: 1 | G139: moeda | H139: Transmissao | Transudeste | aba "Transudeste" | J139: fonte | K139: 5414 | L139: 5338 | M139: 7562 | N139: 20455 | O139: 8888 | P139: 11760 | Q139: 5991 | R139: 4276 | S139: 8090 | T139: 7591 | U139: 4552 | V139: 2359 | W139: 4895 | X139: 2117 | Y139: 2107 | Z139: 5225 | AA139: 4328 | AB139: 4699 | AC139: 5314 | AD139: 6680 | AE139: 5935 | AF139: 3672 | AG139: 2776 | AH139: 4435 | AI139: 3928 | AJ139: 7235
A140: 48 | B140: 1 | G140: moeda | H140: Transmissao | Transleste | aba "Transleste" | J140: fonte | K140: 6395 | L140: 7682 | M140: 11674 | N140: 16433 | O140: 12214 | P140: 16259 | Q140: 8977 | R140: 6607 | S140: 12373 | T140: 11720 | U140: 7207 | V140: 3912 | W140: 7709 | X140: 3530 | Y140: 3519 | Z140: 8162 | AA140: 6857 | AB140: 7362 | AC140: 8284 | AD140: 10303 | AE140: 9195 | AF140: 5859 | AG140: 4573 | AH140: 6627 | AI140: 6118 | AJ140: 11048
A141: 49 | B141: 1 | G141: moeda | H141: Transmissao | Transirapé | aba "Transirapé" | J141: fonte | K141: 13827 | L141: 21423 | M141: 28352 | N141: 26923 | O141: 26869 | P141: 26737 | Q141: 11462 | R141: 7568 | S141: 16523 | T141: 16033 | U141: 9113 | V141: 1196 | W141: 7905 | X141: 551 | Y141: 2447 | Z141: 9014 | AA141: 6608 | AB141: 7553 | AC141: 13378 | AD141: 13906 | AE141: 12179 | AF141: 5952 | AG141: 2723 | AH141: 21417 | AI141: 6358 | AJ141: 15274
A142: 50 | B142: 1 | G142: moeda | H142: Transmissao | EATE | aba "EATE" | J142: fonte | K142: 73371 | L142: 76838 | M142: 119599 | N142: 172701 | O142: 134791 | P142: 182840 | Q142: 89435 | R142: 60356 | S142: 129129 | T142: 121287 | U142: 64751 | V142: 26032 | W142: 70348 | X142: 19009 | Y142: 18724 | Z142: 79422 | AA142: 60003 | AB142: 64939 | AC142: 73684 | AD142: 99562 | AE142: 84531 | AF142: 48536 | AG142: 72832 | AH142: 84444 | AI142: 125373 | AJ142: 194523
A143: 51 | B143: 1 | G143: moeda | H143: Transmissao | ETEP | aba "ETEP" | J143: fonte | K143: 16600 | L143: 16513 | M143: 26746 | N143: 38375 | O143: 30299 | P143: 41039 | Q143: 20165 | R143: 5949 | S143: 29092 | T143: 26372 | U143: 14811 | V143: 6241 | W143: 16005 | X143: 4288 | Y143: 5467 | Z143: 17654 | AA143: 13681 | AB143: 14856 | AC143: 16837 | AD143: 22467 | AE143: 19090 | AF143: 10980 | AG143: 10236 | AH143: 15541 | AI143: 12463 | AJ143: 21406
A144: 52 | B144: 1 | G144: moeda | H144: Transmissao | ECTE | aba "ECTE" | J144: fonte | K144: 15604 | L144: 15517 | M144: 24777 | N144: 43098 | O144: 28355 | P144: 42125 | Q144: 18911 | R144: 12897 | S144: 26960 | T144: 25592 | U144: 13855 | V144: 5870 | W144: 14905 | X144: 4709 | Y144: 4923 | Z144: 16666 | AA144: 12165 | AB144: 13732 | AC144: 15451 | AD144: 20559 | AE144: 17456 | AF144: 10101 | AG144: 7390 | AH144: 11758 | AI144: 10154 | AJ144: 19672
A145: 53 | B145: 1 | G145: moeda | H145: Transmissao | ENTE | aba "ENTE" | J145: fonte | K145: 38199 | L145: 37805 | M145: 58001 | N145: 81006 | O145: 65089 | P145: 85880 | Q145: 47993 | R145: 35666 | S145: 65698 | T145: 62298 | U145: 38456 | V145: 21491 | W145: 41141 | X145: 19332 | Y145: 19405 | Z145: 42473 | AA145: 36470 | AB145: 31858 | AC145: 43194 | AD145: 54036 | AE145: 48236 | AF145: 31218 | AG145: 31858 | AH145: 37352 | AI145: 54445 | AJ145: 87224
A146: 54 | B146: 1 | G146: moeda | H146: Transmissao | ERTE | aba "ERTE" | J146: fonte | K146: 10740 | L146: -28055 | M146: -882 | N146: 22831 | O146: 14836 | P146: 17116 | Q146: 9208 | R146: 7682 | S146: 13059 | T146: 1859 | U146: 12350 | V146: 2303 | W146: 7839 | X146: 4685 | Y146: 3546 | Z146: 10455 | AA146: 7970 | AB146: 8700 | AC146: 9877 | AD146: 12384 | AE146: 10964 | AF146: 6711 | AG146: 4977 | AH146: 17054 | AI146: 7243 | AJ146: 13286
A147: 55 | B147: 1 | G147: moeda | H147: Transmissao | EBTE | aba "EBTE" | J147: fonte | K147: 15194 | L147: 12029 | M147: 28227 | N147: 17477 | O147: 19255 | P147: 18390 | Q147: 19595 | R147: 22928 | S147: 20260 | T147: 25002 | U147: 8490 | V147: 17525 | W147: 22924 | X147: 21243 | Y147: 12336 | Z147: 14833 | AA147: 19503 | AB147: 16120 | AC147: 15327 | AD147: 17970 | AE147: 22331 | AF147: 19450 | AG147: 15263 | AH147: 20256 | AI147: 19948 | AJ147: 23762
A148: 56 | B148: 1 | G148: moeda | H148: Transmissao | Lumitrans | aba "Lumitrans" | J148: fonte | K148: 6182 | L148: 6102 | M148: 8912 | N148: 12350 | O148: 9915 | P148: 13118 | Q148: 6583 | R148: 4921 | S148: 8686 | T148: 8125 | U148: 4914 | V148: 2741 | W148: 5175 | X148: 2442 | Y148: 2394 | Z148: 5415 | AA148: 4568 | AB148: 4898 | AC148: 5485 | AD148: 6781 | AE148: 6045 | AF148: 3906 | AG148: 3082 | AH148: 4630 | AI148: 4147 | AJ148: 7297
A149: 57 | B149: 1 | G149: moeda | H149: Transmissao | STC | aba "STC" | J149: fonte | K149: 5770 | L149: 4180 | M149: 8456 | N149: 7658 | O149: 11471 | P149: 10373 | Q149: 14172 | R149: 12477 | S149: 10893 | T149: 12575 | U149: 6558 | V149: 8208 | W149: 10325 | X149: 9862 | Y149: 7353 | Z149: 8229 | AA149: 9967 | AB149: 8716 | AC149: 8539 | AD149: 9259 | AE149: 10511 | AF149: 9413 | AG149: 178 | AH149: 10703 | AI149: 9069 | AJ149: 10393
A150: 58 | B150: 1 | G150: moeda | H150: Transmissao | ESDE | aba "ESDE" | J150: fonte | K150: 4586 | L150: 1966 | M150: 3665 | N150: -3582 | O150: 5646 | P150: 5312 | Q150: 7027 | R150: 7005 | S150: 5945 | T150: 7231 | U150: 2941 | V150: 4212 | W150: 5775 | X150: 5427 | Y150: 3741 | Z150: 4647 | AA150: 5700 | AB150: 4591 | AC150: 4193 | AD150: 5173 | AE150: 6013 | AF150: 5120 | AG150: -1746 | AH150: 4334 | AI150: 5106 | AJ150: 6157
... A168: 76 | B168: 1 | G168: moeda | H168: Transmissao | AETE | aba "AETE" | J168: fonte | K168: 14681 | L168: 8617 | M168: 13975 | N168: 22902 | O168: 15388 | P168: 21904 | Q168: 9839 | R168: 5896 | S168: 15353 | T168: 14603 | U168: 8005 | V168: 2927 | W168: 8715 | X168: 2498 | Y168: -2516 | Z168: 9491 | AA168: 7656 | AB168: 8310 | AC168: 9232 | AD168: 12312 | AE168: 10785 | AF168: 6367 | AG168: 4348 | AH168: 7635 | AI168: 6489 | AJ168: 13194
A169: 77 | B169: 1 | G169: moeda | H169: Transmissao | TECP | aba "TECP" | J169: fonte | Z169: 218 | AA169: 2522 | AB169: 2347 | AC169: 3360 | AD169: 11719 | AE169: 82577 | AF169: 67999 | AG169: 165995 | AH169: 165338 | AI169: 120196 | AJ169: 161951
A170: 78 | B170: 1 | G170: moeda | H170: Transmissao | TAP | aba "TAP" | J170: fonte | Z170: 0 | AA170: 0 | AB170: 3696 | AC170: -365 | AD170: 8606 | AE170: 2215 | AF170: 0 | AG170: 0 | AH170: 0 | AI170: 0 | AJ170: 0
A171: 79 | B171: 1 | G171: moeda | H171: Transmissao | TCN | aba "TCN" | J171: fonte | AA171: 0 | AB171: 0 | AC171: 2322 | AD171: 2299 | AE171: 1786 | AF171: 3813 | AG171: 7605 | AH171: 16646 | AI171: 0
A172: 80 | B172: 1 | G172: moeda | H172: Transmissao | TPC | aba "TPC" | J172: fonte | AA172: 0 | AB172: 0 | AC172: 1051 | AD172: 1163 | AE172: 2755 | AF172: 2785 | AG172: 3856 | AH172: 7902 | AI172: 10130 | AJ172: 10703
A173: 81 | B173: 1 | G173: moeda | H173: Transmissao | TSA | aba "TSA" | J173: fonte | AC173: 0 | AD173: 51793 | AE173: 502 | AF173: 2806 | AG173: 8948 | AH173: 12498 | AI173: 10483 | AJ173: 7295
A174: 82 | B174: 1 | G174: moeda | H174: Transmissao | TBO | aba "TBO" | J174: fonte | AG174: 3286 | AH174: 5897 | AI174: 7089 | AJ174: 8584
A175: 83 | B175: 1 | G175: moeda | H175: Transmissao | PALCA | aba "PALCA" | J175: fonte | AH175: 26482 | AI175: 2603 | AJ175: 1533
H176: Geracao por usina (aba de cada empresa)
A177: 84 | B177: 1 | G177: moeda | H177: Geracao | Foz do Rio Claro | aba "Foz" | J177: fonte | K177: 18623 | L177: 19100 | M177: 18421 | N177: 19870 | O177: 19478 | P177: 18977 | Q177: 21625 | R177: 21873 | S177: 20272 | T177: 19010 | U177: 20065 | V177: 21489 | W177: 22153 | X177: 21002 | Y177: 20809 | Z177: 22945 | AA177: 21921 | AB177: 21734 | AC177: 22454 | AD177: 24077 | AE177: 24522 | AF177: 23434 | AG177: 23334 | AH177: 25125 | AI177: 25411 | AJ177: 24407
A178: 85 | B178: 1 | G178: moeda | H178: Geracao | Ijuí | aba "IJUÍ" | J178: fonte | K178: 15334 | L178: 13885 | M178: 16367 | N178: 15999 | O178: 16055 | P178: 15930 | Q178: 18366 | R178: 18442 | S178: 17022 | T178: 17258 | U178: 17228 | V178: 19507 | W178: 18983 | X178: 17558 | Y178: 18995 | Z178: 20571 | AA178: 19658 | AB178: 19203 | AC178: 20228 | AD178: 21490 | AE178: 19773 | AF178: 19770 | AG178: 19852 | AH178: 20841 | AI178: 21108 | AJ178: 20774
A179: 86 | B179: 1 | G179: moeda | H179: Geracao | Ferreira Gomes | aba "Ferreira Gomes" | J179: fonte | K179: 52631 | L179: 43989 | M179: 43163 | N179: 55415 | O179: 49370 | P179: 47813 | Q179: 66452 | R179: 78369 | S179: 44559 | T179: 46677 | U179: 47879 | V179: 49725 | W179: 54377 | X179: 55041 | Y179: 54993 | Z179: 54948 | AA179: 55747 | AB179: 57104 | AC179: 58381 | AD179: 77114 | AE179: 70106 | AF179: 58146 | AG179: 62463 | AH179: 65805 | AI179: 66509 | AJ179: 67061
A180: 87 | B180: 1 | G180: moeda | H180: Geracao | La Virgen | aba "La Virgen" | J180: fonte | K180: 0 | L180: 0 | M180: 0 | N180: 0 | O180: 0 | P180: 2558 | Q180: 12707 | R180: 14192 | S180: 18251 | T180: 17015 | U180: 12220 | V180: 19527 | W180: 31933 | X180: 22109 | Y180: 34221 | Z180: 23946 | AA180: 29812 | AB180: 23599 | AC180: 16436 | AD180: 26498 | AE180: 35092 | AF180: 34145 | AG180: 22968 | AH180: 27932 | AI180: 52247 | AJ180: 33452
A181: 88 | B181: 1 | G181: moeda | H181: Geracao | Risaralda (Morro Azul) | aba "Risaralda (Morro Azul)" | J181: fonte | K181: 2674 | L181: 5157 | M181: 9932 | N181: 9794 | O181: 8783 | P181: 11277 | Q181: 8401 | R181: 9626 | S181: 8544 | T181: 9497 | U181: 11611 | V181: 10985 | W181: 9016 | X181: 10217 | Y181: 3542 | Z181: 6746 | AA181: 3406 | AB181: 10491 | AC181: 9284 | AD181: 10102 | AE181: 13431 | AF181: 15171 | AG181: 9725 | AH181: 11063 | AI181: 13188 | AJ181: 9945
A182: 89 | B182: 1 | G182: moeda | H182: Geracao | Queluz | aba "Queluz" | J182: fonte | K182: 16248 | L182: 6448 | M182: 12124 | N182: 17608 | O182: 19738 | P182: 21879 | Q182: 18624 | R182: 22284 | S182: 15772 | T182: 13252 | U182: 15018 | V182: 15462 | W182: 14097 | X182: 13945 | Y182: 13940 | Z182: 14586 | AA182: 13997 | AB182: 12995 | AC182: 15648 | AD182: 21937 | AE182: 15292 | AF182: 14334 | AG182: 11443 | AH182: 12037 | AI182: 19264 | AJ182: 12909
A183: 90 | B183: 1 | G183: moeda | H183: Geracao | Lavrinhas | aba "Lavrinhas" | J183: fonte | K183: 16280 | L183: 7292 | M183: 11255 | N183: 17690 | O183: 19635 | P183: 21937 | Q183: 18735 | R183: 22265 | S183: 15738 | T183: 13163 | U183: 14995 | V183: 15477 | W183: 13581 | X183: 13546 | Y183: 13672 | Z183: 14144 | AA183: 13953 | AB183: 12234 | AC183: 13531 | AD183: 21894 | AE183: 15335 | AF183: 16888 | AG183: 18261 | AH183: 13379 | AI183: 18625 | AJ183: 13067
A184: 91 | B184: 1 | G184: moeda | H184: Geracao | Verde 08 | aba "Verde 08" | J184: fonte | K184: 18875 | L184: 10975 | M184: 9195 | N184: 17263 | O184: 22614 | P184: 18136 | Q184: 16571 | R184: 14689 | S184: 8603 | T184: 4374 | U184: 6817 | V184: 8063 | W184: 11516 | X184: 10734 | Y184: 10983 | Z184: 11809 | AA184: 12324 | AB184: 11292 | AC184: 11624 | AD184: 12227 | AE184: 13293 | AF184: 11798 | AG184: 11951 | AH184: 12879 | AI184: 16181 | AJ184: 12579
A185: 92 | B185: 1 | G185: moeda | H185: Geracao | EDV I | aba "EDV I" | J185: fonte | K185: 3128 | L185: 3125 | M185: 3162 | N185: 3170 | O185: 3233 | P185: 3359 | Q185: 7146 | R185: 3934 | S185: 3559 | T185: 3605 | U185: 3667 | V185: 3671 | W185: 3774 | X185: 3461 | Y185: 4190 | Z185: 4087 | AA185: 2918 | AB185: 1988 | AC185: 2443 | AD185: 5512 | AE185: 2620 | AF185: 3445 | AG185: 4265 | AH185: 4443 | AI185: 3461 | AJ185: 1656
A186: 93 | B186: 1 | G186: moeda | H186: Geracao | EDV II | aba "EDV II" | J186: fonte | K186: 1822 | L186: 1814 | M186: 1813 | N186: 1857 | O186: 1869 | P186: 1969 | Q186: 3030 | R186: 2112 | S186: 2059 | T186: 2094 | U186: 2126 | V186: 2127 | W186: 2220 | X186: 1664 | Y186: 2365 | Z186: 2429 | AA186: 1704 | AB186: 998 | AC186: 1282 | AD186: 2940 | AE186: 1529 | AF186: 1975 | AG186: 2102 | AH186: 2305 | AI186: 1873 | AJ186: 996
A187: 94 | B187: 1 | G187: moeda | H187: Geracao | EDV III | aba "EDV III" | J187: fonte | K187: 2712 | L187: 2704 | M187: 2742 | N187: 2753 | O187: 2841 | P187: 2895 | Q187: 5581 | R187: 3284 | S187: 3078 | T187: 3114 | U187: 3173 | V187: 3162 | W187: 3257 | X187: 3563 | Y187: 3734 | Z187: 3147 | AA187: 2391 | AB187: 1558 | AC187: 1996 | AD187: 4753 | AE187: 2356 | AF187: 3034 | AG187: 3547 | AH187: 3724 | AI187: 2647 | AJ187: 1287
A188: 95 | B188: 1 | G188: moeda | H188: Geracao | EDV IV | aba "EDV IV" | J188: fonte | K188: 4378 | L188: 4379 | M188: 4426 | N188: 4428 | O188: 4413 | P188: 4772 | Q188: 7850 | R188: 5176 | S188: 4988 | T188: 5050 | U188: 5131 | V188: 5148 | W188: 4821 | X188: 4312 | Y188: 5660 | Z188: 4395 | AA188: 4192 | AB188: 2880 | AC188: 3121 | AD188: 7305 | AE188: 3696 | AF188: 4920 | AG188: 5502 | AH188: 5818 | AI188: 6551 | AJ188: 2577
... A192: 99 | B192: 1 | G192: moeda | H192: Geracao | EAP IV | aba "EAP IV" | J192: fonte | K192: 0 | L192: 0 | M192: 0 | N192: 0 | O192: 0 | P192: 0 | Q192: 0 | R192: 0 | S192: 0 | T192: 0 | U192: 0 | V192: 0 | W192: 0 | X192: 0 | Y192: 0 | Z192: 0 | AA192: 0 | AB192: 0 | AC192: 0 | AD192: 0 | AE192: 0 | AF192: 0 | AG192: 0 | AH192: 13379 | AI192: 0 | AJ192: 0
A193: 100 | B193: 1 | G193: moeda | H193: Geracao | UFV Pitombeira | aba "UFV Pitombeira" | J193: fonte | R193: 0 | S193: 0 | T193: 0 | U193: 0 | V193: 0 | W193: 0 | X193: 0 | Y193: 0 | Z193: 46 | AA193: 1680 | AB193: 1922 | AC193: 5140 | AD193: 6823 | AE193: 5728 | AF193: 6613 | AG193: 9452 | AH193: 12013 | AI193: 12872 | AJ193: 9481
H233: CONVENCOES
H234: Linhas de origem: 5 a 193. As formulas da Inputs (2) varrem as linhas 5 a 230; as linhas 194 a 230 estao livres para novas contas.
...

Sheet Inputs (2)
A1: =COUNTIF($B$3:$B$1048576,$B$1) -> 1 | B1: =MAX($B$3:$B$1048576) -> 100
D2: 1Q21 | E2: 2Q21 | F2: 3Q21 | G2: 4Q21 | H2: 2021 | I2: 1Q22 | J2: 2Q22 | K2: 3Q22 | L2: 4Q22 | M2: 2022 | N2: 1Q23 | O2: 2Q23 | P2: 3Q23 | Q2: 4Q23 | R2: 2023 | S2: 1Q24 | T2: 2Q24 | U2: 3Q24 | V2: 4Q24 | W2: 2024 | X2: 1Q25 | Y2: 2Q25 | Z2: 3Q25 | AA2: 4Q25 | AB2: 2025 | AC2: 1Q26 | AD2: 2Q26 | AE2: 3Q26 | AF2: 4Q26 | AG2: 2026 | AH2: 1Q20 | AI2: 2Q20 | AJ2: 3Q20 | AK2: 4Q20 | AL2: 2020 | AN2: Sem dado na fonte: 3Q26, 4Q26 e 2026 (rotulo em cinza). 2020 fica nas colunas AH-AL.
B4: 1 | C4: Net Revenues | D4: =IF(ISNA(MATCH(D$2,Inputs!$K$4:$AJ$4,0)),NA(),IF(SUMPRODUCT((Inputs!$A$5:$A$230=$B4)*ISNUMBER(INDEX(Inputs!$K$5:$AJ$230,0,MATCH(D$2,Inputs!$K$4:$AJ$4,0))))+SUMPRODUCT((Inputs!$C$5:$C$230=$B4)*ISNUMBER(INDEX(Inputs!$K$5:$AJ$230,0,MATCH(D$2,Inputs!$K$4:$AJ$4,0))))+SUMPRODUCT((Inputs!$E$5:$E$230=$B4)*ISNUMBER(INDEX(Inputs!$K$5:$AJ$230,0,MATCH(D$2,Inputs!$K$4:$AJ$4,0))))=0,NA(),SUMPRODUCT((Inputs!$A$5:$A$230=$B4)*Inputs!$B$5:$B$230*(((Inputs!$G$5:$G$230="moeda")+(Inputs!$G$5:$G$230="acoes"))*Inputs!$B$1+((Inputs!$G$5:$G$230<>"moeda")*(Inputs!$G$5:$G$230<>"acoes")))*INDEX(Inputs!$K$5:$AJ$230,0,MATCH(D$2,Inputs!$K$4:$AJ$4,0)))+SUMPRODUCT((Inputs!$C$5:$C$230=$B4)*Inputs!$D$5:$D$230*(((Inputs!$G$5:$G$230="moeda")+(Inputs!$G$5:$G$230="acoes"))*Inputs!$B$1+((Inputs!$G$5:$G$230<>"moeda")*(Inputs!$G$5:$G$230<>"acoes")))*INDEX(Inputs!$K$5:$AJ$230,0,MATCH(D$2,Inputs!$K$4:$AJ$4,0)))+SUMPRODUCT((Inputs!$E$5:$E$230=$B4)*Inputs!$F$5:$F$230*(((Inputs!$G$5:$G$230="moeda")+(Inputs!$G$5:$G$230="acoes"))*Inputs!$B$1+((Inputs!$G$5:$G$230<>"moeda")*(Inputs!$G$5:$G$230<>"acoes")))*INDEX(Inputs!$K$5:$AJ$230,0,MATCH(D$2,Inputs!$K$4:$AJ$4,0))))) -> 1601.474 | E4: =IF(ISNA(MATCH(E$2,Inputs!$K$4:$AJ$4,0)),NA(),IF(SUMPRODUCT((Inputs!$A$5:$A$230=$B4)*ISNUMBER(INDEX(Inputs!$K$5:$AJ$230,0,MATCH(E$2,Inputs!$K$4:$AJ$4,0))))+SUMPRODUCT((Inputs!$C$5:$C$230=$B4)*ISNUMBER(INDEX(Inputs!$K$5:$AJ$230,0,MATCH(E$2,Inputs!$K$4:$AJ$4,0))))+SUMPRODUCT((Inputs!$E$5:$E$230=$B4)*ISNUMBER(INDEX(Inputs!$K$5:$AJ$230,0,MATCH(E$2,Inputs!$K$4:$AJ$4,0))))=0,NA(),SUMPRODUCT((Inputs!$A$5:$A$230=$B4)*Inputs!$B$5:$B$230*(((Inputs!$G$5:$G$230="moeda")+(Inputs!$G$5:$G$230="acoes"))*Inputs!$B$1+((Inputs!$G$5:$G$230<>"moeda")*(Inputs!$G$5:$G$230<>"acoes")))*INDEX(Inputs!$K$5:$AJ$230,0,MATCH(E$2,Inputs!$K$4:$AJ$4,0)))+SUMPRODUCT((Inputs!$C$5:$C$230=$B4)*Inputs!$D$5:$D$230*(((Inputs!$G$5:$G$230="moeda")+(Inputs!$G$5:$G$230="acoes"))*Inputs!$B$1+((Inputs!$G$5:$G$230<>"moeda")*(Inputs!$G$5:$G$230<>"acoes")))*INDEX(Inputs!$K$5:$AJ$230,0,MATCH(E$2,Inputs!$K$4:$AJ$4,0)))+SUMPRODUCT((Inputs!$E$5:$E$230=$B4)*Inputs!$F$5:$F$230*(((Inputs!$G$5:$G$230="moeda")+(Inputs!$G$5:$G$230="acoes"))*Inputs!$B$1+((Inputs!$G$5:$G$230<>"moeda")*(Inputs!$G$5:$G$230<>"acoes")))*INDEX(Inputs!$K$5:$AJ$230,0,MATCH(E$2,Inputs!$K$4:$AJ$4,0))))) -> 1337.141 | F4: =IF(ISNA(MATCH(F$2,Inputs!$K$4:$AJ$4,0)),NA(),IF(SUMPRODUCT((Inputs!$A$5:$A$230=$B4)*ISNUMBER(INDEX(Inputs!$K$5:$AJ$230,0,MATCH(F$2,Inputs!$K$4:$AJ$4,0))))+SUMPRODUCT((Inputs!$C$5:$C$230=$B4)*ISNUMBER(INDEX(Inputs!$K$5:$AJ$230,0,MATCH(F$2,Inputs!$K$4:$AJ$4,0))))+SUMPRODUCT((Inputs!$E$5:$E$230=$B4)*ISNUMBER(INDEX(Inputs!$K$5:$AJ$230,0,MATCH(F$2,Inputs!$K$4:$AJ$4,0))))=0,NA(),SUMPRODUCT((Inputs!$A$5:$A$230=$B4)*Inputs!$B$5:$B$230*(((Inputs!$G$5:$G$230="moeda")+(Inputs!$G$5:$G$230="acoes"))*Inputs!$B$1+((Inputs!$G$5:$G$230<>"moeda")*(Inputs!$G$5:$G$230<>"acoes")))*INDEX(Inputs!$K$5:$AJ$230,0,MATCH(F$2,Inputs!$K$4:$AJ$4,0)))+SUMPRODUCT((Inputs!$C$5:$C$230=$B4)*Inputs!$D$5:$D$230*(((Inputs!$G$5:$G$230="moeda")+(Inputs!$G$5:$G$230="acoes"))*Inputs!$B$1+((Inputs!$G$5:$G$230<>"moeda")*(Inputs!$G$5:$G$230<>"acoes")))*INDEX(Inputs!$K$5:$AJ$230,0,MATCH(F$2,Inputs!$K$4:$AJ$4,0)))+SUMPRODUCT((Inputs!$E$5:$E$230=$B4)*Inputs!$F$5:$F$230*(((Inputs!$G$5:$G$230="moeda")+(Inputs!$G$5:$G$230="acoes"))*Inputs!$B$1+((Inputs!$G$5:$G$230<>"moeda")*(Inputs!$G$5:$G$230<>"acoes")))*INDEX(Inputs!$K$5:$AJ$230,0,MATCH(F$2,Inputs!$K$4:$AJ$4,0))))) -> 1167.652 | G4: =IF(ISNA(MATCH(G$2,Inputs!$K$4:$AJ$4,0)),NA(),IF(SUMPRODUCT((Inputs!$A$5:$A$230=$B4)*ISNUMBER(INDEX(Inputs!$K$5:$AJ$230,0,MATCH(G$2,Inputs!$K$4:$AJ$4,0))))+SUMPRODUCT((Inputs!$C$5:$C$230=$B4)*ISNUMBER(INDEX(Inputs!$K$5:$AJ$230,0,MATCH(G$2,Inputs!$K$4:$AJ$4,0))))+SUMPRODUCT((Inputs!$E$5:$E$230=$B4)*ISNUMBER(INDEX(Inputs!$K$5:$AJ$230,0,MATCH(G$2,Inputs!$K$4:$AJ$4,0))))=0,NA(),SUMPRODUCT((Inputs!$A$5:$A$230=$B4)*Inputs!$B$5:$B$230*(((Inputs!$G$5:$G$230="moeda")+(Inputs!$G$5:$G$230="acoes"))*Inputs!$B$1+((Inputs!$G$5:$G$230<>"moeda")*(Inputs!$G$5:$G$230<>"acoes")))*INDEX(Inputs!$K$5:$AJ$230,0,MATCH(G$2,Inputs!$K$4:$AJ$4,0)))+SUMPRODUCT((Inputs!$C$5:$C$230=$B4)*Inputs!$D$5:$D$230*(((Inputs!$G$5:$G$230="moeda")+(Inputs!$G$5:$G$230="acoes"))*Inputs!$B$1+((Inputs!$G$5:$G$230<>"moeda")*(Inputs!$G$5:$G$230<>"acoes")))*INDEX(Inputs!$K$5:$AJ$230,0,MATCH(G$2,Inputs!$K$4:$AJ$4,0)))+SUMPRODUCT((Inputs!$E$5:$E$230=$B4)*Inputs!$F$5:$F$230*(((Inputs!$G$5:$G$230="moeda")+(Inputs!$G$5:$G$230="acoes"))*Inputs!$B$1+((Inputs!$G$5:$G$230<>"moeda")*(Inputs!$G$5:$G$230<>"acoes")))*INDEX(Inputs!$K$5:$AJ$230,0,MATCH(G$2,Inputs!$K$4:$AJ$4,0))))) -> 1127.941 | H4: =SUM(D4:G4) -> 5234.208 | I4: =IF(ISNA(MATCH(I$2,Inputs!$K$4:$AJ$4,0)),NA(),IF(SUMPRODUCT((Inputs!$A$5:$A$230=$B4)*ISNUMBER(INDEX(Inputs!$K$5:$AJ$230,0,MATCH(I$2,Inputs!$K$4:$AJ$4,0))))+SUMPRODUCT((Inputs!$C$5:$C$230=$B4)*ISNUMBER(INDEX(Inputs!$K$5:$AJ$230,0,MATCH(I$2,Inputs!$K$4:$AJ$4,0))))+SUMPRODUCT((Inputs!$E$5:$E$230=$B4)*ISNUMBER(INDEX(Inputs!$K$5:$AJ$230,0,MATCH(I$2,Inputs!$K$4:$AJ$4,0))))=0,NA(),SUMPRODUCT((Inputs!$A$5:$A$230=$B4)*Inputs!$B$5:$B$230*(((Inputs!$G$5:$G$230="moeda")+(Inputs!$G$5:$G$230="acoes"))*Inputs!$B$1+((Inputs!$G$5:$G$230<>"moeda")*(Inputs!$G$5:$G$230<>"acoes")))*INDEX(Inputs!$K$5:$AJ$230,0,MATCH(I$2,Inputs!$K$4:$AJ$4,0)))+SUMPRODUCT((Inputs!$C$5:$C$230=$B4)*Inputs!$D$5:$D$230*(((Inputs!$G$5:$G$230="moeda")+(Inputs!$G$5:$G$230="acoes"))*Inputs!$B$1+((Inputs!$G$5:$G$230<>"moeda")*(Inputs!$G$5:$G$230<>"acoes")))*INDEX(Inputs!$K$5:$AJ$230,0,MATCH(I$2,Inputs!$K$4:$AJ$4,0)))+SUMPRODUCT((Inputs!$E$5:$E$230=$B4)*Inputs!$F$5:$F$230*(((Inputs!$G$5:$G$230="moeda")+(Inputs!$G$5:$G$230="acoes"))*Inputs!$B$1+((Inputs!$G$5:$G$230<>"moeda")*(Inputs!$G$5:$G$230<>"acoes")))*INDEX(Inputs!$K$5:$AJ$230,0,MATCH(I$2,Inputs!$K$4:$AJ$4,0))))) -> 1280.52 | J4: =IF(ISNA(MATCH(J$2,Inputs!$K$4:$AJ$4,0)),NA(),IF(SUMPRODUCT((Inputs!$A$5:$A$230=$B4)*ISNUMBER(INDEX(Inputs!$K$5:$AJ$230,0,MATCH(J$2,Inputs!$K$4:$AJ$4,0))))+SUMPRODUCT((Inputs!$C$5:$C$230=$B4)*ISNUMBER(INDEX(Inputs!$K$5:$AJ$230,0,MATCH(J$2,Inputs!$K$4:$AJ$4,0))))+SUMPRODUCT((Inputs!$E$5:$E$230=$B4)*ISNUMBER(INDEX(Inputs!$K$5:$AJ$230,0,MATCH(J$2,Inputs!$K$4:$AJ$4,0))))=0,NA(),SUMPRODUCT((Inputs!$A$5:$A$230=$B4)*Inputs!$B$5:$B$230*(((Inputs!$G$5:$G$230="moeda")+(Inputs!$G$5:$G$230="acoes"))*Inputs!$B$1+((Inputs!$G$5:$G$230<>"moeda")*(Inputs!$G$5:$G$230<>"acoes")))*INDEX(Inputs!$K$5:$AJ$230,0,MATCH(J$2,Inputs!$K$4:$AJ$4,0)))+SUMPRODUCT((Inputs!$C$5:$C$230=$B4)*Inputs!$D$5:$D$230*(((Inputs!$G$5:$G$230="moeda")+(Inputs!$G$5:$G$230="acoes"))*Inputs!$B$1+((Inputs!$G$5:$G$230<>"moeda")*(Inputs!$G$5:$G$230<>"acoes")))*INDEX(Inputs!$K$5:$AJ$230,0,MATCH(J$2,Inputs!$K$4:$AJ$4,0)))+SUMPRODUCT((Inputs!$E$5:$E$230=$B4)*Inputs!$F$5:$F$230*(((Inputs!$G$5:$G$230="moeda")+(Inputs!$G$5:$G$230="acoes"))*Inputs!$B$1+((Inputs!$G$5:$G$230<>"moeda")*(Inputs!$G$5:$G$230<>"acoes")))*INDEX(Inputs!$K$5:$AJ$230,0,MATCH(J$2,Inputs!$K$4:$AJ$4,0))))) -> 1168.243 | K4: =IF(ISNA(MATCH(K$2,Inputs!$K$4:$AJ$4,0)),NA(),IF(SUMPRODUCT((Inputs!$A$5:$A$230=$B4)*ISNUMBER(INDEX(Inputs!$K$5:$AJ$230,0,MATCH(K$2,Inputs!$K$4:$AJ$4,0))))+SUMPRODUCT((Inputs!$C$5:$C$230=$B4)*ISNUMBER(INDEX(Inputs!$K$5:$AJ$230,0,MATCH(K$2,Inputs!$K$4:$AJ$4,0))))+SUMPRODUCT((Inputs!$E$5:$E$230=$B4)*ISNUMBER(INDEX(Inputs!$K$5:$AJ$230,0,MATCH(K$2,Inputs!$K$4:$AJ$4,0))))=0,NA(),SUMPRODUCT((Inputs!$A$5:$A$230=$B4)*Inputs!$B$5:$B$230*(((Inputs!$G$5:$G$230="moeda")+(Inputs!$G$5:$G$230="acoes"))*Inputs!$B$1+((Inputs!$G$5:$G$230<>"moeda")*(Inputs!$G$5:$G$230<>"acoes")))*INDEX(Inputs!$K$5:$AJ$230,0,MATCH(K$2,Inputs!$K$4:$AJ$4,0)))+SUMPRODUCT((Inputs!$C$5:$C$230=$B4)*Inputs!$D$5:$D$230*(((Inputs!$G$5:$G$230="moeda")+(Inputs!$G$5:$G$230="acoes"))*Inputs!$B$1+((Inputs!$G$5:$G$230<>"moeda")*(Inputs!$G$5:$G$230<>"acoes")))*INDEX(Inputs!$K$5:$AJ$230,0,MATCH(K$2,Inputs!$K$4:$AJ$4,0)))+SUMPRODUCT((Inputs!$E$5:$E$230=$B4)*Inputs!$F$5:$F$230*(((Inputs!$G$5:$G$230="moeda")+(Inputs!$G$5:$G$230="acoes"))*Inputs!$B$1+((Inputs!$G$5:$G$230<>"moeda")*(Inputs!$G$5:$G$230<>"acoes")))*INDEX(Inputs!$K$5:$AJ$230,0,MATCH(K$2,Inputs!$K$4:$AJ$4,0))))) -> 652.659 | L4: =IF(ISNA(MATCH(L$2,Inputs!$K$4:$AJ$4,0)),NA(),IF(SUMPRODUCT((Inputs!$A$5:$A$230=$B4)*ISNUMBER(INDEX(Inputs!$K$5:$AJ$230,0,MATCH(L$2,Inputs!$K$4:$AJ$4,0))))+SUMPRODUCT((Inputs!$C$5:$C$230=$B4)*ISNUMBER(INDEX(Inputs!$K$5:$AJ$230,0,MATCH(L$2,Inputs!$K$4:$AJ$4,0))))+SUMPRODUCT((Inputs!$E$5:$E$230=$B4)*ISNUMBER(INDEX(Inputs!$K$5:$AJ$230,0,MATCH(L$2,Inputs!$K$4:$AJ$4,0))))=0,NA(),SUMPRODUCT((Inputs!$A$5:$A$230=$B4)*Inputs!$B$5:$B$230*(((Inputs!$G$5:$G$230="moeda")+(Inputs!$G$5:$G$230="acoes"))*Inputs!$B$1+((Inputs!$G$5:$G$230<>"moeda")*(Inputs!$G$5:$G$230<>"acoes")))*INDEX(Inputs!$K$5:$AJ$230,0,MATCH(L$2,Inputs!$K$4:$AJ$4,0)))+SUMPRODUCT((Inputs!$C$5:$C$230=$B4)*Inputs!$D$5:$D$230*(((Inputs!$G$5:$G$230="moeda")+(Inputs!$G$5:$G$230="acoes"))*Inputs!$B$1+((Inputs!$G$5:$G$230<>"moeda")*(Inputs!$G$5:$G$230<>"acoes")))*INDEX(Inputs!$K$5:$AJ$230,0,MATCH(L$2,Inputs!$K$4:$AJ$4,0)))+SUMPRODUCT((Inputs!$E$5:$E$230=$B4)*Inputs!$F$5:$F$230*(((Inputs!$G$5:$G$230="moeda")+(Inputs!$G$5:$G$230="acoes"))*Inputs!$B$1+((Inputs!$G$5:$G$230<>"moeda")*(Inputs!$G$5:$G$230<>"acoes")))*INDEX(Inputs!$K$5:$AJ$230,0,MATCH(L$2,Inputs!$K$4:$AJ$4,0))))) -> 732.286 | M4: =SUM(I4:L4) -> 3833.708 | N4: =IF(ISNA(MATCH(N$2,Inputs!$K$4:$AJ$4,0)),NA(),IF(SUMPRODUCT((Inputs!$A$5:$A$230=$B4)*ISNUMBER(INDEX(Inputs!$K$5:$AJ$230,0,MATCH(N$2,Inputs!$K$4:$AJ$4,0))))+SUMPRODUCT((Inputs!$C$5:$C$230=$B4)*ISNUMBER(INDEX(Inputs!$K$5:$AJ$230,0,MATCH(N$2,Inputs!$K$4:$AJ$4,0))))+SUMPRODUCT((Inputs!$E$5:$E$230=$B4)*ISNUMBER(INDEX(Inputs!$K$5:$AJ$230,0,MATCH(N$2,Inputs!$K$4:$AJ$4,0))))=0,NA(),SUMPRODUCT((Inputs!$A$5:$A$230=$B4)*Inputs!$B$5:$B$230*(((Inputs!$G$5:$G$230="moeda")+(Inputs!$G$5:$G$230="acoes"))*Inputs!$B$1+((Inputs!$G$5:$G$230<>"moeda")*(Inputs!$G$5:$G$230<>"acoes")))*INDEX(Inputs!$K$5:$AJ$230,0,MATCH(N$2,Inputs!$K$4:$AJ$4,0)))+SUMPRODUCT((Inputs!$C$5:$C$230=$B4)*Inputs!$D$5:$D$230*(((Inputs!$G$5:$G$230="moeda")+(Inputs!$G$5:$G$230="acoes"))*Inputs!$B$1+((Inputs!$G$5:$G$230<>"moeda")*(Inputs!$G$5:$G$230<>"acoes")))*INDEX(Inputs!$K$5:$AJ$230,0,MATCH(N$2,Inputs!$K$4:$AJ$4,0)))+SUMPRODUCT((Inputs!$E$5:$E$230=$B4)*Inputs!$F$5:$F$230*(((Inputs!$G$5:$G$230="moeda")+(Inputs!$G$5:$G$230="acoes"))*Inputs!$B$1+((Inputs!$G$5:$G$230<>"moeda")*(Inputs!$G$5:$G$230<>"acoes")))*INDEX(Inputs!$K$5:$AJ$230,0,MATCH(N$2,Inputs!$K$4:$AJ$4,0))))) -> 1003.997 | O4: =IF(ISNA(MATCH(O$2,Inputs!$K$4:$AJ$4,0)),NA(),IF(SUMPRODUCT((Inputs!$A$5:$A$230=$B4)*ISNUMBER(INDEX(Inputs!$K$5:$AJ$230,0,MATCH(O$2,Inputs!$K$4:$AJ$4,0))))+SUMPRODUCT((Inputs!$C$5:$C$230=$B4)*ISNUMBER(INDEX(Inputs!$K$5:$AJ$230,0,MATCH(O$2,Inputs!$K$4:$AJ$4,0))))+SUMPRODUCT((Inputs!$E$5:$E$230=$B4)*ISNUMBER(INDEX(Inputs!$K$5:$AJ$230,0,MATCH(O$2,Inputs!$K$4:$AJ$4,0))))=0,NA(),SUMPRODUCT((Inputs!$A$5:$A$230=$B4)*Inputs!$B$5:$B$230*(((Inputs!$G$5:$G$230="moeda")+(Inputs!$G$5:$G$230="acoes"))*Inputs!$B$1+((Inputs!$G$5:$G$230<>"moeda")*(Inputs!$G$5:$G$230<>"acoes")))*INDEX(Inputs!$K$5:$AJ$230,0,MATCH(O$2,Inputs!$K$4:$AJ$4,0)))+SUMPRODUCT((Inputs!$C$5:$C$230=$B4)*Inputs!$D$5:$D$230*(((Inputs!$G$5:$G$230="moeda")+(Inputs!$G$5:$G$230="acoes"))*Inputs!$B$1+((Inputs!$G$5:$G$230<>"moeda")*(Inputs!$G$5:$G$230<>"acoes")))*INDEX(Inputs!$K$5:$AJ$230,0,MATCH(O$2,Inputs!$K$4:$AJ$4,0)))+SUMPRODUCT((Inputs!$E$5:$E$230=$B4)*Inputs!$F$5:$F$230*(((Inputs!$G$5:$G$230="moeda")+(Inputs!$G$5:$G$230="acoes"))*Inputs!$B$1+((Inputs!$G$5:$G$230<>"moeda")*(Inputs!$G$5:$G$230<>"acoes")))*INDEX(Inputs!$K$5:$AJ$230,0,MATCH(O$2,Inputs!$K$4:$AJ$4,0))))) -> 780.156 | P4: =IF(ISNA(MATCH(P$2,Inputs!$K$4:$AJ$4,0)),NA(),IF(SUMPRODUCT((Inputs!$A$5:$A$230=$B4)*ISNUMBER(INDEX(Inputs!$K$5:$AJ$230,0,MATCH(P$2,Inputs!$K$4:$AJ$4,0))))+SUMPRODUCT((Inputs!$C$5:$C$230=$B4)*ISNUMBER(INDEX(Inputs!$K$5:$AJ$230,0,MATCH(P$2,Inputs!$K$4:$AJ$4,0))))+SUMPRODUCT((Inputs!$E$5:$E$230=$B4)*ISNUMBER(INDEX(Inputs!$K$5:$AJ$230,0,MATCH(P$2,Inputs!$K$4:$AJ$4,0))))=0,NA(),SUMPRODUCT((Inputs!$A$5:$A$230=$B4)*Inputs!$B$5:$B$230*(((Inputs!$G$5:$G$230="moeda")+(Inputs!$G$5:$G$230="acoes"))*Inputs!$B$1+((Inputs!$G$5:$G$230<>"moeda")*(Inputs!$G$5:$G$230<>"acoes")))*INDEX(Inputs!$K$5:$AJ$230,0,MATCH(P$2,Inputs!$K$4:$AJ$4,0)))+SUMPRODUCT((Inputs!$C$5:$C$230=$B4)*Inputs!$D$5:$D$230*(((Inputs!$G$5:$G$230="moeda")+(Inputs!$G$5:$G$230="acoes"))*Inputs!$B$1+((Inputs!$G$5:$G$230<>"moeda")*(Inputs!$G$5:$G$230<>"acoes")))*INDEX(Inputs!$K$5:$AJ$230,0,MATCH(P$2,Inputs!$K$4:$AJ$4,0)))+SUMPRODUCT((Inputs!$E$5:$E$230=$B4)*Inputs!$F$5:$F$230*(((Inputs!$G$5:$G$230="moeda")+(Inputs!$G$5:$G$230="acoes"))*Inputs!$B$1+((Inputs!$G$5:$G$230<>"moeda")*(Inputs!$G$5:$G$230<>"acoes")))*INDEX(Inputs!$K$5:$AJ$230,0,MATCH(P$2,Inputs!$K$4:$AJ$4,0))))) -> 648.957 | Q4: =IF(ISNA(MATCH(Q$2,Inputs!$K$4:$AJ$4,0)),NA(),IF(SUMPRODUCT((Inputs!$A$5:$A$230=$B4)*ISNUMBER(INDEX(Inputs!$K$5:$AJ$230,0,MATCH(Q$2,Inputs!$K$4:$AJ$4,0))))+SUMPRODUCT((Inputs!$C$5:$C$230=$B4)*ISNUMBER(INDEX(Inputs!$K$5:$AJ$230,0,MATCH(Q$2,Inputs!$K$4:$AJ$4,0))))+SUMPRODUCT((Inputs!$E$5:$E$230=$B4)*ISNUMBER(INDEX(Inputs!$K$5:$AJ$230,0,MATCH(Q$2,Inputs!$K$4:$AJ$4,0))))=0,NA(),SUMPRODUCT((Inputs!$A$5:$A$230=$B4)*Inputs!$B$5:$B$230*(((Inputs!$G$5:$G$230="moeda")+(Inputs!$G$5:$G$230="acoes"))*Inputs!$B$1+((Inputs!$G$5:$G$230<>"moeda")*(Inputs!$G$5:$G$230<>"acoes")))*INDEX(Inputs!$K$5:$AJ$230,0,MATCH(Q$2,Inputs!$K$4:$AJ$4,0)))+SUMPRODUCT((Inputs!$C$5:$C$230=$B4)*Inputs!$D$5:$D$230*(((Inputs!$G$5:$G$230="moeda")+(Inputs!$G$5:$G$230="acoes"))*Inputs!$B$1+((Inputs!$G$5:$G$230<>"moeda")*(Inputs!$G$5:$G$230<>"acoes")))*INDEX(Inputs!$K$5:$AJ$230,0,MATCH(Q$2,Inputs!$K$4:$AJ$4,0)))+SUMPRODUCT((Inputs!$E$5:$E$230=$B4)*Inputs!$F$5:$F$230*(((Inputs!$G$5:$G$230="moeda")+(Inputs!$G$5:$G$230="acoes"))*Inputs!$B$1+((Inputs!$G$5:$G$230<>"moeda")*(Inputs!$G$5:$G$230<>"acoes")))*INDEX(Inputs!$K$5:$AJ$230,0,MATCH(Q$2,Inputs!$K$4:$AJ$4,0))))) -> 878.271 | R4: =SUM(N4:Q4) -> 3311.381 | S4: =IF(ISNA(MATCH(S$2,Inputs!$K$4:$AJ$4,0)),NA(),IF(SUMPRODUCT((Inputs!$A$5:$A$230=$B4)*ISNUMBER(INDEX(Inputs!$K$5:$AJ$230,0,MATCH(S$2,Inputs!$K$4:$AJ$4,0))))+SUMPRODUCT((Inputs!$C$5:$C$230=$B4)*ISNUMBER(INDEX(Inputs!$K$5:$AJ$230,0,MATCH(S$2,Inputs!$K$4:$AJ$4,0))))+SUMPRODUCT((Inputs!$E$5:$E$230=$B4)*ISNUMBER(INDEX(Inputs!$K$5:$AJ$230,0,MATCH(S$2,Inputs!$K$4:$AJ$4,0))))=0,NA(),SUMPRODUCT((Inputs!$A$5:$A$230=$B4)*Inputs!$B$5:$B$230*(((Inputs!$G$5:$G$230="moeda")+(Inputs!$G$5:$G$230="acoes"))*Inputs!$B$1+((Inputs!$G$5:$G$230<>"moeda")*(Inputs!$G$5:$G$230<>"acoes")))*INDEX(Inputs!$K$5:$AJ$230,0,MATCH(S$2,Inputs!$K$4:$AJ$4,0)))+SUMPRODUCT((Inputs!$C$5:$C$230=$B4)*Inputs!$D$5:$D$230*(((Inputs!$G$5:$G$230="moeda")+(Inputs!$G$5:$G$230="acoes"))*Inputs!$B$1+((Inputs!$G$5:$G$230<>"moeda")*(Inputs!$G$5:$G$230<>"acoes")))*INDEX(Inputs!$K$5:$AJ$230,0,MATCH(S$2,Inputs!$K$4:$AJ$4,0)))+SUMPRODUCT((Inputs!$E$5:$E$230=$B4)*Inputs!$F$5:$F$230*(((Inputs!$G$5:$G$230="moeda")+(Inputs!$G$5:$G$230="acoes"))*Inputs!$B$1+((Inputs!$G$5:$G$230<>"moeda")*(Inputs!$G$5:$G$230<>"acoes")))*INDEX(Inputs!$K$5:$AJ$230,0,MATCH(S$2,Inputs!$K$4:$AJ$4,0))))) -> 996.535 | T4: =IF(ISNA(MATCH(T$2,Inputs!$K$4:$AJ$4,0)),NA(),IF(SUMPRODUCT((Inputs!$A$5:$A$230=$B4)*ISNUMBER(INDEX(Inputs!$K$5:$AJ$230,0,MATCH(T$2,Inputs!$K$4:$AJ$4,0))))+SUMPRODUCT((Inputs!$C$5:$C$230=$B4)*ISNUMBER(INDEX(Inputs!$K$5:$AJ$230,0,MATCH(T$2,Inputs!$K$4:$AJ$4,0))))+SUMPRODUCT((Inputs!$E$5:$E$230=$B4)*ISNUMBER(INDEX(Inputs!$K$5:$AJ$230,0,MATCH(T$2,Inputs!$K$4:$AJ$4,0))))=0,NA(),SUMPRODUCT((Inputs!$A$5:$A$230=$B4)*Inputs!$B$5:$B$230*(((Inputs!$G$5:$G$230="moeda")+(Inputs!$G$5:$G$230="acoes"))*Inputs!$B$1+((Inputs!$G$5:$G$230<>"moeda")*(Inputs!$G$5:$G$230<>"acoes")))*INDEX(Inputs!$K$5:$AJ$230,0,MATCH(T$2,Inputs!$K$4:$AJ$4,0)))+SUMPRODUCT((Inputs!$C$5:$C$230=$B4)*Inputs!$D$5:$D$230*(((Inputs!$G$5:$G$230="moeda")+(Inputs!$G$5:$G$230="acoes"))*Inputs!$B$1+((Inputs!$G$5:$G$230<>"moeda")*(Inputs!$G$5:$G$230<>"acoes")))*INDEX(Inputs!$K$5:$AJ$230,0,MATCH(T$2,Inputs!$K$4:$AJ$4,0)))+SUMPRODUCT((Inputs!$E$5:$E$230=$B4)*Inputs!$F$5:$F$230*(((Inputs!$G$5:$G$230="moeda")+(Inputs!$G$5:$G$230="acoes"))*Inputs!$B$1+((Inputs!$G$5:$G$230<>"moeda")*(Inputs!$G$5:$G$230<>"acoes")))*INDEX(Inputs!$K$5:$AJ$230,0,MATCH(T$2,Inputs!$K$4:$AJ$4,0))))) -> 953.692 | U4: =IF(ISNA(MATCH(U$2,Inputs!$K$4:$AJ$4,0)),NA(),IF(SUMPRODUCT((Inputs!$A$5:$A$230=$B4)*ISNUMBER(INDEX(Inputs!$K$5:$AJ$230,0,MATCH(U$2,Inputs!$K$4:$AJ$4,0))))+SUMPRODUCT((Inputs!$C$5:$C$230=$B4)*ISNUMBER(INDEX(Inputs!$K$5:$AJ$230,0,MATCH(U$2,Inputs!$K$4:$AJ$4,0))))+SUMPRODUCT((Inputs!$E$5:$E$230=$B4)*ISNUMBER(INDEX(Inputs!$K$5:$AJ$230,0,MATCH(U$2,Inputs!$K$4:$AJ$4,0))))=0,NA(),SUMPRODUCT((Inputs!$A$5:$A$230=$B4)*Inputs!$B$5:$B$230*(((Inputs!$G$5:$G$230="moeda")+(Inputs!$G$5:$G$230="acoes"))*Inputs!$B$1+((Inputs!$G$5:$G$230<>"moeda")*(Inputs!$G$5:$G$230<>"acoes")))*INDEX(Inputs!$K$5:$AJ$230,0,MATCH(U$2,Inputs!$K$4:$AJ$4,0)))+SUMPRODUCT((Inputs!$C$5:$C$230=$B4)*Inputs!$D$5:$D$230*(((Inputs!$G$5:$G$230="moeda")+(Inputs!$G$5:$G$230="acoes"))*Inputs!$B$1+((Inputs!$G$5:$G$230<>"moeda")*(Inputs!$G$5:$G$230<>"acoes")))*INDEX(Inputs!$K$5:$AJ$230,0,MATCH(U$2,Inputs!$K$4:$AJ$4,0)))+SUMPRODUCT((Inputs!$E$5:$E$230=$B4)*Inputs!$F$5:$F$230*(((Inputs!$G$5:$G$230="moeda")+(Inputs!$G$5:$G$230="acoes"))*Inputs!$B$1+((Inputs!$G$5:$G$230<>"moeda")*(Inputs!$G$5:$G$230<>"acoes")))*INDEX(Inputs!$K$5:$AJ$230,0,MATCH(U$2,Inputs!$K$4:$AJ$4,0))))) -> 928.567 | V4: =IF(ISNA(MATCH(V$2,Inputs!$K$4:$AJ$4,0)),NA(),IF(SUMPRODUCT((Inputs!$A$5:$A$230=$B4)*ISNUMBER(INDEX(Inputs!$K$5:$AJ$230,0,MATCH(V$2,Inputs!$K$4:$AJ$4,0))))+SUMPRODUCT((Inputs!$C$5:$C$230=$B4)*ISNUMBER(INDEX(Inputs!$K$5:$AJ$230,0,MATCH(V$2,Inputs!$K$4:$AJ$4,0))))+SUMPRODUCT((Inputs!$E$5:$E$230=$B4)*ISNUMBER(INDEX(Inputs!$K$5:$AJ$230,0,MATCH(V$2,Inputs!$K$4:$AJ$4,0))))=0,NA(),SUMPRODUCT((Inputs!$A$5:$A$230=$B4)*Inputs!$B$5:$B$230*(((Inputs!$G$5:$G$230="moeda")+(Inputs!$G$5:$G$230="acoes"))*Inputs!$B$1+((Inputs!$G$5:$G$230<>"moeda")*(Inputs!$G$5:$G$230<>"acoes")))*INDEX(Inputs!$K$5:$AJ$230,0,MATCH(V$2,Inputs!$K$4:$AJ$4,0)))+SUMPRODUCT((Inputs!$C$5:$C$230=$B4)*Inputs!$D$5:$D$230*(((Inputs!$G$5:$G$230="moeda")+(Inputs!$G$5:$G$230="acoes"))*Inputs!$B$1+((Inputs!$G$5:$G$230<>"moeda")*(Inputs!$G$5:$G$230<>"acoes")))*INDEX(Inputs!$K$5:$AJ$230,0,MATCH(V$2,Inputs!$K$4:$AJ$4,0)))+SUMPRODUCT((Inputs!$E$5:$E$230=$B4)*Inputs!$F$5:$F$230*(((Inputs!$G$5:$G$230="moeda")+(Inputs!$G$5:$G$230="acoes"))*Inputs!$B$1+((Inputs!$G$5:$G$230<>"moeda")*(Inputs!$G$5:$G$230<>"acoes")))*INDEX(Inputs!$K$5:$AJ$230,0,MATCH(V$2,Inputs!$K$4:$AJ$4,0))))) -> 1123.31 | W4: =SUM(S4:V4) -> 4002.104 | X4: =IF(ISNA(MATCH(X$2,Inputs!$K$4:$AJ$4,0)),NA(),IF(SUMPRODUCT((Inputs!$A$5:$A$230=$B4)*ISNUMBER(INDEX(Inputs!$K$5:$AJ$230,0,MATCH(X$2,Inputs!$K$4:$AJ$4,0))))+SUMPRODUCT((Inputs!$C$5:$C$230=$B4)*ISNUMBER(INDEX(Inputs!$K$5:$AJ$230,0,MATCH(X$2,Inputs!$K$4:$AJ$4,0))))+SUMPRODUCT((Inputs!$E$5:$E$230=$B4)*ISNUMBER(INDEX(Inputs!$K$5:$AJ$230,0,MATCH(X$2,Inputs!$K$4:$AJ$4,0))))=0,NA(),SUMPRODUCT((Inputs!$A$5:$A$230=$B4)*Inputs!$B$5:$B$230*(((Inputs!$G$5:$G$230="moeda")+(Inputs!$G$5:$G$230="acoes"))*Inputs!$B$1+((Inputs!$G$5:$G$230<>"moeda")*(Inputs!$G$5:$G$230<>"acoes")))*INDEX(Inputs!$K$5:$AJ$230,0,MATCH(X$2,Inputs!$K$4:$AJ$4,0)))+SUMPRODUCT((Inputs!$C$5:$C$230=$B4)*Inputs!$D$5:$D$230*(((Inputs!$G$5:$G$230="moeda")+(Inputs!$G$5:$G$230="acoes"))*Inputs!$B$1+((Inputs!$G$5:$G$230<>"moeda")*(Inputs!$G$5:$G$230<>"acoes")))*INDEX(Inputs!$K$5:$AJ$230,0,MATCH(X$2,Inputs!$K$4:$AJ$4,0)))+SUMPRODUCT((Inputs!$E$5:$E$230=$B4)*Inputs!$F$5:$F$230*(((Inputs!$G$5:$G$230="moeda")+(Inputs!$G$5:$G$230="acoes"))*Inputs!$B$1+((Inputs!$G$5:$G$230<>"moeda")*(Inputs!$G$5:$G$230<>"acoes")))*INDEX(Inputs!$K$5:$AJ$230,0,MATCH(X$2,Inputs!$K$4:$AJ$4,0))))) -> 1223.731 | Y4: =IF(ISNA(MATCH(Y$2,Inputs!$K$4:$AJ$4,0)),NA(),IF(SUMPRODUCT((Inputs!$A$5:$A$230=$B4)*ISNUMBER(INDEX(Inputs!$K$5:$AJ$230,0,MATCH(Y$2,Inputs!$K$4:$AJ$4,0))))+SUMPRODUCT((Inputs!$C$5:$C$230=$B4)*ISNUMBER(INDEX(Inputs!$K$5:$AJ$230,0,MATCH(Y$2,Inputs!$K$4:$AJ$4,0))))+SUMPRODUCT((Inputs!$E$5:$E$230=$B4)*ISNUMBER(INDEX(Inputs!$K$5:$AJ$230,0,MATCH(Y$2,Inputs!$K$4:$AJ$4,0))))=0,NA(),SUMPRODUCT((Inputs!$A$5:$A$230=$B4)*Inputs!$B$5:$B$230*(((Inputs!$G$5:$G$230="moeda")+(Inputs!$G$5:$G$230="acoes"))*Inputs!$B$1+((Inputs!$G$5:$G$230<>"moeda")*(Inputs!$G$5:$G$230<>"acoes")))*INDEX(Inputs!$K$5:$AJ$230,0,MATCH(Y$2,Inputs!$K$4:$AJ$4,0)))+SUMPRODUCT((Inputs!$C$5:$C$230=$B4)*Inputs!$D$5:$D$230*(((Inputs!$G$5:$G$230="moeda")+(Inputs!$G$5:$G$230="acoes"))*Inputs!$B$1+((Inputs!$G$5:$G$230<>"moeda")*(Inputs!$G$5:$G$230<>"acoes")))*INDEX(Inputs!$K$5:$AJ$230,0,MATCH(Y$2,Inputs!$K$4:$AJ$4,0)))+SUMPRODUCT((Inputs!$E$5:$E$230=$B4)*Inputs!$F$5:$F$230*(((Inputs!$G$5:$G$230="moeda")+(Inputs!$G$5:$G$230="acoes"))*Inputs!$B$1+((Inputs!$G$5:$G$230<>"moeda")*(Inputs!$G$5:$G$230<>"acoes")))*INDEX(Inputs!$K$5:$AJ$230,0,MATCH(Y$2,Inputs!$K$4:$AJ$4,0))))) -> 1047.14 | Z4: =IF(ISNA(MATCH(Z$2,Inputs!$K$4:$AJ$4,0)),NA(),IF(SUMPRODUCT((Inputs!$A$5:$A$230=$B4)*ISNUMBER(INDEX(Inputs!$K$5:$AJ$230,0,MATCH(Z$2,Inputs!$K$4:$AJ$4,0))))+SUMPRODUCT((Inputs!$C$5:$C$230=$B4)*ISNUMBER(INDEX(Inputs!$K$5:$AJ$230,0,MATCH(Z$2,Inputs!$K$4:$AJ$4,0))))+SUMPRODUCT((Inputs!$E$5:$E$230=$B4)*ISNUMBER(INDEX(Inputs!$K$5:$AJ$230,0,MATCH(Z$2,Inputs!$K$4:$AJ$4,0))))=0,NA(),SUMPRODUCT((Inputs!$A$5:$A$230=$B4)*Inputs!$B$5:$B$230*(((Inputs!$G$5:$G$230="moeda")+(Inputs!$G$5:$G$230="acoes"))*Inputs!$B$1+((Inputs!$G$5:$G$230<>"moeda")*(Inputs!$G$5:$G$230<>"acoes")))*INDEX(Inputs!$K$5:$AJ$230,0,MATCH(Z$2,Inputs!$K$4:$AJ$4,0)))+SUMPRODUCT((Inputs!$C$5:$C$230=$B4)*Inputs!$D$5:$D$230*(((Inputs!$G$5:$G$230="moeda")+(Inputs!$G$5:$G$230="acoes"))*Inputs!$B$1+((Inputs!$G$5:$G$230<>"moeda")*(Inputs!$G$5:$G$230<>"acoes")))*INDEX(Inputs!$K$5:$AJ$230,0,MATCH(Z$2,Inputs!$K$4:$AJ$4,0)))+SUMPRODUCT((Inputs!$E$5:$E$230=$B4)*Inputs!$F$5:$F$230*(((Inputs!$G$5:$G$230="moeda")+(Inputs!$G$5:$G$230="acoes"))*Inputs!$B$1+((Inputs!$G$5:$G$230<>"moeda")*(Inputs!$G$5:$G$230<>"acoes")))*INDEX(Inputs!$K$5:$AJ$230,0,MATCH(Z$2,Inputs!$K$4:$AJ$4,0))))) -> 963.353 | AA4: =IF(ISNA(MATCH(AA$2,Inputs!$K$4:$AJ$4,0)),NA(),IF(SUMPRODUCT((Inputs!$A$5:$A$230=$B4)*ISNUMBER(INDEX(Inputs!$K$5:$AJ$230,0,MATCH(AA$2,Inputs!$K$4:$AJ$4,0))))+SUMPRODUCT((Inputs!$C$5:$C$230=$B4)*ISNUMBER(INDEX(Inputs!$K$5:$AJ$230,0,MATCH(AA$2,Inputs!$K$4:$AJ$4,0))))+SUMPRODUCT((Inputs!$E$5:$E$230=$B4)*ISNUMBER(INDEX(Inputs!$K$5:$AJ$230,0,MATCH(AA$2,Inputs!$K$4:$AJ$4,0))))=0,NA(),SUMPRODUCT((Inputs!$A$5:$A$230=$B4)*Inputs!$B$5:$B$230*(((Inputs!$G$5:$G$230="moeda")+(Inputs!$G$5:$G$230="acoes"))*Inputs!$B$1+((Inputs!$G$5:$G$230<>"moeda")*(Inputs!$G$5:$G$230<>"acoes")))*INDEX(Inputs!$K$5:$AJ$230,0,MATCH(AA$2,Inputs!$K$4:$AJ$4,0)))+SUMPRODUCT((Inputs!$C$5:$C$230=$B4)*Inputs!$D$5:$D$230*(((Inputs!$G$5:$G$230="moeda")+(Inputs!$G$5:$G$230="acoes"))*Inputs!$B$1+((Inputs!$G$5:$G$230<>"moeda")*(Inputs!$G$5:$G$230<>"acoes")))*INDEX(Inputs!$K$5:$AJ$230,0,MATCH(AA$2,Inputs!$K$4:$AJ$4,0)))+SUMPRODUCT((Inputs!$E$5:$E$230=$B4)*Inputs!$F$5:$F$230*(((Inputs!$G$5:$G$230="moeda")+(Inputs!$G$5:$G$230="acoes"))*Inputs!$B$1+((Inputs!$G$5:$G$230<>"moeda")*(Inputs!$G$5:$G$230<>"acoes")))*INDEX(Inputs!$K$5:$AJ$230,0,MATCH(AA$2,Inputs!$K$4:$AJ$4,0))))) -> 1163.659 | AB4: =SUM(X4:AA4) -> 4397.883 | AC4: =IF(ISNA(MATCH(AC$2,Inputs!$K$4:$AJ$4,0)),NA(),IF(SUMPRODUCT((Inputs!$A$5:$A$230=$B4)*ISNUMBER(INDEX(Inputs!$K$5:$AJ$230,0,MATCH(AC$2,Inputs!$K$4:$AJ$4,0))))+SUMPRODUCT((Inputs!$C$5:$C$230=$B4)*ISNUMBER(INDEX(Inputs!$K$5:$AJ$230,0,MATCH(AC$2,Inputs!$K$4:$AJ$4,0))))+SUMPRODUCT((Inputs!$E$5:$E$230=$B4)*ISNUMBER(INDEX(Inputs!$K$5:$AJ$230,0,MATCH(AC$2,Inputs!$K$4:$AJ$4,0))))=0,NA(),SUMPRODUCT((Inputs!$A$5:$A$230=$B4)*Inputs!$B$5:$B$230*(((Inputs!$G$5:$G$230="moeda")+(Inputs!$G$5:$G$230="acoes"))*Inputs!$B$1+((Inputs!$G$5:$G$230<>"moeda")*(Inputs!$G$5:$G$230<>"acoes")))*INDEX(Inputs!$K$5:$AJ$230,0,MATCH(AC$2,Inputs!$K$4:$AJ$4,0)))+SUMPRODUCT((Inputs!$C$5:$C$230=$B4)*Inputs!$D$5:$D$230*(((Inputs!$G$5:$G$230="moeda")+(Inputs!$G$5:$G$230="acoes"))*Inputs!$B$1+((Inputs!$G$5:$G$230<>"moeda")*(Inputs!$G$5:$G$230<>"acoes")))*INDEX(Inputs!$K$5:$AJ$230,0,MATCH(AC$2,Inputs!$K$4:$AJ$4,0)))+SUMPRODUCT((Inputs!$E$5:$E$230=$B4)*Inputs!$F$5:$F$230*(((Inputs!$G$5:$G$230="moeda")+(Inputs!$G$5:$G$230="acoes"))*Inputs!$B$1+((Inputs!$G$5:$G$230<>"moeda")*(Inputs!$G$5:$G$230<>"acoes")))*INDEX(Inputs!$K$5:$AJ$230,0,MATCH(AC$2,Inputs!$K$4:$AJ$4,0))))) -> 1255.635 | AD4: =IF(ISNA(MATCH(AD$2,Inputs!$K$4:$AJ$4,0)),NA(),IF(SUMPRODUCT((Inputs!$A$5:$A$230=$B4)*ISNUMBER(INDEX(Inputs!$K$5:$AJ$230,0,MATCH(AD$2,Inputs!$K$4:$AJ$4,0))))+SUMPRODUCT((Inputs!$C$5:$C$230=$B4)*ISNUMBER(INDEX(Inputs!$K$5:$AJ$230,0,MATCH(AD$2,Inputs!$K$4:$AJ$4,0))))+SUMPRODUCT((Inputs!$E$5:$E$230=$B4)*ISNUMBER(INDEX(Inputs!$K$5:$AJ$230,0,MATCH(AD$2,Inputs!$K$4:$AJ$4,0))))=0,NA(),SUMPRODUCT((Inputs!$A$5:$A$230=$B4)*Inputs!$B$5:$B$230*(((Inputs!$G$5:$G$230="moeda")+(Inputs!$G$5:$G$230="acoes"))*Inputs!$B$1+((Inputs!$G$5:$G$230<>"moeda")*(Inputs!$G$5:$G$230<>"acoes")))*INDEX(Inputs!$K$5:$AJ$230,0,MATCH(AD$2,Inputs!$K$4:$AJ$4,0)))+SUMPRODUCT((Inputs!$C$5:$C$230=$B4)*Inputs!$D$5:$D$230*(((Inputs!$G$5:$G$230="moeda")+(Inputs!$G$5:$G$230="acoes"))*Inputs!$B$1+((Inputs!$G$5:$G$230<>"moeda")*(Inputs!$G$5:$G$230<>"acoes")))*INDEX(Inputs!$K$5:$AJ$230,0,MATCH(AD$2,Inputs!$K$4:$AJ$4,0)))+SUMPRODUCT((Inputs!$E$5:$E$230=$B4)*Inputs!$F$5:$F$230*(((Inputs!$G$5:$G$230="moeda")+(Inputs!$G$5:$G$230="acoes"))*Inputs!$B$1+((Inputs!$G$5:$G$230<>"moeda")*(Inputs!$G$5:$G$230<>"acoes")))*INDEX(Inputs!$K$5:$AJ$230,0,MATCH(AD$2,Inputs!$K$4:$AJ$4,0))))) -> 1627.285 | AE4: =IF(ISNA(MATCH(AE$2,Inputs!$K$4:$AJ$4,0)),NA(),IF(SUMPRODUCT((Inputs!$A$5:$A$230=$B4)*ISNUMBER(INDEX(Inputs!$K$5:$AJ$230,0,MATCH(AE$2,Inputs!$K$4:$AJ$4,0))))+SUMPRODUCT((Inputs!$C$5:$C$230=$B4)*ISNUMBER(INDEX(Inputs!$K$5:$AJ$230,0,MATCH(AE$2,Inputs!$K$4:$AJ$4,0))))+SUMPRODUCT((Inputs!$E$5:$E$230=$B4)*ISNUMBER(INDEX(Inputs!$K$5:$AJ$230,0,MATCH(AE$2,Inputs!$K$4:$AJ$4,0))))=0,NA(),SUMPRODUCT((Inputs!$A$5:$A$230=$B4)*Inputs!$B$5:$B$230*(((Inputs!$G$5:$G$230="moeda")+(Inputs!$G$5:$G$230="acoes"))*Inputs!$B$1+((Inputs!$G$5:$G$230<>"moeda")*(Inputs!$G$5:$G$230<>"acoes")))*INDEX(Inputs!$K$5:$AJ$230,0,MATCH(AE$2,Inputs!$K$4:$AJ$4,0)))+SUMPRODUCT((Inputs!$C$5:$C$230=$B4)*Inputs!$D$5:$D$230*(((Inputs!$G$5:$G$230="moeda")+(Inputs!$G$5:$G$230="acoes"))*Inputs!$B$1+((Inputs!$G$5:$G$230<>"moeda")*(Inputs!$G$5:$G$230<>"acoes")))*INDEX(Inputs!$K$5:$AJ$230,0,MATCH(AE$2,Inputs!$K$4:$AJ$4,0)))+SUMPRODUCT((Inputs!$E$5:$E$230=$B4)*Inputs!$F$5:$F$230*(((Inputs!$G$5:$G$230="moeda")+(Inputs!$G$5:$G$230="acoes"))*Inputs!$B$1+((Inputs!$G$5:$G$230<>"moeda")*(Inputs!$G$5:$G$230<>"acoes")))*INDEX(Inputs!$K$5:$AJ$230,0,MATCH(AE$2,Inputs!$K$4:$AJ$4,0))))) -> #N/A | AF4: =IF(ISNA(MATCH(AF$2,Inputs!$K$4:$AJ$4,0)),NA(),IF(SUMPRODUCT((Inputs!$A$5:$A$230=$B4)*ISNUMBER(INDEX(Inputs!$K$5:$AJ$230,0,MATCH(AF$2,Inputs!$K$4:$AJ$4,0))))+SUMPRODUCT((Inputs!$C$5:$C$230=$B4)*ISNUMBER(INDEX(Inputs!$K$5:$AJ$230,0,MATCH(AF$2,Inputs!$K$4:$AJ$4,0))))+SUMPRODUCT((Inputs!$E$5:$E$230=$B4)*ISNUMBER(INDEX(Inputs!$K$5:$AJ$230,0,MATCH(AF$2,Inputs!$K$4:$AJ$4,0))))=0,NA(),SUMPRODUCT((Inputs!$A$5:$A$230=$B4)*Inputs!$B$5:$B$230*(((Inputs!$G$5:$G$230="moeda")+(Inputs!$G$5:$G$230="acoes"))*Inputs!$B$1+((Inputs!$G$5:$G$230<>"moeda")*(Inputs!$G$5:$G$230<>"acoes")))*INDEX(Inputs!$K$5:$AJ$230,0,MATCH(AF$2,Inputs!$K$4:$AJ$4,0)))+SUMPRODUCT((Inputs!$C$5:$C$230=$B4)*Inputs!$D$5:$D$230*(((Inputs!$G$5:$G$230="moeda")+(Inputs!$G$5:$G$230="acoes"))*Inputs!$B$1+((Inputs!$G$5:$G$230<>"moeda")*(Inputs!$G$5:$G$230<>"acoes")))*INDEX(Inputs!$K$5:$AJ$230,0,MATCH(AF$2,Inputs!$K$4:$AJ$4,0)))+SUMPRODUCT((Inputs!$E$5:$E$230=$B4)*Inputs!$F$5:$F$230*(((Inputs!$G$5:$G$230="moeda")+(Inputs!$G$5:$G$230="acoes"))*Inputs!$B$1+((Inputs!$G$5:$G$230<>"moeda")*(Inputs!$G$5:$G$230<>"acoes")))*INDEX(Inputs!$K$5:$AJ$230,0,MATCH(AF$2,Inputs!$K$4:$AJ$4,0))))) -> #N/A | AG4: =SUM(AC4:AF4) -> #N/A | AH4: =IF(ISNA(MATCH(AH$2,Inputs!$K$4:$AJ$4,0)),NA(),IF(SUMPRODUCT((Inputs!$A$5:$A$230=$B4)*ISNUMBER(INDEX(Inputs!$K$5:$AJ$230,0,MATCH(AH$2,Inputs!$K$4:$AJ$4,0))))+SUMPRODUCT((Inputs!$C$5:$C$230=$B4)*ISNUMBER(INDEX(Inputs!$K$5:$AJ$230,0,MATCH(AH$2,Inputs!$K$4:$AJ$4,0))))+SUMPRODUCT((Inputs!$E$5:$E$230=$B4)*ISNUMBER(INDEX(Inputs!$K$5:$AJ$230,0,MATCH(AH$2,Inputs!$K$4:$AJ$4,0))))=0,NA(),SUMPRODUCT((Inputs!$A$5:$A$230=$B4)*Inputs!$B$5:$B$230*(((Inputs!$G$5:$G$230="moeda")+(Inputs!$G$5:$G$230="acoes"))*Inputs!$B$1+((Inputs!$G$5:$G$230<>"moeda")*(Inputs!$G$5:$G$230<>"acoes")))*INDEX(Inputs!$K$5:$AJ$230,0,MATCH(AH$2,Inputs!$K$4:$AJ$4,0)))+SUMPRODUCT((Inputs!$C$5:$C$230=$B4)*Inputs!$D$5:$D$230*(((Inputs!$G$5:$G$230="moeda")+(Inputs!$G$5:$G$230="acoes"))*Inputs!$B$1+((Inputs!$G$5:$G$230<>"moeda")*(Inputs!$G$5:$G$230<>"acoes")))*INDEX(Inputs!$K$5:$AJ$230,0,MATCH(AH$2,Inputs!$K$4:$AJ$4,0)))+SUMPRODUCT((Inputs!$E$5:$E$230=$B4)*Inputs!$F$5:$F$230*(((Inputs!$G$5:$G$230="moeda")+(Inputs!$G$5:$G$230="acoes"))*Inputs!$B$1+((Inputs!$G$5:$G$230<>"moeda")*(Inputs!$G$5:$G$230<>"acoes")))*INDEX(Inputs!$K$5:$AJ$230,0,MATCH(AH$2,Inputs!$K$4:$AJ$4,0))))) -> 1216.927 | AI4: =IF(ISNA(MATCH(AI$2,Inputs!$K$4:$AJ$4,0)),NA(),IF(SUMPRODUCT((Inputs!$A$5:$A$230=$B4)*ISNUMBER(INDEX(Inputs!$K$5:$AJ$230,0,MATCH(AI$2,Inputs!$K$4:$AJ$4,0))))+SUMPRODUCT((Inputs!$C$5:$C$230=$B4)*ISNUMBER(INDEX(Inputs!$K$5:$AJ$230,0,MATCH(AI$2,Inputs!$K$4:$AJ$4,0))))+SUMPRODUCT((Inputs!$E$5:$E$230=$B4)*ISNUMBER(INDEX(Inputs!$K$5:$AJ$230,0,MATCH(AI$2,Inputs!$K$4:$AJ$4,0))))=0,NA(),SUMPRODUCT((Inputs!$A$5:$A$230=$B4)*Inputs!$B$5:$B$230*(((Inputs!$G$5:$G$230="moeda")+(Inputs!$G$5:$G$230="acoes"))*Inputs!$B$1+((Inputs!$G$5:$G$230<>"moeda")*(Inputs!$G$5:$G$230<>"acoes")))*INDEX(Inputs!$K$5:$AJ$230,0,MATCH(AI$2,Inputs!$K$4:$AJ$4,0)))+SUMPRODUCT((Inputs!$C$5:$C$230=$B4)*Inputs!$D$5:$D$230*(((Inputs!$G$5:$G$230="moeda")+(Inputs!$G$5:$G$230="acoes"))*Inputs!$B$1+((Inputs!$G$5:$G$230<>"moeda")*(Inputs!$G$5:$G$230<>"acoes")))*INDEX(Inputs!$K$5:$AJ$230,0,MATCH(AI$2,Inputs!$K$4:$AJ$4,0)))+SUMPRODUCT((Inputs!$E$5:$E$230=$B4)*Inputs!$F$5:$F$230*(((Inputs!$G$5:$G$230="moeda")+(Inputs!$G$5:$G$230="acoes"))*Inputs!$B$1+((Inputs!$G$5:$G$230<>"moeda")*(Inputs!$G$5:$G$230<>"acoes")))*INDEX(Inputs!$K$5:$AJ$230,0,MATCH(AI$2,Inputs!$K$4:$AJ$4,0))))) -> 1026.976 | AJ4: =IF(ISNA(MATCH(AJ$2,Inputs!$K$4:$AJ$4,0)),NA(),IF(SUMPRODUCT((Inputs!$A$5:$A$230=$B4)*ISNUMBER(INDEX(Inputs!$K$5:$AJ$230,0,MATCH(AJ$2,Inputs!$K$4:$AJ$4,0))))+SUMPRODUCT((Inputs!$C$5:$C$230=$B4)*ISNUMBER(INDEX(Inputs!$K$5:$AJ$230,0,MATCH(AJ$2,Inputs!$K$4:$AJ$4,0))))+SUMPRODUCT((Inputs!$E$5:$E$230=$B4)*ISNUMBER(INDEX(Inputs!$K$5:$AJ$230,0,MATCH(AJ$2,Inputs!$K$4:$AJ$4,0))))=0,NA(),SUMPRODUCT((Inputs!$A$5:$A$230=$B4)*Inputs!$B$5:$B$230*(((Inputs!$G$5:$G$230="moeda")+(Inputs!$G$5:$G$230="acoes"))*Inputs!$B$1+((Inputs!$G$5:$G$230<>"moeda")*(Inputs!$G$5:$G$230<>"acoes")))*INDEX(Inputs!$K$5:$AJ$230,0,MATCH(AJ$2,Inputs!$K$4:$AJ$4,0)))+SUMPRODUCT((Inputs!$C$5:$C$230=$B4)*Inputs!$D$5:$D$230*(((Inputs!$G$5:$G$230="moeda")+(Inputs!$G$5:$G$230="acoes"))*Inputs!$B$1+((Inputs!$G$5:$G$230<>"moeda")*(Inputs!$G$5:$G$230<>"acoes")))*INDEX(Inputs!$K$5:$AJ$230,0,MATCH(AJ$2,Inputs!$K$4:$AJ$4,0)))+SUMPRODUCT((Inputs!$E$5:$E$230=$B4)*Inputs!$F$5:$F$230*(((Inputs!$G$5:$G$230="moeda")+(Inputs!$G$5:$G$230="acoes"))*Inputs!$B$1+((Inputs!$G$5:$G$230<>"moeda")*(Inputs!$G$5:$G$230<>"acoes")))*INDEX(Inputs!$K$5:$AJ$230,0,MATCH(AJ$2,Inputs!$K$4:$AJ$4,0))))) -> 1491.323 | AK4: =IF(ISNA(MATCH(AK$2,Inputs!$K$4:$AJ$4,0)),NA(),IF(SUMPRODUCT((Inputs!$A$5:$A$230=$B4)*ISNUMBER(INDEX(Inputs!$K$5:$AJ$230,0,MATCH(AK$2,Inputs!$K$4:$AJ$4,0))))+SUMPRODUCT((Inputs!$C$5:$C$230=$B4)*ISNUMBER(INDEX(Inputs!$K$5:$AJ$230,0,MATCH(AK$2,Inputs!$K$4:$AJ$4,0))))+SUMPRODUCT((Inputs!$E$5:$E$230=$B4)*ISNUMBER(INDEX(Inputs!$K$5:$AJ$230,0,MATCH(AK$2,Inputs!$K$4:$AJ$4,0))))=0,NA(),SUMPRODUCT((Inputs!$A$5:$A$230=$B4)*Inputs!$B$5:$B$230*(((Inputs!$G$5:$G$230="moeda")+(Inputs!$G$5:$G$230="acoes"))*Inputs!$B$1+((Inputs!$G$5:$G$230<>"moeda")*(Inputs!$G$5:$G$230<>"acoes")))*INDEX(Inputs!$K$5:$AJ$230,0,MATCH(AK$2,Inputs!$K$4:$AJ$4,0)))+SUMPRODUCT((Inputs!$C$5:$C$230=$B4)*Inputs!$D$5:$D$230*(((Inputs!$G$5:$G$230="moeda")+(Inputs!$G$5:$G$230="acoes"))*Inputs!$B$1+((Inputs!$G$5:$G$230<>"moeda")*(Inputs!$G$5:$G$230<>"acoes")))*INDEX(Inputs!$K$5:$AJ$230,0,MATCH(AK$2,Inputs!$K$4:$AJ$4,0)))+SUMPRODUCT((Inputs!$E$5:$E$230=$B4)*Inputs!$F$5:$F$230*(((Inputs!$G$5:$G$230="moeda")+(Inputs!$G$5:$G$230="acoes"))*Inputs!$B$1+((Inputs!$G$5:$G$230<>"moeda")*(Inputs!$G$5:$G$230<>"acoes")))*INDEX(Inputs!$K$5:$AJ$230,0,MATCH(AK$2,Inputs!$K$4:$AJ$4,0))))) -> 2405.519 | AL4: =SUM(AH4:AK4) -> 6140.745
B5: 2 | C5: COGS (cash) | D5: =IF(ISNA(MATCH(D$2,Inputs!$K$4:$AJ$4,0)),NA(),IF(SUMPRODUCT((Inputs!$A$5:$A$230=$B5)*ISNUMBER(INDEX(Inputs!$K$5:$AJ$230,0,MATCH(D$2,Inputs!$K$4:$AJ$4,0))))+SUMPRODUCT((Inputs!$C$5:$C$230=$B5)*ISNUMBER(INDEX(Inputs!$K$5:$AJ$230,0,MATCH(D$2,Inputs!$K$4:$AJ$4,0))))+SUMPRODUCT((Inputs!$E$5:$E$230=$B5)*ISNUMBER(INDEX(Inputs!$K$5:$AJ$230,0,MATCH(D$2,Inputs!$K$4:$AJ$4,0))))=0,NA(),SUMPRODUCT((Inputs!$A$5:$A$230=$B5)*Inputs!$B$5:$B$230*(((Inputs!$G$5:$G$230="moeda")+(Inputs!$G$5:$G$230="acoes"))*Inputs!$B$1+((Inputs!$G$5:$G$230<>"moeda")*(Inputs!$G$5:$G$230<>"acoes")))*INDEX(Inputs!$K$5:$AJ$230,0,MATCH(D$2,Inputs!$K$4:$AJ$4,0)))+SUMPRODUCT((Inputs!$C$5:$C$230=$B5)*Inputs!$D$5:$D$230*(((Inputs!$G$5:$G$230="moeda")+(Inputs!$G$5:$G$230="acoes"))*Inputs!$B$1+((Inputs!$G$5:$G$230<>"moeda")*(Inputs!$G$5:$G$230<>"acoes")))*INDEX(Inputs!$K$5:$AJ$230,0,MATCH(D$2,Inputs!$K$4:$AJ$4,0)))+SUMPRODUCT((Inputs!$E$5:$E$230=$B5)*Inputs!$F$5:$F$230*(((Inputs!$G$5:$G$230="moeda")+(Inputs!$G$5:$G$230="acoes"))*Inputs!$B$1+((Inputs!$G$5:$G$230<>"moeda")*(Inputs!$G$5:$G$230<>"acoes")))*INDEX(Inputs!$K$5:$AJ$230,0,MATCH(D$2,Inputs!$K$4:$AJ$4,0))))) -> -471.033 | E5: =IF(ISNA(MATCH(E$2,Inputs!$K$4:$AJ$4,0)),NA(),IF(SUMPRODUCT((Inputs!$A$5:$A$230=$B5)*ISNUMBER(INDEX(Inputs!$K$5:$AJ$230,0,MATCH(E$2,Inputs!$K$4:$AJ$4,0))))+SUMPRODUCT((Inputs!$C$5:$C$230=$B5)*ISNUMBER(INDEX(Inputs!$K$5:$AJ$230,0,MATCH(E$2,Inputs!$K$4:$AJ$4,0))))+SUMPRODUCT((Inputs!$E$5:$E$230=$B5)*ISNUMBER(INDEX(Inputs!$K$5:$AJ$230,0,MATCH(E$2,Inputs!$K$4:$AJ$4,0))))=0,NA(),SUMPRODUCT((Inputs!$A$5:$A$230=$B5)*Inputs!$B$5:$B$230*(((Inputs!$G$5:$G$230="moeda")+(Inputs!$G$5:$G$230="acoes"))*Inputs!$B$1+((Inputs!$G$5:$G$230<>"moeda")*(Inputs!$G$5:$G$230<>"acoes")))*INDEX(Inputs!$K$5:$AJ$230,0,MATCH(E$2,Inputs!$K$4:$AJ$4,0)))+SUMPRODUCT((Inputs!$C$5:$C$230=$B5)*Inputs!$D$5:$D$230*(((Inputs!$G$5:$G$230="moeda")+(Inputs!$G$5:$G$230="acoes"))*Inputs!$B$1+((Inputs!$G$5:$G$230<>"moeda")*(Inputs!$G$5:$G$230<>"acoes")))*INDEX(Inputs!$K$5:$AJ$230,0,MATCH(E$2,Inputs!$K$4:$AJ$4,0)))+SUMPRODUCT((Inputs!$E$5:$E$230=$B5)*Inputs!$F$5:$F$230*(((Inputs!$G$5:$G$230="moeda")+(Inputs!$G$5:$G$230="acoes"))*Inputs!$B$1+((Inputs!$G$5:$G$230<>"moeda")*(Inputs!$G$5:$G$230<>"acoes")))*INDEX(Inputs!$K$5:$AJ$230,0,MATCH(E$2,Inputs!$K$4:$AJ$4,0))))) -> -201.254 | F5: =IF(ISNA(MATCH(F$2,Inputs!$K$4:$AJ$4,0)),NA(),IF(SUMPRODUCT((Inputs!$A$5:$A$230=$B5)*ISNUMBER(INDEX(Inputs!$K$5:$AJ$230,0,MATCH(F$2,Inputs!$K$4:$AJ$4,0))))+SUMPRODUCT((Inputs!$C$5:$C$230=$B5)*ISNUMBER(INDEX(Inputs!$K$5:$AJ$230,0,MATCH(F$2,Inputs!$K$4:$AJ$4,0))))+SUMPRODUCT((Inputs!$E$5:$E$230=$B5)*ISNUMBER(INDEX(Inputs!$K$5:$AJ$230,0,MATCH(F$2,Inputs!$K$4:$AJ$4,0))))=0,NA(),SUMPRODUCT((Inputs!$A$5:$A$230=$B5)*Inputs!$B$5:$B$230*(((Inputs!$G$5:$G$230="moeda")+(Inputs!$G$5:$G$230="acoes"))*Inputs!$B$1+((Inputs!$G$5:$G$230<>"moeda")*(Inputs!$G$5:$G$230<>"acoes")))*INDEX(Inputs!$K$5:$AJ$230,0,MATCH(F$2,Inputs!$K$4:$AJ$4,0)))+SUMPRODUCT((Inputs!$C$5:$C$230=$B5)*Inputs!$D$5:$D$230*(((Inputs!$G$5:$G$230="moeda")+(Inputs!$G$5:$G$230="acoes"))*Inputs!$B$1+((Inputs!$G$5:$G$230<>"moeda")*(Inputs!$G$5:$G$230<>"acoes")))*INDEX(Inputs!$K$5:$AJ$230,0,MATCH(F$2,Inputs!$K$4:$AJ$4,0)))+SUMPRODUCT((Inputs!$E$5:$E$230=$B5)*Inputs!$F$5:$F$230*(((Inputs!$G$5:$G$230="moeda")+(Inputs!$G$5:$G$230="acoes"))*Inputs!$B$1+((Inputs!$G$5:$G$230<>"moeda")*(Inputs!$G$5:$G$230<>"acoes")))*INDEX(Inputs!$K$5:$AJ$230,0,MATCH(F$2,Inputs!$K$4:$AJ$4,0))))) -> -287.047 | G5: =IF(ISNA(MATCH(G$2,Inputs!$K$4:$AJ$4,0)),NA(),IF(SUMPRODUCT((Inputs!$A$5:$A$230=$B5)*ISNUMBER(INDEX(Inputs!$K$5:$AJ$230,0,MATCH(G$2,Inputs!$K$4:$AJ$4,0))))+SUMPRODUCT((Inputs!$C$5:$C$230=$B5)*ISNUMBER(INDEX(Inputs!$K$5:$AJ$230,0,MATCH(G$2,Inputs!$K$4:$AJ$4,0))))+SUMPRODUCT((Inputs!$E$5:$E$230=$B5)*ISNUMBER(INDEX(Inputs!$K$5:$AJ$230,0,MATCH(G$2,Inputs!$K$4:$AJ$4,0))))=0,NA(),SUMPRODUCT((Inputs!$A$5:$A$230=$B5)*Inputs!$B$5:$B$230*(((Inputs!$G$5:$G$230="moeda")+(Inputs!$G$5:$G$230="acoes"))*Inputs!$B$1+((Inputs!$G$5:$G$230<>"moeda")*(Inputs!$G$5:$G$230<>"acoes")))*INDEX(Inputs!$K$5:$AJ$230,0,MATCH(G$2,Inputs!$K$4:$AJ$4,0)))+SUMPRODUCT((Inputs!$C$5:$C$230=$B5)*Inputs!$D$5:$D$230*(((Inputs!$G$5:$G$230="moeda")+(Inputs!$G$5:$G$230="acoes"))*Inputs!$B$1+((Inputs!$G$5:$G$230<>"moeda")*(Inputs!$G$5:$G$230<>"acoes")))*INDEX(Inputs!$K$5:$AJ$230,0,MATCH(G$2,Inputs!$K$4:$AJ$4,0)))+SUMPRODUCT((Inputs!$E$5:$E$230=$B5)*Inputs!$F$5:$F$230*(((Inputs!$G$5:$G$230="moeda")+(Inputs!$G$5:$G$230="acoes"))*Inputs!$B$1+((Inputs!$G$5:$G$230<>"moeda")*(Inputs!$G$5:$G$230<>"acoes")))*INDEX(Inputs!$K$5:$AJ$230,0,MATCH(G$2,Inputs!$K$4:$AJ$4,0))))) -> -305.796 | H5: =SUM(D5:G5) -> -1265.13 | I5: =IF(ISNA(MATCH(I$2,Inputs!$K$4:$AJ$4,0)),NA(),IF(SUMPRODUCT((Inputs!$A$5:$A$230=$B5)*ISNUMBER(INDEX(Inputs!$K$5:$AJ$230,0,MATCH(I$2,Inputs!$K$4:$AJ$4,0))))+SUMPRODUCT((Inputs!$C$5:$C$230=$B5)*ISNUMBER(INDEX(Inputs!$K$5:$AJ$230,0,MATCH(I$2,Inputs!$K$4:$AJ$4,0))))+SUMPRODUCT((Inputs!$E$5:$E$230=$B5)*ISNUMBER(INDEX(Inputs!$K$5:$AJ$230,0,MATCH(I$2,Inputs!$K$4:$AJ$4,0))))=0,NA(),SUMPRODUCT((Inputs!$A$5:$A$230=$B5)*Inputs!$B$5:$B$230*(((Inputs!$G$5:$G$230="moeda")+(Inputs!$G$5:$G$230="acoes"))*Inputs!$B$1+((Inputs!$G$5:$G$230<>"moeda")*(Inputs!$G$5:$G$230<>"acoes")))*INDEX(Inputs!$K$5:$AJ$230,0,MATCH(I$2,Inputs!$K$4:$AJ$4,0)))+SUMPRODUCT((Inputs!$C$5:$C$230=$B5)*Inputs!$D$5:$D$230*(((Inputs!$G$5:$G$230="moeda")+(Inputs!$G$5:$G$230="acoes"))*Inputs!$B$1+((Inputs!$G$5:$G$230<>"moeda")*(Inputs!$G$5:$G$230<>"acoes")))*INDEX(Inputs!$K$5:$AJ$230,0,MATCH(I$2,Inputs!$K$4:$AJ$4,0)))+SUMPRODUCT((Inputs!$E$5:$E$230=$B5)*Inputs!$F$5:$F$230*(((Inputs!$G$5:$G$230="moeda")+(Inputs!$G$5:$G$230="acoes"))*Inputs!$B$1+((Inputs!$G$5:$G$230<>"moeda")*(Inputs!$G$5:$G$230<>"acoes")))*INDEX(Inputs!$K$5:$AJ$230,0,MATCH(I$2,Inputs!$K$4:$AJ$4,0))))) -> -134.789 | J5: =IF(ISNA(MATCH(J$2,Inputs!$K$4:$AJ$4,0)),NA(),IF(SUMPRODUCT((Inputs!$A$5:$A$230=$B5)*ISNUMBER(INDEX(Inputs!$K$5:$AJ$230,0,MATCH(J$2,Inputs!$K$4:$AJ$4,0))))+SUMPRODUCT((Inputs!$C$5:$C$230=$B5)*ISNUMBER(INDEX(Inputs!$K$5:$AJ$230,0,MATCH(J$2,Inputs!$K$4:$AJ$4,0))))+SUMPRODUCT((Inputs!$E$5:$E$230=$B5)*ISNUMBER(INDEX(Inputs!$K$5:$AJ$230,0,MATCH(J$2,Inputs!$K$4:$AJ$4,0))))=0,NA(),SUMPRODUCT((Inputs!$A$5:$A$230=$B5)*Inputs!$B$5:$B$230*(((Inputs!$G$5:$G$230="moeda")+(Inputs!$G$5:$G$230="acoes"))*Inputs!$B$1+((Inputs!$G$5:$G$230<>"moeda")*(Inputs!$G$5:$G$230<>"acoes")))*INDEX(Inputs!$K$5:$AJ$230,0,MATCH(J$2,Inputs!$K$4:$AJ$4,0)))+SUMPRODUCT((Inputs!$C$5:$C$230=$B5)*Inputs!$D$5:$D$230*(((Inputs!$G$5:$G$230="moeda")+(Inputs!$G$5:$G$230="acoes"))*Inputs!$B$1+((Inputs!$G$5:$G$230<>"moeda")*(Inputs!$G$5:$G$230<>"acoes")))*INDEX(Inputs!$K$5:$AJ$230,0,MATCH(J$2,Inputs!$K$4:$AJ$4,0)))+SUMPRODUCT((Inputs!$E$5:$E$230=$B5)*Inputs!$F$5:$F$230*(((Inputs!$G$5:$G$230="moeda")+(Inputs!$G$5:$G$230="acoes"))*Inputs!$B$1+((Inputs!$G$5:$G$230<>"moeda")*(Inputs!$G$5:$G$230<>"acoes")))*INDEX(Inputs!$K$5:$AJ$230,0,MATCH(J$2,Inputs!$K$4:$AJ$4,0))))) -> -123.632 | K5: =IF(ISNA(MATCH(K$2,Inputs!$K$4:$AJ$4,0)),NA(),IF(SUMPRODUCT((Inputs!$A$5:$A$230=$B5)*ISNUMBER(INDEX(Inputs!$K$5:$AJ$230,0,MATCH(K$2,Inputs!$K$4:$AJ$4,0))))+SUMPRODUCT((Inputs!$C$5:$C$230=$B5)*ISNUMBER(INDEX(Inputs!$K$5:$AJ$230,0,MATCH(K$2,Inputs!$K$4:$AJ$4,0))))+SUMPRODUCT((Inputs!$E$5:$E$230=$B5)*ISNUMBER(INDEX(Inputs!$K$5:$AJ$230,0,MATCH(K$2,Inputs!$K$4:$AJ$4,0))))=0,NA(),SUMPRODUCT((Inputs!$A$5:$A$230=$B5)*Inputs!$B$5:$B$230*(((Inputs!$G$5:$G$230="moeda")+(Inputs!$G$5:$G$230="acoes"))*Inputs!$B$1+((Inputs!$G$5:$G$230<>"moeda")*(Inputs!$G$5:$G$230<>"acoes")))*INDEX(Inputs!$K$5:$AJ$230,0,MATCH(K$2,Inputs!$K$4:$AJ$4,0)))+SUMPRODUCT((Inputs!$C$5:$C$230=$B5)*Inputs!$D$5:$D$230*(((Inputs!$G$5:$G$230="moeda")+(Inputs!$G$5:$G$230="acoes"))*Inputs!$B$1+((Inputs!$G$5:$G$230<>"moeda")*(Inputs!$G$5:$G$230<>"acoes")))*INDEX(Inputs!$K$5:$AJ$230,0,MATCH(K$2,Inputs!$K$4:$AJ$4,0)))+SUMPRODUCT((Inputs!$E$5:$E$230=$B5)*Inputs!$F$5:$F$230*(((Inputs!$G$5:$G$230="moeda")+(Inputs!$G$5:$G$230="acoes"))*Inputs!$B$1+((Inputs!$G$5:$G$230<>"moeda")*(Inputs!$G$5:$G$230<>"acoes")))*INDEX(Inputs!$K$5:$AJ$230,0,MATCH(K$2,Inputs!$K$4:$AJ$4,0))))) -> -131.418 | L5: =IF(ISNA(MATCH(L$2,Inputs!$K$4:$AJ$4,0)),NA(),IF(SUMPRODUCT((Inputs!$A$5:$A$230=$B5)*ISNUMBER(INDEX(Inputs!$K$5:$AJ$230,0,MATCH(L$2,Inputs!$K$4:$AJ$4,0))))+SUMPRODUCT((Inputs!$C$5:$C$230=$B5)*ISNUMBER(INDEX(Inputs!$K$5:$AJ$230,0,MATCH(L$2,Inputs!$K$4:$AJ$4,0))))+SUMPRODUCT((Inputs!$E$5:$E$230=$B5)*ISNUMBER(INDEX(Inputs!$K$5:$AJ$230,0,MATCH(L$2,Inputs!$K$4:$AJ$4,0))))=0,NA(),SUMPRODUCT((Inputs!$A$5:$A$230=$B5)*Inputs!$B$5:$B$230*(((Inputs!$G$5:$G$230="moeda")+(Inputs!$G$5:$G$230="acoes"))*Inputs!$B$1+((Inputs!$G$5:$G$230<>"moeda")*(Inputs!$G$5:$G$230<>"acoes")))*INDEX(Inputs!$K$5:$AJ$230,0,MATCH(L$2,Inputs!$K$4:$AJ$4,0)))+SUMPRODUCT((Inputs!$C$5:$C$230=$B5)*Inputs!$D$5:$D$230*(((Inputs!$G$5:$G$230="moeda")+(Inputs!$G$5:$G$230="acoes"))*Inputs!$B$1+((Inputs!$G$5:$G$230<>"moeda")*(Inputs!$G$5:$G$230<>"acoes")))*INDEX(Inputs!$K$5:$AJ$230,0,MATCH(L$2,Inputs!$K$4:$AJ$4,0)))+SUMPRODUCT((Inputs!$E$5:$E$230=$B5)*Inputs!$F$5:$F$230*(((Inputs!$G$5:$G$230="moeda")+(Inputs!$G$5:$G$230="acoes"))*Inputs!$B$1+((Inputs!$G$5:$G$230<>"moeda")*(Inputs!$G$5:$G$230<>"acoes")))*INDEX(Inputs!$K$5:$AJ$230,0,MATCH(L$2,Inputs!$K$4:$AJ$4,0))))) -> -161.074 | M5: =SUM(I5:L5) -> -550.913 | N5: =IF(ISNA(MATCH(N$2,Inputs!$K$4:$AJ$4,0)),NA(),IF(SUMPRODUCT((Inputs!$A$5:$A$230=$B5)*ISNUMBER(INDEX(Inputs!$K$5:$AJ$230,0,MATCH(N$2,Inputs!$K$4:$AJ$4,0))))+SUMPRODUCT((Inputs!$C$5:$C$230=$B5)*ISNUMBER(INDEX(Inputs!$K$5:$AJ$230,0,MATCH(N$2,Inputs!$K$4:$AJ$4,0))))+SUMPRODUCT((Inputs!$E$5:$E$230=$B5)*ISNUMBER(INDEX(Inputs!$K$5:$AJ$230,0,MATCH(N$2,Inputs!$K$4:$AJ$4,0))))=0,NA(),SUMPRODUCT((Inputs!$A$5:$A$230=$B5)*Inputs!$B$5:$B$230*(((Inputs!$G$5:$G$230="moeda")+(Inputs!$G$5:$G$230="acoes"))*Inputs!$B$1+((Inputs!$G$5:$G$230<>"moeda")*(Inputs!$G$5:$G$230<>"acoes")))*INDEX(Inputs!$K$5:$AJ$230,0,MATCH(N$2,Inputs!$K$4:$AJ$4,0)))+SUMPRODUCT((Inputs!$C$5:$C$230=$B5)*Inputs!$D$5:$D$230*(((Inputs!$G$5:$G$230="moeda")+(Inputs!$G$5:$G$230="acoes"))*Inputs!$B$1+((Inputs!$G$5:$G$230<>"moeda")*(Inputs!$G$5:$G$230<>"acoes")))*INDEX(Inputs!$K$5:$AJ$230,0,MATCH(N$2,Inputs!$K$4:$AJ$4,0)))+SUMPRODUCT((Inputs!$E$5:$E$230=$B5)*Inputs!$F$5:$F$230*(((Inputs!$G$5:$G$230="moeda")+(Inputs!$G$5:$G$230="acoes"))*Inputs!$B$1+((Inputs!$G$5:$G$230<>"moeda")*(Inputs!$G$5:$G$230<>"acoes")))*INDEX(Inputs!$K$5:$AJ$230,0,MATCH(N$2,Inputs!$K$4:$AJ$4,0))))) -> -161.718 | O5: =IF(ISNA(MATCH(O$2,Inputs!$K$4:$AJ$4,0)),NA(),IF(SUMPRODUCT((Inputs!$A$5:$A$230=$B5)*ISNUMBER(INDEX(Inputs!$K$5:$AJ$230,0,MATCH(O$2,Inputs!$K$4:$AJ$4,0))))+SUMPRODUCT((Inputs!$C$5:$C$230=$B5)*ISNUMBER(INDEX(Inputs!$K$5:$AJ$230,0,MATCH(O$2,Inputs!$K$4:$AJ$4,0))))+SUMPRODUCT((Inputs!$E$5:$E$230=$B5)*ISNUMBER(INDEX(Inputs!$K$5:$AJ$230,0,MATCH(O$2,Inputs!$K$4:$AJ$4,0))))=0,NA(),SUMPRODUCT((Inputs!$A$5:$A$230=$B5)*Inputs!$B$5:$B$230*(((Inputs!$G$5:$G$230="moeda")+(Inputs!$G$5:$G$230="acoes"))*Inputs!$B$1+((Inputs!$G$5:$G$230<>"moeda")*(Inputs!$G$5:$G$230<>"acoes")))*INDEX(Inputs!$K$5:$AJ$230,0,MATCH(O$2,Inputs!$K$4:$AJ$4,0)))+SUMPRODUCT((Inputs!$C$5:$C$230=$B5)*Inputs!$D$5:$D$230*(((Inputs!$G$5:$G$230="moeda")+(Inputs!$G$5:$G$230="acoes"))*Inputs!$B$1+((Inputs!$G$5:$G$230<>"moeda")*(Inputs!$G$5:$G$230<>"acoes")))*INDEX(Inputs!$K$5:$AJ$230,0,MATCH(O$2,Inputs!$K$4:$AJ$4,0)))+SUMPRODUCT((Inputs!$E$5:$E$230=$B5)*Inputs!$F$5:$F$230*(((Inputs!$G$5:$G$230="moeda")+(Inputs!$G$5:$G$230="acoes"))*Inputs!$B$1+((Inputs!$G$5:$G$230<>"moeda")*(Inputs!$G$5:$G$230<>"acoes")))*INDEX(Inputs!$K$5:$AJ$230,0,MATCH(O$2,Inputs!$K$4:$AJ$4,0))))) -> -136.738 | P5: =IF(ISNA(MATCH(P$2,Inputs!$K$4:$AJ$4,0)),NA(),IF(SUMPRODUCT((Inputs!$A$5:$A$230=$B5)*ISNUMBER(INDEX(Inputs!$K$5:$AJ$230,0,MATCH(P$2,Inputs!$K$4:$AJ$4,0))))+SUMPRODUCT((Inputs!$C$5:$C$230=$B5)*ISNUMBER(INDEX(Inputs!$K$5:$AJ$230,0,MATCH(P$2,Inputs!$K$4:$AJ$4,0))))+SUMPRODUCT((Inputs!$E$5:$E$230=$B5)*ISNUMBER(INDEX(Inputs!$K$5:$AJ$230,0,MATCH(P$2,Inputs!$K$4:$AJ$4,0))))=0,NA(),SUMPRODUCT((Inputs!$A$5:$A$230=$B5)*Inputs!$B$5:$B$230*(((Inputs!$G$5:$G$230="moeda")+(Inputs!$G$5:$G$230="acoes"))*Inputs!$B$1+((Inputs!$G$5:$G$230<>"moeda")*(Inputs!$G$5:$G$230<>"acoes")))*INDEX(Inputs!$K$5:$AJ$230,0,MATCH(P$2,Inputs!$K$4:$AJ$4,0)))+SUMPRODUCT((Inputs!$C$5:$C$230=$B5)*Inputs!$D$5:$D$230*(((Inputs!$G$5:$G$230="moeda")+(Inputs!$G$5:$G$230="acoes"))*Inputs!$B$1+((Inputs!$G$5:$G$230<>"moeda")*(Inputs!$G$5:$G$230<>"acoes")))*INDEX(Inputs!$K$5:$AJ$230,0,MATCH(P$2,Inputs!$K$4:$AJ$4,0)))+SUMPRODUCT((Inputs!$E$5:$E$230=$B5)*Inputs!$F$5:$F$230*(((Inputs!$G$5:$G$230="moeda")+(Inputs!$G$5:$G$230="acoes"))*Inputs!$B$1+((Inputs!$G$5:$G$230<>"moeda")*(Inputs!$G$5:$G$230<>"acoes")))*INDEX(Inputs!$K$5:$AJ$230,0,MATCH(P$2,Inputs!$K$4:$AJ$4,0))))) -> -161.738 | Q5: =IF(ISNA(MATCH(Q$2,Inputs!$K$4:$AJ$4,0)),NA(),IF(SUMPRODUCT((Inputs!$A$5:$A$230=$B5)*ISNUMBER(INDEX(Inputs!$K$5:$AJ$230,0,MATCH(Q$2,Inputs!$K$4:$AJ$4,0))))+SUMPRODUCT((Inputs!$C$5:$C$230=$B5)*ISNUMBER(INDEX(Inputs!$K$5:$AJ$230,0,MATCH(Q$2,Inputs!$K$4:$AJ$4,0))))+SUMPRODUCT((Inputs!$E$5:$E$230=$B5)*ISNUMBER(INDEX(Inputs!$K$5:$AJ$230,0,MATCH(Q$2,Inputs!$K$4:$AJ$4,0))))=0,NA(),SUMPRODUCT((Inputs!$A$5:$A$230=$B5)*Inputs!$B$5:$B$230*(((Inputs!$G$5:$G$230="moeda")+(Inputs!$G$5:$G$230="acoes"))*Inputs!$B$1+((Inputs!$G$5:$G$230<>"moeda")*(Inputs!$G$5:$G$230<>"acoes")))*INDEX(Inputs!$K$5:$AJ$230,0,MATCH(Q$2,Inputs!$K$4:$AJ$4,0)))+SUMPRODUCT((Inputs!$C$5:$C$230=$B5)*Inputs!$D$5:$D$230*(((Inputs!$G$5:$G$230="moeda")+(Inputs!$G$5:$G$230="acoes"))*Inputs!$B$1+((Inputs!$G$5:$G$230<>"moeda")*(Inputs!$G$5:$G$230<>"acoes")))*INDEX(Inputs!$K$5:$AJ$230,0,MATCH(Q$2,Inputs!$K$4:$AJ$4,0)))+SUMPRODUCT((Inputs!$E$5:$E$230=$B5)*Inputs!$F$5:$F$230*(((Inputs!$G$5:$G$230="moeda")+(Inputs!$G$5:$G$230="acoes"))*Inputs!$B$1+((Inputs!$G$5:$G$230<>"moeda")*(Inputs!$G$5:$G$230<>"acoes")))*INDEX(Inputs!$K$5:$AJ$230,0,MATCH(Q$2,Inputs!$K$4:$AJ$4,0))))) -> -189.695 | R5: =SUM(N5:Q5) -> -649.889 | S5: =IF(ISNA(MATCH(S$2,Inputs!$K$4:$AJ$4,0)),NA(),IF(SUMPRODUCT((Inputs!$A$5:$A$230=$B5)*ISNUMBER(INDEX(Inputs!$K$5:$AJ$230,0,MATCH(S$2,Inputs!$K$4:$AJ$4,0))))+SUMPRODUCT((Inputs!$C$5:$C$230=$B5)*ISNUMBER(INDEX(Inputs!$K$5:$AJ$230,0,MATCH(S$2,Inputs!$K$4:$AJ$4,0))))+SUMPRODUCT((Inputs!$E$5:$E$230=$B5)*ISNUMBER(INDEX(Inputs!$K$5:$AJ$230,0,MATCH(S$2,Inputs!$K$4:$AJ$4,0))))=0,NA(),SUMPRODUCT((Inputs!$A$5:$A$230=$B5)*Inputs!$B$5:$B$230*(((Inputs!$G$5:$G$230="moeda")+(Inputs!$G$5:$G$230="acoes"))*Inputs!$B$1+((Inputs!$G$5:$G$230<>"moeda")*(Inputs!$G$5:$G$230<>"acoes")))*INDEX(Inputs!$K$5:$AJ$230,0,MATCH(S$2,Inputs!$K$4:$AJ$4,0)))+SUMPRODUCT((Inputs!$C$5:$C$230=$B5)*Inputs!$D$5:$D$230*(((Inputs!$G$5:$G$230="moeda")+(Inputs!$G$5:$G$230="acoes"))*Inputs!$B$1+((Inputs!$G$5:$G$230<>"moeda")*(Inputs!$G$5:$G$230<>"acoes")))*INDEX(Inputs!$K$5:$AJ$230,0,MATCH(S$2,Inputs!$K$4:$AJ$4,0)))+SUMPRODUCT((Inputs!$E$5:$E$230=$B5)*Inputs!$F$5:$F$230*(((Inputs!$G$5:$G$230="moeda")+(Inputs!$G$5:$G$230="acoes"))*Inputs!$B$1+((Inputs!$G$5:$G$230<>"moeda")*(Inputs!$G$5:$G$230<>"acoes")))*INDEX(Inputs!$K$5:$AJ$230,0,MATCH(S$2,Inputs!$K$4:$AJ$4,0))))) -> -168.17 | T5: =IF(ISNA(MATCH(T$2,Inputs!$K$4:$AJ$4,0)),NA(),IF(SUMPRODUCT((Inputs!$A$5:$A$230=$B5)*ISNUMBER(INDEX(Inputs!$K$5:$AJ$230,0,MATCH(T$2,Inputs!$K$4:$AJ$4,0))))+SUMPRODUCT((Inputs!$C$5:$C$230=$B5)*ISNUMBER(INDEX(Inputs!$K$5:$AJ$230,0,MATCH(T$2,Inputs!$K$4:$AJ$4,0))))+SUMPRODUCT((Inputs!$E$5:$E$230=$B5)*ISNUMBER(INDEX(Inputs!$K$5:$AJ$230,0,MATCH(T$2,Inputs!$K$4:$AJ$4,0))))=0,NA(),SUMPRODUCT((Inputs!$A$5:$A$230=$B5)*Inputs!$B$5:$B$230*(((Inputs!$G$5:$G$230="moeda")+(Inputs!$G$5:$G$230="acoes"))*Inputs!$B$1+((Inputs!$G$5:$G$230<>"moeda")*(Inputs!$G$5:$G$230<>"acoes")))*INDEX(Inputs!$K$5:$AJ$230,0,MATCH(T$2,Inputs!$K$4:$AJ$4,0)))+SUMPRODUCT((Inputs!$C$5:$C$230=$B5)*Inputs!$D$5:$D$230*(((Inputs!$G$5:$G$230="moeda")+(Inputs!$G$5:$G$230="acoes"))*Inputs!$B$1+((Inputs!$G$5:$G$230<>"moeda")*(Inputs!$G$5:$G$230<>"acoes")))*INDEX(Inputs!$K$5:$AJ$230,0,MATCH(T$2,Inputs!$K$4:$AJ$4,0)))+SUMPRODUCT((Inputs!$E$5:$E$230=$B5)*Inputs!$F$5:$F$230*(((Inputs!$G$5:$G$230="moeda")+(Inputs!$G$5:$G$230="acoes"))*Inputs!$B$1+((Inputs!$G$5:$G$230<>"moeda")*(Inputs!$G$5:$G$230<>"acoes")))*INDEX(Inputs!$K$5:$AJ$230,0,MATCH(T$2,Inputs!$K$4:$AJ$4,0))))) -> -180.438 | U5: =IF(ISNA(MATCH(U$2,Inputs!$K$4:$AJ$4,0)),NA(),IF(SUMPRODUCT((Inputs!$A$5:$A$230=$B5)*ISNUMBER(INDEX(Inputs!$K$5:$AJ$230,0,MATCH(U$2,Inputs!$K$4:$AJ$4,0))))+SUMPRODUCT((Inputs!$C$5:$C$230=$B5)*ISNUMBER(INDEX(Inputs!$K$5:$AJ$230,0,MATCH(U$2,Inputs!$K$4:$AJ$4,0))))+SUMPRODUCT((Inputs!$E$5:$E$230=$B5)*ISNUMBER(INDEX(Inputs!$K$5:$AJ$230,0,MATCH(U$2,Inputs!$K$4:$AJ$4,0))))=0,NA(),SUMPRODUCT((Inputs!$A$5:$A$230=$B5)*Inputs!$B$5:$B$230*(((Inputs!$G$5:$G$230="moeda")+(Inputs!$G$5:$G$230="acoes"))*Inputs!$B$1+((Inputs!$G$5:$G$230<>"moeda")*(Inputs!$G$5:$G$230<>"acoes")))*INDEX(Inputs!$K$5:$AJ$230,0,MATCH(U$2,Inputs!$K$4:$AJ$4,0)))+SUMPRODUCT((Inputs!$C$5:$C$230=$B5)*Inputs!$D$5:$D$230*(((Inputs!$G$5:$G$230="moeda")+(Inputs!$G$5:$G$230="acoes"))*Inputs!$B$1+((Inputs!$G$5:$G$230<>"moeda")*(Inputs!$G$5:$G$230<>"acoes")))*INDEX(Inputs!$K$5:$AJ$230,0,MATCH(U$2,Inputs!$K$4:$AJ$4,0)))+SUMPRODUCT((Inputs!$E$5:$E$230=$B5)*Inputs!$F$5:$F$230*(((Inputs!$G$5:$G$230="moeda")+(Inputs!$G$5:$G$230="acoes"))*Inputs!$B$1+((Inputs!$G$5:$G$230<>"moeda")*(Inputs!$G$5:$G$230<>"acoes")))*INDEX(Inputs!$K$5:$AJ$230,0,MATCH(U$2,Inputs!$K$4:$AJ$4,0))))) -> -246.959 | V5: =IF(ISNA(MATCH(V$2,Inputs!$K$4:$AJ$4,0)),NA(),IF(SUMPRODUCT((Inputs!$A$5:$A$230=$B5)*ISNUMBER(INDEX(Inputs!$K$5:$AJ$230,0,MATCH(V$2,Inputs!$K$4:$AJ$4,0))))+SUMPRODUCT((Inputs!$C$5:$C$230=$B5)*ISNUMBER(INDEX(Inputs!$K$5:$AJ$230,0,MATCH(V$2,Inputs!$K$4:$AJ$4,0))))+SUMPRODUCT((Inputs!$E$5:$E$230=$B5)*ISNUMBER(INDEX(Inputs!$K$5:$AJ$230,0,MATCH(V$2,Inputs!$K$4:$AJ$4,0))))=0,NA(),SUMPRODUCT((Inputs!$A$5:$A$230=$B5)*Inputs!$B$5:$B$230*(((Inputs!$G$5:$G$230="moeda")+(Inputs!$G$5:$G$230="acoes"))*Inputs!$B$1+((Inputs!$G$5:$G$230<>"moeda")*(Inputs!$G$5:$G$230<>"acoes")))*INDEX(Inputs!$K$5:$AJ$230,0,MATCH(V$2,Inputs!$K$4:$AJ$4,0)))+SUMPRODUCT((Inputs!$C$5:$C$230=$B5)*Inputs!$D$5:$D$230*(((Inputs!$G$5:$G$230="moeda")+(Inputs!$G$5:$G$230="acoes"))*Inputs!$B$1+((Inputs!$G$5:$G$230<>"moeda")*(Inputs!$G$5:$G$230<>"acoes")))*INDEX(Inputs!$K$5:$AJ$230,0,MATCH(V$2,Inputs!$K$4:$AJ$4,0)))+SUMPRODUCT((Inputs!$E$5:$E$230=$B5)*Inputs!$F$5:$F$230*(((Inputs!$G$5:$G$230="moeda")+(Inputs!$G$5:$G$230="acoes"))*Inputs!$B$1+((Inputs!$G$5:$G$230<>"moeda")*(Inputs!$G$5:$G$230<>"acoes")))*INDEX(Inputs!$K$5:$AJ$230,0,MATCH(V$2,Inputs!$K$4:$AJ$4,0))))) -> -327.35 | W5: =SUM(S5:V5) -> -922.917 | X5: =IF(ISNA(MATCH(X$2,Inputs!$K$4:$AJ$4,0)),NA(),IF(SUMPRODUCT((Inputs!$A$5:$A$230=$B5)*ISNUMBER(INDEX(Inputs!$K$5:$AJ$230,0,MATCH(X$2,Inputs!$K$4:$AJ$4,0))))+SUMPRODUCT((Inputs!$C$5:$C$230=$B5)*ISNUMBER(INDEX(Inputs!$K$5:$AJ$230,0,MATCH(X$2,Inputs!$K$4:$AJ$4,0))))+SUMPRODUCT((Inputs!$E$5:$E$230=$B5)*ISNUMBER(INDEX(Inputs!$K$5:$AJ$230,0,MATCH(X$2,Inputs!$K$4:$AJ$4,0))))=0,NA(),SUMPRODUCT((Inputs!$A$5:$A$230=$B5)*Inputs!$B$5:$B$230*(((Inputs!$G$5:$G$230="moeda")+(Inputs!$G$5:$G$230="acoes"))*Inputs!$B$1+((Inputs!$G$5:$G$230<>"moeda")*(Inputs!$G$5:$G$230<>"acoes")))*INDEX(Inputs!$K$5:$AJ$230,0,MATCH(X$2,Inputs!$K$4:$AJ$4,0)))+SUMPRODUCT((Inputs!$C$5:$C$230=$B5)*Inputs!$D$5:$D$230*(((Inputs!$G$5:$G$230="moeda")+(Inputs!$G$5:$G$230="acoes"))*Inputs!$B$1+((Inputs!$G$5:$G$230<>"moeda")*(Inputs!$G$5:$G$230<>"acoes")))*INDEX(Inputs!$K$5:$AJ$230,0,MATCH(X$2,Inputs!$K$4:$AJ$4,0)))+SUMPRODUCT((Inputs!$E$5:$E$230=$B5)*Inputs!$F$5:$F$230*(((Inputs!$G$5:$G$230="moeda")+(Inputs!$G$5:$G$230="acoes"))*Inputs!$B$1+((Inputs!$G$5:$G$230<>"moeda")*(Inputs!$G$5:$G$230<>"acoes")))*INDEX(Inputs!$K$5:$AJ$230,0,MATCH(X$2,Inputs!$K$4:$AJ$4,0))))) -> -295.198 | Y5: =IF(ISNA(MATCH(Y$2,Inputs!$K$4:$AJ$4,0)),NA(),IF(SUMPRODUCT((Inputs!$A$5:$A$230=$B5)*ISNUMBER(INDEX(Inputs!$K$5:$AJ$230,0,MATCH(Y$2,Inputs!$K$4:$AJ$4,0))))+SUMPRODUCT((Inputs!$C$5:$C$230=$B5)*ISNUMBER(INDEX(Inputs!$K$5:$AJ$230,0,MATCH(Y$2,Inputs!$K$4:$AJ$4,0))))+SUMPRODUCT((Inputs!$E$5:$E$230=$B5)*ISNUMBER(INDEX(Inputs!$K$5:$AJ$230,0,MATCH(Y$2,Inputs!$K$4:$AJ$4,0))))=0,NA(),SUMPRODUCT((Inputs!$A$5:$A$230=$B5)*Inputs!$B$5:$B$230*(((Inputs!$G$5:$G$230="moeda")+(Inputs!$G$5:$G$230="acoes"))*Inputs!$B$1+((Inputs!$G$5:$G$230<>"moeda")*(Inputs!$G$5:$G$230<>"acoes")))*INDEX(Inputs!$K$5:$AJ$230,0,MATCH(Y$2,Inputs!$K$4:$AJ$4,0)))+SUMPRODUCT((Inputs!$C$5:$C$230=$B5)*Inputs!$D$5:$D$230*(((Inputs!$G$5:$G$230="moeda")+(Inputs!$G$5:$G$230="acoes"))*Inputs!$B$1+((Inputs!$G$5:$G$230<>"moeda")*(Inputs!$G$5:$G$230<>"acoes")))*INDEX(Inputs!$K$5:$AJ$230,0,MATCH(Y$2,Inputs!$K$4:$AJ$4,0)))+SUMPRODUCT((Inputs!$E$5:$E$230=$B5)*Inputs!$F$5:$F$230*(((Inputs!$G$5:$G$230="moeda")+(Inputs!$G$5:$G$230="acoes"))*Inputs!$B$1+((Inputs!$G$5:$G$230<>"moeda")*(Inputs!$G$5:$G$230<>"acoes")))*INDEX(Inputs!$K$5:$AJ$230,0,MATCH(Y$2,Inputs!$K$4:$AJ$4,0))))) -> -282.606 | Z5: =IF(ISNA(MATCH(Z$2,Inputs!$K$4:$AJ$4,0)),NA(),IF(SUMPRODUCT((Inputs!$A$5:$A$230=$B5)*ISNUMBER(INDEX(Inputs!$K$5:$AJ$230,0,MATCH(Z$2,Inputs!$K$4:$AJ$4,0))))+SUMPRODUCT((Inputs!$C$5:$C$230=$B5)*ISNUMBER(INDEX(Inputs!$K$5:$AJ$230,0,MATCH(Z$2,Inputs!$K$4:$AJ$4,0))))+SUMPRODUCT((Inputs!$E$5:$E$230=$B5)*ISNUMBER(INDEX(Inputs!$K$5:$AJ$230,0,MATCH(Z$2,Inputs!$K$4:$AJ$4,0))))=0,NA(),SUMPRODUCT((Inputs!$A$5:$A$230=$B5)*Inputs!$B$5:$B$230*(((Inputs!$G$5:$G$230="moeda")+(Inputs!$G$5:$G$230="acoes"))*Inputs!$B$1+((Inputs!$G$5:$G$230<>"moeda")*(Inputs!$G$5:$G$230<>"acoes")))*INDEX(Inputs!$K$5:$AJ$230,0,MATCH(Z$2,Inputs!$K$4:$AJ$4,0)))+SUMPRODUCT((Inputs!$C$5:$C$230=$B5)*Inputs!$D$5:$D$230*(((Inputs!$G$5:$G$230="moeda")+(Inputs!$G$5:$G$230="acoes"))*Inputs!$B$1+((Inputs!$G$5:$G$230<>"moeda")*(Inputs!$G$5:$G$230<>"acoes")))*INDEX(Inputs!$K$5:$AJ$230,0,MATCH(Z$2,Inputs!$K$4:$AJ$4,0)))+SUMPRODUCT((Inputs!$E$5:$E$230=$B5)*Inputs!$F$5:$F$230*(((Inputs!$G$5:$G$230="moeda")+(Inputs!$G$5:$G$230="acoes"))*Inputs!$B$1+((Inputs!$G$5:$G$230<>"moeda")*(Inputs!$G$5:$G$230<>"acoes")))*INDEX(Inputs!$K$5:$AJ$230,0,MATCH(Z$2,Inputs!$K$4:$AJ$4,0))))) -> -245.818 | AA5: =IF(ISNA(MATCH(AA$2,Inputs!$K$4:$AJ$4,0)),NA(),IF(SUMPRODUCT((Inputs!$A$5:$A$230=$B5)*ISNUMBER(INDEX(Inputs!$K$5:$AJ$230,0,MATCH(AA$2,Inputs!$K$4:$AJ$4,0))))+SUMPRODUCT((Inputs!$C$5:$C$230=$B5)*ISNUMBER(INDEX(Inputs!$K$5:$AJ$230,0,MATCH(AA$2,Inputs!$K$4:$AJ$4,0))))+SUMPRODUCT((Inputs!$E$5:$E$230=$B5)*ISNUMBER(INDEX(Inputs!$K$5:$AJ$230,0,MATCH(AA$2,Inputs!$K$4:$AJ$4,0))))=0,NA(),SUMPRODUCT((Inputs!$A$5:$A$230=$B5)*Inputs!$B$5:$B$230*(((Inputs!$G$5:$G$230="moeda")+(Inputs!$G$5:$G$230="acoes"))*Inputs!$B$1+((Inputs!$G$5:$G$230<>"moeda")*(Inputs!$G$5:$G$230<>"acoes")))*INDEX(Inputs!$K$5:$AJ$230,0,MATCH(AA$2,Inputs!$K$4:$AJ$4,0)))+SUMPRODUCT((Inputs!$C$5:$C$230=$B5)*Inputs!$D$5:$D$230*(((Inputs!$G$5:$G$230="moeda")+(Inputs!$G$5:$G$230="acoes"))*Inputs!$B$1+((Inputs!$G$5:$G$230<>"moeda")*(Inputs!$G$5:$G$230<>"acoes")))*INDEX(Inputs!$K$5:$AJ$230,0,MATCH(AA$2,Inputs!$K$4:$AJ$4,0)))+SUMPRODUCT((Inputs!$E$5:$E$230=$B5)*Inputs!$F$5:$F$230*(((Inputs!$G$5:$G$230="moeda")+(Inputs!$G$5:$G$230="acoes"))*Inputs!$B$1+((Inputs!$G$5:$G$230<>"moeda")*(Inputs!$G$5:$G$230<>"acoes")))*INDEX(Inputs!$K$5:$AJ$230,0,MATCH(AA$2,Inputs!$K$4:$AJ$4,0))))) -> -335.941 | AB5: =SUM(X5:AA5) -> -1159.563 | AC5: =IF(ISNA(MATCH(AC$2,Inputs!$K$4:$AJ$4,0)),NA(),IF(SUMPRODUCT((Inputs!$A$5:$A$230=$B5)*ISNUMBER(INDEX(Inputs!$K$5:$AJ$230,0,MATCH(AC$2,Inputs!$K$4:$AJ$4,0))))+SUMPRODUCT((Inputs!$C$5:$C$230=$B5)*ISNUMBER(INDEX(Inputs!$K$5:$AJ$230,0,MATCH(AC$2,Inputs!$K$4:$AJ$4,0))))+SUMPRODUCT((Inputs!$E$5:$E$230=$B5)*ISNUMBER(INDEX(Inputs!$K$5:$AJ$230,0,MATCH(AC$2,Inputs!$K$4:$AJ$4,0))))=0,NA(),SUMPRODUCT((Inputs!$A$5:$A$230=$B5)*Inputs!$B$5:$B$230*(((Inputs!$G$5:$G$230="moeda")+(Inputs!$G$5:$G$230="acoes"))*Inputs!$B$1+((Inputs!$G$5:$G$230<>"moeda")*(Inputs!$G$5:$G$230<>"acoes")))*INDEX(Inputs!$K$5:$AJ$230,0,MATCH(AC$2,Inputs!$K$4:$AJ$4,0)))+SUMPRODUCT((Inputs!$C$5:$C$230=$B5)*Inputs!$D$5:$D$230*(((Inputs!$G$5:$G$230="moeda")+(Inputs!$G$5:$G$230="acoes"))*Inputs!$B$1+((Inputs!$G$5:$G$230<>"moeda")*(Inputs!$G$5:$G$230<>"acoes")))*INDEX(Inputs!$K$5:$AJ$230,0,MATCH(AC$2,Inputs!$K$4:$AJ$4,0)))+SUMPRODUCT((Inputs!$E$5:$E$230=$B5)*Inputs!$F$5:$F$230*(((Inputs!$G$5:$G$230="moeda")+(Inputs!$G$5:$G$230="acoes"))*Inputs!$B$1+((Inputs!$G$5:$G$230<>"moeda")*(Inputs!$G$5:$G$230<>"acoes")))*INDEX(Inputs!$K$5:$AJ$230,0,MATCH(AC$2,Inputs!$K$4:$AJ$4,0))))) -> -409.119 | AD5: =IF(ISNA(MATCH(AD$2,Inputs!$K$4:$AJ$4,0)),NA(),IF(SUMPRODUCT((Inputs!$A$5:$A$230=$B5)*ISNUMBER(INDEX(Inputs!$K$5:$AJ$230,0,MATCH(AD$2,Inputs!$K$4:$AJ$4,0))))+SUMPRODUCT((Inputs!$C$5:$C$230=$B5)*ISNUMBER(INDEX(Inputs!$K$5:$AJ$230,0,MATCH(AD$2,Inputs!$K$4:$AJ$4,0))))+SUMPRODUCT((Inputs!$E$5:$E$230=$B5)*ISNUMBER(INDEX(Inputs!$K$5:$AJ$230,0,MATCH(AD$2,Inputs!$K$4:$AJ$4,0))))=0,NA(),SUMPRODUCT((Inputs!$A$5:$A$230=$B5)*Inputs!$B$5:$B$230*(((Inputs!$G$5:$G$230="moeda")+(Inputs!$G$5:$G$230="acoes"))*Inputs!$B$1+((Inputs!$G$5:$G$230<>"moeda")*(Inputs!$G$5:$G$230<>"acoes")))*INDEX(Inputs!$K$5:$AJ$230,0,MATCH(AD$2,Inputs!$K$4:$AJ$4,0)))+SUMPRODUCT((Inputs!$C$5:$C$230=$B5)*Inputs!$D$5:$D$230*(((Inputs!$G$5:$G$230="moeda")+(Inputs!$G$5:$G$230="acoes"))*Inputs!$B$1+((Inputs!$G$5:$G$230<>"moeda")*(Inputs!$G$5:$G$230<>"acoes")))*INDEX(Inputs!$K$5:$AJ$230,0,MATCH(AD$2,Inputs!$K$4:$AJ$4,0)))+SUMPRODUCT((Inputs!$E$5:$E$230=$B5)*Inputs!$F$5:$F$230*(((Inputs!$G$5:$G$230="moeda")+(Inputs!$G$5:$G$230="acoes"))*Inputs!$B$1+((Inputs!$G$5:$G$230<>"moeda")*(Inputs!$G$5:$G$230<>"acoes")))*INDEX(Inputs!$K$5:$AJ$230,0,MATCH(AD$2,Inputs!$K$4:$AJ$4,0))))) -> -524.176 | AE5: =IF(ISNA(MATCH(AE$2,Inputs!$K$4:$AJ$4,0)),NA(),IF(SUMPRODUCT((Inputs!$A$5:$A$230=$B5)*ISNUMBER(INDEX(Inputs!$K$5:$AJ$230,0,MATCH(AE$2,Inputs!$K$4:$AJ$4,0))))+SUMPRODUCT((Inputs!$C$5:$C$230=$B5)*ISNUMBER(INDEX(Inputs!$K$5:$AJ$230,0,MATCH(AE$2,Inputs!$K$4:$AJ$4,0))))+SUMPRODUCT((Inputs!$E$5:$E$230=$B5)*ISNUMBER(INDEX(Inputs!$K$5:$AJ$230,0,MATCH(AE$2,Inputs!$K$4:$AJ$4,0))))=0,NA(),SUMPRODUCT((Inputs!$A$5:$A$230=$B5)*Inputs!$B$5:$B$230*(((Inputs!$G$5:$G$230="moeda")+(Inputs!$G$5:$G$230="acoes"))*Inputs!$B$1+((Inputs!$G$5:$G$230<>"moeda")*(Inputs!$G$5:$G$230<>"acoes")))*INDEX(Inputs!$K$5:$AJ$230,0,MATCH(AE$2,Inputs!$K$4:$AJ$4,0)))+SUMPRODUCT((Inputs!$C$5:$C$230=$B5)*Inputs!$D$5:$D$230*(((Inputs!$G$5:$G$230="moeda")+(Inputs!$G$5:$G$230="acoes"))*Inputs!$B$1+((Inputs!$G$5:$G$230<>"moeda")*(Inputs!$G$5:$G$230<>"acoes")))*INDEX(Inputs!$K$5:$AJ$230,0,MATCH(AE$2,Inputs!$K$4:$AJ$4,0)))+SUMPRODUCT((Inputs!$E$5:$E$230=$B5)*Inputs!$F$5:$F$230*(((Inputs!$G$5:$G$230="moeda")+(Inputs!$G$5:$G$230="acoes"))*Inputs!$B$1+((Inputs!$G$5:$G$230<>"moeda")*(Inputs!$G$5:$G$230<>"acoes")))*INDEX(Inputs!$K$5:$AJ$230,0,MATCH(AE$2,Inputs!$K$4:$AJ$4,0))))) -> #N/A | AF5: =IF(ISNA(MATCH(AF$2,Inputs!$K$4:$AJ$4,0)),NA(),IF(SUMPRODUCT((Inputs!$A$5:$A$230=$B5)*ISNUMBER(INDEX(Inputs!$K$5:$AJ$230,0,MATCH(AF$2,Inputs!$K$4:$AJ$4,0))))+SUMPRODUCT((Inputs!$C$5:$C$230=$B5)*ISNUMBER(INDEX(Inputs!$K$5:$AJ$230,0,MATCH(AF$2,Inputs!$K$4:$AJ$4,0))))+SUMPRODUCT((Inputs!$E$5:$E$230=$B5)*ISNUMBER(INDEX(Inputs!$K$5:$AJ$230,0,MATCH(AF$2,Inputs!$K$4:$AJ$4,0))))=0,NA(),SUMPRODUCT((Inputs!$A$5:$A$230=$B5)*Inputs!$B$5:$B$230*(((Inputs!$G$5:$G$230="moeda")+(Inputs!$G$5:$G$230="acoes"))*Inputs!$B$1+((Inputs!$G$5:$G$230<>"moeda")*(Inputs!$G$5:$G$230<>"acoes")))*INDEX(Inputs!$K$5:$AJ$230,0,MATCH(AF$2,Inputs!$K$4:$AJ$4,0)))+SUMPRODUCT((Inputs!$C$5:$C$230=$B5)*Inputs!$D$5:$D$230*(((Inputs!$G$5:$G$230="moeda")+(Inputs!$G$5:$G$230="acoes"))*Inputs!$B$1+((Inputs!$G$5:$G$230<>"moeda")*(Inputs!$G$5:$G$230<>"acoes")))*INDEX(Inputs!$K$5:$AJ$230,0,MATCH(AF$2,Inputs!$K$4:$AJ$4,0)))+SUMPRODUCT((Inputs!$E$5:$E$230=$B5)*Inputs!$F$5:$F$230*(((Inputs!$G$5:$G$230="moeda")+(Inputs!$G$5:$G$230="acoes"))*Inputs!$B$1+((Inputs!$G$5:$G$230<>"moeda")*(Inputs!$G$5:$G$230<>"acoes")))*INDEX(Inputs!$K$5:$AJ$230,0,MATCH(AF$2,Inputs!$K$4:$AJ$4,0))))) -> #N/A | AG5: =SUM(AC5:AF5) -> #N/A | AH5: =IF(ISNA(MATCH(AH$2,Inputs!$K$4:$AJ$4,0)),NA(),IF(SUMPRODUCT((Inputs!$A$5:$A$230=$B5)*ISNUMBER(INDEX(Inputs!$K$5:$AJ$230,0,MATCH(AH$2,Inputs!$K$4:$AJ$4,0))))+SUMPRODUCT((Inputs!$C$5:$C$230=$B5)*ISNUMBER(INDEX(Inputs!$K$5:$AJ$230,0,MATCH(AH$2,Inputs!$K$4:$AJ$4,0))))+SUMPRODUCT((Inputs!$E$5:$E$230=$B5)*ISNUMBER(INDEX(Inputs!$K$5:$AJ$230,0,MATCH(AH$2,Inputs!$K$4:$AJ$4,0))))=0,NA(),SUMPRODUCT((Inputs!$A$5:$A$230=$B5)*Inputs!$B$5:$B$230*(((Inputs!$G$5:$G$230="moeda")+(Inputs!$G$5:$G$230="acoes"))*Inputs!$B$1+((Inputs!$G$5:$G$230<>"moeda")*(Inputs!$G$5:$G$230<>"acoes")))*INDEX(Inputs!$K$5:$AJ$230,0,MATCH(AH$2,Inputs!$K$4:$AJ$4,0)))+SUMPRODUCT((Inputs!$C$5:$C$230=$B5)*Inputs!$D$5:$D$230*(((Inputs!$G$5:$G$230="moeda")+(Inputs!$G$5:$G$230="acoes"))*Inputs!$B$1+((Inputs!$G$5:$G$230<>"moeda")*(Inputs!$G$5:$G$230<>"acoes")))*INDEX(Inputs!$K$5:$AJ$230,0,MATCH(AH$2,Inputs!$K$4:$AJ$4,0)))+SUMPRODUCT((Inputs!$E$5:$E$230=$B5)*Inputs!$F$5:$F$230*(((Inputs!$G$5:$G$230="moeda")+(Inputs!$G$5:$G$230="acoes"))*Inputs!$B$1+((Inputs!$G$5:$G$230<>"moeda")*(Inputs!$G$5:$G$230<>"acoes")))*INDEX(Inputs!$K$5:$AJ$230,0,MATCH(AH$2,Inputs!$K$4:$AJ$4,0))))) -> -577.646 | AI5: =IF(ISNA(MATCH(AI$2,Inputs!$K$4:$AJ$4,0)),NA(),IF(SUMPRODUCT((Inputs!$A$5:$A$230=$B5)*ISNUMBER(INDEX(Inputs!$K$5:$AJ$230,0,MATCH(AI$2,Inputs!$K$4:$AJ$4,0))))+SUMPRODUCT((Inputs!$C$5:$C$230=$B5)*ISNUMBER(INDEX(Inputs!$K$5:$AJ$230,0,MATCH(AI$2,Inputs!$K$4:$AJ$4,0))))+SUMPRODUCT((Inputs!$E$5:$E$230=$B5)*ISNUMBER(INDEX(Inputs!$K$5:$AJ$230,0,MATCH(AI$2,Inputs!$K$4:$AJ$4,0))))=0,NA(),SUMPRODUCT((Inputs!$A$5:$A$230=$B5)*Inputs!$B$5:$B$230*(((Inputs!$G$5:$G$230="moeda")+(Inputs!$G$5:$G$230="acoes"))*Inputs!$B$1+((Inputs!$G$5:$G$230<>"moeda")*(Inputs!$G$5:$G$230<>"acoes")))*INDEX(Inputs!$K$5:$AJ$230,0,MATCH(AI$2,Inputs!$K$4:$AJ$4,0)))+SUMPRODUCT((Inputs!$C$5:$C$230=$B5)*Inputs!$D$5:$D$230*(((Inputs!$G$5:$G$230="moeda")+(Inputs!$G$5:$G$230="acoes"))*Inputs!$B$1+((Inputs!$G$5:$G$230<>"moeda")*(Inputs!$G$5:$G$230<>"acoes")))*INDEX(Inputs!$K$5:$AJ$230,0,MATCH(AI$2,Inputs!$K$4:$AJ$4,0)))+SUMPRODUCT((Inputs!$E$5:$E$230=$B5)*Inputs!$F$5:$F$230*(((Inputs!$G$5:$G$230="moeda")+(Inputs!$G$5:$G$230="acoes"))*Inputs!$B$1+((Inputs!$G$5:$G$230<>"moeda")*(Inputs!$G$5:$G$230<>"acoes")))*INDEX(Inputs!$K$5:$AJ$230,0,MATCH(AI$2,Inputs!$K$4:$AJ$4,0))))) -> -576.22 | AJ5: =IF(ISNA(MATCH(AJ$2,Inputs!$K$4:$AJ$4,0)),NA(),IF(SUMPRODUCT((Inputs!$A$5:$A$230=$B5)*ISNUMBER(INDEX(Inputs!$K$5:$AJ$230,0,MATCH(AJ$2,Inputs!$K$4:$AJ$4,0))))+SUMPRODUCT((Inputs!$C$5:$C$230=$B5)*ISNUMBER(INDEX(Inputs!$K$5:$AJ$230,0,MATCH(AJ$2,Inputs!$K$4:$AJ$4,0))))+SUMPRODUCT((Inputs!$E$5:$E$230=$B5)*ISNUMBER(INDEX(Inputs!$K$5:$AJ$230,0,MATCH(AJ$2,Inputs!$K$4:$AJ$4,0))))=0,NA(),SUMPRODUCT((Inputs!$A$5:$A$230=$B5)*Inputs!$B$5:$B$230*(((Inputs!$G$5:$G$230="moeda")+(Inputs!$G$5:$G$230="acoes"))*Inputs!$B$1+((Inputs!$G$5:$G$230<>"moeda")*(Inputs!$G$5:$G$230<>"acoes")))*INDEX(Inputs!$K$5:$AJ$230,0,MATCH(AJ$2,Inputs!$K$4:$AJ$4,0)))+SUMPRODUCT((Inputs!$C$5:$C$230=$B5)*Inputs!$D$5:$D$230*(((Inputs!$G$5:$G$230="moeda")+(Inputs!$G$5:$G$230="acoes"))*Inputs!$B$1+((Inputs!$G$5:$G$230<>"moeda")*(Inputs!$G$5:$G$230<>"acoes")))*INDEX(Inputs!$K$5:$AJ$230,0,MATCH(AJ$2,Inputs!$K$4:$AJ$4,0)))+SUMPRODUCT((Inputs!$E$5:$E$230=$B5)*Inputs!$F$5:$F$230*(((Inputs!$G$5:$G$230="moeda")+(Inputs!$G$5:$G$230="acoes"))*Inputs!$B$1+((Inputs!$G$5:$G$230<>"moeda")*(Inputs!$G$5:$G$230<>"acoes")))*INDEX(Inputs!$K$5:$AJ$230,0,MATCH(AJ$2,Inputs!$K$4:$AJ$4,0))))) -> -742.279 | AK5: =IF(ISNA(MATCH(AK$2,Inputs!$K$4:$AJ$4,0)),NA(),IF(SUMPRODUCT((Inputs!$A$5:$A$230=$B5)*ISNUMBER(INDEX(Inputs!$K$5:$AJ$230,0,MATCH(AK$2,Inputs!$K$4:$AJ$4,0))))+SUMPRODUCT((Inputs!$C$5:$C$230=$B5)*ISNUMBER(INDEX(Inputs!$K$5:$AJ$230,0,MATCH(AK$2,Inputs!$K$4:$AJ$4,0))))+SUMPRODUCT((Inputs!$E$5:$E$230=$B5)*ISNUMBER(INDEX(Inputs!$K$5:$AJ$230,0,MATCH(AK$2,Inputs!$K$4:$AJ$4,0))))=0,NA(),SUMPRODUCT((Inputs!$A$5:$A$230=$B5)*Inputs!$B$5:$B$230*(((Inputs!$G$5:$G$230="moeda")+(Inputs!$G$5:$G$230="acoes"))*Inputs!$B$1+((Inputs!$G$5:$G$230<>"moeda")*(Inputs!$G$5:$G$230<>"acoes")))*INDEX(Inputs!$K$5:$AJ$230,0,MATCH(AK$2,Inputs!$K$4:$AJ$4,0)))+SUMPRODUCT((Inputs!$C$5:$C$230=$B5)*Inputs!$D$5:$D$230*(((Inputs!$G$5:$G$230="moeda")+(Inputs!$G$5:$G$230="acoes"))*Inputs!$B$1+((Inputs!$G$5:$G$230<>"moeda")*(Inputs!$G$5:$G$230<>"acoes")))*INDEX(Inputs!$K$5:$AJ$230,0,MATCH(AK$2,Inputs!$K$4:$AJ$4,0)))+SUMPRODUCT((Inputs!$E$5:$E$230=$B5)*Inputs!$F$5:$F$230*(((Inputs!$G$5:$G$230="moeda")+(Inputs!$G$5:$G$230="acoes"))*Inputs!$B$1+((Inputs!$G$5:$G$230<>"moeda")*(Inputs!$G$5:$G$230<>"acoes")))*INDEX(Inputs!$K$5:$AJ$230,0,MATCH(AK$2,Inputs!$K$4:$AJ$4,0))))) -> -675.582 | AL5: =SUM(AH5:AK5) -> -2571.727
B6: 3 | C6: SG&A and Other (cash) | D6: =IF(ISNA(MATCH(D$2,Inputs!$K$4:$AJ$4,0)),NA(),IF(SUMPRODUCT((Inputs!$A$5:$A$230=$B6)*ISNUMBER(INDEX(Inputs!$K$5:$AJ$230,0,MATCH(D$2,Inputs!$K$4:$AJ$4,0))))+SUMPRODUCT((Inputs!$C$5:$C$230=$B6)*ISNUMBER(INDEX(Inputs!$K$5:$AJ$230,0,MATCH(D$2,Inputs!$K$4:$AJ$4,0))))+SUMPRODUCT((Inputs!$E$5:$E$230=$B6)*ISNUMBER(INDEX(Inputs!$K$5:$AJ$230,0,MATCH(D$2,Inputs!$K$4:$AJ$4,0))))=0,NA(),SUMPRODUCT((Inputs!$A$5:$A$230=$B6)*Inputs!$B$5:$B$230*(((Inputs!$G$5:$G$230="moeda")+(Inputs!$G$5:$G$230="acoes"))*Inputs!$B$1+((Inputs!$G$5:$G$230<>"moeda")*(Inputs!$G$5:$G$230<>"acoes")))*INDEX(Inputs!$K$5:$AJ$230,0,MATCH(D$2,Inputs!$K$4:$AJ$4,0)))+SUMPRODUCT((Inputs!$C$5:$C$230=$B6)*Inputs!$D$5:$D$230*(((Inputs!$G$5:$G$230="moeda")+(Inputs!$G$5:$G$230="acoes"))*Inputs!$B$1+((Inputs!$G$5:$G$230<>"moeda")*(Inputs!$G$5:$G$230<>"acoes")))*INDEX(Inputs!$K$5:$AJ$230,0,MATCH(D$2,Inputs!$K$4:$AJ$4,0)))+SUMPRODUCT((Inputs!$E$5:$E$230=$B6)*Inputs!$F$5:$F$230*(((Inputs!$G$5:$G$230="moeda")+(Inputs!$G$5:$G$230="acoes"))*Inputs!$B$1+((Inputs!$G$5:$G$230<>"moeda")*(Inputs!$G$5:$G$230<>"acoes")))*INDEX(Inputs!$K$5:$AJ$230,0,MATCH(D$2,Inputs!$K$4:$AJ$4,0))))) -> -23.786 | E6: =IF(ISNA(MATCH(E$2,Inputs!$K$4:$AJ$4,0)),NA(),IF(SUMPRODUCT((Inputs!$A$5:$A$230=$B6)*ISNUMBER(INDEX(Inputs!$K$5:$AJ$230,0,MATCH(E$2,Inputs!$K$4:$AJ$4,0))))+SUMPRODUCT((Inputs!$C$5:$C$230=$B6)*ISNUMBER(INDEX(Inputs!$K$5:$AJ$230,0,MATCH(E$2,Inputs!$K$4:$AJ$4,0))))+SUMPRODUCT((Inputs!$E$5:$E$230=$B6)*ISNUMBER(INDEX(Inputs!$K$5:$AJ$230,0,MATCH(E$2,Inputs!$K$4:$AJ$4,0))))=0,NA(),SUMPRODUCT((Inputs!$A$5:$A$230=$B6)*Inputs!$B$5:$B$230*(((Inputs!$G$5:$G$230="moeda")+(Inputs!$G$5:$G$230="acoes"))*Inputs!$B$1+((Inputs!$G$5:$G$230<>"moeda")*(Inputs!$G$5:$G$230<>"acoes")))*INDEX(Inputs!$K$5:$AJ$230,0,MATCH(E$2,Inputs!$K$4:$AJ$4,0)))+SUMPRODUCT((Inputs!$C$5:$C$230=$B6)*Inputs!$D$5:$D$230*(((Inputs!$G$5:$G$230="moeda")+(Inputs!$G$5:$G$230="acoes"))*Inputs!$B$1+((Inputs!$G$5:$G$230<>"moeda")*(Inputs!$G$5:$G$230<>"acoes")))*INDEX(Inputs!$K$5:$AJ$230,0,MATCH(E$2,Inputs!$K$4:$AJ$4,0)))+SUMPRODUCT((Inputs!$E$5:$E$230=$B6)*Inputs!$F$5:$F$230*(((Inputs!$G$5:$G$230="moeda")+(Inputs!$G$5:$G$230="acoes"))*Inputs!$B$1+((Inputs!$G$5:$G$230<>"moeda")*(Inputs!$G$5:$G$230<>"acoes")))*INDEX(Inputs!$K$5:$AJ$230,0,MATCH(E$2,Inputs!$K$4:$AJ$4,0))))) -> -8.006 | F6: =IF(ISNA(MATCH(F$2,Inputs!$K$4:$AJ$4,0)),NA(),IF(SUMPRODUCT((Inputs!$A$5:$A$230=$B6)*ISNUMBER(INDEX(Inputs!$K$5:$AJ$230,0,MATCH(F$2,Inputs!$K$4:$AJ$4,0))))+SUMPRODUCT((Inputs!$C$5:$C$230=$B6)*ISNUMBER(INDEX(Inputs!$K$5:$AJ$230,0,MATCH(F$2,Inputs!$K$4:$AJ$4,0))))+SUMPRODUCT((Inputs!$E$5:$E$230=$B6)*ISNUMBER(INDEX(Inputs!$K$5:$AJ$230,0,MATCH(F$2,Inputs!$K$4:$AJ$4,0))))=0,NA(),SUMPRODUCT((Inputs!$A$5:$A$230=$B6)*Inputs!$B$5:$B$230*(((Inputs!$G$5:$G$230="moeda")+(Inputs!$G$5:$G$230="acoes"))*Inputs!$B$1+((Inputs!$G$5:$G$230<>"moeda")*(Inputs!$G$5:$G$230<>"acoes")))*INDEX(Inputs!$K$5:$AJ$230,0,MATCH(F$2,Inputs!$K$4:$AJ$4,0)))+SUMPRODUCT((Inputs!$C$5:$C$230=$B6)*Inputs!$D$5:$D$230*(((Inputs!$G$5:$G$230="moeda")+(Inputs!$G$5:$G$230="acoes"))*Inputs!$B$1+((Inputs!$G$5:$G$230<>"moeda")*(Inputs!$G$5:$G$230<>"acoes")))*INDEX(Inputs!$K$5:$AJ$230,0,MATCH(F$2,Inputs!$K$4:$AJ$4,0)))+SUMPRODUCT((Inputs!$E$5:$E$230=$B6)*Inputs!$F$5:$F$230*(((Inputs!$G$5:$G$230="moeda")+(Inputs!$G$5:$G$230="acoes"))*Inputs!$B$1+((Inputs!$G$5:$G$230<>"moeda")*(Inputs!$G$5:$G$230<>"acoes")))*INDEX(Inputs!$K$5:$AJ$230,0,MATCH(F$2,Inputs!$K$4:$AJ$4,0))))) -> 21.031 | G6: =IF(ISNA(MATCH(G$2,Inputs!$K$4:$AJ$4,0)),NA(),IF(SUMPRODUCT((Inputs!$A$5:$A$230=$B6)*ISNUMBER(INDEX(Inputs!$K$5:$AJ$230,0,MATCH(G$2,Inputs!$K$4:$AJ$4,0))))+SUMPRODUCT((Inputs!$C$5:$C$230=$B6)*ISNUMBER(INDEX(Inputs!$K$5:$AJ$230,0,MATCH(G$2,Inputs!$K$4:$AJ$4,0))))+SUMPRODUCT((Inputs!$E$5:$E$230=$B6)*ISNUMBER(INDEX(Inputs!$K$5:$AJ$230,0,MATCH(G$2,Inputs!$K$4:$AJ$4,0))))=0,NA(),SUMPRODUCT((Inputs!$A$5:$A$230=$B6)*Inputs!$B$5:$B$230*(((Inputs!$G$5:$G$230="moeda")+(Inputs!$G$5:$G$230="acoes"))*Inputs!$B$1+((Inputs!$G$5:$G$230<>"moeda")*(Inputs!$G$5:$G$230<>"acoes")))*INDEX(Inputs!$K$5:$AJ$230,0,MATCH(G$2,Inputs!$K$4:$AJ$4,0)))+SUMPRODUCT((Inputs!$C$5:$C$230=$B6)*Inputs!$D$5:$D$230*(((Inputs!$G$5:$G$230="moeda")+(Inputs!$G$5:$G$230="acoes"))*Inputs!$B$1+((Inputs!$G$5:$G$230<>"moeda")*(Inputs!$G$5:$G$230<>"acoes")))*INDEX(Inputs!$K$5:$AJ$230,0,MATCH(G$2,Inputs!$K$4:$AJ$4,0)))+SUMPRODUCT((Inputs!$E$5:$E$230=$B6)*Inputs!$F$5:$F$230*(((Inputs!$G$5:$G$230="moeda")+(Inputs!$G$5:$G$230="acoes"))*Inputs!$B$1+((Inputs!$G$5:$G$230<>"moeda")*(Inputs!$G$5:$G$230<>"acoes")))*INDEX(Inputs!$K$5:$AJ$230,0,MATCH(G$2,Inputs!$K$4:$AJ$4,0))))) -> -43.997 | H6: =SUM(D6:G6) -> -54.758 | I6: =IF(ISNA(MATCH(I$2,Inputs!$K$4:$AJ$4,0)),NA(),IF(SUMPRODUCT((Inputs!$A$5:$A$230=$B6)*ISNUMBER(INDEX(Inputs!$K$5:$AJ$230,0,MATCH(I$2,Inputs!$K$4:$AJ$4,0))))+SUMPRODUCT((Inputs!$C$5:$C$230=$B6)*ISNUMBER(INDEX(Inputs!$K$5:$AJ$230,0,MATCH(I$2,Inputs!$K$4:$AJ$4,0))))+SUMPRODUCT((Inputs!$E$5:$E$230=$B6)*ISNUMBER(INDEX(Inputs!$K$5:$AJ$230,0,MATCH(I$2,Inputs!$K$4:$AJ$4,0))))=0,NA(),SUMPRODUCT((Inputs!$A$5:$A$230=$B6)*Inputs!$B$5:$B$230*(((Inputs!$G$5:$G$230="moeda")+(Inputs!$G$5:$G$230="acoes"))*Inputs!$B$1+((Inputs!$G$5:$G$230<>"moeda")*(Inputs!$G$5:$G$230<>"acoes")))*INDEX(Inputs!$K$5:$AJ$230,0,MATCH(I$2,Inputs!$K$4:$AJ$4,0)))+SUMPRODUCT((Inputs!$C$5:$C$230=$B6)*Inputs!$D$5:$D$230*(((Inputs!$G$5:$G$230="moeda")+(Inputs!$G$5:$G$230="acoes"))*Inputs!$B$1+((Inputs!$G$5:$G$230<>"moeda")*(Inputs!$G$5:$G$230<>"acoes")))*INDEX(Inputs!$K$5:$AJ$230,0,MATCH(I$2,Inputs!$K$4:$AJ$4,0)))+SUMPRODUCT((Inputs!$E$5:$E$230=$B6)*Inputs!$F$5:$F$230*(((Inputs!$G$5:$G$230="moeda")+(Inputs!$G$5:$G$230="acoes"))*Inputs!$B$1+((Inputs!$G$5:$G$230<>"moeda")*(Inputs!$G$5:$G$230<>"acoes")))*INDEX(Inputs!$K$5:$AJ$230,0,MATCH(I$2,Inputs!$K$4:$AJ$4,0))))) -> -14.074 | J6: =IF(ISNA(MATCH(J$2,Inputs!$K$4:$AJ$4,0)),NA(),IF(SUMPRODUCT((Inputs!$A$5:$A$230=$B6)*ISNUMBER(INDEX(Inputs!$K$5:$AJ$230,0,MATCH(J$2,Inputs!$K$4:$AJ$4,0))))+SUMPRODUCT((Inputs!$C$5:$C$230=$B6)*ISNUMBER(INDEX(Inputs!$K$5:$AJ$230,0,MATCH(J$2,Inputs!$K$4:$AJ$4,0))))+SUMPRODUCT((Inputs!$E$5:$E$230=$B6)*ISNUMBER(INDEX(Inputs!$K$5:$AJ$230,0,MATCH(J$2,Inputs!$K$4:$AJ$4,0))))=0,NA(),SUMPRODUCT((Inputs!$A$5:$A$230=$B6)*Inputs!$B$5:$B$230*(((Inputs!$G$5:$G$230="moeda")+(Inputs!$G$5:$G$230="acoes"))*Inputs!$B$1+((Inputs!$G$5:$G$230<>"moeda")*(Inputs!$G$5:$G$230<>"acoes")))*INDEX(Inputs!$K$5:$AJ$230,0,MATCH(J$2,Inputs!$K$4:$AJ$4,0)))+SUMPRODUCT((Inputs!$C$5:$C$230=$B6)*Inputs!$D$5:$D$230*(((Inputs!$G$5:$G$230="moeda")+(Inputs!$G$5:$G$230="acoes"))*Inputs!$B$1+((Inputs!$G$5:$G$230<>"moeda")*(Inputs!$G$5:$G$230<>"acoes")))*INDEX(Inputs!$K$5:$AJ$230,0,MATCH(J$2,Inputs!$K$4:$AJ$4,0)))+SUMPRODUCT((Inputs!$E$5:$E$230=$B6)*Inputs!$F$5:$F$230*(((Inputs!$G$5:$G$230="moeda")+(Inputs!$G$5:$G$230="acoes"))*Inputs!$B$1+((Inputs!$G$5:$G$230<>"moeda")*(Inputs!$G$5:$G$230<>"acoes")))*INDEX(Inputs!$K$5:$AJ$230,0,MATCH(J$2,Inputs!$K$4:$AJ$4,0))))) -> -174.015 | K6: =IF(ISNA(MATCH(K$2,Inputs!$K$4:$AJ$4,0)),NA(),IF(SUMPRODUCT((Inputs!$A$5:$A$230=$B6)*ISNUMBER(INDEX(Inputs!$K$5:$AJ$230,0,MATCH(K$2,Inputs!$K$4:$AJ$4,0))))+SUMPRODUCT((Inputs!$C$5:$C$230=$B6)*ISNUMBER(INDEX(Inputs!$K$5:$AJ$230,0,MATCH(K$2,Inputs!$K$4:$AJ$4,0))))+SUMPRODUCT((Inputs!$E$5:$E$230=$B6)*ISNUMBER(INDEX(Inputs!$K$5:$AJ$230,0,MATCH(K$2,Inputs!$K$4:$AJ$4,0))))=0,NA(),SUMPRODUCT((Inputs!$A$5:$A$230=$B6)*Inputs!$B$5:$B$230*(((Inputs!$G$5:$G$230="moeda")+(Inputs!$G$5:$G$230="acoes"))*Inputs!$B$1+((Inputs!$G$5:$G$230<>"moeda")*(Inputs!$G$5:$G$230<>"acoes")))*INDEX(Inputs!$K$5:$AJ$230,0,MATCH(K$2,Inputs!$K$4:$AJ$4,0)))+SUMPRODUCT((Inputs!$C$5:$C$230=$B6)*Inputs!$D$5:$D$230*(((Inputs!$G$5:$G$230="moeda")+(Inputs!$G$5:$G$230="acoes"))*Inputs!$B$1+((Inputs!$G$5:$G$230<>"moeda")*(Inputs!$G$5:$G$230<>"acoes")))*INDEX(Inputs!$K$5:$AJ$230,0,MATCH(K$2,Inputs!$K$4:$AJ$4,0)))+SUMPRODUCT((Inputs!$E$5:$E$230=$B6)*Inputs!$F$5:$F$230*(((Inputs!$G$5:$G$230="moeda")+(Inputs!$G$5:$G$230="acoes"))*Inputs!$B$1+((Inputs!$G$5:$G$230<>"moeda")*(Inputs!$G$5:$G$230<>"acoes")))*INDEX(Inputs!$K$5:$AJ$230,0,MATCH(K$2,Inputs!$K$4:$AJ$4,0))))) -> -36.025 | L6: =IF(ISNA(MATCH(L$2,Inputs!$K$4:$AJ$4,0)),NA(),IF(SUMPRODUCT((Inputs!$A$5:$A$230=$B6)*ISNUMBER(INDEX(Inputs!$K$5:$AJ$230,0,MATCH(L$2,Inputs!$K$4:$AJ$4,0))))+SUMPRODUCT((Inputs!$C$5:$C$230=$B6)*ISNUMBER(INDEX(Inputs!$K$5:$AJ$230,0,MATCH(L$2,Inputs!$K$4:$AJ$4,0))))+SUMPRODUCT((Inputs!$E$5:$E$230=$B6)*ISNUMBER(INDEX(Inputs!$K$5:$AJ$230,0,MATCH(L$2,Inputs!$K$4:$AJ$4,0))))=0,NA(),SUMPRODUCT((Inputs!$A$5:$A$230=$B6)*Inputs!$B$5:$B$230*(((Inputs!$G$5:$G$230="moeda")+(Inputs!$G$5:$G$230="acoes"))*Inputs!$B$1+((Inputs!$G$5:$G$230<>"moeda")*(Inputs!$G$5:$G$230<>"acoes")))*INDEX(Inputs!$K$5:$AJ$230,0,MATCH(L$2,Inputs!$K$4:$AJ$4,0)))+SUMPRODUCT((Inputs!$C$5:$C$230=$B6)*Inputs!$D$5:$D$230*(((Inputs!$G$5:$G$230="moeda")+(Inputs!$G$5:$G$230="acoes"))*Inputs!$B$1+((Inputs!$G$5:$G$230<>"moeda")*(Inputs!$G$5:$G$230<>"acoes")))*INDEX(Inputs!$K$5:$AJ$230,0,MATCH(L$2,Inputs!$K$4:$AJ$4,0)))+SUMPRODUCT((Inputs!$E$5:$E$230=$B6)*Inputs!$F$5:$F$230*(((Inputs!$G$5:$G$230="moeda")+(Inputs!$G$5:$G$230="acoes"))*Inputs!$B$1+((Inputs!$G$5:$G$230<>"moeda")*(Inputs!$G$5:$G$230<>"acoes")))*INDEX(Inputs!$K$5:$AJ$230,0,MATCH(L$2,Inputs!$K$4:$AJ$4,0))))) -> -49.11 | M6: =SUM(I6:L6) -> -273.224 | N6: =IF(ISNA(MATCH(N$2,Inputs!$K$4:$AJ$4,0)),NA(),IF(SUMPRODUCT((Inputs!$A$5:$A$230=$B6)*ISNUMBER(INDEX(Inputs!$K$5:$AJ$230,0,MATCH(N$2,Inputs!$K$4:$AJ$4,0))))+SUMPRODUCT((Inputs!$C$5:$C$230=$B6)*ISNUMBER(INDEX(Inputs!$K$5:$AJ$230,0,MATCH(N$2,Inputs!$K$4:$AJ$4,0))))+SUMPRODUCT((Inputs!$E$5:$E$230=$B6)*ISNUMBER(INDEX(Inputs!$K$5:$AJ$230,0,MATCH(N$2,Inputs!$K$4:$AJ$4,0))))=0,NA(),SUMPRODUCT((Inputs!$A$5:$A$230=$B6)*Inputs!$B$5:$B$230*(((Inputs!$G$5:$G$230="moeda")+(Inputs!$G$5:$G$230="acoes"))*Inputs!$B$1+((Inputs!$G$5:$G$230<>"moeda")*(Inputs!$G$5:$G$230<>"acoes")))*INDEX(Inputs!$K$5:$AJ$230,0,MATCH(N$2,Inputs!$K$4:$AJ$4,0)))+SUMPRODUCT((Inputs!$C$5:$C$230=$B6)*Inputs!$D$5:$D$230*(((Inputs!$G$5:$G$230="moeda")+(Inputs!$G$5:$G$230="acoes"))*Inputs!$B$1+((Inputs!$G$5:$G$230<>"moeda")*(Inputs!$G$5:$G$230<>"acoes")))*INDEX(Inputs!$K$5:$AJ$230,0,MATCH(N$2,Inputs!$K$4:$AJ$4,0)))+SUMPRODUCT((Inputs!$E$5:$E$230=$B6)*Inputs!$F$5:$F$230*(((Inputs!$G$5:$G$230="moeda")+(Inputs!$G$5:$G$230="acoes"))*Inputs!$B$1+((Inputs!$G$5:$G$230<>"moeda")*(Inputs!$G$5:$G$230<>"acoes")))*INDEX(Inputs!$K$5:$AJ$230,0,MATCH(N$2,Inputs!$K$4:$AJ$4,0))))) -> -31.578 | O6: =IF(ISNA(MATCH(O$2,Inputs!$K$4:$AJ$4,0)),NA(),IF(SUMPRODUCT((Inputs!$A$5:$A$230=$B6)*ISNUMBER(INDEX(Inputs!$K$5:$AJ$230,0,MATCH(O$2,Inputs!$K$4:$AJ$4,0))))+SUMPRODUCT((Inputs!$C$5:$C$230=$B6)*ISNUMBER(INDEX(Inputs!$K$5:$AJ$230,0,MATCH(O$2,Inputs!$K$4:$AJ$4,0))))+SUMPRODUCT((Inputs!$E$5:$E$230=$B6)*ISNUMBER(INDEX(Inputs!$K$5:$AJ$230,0,MATCH(O$2,Inputs!$K$4:$AJ$4,0))))=0,NA(),SUMPRODUCT((Inputs!$A$5:$A$230=$B6)*Inputs!$B$5:$B$230*(((Inputs!$G$5:$G$230="moeda")+(Inputs!$G$5:$G$230="acoes"))*Inputs!$B$1+((Inputs!$G$5:$G$230<>"moeda")*(Inputs!$G$5:$G$230<>"acoes")))*INDEX(Inputs!$K$5:$AJ$230,0,MATCH(O$2,Inputs!$K$4:$AJ$4,0)))+SUMPRODUCT((Inputs!$C$5:$C$230=$B6)*Inputs!$D$5:$D$230*(((Inputs!$G$5:$G$230="moeda")+(Inputs!$G$5:$G$230="acoes"))*Inputs!$B$1+((Inputs!$G$5:$G$230<>"moeda")*(Inputs!$G$5:$G$230<>"acoes")))*INDEX(Inputs!$K$5:$AJ$230,0,MATCH(O$2,Inputs!$K$4:$AJ$4,0)))+SUMPRODUCT((Inputs!$E$5:$E$230=$B6)*Inputs!$F$5:$F$230*(((Inputs!$G$5:$G$230="moeda")+(Inputs!$G$5:$G$230="acoes"))*Inputs!$B$1+((Inputs!$G$5:$G$230<>"moeda")*(Inputs!$G$5:$G$230<>"acoes")))*INDEX(Inputs!$K$5:$AJ$230,0,MATCH(O$2,Inputs!$K$4:$AJ$4,0))))) -> -27.46 | P6: =IF(ISNA(MATCH(P$2,Inputs!$K$4:$AJ$4,0)),NA(),IF(SUMPRODUCT((Inputs!$A$5:$A$230=$B6)*ISNUMBER(INDEX(Inputs!$K$5:$AJ$230,0,MATCH(P$2,Inputs!$K$4:$AJ$4,0))))+SUMPRODUCT((Inputs!$C$5:$C$230=$B6)*ISNUMBER(INDEX(Inputs!$K$5:$AJ$230,0,MATCH(P$2,Inputs!$K$4:$AJ$4,0))))+SUMPRODUCT((Inputs!$E$5:$E$230=$B6)*ISNUMBER(INDEX(Inputs!$K$5:$AJ$230,0,MATCH(P$2,Inputs!$K$4:$AJ$4,0))))=0,NA(),SUMPRODUCT((Inputs!$A$5:$A$230=$B6)*Inputs!$B$5:$B$230*(((Inputs!$G$5:$G$230="moeda")+(Inputs!$G$5:$G$230="acoes"))*Inputs!$B$1+((Inputs!$G$5:$G$230<>"moeda")*(Inputs!$G$5:$G$230<>"acoes")))*INDEX(Inputs!$K$5:$AJ$230,0,MATCH(P$2,Inputs!$K$4:$AJ$4,0)))+SUMPRODUCT((Inputs!$C$5:$C$230=$B6)*Inputs!$D$5:$D$230*(((Inputs!$G$5:$G$230="moeda")+(Inputs!$G$5:$G$230="acoes"))*Inputs!$B$1+((Inputs!$G$5:$G$230<>"moeda")*(Inputs!$G$5:$G$230<>"acoes")))*INDEX(Inputs!$K$5:$AJ$230,0,MATCH(P$2,Inputs!$K$4:$AJ$4,0)))+SUMPRODUCT((Inputs!$E$5:$E$230=$B6)*Inputs!$F$5:$F$230*(((Inputs!$G$5:$G$230="moeda")+(Inputs!$G$5:$G$230="acoes"))*Inputs!$B$1+((Inputs!$G$5:$G$230<>"moeda")*(Inputs!$G$5:$G$230<>"acoes")))*INDEX(Inputs!$K$5:$AJ$230,0,MATCH(P$2,Inputs!$K$4:$AJ$4,0))))) -> -38.389 | Q6: =IF(ISNA(MATCH(Q$2,Inputs!$K$4:$AJ$4,0)),NA(),IF(SUMPRODUCT((Inputs!$A$5:$A$230=$B6)*ISNUMBER(INDEX(Inputs!$K$5:$AJ$230,0,MATCH(Q$2,Inputs!$K$4:$AJ$4,0))))+SUMPRODUCT((Inputs!$C$5:$C$230=$B6)*ISNUMBER(INDEX(Inputs!$K$5:$AJ$230,0,MATCH(Q$2,Inputs!$K$4:$AJ$4,0))))+SUMPRODUCT((Inputs!$E$5:$E$230=$B6)*ISNUMBER(INDEX(Inputs!$K$5:$AJ$230,0,MATCH(Q$2,Inputs!$K$4:$AJ$4,0))))=0,NA(),SUMPRODUCT((Inputs!$A$5:$A$230=$B6)*Inputs!$B$5:$B$230*(((Inputs!$G$5:$G$230="moeda")+(Inputs!$G$5:$G$230="acoes"))*Inputs!$B$1+((Inputs!$G$5:$G$230<>"moeda")*(Inputs!$G$5:$G$230<>"acoes")))*INDEX(Inputs!$K$5:$AJ$230,0,MATCH(Q$2,Inputs!$K$4:$AJ$4,0)))+SUMPRODUCT((Inputs!$C$5:$C$230=$B6)*Inputs!$D$5:$D$230*(((Inputs!$G$5:$G$230="moeda")+(Inputs!$G$5:$G$230="acoes"))*Inputs!$B$1+((Inputs!$G$5:$G$230<>"moeda")*(Inputs!$G$5:$G$230<>"acoes")))*INDEX(Inputs!$K$5:$AJ$230,0,MATCH(Q$2,Inputs!$K$4:$AJ$4,0)))+SUMPRODUCT((Inputs!$E$5:$E$230=$B6)*Inputs!$F$5:$F$230*(((Inputs!$G$5:$G$230="moeda")+(Inputs!$G$5:$G$230="acoes"))*Inputs!$B$1+((Inputs!$G$5:$G$230<>"moeda")*(Inputs!$G$5:$G$230<>"acoes")))*INDEX(Inputs!$K$5:$AJ$230,0,MATCH(Q$2,Inputs!$K$4:$AJ$4,0))))) -> -93.626 | R6: =SUM(N6:Q6) -> -191.053 | S6: =IF(ISNA(MATCH(S$2,Inputs!$K$4:$AJ$4,0)),NA(),IF(SUMPRODUCT((Inputs!$A$5:$A$230=$B6)*ISNUMBER(INDEX(Inputs!$K$5:$AJ$230,0,MATCH(S$2,Inputs!$K$4:$AJ$4,0))))+SUMPRODUCT((Inputs!$C$5:$C$230=$B6)*ISNUMBER(INDEX(Inputs!$K$5:$AJ$230,0,MATCH(S$2,Inputs!$K$4:$AJ$4,0))))+SUMPRODUCT((Inputs!$E$5:$E$230=$B6)*ISNUMBER(INDEX(Inputs!$K$5:$AJ$230,0,MATCH(S$2,Inputs!$K$4:$AJ$4,0))))=0,NA(),SUMPRODUCT((Inputs!$A$5:$A$230=$B6)*Inputs!$B$5:$B$230*(((Inputs!$G$5:$G$230="moeda")+(Inputs!$G$5:$G$230="acoes"))*Inputs!$B$1+((Inputs!$G$5:$G$230<>"moeda")*(Inputs!$G$5:$G$230<>"acoes")))*INDEX(Inputs!$K$5:$AJ$230,0,MATCH(S$2,Inputs!$K$4:$AJ$4,0)))+SUMPRODUCT((Inputs!$C$5:$C$230=$B6)*Inputs!$D$5:$D$230*(((Inputs!$G$5:$G$230="moeda")+(Inputs!$G$5:$G$230="acoes"))*Inputs!$B$1+((Inputs!$G$5:$G$230<>"moeda")*(Inputs!$G$5:$G$230<>"acoes")))*INDEX(Inputs!$K$5:$AJ$230,0,MATCH(S$2,Inputs!$K$4:$AJ$4,0)))+SUMPRODUCT((Inputs!$E$5:$E$230=$B6)*Inputs!$F$5:$F$230*(((Inputs!$G$5:$G$230="moeda")+(Inputs!$G$5:$G$230="acoes"))*Inputs!$B$1+((Inputs!$G$5:$G$230<>"moeda")*(Inputs!$G$5:$G$230<>"acoes")))*INDEX(Inputs!$K$5:$AJ$230,0,MATCH(S$2,Inputs!$K$4:$AJ$4,0))))) -> -32.73 | T6: =IF(ISNA(MATCH(T$2,Inputs!$K$4:$AJ$4,0)),NA(),IF(SUMPRODUCT((Inputs!$A$5:$A$230=$B6)*ISNUMBER(INDEX(Inputs!$K$5:$AJ$230,0,MATCH(T$2,Inputs!$K$4:$AJ$4,0))))+SUMPRODUCT((Inputs!$C$5:$C$230=$B6)*ISNUMBER(INDEX(Inputs!$K$5:$AJ$230,0,MATCH(T$2,Inputs!$K$4:$AJ$4,0))))+SUMPRODUCT((Inputs!$E$5:$E$230=$B6)*ISNUMBER(INDEX(Inputs!$K$5:$AJ$230,0,MATCH(T$2,Inputs!$K$4:$AJ$4,0))))=0,NA(),SUMPRODUCT((Inputs!$A$5:$A$230=$B6)*Inputs!$B$5:$B$230*(((Inputs!$G$5:$G$230="moeda")+(Inputs!$G$5:$G$230="acoes"))*Inputs!$B$1+((Inputs!$G$5:$G$230<>"moeda")*(Inputs!$G$5:$G$230<>"acoes")))*INDEX(Inputs!$K$5:$AJ$230,0,MATCH(T$2,Inputs!$K$4:$AJ$4,0)))+SUMPRODUCT((Inputs!$C$5:$C$230=$B6)*Inputs!$D$5:$D$230*(((Inputs!$G$5:$G$230="moeda")+(Inputs!$G$5:$G$230="acoes"))*Inputs!$B$1+((Inputs!$G$5:$G$230<>"moeda")*(Inputs!$G$5:$G$230<>"acoes")))*INDEX(Inputs!$K$5:$AJ$230,0,MATCH(T$2,Inputs!$K$4:$AJ$4,0)))+SUMPRODUCT((Inputs!$E$5:$E$230=$B6)*Inputs!$F$5:$F$230*(((Inputs!$G$5:$G$230="moeda")+(Inputs!$G$5:$G$230="acoes"))*Inputs!$B$1+((Inputs!$G$5:$G$230<>"moeda")*(Inputs!$G$5:$G$230<>"acoes")))*INDEX(Inputs!$K$5:$AJ$230,0,MATCH(T$2,Inputs!$K$4:$AJ$4,0))))) -> -18.387 | U6: =IF(ISNA(MATCH(U$2,Inputs!$K$4:$AJ$4,0)),NA(),IF(SUMPRODUCT((Inputs!$A$5:$A$230=$B6)*ISNUMBER(INDEX(Inputs!$K$5:$AJ$230,0,MATCH(U$2,Inputs!$K$4:$AJ$4,0))))+SUMPRODUCT((Inputs!$C$5:$C$230=$B6)*ISNUMBER(INDEX(Inputs!$K$5:$AJ$230,0,MATCH(U$2,Inputs!$K$4:$AJ$4,0))))+SUMPRODUCT((Inputs!$E$5:$E$230=$B6)*ISNUMBER(INDEX(Inputs!$K$5:$AJ$230,0,MATCH(U$2,Inputs!$K$4:$AJ$4,0))))=0,NA(),SUMPRODUCT((Inputs!$A$5:$A$230=$B6)*Inputs!$B$5:$B$230*(((Inputs!$G$5:$G$230="moeda")+(Inputs!$G$5:$G$230="acoes"))*Inputs!$B$1+((Inputs!$G$5:$G$230<>"moeda")*(Inputs!$G$5:$G$230<>"acoes")))*INDEX(Inputs!$K$5:$AJ$230,0,MATCH(U$2,Inputs!$K$4:$AJ$4,0)))+SUMPRODUCT((Inputs!$C$5:$C$230=$B6)*Inputs!$D$5:$D$230*(((Inputs!$G$5:$G$230="moeda")+(Inputs!$G$5:$G$230="acoes"))*Inputs!$B$1+((Inputs!$G$5:$G$230<>"moeda")*(Inputs!$G$5:$G$230<>"acoes")))*INDEX(Inputs!$K$5:$AJ$230,0,MATCH(U$2,Inputs!$K$4:$AJ$4,0)))+SUMPRODUCT((Inputs!$E$5:$E$230=$B6)*Inputs!$F$5:$F$230*(((Inputs!$G$5:$G$230="moeda")+(Inputs!$G$5:$G$230="acoes"))*Inputs!$B$1+((Inputs!$G$5:$G$230<>"moeda")*(Inputs!$G$5:$G$230<>"acoes")))*INDEX(Inputs!$K$5:$AJ$230,0,MATCH(U$2,Inputs!$K$4:$AJ$4,0))))) -> -37.227 | V6: =IF(ISNA(MATCH(V$2,Inputs!$K$4:$AJ$4,0)),NA(),IF(SUMPRODUCT((Inputs!$A$5:$A$230=$B6)*ISNUMBER(INDEX(Inputs!$K$5:$AJ$230,0,MATCH(V$2,Inputs!$K$4:$AJ$4,0))))+SUMPRODUCT((Inputs!$C$5:$C$230=$B6)*ISNUMBER(INDEX(Inputs!$K$5:$AJ$230,0,MATCH(V$2,Inputs!$K$4:$AJ$4,0))))+SUMPRODUCT((Inputs!$E$5:$E$230=$B6)*ISNUMBER(INDEX(Inputs!$K$5:$AJ$230,0,MATCH(V$2,Inputs!$K$4:$AJ$4,0))))=0,NA(),SUMPRODUCT((Inputs!$A$5:$A$230=$B6)*Inputs!$B$5:$B$230*(((Inputs!$G$5:$G$230="moeda")+(Inputs!$G$5:$G$230="acoes"))*Inputs!$B$1+((Inputs!$G$5:$G$230<>"moeda")*(Inputs!$G$5:$G$230<>"acoes")))*INDEX(Inputs!$K$5:$AJ$230,0,MATCH(V$2,Inputs!$K$4:$AJ$4,0)))+SUMPRODUCT((Inputs!$C$5:$C$230=$B6)*Inputs!$D$5:$D$230*(((Inputs!$G$5:$G$230="moeda")+(Inputs!$G$5:$G$230="acoes"))*Inputs!$B$1+((Inputs!$G$5:$G$230<>"moeda")*(Inputs!$G$5:$G$230<>"acoes")))*INDEX(Inputs!$K$5:$AJ$230,0,MATCH(V$2,Inputs!$K$4:$AJ$4,0)))+SUMPRODUCT((Inputs!$E$5:$E$230=$B6)*Inputs!$F$5:$F$230*(((Inputs!$G$5:$G$230="moeda")+(Inputs!$G$5:$G$230="acoes"))*Inputs!$B$1+((Inputs!$G$5:$G$230<>"moeda")*(Inputs!$G$5:$G$230<>"acoes")))*INDEX(Inputs!$K$5:$AJ$230,0,MATCH(V$2,Inputs!$K$4:$AJ$4,0))))) -> -69.055 | W6: =SUM(S6:V6) -> -157.399 | X6: =IF(ISNA(MATCH(X$2,Inputs!$K$4:$AJ$4,0)),NA(),IF(SUMPRODUCT((Inputs!$A$5:$A$230=$B6)*ISNUMBER(INDEX(Inputs!$K$5:$AJ$230,0,MATCH(X$2,Inputs!$K$4:$AJ$4,0))))+SUMPRODUCT((Inputs!$C$5:$C$230=$B6)*ISNUMBER(INDEX(Inputs!$K$5:$AJ$230,0,MATCH(X$2,Inputs!$K$4:$AJ$4,0))))+SUMPRODUCT((Inputs!$E$5:$E$230=$B6)*ISNUMBER(INDEX(Inputs!$K$5:$AJ$230,0,MATCH(X$2,Inputs!$K$4:$AJ$4,0))))=0,NA(),SUMPRODUCT((Inputs!$A$5:$A$230=$B6)*Inputs!$B$5:$B$230*(((Inputs!$G$5:$G$230="moeda")+(Inputs!$G$5:$G$230="acoes"))*Inputs!$B$1+((Inputs!$G$5:$G$230<>"moeda")*(Inputs!$G$5:$G$230<>"acoes")))*INDEX(Inputs!$K$5:$AJ$230,0,MATCH(X$2,Inputs!$K$4:$AJ$4,0)))+SUMPRODUCT((Inputs!$C$5:$C$230=$B6)*Inputs!$D$5:$D$230*(((Inputs!$G$5:$G$230="moeda")+(Inputs!$G$5:$G$230="acoes"))*Inputs!$B$1+((Inputs!$G$5:$G$230<>"moeda")*(Inputs!$G$5:$G$230<>"acoes")))*INDEX(Inputs!$K$5:$AJ$230,0,MATCH(X$2,Inputs!$K$4:$AJ$4,0)))+SUMPRODUCT((Inputs!$E$5:$E$230=$B6)*Inputs!$F$5:$F$230*(((Inputs!$G$5:$G$230="moeda")+(Inputs!$G$5:$G$230="acoes"))*Inputs!$B$1+((Inputs!$G$5:$G$230<>"moeda")*(Inputs!$G$5:$G$230<>"acoes")))*INDEX(Inputs!$K$5:$AJ$230,0,MATCH(X$2,Inputs!$K$4:$AJ$4,0))))) -> -45.543 | Y6: =IF(ISNA(MATCH(Y$2,Inputs!$K$4:$AJ$4,0)),NA(),IF(SUMPRODUCT((Inputs!$A$5:$A$230=$B6)*ISNUMBER(INDEX(Inputs!$K$5:$AJ$230,0,MATCH(Y$2,Inputs!$K$4:$AJ$4,0))))+SUMPRODUCT((Inputs!$C$5:$C$230=$B6)*ISNUMBER(INDEX(Inputs!$K$5:$AJ$230,0,MATCH(Y$2,Inputs!$K$4:$AJ$4,0))))+SUMPRODUCT((Inputs!$E$5:$E$230=$B6)*ISNUMBER(INDEX(Inputs!$K$5:$AJ$230,0,MATCH(Y$2,Inputs!$K$4:$AJ$4,0))))=0,NA(),SUMPRODUCT((Inputs!$A$5:$A$230=$B6)*Inputs!$B$5:$B$230*(((Inputs!$G$5:$G$230="moeda")+(Inputs!$G$5:$G$230="acoes"))*Inputs!$B$1+((Inputs!$G$5:$G$230<>"moeda")*(Inputs!$G$5:$G$230<>"acoes")))*INDEX(Inputs!$K$5:$AJ$230,0,MATCH(Y$2,Inputs!$K$4:$AJ$4,0)))+SUMPRODUCT((Inputs!$C$5:$C$230=$B6)*Inputs!$D$5:$D$230*(((Inputs!$G$5:$G$230="moeda")+(Inputs!$G$5:$G$230="acoes"))*Inputs!$B$1+((Inputs!$G$5:$G$230<>"moeda")*(Inputs!$G$5:$G$230<>"acoes")))*INDEX(Inputs!$K$5:$AJ$230,0,MATCH(Y$2,Inputs!$K$4:$AJ$4,0)))+SUMPRODUCT((Inputs!$E$5:$E$230=$B6)*Inputs!$F$5:$F$230*(((Inputs!$G$5:$G$230="moeda")+(Inputs!$G$5:$G$230="acoes"))*Inputs!$B$1+((Inputs!$G$5:$G$230<>"moeda")*(Inputs!$G$5:$G$230<>"acoes")))*INDEX(Inputs!$K$5:$AJ$230,0,MATCH(Y$2,Inputs!$K$4:$AJ$4,0))))) -> -84.158 | Z6: =IF(ISNA(MATCH(Z$2,Inputs!$K$4:$AJ$4,0)),NA(),IF(SUMPRODUCT((Inputs!$A$5:$A$230=$B6)*ISNUMBER(INDEX(Inputs!$K$5:$AJ$230,0,MATCH(Z$2,Inputs!$K$4:$AJ$4,0))))+SUMPRODUCT((Inputs!$C$5:$C$230=$B6)*ISNUMBER(INDEX(Inputs!$K$5:$AJ$230,0,MATCH(Z$2,Inputs!$K$4:$AJ$4,0))))+SUMPRODUCT((Inputs!$E$5:$E$230=$B6)*ISNUMBER(INDEX(Inputs!$K$5:$AJ$230,0,MATCH(Z$2,Inputs!$K$4:$AJ$4,0))))=0,NA(),SUMPRODUCT((Inputs!$A$5:$A$230=$B6)*Inputs!$B$5:$B$230*(((Inputs!$G$5:$G$230="moeda")+(Inputs!$G$5:$G$230="acoes"))*Inputs!$B$1+((Inputs!$G$5:$G$230<>"moeda")*(Inputs!$G$5:$G$230<>"acoes")))*INDEX(Inputs!$K$5:$AJ$230,0,MATCH(Z$2,Inputs!$K$4:$AJ$4,0)))+SUMPRODUCT((Inputs!$C$5:$C$230=$B6)*Inputs!$D$5:$D$230*(((Inputs!$G$5:$G$230="moeda")+(Inputs!$G$5:$G$230="acoes"))*Inputs!$B$1+((Inputs!$G$5:$G$230<>"moeda")*(Inputs!$G$5:$G$230<>"acoes")))*INDEX(Inputs!$K$5:$AJ$230,0,MATCH(Z$2,Inputs!$K$4:$AJ$4,0)))+SUMPRODUCT((Inputs!$E$5:$E$230=$B6)*Inputs!$F$5:$F$230*(((Inputs!$G$5:$G$230="moeda")+(Inputs!$G$5:$G$230="acoes"))*Inputs!$B$1+((Inputs!$G$5:$G$230<>"moeda")*(Inputs!$G$5:$G$230<>"acoes")))*INDEX(Inputs!$K$5:$AJ$230,0,MATCH(Z$2,Inputs!$K$4:$AJ$4,0))))) -> -54.184 | AA6: =IF(ISNA(MATCH(AA$2,Inputs!$K$4:$AJ$4,0)),NA(),IF(SUMPRODUCT((Inputs!$A$5:$A$230=$B6)*ISNUMBER(INDEX(Inputs!$K$5:$AJ$230,0,MATCH(AA$2,Inputs!$K$4:$AJ$4,0))))+SUMPRODUCT((Inputs!$C$5:$C$230=$B6)*ISNUMBER(INDEX(Inputs!$K$5:$AJ$230,0,MATCH(AA$2,Inputs!$K$4:$AJ$4,0))))+SUMPRODUCT((Inputs!$E$5:$E$230=$B6)*ISNUMBER(INDEX(Inputs!$K$5:$AJ$230,0,MATCH(AA$2,Inputs!$K$4:$AJ$4,0))))=0,NA(),SUMPRODUCT((Inputs!$A$5:$A$230=$B6)*Inputs!$B$5:$B$230*(((Inputs!$G$5:$G$230="moeda")+(Inputs!$G$5:$G$230="acoes"))*Inputs!$B$1+((Inputs!$G$5:$G$230<>"moeda")*(Inputs!$G$5:$G$230<>"acoes")))*INDEX(Inputs!$K$5:$AJ$230,0,MATCH(AA$2,Inputs!$K$4:$AJ$4,0)))+SUMPRODUCT((Inputs!$C$5:$C$230=$B6)*Inputs!$D$5:$D$230*(((Inputs!$G$5:$G$230="moeda")+(Inputs!$G$5:$G$230="acoes"))*Inputs!$B$1+((Inputs!$G$5:$G$230<>"moeda")*(Inputs!$G$5:$G$230<>"acoes")))*INDEX(Inputs!$K$5:$AJ$230,0,MATCH(AA$2,Inputs!$K$4:$AJ$4,0)))+SUMPRODUCT((Inputs!$E$5:$E$230=$B6)*Inputs!$F$5:$F$230*(((Inputs!$G$5:$G$230="moeda")+(Inputs!$G$5:$G$230="acoes"))*Inputs!$B$1+((Inputs!$G$5:$G$230<>"moeda")*(Inputs!$G$5:$G$230<>"acoes")))*INDEX(Inputs!$K$5:$AJ$230,0,MATCH(AA$2,Inputs!$K$4:$AJ$4,0))))) -> -55.317 | AB6: =SUM(X6:AA6) -> -239.202 | AC6: =IF(ISNA(MATCH(AC$2,Inputs!$K$4:$AJ$4,0)),NA(),IF(SUMPRODUCT((Inputs!$A$5:$A$230=$B6)*ISNUMBER(INDEX(Inputs!$K$5:$AJ$230,0,MATCH(AC$2,Inputs!$K$4:$AJ$4,0))))+SUMPRODUCT((Inputs!$C$5:$C$230=$B6)*ISNUMBER(INDEX(Inputs!$K$5:$AJ$230,0,MATCH(AC$2,Inputs!$K$4:$AJ$4,0))))+SUMPRODUCT((Inputs!$E$5:$E$230=$B6)*ISNUMBER(INDEX(Inputs!$K$5:$AJ$230,0,MATCH(AC$2,Inputs!$K$4:$AJ$4,0))))=0,NA(),SUMPRODUCT((Inputs!$A$5:$A$230=$B6)*Inputs!$B$5:$B$230*(((Inputs!$G$5:$G$230="moeda")+(Inputs!$G$5:$G$230="acoes"))*Inputs!$B$1+((Inputs!$G$5:$G$230<>"moeda")*(Inputs!$G$5:$G$230<>"acoes")))*INDEX(Inputs!$K$5:$AJ$230,0,MATCH(AC$2,Inputs!$K$4:$AJ$4,0)))+SUMPRODUCT((Inputs!$C$5:$C$230=$B6)*Inputs!$D$5:$D$230*(((Inputs!$G$5:$G$230="moeda")+(Inputs!$G$5:$G$230="acoes"))*Inputs!$B$1+((Inputs!$G$5:$G$230<>"moeda")*(Inputs!$G$5:$G$230<>"acoes")))*INDEX(Inputs!$K$5:$AJ$230,0,MATCH(AC$2,Inputs!$K$4:$AJ$4,0)))+SUMPRODUCT((Inputs!$E$5:$E$230=$B6)*Inputs!$F$5:$F$230*(((Inputs!$G$5:$G$230="moeda")+(Inputs!$G$5:$G$230="acoes"))*Inputs!$B$1+((Inputs!$G$5:$G$230<>"moeda")*(Inputs!$G$5:$G$230<>"acoes")))*INDEX(Inputs!$K$5:$AJ$230,0,MATCH(AC$2,Inputs!$K$4:$AJ$4,0))))) -> -59.4 | AD6: =IF(ISNA(MATCH(AD$2,Inputs!$K$4:$AJ$4,0)),NA(),IF(SUMPRODUCT((Inputs!$A$5:$A$230=$B6)*ISNUMBER(INDEX(Inputs!$K$5:$AJ$230,0,MATCH(AD$2,Inputs!$K$4:$AJ$4,0))))+SUMPRODUCT((Inputs!$C$5:$C$230=$B6)*ISNUMBER(INDEX(Inputs!$K$5:$AJ$230,0,MATCH(AD$2,Inputs!$K$4:$AJ$4,0))))+SUMPRODUCT((Inputs!$E$5:$E$230=$B6)*ISNUMBER(INDEX(Inputs!$K$5:$AJ$230,0,MATCH(AD$2,Inputs!$K$4:$AJ$4,0))))=0,NA(),SUMPRODUCT((Inputs!$A$5:$A$230=$B6)*Inputs!$B$5:$B$230*(((Inputs!$G$5:$G$230="moeda")+(Inputs!$G$5:$G$230="acoes"))*Inputs!$B$1+((Inputs!$G$5:$G$230<>"moeda")*(Inputs!$G$5:$G$230<>"acoes")))*INDEX(Inputs!$K$5:$AJ$230,0,MATCH(AD$2,Inputs!$K$4:$AJ$4,0)))+SUMPRODUCT((Inputs!$C$5:$C$230=$B6)*Inputs!$D$5:$D$230*(((Inputs!$G$5:$G$230="moeda")+(Inputs!$G$5:$G$230="acoes"))*Inputs!$B$1+((Inputs!$G$5:$G$230<>"moeda")*(Inputs!$G$5:$G$230<>"acoes")))*INDEX(Inputs!$K$5:$AJ$230,0,MATCH(AD$2,Inputs!$K$4:$AJ$4,0)))+SUMPRODUCT((Inputs!$E$5:$E$230=$B6)*Inputs!$F$5:$F$230*(((Inputs!$G$5:$G$230="moeda")+(Inputs!$G$5:$G$230="acoes"))*Inputs!$B$1+((Inputs!$G$5:$G$230<>"moeda")*(Inputs!$G$5:$G$230<>"acoes")))*INDEX(Inputs!$K$5:$AJ$230,0,MATCH(AD$2,Inputs!$K$4:$AJ$4,0))))) -> -75.963 | AE6: =IF(ISNA(MATCH(AE$2,Inputs!$K$4:$AJ$4,0)),NA(),IF(SUMPRODUCT((Inputs!$A$5:$A$230=$B6)*ISNUMBER(INDEX(Inputs!$K$5:$AJ$230,0,MATCH(AE$2,Inputs!$K$4:$AJ$4,0))))+SUMPRODUCT((Inputs!$C$5:$C$230=$B6)*ISNUMBER(INDEX(Inputs!$K$5:$AJ$230,0,MATCH(AE$2,Inputs!$K$4:$AJ$4,0))))+SUMPRODUCT((Inputs!$E$5:$E$230=$B6)*ISNUMBER(INDEX(Inputs!$K$5:$AJ$230,0,MATCH(AE$2,Inputs!$K$4:$AJ$4,0))))=0,NA(),SUMPRODUCT((Inputs!$A$5:$A$230=$B6)*Inputs!$B$5:$B$230*(((Inputs!$G$5:$G$230="moeda")+(Inputs!$G$5:$G$230="acoes"))*Inputs!$B$1+((Inputs!$G$5:$G$230<>"moeda")*(Inputs!$G$5:$G$230<>"acoes")))*INDEX(Inputs!$K$5:$AJ$230,0,MATCH(AE$2,Inputs!$K$4:$AJ$4,0)))+SUMPRODUCT((Inputs!$C$5:$C$230=$B6)*Inputs!$D$5:$D$230*(((Inputs!$G$5:$G$230="moeda")+(Inputs!$G$5:$G$230="acoes"))*Inputs!$B$1+((Inputs!$G$5:$G$230<>"moeda")*(Inputs!$G$5:$G$230<>"acoes")))*INDEX(Inputs!$K$5:$AJ$230,0,MATCH(AE$2,Inputs!$K$4:$AJ$4,0)))+SUMPRODUCT((Inputs!$E$5:$E$230=$B6)*Inputs!$F$5:$F$230*(((Inputs!$G$5:$G$230="moeda")+(Inputs!$G$5:$G$230="acoes"))*Inputs!$B$1+((Inputs!$G$5:$G$230<>"moeda")*(Inputs!$G$5:$G$230<>"acoes")))*INDEX(Inputs!$K$5:$AJ$230,0,MATCH(AE$2,Inputs!$K$4:$AJ$4,0))))) -> #N/A | AF6: =IF(ISNA(MATCH(AF$2,Inputs!$K$4:$AJ$4,0)),NA(),IF(SUMPRODUCT((Inputs!$A$5:$A$230=$B6)*ISNUMBER(INDEX(Inputs!$K$5:$AJ$230,0,MATCH(AF$2,Inputs!$K$4:$AJ$4,0))))+SUMPRODUCT((Inputs!$C$5:$C$230=$B6)*ISNUMBER(INDEX(Inputs!$K$5:$AJ$230,0,MATCH(AF$2,Inputs!$K$4:$AJ$4,0))))+SUMPRODUCT((Inputs!$E$5:$E$230=$B6)*ISNUMBER(INDEX(Inputs!$K$5:$AJ$230,0,MATCH(AF$2,Inputs!$K$4:$AJ$4,0))))=0,NA(),SUMPRODUCT((Inputs!$A$5:$A$230=$B6)*Inputs!$B$5:$B$230*(((Inputs!$G$5:$G$230="moeda")+(Inputs!$G$5:$G$230="acoes"))*Inputs!$B$1+((Inputs!$G$5:$G$230<>"moeda")*(Inputs!$G$5:$G$230<>"acoes")))*INDEX(Inputs!$K$5:$AJ$230,0,MATCH(AF$2,Inputs!$K$4:$AJ$4,0)))+SUMPRODUCT((Inputs!$C$5:$C$230=$B6)*Inputs!$D$5:$D$230*(((Inputs!$G$5:$G$230="moeda")+(Inputs!$G$5:$G$230="acoes"))*Inputs!$B$1+((Inputs!$G$5:$G$230<>"moeda")*(Inputs!$G$5:$G$230<>"acoes")))*INDEX(Inputs!$K$5:$AJ$230,0,MATCH(AF$2,Inputs!$K$4:$AJ$4,0)))+SUMPRODUCT((Inputs!$E$5:$E$230=$B6)*Inputs!$F$5:$F$230*(((Inputs!$G$5:$G$230="moeda")+(Inputs!$G$5:$G$230="acoes"))*Inputs!$B$1+((Inputs!$G$5:$G$230<>"moeda")*(Inputs!$G$5:$G$230<>"acoes")))*INDEX(Inputs!$K$5:$AJ$230,0,MATCH(AF$2,Inputs!$K$4:$AJ$4,0))))) -> #N/A | AG6: =SUM(AC6:AF6) -> #N/A | AH6: =IF(ISNA(MATCH(AH$2,Inputs!$K$4:$AJ$4,0)),NA(),IF(SUMPRODUCT((Inputs!$A$5:$A$230=$B6)*ISNUMBER(INDEX(Inputs!$K$5:$AJ$230,0,MATCH(AH$2,Inputs!$K$4:$AJ$4,0))))+SUMPRODUCT((Inputs!$C$5:$C$230=$B6)*ISNUMBER(INDEX(Inputs!$K$5:$AJ$230,0,MATCH(AH$2,Inputs!$K$4:$AJ$4,0))))+SUMPRODUCT((Inputs!$E$5:$E$230=$B6)*ISNUMBER(INDEX(Inputs!$K$5:$AJ$230,0,MATCH(AH$2,Inputs!$K$4:$AJ$4,0))))=0,NA(),SUMPRODUCT((Inputs!$A$5:$A$230=$B6)*Inputs!$B$5:$B$230*(((Inputs!$G$5:$G$230="moeda")+(Inputs!$G$5:$G$230="acoes"))*Inputs!$B$1+((Inputs!$G$5:$G$230<>"moeda")*(Inputs!$G$5:$G$230<>"acoes")))*INDEX(Inputs!$K$5:$AJ$230,0,MATCH(AH$2,Inputs!$K$4:$AJ$4,0)))+SUMPRODUCT((Inputs!$C$5:$C$230=$B6)*Inputs!$D$5:$D$230*(((Inputs!$G$5:$G$230="moeda")+(Inputs!$G$5:$G$230="acoes"))*Inputs!$B$1+((Inputs!$G$5:$G$230<>"moeda")*(Inputs!$G$5:$G$230<>"acoes")))*INDEX(Inputs!$K$5:$AJ$230,0,MATCH(AH$2,Inputs!$K$4:$AJ$4,0)))+SUMPRODUCT((Inputs!$E$5:$E$230=$B6)*Inputs!$F$5:$F$230*(((Inputs!$G$5:$G$230="moeda")+(Inputs!$G$5:$G$230="acoes"))*Inputs!$B$1+((Inputs!$G$5:$G$230<>"moeda")*(Inputs!$G$5:$G$230<>"acoes")))*INDEX(Inputs!$K$5:$AJ$230,0,MATCH(AH$2,Inputs!$K$4:$AJ$4,0))))) -> -28.066 | AI6: =IF(ISNA(MATCH(AI$2,Inputs!$K$4:$AJ$4,0)),NA(),IF(SUMPRODUCT((Inputs!$A$5:$A$230=$B6)*ISNUMBER(INDEX(Inputs!$K$5:$AJ$230,0,MATCH(AI$2,Inputs!$K$4:$AJ$4,0))))+SUMPRODUCT((Inputs!$C$5:$C$230=$B6)*ISNUMBER(INDEX(Inputs!$K$5:$AJ$230,0,MATCH(AI$2,Inputs!$K$4:$AJ$4,0))))+SUMPRODUCT((Inputs!$E$5:$E$230=$B6)*ISNUMBER(INDEX(Inputs!$K$5:$AJ$230,0,MATCH(AI$2,Inputs!$K$4:$AJ$4,0))))=0,NA(),SUMPRODUCT((Inputs!$A$5:$A$230=$B6)*Inputs!$B$5:$B$230*(((Inputs!$G$5:$G$230="moeda")+(Inputs!$G$5:$G$230="acoes"))*Inputs!$B$1+((Inputs!$G$5:$G$230<>"moeda")*(Inputs!$G$5:$G$230<>"acoes")))*INDEX(Inputs!$K$5:$AJ$230,0,MATCH(AI$2,Inputs!$K$4:$AJ$4,0)))+SUMPRODUCT((Inputs!$C$5:$C$230=$B6)*Inputs!$D$5:$D$230*(((Inputs!$G$5:$G$230="moeda")+(Inputs!$G$5:$G$230="acoes"))*Inputs!$B$1+((Inputs!$G$5:$G$230<>"moeda")*(Inputs!$G$5:$G$230<>"acoes")))*INDEX(Inputs!$K$5:$AJ$230,0,MATCH(AI$2,Inputs!$K$4:$AJ$4,0)))+SUMPRODUCT((Inputs!$E$5:$E$230=$B6)*Inputs!$F$5:$F$230*(((Inputs!$G$5:$G$230="moeda")+(Inputs!$G$5:$G$230="acoes"))*Inputs!$B$1+((Inputs!$G$5:$G$230<>"moeda")*(Inputs!$G$5:$G$230<>"acoes")))*INDEX(Inputs!$K$5:$AJ$230,0,MATCH(AI$2,Inputs!$K$4:$AJ$4,0))))) -> -29.574 | AJ6: =IF(ISNA(MATCH(AJ$2,Inputs!$K$4:$AJ$4,0)),NA(),IF(SUMPRODUCT((Inputs!$A$5:$A$230=$B6)*ISNUMBER(INDEX(Inputs!$K$5:$AJ$230,0,MATCH(AJ$2,Inputs!$K$4:$AJ$4,0))))+SUMPRODUCT((Inputs!$C$5:$C$230=$B6)*ISNUMBER(INDEX(Inputs!$K$5:$AJ$230,0,MATCH(AJ$2,Inputs!$K$4:$AJ$4,0))))+SUMPRODUCT((Inputs!$E$5:$E$230=$B6)*ISNUMBER(INDEX(Inputs!$K$5:$AJ$230,0,MATCH(AJ$2,Inputs!$K$4:$AJ$4,0))))=0,NA(),SUMPRODUCT((Inputs!$A$5:$A$230=$B6)*Inputs!$B$5:$B$230*(((Inputs!$G$5:$G$230="moeda")+(Inputs!$G$5:$G$230="acoes"))*Inputs!$B$1+((Inputs!$G$5:$G$230<>"moeda")*(Inputs!$G$5:$G$230<>"acoes")))*INDEX(Inputs!$K$5:$AJ$230,0,MATCH(AJ$2,Inputs!$K$4:$AJ$4,0)))+SUMPRODUCT((Inputs!$C$5:$C$230=$B6)*Inputs!$D$5:$D$230*(((Inputs!$G$5:$G$230="moeda")+(Inputs!$G$5:$G$230="acoes"))*Inputs!$B$1+((Inputs!$G$5:$G$230<>"moeda")*(Inputs!$G$5:$G$230<>"acoes")))*INDEX(Inputs!$K$5:$AJ$230,0,MATCH(AJ$2,Inputs!$K$4:$AJ$4,0)))+SUMPRODUCT((Inputs!$E$5:$E$230=$B6)*Inputs!$F$5:$F$230*(((Inputs!$G$5:$G$230="moeda")+(Inputs!$G$5:$G$230="acoes"))*Inputs!$B$1+((Inputs!$G$5:$G$230<>"moeda")*(Inputs!$G$5:$G$230<>"acoes")))*INDEX(Inputs!$K$5:$AJ$230,0,MATCH(AJ$2,Inputs!$K$4:$AJ$4,0))))) -> -21.066 | AK6: =IF(ISNA(MATCH(AK$2,Inputs!$K$4:$AJ$4,0)),NA(),IF(SUMPRODUCT((Inputs!$A$5:$A$230=$B6)*ISNUMBER(INDEX(Inputs!$K$5:$AJ$230,0,MATCH(AK$2,Inputs!$K$4:$AJ$4,0))))+SUMPRODUCT((Inputs!$C$5:$C$230=$B6)*ISNUMBER(INDEX(Inputs!$K$5:$AJ$230,0,MATCH(AK$2,Inputs!$K$4:$AJ$4,0))))+SUMPRODUCT((Inputs!$E$5:$E$230=$B6)*ISNUMBER(INDEX(Inputs!$K$5:$AJ$230,0,MATCH(AK$2,Inputs!$K$4:$AJ$4,0))))=0,NA(),SUMPRODUCT((Inputs!$A$5:$A$230=$B6)*Inputs!$B$5:$B$230*(((Inputs!$G$5:$G$230="moeda")+(Inputs!$G$5:$G$230="acoes"))*Inputs!$B$1+((Inputs!$G$5:$G$230<>"moeda")*(Inputs!$G$5:$G$230<>"acoes")))*INDEX(Inputs!$K$5:$AJ$230,0,MATCH(AK$2,Inputs!$K$4:$AJ$4,0)))+SUMPRODUCT((Inputs!$C$5:$C$230=$B6)*Inputs!$D$5:$D$230*(((Inputs!$G$5:$G$230="moeda")+(Inputs!$G$5:$G$230="acoes"))*Inputs!$B$1+((Inputs!$G$5:$G$230<>"moeda")*(Inputs!$G$5:$G$230<>"acoes")))*INDEX(Inputs!$K$5:$AJ$230,0,MATCH(AK$2,Inputs!$K$4:$AJ$4,0)))+SUMPRODUCT((Inputs!$E$5:$E$230=$B6)*Inputs!$F$5:$F$230*(((Inputs!$G$5:$G$230="moeda")+(Inputs!$G$5:$G$230="acoes"))*Inputs!$B$1+((Inputs!$G$5:$G$230<>"moeda")*(Inputs!$G$5:$G$230<>"acoes")))*INDEX(Inputs!$K$5:$AJ$230,0,MATCH(AK$2,Inputs!$K$4:$AJ$4,0))))) -> -27.349 | AL6: =SUM(AH6:AK6) -> -106.055
B7: 4 | C7: D&A | D7: =IF(ISNA(MATCH(D$2,Inputs!$K$4:$AJ$4,0)),NA(),IF(SUMPRODUCT((Inputs!$A$5:$A$230=$B7)*ISNUMBER(INDEX(Inputs!$K$5:$AJ$230,0,MATCH(D$2,Inputs!$K$4:$AJ$4,0))))+SUMPRODUCT((Inputs!$C$5:$C$230=$B7)*ISNUMBER(INDEX(Inputs!$K$5:$AJ$230,0,MATCH(D$2,Inputs!$K$4:$AJ$4,0))))+SUMPRODUCT((Inputs!$E$5:$E$230=$B7)*ISNUMBER(INDEX(Inputs!$K$5:$AJ$230,0,MATCH(D$2,Inputs!$K$4:$AJ$4,0))))=0,NA(),SUMPRODUCT((Inputs!$A$5:$A$230=$B7)*Inputs!$B$5:$B$230*(((Inputs!$G$5:$G$230="moeda")+(Inputs!$G$5:$G$230="acoes"))*Inputs!$B$1+((Inputs!$G$5:$G$230<>"moeda")*(Inputs!$G$5:$G$230<>"acoes")))*INDEX(Inputs!$K$5:$AJ$230,0,MATCH(D$2,Inputs!$K$4:$AJ$4,0)))+SUMPRODUCT((Inputs!$C$5:$C$230=$B7)*Inputs!$D$5:$D$230*(((Inputs!$G$5:$G$230="moeda")+(Inputs!$G$5:$G$230="acoes"))*Inputs!$B$1+((Inputs!$G$5:$G$230<>"moeda")*(Inputs!$G$5:$G$230<>"acoes")))*INDEX(Inputs!$K$5:$AJ$230,0,MATCH(D$2,Inputs!$K$4:$AJ$4,0)))+SUMPRODUCT((Inputs!$E$5:$E$230=$B7)*Inputs!$F$5:$F$230*(((Inputs!$G$5:$G$230="moeda")+(Inputs!$G$5:$G$230="acoes"))*Inputs!$B$1+((Inputs!$G$5:$G$230<>"moeda")*(Inputs!$G$5:$G$230<>"acoes")))*INDEX(Inputs!$K$5:$AJ$230,0,MATCH(D$2,Inputs!$K$4:$AJ$4,0))))) -> -29.436 | E7: =IF(ISNA(MATCH(E$2,Inputs!$K$4:$AJ$4,0)),NA(),IF(SUMPRODUCT((Inputs!$A$5:$A$230=$B7)*ISNUMBER(INDEX(Inputs!$K$5:$AJ$230,0,MATCH(E$2,Inputs!$K$4:$AJ$4,0))))+SUMPRODUCT((Inputs!$C$5:$C$230=$B7)*ISNUMBER(INDEX(Inputs!$K$5:$AJ$230,0,MATCH(E$2,Inputs!$K$4:$AJ$4,0))))+SUMPRODUCT((Inputs!$E$5:$E$230=$B7)*ISNUMBER(INDEX(Inputs!$K$5:$AJ$230,0,MATCH(E$2,Inputs!$K$4:$AJ$4,0))))=0,NA(),SUMPRODUCT((Inputs!$A$5:$A$230=$B7)*Inputs!$B$5:$B$230*(((Inputs!$G$5:$G$230="moeda")+(Inputs!$G$5:$G$230="acoes"))*Inputs!$B$1+((Inputs!$G$5:$G$230<>"moeda")*(Inputs!$G$5:$G$230<>"acoes")))*INDEX(Inputs!$K$5:$AJ$230,0,MATCH(E$2,Inputs!$K$4:$AJ$4,0)))+SUMPRODUCT((Inputs!$C$5:$C$230=$B7)*Inputs!$D$5:$D$230*(((Inputs!$G$5:$G$230="moeda")+(Inputs!$G$5:$G$230="acoes"))*Inputs!$B$1+((Inputs!$G$5:$G$230<>"moeda")*(Inputs!$G$5:$G$230<>"acoes")))*INDEX(Inputs!$K$5:$AJ$230,0,MATCH(E$2,Inputs!$K$4:$AJ$4,0)))+SUMPRODUCT((Inputs!$E$5:$E$230=$B7)*Inputs!$F$5:$F$230*(((Inputs!$G$5:$G$230="moeda")+(Inputs!$G$5:$G$230="acoes"))*Inputs!$B$1+((Inputs!$G$5:$G$230<>"moeda")*(Inputs!$G$5:$G$230<>"acoes")))*INDEX(Inputs!$K$5:$AJ$230,0,MATCH(E$2,Inputs!$K$4:$AJ$4,0))))) -> -29.857 | F7: =IF(ISNA(MATCH(F$2,Inputs!$K$4:$AJ$4,0)),NA(),IF(SUMPRODUCT((Inputs!$A$5:$A$230=$B7)*ISNUMBER(INDEX(Inputs!$K$5:$AJ$230,0,MATCH(F$2,Inputs!$K$4:$AJ$4,0))))+SUMPRODUCT((Inputs!$C$5:$C$230=$B7)*ISNUMBER(INDEX(Inputs!$K$5:$AJ$230,0,MATCH(F$2,Inputs!$K$4:$AJ$4,0))))+SUMPRODUCT((Inputs!$E$5:$E$230=$B7)*ISNUMBER(INDEX(Inputs!$K$5:$AJ$230,0,MATCH(F$2,Inputs!$K$4:$AJ$4,0))))=0,NA(),SUMPRODUCT((Inputs!$A$5:$A$230=$B7)*Inputs!$B$5:$B$230*(((Inputs!$G$5:$G$230="moeda")+(Inputs!$G$5:$G$230="acoes"))*Inputs!$B$1+((Inputs!$G$5:$G$230<>"moeda")*(Inputs!$G$5:$G$230<>"acoes")))*INDEX(Inputs!$K$5:$AJ$230,0,MATCH(F$2,Inputs!$K$4:$AJ$4,0)))+SUMPRODUCT((Inputs!$C$5:$C$230=$B7)*Inputs!$D$5:$D$230*(((Inputs!$G$5:$G$230="moeda")+(Inputs!$G$5:$G$230="acoes"))*Inputs!$B$1+((Inputs!$G$5:$G$230<>"moeda")*(Inputs!$G$5:$G$230<>"acoes")))*INDEX(Inputs!$K$5:$AJ$230,0,MATCH(F$2,Inputs!$K$4:$AJ$4,0)))+SUMPRODUCT((Inputs!$E$5:$E$230=$B7)*Inputs!$F$5:$F$230*(((Inputs!$G$5:$G$230="moeda")+(Inputs!$G$5:$G$230="acoes"))*Inputs!$B$1+((Inputs!$G$5:$G$230<>"moeda")*(Inputs!$G$5:$G$230<>"acoes")))*INDEX(Inputs!$K$5:$AJ$230,0,MATCH(F$2,Inputs!$K$4:$AJ$4,0))))) -> -44.401 | G7: =IF(ISNA(MATCH(G$2,Inputs!$K$4:$AJ$4,0)),NA(),IF(SUMPRODUCT((Inputs!$A$5:$A$230=$B7)*ISNUMBER(INDEX(Inputs!$K$5:$AJ$230,0,MATCH(G$2,Inputs!$K$4:$AJ$4,0))))+SUMPRODUCT((Inputs!$C$5:$C$230=$B7)*ISNUMBER(INDEX(Inputs!$K$5:$AJ$230,0,MATCH(G$2,Inputs!$K$4:$AJ$4,0))))+SUMPRODUCT((Inputs!$E$5:$E$230=$B7)*ISNUMBER(INDEX(Inputs!$K$5:$AJ$230,0,MATCH(G$2,Inputs!$K$4:$AJ$4,0))))=0,NA(),SUMPRODUCT((Inputs!$A$5:$A$230=$B7)*Inputs!$B$5:$B$230*(((Inputs!$G$5:$G$230="moeda")+(Inputs!$G$5:$G$230="acoes"))*Inputs!$B$1+((Inputs!$G$5:$G$230<>"moeda")*(Inputs!$G$5:$G$230<>"acoes")))*INDEX(Inputs!$K$5:$AJ$230,0,MATCH(G$2,Inputs!$K$4:$AJ$4,0)))+SUMPRODUCT((Inputs!$C$5:$C$230=$B7)*Inputs!$D$5:$D$230*(((Inputs!$G$5:$G$230="moeda")+(Inputs!$G$5:$G$230="acoes"))*Inputs!$B$1+((Inputs!$G$5:$G$230<>"moeda")*(Inputs!$G$5:$G$230<>"acoes")))*INDEX(Inputs!$K$5:$AJ$230,0,MATCH(G$2,Inputs!$K$4:$AJ$4,0)))+SUMPRODUCT((Inputs!$E$5:$E$230=$B7)*Inputs!$F$5:$F$230*(((Inputs!$G$5:$G$230="moeda")+(Inputs!$G$5:$G$230="acoes"))*Inputs!$B$1+((Inputs!$G$5:$G$230<>"moeda")*(Inputs!$G$5:$G$230<>"acoes")))*INDEX(Inputs!$K$5:$AJ$230,0,MATCH(G$2,Inputs!$K$4:$AJ$4,0))))) -> -35.869 | H7: =SUM(D7:G7) -> -139.563 | I7: =IF(ISNA(MATCH(I$2,Inputs!$K$4:$AJ$4,0)),NA(),IF(SUMPRODUCT((Inputs!$A$5:$A$230=$B7)*ISNUMBER(INDEX(Inputs!$K$5:$AJ$230,0,MATCH(I$2,Inputs!$K$4:$AJ$4,0))))+SUMPRODUCT((Inputs!$C$5:$C$230=$B7)*ISNUMBER(INDEX(Inputs!$K$5:$AJ$230,0,MATCH(I$2,Inputs!$K$4:$AJ$4,0))))+SUMPRODUCT((Inputs!$E$5:$E$230=$B7)*ISNUMBER(INDEX(Inputs!$K$5:$AJ$230,0,MATCH(I$2,Inputs!$K$4:$AJ$4,0))))=0,NA(),SUMPRODUCT((Inputs!$A$5:$A$230=$B7)*Inputs!$B$5:$B$230*(((Inputs!$G$5:$G$230="moeda")+(Inputs!$G$5:$G$230="acoes"))*Inputs!$B$1+((Inputs!$G$5:$G$230<>"moeda")*(Inputs!$G$5:$G$230<>"acoes")))*INDEX(Inputs!$K$5:$AJ$230,0,MATCH(I$2,Inputs!$K$4:$AJ$4,0)))+SUMPRODUCT((Inputs!$C$5:$C$230=$B7)*Inputs!$D$5:$D$230*(((Inputs!$G$5:$G$230="moeda")+(Inputs!$G$5:$G$230="acoes"))*Inputs!$B$1+((Inputs!$G$5:$G$230<>"moeda")*(Inputs!$G$5:$G$230<>"acoes")))*INDEX(Inputs!$K$5:$AJ$230,0,MATCH(I$2,Inputs!$K$4:$AJ$4,0)))+SUMPRODUCT((Inputs!$E$5:$E$230=$B7)*Inputs!$F$5:$F$230*(((Inputs!$G$5:$G$230="moeda")+(Inputs!$G$5:$G$230="acoes"))*Inputs!$B$1+((Inputs!$G$5:$G$230<>"moeda")*(Inputs!$G$5:$G$230<>"acoes")))*INDEX(Inputs!$K$5:$AJ$230,0,MATCH(I$2,Inputs!$K$4:$AJ$4,0))))) -> -38.507 | J7: =IF(ISNA(MATCH(J$2,Inputs!$K$4:$AJ$4,0)),NA(),IF(SUMPRODUCT((Inputs!$A$5:$A$230=$B7)*ISNUMBER(INDEX(Inputs!$K$5:$AJ$230,0,MATCH(J$2,Inputs!$K$4:$AJ$4,0))))+SUMPRODUCT((Inputs!$C$5:$C$230=$B7)*ISNUMBER(INDEX(Inputs!$K$5:$AJ$230,0,MATCH(J$2,Inputs!$K$4:$AJ$4,0))))+SUMPRODUCT((Inputs!$E$5:$E$230=$B7)*ISNUMBER(INDEX(Inputs!$K$5:$AJ$230,0,MATCH(J$2,Inputs!$K$4:$AJ$4,0))))=0,NA(),SUMPRODUCT((Inputs!$A$5:$A$230=$B7)*Inputs!$B$5:$B$230*(((Inputs!$G$5:$G$230="moeda")+(Inputs!$G$5:$G$230="acoes"))*Inputs!$B$1+((Inputs!$G$5:$G$230<>"moeda")*(Inputs!$G$5:$G$230<>"acoes")))*INDEX(Inputs!$K$5:$AJ$230,0,MATCH(J$2,Inputs!$K$4:$AJ$4,0)))+SUMPRODUCT((Inputs!$C$5:$C$230=$B7)*Inputs!$D$5:$D$230*(((Inputs!$G$5:$G$230="moeda")+(Inputs!$G$5:$G$230="acoes"))*Inputs!$B$1+((Inputs!$G$5:$G$230<>"moeda")*(Inputs!$G$5:$G$230<>"acoes")))*INDEX(Inputs!$K$5:$AJ$230,0,MATCH(J$2,Inputs!$K$4:$AJ$4,0)))+SUMPRODUCT((Inputs!$E$5:$E$230=$B7)*Inputs!$F$5:$F$230*(((Inputs!$G$5:$G$230="moeda")+(Inputs!$G$5:$G$230="acoes"))*Inputs!$B$1+((Inputs!$G$5:$G$230<>"moeda")*(Inputs!$G$5:$G$230<>"acoes")))*INDEX(Inputs!$K$5:$AJ$230,0,MATCH(J$2,Inputs!$K$4:$AJ$4,0))))) -> -36.456 | K7: =IF(ISNA(MATCH(K$2,Inputs!$K$4:$AJ$4,0)),NA(),IF(SUMPRODUCT((Inputs!$A$5:$A$230=$B7)*ISNUMBER(INDEX(Inputs!$K$5:$AJ$230,0,MATCH(K$2,Inputs!$K$4:$AJ$4,0))))+SUMPRODUCT((Inputs!$C$5:$C$230=$B7)*ISNUMBER(INDEX(Inputs!$K$5:$AJ$230,0,MATCH(K$2,Inputs!$K$4:$AJ$4,0))))+SUMPRODUCT((Inputs!$E$5:$E$230=$B7)*ISNUMBER(INDEX(Inputs!$K$5:$AJ$230,0,MATCH(K$2,Inputs!$K$4:$AJ$4,0))))=0,NA(),SUMPRODUCT((Inputs!$A$5:$A$230=$B7)*Inputs!$B$5:$B$230*(((Inputs!$G$5:$G$230="moeda")+(Inputs!$G$5:$G$230="acoes"))*Inputs!$B$1+((Inputs!$G$5:$G$230<>"moeda")*(Inputs!$G$5:$G$230<>"acoes")))*INDEX(Inputs!$K$5:$AJ$230,0,MATCH(K$2,Inputs!$K$4:$AJ$4,0)))+SUMPRODUCT((Inputs!$C$5:$C$230=$B7)*Inputs!$D$5:$D$230*(((Inputs!$G$5:$G$230="moeda")+(Inputs!$G$5:$G$230="acoes"))*Inputs!$B$1+((Inputs!$G$5:$G$230<>"moeda")*(Inputs!$G$5:$G$230<>"acoes")))*INDEX(Inputs!$K$5:$AJ$230,0,MATCH(K$2,Inputs!$K$4:$AJ$4,0)))+SUMPRODUCT((Inputs!$E$5:$E$230=$B7)*Inputs!$F$5:$F$230*(((Inputs!$G$5:$G$230="moeda")+(Inputs!$G$5:$G$230="acoes"))*Inputs!$B$1+((Inputs!$G$5:$G$230<>"moeda")*(Inputs!$G$5:$G$230<>"acoes")))*INDEX(Inputs!$K$5:$AJ$230,0,MATCH(K$2,Inputs!$K$4:$AJ$4,0))))) -> -36.74 | L7: =IF(ISNA(MATCH(L$2,Inputs!$K$4:$AJ$4,0)),NA(),IF(SUMPRODUCT((Inputs!$A$5:$A$230=$B7)*ISNUMBER(INDEX(Inputs!$K$5:$AJ$230,0,MATCH(L$2,Inputs!$K$4:$AJ$4,0))))+SUMPRODUCT((Inputs!$C$5:$C$230=$B7)*ISNUMBER(INDEX(Inputs!$K$5:$AJ$230,0,MATCH(L$2,Inputs!$K$4:$AJ$4,0))))+SUMPRODUCT((Inputs!$E$5:$E$230=$B7)*ISNUMBER(INDEX(Inputs!$K$5:$AJ$230,0,MATCH(L$2,Inputs!$K$4:$AJ$4,0))))=0,NA(),SUMPRODUCT((Inputs!$A$5:$A$230=$B7)*Inputs!$B$5:$B$230*(((Inputs!$G$5:$G$230="moeda")+(Inputs!$G$5:$G$230="acoes"))*Inputs!$B$1+((Inputs!$G$5:$G$230<>"moeda")*(Inputs!$G$5:$G$230<>"acoes")))*INDEX(Inputs!$K$5:$AJ$230,0,MATCH(L$2,Inputs!$K$4:$AJ$4,0)))+SUMPRODUCT((Inputs!$C$5:$C$230=$B7)*Inputs!$D$5:$D$230*(((Inputs!$G$5:$G$230="moeda")+(Inputs!$G$5:$G$230="acoes"))*Inputs!$B$1+((Inputs!$G$5:$G$230<>"moeda")*(Inputs!$G$5:$G$230<>"acoes")))*INDEX(Inputs!$K$5:$AJ$230,0,MATCH(L$2,Inputs!$K$4:$AJ$4,0)))+SUMPRODUCT((Inputs!$E$5:$E$230=$B7)*Inputs!$F$5:$F$230*(((Inputs!$G$5:$G$230="moeda")+(Inputs!$G$5:$G$230="acoes"))*Inputs!$B$1+((Inputs!$G$5:$G$230<>"moeda")*(Inputs!$G$5:$G$230<>"acoes")))*INDEX(Inputs!$K$5:$AJ$230,0,MATCH(L$2,Inputs!$K$4:$AJ$4,0))))) -> -37.879 | M7: =SUM(I7:L7) -> -149.582 | N7: =IF(ISNA(MATCH(N$2,Inputs!$K$4:$AJ$4,0)),NA(),IF(SUMPRODUCT((Inputs!$A$5:$A$230=$B7)*ISNUMBER(INDEX(Inputs!$K$5:$AJ$230,0,MATCH(N$2,Inputs!$K$4:$AJ$4,0))))+SUMPRODUCT((Inputs!$C$5:$C$230=$B7)*ISNUMBER(INDEX(Inputs!$K$5:$AJ$230,0,MATCH(N$2,Inputs!$K$4:$AJ$4,0))))+SUMPRODUCT((Inputs!$E$5:$E$230=$B7)*ISNUMBER(INDEX(Inputs!$K$5:$AJ$230,0,MATCH(N$2,Inputs!$K$4:$AJ$4,0))))=0,NA(),SUMPRODUCT((Inputs!$A$5:$A$230=$B7)*Inputs!$B$5:$B$230*(((Inputs!$G$5:$G$230="moeda")+(Inputs!$G$5:$G$230="acoes"))*Inputs!$B$1+((Inputs!$G$5:$G$230<>"moeda")*(Inputs!$G$5:$G$230<>"acoes")))*INDEX(Inputs!$K$5:$AJ$230,0,MATCH(N$2,Inputs!$K$4:$AJ$4,0)))+SUMPRODUCT((Inputs!$C$5:$C$230=$B7)*Inputs!$D$5:$D$230*(((Inputs!$G$5:$G$230="moeda")+(Inputs!$G$5:$G$230="acoes"))*Inputs!$B$1+((Inputs!$G$5:$G$230<>"moeda")*(Inputs!$G$5:$G$230<>"acoes")))*INDEX(Inputs!$K$5:$AJ$230,0,MATCH(N$2,Inputs!$K$4:$AJ$4,0)))+SUMPRODUCT((Inputs!$E$5:$E$230=$B7)*Inputs!$F$5:$F$230*(((Inputs!$G$5:$G$230="moeda")+(Inputs!$G$5:$G$230="acoes"))*Inputs!$B$1+((Inputs!$G$5:$G$230<>"moeda")*(Inputs!$G$5:$G$230<>"acoes")))*INDEX(Inputs!$K$5:$AJ$230,0,MATCH(N$2,Inputs!$K$4:$AJ$4,0))))) -> -34.786 | O7: =IF(ISNA(MATCH(O$2,Inputs!$K$4:$AJ$4,0)),NA(),IF(SUMPRODUCT((Inputs!$A$5:$A$230=$B7)*ISNUMBER(INDEX(Inputs!$K$5:$AJ$230,0,MATCH(O$2,Inputs!$K$4:$AJ$4,0))))+SUMPRODUCT((Inputs!$C$5:$C$230=$B7)*ISNUMBER(INDEX(Inputs!$K$5:$AJ$230,0,MATCH(O$2,Inputs!$K$4:$AJ$4,0))))+SUMPRODUCT((Inputs!$E$5:$E$230=$B7)*ISNUMBER(INDEX(Inputs!$K$5:$AJ$230,0,MATCH(O$2,Inputs!$K$4:$AJ$4,0))))=0,NA(),SUMPRODUCT((Inputs!$A$5:$A$230=$B7)*Inputs!$B$5:$B$230*(((Inputs!$G$5:$G$230="moeda")+(Inputs!$G$5:$G$230="acoes"))*Inputs!$B$1+((Inputs!$G$5:$G$230<>"moeda")*(Inputs!$G$5:$G$230<>"acoes")))*INDEX(Inputs!$K$5:$AJ$230,0,MATCH(O$2,Inputs!$K$4:$AJ$4,0)))+SUMPRODUCT((Inputs!$C$5:$C$230=$B7)*Inputs!$D$5:$D$230*(((Inputs!$G$5:$G$230="moeda")+(Inputs!$G$5:$G$230="acoes"))*Inputs!$B$1+((Inputs!$G$5:$G$230<>"moeda")*(Inputs!$G$5:$G$230<>"acoes")))*INDEX(Inputs!$K$5:$AJ$230,0,MATCH(O$2,Inputs!$K$4:$AJ$4,0)))+SUMPRODUCT((Inputs!$E$5:$E$230=$B7)*Inputs!$F$5:$F$230*(((Inputs!$G$5:$G$230="moeda")+(Inputs!$G$5:$G$230="acoes"))*Inputs!$B$1+((Inputs!$G$5:$G$230<>"moeda")*(Inputs!$G$5:$G$230<>"acoes")))*INDEX(Inputs!$K$5:$AJ$230,0,MATCH(O$2,Inputs!$K$4:$AJ$4,0))))) -> -36.346 | P7: =IF(ISNA(MATCH(P$2,Inputs!$K$4:$AJ$4,0)),NA(),IF(SUMPRODUCT((Inputs!$A$5:$A$230=$B7)*ISNUMBER(INDEX(Inputs!$K$5:$AJ$230,0,MATCH(P$2,Inputs!$K$4:$AJ$4,0))))+SUMPRODUCT((Inputs!$C$5:$C$230=$B7)*ISNUMBER(INDEX(Inputs!$K$5:$AJ$230,0,MATCH(P$2,Inputs!$K$4:$AJ$4,0))))+SUMPRODUCT((Inputs!$E$5:$E$230=$B7)*ISNUMBER(INDEX(Inputs!$K$5:$AJ$230,0,MATCH(P$2,Inputs!$K$4:$AJ$4,0))))=0,NA(),SUMPRODUCT((Inputs!$A$5:$A$230=$B7)*Inputs!$B$5:$B$230*(((Inputs!$G$5:$G$230="moeda")+(Inputs!$G$5:$G$230="acoes"))*Inputs!$B$1+((Inputs!$G$5:$G$230<>"moeda")*(Inputs!$G$5:$G$230<>"acoes")))*INDEX(Inputs!$K$5:$AJ$230,0,MATCH(P$2,Inputs!$K$4:$AJ$4,0)))+SUMPRODUCT((Inputs!$C$5:$C$230=$B7)*Inputs!$D$5:$D$230*(((Inputs!$G$5:$G$230="moeda")+(Inputs!$G$5:$G$230="acoes"))*Inputs!$B$1+((Inputs!$G$5:$G$230<>"moeda")*(Inputs!$G$5:$G$230<>"acoes")))*INDEX(Inputs!$K$5:$AJ$230,0,MATCH(P$2,Inputs!$K$4:$AJ$4,0)))+SUMPRODUCT((Inputs!$E$5:$E$230=$B7)*Inputs!$F$5:$F$230*(((Inputs!$G$5:$G$230="moeda")+(Inputs!$G$5:$G$230="acoes"))*Inputs!$B$1+((Inputs!$G$5:$G$230<>"moeda")*(Inputs!$G$5:$G$230<>"acoes")))*INDEX(Inputs!$K$5:$AJ$230,0,MATCH(P$2,Inputs!$K$4:$AJ$4,0))))) -> -40.913 | Q7: =IF(ISNA(MATCH(Q$2,Inputs!$K$4:$AJ$4,0)),NA(),IF(SUMPRODUCT((Inputs!$A$5:$A$230=$B7)*ISNUMBER(INDEX(Inputs!$K$5:$AJ$230,0,MATCH(Q$2,Inputs!$K$4:$AJ$4,0))))+SUMPRODUCT((Inputs!$C$5:$C$230=$B7)*ISNUMBER(INDEX(Inputs!$K$5:$AJ$230,0,MATCH(Q$2,Inputs!$K$4:$AJ$4,0))))+SUMPRODUCT((Inputs!$E$5:$E$230=$B7)*ISNUMBER(INDEX(Inputs!$K$5:$AJ$230,0,MATCH(Q$2,Inputs!$K$4:$AJ$4,0))))=0,NA(),SUMPRODUCT((Inputs!$A$5:$A$230=$B7)*Inputs!$B$5:$B$230*(((Inputs!$G$5:$G$230="moeda")+(Inputs!$G$5:$G$230="acoes"))*Inputs!$B$1+((Inputs!$G$5:$G$230<>"moeda")*(Inputs!$G$5:$G$230<>"acoes")))*INDEX(Inputs!$K$5:$AJ$230,0,MATCH(Q$2,Inputs!$K$4:$AJ$4,0)))+SUMPRODUCT((Inputs!$C$5:$C$230=$B7)*Inputs!$D$5:$D$230*(((Inputs!$G$5:$G$230="moeda")+(Inputs!$G$5:$G$230="acoes"))*Inputs!$B$1+((Inputs!$G$5:$G$230<>"moeda")*(Inputs!$G$5:$G$230<>"acoes")))*INDEX(Inputs!$K$5:$AJ$230,0,MATCH(Q$2,Inputs!$K$4:$AJ$4,0)))+SUMPRODUCT((Inputs!$E$5:$E$230=$B7)*Inputs!$F$5:$F$230*(((Inputs!$G$5:$G$230="moeda")+(Inputs!$G$5:$G$230="acoes"))*Inputs!$B$1+((Inputs!$G$5:$G$230<>"moeda")*(Inputs!$G$5:$G$230<>"acoes")))*INDEX(Inputs!$K$5:$AJ$230,0,MATCH(Q$2,Inputs!$K$4:$AJ$4,0))))) -> -41.867 | R7: =SUM(N7:Q7) -> -153.912 | S7: =IF(ISNA(MATCH(S$2,Inputs!$K$4:$AJ$4,0)),NA(),IF(SUMPRODUCT((Inputs!$A$5:$A$230=$B7)*ISNUMBER(INDEX(Inputs!$K$5:$AJ$230,0,MATCH(S$2,Inputs!$K$4:$AJ$4,0))))+SUMPRODUCT((Inputs!$C$5:$C$230=$B7)*ISNUMBER(INDEX(Inputs!$K$5:$AJ$230,0,MATCH(S$2,Inputs!$K$4:$AJ$4,0))))+SUMPRODUCT((Inputs!$E$5:$E$230=$B7)*ISNUMBER(INDEX(Inputs!$K$5:$AJ$230,0,MATCH(S$2,Inputs!$K$4:$AJ$4,0))))=0,NA(),SUMPRODUCT((Inputs!$A$5:$A$230=$B7)*Inputs!$B$5:$B$230*(((Inputs!$G$5:$G$230="moeda")+(Inputs!$G$5:$G$230="acoes"))*Inputs!$B$1+((Inputs!$G$5:$G$230<>"moeda")*(Inputs!$G$5:$G$230<>"acoes")))*INDEX(Inputs!$K$5:$AJ$230,0,MATCH(S$2,Inputs!$K$4:$AJ$4,0)))+SUMPRODUCT((Inputs!$C$5:$C$230=$B7)*Inputs!$D$5:$D$230*(((Inputs!$G$5:$G$230="moeda")+(Inputs!$G$5:$G$230="acoes"))*Inputs!$B$1+((Inputs!$G$5:$G$230<>"moeda")*(Inputs!$G$5:$G$230<>"acoes")))*INDEX(Inputs!$K$5:$AJ$230,0,MATCH(S$2,Inputs!$K$4:$AJ$4,0)))+SUMPRODUCT((Inputs!$E$5:$E$230=$B7)*Inputs!$F$5:$F$230*(((Inputs!$G$5:$G$230="moeda")+(Inputs!$G$5:$G$230="acoes"))*Inputs!$B$1+((Inputs!$G$5:$G$230<>"moeda")*(Inputs!$G$5:$G$230<>"acoes")))*INDEX(Inputs!$K$5:$AJ$230,0,MATCH(S$2,Inputs!$K$4:$AJ$4,0))))) -> -42.888 | T7: =IF(ISNA(MATCH(T$2,Inputs!$K$4:$AJ$4,0)),NA(),IF(SUMPRODUCT((Inputs!$A$5:$A$230=$B7)*ISNUMBER(INDEX(Inputs!$K$5:$AJ$230,0,MATCH(T$2,Inputs!$K$4:$AJ$4,0))))+SUMPRODUCT((Inputs!$C$5:$C$230=$B7)*ISNUMBER(INDEX(Inputs!$K$5:$AJ$230,0,MATCH(T$2,Inputs!$K$4:$AJ$4,0))))+SUMPRODUCT((Inputs!$E$5:$E$230=$B7)*ISNUMBER(INDEX(Inputs!$K$5:$AJ$230,0,MATCH(T$2,Inputs!$K$4:$AJ$4,0))))=0,NA(),SUMPRODUCT((Inputs!$A$5:$A$230=$B7)*Inputs!$B$5:$B$230*(((Inputs!$G$5:$G$230="moeda")+(Inputs!$G$5:$G$230="acoes"))*Inputs!$B$1+((Inputs!$G$5:$G$230<>"moeda")*(Inputs!$G$5:$G$230<>"acoes")))*INDEX(Inputs!$K$5:$AJ$230,0,MATCH(T$2,Inputs!$K$4:$AJ$4,0)))+SUMPRODUCT((Inputs!$C$5:$C$230=$B7)*Inputs!$D$5:$D$230*(((Inputs!$G$5:$G$230="moeda")+(Inputs!$G$5:$G$230="acoes"))*Inputs!$B$1+((Inputs!$G$5:$G$230<>"moeda")*(Inputs!$G$5:$G$230<>"acoes")))*INDEX(Inputs!$K$5:$AJ$230,0,MATCH(T$2,Inputs!$K$4:$AJ$4,0)))+SUMPRODUCT((Inputs!$E$5:$E$230=$B7)*Inputs!$F$5:$F$230*(((Inputs!$G$5:$G$230="moeda")+(Inputs!$G$5:$G$230="acoes"))*Inputs!$B$1+((Inputs!$G$5:$G$230<>"moeda")*(Inputs!$G$5:$G$230<>"acoes")))*INDEX(Inputs!$K$5:$AJ$230,0,MATCH(T$2,Inputs!$K$4:$AJ$4,0))))) -> -43.985 | U7: =IF(ISNA(MATCH(U$2,Inputs!$K$4:$AJ$4,0)),NA(),IF(SUMPRODUCT((Inputs!$A$5:$A$230=$B7)*ISNUMBER(INDEX(Inputs!$K$5:$AJ$230,0,MATCH(U$2,Inputs!$K$4:$AJ$4,0))))+SUMPRODUCT((Inputs!$C$5:$C$230=$B7)*ISNUMBER(INDEX(Inputs!$K$5:$AJ$230,0,MATCH(U$2,Inputs!$K$4:$AJ$4,0))))+SUMPRODUCT((Inputs!$E$5:$E$230=$B7)*ISNUMBER(INDEX(Inputs!$K$5:$AJ$230,0,MATCH(U$2,Inputs!$K$4:$AJ$4,0))))=0,NA(),SUMPRODUCT((Inputs!$A$5:$A$230=$B7)*Inputs!$B$5:$B$230*(((Inputs!$G$5:$G$230="moeda")+(Inputs!$G$5:$G$230="acoes"))*Inputs!$B$1+((Inputs!$G$5:$G$230<>"moeda")*(Inputs!$G$5:$G$230<>"acoes")))*INDEX(Inputs!$K$5:$AJ$230,0,MATCH(U$2,Inputs!$K$4:$AJ$4,0)))+SUMPRODUCT((Inputs!$C$5:$C$230=$B7)*Inputs!$D$5:$D$230*(((Inputs!$G$5:$G$230="moeda")+(Inputs!$G$5:$G$230="acoes"))*Inputs!$B$1+((Inputs!$G$5:$G$230<>"moeda")*(Inputs!$G$5:$G$230<>"acoes")))*INDEX(Inputs!$K$5:$AJ$230,0,MATCH(U$2,Inputs!$K$4:$AJ$4,0)))+SUMPRODUCT((Inputs!$E$5:$E$230=$B7)*Inputs!$F$5:$F$230*(((Inputs!$G$5:$G$230="moeda")+(Inputs!$G$5:$G$230="acoes"))*Inputs!$B$1+((Inputs!$G$5:$G$230<>"moeda")*(Inputs!$G$5:$G$230<>"acoes")))*INDEX(Inputs!$K$5:$AJ$230,0,MATCH(U$2,Inputs!$K$4:$AJ$4,0))))) -> -45.859 | V7: =IF(ISNA(MATCH(V$2,Inputs!$K$4:$AJ$4,0)),NA(),IF(SUMPRODUCT((Inputs!$A$5:$A$230=$B7)*ISNUMBER(INDEX(Inputs!$K$5:$AJ$230,0,MATCH(V$2,Inputs!$K$4:$AJ$4,0))))+SUMPRODUCT((Inputs!$C$5:$C$230=$B7)*ISNUMBER(INDEX(Inputs!$K$5:$AJ$230,0,MATCH(V$2,Inputs!$K$4:$AJ$4,0))))+SUMPRODUCT((Inputs!$E$5:$E$230=$B7)*ISNUMBER(INDEX(Inputs!$K$5:$AJ$230,0,MATCH(V$2,Inputs!$K$4:$AJ$4,0))))=0,NA(),SUMPRODUCT((Inputs!$A$5:$A$230=$B7)*Inputs!$B$5:$B$230*(((Inputs!$G$5:$G$230="moeda")+(Inputs!$G$5:$G$230="acoes"))*Inputs!$B$1+((Inputs!$G$5:$G$230<>"moeda")*(Inputs!$G$5:$G$230<>"acoes")))*INDEX(Inputs!$K$5:$AJ$230,0,MATCH(V$2,Inputs!$K$4:$AJ$4,0)))+SUMPRODUCT((Inputs!$C$5:$C$230=$B7)*Inputs!$D$5:$D$230*(((Inputs!$G$5:$G$230="moeda")+(Inputs!$G$5:$G$230="acoes"))*Inputs!$B$1+((Inputs!$G$5:$G$230<>"moeda")*(Inputs!$G$5:$G$230<>"acoes")))*INDEX(Inputs!$K$5:$AJ$230,0,MATCH(V$2,Inputs!$K$4:$AJ$4,0)))+SUMPRODUCT((Inputs!$E$5:$E$230=$B7)*Inputs!$F$5:$F$230*(((Inputs!$G$5:$G$230="moeda")+(Inputs!$G$5:$G$230="acoes"))*Inputs!$B$1+((Inputs!$G$5:$G$230<>"moeda")*(Inputs!$G$5:$G$230<>"acoes")))*INDEX(Inputs!$K$5:$AJ$230,0,MATCH(V$2,Inputs!$K$4:$AJ$4,0))))) -> -45.423 | W7: =SUM(S7:V7) -> -178.155 | X7: =IF(ISNA(MATCH(X$2,Inputs!$K$4:$AJ$4,0)),NA(),IF(SUMPRODUCT((Inputs!$A$5:$A$230=$B7)*ISNUMBER(INDEX(Inputs!$K$5:$AJ$230,0,MATCH(X$2,Inputs!$K$4:$AJ$4,0))))+SUMPRODUCT((Inputs!$C$5:$C$230=$B7)*ISNUMBER(INDEX(Inputs!$K$5:$AJ$230,0,MATCH(X$2,Inputs!$K$4:$AJ$4,0))))+SUMPRODUCT((Inputs!$E$5:$E$230=$B7)*ISNUMBER(INDEX(Inputs!$K$5:$AJ$230,0,MATCH(X$2,Inputs!$K$4:$AJ$4,0))))=0,NA(),SUMPRODUCT((Inputs!$A$5:$A$230=$B7)*Inputs!$B$5:$B$230*(((Inputs!$G$5:$G$230="moeda")+(Inputs!$G$5:$G$230="acoes"))*Inputs!$B$1+((Inputs!$G$5:$G$230<>"moeda")*(Inputs!$G$5:$G$230<>"acoes")))*INDEX(Inputs!$K$5:$AJ$230,0,MATCH(X$2,Inputs!$K$4:$AJ$4,0)))+SUMPRODUCT((Inputs!$C$5:$C$230=$B7)*Inputs!$D$5:$D$230*(((Inputs!$G$5:$G$230="moeda")+(Inputs!$G$5:$G$230="acoes"))*Inputs!$B$1+((Inputs!$G$5:$G$230<>"moeda")*(Inputs!$G$5:$G$230<>"acoes")))*INDEX(Inputs!$K$5:$AJ$230,0,MATCH(X$2,Inputs!$K$4:$AJ$4,0)))+SUMPRODUCT((Inputs!$E$5:$E$230=$B7)*Inputs!$F$5:$F$230*(((Inputs!$G$5:$G$230="moeda")+(Inputs!$G$5:$G$230="acoes"))*Inputs!$B$1+((Inputs!$G$5:$G$230<>"moeda")*(Inputs!$G$5:$G$230<>"acoes")))*INDEX(Inputs!$K$5:$AJ$230,0,MATCH(X$2,Inputs!$K$4:$AJ$4,0))))) -> -41.263 | Y7: =IF(ISNA(MATCH(Y$2,Inputs!$K$4:$AJ$4,0)),NA(),IF(SUMPRODUCT((Inputs!$A$5:$A$230=$B7)*ISNUMBER(INDEX(Inputs!$K$5:$AJ$230,0,MATCH(Y$2,Inputs!$K$4:$AJ$4,0))))+SUMPRODUCT((Inputs!$C$5:$C$230=$B7)*ISNUMBER(INDEX(Inputs!$K$5:$AJ$230,0,MATCH(Y$2,Inputs!$K$4:$AJ$4,0))))+SUMPRODUCT((Inputs!$E$5:$E$230=$B7)*ISNUMBER(INDEX(Inputs!$K$5:$AJ$230,0,MATCH(Y$2,Inputs!$K$4:$AJ$4,0))))=0,NA(),SUMPRODUCT((Inputs!$A$5:$A$230=$B7)*Inputs!$B$5:$B$230*(((Inputs!$G$5:$G$230="moeda")+(Inputs!$G$5:$G$230="acoes"))*Inputs!$B$1+((Inputs!$G$5:$G$230<>"moeda")*(Inputs!$G$5:$G$230<>"acoes")))*INDEX(Inputs!$K$5:$AJ$230,0,MATCH(Y$2,Inputs!$K$4:$AJ$4,0)))+SUMPRODUCT((Inputs!$C$5:$C$230=$B7)*Inputs!$D$5:$D$230*(((Inputs!$G$5:$G$230="moeda")+(Inputs!$G$5:$G$230="acoes"))*Inputs!$B$1+((Inputs!$G$5:$G$230<>"moeda")*(Inputs!$G$5:$G$230<>"acoes")))*INDEX(Inputs!$K$5:$AJ$230,0,MATCH(Y$2,Inputs!$K$4:$AJ$4,0)))+SUMPRODUCT((Inputs!$E$5:$E$230=$B7)*Inputs!$F$5:$F$230*(((Inputs!$G$5:$G$230="moeda")+(Inputs!$G$5:$G$230="acoes"))*Inputs!$B$1+((Inputs!$G$5:$G$230<>"moeda")*(Inputs!$G$5:$G$230<>"acoes")))*INDEX(Inputs!$K$5:$AJ$230,0,MATCH(Y$2,Inputs!$K$4:$AJ$4,0))))) -> -45.418 | Z7: =IF(ISNA(MATCH(Z$2,Inputs!$K$4:$AJ$4,0)),NA(),IF(SUMPRODUCT((Inputs!$A$5:$A$230=$B7)*ISNUMBER(INDEX(Inputs!$K$5:$AJ$230,0,MATCH(Z$2,Inputs!$K$4:$AJ$4,0))))+SUMPRODUCT((Inputs!$C$5:$C$230=$B7)*ISNUMBER(INDEX(Inputs!$K$5:$AJ$230,0,MATCH(Z$2,Inputs!$K$4:$AJ$4,0))))+SUMPRODUCT((Inputs!$E$5:$E$230=$B7)*ISNUMBER(INDEX(Inputs!$K$5:$AJ$230,0,MATCH(Z$2,Inputs!$K$4:$AJ$4,0))))=0,NA(),SUMPRODUCT((Inputs!$A$5:$A$230=$B7)*Inputs!$B$5:$B$230*(((Inputs!$G$5:$G$230="moeda")+(Inputs!$G$5:$G$230="acoes"))*Inputs!$B$1+((Inputs!$G$5:$G$230<>"moeda")*(Inputs!$G$5:$G$230<>"acoes")))*INDEX(Inputs!$K$5:$AJ$230,0,MATCH(Z$2,Inputs!$K$4:$AJ$4,0)))+SUMPRODUCT((Inputs!$C$5:$C$230=$B7)*Inputs!$D$5:$D$230*(((Inputs!$G$5:$G$230="moeda")+(Inputs!$G$5:$G$230="acoes"))*Inputs!$B$1+((Inputs!$G$5:$G$230<>"moeda")*(Inputs!$G$5:$G$230<>"acoes")))*INDEX(Inputs!$K$5:$AJ$230,0,MATCH(Z$2,Inputs!$K$4:$AJ$4,0)))+SUMPRODUCT((Inputs!$E$5:$E$230=$B7)*Inputs!$F$5:$F$230*(((Inputs!$G$5:$G$230="moeda")+(Inputs!$G$5:$G$230="acoes"))*Inputs!$B$1+((Inputs!$G$5:$G$230<>"moeda")*(Inputs!$G$5:$G$230<>"acoes")))*INDEX(Inputs!$K$5:$AJ$230,0,MATCH(Z$2,Inputs!$K$4:$AJ$4,0))))) -> -47.651 | AA7: =IF(ISNA(MATCH(AA$2,Inputs!$K$4:$AJ$4,0)),NA(),IF(SUMPRODUCT((Inputs!$A$5:$A$230=$B7)*ISNUMBER(INDEX(Inputs!$K$5:$AJ$230,0,MATCH(AA$2,Inputs!$K$4:$AJ$4,0))))+SUMPRODUCT((Inputs!$C$5:$C$230=$B7)*ISNUMBER(INDEX(Inputs!$K$5:$AJ$230,0,MATCH(AA$2,Inputs!$K$4:$AJ$4,0))))+SUMPRODUCT((Inputs!$E$5:$E$230=$B7)*ISNUMBER(INDEX(Inputs!$K$5:$AJ$230,0,MATCH(AA$2,Inputs!$K$4:$AJ$4,0))))=0,NA(),SUMPRODUCT((Inputs!$A$5:$A$230=$B7)*Inputs!$B$5:$B$230*(((Inputs!$G$5:$G$230="moeda")+(Inputs!$G$5:$G$230="acoes"))*Inputs!$B$1+((Inputs!$G$5:$G$230<>"moeda")*(Inputs!$G$5:$G$230<>"acoes")))*INDEX(Inputs!$K$5:$AJ$230,0,MATCH(AA$2,Inputs!$K$4:$AJ$4,0)))+SUMPRODUCT((Inputs!$C$5:$C$230=$B7)*Inputs!$D$5:$D$230*(((Inputs!$G$5:$G$230="moeda")+(Inputs!$G$5:$G$230="acoes"))*Inputs!$B$1+((Inputs!$G$5:$G$230<>"moeda")*(Inputs!$G$5:$G$230<>"acoes")))*INDEX(Inputs!$K$5:$AJ$230,0,MATCH(AA$2,Inputs!$K$4:$AJ$4,0)))+SUMPRODUCT((Inputs!$E$5:$E$230=$B7)*Inputs!$F$5:$F$230*(((Inputs!$G$5:$G$230="moeda")+(Inputs!$G$5:$G$230="acoes"))*Inputs!$B$1+((Inputs!$G$5:$G$230<>"moeda")*(Inputs!$G$5:$G$230<>"acoes")))*INDEX(Inputs!$K$5:$AJ$230,0,MATCH(AA$2,Inputs!$K$4:$AJ$4,0))))) -> -51.46 | AB7: =SUM(X7:AA7) -> -185.792 | AC7: =IF(ISNA(MATCH(AC$2,Inputs!$K$4:$AJ$4,0)),NA(),IF(SUMPRODUCT((Inputs!$A$5:$A$230=$B7)*ISNUMBER(INDEX(Inputs!$K$5:$AJ$230,0,MATCH(AC$2,Inputs!$K$4:$AJ$4,0))))+SUMPRODUCT((Inputs!$C$5:$C$230=$B7)*ISNUMBER(INDEX(Inputs!$K$5:$AJ$230,0,MATCH(AC$2,Inputs!$K$4:$AJ$4,0))))+SUMPRODUCT((Inputs!$E$5:$E$230=$B7)*ISNUMBER(INDEX(Inputs!$K$5:$AJ$230,0,MATCH(AC$2,Inputs!$K$4:$AJ$4,0))))=0,NA(),SUMPRODUCT((Inputs!$A$5:$A$230=$B7)*Inputs!$B$5:$B$230*(((Inputs!$G$5:$G$230="moeda")+(Inputs!$G$5:$G$230="acoes"))*Inputs!$B$1+((Inputs!$G$5:$G$230<>"moeda")*(Inputs!$G$5:$G$230<>"acoes")))*INDEX(Inputs!$K$5:$AJ$230,0,MATCH(AC$2,Inputs!$K$4:$AJ$4,0)))+SUMPRODUCT((Inputs!$C$5:$C$230=$B7)*Inputs!$D$5:$D$230*(((Inputs!$G$5:$G$230="moeda")+(Inputs!$G$5:$G$230="acoes"))*Inputs!$B$1+((Inputs!$G$5:$G$230<>"moeda")*(Inputs!$G$5:$G$230<>"acoes")))*INDEX(Inputs!$K$5:$AJ$230,0,MATCH(AC$2,Inputs!$K$4:$AJ$4,0)))+SUMPRODUCT((Inputs!$E$5:$E$230=$B7)*Inputs!$F$5:$F$230*(((Inputs!$G$5:$G$230="moeda")+(Inputs!$G$5:$G$230="acoes"))*Inputs!$B$1+((Inputs!$G$5:$G$230<>"moeda")*(Inputs!$G$5:$G$230<>"acoes")))*INDEX(Inputs!$K$5:$AJ$230,0,MATCH(AC$2,Inputs!$K$4:$AJ$4,0))))) -> -56.114 | AD7: =IF(ISNA(MATCH(AD$2,Inputs!$K$4:$AJ$4,0)),NA(),IF(SUMPRODUCT((Inputs!$A$5:$A$230=$B7)*ISNUMBER(INDEX(Inputs!$K$5:$AJ$230,0,MATCH(AD$2,Inputs!$K$4:$AJ$4,0))))+SUMPRODUCT((Inputs!$C$5:$C$230=$B7)*ISNUMBER(INDEX(Inputs!$K$5:$AJ$230,0,MATCH(AD$2,Inputs!$K$4:$AJ$4,0))))+SUMPRODUCT((Inputs!$E$5:$E$230=$B7)*ISNUMBER(INDEX(Inputs!$K$5:$AJ$230,0,MATCH(AD$2,Inputs!$K$4:$AJ$4,0))))=0,NA(),SUMPRODUCT((Inputs!$A$5:$A$230=$B7)*Inputs!$B$5:$B$230*(((Inputs!$G$5:$G$230="moeda")+(Inputs!$G$5:$G$230="acoes"))*Inputs!$B$1+((Inputs!$G$5:$G$230<>"moeda")*(Inputs!$G$5:$G$230<>"acoes")))*INDEX(Inputs!$K$5:$AJ$230,0,MATCH(AD$2,Inputs!$K$4:$AJ$4,0)))+SUMPRODUCT((Inputs!$C$5:$C$230=$B7)*Inputs!$D$5:$D$230*(((Inputs!$G$5:$G$230="moeda")+(Inputs!$G$5:$G$230="acoes"))*Inputs!$B$1+((Inputs!$G$5:$G$230<>"moeda")*(Inputs!$G$5:$G$230<>"acoes")))*INDEX(Inputs!$K$5:$AJ$230,0,MATCH(AD$2,Inputs!$K$4:$AJ$4,0)))+SUMPRODUCT((Inputs!$E$5:$E$230=$B7)*Inputs!$F$5:$F$230*(((Inputs!$G$5:$G$230="moeda")+(Inputs!$G$5:$G$230="acoes"))*Inputs!$B$1+((Inputs!$G$5:$G$230<>"moeda")*(Inputs!$G$5:$G$230<>"acoes")))*INDEX(Inputs!$K$5:$AJ$230,0,MATCH(AD$2,Inputs!$K$4:$AJ$4,0))))) -> -51.589 | AE7: =IF(ISNA(MATCH(AE$2,Inputs!$K$4:$AJ$4,0)),NA(),IF(SUMPRODUCT((Inputs!$A$5:$A$230=$B7)*ISNUMBER(INDEX(Inputs!$K$5:$AJ$230,0,MATCH(AE$2,Inputs!$K$4:$AJ$4,0))))+SUMPRODUCT((Inputs!$C$5:$C$230=$B7)*ISNUMBER(INDEX(Inputs!$K$5:$AJ$230,0,MATCH(AE$2,Inputs!$K$4:$AJ$4,0))))+SUMPRODUCT((Inputs!$E$5:$E$230=$B7)*ISNUMBER(INDEX(Inputs!$K$5:$AJ$230,0,MATCH(AE$2,Inputs!$K$4:$AJ$4,0))))=0,NA(),SUMPRODUCT((Inputs!$A$5:$A$230=$B7)*Inputs!$B$5:$B$230*(((Inputs!$G$5:$G$230="moeda")+(Inputs!$G$5:$G$230="acoes"))*Inputs!$B$1+((Inputs!$G$5:$G$230<>"moeda")*(Inputs!$G$5:$G$230<>"acoes")))*INDEX(Inputs!$K$5:$AJ$230,0,MATCH(AE$2,Inputs!$K$4:$AJ$4,0)))+SUMPRODUCT((Inputs!$C$5:$C$230=$B7)*Inputs!$D$5:$D$230*(((Inputs!$G$5:$G$230="moeda")+(Inputs!$G$5:$G$230="acoes"))*Inputs!$B$1+((Inputs!$G$5:$G$230<>"moeda")*(Inputs!$G$5:$G$230<>"acoes")))*INDEX(Inputs!$K$5:$AJ$230,0,MATCH(AE$2,Inputs!$K$4:$AJ$4,0)))+SUMPRODUCT((Inputs!$E$5:$E$230=$B7)*Inputs!$F$5:$F$230*(((Inputs!$G$5:$G$230="moeda")+(Inputs!$G$5:$G$230="acoes"))*Inputs!$B$1+((Inputs!$G$5:$G$230<>"moeda")*(Inputs!$G$5:$G$230<>"acoes")))*INDEX(Inputs!$K$5:$AJ$230,0,MATCH(AE$2,Inputs!$K$4:$AJ$4,0))))) -> #N/A | AF7: =IF(ISNA(MATCH(AF$2,Inputs!$K$4:$AJ$4,0)),NA(),IF(SUMPRODUCT((Inputs!$A$5:$A$230=$B7)*ISNUMBER(INDEX(Inputs!$K$5:$AJ$230,0,MATCH(AF$2,Inputs!$K$4:$AJ$4,0))))+SUMPRODUCT((Inputs!$C$5:$C$230=$B7)*ISNUMBER(INDEX(Inputs!$K$5:$AJ$230,0,MATCH(AF$2,Inputs!$K$4:$AJ$4,0))))+SUMPRODUCT((Inputs!$E$5:$E$230=$B7)*ISNUMBER(INDEX(Inputs!$K$5:$AJ$230,0,MATCH(AF$2,Inputs!$K$4:$AJ$4,0))))=0,NA(),SUMPRODUCT((Inputs!$A$5:$A$230=$B7)*Inputs!$B$5:$B$230*(((Inputs!$G$5:$G$230="moeda")+(Inputs!$G$5:$G$230="acoes"))*Inputs!$B$1+((Inputs!$G$5:$G$230<>"moeda")*(Inputs!$G$5:$G$230<>"acoes")))*INDEX(Inputs!$K$5:$AJ$230,0,MATCH(AF$2,Inputs!$K$4:$AJ$4,0)))+SUMPRODUCT((Inputs!$C$5:$C$230=$B7)*Inputs!$D$5:$D$230*(((Inputs!$G$5:$G$230="moeda")+(Inputs!$G$5:$G$230="acoes"))*Inputs!$B$1+((Inputs!$G$5:$G$230<>"moeda")*(Inputs!$G$5:$G$230<>"acoes")))*INDEX(Inputs!$K$5:$AJ$230,0,MATCH(AF$2,Inputs!$K$4:$AJ$4,0)))+SUMPRODUCT((Inputs!$E$5:$E$230=$B7)*Inputs!$F$5:$F$230*(((Inputs!$G$5:$G$230="moeda")+(Inputs!$G$5:$G$230="acoes"))*Inputs!$B$1+((Inputs!$G$5:$G$230<>"moeda")*(Inputs!$G$5:$G$230<>"acoes")))*INDEX(Inputs!$K$5:$AJ$230,0,MATCH(AF$2,Inputs!$K$4:$AJ$4,0))))) -> #N/A | AG7: =SUM(AC7:AF7) -> #N/A | AH7: =IF(ISNA(MATCH(AH$2,Inputs!$K$4:$AJ$4,0)),NA(),IF(SUMPRODUCT((Inputs!$A$5:$A$230=$B7)*ISNUMBER(INDEX(Inputs!$K$5:$AJ$230,0,MATCH(AH$2,Inputs!$K$4:$AJ$4,0))))+SUMPRODUCT((Inputs!$C$5:$C$230=$B7)*ISNUMBER(INDEX(Inputs!$K$5:$AJ$230,0,MATCH(AH$2,Inputs!$K$4:$AJ$4,0))))+SUMPRODUCT((Inputs!$E$5:$E$230=$B7)*ISNUMBER(INDEX(Inputs!$K$5:$AJ$230,0,MATCH(AH$2,Inputs!$K$4:$AJ$4,0))))=0,NA(),SUMPRODUCT((Inputs!$A$5:$A$230=$B7)*Inputs!$B$5:$B$230*(((Inputs!$G$5:$G$230="moeda")+(Inputs!$G$5:$G$230="acoes"))*Inputs!$B$1+((Inputs!$G$5:$G$230<>"moeda")*(Inputs!$G$5:$G$230<>"acoes")))*INDEX(Inputs!$K$5:$AJ$230,0,MATCH(AH$2,Inputs!$K$4:$AJ$4,0)))+SUMPRODUCT((Inputs!$C$5:$C$230=$B7)*Inputs!$D$5:$D$230*(((Inputs!$G$5:$G$230="moeda")+(Inputs!$G$5:$G$230="acoes"))*Inputs!$B$1+((Inputs!$G$5:$G$230<>"moeda")*(Inputs!$G$5:$G$230<>"acoes")))*INDEX(Inputs!$K$5:$AJ$230,0,MATCH(AH$2,Inputs!$K$4:$AJ$4,0)))+SUMPRODUCT((Inputs!$E$5:$E$230=$B7)*Inputs!$F$5:$F$230*(((Inputs!$G$5:$G$230="moeda")+(Inputs!$G$5:$G$230="acoes"))*Inputs!$B$1+((Inputs!$G$5:$G$230<>"moeda")*(Inputs!$G$5:$G$230<>"acoes")))*INDEX(Inputs!$K$5:$AJ$230,0,MATCH(AH$2,Inputs!$K$4:$AJ$4,0))))) -> -27.964 | AI7: =IF(ISNA(MATCH(AI$2,Inputs!$K$4:$AJ$4,0)),NA(),IF(SUMPRODUCT((Inputs!$A$5:$A$230=$B7)*ISNUMBER(INDEX(Inputs!$K$5:$AJ$230,0,MATCH(AI$2,Inputs!$K$4:$AJ$4,0))))+SUMPRODUCT((Inputs!$C$5:$C$230=$B7)*ISNUMBER(INDEX(Inputs!$K$5:$AJ$230,0,MATCH(AI$2,Inputs!$K$4:$AJ$4,0))))+SUMPRODUCT((Inputs!$E$5:$E$230=$B7)*ISNUMBER(INDEX(Inputs!$K$5:$AJ$230,0,MATCH(AI$2,Inputs!$K$4:$AJ$4,0))))=0,NA(),SUMPRODUCT((Inputs!$A$5:$A$230=$B7)*Inputs!$B$5:$B$230*(((Inputs!$G$5:$G$230="moeda")+(Inputs!$G$5:$G$230="acoes"))*Inputs!$B$1+((Inputs!$G$5:$G$230<>"moeda")*(Inputs!$G$5:$G$230<>"acoes")))*INDEX(Inputs!$K$5:$AJ$230,0,MATCH(AI$2,Inputs!$K$4:$AJ$4,0)))+SUMPRODUCT((Inputs!$C$5:$C$230=$B7)*Inputs!$D$5:$D$230*(((Inputs!$G$5:$G$230="moeda")+(Inputs!$G$5:$G$230="acoes"))*Inputs!$B$1+((Inputs!$G$5:$G$230<>"moeda")*(Inputs!$G$5:$G$230<>"acoes")))*INDEX(Inputs!$K$5:$AJ$230,0,MATCH(AI$2,Inputs!$K$4:$AJ$4,0)))+SUMPRODUCT((Inputs!$E$5:$E$230=$B7)*Inputs!$F$5:$F$230*(((Inputs!$G$5:$G$230="moeda")+(Inputs!$G$5:$G$230="acoes"))*Inputs!$B$1+((Inputs!$G$5:$G$230<>"moeda")*(Inputs!$G$5:$G$230<>"acoes")))*INDEX(Inputs!$K$5:$AJ$230,0,MATCH(AI$2,Inputs!$K$4:$AJ$4,0))))) -> -49.987 | AJ7: =IF(ISNA(MATCH(AJ$2,Inputs!$K$4:$AJ$4,0)),NA(),IF(SUMPRODUCT((Inputs!$A$5:$A$230=$B7)*ISNUMBER(INDEX(Inputs!$K$5:$AJ$230,0,MATCH(AJ$2,Inputs!$K$4:$AJ$4,0))))+SUMPRODUCT((Inputs!$C$5:$C$230=$B7)*ISNUMBER(INDEX(Inputs!$K$5:$AJ$230,0,MATCH(AJ$2,Inputs!$K$4:$AJ$4,0))))+SUMPRODUCT((Inputs!$E$5:$E$230=$B7)*ISNUMBER(INDEX(Inputs!$K$5:$AJ$230,0,MATCH(AJ$2,Inputs!$K$4:$AJ$4,0))))=0,NA(),SUMPRODUCT((Inputs!$A$5:$A$230=$B7)*Inputs!$B$5:$B$230*(((Inputs!$G$5:$G$230="moeda")+(Inputs!$G$5:$G$230="acoes"))*Inputs!$B$1+((Inputs!$G$5:$G$230<>"moeda")*(Inputs!$G$5:$G$230<>"acoes")))*INDEX(Inputs!$K$5:$AJ$230,0,MATCH(AJ$2,Inputs!$K$4:$AJ$4,0)))+SUMPRODUCT((Inputs!$C$5:$C$230=$B7)*Inputs!$D$5:$D$230*(((Inputs!$G$5:$G$230="moeda")+(Inputs!$G$5:$G$230="acoes"))*Inputs!$B$1+((Inputs!$G$5:$G$230<>"moeda")*(Inputs!$G$5:$G$230<>"acoes")))*INDEX(Inputs!$K$5:$AJ$230,0,MATCH(AJ$2,Inputs!$K$4:$AJ$4,0)))+SUMPRODUCT((Inputs!$E$5:$E$230=$B7)*Inputs!$F$5:$F$230*(((Inputs!$G$5:$G$230="moeda")+(Inputs!$G$5:$G$230="acoes"))*Inputs!$B$1+((Inputs!$G$5:$G$230<>"moeda")*(Inputs!$G$5:$G$230<>"acoes")))*INDEX(Inputs!$K$5:$AJ$230,0,MATCH(AJ$2,Inputs!$K$4:$AJ$4,0))))) -> -28.455 | AK7: =IF(ISNA(MATCH(AK$2,Inputs!$K$4:$AJ$4,0)),NA(),IF(SUMPRODUCT((Inputs!$A$5:$A$230=$B7)*ISNUMBER(INDEX(Inputs!$K$5:$AJ$230,0,MATCH(AK$2,Inputs!$K$4:$AJ$4,0))))+SUMPRODUCT((Inputs!$C$5:$C$230=$B7)*ISNUMBER(INDEX(Inputs!$K$5:$AJ$230,0,MATCH(AK$2,Inputs!$K$4:$AJ$4,0))))+SUMPRODUCT((Inputs!$E$5:$E$230=$B7)*ISNUMBER(INDEX(Inputs!$K$5:$AJ$230,0,MATCH(AK$2,Inputs!$K$4:$AJ$4,0))))=0,NA(),SUMPRODUCT((Inputs!$A$5:$A$230=$B7)*Inputs!$B$5:$B$230*(((Inputs!$G$5:$G$230="moeda")+(Inputs!$G$5:$G$230="acoes"))*Inputs!$B$1+((Inputs!$G$5:$G$230<>"moeda")*(Inputs!$G$5:$G$230<>"acoes")))*INDEX(Inputs!$K$5:$AJ$230,0,MATCH(AK$2,Inputs!$K$4:$AJ$4,0)))+SUMPRODUCT((Inputs!$C$5:$C$230=$B7)*Inputs!$D$5:$D$230*(((Inputs!$G$5:$G$230="moeda")+(Inputs!$G$5:$G$230="acoes"))*Inputs!$B$1+((Inputs!$G$5:$G$230<>"moeda")*(Inputs!$G$5:$G$230<>"acoes")))*INDEX(Inputs!$K$5:$AJ$230,0,MATCH(AK$2,Inputs!$K$4:$AJ$4,0)))+SUMPRODUCT((Inputs!$E$5:$E$230=$B7)*Inputs!$F$5:$F$230*(((Inputs!$G$5:$G$230="moeda")+(Inputs!$G$5:$G$230="acoes"))*Inputs!$B$1+((Inputs!$G$5:$G$230<>"moeda")*(Inputs!$G$5:$G$230<>"acoes")))*INDEX(Inputs!$K$5:$AJ$230,0,MATCH(AK$2,Inputs!$K$4:$AJ$4,0))))) -> -28.779 | AL7: =SUM(AH7:AK7) -> -135.185
