Workbook
Name beta_observed: Valuation!$D$93
Name last_close: Valuation!$G$7
Name ticker: Valuation!$D$7
Name Useful_Life_of_Depreciable_PP_E: "PPElife"
Name beta_observed: #REF!
Name ticker: #REF!
Name costdebtfirm: Valuation!$D$86
Name costequity: Valuation!$D$94
Name debt: Valuation!$G$88
Name debt_weight: Valuation!$J$88
Name g: Valuation!$D$63
Name market_equity: Valuation!$G$89
Name noplat_t1: Valuation!$D$65
Name relevered_beta: Valuation!$M$102
Name risk_free_rate: Valuation!$D$91
Name risk_premium: Valuation!$D$92
Name ronic: Valuation!$D$64
Name stub_year_fraction: Valuation!$D$11
Name totalcap: Valuation!$G$90
Name wacc: Valuation!$D$12

Sheet Inputs
A1: Base histórica normalizada (R$ mil) — convertida da máscara anterior; linhas de origem auditáveis
A2: Fonte / conta original | B2: Código | C2: Conta padronizada | D2: 1Q21 | E2: 2Q21 | F2: 3Q21 | G2: 4Q21 | H2: 2021 | I2: 1Q22 | J2: 2Q22 | K2: 3Q22 | L2: 4Q22 | M2: 2022 | N2: 1Q23 | O2: 2Q23 | P2: 3Q23 | Q2: 4Q23 | R2: 2023 | S2: 1Q24 | T2: 2Q24 | U2: 3Q24 | V2: 4Q24 | W2: 2024 | X2: 1Q25 | Y2: 2Q25 | Z2: 3Q25 | AA2: 4Q25 | AB2: 2025 | AC2: 1Q26 | AD2: 2Q26 | AE2: 3Q26 | AF2: 4Q26 | AG2: 2026
A3: Fonte: ver coluna A de cada linha | C3: Unidade: R$ mil (monetário); demais unidades × 1.000
A4: DRE - TRIMESTRE ISOLADO (aba IS | DRE (w | com IFRS16), bloco Reportado, consolidado l.101-128; R$ milhoes). 1T23+ = CVM; 2020-22 = base pro forma da Cia | C4: [linha bruta, sem código; lançada nas linhas abaixo]
A5: Receita Líquida (DRE l.103) · fonte · unid. moeda | B5: 1 | C5: Net Revenues | D5: 757552 | E5: 1165345 | F5: 1521076 | G5: 1689065 | I5: 1905657 | J5: 2230992 | K5: 2536864 | L5: 2626633 | N5: 2703206 | O5: 2479144 | P5: 2666220 | Q5: 2493444 | S5: 3021646 | T5: 3435604 | U5: 3775864 | V5: 3248157 | X5: 3568231 | Y5: 3679006 | Z5: 3765843 | AA5: 3658975.2 | AC5: 3780645 | AD5: 3765830.2
A6: Custo Ex-depreciação (DRE l.106) · fonte · unid. moeda | B6: 2 | C6: COGS (cash) | D6: -296444 | E6: -605183 | F6: -729162 | G6: -699450 | I6: -822587 | J6: -1085046 | K6: -1337890 | L6: -1440095 | N6: -1511480 | O6: -1276679 | P6: -1479884 | Q6: -1260799 | S6: -1641800 | T6: -1943531 | U6: -2167358 | V6: -1632259 | X6: -1850291 | Y6: -1930489 | Z6: -1923128 | AA6: -1775877.8 | AC6: -1792954.8 | AD6: -1658145
A7: Depreciação (DRE l.107) (depreciacao frota + outros + direito de uso; devolvida abaixo via D&A) · fonte · unid. moeda | B7: 2 | C7: COGS (cash) | D7: -62178 | E7: -72936 | F7: -110706 | G7: -170431 | I7: -212836 | J7: -240909 | K7: -300524 | L7: -380942 | N7: -390033 | O7: -388955 | P7: -412766 | Q7: -906810 | S7: -447805 | T7: -522064 | U7: -551278 | V7: -559350 | X7: -572374 | Y7: -593733 | Z7: -624564 | AA7: -639359.24 | AC7: -650585.92 | AD7: -671563.62
A8: Despesa Ex-depreciação (DRE l.114) · fonte · unid. moeda | B8: 3 | C8: SG&A and Other (cash) | D8: -156605 | E8: -171698 | F8: -178506 | G8: -213003 | I8: -234631 | J8: -257540 | K8: -292522 | L8: -344544 | N8: -332775 | O8: -329942 | P8: -338551 | Q8: -366571 | S8: -320432 | T8: -315813 | U8: -356334 | V8: -371618 | X8: -379610 | Y8: -369393 | Z8: -364059 | AA8: -393047.09 | AC8: -419025.55 | AD8: -420941.57
A9: Depreciação Mais Valia (DRE l.115) (depreciacao de mais-valia) · fonte · unid. moeda | B9: 3 | C9: SG&A and Other (cash) | D9: 0 | E9: 0 | F9: 0 | G9: 0 | I9: 0 | J9: 0 | K9: 0 | L9: 0 | N9: 0 | O9: 0 | P9: 0 | Q9: -139114 | S9: 0 | T9: 0 | U9: 0 | V9: 0 | X9: 0 | Y9: 0 | Z9: 0 | AA9: 0 | AC9: 0 | AD9: 0
A10: Impairment de Depreciação (DRE l.116) (impairment de depreciacao) · fonte · unid. moeda | B10: 3 | C10: SG&A and Other (cash) | D10: 0 | E10: 0 | F10: 0 | G10: 0 | I10: 0 | J10: 0 | K10: 0 | L10: 0 | N10: 0 | O10: 0 | P10: 0 | Q10: 0 | S10: 0 | T10: -26900 | U10: -4696 | V10: 0 | X10: 0 | Y10: 0 | Z10: 0 | AA10: 0 | AC10: 0 | AD10: 0
A11: Despesas Financeiras (DRE l.124) · fonte · unid. moeda | B11: 5 | C11: Interest Expense | D11: -265184 | E11: 239899 | F11: -342257 | G11: -591177 | I11: -394958 | J11: -515803 | K11: -637391 | L11: -662277 | N11: -615278 | O11: -551559 | P11: -590177 | Q11: -614436 | S11: -627625 | T11: -662137 | U11: -707297 | V11: -691837 | X11: -745217 | Y11: -792778 | Z11: -895889 | AA11: -1154513.7 | AC11: -902577.86 | AD11: -1000770.5
A12: Receitas Financeiras (DRE l.125) · fonte · unid. moeda | B12: 6 | C12: Nonoperating Income / (Loss) | D12: 188526 | E12: -307323 | F12: 209511 | G12: 383039 | I12: 107671 | J12: 116444 | K12: 123724 | L12: 161251 | N12: 140596 | O12: 25985 | P12: 47438 | Q12: 59055 | S12: 88865 | T12: 91414 | U12: 112895 | V12: 85172 | X12: 90007 | Y12: 98699 | Z12: 100571 | AA12: 390591.91 | AC12: 148795.41 | AD12: 155135.69
A13: Receita Bruta (DRE l.101) - memoria · memoria · unid. moeda | C13: [linha bruta, sem código; lançada nas linhas abaixo] | D13: 824150 | E13: 1234303 | F13: 1605965 | G13: 1797894 | I13: 2023882 | J13: 2354247 | K13: 2680451 | L13: 2779739 | N13: 2871596 | O13: 2647105 | P13: 2846875 | Q13: 2686001 | S13: 3219943 | T13: 3657546 | U13: 4016702 | V13: 3493321 | X13: 3804719 | Y13: 3930928 | Z13: 4032922 | AA13: 3935855.8 | AC13: 4069234.1 | AD13: 4057515.4
A14: Deduções (DRE l.102) - memoria · memoria · unid. moeda | C14: [linha bruta, sem código; lançada nas linhas abaixo] | D14: -66598 | E14: -68958 | F14: -84889 | G14: -108829 | I14: -118225 | J14: -123255 | K14: -143587 | L14: -153106 | N14: -168390 | O14: -167961 | P14: -180655 | Q14: -192557 | S14: -198297 | T14: -221943 | U14: -240838 | V14: -245164 | X14: -236488 | Y14: -251923 | Z14: -267080 | AA14: -276880.61 | AC14: -288589.17 | AD14: -291685.23
A15: Receita Líquida de Serviços (DRE l.104) - memoria · memoria · unid. moeda | C15: [linha bruta, sem código; lançada nas linhas abaixo] | D15: 483011 | E15: 491865 | F15: 676455 | G15: 879950 | I15: 931895 | J15: 1002358 | K15: 1126436 | L15: 1222226 | N15: 1239742 | O15: 1233781 | P15: 1297318 | Q15: 1339621 | S15: 1495198 | T15: 1608087 | U15: 1744697 | V15: 1791057 | X15: 1878904 | Y15: 1892632 | Z15: 2010812 | AA15: 2096394.1 | AC15: 2205616.5 | AD15: 2295334.6
A16: Custo (DRE l.105) - memoria · memoria · unid. moeda | C16: [linha bruta, sem código; lançada nas linhas abaixo] | D16: -358623 | E16: -678119 | F16: -839868 | G16: -869881 | I16: -1020767 | J16: -1309105 | K16: -1619529 | L16: -1804787 | N16: -1885122 | O16: -1648165 | P16: -1872509 | Q16: -2167697 | S16: -2089568 | T16: -2465595 | U16: -2718636 | V16: -2191609 | X16: -2422665 | Y16: -2524222 | Z16: -2547692 | AA16: -2415237.1 | AC16: -2443540.8 | AD16: -2329708.7
A17: Lucro Bruto (DRE l.111) - memoria · memoria · unid. moeda | C17: [linha bruta, sem código; lançada nas linhas abaixo] | D17: 398929 | E17: 487226 | F17: 681208 | G17: 819185 | I17: 884890 | J17: 921888 | K17: 917335 | L17: 821846 | N17: 818084 | O17: 830979 | P17: 793711 | Q17: 325747 | S17: 932078 | T17: 970009 | U17: 1057228 | V17: 1056548 | X17: 1145565 | Y17: 1154784 | Z17: 1218150 | AA17: 1243738.1 | AC17: 1337104.2 | AD17: 1436121.5
A18: Despesas Administrativas (DRE l.113) - memoria · memoria · unid. moeda | C18: [linha bruta, sem código; lançada nas linhas abaixo] | D18: -156605 | E18: -171698 | F18: -178506 | G18: -213003 | I18: -234631 | J18: -257540 | K18: -292522 | L18: -344544 | N18: -332775 | O18: -329942 | P18: -338551 | Q18: -505686 | S18: -320432 | T18: -342713 | U18: -361030 | V18: -371618 | X18: -379610 | Y18: -369393 | Z18: -364059 | AA18: -393047.09 | AC18: -419025.55 | AD18: -420941.57
A19: EBITDA (DRE l.117) - memoria · memoria · unid. moeda | C19: [linha bruta, sem código; lançada nas linhas abaixo] | D19: 304502 | E19: 388464 | F19: 613408 | G19: 776612 | I19: 863095 | J19: 905256 | K19: 925337 | L19: 858243 | N19: 875342 | O19: 889992 | P19: 867926 | Q19: 866073 | S19: 1059500 | T19: 1149360 | U19: 1247476 | V19: 1244280 | X19: 1338329 | Y19: 1379123 | Z19: 1478656 | AA19: 1490050.3 | AC19: 1568664.6 | AD19: 1686743.6
A20: EBITDA de Serviços (DRE l.118) - memoria · memoria · unid. moeda | C20: [linha bruta, sem código; lançada nas linhas abaixo] | D20: 268221 | E20: 268356 | F20: 426207 | G20: 595052 | I20: 658624 | J20: 700022 | K20: 789148 | L20: 752650 | N20: 788955 | O20: 793534 | P20: 826475 | Q20: 829453 | S20: 1020779 | T20: 1124660 | U20: 1225769 | V20: 1227273 | X20: 1320160 | Y20: 1359482 | Z20: 1460057 | AA20: 1474816.2 | AC20: 1551287.2 | AD20: 1671048.1
A21: EBIT (DRE l.121) - memoria · memoria · unid. moeda | C21: [linha bruta, sem código; lançada nas linhas abaixo] | D21: 242324 | E21: 315528 | F21: 502702 | G21: 606181 | I21: 650259 | J21: 664347 | K21: 624813 | L21: 477301 | N21: 485309 | O21: 501037 | P21: 455160 | Q21: -179939 | S21: 611645 | T21: 627326 | U21: 696198 | V21: 684929 | X21: 765955 | Y21: 785390 | Z21: 854091 | AA21: 850691.02 | AC21: 918078.64 | AD21: 1015180
A22: Resultado Financeiro³ (DRE l.123) - memoria · memoria · unid. moeda | C22: [linha bruta, sem código; lançada nas linhas abaixo] | D22: -76658 | E22: -67424 | F22: -132746 | G22: -208138 | I22: -287287 | J22: -399359 | K22: -513667 | L22: -501027 | N22: -474682 | O22: -525574 | P22: -542739 | Q22: -555381 | S22: -538760 | T22: -570722 | U22: -594402 | V22: -606664 | X22: -655210 | Y22: -694079 | Z22: -795318 | AA22: -763921.74 | AC22: -753782.45 | AD22: -845634.83
A23: EBT (DRE l.126) - memoria · memoria · unid. moeda | C23: [linha bruta, sem código; lançada nas linhas abaixo] | D23: 165666 | E23: 248104 | F23: 369956 | G23: 398043 | I23: 362972 | J23: 264989 | K23: 111146 | L23: -23725 | N23: 10627 | O23: -24537 | P23: -87579 | Q23: -735320 | S23: 72886 | T23: 56604 | U23: 101796 | V23: 78265 | X23: 110745 | Y23: 91311 | Z23: 58774 | AA23: 86769.274 | AC23: 164296.19 | AD23: 169545.13
A24: Lucro Líquido (DRE l.128) - memoria · memoria · unid. moeda | C24: [linha bruta, sem código; lançada nas linhas abaixo] | D24: 109481 | E24: 173921 | F24: 259381 | G24: 276656 | I24: 258068 | J24: 186761 | K24: 93718 | L24: 17831 | N24: 21044 | O24: -17864 | P24: -65721 | Q24: -588309 | S24: 48599 | T24: 42548 | U24: 78194 | V24: 62171 | X24: 78468 | Y24: 67595 | Z24: 69955 | AA24: 102344.11 | AC24: 124513.19 | AD24: 135649.66
A25: DERIVADAS (formula nesta aba) | C25: [linha bruta, sem código; lançada nas linhas abaixo]
A26: Residuo do custo: EBT - (receita + custo ex-dep + depreciacao + despesas + desp. e rec. financeiras). Fecha o lucro bruto/EBT divulgados (1T22-3T23 ~15-20 = outros custos; 1T20 +195,4 e 4T20 -50,1 = base pro forma; demais = arredondamento) · derivada · unid. moeda | B26: 2 | C26: COGS (cash) | D26: =D23-D5-D6-D7-D8-D9-D10-D11-D12 -> -1 | E26: =E23-E5-E6-E7-E8-E9-E10-E11-E12 -> 0 | F26: =F23-F5-F6-F7-F8-F9-F10-F11-F12 -> 0 | G26: =G23-G5-G6-G7-G8-G9-G10-G11-G12 -> 0 | I26: =I23-I5-I6-I7-I8-I9-I10-I11-I12 -> 14656 | J26: =J23-J5-J6-J7-J8-J9-J10-J11-J12 -> 16851 | K26: =K23-K5-K6-K7-K8-K9-K10-K11-K12 -> 18885 | L26: =L23-L5-L6-L7-L8-L9-L10-L11-L12 -> 16249 | N26: =N23-N5-N6-N7-N8-N9-N10-N11-N12 -> 16391 | O26: =O23-O5-O6-O7-O8-O9-O10-O11-O12 -> 17469 | P26: =P23-P5-P6-P7-P8-P9-P10-P11-P12 -> 20141 | Q26: =Q23-Q5-Q6-Q7-Q8-Q9-Q10-Q11-Q12 -> -89 | S26: =S23-S5-S6-S7-S8-S9-S10-S11-S12 -> 37 | T26: =T23-T5-T6-T7-T8-T9-T10-T11-T12 -> 31 | U26: =U23-U5-U6-U7-U8-U9-U10-U11-U12 -> 0 | V26: =V23-V5-V6-V7-V8-V9-V10-V11-V12 -> 0 | X26: =X23-X5-X6-X7-X8-X9-X10-X11-X12 -> -1 | Y26: =Y23-Y5-Y6-Y7-Y8-Y9-Y10-Y11-Y12 -> -1 | Z26: =Z23-Z5-Z6-Z7-Z8-Z9-Z10-Z11-Z12 -> 0 | AA26: =AA23-AA5-AA6-AA7-AA8-AA9-AA10-AA11-AA12 -> 0 | AC26: =AC23-AC5-AC6-AC7-AC8-AC9-AC10-AC11-AC12 -> 0 | AD26: =AD23-AD5-AD6-AD7-AD8-AD9-AD10-AD11-AD12 -> 0
A27: IR/CS = lucro liquido - EBT (a planilha nao abre a linha de IR) · derivada · unid. moeda | B27: 7 | C27: Taxes | D27: =D24-D23 -> -56185 | E27: =E24-E23 -> -74183 | F27: =F24-F23 -> -110575 | G27: =G24-G23 -> -121387 | I27: =I24-I23 -> -104904 | J27: =J24-J23 -> -78228 | K27: =K24-K23 -> -17428 | L27: =L24-L23 -> 41556 | N27: =N24-N23 -> 10417 | O27: =O24-O23 -> 6673 | P27: =P24-P23 -> 21858 | Q27: =Q24-Q23 -> 147011 | S27: =S24-S23 -> -24287 | T27: =T24-T23 -> -14056 | U27: =U24-U23 -> -23602 | V27: =V24-V23 -> -16094 | X27: =X24-X23 -> -32277 | Y27: =Y24-Y23 -> -23716 | Z27: =Z24-Z23 -> 11181 | AA27: =AA24-AA23 -> 15574.833 | AC27: =AC24-AC23 -> -39782.999 | AD27: =AD24-AD23 -> -33895.472
A28: D&A = EBIT - EBITDA (negativo): COD1=4 lanca; COD2=2 devolve ao custo (quase toda depreciacao e de frota). EBITDA do Model = EBITDA divulgado · derivada · unid. moeda | C28: [linha bruta, sem código; lançada nas linhas abaixo] | D28: =D21-D19 -> -62178 | E28: =E21-E19 -> -72936 | F28: =F21-F19 -> -110706 | G28: =G21-G19 -> -170431 | I28: =I21-I19 -> -212836 | J28: =J21-J19 -> -240909 | K28: =K21-K19 -> -300524 | L28: =L21-L19 -> -380942 | N28: =N21-N19 -> -390033 | O28: =O21-O19 -> -388955 | P28: =P21-P19 -> -412766 | Q28: =Q21-Q19 -> -1046012 | S28: =S21-S19 -> -447855 | T28: =T21-T19 -> -522034 | U28: =U21-U19 -> -551278 | V28: =V21-V19 -> -559351 | X28: =X21-X19 -> -572374 | Y28: =Y21-Y19 -> -593733 | Z28: =Z21-Z19 -> -624565 | AA28: =AA21-AA19 -> -639359.24 | AC28: =AC21-AC19 -> -650585.92 | AD28: =AD21-AD19 -> -671563.62
A29: (lançamento) código 4, sinal +1 sobre a linha bruta 28: D&A = EBIT - EBITDA (negativo): COD1=4 lanca; COD2=2 devolve ao custo (quase toda deprecia | B29: 4 | C29: D&A | D29: =IF(D28="","",D28) -> -62178 | E29: =IF(E28="","",E28) -> -72936 | F29: =IF(F28="","",F28) -> -110706 | G29: =IF(G28="","",G28) -> -170431 | I29: =IF(I28="","",I28) -> -212836 | J29: =IF(J28="","",J28) -> -240909 | K29: =IF(K28="","",K28) -> -300524 | L29: =IF(L28="","",L28) -> -380942 | N29: =IF(N28="","",N28) -> -390033 | O29: =IF(O28="","",O28) -> -388955 | P29: =IF(P28="","",P28) -> -412766 | Q29: =IF(Q28="","",Q28) -> -1046012 | S29: =IF(S28="","",S28) -> -447855 | T29: =IF(T28="","",T28) -> -522034 | U29: =IF(U28="","",U28) -> -551278 | V29: =IF(V28="","",V28) -> -559351 | X29: =IF(X28="","",X28) -> -572374 | Y29: =IF(Y28="","",Y28) -> -593733 | Z29: =IF(Z28="","",Z28) -> -624565 | AA29: =IF(AA28="","",AA28) -> -639359.24 | AC29: =IF(AC28="","",AC28) -> -650585.92 | AD29: =IF(AD28="","",AD28) -> -671563.62
A30: (lançamento) código 2, sinal -1 sobre a linha bruta 28: D&A = EBIT - EBITDA (negativo): COD1=4 lanca; COD2=2 devolve ao custo (quase toda deprecia | B30: 2 | C30: COGS (cash) | D30: =IF(D28="","",-1*D28) -> 62178 | E30: =IF(E28="","",-1*E28) -> 72936 | F30: =IF(F28="","",-1*F28) -> 110706 | G30: =IF(G28="","",-1*G28) -> 170431 | I30: =IF(I28="","",-1*I28) -> 212836 | J30: =IF(J28="","",-1*J28) -> 240909 | K30: =IF(K28="","",-1*K28) -> 300524 | L30: =IF(L28="","",-1*L28) -> 380942 | N30: =IF(N28="","",-1*N28) -> 390033 | O30: =IF(O28="","",-1*O28) -> 388955 | P30: =IF(P28="","",-1*P28) -> 412766 | Q30: =IF(Q28="","",-1*Q28) -> 1046012 | S30: =IF(S28="","",-1*S28) -> 447855 | T30: =IF(T28="","",-1*T28) -> 522034 | U30: =IF(U28="","",-1*U28) -> 551278 | V30: =IF(V28="","",-1*V28) -> 559351 | X30: =IF(X28="","",-1*X28) -> 572374 | Y30: =IF(Y28="","",-1*Y28) -> 593733 | Z30: =IF(Z28="","",-1*Z28) -> 624565 | AA30: =IF(AA28="","",-1*AA28) -> 639359.24 | AC30: =IF(AC28="","",-1*AC28) -> 650585.92 | AD30: =IF(AD28="","",-1*AD28) -> 671563.62
A31: Lucro liquido (l.128; sem minoritarios) - COD 44 alimenta o check IS do Model · derivada · unid. moeda | B31: 44 | C31: Lucro liquido (l.128; sem minoritarios) - COD 44 alimenta o | D31: =D24 -> 109481 | E31: =E24 -> 173921 | F31: =F24 -> 259381 | G31: =G24 -> 276656 | I31: =I24 -> 258068 | J31: =J24 -> 186761 | K31: =K24 -> 93718 | L31: =L24 -> 17831 | N31: =N24 -> 21044 | O31: =O24 -> -17864 | P31: =P24 -> -65721 | Q31: =Q24 -> -588309 | S31: =S24 -> 48599 | T31: =T24 -> 42548 | U31: =U24 -> 78194 | V31: =V24 -> 62171 | X31: =X24 -> 78468 | Y31: =Y24 -> 67595 | Z31: =Z24 -> 69955 | AA31: =AA24 -> 102344.11 | AC31: =AC24 -> 124513.19 | AD31: =AD24 -> 135649.66
A32: DFC - ACUMULADO NO ANO (R$ milhoes): Dividendos e JCP pagos, DFC consolidada dos ITR/DFP na CVM (contas 6.03.xx "Dividendos..."). A planilha da Cia nao traz DFC | C32: [linha bruta, sem código; lançada nas linhas abaixo]
A33: Dividendos e JCP pagos - acumulado no ano (CVM; soma das contas 6.03 de dividendos/JCP) · memoria · unid. moeda | C33: [linha bruta, sem código; lançada nas linhas abaixo] | D33: 0 | E33: 0 | F33: -64133 | G33: -106614 | I33: -39311 | J33: -348658 | K33: -395507 | L33: -447638 | N33: -47512 | O33: -138201 | P33: -138200 | Q33: -138200 | S33: 0 | T33: 0 | U33: 0 | V33: 0 | X33: 0 | Y33: -55050 | Z33: -55050 | AA33: -55050 | AC33: 0 | AD33: 0
A34: Dividendos e JCP pagos (trimestralizado) · derivada · unid. moeda | B34: 10 | C34: Common Dividends | D34: =N(D33) -> 0 | E34: =N(E33)-N(D33) -> 0 | F34: =N(F33)-N(E33) -> -64133 | G34: =N(G33)-N(F33) -> -42481 | I34: =N(I33) -> -39311 | J34: =N(J33)-N(I33) -> -309347 | K34: =N(K33)-N(J33) -> -46849 | L34: =N(L33)-N(K33) -> -52131 | N34: =N(N33) -> -47512 | O34: =N(O33)-N(N33) -> -90689 | P34: =N(P33)-N(O33) -> 1 | Q34: =N(Q33)-N(P33) -> 0 | S34: =N(S33) -> 0 | T34: =N(T33)-N(S33) -> 0 | U34: =N(U33)-N(T33) -> 0 | V34: =N(V33)-N(U33) -> 0 | X34: =N(X33) -> 0 | Y34: =N(Y33)-N(X33) -> -55050 | Z34: =N(Z33)-N(Y33) -> 0 | AA34: =N(AA33)-N(Z33) -> 0 | AC34: =N(AC33) -> 0 | AD34: =N(AD33)-N(AC33) -> 0
A35: BALANCO (aba BS | BP (Proforma); R$ milhoes). TVM de longo prazo vai para caixa (cod 11), como no calculo de divida liquida da Cia | C35: [linha bruta, sem código; lançada nas linhas abaixo]
A36: A: Caixa e equivalentes de caixa (BP l.6) · fonte · unid. moeda | B36: 11 | C36: Cash and equivalents (inc. investment securities) | D36: 886551 | E36: 2816548 | F36: 4643996 | G36: 146030 | I36: 903521 | J36: 950708 | K36: 401837 | L36: 551764 | N36: 486982 | O36: 487375 | P36: 356841 | Q36: 133394 | S36: 475274 | T36: 674841 | U36: 568043 | V36: 677895 | X36: 847108 | Y36: 1002896 | Z36: 1671176 | AA36: 1322044 | AC36: 1830668 | AD36: 1648914
A37: A: Títulos, valores mobiliários e aplicações financeiras (BP l.7) -> caixa · fonte · unid. moeda | B37: 11 | C37: Cash and equivalents (inc. investment securities) | D37: 2095684 | E37: 2740207 | F37: 3630317 | G37: 7640423 | I37: 4747063 | J37: 4771989 | K37: 7393620 | L37: 6275771 | N37: 3436117 | O37: 2090491 | P37: 1654286 | Q37: 2865358 | S37: 2736012 | T37: 3010162 | U37: 3407676 | V37: 3613468 | X37: 2190087 | Y37: 2436181 | Z37: 1645729 | AA37: 2799536 | AC37: 3650208 | AD37: 1815879
A38: A: Títulos, valores mobiliários e aplicações financeiras (BP l.19) (LP) -> caixa · fonte · unid. moeda | B38: 11 | C38: Cash and equivalents (inc. investment securities) | D38: 2529645 | E38: 0 | F38: 0 | G38: 0 | I38: 0 | J38: 0 | K38: 0 | L38: 0 | N38: 0 | O38: 0 | P38: 0 | Q38: 0 | S38: 0 | T38: 0 | U38: 0 | V38: 0 | X38: 0 | Y38: 2563 | Z38: 2584 | AA38: 2753815 | AC38: 2612312 | AD38: 4014504
A39: A: Instrumentos financeiros derivativos (BP l.8) · fonte · unid. moeda | B39: 22 | C39: Other non-current assets | D39: 0 | E39: 0 | F39: 0 | G39: 0 | I39: 0 | J39: 0 | K39: 0 | L39: 0 | N39: 0 | O39: 0 | P39: 0 | Q39: 0 | S39: 0 | T39: 0 | U39: 0 | V39: 0 | X39: 0 | Y39: 0 | Z39: 0 | AA39: 0 | AC39: 0 | AD39: 31224
A40: A: Contas a receber (BP l.9) · fonte · unid. moeda | B40: 12 | C40: Accounts receivable | D40: 447114 | E40: 550855 | F40: 631554 | G40: 879885 | I40: 1075725 | J40: 1284046 | K40: 1044110 | L40: 1173855 | N40: 1024973 | O40: 1099135 | P40: 1309929 | Q40: 1343672 | S40: 1541190 | T40: 1684002 | U40: 1736952 | V40: 1441650 | X40: 2183360 | Y40: 2175461 | Z40: 2216498 | AA40: 1989613 | AC40: 2172228 | AD40: 2293273
A41: A: Contas a receber (BP l.21) · fonte · unid. moeda | B41: 12 | C41: Accounts receivable | D41: 3266 | E41: 2840 | F41: 2809 | G41: 7182 | I41: 2110 | J41: 1859 | K41: 1938 | L41: 1879 | N41: 2037 | O41: 1834 | P41: 2373 | Q41: 1741 | S41: 1460 | T41: 29 | U41: 32 | V41: 46 | X41: 9953 | Y41: 10727 | Z41: 51 | AA41: 68 | AC41: 12356 | AD41: 16601
A42: A: Veículos desativados para renovação de frota (BP l.10) (veiculos desativados p/ renovacao = seminovos a venda) · fonte · unid. moeda | B42: 16 | C42: Other current assets | D42: 186615 | E42: 299967 | F42: 335630 | G42: 306031 | I42: 611185 | J42: 636848 | K42: 922505 | L42: 1195478 | N42: 923841 | O42: 782096 | P42: 854867 | Q42: 617403 | S42: 945733 | T42: 858674 | U42: 840300 | V42: 705821 | X42: 1224313 | Y42: 1187739 | Z42: 988590 | AA42: 380837 | AC42: 607159 | AD42: 669663
A43: A: Tributos a recuperar (BP l.11) · fonte · unid. moeda | B43: 16 | C43: Other current assets | D43: 15830 | E43: 17706 | F43: 24078 | G43: 34531 | I43: 92999 | J43: 182980 | K43: 230581 | L43: 22581 | N43: 43777 | O43: 85860 | P43: 121809 | Q43: 157114 | S43: 164223 | T43: 146941 | U43: 194015 | V43: 156839 | X43: 150765 | Y43: 172111 | Z43: 173186 | AA43: 179030 | AC43: 172240 | AD43: 161870
A44: A: Imposto de renda e contribuição social antecipados (BP l.12) · fonte · unid. moeda | B44: 16 | C44: Other current assets | D44: 55244 | E44: 49659 | F44: 71745 | G44: 74712 | I44: 87563 | J44: 106897 | K44: 126995 | L44: 151503 | N44: 141010 | O44: 170638 | P44: 207206 | Q44: 228626 | S44: 226421 | T44: 208491 | U44: 171478 | V44: 243243 | X44: 262550 | Y44: 333338 | Z44: 325527 | AA44: 205498 | AC44: 224054 | AD44: 257089
A45: A: Partes Relacionadas (BP l.13) · fonte · unid. moeda | B45: 16 | C45: Other current assets | D45: 0 | E45: 0 | F45: 0 | G45: 0 | I45: 0 | J45: 4749 | K45: 0 | L45: 0 | N45: 0 | O45: 0 | P45: 0 | Q45: 0 | S45: 0 | T45: 0 | U45: 0 | V45: 4961 | X45: 0 | Y45: 0 | Z45: 0 | AA45: 621 | AC45: 8253 | AD45: 2522
A46: A: Outros créditos e adiantamentos (BP l.14) · fonte · unid. moeda | B46: 16 | C46: Other current assets | D46: 79816 | E46: 65377 | F46: 78356 | G46: 65346 | I46: 165952 | J46: 155560 | K46: 112154 | L46: 69313 | N46: 264915 | O46: 261563 | P46: 241557 | Q46: 83758 | S46: 238757 | T46: 283737 | U46: 211209 | V46: 106997 | X46: 394875 | Y46: 307345 | Z46: 239825 | AA46: 176165 | AC46: 393081 | AD46: 303444
A47: A: Instrumentos financeiros derivativos (BP l.20) · fonte · unid. moeda | B47: 22 | C47: Other non-current assets | D47: 59057 | E47: 37708 | F47: 41686 | G47: 38781 | I47: 35660 | J47: 33572 | K47: 128624 | L47: 85439 | N47: 33296 | O47: 56445 | P47: 2145 | Q47: 2440 | S47: 0 | T47: 467871 | U47: 484887 | V47: 1032263 | X47: 643506 | Y47: 0 | Z47: 0 | AA47: 14300 | AC47: 25256 | AD47: 7299
... A94: A: Estoques - sem linha na planilha (zeros; seminovos a venda estao em veiculos desativados, cod 16). Linha existe para o Model projetar estoque = 0 · derivada · unid. moeda | B94: 13 | C94: Inventories | D94: 0 | E94: 0 | F94: 0 | G94: 0 | I94: 0 | J94: 0 | K94: 0 | L94: 0 | N94: 0 | O94: 0 | P94: 0 | Q94: 0 | S94: 0 | T94: 0 | U94: 0 | V94: 0 | X94: 0 | Y94: 0 | Z94: 0 | AA94: 0 | AC94: 0 | AD94: 0
A95: BALANCO - totais divulgados (memoria) | C95: [linha bruta, sem código; lançada nas linhas abaixo]
A96: Total do ativo (l.37) · memoria · unid. moeda | C96: [linha bruta, sem código; lançada nas linhas abaixo] | D96: 13041956 | E96: 14204671 | F96: 19735813 | G96: 21715853 | I96: 20955436 | J96: 23372858 | K96: 26410242 | L96: 26248893 | N96: 22682051 | O96: 21069958 | P96: 21734567 | Q96: 25119493 | S96: 26185588 | T96: 27684239 | U96: 28574186 | V96: 30573857 | X96: 29211368 | Y96: 29775568 | Z96: 29641564 | AA96: 34925259 | AC96: 35936374 | AD96: 37340960
A97: Total do passivo e PL (l.89) · memoria · unid. moeda | C97: [linha bruta, sem código; lançada nas linhas abaixo] | D97: 13041956 | E97: 14204671 | F97: 19735813 | G97: 21715853 | I97: 20955436 | J97: 23372858 | K97: 26410241 | L97: 26248890 | N97: 22682051 | O97: 21069958 | P97: 21734564 | Q97: 25119490 | S97: 26185588 | T97: 27684239 | U97: 28574186 | V97: 30573857 | X97: 29211368 | Y97: 29775568 | Z97: 29641564 | AA97: 34925260 | AC97: 35936374 | AD97: 37340960
A98: Total do PL (l.87) · memoria · unid. moeda | C98: [linha bruta, sem código; lançada nas linhas abaixo] | D98: 2349551 | E98: 2558846 | F98: 3178125 | G98: 3284472 | I98: 3241286 | J98: 2854538 | K98: 2777078 | L98: 2768684 | N98: 2830875 | O98: 3072099 | P98: 3027688 | Q98: 2522134 | S98: 2513818 | T98: 2503186 | U98: 2658220 | V98: 2492492 | X98: 2607676 | Y98: 2648975 | Z98: 2788634 | AA98: 2967804 | AC98: 3056661 | AD98: 3901507
A99: CHECKS (devem ser 0) | C99: [linha bruta, sem código; lançada nas linhas abaixo]
A100: CHECK: receita + custos + residuo + despesas + resultado financeiro + IR - lucro liquido · derivada · unid. moeda | C100: [linha bruta, sem código; lançada nas linhas abaixo] | D100: =ROUND(D5+D6+D7+D8+D9+D10+D11+D12+D26+D27-D31,1) -> 0 | E100: =ROUND(E5+E6+E7+E8+E9+E10+E11+E12+E26+E27-E31,1) -> 0 | F100: =ROUND(F5+F6+F7+F8+F9+F10+F11+F12+F26+F27-F31,1) -> 0 | G100: =ROUND(G5+G6+G7+G8+G9+G10+G11+G12+G26+G27-G31,1) -> 0 | I100: =ROUND(I5+I6+I7+I8+I9+I10+I11+I12+I26+I27-I31,1) -> 0 | J100: =ROUND(J5+J6+J7+J8+J9+J10+J11+J12+J26+J27-J31,1) -> 0 | K100: =ROUND(K5+K6+K7+K8+K9+K10+K11+K12+K26+K27-K31,1) -> 0 | L100: =ROUND(L5+L6+L7+L8+L9+L10+L11+L12+L26+L27-L31,1) -> 0 | N100: =ROUND(N5+N6+N7+N8+N9+N10+N11+N12+N26+N27-N31,1) -> 0 | O100: =ROUND(O5+O6+O7+O8+O9+O10+O11+O12+O26+O27-O31,1) -> 0 | P100: =ROUND(P5+P6+P7+P8+P9+P10+P11+P12+P26+P27-P31,1) -> 0 | Q100: =ROUND(Q5+Q6+Q7+Q8+Q9+Q10+Q11+Q12+Q26+Q27-Q31,1) -> 0 | S100: =ROUND(S5+S6+S7+S8+S9+S10+S11+S12+S26+S27-S31,1) -> 0 | T100: =ROUND(T5+T6+T7+T8+T9+T10+T11+T12+T26+T27-T31,1) -> 0 | U100: =ROUND(U5+U6+U7+U8+U9+U10+U11+U12+U26+U27-U31,1) -> 0 | V100: =ROUND(V5+V6+V7+V8+V9+V10+V11+V12+V26+V27-V31,1) -> 0 | X100: =ROUND(X5+X6+X7+X8+X9+X10+X11+X12+X26+X27-X31,1) -> 0 | Y100: =ROUND(Y5+Y6+Y7+Y8+Y9+Y10+Y11+Y12+Y26+Y27-Y31,1) -> 0 | Z100: =ROUND(Z5+Z6+Z7+Z8+Z9+Z10+Z11+Z12+Z26+Z27-Z31,1) -> 0 | AA100: =ROUND(AA5+AA6+AA7+AA8+AA9+AA10+AA11+AA12+AA26+AA27-AA31,1) -> 0 | AC100: =ROUND(AC5+AC6+AC7+AC8+AC9+AC10+AC11+AC12+AC26+AC27-AC31,1) -> 0 | AD100: =ROUND(AD5+AD6+AD7+AD8+AD9+AD10+AD11+AD12+AD26+AD27-AD31,1) -> 0
A101: CHECK: contas de ativo - ativo total · derivada · unid. moeda | C101: [linha bruta, sem código; lançada nas linhas abaixo] | D101: =ROUND(D36+D37+D38+D39+D40+D41+D42+D43+D44+D45+D46+D47+D48+D49+D50+D51+D52+D53+D54+D55+D56+D57-D96,1) -> 0 | E101: =ROUND(E36+E37+E38+E39+E40+E41+E42+E43+E44+E45+E46+E47+E48+E49+E50+E51+E52+E53+E54+E55+E56+E57-E96,1) -> 0 | F101: =ROUND(F36+F37+F38+F39+F40+F41+F42+F43+F44+F45+F46+F47+F48+F49+F50+F51+F52+F53+F54+F55+F56+F57-F96,1) -> 0 | G101: =ROUND(G36+G37+G38+G39+G40+G41+G42+G43+G44+G45+G46+G47+G48+G49+G50+G51+G52+G53+G54+G55+G56+G57-G96,1) -> 0 | I101: =ROUND(I36+I37+I38+I39+I40+I41+I42+I43+I44+I45+I46+I47+I48+I49+I50+I51+I52+I53+I54+I55+I56+I57-I96,1) -> 0 | J101: =ROUND(J36+J37+J38+J39+J40+J41+J42+J43+J44+J45+J46+J47+J48+J49+J50+J51+J52+J53+J54+J55+J56+J57-J96,1) -> 0 | K101: =ROUND(K36+K37+K38+K39+K40+K41+K42+K43+K44+K45+K46+K47+K48+K49+K50+K51+K52+K53+K54+K55+K56+K57-K96,1) -> 0 | L101: =ROUND(L36+L37+L38+L39+L40+L41+L42+L43+L44+L45+L46+L47+L48+L49+L50+L51+L52+L53+L54+L55+L56+L57-L96,1) -> 0 | N101: =ROUND(N36+N37+N38+N39+N40+N41+N42+N43+N44+N45+N46+N47+N48+N49+N50+N51+N52+N53+N54+N55+N56+N57-N96,1) -> 0 | O101: =ROUND(O36+O37+O38+O39+O40+O41+O42+O43+O44+O45+O46+O47+O48+O49+O50+O51+O52+O53+O54+O55+O56+O57-O96,1) -> 0 | P101: =ROUND(P36+P37+P38+P39+P40+P41+P42+P43+P44+P45+P46+P47+P48+P49+P50+P51+P52+P53+P54+P55+P56+P57-P96,1) -> 0 | Q101: =ROUND(Q36+Q37+Q38+Q39+Q40+Q41+Q42+Q43+Q44+Q45+Q46+Q47+Q48+Q49+Q50+Q51+Q52+Q53+Q54+Q55+Q56+Q57-Q96,1) -> 0 | S101: =ROUND(S36+S37+S38+S39+S40+S41+S42+S43+S44+S45+S46+S47+S48+S49+S50+S51+S52+S53+S54+S55+S56+S57-S96,1) -> 0 | T101: =ROUND(T36+T37+T38+T39+T40+T41+T42+T43+T44+T45+T46+T47+T48+T49+T50+T51+T52+T53+T54+T55+T56+T57-T96,1) -> 0 | U101: =ROUND(U36+U37+U38+U39+U40+U41+U42+U43+U44+U45+U46+U47+U48+U49+U50+U51+U52+U53+U54+U55+U56+U57-U96,1) -> 0 | V101: =ROUND(V36+V37+V38+V39+V40+V41+V42+V43+V44+V45+V46+V47+V48+V49+V50+V51+V52+V53+V54+V55+V56+V57-V96,1) -> 0 | X101: =ROUND(X36+X37+X38+X39+X40+X41+X42+X43+X44+X45+X46+X47+X48+X49+X50+X51+X52+X53+X54+X55+X56+X57-X96,1) -> 0 | Y101: =ROUND(Y36+Y37+Y38+Y39+Y40+Y41+Y42+Y43+Y44+Y45+Y46+Y47+Y48+Y49+Y50+Y51+Y52+Y53+Y54+Y55+Y56+Y57-Y96,1) -> 0 | Z101: =ROUND(Z36+Z37+Z38+Z39+Z40+Z41+Z42+Z43+Z44+Z45+Z46+Z47+Z48+Z49+Z50+Z51+Z52+Z53+Z54+Z55+Z56+Z57-Z96,1) -> 0 | AA101: =ROUND(AA36+AA37+AA38+AA39+AA40+AA41+AA42+AA43+AA44+AA45+AA46+AA47+AA48+AA49+AA50+AA51+AA52+AA53+AA54+AA55+AA56+AA57-AA96,1) -> 0 | AC101: =ROUND(AC36+AC37+AC38+AC39+AC40+AC41+AC42+AC43+AC44+AC45+AC46+AC47+AC48+AC49+AC50+AC51+AC52+AC53+AC54+AC55+AC56+AC57-AC96,1) -> 0 | AD101: =ROUND(AD36+AD37+AD38+AD39+AD40+AD41+AD42+AD43+AD44+AD45+AD46+AD47+AD48+AD49+AD50+AD51+AD52+AD53+AD54+AD55+AD56+AD57-AD96,1) -> 0
A102: CHECK: passivo + PL - passivo total · derivada · unid. moeda | C102: [linha bruta, sem código; lançada nas linhas abaixo] | D102: =ROUND(D58+D59+D60+D61+D62+D63+D64+D65+D66+D67+D68+D69+D70+D71+D72+D73+D74+D75+D76+D77+D78+D79+D80+D81+D82+D83+D84+D85+D86+D87+D88+D89+D90+D91+D92+D93-D97,1) -> 0 | E102: =ROUND(E58+E59+E60+E61+E62+E63+E64+E65+E66+E67+E68+E69+E70+E71+E72+E73+E74+E75+E76+E77+E78+E79+E80+E81+E82+E83+E84+E85+E86+E87+E88+E89+E90+E91+E92+E93-E97,1) -> 0 | F102: =ROUND(F58+F59+F60+F61+F62+F63+F64+F65+F66+F67+F68+F69+F70+F71+F72+F73+F74+F75+F76+F77+F78+F79+F80+F81+F82+F83+F84+F85+F86+F87+F88+F89+F90+F91+F92+F93-F97,1) -> 0 | G102: =ROUND(G58+G59+G60+G61+G62+G63+G64+G65+G66+G67+G68+G69+G70+G71+G72+G73+G74+G75+G76+G77+G78+G79+G80+G81+G82+G83+G84+G85+G86+G87+G88+G89+G90+G91+G92+G93-G97,1) -> 0 | I102: =ROUND(I58+I59+I60+I61+I62+I63+I64+I65+I66+I67+I68+I69+I70+I71+I72+I73+I74+I75+I76+I77+I78+I79+I80+I81+I82+I83+I84+I85+I86+I87+I88+I89+I90+I91+I92+I93-I97,1) -> 0 | J102: =ROUND(J58+J59+J60+J61+J62+J63+J64+J65+J66+J67+J68+J69+J70+J71+J72+J73+J74+J75+J76+J77+J78+J79+J80+J81+J82+J83+J84+J85+J86+J87+J88+J89+J90+J91+J92+J93-J97,1) -> 0 | K102: =ROUND(K58+K59+K60+K61+K62+K63+K64+K65+K66+K67+K68+K69+K70+K71+K72+K73+K74+K75+K76+K77+K78+K79+K80+K81+K82+K83+K84+K85+K86+K87+K88+K89+K90+K91+K92+K93-K97,1) -> 0 | L102: =ROUND(L58+L59+L60+L61+L62+L63+L64+L65+L66+L67+L68+L69+L70+L71+L72+L73+L74+L75+L76+L77+L78+L79+L80+L81+L82+L83+L84+L85+L86+L87+L88+L89+L90+L91+L92+L93-L97,1) -> 0 | N102: =ROUND(N58+N59+N60+N61+N62+N63+N64+N65+N66+N67+N68+N69+N70+N71+N72+N73+N74+N75+N76+N77+N78+N79+N80+N81+N82+N83+N84+N85+N86+N87+N88+N89+N90+N91+N92+N93-N97,1) -> 0 | O102: =ROUND(O58+O59+O60+O61+O62+O63+O64+O65+O66+O67+O68+O69+O70+O71+O72+O73+O74+O75+O76+O77+O78+O79+O80+O81+O82+O83+O84+O85+O86+O87+O88+O89+O90+O91+O92+O93-O97,1) -> 0 | P102: =ROUND(P58+P59+P60+P61+P62+P63+P64+P65+P66+P67+P68+P69+P70+P71+P72+P73+P74+P75+P76+P77+P78+P79+P80+P81+P82+P83+P84+P85+P86+P87+P88+P89+P90+P91+P92+P93-P97,1) -> 0 | Q102: =ROUND(Q58+Q59+Q60+Q61+Q62+Q63+Q64+Q65+Q66+Q67+Q68+Q69+Q70+Q71+Q72+Q73+Q74+Q75+Q76+Q77+Q78+Q79+Q80+Q81+Q82+Q83+Q84+Q85+Q86+Q87+Q88+Q89+Q90+Q91+Q92+Q93-Q97,1) -> 0 | S102: =ROUND(S58+S59+S60+S61+S62+S63+S64+S65+S66+S67+S68+S69+S70+S71+S72+S73+S74+S75+S76+S77+S78+S79+S80+S81+S82+S83+S84+S85+S86+S87+S88+S89+S90+S91+S92+S93-S97,1) -> 0 | T102: =ROUND(T58+T59+T60+T61+T62+T63+T64+T65+T66+T67+T68+T69+T70+T71+T72+T73+T74+T75+T76+T77+T78+T79+T80+T81+T82+T83+T84+T85+T86+T87+T88+T89+T90+T91+T92+T93-T97,1) -> 0 | U102: =ROUND(U58+U59+U60+U61+U62+U63+U64+U65+U66+U67+U68+U69+U70+U71+U72+U73+U74+U75+U76+U77+U78+U79+U80+U81+U82+U83+U84+U85+U86+U87+U88+U89+U90+U91+U92+U93-U97,1) -> 0 | V102: =ROUND(V58+V59+V60+V61+V62+V63+V64+V65+V66+V67+V68+V69+V70+V71+V72+V73+V74+V75+V76+V77+V78+V79+V80+V81+V82+V83+V84+V85+V86+V87+V88+V89+V90+V91+V92+V93-V97,1) -> -4 | X102: =ROUND(X58+X59+X60+X61+X62+X63+X64+X65+X66+X67+X68+X69+X70+X71+X72+X73+X74+X75+X76+X77+X78+X79+X80+X81+X82+X83+X84+X85+X86+X87+X88+X89+X90+X91+X92+X93-X97,1) -> 0 | Y102: =ROUND(Y58+Y59+Y60+Y61+Y62+Y63+Y64+Y65+Y66+Y67+Y68+Y69+Y70+Y71+Y72+Y73+Y74+Y75+Y76+Y77+Y78+Y79+Y80+Y81+Y82+Y83+Y84+Y85+Y86+Y87+Y88+Y89+Y90+Y91+Y92+Y93-Y97,1) -> 0 | Z102: =ROUND(Z58+Z59+Z60+Z61+Z62+Z63+Z64+Z65+Z66+Z67+Z68+Z69+Z70+Z71+Z72+Z73+Z74+Z75+Z76+Z77+Z78+Z79+Z80+Z81+Z82+Z83+Z84+Z85+Z86+Z87+Z88+Z89+Z90+Z91+Z92+Z93-Z97,1) -> 0 | AA102: =ROUND(AA58+AA59+AA60+AA61+AA62+AA63+AA64+AA65+AA66+AA67+AA68+AA69+AA70+AA71+AA72+AA73+AA74+AA75+AA76+AA77+AA78+AA79+AA80+AA81+AA82+AA83+AA84+AA85+AA86+AA87+AA88+AA89+AA90+AA91+AA92+AA93-AA97,1) -> 0 | AC102: =ROUND(AC58+AC59+AC60+AC61+AC62+AC63+AC64+AC65+AC66+AC67+AC68+AC69+AC70+AC71+AC72+AC73+AC74+AC75+AC76+AC77+AC78+AC79+AC80+AC81+AC82+AC83+AC84+AC85+AC86+AC87+AC88+AC89+AC90+AC91+AC92+AC93-AC97,1) -> 0 | AD102: =ROUND(AD58+AD59+AD60+AD61+AD62+AD63+AD64+AD65+AD66+AD67+AD68+AD69+AD70+AD71+AD72+AD73+AD74+AD75+AD76+AD77+AD78+AD79+AD80+AD81+AD82+AD83+AD84+AD85+AD86+AD87+AD88+AD89+AD90+AD91+AD92+AD93-AD97,1) -> 0
A103: [vazio] cod 8 Equity in affiliates: nao aberto na DRE da planilha (irrelevante) | C103: [linha bruta, sem código; lançada nas linhas abaixo]
A104: [vazio] cod 9 Minority interest: sem minoritarios | C104: [linha bruta, sem código; lançada nas linhas abaixo]
A105: [vazio] cod 13 Estoques: sem linha (seminovos em "veiculos desativados", cod 16) | C105: [linha bruta, sem código; lançada nas linhas abaixo]
A106: [vazio] cod 20 Goodwill: dentro do intangivel | C106: [linha bruta, sem código; lançada nas linhas abaixo]
A107: [vazio] cod 28 Revolver: sem linha propria | C107: [linha bruta, sem código; lançada nas linhas abaixo]
A108: [vazio] cod 32 Convertible debt: inexistente | C108: [linha bruta, sem código; lançada nas linhas abaixo]
A109: [vazio] cod 36 Convertible Preferred Stock: inexistente | C109: [linha bruta, sem código; lançada nas linhas abaixo]
A110: Nota de base: de 1T23 em diante a DRE da planilha bate com a CVM (receita, EBIT e lucro). Em 2020-22 a planilha e pro forma (receita ~3% menor que a CVM; 1T20 lucro 55,1 x CVM -114,4 e 4T20 138,7 x 183,6): mantido o numero da Cia. | C110: [linha bruta, sem código; lançada nas linhas abaixo]
A112: DRIVERS DE RECEITA (codigos 45+): receita e EBITDA por segmento, dados operacionais e capex da Planilha de Fundamentos da Movida (R$ milhoes, fator 1). | C112: [linha bruta, sem código; lançada nas linhas abaixo]
A113: Receita liquida RAC Brasil (DRE l.11) · fonte · unid. moeda | B113: 45 | C113: Receita liquida RAC Brasil (DRE l.11) | D113: 328988 | E113: 308291 | F113: 403799 | G113: 522570 | I113: 552692 | J113: 585184 | K113: 675359 | L113: 682873 | N113: 686638 | O113: 646165 | P113: 651205 | Q113: 674999 | S113: 751762 | T113: 748549 | U113: 764768 | V113: 808526 | X113: 859380 | Y113: 843303 | Z113: 874046 | AA113: 968870.78 | AC113: 1076120.5 | AD113: 1099712.3
A114: Receita liquida RAC Portugal (DRE l.30; desde a aquisicao em 2023) · fonte · unid. moeda | B114: 46 | C114: Receita liquida RAC Portugal (DRE l.30; desde a aquisicao em | D114: 0 | E114: 0 | F114: 0 | G114: 0 | I114: 0 | J114: 0 | K114: 0 | L114: 43829 | N114: 14396 | O114: 29467 | P114: 64989 | Q114: 29385 | S114: 23047 | T114: 43533 | U114: 90502 | V114: 39179 | X114: 26343 | Y114: 53453 | Z114: 103339 | AA114: 43916.766 | AC114: 27887.442 | AD114: 45853.258
A115: Receita liquida GTF - gestao e terceirizacao de frotas (DRE l.68) · fonte · unid. moeda | B115: 47 | C115: Receita liquida GTF - gestao e terceirizacao de frotas (DRE | D115: 154023 | E115: 183574 | F115: 272657 | G115: 357380 | I115: 379203 | J115: 417174 | K115: 451078 | L115: 495524 | N115: 538708 | O115: 558149 | P115: 581123 | Q115: 635236 | S115: 720390 | T115: 816006 | U115: 889427 | V115: 943352 | X115: 993181 | Y115: 995876 | Z115: 1033426 | AA115: 1083606.5 | AC115: 1101608.6 | AD115: 1149769
A116: Receita liquida Seminovos (DRE l.87) · fonte · unid. moeda | B116: 48 | C116: Receita liquida Seminovos (DRE l.87) | D116: 274540 | E116: 673480 | F116: 844620 | G116: 809115 | I116: 973762 | J116: 1228635 | K116: 1410428 | L116: 1404407 | N116: 1463465 | O116: 1245363 | P116: 1368902 | Q116: 1153824 | S116: 1526448 | T116: 1827516 | U116: 2031166 | V116: 1457100 | X116: 1689326 | Y116: 1786374 | Z116: 1755031 | AA116: 1562581.1 | AC116: 1575028.5 | AD116: 1470495.6
A117: EBITDA RAC consolidado (DRE l.61) · fonte · unid. moeda | B117: 49 | C117: EBITDA RAC consolidado (DRE l.61) | D117: 168740 | E117: 140676 | F117: 233091 | G117: 333123 | I117: 373325 | J117: 384781 | K117: 457844 | L117: 416559 | N117: 427387 | O117: 381802 | P117: 395515 | Q117: 367098 | S117: 485485 | T117: 504709 | U117: 550010 | V117: 543336 | X117: 563843 | Y117: 602060 | Z117: 669054 | AA117: 663047.15 | AC117: 717757.55 | AD117: 775951.37
A118: EBITDA GTF (DRE l.80) · fonte · unid. moeda | B118: 50 | C118: EBITDA GTF (DRE l.80) | D118: 99481 | E118: 127681 | F118: 193117 | G118: 261929 | I118: 285299 | J118: 315241 | K118: 331303 | L118: 336091 | N118: 361568 | O118: 411732 | P118: 430960 | Q118: 462355 | S118: 535294 | T118: 619952 | U118: 675759 | V118: 683937 | X118: 756317 | Y118: 757422 | Z118: 791002 | AA118: 811769.08 | AC118: 833529.63 | AD118: 895096.74
A119: EBITDA Seminovos (DRE l.96) · fonte · unid. moeda | B119: 51 | C119: EBITDA Seminovos (DRE l.96) | D119: 36282 | E119: 120108 | F119: 187200 | G119: 181561 | I119: 204472 | J119: 205234 | K119: 136190 | L119: 105593 | N119: 86387 | O119: 96458 | P119: 41451 | Q119: 36566 | S119: 38640 | T119: 24699 | U119: 21709 | V119: 17006 | X119: 18169 | Y119: 19641 | Z119: 18599 | AA119: 15234.03 | AC119: 17377.381 | AD119: 15695.477
A120: RAC - frota no final do periodo (carros; Op Data l.7) · fonte · unid. un | B120: 52 | C120: RAC - frota no final do periodo (carros; Op Data l.7) | D120: 70213000 | E120: 78453000 | F120: 79888000 | G120: 90671000 | I120: 96572000 | J120: 100403000 | K120: 104987000 | L120: 111632000 | N120: 98373000 | O120: 91632000 | P120: 94273000 | Q120: 113150000 | S120: 110091000 | T120: 108716000 | U120: 110182000 | V120: 121942000 | X120: 113257000 | Y120: 120133000 | Z120: 115498000 | AA120: 130634000 | AC120: 125307000 | AD120: 139785000
A121: RAC - frota media operacional Brasil (Op Data l.11) · fonte · unid. un | B121: 53 | C121: RAC - frota media operacional Brasil (Op Data l.11) | D121: 64795778 | E121: 63654352 | F121: 67380652 | G121: 70538359 | I121: 75286000 | J121: 80205000 | K121: 85151000 | L121: 90852000 | N121: 88866199 | O121: 82491000 | P121: 79085543 | Q121: 81070652 | S121: 89703462 | T121: 90071198 | U121: 87264217 | V121: 88526512 | X121: 95097200 | Y121: 91009044 | Z121: 92381456 | AA121: 96659329 | AC121: 1.0275381e+08 | AD121: 1.0881642e+08
A122: RAC - frota media alugada (Op Data l.13) · fonte · unid. un | B122: 54 | C122: RAC - frota media alugada (Op Data l.13) | D122: 51370093 | E122: 50671055 | F122: 55849469 | G122: 57025126 | I122: 57280098 | J122: 63642042 | K122: 65726756 | L122: 69565355 | N122: 69616243 | O122: 64568000 | P122: 64181696 | Q122: 66467207 | S122: 71924826 | T122: 70369758 | U122: 68114141 | V122: 66296152 | X122: 68229900 | Y122: 67397041 | Z122: 66285398 | AA122: 73313193 | AC122: 79411652 | AD122: 82926863
A123: RAC - numero de diarias (mil; Op Data l.15) · fonte · unid. un | B123: 55 | C123: RAC - numero de diarias (mil; Op Data l.15) | D123: 5067042 | E123: 4618390 | F123: 5143355 | G123: 5281203 | I123: 5224573 | J123: 5677490 | K123: 5888846 | L123: 6111338 | N123: 6218754 | O123: 5837236 | P123: 5819624 | Q123: 5945636 | S123: 6414484 | T123: 6200041 | U123: 6004671 | V123: 5958805 | X123: 6026629 | Y123: 6070355 | Z123: 6084784 | AA123: 6688820 | AC123: 7085315.1 | AD123: 7412787
A124: RAC - taxa de ocupacao (Op Data l.16) · fonte · unid. un | B124: 56 | C124: RAC - taxa de ocupacao (Op Data l.16) | D124: 793 | E124: 796 | F124: 829 | G124: 808 | I124: 761 | J124: 793 | K124: 772 | L124: 766 | N124: 784 | O124: 783 | P124: 811 | Q124: 820 | S124: 802 | T124: 781 | U124: 781 | V124: 749 | X124: 717 | Y124: 741 | Z124: 718 | AA124: 758.46991 | AC124: 772.83417 | AD124: 762.08042
... A135: Capex GTF (R$ mi; CAPEX l.19) · fonte · unid. moeda | B135: 67 | C135: Capex GTF (R$ mi; CAPEX l.19) | D135: 400141 | E135: 268452 | F135: 945323 | G135: 961226 | I135: 154340 | J135: 1080363 | K135: 512801 | L135: 791890 | N135: 761790 | O135: 920396 | P135: 1620787 | Q135: 2148859 | S135: 1396221 | T135: 1503655 | U135: 1356178 | V135: 1870277 | X135: 815738.6 | Y135: 1235113.6 | Z135: 1335992 | AA135: 1493408.4 | AC135: 988500.25 | AD135: 1707599.3
A136: Notas: segmentos somam a receita consolidada em todos os trimestres. RAC Portugal so a partir de 2023. Dados operacionais sem fator (unidades, R$ e %). | C136: [linha bruta, sem código; lançada nas linhas abaixo]
A138: Linhas de origem: 4 a 136. A Inputs (2) varre as linhas 4 a 200; as linhas 137 a 200 estão livres. Linhas "(lançamento)" aplicam código e sinal sobre a linha bruta indicada (a máscara tem uma só coluna de código).

Sheet Inputs (2)
A1: =IF(Control!B3="","EMPRESA",Control!B3) -> Movida | B1: Código | C1: Conta padronizada | D1: 2021 | E1: 2021 | F1: 2021 | G1: 2021 | H1: 2021 | I1: 2022 | J1: 2022 | K1: 2022 | L1: 2022 | M1: 2022 | N1: 2023 | O1: 2023 | P1: 2023 | Q1: 2023 | R1: 2023 | S1: 2024 | T1: 2024 | U1: 2024 | V1: 2024 | W1: 2024 | X1: 2025 | Y1: 2025 | Z1: 2025 | AA1: 2025 | AB1: 2025 | AC1: 2026 | AD1: 2026 | AE1: 2026 | AF1: 2026 | AG1: 2026
A2: R$ milhões | C2: Período | D2: 1Q21 | E2: 2Q21 | F2: 3Q21 | G2: 4Q21 | H2: 2021 | I2: 1Q22 | J2: 2Q22 | K2: 3Q22 | L2: 4Q22 | M2: 2022 | N2: 1Q23 | O2: 2Q23 | P2: 3Q23 | Q2: 4Q23 | R2: 2023 | S2: 1Q24 | T2: 2Q24 | U2: 3Q24 | V2: 4Q24 | W2: 2024 | X2: 1Q25 | Y2: 2Q25 | Z2: 3Q25 | AA2: 4Q25 | AB2: 2025 | AC2: 1Q26 | AD2: 2Q26 | AE2: 3Q26 | AF2: 4Q26 | AG2: 2026
A3: Actual flag | C3: 0 = sem dados / 1 = realizado | D3: 1 | E3: 1 | F3: 1 | G3: 1 | H3: 1 | I3: 1 | J3: 1 | K3: 1 | L3: 1 | M3: 1 | N3: 1 | O3: 1 | P3: 1 | Q3: 1 | R3: 1 | S3: 1 | T3: 1 | U3: 1 | V3: 1 | W3: 1 | X3: 1 | Y3: 1 | Z3: 1 | AA3: 1 | AB3: 1 | AC3: 1 | AD3: 1 | AE3: 0 | AF3: 0 | AG3: 0
B4: 1 | C4: Net Revenues | D4: =IF(D$3=0,"",SUMIFS(INDEX(Inputs!$D$4:$AG$200,0,MATCH(D$2,Inputs!$D$2:$AG$2,0)),Inputs!$B$4:$B$200,$B4)/1000) -> 757.552 | E4: =IF(E$3=0,"",SUMIFS(INDEX(Inputs!$D$4:$AG$200,0,MATCH(E$2,Inputs!$D$2:$AG$2,0)),Inputs!$B$4:$B$200,$B4)/1000) -> 1165.345 | F4: =IF(F$3=0,"",SUMIFS(INDEX(Inputs!$D$4:$AG$200,0,MATCH(F$2,Inputs!$D$2:$AG$2,0)),Inputs!$B$4:$B$200,$B4)/1000) -> 1521.076 | G4: =IF(G$3=0,"",SUMIFS(INDEX(Inputs!$D$4:$AG$200,0,MATCH(G$2,Inputs!$D$2:$AG$2,0)),Inputs!$B$4:$B$200,$B4)/1000) -> 1689.065 | H4: =IF(COUNT(D4:G4)=4,SUM(D4:G4),"") -> 5133.038 | I4: =IF(I$3=0,"",SUMIFS(INDEX(Inputs!$D$4:$AG$200,0,MATCH(I$2,Inputs!$D$2:$AG$2,0)),Inputs!$B$4:$B$200,$B4)/1000) -> 1905.657 | J4: =IF(J$3=0,"",SUMIFS(INDEX(Inputs!$D$4:$AG$200,0,MATCH(J$2,Inputs!$D$2:$AG$2,0)),Inputs!$B$4:$B$200,$B4)/1000) -> 2230.992 | K4: =IF(K$3=0,"",SUMIFS(INDEX(Inputs!$D$4:$AG$200,0,MATCH(K$2,Inputs!$D$2:$AG$2,0)),Inputs!$B$4:$B$200,$B4)/1000) -> 2536.864 | L4: =IF(L$3=0,"",SUMIFS(INDEX(Inputs!$D$4:$AG$200,0,MATCH(L$2,Inputs!$D$2:$AG$2,0)),Inputs!$B$4:$B$200,$B4)/1000) -> 2626.633 | M4: =IF(COUNT(I4:L4)=4,SUM(I4:L4),"") -> 9300.146 | N4: =IF(N$3=0,"",SUMIFS(INDEX(Inputs!$D$4:$AG$200,0,MATCH(N$2,Inputs!$D$2:$AG$2,0)),Inputs!$B$4:$B$200,$B4)/1000) -> 2703.206 | O4: =IF(O$3=0,"",SUMIFS(INDEX(Inputs!$D$4:$AG$200,0,MATCH(O$2,Inputs!$D$2:$AG$2,0)),Inputs!$B$4:$B$200,$B4)/1000) -> 2479.144 | P4: =IF(P$3=0,"",SUMIFS(INDEX(Inputs!$D$4:$AG$200,0,MATCH(P$2,Inputs!$D$2:$AG$2,0)),Inputs!$B$4:$B$200,$B4)/1000) -> 2666.22 | Q4: =IF(Q$3=0,"",SUMIFS(INDEX(Inputs!$D$4:$AG$200,0,MATCH(Q$2,Inputs!$D$2:$AG$2,0)),Inputs!$B$4:$B$200,$B4)/1000) -> 2493.444 | R4: =IF(COUNT(N4:Q4)=4,SUM(N4:Q4),"") -> 10342.014 | S4: =IF(S$3=0,"",SUMIFS(INDEX(Inputs!$D$4:$AG$200,0,MATCH(S$2,Inputs!$D$2:$AG$2,0)),Inputs!$B$4:$B$200,$B4)/1000) -> 3021.646 | T4: =IF(T$3=0,"",SUMIFS(INDEX(Inputs!$D$4:$AG$200,0,MATCH(T$2,Inputs!$D$2:$AG$2,0)),Inputs!$B$4:$B$200,$B4)/1000) -> 3435.604 | U4: =IF(U$3=0,"",SUMIFS(INDEX(Inputs!$D$4:$AG$200,0,MATCH(U$2,Inputs!$D$2:$AG$2,0)),Inputs!$B$4:$B$200,$B4)/1000) -> 3775.864 | V4: =IF(V$3=0,"",SUMIFS(INDEX(Inputs!$D$4:$AG$200,0,MATCH(V$2,Inputs!$D$2:$AG$2,0)),Inputs!$B$4:$B$200,$B4)/1000) -> 3248.157 | W4: =IF(COUNT(S4:V4)=4,SUM(S4:V4),"") -> 13481.271 | X4: =IF(X$3=0,"",SUMIFS(INDEX(Inputs!$D$4:$AG$200,0,MATCH(X$2,Inputs!$D$2:$AG$2,0)),Inputs!$B$4:$B$200,$B4)/1000) -> 3568.231 | Y4: =IF(Y$3=0,"",SUMIFS(INDEX(Inputs!$D$4:$AG$200,0,MATCH(Y$2,Inputs!$D$2:$AG$2,0)),Inputs!$B$4:$B$200,$B4)/1000) -> 3679.006 | Z4: =IF(Z$3=0,"",SUMIFS(INDEX(Inputs!$D$4:$AG$200,0,MATCH(Z$2,Inputs!$D$2:$AG$2,0)),Inputs!$B$4:$B$200,$B4)/1000) -> 3765.843 | AA4: =IF(AA$3=0,"",SUMIFS(INDEX(Inputs!$D$4:$AG$200,0,MATCH(AA$2,Inputs!$D$2:$AG$2,0)),Inputs!$B$4:$B$200,$B4)/1000) -> 3658.9752 | AB4: =IF(COUNT(X4:AA4)=4,SUM(X4:AA4),"") -> 14672.055 | AC4: =IF(AC$3=0,"",SUMIFS(INDEX(Inputs!$D$4:$AG$200,0,MATCH(AC$2,Inputs!$D$2:$AG$2,0)),Inputs!$B$4:$B$200,$B4)/1000) -> 3780.645 | AD4: =IF(AD$3=0,"",SUMIFS(INDEX(Inputs!$D$4:$AG$200,0,MATCH(AD$2,Inputs!$D$2:$AG$2,0)),Inputs!$B$4:$B$200,$B4)/1000) -> 3765.8302 | AE4: =IF(AE$3=0,"",SUMIFS(INDEX(Inputs!$D$4:$AG$200,0,MATCH(AE$2,Inputs!$D$2:$AG$2,0)),Inputs!$B$4:$B$200,$B4)/1000) | AF4: =IF(AF$3=0,"",SUMIFS(INDEX(Inputs!$D$4:$AG$200,0,MATCH(AF$2,Inputs!$D$2:$AG$2,0)),Inputs!$B$4:$B$200,$B4)/1000) | AG4: =IF(COUNT(AC4:AF4)=4,SUM(AC4:AF4),"")
B5: 2 | C5: COGS (cash) | D5: =IF(D$3=0,"",SUMIFS(INDEX(Inputs!$D$4:$AG$200,0,MATCH(D$2,Inputs!$D$2:$AG$2,0)),Inputs!$B$4:$B$200,$B5)/1000) -> -296.445 | E5: =IF(E$3=0,"",SUMIFS(INDEX(Inputs!$D$4:$AG$200,0,MATCH(E$2,Inputs!$D$2:$AG$2,0)),Inputs!$B$4:$B$200,$B5)/1000) -> -605.183 | F5: =IF(F$3=0,"",SUMIFS(INDEX(Inputs!$D$4:$AG$200,0,MATCH(F$2,Inputs!$D$2:$AG$2,0)),Inputs!$B$4:$B$200,$B5)/1000) -> -729.162 | G5: =IF(G$3=0,"",SUMIFS(INDEX(Inputs!$D$4:$AG$200,0,MATCH(G$2,Inputs!$D$2:$AG$2,0)),Inputs!$B$4:$B$200,$B5)/1000) -> -699.45 | H5: =IF(COUNT(D5:G5)=4,SUM(D5:G5),"") -> -2330.24 | I5: =IF(I$3=0,"",SUMIFS(INDEX(Inputs!$D$4:$AG$200,0,MATCH(I$2,Inputs!$D$2:$AG$2,0)),Inputs!$B$4:$B$200,$B5)/1000) -> -807.931 | J5: =IF(J$3=0,"",SUMIFS(INDEX(Inputs!$D$4:$AG$200,0,MATCH(J$2,Inputs!$D$2:$AG$2,0)),Inputs!$B$4:$B$200,$B5)/1000) -> -1068.195 | K5: =IF(K$3=0,"",SUMIFS(INDEX(Inputs!$D$4:$AG$200,0,MATCH(K$2,Inputs!$D$2:$AG$2,0)),Inputs!$B$4:$B$200,$B5)/1000) -> -1319.005 | L5: =IF(L$3=0,"",SUMIFS(INDEX(Inputs!$D$4:$AG$200,0,MATCH(L$2,Inputs!$D$2:$AG$2,0)),Inputs!$B$4:$B$200,$B5)/1000) -> -1423.846 | M5: =IF(COUNT(I5:L5)=4,SUM(I5:L5),"") -> -4618.977 | N5: =IF(N$3=0,"",SUMIFS(INDEX(Inputs!$D$4:$AG$200,0,MATCH(N$2,Inputs!$D$2:$AG$2,0)),Inputs!$B$4:$B$200,$B5)/1000) -> -1495.089 | O5: =IF(O$3=0,"",SUMIFS(INDEX(Inputs!$D$4:$AG$200,0,MATCH(O$2,Inputs!$D$2:$AG$2,0)),Inputs!$B$4:$B$200,$B5)/1000) -> -1259.21 | P5: =IF(P$3=0,"",SUMIFS(INDEX(Inputs!$D$4:$AG$200,0,MATCH(P$2,Inputs!$D$2:$AG$2,0)),Inputs!$B$4:$B$200,$B5)/1000) -> -1459.743 | Q5: =IF(Q$3=0,"",SUMIFS(INDEX(Inputs!$D$4:$AG$200,0,MATCH(Q$2,Inputs!$D$2:$AG$2,0)),Inputs!$B$4:$B$200,$B5)/1000) -> -1121.686 | R5: =IF(COUNT(N5:Q5)=4,SUM(N5:Q5),"") -> -5335.728 | S5: =IF(S$3=0,"",SUMIFS(INDEX(Inputs!$D$4:$AG$200,0,MATCH(S$2,Inputs!$D$2:$AG$2,0)),Inputs!$B$4:$B$200,$B5)/1000) -> -1641.713 | T5: =IF(T$3=0,"",SUMIFS(INDEX(Inputs!$D$4:$AG$200,0,MATCH(T$2,Inputs!$D$2:$AG$2,0)),Inputs!$B$4:$B$200,$B5)/1000) -> -1943.53 | U5: =IF(U$3=0,"",SUMIFS(INDEX(Inputs!$D$4:$AG$200,0,MATCH(U$2,Inputs!$D$2:$AG$2,0)),Inputs!$B$4:$B$200,$B5)/1000) -> -2167.358 | V5: =IF(V$3=0,"",SUMIFS(INDEX(Inputs!$D$4:$AG$200,0,MATCH(V$2,Inputs!$D$2:$AG$2,0)),Inputs!$B$4:$B$200,$B5)/1000) -> -1632.258 | W5: =IF(COUNT(S5:V5)=4,SUM(S5:V5),"") -> -7384.859 | X5: =IF(X$3=0,"",SUMIFS(INDEX(Inputs!$D$4:$AG$200,0,MATCH(X$2,Inputs!$D$2:$AG$2,0)),Inputs!$B$4:$B$200,$B5)/1000) -> -1850.292 | Y5: =IF(Y$3=0,"",SUMIFS(INDEX(Inputs!$D$4:$AG$200,0,MATCH(Y$2,Inputs!$D$2:$AG$2,0)),Inputs!$B$4:$B$200,$B5)/1000) -> -1930.49 | Z5: =IF(Z$3=0,"",SUMIFS(INDEX(Inputs!$D$4:$AG$200,0,MATCH(Z$2,Inputs!$D$2:$AG$2,0)),Inputs!$B$4:$B$200,$B5)/1000) -> -1923.127 | AA5: =IF(AA$3=0,"",SUMIFS(INDEX(Inputs!$D$4:$AG$200,0,MATCH(AA$2,Inputs!$D$2:$AG$2,0)),Inputs!$B$4:$B$200,$B5)/1000) -> -1775.8778 | AB5: =IF(COUNT(X5:AA5)=4,SUM(X5:AA5),"") -> -7479.7868 | AC5: =IF(AC$3=0,"",SUMIFS(INDEX(Inputs!$D$4:$AG$200,0,MATCH(AC$2,Inputs!$D$2:$AG$2,0)),Inputs!$B$4:$B$200,$B5)/1000) -> -1792.9548 | AD5: =IF(AD$3=0,"",SUMIFS(INDEX(Inputs!$D$4:$AG$200,0,MATCH(AD$2,Inputs!$D$2:$AG$2,0)),Inputs!$B$4:$B$200,$B5)/1000) -> -1658.145 | AE5: =IF(AE$3=0,"",SUMIFS(INDEX(Inputs!$D$4:$AG$200,0,MATCH(AE$2,Inputs!$D$2:$AG$2,0)),Inputs!$B$4:$B$200,$B5)/1000) | AF5: =IF(AF$3=0,"",SUMIFS(INDEX(Inputs!$D$4:$AG$200,0,MATCH(AF$2,Inputs!$D$2:$AG$2,0)),Inputs!$B$4:$B$200,$B5)/1000) | AG5: =IF(COUNT(AC5:AF5)=4,SUM(AC5:AF5),"")
B6: 3 | C6: SG&A and Other (cash) | D6: =IF(D$3=0,"",SUMIFS(INDEX(Inputs!$D$4:$AG$200,0,MATCH(D$2,Inputs!$D$2:$AG$2,0)),Inputs!$B$4:$B$200,$B6)/1000) -> -156.605 | E6: =IF(E$3=0,"",SUMIFS(INDEX(Inputs!$D$4:$AG$200,0,MATCH(E$2,Inputs!$D$2:$AG$2,0)),Inputs!$B$4:$B$200,$B6)/1000) -> -171.698 | F6: =IF(F$3=0,"",SUMIFS(INDEX(Inputs!$D$4:$AG$200,0,MATCH(F$2,Inputs!$D$2:$AG$2,0)),Inputs!$B$4:$B$200,$B6)/1000) -> -178.506 | G6: =IF(G$3=0,"",SUMIFS(INDEX(Inputs!$D$4:$AG$200,0,MATCH(G$2,Inputs!$D$2:$AG$2,0)),Inputs!$B$4:$B$200,$B6)/1000) -> -213.003 | H6: =IF(COUNT(D6:G6)=4,SUM(D6:G6),"") -> -719.812 | I6: =IF(I$3=0,"",SUMIFS(INDEX(Inputs!$D$4:$AG$200,0,MATCH(I$2,Inputs!$D$2:$AG$2,0)),Inputs!$B$4:$B$200,$B6)/1000) -> -234.631 | J6: =IF(J$3=0,"",SUMIFS(INDEX(Inputs!$D$4:$AG$200,0,MATCH(J$2,Inputs!$D$2:$AG$2,0)),Inputs!$B$4:$B$200,$B6)/1000) -> -257.54 | K6: =IF(K$3=0,"",SUMIFS(INDEX(Inputs!$D$4:$AG$200,0,MATCH(K$2,Inputs!$D$2:$AG$2,0)),Inputs!$B$4:$B$200,$B6)/1000) -> -292.522 | L6: =IF(L$3=0,"",SUMIFS(INDEX(Inputs!$D$4:$AG$200,0,MATCH(L$2,Inputs!$D$2:$AG$2,0)),Inputs!$B$4:$B$200,$B6)/1000) -> -344.544 | M6: =IF(COUNT(I6:L6)=4,SUM(I6:L6),"") -> -1129.237 | N6: =IF(N$3=0,"",SUMIFS(INDEX(Inputs!$D$4:$AG$200,0,MATCH(N$2,Inputs!$D$2:$AG$2,0)),Inputs!$B$4:$B$200,$B6)/1000) -> -332.775 | O6: =IF(O$3=0,"",SUMIFS(INDEX(Inputs!$D$4:$AG$200,0,MATCH(O$2,Inputs!$D$2:$AG$2,0)),Inputs!$B$4:$B$200,$B6)/1000) -> -329.942 | P6: =IF(P$3=0,"",SUMIFS(INDEX(Inputs!$D$4:$AG$200,0,MATCH(P$2,Inputs!$D$2:$AG$2,0)),Inputs!$B$4:$B$200,$B6)/1000) -> -338.551 | Q6: =IF(Q$3=0,"",SUMIFS(INDEX(Inputs!$D$4:$AG$200,0,MATCH(Q$2,Inputs!$D$2:$AG$2,0)),Inputs!$B$4:$B$200,$B6)/1000) -> -505.685 | R6: =IF(COUNT(N6:Q6)=4,SUM(N6:Q6),"") -> -1506.953 | S6: =IF(S$3=0,"",SUMIFS(INDEX(Inputs!$D$4:$AG$200,0,MATCH(S$2,Inputs!$D$2:$AG$2,0)),Inputs!$B$4:$B$200,$B6)/1000) -> -320.432 | T6: =IF(T$3=0,"",SUMIFS(INDEX(Inputs!$D$4:$AG$200,0,MATCH(T$2,Inputs!$D$2:$AG$2,0)),Inputs!$B$4:$B$200,$B6)/1000) -> -342.713 | U6: =IF(U$3=0,"",SUMIFS(INDEX(Inputs!$D$4:$AG$200,0,MATCH(U$2,Inputs!$D$2:$AG$2,0)),Inputs!$B$4:$B$200,$B6)/1000) -> -361.03 | V6: =IF(V$3=0,"",SUMIFS(INDEX(Inputs!$D$4:$AG$200,0,MATCH(V$2,Inputs!$D$2:$AG$2,0)),Inputs!$B$4:$B$200,$B6)/1000) -> -371.618 | W6: =IF(COUNT(S6:V6)=4,SUM(S6:V6),"") -> -1395.793 | X6: =IF(X$3=0,"",SUMIFS(INDEX(Inputs!$D$4:$AG$200,0,MATCH(X$2,Inputs!$D$2:$AG$2,0)),Inputs!$B$4:$B$200,$B6)/1000) -> -379.61 | Y6: =IF(Y$3=0,"",SUMIFS(INDEX(Inputs!$D$4:$AG$200,0,MATCH(Y$2,Inputs!$D$2:$AG$2,0)),Inputs!$B$4:$B$200,$B6)/1000) -> -369.393 | Z6: =IF(Z$3=0,"",SUMIFS(INDEX(Inputs!$D$4:$AG$200,0,MATCH(Z$2,Inputs!$D$2:$AG$2,0)),Inputs!$B$4:$B$200,$B6)/1000) -> -364.059 | AA6: =IF(AA$3=0,"",SUMIFS(INDEX(Inputs!$D$4:$AG$200,0,MATCH(AA$2,Inputs!$D$2:$AG$2,0)),Inputs!$B$4:$B$200,$B6)/1000) -> -393.04709 | AB6: =IF(COUNT(X6:AA6)=4,SUM(X6:AA6),"") -> -1506.1091 | AC6: =IF(AC$3=0,"",SUMIFS(INDEX(Inputs!$D$4:$AG$200,0,MATCH(AC$2,Inputs!$D$2:$AG$2,0)),Inputs!$B$4:$B$200,$B6)/1000) -> -419.02555 | AD6: =IF(AD$3=0,"",SUMIFS(INDEX(Inputs!$D$4:$AG$200,0,MATCH(AD$2,Inputs!$D$2:$AG$2,0)),Inputs!$B$4:$B$200,$B6)/1000) -> -420.94157 | AE6: =IF(AE$3=0,"",SUMIFS(INDEX(Inputs!$D$4:$AG$200,0,MATCH(AE$2,Inputs!$D$2:$AG$2,0)),Inputs!$B$4:$B$200,$B6)/1000) | AF6: =IF(AF$3=0,"",SUMIFS(INDEX(Inputs!$D$4:$AG$200,0,MATCH(AF$2,Inputs!$D$2:$AG$2,0)),Inputs!$B$4:$B$200,$B6)/1000) | AG6: =IF(COUNT(AC6:AF6)=4,SUM(AC6:AF6),"")
B7: 4 | C7: D&A | D7: =IF(D$3=0,"",SUMIFS(INDEX(Inputs!$D$4:$AG$200,0,MATCH(D$2,Inputs!$D$2:$AG$2,0)),Inputs!$B$4:$B$200,$B7)/1000) -> -62.178 | E7: =IF(E$3=0,"",SUMIFS(INDEX(Inputs!$D$4:$AG$200,0,MATCH(E$2,Inputs!$D$2:$AG$2,0)),Inputs!$B$4:$B$200,$B7)/1000) -> -72.936 | F7: =IF(F$3=0,"",SUMIFS(INDEX(Inputs!$D$4:$AG$200,0,MATCH(F$2,Inputs!$D$2:$AG$2,0)),Inputs!$B$4:$B$200,$B7)/1000) -> -110.706 | G7: =IF(G$3=0,"",SUMIFS(INDEX(Inputs!$D$4:$AG$200,0,MATCH(G$2,Inputs!$D$2:$AG$2,0)),Inputs!$B$4:$B$200,$B7)/1000) -> -170.431 | H7: =IF(COUNT(D7:G7)=4,SUM(D7:G7),"") -> -416.251 | I7: =IF(I$3=0,"",SUMIFS(INDEX(Inputs!$D$4:$AG$200,0,MATCH(I$2,Inputs!$D$2:$AG$2,0)),Inputs!$B$4:$B$200,$B7)/1000) -> -212.836 | J7: =IF(J$3=0,"",SUMIFS(INDEX(Inputs!$D$4:$AG$200,0,MATCH(J$2,Inputs!$D$2:$AG$2,0)),Inputs!$B$4:$B$200,$B7)/1000) -> -240.909 | K7: =IF(K$3=0,"",SUMIFS(INDEX(Inputs!$D$4:$AG$200,0,MATCH(K$2,Inputs!$D$2:$AG$2,0)),Inputs!$B$4:$B$200,$B7)/1000) -> -300.524 | L7: =IF(L$3=0,"",SUMIFS(INDEX(Inputs!$D$4:$AG$200,0,MATCH(L$2,Inputs!$D$2:$AG$2,0)),Inputs!$B$4:$B$200,$B7)/1000) -> -380.942 | M7: =IF(COUNT(I7:L7)=4,SUM(I7:L7),"") -> -1135.211 | N7: =IF(N$3=0,"",SUMIFS(INDEX(Inputs!$D$4:$AG$200,0,MATCH(N$2,Inputs!$D$2:$AG$2,0)),Inputs!$B$4:$B$200,$B7)/1000) -> -390.033 | O7: =IF(O$3=0,"",SUMIFS(INDEX(Inputs!$D$4:$AG$200,0,MATCH(O$2,Inputs!$D$2:$AG$2,0)),Inputs!$B$4:$B$200,$B7)/1000) -> -388.955 | P7: =IF(P$3=0,"",SUMIFS(INDEX(Inputs!$D$4:$AG$200,0,MATCH(P$2,Inputs!$D$2:$AG$2,0)),Inputs!$B$4:$B$200,$B7)/1000) -> -412.766 | Q7: =IF(Q$3=0,"",SUMIFS(INDEX(Inputs!$D$4:$AG$200,0,MATCH(Q$2,Inputs!$D$2:$AG$2,0)),Inputs!$B$4:$B$200,$B7)/1000) -> -1046.012 | R7: =IF(COUNT(N7:Q7)=4,SUM(N7:Q7),"") -> -2237.766 | S7: =IF(S$3=0,"",SUMIFS(INDEX(Inputs!$D$4:$AG$200,0,MATCH(S$2,Inputs!$D$2:$AG$2,0)),Inputs!$B$4:$B$200,$B7)/1000) -> -447.855 | T7: =IF(T$3=0,"",SUMIFS(INDEX(Inputs!$D$4:$AG$200,0,MATCH(T$2,Inputs!$D$2:$AG$2,0)),Inputs!$B$4:$B$200,$B7)/1000) -> -522.034 | U7: =IF(U$3=0,"",SUMIFS(INDEX(Inputs!$D$4:$AG$200,0,MATCH(U$2,Inputs!$D$2:$AG$2,0)),Inputs!$B$4:$B$200,$B7)/1000) -> -551.278 | V7: =IF(V$3=0,"",SUMIFS(INDEX(Inputs!$D$4:$AG$200,0,MATCH(V$2,Inputs!$D$2:$AG$2,0)),Inputs!$B$4:$B$200,$B7)/1000) -> -559.351 | W7: =IF(COUNT(S7:V7)=4,SUM(S7:V7),"") -> -2080.518 | X7: =IF(X$3=0,"",SUMIFS(INDEX(Inputs!$D$4:$AG$200,0,MATCH(X$2,Inputs!$D$2:$AG$2,0)),Inputs!$B$4:$B$200,$B7)/1000) -> -572.374 | Y7: =IF(Y$3=0,"",SUMIFS(INDEX(Inputs!$D$4:$AG$200,0,MATCH(Y$2,Inputs!$D$2:$AG$2,0)),Inputs!$B$4:$B$200,$B7)/1000) -> -593.733 | Z7: =IF(Z$3=0,"",SUMIFS(INDEX(Inputs!$D$4:$AG$200,0,MATCH(Z$2,Inputs!$D$2:$AG$2,0)),Inputs!$B$4:$B$200,$B7)/1000) -> -624.565 | AA7: =IF(AA$3=0,"",SUMIFS(INDEX(Inputs!$D$4:$AG$200,0,MATCH(AA$2,Inputs!$D$2:$AG$2,0)),Inputs!$B$4:$B$200,$B7)/1000) -> -639.35924 | AB7: =IF(COUNT(X7:AA7)=4,SUM(X7:AA7),"") -> -2430.0312 | AC7: =IF(AC$3=0,"",SUMIFS(INDEX(Inputs!$D$4:$AG$200,0,MATCH(AC$2,Inputs!$D$2:$AG$2,0)),Inputs!$B$4:$B$200,$B7)/1000) -> -650.58592 | AD7: =IF(AD$3=0,"",SUMIFS(INDEX(Inputs!$D$4:$AG$200,0,MATCH(AD$2,Inputs!$D$2:$AG$2,0)),Inputs!$B$4:$B$200,$B7)/1000) -> -671.56362 | AE7: =IF(AE$3=0,"",SUMIFS(INDEX(Inputs!$D$4:$AG$200,0,MATCH(AE$2,Inputs!$D$2:$AG$2,0)),Inputs!$B$4:$B$200,$B7)/1000) | AF7: =IF(AF$3=0,"",SUMIFS(INDEX(Inputs!$D$4:$AG$200,0,MATCH(AF$2,Inputs!$D$2:$AG$2,0)),Inputs!$B$4:$B$200,$B7)/1000) | AG7: =IF(COUNT(AC7:AF7)=4,SUM(AC7:AF7),"")
B8: 5 | C8: Interest Expense | D8: =IF(D$3=0,"",SUMIFS(INDEX(Inputs!$D$4:$AG$200,0,MATCH(D$2,Inputs!$D$2:$AG$2,0)),Inputs!$B$4:$B$200,$B8)/1000) -> -265.184 | E8: =IF(E$3=0,"",SUMIFS(INDEX(Inputs!$D$4:$AG$200,0,MATCH(E$2,Inputs!$D$2:$AG$2,0)),Inputs!$B$4:$B$200,$B8)/1000) -> 239.899 | F8: =IF(F$3=0,"",SUMIFS(INDEX(Inputs!$D$4:$AG$200,0,MATCH(F$2,Inputs!$D$2:$AG$2,0)),Inputs!$B$4:$B$200,$B8)/1000) -> -342.257 | G8: =IF(G$3=0,"",SUMIFS(INDEX(Inputs!$D$4:$AG$200,0,MATCH(G$2,Inputs!$D$2:$AG$2,0)),Inputs!$B$4:$B$200,$B8)/1000) -> -591.177 | H8: =IF(COUNT(D8:G8)=4,SUM(D8:G8),"") -> -958.719 | I8: =IF(I$3=0,"",SUMIFS(INDEX(Inputs!$D$4:$AG$200,0,MATCH(I$2,Inputs!$D$2:$AG$2,0)),Inputs!$B$4:$B$200,$B8)/1000) -> -394.958 | J8: =IF(J$3=0,"",SUMIFS(INDEX(Inputs!$D$4:$AG$200,0,MATCH(J$2,Inputs!$D$2:$AG$2,0)),Inputs!$B$4:$B$200,$B8)/1000) -> -515.803 | K8: =IF(K$3=0,"",SUMIFS(INDEX(Inputs!$D$4:$AG$200,0,MATCH(K$2,Inputs!$D$2:$AG$2,0)),Inputs!$B$4:$B$200,$B8)/1000) -> -637.391 | L8: =IF(L$3=0,"",SUMIFS(INDEX(Inputs!$D$4:$AG$200,0,MATCH(L$2,Inputs!$D$2:$AG$2,0)),Inputs!$B$4:$B$200,$B8)/1000) -> -662.277 | M8: =IF(COUNT(I8:L8)=4,SUM(I8:L8),"") -> -2210.429 | N8: =IF(N$3=0,"",SUMIFS(INDEX(Inputs!$D$4:$AG$200,0,MATCH(N$2,Inputs!$D$2:$AG$2,0)),Inputs!$B$4:$B$200,$B8)/1000) -> -615.278 | O8: =IF(O$3=0,"",SUMIFS(INDEX(Inputs!$D$4:$AG$200,0,MATCH(O$2,Inputs!$D$2:$AG$2,0)),Inputs!$B$4:$B$200,$B8)/1000) -> -551.559 | P8: =IF(P$3=0,"",SUMIFS(INDEX(Inputs!$D$4:$AG$200,0,MATCH(P$2,Inputs!$D$2:$AG$2,0)),Inputs!$B$4:$B$200,$B8)/1000) -> -590.177 | Q8: =IF(Q$3=0,"",SUMIFS(INDEX(Inputs!$D$4:$AG$200,0,MATCH(Q$2,Inputs!$D$2:$AG$2,0)),Inputs!$B$4:$B$200,$B8)/1000) -> -614.436 | R8: =IF(COUNT(N8:Q8)=4,SUM(N8:Q8),"") -> -2371.45 | S8: =IF(S$3=0,"",SUMIFS(INDEX(Inputs!$D$4:$AG$200,0,MATCH(S$2,Inputs!$D$2:$AG$2,0)),Inputs!$B$4:$B$200,$B8)/1000) -> -627.625 | T8: =IF(T$3=0,"",SUMIFS(INDEX(Inputs!$D$4:$AG$200,0,MATCH(T$2,Inputs!$D$2:$AG$2,0)),Inputs!$B$4:$B$200,$B8)/1000) -> -662.137 | U8: =IF(U$3=0,"",SUMIFS(INDEX(Inputs!$D$4:$AG$200,0,MATCH(U$2,Inputs!$D$2:$AG$2,0)),Inputs!$B$4:$B$200,$B8)/1000) -> -707.297 | V8: =IF(V$3=0,"",SUMIFS(INDEX(Inputs!$D$4:$AG$200,0,MATCH(V$2,Inputs!$D$2:$AG$2,0)),Inputs!$B$4:$B$200,$B8)/1000) -> -691.837 | W8: =IF(COUNT(S8:V8)=4,SUM(S8:V8),"") -> -2688.896 | X8: =IF(X$3=0,"",SUMIFS(INDEX(Inputs!$D$4:$AG$200,0,MATCH(X$2,Inputs!$D$2:$AG$2,0)),Inputs!$B$4:$B$200,$B8)/1000) -> -745.217 | Y8: =IF(Y$3=0,"",SUMIFS(INDEX(Inputs!$D$4:$AG$200,0,MATCH(Y$2,Inputs!$D$2:$AG$2,0)),Inputs!$B$4:$B$200,$B8)/1000) -> -792.778 | Z8: =IF(Z$3=0,"",SUMIFS(INDEX(Inputs!$D$4:$AG$200,0,MATCH(Z$2,Inputs!$D$2:$AG$2,0)),Inputs!$B$4:$B$200,$B8)/1000) -> -895.889 | AA8: =IF(AA$3=0,"",SUMIFS(INDEX(Inputs!$D$4:$AG$200,0,MATCH(AA$2,Inputs!$D$2:$AG$2,0)),Inputs!$B$4:$B$200,$B8)/1000) -> -1154.5137 | AB8: =IF(COUNT(X8:AA8)=4,SUM(X8:AA8),"") -> -3588.3977 | AC8: =IF(AC$3=0,"",SUMIFS(INDEX(Inputs!$D$4:$AG$200,0,MATCH(AC$2,Inputs!$D$2:$AG$2,0)),Inputs!$B$4:$B$200,$B8)/1000) -> -902.57786 | AD8: =IF(AD$3=0,"",SUMIFS(INDEX(Inputs!$D$4:$AG$200,0,MATCH(AD$2,Inputs!$D$2:$AG$2,0)),Inputs!$B$4:$B$200,$B8)/1000) -> -1000.7705 | AE8: =IF(AE$3=0,"",SUMIFS(INDEX(Inputs!$D$4:$AG$200,0,MATCH(AE$2,Inputs!$D$2:$AG$2,0)),Inputs!$B$4:$B$200,$B8)/1000) | AF8: =IF(AF$3=0,"",SUMIFS(INDEX(Inputs!$D$4:$AG$200,0,MATCH(AF$2,Inputs!$D$2:$AG$2,0)),Inputs!$B$4:$B$200,$B8)/1000) | AG8: =IF(COUNT(AC8:AF8)=4,SUM(AC8:AF8),"")
B9: 6 | C9: Nonoperating Income / (Loss) | D9: =IF(D$3=0,"",SUMIFS(INDEX(Inputs!$D$4:$AG$200,0,MATCH(D$2,Inputs!$D$2:$AG$2,0)),Inputs!$B$4:$B$200,$B9)/1000) -> 188.526 | E9: =IF(E$3=0,"",SUMIFS(INDEX(Inputs!$D$4:$AG$200,0,MATCH(E$2,Inputs!$D$2:$AG$2,0)),Inputs!$B$4:$B$200,$B9)/1000) -> -307.323 | F9: =IF(F$3=0,"",SUMIFS(INDEX(Inputs!$D$4:$AG$200,0,MATCH(F$2,Inputs!$D$2:$AG$2,0)),Inputs!$B$4:$B$200,$B9)/1000) -> 209.511 | G9: =IF(G$3=0,"",SUMIFS(INDEX(Inputs!$D$4:$AG$200,0,MATCH(G$2,Inputs!$D$2:$AG$2,0)),Inputs!$B$4:$B$200,$B9)/1000) -> 383.039 | H9: =IF(COUNT(D9:G9)=4,SUM(D9:G9),"") -> 473.753 | I9: =IF(I$3=0,"",SUMIFS(INDEX(Inputs!$D$4:$AG$200,0,MATCH(I$2,Inputs!$D$2:$AG$2,0)),Inputs!$B$4:$B$200,$B9)/1000) -> 107.671 | J9: =IF(J$3=0,"",SUMIFS(INDEX(Inputs!$D$4:$AG$200,0,MATCH(J$2,Inputs!$D$2:$AG$2,0)),Inputs!$B$4:$B$200,$B9)/1000) -> 116.444 | K9: =IF(K$3=0,"",SUMIFS(INDEX(Inputs!$D$4:$AG$200,0,MATCH(K$2,Inputs!$D$2:$AG$2,0)),Inputs!$B$4:$B$200,$B9)/1000) -> 123.724 | L9: =IF(L$3=0,"",SUMIFS(INDEX(Inputs!$D$4:$AG$200,0,MATCH(L$2,Inputs!$D$2:$AG$2,0)),Inputs!$B$4:$B$200,$B9)/1000) -> 161.251 | M9: =IF(COUNT(I9:L9)=4,SUM(I9:L9),"") -> 509.09 | N9: =IF(N$3=0,"",SUMIFS(INDEX(Inputs!$D$4:$AG$200,0,MATCH(N$2,Inputs!$D$2:$AG$2,0)),Inputs!$B$4:$B$200,$B9)/1000) -> 140.596 | O9: =IF(O$3=0,"",SUMIFS(INDEX(Inputs!$D$4:$AG$200,0,MATCH(O$2,Inputs!$D$2:$AG$2,0)),Inputs!$B$4:$B$200,$B9)/1000) -> 25.985 | P9: =IF(P$3=0,"",SUMIFS(INDEX(Inputs!$D$4:$AG$200,0,MATCH(P$2,Inputs!$D$2:$AG$2,0)),Inputs!$B$4:$B$200,$B9)/1000) -> 47.438 | Q9: =IF(Q$3=0,"",SUMIFS(INDEX(Inputs!$D$4:$AG$200,0,MATCH(Q$2,Inputs!$D$2:$AG$2,0)),Inputs!$B$4:$B$200,$B9)/1000) -> 59.055 | R9: =IF(COUNT(N9:Q9)=4,SUM(N9:Q9),"") -> 273.074 | S9: =IF(S$3=0,"",SUMIFS(INDEX(Inputs!$D$4:$AG$200,0,MATCH(S$2,Inputs!$D$2:$AG$2,0)),Inputs!$B$4:$B$200,$B9)/1000) -> 88.865 | T9: =IF(T$3=0,"",SUMIFS(INDEX(Inputs!$D$4:$AG$200,0,MATCH(T$2,Inputs!$D$2:$AG$2,0)),Inputs!$B$4:$B$200,$B9)/1000) -> 91.414 | U9: =IF(U$3=0,"",SUMIFS(INDEX(Inputs!$D$4:$AG$200,0,MATCH(U$2,Inputs!$D$2:$AG$2,0)),Inputs!$B$4:$B$200,$B9)/1000) -> 112.895 | V9: =IF(V$3=0,"",SUMIFS(INDEX(Inputs!$D$4:$AG$200,0,MATCH(V$2,Inputs!$D$2:$AG$2,0)),Inputs!$B$4:$B$200,$B9)/1000) -> 85.172 | W9: =IF(COUNT(S9:V9)=4,SUM(S9:V9),"") -> 378.346 | X9: =IF(X$3=0,"",SUMIFS(INDEX(Inputs!$D$4:$AG$200,0,MATCH(X$2,Inputs!$D$2:$AG$2,0)),Inputs!$B$4:$B$200,$B9)/1000) -> 90.007 | Y9: =IF(Y$3=0,"",SUMIFS(INDEX(Inputs!$D$4:$AG$200,0,MATCH(Y$2,Inputs!$D$2:$AG$2,0)),Inputs!$B$4:$B$200,$B9)/1000) -> 98.699 | Z9: =IF(Z$3=0,"",SUMIFS(INDEX(Inputs!$D$4:$AG$200,0,MATCH(Z$2,Inputs!$D$2:$AG$2,0)),Inputs!$B$4:$B$200,$B9)/1000) -> 100.571 | AA9: =IF(AA$3=0,"",SUMIFS(INDEX(Inputs!$D$4:$AG$200,0,MATCH(AA$2,Inputs!$D$2:$AG$2,0)),Inputs!$B$4:$B$200,$B9)/1000) -> 390.59191 | AB9: =IF(COUNT(X9:AA9)=4,SUM(X9:AA9),"") -> 679.86891 | AC9: =IF(AC$3=0,"",SUMIFS(INDEX(Inputs!$D$4:$AG$200,0,MATCH(AC$2,Inputs!$D$2:$AG$2,0)),Inputs!$B$4:$B$200,$B9)/1000) -> 148.79541 | AD9: =IF(AD$3=0,"",SUMIFS(INDEX(Inputs!$D$4:$AG$200,0,MATCH(AD$2,Inputs!$D$2:$AG$2,0)),Inputs!$B$4:$B$200,$B9)/1000) -> 155.13569 | AE9: =IF(AE$3=0,"",SUMIFS(INDEX(Inputs!$D$4:$AG$200,0,MATCH(AE$2,Inputs!$D$2:$AG$2,0)),Inputs!$B$4:$B$200,$B9)/1000) | AF9: =IF(AF$3=0,"",SUMIFS(INDEX(Inputs!$D$4:$AG$200,0,MATCH(AF$2,Inputs!$D$2:$AG$2,0)),Inputs!$B$4:$B$200,$B9)/1000) | AG9: =IF(COUNT(AC9:AF9)=4,SUM(AC9:AF9),"")
B10: 7 | C10: Taxes | D10: =IF(D$3=0,"",SUMIFS(INDEX(Inputs!$D$4:$AG$200,0,MATCH(D$2,Inputs!$D$2:$AG$2,0)),Inputs!$B$4:$B$200,$B10)/1000) -> -56.185 | E10: =IF(E$3=0,"",SUMIFS(INDEX(Inputs!$D$4:$AG$200,0,MATCH(E$2,Inputs!$D$2:$AG$2,0)),Inputs!$B$4:$B$200,$B10)/1000) -> -74.183 | F10: =IF(F$3=0,"",SUMIFS(INDEX(Inputs!$D$4:$AG$200,0,MATCH(F$2,Inputs!$D$2:$AG$2,0)),Inputs!$B$4:$B$200,$B10)/1000) -> -110.575 | G10: =IF(G$3=0,"",SUMIFS(INDEX(Inputs!$D$4:$AG$200,0,MATCH(G$2,Inputs!$D$2:$AG$2,0)),Inputs!$B$4:$B$200,$B10)/1000) -> -121.387 | H10: =IF(COUNT(D10:G10)=4,SUM(D10:G10),"") -> -362.33 | I10: =IF(I$3=0,"",SUMIFS(INDEX(Inputs!$D$4:$AG$200,0,MATCH(I$2,Inputs!$D$2:$AG$2,0)),Inputs!$B$4:$B$200,$B10)/1000) -> -104.904 | J10: =IF(J$3=0,"",SUMIFS(INDEX(Inputs!$D$4:$AG$200,0,MATCH(J$2,Inputs!$D$2:$AG$2,0)),Inputs!$B$4:$B$200,$B10)/1000) -> -78.228 | K10: =IF(K$3=0,"",SUMIFS(INDEX(Inputs!$D$4:$AG$200,0,MATCH(K$2,Inputs!$D$2:$AG$2,0)),Inputs!$B$4:$B$200,$B10)/1000) -> -17.428 | L10: =IF(L$3=0,"",SUMIFS(INDEX(Inputs!$D$4:$AG$200,0,MATCH(L$2,Inputs!$D$2:$AG$2,0)),Inputs!$B$4:$B$200,$B10)/1000) -> 41.556 | M10: =IF(COUNT(I10:L10)=4,SUM(I10:L10),"") -> -159.004 | N10: =IF(N$3=0,"",SUMIFS(INDEX(Inputs!$D$4:$AG$200,0,MATCH(N$2,Inputs!$D$2:$AG$2,0)),Inputs!$B$4:$B$200,$B10)/1000) -> 10.417 | O10: =IF(O$3=0,"",SUMIFS(INDEX(Inputs!$D$4:$AG$200,0,MATCH(O$2,Inputs!$D$2:$AG$2,0)),Inputs!$B$4:$B$200,$B10)/1000) -> 6.673 | P10: =IF(P$3=0,"",SUMIFS(INDEX(Inputs!$D$4:$AG$200,0,MATCH(P$2,Inputs!$D$2:$AG$2,0)),Inputs!$B$4:$B$200,$B10)/1000) -> 21.858 | Q10: =IF(Q$3=0,"",SUMIFS(INDEX(Inputs!$D$4:$AG$200,0,MATCH(Q$2,Inputs!$D$2:$AG$2,0)),Inputs!$B$4:$B$200,$B10)/1000) -> 147.011 | R10: =IF(COUNT(N10:Q10)=4,SUM(N10:Q10),"") -> 185.959 | S10: =IF(S$3=0,"",SUMIFS(INDEX(Inputs!$D$4:$AG$200,0,MATCH(S$2,Inputs!$D$2:$AG$2,0)),Inputs!$B$4:$B$200,$B10)/1000) -> -24.287 | T10: =IF(T$3=0,"",SUMIFS(INDEX(Inputs!$D$4:$AG$200,0,MATCH(T$2,Inputs!$D$2:$AG$2,0)),Inputs!$B$4:$B$200,$B10)/1000) -> -14.056 | U10: =IF(U$3=0,"",SUMIFS(INDEX(Inputs!$D$4:$AG$200,0,MATCH(U$2,Inputs!$D$2:$AG$2,0)),Inputs!$B$4:$B$200,$B10)/1000) -> -23.602 | V10: =IF(V$3=0,"",SUMIFS(INDEX(Inputs!$D$4:$AG$200,0,MATCH(V$2,Inputs!$D$2:$AG$2,0)),Inputs!$B$4:$B$200,$B10)/1000) -> -16.094 | W10: =IF(COUNT(S10:V10)=4,SUM(S10:V10),"") -> -78.039 | X10: =IF(X$3=0,"",SUMIFS(INDEX(Inputs!$D$4:$AG$200,0,MATCH(X$2,Inputs!$D$2:$AG$2,0)),Inputs!$B$4:$B$200,$B10)/1000) -> -32.277 | Y10: =IF(Y$3=0,"",SUMIFS(INDEX(Inputs!$D$4:$AG$200,0,MATCH(Y$2,Inputs!$D$2:$AG$2,0)),Inputs!$B$4:$B$200,$B10)/1000) -> -23.716 | Z10: =IF(Z$3=0,"",SUMIFS(INDEX(Inputs!$D$4:$AG$200,0,MATCH(Z$2,Inputs!$D$2:$AG$2,0)),Inputs!$B$4:$B$200,$B10)/1000) -> 11.181 | AA10: =IF(AA$3=0,"",SUMIFS(INDEX(Inputs!$D$4:$AG$200,0,MATCH(AA$2,Inputs!$D$2:$AG$2,0)),Inputs!$B$4:$B$200,$B10)/1000) -> 15.574833 | AB10: =IF(COUNT(X10:AA10)=4,SUM(X10:AA10),"") -> -29.237167 | AC10: =IF(AC$3=0,"",SUMIFS(INDEX(Inputs!$D$4:$AG$200,0,MATCH(AC$2,Inputs!$D$2:$AG$2,0)),Inputs!$B$4:$B$200,$B10)/1000) -> -39.782999 | AD10: =IF(AD$3=0,"",SUMIFS(INDEX(Inputs!$D$4:$AG$200,0,MATCH(AD$2,Inputs!$D$2:$AG$2,0)),Inputs!$B$4:$B$200,$B10)/1000) -> -33.895472 | AE10: =IF(AE$3=0,"",SUMIFS(INDEX(Inputs!$D$4:$AG$200,0,MATCH(AE$2,Inputs!$D$2:$AG$2,0)),Inputs!$B$4:$B$200,$B10)/1000) | AF10: =IF(AF$3=0,"",SUMIFS(INDEX(Inputs!$D$4:$AG$200,0,MATCH(AF$2,Inputs!$D$2:$AG$2,0)),Inputs!$B$4:$B$200,$B10)/1000) | AG10: =IF(COUNT(AC10:AF10)=4,SUM(AC10:AF10),"")
B11: 8 | C11: Equity in Income of Affiliates, after tax (enter as +) | D11: =IF(D$3=0,"",SUMIFS(INDEX(Inputs!$D$4:$AG$200,0,MATCH(D$2,Inputs!$D$2:$AG$2,0)),Inputs!$B$4:$B$200,$B11)/1000) -> 0 | E11: =IF(E$3=0,"",SUMIFS(INDEX(Inputs!$D$4:$AG$200,0,MATCH(E$2,Inputs!$D$2:$AG$2,0)),Inputs!$B$4:$B$200,$B11)/1000) -> 0 | F11: =IF(F$3=0,"",SUMIFS(INDEX(Inputs!$D$4:$AG$200,0,MATCH(F$2,Inputs!$D$2:$AG$2,0)),Inputs!$B$4:$B$200,$B11)/1000) -> 0 | G11: =IF(G$3=0,"",SUMIFS(INDEX(Inputs!$D$4:$AG$200,0,MATCH(G$2,Inputs!$D$2:$AG$2,0)),Inputs!$B$4:$B$200,$B11)/1000) -> 0 | H11: =IF(COUNT(D11:G11)=4,SUM(D11:G11),"") -> 0 | I11: =IF(I$3=0,"",SUMIFS(INDEX(Inputs!$D$4:$AG$200,0,MATCH(I$2,Inputs!$D$2:$AG$2,0)),Inputs!$B$4:$B$200,$B11)/1000) -> 0 | J11: =IF(J$3=0,"",SUMIFS(INDEX(Inputs!$D$4:$AG$200,0,MATCH(J$2,Inputs!$D$2:$AG$2,0)),Inputs!$B$4:$B$200,$B11)/1000) -> 0 | K11: =IF(K$3=0,"",SUMIFS(INDEX(Inputs!$D$4:$AG$200,0,MATCH(K$2,Inputs!$D$2:$AG$2,0)),Inputs!$B$4:$B$200,$B11)/1000) -> 0 | L11: =IF(L$3=0,"",SUMIFS(INDEX(Inputs!$D$4:$AG$200,0,MATCH(L$2,Inputs!$D$2:$AG$2,0)),Inputs!$B$4:$B$200,$B11)/1000) -> 0 | M11: =IF(COUNT(I11:L11)=4,SUM(I11:L11),"") -> 0 | N11: =IF(N$3=0,"",SUMIFS(INDEX(Inputs!$D$4:$AG$200,0,MATCH(N$2,Inputs!$D$2:$AG$2,0)),Inputs!$B$4:$B$200,$B11)/1000) -> 0 | O11: =IF(O$3=0,"",SUMIFS(INDEX(Inputs!$D$4:$AG$200,0,MATCH(O$2,Inputs!$D$2:$AG$2,0)),Inputs!$B$4:$B$200,$B11)/1000) -> 0 | P11: =IF(P$3=0,"",SUMIFS(INDEX(Inputs!$D$4:$AG$200,0,MATCH(P$2,Inputs!$D$2:$AG$2,0)),Inputs!$B$4:$B$200,$B11)/1000) -> 0 | Q11: =IF(Q$3=0,"",SUMIFS(INDEX(Inputs!$D$4:$AG$200,0,MATCH(Q$2,Inputs!$D$2:$AG$2,0)),Inputs!$B$4:$B$200,$B11)/1000) -> 0 | R11: =IF(COUNT(N11:Q11)=4,SUM(N11:Q11),"") -> 0 | S11: =IF(S$3=0,"",SUMIFS(INDEX(Inputs!$D$4:$AG$200,0,MATCH(S$2,Inputs!$D$2:$AG$2,0)),Inputs!$B$4:$B$200,$B11)/1000) -> 0 | T11: =IF(T$3=0,"",SUMIFS(INDEX(Inputs!$D$4:$AG$200,0,MATCH(T$2,Inputs!$D$2:$AG$2,0)),Inputs!$B$4:$B$200,$B11)/1000) -> 0 | U11: =IF(U$3=0,"",SUMIFS(INDEX(Inputs!$D$4:$AG$200,0,MATCH(U$2,Inputs!$D$2:$AG$2,0)),Inputs!$B$4:$B$200,$B11)/1000) -> 0 | V11: =IF(V$3=0,"",SUMIFS(INDEX(Inputs!$D$4:$AG$200,0,MATCH(V$2,Inputs!$D$2:$AG$2,0)),Inputs!$B$4:$B$200,$B11)/1000) -> 0 | W11: =IF(COUNT(S11:V11)=4,SUM(S11:V11),"") -> 0 | X11: =IF(X$3=0,"",SUMIFS(INDEX(Inputs!$D$4:$AG$200,0,MATCH(X$2,Inputs!$D$2:$AG$2,0)),Inputs!$B$4:$B$200,$B11)/1000) -> 0 | Y11: =IF(Y$3=0,"",SUMIFS(INDEX(Inputs!$D$4:$AG$200,0,MATCH(Y$2,Inputs!$D$2:$AG$2,0)),Inputs!$B$4:$B$200,$B11)/1000) -> 0 | Z11: =IF(Z$3=0,"",SUMIFS(INDEX(Inputs!$D$4:$AG$200,0,MATCH(Z$2,Inputs!$D$2:$AG$2,0)),Inputs!$B$4:$B$200,$B11)/1000) -> 0 | AA11: =IF(AA$3=0,"",SUMIFS(INDEX(Inputs!$D$4:$AG$200,0,MATCH(AA$2,Inputs!$D$2:$AG$2,0)),Inputs!$B$4:$B$200,$B11)/1000) -> 0 | AB11: =IF(COUNT(X11:AA11)=4,SUM(X11:AA11),"") -> 0 | AC11: =IF(AC$3=0,"",SUMIFS(INDEX(Inputs!$D$4:$AG$200,0,MATCH(AC$2,Inputs!$D$2:$AG$2,0)),Inputs!$B$4:$B$200,$B11)/1000) -> 0 | AD11: =IF(AD$3=0,"",SUMIFS(INDEX(Inputs!$D$4:$AG$200,0,MATCH(AD$2,Inputs!$D$2:$AG$2,0)),Inputs!$B$4:$B$200,$B11)/1000) -> 0 | AE11: =IF(AE$3=0,"",SUMIFS(INDEX(Inputs!$D$4:$AG$200,0,MATCH(AE$2,Inputs!$D$2:$AG$2,0)),Inputs!$B$4:$B$200,$B11)/1000) | AF11: =IF(AF$3=0,"",SUMIFS(INDEX(Inputs!$D$4:$AG$200,0,MATCH(AF$2,Inputs!$D$2:$AG$2,0)),Inputs!$B$4:$B$200,$B11)/1000) | AG11: =IF(COUNT(AC11:AF11)=4,SUM(AC11:AF11),"")
B12: 9 | C12: Minority Interest Expense, after tax (enter as - ) | D12: =IF(D$3=0,"",SUMIFS(INDEX(Inputs!$D$4:$AG$200,0,MATCH(D$2,Inputs!$D$2:$AG$2,0)),Inputs!$B$4:$B$200,$B12)/1000) -> 0 | E12: =IF(E$3=0,"",SUMIFS(INDEX(Inputs!$D$4:$AG$200,0,MATCH(E$2,Inputs!$D$2:$AG$2,0)),Inputs!$B$4:$B$200,$B12)/1000) -> 0 | F12: =IF(F$3=0,"",SUMIFS(INDEX(Inputs!$D$4:$AG$200,0,MATCH(F$2,Inputs!$D$2:$AG$2,0)),Inputs!$B$4:$B$200,$B12)/1000) -> 0 | G12: =IF(G$3=0,"",SUMIFS(INDEX(Inputs!$D$4:$AG$200,0,MATCH(G$2,Inputs!$D$2:$AG$2,0)),Inputs!$B$4:$B$200,$B12)/1000) -> 0 | H12: =IF(COUNT(D12:G12)=4,SUM(D12:G12),"") -> 0 | I12: =IF(I$3=0,"",SUMIFS(INDEX(Inputs!$D$4:$AG$200,0,MATCH(I$2,Inputs!$D$2:$AG$2,0)),Inputs!$B$4:$B$200,$B12)/1000) -> 0 | J12: =IF(J$3=0,"",SUMIFS(INDEX(Inputs!$D$4:$AG$200,0,MATCH(J$2,Inputs!$D$2:$AG$2,0)),Inputs!$B$4:$B$200,$B12)/1000) -> 0 | K12: =IF(K$3=0,"",SUMIFS(INDEX(Inputs!$D$4:$AG$200,0,MATCH(K$2,Inputs!$D$2:$AG$2,0)),Inputs!$B$4:$B$200,$B12)/1000) -> 0 | L12: =IF(L$3=0,"",SUMIFS(INDEX(Inputs!$D$4:$AG$200,0,MATCH(L$2,Inputs!$D$2:$AG$2,0)),Inputs!$B$4:$B$200,$B12)/1000) -> 0 | M12: =IF(COUNT(I12:L12)=4,SUM(I12:L12),"") -> 0 | N12: =IF(N$3=0,"",SUMIFS(INDEX(Inputs!$D$4:$AG$200,0,MATCH(N$2,Inputs!$D$2:$AG$2,0)),Inputs!$B$4:$B$200,$B12)/1000) -> 0 | O12: =IF(O$3=0,"",SUMIFS(INDEX(Inputs!$D$4:$AG$200,0,MATCH(O$2,Inputs!$D$2:$AG$2,0)),Inputs!$B$4:$B$200,$B12)/1000) -> 0 | P12: =IF(P$3=0,"",SUMIFS(INDEX(Inputs!$D$4:$AG$200,0,MATCH(P$2,Inputs!$D$2:$AG$2,0)),Inputs!$B$4:$B$200,$B12)/1000) -> 0 | Q12: =IF(Q$3=0,"",SUMIFS(INDEX(Inputs!$D$4:$AG$200,0,MATCH(Q$2,Inputs!$D$2:$AG$2,0)),Inputs!$B$4:$B$200,$B12)/1000) -> 0 | R12: =IF(COUNT(N12:Q12)=4,SUM(N12:Q12),"") -> 0 | S12: =IF(S$3=0,"",SUMIFS(INDEX(Inputs!$D$4:$AG$200,0,MATCH(S$2,Inputs!$D$2:$AG$2,0)),Inputs!$B$4:$B$200,$B12)/1000) -> 0 | T12: =IF(T$3=0,"",SUMIFS(INDEX(Inputs!$D$4:$AG$200,0,MATCH(T$2,Inputs!$D$2:$AG$2,0)),Inputs!$B$4:$B$200,$B12)/1000) -> 0 | U12: =IF(U$3=0,"",SUMIFS(INDEX(Inputs!$D$4:$AG$200,0,MATCH(U$2,Inputs!$D$2:$AG$2,0)),Inputs!$B$4:$B$200,$B12)/1000) -> 0 | V12: =IF(V$3=0,"",SUMIFS(INDEX(Inputs!$D$4:$AG$200,0,MATCH(V$2,Inputs!$D$2:$AG$2,0)),Inputs!$B$4:$B$200,$B12)/1000) -> 0 | W12: =IF(COUNT(S12:V12)=4,SUM(S12:V12),"") -> 0 | X12: =IF(X$3=0,"",SUMIFS(INDEX(Inputs!$D$4:$AG$200,0,MATCH(X$2,Inputs!$D$2:$AG$2,0)),Inputs!$B$4:$B$200,$B12)/1000) -> 0 | Y12: =IF(Y$3=0,"",SUMIFS(INDEX(Inputs!$D$4:$AG$200,0,MATCH(Y$2,Inputs!$D$2:$AG$2,0)),Inputs!$B$4:$B$200,$B12)/1000) -> 0 | Z12: =IF(Z$3=0,"",SUMIFS(INDEX(Inputs!$D$4:$AG$200,0,MATCH(Z$2,Inputs!$D$2:$AG$2,0)),Inputs!$B$4:$B$200,$B12)/1000) -> 0 | AA12: =IF(AA$3=0,"",SUMIFS(INDEX(Inputs!$D$4:$AG$200,0,MATCH(AA$2,Inputs!$D$2:$AG$2,0)),Inputs!$B$4:$B$200,$B12)/1000) -> 0 | AB12: =IF(COUNT(X12:AA12)=4,SUM(X12:AA12),"") -> 0 | AC12: =IF(AC$3=0,"",SUMIFS(INDEX(Inputs!$D$4:$AG$200,0,MATCH(AC$2,Inputs!$D$2:$AG$2,0)),Inputs!$B$4:$B$200,$B12)/1000) -> 0 | AD12: =IF(AD$3=0,"",SUMIFS(INDEX(Inputs!$D$4:$AG$200,0,MATCH(AD$2,Inputs!$D$2:$AG$2,0)),Inputs!$B$4:$B$200,$B12)/1000) -> 0 | AE12: =IF(AE$3=0,"",SUMIFS(INDEX(Inputs!$D$4:$AG$200,0,MATCH(AE$2,Inputs!$D$2:$AG$2,0)),Inputs!$B$4:$B$200,$B12)/1000) | AF12: =IF(AF$3=0,"",SUMIFS(INDEX(Inputs!$D$4:$AG$200,0,MATCH(AF$2,Inputs!$D$2:$AG$2,0)),Inputs!$B$4:$B$200,$B12)/1000) | AG12: =IF(COUNT(AC12:AF12)=4,SUM(AC12:AF12),"")
B13: 10 | C13: Common Dividends | D13: =IF(D$3=0,"",SUMIFS(INDEX(Inputs!$D$4:$AG$200,0,MATCH(D$2,Inputs!$D$2:$AG$2,0)),Inputs!$B$4:$B$200,$B13)/1000) -> 0 | E13: =IF(E$3=0,"",SUMIFS(INDEX(Inputs!$D$4:$AG$200,0,MATCH(E$2,Inputs!$D$2:$AG$2,0)),Inputs!$B$4:$B$200,$B13)/1000) -> 0 | F13: =IF(F$3=0,"",SUMIFS(INDEX(Inputs!$D$4:$AG$200,0,MATCH(F$2,Inputs!$D$2:$AG$2,0)),Inputs!$B$4:$B$200,$B13)/1000) -> -64.133 | G13: =IF(G$3=0,"",SUMIFS(INDEX(Inputs!$D$4:$AG$200,0,MATCH(G$2,Inputs!$D$2:$AG$2,0)),Inputs!$B$4:$B$200,$B13)/1000) -> -42.481 | H13: =IF(COUNT(D13:G13)=4,SUM(D13:G13),"") -> -106.614 | I13: =IF(I$3=0,"",SUMIFS(INDEX(Inputs!$D$4:$AG$200,0,MATCH(I$2,Inputs!$D$2:$AG$2,0)),Inputs!$B$4:$B$200,$B13)/1000) -> -39.311 | J13: =IF(J$3=0,"",SUMIFS(INDEX(Inputs!$D$4:$AG$200,0,MATCH(J$2,Inputs!$D$2:$AG$2,0)),Inputs!$B$4:$B$200,$B13)/1000) -> -309.347 | K13: =IF(K$3=0,"",SUMIFS(INDEX(Inputs!$D$4:$AG$200,0,MATCH(K$2,Inputs!$D$2:$AG$2,0)),Inputs!$B$4:$B$200,$B13)/1000) -> -46.849 | L13: =IF(L$3=0,"",SUMIFS(INDEX(Inputs!$D$4:$AG$200,0,MATCH(L$2,Inputs!$D$2:$AG$2,0)),Inputs!$B$4:$B$200,$B13)/1000) -> -52.131 | M13: =IF(COUNT(I13:L13)=4,SUM(I13:L13),"") -> -447.638 | N13: =IF(N$3=0,"",SUMIFS(INDEX(Inputs!$D$4:$AG$200,0,MATCH(N$2,Inputs!$D$2:$AG$2,0)),Inputs!$B$4:$B$200,$B13)/1000) -> -47.512 | O13: =IF(O$3=0,"",SUMIFS(INDEX(Inputs!$D$4:$AG$200,0,MATCH(O$2,Inputs!$D$2:$AG$2,0)),Inputs!$B$4:$B$200,$B13)/1000) -> -90.689 | P13: =IF(P$3=0,"",SUMIFS(INDEX(Inputs!$D$4:$AG$200,0,MATCH(P$2,Inputs!$D$2:$AG$2,0)),Inputs!$B$4:$B$200,$B13)/1000) -> 0.001 | Q13: =IF(Q$3=0,"",SUMIFS(INDEX(Inputs!$D$4:$AG$200,0,MATCH(Q$2,Inputs!$D$2:$AG$2,0)),Inputs!$B$4:$B$200,$B13)/1000) -> 0 | R13: =IF(COUNT(N13:Q13)=4,SUM(N13:Q13),"") -> -138.2 | S13: =IF(S$3=0,"",SUMIFS(INDEX(Inputs!$D$4:$AG$200,0,MATCH(S$2,Inputs!$D$2:$AG$2,0)),Inputs!$B$4:$B$200,$B13)/1000) -> 0 | T13: =IF(T$3=0,"",SUMIFS(INDEX(Inputs!$D$4:$AG$200,0,MATCH(T$2,Inputs!$D$2:$AG$2,0)),Inputs!$B$4:$B$200,$B13)/1000) -> 0 | U13: =IF(U$3=0,"",SUMIFS(INDEX(Inputs!$D$4:$AG$200,0,MATCH(U$2,Inputs!$D$2:$AG$2,0)),Inputs!$B$4:$B$200,$B13)/1000) -> 0 | V13: =IF(V$3=0,"",SUMIFS(INDEX(Inputs!$D$4:$AG$200,0,MATCH(V$2,Inputs!$D$2:$AG$2,0)),Inputs!$B$4:$B$200,$B13)/1000) -> 0 | W13: =IF(COUNT(S13:V13)=4,SUM(S13:V13),"") -> 0 | X13: =IF(X$3=0,"",SUMIFS(INDEX(Inputs!$D$4:$AG$200,0,MATCH(X$2,Inputs!$D$2:$AG$2,0)),Inputs!$B$4:$B$200,$B13)/1000) -> 0 | Y13: =IF(Y$3=0,"",SUMIFS(INDEX(Inputs!$D$4:$AG$200,0,MATCH(Y$2,Inputs!$D$2:$AG$2,0)),Inputs!$B$4:$B$200,$B13)/1000) -> -55.05 | Z13: =IF(Z$3=0,"",SUMIFS(INDEX(Inputs!$D$4:$AG$200,0,MATCH(Z$2,Inputs!$D$2:$AG$2,0)),Inputs!$B$4:$B$200,$B13)/1000) -> 0 | AA13: =IF(AA$3=0,"",SUMIFS(INDEX(Inputs!$D$4:$AG$200,0,MATCH(AA$2,Inputs!$D$2:$AG$2,0)),Inputs!$B$4:$B$200,$B13)/1000) -> 0 | AB13: =IF(COUNT(X13:AA13)=4,SUM(X13:AA13),"") -> -55.05 | AC13: =IF(AC$3=0,"",SUMIFS(INDEX(Inputs!$D$4:$AG$200,0,MATCH(AC$2,Inputs!$D$2:$AG$2,0)),Inputs!$B$4:$B$200,$B13)/1000) -> 0 | AD13: =IF(AD$3=0,"",SUMIFS(INDEX(Inputs!$D$4:$AG$200,0,MATCH(AD$2,Inputs!$D$2:$AG$2,0)),Inputs!$B$4:$B$200,$B13)/1000) -> 0 | AE13: =IF(AE$3=0,"",SUMIFS(INDEX(Inputs!$D$4:$AG$200,0,MATCH(AE$2,Inputs!$D$2:$AG$2,0)),Inputs!$B$4:$B$200,$B13)/1000) | AF13: =IF(AF$3=0,"",SUMIFS(INDEX(Inputs!$D$4:$AG$200,0,MATCH(AF$2,Inputs!$D$2:$AG$2,0)),Inputs!$B$4:$B$200,$B13)/1000) | AG13: =IF(COUNT(AC13:AF13)=4,SUM(AC13:AF13),"")
B15: 11 | C15: Cash and equivalents (inc. investment securities) | D15: =IF(D$3=0,"",SUMIFS(INDEX(Inputs!$D$4:$AG$200,0,MATCH(D$2,Inputs!$D$2:$AG$2,0)),Inputs!$B$4:$B$200,$B15)/1000) -> 5511.88 | E15: =IF(E$3=0,"",SUMIFS(INDEX(Inputs!$D$4:$AG$200,0,MATCH(E$2,Inputs!$D$2:$AG$2,0)),Inputs!$B$4:$B$200,$B15)/1000) -> 5556.755 | F15: =IF(F$3=0,"",SUMIFS(INDEX(Inputs!$D$4:$AG$200,0,MATCH(F$2,Inputs!$D$2:$AG$2,0)),Inputs!$B$4:$B$200,$B15)/1000) -> 8274.313 | G15: =IF(G$3=0,"",SUMIFS(INDEX(Inputs!$D$4:$AG$200,0,MATCH(G$2,Inputs!$D$2:$AG$2,0)),Inputs!$B$4:$B$200,$B15)/1000) -> 7786.453 | H15: =IF(G15="","",G15) -> 7786.453 | I15: =IF(I$3=0,"",SUMIFS(INDEX(Inputs!$D$4:$AG$200,0,MATCH(I$2,Inputs!$D$2:$AG$2,0)),Inputs!$B$4:$B$200,$B15)/1000) -> 5650.584 | J15: =IF(J$3=0,"",SUMIFS(INDEX(Inputs!$D$4:$AG$200,0,MATCH(J$2,Inputs!$D$2:$AG$2,0)),Inputs!$B$4:$B$200,$B15)/1000) -> 5722.697 | K15: =IF(K$3=0,"",SUMIFS(INDEX(Inputs!$D$4:$AG$200,0,MATCH(K$2,Inputs!$D$2:$AG$2,0)),Inputs!$B$4:$B$200,$B15)/1000) -> 7795.457 | L15: =IF(L$3=0,"",SUMIFS(INDEX(Inputs!$D$4:$AG$200,0,MATCH(L$2,Inputs!$D$2:$AG$2,0)),Inputs!$B$4:$B$200,$B15)/1000) -> 6827.535 | M15: =IF(L15="","",L15) -> 6827.535 | N15: =IF(N$3=0,"",SUMIFS(INDEX(Inputs!$D$4:$AG$200,0,MATCH(N$2,Inputs!$D$2:$AG$2,0)),Inputs!$B$4:$B$200,$B15)/1000) -> 3923.099 | O15: =IF(O$3=0,"",SUMIFS(INDEX(Inputs!$D$4:$AG$200,0,MATCH(O$2,Inputs!$D$2:$AG$2,0)),Inputs!$B$4:$B$200,$B15)/1000) -> 2577.866 | P15: =IF(P$3=0,"",SUMIFS(INDEX(Inputs!$D$4:$AG$200,0,MATCH(P$2,Inputs!$D$2:$AG$2,0)),Inputs!$B$4:$B$200,$B15)/1000) -> 2011.127 | Q15: =IF(Q$3=0,"",SUMIFS(INDEX(Inputs!$D$4:$AG$200,0,MATCH(Q$2,Inputs!$D$2:$AG$2,0)),Inputs!$B$4:$B$200,$B15)/1000) -> 2998.752 | R15: =IF(Q15="","",Q15) -> 2998.752 | S15: =IF(S$3=0,"",SUMIFS(INDEX(Inputs!$D$4:$AG$200,0,MATCH(S$2,Inputs!$D$2:$AG$2,0)),Inputs!$B$4:$B$200,$B15)/1000) -> 3211.286 | T15: =IF(T$3=0,"",SUMIFS(INDEX(Inputs!$D$4:$AG$200,0,MATCH(T$2,Inputs!$D$2:$AG$2,0)),Inputs!$B$4:$B$200,$B15)/1000) -> 3685.003 | U15: =IF(U$3=0,"",SUMIFS(INDEX(Inputs!$D$4:$AG$200,0,MATCH(U$2,Inputs!$D$2:$AG$2,0)),Inputs!$B$4:$B$200,$B15)/1000) -> 3975.719 | V15: =IF(V$3=0,"",SUMIFS(INDEX(Inputs!$D$4:$AG$200,0,MATCH(V$2,Inputs!$D$2:$AG$2,0)),Inputs!$B$4:$B$200,$B15)/1000) -> 4291.363 | W15: =IF(V15="","",V15) -> 4291.363 | X15: =IF(X$3=0,"",SUMIFS(INDEX(Inputs!$D$4:$AG$200,0,MATCH(X$2,Inputs!$D$2:$AG$2,0)),Inputs!$B$4:$B$200,$B15)/1000) -> 3037.195 | Y15: =IF(Y$3=0,"",SUMIFS(INDEX(Inputs!$D$4:$AG$200,0,MATCH(Y$2,Inputs!$D$2:$AG$2,0)),Inputs!$B$4:$B$200,$B15)/1000) -> 3441.64 | Z15: =IF(Z$3=0,"",SUMIFS(INDEX(Inputs!$D$4:$AG$200,0,MATCH(Z$2,Inputs!$D$2:$AG$2,0)),Inputs!$B$4:$B$200,$B15)/1000) -> 3319.489 | AA15: =IF(AA$3=0,"",SUMIFS(INDEX(Inputs!$D$4:$AG$200,0,MATCH(AA$2,Inputs!$D$2:$AG$2,0)),Inputs!$B$4:$B$200,$B15)/1000) -> 6875.395 | AB15: =IF(AA15="","",AA15) -> 6875.395 | AC15: =IF(AC$3=0,"",SUMIFS(INDEX(Inputs!$D$4:$AG$200,0,MATCH(AC$2,Inputs!$D$2:$AG$2,0)),Inputs!$B$4:$B$200,$B15)/1000) -> 8093.188 | AD15: =IF(AD$3=0,"",SUMIFS(INDEX(Inputs!$D$4:$AG$200,0,MATCH(AD$2,Inputs!$D$2:$AG$2,0)),Inputs!$B$4:$B$200,$B15)/1000) -> 7479.297 | AE15: =IF(AE$3=0,"",SUMIFS(INDEX(Inputs!$D$4:$AG$200,0,MATCH(AE$2,Inputs!$D$2:$AG$2,0)),Inputs!$B$4:$B$200,$B15)/1000) | AF15: =IF(AF$3=0,"",SUMIFS(INDEX(Inputs!$D$4:$AG$200,0,MATCH(AF$2,Inputs!$D$2:$AG$2,0)),Inputs!$B$4:$B$200,$B15)/1000) | AG15: =IF(AF15="","",AF15)
B16: 12 | C16: Accounts receivable | D16: =IF(D$3=0,"",SUMIFS(INDEX(Inputs!$D$4:$AG$200,0,MATCH(D$2,Inputs!$D$2:$AG$2,0)),Inputs!$B$4:$B$200,$B16)/1000) -> 450.38 | E16: =IF(E$3=0,"",SUMIFS(INDEX(Inputs!$D$4:$AG$200,0,MATCH(E$2,Inputs!$D$2:$AG$2,0)),Inputs!$B$4:$B$200,$B16)/1000) -> 553.695 | F16: =IF(F$3=0,"",SUMIFS(INDEX(Inputs!$D$4:$AG$200,0,MATCH(F$2,Inputs!$D$2:$AG$2,0)),Inputs!$B$4:$B$200,$B16)/1000) -> 634.363 | G16: =IF(G$3=0,"",SUMIFS(INDEX(Inputs!$D$4:$AG$200,0,MATCH(G$2,Inputs!$D$2:$AG$2,0)),Inputs!$B$4:$B$200,$B16)/1000) -> 887.067 | H16: =IF(G16="","",G16) -> 887.067 | I16: =IF(I$3=0,"",SUMIFS(INDEX(Inputs!$D$4:$AG$200,0,MATCH(I$2,Inputs!$D$2:$AG$2,0)),Inputs!$B$4:$B$200,$B16)/1000) -> 1077.835 | J16: =IF(J$3=0,"",SUMIFS(INDEX(Inputs!$D$4:$AG$200,0,MATCH(J$2,Inputs!$D$2:$AG$2,0)),Inputs!$B$4:$B$200,$B16)/1000) -> 1285.905 | K16: =IF(K$3=0,"",SUMIFS(INDEX(Inputs!$D$4:$AG$200,0,MATCH(K$2,Inputs!$D$2:$AG$2,0)),Inputs!$B$4:$B$200,$B16)/1000) -> 1046.048 | L16: =IF(L$3=0,"",SUMIFS(INDEX(Inputs!$D$4:$AG$200,0,MATCH(L$2,Inputs!$D$2:$AG$2,0)),Inputs!$B$4:$B$200,$B16)/1000) -> 1175.734 | M16: =IF(L16="","",L16) -> 1175.734 | N16: =IF(N$3=0,"",SUMIFS(INDEX(Inputs!$D$4:$AG$200,0,MATCH(N$2,Inputs!$D$2:$AG$2,0)),Inputs!$B$4:$B$200,$B16)/1000) -> 1027.01 | O16: =IF(O$3=0,"",SUMIFS(INDEX(Inputs!$D$4:$AG$200,0,MATCH(O$2,Inputs!$D$2:$AG$2,0)),Inputs!$B$4:$B$200,$B16)/1000) -> 1100.969 | P16: =IF(P$3=0,"",SUMIFS(INDEX(Inputs!$D$4:$AG$200,0,MATCH(P$2,Inputs!$D$2:$AG$2,0)),Inputs!$B$4:$B$200,$B16)/1000) -> 1312.302 | Q16: =IF(Q$3=0,"",SUMIFS(INDEX(Inputs!$D$4:$AG$200,0,MATCH(Q$2,Inputs!$D$2:$AG$2,0)),Inputs!$B$4:$B$200,$B16)/1000) -> 1345.413 | R16: =IF(Q16="","",Q16) -> 1345.413 | S16: =IF(S$3=0,"",SUMIFS(INDEX(Inputs!$D$4:$AG$200,0,MATCH(S$2,Inputs!$D$2:$AG$2,0)),Inputs!$B$4:$B$200,$B16)/1000) -> 1542.65 | T16: =IF(T$3=0,"",SUMIFS(INDEX(Inputs!$D$4:$AG$200,0,MATCH(T$2,Inputs!$D$2:$AG$2,0)),Inputs!$B$4:$B$200,$B16)/1000) -> 1684.031 | U16: =IF(U$3=0,"",SUMIFS(INDEX(Inputs!$D$4:$AG$200,0,MATCH(U$2,Inputs!$D$2:$AG$2,0)),Inputs!$B$4:$B$200,$B16)/1000) -> 1736.984 | V16: =IF(V$3=0,"",SUMIFS(INDEX(Inputs!$D$4:$AG$200,0,MATCH(V$2,Inputs!$D$2:$AG$2,0)),Inputs!$B$4:$B$200,$B16)/1000) -> 1441.696 | W16: =IF(V16="","",V16) -> 1441.696 | X16: =IF(X$3=0,"",SUMIFS(INDEX(Inputs!$D$4:$AG$200,0,MATCH(X$2,Inputs!$D$2:$AG$2,0)),Inputs!$B$4:$B$200,$B16)/1000) -> 2193.313 | Y16: =IF(Y$3=0,"",SUMIFS(INDEX(Inputs!$D$4:$AG$200,0,MATCH(Y$2,Inputs!$D$2:$AG$2,0)),Inputs!$B$4:$B$200,$B16)/1000) -> 2186.188 | Z16: =IF(Z$3=0,"",SUMIFS(INDEX(Inputs!$D$4:$AG$200,0,MATCH(Z$2,Inputs!$D$2:$AG$2,0)),Inputs!$B$4:$B$200,$B16)/1000) -> 2216.549 | AA16: =IF(AA$3=0,"",SUMIFS(INDEX(Inputs!$D$4:$AG$200,0,MATCH(AA$2,Inputs!$D$2:$AG$2,0)),Inputs!$B$4:$B$200,$B16)/1000) -> 1989.681 | AB16: =IF(AA16="","",AA16) -> 1989.681 | AC16: =IF(AC$3=0,"",SUMIFS(INDEX(Inputs!$D$4:$AG$200,0,MATCH(AC$2,Inputs!$D$2:$AG$2,0)),Inputs!$B$4:$B$200,$B16)/1000) -> 2184.584 | AD16: =IF(AD$3=0,"",SUMIFS(INDEX(Inputs!$D$4:$AG$200,0,MATCH(AD$2,Inputs!$D$2:$AG$2,0)),Inputs!$B$4:$B$200,$B16)/1000) -> 2309.874 | AE16: =IF(AE$3=0,"",SUMIFS(INDEX(Inputs!$D$4:$AG$200,0,MATCH(AE$2,Inputs!$D$2:$AG$2,0)),Inputs!$B$4:$B$200,$B16)/1000) | AF16: =IF(AF$3=0,"",SUMIFS(INDEX(Inputs!$D$4:$AG$200,0,MATCH(AF$2,Inputs!$D$2:$AG$2,0)),Inputs!$B$4:$B$200,$B16)/1000) | AG16: =IF(AF16="","",AF16)
B17: 13 | C17: Inventories | D17: =IF(D$3=0,"",SUMIFS(INDEX(Inputs!$D$4:$AG$200,0,MATCH(D$2,Inputs!$D$2:$AG$2,0)),Inputs!$B$4:$B$200,$B17)/1000) -> 0 | E17: =IF(E$3=0,"",SUMIFS(INDEX(Inputs!$D$4:$AG$200,0,MATCH(E$2,Inputs!$D$2:$AG$2,0)),Inputs!$B$4:$B$200,$B17)/1000) -> 0 | F17: =IF(F$3=0,"",SUMIFS(INDEX(Inputs!$D$4:$AG$200,0,MATCH(F$2,Inputs!$D$2:$AG$2,0)),Inputs!$B$4:$B$200,$B17)/1000) -> 0 | G17: =IF(G$3=0,"",SUMIFS(INDEX(Inputs!$D$4:$AG$200,0,MATCH(G$2,Inputs!$D$2:$AG$2,0)),Inputs!$B$4:$B$200,$B17)/1000) -> 0 | H17: =IF(G17="","",G17) -> 0 | I17: =IF(I$3=0,"",SUMIFS(INDEX(Inputs!$D$4:$AG$200,0,MATCH(I$2,Inputs!$D$2:$AG$2,0)),Inputs!$B$4:$B$200,$B17)/1000) -> 0 | J17: =IF(J$3=0,"",SUMIFS(INDEX(Inputs!$D$4:$AG$200,0,MATCH(J$2,Inputs!$D$2:$AG$2,0)),Inputs!$B$4:$B$200,$B17)/1000) -> 0 | K17: =IF(K$3=0,"",SUMIFS(INDEX(Inputs!$D$4:$AG$200,0,MATCH(K$2,Inputs!$D$2:$AG$2,0)),Inputs!$B$4:$B$200,$B17)/1000) -> 0 | L17: =IF(L$3=0,"",SUMIFS(INDEX(Inputs!$D$4:$AG$200,0,MATCH(L$2,Inputs!$D$2:$AG$2,0)),Inputs!$B$4:$B$200,$B17)/1000) -> 0 | M17: =IF(L17="","",L17) -> 0 | N17: =IF(N$3=0,"",SUMIFS(INDEX(Inputs!$D$4:$AG$200,0,MATCH(N$2,Inputs!$D$2:$AG$2,0)),Inputs!$B$4:$B$200,$B17)/1000) -> 0 | O17: =IF(O$3=0,"",SUMIFS(INDEX(Inputs!$D$4:$AG$200,0,MATCH(O$2,Inputs!$D$2:$AG$2,0)),Inputs!$B$4:$B$200,$B17)/1000) -> 0 | P17: =IF(P$3=0,"",SUMIFS(INDEX(Inputs!$D$4:$AG$200,0,MATCH(P$2,Inputs!$D$2:$AG$2,0)),Inputs!$B$4:$B$200,$B17)/1000) -> 0 | Q17: =IF(Q$3=0,"",SUMIFS(INDEX(Inputs!$D$4:$AG$200,0,MATCH(Q$2,Inputs!$D$2:$AG$2,0)),Inputs!$B$4:$B$200,$B17)/1000) -> 0 | R17: =IF(Q17="","",Q17) -> 0 | S17: =IF(S$3=0,"",SUMIFS(INDEX(Inputs!$D$4:$AG$200,0,MATCH(S$2,Inputs!$D$2:$AG$2,0)),Inputs!$B$4:$B$200,$B17)/1000) -> 0 | T17: =IF(T$3=0,"",SUMIFS(INDEX(Inputs!$D$4:$AG$200,0,MATCH(T$2,Inputs!$D$2:$AG$2,0)),Inputs!$B$4:$B$200,$B17)/1000) -> 0 | U17: =IF(U$3=0,"",SUMIFS(INDEX(Inputs!$D$4:$AG$200,0,MATCH(U$2,Inputs!$D$2:$AG$2,0)),Inputs!$B$4:$B$200,$B17)/1000) -> 0 | V17: =IF(V$3=0,"",SUMIFS(INDEX(Inputs!$D$4:$AG$200,0,MATCH(V$2,Inputs!$D$2:$AG$2,0)),Inputs!$B$4:$B$200,$B17)/1000) -> 0 | W17: =IF(V17="","",V17) -> 0 | X17: =IF(X$3=0,"",SUMIFS(INDEX(Inputs!$D$4:$AG$200,0,MATCH(X$2,Inputs!$D$2:$AG$2,0)),Inputs!$B$4:$B$200,$B17)/1000) -> 0 | Y17: =IF(Y$3=0,"",SUMIFS(INDEX(Inputs!$D$4:$AG$200,0,MATCH(Y$2,Inputs!$D$2:$AG$2,0)),Inputs!$B$4:$B$200,$B17)/1000) -> 0 | Z17: =IF(Z$3=0,"",SUMIFS(INDEX(Inputs!$D$4:$AG$200,0,MATCH(Z$2,Inputs!$D$2:$AG$2,0)),Inputs!$B$4:$B$200,$B17)/1000) -> 0 | AA17: =IF(AA$3=0,"",SUMIFS(INDEX(Inputs!$D$4:$AG$200,0,MATCH(AA$2,Inputs!$D$2:$AG$2,0)),Inputs!$B$4:$B$200,$B17)/1000) -> 0 | AB17: =IF(AA17="","",AA17) -> 0 | AC17: =IF(AC$3=0,"",SUMIFS(INDEX(Inputs!$D$4:$AG$200,0,MATCH(AC$2,Inputs!$D$2:$AG$2,0)),Inputs!$B$4:$B$200,$B17)/1000) -> 0 | AD17: =IF(AD$3=0,"",SUMIFS(INDEX(Inputs!$D$4:$AG$200,0,MATCH(AD$2,Inputs!$D$2:$AG$2,0)),Inputs!$B$4:$B$200,$B17)/1000) -> 0 | AE17: =IF(AE$3=0,"",SUMIFS(INDEX(Inputs!$D$4:$AG$200,0,MATCH(AE$2,Inputs!$D$2:$AG$2,0)),Inputs!$B$4:$B$200,$B17)/1000) | AF17: =IF(AF$3=0,"",SUMIFS(INDEX(Inputs!$D$4:$AG$200,0,MATCH(AF$2,Inputs!$D$2:$AG$2,0)),Inputs!$B$4:$B$200,$B17)/1000) | AG17: =IF(AF17="","",AF17)
B18: 14 | C18: Deferred income taxes | D18: =IF(D$3=0,"",SUMIFS(INDEX(Inputs!$D$4:$AG$200,0,MATCH(D$2,Inputs!$D$2:$AG$2,0)),Inputs!$B$4:$B$200,$B18)/1000) -> 0 | E18: =IF(E$3=0,"",SUMIFS(INDEX(Inputs!$D$4:$AG$200,0,MATCH(E$2,Inputs!$D$2:$AG$2,0)),Inputs!$B$4:$B$200,$B18)/1000) -> 0 | F18: =IF(F$3=0,"",SUMIFS(INDEX(Inputs!$D$4:$AG$200,0,MATCH(F$2,Inputs!$D$2:$AG$2,0)),Inputs!$B$4:$B$200,$B18)/1000) -> 0 | G18: =IF(G$3=0,"",SUMIFS(INDEX(Inputs!$D$4:$AG$200,0,MATCH(G$2,Inputs!$D$2:$AG$2,0)),Inputs!$B$4:$B$200,$B18)/1000) -> 0 | H18: =IF(G18="","",G18) -> 0 | I18: =IF(I$3=0,"",SUMIFS(INDEX(Inputs!$D$4:$AG$200,0,MATCH(I$2,Inputs!$D$2:$AG$2,0)),Inputs!$B$4:$B$200,$B18)/1000) -> 0 | J18: =IF(J$3=0,"",SUMIFS(INDEX(Inputs!$D$4:$AG$200,0,MATCH(J$2,Inputs!$D$2:$AG$2,0)),Inputs!$B$4:$B$200,$B18)/1000) -> 0 | K18: =IF(K$3=0,"",SUMIFS(INDEX(Inputs!$D$4:$AG$200,0,MATCH(K$2,Inputs!$D$2:$AG$2,0)),Inputs!$B$4:$B$200,$B18)/1000) -> 0 | L18: =IF(L$3=0,"",SUMIFS(INDEX(Inputs!$D$4:$AG$200,0,MATCH(L$2,Inputs!$D$2:$AG$2,0)),Inputs!$B$4:$B$200,$B18)/1000) -> 0 | M18: =IF(L18="","",L18) -> 0 | N18: =IF(N$3=0,"",SUMIFS(INDEX(Inputs!$D$4:$AG$200,0,MATCH(N$2,Inputs!$D$2:$AG$2,0)),Inputs!$B$4:$B$200,$B18)/1000) -> 0 | O18: =IF(O$3=0,"",SUMIFS(INDEX(Inputs!$D$4:$AG$200,0,MATCH(O$2,Inputs!$D$2:$AG$2,0)),Inputs!$B$4:$B$200,$B18)/1000) -> 0 | P18: =IF(P$3=0,"",SUMIFS(INDEX(Inputs!$D$4:$AG$200,0,MATCH(P$2,Inputs!$D$2:$AG$2,0)),Inputs!$B$4:$B$200,$B18)/1000) -> 0 | Q18: =IF(Q$3=0,"",SUMIFS(INDEX(Inputs!$D$4:$AG$200,0,MATCH(Q$2,Inputs!$D$2:$AG$2,0)),Inputs!$B$4:$B$200,$B18)/1000) -> 0 | R18: =IF(Q18="","",Q18) -> 0 | S18: =IF(S$3=0,"",SUMIFS(INDEX(Inputs!$D$4:$AG$200,0,MATCH(S$2,Inputs!$D$2:$AG$2,0)),Inputs!$B$4:$B$200,$B18)/1000) -> 0 | T18: =IF(T$3=0,"",SUMIFS(INDEX(Inputs!$D$4:$AG$200,0,MATCH(T$2,Inputs!$D$2:$AG$2,0)),Inputs!$B$4:$B$200,$B18)/1000) -> 0 | U18: =IF(U$3=0,"",SUMIFS(INDEX(Inputs!$D$4:$AG$200,0,MATCH(U$2,Inputs!$D$2:$AG$2,0)),Inputs!$B$4:$B$200,$B18)/1000) -> 0 | V18: =IF(V$3=0,"",SUMIFS(INDEX(Inputs!$D$4:$AG$200,0,MATCH(V$2,Inputs!$D$2:$AG$2,0)),Inputs!$B$4:$B$200,$B18)/1000) -> 0 | W18: =IF(V18="","",V18) -> 0 | X18: =IF(X$3=0,"",SUMIFS(INDEX(Inputs!$D$4:$AG$200,0,MATCH(X$2,Inputs!$D$2:$AG$2,0)),Inputs!$B$4:$B$200,$B18)/1000) -> 0 | Y18: =IF(Y$3=0,"",SUMIFS(INDEX(Inputs!$D$4:$AG$200,0,MATCH(Y$2,Inputs!$D$2:$AG$2,0)),Inputs!$B$4:$B$200,$B18)/1000) -> 0 | Z18: =IF(Z$3=0,"",SUMIFS(INDEX(Inputs!$D$4:$AG$200,0,MATCH(Z$2,Inputs!$D$2:$AG$2,0)),Inputs!$B$4:$B$200,$B18)/1000) -> 0 | AA18: =IF(AA$3=0,"",SUMIFS(INDEX(Inputs!$D$4:$AG$200,0,MATCH(AA$2,Inputs!$D$2:$AG$2,0)),Inputs!$B$4:$B$200,$B18)/1000) -> 0 | AB18: =IF(AA18="","",AA18) -> 0 | AC18: =IF(AC$3=0,"",SUMIFS(INDEX(Inputs!$D$4:$AG$200,0,MATCH(AC$2,Inputs!$D$2:$AG$2,0)),Inputs!$B$4:$B$200,$B18)/1000) -> 0 | AD18: =IF(AD$3=0,"",SUMIFS(INDEX(Inputs!$D$4:$AG$200,0,MATCH(AD$2,Inputs!$D$2:$AG$2,0)),Inputs!$B$4:$B$200,$B18)/1000) -> 0 | AE18: =IF(AE$3=0,"",SUMIFS(INDEX(Inputs!$D$4:$AG$200,0,MATCH(AE$2,Inputs!$D$2:$AG$2,0)),Inputs!$B$4:$B$200,$B18)/1000) | AF18: =IF(AF$3=0,"",SUMIFS(INDEX(Inputs!$D$4:$AG$200,0,MATCH(AF$2,Inputs!$D$2:$AG$2,0)),Inputs!$B$4:$B$200,$B18)/1000) | AG18: =IF(AF18="","",AF18)
B19: 15 | C19: Prepaid expenses | D19: =IF(D$3=0,"",SUMIFS(INDEX(Inputs!$D$4:$AG$200,0,MATCH(D$2,Inputs!$D$2:$AG$2,0)),Inputs!$B$4:$B$200,$B19)/1000) -> 0 | E19: =IF(E$3=0,"",SUMIFS(INDEX(Inputs!$D$4:$AG$200,0,MATCH(E$2,Inputs!$D$2:$AG$2,0)),Inputs!$B$4:$B$200,$B19)/1000) -> 0 | F19: =IF(F$3=0,"",SUMIFS(INDEX(Inputs!$D$4:$AG$200,0,MATCH(F$2,Inputs!$D$2:$AG$2,0)),Inputs!$B$4:$B$200,$B19)/1000) -> 0 | G19: =IF(G$3=0,"",SUMIFS(INDEX(Inputs!$D$4:$AG$200,0,MATCH(G$2,Inputs!$D$2:$AG$2,0)),Inputs!$B$4:$B$200,$B19)/1000) -> 0 | H19: =IF(G19="","",G19) -> 0 | I19: =IF(I$3=0,"",SUMIFS(INDEX(Inputs!$D$4:$AG$200,0,MATCH(I$2,Inputs!$D$2:$AG$2,0)),Inputs!$B$4:$B$200,$B19)/1000) -> 0 | J19: =IF(J$3=0,"",SUMIFS(INDEX(Inputs!$D$4:$AG$200,0,MATCH(J$2,Inputs!$D$2:$AG$2,0)),Inputs!$B$4:$B$200,$B19)/1000) -> 0 | K19: =IF(K$3=0,"",SUMIFS(INDEX(Inputs!$D$4:$AG$200,0,MATCH(K$2,Inputs!$D$2:$AG$2,0)),Inputs!$B$4:$B$200,$B19)/1000) -> 0 | L19: =IF(L$3=0,"",SUMIFS(INDEX(Inputs!$D$4:$AG$200,0,MATCH(L$2,Inputs!$D$2:$AG$2,0)),Inputs!$B$4:$B$200,$B19)/1000) -> 0 | M19: =IF(L19="","",L19) -> 0 | N19: =IF(N$3=0,"",SUMIFS(INDEX(Inputs!$D$4:$AG$200,0,MATCH(N$2,Inputs!$D$2:$AG$2,0)),Inputs!$B$4:$B$200,$B19)/1000) -> 0 | O19: =IF(O$3=0,"",SUMIFS(INDEX(Inputs!$D$4:$AG$200,0,MATCH(O$2,Inputs!$D$2:$AG$2,0)),Inputs!$B$4:$B$200,$B19)/1000) -> 0 | P19: =IF(P$3=0,"",SUMIFS(INDEX(Inputs!$D$4:$AG$200,0,MATCH(P$2,Inputs!$D$2:$AG$2,0)),Inputs!$B$4:$B$200,$B19)/1000) -> 0 | Q19: =IF(Q$3=0,"",SUMIFS(INDEX(Inputs!$D$4:$AG$200,0,MATCH(Q$2,Inputs!$D$2:$AG$2,0)),Inputs!$B$4:$B$200,$B19)/1000) -> 0 | R19: =IF(Q19="","",Q19) -> 0 | S19: =IF(S$3=0,"",SUMIFS(INDEX(Inputs!$D$4:$AG$200,0,MATCH(S$2,Inputs!$D$2:$AG$2,0)),Inputs!$B$4:$B$200,$B19)/1000) -> 0 | T19: =IF(T$3=0,"",SUMIFS(INDEX(Inputs!$D$4:$AG$200,0,MATCH(T$2,Inputs!$D$2:$AG$2,0)),Inputs!$B$4:$B$200,$B19)/1000) -> 0 | U19: =IF(U$3=0,"",SUMIFS(INDEX(Inputs!$D$4:$AG$200,0,MATCH(U$2,Inputs!$D$2:$AG$2,0)),Inputs!$B$4:$B$200,$B19)/1000) -> 0 | V19: =IF(V$3=0,"",SUMIFS(INDEX(Inputs!$D$4:$AG$200,0,MATCH(V$2,Inputs!$D$2:$AG$2,0)),Inputs!$B$4:$B$200,$B19)/1000) -> 0 | W19: =IF(V19="","",V19) -> 0 | X19: =IF(X$3=0,"",SUMIFS(INDEX(Inputs!$D$4:$AG$200,0,MATCH(X$2,Inputs!$D$2:$AG$2,0)),Inputs!$B$4:$B$200,$B19)/1000) -> 0 | Y19: =IF(Y$3=0,"",SUMIFS(INDEX(Inputs!$D$4:$AG$200,0,MATCH(Y$2,Inputs!$D$2:$AG$2,0)),Inputs!$B$4:$B$200,$B19)/1000) -> 0 | Z19: =IF(Z$3=0,"",SUMIFS(INDEX(Inputs!$D$4:$AG$200,0,MATCH(Z$2,Inputs!$D$2:$AG$2,0)),Inputs!$B$4:$B$200,$B19)/1000) -> 0 | AA19: =IF(AA$3=0,"",SUMIFS(INDEX(Inputs!$D$4:$AG$200,0,MATCH(AA$2,Inputs!$D$2:$AG$2,0)),Inputs!$B$4:$B$200,$B19)/1000) -> 0 | AB19: =IF(AA19="","",AA19) -> 0 | AC19: =IF(AC$3=0,"",SUMIFS(INDEX(Inputs!$D$4:$AG$200,0,MATCH(AC$2,Inputs!$D$2:$AG$2,0)),Inputs!$B$4:$B$200,$B19)/1000) -> 0 | AD19: =IF(AD$3=0,"",SUMIFS(INDEX(Inputs!$D$4:$AG$200,0,MATCH(AD$2,Inputs!$D$2:$AG$2,0)),Inputs!$B$4:$B$200,$B19)/1000) -> 0 | AE19: =IF(AE$3=0,"",SUMIFS(INDEX(Inputs!$D$4:$AG$200,0,MATCH(AE$2,Inputs!$D$2:$AG$2,0)),Inputs!$B$4:$B$200,$B19)/1000) | AF19: =IF(AF$3=0,"",SUMIFS(INDEX(Inputs!$D$4:$AG$200,0,MATCH(AF$2,Inputs!$D$2:$AG$2,0)),Inputs!$B$4:$B$200,$B19)/1000) | AG19: =IF(AF19="","",AF19)
B20: 16 | C20: Other current assets | D20: =IF(D$3=0,"",SUMIFS(INDEX(Inputs!$D$4:$AG$200,0,MATCH(D$2,Inputs!$D$2:$AG$2,0)),Inputs!$B$4:$B$200,$B20)/1000) -> 337.505 | E20: =IF(E$3=0,"",SUMIFS(INDEX(Inputs!$D$4:$AG$200,0,MATCH(E$2,Inputs!$D$2:$AG$2,0)),Inputs!$B$4:$B$200,$B20)/1000) -> 432.709 | F20: =IF(F$3=0,"",SUMIFS(INDEX(Inputs!$D$4:$AG$200,0,MATCH(F$2,Inputs!$D$2:$AG$2,0)),Inputs!$B$4:$B$200,$B20)/1000) -> 509.809 | G20: =IF(G$3=0,"",SUMIFS(INDEX(Inputs!$D$4:$AG$200,0,MATCH(G$2,Inputs!$D$2:$AG$2,0)),Inputs!$B$4:$B$200,$B20)/1000) -> 480.62 | H20: =IF(G20="","",G20) -> 480.62 | I20: =IF(I$3=0,"",SUMIFS(INDEX(Inputs!$D$4:$AG$200,0,MATCH(I$2,Inputs!$D$2:$AG$2,0)),Inputs!$B$4:$B$200,$B20)/1000) -> 957.699 | J20: =IF(J$3=0,"",SUMIFS(INDEX(Inputs!$D$4:$AG$200,0,MATCH(J$2,Inputs!$D$2:$AG$2,0)),Inputs!$B$4:$B$200,$B20)/1000) -> 1087.034 | K20: =IF(K$3=0,"",SUMIFS(INDEX(Inputs!$D$4:$AG$200,0,MATCH(K$2,Inputs!$D$2:$AG$2,0)),Inputs!$B$4:$B$200,$B20)/1000) -> 1392.235 | L20: =IF(L$3=0,"",SUMIFS(INDEX(Inputs!$D$4:$AG$200,0,MATCH(L$2,Inputs!$D$2:$AG$2,0)),Inputs!$B$4:$B$200,$B20)/1000) -> 1438.875 | M20: =IF(L20="","",L20) -> 1438.875 | N20: =IF(N$3=0,"",SUMIFS(INDEX(Inputs!$D$4:$AG$200,0,MATCH(N$2,Inputs!$D$2:$AG$2,0)),Inputs!$B$4:$B$200,$B20)/1000) -> 1373.543 | O20: =IF(O$3=0,"",SUMIFS(INDEX(Inputs!$D$4:$AG$200,0,MATCH(O$2,Inputs!$D$2:$AG$2,0)),Inputs!$B$4:$B$200,$B20)/1000) -> 1300.157 | P20: =IF(P$3=0,"",SUMIFS(INDEX(Inputs!$D$4:$AG$200,0,MATCH(P$2,Inputs!$D$2:$AG$2,0)),Inputs!$B$4:$B$200,$B20)/1000) -> 1425.439 | Q20: =IF(Q$3=0,"",SUMIFS(INDEX(Inputs!$D$4:$AG$200,0,MATCH(Q$2,Inputs!$D$2:$AG$2,0)),Inputs!$B$4:$B$200,$B20)/1000) -> 1086.901 | R20: =IF(Q20="","",Q20) -> 1086.901 | S20: =IF(S$3=0,"",SUMIFS(INDEX(Inputs!$D$4:$AG$200,0,MATCH(S$2,Inputs!$D$2:$AG$2,0)),Inputs!$B$4:$B$200,$B20)/1000) -> 1575.134 | T20: =IF(T$3=0,"",SUMIFS(INDEX(Inputs!$D$4:$AG$200,0,MATCH(T$2,Inputs!$D$2:$AG$2,0)),Inputs!$B$4:$B$200,$B20)/1000) -> 1497.843 | U20: =IF(U$3=0,"",SUMIFS(INDEX(Inputs!$D$4:$AG$200,0,MATCH(U$2,Inputs!$D$2:$AG$2,0)),Inputs!$B$4:$B$200,$B20)/1000) -> 1417.002 | V20: =IF(V$3=0,"",SUMIFS(INDEX(Inputs!$D$4:$AG$200,0,MATCH(V$2,Inputs!$D$2:$AG$2,0)),Inputs!$B$4:$B$200,$B20)/1000) -> 1217.861 | W20: =IF(V20="","",V20) -> 1217.861 | X20: =IF(X$3=0,"",SUMIFS(INDEX(Inputs!$D$4:$AG$200,0,MATCH(X$2,Inputs!$D$2:$AG$2,0)),Inputs!$B$4:$B$200,$B20)/1000) -> 2032.503 | Y20: =IF(Y$3=0,"",SUMIFS(INDEX(Inputs!$D$4:$AG$200,0,MATCH(Y$2,Inputs!$D$2:$AG$2,0)),Inputs!$B$4:$B$200,$B20)/1000) -> 2000.533 | Z20: =IF(Z$3=0,"",SUMIFS(INDEX(Inputs!$D$4:$AG$200,0,MATCH(Z$2,Inputs!$D$2:$AG$2,0)),Inputs!$B$4:$B$200,$B20)/1000) -> 1727.128 | AA20: =IF(AA$3=0,"",SUMIFS(INDEX(Inputs!$D$4:$AG$200,0,MATCH(AA$2,Inputs!$D$2:$AG$2,0)),Inputs!$B$4:$B$200,$B20)/1000) -> 942.151 | AB20: =IF(AA20="","",AA20) -> 942.151 | AC20: =IF(AC$3=0,"",SUMIFS(INDEX(Inputs!$D$4:$AG$200,0,MATCH(AC$2,Inputs!$D$2:$AG$2,0)),Inputs!$B$4:$B$200,$B20)/1000) -> 1404.787 | AD20: =IF(AD$3=0,"",SUMIFS(INDEX(Inputs!$D$4:$AG$200,0,MATCH(AD$2,Inputs!$D$2:$AG$2,0)),Inputs!$B$4:$B$200,$B20)/1000) -> 1394.588 | AE20: =IF(AE$3=0,"",SUMIFS(INDEX(Inputs!$D$4:$AG$200,0,MATCH(AE$2,Inputs!$D$2:$AG$2,0)),Inputs!$B$4:$B$200,$B20)/1000) | AF20: =IF(AF$3=0,"",SUMIFS(INDEX(Inputs!$D$4:$AG$200,0,MATCH(AF$2,Inputs!$D$2:$AG$2,0)),Inputs!$B$4:$B$200,$B20)/1000) | AG20: =IF(AF20="","",AF20)
B21: 17 | C21: Equity in affiliates | D21: =IF(D$3=0,"",SUMIFS(INDEX(Inputs!$D$4:$AG$200,0,MATCH(D$2,Inputs!$D$2:$AG$2,0)),Inputs!$B$4:$B$200,$B21)/1000) -> 1.985 | E21: =IF(E$3=0,"",SUMIFS(INDEX(Inputs!$D$4:$AG$200,0,MATCH(E$2,Inputs!$D$2:$AG$2,0)),Inputs!$B$4:$B$200,$B21)/1000) -> 2.141 | F21: =IF(F$3=0,"",SUMIFS(INDEX(Inputs!$D$4:$AG$200,0,MATCH(F$2,Inputs!$D$2:$AG$2,0)),Inputs!$B$4:$B$200,$B21)/1000) -> 1.202 | G21: =IF(G$3=0,"",SUMIFS(INDEX(Inputs!$D$4:$AG$200,0,MATCH(G$2,Inputs!$D$2:$AG$2,0)),Inputs!$B$4:$B$200,$B21)/1000) -> 1.191 | H21: =IF(G21="","",G21) -> 1.191 | I21: =IF(I$3=0,"",SUMIFS(INDEX(Inputs!$D$4:$AG$200,0,MATCH(I$2,Inputs!$D$2:$AG$2,0)),Inputs!$B$4:$B$200,$B21)/1000) -> 1.188 | J21: =IF(J$3=0,"",SUMIFS(INDEX(Inputs!$D$4:$AG$200,0,MATCH(J$2,Inputs!$D$2:$AG$2,0)),Inputs!$B$4:$B$200,$B21)/1000) -> 1.139 | K21: =IF(K$3=0,"",SUMIFS(INDEX(Inputs!$D$4:$AG$200,0,MATCH(K$2,Inputs!$D$2:$AG$2,0)),Inputs!$B$4:$B$200,$B21)/1000) -> 1.107 | L21: =IF(L$3=0,"",SUMIFS(INDEX(Inputs!$D$4:$AG$200,0,MATCH(L$2,Inputs!$D$2:$AG$2,0)),Inputs!$B$4:$B$200,$B21)/1000) -> 1.102 | M21: =IF(L21="","",L21) -> 1.102 | N21: =IF(N$3=0,"",SUMIFS(INDEX(Inputs!$D$4:$AG$200,0,MATCH(N$2,Inputs!$D$2:$AG$2,0)),Inputs!$B$4:$B$200,$B21)/1000) -> 1.094 | O21: =IF(O$3=0,"",SUMIFS(INDEX(Inputs!$D$4:$AG$200,0,MATCH(O$2,Inputs!$D$2:$AG$2,0)),Inputs!$B$4:$B$200,$B21)/1000) -> 1.113 | P21: =IF(P$3=0,"",SUMIFS(INDEX(Inputs!$D$4:$AG$200,0,MATCH(P$2,Inputs!$D$2:$AG$2,0)),Inputs!$B$4:$B$200,$B21)/1000) -> 0.676 | Q21: =IF(Q$3=0,"",SUMIFS(INDEX(Inputs!$D$4:$AG$200,0,MATCH(Q$2,Inputs!$D$2:$AG$2,0)),Inputs!$B$4:$B$200,$B21)/1000) -> 1.142 | R21: =IF(Q21="","",Q21) -> 1.142 | S21: =IF(S$3=0,"",SUMIFS(INDEX(Inputs!$D$4:$AG$200,0,MATCH(S$2,Inputs!$D$2:$AG$2,0)),Inputs!$B$4:$B$200,$B21)/1000) -> 0.612 | T21: =IF(T$3=0,"",SUMIFS(INDEX(Inputs!$D$4:$AG$200,0,MATCH(T$2,Inputs!$D$2:$AG$2,0)),Inputs!$B$4:$B$200,$B21)/1000) -> 0.589 | U21: =IF(U$3=0,"",SUMIFS(INDEX(Inputs!$D$4:$AG$200,0,MATCH(U$2,Inputs!$D$2:$AG$2,0)),Inputs!$B$4:$B$200,$B21)/1000) -> 0.562 | V21: =IF(V$3=0,"",SUMIFS(INDEX(Inputs!$D$4:$AG$200,0,MATCH(V$2,Inputs!$D$2:$AG$2,0)),Inputs!$B$4:$B$200,$B21)/1000) -> 0.562 | W21: =IF(V21="","",V21) -> 0.562 | X21: =IF(X$3=0,"",SUMIFS(INDEX(Inputs!$D$4:$AG$200,0,MATCH(X$2,Inputs!$D$2:$AG$2,0)),Inputs!$B$4:$B$200,$B21)/1000) -> 0.562 | Y21: =IF(Y$3=0,"",SUMIFS(INDEX(Inputs!$D$4:$AG$200,0,MATCH(Y$2,Inputs!$D$2:$AG$2,0)),Inputs!$B$4:$B$200,$B21)/1000) -> 0 | Z21: =IF(Z$3=0,"",SUMIFS(INDEX(Inputs!$D$4:$AG$200,0,MATCH(Z$2,Inputs!$D$2:$AG$2,0)),Inputs!$B$4:$B$200,$B21)/1000) -> 18.175 | AA21: =IF(AA$3=0,"",SUMIFS(INDEX(Inputs!$D$4:$AG$200,0,MATCH(AA$2,Inputs!$D$2:$AG$2,0)),Inputs!$B$4:$B$200,$B21)/1000) -> 19.697 | AB21: =IF(AA21="","",AA21) -> 19.697 | AC21: =IF(AC$3=0,"",SUMIFS(INDEX(Inputs!$D$4:$AG$200,0,MATCH(AC$2,Inputs!$D$2:$AG$2,0)),Inputs!$B$4:$B$200,$B21)/1000) -> 20.087 | AD21: =IF(AD$3=0,"",SUMIFS(INDEX(Inputs!$D$4:$AG$200,0,MATCH(AD$2,Inputs!$D$2:$AG$2,0)),Inputs!$B$4:$B$200,$B21)/1000) -> 38.7 | AE21: =IF(AE$3=0,"",SUMIFS(INDEX(Inputs!$D$4:$AG$200,0,MATCH(AE$2,Inputs!$D$2:$AG$2,0)),Inputs!$B$4:$B$200,$B21)/1000) | AF21: =IF(AF$3=0,"",SUMIFS(INDEX(Inputs!$D$4:$AG$200,0,MATCH(AF$2,Inputs!$D$2:$AG$2,0)),Inputs!$B$4:$B$200,$B21)/1000) | AG21: =IF(AF21="","",AF21)
B22: 18 | C22: PP&E | D22: =IF(D$3=0,"",SUMIFS(INDEX(Inputs!$D$4:$AG$200,0,MATCH(D$2,Inputs!$D$2:$AG$2,0)),Inputs!$B$4:$B$200,$B22)/1000) -> 6358.238 | E22: =IF(E$3=0,"",SUMIFS(INDEX(Inputs!$D$4:$AG$200,0,MATCH(E$2,Inputs!$D$2:$AG$2,0)),Inputs!$B$4:$B$200,$B22)/1000) -> 7287.437 | F22: =IF(F$3=0,"",SUMIFS(INDEX(Inputs!$D$4:$AG$200,0,MATCH(F$2,Inputs!$D$2:$AG$2,0)),Inputs!$B$4:$B$200,$B22)/1000) -> 9856.908 | G22: =IF(G$3=0,"",SUMIFS(INDEX(Inputs!$D$4:$AG$200,0,MATCH(G$2,Inputs!$D$2:$AG$2,0)),Inputs!$B$4:$B$200,$B22)/1000) -> 12140.029 | H22: =IF(G22="","",G22) -> 12140.029 | I22: =IF(I$3=0,"",SUMIFS(INDEX(Inputs!$D$4:$AG$200,0,MATCH(I$2,Inputs!$D$2:$AG$2,0)),Inputs!$B$4:$B$200,$B22)/1000) -> 12833.83 | J22: =IF(J$3=0,"",SUMIFS(INDEX(Inputs!$D$4:$AG$200,0,MATCH(J$2,Inputs!$D$2:$AG$2,0)),Inputs!$B$4:$B$200,$B22)/1000) -> 14798.069 | K22: =IF(K$3=0,"",SUMIFS(INDEX(Inputs!$D$4:$AG$200,0,MATCH(K$2,Inputs!$D$2:$AG$2,0)),Inputs!$B$4:$B$200,$B22)/1000) -> 15290.954 | L22: =IF(L$3=0,"",SUMIFS(INDEX(Inputs!$D$4:$AG$200,0,MATCH(L$2,Inputs!$D$2:$AG$2,0)),Inputs!$B$4:$B$200,$B22)/1000) -> 15842.199 | M22: =IF(L22="","",L22) -> 15842.199 | N22: =IF(N$3=0,"",SUMIFS(INDEX(Inputs!$D$4:$AG$200,0,MATCH(N$2,Inputs!$D$2:$AG$2,0)),Inputs!$B$4:$B$200,$B22)/1000) -> 15303.402 | O22: =IF(O$3=0,"",SUMIFS(INDEX(Inputs!$D$4:$AG$200,0,MATCH(O$2,Inputs!$D$2:$AG$2,0)),Inputs!$B$4:$B$200,$B22)/1000) -> 15083.106 | P22: =IF(P$3=0,"",SUMIFS(INDEX(Inputs!$D$4:$AG$200,0,MATCH(P$2,Inputs!$D$2:$AG$2,0)),Inputs!$B$4:$B$200,$B22)/1000) -> 16021.303 | Q22: =IF(Q$3=0,"",SUMIFS(INDEX(Inputs!$D$4:$AG$200,0,MATCH(Q$2,Inputs!$D$2:$AG$2,0)),Inputs!$B$4:$B$200,$B22)/1000) -> 18637.281 | R22: =IF(Q22="","",Q22) -> 18637.281 | S22: =IF(S$3=0,"",SUMIFS(INDEX(Inputs!$D$4:$AG$200,0,MATCH(S$2,Inputs!$D$2:$AG$2,0)),Inputs!$B$4:$B$200,$B22)/1000) -> 18762.548 | T22: =IF(T$3=0,"",SUMIFS(INDEX(Inputs!$D$4:$AG$200,0,MATCH(T$2,Inputs!$D$2:$AG$2,0)),Inputs!$B$4:$B$200,$B22)/1000) -> 19168.4 | U22: =IF(U$3=0,"",SUMIFS(INDEX(Inputs!$D$4:$AG$200,0,MATCH(U$2,Inputs!$D$2:$AG$2,0)),Inputs!$B$4:$B$200,$B22)/1000) -> 19724.886 | V22: =IF(V$3=0,"",SUMIFS(INDEX(Inputs!$D$4:$AG$200,0,MATCH(V$2,Inputs!$D$2:$AG$2,0)),Inputs!$B$4:$B$200,$B22)/1000) -> 21912.952 | W22: =IF(V22="","",V22) -> 21912.952 | X22: =IF(X$3=0,"",SUMIFS(INDEX(Inputs!$D$4:$AG$200,0,MATCH(X$2,Inputs!$D$2:$AG$2,0)),Inputs!$B$4:$B$200,$B22)/1000) -> 20671.846 | Y22: =IF(Y$3=0,"",SUMIFS(INDEX(Inputs!$D$4:$AG$200,0,MATCH(Y$2,Inputs!$D$2:$AG$2,0)),Inputs!$B$4:$B$200,$B22)/1000) -> 21464.854 | Z22: =IF(Z$3=0,"",SUMIFS(INDEX(Inputs!$D$4:$AG$200,0,MATCH(Z$2,Inputs!$D$2:$AG$2,0)),Inputs!$B$4:$B$200,$B22)/1000) -> 21621.948 | AA22: =IF(AA$3=0,"",SUMIFS(INDEX(Inputs!$D$4:$AG$200,0,MATCH(AA$2,Inputs!$D$2:$AG$2,0)),Inputs!$B$4:$B$200,$B22)/1000) -> 24160.768 | AB22: =IF(AA22="","",AA22) -> 24160.768 | AC22: =IF(AC$3=0,"",SUMIFS(INDEX(Inputs!$D$4:$AG$200,0,MATCH(AC$2,Inputs!$D$2:$AG$2,0)),Inputs!$B$4:$B$200,$B22)/1000) -> 23242.795 | AD22: =IF(AD$3=0,"",SUMIFS(INDEX(Inputs!$D$4:$AG$200,0,MATCH(AD$2,Inputs!$D$2:$AG$2,0)),Inputs!$B$4:$B$200,$B22)/1000) -> 25078.365 | AE22: =IF(AE$3=0,"",SUMIFS(INDEX(Inputs!$D$4:$AG$200,0,MATCH(AE$2,Inputs!$D$2:$AG$2,0)),Inputs!$B$4:$B$200,$B22)/1000) | AF22: =IF(AF$3=0,"",SUMIFS(INDEX(Inputs!$D$4:$AG$200,0,MATCH(AF$2,Inputs!$D$2:$AG$2,0)),Inputs!$B$4:$B$200,$B22)/1000) | AG22: =IF(AF22="","",AF22)
B23: 19 | C23: Right-of-use-assets | D23: =IF(D$3=0,"",SUMIFS(INDEX(Inputs!$D$4:$AG$200,0,MATCH(D$2,Inputs!$D$2:$AG$2,0)),Inputs!$B$4:$B$200,$B23)/1000) -> 0 | E23: =IF(E$3=0,"",SUMIFS(INDEX(Inputs!$D$4:$AG$200,0,MATCH(E$2,Inputs!$D$2:$AG$2,0)),Inputs!$B$4:$B$200,$B23)/1000) -> 0 | F23: =IF(F$3=0,"",SUMIFS(INDEX(Inputs!$D$4:$AG$200,0,MATCH(F$2,Inputs!$D$2:$AG$2,0)),Inputs!$B$4:$B$200,$B23)/1000) -> 0 | G23: =IF(G$3=0,"",SUMIFS(INDEX(Inputs!$D$4:$AG$200,0,MATCH(G$2,Inputs!$D$2:$AG$2,0)),Inputs!$B$4:$B$200,$B23)/1000) -> 0 | H23: =IF(G23="","",G23) -> 0 | I23: =IF(I$3=0,"",SUMIFS(INDEX(Inputs!$D$4:$AG$200,0,MATCH(I$2,Inputs!$D$2:$AG$2,0)),Inputs!$B$4:$B$200,$B23)/1000) -> 0 | J23: =IF(J$3=0,"",SUMIFS(INDEX(Inputs!$D$4:$AG$200,0,MATCH(J$2,Inputs!$D$2:$AG$2,0)),Inputs!$B$4:$B$200,$B23)/1000) -> 0 | K23: =IF(K$3=0,"",SUMIFS(INDEX(Inputs!$D$4:$AG$200,0,MATCH(K$2,Inputs!$D$2:$AG$2,0)),Inputs!$B$4:$B$200,$B23)/1000) -> 0 | L23: =IF(L$3=0,"",SUMIFS(INDEX(Inputs!$D$4:$AG$200,0,MATCH(L$2,Inputs!$D$2:$AG$2,0)),Inputs!$B$4:$B$200,$B23)/1000) -> 0 | M23: =IF(L23="","",L23) -> 0 | N23: =IF(N$3=0,"",SUMIFS(INDEX(Inputs!$D$4:$AG$200,0,MATCH(N$2,Inputs!$D$2:$AG$2,0)),Inputs!$B$4:$B$200,$B23)/1000) -> 0 | O23: =IF(O$3=0,"",SUMIFS(INDEX(Inputs!$D$4:$AG$200,0,MATCH(O$2,Inputs!$D$2:$AG$2,0)),Inputs!$B$4:$B$200,$B23)/1000) -> 0 | P23: =IF(P$3=0,"",SUMIFS(INDEX(Inputs!$D$4:$AG$200,0,MATCH(P$2,Inputs!$D$2:$AG$2,0)),Inputs!$B$4:$B$200,$B23)/1000) -> 0 | Q23: =IF(Q$3=0,"",SUMIFS(INDEX(Inputs!$D$4:$AG$200,0,MATCH(Q$2,Inputs!$D$2:$AG$2,0)),Inputs!$B$4:$B$200,$B23)/1000) -> 0 | R23: =IF(Q23="","",Q23) -> 0 | S23: =IF(S$3=0,"",SUMIFS(INDEX(Inputs!$D$4:$AG$200,0,MATCH(S$2,Inputs!$D$2:$AG$2,0)),Inputs!$B$4:$B$200,$B23)/1000) -> 0 | T23: =IF(T$3=0,"",SUMIFS(INDEX(Inputs!$D$4:$AG$200,0,MATCH(T$2,Inputs!$D$2:$AG$2,0)),Inputs!$B$4:$B$200,$B23)/1000) -> 0 | U23: =IF(U$3=0,"",SUMIFS(INDEX(Inputs!$D$4:$AG$200,0,MATCH(U$2,Inputs!$D$2:$AG$2,0)),Inputs!$B$4:$B$200,$B23)/1000) -> 0 | V23: =IF(V$3=0,"",SUMIFS(INDEX(Inputs!$D$4:$AG$200,0,MATCH(V$2,Inputs!$D$2:$AG$2,0)),Inputs!$B$4:$B$200,$B23)/1000) -> 0 | W23: =IF(V23="","",V23) -> 0 | X23: =IF(X$3=0,"",SUMIFS(INDEX(Inputs!$D$4:$AG$200,0,MATCH(X$2,Inputs!$D$2:$AG$2,0)),Inputs!$B$4:$B$200,$B23)/1000) -> 0 | Y23: =IF(Y$3=0,"",SUMIFS(INDEX(Inputs!$D$4:$AG$200,0,MATCH(Y$2,Inputs!$D$2:$AG$2,0)),Inputs!$B$4:$B$200,$B23)/1000) -> 0 | Z23: =IF(Z$3=0,"",SUMIFS(INDEX(Inputs!$D$4:$AG$200,0,MATCH(Z$2,Inputs!$D$2:$AG$2,0)),Inputs!$B$4:$B$200,$B23)/1000) -> 0 | AA23: =IF(AA$3=0,"",SUMIFS(INDEX(Inputs!$D$4:$AG$200,0,MATCH(AA$2,Inputs!$D$2:$AG$2,0)),Inputs!$B$4:$B$200,$B23)/1000) -> 0 | AB23: =IF(AA23="","",AA23) -> 0 | AC23: =IF(AC$3=0,"",SUMIFS(INDEX(Inputs!$D$4:$AG$200,0,MATCH(AC$2,Inputs!$D$2:$AG$2,0)),Inputs!$B$4:$B$200,$B23)/1000) -> 0 | AD23: =IF(AD$3=0,"",SUMIFS(INDEX(Inputs!$D$4:$AG$200,0,MATCH(AD$2,Inputs!$D$2:$AG$2,0)),Inputs!$B$4:$B$200,$B23)/1000) -> 0 | AE23: =IF(AE$3=0,"",SUMIFS(INDEX(Inputs!$D$4:$AG$200,0,MATCH(AE$2,Inputs!$D$2:$AG$2,0)),Inputs!$B$4:$B$200,$B23)/1000) | AF23: =IF(AF$3=0,"",SUMIFS(INDEX(Inputs!$D$4:$AG$200,0,MATCH(AF$2,Inputs!$D$2:$AG$2,0)),Inputs!$B$4:$B$200,$B23)/1000) | AG23: =IF(AF23="","",AF23)
B24: 20 | C24: Goodwill | D24: =IF(D$3=0,"",SUMIFS(INDEX(Inputs!$D$4:$AG$200,0,MATCH(D$2,Inputs!$D$2:$AG$2,0)),Inputs!$B$4:$B$200,$B24)/1000) -> 0 | E24: =IF(E$3=0,"",SUMIFS(INDEX(Inputs!$D$4:$AG$200,0,MATCH(E$2,Inputs!$D$2:$AG$2,0)),Inputs!$B$4:$B$200,$B24)/1000) -> 0 | F24: =IF(F$3=0,"",SUMIFS(INDEX(Inputs!$D$4:$AG$200,0,MATCH(F$2,Inputs!$D$2:$AG$2,0)),Inputs!$B$4:$B$200,$B24)/1000) -> 0 | G24: =IF(G$3=0,"",SUMIFS(INDEX(Inputs!$D$4:$AG$200,0,MATCH(G$2,Inputs!$D$2:$AG$2,0)),Inputs!$B$4:$B$200,$B24)/1000) -> 0 | H24: =IF(G24="","",G24) -> 0 | I24: =IF(I$3=0,"",SUMIFS(INDEX(Inputs!$D$4:$AG$200,0,MATCH(I$2,Inputs!$D$2:$AG$2,0)),Inputs!$B$4:$B$200,$B24)/1000) -> 0 | J24: =IF(J$3=0,"",SUMIFS(INDEX(Inputs!$D$4:$AG$200,0,MATCH(J$2,Inputs!$D$2:$AG$2,0)),Inputs!$B$4:$B$200,$B24)/1000) -> 0 | K24: =IF(K$3=0,"",SUMIFS(INDEX(Inputs!$D$4:$AG$200,0,MATCH(K$2,Inputs!$D$2:$AG$2,0)),Inputs!$B$4:$B$200,$B24)/1000) -> 0 | L24: =IF(L$3=0,"",SUMIFS(INDEX(Inputs!$D$4:$AG$200,0,MATCH(L$2,Inputs!$D$2:$AG$2,0)),Inputs!$B$4:$B$200,$B24)/1000) -> 0 | M24: =IF(L24="","",L24) -> 0 | N24: =IF(N$3=0,"",SUMIFS(INDEX(Inputs!$D$4:$AG$200,0,MATCH(N$2,Inputs!$D$2:$AG$2,0)),Inputs!$B$4:$B$200,$B24)/1000) -> 0 | O24: =IF(O$3=0,"",SUMIFS(INDEX(Inputs!$D$4:$AG$200,0,MATCH(O$2,Inputs!$D$2:$AG$2,0)),Inputs!$B$4:$B$200,$B24)/1000) -> 0 | P24: =IF(P$3=0,"",SUMIFS(INDEX(Inputs!$D$4:$AG$200,0,MATCH(P$2,Inputs!$D$2:$AG$2,0)),Inputs!$B$4:$B$200,$B24)/1000) -> 0 | Q24: =IF(Q$3=0,"",SUMIFS(INDEX(Inputs!$D$4:$AG$200,0,MATCH(Q$2,Inputs!$D$2:$AG$2,0)),Inputs!$B$4:$B$200,$B24)/1000) -> 0 | R24: =IF(Q24="","",Q24) -> 0 | S24: =IF(S$3=0,"",SUMIFS(INDEX(Inputs!$D$4:$AG$200,0,MATCH(S$2,Inputs!$D$2:$AG$2,0)),Inputs!$B$4:$B$200,$B24)/1000) -> 0 | T24: =IF(T$3=0,"",SUMIFS(INDEX(Inputs!$D$4:$AG$200,0,MATCH(T$2,Inputs!$D$2:$AG$2,0)),Inputs!$B$4:$B$200,$B24)/1000) -> 0 | U24: =IF(U$3=0,"",SUMIFS(INDEX(Inputs!$D$4:$AG$200,0,MATCH(U$2,Inputs!$D$2:$AG$2,0)),Inputs!$B$4:$B$200,$B24)/1000) -> 0 | V24: =IF(V$3=0,"",SUMIFS(INDEX(Inputs!$D$4:$AG$200,0,MATCH(V$2,Inputs!$D$2:$AG$2,0)),Inputs!$B$4:$B$200,$B24)/1000) -> 0 | W24: =IF(V24="","",V24) -> 0 | X24: =IF(X$3=0,"",SUMIFS(INDEX(Inputs!$D$4:$AG$200,0,MATCH(X$2,Inputs!$D$2:$AG$2,0)),Inputs!$B$4:$B$200,$B24)/1000) -> 0 | Y24: =IF(Y$3=0,"",SUMIFS(INDEX(Inputs!$D$4:$AG$200,0,MATCH(Y$2,Inputs!$D$2:$AG$2,0)),Inputs!$B$4:$B$200,$B24)/1000) -> 0 | Z24: =IF(Z$3=0,"",SUMIFS(INDEX(Inputs!$D$4:$AG$200,0,MATCH(Z$2,Inputs!$D$2:$AG$2,0)),Inputs!$B$4:$B$200,$B24)/1000) -> 0 | AA24: =IF(AA$3=0,"",SUMIFS(INDEX(Inputs!$D$4:$AG$200,0,MATCH(AA$2,Inputs!$D$2:$AG$2,0)),Inputs!$B$4:$B$200,$B24)/1000) -> 0 | AB24: =IF(AA24="","",AA24) -> 0 | AC24: =IF(AC$3=0,"",SUMIFS(INDEX(Inputs!$D$4:$AG$200,0,MATCH(AC$2,Inputs!$D$2:$AG$2,0)),Inputs!$B$4:$B$200,$B24)/1000) -> 0 | AD24: =IF(AD$3=0,"",SUMIFS(INDEX(Inputs!$D$4:$AG$200,0,MATCH(AD$2,Inputs!$D$2:$AG$2,0)),Inputs!$B$4:$B$200,$B24)/1000) -> 0 | AE24: =IF(AE$3=0,"",SUMIFS(INDEX(Inputs!$D$4:$AG$200,0,MATCH(AE$2,Inputs!$D$2:$AG$2,0)),Inputs!$B$4:$B$200,$B24)/1000) | AF24: =IF(AF$3=0,"",SUMIFS(INDEX(Inputs!$D$4:$AG$200,0,MATCH(AF$2,Inputs!$D$2:$AG$2,0)),Inputs!$B$4:$B$200,$B24)/1000) | AG24: =IF(AF24="","",AF24)
B25: 21 | C25: Intangibles | D25: =IF(D$3=0,"",SUMIFS(INDEX(Inputs!$D$4:$AG$200,0,MATCH(D$2,Inputs!$D$2:$AG$2,0)),Inputs!$B$4:$B$200,$B25)/1000) -> 156.288 | E25: =IF(E$3=0,"",SUMIFS(INDEX(Inputs!$D$4:$AG$200,0,MATCH(E$2,Inputs!$D$2:$AG$2,0)),Inputs!$B$4:$B$200,$B25)/1000) -> 157.252 | F25: =IF(F$3=0,"",SUMIFS(INDEX(Inputs!$D$4:$AG$200,0,MATCH(F$2,Inputs!$D$2:$AG$2,0)),Inputs!$B$4:$B$200,$B25)/1000) -> 168.4 | G25: =IF(G$3=0,"",SUMIFS(INDEX(Inputs!$D$4:$AG$200,0,MATCH(G$2,Inputs!$D$2:$AG$2,0)),Inputs!$B$4:$B$200,$B25)/1000) -> 175.044 | H25: =IF(G25="","",G25) -> 175.044 | I25: =IF(I$3=0,"",SUMIFS(INDEX(Inputs!$D$4:$AG$200,0,MATCH(I$2,Inputs!$D$2:$AG$2,0)),Inputs!$B$4:$B$200,$B25)/1000) -> 181.788 | J25: =IF(J$3=0,"",SUMIFS(INDEX(Inputs!$D$4:$AG$200,0,MATCH(J$2,Inputs!$D$2:$AG$2,0)),Inputs!$B$4:$B$200,$B25)/1000) -> 200.519 | K25: =IF(K$3=0,"",SUMIFS(INDEX(Inputs!$D$4:$AG$200,0,MATCH(K$2,Inputs!$D$2:$AG$2,0)),Inputs!$B$4:$B$200,$B25)/1000) -> 210.136 | L25: =IF(L$3=0,"",SUMIFS(INDEX(Inputs!$D$4:$AG$200,0,MATCH(L$2,Inputs!$D$2:$AG$2,0)),Inputs!$B$4:$B$200,$B25)/1000) -> 287.792 | M25: =IF(L25="","",L25) -> 287.792 | N25: =IF(N$3=0,"",SUMIFS(INDEX(Inputs!$D$4:$AG$200,0,MATCH(N$2,Inputs!$D$2:$AG$2,0)),Inputs!$B$4:$B$200,$B25)/1000) -> 298.068 | O25: =IF(O$3=0,"",SUMIFS(INDEX(Inputs!$D$4:$AG$200,0,MATCH(O$2,Inputs!$D$2:$AG$2,0)),Inputs!$B$4:$B$200,$B25)/1000) -> 299.325 | P25: =IF(P$3=0,"",SUMIFS(INDEX(Inputs!$D$4:$AG$200,0,MATCH(P$2,Inputs!$D$2:$AG$2,0)),Inputs!$B$4:$B$200,$B25)/1000) -> 304.534 | Q25: =IF(Q$3=0,"",SUMIFS(INDEX(Inputs!$D$4:$AG$200,0,MATCH(Q$2,Inputs!$D$2:$AG$2,0)),Inputs!$B$4:$B$200,$B25)/1000) -> 336.311 | R25: =IF(Q25="","",Q25) -> 336.311 | S25: =IF(S$3=0,"",SUMIFS(INDEX(Inputs!$D$4:$AG$200,0,MATCH(S$2,Inputs!$D$2:$AG$2,0)),Inputs!$B$4:$B$200,$B25)/1000) -> 329.214 | T25: =IF(T$3=0,"",SUMIFS(INDEX(Inputs!$D$4:$AG$200,0,MATCH(T$2,Inputs!$D$2:$AG$2,0)),Inputs!$B$4:$B$200,$B25)/1000) -> 335.703 | U25: =IF(U$3=0,"",SUMIFS(INDEX(Inputs!$D$4:$AG$200,0,MATCH(U$2,Inputs!$D$2:$AG$2,0)),Inputs!$B$4:$B$200,$B25)/1000) -> 339.4 | V25: =IF(V$3=0,"",SUMIFS(INDEX(Inputs!$D$4:$AG$200,0,MATCH(V$2,Inputs!$D$2:$AG$2,0)),Inputs!$B$4:$B$200,$B25)/1000) -> 342.163 | W25: =IF(V25="","",V25) -> 342.163 | X25: =IF(X$3=0,"",SUMIFS(INDEX(Inputs!$D$4:$AG$200,0,MATCH(X$2,Inputs!$D$2:$AG$2,0)),Inputs!$B$4:$B$200,$B25)/1000) -> 348.058 | Y25: =IF(Y$3=0,"",SUMIFS(INDEX(Inputs!$D$4:$AG$200,0,MATCH(Y$2,Inputs!$D$2:$AG$2,0)),Inputs!$B$4:$B$200,$B25)/1000) -> 353.536 | Z25: =IF(Z$3=0,"",SUMIFS(INDEX(Inputs!$D$4:$AG$200,0,MATCH(Z$2,Inputs!$D$2:$AG$2,0)),Inputs!$B$4:$B$200,$B25)/1000) -> 347.501 | AA25: =IF(AA$3=0,"",SUMIFS(INDEX(Inputs!$D$4:$AG$200,0,MATCH(AA$2,Inputs!$D$2:$AG$2,0)),Inputs!$B$4:$B$200,$B25)/1000) -> 350.075 | AB25: =IF(AA25="","",AA25) -> 350.075 | AC25: =IF(AC$3=0,"",SUMIFS(INDEX(Inputs!$D$4:$AG$200,0,MATCH(AC$2,Inputs!$D$2:$AG$2,0)),Inputs!$B$4:$B$200,$B25)/1000) -> 357.283 | AD25: =IF(AD$3=0,"",SUMIFS(INDEX(Inputs!$D$4:$AG$200,0,MATCH(AD$2,Inputs!$D$2:$AG$2,0)),Inputs!$B$4:$B$200,$B25)/1000) -> 384.741 | AE25: =IF(AE$3=0,"",SUMIFS(INDEX(Inputs!$D$4:$AG$200,0,MATCH(AE$2,Inputs!$D$2:$AG$2,0)),Inputs!$B$4:$B$200,$B25)/1000) | AF25: =IF(AF$3=0,"",SUMIFS(INDEX(Inputs!$D$4:$AG$200,0,MATCH(AF$2,Inputs!$D$2:$AG$2,0)),Inputs!$B$4:$B$200,$B25)/1000) | AG25: =IF(AF25="","",AF25)
B26: 22 | C26: Other non-current assets | D26: =IF(D$3=0,"",SUMIFS(INDEX(Inputs!$D$4:$AG$200,0,MATCH(D$2,Inputs!$D$2:$AG$2,0)),Inputs!$B$4:$B$200,$B26)/1000) -> 225.68 | E26: =IF(E$3=0,"",SUMIFS(INDEX(Inputs!$D$4:$AG$200,0,MATCH(E$2,Inputs!$D$2:$AG$2,0)),Inputs!$B$4:$B$200,$B26)/1000) -> 214.682 | F26: =IF(F$3=0,"",SUMIFS(INDEX(Inputs!$D$4:$AG$200,0,MATCH(F$2,Inputs!$D$2:$AG$2,0)),Inputs!$B$4:$B$200,$B26)/1000) -> 290.818 | G26: =IF(G$3=0,"",SUMIFS(INDEX(Inputs!$D$4:$AG$200,0,MATCH(G$2,Inputs!$D$2:$AG$2,0)),Inputs!$B$4:$B$200,$B26)/1000) -> 245.449 | H26: =IF(G26="","",G26) -> 245.449 | I26: =IF(I$3=0,"",SUMIFS(INDEX(Inputs!$D$4:$AG$200,0,MATCH(I$2,Inputs!$D$2:$AG$2,0)),Inputs!$B$4:$B$200,$B26)/1000) -> 252.512 | J26: =IF(J$3=0,"",SUMIFS(INDEX(Inputs!$D$4:$AG$200,0,MATCH(J$2,Inputs!$D$2:$AG$2,0)),Inputs!$B$4:$B$200,$B26)/1000) -> 277.495 | K26: =IF(K$3=0,"",SUMIFS(INDEX(Inputs!$D$4:$AG$200,0,MATCH(K$2,Inputs!$D$2:$AG$2,0)),Inputs!$B$4:$B$200,$B26)/1000) -> 674.305 | L26: =IF(L$3=0,"",SUMIFS(INDEX(Inputs!$D$4:$AG$200,0,MATCH(L$2,Inputs!$D$2:$AG$2,0)),Inputs!$B$4:$B$200,$B26)/1000) -> 675.656 | M26: =IF(L26="","",L26) -> 675.656 | N26: =IF(N$3=0,"",SUMIFS(INDEX(Inputs!$D$4:$AG$200,0,MATCH(N$2,Inputs!$D$2:$AG$2,0)),Inputs!$B$4:$B$200,$B26)/1000) -> 755.835 | O26: =IF(O$3=0,"",SUMIFS(INDEX(Inputs!$D$4:$AG$200,0,MATCH(O$2,Inputs!$D$2:$AG$2,0)),Inputs!$B$4:$B$200,$B26)/1000) -> 707.422 | P26: =IF(P$3=0,"",SUMIFS(INDEX(Inputs!$D$4:$AG$200,0,MATCH(P$2,Inputs!$D$2:$AG$2,0)),Inputs!$B$4:$B$200,$B26)/1000) -> 659.186 | Q26: =IF(Q$3=0,"",SUMIFS(INDEX(Inputs!$D$4:$AG$200,0,MATCH(Q$2,Inputs!$D$2:$AG$2,0)),Inputs!$B$4:$B$200,$B26)/1000) -> 713.693 | R26: =IF(Q26="","",Q26) -> 713.693 | S26: =IF(S$3=0,"",SUMIFS(INDEX(Inputs!$D$4:$AG$200,0,MATCH(S$2,Inputs!$D$2:$AG$2,0)),Inputs!$B$4:$B$200,$B26)/1000) -> 764.144 | T26: =IF(T$3=0,"",SUMIFS(INDEX(Inputs!$D$4:$AG$200,0,MATCH(T$2,Inputs!$D$2:$AG$2,0)),Inputs!$B$4:$B$200,$B26)/1000) -> 1312.67 | U26: =IF(U$3=0,"",SUMIFS(INDEX(Inputs!$D$4:$AG$200,0,MATCH(U$2,Inputs!$D$2:$AG$2,0)),Inputs!$B$4:$B$200,$B26)/1000) -> 1379.633 | V26: =IF(V$3=0,"",SUMIFS(INDEX(Inputs!$D$4:$AG$200,0,MATCH(V$2,Inputs!$D$2:$AG$2,0)),Inputs!$B$4:$B$200,$B26)/1000) -> 1367.26 | W26: =IF(V26="","",V26) -> 1367.26 | X26: =IF(X$3=0,"",SUMIFS(INDEX(Inputs!$D$4:$AG$200,0,MATCH(X$2,Inputs!$D$2:$AG$2,0)),Inputs!$B$4:$B$200,$B26)/1000) -> 927.891 | Y26: =IF(Y$3=0,"",SUMIFS(INDEX(Inputs!$D$4:$AG$200,0,MATCH(Y$2,Inputs!$D$2:$AG$2,0)),Inputs!$B$4:$B$200,$B26)/1000) -> 328.817 | Z26: =IF(Z$3=0,"",SUMIFS(INDEX(Inputs!$D$4:$AG$200,0,MATCH(Z$2,Inputs!$D$2:$AG$2,0)),Inputs!$B$4:$B$200,$B26)/1000) -> 390.774 | AA26: =IF(AA$3=0,"",SUMIFS(INDEX(Inputs!$D$4:$AG$200,0,MATCH(AA$2,Inputs!$D$2:$AG$2,0)),Inputs!$B$4:$B$200,$B26)/1000) -> 587.492 | AB26: =IF(AA26="","",AA26) -> 587.492 | AC26: =IF(AC$3=0,"",SUMIFS(INDEX(Inputs!$D$4:$AG$200,0,MATCH(AC$2,Inputs!$D$2:$AG$2,0)),Inputs!$B$4:$B$200,$B26)/1000) -> 633.65 | AD26: =IF(AD$3=0,"",SUMIFS(INDEX(Inputs!$D$4:$AG$200,0,MATCH(AD$2,Inputs!$D$2:$AG$2,0)),Inputs!$B$4:$B$200,$B26)/1000) -> 655.395 | AE26: =IF(AE$3=0,"",SUMIFS(INDEX(Inputs!$D$4:$AG$200,0,MATCH(AE$2,Inputs!$D$2:$AG$2,0)),Inputs!$B$4:$B$200,$B26)/1000) | AF26: =IF(AF$3=0,"",SUMIFS(INDEX(Inputs!$D$4:$AG$200,0,MATCH(AF$2,Inputs!$D$2:$AG$2,0)),Inputs!$B$4:$B$200,$B26)/1000) | AG26: =IF(AF26="","",AF26)
... B47: 41 | C47: Retained earnings | D47: =IF(D$3=0,"",SUMIFS(INDEX(Inputs!$D$4:$AG$200,0,MATCH(D$2,Inputs!$D$2:$AG$2,0)),Inputs!$B$4:$B$200,$B47)/1000) -> 394.069 | E47: =IF(E$3=0,"",SUMIFS(INDEX(Inputs!$D$4:$AG$200,0,MATCH(E$2,Inputs!$D$2:$AG$2,0)),Inputs!$B$4:$B$200,$B47)/1000) -> 544.089 | F47: =IF(F$3=0,"",SUMIFS(INDEX(Inputs!$D$4:$AG$200,0,MATCH(F$2,Inputs!$D$2:$AG$2,0)),Inputs!$B$4:$B$200,$B47)/1000) -> 771.873 | G47: =IF(G$3=0,"",SUMIFS(INDEX(Inputs!$D$4:$AG$200,0,MATCH(G$2,Inputs!$D$2:$AG$2,0)),Inputs!$B$4:$B$200,$B47)/1000) -> 913.96 | H47: =IF(G47="","",G47) -> 913.96 | I47: =IF(I$3=0,"",SUMIFS(INDEX(Inputs!$D$4:$AG$200,0,MATCH(I$2,Inputs!$D$2:$AG$2,0)),Inputs!$B$4:$B$200,$B47)/1000) -> 1118.054 | J47: =IF(J$3=0,"",SUMIFS(INDEX(Inputs!$D$4:$AG$200,0,MATCH(J$2,Inputs!$D$2:$AG$2,0)),Inputs!$B$4:$B$200,$B47)/1000) -> 1034.26 | K47: =IF(K$3=0,"",SUMIFS(INDEX(Inputs!$D$4:$AG$200,0,MATCH(K$2,Inputs!$D$2:$AG$2,0)),Inputs!$B$4:$B$200,$B47)/1000) -> 1072.979 | L47: =IF(L$3=0,"",SUMIFS(INDEX(Inputs!$D$4:$AG$200,0,MATCH(L$2,Inputs!$D$2:$AG$2,0)),Inputs!$B$4:$B$200,$B47)/1000) -> 992.503 | M47: =IF(L47="","",L47) -> 992.503 | N47: =IF(N$3=0,"",SUMIFS(INDEX(Inputs!$D$4:$AG$200,0,MATCH(N$2,Inputs!$D$2:$AG$2,0)),Inputs!$B$4:$B$200,$B47)/1000) -> 1013.55 | O47: =IF(O$3=0,"",SUMIFS(INDEX(Inputs!$D$4:$AG$200,0,MATCH(O$2,Inputs!$D$2:$AG$2,0)),Inputs!$B$4:$B$200,$B47)/1000) -> 995.684 | P47: =IF(P$3=0,"",SUMIFS(INDEX(Inputs!$D$4:$AG$200,0,MATCH(P$2,Inputs!$D$2:$AG$2,0)),Inputs!$B$4:$B$200,$B47)/1000) -> 929.958 | Q47: =IF(Q$3=0,"",SUMIFS(INDEX(Inputs!$D$4:$AG$200,0,MATCH(Q$2,Inputs!$D$2:$AG$2,0)),Inputs!$B$4:$B$200,$B47)/1000) -> 341.65 | R47: =IF(Q47="","",Q47) -> 341.65 | S47: =IF(S$3=0,"",SUMIFS(INDEX(Inputs!$D$4:$AG$200,0,MATCH(S$2,Inputs!$D$2:$AG$2,0)),Inputs!$B$4:$B$200,$B47)/1000) -> 390.201 | T47: =IF(T$3=0,"",SUMIFS(INDEX(Inputs!$D$4:$AG$200,0,MATCH(T$2,Inputs!$D$2:$AG$2,0)),Inputs!$B$4:$B$200,$B47)/1000) -> 432.75 | U47: =IF(U$3=0,"",SUMIFS(INDEX(Inputs!$D$4:$AG$200,0,MATCH(U$2,Inputs!$D$2:$AG$2,0)),Inputs!$B$4:$B$200,$B47)/1000) -> 510.974 | V47: =IF(V$3=0,"",SUMIFS(INDEX(Inputs!$D$4:$AG$200,0,MATCH(V$2,Inputs!$D$2:$AG$2,0)),Inputs!$B$4:$B$200,$B47)/1000) -> 509.847 | W47: =IF(V47="","",V47) -> 509.847 | X47: =IF(X$3=0,"",SUMIFS(INDEX(Inputs!$D$4:$AG$200,0,MATCH(X$2,Inputs!$D$2:$AG$2,0)),Inputs!$B$4:$B$200,$B47)/1000) -> 588.314 | Y47: =IF(Y$3=0,"",SUMIFS(INDEX(Inputs!$D$4:$AG$200,0,MATCH(Y$2,Inputs!$D$2:$AG$2,0)),Inputs!$B$4:$B$200,$B47)/1000) -> 655.91 | Z47: =IF(Z$3=0,"",SUMIFS(INDEX(Inputs!$D$4:$AG$200,0,MATCH(Z$2,Inputs!$D$2:$AG$2,0)),Inputs!$B$4:$B$200,$B47)/1000) -> 725.865 | AA47: =IF(AA$3=0,"",SUMIFS(INDEX(Inputs!$D$4:$AG$200,0,MATCH(AA$2,Inputs!$D$2:$AG$2,0)),Inputs!$B$4:$B$200,$B47)/1000) -> 573.211 | AB47: =IF(AA47="","",AA47) -> 573.211 | AC47: =IF(AC$3=0,"",SUMIFS(INDEX(Inputs!$D$4:$AG$200,0,MATCH(AC$2,Inputs!$D$2:$AG$2,0)),Inputs!$B$4:$B$200,$B47)/1000) -> 595.395 | AD47: =IF(AD$3=0,"",SUMIFS(INDEX(Inputs!$D$4:$AG$200,0,MATCH(AD$2,Inputs!$D$2:$AG$2,0)),Inputs!$B$4:$B$200,$B47)/1000) -> 731.045 | AE47: =IF(AE$3=0,"",SUMIFS(INDEX(Inputs!$D$4:$AG$200,0,MATCH(AE$2,Inputs!$D$2:$AG$2,0)),Inputs!$B$4:$B$200,$B47)/1000) | AF47: =IF(AF$3=0,"",SUMIFS(INDEX(Inputs!$D$4:$AG$200,0,MATCH(AF$2,Inputs!$D$2:$AG$2,0)),Inputs!$B$4:$B$200,$B47)/1000) | AG47: =IF(AF47="","",AF47)
B50: 44 | C50: Net income reported (lucro líquido reportado) — base do check de DRE [Model linha 4] | D50: =IF(SUMPRODUCT((Inputs!$B$4:$B$200=$B50)*ISNUMBER(INDEX(Inputs!$D$4:$AG$200,0,MATCH(D$2,Inputs!$D$2:$AG$2,0))))=0,"",SUMIFS(INDEX(Inputs!$D$4:$AG$200,0,MATCH(D$2,Inputs!$D$2:$AG$2,0)),Inputs!$B$4:$B$200,$B50)/1000) -> 109.481 | E50: =IF(SUMPRODUCT((Inputs!$B$4:$B$200=$B50)*ISNUMBER(INDEX(Inputs!$D$4:$AG$200,0,MATCH(E$2,Inputs!$D$2:$AG$2,0))))=0,"",SUMIFS(INDEX(Inputs!$D$4:$AG$200,0,MATCH(E$2,Inputs!$D$2:$AG$2,0)),Inputs!$B$4:$B$200,$B50)/1000) -> 173.921 | F50: =IF(SUMPRODUCT((Inputs!$B$4:$B$200=$B50)*ISNUMBER(INDEX(Inputs!$D$4:$AG$200,0,MATCH(F$2,Inputs!$D$2:$AG$2,0))))=0,"",SUMIFS(INDEX(Inputs!$D$4:$AG$200,0,MATCH(F$2,Inputs!$D$2:$AG$2,0)),Inputs!$B$4:$B$200,$B50)/1000) -> 259.381 | G50: =IF(SUMPRODUCT((Inputs!$B$4:$B$200=$B50)*ISNUMBER(INDEX(Inputs!$D$4:$AG$200,0,MATCH(G$2,Inputs!$D$2:$AG$2,0))))=0,"",SUMIFS(INDEX(Inputs!$D$4:$AG$200,0,MATCH(G$2,Inputs!$D$2:$AG$2,0)),Inputs!$B$4:$B$200,$B50)/1000) -> 276.656 | H50: =IF(COUNT(D50:G50)=4,SUM(D50:G50),"") -> 819.439 | I50: =IF(SUMPRODUCT((Inputs!$B$4:$B$200=$B50)*ISNUMBER(INDEX(Inputs!$D$4:$AG$200,0,MATCH(I$2,Inputs!$D$2:$AG$2,0))))=0,"",SUMIFS(INDEX(Inputs!$D$4:$AG$200,0,MATCH(I$2,Inputs!$D$2:$AG$2,0)),Inputs!$B$4:$B$200,$B50)/1000) -> 258.068 | J50: =IF(SUMPRODUCT((Inputs!$B$4:$B$200=$B50)*ISNUMBER(INDEX(Inputs!$D$4:$AG$200,0,MATCH(J$2,Inputs!$D$2:$AG$2,0))))=0,"",SUMIFS(INDEX(Inputs!$D$4:$AG$200,0,MATCH(J$2,Inputs!$D$2:$AG$2,0)),Inputs!$B$4:$B$200,$B50)/1000) -> 186.761 | K50: =IF(SUMPRODUCT((Inputs!$B$4:$B$200=$B50)*ISNUMBER(INDEX(Inputs!$D$4:$AG$200,0,MATCH(K$2,Inputs!$D$2:$AG$2,0))))=0,"",SUMIFS(INDEX(Inputs!$D$4:$AG$200,0,MATCH(K$2,Inputs!$D$2:$AG$2,0)),Inputs!$B$4:$B$200,$B50)/1000) -> 93.718 | L50: =IF(SUMPRODUCT((Inputs!$B$4:$B$200=$B50)*ISNUMBER(INDEX(Inputs!$D$4:$AG$200,0,MATCH(L$2,Inputs!$D$2:$AG$2,0))))=0,"",SUMIFS(INDEX(Inputs!$D$4:$AG$200,0,MATCH(L$2,Inputs!$D$2:$AG$2,0)),Inputs!$B$4:$B$200,$B50)/1000) -> 17.831 | M50: =IF(COUNT(I50:L50)=4,SUM(I50:L50),"") -> 556.378 | N50: =IF(SUMPRODUCT((Inputs!$B$4:$B$200=$B50)*ISNUMBER(INDEX(Inputs!$D$4:$AG$200,0,MATCH(N$2,Inputs!$D$2:$AG$2,0))))=0,"",SUMIFS(INDEX(Inputs!$D$4:$AG$200,0,MATCH(N$2,Inputs!$D$2:$AG$2,0)),Inputs!$B$4:$B$200,$B50)/1000) -> 21.044 | O50: =IF(SUMPRODUCT((Inputs!$B$4:$B$200=$B50)*ISNUMBER(INDEX(Inputs!$D$4:$AG$200,0,MATCH(O$2,Inputs!$D$2:$AG$2,0))))=0,"",SUMIFS(INDEX(Inputs!$D$4:$AG$200,0,MATCH(O$2,Inputs!$D$2:$AG$2,0)),Inputs!$B$4:$B$200,$B50)/1000) -> -17.864 | P50: =IF(SUMPRODUCT((Inputs!$B$4:$B$200=$B50)*ISNUMBER(INDEX(Inputs!$D$4:$AG$200,0,MATCH(P$2,Inputs!$D$2:$AG$2,0))))=0,"",SUMIFS(INDEX(Inputs!$D$4:$AG$200,0,MATCH(P$2,Inputs!$D$2:$AG$2,0)),Inputs!$B$4:$B$200,$B50)/1000) -> -65.721 | Q50: =IF(SUMPRODUCT((Inputs!$B$4:$B$200=$B50)*ISNUMBER(INDEX(Inputs!$D$4:$AG$200,0,MATCH(Q$2,Inputs!$D$2:$AG$2,0))))=0,"",SUMIFS(INDEX(Inputs!$D$4:$AG$200,0,MATCH(Q$2,Inputs!$D$2:$AG$2,0)),Inputs!$B$4:$B$200,$B50)/1000) -> -588.309 | R50: =IF(COUNT(N50:Q50)=4,SUM(N50:Q50),"") -> -650.85 | S50: =IF(SUMPRODUCT((Inputs!$B$4:$B$200=$B50)*ISNUMBER(INDEX(Inputs!$D$4:$AG$200,0,MATCH(S$2,Inputs!$D$2:$AG$2,0))))=0,"",SUMIFS(INDEX(Inputs!$D$4:$AG$200,0,MATCH(S$2,Inputs!$D$2:$AG$2,0)),Inputs!$B$4:$B$200,$B50)/1000) -> 48.599 | T50: =IF(SUMPRODUCT((Inputs!$B$4:$B$200=$B50)*ISNUMBER(INDEX(Inputs!$D$4:$AG$200,0,MATCH(T$2,Inputs!$D$2:$AG$2,0))))=0,"",SUMIFS(INDEX(Inputs!$D$4:$AG$200,0,MATCH(T$2,Inputs!$D$2:$AG$2,0)),Inputs!$B$4:$B$200,$B50)/1000) -> 42.548 | U50: =IF(SUMPRODUCT((Inputs!$B$4:$B$200=$B50)*ISNUMBER(INDEX(Inputs!$D$4:$AG$200,0,MATCH(U$2,Inputs!$D$2:$AG$2,0))))=0,"",SUMIFS(INDEX(Inputs!$D$4:$AG$200,0,MATCH(U$2,Inputs!$D$2:$AG$2,0)),Inputs!$B$4:$B$200,$B50)/1000) -> 78.194 | V50: =IF(SUMPRODUCT((Inputs!$B$4:$B$200=$B50)*ISNUMBER(INDEX(Inputs!$D$4:$AG$200,0,MATCH(V$2,Inputs!$D$2:$AG$2,0))))=0,"",SUMIFS(INDEX(Inputs!$D$4:$AG$200,0,MATCH(V$2,Inputs!$D$2:$AG$2,0)),Inputs!$B$4:$B$200,$B50)/1000) -> 62.171 | W50: =IF(COUNT(S50:V50)=4,SUM(S50:V50),"") -> 231.512 | X50: =IF(SUMPRODUCT((Inputs!$B$4:$B$200=$B50)*ISNUMBER(INDEX(Inputs!$D$4:$AG$200,0,MATCH(X$2,Inputs!$D$2:$AG$2,0))))=0,"",SUMIFS(INDEX(Inputs!$D$4:$AG$200,0,MATCH(X$2,Inputs!$D$2:$AG$2,0)),Inputs!$B$4:$B$200,$B50)/1000) -> 78.468 | Y50: =IF(SUMPRODUCT((Inputs!$B$4:$B$200=$B50)*ISNUMBER(INDEX(Inputs!$D$4:$AG$200,0,MATCH(Y$2,Inputs!$D$2:$AG$2,0))))=0,"",SUMIFS(INDEX(Inputs!$D$4:$AG$200,0,MATCH(Y$2,Inputs!$D$2:$AG$2,0)),Inputs!$B$4:$B$200,$B50)/1000) -> 67.595 | Z50: =IF(SUMPRODUCT((Inputs!$B$4:$B$200=$B50)*ISNUMBER(INDEX(Inputs!$D$4:$AG$200,0,MATCH(Z$2,Inputs!$D$2:$AG$2,0))))=0,"",SUMIFS(INDEX(Inputs!$D$4:$AG$200,0,MATCH(Z$2,Inputs!$D$2:$AG$2,0)),Inputs!$B$4:$B$200,$B50)/1000) -> 69.955 | AA50: =IF(SUMPRODUCT((Inputs!$B$4:$B$200=$B50)*ISNUMBER(INDEX(Inputs!$D$4:$AG$200,0,MATCH(AA$2,Inputs!$D$2:$AG$2,0))))=0,"",SUMIFS(INDEX(Inputs!$D$4:$AG$200,0,MATCH(AA$2,Inputs!$D$2:$AG$2,0)),Inputs!$B$4:$B$200,$B50)/1000) -> 102.34411 | AB50: =IF(COUNT(X50:AA50)=4,SUM(X50:AA50),"") -> 318.36211 | AC50: =IF(SUMPRODUCT((Inputs!$B$4:$B$200=$B50)*ISNUMBER(INDEX(Inputs!$D$4:$AG$200,0,MATCH(AC$2,Inputs!$D$2:$AG$2,0))))=0,"",SUMIFS(INDEX(Inputs!$D$4:$AG$200,0,MATCH(AC$2,Inputs!$D$2:$AG$2,0)),Inputs!$B$4:$B$200,$B50)/1000) -> 124.51319 | AD50: =IF(SUMPRODUCT((Inputs!$B$4:$B$200=$B50)*ISNUMBER(INDEX(Inputs!$D$4:$AG$200,0,MATCH(AD$2,Inputs!$D$2:$AG$2,0))))=0,"",SUMIFS(INDEX(Inputs!$D$4:$AG$200,0,MATCH(AD$2,Inputs!$D$2:$AG$2,0)),Inputs!$B$4:$B$200,$B50)/1000) -> 135.64966 | AE50: =IF(SUMPRODUCT((Inputs!$B$4:$B$200=$B50)*ISNUMBER(INDEX(Inputs!$D$4:$AG$200,0,MATCH(AE$2,Inputs!$D$2:$AG$2,0))))=0,"",SUMIFS(INDEX(Inputs!$D$4:$AG$200,0,MATCH(AE$2,Inputs!$D$2:$AG$2,0)),Inputs!$B$4:$B$200,$B50)/1000) | AF50: =IF(SUMPRODUCT((Inputs!$B$4:$B$200=$B50)*ISNUMBER(INDEX(Inputs!$D$4:$AG$200,0,MATCH(AF$2,Inputs!$D$2:$AG$2,0))))=0,"",SUMIFS(INDEX(Inputs!$D$4:$AG$200,0,MATCH(AF$2,Inputs!$D$2:$AG$2,0)),Inputs!$B$4:$B$200,$B50)/1000) | AG50: =IF(COUNT(AC50:AF50)=4,SUM(AC50:AF50),"")
C52: Drivers de receita (memo) - codigos 45+ [Model, bloco abaixo da receita liquida]
B53: 45 | C53: Receita liquida RAC Brasil (DRE l.11) | D53: =IF(SUMPRODUCT((Inputs!$B$4:$B$200=$B53)*ISNUMBER(INDEX(Inputs!$D$4:$AG$200,0,MATCH(D$2,Inputs!$D$2:$AG$2,0))))=0,"",SUMIFS(INDEX(Inputs!$D$4:$AG$200,0,MATCH(D$2,Inputs!$D$2:$AG$2,0)),Inputs!$B$4:$B$200,$B53)/1000) -> 328.988 | E53: =IF(SUMPRODUCT((Inputs!$B$4:$B$200=$B53)*ISNUMBER(INDEX(Inputs!$D$4:$AG$200,0,MATCH(E$2,Inputs!$D$2:$AG$2,0))))=0,"",SUMIFS(INDEX(Inputs!$D$4:$AG$200,0,MATCH(E$2,Inputs!$D$2:$AG$2,0)),Inputs!$B$4:$B$200,$B53)/1000) -> 308.291 | F53: =IF(SUMPRODUCT((Inputs!$B$4:$B$200=$B53)*ISNUMBER(INDEX(Inputs!$D$4:$AG$200,0,MATCH(F$2,Inputs!$D$2:$AG$2,0))))=0,"",SUMIFS(INDEX(Inputs!$D$4:$AG$200,0,MATCH(F$2,Inputs!$D$2:$AG$2,0)),Inputs!$B$4:$B$200,$B53)/1000) -> 403.799 | G53: =IF(SUMPRODUCT((Inputs!$B$4:$B$200=$B53)*ISNUMBER(INDEX(Inputs!$D$4:$AG$200,0,MATCH(G$2,Inputs!$D$2:$AG$2,0))))=0,"",SUMIFS(INDEX(Inputs!$D$4:$AG$200,0,MATCH(G$2,Inputs!$D$2:$AG$2,0)),Inputs!$B$4:$B$200,$B53)/1000) -> 522.57 | H53: =IF(COUNT(D53:G53)=4,SUM(D53:G53),"") -> 1563.648 | I53: =IF(SUMPRODUCT((Inputs!$B$4:$B$200=$B53)*ISNUMBER(INDEX(Inputs!$D$4:$AG$200,0,MATCH(I$2,Inputs!$D$2:$AG$2,0))))=0,"",SUMIFS(INDEX(Inputs!$D$4:$AG$200,0,MATCH(I$2,Inputs!$D$2:$AG$2,0)),Inputs!$B$4:$B$200,$B53)/1000) -> 552.692 | J53: =IF(SUMPRODUCT((Inputs!$B$4:$B$200=$B53)*ISNUMBER(INDEX(Inputs!$D$4:$AG$200,0,MATCH(J$2,Inputs!$D$2:$AG$2,0))))=0,"",SUMIFS(INDEX(Inputs!$D$4:$AG$200,0,MATCH(J$2,Inputs!$D$2:$AG$2,0)),Inputs!$B$4:$B$200,$B53)/1000) -> 585.184 | K53: =IF(SUMPRODUCT((Inputs!$B$4:$B$200=$B53)*ISNUMBER(INDEX(Inputs!$D$4:$AG$200,0,MATCH(K$2,Inputs!$D$2:$AG$2,0))))=0,"",SUMIFS(INDEX(Inputs!$D$4:$AG$200,0,MATCH(K$2,Inputs!$D$2:$AG$2,0)),Inputs!$B$4:$B$200,$B53)/1000) -> 675.359 | L53: =IF(SUMPRODUCT((Inputs!$B$4:$B$200=$B53)*ISNUMBER(INDEX(Inputs!$D$4:$AG$200,0,MATCH(L$2,Inputs!$D$2:$AG$2,0))))=0,"",SUMIFS(INDEX(Inputs!$D$4:$AG$200,0,MATCH(L$2,Inputs!$D$2:$AG$2,0)),Inputs!$B$4:$B$200,$B53)/1000) -> 682.873 | M53: =IF(COUNT(I53:L53)=4,SUM(I53:L53),"") -> 2496.108 | N53: =IF(SUMPRODUCT((Inputs!$B$4:$B$200=$B53)*ISNUMBER(INDEX(Inputs!$D$4:$AG$200,0,MATCH(N$2,Inputs!$D$2:$AG$2,0))))=0,"",SUMIFS(INDEX(Inputs!$D$4:$AG$200,0,MATCH(N$2,Inputs!$D$2:$AG$2,0)),Inputs!$B$4:$B$200,$B53)/1000) -> 686.638 | O53: =IF(SUMPRODUCT((Inputs!$B$4:$B$200=$B53)*ISNUMBER(INDEX(Inputs!$D$4:$AG$200,0,MATCH(O$2,Inputs!$D$2:$AG$2,0))))=0,"",SUMIFS(INDEX(Inputs!$D$4:$AG$200,0,MATCH(O$2,Inputs!$D$2:$AG$2,0)),Inputs!$B$4:$B$200,$B53)/1000) -> 646.165 | P53: =IF(SUMPRODUCT((Inputs!$B$4:$B$200=$B53)*ISNUMBER(INDEX(Inputs!$D$4:$AG$200,0,MATCH(P$2,Inputs!$D$2:$AG$2,0))))=0,"",SUMIFS(INDEX(Inputs!$D$4:$AG$200,0,MATCH(P$2,Inputs!$D$2:$AG$2,0)),Inputs!$B$4:$B$200,$B53)/1000) -> 651.205 | Q53: =IF(SUMPRODUCT((Inputs!$B$4:$B$200=$B53)*ISNUMBER(INDEX(Inputs!$D$4:$AG$200,0,MATCH(Q$2,Inputs!$D$2:$AG$2,0))))=0,"",SUMIFS(INDEX(Inputs!$D$4:$AG$200,0,MATCH(Q$2,Inputs!$D$2:$AG$2,0)),Inputs!$B$4:$B$200,$B53)/1000) -> 674.999 | R53: =IF(COUNT(N53:Q53)=4,SUM(N53:Q53),"") -> 2659.007 | S53: =IF(SUMPRODUCT((Inputs!$B$4:$B$200=$B53)*ISNUMBER(INDEX(Inputs!$D$4:$AG$200,0,MATCH(S$2,Inputs!$D$2:$AG$2,0))))=0,"",SUMIFS(INDEX(Inputs!$D$4:$AG$200,0,MATCH(S$2,Inputs!$D$2:$AG$2,0)),Inputs!$B$4:$B$200,$B53)/1000) -> 751.762 | T53: =IF(SUMPRODUCT((Inputs!$B$4:$B$200=$B53)*ISNUMBER(INDEX(Inputs!$D$4:$AG$200,0,MATCH(T$2,Inputs!$D$2:$AG$2,0))))=0,"",SUMIFS(INDEX(Inputs!$D$4:$AG$200,0,MATCH(T$2,Inputs!$D$2:$AG$2,0)),Inputs!$B$4:$B$200,$B53)/1000) -> 748.549 | U53: =IF(SUMPRODUCT((Inputs!$B$4:$B$200=$B53)*ISNUMBER(INDEX(Inputs!$D$4:$AG$200,0,MATCH(U$2,Inputs!$D$2:$AG$2,0))))=0,"",SUMIFS(INDEX(Inputs!$D$4:$AG$200,0,MATCH(U$2,Inputs!$D$2:$AG$2,0)),Inputs!$B$4:$B$200,$B53)/1000) -> 764.768 | V53: =IF(SUMPRODUCT((Inputs!$B$4:$B$200=$B53)*ISNUMBER(INDEX(Inputs!$D$4:$AG$200,0,MATCH(V$2,Inputs!$D$2:$AG$2,0))))=0,"",SUMIFS(INDEX(Inputs!$D$4:$AG$200,0,MATCH(V$2,Inputs!$D$2:$AG$2,0)),Inputs!$B$4:$B$200,$B53)/1000) -> 808.526 | W53: =IF(COUNT(S53:V53)=4,SUM(S53:V53),"") -> 3073.605 | X53: =IF(SUMPRODUCT((Inputs!$B$4:$B$200=$B53)*ISNUMBER(INDEX(Inputs!$D$4:$AG$200,0,MATCH(X$2,Inputs!$D$2:$AG$2,0))))=0,"",SUMIFS(INDEX(Inputs!$D$4:$AG$200,0,MATCH(X$2,Inputs!$D$2:$AG$2,0)),Inputs!$B$4:$B$200,$B53)/1000) -> 859.38 | Y53: =IF(SUMPRODUCT((Inputs!$B$4:$B$200=$B53)*ISNUMBER(INDEX(Inputs!$D$4:$AG$200,0,MATCH(Y$2,Inputs!$D$2:$AG$2,0))))=0,"",SUMIFS(INDEX(Inputs!$D$4:$AG$200,0,MATCH(Y$2,Inputs!$D$2:$AG$2,0)),Inputs!$B$4:$B$200,$B53)/1000) -> 843.303 | Z53: =IF(SUMPRODUCT((Inputs!$B$4:$B$200=$B53)*ISNUMBER(INDEX(Inputs!$D$4:$AG$200,0,MATCH(Z$2,Inputs!$D$2:$AG$2,0))))=0,"",SUMIFS(INDEX(Inputs!$D$4:$AG$200,0,MATCH(Z$2,Inputs!$D$2:$AG$2,0)),Inputs!$B$4:$B$200,$B53)/1000) -> 874.046 | AA53: =IF(SUMPRODUCT((Inputs!$B$4:$B$200=$B53)*ISNUMBER(INDEX(Inputs!$D$4:$AG$200,0,MATCH(AA$2,Inputs!$D$2:$AG$2,0))))=0,"",SUMIFS(INDEX(Inputs!$D$4:$AG$200,0,MATCH(AA$2,Inputs!$D$2:$AG$2,0)),Inputs!$B$4:$B$200,$B53)/1000) -> 968.87078 | AB53: =IF(COUNT(X53:AA53)=4,SUM(X53:AA53),"") -> 3545.5998 | AC53: =IF(SUMPRODUCT((Inputs!$B$4:$B$200=$B53)*ISNUMBER(INDEX(Inputs!$D$4:$AG$200,0,MATCH(AC$2,Inputs!$D$2:$AG$2,0))))=0,"",SUMIFS(INDEX(Inputs!$D$4:$AG$200,0,MATCH(AC$2,Inputs!$D$2:$AG$2,0)),Inputs!$B$4:$B$200,$B53)/1000) -> 1076.1205 | AD53: =IF(SUMPRODUCT((Inputs!$B$4:$B$200=$B53)*ISNUMBER(INDEX(Inputs!$D$4:$AG$200,0,MATCH(AD$2,Inputs!$D$2:$AG$2,0))))=0,"",SUMIFS(INDEX(Inputs!$D$4:$AG$200,0,MATCH(AD$2,Inputs!$D$2:$AG$2,0)),Inputs!$B$4:$B$200,$B53)/1000) -> 1099.7123 | AE53: =IF(SUMPRODUCT((Inputs!$B$4:$B$200=$B53)*ISNUMBER(INDEX(Inputs!$D$4:$AG$200,0,MATCH(AE$2,Inputs!$D$2:$AG$2,0))))=0,"",SUMIFS(INDEX(Inputs!$D$4:$AG$200,0,MATCH(AE$2,Inputs!$D$2:$AG$2,0)),Inputs!$B$4:$B$200,$B53)/1000) | AF53: =IF(SUMPRODUCT((Inputs!$B$4:$B$200=$B53)*ISNUMBER(INDEX(Inputs!$D$4:$AG$200,0,MATCH(AF$2,Inputs!$D$2:$AG$2,0))))=0,"",SUMIFS(INDEX(Inputs!$D$4:$AG$200,0,MATCH(AF$2,Inputs!$D$2:$AG$2,0)),Inputs!$B$4:$B$200,$B53)/1000) | AG53: =IF(COUNT(AC53:AF53)=4,SUM(AC53:AF53),"")
B54: 46 | C54: Receita liquida RAC Portugal (DRE l.30; desde a aquisicao em 2023) | D54: =IF(SUMPRODUCT((Inputs!$B$4:$B$200=$B54)*ISNUMBER(INDEX(Inputs!$D$4:$AG$200,0,MATCH(D$2,Inputs!$D$2:$AG$2,0))))=0,"",SUMIFS(INDEX(Inputs!$D$4:$AG$200,0,MATCH(D$2,Inputs!$D$2:$AG$2,0)),Inputs!$B$4:$B$200,$B54)/1000) -> 0 | E54: =IF(SUMPRODUCT((Inputs!$B$4:$B$200=$B54)*ISNUMBER(INDEX(Inputs!$D$4:$AG$200,0,MATCH(E$2,Inputs!$D$2:$AG$2,0))))=0,"",SUMIFS(INDEX(Inputs!$D$4:$AG$200,0,MATCH(E$2,Inputs!$D$2:$AG$2,0)),Inputs!$B$4:$B$200,$B54)/1000) -> 0 | F54: =IF(SUMPRODUCT((Inputs!$B$4:$B$200=$B54)*ISNUMBER(INDEX(Inputs!$D$4:$AG$200,0,MATCH(F$2,Inputs!$D$2:$AG$2,0))))=0,"",SUMIFS(INDEX(Inputs!$D$4:$AG$200,0,MATCH(F$2,Inputs!$D$2:$AG$2,0)),Inputs!$B$4:$B$200,$B54)/1000) -> 0 | G54: =IF(SUMPRODUCT((Inputs!$B$4:$B$200=$B54)*ISNUMBER(INDEX(Inputs!$D$4:$AG$200,0,MATCH(G$2,Inputs!$D$2:$AG$2,0))))=0,"",SUMIFS(INDEX(Inputs!$D$4:$AG$200,0,MATCH(G$2,Inputs!$D$2:$AG$2,0)),Inputs!$B$4:$B$200,$B54)/1000) -> 0 | H54: =IF(COUNT(D54:G54)=4,SUM(D54:G54),"") -> 0 | I54: =IF(SUMPRODUCT((Inputs!$B$4:$B$200=$B54)*ISNUMBER(INDEX(Inputs!$D$4:$AG$200,0,MATCH(I$2,Inputs!$D$2:$AG$2,0))))=0,"",SUMIFS(INDEX(Inputs!$D$4:$AG$200,0,MATCH(I$2,Inputs!$D$2:$AG$2,0)),Inputs!$B$4:$B$200,$B54)/1000) -> 0 | J54: =IF(SUMPRODUCT((Inputs!$B$4:$B$200=$B54)*ISNUMBER(INDEX(Inputs!$D$4:$AG$200,0,MATCH(J$2,Inputs!$D$2:$AG$2,0))))=0,"",SUMIFS(INDEX(Inputs!$D$4:$AG$200,0,MATCH(J$2,Inputs!$D$2:$AG$2,0)),Inputs!$B$4:$B$200,$B54)/1000) -> 0 | K54: =IF(SUMPRODUCT((Inputs!$B$4:$B$200=$B54)*ISNUMBER(INDEX(Inputs!$D$4:$AG$200,0,MATCH(K$2,Inputs!$D$2:$AG$2,0))))=0,"",SUMIFS(INDEX(Inputs!$D$4:$AG$200,0,MATCH(K$2,Inputs!$D$2:$AG$2,0)),Inputs!$B$4:$B$200,$B54)/1000) -> 0 | L54: =IF(SUMPRODUCT((Inputs!$B$4:$B$200=$B54)*ISNUMBER(INDEX(Inputs!$D$4:$AG$200,0,MATCH(L$2,Inputs!$D$2:$AG$2,0))))=0,"",SUMIFS(INDEX(Inputs!$D$4:$AG$200,0,MATCH(L$2,Inputs!$D$2:$AG$2,0)),Inputs!$B$4:$B$200,$B54)/1000) -> 43.829 | M54: =IF(COUNT(I54:L54)=4,SUM(I54:L54),"") -> 43.829 | N54: =IF(SUMPRODUCT((Inputs!$B$4:$B$200=$B54)*ISNUMBER(INDEX(Inputs!$D$4:$AG$200,0,MATCH(N$2,Inputs!$D$2:$AG$2,0))))=0,"",SUMIFS(INDEX(Inputs!$D$4:$AG$200,0,MATCH(N$2,Inputs!$D$2:$AG$2,0)),Inputs!$B$4:$B$200,$B54)/1000) -> 14.396 | O54: =IF(SUMPRODUCT((Inputs!$B$4:$B$200=$B54)*ISNUMBER(INDEX(Inputs!$D$4:$AG$200,0,MATCH(O$2,Inputs!$D$2:$AG$2,0))))=0,"",SUMIFS(INDEX(Inputs!$D$4:$AG$200,0,MATCH(O$2,Inputs!$D$2:$AG$2,0)),Inputs!$B$4:$B$200,$B54)/1000) -> 29.467 | P54: =IF(SUMPRODUCT((Inputs!$B$4:$B$200=$B54)*ISNUMBER(INDEX(Inputs!$D$4:$AG$200,0,MATCH(P$2,Inputs!$D$2:$AG$2,0))))=0,"",SUMIFS(INDEX(Inputs!$D$4:$AG$200,0,MATCH(P$2,Inputs!$D$2:$AG$2,0)),Inputs!$B$4:$B$200,$B54)/1000) -> 64.989 | Q54: =IF(SUMPRODUCT((Inputs!$B$4:$B$200=$B54)*ISNUMBER(INDEX(Inputs!$D$4:$AG$200,0,MATCH(Q$2,Inputs!$D$2:$AG$2,0))))=0,"",SUMIFS(INDEX(Inputs!$D$4:$AG$200,0,MATCH(Q$2,Inputs!$D$2:$AG$2,0)),Inputs!$B$4:$B$200,$B54)/1000) -> 29.385 | R54: =IF(COUNT(N54:Q54)=4,SUM(N54:Q54),"") -> 138.237 | S54: =IF(SUMPRODUCT((Inputs!$B$4:$B$200=$B54)*ISNUMBER(INDEX(Inputs!$D$4:$AG$200,0,MATCH(S$2,Inputs!$D$2:$AG$2,0))))=0,"",SUMIFS(INDEX(Inputs!$D$4:$AG$200,0,MATCH(S$2,Inputs!$D$2:$AG$2,0)),Inputs!$B$4:$B$200,$B54)/1000) -> 23.047 | T54: =IF(SUMPRODUCT((Inputs!$B$4:$B$200=$B54)*ISNUMBER(INDEX(Inputs!$D$4:$AG$200,0,MATCH(T$2,Inputs!$D$2:$AG$2,0))))=0,"",SUMIFS(INDEX(Inputs!$D$4:$AG$200,0,MATCH(T$2,Inputs!$D$2:$AG$2,0)),Inputs!$B$4:$B$200,$B54)/1000) -> 43.533 | U54: =IF(SUMPRODUCT((Inputs!$B$4:$B$200=$B54)*ISNUMBER(INDEX(Inputs!$D$4:$AG$200,0,MATCH(U$2,Inputs!$D$2:$AG$2,0))))=0,"",SUMIFS(INDEX(Inputs!$D$4:$AG$200,0,MATCH(U$2,Inputs!$D$2:$AG$2,0)),Inputs!$B$4:$B$200,$B54)/1000) -> 90.502 | V54: =IF(SUMPRODUCT((Inputs!$B$4:$B$200=$B54)*ISNUMBER(INDEX(Inputs!$D$4:$AG$200,0,MATCH(V$2,Inputs!$D$2:$AG$2,0))))=0,"",SUMIFS(INDEX(Inputs!$D$4:$AG$200,0,MATCH(V$2,Inputs!$D$2:$AG$2,0)),Inputs!$B$4:$B$200,$B54)/1000) -> 39.179 | W54: =IF(COUNT(S54:V54)=4,SUM(S54:V54),"") -> 196.261 | X54: =IF(SUMPRODUCT((Inputs!$B$4:$B$200=$B54)*ISNUMBER(INDEX(Inputs!$D$4:$AG$200,0,MATCH(X$2,Inputs!$D$2:$AG$2,0))))=0,"",SUMIFS(INDEX(Inputs!$D$4:$AG$200,0,MATCH(X$2,Inputs!$D$2:$AG$2,0)),Inputs!$B$4:$B$200,$B54)/1000) -> 26.343 | Y54: =IF(SUMPRODUCT((Inputs!$B$4:$B$200=$B54)*ISNUMBER(INDEX(Inputs!$D$4:$AG$200,0,MATCH(Y$2,Inputs!$D$2:$AG$2,0))))=0,"",SUMIFS(INDEX(Inputs!$D$4:$AG$200,0,MATCH(Y$2,Inputs!$D$2:$AG$2,0)),Inputs!$B$4:$B$200,$B54)/1000) -> 53.453 | Z54: =IF(SUMPRODUCT((Inputs!$B$4:$B$200=$B54)*ISNUMBER(INDEX(Inputs!$D$4:$AG$200,0,MATCH(Z$2,Inputs!$D$2:$AG$2,0))))=0,"",SUMIFS(INDEX(Inputs!$D$4:$AG$200,0,MATCH(Z$2,Inputs!$D$2:$AG$2,0)),Inputs!$B$4:$B$200,$B54)/1000) -> 103.339 | AA54: =IF(SUMPRODUCT((Inputs!$B$4:$B$200=$B54)*ISNUMBER(INDEX(Inputs!$D$4:$AG$200,0,MATCH(AA$2,Inputs!$D$2:$AG$2,0))))=0,"",SUMIFS(INDEX(Inputs!$D$4:$AG$200,0,MATCH(AA$2,Inputs!$D$2:$AG$2,0)),Inputs!$B$4:$B$200,$B54)/1000) -> 43.916766 | AB54: =IF(COUNT(X54:AA54)=4,SUM(X54:AA54),"") -> 227.05177 | AC54: =IF(SUMPRODUCT((Inputs!$B$4:$B$200=$B54)*ISNUMBER(INDEX(Inputs!$D$4:$AG$200,0,MATCH(AC$2,Inputs!$D$2:$AG$2,0))))=0,"",SUMIFS(INDEX(Inputs!$D$4:$AG$200,0,MATCH(AC$2,Inputs!$D$2:$AG$2,0)),Inputs!$B$4:$B$200,$B54)/1000) -> 27.887442 | AD54: =IF(SUMPRODUCT((Inputs!$B$4:$B$200=$B54)*ISNUMBER(INDEX(Inputs!$D$4:$AG$200,0,MATCH(AD$2,Inputs!$D$2:$AG$2,0))))=0,"",SUMIFS(INDEX(Inputs!$D$4:$AG$200,0,MATCH(AD$2,Inputs!$D$2:$AG$2,0)),Inputs!$B$4:$B$200,$B54)/1000) -> 45.853258 | AE54: =IF(SUMPRODUCT((Inputs!$B$4:$B$200=$B54)*ISNUMBER(INDEX(Inputs!$D$4:$AG$200,0,MATCH(AE$2,Inputs!$D$2:$AG$2,0))))=0,"",SUMIFS(INDEX(Inputs!$D$4:$AG$200,0,MATCH(AE$2,Inputs!$D$2:$AG$2,0)),Inputs!$B$4:$B$200,$B54)/1000) | AF54: =IF(SUMPRODUCT((Inputs!$B$4:$B$200=$B54)*ISNUMBER(INDEX(Inputs!$D$4:$AG$200,0,MATCH(AF$2,Inputs!$D$2:$AG$2,0))))=0,"",SUMIFS(INDEX(Inputs!$D$4:$AG$200,0,MATCH(AF$2,Inputs!$D$2:$AG$2,0)),Inputs!$B$4:$B$200,$B54)/1000) | AG54: =IF(COUNT(AC54:AF54)=4,SUM(AC54:AF54),"")
B55: 47 | C55: Receita liquida GTF - gestao e terceirizacao de frotas (DRE l.68) | D55: =IF(SUMPRODUCT((Inputs!$B$4:$B$200=$B55)*ISNUMBER(INDEX(Inputs!$D$4:$AG$200,0,MATCH(D$2,Inputs!$D$2:$AG$2,0))))=0,"",SUMIFS(INDEX(Inputs!$D$4:$AG$200,0,MATCH(D$2,Inputs!$D$2:$AG$2,0)),Inputs!$B$4:$B$200,$B55)/1000) -> 154.023 | E55: =IF(SUMPRODUCT((Inputs!$B$4:$B$200=$B55)*ISNUMBER(INDEX(Inputs!$D$4:$AG$200,0,MATCH(E$2,Inputs!$D$2:$AG$2,0))))=0,"",SUMIFS(INDEX(Inputs!$D$4:$AG$200,0,MATCH(E$2,Inputs!$D$2:$AG$2,0)),Inputs!$B$4:$B$200,$B55)/1000) -> 183.574 | F55: =IF(SUMPRODUCT((Inputs!$B$4:$B$200=$B55)*ISNUMBER(INDEX(Inputs!$D$4:$AG$200,0,MATCH(F$2,Inputs!$D$2:$AG$2,0))))=0,"",SUMIFS(INDEX(Inputs!$D$4:$AG$200,0,MATCH(F$2,Inputs!$D$2:$AG$2,0)),Inputs!$B$4:$B$200,$B55)/1000) -> 272.657 | G55: =IF(SUMPRODUCT((Inputs!$B$4:$B$200=$B55)*ISNUMBER(INDEX(Inputs!$D$4:$AG$200,0,MATCH(G$2,Inputs!$D$2:$AG$2,0))))=0,"",SUMIFS(INDEX(Inputs!$D$4:$AG$200,0,MATCH(G$2,Inputs!$D$2:$AG$2,0)),Inputs!$B$4:$B$200,$B55)/1000) -> 357.38 | H55: =IF(COUNT(D55:G55)=4,SUM(D55:G55),"") -> 967.634 | I55: =IF(SUMPRODUCT((Inputs!$B$4:$B$200=$B55)*ISNUMBER(INDEX(Inputs!$D$4:$AG$200,0,MATCH(I$2,Inputs!$D$2:$AG$2,0))))=0,"",SUMIFS(INDEX(Inputs!$D$4:$AG$200,0,MATCH(I$2,Inputs!$D$2:$AG$2,0)),Inputs!$B$4:$B$200,$B55)/1000) -> 379.203 | J55: =IF(SUMPRODUCT((Inputs!$B$4:$B$200=$B55)*ISNUMBER(INDEX(Inputs!$D$4:$AG$200,0,MATCH(J$2,Inputs!$D$2:$AG$2,0))))=0,"",SUMIFS(INDEX(Inputs!$D$4:$AG$200,0,MATCH(J$2,Inputs!$D$2:$AG$2,0)),Inputs!$B$4:$B$200,$B55)/1000) -> 417.174 | K55: =IF(SUMPRODUCT((Inputs!$B$4:$B$200=$B55)*ISNUMBER(INDEX(Inputs!$D$4:$AG$200,0,MATCH(K$2,Inputs!$D$2:$AG$2,0))))=0,"",SUMIFS(INDEX(Inputs!$D$4:$AG$200,0,MATCH(K$2,Inputs!$D$2:$AG$2,0)),Inputs!$B$4:$B$200,$B55)/1000) -> 451.078 | L55: =IF(SUMPRODUCT((Inputs!$B$4:$B$200=$B55)*ISNUMBER(INDEX(Inputs!$D$4:$AG$200,0,MATCH(L$2,Inputs!$D$2:$AG$2,0))))=0,"",SUMIFS(INDEX(Inputs!$D$4:$AG$200,0,MATCH(L$2,Inputs!$D$2:$AG$2,0)),Inputs!$B$4:$B$200,$B55)/1000) -> 495.524 | M55: =IF(COUNT(I55:L55)=4,SUM(I55:L55),"") -> 1742.979 | N55: =IF(SUMPRODUCT((Inputs!$B$4:$B$200=$B55)*ISNUMBER(INDEX(Inputs!$D$4:$AG$200,0,MATCH(N$2,Inputs!$D$2:$AG$2,0))))=0,"",SUMIFS(INDEX(Inputs!$D$4:$AG$200,0,MATCH(N$2,Inputs!$D$2:$AG$2,0)),Inputs!$B$4:$B$200,$B55)/1000) -> 538.708 | O55: =IF(SUMPRODUCT((Inputs!$B$4:$B$200=$B55)*ISNUMBER(INDEX(Inputs!$D$4:$AG$200,0,MATCH(O$2,Inputs!$D$2:$AG$2,0))))=0,"",SUMIFS(INDEX(Inputs!$D$4:$AG$200,0,MATCH(O$2,Inputs!$D$2:$AG$2,0)),Inputs!$B$4:$B$200,$B55)/1000) -> 558.149 | P55: =IF(SUMPRODUCT((Inputs!$B$4:$B$200=$B55)*ISNUMBER(INDEX(Inputs!$D$4:$AG$200,0,MATCH(P$2,Inputs!$D$2:$AG$2,0))))=0,"",SUMIFS(INDEX(Inputs!$D$4:$AG$200,0,MATCH(P$2,Inputs!$D$2:$AG$2,0)),Inputs!$B$4:$B$200,$B55)/1000) -> 581.123 | Q55: =IF(SUMPRODUCT((Inputs!$B$4:$B$200=$B55)*ISNUMBER(INDEX(Inputs!$D$4:$AG$200,0,MATCH(Q$2,Inputs!$D$2:$AG$2,0))))=0,"",SUMIFS(INDEX(Inputs!$D$4:$AG$200,0,MATCH(Q$2,Inputs!$D$2:$AG$2,0)),Inputs!$B$4:$B$200,$B55)/1000) -> 635.236 | R55: =IF(COUNT(N55:Q55)=4,SUM(N55:Q55),"") -> 2313.216 | S55: =IF(SUMPRODUCT((Inputs!$B$4:$B$200=$B55)*ISNUMBER(INDEX(Inputs!$D$4:$AG$200,0,MATCH(S$2,Inputs!$D$2:$AG$2,0))))=0,"",SUMIFS(INDEX(Inputs!$D$4:$AG$200,0,MATCH(S$2,Inputs!$D$2:$AG$2,0)),Inputs!$B$4:$B$200,$B55)/1000) -> 720.39 | T55: =IF(SUMPRODUCT((Inputs!$B$4:$B$200=$B55)*ISNUMBER(INDEX(Inputs!$D$4:$AG$200,0,MATCH(T$2,Inputs!$D$2:$AG$2,0))))=0,"",SUMIFS(INDEX(Inputs!$D$4:$AG$200,0,MATCH(T$2,Inputs!$D$2:$AG$2,0)),Inputs!$B$4:$B$200,$B55)/1000) -> 816.006 | U55: =IF(SUMPRODUCT((Inputs!$B$4:$B$200=$B55)*ISNUMBER(INDEX(Inputs!$D$4:$AG$200,0,MATCH(U$2,Inputs!$D$2:$AG$2,0))))=0,"",SUMIFS(INDEX(Inputs!$D$4:$AG$200,0,MATCH(U$2,Inputs!$D$2:$AG$2,0)),Inputs!$B$4:$B$200,$B55)/1000) -> 889.427 | V55: =IF(SUMPRODUCT((Inputs!$B$4:$B$200=$B55)*ISNUMBER(INDEX(Inputs!$D$4:$AG$200,0,MATCH(V$2,Inputs!$D$2:$AG$2,0))))=0,"",SUMIFS(INDEX(Inputs!$D$4:$AG$200,0,MATCH(V$2,Inputs!$D$2:$AG$2,0)),Inputs!$B$4:$B$200,$B55)/1000) -> 943.352 | W55: =IF(COUNT(S55:V55)=4,SUM(S55:V55),"") -> 3369.175 | X55: =IF(SUMPRODUCT((Inputs!$B$4:$B$200=$B55)*ISNUMBER(INDEX(Inputs!$D$4:$AG$200,0,MATCH(X$2,Inputs!$D$2:$AG$2,0))))=0,"",SUMIFS(INDEX(Inputs!$D$4:$AG$200,0,MATCH(X$2,Inputs!$D$2:$AG$2,0)),Inputs!$B$4:$B$200,$B55)/1000) -> 993.181 | Y55: =IF(SUMPRODUCT((Inputs!$B$4:$B$200=$B55)*ISNUMBER(INDEX(Inputs!$D$4:$AG$200,0,MATCH(Y$2,Inputs!$D$2:$AG$2,0))))=0,"",SUMIFS(INDEX(Inputs!$D$4:$AG$200,0,MATCH(Y$2,Inputs!$D$2:$AG$2,0)),Inputs!$B$4:$B$200,$B55)/1000) -> 995.876 | Z55: =IF(SUMPRODUCT((Inputs!$B$4:$B$200=$B55)*ISNUMBER(INDEX(Inputs!$D$4:$AG$200,0,MATCH(Z$2,Inputs!$D$2:$AG$2,0))))=0,"",SUMIFS(INDEX(Inputs!$D$4:$AG$200,0,MATCH(Z$2,Inputs!$D$2:$AG$2,0)),Inputs!$B$4:$B$200,$B55)/1000) -> 1033.426 | AA55: =IF(SUMPRODUCT((Inputs!$B$4:$B$200=$B55)*ISNUMBER(INDEX(Inputs!$D$4:$AG$200,0,MATCH(AA$2,Inputs!$D$2:$AG$2,0))))=0,"",SUMIFS(INDEX(Inputs!$D$4:$AG$200,0,MATCH(AA$2,Inputs!$D$2:$AG$2,0)),Inputs!$B$4:$B$200,$B55)/1000) -> 1083.6065 | AB55: =IF(COUNT(X55:AA55)=4,SUM(X55:AA55),"") -> 4106.0895 | AC55: =IF(SUMPRODUCT((Inputs!$B$4:$B$200=$B55)*ISNUMBER(INDEX(Inputs!$D$4:$AG$200,0,MATCH(AC$2,Inputs!$D$2:$AG$2,0))))=0,"",SUMIFS(INDEX(Inputs!$D$4:$AG$200,0,MATCH(AC$2,Inputs!$D$2:$AG$2,0)),Inputs!$B$4:$B$200,$B55)/1000) -> 1101.6086 | AD55: =IF(SUMPRODUCT((Inputs!$B$4:$B$200=$B55)*ISNUMBER(INDEX(Inputs!$D$4:$AG$200,0,MATCH(AD$2,Inputs!$D$2:$AG$2,0))))=0,"",SUMIFS(INDEX(Inputs!$D$4:$AG$200,0,MATCH(AD$2,Inputs!$D$2:$AG$2,0)),Inputs!$B$4:$B$200,$B55)/1000) -> 1149.769 | AE55: =IF(SUMPRODUCT((Inputs!$B$4:$B$200=$B55)*ISNUMBER(INDEX(Inputs!$D$4:$AG$200,0,MATCH(AE$2,Inputs!$D$2:$AG$2,0))))=0,"",SUMIFS(INDEX(Inputs!$D$4:$AG$200,0,MATCH(AE$2,Inputs!$D$2:$AG$2,0)),Inputs!$B$4:$B$200,$B55)/1000) | AF55: =IF(SUMPRODUCT((Inputs!$B$4:$B$200=$B55)*ISNUMBER(INDEX(Inputs!$D$4:$AG$200,0,MATCH(AF$2,Inputs!$D$2:$AG$2,0))))=0,"",SUMIFS(INDEX(Inputs!$D$4:$AG$200,0,MATCH(AF$2,Inputs!$D$2:$AG$2,0)),Inputs!$B$4:$B$200,$B55)/1000) | AG55: =IF(COUNT(AC55:AF55)=4,SUM(AC55:AF55),"")
B56: 48 | C56: Receita liquida Seminovos (DRE l.87) | D56: =IF(SUMPRODUCT((Inputs!$B$4:$B$200=$B56)*ISNUMBER(INDEX(Inputs!$D$4:$AG$200,0,MATCH(D$2,Inputs!$D$2:$AG$2,0))))=0,"",SUMIFS(INDEX(Inputs!$D$4:$AG$200,0,MATCH(D$2,Inputs!$D$2:$AG$2,0)),Inputs!$B$4:$B$200,$B56)/1000) -> 274.54 | E56: =IF(SUMPRODUCT((Inputs!$B$4:$B$200=$B56)*ISNUMBER(INDEX(Inputs!$D$4:$AG$200,0,MATCH(E$2,Inputs!$D$2:$AG$2,0))))=0,"",SUMIFS(INDEX(Inputs!$D$4:$AG$200,0,MATCH(E$2,Inputs!$D$2:$AG$2,0)),Inputs!$B$4:$B$200,$B56)/1000) -> 673.48 | F56: =IF(SUMPRODUCT((Inputs!$B$4:$B$200=$B56)*ISNUMBER(INDEX(Inputs!$D$4:$AG$200,0,MATCH(F$2,Inputs!$D$2:$AG$2,0))))=0,"",SUMIFS(INDEX(Inputs!$D$4:$AG$200,0,MATCH(F$2,Inputs!$D$2:$AG$2,0)),Inputs!$B$4:$B$200,$B56)/1000) -> 844.62 | G56: =IF(SUMPRODUCT((Inputs!$B$4:$B$200=$B56)*ISNUMBER(INDEX(Inputs!$D$4:$AG$200,0,MATCH(G$2,Inputs!$D$2:$AG$2,0))))=0,"",SUMIFS(INDEX(Inputs!$D$4:$AG$200,0,MATCH(G$2,Inputs!$D$2:$AG$2,0)),Inputs!$B$4:$B$200,$B56)/1000) -> 809.115 | H56: =IF(COUNT(D56:G56)=4,SUM(D56:G56),"") -> 2601.755 | I56: =IF(SUMPRODUCT((Inputs!$B$4:$B$200=$B56)*ISNUMBER(INDEX(Inputs!$D$4:$AG$200,0,MATCH(I$2,Inputs!$D$2:$AG$2,0))))=0,"",SUMIFS(INDEX(Inputs!$D$4:$AG$200,0,MATCH(I$2,Inputs!$D$2:$AG$2,0)),Inputs!$B$4:$B$200,$B56)/1000) -> 973.762 | J56: =IF(SUMPRODUCT((Inputs!$B$4:$B$200=$B56)*ISNUMBER(INDEX(Inputs!$D$4:$AG$200,0,MATCH(J$2,Inputs!$D$2:$AG$2,0))))=0,"",SUMIFS(INDEX(Inputs!$D$4:$AG$200,0,MATCH(J$2,Inputs!$D$2:$AG$2,0)),Inputs!$B$4:$B$200,$B56)/1000) -> 1228.635 | K56: =IF(SUMPRODUCT((Inputs!$B$4:$B$200=$B56)*ISNUMBER(INDEX(Inputs!$D$4:$AG$200,0,MATCH(K$2,Inputs!$D$2:$AG$2,0))))=0,"",SUMIFS(INDEX(Inputs!$D$4:$AG$200,0,MATCH(K$2,Inputs!$D$2:$AG$2,0)),Inputs!$B$4:$B$200,$B56)/1000) -> 1410.428 | L56: =IF(SUMPRODUCT((Inputs!$B$4:$B$200=$B56)*ISNUMBER(INDEX(Inputs!$D$4:$AG$200,0,MATCH(L$2,Inputs!$D$2:$AG$2,0))))=0,"",SUMIFS(INDEX(Inputs!$D$4:$AG$200,0,MATCH(L$2,Inputs!$D$2:$AG$2,0)),Inputs!$B$4:$B$200,$B56)/1000) -> 1404.407 | M56: =IF(COUNT(I56:L56)=4,SUM(I56:L56),"") -> 5017.232 | N56: =IF(SUMPRODUCT((Inputs!$B$4:$B$200=$B56)*ISNUMBER(INDEX(Inputs!$D$4:$AG$200,0,MATCH(N$2,Inputs!$D$2:$AG$2,0))))=0,"",SUMIFS(INDEX(Inputs!$D$4:$AG$200,0,MATCH(N$2,Inputs!$D$2:$AG$2,0)),Inputs!$B$4:$B$200,$B56)/1000) -> 1463.465 | O56: =IF(SUMPRODUCT((Inputs!$B$4:$B$200=$B56)*ISNUMBER(INDEX(Inputs!$D$4:$AG$200,0,MATCH(O$2,Inputs!$D$2:$AG$2,0))))=0,"",SUMIFS(INDEX(Inputs!$D$4:$AG$200,0,MATCH(O$2,Inputs!$D$2:$AG$2,0)),Inputs!$B$4:$B$200,$B56)/1000) -> 1245.363 | P56: =IF(SUMPRODUCT((Inputs!$B$4:$B$200=$B56)*ISNUMBER(INDEX(Inputs!$D$4:$AG$200,0,MATCH(P$2,Inputs!$D$2:$AG$2,0))))=0,"",SUMIFS(INDEX(Inputs!$D$4:$AG$200,0,MATCH(P$2,Inputs!$D$2:$AG$2,0)),Inputs!$B$4:$B$200,$B56)/1000) -> 1368.902 | Q56: =IF(SUMPRODUCT((Inputs!$B$4:$B$200=$B56)*ISNUMBER(INDEX(Inputs!$D$4:$AG$200,0,MATCH(Q$2,Inputs!$D$2:$AG$2,0))))=0,"",SUMIFS(INDEX(Inputs!$D$4:$AG$200,0,MATCH(Q$2,Inputs!$D$2:$AG$2,0)),Inputs!$B$4:$B$200,$B56)/1000) -> 1153.824 | R56: =IF(COUNT(N56:Q56)=4,SUM(N56:Q56),"") -> 5231.554 | S56: =IF(SUMPRODUCT((Inputs!$B$4:$B$200=$B56)*ISNUMBER(INDEX(Inputs!$D$4:$AG$200,0,MATCH(S$2,Inputs!$D$2:$AG$2,0))))=0,"",SUMIFS(INDEX(Inputs!$D$4:$AG$200,0,MATCH(S$2,Inputs!$D$2:$AG$2,0)),Inputs!$B$4:$B$200,$B56)/1000) -> 1526.448 | T56: =IF(SUMPRODUCT((Inputs!$B$4:$B$200=$B56)*ISNUMBER(INDEX(Inputs!$D$4:$AG$200,0,MATCH(T$2,Inputs!$D$2:$AG$2,0))))=0,"",SUMIFS(INDEX(Inputs!$D$4:$AG$200,0,MATCH(T$2,Inputs!$D$2:$AG$2,0)),Inputs!$B$4:$B$200,$B56)/1000) -> 1827.516 | U56: =IF(SUMPRODUCT((Inputs!$B$4:$B$200=$B56)*ISNUMBER(INDEX(Inputs!$D$4:$AG$200,0,MATCH(U$2,Inputs!$D$2:$AG$2,0))))=0,"",SUMIFS(INDEX(Inputs!$D$4:$AG$200,0,MATCH(U$2,Inputs!$D$2:$AG$2,0)),Inputs!$B$4:$B$200,$B56)/1000) -> 2031.166 | V56: =IF(SUMPRODUCT((Inputs!$B$4:$B$200=$B56)*ISNUMBER(INDEX(Inputs!$D$4:$AG$200,0,MATCH(V$2,Inputs!$D$2:$AG$2,0))))=0,"",SUMIFS(INDEX(Inputs!$D$4:$AG$200,0,MATCH(V$2,Inputs!$D$2:$AG$2,0)),Inputs!$B$4:$B$200,$B56)/1000) -> 1457.1 | W56: =IF(COUNT(S56:V56)=4,SUM(S56:V56),"") -> 6842.23 | X56: =IF(SUMPRODUCT((Inputs!$B$4:$B$200=$B56)*ISNUMBER(INDEX(Inputs!$D$4:$AG$200,0,MATCH(X$2,Inputs!$D$2:$AG$2,0))))=0,"",SUMIFS(INDEX(Inputs!$D$4:$AG$200,0,MATCH(X$2,Inputs!$D$2:$AG$2,0)),Inputs!$B$4:$B$200,$B56)/1000) -> 1689.326 | Y56: =IF(SUMPRODUCT((Inputs!$B$4:$B$200=$B56)*ISNUMBER(INDEX(Inputs!$D$4:$AG$200,0,MATCH(Y$2,Inputs!$D$2:$AG$2,0))))=0,"",SUMIFS(INDEX(Inputs!$D$4:$AG$200,0,MATCH(Y$2,Inputs!$D$2:$AG$2,0)),Inputs!$B$4:$B$200,$B56)/1000) -> 1786.374 | Z56: =IF(SUMPRODUCT((Inputs!$B$4:$B$200=$B56)*ISNUMBER(INDEX(Inputs!$D$4:$AG$200,0,MATCH(Z$2,Inputs!$D$2:$AG$2,0))))=0,"",SUMIFS(INDEX(Inputs!$D$4:$AG$200,0,MATCH(Z$2,Inputs!$D$2:$AG$2,0)),Inputs!$B$4:$B$200,$B56)/1000) -> 1755.031 | AA56: =IF(SUMPRODUCT((Inputs!$B$4:$B$200=$B56)*ISNUMBER(INDEX(Inputs!$D$4:$AG$200,0,MATCH(AA$2,Inputs!$D$2:$AG$2,0))))=0,"",SUMIFS(INDEX(Inputs!$D$4:$AG$200,0,MATCH(AA$2,Inputs!$D$2:$AG$2,0)),Inputs!$B$4:$B$200,$B56)/1000) -> 1562.5811 | AB56: =IF(COUNT(X56:AA56)=4,SUM(X56:AA56),"") -> 6793.3121 | AC56: =IF(SUMPRODUCT((Inputs!$B$4:$B$200=$B56)*ISNUMBER(INDEX(Inputs!$D$4:$AG$200,0,MATCH(AC$2,Inputs!$D$2:$AG$2,0))))=0,"",SUMIFS(INDEX(Inputs!$D$4:$AG$200,0,MATCH(AC$2,Inputs!$D$2:$AG$2,0)),Inputs!$B$4:$B$200,$B56)/1000) -> 1575.0285 | AD56: =IF(SUMPRODUCT((Inputs!$B$4:$B$200=$B56)*ISNUMBER(INDEX(Inputs!$D$4:$AG$200,0,MATCH(AD$2,Inputs!$D$2:$AG$2,0))))=0,"",SUMIFS(INDEX(Inputs!$D$4:$AG$200,0,MATCH(AD$2,Inputs!$D$2:$AG$2,0)),Inputs!$B$4:$B$200,$B56)/1000) -> 1470.4956 | AE56: =IF(SUMPRODUCT((Inputs!$B$4:$B$200=$B56)*ISNUMBER(INDEX(Inputs!$D$4:$AG$200,0,MATCH(AE$2,Inputs!$D$2:$AG$2,0))))=0,"",SUMIFS(INDEX(Inputs!$D$4:$AG$200,0,MATCH(AE$2,Inputs!$D$2:$AG$2,0)),Inputs!$B$4:$B$200,$B56)/1000) | AF56: =IF(SUMPRODUCT((Inputs!$B$4:$B$200=$B56)*ISNUMBER(INDEX(Inputs!$D$4:$AG$200,0,MATCH(AF$2,Inputs!$D$2:$AG$2,0))))=0,"",SUMIFS(INDEX(Inputs!$D$4:$AG$200,0,MATCH(AF$2,Inputs!$D$2:$AG$2,0)),Inputs!$B$4:$B$200,$B56)/1000) | AG56: =IF(COUNT(AC56:AF56)=4,SUM(AC56:AF56),"")
B57: 49 | C57: EBITDA RAC consolidado (DRE l.61) | D57: =IF(SUMPRODUCT((Inputs!$B$4:$B$200=$B57)*ISNUMBER(INDEX(Inputs!$D$4:$AG$200,0,MATCH(D$2,Inputs!$D$2:$AG$2,0))))=0,"",SUMIFS(INDEX(Inputs!$D$4:$AG$200,0,MATCH(D$2,Inputs!$D$2:$AG$2,0)),Inputs!$B$4:$B$200,$B57)/1000) -> 168.74 | E57: =IF(SUMPRODUCT((Inputs!$B$4:$B$200=$B57)*ISNUMBER(INDEX(Inputs!$D$4:$AG$200,0,MATCH(E$2,Inputs!$D$2:$AG$2,0))))=0,"",SUMIFS(INDEX(Inputs!$D$4:$AG$200,0,MATCH(E$2,Inputs!$D$2:$AG$2,0)),Inputs!$B$4:$B$200,$B57)/1000) -> 140.676 | F57: =IF(SUMPRODUCT((Inputs!$B$4:$B$200=$B57)*ISNUMBER(INDEX(Inputs!$D$4:$AG$200,0,MATCH(F$2,Inputs!$D$2:$AG$2,0))))=0,"",SUMIFS(INDEX(Inputs!$D$4:$AG$200,0,MATCH(F$2,Inputs!$D$2:$AG$2,0)),Inputs!$B$4:$B$200,$B57)/1000) -> 233.091 | G57: =IF(SUMPRODUCT((Inputs!$B$4:$B$200=$B57)*ISNUMBER(INDEX(Inputs!$D$4:$AG$200,0,MATCH(G$2,Inputs!$D$2:$AG$2,0))))=0,"",SUMIFS(INDEX(Inputs!$D$4:$AG$200,0,MATCH(G$2,Inputs!$D$2:$AG$2,0)),Inputs!$B$4:$B$200,$B57)/1000) -> 333.123 | H57: =IF(COUNT(D57:G57)=4,SUM(D57:G57),"") -> 875.63 | I57: =IF(SUMPRODUCT((Inputs!$B$4:$B$200=$B57)*ISNUMBER(INDEX(Inputs!$D$4:$AG$200,0,MATCH(I$2,Inputs!$D$2:$AG$2,0))))=0,"",SUMIFS(INDEX(Inputs!$D$4:$AG$200,0,MATCH(I$2,Inputs!$D$2:$AG$2,0)),Inputs!$B$4:$B$200,$B57)/1000) -> 373.325 | J57: =IF(SUMPRODUCT((Inputs!$B$4:$B$200=$B57)*ISNUMBER(INDEX(Inputs!$D$4:$AG$200,0,MATCH(J$2,Inputs!$D$2:$AG$2,0))))=0,"",SUMIFS(INDEX(Inputs!$D$4:$AG$200,0,MATCH(J$2,Inputs!$D$2:$AG$2,0)),Inputs!$B$4:$B$200,$B57)/1000) -> 384.781 | K57: =IF(SUMPRODUCT((Inputs!$B$4:$B$200=$B57)*ISNUMBER(INDEX(Inputs!$D$4:$AG$200,0,MATCH(K$2,Inputs!$D$2:$AG$2,0))))=0,"",SUMIFS(INDEX(Inputs!$D$4:$AG$200,0,MATCH(K$2,Inputs!$D$2:$AG$2,0)),Inputs!$B$4:$B$200,$B57)/1000) -> 457.844 | L57: =IF(SUMPRODUCT((Inputs!$B$4:$B$200=$B57)*ISNUMBER(INDEX(Inputs!$D$4:$AG$200,0,MATCH(L$2,Inputs!$D$2:$AG$2,0))))=0,"",SUMIFS(INDEX(Inputs!$D$4:$AG$200,0,MATCH(L$2,Inputs!$D$2:$AG$2,0)),Inputs!$B$4:$B$200,$B57)/1000) -> 416.559 | M57: =IF(COUNT(I57:L57)=4,SUM(I57:L57),"") -> 1632.509 | N57: =IF(SUMPRODUCT((Inputs!$B$4:$B$200=$B57)*ISNUMBER(INDEX(Inputs!$D$4:$AG$200,0,MATCH(N$2,Inputs!$D$2:$AG$2,0))))=0,"",SUMIFS(INDEX(Inputs!$D$4:$AG$200,0,MATCH(N$2,Inputs!$D$2:$AG$2,0)),Inputs!$B$4:$B$200,$B57)/1000) -> 427.387 | O57: =IF(SUMPRODUCT((Inputs!$B$4:$B$200=$B57)*ISNUMBER(INDEX(Inputs!$D$4:$AG$200,0,MATCH(O$2,Inputs!$D$2:$AG$2,0))))=0,"",SUMIFS(INDEX(Inputs!$D$4:$AG$200,0,MATCH(O$2,Inputs!$D$2:$AG$2,0)),Inputs!$B$4:$B$200,$B57)/1000) -> 381.802 | P57: =IF(SUMPRODUCT((Inputs!$B$4:$B$200=$B57)*ISNUMBER(INDEX(Inputs!$D$4:$AG$200,0,MATCH(P$2,Inputs!$D$2:$AG$2,0))))=0,"",SUMIFS(INDEX(Inputs!$D$4:$AG$200,0,MATCH(P$2,Inputs!$D$2:$AG$2,0)),Inputs!$B$4:$B$200,$B57)/1000) -> 395.515 | Q57: =IF(SUMPRODUCT((Inputs!$B$4:$B$200=$B57)*ISNUMBER(INDEX(Inputs!$D$4:$AG$200,0,MATCH(Q$2,Inputs!$D$2:$AG$2,0))))=0,"",SUMIFS(INDEX(Inputs!$D$4:$AG$200,0,MATCH(Q$2,Inputs!$D$2:$AG$2,0)),Inputs!$B$4:$B$200,$B57)/1000) -> 367.098 | R57: =IF(COUNT(N57:Q57)=4,SUM(N57:Q57),"") -> 1571.802 | S57: =IF(SUMPRODUCT((Inputs!$B$4:$B$200=$B57)*ISNUMBER(INDEX(Inputs!$D$4:$AG$200,0,MATCH(S$2,Inputs!$D$2:$AG$2,0))))=0,"",SUMIFS(INDEX(Inputs!$D$4:$AG$200,0,MATCH(S$2,Inputs!$D$2:$AG$2,0)),Inputs!$B$4:$B$200,$B57)/1000) -> 485.485 | T57: =IF(SUMPRODUCT((Inputs!$B$4:$B$200=$B57)*ISNUMBER(INDEX(Inputs!$D$4:$AG$200,0,MATCH(T$2,Inputs!$D$2:$AG$2,0))))=0,"",SUMIFS(INDEX(Inputs!$D$4:$AG$200,0,MATCH(T$2,Inputs!$D$2:$AG$2,0)),Inputs!$B$4:$B$200,$B57)/1000) -> 504.709 | U57: =IF(SUMPRODUCT((Inputs!$B$4:$B$200=$B57)*ISNUMBER(INDEX(Inputs!$D$4:$AG$200,0,MATCH(U$2,Inputs!$D$2:$AG$2,0))))=0,"",SUMIFS(INDEX(Inputs!$D$4:$AG$200,0,MATCH(U$2,Inputs!$D$2:$AG$2,0)),Inputs!$B$4:$B$200,$B57)/1000) -> 550.01 | V57: =IF(SUMPRODUCT((Inputs!$B$4:$B$200=$B57)*ISNUMBER(INDEX(Inputs!$D$4:$AG$200,0,MATCH(V$2,Inputs!$D$2:$AG$2,0))))=0,"",SUMIFS(INDEX(Inputs!$D$4:$AG$200,0,MATCH(V$2,Inputs!$D$2:$AG$2,0)),Inputs!$B$4:$B$200,$B57)/1000) -> 543.336 | W57: =IF(COUNT(S57:V57)=4,SUM(S57:V57),"") -> 2083.54 | X57: =IF(SUMPRODUCT((Inputs!$B$4:$B$200=$B57)*ISNUMBER(INDEX(Inputs!$D$4:$AG$200,0,MATCH(X$2,Inputs!$D$2:$AG$2,0))))=0,"",SUMIFS(INDEX(Inputs!$D$4:$AG$200,0,MATCH(X$2,Inputs!$D$2:$AG$2,0)),Inputs!$B$4:$B$200,$B57)/1000) -> 563.843 | Y57: =IF(SUMPRODUCT((Inputs!$B$4:$B$200=$B57)*ISNUMBER(INDEX(Inputs!$D$4:$AG$200,0,MATCH(Y$2,Inputs!$D$2:$AG$2,0))))=0,"",SUMIFS(INDEX(Inputs!$D$4:$AG$200,0,MATCH(Y$2,Inputs!$D$2:$AG$2,0)),Inputs!$B$4:$B$200,$B57)/1000) -> 602.06 | Z57: =IF(SUMPRODUCT((Inputs!$B$4:$B$200=$B57)*ISNUMBER(INDEX(Inputs!$D$4:$AG$200,0,MATCH(Z$2,Inputs!$D$2:$AG$2,0))))=0,"",SUMIFS(INDEX(Inputs!$D$4:$AG$200,0,MATCH(Z$2,Inputs!$D$2:$AG$2,0)),Inputs!$B$4:$B$200,$B57)/1000) -> 669.054 | AA57: =IF(SUMPRODUCT((Inputs!$B$4:$B$200=$B57)*ISNUMBER(INDEX(Inputs!$D$4:$AG$200,0,MATCH(AA$2,Inputs!$D$2:$AG$2,0))))=0,"",SUMIFS(INDEX(Inputs!$D$4:$AG$200,0,MATCH(AA$2,Inputs!$D$2:$AG$2,0)),Inputs!$B$4:$B$200,$B57)/1000) -> 663.04715 | AB57: =IF(COUNT(X57:AA57)=4,SUM(X57:AA57),"") -> 2498.0042 | AC57: =IF(SUMPRODUCT((Inputs!$B$4:$B$200=$B57)*ISNUMBER(INDEX(Inputs!$D$4:$AG$200,0,MATCH(AC$2,Inputs!$D$2:$AG$2,0))))=0,"",SUMIFS(INDEX(Inputs!$D$4:$AG$200,0,MATCH(AC$2,Inputs!$D$2:$AG$2,0)),Inputs!$B$4:$B$200,$B57)/1000) -> 717.75755 | AD57: =IF(SUMPRODUCT((Inputs!$B$4:$B$200=$B57)*ISNUMBER(INDEX(Inputs!$D$4:$AG$200,0,MATCH(AD$2,Inputs!$D$2:$AG$2,0))))=0,"",SUMIFS(INDEX(Inputs!$D$4:$AG$200,0,MATCH(AD$2,Inputs!$D$2:$AG$2,0)),Inputs!$B$4:$B$200,$B57)/1000) -> 775.95137 | AE57: =IF(SUMPRODUCT((Inputs!$B$4:$B$200=$B57)*ISNUMBER(INDEX(Inputs!$D$4:$AG$200,0,MATCH(AE$2,Inputs!$D$2:$AG$2,0))))=0,"",SUMIFS(INDEX(Inputs!$D$4:$AG$200,0,MATCH(AE$2,Inputs!$D$2:$AG$2,0)),Inputs!$B$4:$B$200,$B57)/1000) | AF57: =IF(SUMPRODUCT((Inputs!$B$4:$B$200=$B57)*ISNUMBER(INDEX(Inputs!$D$4:$AG$200,0,MATCH(AF$2,Inputs!$D$2:$AG$2,0))))=0,"",SUMIFS(INDEX(Inputs!$D$4:$AG$200,0,MATCH(AF$2,Inputs!$D$2:$AG$2,0)),Inputs!$B$4:$B$200,$B57)/1000) | AG57: =IF(COUNT(AC57:AF57)=4,SUM(AC57:AF57),"")
B58: 50 | C58: EBITDA GTF (DRE l.80) | D58: =IF(SUMPRODUCT((Inputs!$B$4:$B$200=$B58)*ISNUMBER(INDEX(Inputs!$D$4:$AG$200,0,MATCH(D$2,Inputs!$D$2:$AG$2,0))))=0,"",SUMIFS(INDEX(Inputs!$D$4:$AG$200,0,MATCH(D$2,Inputs!$D$2:$AG$2,0)),Inputs!$B$4:$B$200,$B58)/1000) -> 99.481 | E58: =IF(SUMPRODUCT((Inputs!$B$4:$B$200=$B58)*ISNUMBER(INDEX(Inputs!$D$4:$AG$200,0,MATCH(E$2,Inputs!$D$2:$AG$2,0))))=0,"",SUMIFS(INDEX(Inputs!$D$4:$AG$200,0,MATCH(E$2,Inputs!$D$2:$AG$2,0)),Inputs!$B$4:$B$200,$B58)/1000) -> 127.681 | F58: =IF(SUMPRODUCT((Inputs!$B$4:$B$200=$B58)*ISNUMBER(INDEX(Inputs!$D$4:$AG$200,0,MATCH(F$2,Inputs!$D$2:$AG$2,0))))=0,"",SUMIFS(INDEX(Inputs!$D$4:$AG$200,0,MATCH(F$2,Inputs!$D$2:$AG$2,0)),Inputs!$B$4:$B$200,$B58)/1000) -> 193.117 | G58: =IF(SUMPRODUCT((Inputs!$B$4:$B$200=$B58)*ISNUMBER(INDEX(Inputs!$D$4:$AG$200,0,MATCH(G$2,Inputs!$D$2:$AG$2,0))))=0,"",SUMIFS(INDEX(Inputs!$D$4:$AG$200,0,MATCH(G$2,Inputs!$D$2:$AG$2,0)),Inputs!$B$4:$B$200,$B58)/1000) -> 261.929 | H58: =IF(COUNT(D58:G58)=4,SUM(D58:G58),"") -> 682.208 | I58: =IF(SUMPRODUCT((Inputs!$B$4:$B$200=$B58)*ISNUMBER(INDEX(Inputs!$D$4:$AG$200,0,MATCH(I$2,Inputs!$D$2:$AG$2,0))))=0,"",SUMIFS(INDEX(Inputs!$D$4:$AG$200,0,MATCH(I$2,Inputs!$D$2:$AG$2,0)),Inputs!$B$4:$B$200,$B58)/1000) -> 285.299 | J58: =IF(SUMPRODUCT((Inputs!$B$4:$B$200=$B58)*ISNUMBER(INDEX(Inputs!$D$4:$AG$200,0,MATCH(J$2,Inputs!$D$2:$AG$2,0))))=0,"",SUMIFS(INDEX(Inputs!$D$4:$AG$200,0,MATCH(J$2,Inputs!$D$2:$AG$2,0)),Inputs!$B$4:$B$200,$B58)/1000) -> 315.241 | K58: =IF(SUMPRODUCT((Inputs!$B$4:$B$200=$B58)*ISNUMBER(INDEX(Inputs!$D$4:$AG$200,0,MATCH(K$2,Inputs!$D$2:$AG$2,0))))=0,"",SUMIFS(INDEX(Inputs!$D$4:$AG$200,0,MATCH(K$2,Inputs!$D$2:$AG$2,0)),Inputs!$B$4:$B$200,$B58)/1000) -> 331.303 | L58: =IF(SUMPRODUCT((Inputs!$B$4:$B$200=$B58)*ISNUMBER(INDEX(Inputs!$D$4:$AG$200,0,MATCH(L$2,Inputs!$D$2:$AG$2,0))))=0,"",SUMIFS(INDEX(Inputs!$D$4:$AG$200,0,MATCH(L$2,Inputs!$D$2:$AG$2,0)),Inputs!$B$4:$B$200,$B58)/1000) -> 336.091 | M58: =IF(COUNT(I58:L58)=4,SUM(I58:L58),"") -> 1267.934 | N58: =IF(SUMPRODUCT((Inputs!$B$4:$B$200=$B58)*ISNUMBER(INDEX(Inputs!$D$4:$AG$200,0,MATCH(N$2,Inputs!$D$2:$AG$2,0))))=0,"",SUMIFS(INDEX(Inputs!$D$4:$AG$200,0,MATCH(N$2,Inputs!$D$2:$AG$2,0)),Inputs!$B$4:$B$200,$B58)/1000) -> 361.568 | O58: =IF(SUMPRODUCT((Inputs!$B$4:$B$200=$B58)*ISNUMBER(INDEX(Inputs!$D$4:$AG$200,0,MATCH(O$2,Inputs!$D$2:$AG$2,0))))=0,"",SUMIFS(INDEX(Inputs!$D$4:$AG$200,0,MATCH(O$2,Inputs!$D$2:$AG$2,0)),Inputs!$B$4:$B$200,$B58)/1000) -> 411.732 | P58: =IF(SUMPRODUCT((Inputs!$B$4:$B$200=$B58)*ISNUMBER(INDEX(Inputs!$D$4:$AG$200,0,MATCH(P$2,Inputs!$D$2:$AG$2,0))))=0,"",SUMIFS(INDEX(Inputs!$D$4:$AG$200,0,MATCH(P$2,Inputs!$D$2:$AG$2,0)),Inputs!$B$4:$B$200,$B58)/1000) -> 430.96 | Q58: =IF(SUMPRODUCT((Inputs!$B$4:$B$200=$B58)*ISNUMBER(INDEX(Inputs!$D$4:$AG$200,0,MATCH(Q$2,Inputs!$D$2:$AG$2,0))))=0,"",SUMIFS(INDEX(Inputs!$D$4:$AG$200,0,MATCH(Q$2,Inputs!$D$2:$AG$2,0)),Inputs!$B$4:$B$200,$B58)/1000) -> 462.355 | R58: =IF(COUNT(N58:Q58)=4,SUM(N58:Q58),"") -> 1666.615 | S58: =IF(SUMPRODUCT((Inputs!$B$4:$B$200=$B58)*ISNUMBER(INDEX(Inputs!$D$4:$AG$200,0,MATCH(S$2,Inputs!$D$2:$AG$2,0))))=0,"",SUMIFS(INDEX(Inputs!$D$4:$AG$200,0,MATCH(S$2,Inputs!$D$2:$AG$2,0)),Inputs!$B$4:$B$200,$B58)/1000) -> 535.294 | T58: =IF(SUMPRODUCT((Inputs!$B$4:$B$200=$B58)*ISNUMBER(INDEX(Inputs!$D$4:$AG$200,0,MATCH(T$2,Inputs!$D$2:$AG$2,0))))=0,"",SUMIFS(INDEX(Inputs!$D$4:$AG$200,0,MATCH(T$2,Inputs!$D$2:$AG$2,0)),Inputs!$B$4:$B$200,$B58)/1000) -> 619.952 | U58: =IF(SUMPRODUCT((Inputs!$B$4:$B$200=$B58)*ISNUMBER(INDEX(Inputs!$D$4:$AG$200,0,MATCH(U$2,Inputs!$D$2:$AG$2,0))))=0,"",SUMIFS(INDEX(Inputs!$D$4:$AG$200,0,MATCH(U$2,Inputs!$D$2:$AG$2,0)),Inputs!$B$4:$B$200,$B58)/1000) -> 675.759 | V58: =IF(SUMPRODUCT((Inputs!$B$4:$B$200=$B58)*ISNUMBER(INDEX(Inputs!$D$4:$AG$200,0,MATCH(V$2,Inputs!$D$2:$AG$2,0))))=0,"",SUMIFS(INDEX(Inputs!$D$4:$AG$200,0,MATCH(V$2,Inputs!$D$2:$AG$2,0)),Inputs!$B$4:$B$200,$B58)/1000) -> 683.937 | W58: =IF(COUNT(S58:V58)=4,SUM(S58:V58),"") -> 2514.942 | X58: =IF(SUMPRODUCT((Inputs!$B$4:$B$200=$B58)*ISNUMBER(INDEX(Inputs!$D$4:$AG$200,0,MATCH(X$2,Inputs!$D$2:$AG$2,0))))=0,"",SUMIFS(INDEX(Inputs!$D$4:$AG$200,0,MATCH(X$2,Inputs!$D$2:$AG$2,0)),Inputs!$B$4:$B$200,$B58)/1000) -> 756.317 | Y58: =IF(SUMPRODUCT((Inputs!$B$4:$B$200=$B58)*ISNUMBER(INDEX(Inputs!$D$4:$AG$200,0,MATCH(Y$2,Inputs!$D$2:$AG$2,0))))=0,"",SUMIFS(INDEX(Inputs!$D$4:$AG$200,0,MATCH(Y$2,Inputs!$D$2:$AG$2,0)),Inputs!$B$4:$B$200,$B58)/1000) -> 757.422 | Z58: =IF(SUMPRODUCT((Inputs!$B$4:$B$200=$B58)*ISNUMBER(INDEX(Inputs!$D$4:$AG$200,0,MATCH(Z$2,Inputs!$D$2:$AG$2,0))))=0,"",SUMIFS(INDEX(Inputs!$D$4:$AG$200,0,MATCH(Z$2,Inputs!$D$2:$AG$2,0)),Inputs!$B$4:$B$200,$B58)/1000) -> 791.002 | AA58: =IF(SUMPRODUCT((Inputs!$B$4:$B$200=$B58)*ISNUMBER(INDEX(Inputs!$D$4:$AG$200,0,MATCH(AA$2,Inputs!$D$2:$AG$2,0))))=0,"",SUMIFS(INDEX(Inputs!$D$4:$AG$200,0,MATCH(AA$2,Inputs!$D$2:$AG$2,0)),Inputs!$B$4:$B$200,$B58)/1000) -> 811.76908 | AB58: =IF(COUNT(X58:AA58)=4,SUM(X58:AA58),"") -> 3116.5101 | AC58: =IF(SUMPRODUCT((Inputs!$B$4:$B$200=$B58)*ISNUMBER(INDEX(Inputs!$D$4:$AG$200,0,MATCH(AC$2,Inputs!$D$2:$AG$2,0))))=0,"",SUMIFS(INDEX(Inputs!$D$4:$AG$200,0,MATCH(AC$2,Inputs!$D$2:$AG$2,0)),Inputs!$B$4:$B$200,$B58)/1000) -> 833.52963 | AD58: =IF(SUMPRODUCT((Inputs!$B$4:$B$200=$B58)*ISNUMBER(INDEX(Inputs!$D$4:$AG$200,0,MATCH(AD$2,Inputs!$D$2:$AG$2,0))))=0,"",SUMIFS(INDEX(Inputs!$D$4:$AG$200,0,MATCH(AD$2,Inputs!$D$2:$AG$2,0)),Inputs!$B$4:$B$200,$B58)/1000) -> 895.09674 | AE58: =IF(SUMPRODUCT((Inputs!$B$4:$B$200=$B58)*ISNUMBER(INDEX(Inputs!$D$4:$AG$200,0,MATCH(AE$2,Inputs!$D$2:$AG$2,0))))=0,"",SUMIFS(INDEX(Inputs!$D$4:$AG$200,0,MATCH(AE$2,Inputs!$D$2:$AG$2,0)),Inputs!$B$4:$B$200,$B58)/1000) | AF58: =IF(SUMPRODUCT((Inputs!$B$4:$B$200=$B58)*ISNUMBER(INDEX(Inputs!$D$4:$AG$200,0,MATCH(AF$2,Inputs!$D$2:$AG$2,0))))=0,"",SUMIFS(INDEX(Inputs!$D$4:$AG$200,0,MATCH(AF$2,Inputs!$D$2:$AG$2,0)),Inputs!$B$4:$B$200,$B58)/1000) | AG58: =IF(COUNT(AC58:AF58)=4,SUM(AC58:AF58),"")
B59: 51 | C59: EBITDA Seminovos (DRE l.96) | D59: =IF(SUMPRODUCT((Inputs!$B$4:$B$200=$B59)*ISNUMBER(INDEX(Inputs!$D$4:$AG$200,0,MATCH(D$2,Inputs!$D$2:$AG$2,0))))=0,"",SUMIFS(INDEX(Inputs!$D$4:$AG$200,0,MATCH(D$2,Inputs!$D$2:$AG$2,0)),Inputs!$B$4:$B$200,$B59)/1000) -> 36.282 | E59: =IF(SUMPRODUCT((Inputs!$B$4:$B$200=$B59)*ISNUMBER(INDEX(Inputs!$D$4:$AG$200,0,MATCH(E$2,Inputs!$D$2:$AG$2,0))))=0,"",SUMIFS(INDEX(Inputs!$D$4:$AG$200,0,MATCH(E$2,Inputs!$D$2:$AG$2,0)),Inputs!$B$4:$B$200,$B59)/1000) -> 120.108 | F59: =IF(SUMPRODUCT((Inputs!$B$4:$B$200=$B59)*ISNUMBER(INDEX(Inputs!$D$4:$AG$200,0,MATCH(F$2,Inputs!$D$2:$AG$2,0))))=0,"",SUMIFS(INDEX(Inputs!$D$4:$AG$200,0,MATCH(F$2,Inputs!$D$2:$AG$2,0)),Inputs!$B$4:$B$200,$B59)/1000) -> 187.2 | G59: =IF(SUMPRODUCT((Inputs!$B$4:$B$200=$B59)*ISNUMBER(INDEX(Inputs!$D$4:$AG$200,0,MATCH(G$2,Inputs!$D$2:$AG$2,0))))=0,"",SUMIFS(INDEX(Inputs!$D$4:$AG$200,0,MATCH(G$2,Inputs!$D$2:$AG$2,0)),Inputs!$B$4:$B$200,$B59)/1000) -> 181.561 | H59: =IF(COUNT(D59:G59)=4,SUM(D59:G59),"") -> 525.151 | I59: =IF(SUMPRODUCT((Inputs!$B$4:$B$200=$B59)*ISNUMBER(INDEX(Inputs!$D$4:$AG$200,0,MATCH(I$2,Inputs!$D$2:$AG$2,0))))=0,"",SUMIFS(INDEX(Inputs!$D$4:$AG$200,0,MATCH(I$2,Inputs!$D$2:$AG$2,0)),Inputs!$B$4:$B$200,$B59)/1000) -> 204.472 | J59: =IF(SUMPRODUCT((Inputs!$B$4:$B$200=$B59)*ISNUMBER(INDEX(Inputs!$D$4:$AG$200,0,MATCH(J$2,Inputs!$D$2:$AG$2,0))))=0,"",SUMIFS(INDEX(Inputs!$D$4:$AG$200,0,MATCH(J$2,Inputs!$D$2:$AG$2,0)),Inputs!$B$4:$B$200,$B59)/1000) -> 205.234 | K59: =IF(SUMPRODUCT((Inputs!$B$4:$B$200=$B59)*ISNUMBER(INDEX(Inputs!$D$4:$AG$200,0,MATCH(K$2,Inputs!$D$2:$AG$2,0))))=0,"",SUMIFS(INDEX(Inputs!$D$4:$AG$200,0,MATCH(K$2,Inputs!$D$2:$AG$2,0)),Inputs!$B$4:$B$200,$B59)/1000) -> 136.19 | L59: =IF(SUMPRODUCT((Inputs!$B$4:$B$200=$B59)*ISNUMBER(INDEX(Inputs!$D$4:$AG$200,0,MATCH(L$2,Inputs!$D$2:$AG$2,0))))=0,"",SUMIFS(INDEX(Inputs!$D$4:$AG$200,0,MATCH(L$2,Inputs!$D$2:$AG$2,0)),Inputs!$B$4:$B$200,$B59)/1000) -> 105.593 | M59: =IF(COUNT(I59:L59)=4,SUM(I59:L59),"") -> 651.489 | N59: =IF(SUMPRODUCT((Inputs!$B$4:$B$200=$B59)*ISNUMBER(INDEX(Inputs!$D$4:$AG$200,0,MATCH(N$2,Inputs!$D$2:$AG$2,0))))=0,"",SUMIFS(INDEX(Inputs!$D$4:$AG$200,0,MATCH(N$2,Inputs!$D$2:$AG$2,0)),Inputs!$B$4:$B$200,$B59)/1000) -> 86.387 | O59: =IF(SUMPRODUCT((Inputs!$B$4:$B$200=$B59)*ISNUMBER(INDEX(Inputs!$D$4:$AG$200,0,MATCH(O$2,Inputs!$D$2:$AG$2,0))))=0,"",SUMIFS(INDEX(Inputs!$D$4:$AG$200,0,MATCH(O$2,Inputs!$D$2:$AG$2,0)),Inputs!$B$4:$B$200,$B59)/1000) -> 96.458 | P59: =IF(SUMPRODUCT((Inputs!$B$4:$B$200=$B59)*ISNUMBER(INDEX(Inputs!$D$4:$AG$200,0,MATCH(P$2,Inputs!$D$2:$AG$2,0))))=0,"",SUMIFS(INDEX(Inputs!$D$4:$AG$200,0,MATCH(P$2,Inputs!$D$2:$AG$2,0)),Inputs!$B$4:$B$200,$B59)/1000) -> 41.451 | Q59: =IF(SUMPRODUCT((Inputs!$B$4:$B$200=$B59)*ISNUMBER(INDEX(Inputs!$D$4:$AG$200,0,MATCH(Q$2,Inputs!$D$2:$AG$2,0))))=0,"",SUMIFS(INDEX(Inputs!$D$4:$AG$200,0,MATCH(Q$2,Inputs!$D$2:$AG$2,0)),Inputs!$B$4:$B$200,$B59)/1000) -> 36.566 | R59: =IF(COUNT(N59:Q59)=4,SUM(N59:Q59),"") -> 260.862 | S59: =IF(SUMPRODUCT((Inputs!$B$4:$B$200=$B59)*ISNUMBER(INDEX(Inputs!$D$4:$AG$200,0,MATCH(S$2,Inputs!$D$2:$AG$2,0))))=0,"",SUMIFS(INDEX(Inputs!$D$4:$AG$200,0,MATCH(S$2,Inputs!$D$2:$AG$2,0)),Inputs!$B$4:$B$200,$B59)/1000) -> 38.64 | T59: =IF(SUMPRODUCT((Inputs!$B$4:$B$200=$B59)*ISNUMBER(INDEX(Inputs!$D$4:$AG$200,0,MATCH(T$2,Inputs!$D$2:$AG$2,0))))=0,"",SUMIFS(INDEX(Inputs!$D$4:$AG$200,0,MATCH(T$2,Inputs!$D$2:$AG$2,0)),Inputs!$B$4:$B$200,$B59)/1000) -> 24.699 | U59: =IF(SUMPRODUCT((Inputs!$B$4:$B$200=$B59)*ISNUMBER(INDEX(Inputs!$D$4:$AG$200,0,MATCH(U$2,Inputs!$D$2:$AG$2,0))))=0,"",SUMIFS(INDEX(Inputs!$D$4:$AG$200,0,MATCH(U$2,Inputs!$D$2:$AG$2,0)),Inputs!$B$4:$B$200,$B59)/1000) -> 21.709 | V59: =IF(SUMPRODUCT((Inputs!$B$4:$B$200=$B59)*ISNUMBER(INDEX(Inputs!$D$4:$AG$200,0,MATCH(V$2,Inputs!$D$2:$AG$2,0))))=0,"",SUMIFS(INDEX(Inputs!$D$4:$AG$200,0,MATCH(V$2,Inputs!$D$2:$AG$2,0)),Inputs!$B$4:$B$200,$B59)/1000) -> 17.006 | W59: =IF(COUNT(S59:V59)=4,SUM(S59:V59),"") -> 102.054 | X59: =IF(SUMPRODUCT((Inputs!$B$4:$B$200=$B59)*ISNUMBER(INDEX(Inputs!$D$4:$AG$200,0,MATCH(X$2,Inputs!$D$2:$AG$2,0))))=0,"",SUMIFS(INDEX(Inputs!$D$4:$AG$200,0,MATCH(X$2,Inputs!$D$2:$AG$2,0)),Inputs!$B$4:$B$200,$B59)/1000) -> 18.169 | Y59: =IF(SUMPRODUCT((Inputs!$B$4:$B$200=$B59)*ISNUMBER(INDEX(Inputs!$D$4:$AG$200,0,MATCH(Y$2,Inputs!$D$2:$AG$2,0))))=0,"",SUMIFS(INDEX(Inputs!$D$4:$AG$200,0,MATCH(Y$2,Inputs!$D$2:$AG$2,0)),Inputs!$B$4:$B$200,$B59)/1000) -> 19.641 | Z59: =IF(SUMPRODUCT((Inputs!$B$4:$B$200=$B59)*ISNUMBER(INDEX(Inputs!$D$4:$AG$200,0,MATCH(Z$2,Inputs!$D$2:$AG$2,0))))=0,"",SUMIFS(INDEX(Inputs!$D$4:$AG$200,0,MATCH(Z$2,Inputs!$D$2:$AG$2,0)),Inputs!$B$4:$B$200,$B59)/1000) -> 18.599 | AA59: =IF(SUMPRODUCT((Inputs!$B$4:$B$200=$B59)*ISNUMBER(INDEX(Inputs!$D$4:$AG$200,0,MATCH(AA$2,Inputs!$D$2:$AG$2,0))))=0,"",SUMIFS(INDEX(Inputs!$D$4:$AG$200,0,MATCH(AA$2,Inputs!$D$2:$AG$2,0)),Inputs!$B$4:$B$200,$B59)/1000) -> 15.23403 | AB59: =IF(COUNT(X59:AA59)=4,SUM(X59:AA59),"") -> 71.64303 | AC59: =IF(SUMPRODUCT((Inputs!$B$4:$B$200=$B59)*ISNUMBER(INDEX(Inputs!$D$4:$AG$200,0,MATCH(AC$2,Inputs!$D$2:$AG$2,0))))=0,"",SUMIFS(INDEX(Inputs!$D$4:$AG$200,0,MATCH(AC$2,Inputs!$D$2:$AG$2,0)),Inputs!$B$4:$B$200,$B59)/1000) -> 17.377381 | AD59: =IF(SUMPRODUCT((Inputs!$B$4:$B$200=$B59)*ISNUMBER(INDEX(Inputs!$D$4:$AG$200,0,MATCH(AD$2,Inputs!$D$2:$AG$2,0))))=0,"",SUMIFS(INDEX(Inputs!$D$4:$AG$200,0,MATCH(AD$2,Inputs!$D$2:$AG$2,0)),Inputs!$B$4:$B$200,$B59)/1000) -> 15.695477 | AE59: =IF(SUMPRODUCT((Inputs!$B$4:$B$200=$B59)*ISNUMBER(INDEX(Inputs!$D$4:$AG$200,0,MATCH(AE$2,Inputs!$D$2:$AG$2,0))))=0,"",SUMIFS(INDEX(Inputs!$D$4:$AG$200,0,MATCH(AE$2,Inputs!$D$2:$AG$2,0)),Inputs!$B$4:$B$200,$B59)/1000) | AF59: =IF(SUMPRODUCT((Inputs!$B$4:$B$200=$B59)*ISNUMBER(INDEX(Inputs!$D$4:$AG$200,0,MATCH(AF$2,Inputs!$D$2:$AG$2,0))))=0,"",SUMIFS(INDEX(Inputs!$D$4:$AG$200,0,MATCH(AF$2,Inputs!$D$2:$AG$2,0)),Inputs!$B$4:$B$200,$B59)/1000) | AG59: =IF(COUNT(AC59:AF59)=4,SUM(AC59:AF59),"")
B60: 52 | C60: RAC - frota no final do periodo (carros; Op Data l.7) | D60: =IF(SUMPRODUCT((Inputs!$B$4:$B$200=$B60)*ISNUMBER(INDEX(Inputs!$D$4:$AG$200,0,MATCH(D$2,Inputs!$D$2:$AG$2,0))))=0,"",SUMIFS(INDEX(Inputs!$D$4:$AG$200,0,MATCH(D$2,Inputs!$D$2:$AG$2,0)),Inputs!$B$4:$B$200,$B60)/1000) -> 70213 | E60: =IF(SUMPRODUCT((Inputs!$B$4:$B$200=$B60)*ISNUMBER(INDEX(Inputs!$D$4:$AG$200,0,MATCH(E$2,Inputs!$D$2:$AG$2,0))))=0,"",SUMIFS(INDEX(Inputs!$D$4:$AG$200,0,MATCH(E$2,Inputs!$D$2:$AG$2,0)),Inputs!$B$4:$B$200,$B60)/1000) -> 78453 | F60: =IF(SUMPRODUCT((Inputs!$B$4:$B$200=$B60)*ISNUMBER(INDEX(Inputs!$D$4:$AG$200,0,MATCH(F$2,Inputs!$D$2:$AG$2,0))))=0,"",SUMIFS(INDEX(Inputs!$D$4:$AG$200,0,MATCH(F$2,Inputs!$D$2:$AG$2,0)),Inputs!$B$4:$B$200,$B60)/1000) -> 79888 | G60: =IF(SUMPRODUCT((Inputs!$B$4:$B$200=$B60)*ISNUMBER(INDEX(Inputs!$D$4:$AG$200,0,MATCH(G$2,Inputs!$D$2:$AG$2,0))))=0,"",SUMIFS(INDEX(Inputs!$D$4:$AG$200,0,MATCH(G$2,Inputs!$D$2:$AG$2,0)),Inputs!$B$4:$B$200,$B60)/1000) -> 90671 | H60: =IF(COUNT(D60:G60)=4,SUM(D60:G60),"") -> 319225 | I60: =IF(SUMPRODUCT((Inputs!$B$4:$B$200=$B60)*ISNUMBER(INDEX(Inputs!$D$4:$AG$200,0,MATCH(I$2,Inputs!$D$2:$AG$2,0))))=0,"",SUMIFS(INDEX(Inputs!$D$4:$AG$200,0,MATCH(I$2,Inputs!$D$2:$AG$2,0)),Inputs!$B$4:$B$200,$B60)/1000) -> 96572 | J60: =IF(SUMPRODUCT((Inputs!$B$4:$B$200=$B60)*ISNUMBER(INDEX(Inputs!$D$4:$AG$200,0,MATCH(J$2,Inputs!$D$2:$AG$2,0))))=0,"",SUMIFS(INDEX(Inputs!$D$4:$AG$200,0,MATCH(J$2,Inputs!$D$2:$AG$2,0)),Inputs!$B$4:$B$200,$B60)/1000) -> 100403 | K60: =IF(SUMPRODUCT((Inputs!$B$4:$B$200=$B60)*ISNUMBER(INDEX(Inputs!$D$4:$AG$200,0,MATCH(K$2,Inputs!$D$2:$AG$2,0))))=0,"",SUMIFS(INDEX(Inputs!$D$4:$AG$200,0,MATCH(K$2,Inputs!$D$2:$AG$2,0)),Inputs!$B$4:$B$200,$B60)/1000) -> 104987 | L60: =IF(SUMPRODUCT((Inputs!$B$4:$B$200=$B60)*ISNUMBER(INDEX(Inputs!$D$4:$AG$200,0,MATCH(L$2,Inputs!$D$2:$AG$2,0))))=0,"",SUMIFS(INDEX(Inputs!$D$4:$AG$200,0,MATCH(L$2,Inputs!$D$2:$AG$2,0)),Inputs!$B$4:$B$200,$B60)/1000) -> 111632 | M60: =IF(COUNT(I60:L60)=4,SUM(I60:L60),"") -> 413594 | N60: =IF(SUMPRODUCT((Inputs!$B$4:$B$200=$B60)*ISNUMBER(INDEX(Inputs!$D$4:$AG$200,0,MATCH(N$2,Inputs!$D$2:$AG$2,0))))=0,"",SUMIFS(INDEX(Inputs!$D$4:$AG$200,0,MATCH(N$2,Inputs!$D$2:$AG$2,0)),Inputs!$B$4:$B$200,$B60)/1000) -> 98373 | O60: =IF(SUMPRODUCT((Inputs!$B$4:$B$200=$B60)*ISNUMBER(INDEX(Inputs!$D$4:$AG$200,0,MATCH(O$2,Inputs!$D$2:$AG$2,0))))=0,"",SUMIFS(INDEX(Inputs!$D$4:$AG$200,0,MATCH(O$2,Inputs!$D$2:$AG$2,0)),Inputs!$B$4:$B$200,$B60)/1000) -> 91632 | P60: =IF(SUMPRODUCT((Inputs!$B$4:$B$200=$B60)*ISNUMBER(INDEX(Inputs!$D$4:$AG$200,0,MATCH(P$2,Inputs!$D$2:$AG$2,0))))=0,"",SUMIFS(INDEX(Inputs!$D$4:$AG$200,0,MATCH(P$2,Inputs!$D$2:$AG$2,0)),Inputs!$B$4:$B$200,$B60)/1000) -> 94273 | Q60: =IF(SUMPRODUCT((Inputs!$B$4:$B$200=$B60)*ISNUMBER(INDEX(Inputs!$D$4:$AG$200,0,MATCH(Q$2,Inputs!$D$2:$AG$2,0))))=0,"",SUMIFS(INDEX(Inputs!$D$4:$AG$200,0,MATCH(Q$2,Inputs!$D$2:$AG$2,0)),Inputs!$B$4:$B$200,$B60)/1000) -> 113150 | R60: =IF(COUNT(N60:Q60)=4,SUM(N60:Q60),"") -> 397428 | S60: =IF(SUMPRODUCT((Inputs!$B$4:$B$200=$B60)*ISNUMBER(INDEX(Inputs!$D$4:$AG$200,0,MATCH(S$2,Inputs!$D$2:$AG$2,0))))=0,"",SUMIFS(INDEX(Inputs!$D$4:$AG$200,0,MATCH(S$2,Inputs!$D$2:$AG$2,0)),Inputs!$B$4:$B$200,$B60)/1000) -> 110091 | T60: =IF(SUMPRODUCT((Inputs!$B$4:$B$200=$B60)*ISNUMBER(INDEX(Inputs!$D$4:$AG$200,0,MATCH(T$2,Inputs!$D$2:$AG$2,0))))=0,"",SUMIFS(INDEX(Inputs!$D$4:$AG$200,0,MATCH(T$2,Inputs!$D$2:$AG$2,0)),Inputs!$B$4:$B$200,$B60)/1000) -> 108716 | U60: =IF(SUMPRODUCT((Inputs!$B$4:$B$200=$B60)*ISNUMBER(INDEX(Inputs!$D$4:$AG$200,0,MATCH(U$2,Inputs!$D$2:$AG$2,0))))=0,"",SUMIFS(INDEX(Inputs!$D$4:$AG$200,0,MATCH(U$2,Inputs!$D$2:$AG$2,0)),Inputs!$B$4:$B$200,$B60)/1000) -> 110182 | V60: =IF(SUMPRODUCT((Inputs!$B$4:$B$200=$B60)*ISNUMBER(INDEX(Inputs!$D$4:$AG$200,0,MATCH(V$2,Inputs!$D$2:$AG$2,0))))=0,"",SUMIFS(INDEX(Inputs!$D$4:$AG$200,0,MATCH(V$2,Inputs!$D$2:$AG$2,0)),Inputs!$B$4:$B$200,$B60)/1000) -> 121942 | W60: =IF(COUNT(S60:V60)=4,SUM(S60:V60),"") -> 450931 | X60: =IF(SUMPRODUCT((Inputs!$B$4:$B$200=$B60)*ISNUMBER(INDEX(Inputs!$D$4:$AG$200,0,MATCH(X$2,Inputs!$D$2:$AG$2,0))))=0,"",SUMIFS(INDEX(Inputs!$D$4:$AG$200,0,MATCH(X$2,Inputs!$D$2:$AG$2,0)),Inputs!$B$4:$B$200,$B60)/1000) -> 113257 | Y60: =IF(SUMPRODUCT((Inputs!$B$4:$B$200=$B60)*ISNUMBER(INDEX(Inputs!$D$4:$AG$200,0,MATCH(Y$2,Inputs!$D$2:$AG$2,0))))=0,"",SUMIFS(INDEX(Inputs!$D$4:$AG$200,0,MATCH(Y$2,Inputs!$D$2:$AG$2,0)),Inputs!$B$4:$B$200,$B60)/1000) -> 120133 | Z60: =IF(SUMPRODUCT((Inputs!$B$4:$B$200=$B60)*ISNUMBER(INDEX(Inputs!$D$4:$AG$200,0,MATCH(Z$2,Inputs!$D$2:$AG$2,0))))=0,"",SUMIFS(INDEX(Inputs!$D$4:$AG$200,0,MATCH(Z$2,Inputs!$D$2:$AG$2,0)),Inputs!$B$4:$B$200,$B60)/1000) -> 115498 | AA60: =IF(SUMPRODUCT((Inputs!$B$4:$B$200=$B60)*ISNUMBER(INDEX(Inputs!$D$4:$AG$200,0,MATCH(AA$2,Inputs!$D$2:$AG$2,0))))=0,"",SUMIFS(INDEX(Inputs!$D$4:$AG$200,0,MATCH(AA$2,Inputs!$D$2:$AG$2,0)),Inputs!$B$4:$B$200,$B60)/1000) -> 130634 | AB60: =IF(COUNT(X60:AA60)=4,SUM(X60:AA60),"") -> 479522 | AC60: =IF(SUMPRODUCT((Inputs!$B$4:$B$200=$B60)*ISNUMBER(INDEX(Inputs!$D$4:$AG$200,0,MATCH(AC$2,Inputs!$D$2:$AG$2,0))))=0,"",SUMIFS(INDEX(Inputs!$D$4:$AG$200,0,MATCH(AC$2,Inputs!$D$2:$AG$2,0)),Inputs!$B$4:$B$200,$B60)/1000) -> 125307 | AD60: =IF(SUMPRODUCT((Inputs!$B$4:$B$200=$B60)*ISNUMBER(INDEX(Inputs!$D$4:$AG$200,0,MATCH(AD$2,Inputs!$D$2:$AG$2,0))))=0,"",SUMIFS(INDEX(Inputs!$D$4:$AG$200,0,MATCH(AD$2,Inputs!$D$2:$AG$2,0)),Inputs!$B$4:$B$200,$B60)/1000) -> 139785 | AE60: =IF(SUMPRODUCT((Inputs!$B$4:$B$200=$B60)*ISNUMBER(INDEX(Inputs!$D$4:$AG$200,0,MATCH(AE$2,Inputs!$D$2:$AG$2,0))))=0,"",SUMIFS(INDEX(Inputs!$D$4:$AG$200,0,MATCH(AE$2,Inputs!$D$2:$AG$2,0)),Inputs!$B$4:$B$200,$B60)/1000) | AF60: =IF(SUMPRODUCT((Inputs!$B$4:$B$200=$B60)*ISNUMBER(INDEX(Inputs!$D$4:$AG$200,0,MATCH(AF$2,Inputs!$D$2:$AG$2,0))))=0,"",SUMIFS(INDEX(Inputs!$D$4:$AG$200,0,MATCH(AF$2,Inputs!$D$2:$AG$2,0)),Inputs!$B$4:$B$200,$B60)/1000) | AG60: =IF(COUNT(AC60:AF60)=4,SUM(AC60:AF60),"")
B61: 53 | C61: RAC - frota media operacional Brasil (Op Data l.11) | D61: =IF(SUMPRODUCT((Inputs!$B$4:$B$200=$B61)*ISNUMBER(INDEX(Inputs!$D$4:$AG$200,0,MATCH(D$2,Inputs!$D$2:$AG$2,0))))=0,"",SUMIFS(INDEX(Inputs!$D$4:$AG$200,0,MATCH(D$2,Inputs!$D$2:$AG$2,0)),Inputs!$B$4:$B$200,$B61)/1000) -> 64795.778 | E61: =IF(SUMPRODUCT((Inputs!$B$4:$B$200=$B61)*ISNUMBER(INDEX(Inputs!$D$4:$AG$200,0,MATCH(E$2,Inputs!$D$2:$AG$2,0))))=0,"",SUMIFS(INDEX(Inputs!$D$4:$AG$200,0,MATCH(E$2,Inputs!$D$2:$AG$2,0)),Inputs!$B$4:$B$200,$B61)/1000) -> 63654.352 | F61: =IF(SUMPRODUCT((Inputs!$B$4:$B$200=$B61)*ISNUMBER(INDEX(Inputs!$D$4:$AG$200,0,MATCH(F$2,Inputs!$D$2:$AG$2,0))))=0,"",SUMIFS(INDEX(Inputs!$D$4:$AG$200,0,MATCH(F$2,Inputs!$D$2:$AG$2,0)),Inputs!$B$4:$B$200,$B61)/1000) -> 67380.652 | G61: =IF(SUMPRODUCT((Inputs!$B$4:$B$200=$B61)*ISNUMBER(INDEX(Inputs!$D$4:$AG$200,0,MATCH(G$2,Inputs!$D$2:$AG$2,0))))=0,"",SUMIFS(INDEX(Inputs!$D$4:$AG$200,0,MATCH(G$2,Inputs!$D$2:$AG$2,0)),Inputs!$B$4:$B$200,$B61)/1000) -> 70538.359 | H61: =IF(COUNT(D61:G61)=4,SUM(D61:G61),"") -> 266369.14 | I61: =IF(SUMPRODUCT((Inputs!$B$4:$B$200=$B61)*ISNUMBER(INDEX(Inputs!$D$4:$AG$200,0,MATCH(I$2,Inputs!$D$2:$AG$2,0))))=0,"",SUMIFS(INDEX(Inputs!$D$4:$AG$200,0,MATCH(I$2,Inputs!$D$2:$AG$2,0)),Inputs!$B$4:$B$200,$B61)/1000) -> 75286 | J61: =IF(SUMPRODUCT((Inputs!$B$4:$B$200=$B61)*ISNUMBER(INDEX(Inputs!$D$4:$AG$200,0,MATCH(J$2,Inputs!$D$2:$AG$2,0))))=0,"",SUMIFS(INDEX(Inputs!$D$4:$AG$200,0,MATCH(J$2,Inputs!$D$2:$AG$2,0)),Inputs!$B$4:$B$200,$B61)/1000) -> 80205 | K61: =IF(SUMPRODUCT((Inputs!$B$4:$B$200=$B61)*ISNUMBER(INDEX(Inputs!$D$4:$AG$200,0,MATCH(K$2,Inputs!$D$2:$AG$2,0))))=0,"",SUMIFS(INDEX(Inputs!$D$4:$AG$200,0,MATCH(K$2,Inputs!$D$2:$AG$2,0)),Inputs!$B$4:$B$200,$B61)/1000) -> 85151 | L61: =IF(SUMPRODUCT((Inputs!$B$4:$B$200=$B61)*ISNUMBER(INDEX(Inputs!$D$4:$AG$200,0,MATCH(L$2,Inputs!$D$2:$AG$2,0))))=0,"",SUMIFS(INDEX(Inputs!$D$4:$AG$200,0,MATCH(L$2,Inputs!$D$2:$AG$2,0)),Inputs!$B$4:$B$200,$B61)/1000) -> 90852 | M61: =IF(COUNT(I61:L61)=4,SUM(I61:L61),"") -> 331494 | N61: =IF(SUMPRODUCT((Inputs!$B$4:$B$200=$B61)*ISNUMBER(INDEX(Inputs!$D$4:$AG$200,0,MATCH(N$2,Inputs!$D$2:$AG$2,0))))=0,"",SUMIFS(INDEX(Inputs!$D$4:$AG$200,0,MATCH(N$2,Inputs!$D$2:$AG$2,0)),Inputs!$B$4:$B$200,$B61)/1000) -> 88866.199 | O61: =IF(SUMPRODUCT((Inputs!$B$4:$B$200=$B61)*ISNUMBER(INDEX(Inputs!$D$4:$AG$200,0,MATCH(O$2,Inputs!$D$2:$AG$2,0))))=0,"",SUMIFS(INDEX(Inputs!$D$4:$AG$200,0,MATCH(O$2,Inputs!$D$2:$AG$2,0)),Inputs!$B$4:$B$200,$B61)/1000) -> 82491 | P61: =IF(SUMPRODUCT((Inputs!$B$4:$B$200=$B61)*ISNUMBER(INDEX(Inputs!$D$4:$AG$200,0,MATCH(P$2,Inputs!$D$2:$AG$2,0))))=0,"",SUMIFS(INDEX(Inputs!$D$4:$AG$200,0,MATCH(P$2,Inputs!$D$2:$AG$2,0)),Inputs!$B$4:$B$200,$B61)/1000) -> 79085.543 | Q61: =IF(SUMPRODUCT((Inputs!$B$4:$B$200=$B61)*ISNUMBER(INDEX(Inputs!$D$4:$AG$200,0,MATCH(Q$2,Inputs!$D$2:$AG$2,0))))=0,"",SUMIFS(INDEX(Inputs!$D$4:$AG$200,0,MATCH(Q$2,Inputs!$D$2:$AG$2,0)),Inputs!$B$4:$B$200,$B61)/1000) -> 81070.652 | R61: =IF(COUNT(N61:Q61)=4,SUM(N61:Q61),"") -> 331513.39 | S61: =IF(SUMPRODUCT((Inputs!$B$4:$B$200=$B61)*ISNUMBER(INDEX(Inputs!$D$4:$AG$200,0,MATCH(S$2,Inputs!$D$2:$AG$2,0))))=0,"",SUMIFS(INDEX(Inputs!$D$4:$AG$200,0,MATCH(S$2,Inputs!$D$2:$AG$2,0)),Inputs!$B$4:$B$200,$B61)/1000) -> 89703.462 | T61: =IF(SUMPRODUCT((Inputs!$B$4:$B$200=$B61)*ISNUMBER(INDEX(Inputs!$D$4:$AG$200,0,MATCH(T$2,Inputs!$D$2:$AG$2,0))))=0,"",SUMIFS(INDEX(Inputs!$D$4:$AG$200,0,MATCH(T$2,Inputs!$D$2:$AG$2,0)),Inputs!$B$4:$B$200,$B61)/1000) -> 90071.198 | U61: =IF(SUMPRODUCT((Inputs!$B$4:$B$200=$B61)*ISNUMBER(INDEX(Inputs!$D$4:$AG$200,0,MATCH(U$2,Inputs!$D$2:$AG$2,0))))=0,"",SUMIFS(INDEX(Inputs!$D$4:$AG$200,0,MATCH(U$2,Inputs!$D$2:$AG$2,0)),Inputs!$B$4:$B$200,$B61)/1000) -> 87264.217 | V61: =IF(SUMPRODUCT((Inputs!$B$4:$B$200=$B61)*ISNUMBER(INDEX(Inputs!$D$4:$AG$200,0,MATCH(V$2,Inputs!$D$2:$AG$2,0))))=0,"",SUMIFS(INDEX(Inputs!$D$4:$AG$200,0,MATCH(V$2,Inputs!$D$2:$AG$2,0)),Inputs!$B$4:$B$200,$B61)/1000) -> 88526.512 | W61: =IF(COUNT(S61:V61)=4,SUM(S61:V61),"") -> 355565.39 | X61: =IF(SUMPRODUCT((Inputs!$B$4:$B$200=$B61)*ISNUMBER(INDEX(Inputs!$D$4:$AG$200,0,MATCH(X$2,Inputs!$D$2:$AG$2,0))))=0,"",SUMIFS(INDEX(Inputs!$D$4:$AG$200,0,MATCH(X$2,Inputs!$D$2:$AG$2,0)),Inputs!$B$4:$B$200,$B61)/1000) -> 95097.2 | Y61: =IF(SUMPRODUCT((Inputs!$B$4:$B$200=$B61)*ISNUMBER(INDEX(Inputs!$D$4:$AG$200,0,MATCH(Y$2,Inputs!$D$2:$AG$2,0))))=0,"",SUMIFS(INDEX(Inputs!$D$4:$AG$200,0,MATCH(Y$2,Inputs!$D$2:$AG$2,0)),Inputs!$B$4:$B$200,$B61)/1000) -> 91009.044 | Z61: =IF(SUMPRODUCT((Inputs!$B$4:$B$200=$B61)*ISNUMBER(INDEX(Inputs!$D$4:$AG$200,0,MATCH(Z$2,Inputs!$D$2:$AG$2,0))))=0,"",SUMIFS(INDEX(Inputs!$D$4:$AG$200,0,MATCH(Z$2,Inputs!$D$2:$AG$2,0)),Inputs!$B$4:$B$200,$B61)/1000) -> 92381.456 | AA61: =IF(SUMPRODUCT((Inputs!$B$4:$B$200=$B61)*ISNUMBER(INDEX(Inputs!$D$4:$AG$200,0,MATCH(AA$2,Inputs!$D$2:$AG$2,0))))=0,"",SUMIFS(INDEX(Inputs!$D$4:$AG$200,0,MATCH(AA$2,Inputs!$D$2:$AG$2,0)),Inputs!$B$4:$B$200,$B61)/1000) -> 96659.329 | AB61: =IF(COUNT(X61:AA61)=4,SUM(X61:AA61),"") -> 375147.03 | AC61: =IF(SUMPRODUCT((Inputs!$B$4:$B$200=$B61)*ISNUMBER(INDEX(Inputs!$D$4:$AG$200,0,MATCH(AC$2,Inputs!$D$2:$AG$2,0))))=0,"",SUMIFS(INDEX(Inputs!$D$4:$AG$200,0,MATCH(AC$2,Inputs!$D$2:$AG$2,0)),Inputs!$B$4:$B$200,$B61)/1000) -> 102753.81 | AD61: =IF(SUMPRODUCT((Inputs!$B$4:$B$200=$B61)*ISNUMBER(INDEX(Inputs!$D$4:$AG$200,0,MATCH(AD$2,Inputs!$D$2:$AG$2,0))))=0,"",SUMIFS(INDEX(Inputs!$D$4:$AG$200,0,MATCH(AD$2,Inputs!$D$2:$AG$2,0)),Inputs!$B$4:$B$200,$B61)/1000) -> 108816.42 | AE61: =IF(SUMPRODUCT((Inputs!$B$4:$B$200=$B61)*ISNUMBER(INDEX(Inputs!$D$4:$AG$200,0,MATCH(AE$2,Inputs!$D$2:$AG$2,0))))=0,"",SUMIFS(INDEX(Inputs!$D$4:$AG$200,0,MATCH(AE$2,Inputs!$D$2:$AG$2,0)),Inputs!$B$4:$B$200,$B61)/1000) | AF61: =IF(SUMPRODUCT((Inputs!$B$4:$B$200=$B61)*ISNUMBER(INDEX(Inputs!$D$4:$AG$200,0,MATCH(AF$2,Inputs!$D$2:$AG$2,0))))=0,"",SUMIFS(INDEX(Inputs!$D$4:$AG$200,0,MATCH(AF$2,Inputs!$D$2:$AG$2,0)),Inputs!$B$4:$B$200,$B61)/1000) | AG61: =IF(COUNT(AC61:AF61)=4,SUM(AC61:AF61),"")
B62: 54 | C62: RAC - frota media alugada (Op Data l.13) | D62: =IF(SUMPRODUCT((Inputs!$B$4:$B$200=$B62)*ISNUMBER(INDEX(Inputs!$D$4:$AG$200,0,MATCH(D$2,Inputs!$D$2:$AG$2,0))))=0,"",SUMIFS(INDEX(Inputs!$D$4:$AG$200,0,MATCH(D$2,Inputs!$D$2:$AG$2,0)),Inputs!$B$4:$B$200,$B62)/1000) -> 51370.093 | E62: =IF(SUMPRODUCT((Inputs!$B$4:$B$200=$B62)*ISNUMBER(INDEX(Inputs!$D$4:$AG$200,0,MATCH(E$2,Inputs!$D$2:$AG$2,0))))=0,"",SUMIFS(INDEX(Inputs!$D$4:$AG$200,0,MATCH(E$2,Inputs!$D$2:$AG$2,0)),Inputs!$B$4:$B$200,$B62)/1000) -> 50671.055 | F62: =IF(SUMPRODUCT((Inputs!$B$4:$B$200=$B62)*ISNUMBER(INDEX(Inputs!$D$4:$AG$200,0,MATCH(F$2,Inputs!$D$2:$AG$2,0))))=0,"",SUMIFS(INDEX(Inputs!$D$4:$AG$200,0,MATCH(F$2,Inputs!$D$2:$AG$2,0)),Inputs!$B$4:$B$200,$B62)/1000) -> 55849.469 | G62: =IF(SUMPRODUCT((Inputs!$B$4:$B$200=$B62)*ISNUMBER(INDEX(Inputs!$D$4:$AG$200,0,MATCH(G$2,Inputs!$D$2:$AG$2,0))))=0,"",SUMIFS(INDEX(Inputs!$D$4:$AG$200,0,MATCH(G$2,Inputs!$D$2:$AG$2,0)),Inputs!$B$4:$B$200,$B62)/1000) -> 57025.126 | H62: =IF(COUNT(D62:G62)=4,SUM(D62:G62),"") -> 214915.74 | I62: =IF(SUMPRODUCT((Inputs!$B$4:$B$200=$B62)*ISNUMBER(INDEX(Inputs!$D$4:$AG$200,0,MATCH(I$2,Inputs!$D$2:$AG$2,0))))=0,"",SUMIFS(INDEX(Inputs!$D$4:$AG$200,0,MATCH(I$2,Inputs!$D$2:$AG$2,0)),Inputs!$B$4:$B$200,$B62)/1000) -> 57280.098 | J62: =IF(SUMPRODUCT((Inputs!$B$4:$B$200=$B62)*ISNUMBER(INDEX(Inputs!$D$4:$AG$200,0,MATCH(J$2,Inputs!$D$2:$AG$2,0))))=0,"",SUMIFS(INDEX(Inputs!$D$4:$AG$200,0,MATCH(J$2,Inputs!$D$2:$AG$2,0)),Inputs!$B$4:$B$200,$B62)/1000) -> 63642.042 | K62: =IF(SUMPRODUCT((Inputs!$B$4:$B$200=$B62)*ISNUMBER(INDEX(Inputs!$D$4:$AG$200,0,MATCH(K$2,Inputs!$D$2:$AG$2,0))))=0,"",SUMIFS(INDEX(Inputs!$D$4:$AG$200,0,MATCH(K$2,Inputs!$D$2:$AG$2,0)),Inputs!$B$4:$B$200,$B62)/1000) -> 65726.756 | L62: =IF(SUMPRODUCT((Inputs!$B$4:$B$200=$B62)*ISNUMBER(INDEX(Inputs!$D$4:$AG$200,0,MATCH(L$2,Inputs!$D$2:$AG$2,0))))=0,"",SUMIFS(INDEX(Inputs!$D$4:$AG$200,0,MATCH(L$2,Inputs!$D$2:$AG$2,0)),Inputs!$B$4:$B$200,$B62)/1000) -> 69565.355 | M62: =IF(COUNT(I62:L62)=4,SUM(I62:L62),"") -> 256214.25 | N62: =IF(SUMPRODUCT((Inputs!$B$4:$B$200=$B62)*ISNUMBER(INDEX(Inputs!$D$4:$AG$200,0,MATCH(N$2,Inputs!$D$2:$AG$2,0))))=0,"",SUMIFS(INDEX(Inputs!$D$4:$AG$200,0,MATCH(N$2,Inputs!$D$2:$AG$2,0)),Inputs!$B$4:$B$200,$B62)/1000) -> 69616.243 | O62: =IF(SUMPRODUCT((Inputs!$B$4:$B$200=$B62)*ISNUMBER(INDEX(Inputs!$D$4:$AG$200,0,MATCH(O$2,Inputs!$D$2:$AG$2,0))))=0,"",SUMIFS(INDEX(Inputs!$D$4:$AG$200,0,MATCH(O$2,Inputs!$D$2:$AG$2,0)),Inputs!$B$4:$B$200,$B62)/1000) -> 64568 | P62: =IF(SUMPRODUCT((Inputs!$B$4:$B$200=$B62)*ISNUMBER(INDEX(Inputs!$D$4:$AG$200,0,MATCH(P$2,Inputs!$D$2:$AG$2,0))))=0,"",SUMIFS(INDEX(Inputs!$D$4:$AG$200,0,MATCH(P$2,Inputs!$D$2:$AG$2,0)),Inputs!$B$4:$B$200,$B62)/1000) -> 64181.696 | Q62: =IF(SUMPRODUCT((Inputs!$B$4:$B$200=$B62)*ISNUMBER(INDEX(Inputs!$D$4:$AG$200,0,MATCH(Q$2,Inputs!$D$2:$AG$2,0))))=0,"",SUMIFS(INDEX(Inputs!$D$4:$AG$200,0,MATCH(Q$2,Inputs!$D$2:$AG$2,0)),Inputs!$B$4:$B$200,$B62)/1000) -> 66467.207 | R62: =IF(COUNT(N62:Q62)=4,SUM(N62:Q62),"") -> 264833.15 | S62: =IF(SUMPRODUCT((Inputs!$B$4:$B$200=$B62)*ISNUMBER(INDEX(Inputs!$D$4:$AG$200,0,MATCH(S$2,Inputs!$D$2:$AG$2,0))))=0,"",SUMIFS(INDEX(Inputs!$D$4:$AG$200,0,MATCH(S$2,Inputs!$D$2:$AG$2,0)),Inputs!$B$4:$B$200,$B62)/1000) -> 71924.826 | T62: =IF(SUMPRODUCT((Inputs!$B$4:$B$200=$B62)*ISNUMBER(INDEX(Inputs!$D$4:$AG$200,0,MATCH(T$2,Inputs!$D$2:$AG$2,0))))=0,"",SUMIFS(INDEX(Inputs!$D$4:$AG$200,0,MATCH(T$2,Inputs!$D$2:$AG$2,0)),Inputs!$B$4:$B$200,$B62)/1000) -> 70369.758 | U62: =IF(SUMPRODUCT((Inputs!$B$4:$B$200=$B62)*ISNUMBER(INDEX(Inputs!$D$4:$AG$200,0,MATCH(U$2,Inputs!$D$2:$AG$2,0))))=0,"",SUMIFS(INDEX(Inputs!$D$4:$AG$200,0,MATCH(U$2,Inputs!$D$2:$AG$2,0)),Inputs!$B$4:$B$200,$B62)/1000) -> 68114.141 | V62: =IF(SUMPRODUCT((Inputs!$B$4:$B$200=$B62)*ISNUMBER(INDEX(Inputs!$D$4:$AG$200,0,MATCH(V$2,Inputs!$D$2:$AG$2,0))))=0,"",SUMIFS(INDEX(Inputs!$D$4:$AG$200,0,MATCH(V$2,Inputs!$D$2:$AG$2,0)),Inputs!$B$4:$B$200,$B62)/1000) -> 66296.152 | W62: =IF(COUNT(S62:V62)=4,SUM(S62:V62),"") -> 276704.88 | X62: =IF(SUMPRODUCT((Inputs!$B$4:$B$200=$B62)*ISNUMBER(INDEX(Inputs!$D$4:$AG$200,0,MATCH(X$2,Inputs!$D$2:$AG$2,0))))=0,"",SUMIFS(INDEX(Inputs!$D$4:$AG$200,0,MATCH(X$2,Inputs!$D$2:$AG$2,0)),Inputs!$B$4:$B$200,$B62)/1000) -> 68229.9 | Y62: =IF(SUMPRODUCT((Inputs!$B$4:$B$200=$B62)*ISNUMBER(INDEX(Inputs!$D$4:$AG$200,0,MATCH(Y$2,Inputs!$D$2:$AG$2,0))))=0,"",SUMIFS(INDEX(Inputs!$D$4:$AG$200,0,MATCH(Y$2,Inputs!$D$2:$AG$2,0)),Inputs!$B$4:$B$200,$B62)/1000) -> 67397.041 | Z62: =IF(SUMPRODUCT((Inputs!$B$4:$B$200=$B62)*ISNUMBER(INDEX(Inputs!$D$4:$AG$200,0,MATCH(Z$2,Inputs!$D$2:$AG$2,0))))=0,"",SUMIFS(INDEX(Inputs!$D$4:$AG$200,0,MATCH(Z$2,Inputs!$D$2:$AG$2,0)),Inputs!$B$4:$B$200,$B62)/1000) -> 66285.398 | AA62: =IF(SUMPRODUCT((Inputs!$B$4:$B$200=$B62)*ISNUMBER(INDEX(Inputs!$D$4:$AG$200,0,MATCH(AA$2,Inputs!$D$2:$AG$2,0))))=0,"",SUMIFS(INDEX(Inputs!$D$4:$AG$200,0,MATCH(AA$2,Inputs!$D$2:$AG$2,0)),Inputs!$B$4:$B$200,$B62)/1000) -> 73313.193 | AB62: =IF(COUNT(X62:AA62)=4,SUM(X62:AA62),"") -> 275225.53 | AC62: =IF(SUMPRODUCT((Inputs!$B$4:$B$200=$B62)*ISNUMBER(INDEX(Inputs!$D$4:$AG$200,0,MATCH(AC$2,Inputs!$D$2:$AG$2,0))))=0,"",SUMIFS(INDEX(Inputs!$D$4:$AG$200,0,MATCH(AC$2,Inputs!$D$2:$AG$2,0)),Inputs!$B$4:$B$200,$B62)/1000) -> 79411.652 | AD62: =IF(SUMPRODUCT((Inputs!$B$4:$B$200=$B62)*ISNUMBER(INDEX(Inputs!$D$4:$AG$200,0,MATCH(AD$2,Inputs!$D$2:$AG$2,0))))=0,"",SUMIFS(INDEX(Inputs!$D$4:$AG$200,0,MATCH(AD$2,Inputs!$D$2:$AG$2,0)),Inputs!$B$4:$B$200,$B62)/1000) -> 82926.863 | AE62: =IF(SUMPRODUCT((Inputs!$B$4:$B$200=$B62)*ISNUMBER(INDEX(Inputs!$D$4:$AG$200,0,MATCH(AE$2,Inputs!$D$2:$AG$2,0))))=0,"",SUMIFS(INDEX(Inputs!$D$4:$AG$200,0,MATCH(AE$2,Inputs!$D$2:$AG$2,0)),Inputs!$B$4:$B$200,$B62)/1000) | AF62: =IF(SUMPRODUCT((Inputs!$B$4:$B$200=$B62)*ISNUMBER(INDEX(Inputs!$D$4:$AG$200,0,MATCH(AF$2,Inputs!$D$2:$AG$2,0))))=0,"",SUMIFS(INDEX(Inputs!$D$4:$AG$200,0,MATCH(AF$2,Inputs!$D$2:$AG$2,0)),Inputs!$B$4:$B$200,$B62)/1000) | AG62: =IF(COUNT(AC62:AF62)=4,SUM(AC62:AF62),"")
B63: 55 | C63: RAC - numero de diarias (mil; Op Data l.15) | D63: =IF(SUMPRODUCT((Inputs!$B$4:$B$200=$B63)*ISNUMBER(INDEX(Inputs!$D$4:$AG$200,0,MATCH(D$2,Inputs!$D$2:$AG$2,0))))=0,"",SUMIFS(INDEX(Inputs!$D$4:$AG$200,0,MATCH(D$2,Inputs!$D$2:$AG$2,0)),Inputs!$B$4:$B$200,$B63)/1000) -> 5067.042 | E63: =IF(SUMPRODUCT((Inputs!$B$4:$B$200=$B63)*ISNUMBER(INDEX(Inputs!$D$4:$AG$200,0,MATCH(E$2,Inputs!$D$2:$AG$2,0))))=0,"",SUMIFS(INDEX(Inputs!$D$4:$AG$200,0,MATCH(E$2,Inputs!$D$2:$AG$2,0)),Inputs!$B$4:$B$200,$B63)/1000) -> 4618.39 | F63: =IF(SUMPRODUCT((Inputs!$B$4:$B$200=$B63)*ISNUMBER(INDEX(Inputs!$D$4:$AG$200,0,MATCH(F$2,Inputs!$D$2:$AG$2,0))))=0,"",SUMIFS(INDEX(Inputs!$D$4:$AG$200,0,MATCH(F$2,Inputs!$D$2:$AG$2,0)),Inputs!$B$4:$B$200,$B63)/1000) -> 5143.355 | G63: =IF(SUMPRODUCT((Inputs!$B$4:$B$200=$B63)*ISNUMBER(INDEX(Inputs!$D$4:$AG$200,0,MATCH(G$2,Inputs!$D$2:$AG$2,0))))=0,"",SUMIFS(INDEX(Inputs!$D$4:$AG$200,0,MATCH(G$2,Inputs!$D$2:$AG$2,0)),Inputs!$B$4:$B$200,$B63)/1000) -> 5281.203 | H63: =IF(COUNT(D63:G63)=4,SUM(D63:G63),"") -> 20109.99 | I63: =IF(SUMPRODUCT((Inputs!$B$4:$B$200=$B63)*ISNUMBER(INDEX(Inputs!$D$4:$AG$200,0,MATCH(I$2,Inputs!$D$2:$AG$2,0))))=0,"",SUMIFS(INDEX(Inputs!$D$4:$AG$200,0,MATCH(I$2,Inputs!$D$2:$AG$2,0)),Inputs!$B$4:$B$200,$B63)/1000) -> 5224.573 | J63: =IF(SUMPRODUCT((Inputs!$B$4:$B$200=$B63)*ISNUMBER(INDEX(Inputs!$D$4:$AG$200,0,MATCH(J$2,Inputs!$D$2:$AG$2,0))))=0,"",SUMIFS(INDEX(Inputs!$D$4:$AG$200,0,MATCH(J$2,Inputs!$D$2:$AG$2,0)),Inputs!$B$4:$B$200,$B63)/1000) -> 5677.49 | K63: =IF(SUMPRODUCT((Inputs!$B$4:$B$200=$B63)*ISNUMBER(INDEX(Inputs!$D$4:$AG$200,0,MATCH(K$2,Inputs!$D$2:$AG$2,0))))=0,"",SUMIFS(INDEX(Inputs!$D$4:$AG$200,0,MATCH(K$2,Inputs!$D$2:$AG$2,0)),Inputs!$B$4:$B$200,$B63)/1000) -> 5888.846 | L63: =IF(SUMPRODUCT((Inputs!$B$4:$B$200=$B63)*ISNUMBER(INDEX(Inputs!$D$4:$AG$200,0,MATCH(L$2,Inputs!$D$2:$AG$2,0))))=0,"",SUMIFS(INDEX(Inputs!$D$4:$AG$200,0,MATCH(L$2,Inputs!$D$2:$AG$2,0)),Inputs!$B$4:$B$200,$B63)/1000) -> 6111.338 | M63: =IF(COUNT(I63:L63)=4,SUM(I63:L63),"") -> 22902.247 | N63: =IF(SUMPRODUCT((Inputs!$B$4:$B$200=$B63)*ISNUMBER(INDEX(Inputs!$D$4:$AG$200,0,MATCH(N$2,Inputs!$D$2:$AG$2,0))))=0,"",SUMIFS(INDEX(Inputs!$D$4:$AG$200,0,MATCH(N$2,Inputs!$D$2:$AG$2,0)),Inputs!$B$4:$B$200,$B63)/1000) -> 6218.754 | O63: =IF(SUMPRODUCT((Inputs!$B$4:$B$200=$B63)*ISNUMBER(INDEX(Inputs!$D$4:$AG$200,0,MATCH(O$2,Inputs!$D$2:$AG$2,0))))=0,"",SUMIFS(INDEX(Inputs!$D$4:$AG$200,0,MATCH(O$2,Inputs!$D$2:$AG$2,0)),Inputs!$B$4:$B$200,$B63)/1000) -> 5837.236 | P63: =IF(SUMPRODUCT((Inputs!$B$4:$B$200=$B63)*ISNUMBER(INDEX(Inputs!$D$4:$AG$200,0,MATCH(P$2,Inputs!$D$2:$AG$2,0))))=0,"",SUMIFS(INDEX(Inputs!$D$4:$AG$200,0,MATCH(P$2,Inputs!$D$2:$AG$2,0)),Inputs!$B$4:$B$200,$B63)/1000) -> 5819.624 | Q63: =IF(SUMPRODUCT((Inputs!$B$4:$B$200=$B63)*ISNUMBER(INDEX(Inputs!$D$4:$AG$200,0,MATCH(Q$2,Inputs!$D$2:$AG$2,0))))=0,"",SUMIFS(INDEX(Inputs!$D$4:$AG$200,0,MATCH(Q$2,Inputs!$D$2:$AG$2,0)),Inputs!$B$4:$B$200,$B63)/1000) -> 5945.636 | R63: =IF(COUNT(N63:Q63)=4,SUM(N63:Q63),"") -> 23821.25 | S63: =IF(SUMPRODUCT((Inputs!$B$4:$B$200=$B63)*ISNUMBER(INDEX(Inputs!$D$4:$AG$200,0,MATCH(S$2,Inputs!$D$2:$AG$2,0))))=0,"",SUMIFS(INDEX(Inputs!$D$4:$AG$200,0,MATCH(S$2,Inputs!$D$2:$AG$2,0)),Inputs!$B$4:$B$200,$B63)/1000) -> 6414.484 | T63: =IF(SUMPRODUCT((Inputs!$B$4:$B$200=$B63)*ISNUMBER(INDEX(Inputs!$D$4:$AG$200,0,MATCH(T$2,Inputs!$D$2:$AG$2,0))))=0,"",SUMIFS(INDEX(Inputs!$D$4:$AG$200,0,MATCH(T$2,Inputs!$D$2:$AG$2,0)),Inputs!$B$4:$B$200,$B63)/1000) -> 6200.041 | U63: =IF(SUMPRODUCT((Inputs!$B$4:$B$200=$B63)*ISNUMBER(INDEX(Inputs!$D$4:$AG$200,0,MATCH(U$2,Inputs!$D$2:$AG$2,0))))=0,"",SUMIFS(INDEX(Inputs!$D$4:$AG$200,0,MATCH(U$2,Inputs!$D$2:$AG$2,0)),Inputs!$B$4:$B$200,$B63)/1000) -> 6004.671 | V63: =IF(SUMPRODUCT((Inputs!$B$4:$B$200=$B63)*ISNUMBER(INDEX(Inputs!$D$4:$AG$200,0,MATCH(V$2,Inputs!$D$2:$AG$2,0))))=0,"",SUMIFS(INDEX(Inputs!$D$4:$AG$200,0,MATCH(V$2,Inputs!$D$2:$AG$2,0)),Inputs!$B$4:$B$200,$B63)/1000) -> 5958.805 | W63: =IF(COUNT(S63:V63)=4,SUM(S63:V63),"") -> 24578.001 | X63: =IF(SUMPRODUCT((Inputs!$B$4:$B$200=$B63)*ISNUMBER(INDEX(Inputs!$D$4:$AG$200,0,MATCH(X$2,Inputs!$D$2:$AG$2,0))))=0,"",SUMIFS(INDEX(Inputs!$D$4:$AG$200,0,MATCH(X$2,Inputs!$D$2:$AG$2,0)),Inputs!$B$4:$B$200,$B63)/1000) -> 6026.629 | Y63: =IF(SUMPRODUCT((Inputs!$B$4:$B$200=$B63)*ISNUMBER(INDEX(Inputs!$D$4:$AG$200,0,MATCH(Y$2,Inputs!$D$2:$AG$2,0))))=0,"",SUMIFS(INDEX(Inputs!$D$4:$AG$200,0,MATCH(Y$2,Inputs!$D$2:$AG$2,0)),Inputs!$B$4:$B$200,$B63)/1000) -> 6070.355 | Z63: =IF(SUMPRODUCT((Inputs!$B$4:$B$200=$B63)*ISNUMBER(INDEX(Inputs!$D$4:$AG$200,0,MATCH(Z$2,Inputs!$D$2:$AG$2,0))))=0,"",SUMIFS(INDEX(Inputs!$D$4:$AG$200,0,MATCH(Z$2,Inputs!$D$2:$AG$2,0)),Inputs!$B$4:$B$200,$B63)/1000) -> 6084.784 | AA63: =IF(SUMPRODUCT((Inputs!$B$4:$B$200=$B63)*ISNUMBER(INDEX(Inputs!$D$4:$AG$200,0,MATCH(AA$2,Inputs!$D$2:$AG$2,0))))=0,"",SUMIFS(INDEX(Inputs!$D$4:$AG$200,0,MATCH(AA$2,Inputs!$D$2:$AG$2,0)),Inputs!$B$4:$B$200,$B63)/1000) -> 6688.82 | AB63: =IF(COUNT(X63:AA63)=4,SUM(X63:AA63),"") -> 24870.588 | AC63: =IF(SUMPRODUCT((Inputs!$B$4:$B$200=$B63)*ISNUMBER(INDEX(Inputs!$D$4:$AG$200,0,MATCH(AC$2,Inputs!$D$2:$AG$2,0))))=0,"",SUMIFS(INDEX(Inputs!$D$4:$AG$200,0,MATCH(AC$2,Inputs!$D$2:$AG$2,0)),Inputs!$B$4:$B$200,$B63)/1000) -> 7085.3151 | AD63: =IF(SUMPRODUCT((Inputs!$B$4:$B$200=$B63)*ISNUMBER(INDEX(Inputs!$D$4:$AG$200,0,MATCH(AD$2,Inputs!$D$2:$AG$2,0))))=0,"",SUMIFS(INDEX(Inputs!$D$4:$AG$200,0,MATCH(AD$2,Inputs!$D$2:$AG$2,0)),Inputs!$B$4:$B$200,$B63)/1000) -> 7412.787 | AE63: =IF(SUMPRODUCT((Inputs!$B$4:$B$200=$B63)*ISNUMBER(INDEX(Inputs!$D$4:$AG$200,0,MATCH(AE$2,Inputs!$D$2:$AG$2,0))))=0,"",SUMIFS(INDEX(Inputs!$D$4:$AG$200,0,MATCH(AE$2,Inputs!$D$2:$AG$2,0)),Inputs!$B$4:$B$200,$B63)/1000) | AF63: =IF(SUMPRODUCT((Inputs!$B$4:$B$200=$B63)*ISNUMBER(INDEX(Inputs!$D$4:$AG$200,0,MATCH(AF$2,Inputs!$D$2:$AG$2,0))))=0,"",SUMIFS(INDEX(Inputs!$D$4:$AG$200,0,MATCH(AF$2,Inputs!$D$2:$AG$2,0)),Inputs!$B$4:$B$200,$B63)/1000) | AG63: =IF(COUNT(AC63:AF63)=4,SUM(AC63:AF63),"")
B64: 56 | C64: RAC - taxa de ocupacao (Op Data l.16) | D64: =IF(SUMPRODUCT((Inputs!$B$4:$B$200=$B64)*ISNUMBER(INDEX(Inputs!$D$4:$AG$200,0,MATCH(D$2,Inputs!$D$2:$AG$2,0))))=0,"",SUMIFS(INDEX(Inputs!$D$4:$AG$200,0,MATCH(D$2,Inputs!$D$2:$AG$2,0)),Inputs!$B$4:$B$200,$B64)/1000) -> 0.793 | E64: =IF(SUMPRODUCT((Inputs!$B$4:$B$200=$B64)*ISNUMBER(INDEX(Inputs!$D$4:$AG$200,0,MATCH(E$2,Inputs!$D$2:$AG$2,0))))=0,"",SUMIFS(INDEX(Inputs!$D$4:$AG$200,0,MATCH(E$2,Inputs!$D$2:$AG$2,0)),Inputs!$B$4:$B$200,$B64)/1000) -> 0.796 | F64: =IF(SUMPRODUCT((Inputs!$B$4:$B$200=$B64)*ISNUMBER(INDEX(Inputs!$D$4:$AG$200,0,MATCH(F$2,Inputs!$D$2:$AG$2,0))))=0,"",SUMIFS(INDEX(Inputs!$D$4:$AG$200,0,MATCH(F$2,Inputs!$D$2:$AG$2,0)),Inputs!$B$4:$B$200,$B64)/1000) -> 0.829 | G64: =IF(SUMPRODUCT((Inputs!$B$4:$B$200=$B64)*ISNUMBER(INDEX(Inputs!$D$4:$AG$200,0,MATCH(G$2,Inputs!$D$2:$AG$2,0))))=0,"",SUMIFS(INDEX(Inputs!$D$4:$AG$200,0,MATCH(G$2,Inputs!$D$2:$AG$2,0)),Inputs!$B$4:$B$200,$B64)/1000) -> 0.808 | H64: =IF(COUNT(D64:G64)=4,SUM(D64:G64),"") -> 3.226 | I64: =IF(SUMPRODUCT((Inputs!$B$4:$B$200=$B64)*ISNUMBER(INDEX(Inputs!$D$4:$AG$200,0,MATCH(I$2,Inputs!$D$2:$AG$2,0))))=0,"",SUMIFS(INDEX(Inputs!$D$4:$AG$200,0,MATCH(I$2,Inputs!$D$2:$AG$2,0)),Inputs!$B$4:$B$200,$B64)/1000) -> 0.761 | J64: =IF(SUMPRODUCT((Inputs!$B$4:$B$200=$B64)*ISNUMBER(INDEX(Inputs!$D$4:$AG$200,0,MATCH(J$2,Inputs!$D$2:$AG$2,0))))=0,"",SUMIFS(INDEX(Inputs!$D$4:$AG$200,0,MATCH(J$2,Inputs!$D$2:$AG$2,0)),Inputs!$B$4:$B$200,$B64)/1000) -> 0.793 | K64: =IF(SUMPRODUCT((Inputs!$B$4:$B$200=$B64)*ISNUMBER(INDEX(Inputs!$D$4:$AG$200,0,MATCH(K$2,Inputs!$D$2:$AG$2,0))))=0,"",SUMIFS(INDEX(Inputs!$D$4:$AG$200,0,MATCH(K$2,Inputs!$D$2:$AG$2,0)),Inputs!$B$4:$B$200,$B64)/1000) -> 0.772 | L64: =IF(SUMPRODUCT((Inputs!$B$4:$B$200=$B64)*ISNUMBER(INDEX(Inputs!$D$4:$AG$200,0,MATCH(L$2,Inputs!$D$2:$AG$2,0))))=0,"",SUMIFS(INDEX(Inputs!$D$4:$AG$200,0,MATCH(L$2,Inputs!$D$2:$AG$2,0)),Inputs!$B$4:$B$200,$B64)/1000) -> 0.766 | M64: =IF(COUNT(I64:L64)=4,SUM(I64:L64),"") -> 3.092 | N64: =IF(SUMPRODUCT((Inputs!$B$4:$B$200=$B64)*ISNUMBER(INDEX(Inputs!$D$4:$AG$200,0,MATCH(N$2,Inputs!$D$2:$AG$2,0))))=0,"",SUMIFS(INDEX(Inputs!$D$4:$AG$200,0,MATCH(N$2,Inputs!$D$2:$AG$2,0)),Inputs!$B$4:$B$200,$B64)/1000) -> 0.784 | O64: =IF(SUMPRODUCT((Inputs!$B$4:$B$200=$B64)*ISNUMBER(INDEX(Inputs!$D$4:$AG$200,0,MATCH(O$2,Inputs!$D$2:$AG$2,0))))=0,"",SUMIFS(INDEX(Inputs!$D$4:$AG$200,0,MATCH(O$2,Inputs!$D$2:$AG$2,0)),Inputs!$B$4:$B$200,$B64)/1000) -> 0.783 | P64: =IF(SUMPRODUCT((Inputs!$B$4:$B$200=$B64)*ISNUMBER(INDEX(Inputs!$D$4:$AG$200,0,MATCH(P$2,Inputs!$D$2:$AG$2,0))))=0,"",SUMIFS(INDEX(Inputs!$D$4:$AG$200,0,MATCH(P$2,Inputs!$D$2:$AG$2,0)),Inputs!$B$4:$B$200,$B64)/1000) -> 0.811 | Q64: =IF(SUMPRODUCT((Inputs!$B$4:$B$200=$B64)*ISNUMBER(INDEX(Inputs!$D$4:$AG$200,0,MATCH(Q$2,Inputs!$D$2:$AG$2,0))))=0,"",SUMIFS(INDEX(Inputs!$D$4:$AG$200,0,MATCH(Q$2,Inputs!$D$2:$AG$2,0)),Inputs!$B$4:$B$200,$B64)/1000) -> 0.82 | R64: =IF(COUNT(N64:Q64)=4,SUM(N64:Q64),"") -> 3.198 | S64: =IF(SUMPRODUCT((Inputs!$B$4:$B$200=$B64)*ISNUMBER(INDEX(Inputs!$D$4:$AG$200,0,MATCH(S$2,Inputs!$D$2:$AG$2,0))))=0,"",SUMIFS(INDEX(Inputs!$D$4:$AG$200,0,MATCH(S$2,Inputs!$D$2:$AG$2,0)),Inputs!$B$4:$B$200,$B64)/1000) -> 0.802 | T64: =IF(SUMPRODUCT((Inputs!$B$4:$B$200=$B64)*ISNUMBER(INDEX(Inputs!$D$4:$AG$200,0,MATCH(T$2,Inputs!$D$2:$AG$2,0))))=0,"",SUMIFS(INDEX(Inputs!$D$4:$AG$200,0,MATCH(T$2,Inputs!$D$2:$AG$2,0)),Inputs!$B$4:$B$200,$B64)/1000) -> 0.781 | U64: =IF(SUMPRODUCT((Inputs!$B$4:$B$200=$B64)*ISNUMBER(INDEX(Inputs!$D$4:$AG$200,0,MATCH(U$2,Inputs!$D$2:$AG$2,0))))=0,"",SUMIFS(INDEX(Inputs!$D$4:$AG$200,0,MATCH(U$2,Inputs!$D$2:$AG$2,0)),Inputs!$B$4:$B$200,$B64)/1000) -> 0.781 | V64: =IF(SUMPRODUCT((Inputs!$B$4:$B$200=$B64)*ISNUMBER(INDEX(Inputs!$D$4:$AG$200,0,MATCH(V$2,Inputs!$D$2:$AG$2,0))))=0,"",SUMIFS(INDEX(Inputs!$D$4:$AG$200,0,MATCH(V$2,Inputs!$D$2:$AG$2,0)),Inputs!$B$4:$B$200,$B64)/1000) -> 0.749 | W64: =IF(COUNT(S64:V64)=4,SUM(S64:V64),"") -> 3.113 | X64: =IF(SUMPRODUCT((Inputs!$B$4:$B$200=$B64)*ISNUMBER(INDEX(Inputs!$D$4:$AG$200,0,MATCH(X$2,Inputs!$D$2:$AG$2,0))))=0,"",SUMIFS(INDEX(Inputs!$D$4:$AG$200,0,MATCH(X$2,Inputs!$D$2:$AG$2,0)),Inputs!$B$4:$B$200,$B64)/1000) -> 0.717 | Y64: =IF(SUMPRODUCT((Inputs!$B$4:$B$200=$B64)*ISNUMBER(INDEX(Inputs!$D$4:$AG$200,0,MATCH(Y$2,Inputs!$D$2:$AG$2,0))))=0,"",SUMIFS(INDEX(Inputs!$D$4:$AG$200,0,MATCH(Y$2,Inputs!$D$2:$AG$2,0)),Inputs!$B$4:$B$200,$B64)/1000) -> 0.741 | Z64: =IF(SUMPRODUCT((Inputs!$B$4:$B$200=$B64)*ISNUMBER(INDEX(Inputs!$D$4:$AG$200,0,MATCH(Z$2,Inputs!$D$2:$AG$2,0))))=0,"",SUMIFS(INDEX(Inputs!$D$4:$AG$200,0,MATCH(Z$2,Inputs!$D$2:$AG$2,0)),Inputs!$B$4:$B$200,$B64)/1000) -> 0.718 | AA64: =IF(SUMPRODUCT((Inputs!$B$4:$B$200=$B64)*ISNUMBER(INDEX(Inputs!$D$4:$AG$200,0,MATCH(AA$2,Inputs!$D$2:$AG$2,0))))=0,"",SUMIFS(INDEX(Inputs!$D$4:$AG$200,0,MATCH(AA$2,Inputs!$D$2:$AG$2,0)),Inputs!$B$4:$B$200,$B64)/1000) -> 0.75846991 | AB64: =IF(COUNT(X64:AA64)=4,SUM(X64:AA64),"") -> 2.9344699 | AC64: =IF(SUMPRODUCT((Inputs!$B$4:$B$200=$B64)*ISNUMBER(INDEX(Inputs!$D$4:$AG$200,0,MATCH(AC$2,Inputs!$D$2:$AG$2,0))))=0,"",SUMIFS(INDEX(Inputs!$D$4:$AG$200,0,MATCH(AC$2,Inputs!$D$2:$AG$2,0)),Inputs!$B$4:$B$200,$B64)/1000) -> 0.77283417 | AD64: =IF(SUMPRODUCT((Inputs!$B$4:$B$200=$B64)*ISNUMBER(INDEX(Inputs!$D$4:$AG$200,0,MATCH(AD$2,Inputs!$D$2:$AG$2,0))))=0,"",SUMIFS(INDEX(Inputs!$D$4:$AG$200,0,MATCH(AD$2,Inputs!$D$2:$AG$2,0)),Inputs!$B$4:$B$200,$B64)/1000) -> 0.76208042 | AE64: =IF(SUMPRODUCT((Inputs!$B$4:$B$200=$B64)*ISNUMBER(INDEX(Inputs!$D$4:$AG$200,0,MATCH(AE$2,Inputs!$D$2:$AG$2,0))))=0,"",SUMIFS(INDEX(Inputs!$D$4:$AG$200,0,MATCH(AE$2,Inputs!$D$2:$AG$2,0)),Inputs!$B$4:$B$200,$B64)/1000) | AF64: =IF(SUMPRODUCT((Inputs!$B$4:$B$200=$B64)*ISNUMBER(INDEX(Inputs!$D$4:$AG$200,0,MATCH(AF$2,Inputs!$D$2:$AG$2,0))))=0,"",SUMIFS(INDEX(Inputs!$D$4:$AG$200,0,MATCH(AF$2,Inputs!$D$2:$AG$2,0)),Inputs!$B$4:$B$200,$B64)/1000) | AG64: =IF(COUNT(AC64:AF64)=4,SUM(AC64:AF64),"")
