Workbook

Sheet Inputs
B1: Fator de escala | C1: Fonte já na unidade final = 1 · fonte em milhares = 0,001 | D1: 1 | F1: MODELO-BASE VAZIO — BANCOS DOS EUA (US GAAP). Preencha os valores nas linhas abaixo e as datas de primeiro e último trimestre no painel. Fonte preferencial: 10-Q/10-K (SEC XBRL) e earnings supplement da companhia. Macro histórico do FRED (St. Louis Fed).
B2: COD | C2: Conta (como divulgada) | D2: Fonte · ORIGEM · unidade | E2: 1T20 | F2: 2T20 | G2: 3T20 | H2: 4T20 | I2: 1T21 | J2: 2T21 | K2: 3T21 | L2: 4T21 | M2: 1T22 | N2: 2T22 | O2: 3T22 | P2: 4T22 | Q2: 1T23 | R2: 2T23 | S2: 3T23 | T2: 4T23 | U2: 1T24 | V2: 2T24 | W2: 3T24 | X2: 4T24 | Y2: 1T25 | Z2: 2T25 | AA2: 3T25 | AB2: 4T25 | AC2: 1T26 | AD2: 2T26 | AE2: 3T26 | AF2: 4T26 | AG2: 1T27 | AH2: 2T27 | AI2: 3T27 | AJ2: 4T27 | AK2: 1T28 | AL2: 2T28 | AM2: 3T28 | AN2: 4T28 | AO2: 1T29 | AP2: 2T29 | AQ2: 3T29 | AR2: 4T29 | AS2: 1T30 | AT2: 2T30 | AU2: 3T30 | AV2: 4T30
C5: ATIVO
B6: cash | C6: Caixa e depósitos não remunerados em bancos | D6: preencher: fonte e linha · fonte · moeda
B7: resale | C7: Fed funds vendidos e compromissadas reversas | D7: preencher: fonte e linha · fonte · moeda
B8: dep_banks | C8: Depósitos remunerados em bancos (inclui Federal Reserve) | D8: preencher: fonte e linha · fonte · moeda
B9: sec_borrowed | C9: Títulos tomados em empréstimo (securities borrowed) | D9: preencher: fonte e linha · fonte · moeda
B10: liq_acl | C10: (Provisão para perdas — aplicações de liquidez) | D10: preencher: fonte e linha · fonte · moeda
B11: trading | C11: Ativos de trading (inclui derivativos a receber) | D11: preencher: fonte e linha · fonte · moeda
B12: afs | C12: Títulos disponíveis para venda (AFS, valor justo) | D12: preencher: fonte e linha · fonte · moeda
B13: htm | C13: Títulos mantidos até o vencimento (HTM, custo amortizado) | D13: preencher: fonte e linha · fonte · moeda
B14: sec_acl | C14: (Provisão para perdas — títulos, quando à parte) | D14: preencher: fonte e linha · fonte · moeda
B15: deriv_a | C15: Derivativos a receber (quando fora de trading) | D15: preencher: fonte e linha · fonte · moeda
B16: loans | C16: Empréstimos, líquidos de receitas diferidas | D16: preencher: fonte e linha · fonte · moeda
B17: loans_fv | C17: Empréstimos a valor justo / mantidos para venda (quando à parte) | D17: preencher: fonte e linha · fonte · moeda
... B25: gw_intang | C25: Goodwill, MSRs e outros intangíveis | D25: preencher: fonte e linha · fonte · moeda
C27: PASSIVO
B28: dep_nib | C28: Depósitos sem juros (noninterest-bearing) | D28: preencher: fonte e linha · fonte · moeda
B29: dep_ib | C29: Depósitos com juros (interest-bearing) | D29: preencher: fonte e linha · fonte · moeda
B30: dep_x1 | C30: Depósitos — abertura adicional (quando a fonte separa) | D30: preencher: fonte e linha · fonte · moeda
B31: dep_time | C31: Depósitos a prazo (time deposits, quando à parte) | D31: preencher: fonte e linha · fonte · moeda
B32: dep_other | C32: Outros depósitos (quando à parte) | D32: preencher: fonte e linha · fonte · moeda
B33: repo | C33: Fed funds comprados e compromissadas (repos) | D33: preencher: fonte e linha · fonte · moeda
B34: st_borr | C34: Captações de curto prazo (short-term borrowings) | D34: preencher: fonte e linha · fonte · moeda
B35: sec_loaned | C35: Títulos emprestados (securities loaned, quando à parte) | D35: preencher: fonte e linha · fonte · moeda
B36: ltd | C36: Dívida de longo prazo (inclui subordinada) | D36: preencher: fonte e linha · fonte · moeda
B37: vie | C37: Participações emitidas por VIEs consolidadas | D37: preencher: fonte e linha · fonte · moeda
B38: ltd_x | C38: Outras emissões (quando à parte) | D38: preencher: fonte e linha · fonte · moeda
B39: sub_debt | C39: Dívida subordinada (quando à parte) | D39: preencher: fonte e linha · fonte · moeda
... B48: other_l | C48: Contas a pagar e outros passivos | D48: preencher: fonte e linha · fonte · moeda
C50: PATRIMÔNIO LÍQUIDO
B51: common_stk | C51: Ações ordinárias (valor nominal) | D51: preencher: fonte e linha · fonte · moeda
B52: apic | C52: Capital adicional integralizado (APIC) e outros | D52: preencher: fonte e linha · fonte · moeda
B53: ret_earn | C53: Lucros retidos | D53: preencher: fonte e linha · fonte · moeda
B54: aoci | C54: Outros resultados abrangentes acumulados (AOCI) | D54: preencher: fonte e linha · fonte · moeda
B55: treasury | C55: (Ações em tesouraria, a custo) | D55: preencher: fonte e linha · fonte · moeda
B56: nci | C56: Participação de não controladores | D56: preencher: fonte e linha · fonte · moeda
C58: DEMONSTRAÇÃO DO RESULTADO (US GAAP)
B59: ii_loans | C59: Juros de empréstimos | D59: preencher: fonte e linha · fonte · moeda
B60: ii_sec | C60: Juros de títulos e ativos de trading | D60: preencher: fonte e linha · fonte · moeda
B61: ii_repo | C61: Juros de compromissadas reversas e securities borrowed | D61: preencher: fonte e linha · fonte · moeda
B62: ii_other | C62: Juros de depósitos em bancos e outros | D62: preencher: fonte e linha · fonte · moeda
B63: ie_dep | C63: (Juros de depósitos) | D63: preencher: fonte e linha · fonte · moeda
B64: ie_ltd | C64: (Juros de dívida de longo prazo e VIEs) | D64: preencher: fonte e linha · fonte · moeda
B65: ie_st | C65: (Juros de compromissadas, curto prazo, trading e outros) | D65: preencher: fonte e linha · fonte · moeda
B66: ie_other | C66: (Outras despesas de juros, quando à parte) | D66: preencher: fonte e linha · fonte · moeda
B67: provision | C67: (Provisão para perdas de crédito) | D67: preencher: fonte e linha · fonte · moeda
B68: recoveries | C68: Recuperações (quando à parte; nos EUA a provisão já é líquida) | D68: preencher: fonte e linha · fonte · moeda
B69: fees | C69: Receitas de tarifas e comissões | D69: preencher: fonte e linha · fonte · moeda
B70: principal | C70: Resultado de trading (principal transactions) | D70: preencher: fonte e linha · fonte · moeda
... B83: nci_ni | C83: (Lucro atribuído a não controladores) | D83: preencher: fonte e linha · fonte · moeda
C85: DADOS COMPLEMENTARES
B86: loans_tot | C86: Empréstimos totais | D86: preencher: fonte e linha · fonte · moeda
B87: loans_cons | C87: Consumo ex-cartão (consumer ex-card) | D87: preencher: fonte e linha · fonte · moeda
B88: loans_wh | C88: Atacado (wholesale / commercial) | D88: preencher: fonte e linha · fonte · moeda
B89: loans_card | C89: Cartão de crédito | D89: preencher: fonte e linha · fonte · moeda
B90: nonaccrual | C90: Empréstimos em nonaccrual | D90: preencher: fonte e linha · fonte · moeda
B91: npa | C91: Ativos não performados (nonperforming assets) | D91: preencher: fonte e linha · fonte · moeda
B92: acl_cons | C92: ACL — consumo ex-cartão | D92: preencher: fonte e linha · fonte · moeda
B93: acl_lrc | C93: ACL de compromissos de crédito (fora do balanço) | D93: preencher: fonte e linha · fonte · moeda
B94: acl_secs | C94: ACL de títulos (AFS e HTM) | D94: preencher: fonte e linha · fonte · moeda
B95: acl_tot | C95: ACL total de empréstimos (saldo positivo) | D95: preencher: fonte e linha · fonte · moeda
B96: dpd90 | C96: Vencidos há 90+ dias ainda acumulando juros | D96: preencher: fonte e linha · fonte · moeda
B97: dpd30 | C97: Vencidos de 30 a 89 dias | D97: preencher: fonte e linha · fonte · moeda
... B148: adm_oth | C148: (Demais despesas administrativas) | D148: preencher: fonte e linha · fonte · moeda
C150: Linhas derivadas por fórmula dentro da própria Inputs
C151: CONTAS ESPECÍFICAS DE BANCOS DOS EUA
B152: pref | C152: Ações preferenciais (valor contábil) | D152: preencher: fonte e linha · fonte · moeda
B153: div_pref | D153: preencher: fonte e linha · fonte · moeda
B154: slr | C154: Supplementary leverage ratio — SLR (%) | D154: preencher: fonte e linha · fonte · pct
B155: rwa_adv | C155: RWA — abordagem avançada (Advanced) | D155: preencher: fonte e linha · fonte · moeda
B156: cet1r_adv | C156: Índice CET1 reportado — Advanced (%) | D156: preencher: fonte e linha · fonte · pct
B157: msr | C157: MSRs — direitos de serviço de hipotecas (dentro de goodwill e intangíveis) | D157: preencher: fonte e linha · fonte · moeda
C159: Espaço livre até a linha 190 (linhas 160 a 190) para novas linhas de origem. Qualquer linha com um código existente é somada automaticamente pela Inputs (2).
C196: IDENTIFICAÇÃO E MERCADO | D196: COMPANY & MARKET DATA
C197: Instituição | D197: Institution
C198: Ticker | D198: Ticker
C199: Tipo de banco / norma contábil | D199: Segment / accounting standard
C200: Moeda de reporte | D200: Reporting currency | E200: US$ | BI200: Escolha a moeda aqui. Os títulos do Model, da Inputs (2) e do Valuation leem esta célula, então trocar BRL por USD renomeia a planilha inteira. O que a célula não faz é converter valor: conversão de moeda é outra coisa.
C201: Escala dos valores | D201: Scale | E201: milhões
C202: Unidade monetária (moeda + escala) | D202: Currency unit | E202: =E200&" "&E201 -> US$ milhões
C203: Último trimestre reportado (data de fechamento) | D203: Last reported quarter | BI203: Esta data controla todo o modelo: colunas entre o primeiro e o último trimestre são lidas como realizado; as demais são projetadas.
C204: Primeiro trimestre com dado na fonte | D204: First quarter covered by the source | BI204: Séries que começam depois da grade do modelo: as colunas anteriores ficam fora do realizado em vez de entrar como zero realizado.
C205: Data-base do valuation | D205: Valuation date
C206: ="Preço da ação ("&Inputs!$E$200&")" -> Preço da ação (US$) | D206: Share price | BI206: Preço e quantidade de ações são premissa sua, não vêm da série histórica. A quantidade de ações entra em milhões, na mesma escala do modelo, para o LPA e o VPA saírem por ação.
C207: Ações ordinárias emitidas (milhões) | D207: Common shares (mn)
C208: Ações preferenciais (não entram na contagem ordinária) | D208: Preferred shares (mn)
C209: (-) Ações em tesouraria (milhões, negativo) | D209: (-) Treasury shares (mn)
C210: Ações ordinárias em circulação (milhões) | D210: Shares ex-treasury (mn) | E210: =E207+E208+E209 -> 0
C211: ="Market cap ("&Inputs!$E$202&")" -> Market cap (US$ milhões) | D211: Market capitalisation | E211: =E206*E210 -> 0
C213: GRADE DE PERÍODOS | D213: PERIOD GRID
C214: Data de fechamento | D214: Period end | E214: =DATE(2020,4,1)-1 -> 43921 | F214: =DATE(2020,7,1)-1 -> 44012 | G214: =DATE(2020,10,1)-1 -> 44104 | H214: =DATE(2020,13,1)-1 -> 44196 | I214: =H214 -> 44196 | J214: =DATE(2021,4,1)-1 -> 44286 | K214: =DATE(2021,7,1)-1 -> 44377 | L214: =DATE(2021,10,1)-1 -> 44469 | M214: =DATE(2021,13,1)-1 -> 44561 | N214: =M214 -> 44561 | O214: =DATE(2022,4,1)-1 -> 44651 | P214: =DATE(2022,7,1)-1 -> 44742 | Q214: =DATE(2022,10,1)-1 -> 44834 | R214: =DATE(2022,13,1)-1 -> 44926 | S214: =R214 -> 44926 | T214: =DATE(2023,4,1)-1 -> 45016 | U214: =DATE(2023,7,1)-1 -> 45107 | V214: =DATE(2023,10,1)-1 -> 45199 | W214: =DATE(2023,13,1)-1 -> 45291 | X214: =W214 -> 45291 | Y214: =DATE(2024,4,1)-1 -> 45382 | Z214: =DATE(2024,7,1)-1 -> 45473 | AA214: =DATE(2024,10,1)-1 -> 45565 | AB214: =DATE(2024,13,1)-1 -> 45657 | AC214: =AB214 -> 45657 | AD214: =DATE(2025,4,1)-1 -> 45747 | AE214: =DATE(2025,7,1)-1 -> 45838 | AF214: =DATE(2025,10,1)-1 -> 45930 | AG214: =DATE(2025,13,1)-1 -> 46022 | AH214: =AG214 -> 46022 | AI214: =DATE(2026,4,1)-1 -> 46112 | AJ214: =DATE(2026,7,1)-1 -> 46203 | AK214: =DATE(2026,10,1)-1 -> 46295 | AL214: =DATE(2026,13,1)-1 -> 46387 | AM214: =AL214 -> 46387 | AN214: =DATE(2027,4,1)-1 -> 46477 | AO214: =DATE(2027,7,1)-1 -> 46568 | AP214: =DATE(2027,10,1)-1 -> 46660 | AQ214: =DATE(2027,13,1)-1 -> 46752 | AR214: =AQ214 -> 46752 | AS214: =DATE(2028,4,1)-1 -> 46843 | AT214: =DATE(2028,7,1)-1 -> 46934 | AU214: =DATE(2028,10,1)-1 -> 47026 | AV214: =DATE(2028,13,1)-1 -> 47118 | AW214: =AV214 -> 47118 | AX214: =DATE(2029,4,1)-1 -> 47208 | AY214: =DATE(2029,7,1)-1 -> 47299 | AZ214: =DATE(2029,10,1)-1 -> 47391 | BA214: =DATE(2029,13,1)-1 -> 47483 | BB214: =BA214 -> 47483 | BC214: =DATE(2030,4,1)-1 -> 47573 | BD214: =DATE(2030,7,1)-1 -> 47664 | BE214: =DATE(2030,10,1)-1 -> 47756 | BF214: =DATE(2030,13,1)-1 -> 47848 | BG214: =BF214 -> 47848
C215: Ano | D215: Year | E215: 2020 | F215: 2020 | G215: 2020 | H215: 2020 | I215: 2020 | J215: 2021 | K215: 2021 | L215: 2021 | M215: 2021 | N215: 2021 | O215: 2022 | P215: 2022 | Q215: 2022 | R215: 2022 | S215: 2022 | T215: 2023 | U215: 2023 | V215: 2023 | W215: 2023 | X215: 2023 | Y215: 2024 | Z215: 2024 | AA215: 2024 | AB215: 2024 | AC215: 2024 | AD215: 2025 | AE215: 2025 | AF215: 2025 | AG215: 2025 | AH215: 2025 | AI215: 2026 | AJ215: 2026 | AK215: 2026 | AL215: 2026 | AM215: 2026 | AN215: 2027 | AO215: 2027 | AP215: 2027 | AQ215: 2027 | AR215: 2027 | AS215: 2028 | AT215: 2028 | AU215: 2028 | AV215: 2028 | AW215: 2028 | AX215: 2029 | AY215: 2029 | AZ215: 2029 | BA215: 2029 | BB215: 2029 | BC215: 2030 | BD215: 2030 | BE215: 2030 | BF215: 2030 | BG215: 2030
C216: Período | D216: Period | E216: ="1Q"&RIGHT(E215,2) -> 1Q20 | F216: ="2Q"&RIGHT(F215,2) -> 2Q20 | G216: ="3Q"&RIGHT(G215,2) -> 3Q20 | H216: ="4Q"&RIGHT(H215,2) -> 4Q20 | I216: ="FY"&RIGHT(I215,2) -> FY20 | J216: ="1Q"&RIGHT(J215,2) -> 1Q21 | K216: ="2Q"&RIGHT(K215,2) -> 2Q21 | L216: ="3Q"&RIGHT(L215,2) -> 3Q21 | M216: ="4Q"&RIGHT(M215,2) -> 4Q21 | N216: ="FY"&RIGHT(N215,2) -> FY21 | O216: ="1Q"&RIGHT(O215,2) -> 1Q22 | P216: ="2Q"&RIGHT(P215,2) -> 2Q22 | Q216: ="3Q"&RIGHT(Q215,2) -> 3Q22 | R216: ="4Q"&RIGHT(R215,2) -> 4Q22 | S216: ="FY"&RIGHT(S215,2) -> FY22 | T216: ="1Q"&RIGHT(T215,2) -> 1Q23 | U216: ="2Q"&RIGHT(U215,2) -> 2Q23 | V216: ="3Q"&RIGHT(V215,2) -> 3Q23 | W216: ="4Q"&RIGHT(W215,2) -> 4Q23 | X216: ="FY"&RIGHT(X215,2) -> FY23 | Y216: ="1Q"&RIGHT(Y215,2) -> 1Q24 | Z216: ="2Q"&RIGHT(Z215,2) -> 2Q24 | AA216: ="3Q"&RIGHT(AA215,2) -> 3Q24 | AB216: ="4Q"&RIGHT(AB215,2) -> 4Q24 | AC216: ="FY"&RIGHT(AC215,2) -> FY24 | AD216: ="1Q"&RIGHT(AD215,2) -> 1Q25 | AE216: ="2Q"&RIGHT(AE215,2) -> 2Q25 | AF216: ="3Q"&RIGHT(AF215,2) -> 3Q25 | AG216: ="4Q"&RIGHT(AG215,2) -> 4Q25 | AH216: ="FY"&RIGHT(AH215,2) -> FY25 | AI216: ="1Q"&RIGHT(AI215,2) -> 1Q26 | AJ216: ="2Q"&RIGHT(AJ215,2) -> 2Q26 | AK216: ="3Q"&RIGHT(AK215,2) -> 3Q26 | AL216: ="4Q"&RIGHT(AL215,2) -> 4Q26 | AM216: ="FY"&RIGHT(AM215,2) -> FY26 | AN216: ="1Q"&RIGHT(AN215,2) -> 1Q27 | AO216: ="2Q"&RIGHT(AO215,2) -> 2Q27 | AP216: ="3Q"&RIGHT(AP215,2) -> 3Q27 | AQ216: ="4Q"&RIGHT(AQ215,2) -> 4Q27 | AR216: ="FY"&RIGHT(AR215,2) -> FY27 | AS216: ="1Q"&RIGHT(AS215,2) -> 1Q28 | AT216: ="2Q"&RIGHT(AT215,2) -> 2Q28 | AU216: ="3Q"&RIGHT(AU215,2) -> 3Q28 | AV216: ="4Q"&RIGHT(AV215,2) -> 4Q28 | AW216: ="FY"&RIGHT(AW215,2) -> FY28 | AX216: ="1Q"&RIGHT(AX215,2) -> 1Q29 | AY216: ="2Q"&RIGHT(AY215,2) -> 2Q29 | AZ216: ="3Q"&RIGHT(AZ215,2) -> 3Q29 | BA216: ="4Q"&RIGHT(BA215,2) -> 4Q29 | BB216: ="FY"&RIGHT(BB215,2) -> FY29 | BC216: ="1Q"&RIGHT(BC215,2) -> 1Q30 | BD216: ="2Q"&RIGHT(BD215,2) -> 2Q30 | BE216: ="3Q"&RIGHT(BE215,2) -> 3Q30 | BF216: ="4Q"&RIGHT(BF215,2) -> 4Q30 | BG216: ="FY"&RIGHT(BG215,2) -> FY30
C217: Realizado (1) / Projetado (0) | D217: Actual (1) / Forecast (0) | E217: =IF(AND(E214>=Inputs!$E$204,E214<=Inputs!$E$203),1,0) -> 0 | F217: =IF(AND(F214>=Inputs!$E$204,F214<=Inputs!$E$203),1,0) -> 0 | G217: =IF(AND(G214>=Inputs!$E$204,G214<=Inputs!$E$203),1,0) -> 0 | H217: =IF(AND(H214>=Inputs!$E$204,H214<=Inputs!$E$203),1,0) -> 0 | I217: =IF(AND(I214>=Inputs!$E$204,I214<=Inputs!$E$203),1,0) -> 0 | J217: =IF(AND(J214>=Inputs!$E$204,J214<=Inputs!$E$203),1,0) -> 0 | K217: =IF(AND(K214>=Inputs!$E$204,K214<=Inputs!$E$203),1,0) -> 0 | L217: =IF(AND(L214>=Inputs!$E$204,L214<=Inputs!$E$203),1,0) -> 0 | ... BG217: =IF(AND(BG214>=Inputs!$E$204,BG214<=Inputs!$E$203),1,0) -> 0 | BI217: Não editar: derivado da data do último trimestre reportado.
C219: DRIVERS IMPLÍCITOS NO HISTÓRICO — CALCULADOS DA INPUTS (2) | D219: IMPLIED DRIVERS — DERIVED FROM REPORTED DATA | BI219: Espelho das premissas dos blocos abaixo, calculado do reportado. Serve para você ver a variação realizada antes de escolher a projeção. Nenhuma linha daqui é lida pelo Model, então não há referência circular: basta copiar o número que fizer sentido para a célula amarela do bloco correspondente. Coluna sem dado na fonte fica vazia.
C220: Crédito, tesouraria e funding — realizado | D220: Loans, treasury and funding — actual
C221: Carteira de crédito bruta — crescimento % QoQ | D221: Gross loan growth QoQ | F221: =IFERROR(IF(('Inputs (2)'!E18+'Inputs (2)'!E19)=0,"",('Inputs (2)'!F18+'Inputs (2)'!F19)/('Inputs (2)'!E18+'Inputs (2)'!E19)-1),"") | G221: =IFERROR(IF(('Inputs (2)'!F18+'Inputs (2)'!F19)=0,"",('Inputs (2)'!G18+'Inputs (2)'!G19)/('Inputs (2)'!F18+'Inputs (2)'!F19)-1),"") | H221: =IFERROR(IF(('Inputs (2)'!G18+'Inputs (2)'!G19)=0,"",('Inputs (2)'!H18+'Inputs (2)'!H19)/('Inputs (2)'!G18+'Inputs (2)'!G19)-1),"") | J221: =IFERROR(IF(('Inputs (2)'!H18+'Inputs (2)'!H19)=0,"",('Inputs (2)'!J18+'Inputs (2)'!J19)/('Inputs (2)'!H18+'Inputs (2)'!H19)-1),"") | K221: =IFERROR(IF(('Inputs (2)'!J18+'Inputs (2)'!J19)=0,"",('Inputs (2)'!K18+'Inputs (2)'!K19)/('Inputs (2)'!J18+'Inputs (2)'!J19)-1),"") | L221: =IFERROR(IF(('Inputs (2)'!K18+'Inputs (2)'!K19)=0,"",('Inputs (2)'!L18+'Inputs (2)'!L19)/('Inputs (2)'!K18+'Inputs (2)'!K19)-1),"") | M221: =IFERROR(IF(('Inputs (2)'!L18+'Inputs (2)'!L19)=0,"",('Inputs (2)'!M18+'Inputs (2)'!M19)/('Inputs (2)'!L18+'Inputs (2)'!L19)-1),"") | N221: =IFERROR(IF(('Inputs (2)'!I18+'Inputs (2)'!I19)=0,"",('Inputs (2)'!N18+'Inputs (2)'!N19)/('Inputs (2)'!I18+'Inputs (2)'!I19)-1),"") | O221: =IFERROR(IF(('Inputs (2)'!M18+'Inputs (2)'!M19)=0,"",('Inputs (2)'!O18+'Inputs (2)'!O19)/('Inputs (2)'!M18+'Inputs (2)'!M19)-1),"") | P221: =IFERROR(IF(('Inputs (2)'!O18+'Inputs (2)'!O19)=0,"",('Inputs (2)'!P18+'Inputs (2)'!P19)/('Inputs (2)'!O18+'Inputs (2)'!O19)-1),"") | Q221: =IFERROR(IF(('Inputs (2)'!P18+'Inputs (2)'!P19)=0,"",('Inputs (2)'!Q18+'Inputs (2)'!Q19)/('Inputs (2)'!P18+'Inputs (2)'!P19)-1),"") | R221: =IFERROR(IF(('Inputs (2)'!Q18+'Inputs (2)'!Q19)=0,"",('Inputs (2)'!R18+'Inputs (2)'!R19)/('Inputs (2)'!Q18+'Inputs (2)'!Q19)-1),"") | S221: =IFERROR(IF(('Inputs (2)'!N18+'Inputs (2)'!N19)=0,"",('Inputs (2)'!S18+'Inputs (2)'!S19)/('Inputs (2)'!N18+'Inputs (2)'!N19)-1),"") | T221: =IFERROR(IF(('Inputs (2)'!R18+'Inputs (2)'!R19)=0,"",('Inputs (2)'!T18+'Inputs (2)'!T19)/('Inputs (2)'!R18+'Inputs (2)'!R19)-1),"") | U221: =IFERROR(IF(('Inputs (2)'!T18+'Inputs (2)'!T19)=0,"",('Inputs (2)'!U18+'Inputs (2)'!U19)/('Inputs (2)'!T18+'Inputs (2)'!T19)-1),"") | V221: =IFERROR(IF(('Inputs (2)'!U18+'Inputs (2)'!U19)=0,"",('Inputs (2)'!V18+'Inputs (2)'!V19)/('Inputs (2)'!U18+'Inputs (2)'!U19)-1),"") | W221: =IFERROR(IF(('Inputs (2)'!V18+'Inputs (2)'!V19)=0,"",('Inputs (2)'!W18+'Inputs (2)'!W19)/('Inputs (2)'!V18+'Inputs (2)'!V19)-1),"") | X221: =IFERROR(IF(('Inputs (2)'!S18+'Inputs (2)'!S19)=0,"",('Inputs (2)'!X18+'Inputs (2)'!X19)/('Inputs (2)'!S18+'Inputs (2)'!S19)-1),"") | Y221: =IFERROR(IF(('Inputs (2)'!W18+'Inputs (2)'!W19)=0,"",('Inputs (2)'!Y18+'Inputs (2)'!Y19)/('Inputs (2)'!W18+'Inputs (2)'!W19)-1),"") | Z221: =IFERROR(IF(('Inputs (2)'!Y18+'Inputs (2)'!Y19)=0,"",('Inputs (2)'!Z18+'Inputs (2)'!Z19)/('Inputs (2)'!Y18+'Inputs (2)'!Y19)-1),"") | AA221: =IFERROR(IF(('Inputs (2)'!Z18+'Inputs (2)'!Z19)=0,"",('Inputs (2)'!AA18+'Inputs (2)'!AA19)/('Inputs (2)'!Z18+'Inputs (2)'!Z19)-1),"") | AB221: =IFERROR(IF(('Inputs (2)'!AA18+'Inputs (2)'!AA19)=0,"",('Inputs (2)'!AB18+'Inputs (2)'!AB19)/('Inputs (2)'!AA18+'Inputs (2)'!AA19)-1),"") | AC221: =IFERROR(IF(('Inputs (2)'!X18+'Inputs (2)'!X19)=0,"",('Inputs (2)'!AC18+'Inputs (2)'!AC19)/('Inputs (2)'!X18+'Inputs (2)'!X19)-1),"") | AD221: =IFERROR(IF(('Inputs (2)'!AB18+'Inputs (2)'!AB19)=0,"",('Inputs (2)'!AD18+'Inputs (2)'!AD19)/('Inputs (2)'!AB18+'Inputs (2)'!AB19)-1),"") | AE221: =IFERROR(IF(('Inputs (2)'!AD18+'Inputs (2)'!AD19)=0,"",('Inputs (2)'!AE18+'Inputs (2)'!AE19)/('Inputs (2)'!AD18+'Inputs (2)'!AD19)-1),"") | AF221: =IFERROR(IF(('Inputs (2)'!AE18+'Inputs (2)'!AE19)=0,"",('Inputs (2)'!AF18+'Inputs (2)'!AF19)/('Inputs (2)'!AE18+'Inputs (2)'!AE19)-1),"") | AG221: =IFERROR(IF(('Inputs (2)'!AF18+'Inputs (2)'!AF19)=0,"",('Inputs (2)'!AG18+'Inputs (2)'!AG19)/('Inputs (2)'!AF18+'Inputs (2)'!AF19)-1),"") | AH221: =IFERROR(IF(('Inputs (2)'!AC18+'Inputs (2)'!AC19)=0,"",('Inputs (2)'!AH18+'Inputs (2)'!AH19)/('Inputs (2)'!AC18+'Inputs (2)'!AC19)-1),"") | AI221: =IFERROR(IF(('Inputs (2)'!AG18+'Inputs (2)'!AG19)=0,"",('Inputs (2)'!AI18+'Inputs (2)'!AI19)/('Inputs (2)'!AG18+'Inputs (2)'!AG19)-1),"") | AJ221: =IFERROR(IF(('Inputs (2)'!AI18+'Inputs (2)'!AI19)=0,"",('Inputs (2)'!AJ18+'Inputs (2)'!AJ19)/('Inputs (2)'!AI18+'Inputs (2)'!AI19)-1),"") | AK221: =IFERROR(IF(('Inputs (2)'!AJ18+'Inputs (2)'!AJ19)=0,"",('Inputs (2)'!AK18+'Inputs (2)'!AK19)/('Inputs (2)'!AJ18+'Inputs (2)'!AJ19)-1),"") | AL221: =IFERROR(IF(('Inputs (2)'!AK18+'Inputs (2)'!AK19)=0,"",('Inputs (2)'!AL18+'Inputs (2)'!AL19)/('Inputs (2)'!AK18+'Inputs (2)'!AK19)-1),"") | AM221: =IFERROR(IF(('Inputs (2)'!AH18+'Inputs (2)'!AH19)=0,"",('Inputs (2)'!AM18+'Inputs (2)'!AM19)/('Inputs (2)'!AH18+'Inputs (2)'!AH19)-1),"") | AN221: =IFERROR(IF(('Inputs (2)'!AL18+'Inputs (2)'!AL19)=0,"",('Inputs (2)'!AN18+'Inputs (2)'!AN19)/('Inputs (2)'!AL18+'Inputs (2)'!AL19)-1),"") | AO221: =IFERROR(IF(('Inputs (2)'!AN18+'Inputs (2)'!AN19)=0,"",('Inputs (2)'!AO18+'Inputs (2)'!AO19)/('Inputs (2)'!AN18+'Inputs (2)'!AN19)-1),"") | AP221: =IFERROR(IF(('Inputs (2)'!AO18+'Inputs (2)'!AO19)=0,"",('Inputs (2)'!AP18+'Inputs (2)'!AP19)/('Inputs (2)'!AO18+'Inputs (2)'!AO19)-1),"") | AQ221: =IFERROR(IF(('Inputs (2)'!AP18+'Inputs (2)'!AP19)=0,"",('Inputs (2)'!AQ18+'Inputs (2)'!AQ19)/('Inputs (2)'!AP18+'Inputs (2)'!AP19)-1),"") | AR221: =IFERROR(IF(('Inputs (2)'!AM18+'Inputs (2)'!AM19)=0,"",('Inputs (2)'!AR18+'Inputs (2)'!AR19)/('Inputs (2)'!AM18+'Inputs (2)'!AM19)-1),"") | AS221: =IFERROR(IF(('Inputs (2)'!AQ18+'Inputs (2)'!AQ19)=0,"",('Inputs (2)'!AS18+'Inputs (2)'!AS19)/('Inputs (2)'!AQ18+'Inputs (2)'!AQ19)-1),"") | AT221: =IFERROR(IF(('Inputs (2)'!AS18+'Inputs (2)'!AS19)=0,"",('Inputs (2)'!AT18+'Inputs (2)'!AT19)/('Inputs (2)'!AS18+'Inputs (2)'!AS19)-1),"") | AU221: =IFERROR(IF(('Inputs (2)'!AT18+'Inputs (2)'!AT19)=0,"",('Inputs (2)'!AU18+'Inputs (2)'!AU19)/('Inputs (2)'!AT18+'Inputs (2)'!AT19)-1),"") | AV221: =IFERROR(IF(('Inputs (2)'!AU18+'Inputs (2)'!AU19)=0,"",('Inputs (2)'!AV18+'Inputs (2)'!AV19)/('Inputs (2)'!AU18+'Inputs (2)'!AU19)-1),"") | AW221: =IFERROR(IF(('Inputs (2)'!AR18+'Inputs (2)'!AR19)=0,"",('Inputs (2)'!AW18+'Inputs (2)'!AW19)/('Inputs (2)'!AR18+'Inputs (2)'!AR19)-1),"") | AX221: =IFERROR(IF(('Inputs (2)'!AV18+'Inputs (2)'!AV19)=0,"",('Inputs (2)'!AX18+'Inputs (2)'!AX19)/('Inputs (2)'!AV18+'Inputs (2)'!AV19)-1),"") | AY221: =IFERROR(IF(('Inputs (2)'!AX18+'Inputs (2)'!AX19)=0,"",('Inputs (2)'!AY18+'Inputs (2)'!AY19)/('Inputs (2)'!AX18+'Inputs (2)'!AX19)-1),"") | AZ221: =IFERROR(IF(('Inputs (2)'!AY18+'Inputs (2)'!AY19)=0,"",('Inputs (2)'!AZ18+'Inputs (2)'!AZ19)/('Inputs (2)'!AY18+'Inputs (2)'!AY19)-1),"") | BA221: =IFERROR(IF(('Inputs (2)'!AZ18+'Inputs (2)'!AZ19)=0,"",('Inputs (2)'!BA18+'Inputs (2)'!BA19)/('Inputs (2)'!AZ18+'Inputs (2)'!AZ19)-1),"") | BB221: =IFERROR(IF(('Inputs (2)'!AW18+'Inputs (2)'!AW19)=0,"",('Inputs (2)'!BB18+'Inputs (2)'!BB19)/('Inputs (2)'!AW18+'Inputs (2)'!AW19)-1),"") | BC221: =IFERROR(IF(('Inputs (2)'!BA18+'Inputs (2)'!BA19)=0,"",('Inputs (2)'!BC18+'Inputs (2)'!BC19)/('Inputs (2)'!BA18+'Inputs (2)'!BA19)-1),"") | BD221: =IFERROR(IF(('Inputs (2)'!BC18+'Inputs (2)'!BC19)=0,"",('Inputs (2)'!BD18+'Inputs (2)'!BD19)/('Inputs (2)'!BC18+'Inputs (2)'!BC19)-1),"") | BE221: =IFERROR(IF(('Inputs (2)'!BD18+'Inputs (2)'!BD19)=0,"",('Inputs (2)'!BE18+'Inputs (2)'!BE19)/('Inputs (2)'!BD18+'Inputs (2)'!BD19)-1),"") | BF221: =IFERROR(IF(('Inputs (2)'!BE18+'Inputs (2)'!BE19)=0,"",('Inputs (2)'!BF18+'Inputs (2)'!BF19)/('Inputs (2)'!BE18+'Inputs (2)'!BE19)-1),"") | BG221: =IFERROR(IF(('Inputs (2)'!BB18+'Inputs (2)'!BB19)=0,"",('Inputs (2)'!BG18+'Inputs (2)'!BG19)/('Inputs (2)'!BB18+'Inputs (2)'!BB19)-1),"")
C222: Rendimento médio dos empréstimos (% a.a.) | D222: Average loan yield | E222: =IFERROR(IF(OR(('Inputs (2)'!E18+'Inputs (2)'!E19)=0,('Inputs (2)'!E72)=0),"",('Inputs (2)'!E72)*4/('Inputs (2)'!E18+'Inputs (2)'!E19)),"") | F222: =IFERROR(IF(OR(AVERAGE(('Inputs (2)'!E18+'Inputs (2)'!E19),('Inputs (2)'!F18+'Inputs (2)'!F19))=0,('Inputs (2)'!F72)=0),"",('Inputs (2)'!F72)*4/AVERAGE(('Inputs (2)'!E18+'Inputs (2)'!E19),('Inputs (2)'!F18+'Inputs (2)'!F19))),"") | G222: =IFERROR(IF(OR(AVERAGE(('Inputs (2)'!F18+'Inputs (2)'!F19),('Inputs (2)'!G18+'Inputs (2)'!G19))=0,('Inputs (2)'!G72)=0),"",('Inputs (2)'!G72)*4/AVERAGE(('Inputs (2)'!F18+'Inputs (2)'!F19),('Inputs (2)'!G18+'Inputs (2)'!G19))),"") | H222: =IFERROR(IF(OR(AVERAGE(('Inputs (2)'!G18+'Inputs (2)'!G19),('Inputs (2)'!H18+'Inputs (2)'!H19))=0,('Inputs (2)'!H72)=0),"",('Inputs (2)'!H72)*4/AVERAGE(('Inputs (2)'!G18+'Inputs (2)'!G19),('Inputs (2)'!H18+'Inputs (2)'!H19))),"") | I222: =IFERROR(IF(OR(('Inputs (2)'!I18+'Inputs (2)'!I19)=0,('Inputs (2)'!I72)=0),"",('Inputs (2)'!I72)/('Inputs (2)'!I18+'Inputs (2)'!I19)),"") | J222: =IFERROR(IF(OR(AVERAGE(('Inputs (2)'!H18+'Inputs (2)'!H19),('Inputs (2)'!J18+'Inputs (2)'!J19))=0,('Inputs (2)'!J72)=0),"",('Inputs (2)'!J72)*4/AVERAGE(('Inputs (2)'!H18+'Inputs (2)'!H19),('Inputs (2)'!J18+'Inputs (2)'!J19))),"") | K222: =IFERROR(IF(OR(AVERAGE(('Inputs (2)'!J18+'Inputs (2)'!J19),('Inputs (2)'!K18+'Inputs (2)'!K19))=0,('Inputs (2)'!K72)=0),"",('Inputs (2)'!K72)*4/AVERAGE(('Inputs (2)'!J18+'Inputs (2)'!J19),('Inputs (2)'!K18+'Inputs (2)'!K19))),"") | L222: =IFERROR(IF(OR(AVERAGE(('Inputs (2)'!K18+'Inputs (2)'!K19),('Inputs (2)'!L18+'Inputs (2)'!L19))=0,('Inputs (2)'!L72)=0),"",('Inputs (2)'!L72)*4/AVERAGE(('Inputs (2)'!K18+'Inputs (2)'!K19),('Inputs (2)'!L18+'Inputs (2)'!L19))),"") | M222: =IFERROR(IF(OR(AVERAGE(('Inputs (2)'!L18+'Inputs (2)'!L19),('Inputs (2)'!M18+'Inputs (2)'!M19))=0,('Inputs (2)'!M72)=0),"",('Inputs (2)'!M72)*4/AVERAGE(('Inputs (2)'!L18+'Inputs (2)'!L19),('Inputs (2)'!M18+'Inputs (2)'!M19))),"") | N222: =IFERROR(IF(OR(AVERAGE(('Inputs (2)'!I18+'Inputs (2)'!I19),('Inputs (2)'!N18+'Inputs (2)'!N19))=0,('Inputs (2)'!N72)=0),"",('Inputs (2)'!N72)/AVERAGE(('Inputs (2)'!I18+'Inputs (2)'!I19),('Inputs (2)'!N18+'Inputs (2)'!N19))),"") | O222: =IFERROR(IF(OR(AVERAGE(('Inputs (2)'!M18+'Inputs (2)'!M19),('Inputs (2)'!O18+'Inputs (2)'!O19))=0,('Inputs (2)'!O72)=0),"",('Inputs (2)'!O72)*4/AVERAGE(('Inputs (2)'!M18+'Inputs (2)'!M19),('Inputs (2)'!O18+'Inputs (2)'!O19))),"") | P222: =IFERROR(IF(OR(AVERAGE(('Inputs (2)'!O18+'Inputs (2)'!O19),('Inputs (2)'!P18+'Inputs (2)'!P19))=0,('Inputs (2)'!P72)=0),"",('Inputs (2)'!P72)*4/AVERAGE(('Inputs (2)'!O18+'Inputs (2)'!O19),('Inputs (2)'!P18+'Inputs (2)'!P19))),"") | Q222: =IFERROR(IF(OR(AVERAGE(('Inputs (2)'!P18+'Inputs (2)'!P19),('Inputs (2)'!Q18+'Inputs (2)'!Q19))=0,('Inputs (2)'!Q72)=0),"",('Inputs (2)'!Q72)*4/AVERAGE(('Inputs (2)'!P18+'Inputs (2)'!P19),('Inputs (2)'!Q18+'Inputs (2)'!Q19))),"") | R222: =IFERROR(IF(OR(AVERAGE(('Inputs (2)'!Q18+'Inputs (2)'!Q19),('Inputs (2)'!R18+'Inputs (2)'!R19))=0,('Inputs (2)'!R72)=0),"",('Inputs (2)'!R72)*4/AVERAGE(('Inputs (2)'!Q18+'Inputs (2)'!Q19),('Inputs (2)'!R18+'Inputs (2)'!R19))),"") | S222: =IFERROR(IF(OR(AVERAGE(('Inputs (2)'!N18+'Inputs (2)'!N19),('Inputs (2)'!S18+'Inputs (2)'!S19))=0,('Inputs (2)'!S72)=0),"",('Inputs (2)'!S72)/AVERAGE(('Inputs (2)'!N18+'Inputs (2)'!N19),('Inputs (2)'!S18+'Inputs (2)'!S19))),"") | T222: =IFERROR(IF(OR(AVERAGE(('Inputs (2)'!R18+'Inputs (2)'!R19),('Inputs (2)'!T18+'Inputs (2)'!T19))=0,('Inputs (2)'!T72)=0),"",('Inputs (2)'!T72)*4/AVERAGE(('Inputs (2)'!R18+'Inputs (2)'!R19),('Inputs (2)'!T18+'Inputs (2)'!T19))),"") | U222: =IFERROR(IF(OR(AVERAGE(('Inputs (2)'!T18+'Inputs (2)'!T19),('Inputs (2)'!U18+'Inputs (2)'!U19))=0,('Inputs (2)'!U72)=0),"",('Inputs (2)'!U72)*4/AVERAGE(('Inputs (2)'!T18+'Inputs (2)'!T19),('Inputs (2)'!U18+'Inputs (2)'!U19))),"") | V222: =IFERROR(IF(OR(AVERAGE(('Inputs (2)'!U18+'Inputs (2)'!U19),('Inputs (2)'!V18+'Inputs (2)'!V19))=0,('Inputs (2)'!V72)=0),"",('Inputs (2)'!V72)*4/AVERAGE(('Inputs (2)'!U18+'Inputs (2)'!U19),('Inputs (2)'!V18+'Inputs (2)'!V19))),"") | W222: =IFERROR(IF(OR(AVERAGE(('Inputs (2)'!V18+'Inputs (2)'!V19),('Inputs (2)'!W18+'Inputs (2)'!W19))=0,('Inputs (2)'!W72)=0),"",('Inputs (2)'!W72)*4/AVERAGE(('Inputs (2)'!V18+'Inputs (2)'!V19),('Inputs (2)'!W18+'Inputs (2)'!W19))),"") | X222: =IFERROR(IF(OR(AVERAGE(('Inputs (2)'!S18+'Inputs (2)'!S19),('Inputs (2)'!X18+'Inputs (2)'!X19))=0,('Inputs (2)'!X72)=0),"",('Inputs (2)'!X72)/AVERAGE(('Inputs (2)'!S18+'Inputs (2)'!S19),('Inputs (2)'!X18+'Inputs (2)'!X19))),"") | Y222: =IFERROR(IF(OR(AVERAGE(('Inputs (2)'!W18+'Inputs (2)'!W19),('Inputs (2)'!Y18+'Inputs (2)'!Y19))=0,('Inputs (2)'!Y72)=0),"",('Inputs (2)'!Y72)*4/AVERAGE(('Inputs (2)'!W18+'Inputs (2)'!W19),('Inputs (2)'!Y18+'Inputs (2)'!Y19))),"") | Z222: =IFERROR(IF(OR(AVERAGE(('Inputs (2)'!Y18+'Inputs (2)'!Y19),('Inputs (2)'!Z18+'Inputs (2)'!Z19))=0,('Inputs (2)'!Z72)=0),"",('Inputs (2)'!Z72)*4/AVERAGE(('Inputs (2)'!Y18+'Inputs (2)'!Y19),('Inputs (2)'!Z18+'Inputs (2)'!Z19))),"") | AA222: =IFERROR(IF(OR(AVERAGE(('Inputs (2)'!Z18+'Inputs (2)'!Z19),('Inputs (2)'!AA18+'Inputs (2)'!AA19))=0,('Inputs (2)'!AA72)=0),"",('Inputs (2)'!AA72)*4/AVERAGE(('Inputs (2)'!Z18+'Inputs (2)'!Z19),('Inputs (2)'!AA18+'Inputs (2)'!AA19))),"") | AB222: =IFERROR(IF(OR(AVERAGE(('Inputs (2)'!AA18+'Inputs (2)'!AA19),('Inputs (2)'!AB18+'Inputs (2)'!AB19))=0,('Inputs (2)'!AB72)=0),"",('Inputs (2)'!AB72)*4/AVERAGE(('Inputs (2)'!AA18+'Inputs (2)'!AA19),('Inputs (2)'!AB18+'Inputs (2)'!AB19))),"") | AC222: =IFERROR(IF(OR(AVERAGE(('Inputs (2)'!X18+'Inputs (2)'!X19),('Inputs (2)'!AC18+'Inputs (2)'!AC19))=0,('Inputs (2)'!AC72)=0),"",('Inputs (2)'!AC72)/AVERAGE(('Inputs (2)'!X18+'Inputs (2)'!X19),('Inputs (2)'!AC18+'Inputs (2)'!AC19))),"") | AD222: =IFERROR(IF(OR(AVERAGE(('Inputs (2)'!AB18+'Inputs (2)'!AB19),('Inputs (2)'!AD18+'Inputs (2)'!AD19))=0,('Inputs (2)'!AD72)=0),"",('Inputs (2)'!AD72)*4/AVERAGE(('Inputs (2)'!AB18+'Inputs (2)'!AB19),('Inputs (2)'!AD18+'Inputs (2)'!AD19))),"") | AE222: =IFERROR(IF(OR(AVERAGE(('Inputs (2)'!AD18+'Inputs (2)'!AD19),('Inputs (2)'!AE18+'Inputs (2)'!AE19))=0,('Inputs (2)'!AE72)=0),"",('Inputs (2)'!AE72)*4/AVERAGE(('Inputs (2)'!AD18+'Inputs (2)'!AD19),('Inputs (2)'!AE18+'Inputs (2)'!AE19))),"") | AF222: =IFERROR(IF(OR(AVERAGE(('Inputs (2)'!AE18+'Inputs (2)'!AE19),('Inputs (2)'!AF18+'Inputs (2)'!AF19))=0,('Inputs (2)'!AF72)=0),"",('Inputs (2)'!AF72)*4/AVERAGE(('Inputs (2)'!AE18+'Inputs (2)'!AE19),('Inputs (2)'!AF18+'Inputs (2)'!AF19))),"") | AG222: =IFERROR(IF(OR(AVERAGE(('Inputs (2)'!AF18+'Inputs (2)'!AF19),('Inputs (2)'!AG18+'Inputs (2)'!AG19))=0,('Inputs (2)'!AG72)=0),"",('Inputs (2)'!AG72)*4/AVERAGE(('Inputs (2)'!AF18+'Inputs (2)'!AF19),('Inputs (2)'!AG18+'Inputs (2)'!AG19))),"") | AH222: =IFERROR(IF(OR(AVERAGE(('Inputs (2)'!AC18+'Inputs (2)'!AC19),('Inputs (2)'!AH18+'Inputs (2)'!AH19))=0,('Inputs (2)'!AH72)=0),"",('Inputs (2)'!AH72)/AVERAGE(('Inputs (2)'!AC18+'Inputs (2)'!AC19),('Inputs (2)'!AH18+'Inputs (2)'!AH19))),"") | AI222: =IFERROR(IF(OR(AVERAGE(('Inputs (2)'!AG18+'Inputs (2)'!AG19),('Inputs (2)'!AI18+'Inputs (2)'!AI19))=0,('Inputs (2)'!AI72)=0),"",('Inputs (2)'!AI72)*4/AVERAGE(('Inputs (2)'!AG18+'Inputs (2)'!AG19),('Inputs (2)'!AI18+'Inputs (2)'!AI19))),"") | AJ222: =IFERROR(IF(OR(AVERAGE(('Inputs (2)'!AI18+'Inputs (2)'!AI19),('Inputs (2)'!AJ18+'Inputs (2)'!AJ19))=0,('Inputs (2)'!AJ72)=0),"",('Inputs (2)'!AJ72)*4/AVERAGE(('Inputs (2)'!AI18+'Inputs (2)'!AI19),('Inputs (2)'!AJ18+'Inputs (2)'!AJ19))),"") | AK222: =IFERROR(IF(OR(AVERAGE(('Inputs (2)'!AJ18+'Inputs (2)'!AJ19),('Inputs (2)'!AK18+'Inputs (2)'!AK19))=0,('Inputs (2)'!AK72)=0),"",('Inputs (2)'!AK72)*4/AVERAGE(('Inputs (2)'!AJ18+'Inputs (2)'!AJ19),('Inputs (2)'!AK18+'Inputs (2)'!AK19))),"") | AL222: =IFERROR(IF(OR(AVERAGE(('Inputs (2)'!AK18+'Inputs (2)'!AK19),('Inputs (2)'!AL18+'Inputs (2)'!AL19))=0,('Inputs (2)'!AL72)=0),"",('Inputs (2)'!AL72)*4/AVERAGE(('Inputs (2)'!AK18+'Inputs (2)'!AK19),('Inputs (2)'!AL18+'Inputs (2)'!AL19))),"") | AM222: =IFERROR(IF(OR(AVERAGE(('Inputs (2)'!AH18+'Inputs (2)'!AH19),('Inputs (2)'!AM18+'Inputs (2)'!AM19))=0,('Inputs (2)'!AM72)=0),"",('Inputs (2)'!AM72)/AVERAGE(('Inputs (2)'!AH18+'Inputs (2)'!AH19),('Inputs (2)'!AM18+'Inputs (2)'!AM19))),"") | AN222: =IFERROR(IF(OR(AVERAGE(('Inputs (2)'!AL18+'Inputs (2)'!AL19),('Inputs (2)'!AN18+'Inputs (2)'!AN19))=0,('Inputs (2)'!AN72)=0),"",('Inputs (2)'!AN72)*4/AVERAGE(('Inputs (2)'!AL18+'Inputs (2)'!AL19),('Inputs (2)'!AN18+'Inputs (2)'!AN19))),"") | AO222: =IFERROR(IF(OR(AVERAGE(('Inputs (2)'!AN18+'Inputs (2)'!AN19),('Inputs (2)'!AO18+'Inputs (2)'!AO19))=0,('Inputs (2)'!AO72)=0),"",('Inputs (2)'!AO72)*4/AVERAGE(('Inputs (2)'!AN18+'Inputs (2)'!AN19),('Inputs (2)'!AO18+'Inputs (2)'!AO19))),"") | AP222: =IFERROR(IF(OR(AVERAGE(('Inputs (2)'!AO18+'Inputs (2)'!AO19),('Inputs (2)'!AP18+'Inputs (2)'!AP19))=0,('Inputs (2)'!AP72)=0),"",('Inputs (2)'!AP72)*4/AVERAGE(('Inputs (2)'!AO18+'Inputs (2)'!AO19),('Inputs (2)'!AP18+'Inputs (2)'!AP19))),"") | AQ222: =IFERROR(IF(OR(AVERAGE(('Inputs (2)'!AP18+'Inputs (2)'!AP19),('Inputs (2)'!AQ18+'Inputs (2)'!AQ19))=0,('Inputs (2)'!AQ72)=0),"",('Inputs (2)'!AQ72)*4/AVERAGE(('Inputs (2)'!AP18+'Inputs (2)'!AP19),('Inputs (2)'!AQ18+'Inputs (2)'!AQ19))),"") | AR222: =IFERROR(IF(OR(AVERAGE(('Inputs (2)'!AM18+'Inputs (2)'!AM19),('Inputs (2)'!AR18+'Inputs (2)'!AR19))=0,('Inputs (2)'!AR72)=0),"",('Inputs (2)'!AR72)/AVERAGE(('Inputs (2)'!AM18+'Inputs (2)'!AM19),('Inputs (2)'!AR18+'Inputs (2)'!AR19))),"") | AS222: =IFERROR(IF(OR(AVERAGE(('Inputs (2)'!AQ18+'Inputs (2)'!AQ19),('Inputs (2)'!AS18+'Inputs (2)'!AS19))=0,('Inputs (2)'!AS72)=0),"",('Inputs (2)'!AS72)*4/AVERAGE(('Inputs (2)'!AQ18+'Inputs (2)'!AQ19),('Inputs (2)'!AS18+'Inputs (2)'!AS19))),"") | AT222: =IFERROR(IF(OR(AVERAGE(('Inputs (2)'!AS18+'Inputs (2)'!AS19),('Inputs (2)'!AT18+'Inputs (2)'!AT19))=0,('Inputs (2)'!AT72)=0),"",('Inputs (2)'!AT72)*4/AVERAGE(('Inputs (2)'!AS18+'Inputs (2)'!AS19),('Inputs (2)'!AT18+'Inputs (2)'!AT19))),"") | AU222: =IFERROR(IF(OR(AVERAGE(('Inputs (2)'!AT18+'Inputs (2)'!AT19),('Inputs (2)'!AU18+'Inputs (2)'!AU19))=0,('Inputs (2)'!AU72)=0),"",('Inputs (2)'!AU72)*4/AVERAGE(('Inputs (2)'!AT18+'Inputs (2)'!AT19),('Inputs (2)'!AU18+'Inputs (2)'!AU19))),"") | AV222: =IFERROR(IF(OR(AVERAGE(('Inputs (2)'!AU18+'Inputs (2)'!AU19),('Inputs (2)'!AV18+'Inputs (2)'!AV19))=0,('Inputs (2)'!AV72)=0),"",('Inputs (2)'!AV72)*4/AVERAGE(('Inputs (2)'!AU18+'Inputs (2)'!AU19),('Inputs (2)'!AV18+'Inputs (2)'!AV19))),"") | AW222: =IFERROR(IF(OR(AVERAGE(('Inputs (2)'!AR18+'Inputs (2)'!AR19),('Inputs (2)'!AW18+'Inputs (2)'!AW19))=0,('Inputs (2)'!AW72)=0),"",('Inputs (2)'!AW72)/AVERAGE(('Inputs (2)'!AR18+'Inputs (2)'!AR19),('Inputs (2)'!AW18+'Inputs (2)'!AW19))),"") | AX222: =IFERROR(IF(OR(AVERAGE(('Inputs (2)'!AV18+'Inputs (2)'!AV19),('Inputs (2)'!AX18+'Inputs (2)'!AX19))=0,('Inputs (2)'!AX72)=0),"",('Inputs (2)'!AX72)*4/AVERAGE(('Inputs (2)'!AV18+'Inputs (2)'!AV19),('Inputs (2)'!AX18+'Inputs (2)'!AX19))),"") | AY222: =IFERROR(IF(OR(AVERAGE(('Inputs (2)'!AX18+'Inputs (2)'!AX19),('Inputs (2)'!AY18+'Inputs (2)'!AY19))=0,('Inputs (2)'!AY72)=0),"",('Inputs (2)'!AY72)*4/AVERAGE(('Inputs (2)'!AX18+'Inputs (2)'!AX19),('Inputs (2)'!AY18+'Inputs (2)'!AY19))),"") | AZ222: =IFERROR(IF(OR(AVERAGE(('Inputs (2)'!AY18+'Inputs (2)'!AY19),('Inputs (2)'!AZ18+'Inputs (2)'!AZ19))=0,('Inputs (2)'!AZ72)=0),"",('Inputs (2)'!AZ72)*4/AVERAGE(('Inputs (2)'!AY18+'Inputs (2)'!AY19),('Inputs (2)'!AZ18+'Inputs (2)'!AZ19))),"") | BA222: =IFERROR(IF(OR(AVERAGE(('Inputs (2)'!AZ18+'Inputs (2)'!AZ19),('Inputs (2)'!BA18+'Inputs (2)'!BA19))=0,('Inputs (2)'!BA72)=0),"",('Inputs (2)'!BA72)*4/AVERAGE(('Inputs (2)'!AZ18+'Inputs (2)'!AZ19),('Inputs (2)'!BA18+'Inputs (2)'!BA19))),"") | BB222: =IFERROR(IF(OR(AVERAGE(('Inputs (2)'!AW18+'Inputs (2)'!AW19),('Inputs (2)'!BB18+'Inputs (2)'!BB19))=0,('Inputs (2)'!BB72)=0),"",('Inputs (2)'!BB72)/AVERAGE(('Inputs (2)'!AW18+'Inputs (2)'!AW19),('Inputs (2)'!BB18+'Inputs (2)'!BB19))),"") | BC222: =IFERROR(IF(OR(AVERAGE(('Inputs (2)'!BA18+'Inputs (2)'!BA19),('Inputs (2)'!BC18+'Inputs (2)'!BC19))=0,('Inputs (2)'!BC72)=0),"",('Inputs (2)'!BC72)*4/AVERAGE(('Inputs (2)'!BA18+'Inputs (2)'!BA19),('Inputs (2)'!BC18+'Inputs (2)'!BC19))),"") | BD222: =IFERROR(IF(OR(AVERAGE(('Inputs (2)'!BC18+'Inputs (2)'!BC19),('Inputs (2)'!BD18+'Inputs (2)'!BD19))=0,('Inputs (2)'!BD72)=0),"",('Inputs (2)'!BD72)*4/AVERAGE(('Inputs (2)'!BC18+'Inputs (2)'!BC19),('Inputs (2)'!BD18+'Inputs (2)'!BD19))),"") | BE222: =IFERROR(IF(OR(AVERAGE(('Inputs (2)'!BD18+'Inputs (2)'!BD19),('Inputs (2)'!BE18+'Inputs (2)'!BE19))=0,('Inputs (2)'!BE72)=0),"",('Inputs (2)'!BE72)*4/AVERAGE(('Inputs (2)'!BD18+'Inputs (2)'!BD19),('Inputs (2)'!BE18+'Inputs (2)'!BE19))),"") | BF222: =IFERROR(IF(OR(AVERAGE(('Inputs (2)'!BE18+'Inputs (2)'!BE19),('Inputs (2)'!BF18+'Inputs (2)'!BF19))=0,('Inputs (2)'!BF72)=0),"",('Inputs (2)'!BF72)*4/AVERAGE(('Inputs (2)'!BE18+'Inputs (2)'!BE19),('Inputs (2)'!BF18+'Inputs (2)'!BF19))),"") | BG222: =IFERROR(IF(OR(AVERAGE(('Inputs (2)'!BB18+'Inputs (2)'!BB19),('Inputs (2)'!BG18+'Inputs (2)'!BG19))=0,('Inputs (2)'!BG72)=0),"",('Inputs (2)'!BG72)/AVERAGE(('Inputs (2)'!BB18+'Inputs (2)'!BB19),('Inputs (2)'!BG18+'Inputs (2)'!BG19))),"")
C223: Custo do crédito (% da carteira média, a.a.) | D223: Cost of risk | E223: =IFERROR(IF(OR(ABS(('Inputs (2)'!E18+'Inputs (2)'!E19))=0,('Inputs (2)'!E83)=0),"",ABS('Inputs (2)'!E83)*4/ABS(('Inputs (2)'!E18+'Inputs (2)'!E19))),"") | F223: =IFERROR(IF(OR(ABS(AVERAGE(('Inputs (2)'!E18+'Inputs (2)'!E19),('Inputs (2)'!F18+'Inputs (2)'!F19)))=0,('Inputs (2)'!F83)=0),"",ABS('Inputs (2)'!F83)*4/ABS(AVERAGE(('Inputs (2)'!E18+'Inputs (2)'!E19),('Inputs (2)'!F18+'Inputs (2)'!F19)))),"") | G223: =IFERROR(IF(OR(ABS(AVERAGE(('Inputs (2)'!F18+'Inputs (2)'!F19),('Inputs (2)'!G18+'Inputs (2)'!G19)))=0,('Inputs (2)'!G83)=0),"",ABS('Inputs (2)'!G83)*4/ABS(AVERAGE(('Inputs (2)'!F18+'Inputs (2)'!F19),('Inputs (2)'!G18+'Inputs (2)'!G19)))),"") | H223: =IFERROR(IF(OR(ABS(AVERAGE(('Inputs (2)'!G18+'Inputs (2)'!G19),('Inputs (2)'!H18+'Inputs (2)'!H19)))=0,('Inputs (2)'!H83)=0),"",ABS('Inputs (2)'!H83)*4/ABS(AVERAGE(('Inputs (2)'!G18+'Inputs (2)'!G19),('Inputs (2)'!H18+'Inputs (2)'!H19)))),"") | I223: =IFERROR(IF(OR(ABS(('Inputs (2)'!I18+'Inputs (2)'!I19))=0,('Inputs (2)'!I83)=0),"",ABS('Inputs (2)'!I83)/ABS(('Inputs (2)'!I18+'Inputs (2)'!I19))),"") | J223: =IFERROR(IF(OR(ABS(AVERAGE(('Inputs (2)'!H18+'Inputs (2)'!H19),('Inputs (2)'!J18+'Inputs (2)'!J19)))=0,('Inputs (2)'!J83)=0),"",ABS('Inputs (2)'!J83)*4/ABS(AVERAGE(('Inputs (2)'!H18+'Inputs (2)'!H19),('Inputs (2)'!J18+'Inputs (2)'!J19)))),"") | K223: =IFERROR(IF(OR(ABS(AVERAGE(('Inputs (2)'!J18+'Inputs (2)'!J19),('Inputs (2)'!K18+'Inputs (2)'!K19)))=0,('Inputs (2)'!K83)=0),"",ABS('Inputs (2)'!K83)*4/ABS(AVERAGE(('Inputs (2)'!J18+'Inputs (2)'!J19),('Inputs (2)'!K18+'Inputs (2)'!K19)))),"") | L223: =IFERROR(IF(OR(ABS(AVERAGE(('Inputs (2)'!K18+'Inputs (2)'!K19),('Inputs (2)'!L18+'Inputs (2)'!L19)))=0,('Inputs (2)'!L83)=0),"",ABS('Inputs (2)'!L83)*4/ABS(AVERAGE(('Inputs (2)'!K18+'Inputs (2)'!K19),('Inputs (2)'!L18+'Inputs (2)'!L19)))),"") | M223: =IFERROR(IF(OR(ABS(AVERAGE(('Inputs (2)'!L18+'Inputs (2)'!L19),('Inputs (2)'!M18+'Inputs (2)'!M19)))=0,('Inputs (2)'!M83)=0),"",ABS('Inputs (2)'!M83)*4/ABS(AVERAGE(('Inputs (2)'!L18+'Inputs (2)'!L19),('Inputs (2)'!M18+'Inputs (2)'!M19)))),"") | N223: =IFERROR(IF(OR(ABS(AVERAGE(('Inputs (2)'!I18+'Inputs (2)'!I19),('Inputs (2)'!N18+'Inputs (2)'!N19)))=0,('Inputs (2)'!N83)=0),"",ABS('Inputs (2)'!N83)/ABS(AVERAGE(('Inputs (2)'!I18+'Inputs (2)'!I19),('Inputs (2)'!N18+'Inputs (2)'!N19)))),"") | O223: =IFERROR(IF(OR(ABS(AVERAGE(('Inputs (2)'!M18+'Inputs (2)'!M19),('Inputs (2)'!O18+'Inputs (2)'!O19)))=0,('Inputs (2)'!O83)=0),"",ABS('Inputs (2)'!O83)*4/ABS(AVERAGE(('Inputs (2)'!M18+'Inputs (2)'!M19),('Inputs (2)'!O18+'Inputs (2)'!O19)))),"") | P223: =IFERROR(IF(OR(ABS(AVERAGE(('Inputs (2)'!O18+'Inputs (2)'!O19),('Inputs (2)'!P18+'Inputs (2)'!P19)))=0,('Inputs (2)'!P83)=0),"",ABS('Inputs (2)'!P83)*4/ABS(AVERAGE(('Inputs (2)'!O18+'Inputs (2)'!O19),('Inputs (2)'!P18+'Inputs (2)'!P19)))),"") | Q223: =IFERROR(IF(OR(ABS(AVERAGE(('Inputs (2)'!P18+'Inputs (2)'!P19),('Inputs (2)'!Q18+'Inputs (2)'!Q19)))=0,('Inputs (2)'!Q83)=0),"",ABS('Inputs (2)'!Q83)*4/ABS(AVERAGE(('Inputs (2)'!P18+'Inputs (2)'!P19),('Inputs (2)'!Q18+'Inputs (2)'!Q19)))),"") | R223: =IFERROR(IF(OR(ABS(AVERAGE(('Inputs (2)'!Q18+'Inputs (2)'!Q19),('Inputs (2)'!R18+'Inputs (2)'!R19)))=0,('Inputs (2)'!R83)=0),"",ABS('Inputs (2)'!R83)*4/ABS(AVERAGE(('Inputs (2)'!Q18+'Inputs (2)'!Q19),('Inputs (2)'!R18+'Inputs (2)'!R19)))),"") | S223: =IFERROR(IF(OR(ABS(AVERAGE(('Inputs (2)'!N18+'Inputs (2)'!N19),('Inputs (2)'!S18+'Inputs (2)'!S19)))=0,('Inputs (2)'!S83)=0),"",ABS('Inputs (2)'!S83)/ABS(AVERAGE(('Inputs (2)'!N18+'Inputs (2)'!N19),('Inputs (2)'!S18+'Inputs (2)'!S19)))),"") | T223: =IFERROR(IF(OR(ABS(AVERAGE(('Inputs (2)'!R18+'Inputs (2)'!R19),('Inputs (2)'!T18+'Inputs (2)'!T19)))=0,('Inputs (2)'!T83)=0),"",ABS('Inputs (2)'!T83)*4/ABS(AVERAGE(('Inputs (2)'!R18+'Inputs (2)'!R19),('Inputs (2)'!T18+'Inputs (2)'!T19)))),"") | U223: =IFERROR(IF(OR(ABS(AVERAGE(('Inputs (2)'!T18+'Inputs (2)'!T19),('Inputs (2)'!U18+'Inputs (2)'!U19)))=0,('Inputs (2)'!U83)=0),"",ABS('Inputs (2)'!U83)*4/ABS(AVERAGE(('Inputs (2)'!T18+'Inputs (2)'!T19),('Inputs (2)'!U18+'Inputs (2)'!U19)))),"") | V223: =IFERROR(IF(OR(ABS(AVERAGE(('Inputs (2)'!U18+'Inputs (2)'!U19),('Inputs (2)'!V18+'Inputs (2)'!V19)))=0,('Inputs (2)'!V83)=0),"",ABS('Inputs (2)'!V83)*4/ABS(AVERAGE(('Inputs (2)'!U18+'Inputs (2)'!U19),('Inputs (2)'!V18+'Inputs (2)'!V19)))),"") | W223: =IFERROR(IF(OR(ABS(AVERAGE(('Inputs (2)'!V18+'Inputs (2)'!V19),('Inputs (2)'!W18+'Inputs (2)'!W19)))=0,('Inputs (2)'!W83)=0),"",ABS('Inputs (2)'!W83)*4/ABS(AVERAGE(('Inputs (2)'!V18+'Inputs (2)'!V19),('Inputs (2)'!W18+'Inputs (2)'!W19)))),"") | X223: =IFERROR(IF(OR(ABS(AVERAGE(('Inputs (2)'!S18+'Inputs (2)'!S19),('Inputs (2)'!X18+'Inputs (2)'!X19)))=0,('Inputs (2)'!X83)=0),"",ABS('Inputs (2)'!X83)/ABS(AVERAGE(('Inputs (2)'!S18+'Inputs (2)'!S19),('Inputs (2)'!X18+'Inputs (2)'!X19)))),"") | Y223: =IFERROR(IF(OR(ABS(AVERAGE(('Inputs (2)'!W18+'Inputs (2)'!W19),('Inputs (2)'!Y18+'Inputs (2)'!Y19)))=0,('Inputs (2)'!Y83)=0),"",ABS('Inputs (2)'!Y83)*4/ABS(AVERAGE(('Inputs (2)'!W18+'Inputs (2)'!W19),('Inputs (2)'!Y18+'Inputs (2)'!Y19)))),"") | Z223: =IFERROR(IF(OR(ABS(AVERAGE(('Inputs (2)'!Y18+'Inputs (2)'!Y19),('Inputs (2)'!Z18+'Inputs (2)'!Z19)))=0,('Inputs (2)'!Z83)=0),"",ABS('Inputs (2)'!Z83)*4/ABS(AVERAGE(('Inputs (2)'!Y18+'Inputs (2)'!Y19),('Inputs (2)'!Z18+'Inputs (2)'!Z19)))),"") | AA223: =IFERROR(IF(OR(ABS(AVERAGE(('Inputs (2)'!Z18+'Inputs (2)'!Z19),('Inputs (2)'!AA18+'Inputs (2)'!AA19)))=0,('Inputs (2)'!AA83)=0),"",ABS('Inputs (2)'!AA83)*4/ABS(AVERAGE(('Inputs (2)'!Z18+'Inputs (2)'!Z19),('Inputs (2)'!AA18+'Inputs (2)'!AA19)))),"") | AB223: =IFERROR(IF(OR(ABS(AVERAGE(('Inputs (2)'!AA18+'Inputs (2)'!AA19),('Inputs (2)'!AB18+'Inputs (2)'!AB19)))=0,('Inputs (2)'!AB83)=0),"",ABS('Inputs (2)'!AB83)*4/ABS(AVERAGE(('Inputs (2)'!AA18+'Inputs (2)'!AA19),('Inputs (2)'!AB18+'Inputs (2)'!AB19)))),"") | AC223: =IFERROR(IF(OR(ABS(AVERAGE(('Inputs (2)'!X18+'Inputs (2)'!X19),('Inputs (2)'!AC18+'Inputs (2)'!AC19)))=0,('Inputs (2)'!AC83)=0),"",ABS('Inputs (2)'!AC83)/ABS(AVERAGE(('Inputs (2)'!X18+'Inputs (2)'!X19),('Inputs (2)'!AC18+'Inputs (2)'!AC19)))),"") | AD223: =IFERROR(IF(OR(ABS(AVERAGE(('Inputs (2)'!AB18+'Inputs (2)'!AB19),('Inputs (2)'!AD18+'Inputs (2)'!AD19)))=0,('Inputs (2)'!AD83)=0),"",ABS('Inputs (2)'!AD83)*4/ABS(AVERAGE(('Inputs (2)'!AB18+'Inputs (2)'!AB19),('Inputs (2)'!AD18+'Inputs (2)'!AD19)))),"") | AE223: =IFERROR(IF(OR(ABS(AVERAGE(('Inputs (2)'!AD18+'Inputs (2)'!AD19),('Inputs (2)'!AE18+'Inputs (2)'!AE19)))=0,('Inputs (2)'!AE83)=0),"",ABS('Inputs (2)'!AE83)*4/ABS(AVERAGE(('Inputs (2)'!AD18+'Inputs (2)'!AD19),('Inputs (2)'!AE18+'Inputs (2)'!AE19)))),"") | AF223: =IFERROR(IF(OR(ABS(AVERAGE(('Inputs (2)'!AE18+'Inputs (2)'!AE19),('Inputs (2)'!AF18+'Inputs (2)'!AF19)))=0,('Inputs (2)'!AF83)=0),"",ABS('Inputs (2)'!AF83)*4/ABS(AVERAGE(('Inputs (2)'!AE18+'Inputs (2)'!AE19),('Inputs (2)'!AF18+'Inputs (2)'!AF19)))),"") | AG223: =IFERROR(IF(OR(ABS(AVERAGE(('Inputs (2)'!AF18+'Inputs (2)'!AF19),('Inputs (2)'!AG18+'Inputs (2)'!AG19)))=0,('Inputs (2)'!AG83)=0),"",ABS('Inputs (2)'!AG83)*4/ABS(AVERAGE(('Inputs (2)'!AF18+'Inputs (2)'!AF19),('Inputs (2)'!AG18+'Inputs (2)'!AG19)))),"") | AH223: =IFERROR(IF(OR(ABS(AVERAGE(('Inputs (2)'!AC18+'Inputs (2)'!AC19),('Inputs (2)'!AH18+'Inputs (2)'!AH19)))=0,('Inputs (2)'!AH83)=0),"",ABS('Inputs (2)'!AH83)/ABS(AVERAGE(('Inputs (2)'!AC18+'Inputs (2)'!AC19),('Inputs (2)'!AH18+'Inputs (2)'!AH19)))),"") | AI223: =IFERROR(IF(OR(ABS(AVERAGE(('Inputs (2)'!AG18+'Inputs (2)'!AG19),('Inputs (2)'!AI18+'Inputs (2)'!AI19)))=0,('Inputs (2)'!AI83)=0),"",ABS('Inputs (2)'!AI83)*4/ABS(AVERAGE(('Inputs (2)'!AG18+'Inputs (2)'!AG19),('Inputs (2)'!AI18+'Inputs (2)'!AI19)))),"") | AJ223: =IFERROR(IF(OR(ABS(AVERAGE(('Inputs (2)'!AI18+'Inputs (2)'!AI19),('Inputs (2)'!AJ18+'Inputs (2)'!AJ19)))=0,('Inputs (2)'!AJ83)=0),"",ABS('Inputs (2)'!AJ83)*4/ABS(AVERAGE(('Inputs (2)'!AI18+'Inputs (2)'!AI19),('Inputs (2)'!AJ18+'Inputs (2)'!AJ19)))),"") | AK223: =IFERROR(IF(OR(ABS(AVERAGE(('Inputs (2)'!AJ18+'Inputs (2)'!AJ19),('Inputs (2)'!AK18+'Inputs (2)'!AK19)))=0,('Inputs (2)'!AK83)=0),"",ABS('Inputs (2)'!AK83)*4/ABS(AVERAGE(('Inputs (2)'!AJ18+'Inputs (2)'!AJ19),('Inputs (2)'!AK18+'Inputs (2)'!AK19)))),"") | AL223: =IFERROR(IF(OR(ABS(AVERAGE(('Inputs (2)'!AK18+'Inputs (2)'!AK19),('Inputs (2)'!AL18+'Inputs (2)'!AL19)))=0,('Inputs (2)'!AL83)=0),"",ABS('Inputs (2)'!AL83)*4/ABS(AVERAGE(('Inputs (2)'!AK18+'Inputs (2)'!AK19),('Inputs (2)'!AL18+'Inputs (2)'!AL19)))),"") | AM223: =IFERROR(IF(OR(ABS(AVERAGE(('Inputs (2)'!AH18+'Inputs (2)'!AH19),('Inputs (2)'!AM18+'Inputs (2)'!AM19)))=0,('Inputs (2)'!AM83)=0),"",ABS('Inputs (2)'!AM83)/ABS(AVERAGE(('Inputs (2)'!AH18+'Inputs (2)'!AH19),('Inputs (2)'!AM18+'Inputs (2)'!AM19)))),"") | AN223: =IFERROR(IF(OR(ABS(AVERAGE(('Inputs (2)'!AL18+'Inputs (2)'!AL19),('Inputs (2)'!AN18+'Inputs (2)'!AN19)))=0,('Inputs (2)'!AN83)=0),"",ABS('Inputs (2)'!AN83)*4/ABS(AVERAGE(('Inputs (2)'!AL18+'Inputs (2)'!AL19),('Inputs (2)'!AN18+'Inputs (2)'!AN19)))),"") | AO223: =IFERROR(IF(OR(ABS(AVERAGE(('Inputs (2)'!AN18+'Inputs (2)'!AN19),('Inputs (2)'!AO18+'Inputs (2)'!AO19)))=0,('Inputs (2)'!AO83)=0),"",ABS('Inputs (2)'!AO83)*4/ABS(AVERAGE(('Inputs (2)'!AN18+'Inputs (2)'!AN19),('Inputs (2)'!AO18+'Inputs (2)'!AO19)))),"") | AP223: =IFERROR(IF(OR(ABS(AVERAGE(('Inputs (2)'!AO18+'Inputs (2)'!AO19),('Inputs (2)'!AP18+'Inputs (2)'!AP19)))=0,('Inputs (2)'!AP83)=0),"",ABS('Inputs (2)'!AP83)*4/ABS(AVERAGE(('Inputs (2)'!AO18+'Inputs (2)'!AO19),('Inputs (2)'!AP18+'Inputs (2)'!AP19)))),"") | AQ223: =IFERROR(IF(OR(ABS(AVERAGE(('Inputs (2)'!AP18+'Inputs (2)'!AP19),('Inputs (2)'!AQ18+'Inputs (2)'!AQ19)))=0,('Inputs (2)'!AQ83)=0),"",ABS('Inputs (2)'!AQ83)*4/ABS(AVERAGE(('Inputs (2)'!AP18+'Inputs (2)'!AP19),('Inputs (2)'!AQ18+'Inputs (2)'!AQ19)))),"") | AR223: =IFERROR(IF(OR(ABS(AVERAGE(('Inputs (2)'!AM18+'Inputs (2)'!AM19),('Inputs (2)'!AR18+'Inputs (2)'!AR19)))=0,('Inputs (2)'!AR83)=0),"",ABS('Inputs (2)'!AR83)/ABS(AVERAGE(('Inputs (2)'!AM18+'Inputs (2)'!AM19),('Inputs (2)'!AR18+'Inputs (2)'!AR19)))),"") | AS223: =IFERROR(IF(OR(ABS(AVERAGE(('Inputs (2)'!AQ18+'Inputs (2)'!AQ19),('Inputs (2)'!AS18+'Inputs (2)'!AS19)))=0,('Inputs (2)'!AS83)=0),"",ABS('Inputs (2)'!AS83)*4/ABS(AVERAGE(('Inputs (2)'!AQ18+'Inputs (2)'!AQ19),('Inputs (2)'!AS18+'Inputs (2)'!AS19)))),"") | AT223: =IFERROR(IF(OR(ABS(AVERAGE(('Inputs (2)'!AS18+'Inputs (2)'!AS19),('Inputs (2)'!AT18+'Inputs (2)'!AT19)))=0,('Inputs (2)'!AT83)=0),"",ABS('Inputs (2)'!AT83)*4/ABS(AVERAGE(('Inputs (2)'!AS18+'Inputs (2)'!AS19),('Inputs (2)'!AT18+'Inputs (2)'!AT19)))),"") | AU223: =IFERROR(IF(OR(ABS(AVERAGE(('Inputs (2)'!AT18+'Inputs (2)'!AT19),('Inputs (2)'!AU18+'Inputs (2)'!AU19)))=0,('Inputs (2)'!AU83)=0),"",ABS('Inputs (2)'!AU83)*4/ABS(AVERAGE(('Inputs (2)'!AT18+'Inputs (2)'!AT19),('Inputs (2)'!AU18+'Inputs (2)'!AU19)))),"") | AV223: =IFERROR(IF(OR(ABS(AVERAGE(('Inputs (2)'!AU18+'Inputs (2)'!AU19),('Inputs (2)'!AV18+'Inputs (2)'!AV19)))=0,('Inputs (2)'!AV83)=0),"",ABS('Inputs (2)'!AV83)*4/ABS(AVERAGE(('Inputs (2)'!AU18+'Inputs (2)'!AU19),('Inputs (2)'!AV18+'Inputs (2)'!AV19)))),"") | AW223: =IFERROR(IF(OR(ABS(AVERAGE(('Inputs (2)'!AR18+'Inputs (2)'!AR19),('Inputs (2)'!AW18+'Inputs (2)'!AW19)))=0,('Inputs (2)'!AW83)=0),"",ABS('Inputs (2)'!AW83)/ABS(AVERAGE(('Inputs (2)'!AR18+'Inputs (2)'!AR19),('Inputs (2)'!AW18+'Inputs (2)'!AW19)))),"") | AX223: =IFERROR(IF(OR(ABS(AVERAGE(('Inputs (2)'!AV18+'Inputs (2)'!AV19),('Inputs (2)'!AX18+'Inputs (2)'!AX19)))=0,('Inputs (2)'!AX83)=0),"",ABS('Inputs (2)'!AX83)*4/ABS(AVERAGE(('Inputs (2)'!AV18+'Inputs (2)'!AV19),('Inputs (2)'!AX18+'Inputs (2)'!AX19)))),"") | AY223: =IFERROR(IF(OR(ABS(AVERAGE(('Inputs (2)'!AX18+'Inputs (2)'!AX19),('Inputs (2)'!AY18+'Inputs (2)'!AY19)))=0,('Inputs (2)'!AY83)=0),"",ABS('Inputs (2)'!AY83)*4/ABS(AVERAGE(('Inputs (2)'!AX18+'Inputs (2)'!AX19),('Inputs (2)'!AY18+'Inputs (2)'!AY19)))),"") | AZ223: =IFERROR(IF(OR(ABS(AVERAGE(('Inputs (2)'!AY18+'Inputs (2)'!AY19),('Inputs (2)'!AZ18+'Inputs (2)'!AZ19)))=0,('Inputs (2)'!AZ83)=0),"",ABS('Inputs (2)'!AZ83)*4/ABS(AVERAGE(('Inputs (2)'!AY18+'Inputs (2)'!AY19),('Inputs (2)'!AZ18+'Inputs (2)'!AZ19)))),"") | BA223: =IFERROR(IF(OR(ABS(AVERAGE(('Inputs (2)'!AZ18+'Inputs (2)'!AZ19),('Inputs (2)'!BA18+'Inputs (2)'!BA19)))=0,('Inputs (2)'!BA83)=0),"",ABS('Inputs (2)'!BA83)*4/ABS(AVERAGE(('Inputs (2)'!AZ18+'Inputs (2)'!AZ19),('Inputs (2)'!BA18+'Inputs (2)'!BA19)))),"") | BB223: =IFERROR(IF(OR(ABS(AVERAGE(('Inputs (2)'!AW18+'Inputs (2)'!AW19),('Inputs (2)'!BB18+'Inputs (2)'!BB19)))=0,('Inputs (2)'!BB83)=0),"",ABS('Inputs (2)'!BB83)/ABS(AVERAGE(('Inputs (2)'!AW18+'Inputs (2)'!AW19),('Inputs (2)'!BB18+'Inputs (2)'!BB19)))),"") | BC223: =IFERROR(IF(OR(ABS(AVERAGE(('Inputs (2)'!BA18+'Inputs (2)'!BA19),('Inputs (2)'!BC18+'Inputs (2)'!BC19)))=0,('Inputs (2)'!BC83)=0),"",ABS('Inputs (2)'!BC83)*4/ABS(AVERAGE(('Inputs (2)'!BA18+'Inputs (2)'!BA19),('Inputs (2)'!BC18+'Inputs (2)'!BC19)))),"") | BD223: =IFERROR(IF(OR(ABS(AVERAGE(('Inputs (2)'!BC18+'Inputs (2)'!BC19),('Inputs (2)'!BD18+'Inputs (2)'!BD19)))=0,('Inputs (2)'!BD83)=0),"",ABS('Inputs (2)'!BD83)*4/ABS(AVERAGE(('Inputs (2)'!BC18+'Inputs (2)'!BC19),('Inputs (2)'!BD18+'Inputs (2)'!BD19)))),"") | BE223: =IFERROR(IF(OR(ABS(AVERAGE(('Inputs (2)'!BD18+'Inputs (2)'!BD19),('Inputs (2)'!BE18+'Inputs (2)'!BE19)))=0,('Inputs (2)'!BE83)=0),"",ABS('Inputs (2)'!BE83)*4/ABS(AVERAGE(('Inputs (2)'!BD18+'Inputs (2)'!BD19),('Inputs (2)'!BE18+'Inputs (2)'!BE19)))),"") | BF223: =IFERROR(IF(OR(ABS(AVERAGE(('Inputs (2)'!BE18+'Inputs (2)'!BE19),('Inputs (2)'!BF18+'Inputs (2)'!BF19)))=0,('Inputs (2)'!BF83)=0),"",ABS('Inputs (2)'!BF83)*4/ABS(AVERAGE(('Inputs (2)'!BE18+'Inputs (2)'!BE19),('Inputs (2)'!BF18+'Inputs (2)'!BF19)))),"") | BG223: =IFERROR(IF(OR(ABS(AVERAGE(('Inputs (2)'!BB18+'Inputs (2)'!BB19),('Inputs (2)'!BG18+'Inputs (2)'!BG19)))=0,('Inputs (2)'!BG83)=0),"",ABS('Inputs (2)'!BG83)/ABS(AVERAGE(('Inputs (2)'!BB18+'Inputs (2)'!BB19),('Inputs (2)'!BG18+'Inputs (2)'!BG19)))),"")
...

Sheet Inputs (2)
C1: ="Demonstrações reportadas — valores em "&Inputs!$E$202 -> Demonstrações reportadas — valores em US$ milhões | D1: Reported financials | E1: =DATE(2020,4,1)-1 -> 43921 | F1: =DATE(2020,7,1)-1 -> 44012 | G1: =DATE(2020,10,1)-1 -> 44104 | H1: =DATE(2020,13,1)-1 -> 44196 | I1: =H1 -> 44196 | J1: =DATE(2021,4,1)-1 -> 44286 | K1: =DATE(2021,7,1)-1 -> 44377 | L1: =DATE(2021,10,1)-1 -> 44469 | M1: =DATE(2021,13,1)-1 -> 44561 | N1: =M1 -> 44561 | O1: =DATE(2022,4,1)-1 -> 44651 | P1: =DATE(2022,7,1)-1 -> 44742 | Q1: =DATE(2022,10,1)-1 -> 44834 | R1: =DATE(2022,13,1)-1 -> 44926 | S1: =R1 -> 44926 | T1: =DATE(2023,4,1)-1 -> 45016 | U1: =DATE(2023,7,1)-1 -> 45107 | V1: =DATE(2023,10,1)-1 -> 45199 | W1: =DATE(2023,13,1)-1 -> 45291 | X1: =W1 -> 45291 | Y1: =DATE(2024,4,1)-1 -> 45382 | Z1: =DATE(2024,7,1)-1 -> 45473 | AA1: =DATE(2024,10,1)-1 -> 45565 | AB1: =DATE(2024,13,1)-1 -> 45657 | AC1: =AB1 -> 45657 | AD1: =DATE(2025,4,1)-1 -> 45747 | AE1: =DATE(2025,7,1)-1 -> 45838 | AF1: =DATE(2025,10,1)-1 -> 45930 | AG1: =DATE(2025,13,1)-1 -> 46022 | AH1: =AG1 -> 46022 | AI1: =DATE(2026,4,1)-1 -> 46112 | AJ1: =DATE(2026,7,1)-1 -> 46203 | AK1: =DATE(2026,10,1)-1 -> 46295 | AL1: =DATE(2026,13,1)-1 -> 46387 | AM1: =AL1 -> 46387 | AN1: =DATE(2027,4,1)-1 -> 46477 | AO1: =DATE(2027,7,1)-1 -> 46568 | AP1: =DATE(2027,10,1)-1 -> 46660 | AQ1: =DATE(2027,13,1)-1 -> 46752 | AR1: =AQ1 -> 46752 | AS1: =DATE(2028,4,1)-1 -> 46843 | AT1: =DATE(2028,7,1)-1 -> 46934 | AU1: =DATE(2028,10,1)-1 -> 47026 | AV1: =DATE(2028,13,1)-1 -> 47118 | AW1: =AV1 -> 47118 | AX1: =DATE(2029,4,1)-1 -> 47208 | AY1: =DATE(2029,7,1)-1 -> 47299 | AZ1: =DATE(2029,10,1)-1 -> 47391 | BA1: =DATE(2029,13,1)-1 -> 47483 | BB1: =BA1 -> 47483 | BC1: =DATE(2030,4,1)-1 -> 47573 | BD1: =DATE(2030,7,1)-1 -> 47664 | BE1: =DATE(2030,10,1)-1 -> 47756 | BF1: =DATE(2030,13,1)-1 -> 47848 | BG1: =BF1 -> 47848
B2: COD | E2: 2020 | F2: 2020 | G2: 2020 | H2: 2020 | I2: 2020 | J2: 2021 | K2: 2021 | L2: 2021 | M2: 2021 | N2: 2021 | O2: 2022 | P2: 2022 | Q2: 2022 | R2: 2022 | S2: 2022 | T2: 2023 | U2: 2023 | V2: 2023 | W2: 2023 | X2: 2023 | Y2: 2024 | Z2: 2024 | AA2: 2024 | AB2: 2024 | AC2: 2024 | AD2: 2025 | AE2: 2025 | AF2: 2025 | AG2: 2025 | AH2: 2025 | AI2: 2026 | AJ2: 2026 | AK2: 2026 | AL2: 2026 | AM2: 2026 | AN2: 2027 | AO2: 2027 | AP2: 2027 | AQ2: 2027 | AR2: 2027 | AS2: 2028 | AT2: 2028 | AU2: 2028 | AV2: 2028 | AW2: 2028 | AX2: 2029 | AY2: 2029 | AZ2: 2029 | BA2: 2029 | BB2: 2029 | BC2: 2030 | BD2: 2030 | BE2: 2030 | BF2: 2030 | BG2: 2030
C3: Período | D3: Period | E3: ="1Q"&RIGHT(E2,2) -> 1Q20 | F3: ="2Q"&RIGHT(F2,2) -> 2Q20 | G3: ="3Q"&RIGHT(G2,2) -> 3Q20 | H3: ="4Q"&RIGHT(H2,2) -> 4Q20 | I3: ="FY"&RIGHT(I2,2) -> FY20 | J3: ="1Q"&RIGHT(J2,2) -> 1Q21 | K3: ="2Q"&RIGHT(K2,2) -> 2Q21 | L3: ="3Q"&RIGHT(L2,2) -> 3Q21 | M3: ="4Q"&RIGHT(M2,2) -> 4Q21 | N3: ="FY"&RIGHT(N2,2) -> FY21 | O3: ="1Q"&RIGHT(O2,2) -> 1Q22 | P3: ="2Q"&RIGHT(P2,2) -> 2Q22 | Q3: ="3Q"&RIGHT(Q2,2) -> 3Q22 | R3: ="4Q"&RIGHT(R2,2) -> 4Q22 | S3: ="FY"&RIGHT(S2,2) -> FY22 | T3: ="1Q"&RIGHT(T2,2) -> 1Q23 | U3: ="2Q"&RIGHT(U2,2) -> 2Q23 | V3: ="3Q"&RIGHT(V2,2) -> 3Q23 | W3: ="4Q"&RIGHT(W2,2) -> 4Q23 | X3: ="FY"&RIGHT(X2,2) -> FY23 | Y3: ="1Q"&RIGHT(Y2,2) -> 1Q24 | Z3: ="2Q"&RIGHT(Z2,2) -> 2Q24 | AA3: ="3Q"&RIGHT(AA2,2) -> 3Q24 | AB3: ="4Q"&RIGHT(AB2,2) -> 4Q24 | AC3: ="FY"&RIGHT(AC2,2) -> FY24 | AD3: ="1Q"&RIGHT(AD2,2) -> 1Q25 | AE3: ="2Q"&RIGHT(AE2,2) -> 2Q25 | AF3: ="3Q"&RIGHT(AF2,2) -> 3Q25 | AG3: ="4Q"&RIGHT(AG2,2) -> 4Q25 | AH3: ="FY"&RIGHT(AH2,2) -> FY25 | AI3: ="1Q"&RIGHT(AI2,2) -> 1Q26 | AJ3: ="2Q"&RIGHT(AJ2,2) -> 2Q26 | AK3: ="3Q"&RIGHT(AK2,2) -> 3Q26 | AL3: ="4Q"&RIGHT(AL2,2) -> 4Q26 | AM3: ="FY"&RIGHT(AM2,2) -> FY26 | AN3: ="1Q"&RIGHT(AN2,2) -> 1Q27 | AO3: ="2Q"&RIGHT(AO2,2) -> 2Q27 | AP3: ="3Q"&RIGHT(AP2,2) -> 3Q27 | AQ3: ="4Q"&RIGHT(AQ2,2) -> 4Q27 | AR3: ="FY"&RIGHT(AR2,2) -> FY27 | AS3: ="1Q"&RIGHT(AS2,2) -> 1Q28 | AT3: ="2Q"&RIGHT(AT2,2) -> 2Q28 | AU3: ="3Q"&RIGHT(AU2,2) -> 3Q28 | AV3: ="4Q"&RIGHT(AV2,2) -> 4Q28 | AW3: ="FY"&RIGHT(AW2,2) -> FY28 | AX3: ="1Q"&RIGHT(AX2,2) -> 1Q29 | AY3: ="2Q"&RIGHT(AY2,2) -> 2Q29 | AZ3: ="3Q"&RIGHT(AZ2,2) -> 3Q29 | BA3: ="4Q"&RIGHT(BA2,2) -> 4Q29 | BB3: ="FY"&RIGHT(BB2,2) -> FY29 | BC3: ="1Q"&RIGHT(BC2,2) -> 1Q30 | BD3: ="2Q"&RIGHT(BD2,2) -> 2Q30 | BE3: ="3Q"&RIGHT(BE2,2) -> 3Q30 | BF3: ="4Q"&RIGHT(BF2,2) -> 4Q30 | BG3: ="FY"&RIGHT(BG2,2) -> FY30
C4: ATIVO | D4: ASSETS
B5: cash | C5: Caixa e depósitos não remunerados em bancos | D5: Cash and due from banks | E5: =IF(ISNA(SUMIFS(INDEX(Inputs!$B$2:$AZ$190,,MATCH(SUBSTITUTE(E$3,"Q","T"),Inputs!$B$2:$AZ$2,0)),Inputs!$B$2:$B$190,$B5)*Inputs!$D$1),"",SUMIFS(INDEX(Inputs!$B$2:$AZ$190,,MATCH(SUBSTITUTE(E$3,"Q","T"),Inputs!$B$2:$AZ$2,0)),Inputs!$B$2:$B$190,$B5)*Inputs!$D$1) -> 0 | F5: =IF(ISNA(SUMIFS(INDEX(Inputs!$B$2:$AZ$190,,MATCH(SUBSTITUTE(F$3,"Q","T"),Inputs!$B$2:$AZ$2,0)),Inputs!$B$2:$B$190,$B5)*Inputs!$D$1),"",SUMIFS(INDEX(Inputs!$B$2:$AZ$190,,MATCH(SUBSTITUTE(F$3,"Q","T"),Inputs!$B$2:$AZ$2,0)),Inputs!$B$2:$B$190,$B5)*Inputs!$D$1) -> 0 | G5: =IF(ISNA(SUMIFS(INDEX(Inputs!$B$2:$AZ$190,,MATCH(SUBSTITUTE(G$3,"Q","T"),Inputs!$B$2:$AZ$2,0)),Inputs!$B$2:$B$190,$B5)*Inputs!$D$1),"",SUMIFS(INDEX(Inputs!$B$2:$AZ$190,,MATCH(SUBSTITUTE(G$3,"Q","T"),Inputs!$B$2:$AZ$2,0)),Inputs!$B$2:$B$190,$B5)*Inputs!$D$1) -> 0 | H5: =IF(ISNA(SUMIFS(INDEX(Inputs!$B$2:$AZ$190,,MATCH(SUBSTITUTE(H$3,"Q","T"),Inputs!$B$2:$AZ$2,0)),Inputs!$B$2:$B$190,$B5)*Inputs!$D$1),"",SUMIFS(INDEX(Inputs!$B$2:$AZ$190,,MATCH(SUBSTITUTE(H$3,"Q","T"),Inputs!$B$2:$AZ$2,0)),Inputs!$B$2:$B$190,$B5)*Inputs!$D$1) -> 0 | I5: =H5 -> 0 | J5: =IF(ISNA(SUMIFS(INDEX(Inputs!$B$2:$AZ$190,,MATCH(SUBSTITUTE(J$3,"Q","T"),Inputs!$B$2:$AZ$2,0)),Inputs!$B$2:$B$190,$B5)*Inputs!$D$1),"",SUMIFS(INDEX(Inputs!$B$2:$AZ$190,,MATCH(SUBSTITUTE(J$3,"Q","T"),Inputs!$B$2:$AZ$2,0)),Inputs!$B$2:$B$190,$B5)*Inputs!$D$1) -> 0 | K5: =IF(ISNA(SUMIFS(INDEX(Inputs!$B$2:$AZ$190,,MATCH(SUBSTITUTE(K$3,"Q","T"),Inputs!$B$2:$AZ$2,0)),Inputs!$B$2:$B$190,$B5)*Inputs!$D$1),"",SUMIFS(INDEX(Inputs!$B$2:$AZ$190,,MATCH(SUBSTITUTE(K$3,"Q","T"),Inputs!$B$2:$AZ$2,0)),Inputs!$B$2:$B$190,$B5)*Inputs!$D$1) -> 0 | L5: =IF(ISNA(SUMIFS(INDEX(Inputs!$B$2:$AZ$190,,MATCH(SUBSTITUTE(L$3,"Q","T"),Inputs!$B$2:$AZ$2,0)),Inputs!$B$2:$B$190,$B5)*Inputs!$D$1),"",SUMIFS(INDEX(Inputs!$B$2:$AZ$190,,MATCH(SUBSTITUTE(L$3,"Q","T"),Inputs!$B$2:$AZ$2,0)),Inputs!$B$2:$B$190,$B5)*Inputs!$D$1) -> 0 | M5: =IF(ISNA(SUMIFS(INDEX(Inputs!$B$2:$AZ$190,,MATCH(SUBSTITUTE(M$3,"Q","T"),Inputs!$B$2:$AZ$2,0)),Inputs!$B$2:$B$190,$B5)*Inputs!$D$1),"",SUMIFS(INDEX(Inputs!$B$2:$AZ$190,,MATCH(SUBSTITUTE(M$3,"Q","T"),Inputs!$B$2:$AZ$2,0)),Inputs!$B$2:$B$190,$B5)*Inputs!$D$1) -> 0 | N5: =M5 -> 0 | O5: =IF(ISNA(SUMIFS(INDEX(Inputs!$B$2:$AZ$190,,MATCH(SUBSTITUTE(O$3,"Q","T"),Inputs!$B$2:$AZ$2,0)),Inputs!$B$2:$B$190,$B5)*Inputs!$D$1),"",SUMIFS(INDEX(Inputs!$B$2:$AZ$190,,MATCH(SUBSTITUTE(O$3,"Q","T"),Inputs!$B$2:$AZ$2,0)),Inputs!$B$2:$B$190,$B5)*Inputs!$D$1) -> 0 | P5: =IF(ISNA(SUMIFS(INDEX(Inputs!$B$2:$AZ$190,,MATCH(SUBSTITUTE(P$3,"Q","T"),Inputs!$B$2:$AZ$2,0)),Inputs!$B$2:$B$190,$B5)*Inputs!$D$1),"",SUMIFS(INDEX(Inputs!$B$2:$AZ$190,,MATCH(SUBSTITUTE(P$3,"Q","T"),Inputs!$B$2:$AZ$2,0)),Inputs!$B$2:$B$190,$B5)*Inputs!$D$1) -> 0 | Q5: =IF(ISNA(SUMIFS(INDEX(Inputs!$B$2:$AZ$190,,MATCH(SUBSTITUTE(Q$3,"Q","T"),Inputs!$B$2:$AZ$2,0)),Inputs!$B$2:$B$190,$B5)*Inputs!$D$1),"",SUMIFS(INDEX(Inputs!$B$2:$AZ$190,,MATCH(SUBSTITUTE(Q$3,"Q","T"),Inputs!$B$2:$AZ$2,0)),Inputs!$B$2:$B$190,$B5)*Inputs!$D$1) -> 0 | R5: =IF(ISNA(SUMIFS(INDEX(Inputs!$B$2:$AZ$190,,MATCH(SUBSTITUTE(R$3,"Q","T"),Inputs!$B$2:$AZ$2,0)),Inputs!$B$2:$B$190,$B5)*Inputs!$D$1),"",SUMIFS(INDEX(Inputs!$B$2:$AZ$190,,MATCH(SUBSTITUTE(R$3,"Q","T"),Inputs!$B$2:$AZ$2,0)),Inputs!$B$2:$B$190,$B5)*Inputs!$D$1) -> 0 | S5: =R5 -> 0 | T5: =IF(ISNA(SUMIFS(INDEX(Inputs!$B$2:$AZ$190,,MATCH(SUBSTITUTE(T$3,"Q","T"),Inputs!$B$2:$AZ$2,0)),Inputs!$B$2:$B$190,$B5)*Inputs!$D$1),"",SUMIFS(INDEX(Inputs!$B$2:$AZ$190,,MATCH(SUBSTITUTE(T$3,"Q","T"),Inputs!$B$2:$AZ$2,0)),Inputs!$B$2:$B$190,$B5)*Inputs!$D$1) -> 0 | U5: =IF(ISNA(SUMIFS(INDEX(Inputs!$B$2:$AZ$190,,MATCH(SUBSTITUTE(U$3,"Q","T"),Inputs!$B$2:$AZ$2,0)),Inputs!$B$2:$B$190,$B5)*Inputs!$D$1),"",SUMIFS(INDEX(Inputs!$B$2:$AZ$190,,MATCH(SUBSTITUTE(U$3,"Q","T"),Inputs!$B$2:$AZ$2,0)),Inputs!$B$2:$B$190,$B5)*Inputs!$D$1) -> 0 | V5: =IF(ISNA(SUMIFS(INDEX(Inputs!$B$2:$AZ$190,,MATCH(SUBSTITUTE(V$3,"Q","T"),Inputs!$B$2:$AZ$2,0)),Inputs!$B$2:$B$190,$B5)*Inputs!$D$1),"",SUMIFS(INDEX(Inputs!$B$2:$AZ$190,,MATCH(SUBSTITUTE(V$3,"Q","T"),Inputs!$B$2:$AZ$2,0)),Inputs!$B$2:$B$190,$B5)*Inputs!$D$1) -> 0 | W5: =IF(ISNA(SUMIFS(INDEX(Inputs!$B$2:$AZ$190,,MATCH(SUBSTITUTE(W$3,"Q","T"),Inputs!$B$2:$AZ$2,0)),Inputs!$B$2:$B$190,$B5)*Inputs!$D$1),"",SUMIFS(INDEX(Inputs!$B$2:$AZ$190,,MATCH(SUBSTITUTE(W$3,"Q","T"),Inputs!$B$2:$AZ$2,0)),Inputs!$B$2:$B$190,$B5)*Inputs!$D$1) -> 0 | X5: =W5 -> 0 | Y5: =IF(ISNA(SUMIFS(INDEX(Inputs!$B$2:$AZ$190,,MATCH(SUBSTITUTE(Y$3,"Q","T"),Inputs!$B$2:$AZ$2,0)),Inputs!$B$2:$B$190,$B5)*Inputs!$D$1),"",SUMIFS(INDEX(Inputs!$B$2:$AZ$190,,MATCH(SUBSTITUTE(Y$3,"Q","T"),Inputs!$B$2:$AZ$2,0)),Inputs!$B$2:$B$190,$B5)*Inputs!$D$1) -> 0 | Z5: =IF(ISNA(SUMIFS(INDEX(Inputs!$B$2:$AZ$190,,MATCH(SUBSTITUTE(Z$3,"Q","T"),Inputs!$B$2:$AZ$2,0)),Inputs!$B$2:$B$190,$B5)*Inputs!$D$1),"",SUMIFS(INDEX(Inputs!$B$2:$AZ$190,,MATCH(SUBSTITUTE(Z$3,"Q","T"),Inputs!$B$2:$AZ$2,0)),Inputs!$B$2:$B$190,$B5)*Inputs!$D$1) -> 0 | AA5: =IF(ISNA(SUMIFS(INDEX(Inputs!$B$2:$AZ$190,,MATCH(SUBSTITUTE(AA$3,"Q","T"),Inputs!$B$2:$AZ$2,0)),Inputs!$B$2:$B$190,$B5)*Inputs!$D$1),"",SUMIFS(INDEX(Inputs!$B$2:$AZ$190,,MATCH(SUBSTITUTE(AA$3,"Q","T"),Inputs!$B$2:$AZ$2,0)),Inputs!$B$2:$B$190,$B5)*Inputs!$D$1) -> 0 | AB5: =IF(ISNA(SUMIFS(INDEX(Inputs!$B$2:$AZ$190,,MATCH(SUBSTITUTE(AB$3,"Q","T"),Inputs!$B$2:$AZ$2,0)),Inputs!$B$2:$B$190,$B5)*Inputs!$D$1),"",SUMIFS(INDEX(Inputs!$B$2:$AZ$190,,MATCH(SUBSTITUTE(AB$3,"Q","T"),Inputs!$B$2:$AZ$2,0)),Inputs!$B$2:$B$190,$B5)*Inputs!$D$1) -> 0 | AC5: =AB5 -> 0 | AD5: =IF(ISNA(SUMIFS(INDEX(Inputs!$B$2:$AZ$190,,MATCH(SUBSTITUTE(AD$3,"Q","T"),Inputs!$B$2:$AZ$2,0)),Inputs!$B$2:$B$190,$B5)*Inputs!$D$1),"",SUMIFS(INDEX(Inputs!$B$2:$AZ$190,,MATCH(SUBSTITUTE(AD$3,"Q","T"),Inputs!$B$2:$AZ$2,0)),Inputs!$B$2:$B$190,$B5)*Inputs!$D$1) -> 0 | AE5: =IF(ISNA(SUMIFS(INDEX(Inputs!$B$2:$AZ$190,,MATCH(SUBSTITUTE(AE$3,"Q","T"),Inputs!$B$2:$AZ$2,0)),Inputs!$B$2:$B$190,$B5)*Inputs!$D$1),"",SUMIFS(INDEX(Inputs!$B$2:$AZ$190,,MATCH(SUBSTITUTE(AE$3,"Q","T"),Inputs!$B$2:$AZ$2,0)),Inputs!$B$2:$B$190,$B5)*Inputs!$D$1) -> 0 | AF5: =IF(ISNA(SUMIFS(INDEX(Inputs!$B$2:$AZ$190,,MATCH(SUBSTITUTE(AF$3,"Q","T"),Inputs!$B$2:$AZ$2,0)),Inputs!$B$2:$B$190,$B5)*Inputs!$D$1),"",SUMIFS(INDEX(Inputs!$B$2:$AZ$190,,MATCH(SUBSTITUTE(AF$3,"Q","T"),Inputs!$B$2:$AZ$2,0)),Inputs!$B$2:$B$190,$B5)*Inputs!$D$1) -> 0 | AG5: =IF(ISNA(SUMIFS(INDEX(Inputs!$B$2:$AZ$190,,MATCH(SUBSTITUTE(AG$3,"Q","T"),Inputs!$B$2:$AZ$2,0)),Inputs!$B$2:$B$190,$B5)*Inputs!$D$1),"",SUMIFS(INDEX(Inputs!$B$2:$AZ$190,,MATCH(SUBSTITUTE(AG$3,"Q","T"),Inputs!$B$2:$AZ$2,0)),Inputs!$B$2:$B$190,$B5)*Inputs!$D$1) -> 0 | AH5: =AG5 -> 0 | AI5: =IF(ISNA(SUMIFS(INDEX(Inputs!$B$2:$AZ$190,,MATCH(SUBSTITUTE(AI$3,"Q","T"),Inputs!$B$2:$AZ$2,0)),Inputs!$B$2:$B$190,$B5)*Inputs!$D$1),"",SUMIFS(INDEX(Inputs!$B$2:$AZ$190,,MATCH(SUBSTITUTE(AI$3,"Q","T"),Inputs!$B$2:$AZ$2,0)),Inputs!$B$2:$B$190,$B5)*Inputs!$D$1) -> 0 | AJ5: =IF(ISNA(SUMIFS(INDEX(Inputs!$B$2:$AZ$190,,MATCH(SUBSTITUTE(AJ$3,"Q","T"),Inputs!$B$2:$AZ$2,0)),Inputs!$B$2:$B$190,$B5)*Inputs!$D$1),"",SUMIFS(INDEX(Inputs!$B$2:$AZ$190,,MATCH(SUBSTITUTE(AJ$3,"Q","T"),Inputs!$B$2:$AZ$2,0)),Inputs!$B$2:$B$190,$B5)*Inputs!$D$1) -> 0 | AK5: =IF(ISNA(SUMIFS(INDEX(Inputs!$B$2:$AZ$190,,MATCH(SUBSTITUTE(AK$3,"Q","T"),Inputs!$B$2:$AZ$2,0)),Inputs!$B$2:$B$190,$B5)*Inputs!$D$1),"",SUMIFS(INDEX(Inputs!$B$2:$AZ$190,,MATCH(SUBSTITUTE(AK$3,"Q","T"),Inputs!$B$2:$AZ$2,0)),Inputs!$B$2:$B$190,$B5)*Inputs!$D$1) -> 0 | AL5: =IF(ISNA(SUMIFS(INDEX(Inputs!$B$2:$AZ$190,,MATCH(SUBSTITUTE(AL$3,"Q","T"),Inputs!$B$2:$AZ$2,0)),Inputs!$B$2:$B$190,$B5)*Inputs!$D$1),"",SUMIFS(INDEX(Inputs!$B$2:$AZ$190,,MATCH(SUBSTITUTE(AL$3,"Q","T"),Inputs!$B$2:$AZ$2,0)),Inputs!$B$2:$B$190,$B5)*Inputs!$D$1) -> 0 | AM5: =AL5 -> 0 | AN5: =IF(ISNA(SUMIFS(INDEX(Inputs!$B$2:$AZ$190,,MATCH(SUBSTITUTE(AN$3,"Q","T"),Inputs!$B$2:$AZ$2,0)),Inputs!$B$2:$B$190,$B5)*Inputs!$D$1),"",SUMIFS(INDEX(Inputs!$B$2:$AZ$190,,MATCH(SUBSTITUTE(AN$3,"Q","T"),Inputs!$B$2:$AZ$2,0)),Inputs!$B$2:$B$190,$B5)*Inputs!$D$1) -> 0 | AO5: =IF(ISNA(SUMIFS(INDEX(Inputs!$B$2:$AZ$190,,MATCH(SUBSTITUTE(AO$3,"Q","T"),Inputs!$B$2:$AZ$2,0)),Inputs!$B$2:$B$190,$B5)*Inputs!$D$1),"",SUMIFS(INDEX(Inputs!$B$2:$AZ$190,,MATCH(SUBSTITUTE(AO$3,"Q","T"),Inputs!$B$2:$AZ$2,0)),Inputs!$B$2:$B$190,$B5)*Inputs!$D$1) -> 0 | AP5: =IF(ISNA(SUMIFS(INDEX(Inputs!$B$2:$AZ$190,,MATCH(SUBSTITUTE(AP$3,"Q","T"),Inputs!$B$2:$AZ$2,0)),Inputs!$B$2:$B$190,$B5)*Inputs!$D$1),"",SUMIFS(INDEX(Inputs!$B$2:$AZ$190,,MATCH(SUBSTITUTE(AP$3,"Q","T"),Inputs!$B$2:$AZ$2,0)),Inputs!$B$2:$B$190,$B5)*Inputs!$D$1) -> 0 | AQ5: =IF(ISNA(SUMIFS(INDEX(Inputs!$B$2:$AZ$190,,MATCH(SUBSTITUTE(AQ$3,"Q","T"),Inputs!$B$2:$AZ$2,0)),Inputs!$B$2:$B$190,$B5)*Inputs!$D$1),"",SUMIFS(INDEX(Inputs!$B$2:$AZ$190,,MATCH(SUBSTITUTE(AQ$3,"Q","T"),Inputs!$B$2:$AZ$2,0)),Inputs!$B$2:$B$190,$B5)*Inputs!$D$1) -> 0 | AR5: =AQ5 -> 0 | AS5: =IF(ISNA(SUMIFS(INDEX(Inputs!$B$2:$AZ$190,,MATCH(SUBSTITUTE(AS$3,"Q","T"),Inputs!$B$2:$AZ$2,0)),Inputs!$B$2:$B$190,$B5)*Inputs!$D$1),"",SUMIFS(INDEX(Inputs!$B$2:$AZ$190,,MATCH(SUBSTITUTE(AS$3,"Q","T"),Inputs!$B$2:$AZ$2,0)),Inputs!$B$2:$B$190,$B5)*Inputs!$D$1) -> 0 | AT5: =IF(ISNA(SUMIFS(INDEX(Inputs!$B$2:$AZ$190,,MATCH(SUBSTITUTE(AT$3,"Q","T"),Inputs!$B$2:$AZ$2,0)),Inputs!$B$2:$B$190,$B5)*Inputs!$D$1),"",SUMIFS(INDEX(Inputs!$B$2:$AZ$190,,MATCH(SUBSTITUTE(AT$3,"Q","T"),Inputs!$B$2:$AZ$2,0)),Inputs!$B$2:$B$190,$B5)*Inputs!$D$1) -> 0 | AU5: =IF(ISNA(SUMIFS(INDEX(Inputs!$B$2:$AZ$190,,MATCH(SUBSTITUTE(AU$3,"Q","T"),Inputs!$B$2:$AZ$2,0)),Inputs!$B$2:$B$190,$B5)*Inputs!$D$1),"",SUMIFS(INDEX(Inputs!$B$2:$AZ$190,,MATCH(SUBSTITUTE(AU$3,"Q","T"),Inputs!$B$2:$AZ$2,0)),Inputs!$B$2:$B$190,$B5)*Inputs!$D$1) -> 0 | AV5: =IF(ISNA(SUMIFS(INDEX(Inputs!$B$2:$AZ$190,,MATCH(SUBSTITUTE(AV$3,"Q","T"),Inputs!$B$2:$AZ$2,0)),Inputs!$B$2:$B$190,$B5)*Inputs!$D$1),"",SUMIFS(INDEX(Inputs!$B$2:$AZ$190,,MATCH(SUBSTITUTE(AV$3,"Q","T"),Inputs!$B$2:$AZ$2,0)),Inputs!$B$2:$B$190,$B5)*Inputs!$D$1) -> 0 | AW5: =AV5 -> 0 | AX5: =IF(ISNA(SUMIFS(INDEX(Inputs!$B$2:$AZ$190,,MATCH(SUBSTITUTE(AX$3,"Q","T"),Inputs!$B$2:$AZ$2,0)),Inputs!$B$2:$B$190,$B5)*Inputs!$D$1),"",SUMIFS(INDEX(Inputs!$B$2:$AZ$190,,MATCH(SUBSTITUTE(AX$3,"Q","T"),Inputs!$B$2:$AZ$2,0)),Inputs!$B$2:$B$190,$B5)*Inputs!$D$1) -> 0 | AY5: =IF(ISNA(SUMIFS(INDEX(Inputs!$B$2:$AZ$190,,MATCH(SUBSTITUTE(AY$3,"Q","T"),Inputs!$B$2:$AZ$2,0)),Inputs!$B$2:$B$190,$B5)*Inputs!$D$1),"",SUMIFS(INDEX(Inputs!$B$2:$AZ$190,,MATCH(SUBSTITUTE(AY$3,"Q","T"),Inputs!$B$2:$AZ$2,0)),Inputs!$B$2:$B$190,$B5)*Inputs!$D$1) -> 0 | AZ5: =IF(ISNA(SUMIFS(INDEX(Inputs!$B$2:$AZ$190,,MATCH(SUBSTITUTE(AZ$3,"Q","T"),Inputs!$B$2:$AZ$2,0)),Inputs!$B$2:$B$190,$B5)*Inputs!$D$1),"",SUMIFS(INDEX(Inputs!$B$2:$AZ$190,,MATCH(SUBSTITUTE(AZ$3,"Q","T"),Inputs!$B$2:$AZ$2,0)),Inputs!$B$2:$B$190,$B5)*Inputs!$D$1) -> 0 | BA5: =IF(ISNA(SUMIFS(INDEX(Inputs!$B$2:$AZ$190,,MATCH(SUBSTITUTE(BA$3,"Q","T"),Inputs!$B$2:$AZ$2,0)),Inputs!$B$2:$B$190,$B5)*Inputs!$D$1),"",SUMIFS(INDEX(Inputs!$B$2:$AZ$190,,MATCH(SUBSTITUTE(BA$3,"Q","T"),Inputs!$B$2:$AZ$2,0)),Inputs!$B$2:$B$190,$B5)*Inputs!$D$1) -> 0 | BB5: =BA5 -> 0 | BC5: =IF(ISNA(SUMIFS(INDEX(Inputs!$B$2:$AZ$190,,MATCH(SUBSTITUTE(BC$3,"Q","T"),Inputs!$B$2:$AZ$2,0)),Inputs!$B$2:$B$190,$B5)*Inputs!$D$1),"",SUMIFS(INDEX(Inputs!$B$2:$AZ$190,,MATCH(SUBSTITUTE(BC$3,"Q","T"),Inputs!$B$2:$AZ$2,0)),Inputs!$B$2:$B$190,$B5)*Inputs!$D$1) -> 0 | BD5: =IF(ISNA(SUMIFS(INDEX(Inputs!$B$2:$AZ$190,,MATCH(SUBSTITUTE(BD$3,"Q","T"),Inputs!$B$2:$AZ$2,0)),Inputs!$B$2:$B$190,$B5)*Inputs!$D$1),"",SUMIFS(INDEX(Inputs!$B$2:$AZ$190,,MATCH(SUBSTITUTE(BD$3,"Q","T"),Inputs!$B$2:$AZ$2,0)),Inputs!$B$2:$B$190,$B5)*Inputs!$D$1) -> 0 | BE5: =IF(ISNA(SUMIFS(INDEX(Inputs!$B$2:$AZ$190,,MATCH(SUBSTITUTE(BE$3,"Q","T"),Inputs!$B$2:$AZ$2,0)),Inputs!$B$2:$B$190,$B5)*Inputs!$D$1),"",SUMIFS(INDEX(Inputs!$B$2:$AZ$190,,MATCH(SUBSTITUTE(BE$3,"Q","T"),Inputs!$B$2:$AZ$2,0)),Inputs!$B$2:$B$190,$B5)*Inputs!$D$1) -> 0 | BF5: =IF(ISNA(SUMIFS(INDEX(Inputs!$B$2:$AZ$190,,MATCH(SUBSTITUTE(BF$3,"Q","T"),Inputs!$B$2:$AZ$2,0)),Inputs!$B$2:$B$190,$B5)*Inputs!$D$1),"",SUMIFS(INDEX(Inputs!$B$2:$AZ$190,,MATCH(SUBSTITUTE(BF$3,"Q","T"),Inputs!$B$2:$AZ$2,0)),Inputs!$B$2:$B$190,$B5)*Inputs!$D$1) -> 0 | BG5: =BF5 -> 0
C6: Aplicações de liquidez | D6: Liquidity placements | E6: =IFERROR(E7+E8+E9+E10,"") -> 0 | F6: =IFERROR(F7+F8+F9+F10,"") -> 0 | G6: =IFERROR(G7+G8+G9+G10,"") -> 0 | H6: =IFERROR(H7+H8+H9+H10,"") -> 0 | I6: =H6 -> 0 | J6: =IFERROR(J7+J8+J9+J10,"") -> 0 | K6: =IFERROR(K7+K8+K9+K10,"") -> 0 | L6: =IFERROR(L7+L8+L9+L10,"") -> 0 | M6: =IFERROR(M7+M8+M9+M10,"") -> 0 | N6: =M6 -> 0 | O6: =IFERROR(O7+O8+O9+O10,"") -> 0 | P6: =IFERROR(P7+P8+P9+P10,"") -> 0 | Q6: =IFERROR(Q7+Q8+Q9+Q10,"") -> 0 | R6: =IFERROR(R7+R8+R9+R10,"") -> 0 | S6: =R6 -> 0 | T6: =IFERROR(T7+T8+T9+T10,"") -> 0 | U6: =IFERROR(U7+U8+U9+U10,"") -> 0 | V6: =IFERROR(V7+V8+V9+V10,"") -> 0 | W6: =IFERROR(W7+W8+W9+W10,"") -> 0 | X6: =W6 -> 0 | Y6: =IFERROR(Y7+Y8+Y9+Y10,"") -> 0 | Z6: =IFERROR(Z7+Z8+Z9+Z10,"") -> 0 | AA6: =IFERROR(AA7+AA8+AA9+AA10,"") -> 0 | AB6: =IFERROR(AB7+AB8+AB9+AB10,"") -> 0 | AC6: =AB6 -> 0 | AD6: =IFERROR(AD7+AD8+AD9+AD10,"") -> 0 | AE6: =IFERROR(AE7+AE8+AE9+AE10,"") -> 0 | AF6: =IFERROR(AF7+AF8+AF9+AF10,"") -> 0 | AG6: =IFERROR(AG7+AG8+AG9+AG10,"") -> 0 | AH6: =AG6 -> 0 | AI6: =IFERROR(AI7+AI8+AI9+AI10,"") -> 0 | AJ6: =IFERROR(AJ7+AJ8+AJ9+AJ10,"") -> 0 | AK6: =IFERROR(AK7+AK8+AK9+AK10,"") -> 0 | AL6: =IFERROR(AL7+AL8+AL9+AL10,"") -> 0 | AM6: =AL6 -> 0 | AN6: =IFERROR(AN7+AN8+AN9+AN10,"") -> 0 | AO6: =IFERROR(AO7+AO8+AO9+AO10,"") -> 0 | AP6: =IFERROR(AP7+AP8+AP9+AP10,"") -> 0 | AQ6: =IFERROR(AQ7+AQ8+AQ9+AQ10,"") -> 0 | AR6: =AQ6 -> 0 | AS6: =IFERROR(AS7+AS8+AS9+AS10,"") -> 0 | AT6: =IFERROR(AT7+AT8+AT9+AT10,"") -> 0 | AU6: =IFERROR(AU7+AU8+AU9+AU10,"") -> 0 | AV6: =IFERROR(AV7+AV8+AV9+AV10,"") -> 0 | AW6: =AV6 -> 0 | AX6: =IFERROR(AX7+AX8+AX9+AX10,"") -> 0 | AY6: =IFERROR(AY7+AY8+AY9+AY10,"") -> 0 | AZ6: =IFERROR(AZ7+AZ8+AZ9+AZ10,"") -> 0 | BA6: =IFERROR(BA7+BA8+BA9+BA10,"") -> 0 | BB6: =BA6 -> 0 | BC6: =IFERROR(BC7+BC8+BC9+BC10,"") -> 0 | BD6: =IFERROR(BD7+BD8+BD9+BD10,"") -> 0 | BE6: =IFERROR(BE7+BE8+BE9+BE10,"") -> 0 | BF6: =IFERROR(BF7+BF8+BF9+BF10,"") -> 0 | BG6: =BF6 -> 0
B7: resale | C7: Fed funds vendidos e compromissadas reversas | D7: Fed funds sold and securities purchased under resale agreements | E7: =IF(ISNA(SUMIFS(INDEX(Inputs!$B$2:$AZ$190,,MATCH(SUBSTITUTE(E$3,"Q","T"),Inputs!$B$2:$AZ$2,0)),Inputs!$B$2:$B$190,$B7)*Inputs!$D$1),"",SUMIFS(INDEX(Inputs!$B$2:$AZ$190,,MATCH(SUBSTITUTE(E$3,"Q","T"),Inputs!$B$2:$AZ$2,0)),Inputs!$B$2:$B$190,$B7)*Inputs!$D$1) -> 0 | F7: =IF(ISNA(SUMIFS(INDEX(Inputs!$B$2:$AZ$190,,MATCH(SUBSTITUTE(F$3,"Q","T"),Inputs!$B$2:$AZ$2,0)),Inputs!$B$2:$B$190,$B7)*Inputs!$D$1),"",SUMIFS(INDEX(Inputs!$B$2:$AZ$190,,MATCH(SUBSTITUTE(F$3,"Q","T"),Inputs!$B$2:$AZ$2,0)),Inputs!$B$2:$B$190,$B7)*Inputs!$D$1) -> 0 | G7: =IF(ISNA(SUMIFS(INDEX(Inputs!$B$2:$AZ$190,,MATCH(SUBSTITUTE(G$3,"Q","T"),Inputs!$B$2:$AZ$2,0)),Inputs!$B$2:$B$190,$B7)*Inputs!$D$1),"",SUMIFS(INDEX(Inputs!$B$2:$AZ$190,,MATCH(SUBSTITUTE(G$3,"Q","T"),Inputs!$B$2:$AZ$2,0)),Inputs!$B$2:$B$190,$B7)*Inputs!$D$1) -> 0 | H7: =IF(ISNA(SUMIFS(INDEX(Inputs!$B$2:$AZ$190,,MATCH(SUBSTITUTE(H$3,"Q","T"),Inputs!$B$2:$AZ$2,0)),Inputs!$B$2:$B$190,$B7)*Inputs!$D$1),"",SUMIFS(INDEX(Inputs!$B$2:$AZ$190,,MATCH(SUBSTITUTE(H$3,"Q","T"),Inputs!$B$2:$AZ$2,0)),Inputs!$B$2:$B$190,$B7)*Inputs!$D$1) -> 0 | I7: =H7 -> 0 | J7: =IF(ISNA(SUMIFS(INDEX(Inputs!$B$2:$AZ$190,,MATCH(SUBSTITUTE(J$3,"Q","T"),Inputs!$B$2:$AZ$2,0)),Inputs!$B$2:$B$190,$B7)*Inputs!$D$1),"",SUMIFS(INDEX(Inputs!$B$2:$AZ$190,,MATCH(SUBSTITUTE(J$3,"Q","T"),Inputs!$B$2:$AZ$2,0)),Inputs!$B$2:$B$190,$B7)*Inputs!$D$1) -> 0 | K7: =IF(ISNA(SUMIFS(INDEX(Inputs!$B$2:$AZ$190,,MATCH(SUBSTITUTE(K$3,"Q","T"),Inputs!$B$2:$AZ$2,0)),Inputs!$B$2:$B$190,$B7)*Inputs!$D$1),"",SUMIFS(INDEX(Inputs!$B$2:$AZ$190,,MATCH(SUBSTITUTE(K$3,"Q","T"),Inputs!$B$2:$AZ$2,0)),Inputs!$B$2:$B$190,$B7)*Inputs!$D$1) -> 0 | L7: =IF(ISNA(SUMIFS(INDEX(Inputs!$B$2:$AZ$190,,MATCH(SUBSTITUTE(L$3,"Q","T"),Inputs!$B$2:$AZ$2,0)),Inputs!$B$2:$B$190,$B7)*Inputs!$D$1),"",SUMIFS(INDEX(Inputs!$B$2:$AZ$190,,MATCH(SUBSTITUTE(L$3,"Q","T"),Inputs!$B$2:$AZ$2,0)),Inputs!$B$2:$B$190,$B7)*Inputs!$D$1) -> 0 | M7: =IF(ISNA(SUMIFS(INDEX(Inputs!$B$2:$AZ$190,,MATCH(SUBSTITUTE(M$3,"Q","T"),Inputs!$B$2:$AZ$2,0)),Inputs!$B$2:$B$190,$B7)*Inputs!$D$1),"",SUMIFS(INDEX(Inputs!$B$2:$AZ$190,,MATCH(SUBSTITUTE(M$3,"Q","T"),Inputs!$B$2:$AZ$2,0)),Inputs!$B$2:$B$190,$B7)*Inputs!$D$1) -> 0 | N7: =M7 -> 0 | O7: =IF(ISNA(SUMIFS(INDEX(Inputs!$B$2:$AZ$190,,MATCH(SUBSTITUTE(O$3,"Q","T"),Inputs!$B$2:$AZ$2,0)),Inputs!$B$2:$B$190,$B7)*Inputs!$D$1),"",SUMIFS(INDEX(Inputs!$B$2:$AZ$190,,MATCH(SUBSTITUTE(O$3,"Q","T"),Inputs!$B$2:$AZ$2,0)),Inputs!$B$2:$B$190,$B7)*Inputs!$D$1) -> 0 | P7: =IF(ISNA(SUMIFS(INDEX(Inputs!$B$2:$AZ$190,,MATCH(SUBSTITUTE(P$3,"Q","T"),Inputs!$B$2:$AZ$2,0)),Inputs!$B$2:$B$190,$B7)*Inputs!$D$1),"",SUMIFS(INDEX(Inputs!$B$2:$AZ$190,,MATCH(SUBSTITUTE(P$3,"Q","T"),Inputs!$B$2:$AZ$2,0)),Inputs!$B$2:$B$190,$B7)*Inputs!$D$1) -> 0 | Q7: =IF(ISNA(SUMIFS(INDEX(Inputs!$B$2:$AZ$190,,MATCH(SUBSTITUTE(Q$3,"Q","T"),Inputs!$B$2:$AZ$2,0)),Inputs!$B$2:$B$190,$B7)*Inputs!$D$1),"",SUMIFS(INDEX(Inputs!$B$2:$AZ$190,,MATCH(SUBSTITUTE(Q$3,"Q","T"),Inputs!$B$2:$AZ$2,0)),Inputs!$B$2:$B$190,$B7)*Inputs!$D$1) -> 0 | R7: =IF(ISNA(SUMIFS(INDEX(Inputs!$B$2:$AZ$190,,MATCH(SUBSTITUTE(R$3,"Q","T"),Inputs!$B$2:$AZ$2,0)),Inputs!$B$2:$B$190,$B7)*Inputs!$D$1),"",SUMIFS(INDEX(Inputs!$B$2:$AZ$190,,MATCH(SUBSTITUTE(R$3,"Q","T"),Inputs!$B$2:$AZ$2,0)),Inputs!$B$2:$B$190,$B7)*Inputs!$D$1) -> 0 | S7: =R7 -> 0 | T7: =IF(ISNA(SUMIFS(INDEX(Inputs!$B$2:$AZ$190,,MATCH(SUBSTITUTE(T$3,"Q","T"),Inputs!$B$2:$AZ$2,0)),Inputs!$B$2:$B$190,$B7)*Inputs!$D$1),"",SUMIFS(INDEX(Inputs!$B$2:$AZ$190,,MATCH(SUBSTITUTE(T$3,"Q","T"),Inputs!$B$2:$AZ$2,0)),Inputs!$B$2:$B$190,$B7)*Inputs!$D$1) -> 0 | U7: =IF(ISNA(SUMIFS(INDEX(Inputs!$B$2:$AZ$190,,MATCH(SUBSTITUTE(U$3,"Q","T"),Inputs!$B$2:$AZ$2,0)),Inputs!$B$2:$B$190,$B7)*Inputs!$D$1),"",SUMIFS(INDEX(Inputs!$B$2:$AZ$190,,MATCH(SUBSTITUTE(U$3,"Q","T"),Inputs!$B$2:$AZ$2,0)),Inputs!$B$2:$B$190,$B7)*Inputs!$D$1) -> 0 | V7: =IF(ISNA(SUMIFS(INDEX(Inputs!$B$2:$AZ$190,,MATCH(SUBSTITUTE(V$3,"Q","T"),Inputs!$B$2:$AZ$2,0)),Inputs!$B$2:$B$190,$B7)*Inputs!$D$1),"",SUMIFS(INDEX(Inputs!$B$2:$AZ$190,,MATCH(SUBSTITUTE(V$3,"Q","T"),Inputs!$B$2:$AZ$2,0)),Inputs!$B$2:$B$190,$B7)*Inputs!$D$1) -> 0 | W7: =IF(ISNA(SUMIFS(INDEX(Inputs!$B$2:$AZ$190,,MATCH(SUBSTITUTE(W$3,"Q","T"),Inputs!$B$2:$AZ$2,0)),Inputs!$B$2:$B$190,$B7)*Inputs!$D$1),"",SUMIFS(INDEX(Inputs!$B$2:$AZ$190,,MATCH(SUBSTITUTE(W$3,"Q","T"),Inputs!$B$2:$AZ$2,0)),Inputs!$B$2:$B$190,$B7)*Inputs!$D$1) -> 0 | X7: =W7 -> 0 | Y7: =IF(ISNA(SUMIFS(INDEX(Inputs!$B$2:$AZ$190,,MATCH(SUBSTITUTE(Y$3,"Q","T"),Inputs!$B$2:$AZ$2,0)),Inputs!$B$2:$B$190,$B7)*Inputs!$D$1),"",SUMIFS(INDEX(Inputs!$B$2:$AZ$190,,MATCH(SUBSTITUTE(Y$3,"Q","T"),Inputs!$B$2:$AZ$2,0)),Inputs!$B$2:$B$190,$B7)*Inputs!$D$1) -> 0 | Z7: =IF(ISNA(SUMIFS(INDEX(Inputs!$B$2:$AZ$190,,MATCH(SUBSTITUTE(Z$3,"Q","T"),Inputs!$B$2:$AZ$2,0)),Inputs!$B$2:$B$190,$B7)*Inputs!$D$1),"",SUMIFS(INDEX(Inputs!$B$2:$AZ$190,,MATCH(SUBSTITUTE(Z$3,"Q","T"),Inputs!$B$2:$AZ$2,0)),Inputs!$B$2:$B$190,$B7)*Inputs!$D$1) -> 0 | AA7: =IF(ISNA(SUMIFS(INDEX(Inputs!$B$2:$AZ$190,,MATCH(SUBSTITUTE(AA$3,"Q","T"),Inputs!$B$2:$AZ$2,0)),Inputs!$B$2:$B$190,$B7)*Inputs!$D$1),"",SUMIFS(INDEX(Inputs!$B$2:$AZ$190,,MATCH(SUBSTITUTE(AA$3,"Q","T"),Inputs!$B$2:$AZ$2,0)),Inputs!$B$2:$B$190,$B7)*Inputs!$D$1) -> 0 | AB7: =IF(ISNA(SUMIFS(INDEX(Inputs!$B$2:$AZ$190,,MATCH(SUBSTITUTE(AB$3,"Q","T"),Inputs!$B$2:$AZ$2,0)),Inputs!$B$2:$B$190,$B7)*Inputs!$D$1),"",SUMIFS(INDEX(Inputs!$B$2:$AZ$190,,MATCH(SUBSTITUTE(AB$3,"Q","T"),Inputs!$B$2:$AZ$2,0)),Inputs!$B$2:$B$190,$B7)*Inputs!$D$1) -> 0 | AC7: =AB7 -> 0 | AD7: =IF(ISNA(SUMIFS(INDEX(Inputs!$B$2:$AZ$190,,MATCH(SUBSTITUTE(AD$3,"Q","T"),Inputs!$B$2:$AZ$2,0)),Inputs!$B$2:$B$190,$B7)*Inputs!$D$1),"",SUMIFS(INDEX(Inputs!$B$2:$AZ$190,,MATCH(SUBSTITUTE(AD$3,"Q","T"),Inputs!$B$2:$AZ$2,0)),Inputs!$B$2:$B$190,$B7)*Inputs!$D$1) -> 0 | AE7: =IF(ISNA(SUMIFS(INDEX(Inputs!$B$2:$AZ$190,,MATCH(SUBSTITUTE(AE$3,"Q","T"),Inputs!$B$2:$AZ$2,0)),Inputs!$B$2:$B$190,$B7)*Inputs!$D$1),"",SUMIFS(INDEX(Inputs!$B$2:$AZ$190,,MATCH(SUBSTITUTE(AE$3,"Q","T"),Inputs!$B$2:$AZ$2,0)),Inputs!$B$2:$B$190,$B7)*Inputs!$D$1) -> 0 | AF7: =IF(ISNA(SUMIFS(INDEX(Inputs!$B$2:$AZ$190,,MATCH(SUBSTITUTE(AF$3,"Q","T"),Inputs!$B$2:$AZ$2,0)),Inputs!$B$2:$B$190,$B7)*Inputs!$D$1),"",SUMIFS(INDEX(Inputs!$B$2:$AZ$190,,MATCH(SUBSTITUTE(AF$3,"Q","T"),Inputs!$B$2:$AZ$2,0)),Inputs!$B$2:$B$190,$B7)*Inputs!$D$1) -> 0 | AG7: =IF(ISNA(SUMIFS(INDEX(Inputs!$B$2:$AZ$190,,MATCH(SUBSTITUTE(AG$3,"Q","T"),Inputs!$B$2:$AZ$2,0)),Inputs!$B$2:$B$190,$B7)*Inputs!$D$1),"",SUMIFS(INDEX(Inputs!$B$2:$AZ$190,,MATCH(SUBSTITUTE(AG$3,"Q","T"),Inputs!$B$2:$AZ$2,0)),Inputs!$B$2:$B$190,$B7)*Inputs!$D$1) -> 0 | AH7: =AG7 -> 0 | AI7: =IF(ISNA(SUMIFS(INDEX(Inputs!$B$2:$AZ$190,,MATCH(SUBSTITUTE(AI$3,"Q","T"),Inputs!$B$2:$AZ$2,0)),Inputs!$B$2:$B$190,$B7)*Inputs!$D$1),"",SUMIFS(INDEX(Inputs!$B$2:$AZ$190,,MATCH(SUBSTITUTE(AI$3,"Q","T"),Inputs!$B$2:$AZ$2,0)),Inputs!$B$2:$B$190,$B7)*Inputs!$D$1) -> 0 | AJ7: =IF(ISNA(SUMIFS(INDEX(Inputs!$B$2:$AZ$190,,MATCH(SUBSTITUTE(AJ$3,"Q","T"),Inputs!$B$2:$AZ$2,0)),Inputs!$B$2:$B$190,$B7)*Inputs!$D$1),"",SUMIFS(INDEX(Inputs!$B$2:$AZ$190,,MATCH(SUBSTITUTE(AJ$3,"Q","T"),Inputs!$B$2:$AZ$2,0)),Inputs!$B$2:$B$190,$B7)*Inputs!$D$1) -> 0 | AK7: =IF(ISNA(SUMIFS(INDEX(Inputs!$B$2:$AZ$190,,MATCH(SUBSTITUTE(AK$3,"Q","T"),Inputs!$B$2:$AZ$2,0)),Inputs!$B$2:$B$190,$B7)*Inputs!$D$1),"",SUMIFS(INDEX(Inputs!$B$2:$AZ$190,,MATCH(SUBSTITUTE(AK$3,"Q","T"),Inputs!$B$2:$AZ$2,0)),Inputs!$B$2:$B$190,$B7)*Inputs!$D$1) -> 0 | AL7: =IF(ISNA(SUMIFS(INDEX(Inputs!$B$2:$AZ$190,,MATCH(SUBSTITUTE(AL$3,"Q","T"),Inputs!$B$2:$AZ$2,0)),Inputs!$B$2:$B$190,$B7)*Inputs!$D$1),"",SUMIFS(INDEX(Inputs!$B$2:$AZ$190,,MATCH(SUBSTITUTE(AL$3,"Q","T"),Inputs!$B$2:$AZ$2,0)),Inputs!$B$2:$B$190,$B7)*Inputs!$D$1) -> 0 | AM7: =AL7 -> 0 | AN7: =IF(ISNA(SUMIFS(INDEX(Inputs!$B$2:$AZ$190,,MATCH(SUBSTITUTE(AN$3,"Q","T"),Inputs!$B$2:$AZ$2,0)),Inputs!$B$2:$B$190,$B7)*Inputs!$D$1),"",SUMIFS(INDEX(Inputs!$B$2:$AZ$190,,MATCH(SUBSTITUTE(AN$3,"Q","T"),Inputs!$B$2:$AZ$2,0)),Inputs!$B$2:$B$190,$B7)*Inputs!$D$1) -> 0 | AO7: =IF(ISNA(SUMIFS(INDEX(Inputs!$B$2:$AZ$190,,MATCH(SUBSTITUTE(AO$3,"Q","T"),Inputs!$B$2:$AZ$2,0)),Inputs!$B$2:$B$190,$B7)*Inputs!$D$1),"",SUMIFS(INDEX(Inputs!$B$2:$AZ$190,,MATCH(SUBSTITUTE(AO$3,"Q","T"),Inputs!$B$2:$AZ$2,0)),Inputs!$B$2:$B$190,$B7)*Inputs!$D$1) -> 0 | AP7: =IF(ISNA(SUMIFS(INDEX(Inputs!$B$2:$AZ$190,,MATCH(SUBSTITUTE(AP$3,"Q","T"),Inputs!$B$2:$AZ$2,0)),Inputs!$B$2:$B$190,$B7)*Inputs!$D$1),"",SUMIFS(INDEX(Inputs!$B$2:$AZ$190,,MATCH(SUBSTITUTE(AP$3,"Q","T"),Inputs!$B$2:$AZ$2,0)),Inputs!$B$2:$B$190,$B7)*Inputs!$D$1) -> 0 | AQ7: =IF(ISNA(SUMIFS(INDEX(Inputs!$B$2:$AZ$190,,MATCH(SUBSTITUTE(AQ$3,"Q","T"),Inputs!$B$2:$AZ$2,0)),Inputs!$B$2:$B$190,$B7)*Inputs!$D$1),"",SUMIFS(INDEX(Inputs!$B$2:$AZ$190,,MATCH(SUBSTITUTE(AQ$3,"Q","T"),Inputs!$B$2:$AZ$2,0)),Inputs!$B$2:$B$190,$B7)*Inputs!$D$1) -> 0 | AR7: =AQ7 -> 0 | AS7: =IF(ISNA(SUMIFS(INDEX(Inputs!$B$2:$AZ$190,,MATCH(SUBSTITUTE(AS$3,"Q","T"),Inputs!$B$2:$AZ$2,0)),Inputs!$B$2:$B$190,$B7)*Inputs!$D$1),"",SUMIFS(INDEX(Inputs!$B$2:$AZ$190,,MATCH(SUBSTITUTE(AS$3,"Q","T"),Inputs!$B$2:$AZ$2,0)),Inputs!$B$2:$B$190,$B7)*Inputs!$D$1) -> 0 | AT7: =IF(ISNA(SUMIFS(INDEX(Inputs!$B$2:$AZ$190,,MATCH(SUBSTITUTE(AT$3,"Q","T"),Inputs!$B$2:$AZ$2,0)),Inputs!$B$2:$B$190,$B7)*Inputs!$D$1),"",SUMIFS(INDEX(Inputs!$B$2:$AZ$190,,MATCH(SUBSTITUTE(AT$3,"Q","T"),Inputs!$B$2:$AZ$2,0)),Inputs!$B$2:$B$190,$B7)*Inputs!$D$1) -> 0 | AU7: =IF(ISNA(SUMIFS(INDEX(Inputs!$B$2:$AZ$190,,MATCH(SUBSTITUTE(AU$3,"Q","T"),Inputs!$B$2:$AZ$2,0)),Inputs!$B$2:$B$190,$B7)*Inputs!$D$1),"",SUMIFS(INDEX(Inputs!$B$2:$AZ$190,,MATCH(SUBSTITUTE(AU$3,"Q","T"),Inputs!$B$2:$AZ$2,0)),Inputs!$B$2:$B$190,$B7)*Inputs!$D$1) -> 0 | AV7: =IF(ISNA(SUMIFS(INDEX(Inputs!$B$2:$AZ$190,,MATCH(SUBSTITUTE(AV$3,"Q","T"),Inputs!$B$2:$AZ$2,0)),Inputs!$B$2:$B$190,$B7)*Inputs!$D$1),"",SUMIFS(INDEX(Inputs!$B$2:$AZ$190,,MATCH(SUBSTITUTE(AV$3,"Q","T"),Inputs!$B$2:$AZ$2,0)),Inputs!$B$2:$B$190,$B7)*Inputs!$D$1) -> 0 | AW7: =AV7 -> 0 | AX7: =IF(ISNA(SUMIFS(INDEX(Inputs!$B$2:$AZ$190,,MATCH(SUBSTITUTE(AX$3,"Q","T"),Inputs!$B$2:$AZ$2,0)),Inputs!$B$2:$B$190,$B7)*Inputs!$D$1),"",SUMIFS(INDEX(Inputs!$B$2:$AZ$190,,MATCH(SUBSTITUTE(AX$3,"Q","T"),Inputs!$B$2:$AZ$2,0)),Inputs!$B$2:$B$190,$B7)*Inputs!$D$1) -> 0 | AY7: =IF(ISNA(SUMIFS(INDEX(Inputs!$B$2:$AZ$190,,MATCH(SUBSTITUTE(AY$3,"Q","T"),Inputs!$B$2:$AZ$2,0)),Inputs!$B$2:$B$190,$B7)*Inputs!$D$1),"",SUMIFS(INDEX(Inputs!$B$2:$AZ$190,,MATCH(SUBSTITUTE(AY$3,"Q","T"),Inputs!$B$2:$AZ$2,0)),Inputs!$B$2:$B$190,$B7)*Inputs!$D$1) -> 0 | AZ7: =IF(ISNA(SUMIFS(INDEX(Inputs!$B$2:$AZ$190,,MATCH(SUBSTITUTE(AZ$3,"Q","T"),Inputs!$B$2:$AZ$2,0)),Inputs!$B$2:$B$190,$B7)*Inputs!$D$1),"",SUMIFS(INDEX(Inputs!$B$2:$AZ$190,,MATCH(SUBSTITUTE(AZ$3,"Q","T"),Inputs!$B$2:$AZ$2,0)),Inputs!$B$2:$B$190,$B7)*Inputs!$D$1) -> 0 | BA7: =IF(ISNA(SUMIFS(INDEX(Inputs!$B$2:$AZ$190,,MATCH(SUBSTITUTE(BA$3,"Q","T"),Inputs!$B$2:$AZ$2,0)),Inputs!$B$2:$B$190,$B7)*Inputs!$D$1),"",SUMIFS(INDEX(Inputs!$B$2:$AZ$190,,MATCH(SUBSTITUTE(BA$3,"Q","T"),Inputs!$B$2:$AZ$2,0)),Inputs!$B$2:$B$190,$B7)*Inputs!$D$1) -> 0 | BB7: =BA7 -> 0 | BC7: =IF(ISNA(SUMIFS(INDEX(Inputs!$B$2:$AZ$190,,MATCH(SUBSTITUTE(BC$3,"Q","T"),Inputs!$B$2:$AZ$2,0)),Inputs!$B$2:$B$190,$B7)*Inputs!$D$1),"",SUMIFS(INDEX(Inputs!$B$2:$AZ$190,,MATCH(SUBSTITUTE(BC$3,"Q","T"),Inputs!$B$2:$AZ$2,0)),Inputs!$B$2:$B$190,$B7)*Inputs!$D$1) -> 0 | BD7: =IF(ISNA(SUMIFS(INDEX(Inputs!$B$2:$AZ$190,,MATCH(SUBSTITUTE(BD$3,"Q","T"),Inputs!$B$2:$AZ$2,0)),Inputs!$B$2:$B$190,$B7)*Inputs!$D$1),"",SUMIFS(INDEX(Inputs!$B$2:$AZ$190,,MATCH(SUBSTITUTE(BD$3,"Q","T"),Inputs!$B$2:$AZ$2,0)),Inputs!$B$2:$B$190,$B7)*Inputs!$D$1) -> 0 | BE7: =IF(ISNA(SUMIFS(INDEX(Inputs!$B$2:$AZ$190,,MATCH(SUBSTITUTE(BE$3,"Q","T"),Inputs!$B$2:$AZ$2,0)),Inputs!$B$2:$B$190,$B7)*Inputs!$D$1),"",SUMIFS(INDEX(Inputs!$B$2:$AZ$190,,MATCH(SUBSTITUTE(BE$3,"Q","T"),Inputs!$B$2:$AZ$2,0)),Inputs!$B$2:$B$190,$B7)*Inputs!$D$1) -> 0 | BF7: =IF(ISNA(SUMIFS(INDEX(Inputs!$B$2:$AZ$190,,MATCH(SUBSTITUTE(BF$3,"Q","T"),Inputs!$B$2:$AZ$2,0)),Inputs!$B$2:$B$190,$B7)*Inputs!$D$1),"",SUMIFS(INDEX(Inputs!$B$2:$AZ$190,,MATCH(SUBSTITUTE(BF$3,"Q","T"),Inputs!$B$2:$AZ$2,0)),Inputs!$B$2:$B$190,$B7)*Inputs!$D$1) -> 0 | BG7: =BF7 -> 0
B8: dep_banks | C8: Depósitos remunerados em bancos (inclui Federal Reserve) | D8: Deposits with banks | E8: =IF(ISNA(SUMIFS(INDEX(Inputs!$B$2:$AZ$190,,MATCH(SUBSTITUTE(E$3,"Q","T"),Inputs!$B$2:$AZ$2,0)),Inputs!$B$2:$B$190,$B8)*Inputs!$D$1),"",SUMIFS(INDEX(Inputs!$B$2:$AZ$190,,MATCH(SUBSTITUTE(E$3,"Q","T"),Inputs!$B$2:$AZ$2,0)),Inputs!$B$2:$B$190,$B8)*Inputs!$D$1) -> 0 | F8: =IF(ISNA(SUMIFS(INDEX(Inputs!$B$2:$AZ$190,,MATCH(SUBSTITUTE(F$3,"Q","T"),Inputs!$B$2:$AZ$2,0)),Inputs!$B$2:$B$190,$B8)*Inputs!$D$1),"",SUMIFS(INDEX(Inputs!$B$2:$AZ$190,,MATCH(SUBSTITUTE(F$3,"Q","T"),Inputs!$B$2:$AZ$2,0)),Inputs!$B$2:$B$190,$B8)*Inputs!$D$1) -> 0 | G8: =IF(ISNA(SUMIFS(INDEX(Inputs!$B$2:$AZ$190,,MATCH(SUBSTITUTE(G$3,"Q","T"),Inputs!$B$2:$AZ$2,0)),Inputs!$B$2:$B$190,$B8)*Inputs!$D$1),"",SUMIFS(INDEX(Inputs!$B$2:$AZ$190,,MATCH(SUBSTITUTE(G$3,"Q","T"),Inputs!$B$2:$AZ$2,0)),Inputs!$B$2:$B$190,$B8)*Inputs!$D$1) -> 0 | H8: =IF(ISNA(SUMIFS(INDEX(Inputs!$B$2:$AZ$190,,MATCH(SUBSTITUTE(H$3,"Q","T"),Inputs!$B$2:$AZ$2,0)),Inputs!$B$2:$B$190,$B8)*Inputs!$D$1),"",SUMIFS(INDEX(Inputs!$B$2:$AZ$190,,MATCH(SUBSTITUTE(H$3,"Q","T"),Inputs!$B$2:$AZ$2,0)),Inputs!$B$2:$B$190,$B8)*Inputs!$D$1) -> 0 | I8: =H8 -> 0 | J8: =IF(ISNA(SUMIFS(INDEX(Inputs!$B$2:$AZ$190,,MATCH(SUBSTITUTE(J$3,"Q","T"),Inputs!$B$2:$AZ$2,0)),Inputs!$B$2:$B$190,$B8)*Inputs!$D$1),"",SUMIFS(INDEX(Inputs!$B$2:$AZ$190,,MATCH(SUBSTITUTE(J$3,"Q","T"),Inputs!$B$2:$AZ$2,0)),Inputs!$B$2:$B$190,$B8)*Inputs!$D$1) -> 0 | K8: =IF(ISNA(SUMIFS(INDEX(Inputs!$B$2:$AZ$190,,MATCH(SUBSTITUTE(K$3,"Q","T"),Inputs!$B$2:$AZ$2,0)),Inputs!$B$2:$B$190,$B8)*Inputs!$D$1),"",SUMIFS(INDEX(Inputs!$B$2:$AZ$190,,MATCH(SUBSTITUTE(K$3,"Q","T"),Inputs!$B$2:$AZ$2,0)),Inputs!$B$2:$B$190,$B8)*Inputs!$D$1) -> 0 | L8: =IF(ISNA(SUMIFS(INDEX(Inputs!$B$2:$AZ$190,,MATCH(SUBSTITUTE(L$3,"Q","T"),Inputs!$B$2:$AZ$2,0)),Inputs!$B$2:$B$190,$B8)*Inputs!$D$1),"",SUMIFS(INDEX(Inputs!$B$2:$AZ$190,,MATCH(SUBSTITUTE(L$3,"Q","T"),Inputs!$B$2:$AZ$2,0)),Inputs!$B$2:$B$190,$B8)*Inputs!$D$1) -> 0 | M8: =IF(ISNA(SUMIFS(INDEX(Inputs!$B$2:$AZ$190,,MATCH(SUBSTITUTE(M$3,"Q","T"),Inputs!$B$2:$AZ$2,0)),Inputs!$B$2:$B$190,$B8)*Inputs!$D$1),"",SUMIFS(INDEX(Inputs!$B$2:$AZ$190,,MATCH(SUBSTITUTE(M$3,"Q","T"),Inputs!$B$2:$AZ$2,0)),Inputs!$B$2:$B$190,$B8)*Inputs!$D$1) -> 0 | N8: =M8 -> 0 | O8: =IF(ISNA(SUMIFS(INDEX(Inputs!$B$2:$AZ$190,,MATCH(SUBSTITUTE(O$3,"Q","T"),Inputs!$B$2:$AZ$2,0)),Inputs!$B$2:$B$190,$B8)*Inputs!$D$1),"",SUMIFS(INDEX(Inputs!$B$2:$AZ$190,,MATCH(SUBSTITUTE(O$3,"Q","T"),Inputs!$B$2:$AZ$2,0)),Inputs!$B$2:$B$190,$B8)*Inputs!$D$1) -> 0 | P8: =IF(ISNA(SUMIFS(INDEX(Inputs!$B$2:$AZ$190,,MATCH(SUBSTITUTE(P$3,"Q","T"),Inputs!$B$2:$AZ$2,0)),Inputs!$B$2:$B$190,$B8)*Inputs!$D$1),"",SUMIFS(INDEX(Inputs!$B$2:$AZ$190,,MATCH(SUBSTITUTE(P$3,"Q","T"),Inputs!$B$2:$AZ$2,0)),Inputs!$B$2:$B$190,$B8)*Inputs!$D$1) -> 0 | Q8: =IF(ISNA(SUMIFS(INDEX(Inputs!$B$2:$AZ$190,,MATCH(SUBSTITUTE(Q$3,"Q","T"),Inputs!$B$2:$AZ$2,0)),Inputs!$B$2:$B$190,$B8)*Inputs!$D$1),"",SUMIFS(INDEX(Inputs!$B$2:$AZ$190,,MATCH(SUBSTITUTE(Q$3,"Q","T"),Inputs!$B$2:$AZ$2,0)),Inputs!$B$2:$B$190,$B8)*Inputs!$D$1) -> 0 | R8: =IF(ISNA(SUMIFS(INDEX(Inputs!$B$2:$AZ$190,,MATCH(SUBSTITUTE(R$3,"Q","T"),Inputs!$B$2:$AZ$2,0)),Inputs!$B$2:$B$190,$B8)*Inputs!$D$1),"",SUMIFS(INDEX(Inputs!$B$2:$AZ$190,,MATCH(SUBSTITUTE(R$3,"Q","T"),Inputs!$B$2:$AZ$2,0)),Inputs!$B$2:$B$190,$B8)*Inputs!$D$1) -> 0 | S8: =R8 -> 0 | T8: =IF(ISNA(SUMIFS(INDEX(Inputs!$B$2:$AZ$190,,MATCH(SUBSTITUTE(T$3,"Q","T"),Inputs!$B$2:$AZ$2,0)),Inputs!$B$2:$B$190,$B8)*Inputs!$D$1),"",SUMIFS(INDEX(Inputs!$B$2:$AZ$190,,MATCH(SUBSTITUTE(T$3,"Q","T"),Inputs!$B$2:$AZ$2,0)),Inputs!$B$2:$B$190,$B8)*Inputs!$D$1) -> 0 | U8: =IF(ISNA(SUMIFS(INDEX(Inputs!$B$2:$AZ$190,,MATCH(SUBSTITUTE(U$3,"Q","T"),Inputs!$B$2:$AZ$2,0)),Inputs!$B$2:$B$190,$B8)*Inputs!$D$1),"",SUMIFS(INDEX(Inputs!$B$2:$AZ$190,,MATCH(SUBSTITUTE(U$3,"Q","T"),Inputs!$B$2:$AZ$2,0)),Inputs!$B$2:$B$190,$B8)*Inputs!$D$1) -> 0 | V8: =IF(ISNA(SUMIFS(INDEX(Inputs!$B$2:$AZ$190,,MATCH(SUBSTITUTE(V$3,"Q","T"),Inputs!$B$2:$AZ$2,0)),Inputs!$B$2:$B$190,$B8)*Inputs!$D$1),"",SUMIFS(INDEX(Inputs!$B$2:$AZ$190,,MATCH(SUBSTITUTE(V$3,"Q","T"),Inputs!$B$2:$AZ$2,0)),Inputs!$B$2:$B$190,$B8)*Inputs!$D$1) -> 0 | W8: =IF(ISNA(SUMIFS(INDEX(Inputs!$B$2:$AZ$190,,MATCH(SUBSTITUTE(W$3,"Q","T"),Inputs!$B$2:$AZ$2,0)),Inputs!$B$2:$B$190,$B8)*Inputs!$D$1),"",SUMIFS(INDEX(Inputs!$B$2:$AZ$190,,MATCH(SUBSTITUTE(W$3,"Q","T"),Inputs!$B$2:$AZ$2,0)),Inputs!$B$2:$B$190,$B8)*Inputs!$D$1) -> 0 | X8: =W8 -> 0 | Y8: =IF(ISNA(SUMIFS(INDEX(Inputs!$B$2:$AZ$190,,MATCH(SUBSTITUTE(Y$3,"Q","T"),Inputs!$B$2:$AZ$2,0)),Inputs!$B$2:$B$190,$B8)*Inputs!$D$1),"",SUMIFS(INDEX(Inputs!$B$2:$AZ$190,,MATCH(SUBSTITUTE(Y$3,"Q","T"),Inputs!$B$2:$AZ$2,0)),Inputs!$B$2:$B$190,$B8)*Inputs!$D$1) -> 0 | Z8: =IF(ISNA(SUMIFS(INDEX(Inputs!$B$2:$AZ$190,,MATCH(SUBSTITUTE(Z$3,"Q","T"),Inputs!$B$2:$AZ$2,0)),Inputs!$B$2:$B$190,$B8)*Inputs!$D$1),"",SUMIFS(INDEX(Inputs!$B$2:$AZ$190,,MATCH(SUBSTITUTE(Z$3,"Q","T"),Inputs!$B$2:$AZ$2,0)),Inputs!$B$2:$B$190,$B8)*Inputs!$D$1) -> 0 | AA8: =IF(ISNA(SUMIFS(INDEX(Inputs!$B$2:$AZ$190,,MATCH(SUBSTITUTE(AA$3,"Q","T"),Inputs!$B$2:$AZ$2,0)),Inputs!$B$2:$B$190,$B8)*Inputs!$D$1),"",SUMIFS(INDEX(Inputs!$B$2:$AZ$190,,MATCH(SUBSTITUTE(AA$3,"Q","T"),Inputs!$B$2:$AZ$2,0)),Inputs!$B$2:$B$190,$B8)*Inputs!$D$1) -> 0 | AB8: =IF(ISNA(SUMIFS(INDEX(Inputs!$B$2:$AZ$190,,MATCH(SUBSTITUTE(AB$3,"Q","T"),Inputs!$B$2:$AZ$2,0)),Inputs!$B$2:$B$190,$B8)*Inputs!$D$1),"",SUMIFS(INDEX(Inputs!$B$2:$AZ$190,,MATCH(SUBSTITUTE(AB$3,"Q","T"),Inputs!$B$2:$AZ$2,0)),Inputs!$B$2:$B$190,$B8)*Inputs!$D$1) -> 0 | AC8: =AB8 -> 0 | AD8: =IF(ISNA(SUMIFS(INDEX(Inputs!$B$2:$AZ$190,,MATCH(SUBSTITUTE(AD$3,"Q","T"),Inputs!$B$2:$AZ$2,0)),Inputs!$B$2:$B$190,$B8)*Inputs!$D$1),"",SUMIFS(INDEX(Inputs!$B$2:$AZ$190,,MATCH(SUBSTITUTE(AD$3,"Q","T"),Inputs!$B$2:$AZ$2,0)),Inputs!$B$2:$B$190,$B8)*Inputs!$D$1) -> 0 | AE8: =IF(ISNA(SUMIFS(INDEX(Inputs!$B$2:$AZ$190,,MATCH(SUBSTITUTE(AE$3,"Q","T"),Inputs!$B$2:$AZ$2,0)),Inputs!$B$2:$B$190,$B8)*Inputs!$D$1),"",SUMIFS(INDEX(Inputs!$B$2:$AZ$190,,MATCH(SUBSTITUTE(AE$3,"Q","T"),Inputs!$B$2:$AZ$2,0)),Inputs!$B$2:$B$190,$B8)*Inputs!$D$1) -> 0 | AF8: =IF(ISNA(SUMIFS(INDEX(Inputs!$B$2:$AZ$190,,MATCH(SUBSTITUTE(AF$3,"Q","T"),Inputs!$B$2:$AZ$2,0)),Inputs!$B$2:$B$190,$B8)*Inputs!$D$1),"",SUMIFS(INDEX(Inputs!$B$2:$AZ$190,,MATCH(SUBSTITUTE(AF$3,"Q","T"),Inputs!$B$2:$AZ$2,0)),Inputs!$B$2:$B$190,$B8)*Inputs!$D$1) -> 0 | AG8: =IF(ISNA(SUMIFS(INDEX(Inputs!$B$2:$AZ$190,,MATCH(SUBSTITUTE(AG$3,"Q","T"),Inputs!$B$2:$AZ$2,0)),Inputs!$B$2:$B$190,$B8)*Inputs!$D$1),"",SUMIFS(INDEX(Inputs!$B$2:$AZ$190,,MATCH(SUBSTITUTE(AG$3,"Q","T"),Inputs!$B$2:$AZ$2,0)),Inputs!$B$2:$B$190,$B8)*Inputs!$D$1) -> 0 | AH8: =AG8 -> 0 | AI8: =IF(ISNA(SUMIFS(INDEX(Inputs!$B$2:$AZ$190,,MATCH(SUBSTITUTE(AI$3,"Q","T"),Inputs!$B$2:$AZ$2,0)),Inputs!$B$2:$B$190,$B8)*Inputs!$D$1),"",SUMIFS(INDEX(Inputs!$B$2:$AZ$190,,MATCH(SUBSTITUTE(AI$3,"Q","T"),Inputs!$B$2:$AZ$2,0)),Inputs!$B$2:$B$190,$B8)*Inputs!$D$1) -> 0 | AJ8: =IF(ISNA(SUMIFS(INDEX(Inputs!$B$2:$AZ$190,,MATCH(SUBSTITUTE(AJ$3,"Q","T"),Inputs!$B$2:$AZ$2,0)),Inputs!$B$2:$B$190,$B8)*Inputs!$D$1),"",SUMIFS(INDEX(Inputs!$B$2:$AZ$190,,MATCH(SUBSTITUTE(AJ$3,"Q","T"),Inputs!$B$2:$AZ$2,0)),Inputs!$B$2:$B$190,$B8)*Inputs!$D$1) -> 0 | AK8: =IF(ISNA(SUMIFS(INDEX(Inputs!$B$2:$AZ$190,,MATCH(SUBSTITUTE(AK$3,"Q","T"),Inputs!$B$2:$AZ$2,0)),Inputs!$B$2:$B$190,$B8)*Inputs!$D$1),"",SUMIFS(INDEX(Inputs!$B$2:$AZ$190,,MATCH(SUBSTITUTE(AK$3,"Q","T"),Inputs!$B$2:$AZ$2,0)),Inputs!$B$2:$B$190,$B8)*Inputs!$D$1) -> 0 | AL8: =IF(ISNA(SUMIFS(INDEX(Inputs!$B$2:$AZ$190,,MATCH(SUBSTITUTE(AL$3,"Q","T"),Inputs!$B$2:$AZ$2,0)),Inputs!$B$2:$B$190,$B8)*Inputs!$D$1),"",SUMIFS(INDEX(Inputs!$B$2:$AZ$190,,MATCH(SUBSTITUTE(AL$3,"Q","T"),Inputs!$B$2:$AZ$2,0)),Inputs!$B$2:$B$190,$B8)*Inputs!$D$1) -> 0 | AM8: =AL8 -> 0 | AN8: =IF(ISNA(SUMIFS(INDEX(Inputs!$B$2:$AZ$190,,MATCH(SUBSTITUTE(AN$3,"Q","T"),Inputs!$B$2:$AZ$2,0)),Inputs!$B$2:$B$190,$B8)*Inputs!$D$1),"",SUMIFS(INDEX(Inputs!$B$2:$AZ$190,,MATCH(SUBSTITUTE(AN$3,"Q","T"),Inputs!$B$2:$AZ$2,0)),Inputs!$B$2:$B$190,$B8)*Inputs!$D$1) -> 0 | AO8: =IF(ISNA(SUMIFS(INDEX(Inputs!$B$2:$AZ$190,,MATCH(SUBSTITUTE(AO$3,"Q","T"),Inputs!$B$2:$AZ$2,0)),Inputs!$B$2:$B$190,$B8)*Inputs!$D$1),"",SUMIFS(INDEX(Inputs!$B$2:$AZ$190,,MATCH(SUBSTITUTE(AO$3,"Q","T"),Inputs!$B$2:$AZ$2,0)),Inputs!$B$2:$B$190,$B8)*Inputs!$D$1) -> 0 | AP8: =IF(ISNA(SUMIFS(INDEX(Inputs!$B$2:$AZ$190,,MATCH(SUBSTITUTE(AP$3,"Q","T"),Inputs!$B$2:$AZ$2,0)),Inputs!$B$2:$B$190,$B8)*Inputs!$D$1),"",SUMIFS(INDEX(Inputs!$B$2:$AZ$190,,MATCH(SUBSTITUTE(AP$3,"Q","T"),Inputs!$B$2:$AZ$2,0)),Inputs!$B$2:$B$190,$B8)*Inputs!$D$1) -> 0 | AQ8: =IF(ISNA(SUMIFS(INDEX(Inputs!$B$2:$AZ$190,,MATCH(SUBSTITUTE(AQ$3,"Q","T"),Inputs!$B$2:$AZ$2,0)),Inputs!$B$2:$B$190,$B8)*Inputs!$D$1),"",SUMIFS(INDEX(Inputs!$B$2:$AZ$190,,MATCH(SUBSTITUTE(AQ$3,"Q","T"),Inputs!$B$2:$AZ$2,0)),Inputs!$B$2:$B$190,$B8)*Inputs!$D$1) -> 0 | AR8: =AQ8 -> 0 | AS8: =IF(ISNA(SUMIFS(INDEX(Inputs!$B$2:$AZ$190,,MATCH(SUBSTITUTE(AS$3,"Q","T"),Inputs!$B$2:$AZ$2,0)),Inputs!$B$2:$B$190,$B8)*Inputs!$D$1),"",SUMIFS(INDEX(Inputs!$B$2:$AZ$190,,MATCH(SUBSTITUTE(AS$3,"Q","T"),Inputs!$B$2:$AZ$2,0)),Inputs!$B$2:$B$190,$B8)*Inputs!$D$1) -> 0 | AT8: =IF(ISNA(SUMIFS(INDEX(Inputs!$B$2:$AZ$190,,MATCH(SUBSTITUTE(AT$3,"Q","T"),Inputs!$B$2:$AZ$2,0)),Inputs!$B$2:$B$190,$B8)*Inputs!$D$1),"",SUMIFS(INDEX(Inputs!$B$2:$AZ$190,,MATCH(SUBSTITUTE(AT$3,"Q","T"),Inputs!$B$2:$AZ$2,0)),Inputs!$B$2:$B$190,$B8)*Inputs!$D$1) -> 0 | AU8: =IF(ISNA(SUMIFS(INDEX(Inputs!$B$2:$AZ$190,,MATCH(SUBSTITUTE(AU$3,"Q","T"),Inputs!$B$2:$AZ$2,0)),Inputs!$B$2:$B$190,$B8)*Inputs!$D$1),"",SUMIFS(INDEX(Inputs!$B$2:$AZ$190,,MATCH(SUBSTITUTE(AU$3,"Q","T"),Inputs!$B$2:$AZ$2,0)),Inputs!$B$2:$B$190,$B8)*Inputs!$D$1) -> 0 | AV8: =IF(ISNA(SUMIFS(INDEX(Inputs!$B$2:$AZ$190,,MATCH(SUBSTITUTE(AV$3,"Q","T"),Inputs!$B$2:$AZ$2,0)),Inputs!$B$2:$B$190,$B8)*Inputs!$D$1),"",SUMIFS(INDEX(Inputs!$B$2:$AZ$190,,MATCH(SUBSTITUTE(AV$3,"Q","T"),Inputs!$B$2:$AZ$2,0)),Inputs!$B$2:$B$190,$B8)*Inputs!$D$1) -> 0 | AW8: =AV8 -> 0 | AX8: =IF(ISNA(SUMIFS(INDEX(Inputs!$B$2:$AZ$190,,MATCH(SUBSTITUTE(AX$3,"Q","T"),Inputs!$B$2:$AZ$2,0)),Inputs!$B$2:$B$190,$B8)*Inputs!$D$1),"",SUMIFS(INDEX(Inputs!$B$2:$AZ$190,,MATCH(SUBSTITUTE(AX$3,"Q","T"),Inputs!$B$2:$AZ$2,0)),Inputs!$B$2:$B$190,$B8)*Inputs!$D$1) -> 0 | AY8: =IF(ISNA(SUMIFS(INDEX(Inputs!$B$2:$AZ$190,,MATCH(SUBSTITUTE(AY$3,"Q","T"),Inputs!$B$2:$AZ$2,0)),Inputs!$B$2:$B$190,$B8)*Inputs!$D$1),"",SUMIFS(INDEX(Inputs!$B$2:$AZ$190,,MATCH(SUBSTITUTE(AY$3,"Q","T"),Inputs!$B$2:$AZ$2,0)),Inputs!$B$2:$B$190,$B8)*Inputs!$D$1) -> 0 | AZ8: =IF(ISNA(SUMIFS(INDEX(Inputs!$B$2:$AZ$190,,MATCH(SUBSTITUTE(AZ$3,"Q","T"),Inputs!$B$2:$AZ$2,0)),Inputs!$B$2:$B$190,$B8)*Inputs!$D$1),"",SUMIFS(INDEX(Inputs!$B$2:$AZ$190,,MATCH(SUBSTITUTE(AZ$3,"Q","T"),Inputs!$B$2:$AZ$2,0)),Inputs!$B$2:$B$190,$B8)*Inputs!$D$1) -> 0 | BA8: =IF(ISNA(SUMIFS(INDEX(Inputs!$B$2:$AZ$190,,MATCH(SUBSTITUTE(BA$3,"Q","T"),Inputs!$B$2:$AZ$2,0)),Inputs!$B$2:$B$190,$B8)*Inputs!$D$1),"",SUMIFS(INDEX(Inputs!$B$2:$AZ$190,,MATCH(SUBSTITUTE(BA$3,"Q","T"),Inputs!$B$2:$AZ$2,0)),Inputs!$B$2:$B$190,$B8)*Inputs!$D$1) -> 0 | BB8: =BA8 -> 0 | BC8: =IF(ISNA(SUMIFS(INDEX(Inputs!$B$2:$AZ$190,,MATCH(SUBSTITUTE(BC$3,"Q","T"),Inputs!$B$2:$AZ$2,0)),Inputs!$B$2:$B$190,$B8)*Inputs!$D$1),"",SUMIFS(INDEX(Inputs!$B$2:$AZ$190,,MATCH(SUBSTITUTE(BC$3,"Q","T"),Inputs!$B$2:$AZ$2,0)),Inputs!$B$2:$B$190,$B8)*Inputs!$D$1) -> 0 | BD8: =IF(ISNA(SUMIFS(INDEX(Inputs!$B$2:$AZ$190,,MATCH(SUBSTITUTE(BD$3,"Q","T"),Inputs!$B$2:$AZ$2,0)),Inputs!$B$2:$B$190,$B8)*Inputs!$D$1),"",SUMIFS(INDEX(Inputs!$B$2:$AZ$190,,MATCH(SUBSTITUTE(BD$3,"Q","T"),Inputs!$B$2:$AZ$2,0)),Inputs!$B$2:$B$190,$B8)*Inputs!$D$1) -> 0 | BE8: =IF(ISNA(SUMIFS(INDEX(Inputs!$B$2:$AZ$190,,MATCH(SUBSTITUTE(BE$3,"Q","T"),Inputs!$B$2:$AZ$2,0)),Inputs!$B$2:$B$190,$B8)*Inputs!$D$1),"",SUMIFS(INDEX(Inputs!$B$2:$AZ$190,,MATCH(SUBSTITUTE(BE$3,"Q","T"),Inputs!$B$2:$AZ$2,0)),Inputs!$B$2:$B$190,$B8)*Inputs!$D$1) -> 0 | BF8: =IF(ISNA(SUMIFS(INDEX(Inputs!$B$2:$AZ$190,,MATCH(SUBSTITUTE(BF$3,"Q","T"),Inputs!$B$2:$AZ$2,0)),Inputs!$B$2:$B$190,$B8)*Inputs!$D$1),"",SUMIFS(INDEX(Inputs!$B$2:$AZ$190,,MATCH(SUBSTITUTE(BF$3,"Q","T"),Inputs!$B$2:$AZ$2,0)),Inputs!$B$2:$B$190,$B8)*Inputs!$D$1) -> 0 | BG8: =BF8 -> 0
B9: sec_borrowed | C9: Títulos tomados em empréstimo (securities borrowed) | D9: Securities borrowed | E9: =IF(ISNA(SUMIFS(INDEX(Inputs!$B$2:$AZ$190,,MATCH(SUBSTITUTE(E$3,"Q","T"),Inputs!$B$2:$AZ$2,0)),Inputs!$B$2:$B$190,$B9)*Inputs!$D$1),"",SUMIFS(INDEX(Inputs!$B$2:$AZ$190,,MATCH(SUBSTITUTE(E$3,"Q","T"),Inputs!$B$2:$AZ$2,0)),Inputs!$B$2:$B$190,$B9)*Inputs!$D$1) -> 0 | F9: =IF(ISNA(SUMIFS(INDEX(Inputs!$B$2:$AZ$190,,MATCH(SUBSTITUTE(F$3,"Q","T"),Inputs!$B$2:$AZ$2,0)),Inputs!$B$2:$B$190,$B9)*Inputs!$D$1),"",SUMIFS(INDEX(Inputs!$B$2:$AZ$190,,MATCH(SUBSTITUTE(F$3,"Q","T"),Inputs!$B$2:$AZ$2,0)),Inputs!$B$2:$B$190,$B9)*Inputs!$D$1) -> 0 | G9: =IF(ISNA(SUMIFS(INDEX(Inputs!$B$2:$AZ$190,,MATCH(SUBSTITUTE(G$3,"Q","T"),Inputs!$B$2:$AZ$2,0)),Inputs!$B$2:$B$190,$B9)*Inputs!$D$1),"",SUMIFS(INDEX(Inputs!$B$2:$AZ$190,,MATCH(SUBSTITUTE(G$3,"Q","T"),Inputs!$B$2:$AZ$2,0)),Inputs!$B$2:$B$190,$B9)*Inputs!$D$1) -> 0 | H9: =IF(ISNA(SUMIFS(INDEX(Inputs!$B$2:$AZ$190,,MATCH(SUBSTITUTE(H$3,"Q","T"),Inputs!$B$2:$AZ$2,0)),Inputs!$B$2:$B$190,$B9)*Inputs!$D$1),"",SUMIFS(INDEX(Inputs!$B$2:$AZ$190,,MATCH(SUBSTITUTE(H$3,"Q","T"),Inputs!$B$2:$AZ$2,0)),Inputs!$B$2:$B$190,$B9)*Inputs!$D$1) -> 0 | I9: =H9 -> 0 | J9: =IF(ISNA(SUMIFS(INDEX(Inputs!$B$2:$AZ$190,,MATCH(SUBSTITUTE(J$3,"Q","T"),Inputs!$B$2:$AZ$2,0)),Inputs!$B$2:$B$190,$B9)*Inputs!$D$1),"",SUMIFS(INDEX(Inputs!$B$2:$AZ$190,,MATCH(SUBSTITUTE(J$3,"Q","T"),Inputs!$B$2:$AZ$2,0)),Inputs!$B$2:$B$190,$B9)*Inputs!$D$1) -> 0 | K9: =IF(ISNA(SUMIFS(INDEX(Inputs!$B$2:$AZ$190,,MATCH(SUBSTITUTE(K$3,"Q","T"),Inputs!$B$2:$AZ$2,0)),Inputs!$B$2:$B$190,$B9)*Inputs!$D$1),"",SUMIFS(INDEX(Inputs!$B$2:$AZ$190,,MATCH(SUBSTITUTE(K$3,"Q","T"),Inputs!$B$2:$AZ$2,0)),Inputs!$B$2:$B$190,$B9)*Inputs!$D$1) -> 0 | L9: =IF(ISNA(SUMIFS(INDEX(Inputs!$B$2:$AZ$190,,MATCH(SUBSTITUTE(L$3,"Q","T"),Inputs!$B$2:$AZ$2,0)),Inputs!$B$2:$B$190,$B9)*Inputs!$D$1),"",SUMIFS(INDEX(Inputs!$B$2:$AZ$190,,MATCH(SUBSTITUTE(L$3,"Q","T"),Inputs!$B$2:$AZ$2,0)),Inputs!$B$2:$B$190,$B9)*Inputs!$D$1) -> 0 | M9: =IF(ISNA(SUMIFS(INDEX(Inputs!$B$2:$AZ$190,,MATCH(SUBSTITUTE(M$3,"Q","T"),Inputs!$B$2:$AZ$2,0)),Inputs!$B$2:$B$190,$B9)*Inputs!$D$1),"",SUMIFS(INDEX(Inputs!$B$2:$AZ$190,,MATCH(SUBSTITUTE(M$3,"Q","T"),Inputs!$B$2:$AZ$2,0)),Inputs!$B$2:$B$190,$B9)*Inputs!$D$1) -> 0 | N9: =M9 -> 0 | O9: =IF(ISNA(SUMIFS(INDEX(Inputs!$B$2:$AZ$190,,MATCH(SUBSTITUTE(O$3,"Q","T"),Inputs!$B$2:$AZ$2,0)),Inputs!$B$2:$B$190,$B9)*Inputs!$D$1),"",SUMIFS(INDEX(Inputs!$B$2:$AZ$190,,MATCH(SUBSTITUTE(O$3,"Q","T"),Inputs!$B$2:$AZ$2,0)),Inputs!$B$2:$B$190,$B9)*Inputs!$D$1) -> 0 | P9: =IF(ISNA(SUMIFS(INDEX(Inputs!$B$2:$AZ$190,,MATCH(SUBSTITUTE(P$3,"Q","T"),Inputs!$B$2:$AZ$2,0)),Inputs!$B$2:$B$190,$B9)*Inputs!$D$1),"",SUMIFS(INDEX(Inputs!$B$2:$AZ$190,,MATCH(SUBSTITUTE(P$3,"Q","T"),Inputs!$B$2:$AZ$2,0)),Inputs!$B$2:$B$190,$B9)*Inputs!$D$1) -> 0 | Q9: =IF(ISNA(SUMIFS(INDEX(Inputs!$B$2:$AZ$190,,MATCH(SUBSTITUTE(Q$3,"Q","T"),Inputs!$B$2:$AZ$2,0)),Inputs!$B$2:$B$190,$B9)*Inputs!$D$1),"",SUMIFS(INDEX(Inputs!$B$2:$AZ$190,,MATCH(SUBSTITUTE(Q$3,"Q","T"),Inputs!$B$2:$AZ$2,0)),Inputs!$B$2:$B$190,$B9)*Inputs!$D$1) -> 0 | R9: =IF(ISNA(SUMIFS(INDEX(Inputs!$B$2:$AZ$190,,MATCH(SUBSTITUTE(R$3,"Q","T"),Inputs!$B$2:$AZ$2,0)),Inputs!$B$2:$B$190,$B9)*Inputs!$D$1),"",SUMIFS(INDEX(Inputs!$B$2:$AZ$190,,MATCH(SUBSTITUTE(R$3,"Q","T"),Inputs!$B$2:$AZ$2,0)),Inputs!$B$2:$B$190,$B9)*Inputs!$D$1) -> 0 | S9: =R9 -> 0 | T9: =IF(ISNA(SUMIFS(INDEX(Inputs!$B$2:$AZ$190,,MATCH(SUBSTITUTE(T$3,"Q","T"),Inputs!$B$2:$AZ$2,0)),Inputs!$B$2:$B$190,$B9)*Inputs!$D$1),"",SUMIFS(INDEX(Inputs!$B$2:$AZ$190,,MATCH(SUBSTITUTE(T$3,"Q","T"),Inputs!$B$2:$AZ$2,0)),Inputs!$B$2:$B$190,$B9)*Inputs!$D$1) -> 0 | U9: =IF(ISNA(SUMIFS(INDEX(Inputs!$B$2:$AZ$190,,MATCH(SUBSTITUTE(U$3,"Q","T"),Inputs!$B$2:$AZ$2,0)),Inputs!$B$2:$B$190,$B9)*Inputs!$D$1),"",SUMIFS(INDEX(Inputs!$B$2:$AZ$190,,MATCH(SUBSTITUTE(U$3,"Q","T"),Inputs!$B$2:$AZ$2,0)),Inputs!$B$2:$B$190,$B9)*Inputs!$D$1) -> 0 | V9: =IF(ISNA(SUMIFS(INDEX(Inputs!$B$2:$AZ$190,,MATCH(SUBSTITUTE(V$3,"Q","T"),Inputs!$B$2:$AZ$2,0)),Inputs!$B$2:$B$190,$B9)*Inputs!$D$1),"",SUMIFS(INDEX(Inputs!$B$2:$AZ$190,,MATCH(SUBSTITUTE(V$3,"Q","T"),Inputs!$B$2:$AZ$2,0)),Inputs!$B$2:$B$190,$B9)*Inputs!$D$1) -> 0 | W9: =IF(ISNA(SUMIFS(INDEX(Inputs!$B$2:$AZ$190,,MATCH(SUBSTITUTE(W$3,"Q","T"),Inputs!$B$2:$AZ$2,0)),Inputs!$B$2:$B$190,$B9)*Inputs!$D$1),"",SUMIFS(INDEX(Inputs!$B$2:$AZ$190,,MATCH(SUBSTITUTE(W$3,"Q","T"),Inputs!$B$2:$AZ$2,0)),Inputs!$B$2:$B$190,$B9)*Inputs!$D$1) -> 0 | X9: =W9 -> 0 | Y9: =IF(ISNA(SUMIFS(INDEX(Inputs!$B$2:$AZ$190,,MATCH(SUBSTITUTE(Y$3,"Q","T"),Inputs!$B$2:$AZ$2,0)),Inputs!$B$2:$B$190,$B9)*Inputs!$D$1),"",SUMIFS(INDEX(Inputs!$B$2:$AZ$190,,MATCH(SUBSTITUTE(Y$3,"Q","T"),Inputs!$B$2:$AZ$2,0)),Inputs!$B$2:$B$190,$B9)*Inputs!$D$1) -> 0 | Z9: =IF(ISNA(SUMIFS(INDEX(Inputs!$B$2:$AZ$190,,MATCH(SUBSTITUTE(Z$3,"Q","T"),Inputs!$B$2:$AZ$2,0)),Inputs!$B$2:$B$190,$B9)*Inputs!$D$1),"",SUMIFS(INDEX(Inputs!$B$2:$AZ$190,,MATCH(SUBSTITUTE(Z$3,"Q","T"),Inputs!$B$2:$AZ$2,0)),Inputs!$B$2:$B$190,$B9)*Inputs!$D$1) -> 0 | AA9: =IF(ISNA(SUMIFS(INDEX(Inputs!$B$2:$AZ$190,,MATCH(SUBSTITUTE(AA$3,"Q","T"),Inputs!$B$2:$AZ$2,0)),Inputs!$B$2:$B$190,$B9)*Inputs!$D$1),"",SUMIFS(INDEX(Inputs!$B$2:$AZ$190,,MATCH(SUBSTITUTE(AA$3,"Q","T"),Inputs!$B$2:$AZ$2,0)),Inputs!$B$2:$B$190,$B9)*Inputs!$D$1) -> 0 | AB9: =IF(ISNA(SUMIFS(INDEX(Inputs!$B$2:$AZ$190,,MATCH(SUBSTITUTE(AB$3,"Q","T"),Inputs!$B$2:$AZ$2,0)),Inputs!$B$2:$B$190,$B9)*Inputs!$D$1),"",SUMIFS(INDEX(Inputs!$B$2:$AZ$190,,MATCH(SUBSTITUTE(AB$3,"Q","T"),Inputs!$B$2:$AZ$2,0)),Inputs!$B$2:$B$190,$B9)*Inputs!$D$1) -> 0 | AC9: =AB9 -> 0 | AD9: =IF(ISNA(SUMIFS(INDEX(Inputs!$B$2:$AZ$190,,MATCH(SUBSTITUTE(AD$3,"Q","T"),Inputs!$B$2:$AZ$2,0)),Inputs!$B$2:$B$190,$B9)*Inputs!$D$1),"",SUMIFS(INDEX(Inputs!$B$2:$AZ$190,,MATCH(SUBSTITUTE(AD$3,"Q","T"),Inputs!$B$2:$AZ$2,0)),Inputs!$B$2:$B$190,$B9)*Inputs!$D$1) -> 0 | AE9: =IF(ISNA(SUMIFS(INDEX(Inputs!$B$2:$AZ$190,,MATCH(SUBSTITUTE(AE$3,"Q","T"),Inputs!$B$2:$AZ$2,0)),Inputs!$B$2:$B$190,$B9)*Inputs!$D$1),"",SUMIFS(INDEX(Inputs!$B$2:$AZ$190,,MATCH(SUBSTITUTE(AE$3,"Q","T"),Inputs!$B$2:$AZ$2,0)),Inputs!$B$2:$B$190,$B9)*Inputs!$D$1) -> 0 | AF9: =IF(ISNA(SUMIFS(INDEX(Inputs!$B$2:$AZ$190,,MATCH(SUBSTITUTE(AF$3,"Q","T"),Inputs!$B$2:$AZ$2,0)),Inputs!$B$2:$B$190,$B9)*Inputs!$D$1),"",SUMIFS(INDEX(Inputs!$B$2:$AZ$190,,MATCH(SUBSTITUTE(AF$3,"Q","T"),Inputs!$B$2:$AZ$2,0)),Inputs!$B$2:$B$190,$B9)*Inputs!$D$1) -> 0 | AG9: =IF(ISNA(SUMIFS(INDEX(Inputs!$B$2:$AZ$190,,MATCH(SUBSTITUTE(AG$3,"Q","T"),Inputs!$B$2:$AZ$2,0)),Inputs!$B$2:$B$190,$B9)*Inputs!$D$1),"",SUMIFS(INDEX(Inputs!$B$2:$AZ$190,,MATCH(SUBSTITUTE(AG$3,"Q","T"),Inputs!$B$2:$AZ$2,0)),Inputs!$B$2:$B$190,$B9)*Inputs!$D$1) -> 0 | AH9: =AG9 -> 0 | AI9: =IF(ISNA(SUMIFS(INDEX(Inputs!$B$2:$AZ$190,,MATCH(SUBSTITUTE(AI$3,"Q","T"),Inputs!$B$2:$AZ$2,0)),Inputs!$B$2:$B$190,$B9)*Inputs!$D$1),"",SUMIFS(INDEX(Inputs!$B$2:$AZ$190,,MATCH(SUBSTITUTE(AI$3,"Q","T"),Inputs!$B$2:$AZ$2,0)),Inputs!$B$2:$B$190,$B9)*Inputs!$D$1) -> 0 | AJ9: =IF(ISNA(SUMIFS(INDEX(Inputs!$B$2:$AZ$190,,MATCH(SUBSTITUTE(AJ$3,"Q","T"),Inputs!$B$2:$AZ$2,0)),Inputs!$B$2:$B$190,$B9)*Inputs!$D$1),"",SUMIFS(INDEX(Inputs!$B$2:$AZ$190,,MATCH(SUBSTITUTE(AJ$3,"Q","T"),Inputs!$B$2:$AZ$2,0)),Inputs!$B$2:$B$190,$B9)*Inputs!$D$1) -> 0 | AK9: =IF(ISNA(SUMIFS(INDEX(Inputs!$B$2:$AZ$190,,MATCH(SUBSTITUTE(AK$3,"Q","T"),Inputs!$B$2:$AZ$2,0)),Inputs!$B$2:$B$190,$B9)*Inputs!$D$1),"",SUMIFS(INDEX(Inputs!$B$2:$AZ$190,,MATCH(SUBSTITUTE(AK$3,"Q","T"),Inputs!$B$2:$AZ$2,0)),Inputs!$B$2:$B$190,$B9)*Inputs!$D$1) -> 0 | AL9: =IF(ISNA(SUMIFS(INDEX(Inputs!$B$2:$AZ$190,,MATCH(SUBSTITUTE(AL$3,"Q","T"),Inputs!$B$2:$AZ$2,0)),Inputs!$B$2:$B$190,$B9)*Inputs!$D$1),"",SUMIFS(INDEX(Inputs!$B$2:$AZ$190,,MATCH(SUBSTITUTE(AL$3,"Q","T"),Inputs!$B$2:$AZ$2,0)),Inputs!$B$2:$B$190,$B9)*Inputs!$D$1) -> 0 | AM9: =AL9 -> 0 | AN9: =IF(ISNA(SUMIFS(INDEX(Inputs!$B$2:$AZ$190,,MATCH(SUBSTITUTE(AN$3,"Q","T"),Inputs!$B$2:$AZ$2,0)),Inputs!$B$2:$B$190,$B9)*Inputs!$D$1),"",SUMIFS(INDEX(Inputs!$B$2:$AZ$190,,MATCH(SUBSTITUTE(AN$3,"Q","T"),Inputs!$B$2:$AZ$2,0)),Inputs!$B$2:$B$190,$B9)*Inputs!$D$1) -> 0 | AO9: =IF(ISNA(SUMIFS(INDEX(Inputs!$B$2:$AZ$190,,MATCH(SUBSTITUTE(AO$3,"Q","T"),Inputs!$B$2:$AZ$2,0)),Inputs!$B$2:$B$190,$B9)*Inputs!$D$1),"",SUMIFS(INDEX(Inputs!$B$2:$AZ$190,,MATCH(SUBSTITUTE(AO$3,"Q","T"),Inputs!$B$2:$AZ$2,0)),Inputs!$B$2:$B$190,$B9)*Inputs!$D$1) -> 0 | AP9: =IF(ISNA(SUMIFS(INDEX(Inputs!$B$2:$AZ$190,,MATCH(SUBSTITUTE(AP$3,"Q","T"),Inputs!$B$2:$AZ$2,0)),Inputs!$B$2:$B$190,$B9)*Inputs!$D$1),"",SUMIFS(INDEX(Inputs!$B$2:$AZ$190,,MATCH(SUBSTITUTE(AP$3,"Q","T"),Inputs!$B$2:$AZ$2,0)),Inputs!$B$2:$B$190,$B9)*Inputs!$D$1) -> 0 | AQ9: =IF(ISNA(SUMIFS(INDEX(Inputs!$B$2:$AZ$190,,MATCH(SUBSTITUTE(AQ$3,"Q","T"),Inputs!$B$2:$AZ$2,0)),Inputs!$B$2:$B$190,$B9)*Inputs!$D$1),"",SUMIFS(INDEX(Inputs!$B$2:$AZ$190,,MATCH(SUBSTITUTE(AQ$3,"Q","T"),Inputs!$B$2:$AZ$2,0)),Inputs!$B$2:$B$190,$B9)*Inputs!$D$1) -> 0 | AR9: =AQ9 -> 0 | AS9: =IF(ISNA(SUMIFS(INDEX(Inputs!$B$2:$AZ$190,,MATCH(SUBSTITUTE(AS$3,"Q","T"),Inputs!$B$2:$AZ$2,0)),Inputs!$B$2:$B$190,$B9)*Inputs!$D$1),"",SUMIFS(INDEX(Inputs!$B$2:$AZ$190,,MATCH(SUBSTITUTE(AS$3,"Q","T"),Inputs!$B$2:$AZ$2,0)),Inputs!$B$2:$B$190,$B9)*Inputs!$D$1) -> 0 | AT9: =IF(ISNA(SUMIFS(INDEX(Inputs!$B$2:$AZ$190,,MATCH(SUBSTITUTE(AT$3,"Q","T"),Inputs!$B$2:$AZ$2,0)),Inputs!$B$2:$B$190,$B9)*Inputs!$D$1),"",SUMIFS(INDEX(Inputs!$B$2:$AZ$190,,MATCH(SUBSTITUTE(AT$3,"Q","T"),Inputs!$B$2:$AZ$2,0)),Inputs!$B$2:$B$190,$B9)*Inputs!$D$1) -> 0 | AU9: =IF(ISNA(SUMIFS(INDEX(Inputs!$B$2:$AZ$190,,MATCH(SUBSTITUTE(AU$3,"Q","T"),Inputs!$B$2:$AZ$2,0)),Inputs!$B$2:$B$190,$B9)*Inputs!$D$1),"",SUMIFS(INDEX(Inputs!$B$2:$AZ$190,,MATCH(SUBSTITUTE(AU$3,"Q","T"),Inputs!$B$2:$AZ$2,0)),Inputs!$B$2:$B$190,$B9)*Inputs!$D$1) -> 0 | AV9: =IF(ISNA(SUMIFS(INDEX(Inputs!$B$2:$AZ$190,,MATCH(SUBSTITUTE(AV$3,"Q","T"),Inputs!$B$2:$AZ$2,0)),Inputs!$B$2:$B$190,$B9)*Inputs!$D$1),"",SUMIFS(INDEX(Inputs!$B$2:$AZ$190,,MATCH(SUBSTITUTE(AV$3,"Q","T"),Inputs!$B$2:$AZ$2,0)),Inputs!$B$2:$B$190,$B9)*Inputs!$D$1) -> 0 | AW9: =AV9 -> 0 | AX9: =IF(ISNA(SUMIFS(INDEX(Inputs!$B$2:$AZ$190,,MATCH(SUBSTITUTE(AX$3,"Q","T"),Inputs!$B$2:$AZ$2,0)),Inputs!$B$2:$B$190,$B9)*Inputs!$D$1),"",SUMIFS(INDEX(Inputs!$B$2:$AZ$190,,MATCH(SUBSTITUTE(AX$3,"Q","T"),Inputs!$B$2:$AZ$2,0)),Inputs!$B$2:$B$190,$B9)*Inputs!$D$1) -> 0 | AY9: =IF(ISNA(SUMIFS(INDEX(Inputs!$B$2:$AZ$190,,MATCH(SUBSTITUTE(AY$3,"Q","T"),Inputs!$B$2:$AZ$2,0)),Inputs!$B$2:$B$190,$B9)*Inputs!$D$1),"",SUMIFS(INDEX(Inputs!$B$2:$AZ$190,,MATCH(SUBSTITUTE(AY$3,"Q","T"),Inputs!$B$2:$AZ$2,0)),Inputs!$B$2:$B$190,$B9)*Inputs!$D$1) -> 0 | AZ9: =IF(ISNA(SUMIFS(INDEX(Inputs!$B$2:$AZ$190,,MATCH(SUBSTITUTE(AZ$3,"Q","T"),Inputs!$B$2:$AZ$2,0)),Inputs!$B$2:$B$190,$B9)*Inputs!$D$1),"",SUMIFS(INDEX(Inputs!$B$2:$AZ$190,,MATCH(SUBSTITUTE(AZ$3,"Q","T"),Inputs!$B$2:$AZ$2,0)),Inputs!$B$2:$B$190,$B9)*Inputs!$D$1) -> 0 | BA9: =IF(ISNA(SUMIFS(INDEX(Inputs!$B$2:$AZ$190,,MATCH(SUBSTITUTE(BA$3,"Q","T"),Inputs!$B$2:$AZ$2,0)),Inputs!$B$2:$B$190,$B9)*Inputs!$D$1),"",SUMIFS(INDEX(Inputs!$B$2:$AZ$190,,MATCH(SUBSTITUTE(BA$3,"Q","T"),Inputs!$B$2:$AZ$2,0)),Inputs!$B$2:$B$190,$B9)*Inputs!$D$1) -> 0 | BB9: =BA9 -> 0 | BC9: =IF(ISNA(SUMIFS(INDEX(Inputs!$B$2:$AZ$190,,MATCH(SUBSTITUTE(BC$3,"Q","T"),Inputs!$B$2:$AZ$2,0)),Inputs!$B$2:$B$190,$B9)*Inputs!$D$1),"",SUMIFS(INDEX(Inputs!$B$2:$AZ$190,,MATCH(SUBSTITUTE(BC$3,"Q","T"),Inputs!$B$2:$AZ$2,0)),Inputs!$B$2:$B$190,$B9)*Inputs!$D$1) -> 0 | BD9: =IF(ISNA(SUMIFS(INDEX(Inputs!$B$2:$AZ$190,,MATCH(SUBSTITUTE(BD$3,"Q","T"),Inputs!$B$2:$AZ$2,0)),Inputs!$B$2:$B$190,$B9)*Inputs!$D$1),"",SUMIFS(INDEX(Inputs!$B$2:$AZ$190,,MATCH(SUBSTITUTE(BD$3,"Q","T"),Inputs!$B$2:$AZ$2,0)),Inputs!$B$2:$B$190,$B9)*Inputs!$D$1) -> 0 | BE9: =IF(ISNA(SUMIFS(INDEX(Inputs!$B$2:$AZ$190,,MATCH(SUBSTITUTE(BE$3,"Q","T"),Inputs!$B$2:$AZ$2,0)),Inputs!$B$2:$B$190,$B9)*Inputs!$D$1),"",SUMIFS(INDEX(Inputs!$B$2:$AZ$190,,MATCH(SUBSTITUTE(BE$3,"Q","T"),Inputs!$B$2:$AZ$2,0)),Inputs!$B$2:$B$190,$B9)*Inputs!$D$1) -> 0 | BF9: =IF(ISNA(SUMIFS(INDEX(Inputs!$B$2:$AZ$190,,MATCH(SUBSTITUTE(BF$3,"Q","T"),Inputs!$B$2:$AZ$2,0)),Inputs!$B$2:$B$190,$B9)*Inputs!$D$1),"",SUMIFS(INDEX(Inputs!$B$2:$AZ$190,,MATCH(SUBSTITUTE(BF$3,"Q","T"),Inputs!$B$2:$AZ$2,0)),Inputs!$B$2:$B$190,$B9)*Inputs!$D$1) -> 0 | BG9: =BF9 -> 0
B10: liq_acl | C10: (Provisão para perdas — aplicações de liquidez) | D10: (Allowance — liquidity placements) | E10: =IF(ISNA(SUMIFS(INDEX(Inputs!$B$2:$AZ$190,,MATCH(SUBSTITUTE(E$3,"Q","T"),Inputs!$B$2:$AZ$2,0)),Inputs!$B$2:$B$190,$B10)*Inputs!$D$1),"",SUMIFS(INDEX(Inputs!$B$2:$AZ$190,,MATCH(SUBSTITUTE(E$3,"Q","T"),Inputs!$B$2:$AZ$2,0)),Inputs!$B$2:$B$190,$B10)*Inputs!$D$1) -> 0 | F10: =IF(ISNA(SUMIFS(INDEX(Inputs!$B$2:$AZ$190,,MATCH(SUBSTITUTE(F$3,"Q","T"),Inputs!$B$2:$AZ$2,0)),Inputs!$B$2:$B$190,$B10)*Inputs!$D$1),"",SUMIFS(INDEX(Inputs!$B$2:$AZ$190,,MATCH(SUBSTITUTE(F$3,"Q","T"),Inputs!$B$2:$AZ$2,0)),Inputs!$B$2:$B$190,$B10)*Inputs!$D$1) -> 0 | G10: =IF(ISNA(SUMIFS(INDEX(Inputs!$B$2:$AZ$190,,MATCH(SUBSTITUTE(G$3,"Q","T"),Inputs!$B$2:$AZ$2,0)),Inputs!$B$2:$B$190,$B10)*Inputs!$D$1),"",SUMIFS(INDEX(Inputs!$B$2:$AZ$190,,MATCH(SUBSTITUTE(G$3,"Q","T"),Inputs!$B$2:$AZ$2,0)),Inputs!$B$2:$B$190,$B10)*Inputs!$D$1) -> 0 | H10: =IF(ISNA(SUMIFS(INDEX(Inputs!$B$2:$AZ$190,,MATCH(SUBSTITUTE(H$3,"Q","T"),Inputs!$B$2:$AZ$2,0)),Inputs!$B$2:$B$190,$B10)*Inputs!$D$1),"",SUMIFS(INDEX(Inputs!$B$2:$AZ$190,,MATCH(SUBSTITUTE(H$3,"Q","T"),Inputs!$B$2:$AZ$2,0)),Inputs!$B$2:$B$190,$B10)*Inputs!$D$1) -> 0 | I10: =H10 -> 0 | J10: =IF(ISNA(SUMIFS(INDEX(Inputs!$B$2:$AZ$190,,MATCH(SUBSTITUTE(J$3,"Q","T"),Inputs!$B$2:$AZ$2,0)),Inputs!$B$2:$B$190,$B10)*Inputs!$D$1),"",SUMIFS(INDEX(Inputs!$B$2:$AZ$190,,MATCH(SUBSTITUTE(J$3,"Q","T"),Inputs!$B$2:$AZ$2,0)),Inputs!$B$2:$B$190,$B10)*Inputs!$D$1) -> 0 | K10: =IF(ISNA(SUMIFS(INDEX(Inputs!$B$2:$AZ$190,,MATCH(SUBSTITUTE(K$3,"Q","T"),Inputs!$B$2:$AZ$2,0)),Inputs!$B$2:$B$190,$B10)*Inputs!$D$1),"",SUMIFS(INDEX(Inputs!$B$2:$AZ$190,,MATCH(SUBSTITUTE(K$3,"Q","T"),Inputs!$B$2:$AZ$2,0)),Inputs!$B$2:$B$190,$B10)*Inputs!$D$1) -> 0 | L10: =IF(ISNA(SUMIFS(INDEX(Inputs!$B$2:$AZ$190,,MATCH(SUBSTITUTE(L$3,"Q","T"),Inputs!$B$2:$AZ$2,0)),Inputs!$B$2:$B$190,$B10)*Inputs!$D$1),"",SUMIFS(INDEX(Inputs!$B$2:$AZ$190,,MATCH(SUBSTITUTE(L$3,"Q","T"),Inputs!$B$2:$AZ$2,0)),Inputs!$B$2:$B$190,$B10)*Inputs!$D$1) -> 0 | M10: =IF(ISNA(SUMIFS(INDEX(Inputs!$B$2:$AZ$190,,MATCH(SUBSTITUTE(M$3,"Q","T"),Inputs!$B$2:$AZ$2,0)),Inputs!$B$2:$B$190,$B10)*Inputs!$D$1),"",SUMIFS(INDEX(Inputs!$B$2:$AZ$190,,MATCH(SUBSTITUTE(M$3,"Q","T"),Inputs!$B$2:$AZ$2,0)),Inputs!$B$2:$B$190,$B10)*Inputs!$D$1) -> 0 | N10: =M10 -> 0 | O10: =IF(ISNA(SUMIFS(INDEX(Inputs!$B$2:$AZ$190,,MATCH(SUBSTITUTE(O$3,"Q","T"),Inputs!$B$2:$AZ$2,0)),Inputs!$B$2:$B$190,$B10)*Inputs!$D$1),"",SUMIFS(INDEX(Inputs!$B$2:$AZ$190,,MATCH(SUBSTITUTE(O$3,"Q","T"),Inputs!$B$2:$AZ$2,0)),Inputs!$B$2:$B$190,$B10)*Inputs!$D$1) -> 0 | P10: =IF(ISNA(SUMIFS(INDEX(Inputs!$B$2:$AZ$190,,MATCH(SUBSTITUTE(P$3,"Q","T"),Inputs!$B$2:$AZ$2,0)),Inputs!$B$2:$B$190,$B10)*Inputs!$D$1),"",SUMIFS(INDEX(Inputs!$B$2:$AZ$190,,MATCH(SUBSTITUTE(P$3,"Q","T"),Inputs!$B$2:$AZ$2,0)),Inputs!$B$2:$B$190,$B10)*Inputs!$D$1) -> 0 | Q10: =IF(ISNA(SUMIFS(INDEX(Inputs!$B$2:$AZ$190,,MATCH(SUBSTITUTE(Q$3,"Q","T"),Inputs!$B$2:$AZ$2,0)),Inputs!$B$2:$B$190,$B10)*Inputs!$D$1),"",SUMIFS(INDEX(Inputs!$B$2:$AZ$190,,MATCH(SUBSTITUTE(Q$3,"Q","T"),Inputs!$B$2:$AZ$2,0)),Inputs!$B$2:$B$190,$B10)*Inputs!$D$1) -> 0 | R10: =IF(ISNA(SUMIFS(INDEX(Inputs!$B$2:$AZ$190,,MATCH(SUBSTITUTE(R$3,"Q","T"),Inputs!$B$2:$AZ$2,0)),Inputs!$B$2:$B$190,$B10)*Inputs!$D$1),"",SUMIFS(INDEX(Inputs!$B$2:$AZ$190,,MATCH(SUBSTITUTE(R$3,"Q","T"),Inputs!$B$2:$AZ$2,0)),Inputs!$B$2:$B$190,$B10)*Inputs!$D$1) -> 0 | S10: =R10 -> 0 | T10: =IF(ISNA(SUMIFS(INDEX(Inputs!$B$2:$AZ$190,,MATCH(SUBSTITUTE(T$3,"Q","T"),Inputs!$B$2:$AZ$2,0)),Inputs!$B$2:$B$190,$B10)*Inputs!$D$1),"",SUMIFS(INDEX(Inputs!$B$2:$AZ$190,,MATCH(SUBSTITUTE(T$3,"Q","T"),Inputs!$B$2:$AZ$2,0)),Inputs!$B$2:$B$190,$B10)*Inputs!$D$1) -> 0 | U10: =IF(ISNA(SUMIFS(INDEX(Inputs!$B$2:$AZ$190,,MATCH(SUBSTITUTE(U$3,"Q","T"),Inputs!$B$2:$AZ$2,0)),Inputs!$B$2:$B$190,$B10)*Inputs!$D$1),"",SUMIFS(INDEX(Inputs!$B$2:$AZ$190,,MATCH(SUBSTITUTE(U$3,"Q","T"),Inputs!$B$2:$AZ$2,0)),Inputs!$B$2:$B$190,$B10)*Inputs!$D$1) -> 0 | V10: =IF(ISNA(SUMIFS(INDEX(Inputs!$B$2:$AZ$190,,MATCH(SUBSTITUTE(V$3,"Q","T"),Inputs!$B$2:$AZ$2,0)),Inputs!$B$2:$B$190,$B10)*Inputs!$D$1),"",SUMIFS(INDEX(Inputs!$B$2:$AZ$190,,MATCH(SUBSTITUTE(V$3,"Q","T"),Inputs!$B$2:$AZ$2,0)),Inputs!$B$2:$B$190,$B10)*Inputs!$D$1) -> 0 | W10: =IF(ISNA(SUMIFS(INDEX(Inputs!$B$2:$AZ$190,,MATCH(SUBSTITUTE(W$3,"Q","T"),Inputs!$B$2:$AZ$2,0)),Inputs!$B$2:$B$190,$B10)*Inputs!$D$1),"",SUMIFS(INDEX(Inputs!$B$2:$AZ$190,,MATCH(SUBSTITUTE(W$3,"Q","T"),Inputs!$B$2:$AZ$2,0)),Inputs!$B$2:$B$190,$B10)*Inputs!$D$1) -> 0 | X10: =W10 -> 0 | Y10: =IF(ISNA(SUMIFS(INDEX(Inputs!$B$2:$AZ$190,,MATCH(SUBSTITUTE(Y$3,"Q","T"),Inputs!$B$2:$AZ$2,0)),Inputs!$B$2:$B$190,$B10)*Inputs!$D$1),"",SUMIFS(INDEX(Inputs!$B$2:$AZ$190,,MATCH(SUBSTITUTE(Y$3,"Q","T"),Inputs!$B$2:$AZ$2,0)),Inputs!$B$2:$B$190,$B10)*Inputs!$D$1) -> 0 | Z10: =IF(ISNA(SUMIFS(INDEX(Inputs!$B$2:$AZ$190,,MATCH(SUBSTITUTE(Z$3,"Q","T"),Inputs!$B$2:$AZ$2,0)),Inputs!$B$2:$B$190,$B10)*Inputs!$D$1),"",SUMIFS(INDEX(Inputs!$B$2:$AZ$190,,MATCH(SUBSTITUTE(Z$3,"Q","T"),Inputs!$B$2:$AZ$2,0)),Inputs!$B$2:$B$190,$B10)*Inputs!$D$1) -> 0 | AA10: =IF(ISNA(SUMIFS(INDEX(Inputs!$B$2:$AZ$190,,MATCH(SUBSTITUTE(AA$3,"Q","T"),Inputs!$B$2:$AZ$2,0)),Inputs!$B$2:$B$190,$B10)*Inputs!$D$1),"",SUMIFS(INDEX(Inputs!$B$2:$AZ$190,,MATCH(SUBSTITUTE(AA$3,"Q","T"),Inputs!$B$2:$AZ$2,0)),Inputs!$B$2:$B$190,$B10)*Inputs!$D$1) -> 0 | AB10: =IF(ISNA(SUMIFS(INDEX(Inputs!$B$2:$AZ$190,,MATCH(SUBSTITUTE(AB$3,"Q","T"),Inputs!$B$2:$AZ$2,0)),Inputs!$B$2:$B$190,$B10)*Inputs!$D$1),"",SUMIFS(INDEX(Inputs!$B$2:$AZ$190,,MATCH(SUBSTITUTE(AB$3,"Q","T"),Inputs!$B$2:$AZ$2,0)),Inputs!$B$2:$B$190,$B10)*Inputs!$D$1) -> 0 | AC10: =AB10 -> 0 | AD10: =IF(ISNA(SUMIFS(INDEX(Inputs!$B$2:$AZ$190,,MATCH(SUBSTITUTE(AD$3,"Q","T"),Inputs!$B$2:$AZ$2,0)),Inputs!$B$2:$B$190,$B10)*Inputs!$D$1),"",SUMIFS(INDEX(Inputs!$B$2:$AZ$190,,MATCH(SUBSTITUTE(AD$3,"Q","T"),Inputs!$B$2:$AZ$2,0)),Inputs!$B$2:$B$190,$B10)*Inputs!$D$1) -> 0 | AE10: =IF(ISNA(SUMIFS(INDEX(Inputs!$B$2:$AZ$190,,MATCH(SUBSTITUTE(AE$3,"Q","T"),Inputs!$B$2:$AZ$2,0)),Inputs!$B$2:$B$190,$B10)*Inputs!$D$1),"",SUMIFS(INDEX(Inputs!$B$2:$AZ$190,,MATCH(SUBSTITUTE(AE$3,"Q","T"),Inputs!$B$2:$AZ$2,0)),Inputs!$B$2:$B$190,$B10)*Inputs!$D$1) -> 0 | AF10: =IF(ISNA(SUMIFS(INDEX(Inputs!$B$2:$AZ$190,,MATCH(SUBSTITUTE(AF$3,"Q","T"),Inputs!$B$2:$AZ$2,0)),Inputs!$B$2:$B$190,$B10)*Inputs!$D$1),"",SUMIFS(INDEX(Inputs!$B$2:$AZ$190,,MATCH(SUBSTITUTE(AF$3,"Q","T"),Inputs!$B$2:$AZ$2,0)),Inputs!$B$2:$B$190,$B10)*Inputs!$D$1) -> 0 | AG10: =IF(ISNA(SUMIFS(INDEX(Inputs!$B$2:$AZ$190,,MATCH(SUBSTITUTE(AG$3,"Q","T"),Inputs!$B$2:$AZ$2,0)),Inputs!$B$2:$B$190,$B10)*Inputs!$D$1),"",SUMIFS(INDEX(Inputs!$B$2:$AZ$190,,MATCH(SUBSTITUTE(AG$3,"Q","T"),Inputs!$B$2:$AZ$2,0)),Inputs!$B$2:$B$190,$B10)*Inputs!$D$1) -> 0 | AH10: =AG10 -> 0 | AI10: =IF(ISNA(SUMIFS(INDEX(Inputs!$B$2:$AZ$190,,MATCH(SUBSTITUTE(AI$3,"Q","T"),Inputs!$B$2:$AZ$2,0)),Inputs!$B$2:$B$190,$B10)*Inputs!$D$1),"",SUMIFS(INDEX(Inputs!$B$2:$AZ$190,,MATCH(SUBSTITUTE(AI$3,"Q","T"),Inputs!$B$2:$AZ$2,0)),Inputs!$B$2:$B$190,$B10)*Inputs!$D$1) -> 0 | AJ10: =IF(ISNA(SUMIFS(INDEX(Inputs!$B$2:$AZ$190,,MATCH(SUBSTITUTE(AJ$3,"Q","T"),Inputs!$B$2:$AZ$2,0)),Inputs!$B$2:$B$190,$B10)*Inputs!$D$1),"",SUMIFS(INDEX(Inputs!$B$2:$AZ$190,,MATCH(SUBSTITUTE(AJ$3,"Q","T"),Inputs!$B$2:$AZ$2,0)),Inputs!$B$2:$B$190,$B10)*Inputs!$D$1) -> 0 | AK10: =IF(ISNA(SUMIFS(INDEX(Inputs!$B$2:$AZ$190,,MATCH(SUBSTITUTE(AK$3,"Q","T"),Inputs!$B$2:$AZ$2,0)),Inputs!$B$2:$B$190,$B10)*Inputs!$D$1),"",SUMIFS(INDEX(Inputs!$B$2:$AZ$190,,MATCH(SUBSTITUTE(AK$3,"Q","T"),Inputs!$B$2:$AZ$2,0)),Inputs!$B$2:$B$190,$B10)*Inputs!$D$1) -> 0 | AL10: =IF(ISNA(SUMIFS(INDEX(Inputs!$B$2:$AZ$190,,MATCH(SUBSTITUTE(AL$3,"Q","T"),Inputs!$B$2:$AZ$2,0)),Inputs!$B$2:$B$190,$B10)*Inputs!$D$1),"",SUMIFS(INDEX(Inputs!$B$2:$AZ$190,,MATCH(SUBSTITUTE(AL$3,"Q","T"),Inputs!$B$2:$AZ$2,0)),Inputs!$B$2:$B$190,$B10)*Inputs!$D$1) -> 0 | AM10: =AL10 -> 0 | AN10: =IF(ISNA(SUMIFS(INDEX(Inputs!$B$2:$AZ$190,,MATCH(SUBSTITUTE(AN$3,"Q","T"),Inputs!$B$2:$AZ$2,0)),Inputs!$B$2:$B$190,$B10)*Inputs!$D$1),"",SUMIFS(INDEX(Inputs!$B$2:$AZ$190,,MATCH(SUBSTITUTE(AN$3,"Q","T"),Inputs!$B$2:$AZ$2,0)),Inputs!$B$2:$B$190,$B10)*Inputs!$D$1) -> 0 | AO10: =IF(ISNA(SUMIFS(INDEX(Inputs!$B$2:$AZ$190,,MATCH(SUBSTITUTE(AO$3,"Q","T"),Inputs!$B$2:$AZ$2,0)),Inputs!$B$2:$B$190,$B10)*Inputs!$D$1),"",SUMIFS(INDEX(Inputs!$B$2:$AZ$190,,MATCH(SUBSTITUTE(AO$3,"Q","T"),Inputs!$B$2:$AZ$2,0)),Inputs!$B$2:$B$190,$B10)*Inputs!$D$1) -> 0 | AP10: =IF(ISNA(SUMIFS(INDEX(Inputs!$B$2:$AZ$190,,MATCH(SUBSTITUTE(AP$3,"Q","T"),Inputs!$B$2:$AZ$2,0)),Inputs!$B$2:$B$190,$B10)*Inputs!$D$1),"",SUMIFS(INDEX(Inputs!$B$2:$AZ$190,,MATCH(SUBSTITUTE(AP$3,"Q","T"),Inputs!$B$2:$AZ$2,0)),Inputs!$B$2:$B$190,$B10)*Inputs!$D$1) -> 0 | AQ10: =IF(ISNA(SUMIFS(INDEX(Inputs!$B$2:$AZ$190,,MATCH(SUBSTITUTE(AQ$3,"Q","T"),Inputs!$B$2:$AZ$2,0)),Inputs!$B$2:$B$190,$B10)*Inputs!$D$1),"",SUMIFS(INDEX(Inputs!$B$2:$AZ$190,,MATCH(SUBSTITUTE(AQ$3,"Q","T"),Inputs!$B$2:$AZ$2,0)),Inputs!$B$2:$B$190,$B10)*Inputs!$D$1) -> 0 | AR10: =AQ10 -> 0 | AS10: =IF(ISNA(SUMIFS(INDEX(Inputs!$B$2:$AZ$190,,MATCH(SUBSTITUTE(AS$3,"Q","T"),Inputs!$B$2:$AZ$2,0)),Inputs!$B$2:$B$190,$B10)*Inputs!$D$1),"",SUMIFS(INDEX(Inputs!$B$2:$AZ$190,,MATCH(SUBSTITUTE(AS$3,"Q","T"),Inputs!$B$2:$AZ$2,0)),Inputs!$B$2:$B$190,$B10)*Inputs!$D$1) -> 0 | AT10: =IF(ISNA(SUMIFS(INDEX(Inputs!$B$2:$AZ$190,,MATCH(SUBSTITUTE(AT$3,"Q","T"),Inputs!$B$2:$AZ$2,0)),Inputs!$B$2:$B$190,$B10)*Inputs!$D$1),"",SUMIFS(INDEX(Inputs!$B$2:$AZ$190,,MATCH(SUBSTITUTE(AT$3,"Q","T"),Inputs!$B$2:$AZ$2,0)),Inputs!$B$2:$B$190,$B10)*Inputs!$D$1) -> 0 | AU10: =IF(ISNA(SUMIFS(INDEX(Inputs!$B$2:$AZ$190,,MATCH(SUBSTITUTE(AU$3,"Q","T"),Inputs!$B$2:$AZ$2,0)),Inputs!$B$2:$B$190,$B10)*Inputs!$D$1),"",SUMIFS(INDEX(Inputs!$B$2:$AZ$190,,MATCH(SUBSTITUTE(AU$3,"Q","T"),Inputs!$B$2:$AZ$2,0)),Inputs!$B$2:$B$190,$B10)*Inputs!$D$1) -> 0 | AV10: =IF(ISNA(SUMIFS(INDEX(Inputs!$B$2:$AZ$190,,MATCH(SUBSTITUTE(AV$3,"Q","T"),Inputs!$B$2:$AZ$2,0)),Inputs!$B$2:$B$190,$B10)*Inputs!$D$1),"",SUMIFS(INDEX(Inputs!$B$2:$AZ$190,,MATCH(SUBSTITUTE(AV$3,"Q","T"),Inputs!$B$2:$AZ$2,0)),Inputs!$B$2:$B$190,$B10)*Inputs!$D$1) -> 0 | AW10: =AV10 -> 0 | AX10: =IF(ISNA(SUMIFS(INDEX(Inputs!$B$2:$AZ$190,,MATCH(SUBSTITUTE(AX$3,"Q","T"),Inputs!$B$2:$AZ$2,0)),Inputs!$B$2:$B$190,$B10)*Inputs!$D$1),"",SUMIFS(INDEX(Inputs!$B$2:$AZ$190,,MATCH(SUBSTITUTE(AX$3,"Q","T"),Inputs!$B$2:$AZ$2,0)),Inputs!$B$2:$B$190,$B10)*Inputs!$D$1) -> 0 | AY10: =IF(ISNA(SUMIFS(INDEX(Inputs!$B$2:$AZ$190,,MATCH(SUBSTITUTE(AY$3,"Q","T"),Inputs!$B$2:$AZ$2,0)),Inputs!$B$2:$B$190,$B10)*Inputs!$D$1),"",SUMIFS(INDEX(Inputs!$B$2:$AZ$190,,MATCH(SUBSTITUTE(AY$3,"Q","T"),Inputs!$B$2:$AZ$2,0)),Inputs!$B$2:$B$190,$B10)*Inputs!$D$1) -> 0 | AZ10: =IF(ISNA(SUMIFS(INDEX(Inputs!$B$2:$AZ$190,,MATCH(SUBSTITUTE(AZ$3,"Q","T"),Inputs!$B$2:$AZ$2,0)),Inputs!$B$2:$B$190,$B10)*Inputs!$D$1),"",SUMIFS(INDEX(Inputs!$B$2:$AZ$190,,MATCH(SUBSTITUTE(AZ$3,"Q","T"),Inputs!$B$2:$AZ$2,0)),Inputs!$B$2:$B$190,$B10)*Inputs!$D$1) -> 0 | BA10: =IF(ISNA(SUMIFS(INDEX(Inputs!$B$2:$AZ$190,,MATCH(SUBSTITUTE(BA$3,"Q","T"),Inputs!$B$2:$AZ$2,0)),Inputs!$B$2:$B$190,$B10)*Inputs!$D$1),"",SUMIFS(INDEX(Inputs!$B$2:$AZ$190,,MATCH(SUBSTITUTE(BA$3,"Q","T"),Inputs!$B$2:$AZ$2,0)),Inputs!$B$2:$B$190,$B10)*Inputs!$D$1) -> 0 | BB10: =BA10 -> 0 | BC10: =IF(ISNA(SUMIFS(INDEX(Inputs!$B$2:$AZ$190,,MATCH(SUBSTITUTE(BC$3,"Q","T"),Inputs!$B$2:$AZ$2,0)),Inputs!$B$2:$B$190,$B10)*Inputs!$D$1),"",SUMIFS(INDEX(Inputs!$B$2:$AZ$190,,MATCH(SUBSTITUTE(BC$3,"Q","T"),Inputs!$B$2:$AZ$2,0)),Inputs!$B$2:$B$190,$B10)*Inputs!$D$1) -> 0 | BD10: =IF(ISNA(SUMIFS(INDEX(Inputs!$B$2:$AZ$190,,MATCH(SUBSTITUTE(BD$3,"Q","T"),Inputs!$B$2:$AZ$2,0)),Inputs!$B$2:$B$190,$B10)*Inputs!$D$1),"",SUMIFS(INDEX(Inputs!$B$2:$AZ$190,,MATCH(SUBSTITUTE(BD$3,"Q","T"),Inputs!$B$2:$AZ$2,0)),Inputs!$B$2:$B$190,$B10)*Inputs!$D$1) -> 0 | BE10: =IF(ISNA(SUMIFS(INDEX(Inputs!$B$2:$AZ$190,,MATCH(SUBSTITUTE(BE$3,"Q","T"),Inputs!$B$2:$AZ$2,0)),Inputs!$B$2:$B$190,$B10)*Inputs!$D$1),"",SUMIFS(INDEX(Inputs!$B$2:$AZ$190,,MATCH(SUBSTITUTE(BE$3,"Q","T"),Inputs!$B$2:$AZ$2,0)),Inputs!$B$2:$B$190,$B10)*Inputs!$D$1) -> 0 | BF10: =IF(ISNA(SUMIFS(INDEX(Inputs!$B$2:$AZ$190,,MATCH(SUBSTITUTE(BF$3,"Q","T"),Inputs!$B$2:$AZ$2,0)),Inputs!$B$2:$B$190,$B10)*Inputs!$D$1),"",SUMIFS(INDEX(Inputs!$B$2:$AZ$190,,MATCH(SUBSTITUTE(BF$3,"Q","T"),Inputs!$B$2:$AZ$2,0)),Inputs!$B$2:$B$190,$B10)*Inputs!$D$1) -> 0 | BG10: =BF10 -> 0
C11: Títulos e ativos de trading | D11: Securities and trading assets | E11: =IFERROR(E12+E13+E14+E15,"") -> 0 | F11: =IFERROR(F12+F13+F14+F15,"") -> 0 | G11: =IFERROR(G12+G13+G14+G15,"") -> 0 | H11: =IFERROR(H12+H13+H14+H15,"") -> 0 | I11: =H11 -> 0 | J11: =IFERROR(J12+J13+J14+J15,"") -> 0 | K11: =IFERROR(K12+K13+K14+K15,"") -> 0 | L11: =IFERROR(L12+L13+L14+L15,"") -> 0 | M11: =IFERROR(M12+M13+M14+M15,"") -> 0 | N11: =M11 -> 0 | O11: =IFERROR(O12+O13+O14+O15,"") -> 0 | P11: =IFERROR(P12+P13+P14+P15,"") -> 0 | Q11: =IFERROR(Q12+Q13+Q14+Q15,"") -> 0 | R11: =IFERROR(R12+R13+R14+R15,"") -> 0 | S11: =R11 -> 0 | T11: =IFERROR(T12+T13+T14+T15,"") -> 0 | U11: =IFERROR(U12+U13+U14+U15,"") -> 0 | V11: =IFERROR(V12+V13+V14+V15,"") -> 0 | W11: =IFERROR(W12+W13+W14+W15,"") -> 0 | X11: =W11 -> 0 | Y11: =IFERROR(Y12+Y13+Y14+Y15,"") -> 0 | Z11: =IFERROR(Z12+Z13+Z14+Z15,"") -> 0 | AA11: =IFERROR(AA12+AA13+AA14+AA15,"") -> 0 | AB11: =IFERROR(AB12+AB13+AB14+AB15,"") -> 0 | AC11: =AB11 -> 0 | AD11: =IFERROR(AD12+AD13+AD14+AD15,"") -> 0 | AE11: =IFERROR(AE12+AE13+AE14+AE15,"") -> 0 | AF11: =IFERROR(AF12+AF13+AF14+AF15,"") -> 0 | AG11: =IFERROR(AG12+AG13+AG14+AG15,"") -> 0 | AH11: =AG11 -> 0 | AI11: =IFERROR(AI12+AI13+AI14+AI15,"") -> 0 | AJ11: =IFERROR(AJ12+AJ13+AJ14+AJ15,"") -> 0 | AK11: =IFERROR(AK12+AK13+AK14+AK15,"") -> 0 | AL11: =IFERROR(AL12+AL13+AL14+AL15,"") -> 0 | AM11: =AL11 -> 0 | AN11: =IFERROR(AN12+AN13+AN14+AN15,"") -> 0 | AO11: =IFERROR(AO12+AO13+AO14+AO15,"") -> 0 | AP11: =IFERROR(AP12+AP13+AP14+AP15,"") -> 0 | AQ11: =IFERROR(AQ12+AQ13+AQ14+AQ15,"") -> 0 | AR11: =AQ11 -> 0 | AS11: =IFERROR(AS12+AS13+AS14+AS15,"") -> 0 | AT11: =IFERROR(AT12+AT13+AT14+AT15,"") -> 0 | AU11: =IFERROR(AU12+AU13+AU14+AU15,"") -> 0 | AV11: =IFERROR(AV12+AV13+AV14+AV15,"") -> 0 | AW11: =AV11 -> 0 | AX11: =IFERROR(AX12+AX13+AX14+AX15,"") -> 0 | AY11: =IFERROR(AY12+AY13+AY14+AY15,"") -> 0 | AZ11: =IFERROR(AZ12+AZ13+AZ14+AZ15,"") -> 0 | BA11: =IFERROR(BA12+BA13+BA14+BA15,"") -> 0 | BB11: =BA11 -> 0 | BC11: =IFERROR(BC12+BC13+BC14+BC15,"") -> 0 | BD11: =IFERROR(BD12+BD13+BD14+BD15,"") -> 0 | BE11: =IFERROR(BE12+BE13+BE14+BE15,"") -> 0 | BF11: =IFERROR(BF12+BF13+BF14+BF15,"") -> 0 | BG11: =BF11 -> 0
B12: trading | C12: Ativos de trading (inclui derivativos a receber) | D12: Trading assets (incl. derivative receivables) | E12: =IF(ISNA(SUMIFS(INDEX(Inputs!$B$2:$AZ$190,,MATCH(SUBSTITUTE(E$3,"Q","T"),Inputs!$B$2:$AZ$2,0)),Inputs!$B$2:$B$190,$B12)*Inputs!$D$1),"",SUMIFS(INDEX(Inputs!$B$2:$AZ$190,,MATCH(SUBSTITUTE(E$3,"Q","T"),Inputs!$B$2:$AZ$2,0)),Inputs!$B$2:$B$190,$B12)*Inputs!$D$1) -> 0 | F12: =IF(ISNA(SUMIFS(INDEX(Inputs!$B$2:$AZ$190,,MATCH(SUBSTITUTE(F$3,"Q","T"),Inputs!$B$2:$AZ$2,0)),Inputs!$B$2:$B$190,$B12)*Inputs!$D$1),"",SUMIFS(INDEX(Inputs!$B$2:$AZ$190,,MATCH(SUBSTITUTE(F$3,"Q","T"),Inputs!$B$2:$AZ$2,0)),Inputs!$B$2:$B$190,$B12)*Inputs!$D$1) -> 0 | G12: =IF(ISNA(SUMIFS(INDEX(Inputs!$B$2:$AZ$190,,MATCH(SUBSTITUTE(G$3,"Q","T"),Inputs!$B$2:$AZ$2,0)),Inputs!$B$2:$B$190,$B12)*Inputs!$D$1),"",SUMIFS(INDEX(Inputs!$B$2:$AZ$190,,MATCH(SUBSTITUTE(G$3,"Q","T"),Inputs!$B$2:$AZ$2,0)),Inputs!$B$2:$B$190,$B12)*Inputs!$D$1) -> 0 | H12: =IF(ISNA(SUMIFS(INDEX(Inputs!$B$2:$AZ$190,,MATCH(SUBSTITUTE(H$3,"Q","T"),Inputs!$B$2:$AZ$2,0)),Inputs!$B$2:$B$190,$B12)*Inputs!$D$1),"",SUMIFS(INDEX(Inputs!$B$2:$AZ$190,,MATCH(SUBSTITUTE(H$3,"Q","T"),Inputs!$B$2:$AZ$2,0)),Inputs!$B$2:$B$190,$B12)*Inputs!$D$1) -> 0 | I12: =H12 -> 0 | J12: =IF(ISNA(SUMIFS(INDEX(Inputs!$B$2:$AZ$190,,MATCH(SUBSTITUTE(J$3,"Q","T"),Inputs!$B$2:$AZ$2,0)),Inputs!$B$2:$B$190,$B12)*Inputs!$D$1),"",SUMIFS(INDEX(Inputs!$B$2:$AZ$190,,MATCH(SUBSTITUTE(J$3,"Q","T"),Inputs!$B$2:$AZ$2,0)),Inputs!$B$2:$B$190,$B12)*Inputs!$D$1) -> 0 | K12: =IF(ISNA(SUMIFS(INDEX(Inputs!$B$2:$AZ$190,,MATCH(SUBSTITUTE(K$3,"Q","T"),Inputs!$B$2:$AZ$2,0)),Inputs!$B$2:$B$190,$B12)*Inputs!$D$1),"",SUMIFS(INDEX(Inputs!$B$2:$AZ$190,,MATCH(SUBSTITUTE(K$3,"Q","T"),Inputs!$B$2:$AZ$2,0)),Inputs!$B$2:$B$190,$B12)*Inputs!$D$1) -> 0 | L12: =IF(ISNA(SUMIFS(INDEX(Inputs!$B$2:$AZ$190,,MATCH(SUBSTITUTE(L$3,"Q","T"),Inputs!$B$2:$AZ$2,0)),Inputs!$B$2:$B$190,$B12)*Inputs!$D$1),"",SUMIFS(INDEX(Inputs!$B$2:$AZ$190,,MATCH(SUBSTITUTE(L$3,"Q","T"),Inputs!$B$2:$AZ$2,0)),Inputs!$B$2:$B$190,$B12)*Inputs!$D$1) -> 0 | M12: =IF(ISNA(SUMIFS(INDEX(Inputs!$B$2:$AZ$190,,MATCH(SUBSTITUTE(M$3,"Q","T"),Inputs!$B$2:$AZ$2,0)),Inputs!$B$2:$B$190,$B12)*Inputs!$D$1),"",SUMIFS(INDEX(Inputs!$B$2:$AZ$190,,MATCH(SUBSTITUTE(M$3,"Q","T"),Inputs!$B$2:$AZ$2,0)),Inputs!$B$2:$B$190,$B12)*Inputs!$D$1) -> 0 | N12: =M12 -> 0 | O12: =IF(ISNA(SUMIFS(INDEX(Inputs!$B$2:$AZ$190,,MATCH(SUBSTITUTE(O$3,"Q","T"),Inputs!$B$2:$AZ$2,0)),Inputs!$B$2:$B$190,$B12)*Inputs!$D$1),"",SUMIFS(INDEX(Inputs!$B$2:$AZ$190,,MATCH(SUBSTITUTE(O$3,"Q","T"),Inputs!$B$2:$AZ$2,0)),Inputs!$B$2:$B$190,$B12)*Inputs!$D$1) -> 0 | P12: =IF(ISNA(SUMIFS(INDEX(Inputs!$B$2:$AZ$190,,MATCH(SUBSTITUTE(P$3,"Q","T"),Inputs!$B$2:$AZ$2,0)),Inputs!$B$2:$B$190,$B12)*Inputs!$D$1),"",SUMIFS(INDEX(Inputs!$B$2:$AZ$190,,MATCH(SUBSTITUTE(P$3,"Q","T"),Inputs!$B$2:$AZ$2,0)),Inputs!$B$2:$B$190,$B12)*Inputs!$D$1) -> 0 | Q12: =IF(ISNA(SUMIFS(INDEX(Inputs!$B$2:$AZ$190,,MATCH(SUBSTITUTE(Q$3,"Q","T"),Inputs!$B$2:$AZ$2,0)),Inputs!$B$2:$B$190,$B12)*Inputs!$D$1),"",SUMIFS(INDEX(Inputs!$B$2:$AZ$190,,MATCH(SUBSTITUTE(Q$3,"Q","T"),Inputs!$B$2:$AZ$2,0)),Inputs!$B$2:$B$190,$B12)*Inputs!$D$1) -> 0 | R12: =IF(ISNA(SUMIFS(INDEX(Inputs!$B$2:$AZ$190,,MATCH(SUBSTITUTE(R$3,"Q","T"),Inputs!$B$2:$AZ$2,0)),Inputs!$B$2:$B$190,$B12)*Inputs!$D$1),"",SUMIFS(INDEX(Inputs!$B$2:$AZ$190,,MATCH(SUBSTITUTE(R$3,"Q","T"),Inputs!$B$2:$AZ$2,0)),Inputs!$B$2:$B$190,$B12)*Inputs!$D$1) -> 0 | S12: =R12 -> 0 | T12: =IF(ISNA(SUMIFS(INDEX(Inputs!$B$2:$AZ$190,,MATCH(SUBSTITUTE(T$3,"Q","T"),Inputs!$B$2:$AZ$2,0)),Inputs!$B$2:$B$190,$B12)*Inputs!$D$1),"",SUMIFS(INDEX(Inputs!$B$2:$AZ$190,,MATCH(SUBSTITUTE(T$3,"Q","T"),Inputs!$B$2:$AZ$2,0)),Inputs!$B$2:$B$190,$B12)*Inputs!$D$1) -> 0 | U12: =IF(ISNA(SUMIFS(INDEX(Inputs!$B$2:$AZ$190,,MATCH(SUBSTITUTE(U$3,"Q","T"),Inputs!$B$2:$AZ$2,0)),Inputs!$B$2:$B$190,$B12)*Inputs!$D$1),"",SUMIFS(INDEX(Inputs!$B$2:$AZ$190,,MATCH(SUBSTITUTE(U$3,"Q","T"),Inputs!$B$2:$AZ$2,0)),Inputs!$B$2:$B$190,$B12)*Inputs!$D$1) -> 0 | V12: =IF(ISNA(SUMIFS(INDEX(Inputs!$B$2:$AZ$190,,MATCH(SUBSTITUTE(V$3,"Q","T"),Inputs!$B$2:$AZ$2,0)),Inputs!$B$2:$B$190,$B12)*Inputs!$D$1),"",SUMIFS(INDEX(Inputs!$B$2:$AZ$190,,MATCH(SUBSTITUTE(V$3,"Q","T"),Inputs!$B$2:$AZ$2,0)),Inputs!$B$2:$B$190,$B12)*Inputs!$D$1) -> 0 | W12: =IF(ISNA(SUMIFS(INDEX(Inputs!$B$2:$AZ$190,,MATCH(SUBSTITUTE(W$3,"Q","T"),Inputs!$B$2:$AZ$2,0)),Inputs!$B$2:$B$190,$B12)*Inputs!$D$1),"",SUMIFS(INDEX(Inputs!$B$2:$AZ$190,,MATCH(SUBSTITUTE(W$3,"Q","T"),Inputs!$B$2:$AZ$2,0)),Inputs!$B$2:$B$190,$B12)*Inputs!$D$1) -> 0 | X12: =W12 -> 0 | Y12: =IF(ISNA(SUMIFS(INDEX(Inputs!$B$2:$AZ$190,,MATCH(SUBSTITUTE(Y$3,"Q","T"),Inputs!$B$2:$AZ$2,0)),Inputs!$B$2:$B$190,$B12)*Inputs!$D$1),"",SUMIFS(INDEX(Inputs!$B$2:$AZ$190,,MATCH(SUBSTITUTE(Y$3,"Q","T"),Inputs!$B$2:$AZ$2,0)),Inputs!$B$2:$B$190,$B12)*Inputs!$D$1) -> 0 | Z12: =IF(ISNA(SUMIFS(INDEX(Inputs!$B$2:$AZ$190,,MATCH(SUBSTITUTE(Z$3,"Q","T"),Inputs!$B$2:$AZ$2,0)),Inputs!$B$2:$B$190,$B12)*Inputs!$D$1),"",SUMIFS(INDEX(Inputs!$B$2:$AZ$190,,MATCH(SUBSTITUTE(Z$3,"Q","T"),Inputs!$B$2:$AZ$2,0)),Inputs!$B$2:$B$190,$B12)*Inputs!$D$1) -> 0 | AA12: =IF(ISNA(SUMIFS(INDEX(Inputs!$B$2:$AZ$190,,MATCH(SUBSTITUTE(AA$3,"Q","T"),Inputs!$B$2:$AZ$2,0)),Inputs!$B$2:$B$190,$B12)*Inputs!$D$1),"",SUMIFS(INDEX(Inputs!$B$2:$AZ$190,,MATCH(SUBSTITUTE(AA$3,"Q","T"),Inputs!$B$2:$AZ$2,0)),Inputs!$B$2:$B$190,$B12)*Inputs!$D$1) -> 0 | AB12: =IF(ISNA(SUMIFS(INDEX(Inputs!$B$2:$AZ$190,,MATCH(SUBSTITUTE(AB$3,"Q","T"),Inputs!$B$2:$AZ$2,0)),Inputs!$B$2:$B$190,$B12)*Inputs!$D$1),"",SUMIFS(INDEX(Inputs!$B$2:$AZ$190,,MATCH(SUBSTITUTE(AB$3,"Q","T"),Inputs!$B$2:$AZ$2,0)),Inputs!$B$2:$B$190,$B12)*Inputs!$D$1) -> 0 | AC12: =AB12 -> 0 | AD12: =IF(ISNA(SUMIFS(INDEX(Inputs!$B$2:$AZ$190,,MATCH(SUBSTITUTE(AD$3,"Q","T"),Inputs!$B$2:$AZ$2,0)),Inputs!$B$2:$B$190,$B12)*Inputs!$D$1),"",SUMIFS(INDEX(Inputs!$B$2:$AZ$190,,MATCH(SUBSTITUTE(AD$3,"Q","T"),Inputs!$B$2:$AZ$2,0)),Inputs!$B$2:$B$190,$B12)*Inputs!$D$1) -> 0 | AE12: =IF(ISNA(SUMIFS(INDEX(Inputs!$B$2:$AZ$190,,MATCH(SUBSTITUTE(AE$3,"Q","T"),Inputs!$B$2:$AZ$2,0)),Inputs!$B$2:$B$190,$B12)*Inputs!$D$1),"",SUMIFS(INDEX(Inputs!$B$2:$AZ$190,,MATCH(SUBSTITUTE(AE$3,"Q","T"),Inputs!$B$2:$AZ$2,0)),Inputs!$B$2:$B$190,$B12)*Inputs!$D$1) -> 0 | AF12: =IF(ISNA(SUMIFS(INDEX(Inputs!$B$2:$AZ$190,,MATCH(SUBSTITUTE(AF$3,"Q","T"),Inputs!$B$2:$AZ$2,0)),Inputs!$B$2:$B$190,$B12)*Inputs!$D$1),"",SUMIFS(INDEX(Inputs!$B$2:$AZ$190,,MATCH(SUBSTITUTE(AF$3,"Q","T"),Inputs!$B$2:$AZ$2,0)),Inputs!$B$2:$B$190,$B12)*Inputs!$D$1) -> 0 | AG12: =IF(ISNA(SUMIFS(INDEX(Inputs!$B$2:$AZ$190,,MATCH(SUBSTITUTE(AG$3,"Q","T"),Inputs!$B$2:$AZ$2,0)),Inputs!$B$2:$B$190,$B12)*Inputs!$D$1),"",SUMIFS(INDEX(Inputs!$B$2:$AZ$190,,MATCH(SUBSTITUTE(AG$3,"Q","T"),Inputs!$B$2:$AZ$2,0)),Inputs!$B$2:$B$190,$B12)*Inputs!$D$1) -> 0 | AH12: =AG12 -> 0 | AI12: =IF(ISNA(SUMIFS(INDEX(Inputs!$B$2:$AZ$190,,MATCH(SUBSTITUTE(AI$3,"Q","T"),Inputs!$B$2:$AZ$2,0)),Inputs!$B$2:$B$190,$B12)*Inputs!$D$1),"",SUMIFS(INDEX(Inputs!$B$2:$AZ$190,,MATCH(SUBSTITUTE(AI$3,"Q","T"),Inputs!$B$2:$AZ$2,0)),Inputs!$B$2:$B$190,$B12)*Inputs!$D$1) -> 0 | AJ12: =IF(ISNA(SUMIFS(INDEX(Inputs!$B$2:$AZ$190,,MATCH(SUBSTITUTE(AJ$3,"Q","T"),Inputs!$B$2:$AZ$2,0)),Inputs!$B$2:$B$190,$B12)*Inputs!$D$1),"",SUMIFS(INDEX(Inputs!$B$2:$AZ$190,,MATCH(SUBSTITUTE(AJ$3,"Q","T"),Inputs!$B$2:$AZ$2,0)),Inputs!$B$2:$B$190,$B12)*Inputs!$D$1) -> 0 | AK12: =IF(ISNA(SUMIFS(INDEX(Inputs!$B$2:$AZ$190,,MATCH(SUBSTITUTE(AK$3,"Q","T"),Inputs!$B$2:$AZ$2,0)),Inputs!$B$2:$B$190,$B12)*Inputs!$D$1),"",SUMIFS(INDEX(Inputs!$B$2:$AZ$190,,MATCH(SUBSTITUTE(AK$3,"Q","T"),Inputs!$B$2:$AZ$2,0)),Inputs!$B$2:$B$190,$B12)*Inputs!$D$1) -> 0 | AL12: =IF(ISNA(SUMIFS(INDEX(Inputs!$B$2:$AZ$190,,MATCH(SUBSTITUTE(AL$3,"Q","T"),Inputs!$B$2:$AZ$2,0)),Inputs!$B$2:$B$190,$B12)*Inputs!$D$1),"",SUMIFS(INDEX(Inputs!$B$2:$AZ$190,,MATCH(SUBSTITUTE(AL$3,"Q","T"),Inputs!$B$2:$AZ$2,0)),Inputs!$B$2:$B$190,$B12)*Inputs!$D$1) -> 0 | AM12: =AL12 -> 0 | AN12: =IF(ISNA(SUMIFS(INDEX(Inputs!$B$2:$AZ$190,,MATCH(SUBSTITUTE(AN$3,"Q","T"),Inputs!$B$2:$AZ$2,0)),Inputs!$B$2:$B$190,$B12)*Inputs!$D$1),"",SUMIFS(INDEX(Inputs!$B$2:$AZ$190,,MATCH(SUBSTITUTE(AN$3,"Q","T"),Inputs!$B$2:$AZ$2,0)),Inputs!$B$2:$B$190,$B12)*Inputs!$D$1) -> 0 | AO12: =IF(ISNA(SUMIFS(INDEX(Inputs!$B$2:$AZ$190,,MATCH(SUBSTITUTE(AO$3,"Q","T"),Inputs!$B$2:$AZ$2,0)),Inputs!$B$2:$B$190,$B12)*Inputs!$D$1),"",SUMIFS(INDEX(Inputs!$B$2:$AZ$190,,MATCH(SUBSTITUTE(AO$3,"Q","T"),Inputs!$B$2:$AZ$2,0)),Inputs!$B$2:$B$190,$B12)*Inputs!$D$1) -> 0 | AP12: =IF(ISNA(SUMIFS(INDEX(Inputs!$B$2:$AZ$190,,MATCH(SUBSTITUTE(AP$3,"Q","T"),Inputs!$B$2:$AZ$2,0)),Inputs!$B$2:$B$190,$B12)*Inputs!$D$1),"",SUMIFS(INDEX(Inputs!$B$2:$AZ$190,,MATCH(SUBSTITUTE(AP$3,"Q","T"),Inputs!$B$2:$AZ$2,0)),Inputs!$B$2:$B$190,$B12)*Inputs!$D$1) -> 0 | AQ12: =IF(ISNA(SUMIFS(INDEX(Inputs!$B$2:$AZ$190,,MATCH(SUBSTITUTE(AQ$3,"Q","T"),Inputs!$B$2:$AZ$2,0)),Inputs!$B$2:$B$190,$B12)*Inputs!$D$1),"",SUMIFS(INDEX(Inputs!$B$2:$AZ$190,,MATCH(SUBSTITUTE(AQ$3,"Q","T"),Inputs!$B$2:$AZ$2,0)),Inputs!$B$2:$B$190,$B12)*Inputs!$D$1) -> 0 | AR12: =AQ12 -> 0 | AS12: =IF(ISNA(SUMIFS(INDEX(Inputs!$B$2:$AZ$190,,MATCH(SUBSTITUTE(AS$3,"Q","T"),Inputs!$B$2:$AZ$2,0)),Inputs!$B$2:$B$190,$B12)*Inputs!$D$1),"",SUMIFS(INDEX(Inputs!$B$2:$AZ$190,,MATCH(SUBSTITUTE(AS$3,"Q","T"),Inputs!$B$2:$AZ$2,0)),Inputs!$B$2:$B$190,$B12)*Inputs!$D$1) -> 0 | AT12: =IF(ISNA(SUMIFS(INDEX(Inputs!$B$2:$AZ$190,,MATCH(SUBSTITUTE(AT$3,"Q","T"),Inputs!$B$2:$AZ$2,0)),Inputs!$B$2:$B$190,$B12)*Inputs!$D$1),"",SUMIFS(INDEX(Inputs!$B$2:$AZ$190,,MATCH(SUBSTITUTE(AT$3,"Q","T"),Inputs!$B$2:$AZ$2,0)),Inputs!$B$2:$B$190,$B12)*Inputs!$D$1) -> 0 | AU12: =IF(ISNA(SUMIFS(INDEX(Inputs!$B$2:$AZ$190,,MATCH(SUBSTITUTE(AU$3,"Q","T"),Inputs!$B$2:$AZ$2,0)),Inputs!$B$2:$B$190,$B12)*Inputs!$D$1),"",SUMIFS(INDEX(Inputs!$B$2:$AZ$190,,MATCH(SUBSTITUTE(AU$3,"Q","T"),Inputs!$B$2:$AZ$2,0)),Inputs!$B$2:$B$190,$B12)*Inputs!$D$1) -> 0 | AV12: =IF(ISNA(SUMIFS(INDEX(Inputs!$B$2:$AZ$190,,MATCH(SUBSTITUTE(AV$3,"Q","T"),Inputs!$B$2:$AZ$2,0)),Inputs!$B$2:$B$190,$B12)*Inputs!$D$1),"",SUMIFS(INDEX(Inputs!$B$2:$AZ$190,,MATCH(SUBSTITUTE(AV$3,"Q","T"),Inputs!$B$2:$AZ$2,0)),Inputs!$B$2:$B$190,$B12)*Inputs!$D$1) -> 0 | AW12: =AV12 -> 0 | AX12: =IF(ISNA(SUMIFS(INDEX(Inputs!$B$2:$AZ$190,,MATCH(SUBSTITUTE(AX$3,"Q","T"),Inputs!$B$2:$AZ$2,0)),Inputs!$B$2:$B$190,$B12)*Inputs!$D$1),"",SUMIFS(INDEX(Inputs!$B$2:$AZ$190,,MATCH(SUBSTITUTE(AX$3,"Q","T"),Inputs!$B$2:$AZ$2,0)),Inputs!$B$2:$B$190,$B12)*Inputs!$D$1) -> 0 | AY12: =IF(ISNA(SUMIFS(INDEX(Inputs!$B$2:$AZ$190,,MATCH(SUBSTITUTE(AY$3,"Q","T"),Inputs!$B$2:$AZ$2,0)),Inputs!$B$2:$B$190,$B12)*Inputs!$D$1),"",SUMIFS(INDEX(Inputs!$B$2:$AZ$190,,MATCH(SUBSTITUTE(AY$3,"Q","T"),Inputs!$B$2:$AZ$2,0)),Inputs!$B$2:$B$190,$B12)*Inputs!$D$1) -> 0 | AZ12: =IF(ISNA(SUMIFS(INDEX(Inputs!$B$2:$AZ$190,,MATCH(SUBSTITUTE(AZ$3,"Q","T"),Inputs!$B$2:$AZ$2,0)),Inputs!$B$2:$B$190,$B12)*Inputs!$D$1),"",SUMIFS(INDEX(Inputs!$B$2:$AZ$190,,MATCH(SUBSTITUTE(AZ$3,"Q","T"),Inputs!$B$2:$AZ$2,0)),Inputs!$B$2:$B$190,$B12)*Inputs!$D$1) -> 0 | BA12: =IF(ISNA(SUMIFS(INDEX(Inputs!$B$2:$AZ$190,,MATCH(SUBSTITUTE(BA$3,"Q","T"),Inputs!$B$2:$AZ$2,0)),Inputs!$B$2:$B$190,$B12)*Inputs!$D$1),"",SUMIFS(INDEX(Inputs!$B$2:$AZ$190,,MATCH(SUBSTITUTE(BA$3,"Q","T"),Inputs!$B$2:$AZ$2,0)),Inputs!$B$2:$B$190,$B12)*Inputs!$D$1) -> 0 | BB12: =BA12 -> 0 | BC12: =IF(ISNA(SUMIFS(INDEX(Inputs!$B$2:$AZ$190,,MATCH(SUBSTITUTE(BC$3,"Q","T"),Inputs!$B$2:$AZ$2,0)),Inputs!$B$2:$B$190,$B12)*Inputs!$D$1),"",SUMIFS(INDEX(Inputs!$B$2:$AZ$190,,MATCH(SUBSTITUTE(BC$3,"Q","T"),Inputs!$B$2:$AZ$2,0)),Inputs!$B$2:$B$190,$B12)*Inputs!$D$1) -> 0 | BD12: =IF(ISNA(SUMIFS(INDEX(Inputs!$B$2:$AZ$190,,MATCH(SUBSTITUTE(BD$3,"Q","T"),Inputs!$B$2:$AZ$2,0)),Inputs!$B$2:$B$190,$B12)*Inputs!$D$1),"",SUMIFS(INDEX(Inputs!$B$2:$AZ$190,,MATCH(SUBSTITUTE(BD$3,"Q","T"),Inputs!$B$2:$AZ$2,0)),Inputs!$B$2:$B$190,$B12)*Inputs!$D$1) -> 0 | BE12: =IF(ISNA(SUMIFS(INDEX(Inputs!$B$2:$AZ$190,,MATCH(SUBSTITUTE(BE$3,"Q","T"),Inputs!$B$2:$AZ$2,0)),Inputs!$B$2:$B$190,$B12)*Inputs!$D$1),"",SUMIFS(INDEX(Inputs!$B$2:$AZ$190,,MATCH(SUBSTITUTE(BE$3,"Q","T"),Inputs!$B$2:$AZ$2,0)),Inputs!$B$2:$B$190,$B12)*Inputs!$D$1) -> 0 | BF12: =IF(ISNA(SUMIFS(INDEX(Inputs!$B$2:$AZ$190,,MATCH(SUBSTITUTE(BF$3,"Q","T"),Inputs!$B$2:$AZ$2,0)),Inputs!$B$2:$B$190,$B12)*Inputs!$D$1),"",SUMIFS(INDEX(Inputs!$B$2:$AZ$190,,MATCH(SUBSTITUTE(BF$3,"Q","T"),Inputs!$B$2:$AZ$2,0)),Inputs!$B$2:$B$190,$B12)*Inputs!$D$1) -> 0 | BG12: =BF12 -> 0
B13: afs | C13: Títulos disponíveis para venda (AFS, valor justo) | D13: Available-for-sale securities, at fair value | E13: =IF(ISNA(SUMIFS(INDEX(Inputs!$B$2:$AZ$190,,MATCH(SUBSTITUTE(E$3,"Q","T"),Inputs!$B$2:$AZ$2,0)),Inputs!$B$2:$B$190,$B13)*Inputs!$D$1),"",SUMIFS(INDEX(Inputs!$B$2:$AZ$190,,MATCH(SUBSTITUTE(E$3,"Q","T"),Inputs!$B$2:$AZ$2,0)),Inputs!$B$2:$B$190,$B13)*Inputs!$D$1) -> 0 | F13: =IF(ISNA(SUMIFS(INDEX(Inputs!$B$2:$AZ$190,,MATCH(SUBSTITUTE(F$3,"Q","T"),Inputs!$B$2:$AZ$2,0)),Inputs!$B$2:$B$190,$B13)*Inputs!$D$1),"",SUMIFS(INDEX(Inputs!$B$2:$AZ$190,,MATCH(SUBSTITUTE(F$3,"Q","T"),Inputs!$B$2:$AZ$2,0)),Inputs!$B$2:$B$190,$B13)*Inputs!$D$1) -> 0 | G13: =IF(ISNA(SUMIFS(INDEX(Inputs!$B$2:$AZ$190,,MATCH(SUBSTITUTE(G$3,"Q","T"),Inputs!$B$2:$AZ$2,0)),Inputs!$B$2:$B$190,$B13)*Inputs!$D$1),"",SUMIFS(INDEX(Inputs!$B$2:$AZ$190,,MATCH(SUBSTITUTE(G$3,"Q","T"),Inputs!$B$2:$AZ$2,0)),Inputs!$B$2:$B$190,$B13)*Inputs!$D$1) -> 0 | H13: =IF(ISNA(SUMIFS(INDEX(Inputs!$B$2:$AZ$190,,MATCH(SUBSTITUTE(H$3,"Q","T"),Inputs!$B$2:$AZ$2,0)),Inputs!$B$2:$B$190,$B13)*Inputs!$D$1),"",SUMIFS(INDEX(Inputs!$B$2:$AZ$190,,MATCH(SUBSTITUTE(H$3,"Q","T"),Inputs!$B$2:$AZ$2,0)),Inputs!$B$2:$B$190,$B13)*Inputs!$D$1) -> 0 | I13: =H13 -> 0 | J13: =IF(ISNA(SUMIFS(INDEX(Inputs!$B$2:$AZ$190,,MATCH(SUBSTITUTE(J$3,"Q","T"),Inputs!$B$2:$AZ$2,0)),Inputs!$B$2:$B$190,$B13)*Inputs!$D$1),"",SUMIFS(INDEX(Inputs!$B$2:$AZ$190,,MATCH(SUBSTITUTE(J$3,"Q","T"),Inputs!$B$2:$AZ$2,0)),Inputs!$B$2:$B$190,$B13)*Inputs!$D$1) -> 0 | K13: =IF(ISNA(SUMIFS(INDEX(Inputs!$B$2:$AZ$190,,MATCH(SUBSTITUTE(K$3,"Q","T"),Inputs!$B$2:$AZ$2,0)),Inputs!$B$2:$B$190,$B13)*Inputs!$D$1),"",SUMIFS(INDEX(Inputs!$B$2:$AZ$190,,MATCH(SUBSTITUTE(K$3,"Q","T"),Inputs!$B$2:$AZ$2,0)),Inputs!$B$2:$B$190,$B13)*Inputs!$D$1) -> 0 | L13: =IF(ISNA(SUMIFS(INDEX(Inputs!$B$2:$AZ$190,,MATCH(SUBSTITUTE(L$3,"Q","T"),Inputs!$B$2:$AZ$2,0)),Inputs!$B$2:$B$190,$B13)*Inputs!$D$1),"",SUMIFS(INDEX(Inputs!$B$2:$AZ$190,,MATCH(SUBSTITUTE(L$3,"Q","T"),Inputs!$B$2:$AZ$2,0)),Inputs!$B$2:$B$190,$B13)*Inputs!$D$1) -> 0 | M13: =IF(ISNA(SUMIFS(INDEX(Inputs!$B$2:$AZ$190,,MATCH(SUBSTITUTE(M$3,"Q","T"),Inputs!$B$2:$AZ$2,0)),Inputs!$B$2:$B$190,$B13)*Inputs!$D$1),"",SUMIFS(INDEX(Inputs!$B$2:$AZ$190,,MATCH(SUBSTITUTE(M$3,"Q","T"),Inputs!$B$2:$AZ$2,0)),Inputs!$B$2:$B$190,$B13)*Inputs!$D$1) -> 0 | N13: =M13 -> 0 | O13: =IF(ISNA(SUMIFS(INDEX(Inputs!$B$2:$AZ$190,,MATCH(SUBSTITUTE(O$3,"Q","T"),Inputs!$B$2:$AZ$2,0)),Inputs!$B$2:$B$190,$B13)*Inputs!$D$1),"",SUMIFS(INDEX(Inputs!$B$2:$AZ$190,,MATCH(SUBSTITUTE(O$3,"Q","T"),Inputs!$B$2:$AZ$2,0)),Inputs!$B$2:$B$190,$B13)*Inputs!$D$1) -> 0 | P13: =IF(ISNA(SUMIFS(INDEX(Inputs!$B$2:$AZ$190,,MATCH(SUBSTITUTE(P$3,"Q","T"),Inputs!$B$2:$AZ$2,0)),Inputs!$B$2:$B$190,$B13)*Inputs!$D$1),"",SUMIFS(INDEX(Inputs!$B$2:$AZ$190,,MATCH(SUBSTITUTE(P$3,"Q","T"),Inputs!$B$2:$AZ$2,0)),Inputs!$B$2:$B$190,$B13)*Inputs!$D$1) -> 0 | Q13: =IF(ISNA(SUMIFS(INDEX(Inputs!$B$2:$AZ$190,,MATCH(SUBSTITUTE(Q$3,"Q","T"),Inputs!$B$2:$AZ$2,0)),Inputs!$B$2:$B$190,$B13)*Inputs!$D$1),"",SUMIFS(INDEX(Inputs!$B$2:$AZ$190,,MATCH(SUBSTITUTE(Q$3,"Q","T"),Inputs!$B$2:$AZ$2,0)),Inputs!$B$2:$B$190,$B13)*Inputs!$D$1) -> 0 | R13: =IF(ISNA(SUMIFS(INDEX(Inputs!$B$2:$AZ$190,,MATCH(SUBSTITUTE(R$3,"Q","T"),Inputs!$B$2:$AZ$2,0)),Inputs!$B$2:$B$190,$B13)*Inputs!$D$1),"",SUMIFS(INDEX(Inputs!$B$2:$AZ$190,,MATCH(SUBSTITUTE(R$3,"Q","T"),Inputs!$B$2:$AZ$2,0)),Inputs!$B$2:$B$190,$B13)*Inputs!$D$1) -> 0 | S13: =R13 -> 0 | T13: =IF(ISNA(SUMIFS(INDEX(Inputs!$B$2:$AZ$190,,MATCH(SUBSTITUTE(T$3,"Q","T"),Inputs!$B$2:$AZ$2,0)),Inputs!$B$2:$B$190,$B13)*Inputs!$D$1),"",SUMIFS(INDEX(Inputs!$B$2:$AZ$190,,MATCH(SUBSTITUTE(T$3,"Q","T"),Inputs!$B$2:$AZ$2,0)),Inputs!$B$2:$B$190,$B13)*Inputs!$D$1) -> 0 | U13: =IF(ISNA(SUMIFS(INDEX(Inputs!$B$2:$AZ$190,,MATCH(SUBSTITUTE(U$3,"Q","T"),Inputs!$B$2:$AZ$2,0)),Inputs!$B$2:$B$190,$B13)*Inputs!$D$1),"",SUMIFS(INDEX(Inputs!$B$2:$AZ$190,,MATCH(SUBSTITUTE(U$3,"Q","T"),Inputs!$B$2:$AZ$2,0)),Inputs!$B$2:$B$190,$B13)*Inputs!$D$1) -> 0 | V13: =IF(ISNA(SUMIFS(INDEX(Inputs!$B$2:$AZ$190,,MATCH(SUBSTITUTE(V$3,"Q","T"),Inputs!$B$2:$AZ$2,0)),Inputs!$B$2:$B$190,$B13)*Inputs!$D$1),"",SUMIFS(INDEX(Inputs!$B$2:$AZ$190,,MATCH(SUBSTITUTE(V$3,"Q","T"),Inputs!$B$2:$AZ$2,0)),Inputs!$B$2:$B$190,$B13)*Inputs!$D$1) -> 0 | W13: =IF(ISNA(SUMIFS(INDEX(Inputs!$B$2:$AZ$190,,MATCH(SUBSTITUTE(W$3,"Q","T"),Inputs!$B$2:$AZ$2,0)),Inputs!$B$2:$B$190,$B13)*Inputs!$D$1),"",SUMIFS(INDEX(Inputs!$B$2:$AZ$190,,MATCH(SUBSTITUTE(W$3,"Q","T"),Inputs!$B$2:$AZ$2,0)),Inputs!$B$2:$B$190,$B13)*Inputs!$D$1) -> 0 | X13: =W13 -> 0 | Y13: =IF(ISNA(SUMIFS(INDEX(Inputs!$B$2:$AZ$190,,MATCH(SUBSTITUTE(Y$3,"Q","T"),Inputs!$B$2:$AZ$2,0)),Inputs!$B$2:$B$190,$B13)*Inputs!$D$1),"",SUMIFS(INDEX(Inputs!$B$2:$AZ$190,,MATCH(SUBSTITUTE(Y$3,"Q","T"),Inputs!$B$2:$AZ$2,0)),Inputs!$B$2:$B$190,$B13)*Inputs!$D$1) -> 0 | Z13: =IF(ISNA(SUMIFS(INDEX(Inputs!$B$2:$AZ$190,,MATCH(SUBSTITUTE(Z$3,"Q","T"),Inputs!$B$2:$AZ$2,0)),Inputs!$B$2:$B$190,$B13)*Inputs!$D$1),"",SUMIFS(INDEX(Inputs!$B$2:$AZ$190,,MATCH(SUBSTITUTE(Z$3,"Q","T"),Inputs!$B$2:$AZ$2,0)),Inputs!$B$2:$B$190,$B13)*Inputs!$D$1) -> 0 | AA13: =IF(ISNA(SUMIFS(INDEX(Inputs!$B$2:$AZ$190,,MATCH(SUBSTITUTE(AA$3,"Q","T"),Inputs!$B$2:$AZ$2,0)),Inputs!$B$2:$B$190,$B13)*Inputs!$D$1),"",SUMIFS(INDEX(Inputs!$B$2:$AZ$190,,MATCH(SUBSTITUTE(AA$3,"Q","T"),Inputs!$B$2:$AZ$2,0)),Inputs!$B$2:$B$190,$B13)*Inputs!$D$1) -> 0 | AB13: =IF(ISNA(SUMIFS(INDEX(Inputs!$B$2:$AZ$190,,MATCH(SUBSTITUTE(AB$3,"Q","T"),Inputs!$B$2:$AZ$2,0)),Inputs!$B$2:$B$190,$B13)*Inputs!$D$1),"",SUMIFS(INDEX(Inputs!$B$2:$AZ$190,,MATCH(SUBSTITUTE(AB$3,"Q","T"),Inputs!$B$2:$AZ$2,0)),Inputs!$B$2:$B$190,$B13)*Inputs!$D$1) -> 0 | AC13: =AB13 -> 0 | AD13: =IF(ISNA(SUMIFS(INDEX(Inputs!$B$2:$AZ$190,,MATCH(SUBSTITUTE(AD$3,"Q","T"),Inputs!$B$2:$AZ$2,0)),Inputs!$B$2:$B$190,$B13)*Inputs!$D$1),"",SUMIFS(INDEX(Inputs!$B$2:$AZ$190,,MATCH(SUBSTITUTE(AD$3,"Q","T"),Inputs!$B$2:$AZ$2,0)),Inputs!$B$2:$B$190,$B13)*Inputs!$D$1) -> 0 | AE13: =IF(ISNA(SUMIFS(INDEX(Inputs!$B$2:$AZ$190,,MATCH(SUBSTITUTE(AE$3,"Q","T"),Inputs!$B$2:$AZ$2,0)),Inputs!$B$2:$B$190,$B13)*Inputs!$D$1),"",SUMIFS(INDEX(Inputs!$B$2:$AZ$190,,MATCH(SUBSTITUTE(AE$3,"Q","T"),Inputs!$B$2:$AZ$2,0)),Inputs!$B$2:$B$190,$B13)*Inputs!$D$1) -> 0 | AF13: =IF(ISNA(SUMIFS(INDEX(Inputs!$B$2:$AZ$190,,MATCH(SUBSTITUTE(AF$3,"Q","T"),Inputs!$B$2:$AZ$2,0)),Inputs!$B$2:$B$190,$B13)*Inputs!$D$1),"",SUMIFS(INDEX(Inputs!$B$2:$AZ$190,,MATCH(SUBSTITUTE(AF$3,"Q","T"),Inputs!$B$2:$AZ$2,0)),Inputs!$B$2:$B$190,$B13)*Inputs!$D$1) -> 0 | AG13: =IF(ISNA(SUMIFS(INDEX(Inputs!$B$2:$AZ$190,,MATCH(SUBSTITUTE(AG$3,"Q","T"),Inputs!$B$2:$AZ$2,0)),Inputs!$B$2:$B$190,$B13)*Inputs!$D$1),"",SUMIFS(INDEX(Inputs!$B$2:$AZ$190,,MATCH(SUBSTITUTE(AG$3,"Q","T"),Inputs!$B$2:$AZ$2,0)),Inputs!$B$2:$B$190,$B13)*Inputs!$D$1) -> 0 | AH13: =AG13 -> 0 | AI13: =IF(ISNA(SUMIFS(INDEX(Inputs!$B$2:$AZ$190,,MATCH(SUBSTITUTE(AI$3,"Q","T"),Inputs!$B$2:$AZ$2,0)),Inputs!$B$2:$B$190,$B13)*Inputs!$D$1),"",SUMIFS(INDEX(Inputs!$B$2:$AZ$190,,MATCH(SUBSTITUTE(AI$3,"Q","T"),Inputs!$B$2:$AZ$2,0)),Inputs!$B$2:$B$190,$B13)*Inputs!$D$1) -> 0 | AJ13: =IF(ISNA(SUMIFS(INDEX(Inputs!$B$2:$AZ$190,,MATCH(SUBSTITUTE(AJ$3,"Q","T"),Inputs!$B$2:$AZ$2,0)),Inputs!$B$2:$B$190,$B13)*Inputs!$D$1),"",SUMIFS(INDEX(Inputs!$B$2:$AZ$190,,MATCH(SUBSTITUTE(AJ$3,"Q","T"),Inputs!$B$2:$AZ$2,0)),Inputs!$B$2:$B$190,$B13)*Inputs!$D$1) -> 0 | AK13: =IF(ISNA(SUMIFS(INDEX(Inputs!$B$2:$AZ$190,,MATCH(SUBSTITUTE(AK$3,"Q","T"),Inputs!$B$2:$AZ$2,0)),Inputs!$B$2:$B$190,$B13)*Inputs!$D$1),"",SUMIFS(INDEX(Inputs!$B$2:$AZ$190,,MATCH(SUBSTITUTE(AK$3,"Q","T"),Inputs!$B$2:$AZ$2,0)),Inputs!$B$2:$B$190,$B13)*Inputs!$D$1) -> 0 | AL13: =IF(ISNA(SUMIFS(INDEX(Inputs!$B$2:$AZ$190,,MATCH(SUBSTITUTE(AL$3,"Q","T"),Inputs!$B$2:$AZ$2,0)),Inputs!$B$2:$B$190,$B13)*Inputs!$D$1),"",SUMIFS(INDEX(Inputs!$B$2:$AZ$190,,MATCH(SUBSTITUTE(AL$3,"Q","T"),Inputs!$B$2:$AZ$2,0)),Inputs!$B$2:$B$190,$B13)*Inputs!$D$1) -> 0 | AM13: =AL13 -> 0 | AN13: =IF(ISNA(SUMIFS(INDEX(Inputs!$B$2:$AZ$190,,MATCH(SUBSTITUTE(AN$3,"Q","T"),Inputs!$B$2:$AZ$2,0)),Inputs!$B$2:$B$190,$B13)*Inputs!$D$1),"",SUMIFS(INDEX(Inputs!$B$2:$AZ$190,,MATCH(SUBSTITUTE(AN$3,"Q","T"),Inputs!$B$2:$AZ$2,0)),Inputs!$B$2:$B$190,$B13)*Inputs!$D$1) -> 0 | AO13: =IF(ISNA(SUMIFS(INDEX(Inputs!$B$2:$AZ$190,,MATCH(SUBSTITUTE(AO$3,"Q","T"),Inputs!$B$2:$AZ$2,0)),Inputs!$B$2:$B$190,$B13)*Inputs!$D$1),"",SUMIFS(INDEX(Inputs!$B$2:$AZ$190,,MATCH(SUBSTITUTE(AO$3,"Q","T"),Inputs!$B$2:$AZ$2,0)),Inputs!$B$2:$B$190,$B13)*Inputs!$D$1) -> 0 | AP13: =IF(ISNA(SUMIFS(INDEX(Inputs!$B$2:$AZ$190,,MATCH(SUBSTITUTE(AP$3,"Q","T"),Inputs!$B$2:$AZ$2,0)),Inputs!$B$2:$B$190,$B13)*Inputs!$D$1),"",SUMIFS(INDEX(Inputs!$B$2:$AZ$190,,MATCH(SUBSTITUTE(AP$3,"Q","T"),Inputs!$B$2:$AZ$2,0)),Inputs!$B$2:$B$190,$B13)*Inputs!$D$1) -> 0 | AQ13: =IF(ISNA(SUMIFS(INDEX(Inputs!$B$2:$AZ$190,,MATCH(SUBSTITUTE(AQ$3,"Q","T"),Inputs!$B$2:$AZ$2,0)),Inputs!$B$2:$B$190,$B13)*Inputs!$D$1),"",SUMIFS(INDEX(Inputs!$B$2:$AZ$190,,MATCH(SUBSTITUTE(AQ$3,"Q","T"),Inputs!$B$2:$AZ$2,0)),Inputs!$B$2:$B$190,$B13)*Inputs!$D$1) -> 0 | AR13: =AQ13 -> 0 | AS13: =IF(ISNA(SUMIFS(INDEX(Inputs!$B$2:$AZ$190,,MATCH(SUBSTITUTE(AS$3,"Q","T"),Inputs!$B$2:$AZ$2,0)),Inputs!$B$2:$B$190,$B13)*Inputs!$D$1),"",SUMIFS(INDEX(Inputs!$B$2:$AZ$190,,MATCH(SUBSTITUTE(AS$3,"Q","T"),Inputs!$B$2:$AZ$2,0)),Inputs!$B$2:$B$190,$B13)*Inputs!$D$1) -> 0 | AT13: =IF(ISNA(SUMIFS(INDEX(Inputs!$B$2:$AZ$190,,MATCH(SUBSTITUTE(AT$3,"Q","T"),Inputs!$B$2:$AZ$2,0)),Inputs!$B$2:$B$190,$B13)*Inputs!$D$1),"",SUMIFS(INDEX(Inputs!$B$2:$AZ$190,,MATCH(SUBSTITUTE(AT$3,"Q","T"),Inputs!$B$2:$AZ$2,0)),Inputs!$B$2:$B$190,$B13)*Inputs!$D$1) -> 0 | AU13: =IF(ISNA(SUMIFS(INDEX(Inputs!$B$2:$AZ$190,,MATCH(SUBSTITUTE(AU$3,"Q","T"),Inputs!$B$2:$AZ$2,0)),Inputs!$B$2:$B$190,$B13)*Inputs!$D$1),"",SUMIFS(INDEX(Inputs!$B$2:$AZ$190,,MATCH(SUBSTITUTE(AU$3,"Q","T"),Inputs!$B$2:$AZ$2,0)),Inputs!$B$2:$B$190,$B13)*Inputs!$D$1) -> 0 | AV13: =IF(ISNA(SUMIFS(INDEX(Inputs!$B$2:$AZ$190,,MATCH(SUBSTITUTE(AV$3,"Q","T"),Inputs!$B$2:$AZ$2,0)),Inputs!$B$2:$B$190,$B13)*Inputs!$D$1),"",SUMIFS(INDEX(Inputs!$B$2:$AZ$190,,MATCH(SUBSTITUTE(AV$3,"Q","T"),Inputs!$B$2:$AZ$2,0)),Inputs!$B$2:$B$190,$B13)*Inputs!$D$1) -> 0 | AW13: =AV13 -> 0 | AX13: =IF(ISNA(SUMIFS(INDEX(Inputs!$B$2:$AZ$190,,MATCH(SUBSTITUTE(AX$3,"Q","T"),Inputs!$B$2:$AZ$2,0)),Inputs!$B$2:$B$190,$B13)*Inputs!$D$1),"",SUMIFS(INDEX(Inputs!$B$2:$AZ$190,,MATCH(SUBSTITUTE(AX$3,"Q","T"),Inputs!$B$2:$AZ$2,0)),Inputs!$B$2:$B$190,$B13)*Inputs!$D$1) -> 0 | AY13: =IF(ISNA(SUMIFS(INDEX(Inputs!$B$2:$AZ$190,,MATCH(SUBSTITUTE(AY$3,"Q","T"),Inputs!$B$2:$AZ$2,0)),Inputs!$B$2:$B$190,$B13)*Inputs!$D$1),"",SUMIFS(INDEX(Inputs!$B$2:$AZ$190,,MATCH(SUBSTITUTE(AY$3,"Q","T"),Inputs!$B$2:$AZ$2,0)),Inputs!$B$2:$B$190,$B13)*Inputs!$D$1) -> 0 | AZ13: =IF(ISNA(SUMIFS(INDEX(Inputs!$B$2:$AZ$190,,MATCH(SUBSTITUTE(AZ$3,"Q","T"),Inputs!$B$2:$AZ$2,0)),Inputs!$B$2:$B$190,$B13)*Inputs!$D$1),"",SUMIFS(INDEX(Inputs!$B$2:$AZ$190,,MATCH(SUBSTITUTE(AZ$3,"Q","T"),Inputs!$B$2:$AZ$2,0)),Inputs!$B$2:$B$190,$B13)*Inputs!$D$1) -> 0 | BA13: =IF(ISNA(SUMIFS(INDEX(Inputs!$B$2:$AZ$190,,MATCH(SUBSTITUTE(BA$3,"Q","T"),Inputs!$B$2:$AZ$2,0)),Inputs!$B$2:$B$190,$B13)*Inputs!$D$1),"",SUMIFS(INDEX(Inputs!$B$2:$AZ$190,,MATCH(SUBSTITUTE(BA$3,"Q","T"),Inputs!$B$2:$AZ$2,0)),Inputs!$B$2:$B$190,$B13)*Inputs!$D$1) -> 0 | BB13: =BA13 -> 0 | BC13: =IF(ISNA(SUMIFS(INDEX(Inputs!$B$2:$AZ$190,,MATCH(SUBSTITUTE(BC$3,"Q","T"),Inputs!$B$2:$AZ$2,0)),Inputs!$B$2:$B$190,$B13)*Inputs!$D$1),"",SUMIFS(INDEX(Inputs!$B$2:$AZ$190,,MATCH(SUBSTITUTE(BC$3,"Q","T"),Inputs!$B$2:$AZ$2,0)),Inputs!$B$2:$B$190,$B13)*Inputs!$D$1) -> 0 | BD13: =IF(ISNA(SUMIFS(INDEX(Inputs!$B$2:$AZ$190,,MATCH(SUBSTITUTE(BD$3,"Q","T"),Inputs!$B$2:$AZ$2,0)),Inputs!$B$2:$B$190,$B13)*Inputs!$D$1),"",SUMIFS(INDEX(Inputs!$B$2:$AZ$190,,MATCH(SUBSTITUTE(BD$3,"Q","T"),Inputs!$B$2:$AZ$2,0)),Inputs!$B$2:$B$190,$B13)*Inputs!$D$1) -> 0 | BE13: =IF(ISNA(SUMIFS(INDEX(Inputs!$B$2:$AZ$190,,MATCH(SUBSTITUTE(BE$3,"Q","T"),Inputs!$B$2:$AZ$2,0)),Inputs!$B$2:$B$190,$B13)*Inputs!$D$1),"",SUMIFS(INDEX(Inputs!$B$2:$AZ$190,,MATCH(SUBSTITUTE(BE$3,"Q","T"),Inputs!$B$2:$AZ$2,0)),Inputs!$B$2:$B$190,$B13)*Inputs!$D$1) -> 0 | BF13: =IF(ISNA(SUMIFS(INDEX(Inputs!$B$2:$AZ$190,,MATCH(SUBSTITUTE(BF$3,"Q","T"),Inputs!$B$2:$AZ$2,0)),Inputs!$B$2:$B$190,$B13)*Inputs!$D$1),"",SUMIFS(INDEX(Inputs!$B$2:$AZ$190,,MATCH(SUBSTITUTE(BF$3,"Q","T"),Inputs!$B$2:$AZ$2,0)),Inputs!$B$2:$B$190,$B13)*Inputs!$D$1) -> 0 | BG13: =BF13 -> 0
B14: htm | C14: Títulos mantidos até o vencimento (HTM, custo amortizado) | D14: Held-to-maturity securities | E14: =IF(ISNA(SUMIFS(INDEX(Inputs!$B$2:$AZ$190,,MATCH(SUBSTITUTE(E$3,"Q","T"),Inputs!$B$2:$AZ$2,0)),Inputs!$B$2:$B$190,$B14)*Inputs!$D$1),"",SUMIFS(INDEX(Inputs!$B$2:$AZ$190,,MATCH(SUBSTITUTE(E$3,"Q","T"),Inputs!$B$2:$AZ$2,0)),Inputs!$B$2:$B$190,$B14)*Inputs!$D$1) -> 0 | F14: =IF(ISNA(SUMIFS(INDEX(Inputs!$B$2:$AZ$190,,MATCH(SUBSTITUTE(F$3,"Q","T"),Inputs!$B$2:$AZ$2,0)),Inputs!$B$2:$B$190,$B14)*Inputs!$D$1),"",SUMIFS(INDEX(Inputs!$B$2:$AZ$190,,MATCH(SUBSTITUTE(F$3,"Q","T"),Inputs!$B$2:$AZ$2,0)),Inputs!$B$2:$B$190,$B14)*Inputs!$D$1) -> 0 | G14: =IF(ISNA(SUMIFS(INDEX(Inputs!$B$2:$AZ$190,,MATCH(SUBSTITUTE(G$3,"Q","T"),Inputs!$B$2:$AZ$2,0)),Inputs!$B$2:$B$190,$B14)*Inputs!$D$1),"",SUMIFS(INDEX(Inputs!$B$2:$AZ$190,,MATCH(SUBSTITUTE(G$3,"Q","T"),Inputs!$B$2:$AZ$2,0)),Inputs!$B$2:$B$190,$B14)*Inputs!$D$1) -> 0 | H14: =IF(ISNA(SUMIFS(INDEX(Inputs!$B$2:$AZ$190,,MATCH(SUBSTITUTE(H$3,"Q","T"),Inputs!$B$2:$AZ$2,0)),Inputs!$B$2:$B$190,$B14)*Inputs!$D$1),"",SUMIFS(INDEX(Inputs!$B$2:$AZ$190,,MATCH(SUBSTITUTE(H$3,"Q","T"),Inputs!$B$2:$AZ$2,0)),Inputs!$B$2:$B$190,$B14)*Inputs!$D$1) -> 0 | I14: =H14 -> 0 | J14: =IF(ISNA(SUMIFS(INDEX(Inputs!$B$2:$AZ$190,,MATCH(SUBSTITUTE(J$3,"Q","T"),Inputs!$B$2:$AZ$2,0)),Inputs!$B$2:$B$190,$B14)*Inputs!$D$1),"",SUMIFS(INDEX(Inputs!$B$2:$AZ$190,,MATCH(SUBSTITUTE(J$3,"Q","T"),Inputs!$B$2:$AZ$2,0)),Inputs!$B$2:$B$190,$B14)*Inputs!$D$1) -> 0 | K14: =IF(ISNA(SUMIFS(INDEX(Inputs!$B$2:$AZ$190,,MATCH(SUBSTITUTE(K$3,"Q","T"),Inputs!$B$2:$AZ$2,0)),Inputs!$B$2:$B$190,$B14)*Inputs!$D$1),"",SUMIFS(INDEX(Inputs!$B$2:$AZ$190,,MATCH(SUBSTITUTE(K$3,"Q","T"),Inputs!$B$2:$AZ$2,0)),Inputs!$B$2:$B$190,$B14)*Inputs!$D$1) -> 0 | L14: =IF(ISNA(SUMIFS(INDEX(Inputs!$B$2:$AZ$190,,MATCH(SUBSTITUTE(L$3,"Q","T"),Inputs!$B$2:$AZ$2,0)),Inputs!$B$2:$B$190,$B14)*Inputs!$D$1),"",SUMIFS(INDEX(Inputs!$B$2:$AZ$190,,MATCH(SUBSTITUTE(L$3,"Q","T"),Inputs!$B$2:$AZ$2,0)),Inputs!$B$2:$B$190,$B14)*Inputs!$D$1) -> 0 | M14: =IF(ISNA(SUMIFS(INDEX(Inputs!$B$2:$AZ$190,,MATCH(SUBSTITUTE(M$3,"Q","T"),Inputs!$B$2:$AZ$2,0)),Inputs!$B$2:$B$190,$B14)*Inputs!$D$1),"",SUMIFS(INDEX(Inputs!$B$2:$AZ$190,,MATCH(SUBSTITUTE(M$3,"Q","T"),Inputs!$B$2:$AZ$2,0)),Inputs!$B$2:$B$190,$B14)*Inputs!$D$1) -> 0 | N14: =M14 -> 0 | O14: =IF(ISNA(SUMIFS(INDEX(Inputs!$B$2:$AZ$190,,MATCH(SUBSTITUTE(O$3,"Q","T"),Inputs!$B$2:$AZ$2,0)),Inputs!$B$2:$B$190,$B14)*Inputs!$D$1),"",SUMIFS(INDEX(Inputs!$B$2:$AZ$190,,MATCH(SUBSTITUTE(O$3,"Q","T"),Inputs!$B$2:$AZ$2,0)),Inputs!$B$2:$B$190,$B14)*Inputs!$D$1) -> 0 | P14: =IF(ISNA(SUMIFS(INDEX(Inputs!$B$2:$AZ$190,,MATCH(SUBSTITUTE(P$3,"Q","T"),Inputs!$B$2:$AZ$2,0)),Inputs!$B$2:$B$190,$B14)*Inputs!$D$1),"",SUMIFS(INDEX(Inputs!$B$2:$AZ$190,,MATCH(SUBSTITUTE(P$3,"Q","T"),Inputs!$B$2:$AZ$2,0)),Inputs!$B$2:$B$190,$B14)*Inputs!$D$1) -> 0 | Q14: =IF(ISNA(SUMIFS(INDEX(Inputs!$B$2:$AZ$190,,MATCH(SUBSTITUTE(Q$3,"Q","T"),Inputs!$B$2:$AZ$2,0)),Inputs!$B$2:$B$190,$B14)*Inputs!$D$1),"",SUMIFS(INDEX(Inputs!$B$2:$AZ$190,,MATCH(SUBSTITUTE(Q$3,"Q","T"),Inputs!$B$2:$AZ$2,0)),Inputs!$B$2:$B$190,$B14)*Inputs!$D$1) -> 0 | R14: =IF(ISNA(SUMIFS(INDEX(Inputs!$B$2:$AZ$190,,MATCH(SUBSTITUTE(R$3,"Q","T"),Inputs!$B$2:$AZ$2,0)),Inputs!$B$2:$B$190,$B14)*Inputs!$D$1),"",SUMIFS(INDEX(Inputs!$B$2:$AZ$190,,MATCH(SUBSTITUTE(R$3,"Q","T"),Inputs!$B$2:$AZ$2,0)),Inputs!$B$2:$B$190,$B14)*Inputs!$D$1) -> 0 | S14: =R14 -> 0 | T14: =IF(ISNA(SUMIFS(INDEX(Inputs!$B$2:$AZ$190,,MATCH(SUBSTITUTE(T$3,"Q","T"),Inputs!$B$2:$AZ$2,0)),Inputs!$B$2:$B$190,$B14)*Inputs!$D$1),"",SUMIFS(INDEX(Inputs!$B$2:$AZ$190,,MATCH(SUBSTITUTE(T$3,"Q","T"),Inputs!$B$2:$AZ$2,0)),Inputs!$B$2:$B$190,$B14)*Inputs!$D$1) -> 0 | U14: =IF(ISNA(SUMIFS(INDEX(Inputs!$B$2:$AZ$190,,MATCH(SUBSTITUTE(U$3,"Q","T"),Inputs!$B$2:$AZ$2,0)),Inputs!$B$2:$B$190,$B14)*Inputs!$D$1),"",SUMIFS(INDEX(Inputs!$B$2:$AZ$190,,MATCH(SUBSTITUTE(U$3,"Q","T"),Inputs!$B$2:$AZ$2,0)),Inputs!$B$2:$B$190,$B14)*Inputs!$D$1) -> 0 | V14: =IF(ISNA(SUMIFS(INDEX(Inputs!$B$2:$AZ$190,,MATCH(SUBSTITUTE(V$3,"Q","T"),Inputs!$B$2:$AZ$2,0)),Inputs!$B$2:$B$190,$B14)*Inputs!$D$1),"",SUMIFS(INDEX(Inputs!$B$2:$AZ$190,,MATCH(SUBSTITUTE(V$3,"Q","T"),Inputs!$B$2:$AZ$2,0)),Inputs!$B$2:$B$190,$B14)*Inputs!$D$1) -> 0 | W14: =IF(ISNA(SUMIFS(INDEX(Inputs!$B$2:$AZ$190,,MATCH(SUBSTITUTE(W$3,"Q","T"),Inputs!$B$2:$AZ$2,0)),Inputs!$B$2:$B$190,$B14)*Inputs!$D$1),"",SUMIFS(INDEX(Inputs!$B$2:$AZ$190,,MATCH(SUBSTITUTE(W$3,"Q","T"),Inputs!$B$2:$AZ$2,0)),Inputs!$B$2:$B$190,$B14)*Inputs!$D$1) -> 0 | X14: =W14 -> 0 | Y14: =IF(ISNA(SUMIFS(INDEX(Inputs!$B$2:$AZ$190,,MATCH(SUBSTITUTE(Y$3,"Q","T"),Inputs!$B$2:$AZ$2,0)),Inputs!$B$2:$B$190,$B14)*Inputs!$D$1),"",SUMIFS(INDEX(Inputs!$B$2:$AZ$190,,MATCH(SUBSTITUTE(Y$3,"Q","T"),Inputs!$B$2:$AZ$2,0)),Inputs!$B$2:$B$190,$B14)*Inputs!$D$1) -> 0 | Z14: =IF(ISNA(SUMIFS(INDEX(Inputs!$B$2:$AZ$190,,MATCH(SUBSTITUTE(Z$3,"Q","T"),Inputs!$B$2:$AZ$2,0)),Inputs!$B$2:$B$190,$B14)*Inputs!$D$1),"",SUMIFS(INDEX(Inputs!$B$2:$AZ$190,,MATCH(SUBSTITUTE(Z$3,"Q","T"),Inputs!$B$2:$AZ$2,0)),Inputs!$B$2:$B$190,$B14)*Inputs!$D$1) -> 0 | AA14: =IF(ISNA(SUMIFS(INDEX(Inputs!$B$2:$AZ$190,,MATCH(SUBSTITUTE(AA$3,"Q","T"),Inputs!$B$2:$AZ$2,0)),Inputs!$B$2:$B$190,$B14)*Inputs!$D$1),"",SUMIFS(INDEX(Inputs!$B$2:$AZ$190,,MATCH(SUBSTITUTE(AA$3,"Q","T"),Inputs!$B$2:$AZ$2,0)),Inputs!$B$2:$B$190,$B14)*Inputs!$D$1) -> 0 | AB14: =IF(ISNA(SUMIFS(INDEX(Inputs!$B$2:$AZ$190,,MATCH(SUBSTITUTE(AB$3,"Q","T"),Inputs!$B$2:$AZ$2,0)),Inputs!$B$2:$B$190,$B14)*Inputs!$D$1),"",SUMIFS(INDEX(Inputs!$B$2:$AZ$190,,MATCH(SUBSTITUTE(AB$3,"Q","T"),Inputs!$B$2:$AZ$2,0)),Inputs!$B$2:$B$190,$B14)*Inputs!$D$1) -> 0 | AC14: =AB14 -> 0 | AD14: =IF(ISNA(SUMIFS(INDEX(Inputs!$B$2:$AZ$190,,MATCH(SUBSTITUTE(AD$3,"Q","T"),Inputs!$B$2:$AZ$2,0)),Inputs!$B$2:$B$190,$B14)*Inputs!$D$1),"",SUMIFS(INDEX(Inputs!$B$2:$AZ$190,,MATCH(SUBSTITUTE(AD$3,"Q","T"),Inputs!$B$2:$AZ$2,0)),Inputs!$B$2:$B$190,$B14)*Inputs!$D$1) -> 0 | AE14: =IF(ISNA(SUMIFS(INDEX(Inputs!$B$2:$AZ$190,,MATCH(SUBSTITUTE(AE$3,"Q","T"),Inputs!$B$2:$AZ$2,0)),Inputs!$B$2:$B$190,$B14)*Inputs!$D$1),"",SUMIFS(INDEX(Inputs!$B$2:$AZ$190,,MATCH(SUBSTITUTE(AE$3,"Q","T"),Inputs!$B$2:$AZ$2,0)),Inputs!$B$2:$B$190,$B14)*Inputs!$D$1) -> 0 | AF14: =IF(ISNA(SUMIFS(INDEX(Inputs!$B$2:$AZ$190,,MATCH(SUBSTITUTE(AF$3,"Q","T"),Inputs!$B$2:$AZ$2,0)),Inputs!$B$2:$B$190,$B14)*Inputs!$D$1),"",SUMIFS(INDEX(Inputs!$B$2:$AZ$190,,MATCH(SUBSTITUTE(AF$3,"Q","T"),Inputs!$B$2:$AZ$2,0)),Inputs!$B$2:$B$190,$B14)*Inputs!$D$1) -> 0 | AG14: =IF(ISNA(SUMIFS(INDEX(Inputs!$B$2:$AZ$190,,MATCH(SUBSTITUTE(AG$3,"Q","T"),Inputs!$B$2:$AZ$2,0)),Inputs!$B$2:$B$190,$B14)*Inputs!$D$1),"",SUMIFS(INDEX(Inputs!$B$2:$AZ$190,,MATCH(SUBSTITUTE(AG$3,"Q","T"),Inputs!$B$2:$AZ$2,0)),Inputs!$B$2:$B$190,$B14)*Inputs!$D$1) -> 0 | AH14: =AG14 -> 0 | AI14: =IF(ISNA(SUMIFS(INDEX(Inputs!$B$2:$AZ$190,,MATCH(SUBSTITUTE(AI$3,"Q","T"),Inputs!$B$2:$AZ$2,0)),Inputs!$B$2:$B$190,$B14)*Inputs!$D$1),"",SUMIFS(INDEX(Inputs!$B$2:$AZ$190,,MATCH(SUBSTITUTE(AI$3,"Q","T"),Inputs!$B$2:$AZ$2,0)),Inputs!$B$2:$B$190,$B14)*Inputs!$D$1) -> 0 | AJ14: =IF(ISNA(SUMIFS(INDEX(Inputs!$B$2:$AZ$190,,MATCH(SUBSTITUTE(AJ$3,"Q","T"),Inputs!$B$2:$AZ$2,0)),Inputs!$B$2:$B$190,$B14)*Inputs!$D$1),"",SUMIFS(INDEX(Inputs!$B$2:$AZ$190,,MATCH(SUBSTITUTE(AJ$3,"Q","T"),Inputs!$B$2:$AZ$2,0)),Inputs!$B$2:$B$190,$B14)*Inputs!$D$1) -> 0 | AK14: =IF(ISNA(SUMIFS(INDEX(Inputs!$B$2:$AZ$190,,MATCH(SUBSTITUTE(AK$3,"Q","T"),Inputs!$B$2:$AZ$2,0)),Inputs!$B$2:$B$190,$B14)*Inputs!$D$1),"",SUMIFS(INDEX(Inputs!$B$2:$AZ$190,,MATCH(SUBSTITUTE(AK$3,"Q","T"),Inputs!$B$2:$AZ$2,0)),Inputs!$B$2:$B$190,$B14)*Inputs!$D$1) -> 0 | AL14: =IF(ISNA(SUMIFS(INDEX(Inputs!$B$2:$AZ$190,,MATCH(SUBSTITUTE(AL$3,"Q","T"),Inputs!$B$2:$AZ$2,0)),Inputs!$B$2:$B$190,$B14)*Inputs!$D$1),"",SUMIFS(INDEX(Inputs!$B$2:$AZ$190,,MATCH(SUBSTITUTE(AL$3,"Q","T"),Inputs!$B$2:$AZ$2,0)),Inputs!$B$2:$B$190,$B14)*Inputs!$D$1) -> 0 | AM14: =AL14 -> 0 | AN14: =IF(ISNA(SUMIFS(INDEX(Inputs!$B$2:$AZ$190,,MATCH(SUBSTITUTE(AN$3,"Q","T"),Inputs!$B$2:$AZ$2,0)),Inputs!$B$2:$B$190,$B14)*Inputs!$D$1),"",SUMIFS(INDEX(Inputs!$B$2:$AZ$190,,MATCH(SUBSTITUTE(AN$3,"Q","T"),Inputs!$B$2:$AZ$2,0)),Inputs!$B$2:$B$190,$B14)*Inputs!$D$1) -> 0 | AO14: =IF(ISNA(SUMIFS(INDEX(Inputs!$B$2:$AZ$190,,MATCH(SUBSTITUTE(AO$3,"Q","T"),Inputs!$B$2:$AZ$2,0)),Inputs!$B$2:$B$190,$B14)*Inputs!$D$1),"",SUMIFS(INDEX(Inputs!$B$2:$AZ$190,,MATCH(SUBSTITUTE(AO$3,"Q","T"),Inputs!$B$2:$AZ$2,0)),Inputs!$B$2:$B$190,$B14)*Inputs!$D$1) -> 0 | AP14: =IF(ISNA(SUMIFS(INDEX(Inputs!$B$2:$AZ$190,,MATCH(SUBSTITUTE(AP$3,"Q","T"),Inputs!$B$2:$AZ$2,0)),Inputs!$B$2:$B$190,$B14)*Inputs!$D$1),"",SUMIFS(INDEX(Inputs!$B$2:$AZ$190,,MATCH(SUBSTITUTE(AP$3,"Q","T"),Inputs!$B$2:$AZ$2,0)),Inputs!$B$2:$B$190,$B14)*Inputs!$D$1) -> 0 | AQ14: =IF(ISNA(SUMIFS(INDEX(Inputs!$B$2:$AZ$190,,MATCH(SUBSTITUTE(AQ$3,"Q","T"),Inputs!$B$2:$AZ$2,0)),Inputs!$B$2:$B$190,$B14)*Inputs!$D$1),"",SUMIFS(INDEX(Inputs!$B$2:$AZ$190,,MATCH(SUBSTITUTE(AQ$3,"Q","T"),Inputs!$B$2:$AZ$2,0)),Inputs!$B$2:$B$190,$B14)*Inputs!$D$1) -> 0 | AR14: =AQ14 -> 0 | AS14: =IF(ISNA(SUMIFS(INDEX(Inputs!$B$2:$AZ$190,,MATCH(SUBSTITUTE(AS$3,"Q","T"),Inputs!$B$2:$AZ$2,0)),Inputs!$B$2:$B$190,$B14)*Inputs!$D$1),"",SUMIFS(INDEX(Inputs!$B$2:$AZ$190,,MATCH(SUBSTITUTE(AS$3,"Q","T"),Inputs!$B$2:$AZ$2,0)),Inputs!$B$2:$B$190,$B14)*Inputs!$D$1) -> 0 | AT14: =IF(ISNA(SUMIFS(INDEX(Inputs!$B$2:$AZ$190,,MATCH(SUBSTITUTE(AT$3,"Q","T"),Inputs!$B$2:$AZ$2,0)),Inputs!$B$2:$B$190,$B14)*Inputs!$D$1),"",SUMIFS(INDEX(Inputs!$B$2:$AZ$190,,MATCH(SUBSTITUTE(AT$3,"Q","T"),Inputs!$B$2:$AZ$2,0)),Inputs!$B$2:$B$190,$B14)*Inputs!$D$1) -> 0 | AU14: =IF(ISNA(SUMIFS(INDEX(Inputs!$B$2:$AZ$190,,MATCH(SUBSTITUTE(AU$3,"Q","T"),Inputs!$B$2:$AZ$2,0)),Inputs!$B$2:$B$190,$B14)*Inputs!$D$1),"",SUMIFS(INDEX(Inputs!$B$2:$AZ$190,,MATCH(SUBSTITUTE(AU$3,"Q","T"),Inputs!$B$2:$AZ$2,0)),Inputs!$B$2:$B$190,$B14)*Inputs!$D$1) -> 0 | AV14: =IF(ISNA(SUMIFS(INDEX(Inputs!$B$2:$AZ$190,,MATCH(SUBSTITUTE(AV$3,"Q","T"),Inputs!$B$2:$AZ$2,0)),Inputs!$B$2:$B$190,$B14)*Inputs!$D$1),"",SUMIFS(INDEX(Inputs!$B$2:$AZ$190,,MATCH(SUBSTITUTE(AV$3,"Q","T"),Inputs!$B$2:$AZ$2,0)),Inputs!$B$2:$B$190,$B14)*Inputs!$D$1) -> 0 | AW14: =AV14 -> 0 | AX14: =IF(ISNA(SUMIFS(INDEX(Inputs!$B$2:$AZ$190,,MATCH(SUBSTITUTE(AX$3,"Q","T"),Inputs!$B$2:$AZ$2,0)),Inputs!$B$2:$B$190,$B14)*Inputs!$D$1),"",SUMIFS(INDEX(Inputs!$B$2:$AZ$190,,MATCH(SUBSTITUTE(AX$3,"Q","T"),Inputs!$B$2:$AZ$2,0)),Inputs!$B$2:$B$190,$B14)*Inputs!$D$1) -> 0 | AY14: =IF(ISNA(SUMIFS(INDEX(Inputs!$B$2:$AZ$190,,MATCH(SUBSTITUTE(AY$3,"Q","T"),Inputs!$B$2:$AZ$2,0)),Inputs!$B$2:$B$190,$B14)*Inputs!$D$1),"",SUMIFS(INDEX(Inputs!$B$2:$AZ$190,,MATCH(SUBSTITUTE(AY$3,"Q","T"),Inputs!$B$2:$AZ$2,0)),Inputs!$B$2:$B$190,$B14)*Inputs!$D$1) -> 0 | AZ14: =IF(ISNA(SUMIFS(INDEX(Inputs!$B$2:$AZ$190,,MATCH(SUBSTITUTE(AZ$3,"Q","T"),Inputs!$B$2:$AZ$2,0)),Inputs!$B$2:$B$190,$B14)*Inputs!$D$1),"",SUMIFS(INDEX(Inputs!$B$2:$AZ$190,,MATCH(SUBSTITUTE(AZ$3,"Q","T"),Inputs!$B$2:$AZ$2,0)),Inputs!$B$2:$B$190,$B14)*Inputs!$D$1) -> 0 | BA14: =IF(ISNA(SUMIFS(INDEX(Inputs!$B$2:$AZ$190,,MATCH(SUBSTITUTE(BA$3,"Q","T"),Inputs!$B$2:$AZ$2,0)),Inputs!$B$2:$B$190,$B14)*Inputs!$D$1),"",SUMIFS(INDEX(Inputs!$B$2:$AZ$190,,MATCH(SUBSTITUTE(BA$3,"Q","T"),Inputs!$B$2:$AZ$2,0)),Inputs!$B$2:$B$190,$B14)*Inputs!$D$1) -> 0 | BB14: =BA14 -> 0 | BC14: =IF(ISNA(SUMIFS(INDEX(Inputs!$B$2:$AZ$190,,MATCH(SUBSTITUTE(BC$3,"Q","T"),Inputs!$B$2:$AZ$2,0)),Inputs!$B$2:$B$190,$B14)*Inputs!$D$1),"",SUMIFS(INDEX(Inputs!$B$2:$AZ$190,,MATCH(SUBSTITUTE(BC$3,"Q","T"),Inputs!$B$2:$AZ$2,0)),Inputs!$B$2:$B$190,$B14)*Inputs!$D$1) -> 0 | BD14: =IF(ISNA(SUMIFS(INDEX(Inputs!$B$2:$AZ$190,,MATCH(SUBSTITUTE(BD$3,"Q","T"),Inputs!$B$2:$AZ$2,0)),Inputs!$B$2:$B$190,$B14)*Inputs!$D$1),"",SUMIFS(INDEX(Inputs!$B$2:$AZ$190,,MATCH(SUBSTITUTE(BD$3,"Q","T"),Inputs!$B$2:$AZ$2,0)),Inputs!$B$2:$B$190,$B14)*Inputs!$D$1) -> 0 | BE14: =IF(ISNA(SUMIFS(INDEX(Inputs!$B$2:$AZ$190,,MATCH(SUBSTITUTE(BE$3,"Q","T"),Inputs!$B$2:$AZ$2,0)),Inputs!$B$2:$B$190,$B14)*Inputs!$D$1),"",SUMIFS(INDEX(Inputs!$B$2:$AZ$190,,MATCH(SUBSTITUTE(BE$3,"Q","T"),Inputs!$B$2:$AZ$2,0)),Inputs!$B$2:$B$190,$B14)*Inputs!$D$1) -> 0 | BF14: =IF(ISNA(SUMIFS(INDEX(Inputs!$B$2:$AZ$190,,MATCH(SUBSTITUTE(BF$3,"Q","T"),Inputs!$B$2:$AZ$2,0)),Inputs!$B$2:$B$190,$B14)*Inputs!$D$1),"",SUMIFS(INDEX(Inputs!$B$2:$AZ$190,,MATCH(SUBSTITUTE(BF$3,"Q","T"),Inputs!$B$2:$AZ$2,0)),Inputs!$B$2:$B$190,$B14)*Inputs!$D$1) -> 0 | BG14: =BF14 -> 0
B15: sec_acl | C15: (Provisão para perdas — títulos, quando à parte) | D15: (Allowance — securities) | E15: =IF(ISNA(SUMIFS(INDEX(Inputs!$B$2:$AZ$190,,MATCH(SUBSTITUTE(E$3,"Q","T"),Inputs!$B$2:$AZ$2,0)),Inputs!$B$2:$B$190,$B15)*Inputs!$D$1),"",SUMIFS(INDEX(Inputs!$B$2:$AZ$190,,MATCH(SUBSTITUTE(E$3,"Q","T"),Inputs!$B$2:$AZ$2,0)),Inputs!$B$2:$B$190,$B15)*Inputs!$D$1) -> 0 | F15: =IF(ISNA(SUMIFS(INDEX(Inputs!$B$2:$AZ$190,,MATCH(SUBSTITUTE(F$3,"Q","T"),Inputs!$B$2:$AZ$2,0)),Inputs!$B$2:$B$190,$B15)*Inputs!$D$1),"",SUMIFS(INDEX(Inputs!$B$2:$AZ$190,,MATCH(SUBSTITUTE(F$3,"Q","T"),Inputs!$B$2:$AZ$2,0)),Inputs!$B$2:$B$190,$B15)*Inputs!$D$1) -> 0 | G15: =IF(ISNA(SUMIFS(INDEX(Inputs!$B$2:$AZ$190,,MATCH(SUBSTITUTE(G$3,"Q","T"),Inputs!$B$2:$AZ$2,0)),Inputs!$B$2:$B$190,$B15)*Inputs!$D$1),"",SUMIFS(INDEX(Inputs!$B$2:$AZ$190,,MATCH(SUBSTITUTE(G$3,"Q","T"),Inputs!$B$2:$AZ$2,0)),Inputs!$B$2:$B$190,$B15)*Inputs!$D$1) -> 0 | H15: =IF(ISNA(SUMIFS(INDEX(Inputs!$B$2:$AZ$190,,MATCH(SUBSTITUTE(H$3,"Q","T"),Inputs!$B$2:$AZ$2,0)),Inputs!$B$2:$B$190,$B15)*Inputs!$D$1),"",SUMIFS(INDEX(Inputs!$B$2:$AZ$190,,MATCH(SUBSTITUTE(H$3,"Q","T"),Inputs!$B$2:$AZ$2,0)),Inputs!$B$2:$B$190,$B15)*Inputs!$D$1) -> 0 | I15: =H15 -> 0 | J15: =IF(ISNA(SUMIFS(INDEX(Inputs!$B$2:$AZ$190,,MATCH(SUBSTITUTE(J$3,"Q","T"),Inputs!$B$2:$AZ$2,0)),Inputs!$B$2:$B$190,$B15)*Inputs!$D$1),"",SUMIFS(INDEX(Inputs!$B$2:$AZ$190,,MATCH(SUBSTITUTE(J$3,"Q","T"),Inputs!$B$2:$AZ$2,0)),Inputs!$B$2:$B$190,$B15)*Inputs!$D$1) -> 0 | K15: =IF(ISNA(SUMIFS(INDEX(Inputs!$B$2:$AZ$190,,MATCH(SUBSTITUTE(K$3,"Q","T"),Inputs!$B$2:$AZ$2,0)),Inputs!$B$2:$B$190,$B15)*Inputs!$D$1),"",SUMIFS(INDEX(Inputs!$B$2:$AZ$190,,MATCH(SUBSTITUTE(K$3,"Q","T"),Inputs!$B$2:$AZ$2,0)),Inputs!$B$2:$B$190,$B15)*Inputs!$D$1) -> 0 | L15: =IF(ISNA(SUMIFS(INDEX(Inputs!$B$2:$AZ$190,,MATCH(SUBSTITUTE(L$3,"Q","T"),Inputs!$B$2:$AZ$2,0)),Inputs!$B$2:$B$190,$B15)*Inputs!$D$1),"",SUMIFS(INDEX(Inputs!$B$2:$AZ$190,,MATCH(SUBSTITUTE(L$3,"Q","T"),Inputs!$B$2:$AZ$2,0)),Inputs!$B$2:$B$190,$B15)*Inputs!$D$1) -> 0 | M15: =IF(ISNA(SUMIFS(INDEX(Inputs!$B$2:$AZ$190,,MATCH(SUBSTITUTE(M$3,"Q","T"),Inputs!$B$2:$AZ$2,0)),Inputs!$B$2:$B$190,$B15)*Inputs!$D$1),"",SUMIFS(INDEX(Inputs!$B$2:$AZ$190,,MATCH(SUBSTITUTE(M$3,"Q","T"),Inputs!$B$2:$AZ$2,0)),Inputs!$B$2:$B$190,$B15)*Inputs!$D$1) -> 0 | N15: =M15 -> 0 | O15: =IF(ISNA(SUMIFS(INDEX(Inputs!$B$2:$AZ$190,,MATCH(SUBSTITUTE(O$3,"Q","T"),Inputs!$B$2:$AZ$2,0)),Inputs!$B$2:$B$190,$B15)*Inputs!$D$1),"",SUMIFS(INDEX(Inputs!$B$2:$AZ$190,,MATCH(SUBSTITUTE(O$3,"Q","T"),Inputs!$B$2:$AZ$2,0)),Inputs!$B$2:$B$190,$B15)*Inputs!$D$1) -> 0 | P15: =IF(ISNA(SUMIFS(INDEX(Inputs!$B$2:$AZ$190,,MATCH(SUBSTITUTE(P$3,"Q","T"),Inputs!$B$2:$AZ$2,0)),Inputs!$B$2:$B$190,$B15)*Inputs!$D$1),"",SUMIFS(INDEX(Inputs!$B$2:$AZ$190,,MATCH(SUBSTITUTE(P$3,"Q","T"),Inputs!$B$2:$AZ$2,0)),Inputs!$B$2:$B$190,$B15)*Inputs!$D$1) -> 0 | Q15: =IF(ISNA(SUMIFS(INDEX(Inputs!$B$2:$AZ$190,,MATCH(SUBSTITUTE(Q$3,"Q","T"),Inputs!$B$2:$AZ$2,0)),Inputs!$B$2:$B$190,$B15)*Inputs!$D$1),"",SUMIFS(INDEX(Inputs!$B$2:$AZ$190,,MATCH(SUBSTITUTE(Q$3,"Q","T"),Inputs!$B$2:$AZ$2,0)),Inputs!$B$2:$B$190,$B15)*Inputs!$D$1) -> 0 | R15: =IF(ISNA(SUMIFS(INDEX(Inputs!$B$2:$AZ$190,,MATCH(SUBSTITUTE(R$3,"Q","T"),Inputs!$B$2:$AZ$2,0)),Inputs!$B$2:$B$190,$B15)*Inputs!$D$1),"",SUMIFS(INDEX(Inputs!$B$2:$AZ$190,,MATCH(SUBSTITUTE(R$3,"Q","T"),Inputs!$B$2:$AZ$2,0)),Inputs!$B$2:$B$190,$B15)*Inputs!$D$1) -> 0 | S15: =R15 -> 0 | T15: =IF(ISNA(SUMIFS(INDEX(Inputs!$B$2:$AZ$190,,MATCH(SUBSTITUTE(T$3,"Q","T"),Inputs!$B$2:$AZ$2,0)),Inputs!$B$2:$B$190,$B15)*Inputs!$D$1),"",SUMIFS(INDEX(Inputs!$B$2:$AZ$190,,MATCH(SUBSTITUTE(T$3,"Q","T"),Inputs!$B$2:$AZ$2,0)),Inputs!$B$2:$B$190,$B15)*Inputs!$D$1) -> 0 | U15: =IF(ISNA(SUMIFS(INDEX(Inputs!$B$2:$AZ$190,,MATCH(SUBSTITUTE(U$3,"Q","T"),Inputs!$B$2:$AZ$2,0)),Inputs!$B$2:$B$190,$B15)*Inputs!$D$1),"",SUMIFS(INDEX(Inputs!$B$2:$AZ$190,,MATCH(SUBSTITUTE(U$3,"Q","T"),Inputs!$B$2:$AZ$2,0)),Inputs!$B$2:$B$190,$B15)*Inputs!$D$1) -> 0 | V15: =IF(ISNA(SUMIFS(INDEX(Inputs!$B$2:$AZ$190,,MATCH(SUBSTITUTE(V$3,"Q","T"),Inputs!$B$2:$AZ$2,0)),Inputs!$B$2:$B$190,$B15)*Inputs!$D$1),"",SUMIFS(INDEX(Inputs!$B$2:$AZ$190,,MATCH(SUBSTITUTE(V$3,"Q","T"),Inputs!$B$2:$AZ$2,0)),Inputs!$B$2:$B$190,$B15)*Inputs!$D$1) -> 0 | W15: =IF(ISNA(SUMIFS(INDEX(Inputs!$B$2:$AZ$190,,MATCH(SUBSTITUTE(W$3,"Q","T"),Inputs!$B$2:$AZ$2,0)),Inputs!$B$2:$B$190,$B15)*Inputs!$D$1),"",SUMIFS(INDEX(Inputs!$B$2:$AZ$190,,MATCH(SUBSTITUTE(W$3,"Q","T"),Inputs!$B$2:$AZ$2,0)),Inputs!$B$2:$B$190,$B15)*Inputs!$D$1) -> 0 | X15: =W15 -> 0 | Y15: =IF(ISNA(SUMIFS(INDEX(Inputs!$B$2:$AZ$190,,MATCH(SUBSTITUTE(Y$3,"Q","T"),Inputs!$B$2:$AZ$2,0)),Inputs!$B$2:$B$190,$B15)*Inputs!$D$1),"",SUMIFS(INDEX(Inputs!$B$2:$AZ$190,,MATCH(SUBSTITUTE(Y$3,"Q","T"),Inputs!$B$2:$AZ$2,0)),Inputs!$B$2:$B$190,$B15)*Inputs!$D$1) -> 0 | Z15: =IF(ISNA(SUMIFS(INDEX(Inputs!$B$2:$AZ$190,,MATCH(SUBSTITUTE(Z$3,"Q","T"),Inputs!$B$2:$AZ$2,0)),Inputs!$B$2:$B$190,$B15)*Inputs!$D$1),"",SUMIFS(INDEX(Inputs!$B$2:$AZ$190,,MATCH(SUBSTITUTE(Z$3,"Q","T"),Inputs!$B$2:$AZ$2,0)),Inputs!$B$2:$B$190,$B15)*Inputs!$D$1) -> 0 | AA15: =IF(ISNA(SUMIFS(INDEX(Inputs!$B$2:$AZ$190,,MATCH(SUBSTITUTE(AA$3,"Q","T"),Inputs!$B$2:$AZ$2,0)),Inputs!$B$2:$B$190,$B15)*Inputs!$D$1),"",SUMIFS(INDEX(Inputs!$B$2:$AZ$190,,MATCH(SUBSTITUTE(AA$3,"Q","T"),Inputs!$B$2:$AZ$2,0)),Inputs!$B$2:$B$190,$B15)*Inputs!$D$1) -> 0 | AB15: =IF(ISNA(SUMIFS(INDEX(Inputs!$B$2:$AZ$190,,MATCH(SUBSTITUTE(AB$3,"Q","T"),Inputs!$B$2:$AZ$2,0)),Inputs!$B$2:$B$190,$B15)*Inputs!$D$1),"",SUMIFS(INDEX(Inputs!$B$2:$AZ$190,,MATCH(SUBSTITUTE(AB$3,"Q","T"),Inputs!$B$2:$AZ$2,0)),Inputs!$B$2:$B$190,$B15)*Inputs!$D$1) -> 0 | AC15: =AB15 -> 0 | AD15: =IF(ISNA(SUMIFS(INDEX(Inputs!$B$2:$AZ$190,,MATCH(SUBSTITUTE(AD$3,"Q","T"),Inputs!$B$2:$AZ$2,0)),Inputs!$B$2:$B$190,$B15)*Inputs!$D$1),"",SUMIFS(INDEX(Inputs!$B$2:$AZ$190,,MATCH(SUBSTITUTE(AD$3,"Q","T"),Inputs!$B$2:$AZ$2,0)),Inputs!$B$2:$B$190,$B15)*Inputs!$D$1) -> 0 | AE15: =IF(ISNA(SUMIFS(INDEX(Inputs!$B$2:$AZ$190,,MATCH(SUBSTITUTE(AE$3,"Q","T"),Inputs!$B$2:$AZ$2,0)),Inputs!$B$2:$B$190,$B15)*Inputs!$D$1),"",SUMIFS(INDEX(Inputs!$B$2:$AZ$190,,MATCH(SUBSTITUTE(AE$3,"Q","T"),Inputs!$B$2:$AZ$2,0)),Inputs!$B$2:$B$190,$B15)*Inputs!$D$1) -> 0 | AF15: =IF(ISNA(SUMIFS(INDEX(Inputs!$B$2:$AZ$190,,MATCH(SUBSTITUTE(AF$3,"Q","T"),Inputs!$B$2:$AZ$2,0)),Inputs!$B$2:$B$190,$B15)*Inputs!$D$1),"",SUMIFS(INDEX(Inputs!$B$2:$AZ$190,,MATCH(SUBSTITUTE(AF$3,"Q","T"),Inputs!$B$2:$AZ$2,0)),Inputs!$B$2:$B$190,$B15)*Inputs!$D$1) -> 0 | AG15: =IF(ISNA(SUMIFS(INDEX(Inputs!$B$2:$AZ$190,,MATCH(SUBSTITUTE(AG$3,"Q","T"),Inputs!$B$2:$AZ$2,0)),Inputs!$B$2:$B$190,$B15)*Inputs!$D$1),"",SUMIFS(INDEX(Inputs!$B$2:$AZ$190,,MATCH(SUBSTITUTE(AG$3,"Q","T"),Inputs!$B$2:$AZ$2,0)),Inputs!$B$2:$B$190,$B15)*Inputs!$D$1) -> 0 | AH15: =AG15 -> 0 | AI15: =IF(ISNA(SUMIFS(INDEX(Inputs!$B$2:$AZ$190,,MATCH(SUBSTITUTE(AI$3,"Q","T"),Inputs!$B$2:$AZ$2,0)),Inputs!$B$2:$B$190,$B15)*Inputs!$D$1),"",SUMIFS(INDEX(Inputs!$B$2:$AZ$190,,MATCH(SUBSTITUTE(AI$3,"Q","T"),Inputs!$B$2:$AZ$2,0)),Inputs!$B$2:$B$190,$B15)*Inputs!$D$1) -> 0 | AJ15: =IF(ISNA(SUMIFS(INDEX(Inputs!$B$2:$AZ$190,,MATCH(SUBSTITUTE(AJ$3,"Q","T"),Inputs!$B$2:$AZ$2,0)),Inputs!$B$2:$B$190,$B15)*Inputs!$D$1),"",SUMIFS(INDEX(Inputs!$B$2:$AZ$190,,MATCH(SUBSTITUTE(AJ$3,"Q","T"),Inputs!$B$2:$AZ$2,0)),Inputs!$B$2:$B$190,$B15)*Inputs!$D$1) -> 0 | AK15: =IF(ISNA(SUMIFS(INDEX(Inputs!$B$2:$AZ$190,,MATCH(SUBSTITUTE(AK$3,"Q","T"),Inputs!$B$2:$AZ$2,0)),Inputs!$B$2:$B$190,$B15)*Inputs!$D$1),"",SUMIFS(INDEX(Inputs!$B$2:$AZ$190,,MATCH(SUBSTITUTE(AK$3,"Q","T"),Inputs!$B$2:$AZ$2,0)),Inputs!$B$2:$B$190,$B15)*Inputs!$D$1) -> 0 | AL15: =IF(ISNA(SUMIFS(INDEX(Inputs!$B$2:$AZ$190,,MATCH(SUBSTITUTE(AL$3,"Q","T"),Inputs!$B$2:$AZ$2,0)),Inputs!$B$2:$B$190,$B15)*Inputs!$D$1),"",SUMIFS(INDEX(Inputs!$B$2:$AZ$190,,MATCH(SUBSTITUTE(AL$3,"Q","T"),Inputs!$B$2:$AZ$2,0)),Inputs!$B$2:$B$190,$B15)*Inputs!$D$1) -> 0 | AM15: =AL15 -> 0 | AN15: =IF(ISNA(SUMIFS(INDEX(Inputs!$B$2:$AZ$190,,MATCH(SUBSTITUTE(AN$3,"Q","T"),Inputs!$B$2:$AZ$2,0)),Inputs!$B$2:$B$190,$B15)*Inputs!$D$1),"",SUMIFS(INDEX(Inputs!$B$2:$AZ$190,,MATCH(SUBSTITUTE(AN$3,"Q","T"),Inputs!$B$2:$AZ$2,0)),Inputs!$B$2:$B$190,$B15)*Inputs!$D$1) -> 0 | AO15: =IF(ISNA(SUMIFS(INDEX(Inputs!$B$2:$AZ$190,,MATCH(SUBSTITUTE(AO$3,"Q","T"),Inputs!$B$2:$AZ$2,0)),Inputs!$B$2:$B$190,$B15)*Inputs!$D$1),"",SUMIFS(INDEX(Inputs!$B$2:$AZ$190,,MATCH(SUBSTITUTE(AO$3,"Q","T"),Inputs!$B$2:$AZ$2,0)),Inputs!$B$2:$B$190,$B15)*Inputs!$D$1) -> 0 | AP15: =IF(ISNA(SUMIFS(INDEX(Inputs!$B$2:$AZ$190,,MATCH(SUBSTITUTE(AP$3,"Q","T"),Inputs!$B$2:$AZ$2,0)),Inputs!$B$2:$B$190,$B15)*Inputs!$D$1),"",SUMIFS(INDEX(Inputs!$B$2:$AZ$190,,MATCH(SUBSTITUTE(AP$3,"Q","T"),Inputs!$B$2:$AZ$2,0)),Inputs!$B$2:$B$190,$B15)*Inputs!$D$1) -> 0 | AQ15: =IF(ISNA(SUMIFS(INDEX(Inputs!$B$2:$AZ$190,,MATCH(SUBSTITUTE(AQ$3,"Q","T"),Inputs!$B$2:$AZ$2,0)),Inputs!$B$2:$B$190,$B15)*Inputs!$D$1),"",SUMIFS(INDEX(Inputs!$B$2:$AZ$190,,MATCH(SUBSTITUTE(AQ$3,"Q","T"),Inputs!$B$2:$AZ$2,0)),Inputs!$B$2:$B$190,$B15)*Inputs!$D$1) -> 0 | AR15: =AQ15 -> 0 | AS15: =IF(ISNA(SUMIFS(INDEX(Inputs!$B$2:$AZ$190,,MATCH(SUBSTITUTE(AS$3,"Q","T"),Inputs!$B$2:$AZ$2,0)),Inputs!$B$2:$B$190,$B15)*Inputs!$D$1),"",SUMIFS(INDEX(Inputs!$B$2:$AZ$190,,MATCH(SUBSTITUTE(AS$3,"Q","T"),Inputs!$B$2:$AZ$2,0)),Inputs!$B$2:$B$190,$B15)*Inputs!$D$1) -> 0 | AT15: =IF(ISNA(SUMIFS(INDEX(Inputs!$B$2:$AZ$190,,MATCH(SUBSTITUTE(AT$3,"Q","T"),Inputs!$B$2:$AZ$2,0)),Inputs!$B$2:$B$190,$B15)*Inputs!$D$1),"",SUMIFS(INDEX(Inputs!$B$2:$AZ$190,,MATCH(SUBSTITUTE(AT$3,"Q","T"),Inputs!$B$2:$AZ$2,0)),Inputs!$B$2:$B$190,$B15)*Inputs!$D$1) -> 0 | AU15: =IF(ISNA(SUMIFS(INDEX(Inputs!$B$2:$AZ$190,,MATCH(SUBSTITUTE(AU$3,"Q","T"),Inputs!$B$2:$AZ$2,0)),Inputs!$B$2:$B$190,$B15)*Inputs!$D$1),"",SUMIFS(INDEX(Inputs!$B$2:$AZ$190,,MATCH(SUBSTITUTE(AU$3,"Q","T"),Inputs!$B$2:$AZ$2,0)),Inputs!$B$2:$B$190,$B15)*Inputs!$D$1) -> 0 | AV15: =IF(ISNA(SUMIFS(INDEX(Inputs!$B$2:$AZ$190,,MATCH(SUBSTITUTE(AV$3,"Q","T"),Inputs!$B$2:$AZ$2,0)),Inputs!$B$2:$B$190,$B15)*Inputs!$D$1),"",SUMIFS(INDEX(Inputs!$B$2:$AZ$190,,MATCH(SUBSTITUTE(AV$3,"Q","T"),Inputs!$B$2:$AZ$2,0)),Inputs!$B$2:$B$190,$B15)*Inputs!$D$1) -> 0 | AW15: =AV15 -> 0 | AX15: =IF(ISNA(SUMIFS(INDEX(Inputs!$B$2:$AZ$190,,MATCH(SUBSTITUTE(AX$3,"Q","T"),Inputs!$B$2:$AZ$2,0)),Inputs!$B$2:$B$190,$B15)*Inputs!$D$1),"",SUMIFS(INDEX(Inputs!$B$2:$AZ$190,,MATCH(SUBSTITUTE(AX$3,"Q","T"),Inputs!$B$2:$AZ$2,0)),Inputs!$B$2:$B$190,$B15)*Inputs!$D$1) -> 0 | AY15: =IF(ISNA(SUMIFS(INDEX(Inputs!$B$2:$AZ$190,,MATCH(SUBSTITUTE(AY$3,"Q","T"),Inputs!$B$2:$AZ$2,0)),Inputs!$B$2:$B$190,$B15)*Inputs!$D$1),"",SUMIFS(INDEX(Inputs!$B$2:$AZ$190,,MATCH(SUBSTITUTE(AY$3,"Q","T"),Inputs!$B$2:$AZ$2,0)),Inputs!$B$2:$B$190,$B15)*Inputs!$D$1) -> 0 | AZ15: =IF(ISNA(SUMIFS(INDEX(Inputs!$B$2:$AZ$190,,MATCH(SUBSTITUTE(AZ$3,"Q","T"),Inputs!$B$2:$AZ$2,0)),Inputs!$B$2:$B$190,$B15)*Inputs!$D$1),"",SUMIFS(INDEX(Inputs!$B$2:$AZ$190,,MATCH(SUBSTITUTE(AZ$3,"Q","T"),Inputs!$B$2:$AZ$2,0)),Inputs!$B$2:$B$190,$B15)*Inputs!$D$1) -> 0 | BA15: =IF(ISNA(SUMIFS(INDEX(Inputs!$B$2:$AZ$190,,MATCH(SUBSTITUTE(BA$3,"Q","T"),Inputs!$B$2:$AZ$2,0)),Inputs!$B$2:$B$190,$B15)*Inputs!$D$1),"",SUMIFS(INDEX(Inputs!$B$2:$AZ$190,,MATCH(SUBSTITUTE(BA$3,"Q","T"),Inputs!$B$2:$AZ$2,0)),Inputs!$B$2:$B$190,$B15)*Inputs!$D$1) -> 0 | BB15: =BA15 -> 0 | BC15: =IF(ISNA(SUMIFS(INDEX(Inputs!$B$2:$AZ$190,,MATCH(SUBSTITUTE(BC$3,"Q","T"),Inputs!$B$2:$AZ$2,0)),Inputs!$B$2:$B$190,$B15)*Inputs!$D$1),"",SUMIFS(INDEX(Inputs!$B$2:$AZ$190,,MATCH(SUBSTITUTE(BC$3,"Q","T"),Inputs!$B$2:$AZ$2,0)),Inputs!$B$2:$B$190,$B15)*Inputs!$D$1) -> 0 | BD15: =IF(ISNA(SUMIFS(INDEX(Inputs!$B$2:$AZ$190,,MATCH(SUBSTITUTE(BD$3,"Q","T"),Inputs!$B$2:$AZ$2,0)),Inputs!$B$2:$B$190,$B15)*Inputs!$D$1),"",SUMIFS(INDEX(Inputs!$B$2:$AZ$190,,MATCH(SUBSTITUTE(BD$3,"Q","T"),Inputs!$B$2:$AZ$2,0)),Inputs!$B$2:$B$190,$B15)*Inputs!$D$1) -> 0 | BE15: =IF(ISNA(SUMIFS(INDEX(Inputs!$B$2:$AZ$190,,MATCH(SUBSTITUTE(BE$3,"Q","T"),Inputs!$B$2:$AZ$2,0)),Inputs!$B$2:$B$190,$B15)*Inputs!$D$1),"",SUMIFS(INDEX(Inputs!$B$2:$AZ$190,,MATCH(SUBSTITUTE(BE$3,"Q","T"),Inputs!$B$2:$AZ$2,0)),Inputs!$B$2:$B$190,$B15)*Inputs!$D$1) -> 0 | BF15: =IF(ISNA(SUMIFS(INDEX(Inputs!$B$2:$AZ$190,,MATCH(SUBSTITUTE(BF$3,"Q","T"),Inputs!$B$2:$AZ$2,0)),Inputs!$B$2:$B$190,$B15)*Inputs!$D$1),"",SUMIFS(INDEX(Inputs!$B$2:$AZ$190,,MATCH(SUBSTITUTE(BF$3,"Q","T"),Inputs!$B$2:$AZ$2,0)),Inputs!$B$2:$B$190,$B15)*Inputs!$D$1) -> 0 | BG15: =BF15 -> 0
B16: deriv_a | C16: Derivativos a receber (quando fora de trading) | D16: Derivative receivables, if separate | E16: =IF(ISNA(SUMIFS(INDEX(Inputs!$B$2:$AZ$190,,MATCH(SUBSTITUTE(E$3,"Q","T"),Inputs!$B$2:$AZ$2,0)),Inputs!$B$2:$B$190,$B16)*Inputs!$D$1),"",SUMIFS(INDEX(Inputs!$B$2:$AZ$190,,MATCH(SUBSTITUTE(E$3,"Q","T"),Inputs!$B$2:$AZ$2,0)),Inputs!$B$2:$B$190,$B16)*Inputs!$D$1) -> 0 | F16: =IF(ISNA(SUMIFS(INDEX(Inputs!$B$2:$AZ$190,,MATCH(SUBSTITUTE(F$3,"Q","T"),Inputs!$B$2:$AZ$2,0)),Inputs!$B$2:$B$190,$B16)*Inputs!$D$1),"",SUMIFS(INDEX(Inputs!$B$2:$AZ$190,,MATCH(SUBSTITUTE(F$3,"Q","T"),Inputs!$B$2:$AZ$2,0)),Inputs!$B$2:$B$190,$B16)*Inputs!$D$1) -> 0 | G16: =IF(ISNA(SUMIFS(INDEX(Inputs!$B$2:$AZ$190,,MATCH(SUBSTITUTE(G$3,"Q","T"),Inputs!$B$2:$AZ$2,0)),Inputs!$B$2:$B$190,$B16)*Inputs!$D$1),"",SUMIFS(INDEX(Inputs!$B$2:$AZ$190,,MATCH(SUBSTITUTE(G$3,"Q","T"),Inputs!$B$2:$AZ$2,0)),Inputs!$B$2:$B$190,$B16)*Inputs!$D$1) -> 0 | H16: =IF(ISNA(SUMIFS(INDEX(Inputs!$B$2:$AZ$190,,MATCH(SUBSTITUTE(H$3,"Q","T"),Inputs!$B$2:$AZ$2,0)),Inputs!$B$2:$B$190,$B16)*Inputs!$D$1),"",SUMIFS(INDEX(Inputs!$B$2:$AZ$190,,MATCH(SUBSTITUTE(H$3,"Q","T"),Inputs!$B$2:$AZ$2,0)),Inputs!$B$2:$B$190,$B16)*Inputs!$D$1) -> 0 | I16: =H16 -> 0 | J16: =IF(ISNA(SUMIFS(INDEX(Inputs!$B$2:$AZ$190,,MATCH(SUBSTITUTE(J$3,"Q","T"),Inputs!$B$2:$AZ$2,0)),Inputs!$B$2:$B$190,$B16)*Inputs!$D$1),"",SUMIFS(INDEX(Inputs!$B$2:$AZ$190,,MATCH(SUBSTITUTE(J$3,"Q","T"),Inputs!$B$2:$AZ$2,0)),Inputs!$B$2:$B$190,$B16)*Inputs!$D$1) -> 0 | K16: =IF(ISNA(SUMIFS(INDEX(Inputs!$B$2:$AZ$190,,MATCH(SUBSTITUTE(K$3,"Q","T"),Inputs!$B$2:$AZ$2,0)),Inputs!$B$2:$B$190,$B16)*Inputs!$D$1),"",SUMIFS(INDEX(Inputs!$B$2:$AZ$190,,MATCH(SUBSTITUTE(K$3,"Q","T"),Inputs!$B$2:$AZ$2,0)),Inputs!$B$2:$B$190,$B16)*Inputs!$D$1) -> 0 | L16: =IF(ISNA(SUMIFS(INDEX(Inputs!$B$2:$AZ$190,,MATCH(SUBSTITUTE(L$3,"Q","T"),Inputs!$B$2:$AZ$2,0)),Inputs!$B$2:$B$190,$B16)*Inputs!$D$1),"",SUMIFS(INDEX(Inputs!$B$2:$AZ$190,,MATCH(SUBSTITUTE(L$3,"Q","T"),Inputs!$B$2:$AZ$2,0)),Inputs!$B$2:$B$190,$B16)*Inputs!$D$1) -> 0 | M16: =IF(ISNA(SUMIFS(INDEX(Inputs!$B$2:$AZ$190,,MATCH(SUBSTITUTE(M$3,"Q","T"),Inputs!$B$2:$AZ$2,0)),Inputs!$B$2:$B$190,$B16)*Inputs!$D$1),"",SUMIFS(INDEX(Inputs!$B$2:$AZ$190,,MATCH(SUBSTITUTE(M$3,"Q","T"),Inputs!$B$2:$AZ$2,0)),Inputs!$B$2:$B$190,$B16)*Inputs!$D$1) -> 0 | N16: =M16 -> 0 | O16: =IF(ISNA(SUMIFS(INDEX(Inputs!$B$2:$AZ$190,,MATCH(SUBSTITUTE(O$3,"Q","T"),Inputs!$B$2:$AZ$2,0)),Inputs!$B$2:$B$190,$B16)*Inputs!$D$1),"",SUMIFS(INDEX(Inputs!$B$2:$AZ$190,,MATCH(SUBSTITUTE(O$3,"Q","T"),Inputs!$B$2:$AZ$2,0)),Inputs!$B$2:$B$190,$B16)*Inputs!$D$1) -> 0 | P16: =IF(ISNA(SUMIFS(INDEX(Inputs!$B$2:$AZ$190,,MATCH(SUBSTITUTE(P$3,"Q","T"),Inputs!$B$2:$AZ$2,0)),Inputs!$B$2:$B$190,$B16)*Inputs!$D$1),"",SUMIFS(INDEX(Inputs!$B$2:$AZ$190,,MATCH(SUBSTITUTE(P$3,"Q","T"),Inputs!$B$2:$AZ$2,0)),Inputs!$B$2:$B$190,$B16)*Inputs!$D$1) -> 0 | Q16: =IF(ISNA(SUMIFS(INDEX(Inputs!$B$2:$AZ$190,,MATCH(SUBSTITUTE(Q$3,"Q","T"),Inputs!$B$2:$AZ$2,0)),Inputs!$B$2:$B$190,$B16)*Inputs!$D$1),"",SUMIFS(INDEX(Inputs!$B$2:$AZ$190,,MATCH(SUBSTITUTE(Q$3,"Q","T"),Inputs!$B$2:$AZ$2,0)),Inputs!$B$2:$B$190,$B16)*Inputs!$D$1) -> 0 | R16: =IF(ISNA(SUMIFS(INDEX(Inputs!$B$2:$AZ$190,,MATCH(SUBSTITUTE(R$3,"Q","T"),Inputs!$B$2:$AZ$2,0)),Inputs!$B$2:$B$190,$B16)*Inputs!$D$1),"",SUMIFS(INDEX(Inputs!$B$2:$AZ$190,,MATCH(SUBSTITUTE(R$3,"Q","T"),Inputs!$B$2:$AZ$2,0)),Inputs!$B$2:$B$190,$B16)*Inputs!$D$1) -> 0 | S16: =R16 -> 0 | T16: =IF(ISNA(SUMIFS(INDEX(Inputs!$B$2:$AZ$190,,MATCH(SUBSTITUTE(T$3,"Q","T"),Inputs!$B$2:$AZ$2,0)),Inputs!$B$2:$B$190,$B16)*Inputs!$D$1),"",SUMIFS(INDEX(Inputs!$B$2:$AZ$190,,MATCH(SUBSTITUTE(T$3,"Q","T"),Inputs!$B$2:$AZ$2,0)),Inputs!$B$2:$B$190,$B16)*Inputs!$D$1) -> 0 | U16: =IF(ISNA(SUMIFS(INDEX(Inputs!$B$2:$AZ$190,,MATCH(SUBSTITUTE(U$3,"Q","T"),Inputs!$B$2:$AZ$2,0)),Inputs!$B$2:$B$190,$B16)*Inputs!$D$1),"",SUMIFS(INDEX(Inputs!$B$2:$AZ$190,,MATCH(SUBSTITUTE(U$3,"Q","T"),Inputs!$B$2:$AZ$2,0)),Inputs!$B$2:$B$190,$B16)*Inputs!$D$1) -> 0 | V16: =IF(ISNA(SUMIFS(INDEX(Inputs!$B$2:$AZ$190,,MATCH(SUBSTITUTE(V$3,"Q","T"),Inputs!$B$2:$AZ$2,0)),Inputs!$B$2:$B$190,$B16)*Inputs!$D$1),"",SUMIFS(INDEX(Inputs!$B$2:$AZ$190,,MATCH(SUBSTITUTE(V$3,"Q","T"),Inputs!$B$2:$AZ$2,0)),Inputs!$B$2:$B$190,$B16)*Inputs!$D$1) -> 0 | W16: =IF(ISNA(SUMIFS(INDEX(Inputs!$B$2:$AZ$190,,MATCH(SUBSTITUTE(W$3,"Q","T"),Inputs!$B$2:$AZ$2,0)),Inputs!$B$2:$B$190,$B16)*Inputs!$D$1),"",SUMIFS(INDEX(Inputs!$B$2:$AZ$190,,MATCH(SUBSTITUTE(W$3,"Q","T"),Inputs!$B$2:$AZ$2,0)),Inputs!$B$2:$B$190,$B16)*Inputs!$D$1) -> 0 | X16: =W16 -> 0 | Y16: =IF(ISNA(SUMIFS(INDEX(Inputs!$B$2:$AZ$190,,MATCH(SUBSTITUTE(Y$3,"Q","T"),Inputs!$B$2:$AZ$2,0)),Inputs!$B$2:$B$190,$B16)*Inputs!$D$1),"",SUMIFS(INDEX(Inputs!$B$2:$AZ$190,,MATCH(SUBSTITUTE(Y$3,"Q","T"),Inputs!$B$2:$AZ$2,0)),Inputs!$B$2:$B$190,$B16)*Inputs!$D$1) -> 0 | Z16: =IF(ISNA(SUMIFS(INDEX(Inputs!$B$2:$AZ$190,,MATCH(SUBSTITUTE(Z$3,"Q","T"),Inputs!$B$2:$AZ$2,0)),Inputs!$B$2:$B$190,$B16)*Inputs!$D$1),"",SUMIFS(INDEX(Inputs!$B$2:$AZ$190,,MATCH(SUBSTITUTE(Z$3,"Q","T"),Inputs!$B$2:$AZ$2,0)),Inputs!$B$2:$B$190,$B16)*Inputs!$D$1) -> 0 | AA16: =IF(ISNA(SUMIFS(INDEX(Inputs!$B$2:$AZ$190,,MATCH(SUBSTITUTE(AA$3,"Q","T"),Inputs!$B$2:$AZ$2,0)),Inputs!$B$2:$B$190,$B16)*Inputs!$D$1),"",SUMIFS(INDEX(Inputs!$B$2:$AZ$190,,MATCH(SUBSTITUTE(AA$3,"Q","T"),Inputs!$B$2:$AZ$2,0)),Inputs!$B$2:$B$190,$B16)*Inputs!$D$1) -> 0 | AB16: =IF(ISNA(SUMIFS(INDEX(Inputs!$B$2:$AZ$190,,MATCH(SUBSTITUTE(AB$3,"Q","T"),Inputs!$B$2:$AZ$2,0)),Inputs!$B$2:$B$190,$B16)*Inputs!$D$1),"",SUMIFS(INDEX(Inputs!$B$2:$AZ$190,,MATCH(SUBSTITUTE(AB$3,"Q","T"),Inputs!$B$2:$AZ$2,0)),Inputs!$B$2:$B$190,$B16)*Inputs!$D$1) -> 0 | AC16: =AB16 -> 0 | AD16: =IF(ISNA(SUMIFS(INDEX(Inputs!$B$2:$AZ$190,,MATCH(SUBSTITUTE(AD$3,"Q","T"),Inputs!$B$2:$AZ$2,0)),Inputs!$B$2:$B$190,$B16)*Inputs!$D$1),"",SUMIFS(INDEX(Inputs!$B$2:$AZ$190,,MATCH(SUBSTITUTE(AD$3,"Q","T"),Inputs!$B$2:$AZ$2,0)),Inputs!$B$2:$B$190,$B16)*Inputs!$D$1) -> 0 | AE16: =IF(ISNA(SUMIFS(INDEX(Inputs!$B$2:$AZ$190,,MATCH(SUBSTITUTE(AE$3,"Q","T"),Inputs!$B$2:$AZ$2,0)),Inputs!$B$2:$B$190,$B16)*Inputs!$D$1),"",SUMIFS(INDEX(Inputs!$B$2:$AZ$190,,MATCH(SUBSTITUTE(AE$3,"Q","T"),Inputs!$B$2:$AZ$2,0)),Inputs!$B$2:$B$190,$B16)*Inputs!$D$1) -> 0 | AF16: =IF(ISNA(SUMIFS(INDEX(Inputs!$B$2:$AZ$190,,MATCH(SUBSTITUTE(AF$3,"Q","T"),Inputs!$B$2:$AZ$2,0)),Inputs!$B$2:$B$190,$B16)*Inputs!$D$1),"",SUMIFS(INDEX(Inputs!$B$2:$AZ$190,,MATCH(SUBSTITUTE(AF$3,"Q","T"),Inputs!$B$2:$AZ$2,0)),Inputs!$B$2:$B$190,$B16)*Inputs!$D$1) -> 0 | AG16: =IF(ISNA(SUMIFS(INDEX(Inputs!$B$2:$AZ$190,,MATCH(SUBSTITUTE(AG$3,"Q","T"),Inputs!$B$2:$AZ$2,0)),Inputs!$B$2:$B$190,$B16)*Inputs!$D$1),"",SUMIFS(INDEX(Inputs!$B$2:$AZ$190,,MATCH(SUBSTITUTE(AG$3,"Q","T"),Inputs!$B$2:$AZ$2,0)),Inputs!$B$2:$B$190,$B16)*Inputs!$D$1) -> 0 | AH16: =AG16 -> 0 | AI16: =IF(ISNA(SUMIFS(INDEX(Inputs!$B$2:$AZ$190,,MATCH(SUBSTITUTE(AI$3,"Q","T"),Inputs!$B$2:$AZ$2,0)),Inputs!$B$2:$B$190,$B16)*Inputs!$D$1),"",SUMIFS(INDEX(Inputs!$B$2:$AZ$190,,MATCH(SUBSTITUTE(AI$3,"Q","T"),Inputs!$B$2:$AZ$2,0)),Inputs!$B$2:$B$190,$B16)*Inputs!$D$1) -> 0 | AJ16: =IF(ISNA(SUMIFS(INDEX(Inputs!$B$2:$AZ$190,,MATCH(SUBSTITUTE(AJ$3,"Q","T"),Inputs!$B$2:$AZ$2,0)),Inputs!$B$2:$B$190,$B16)*Inputs!$D$1),"",SUMIFS(INDEX(Inputs!$B$2:$AZ$190,,MATCH(SUBSTITUTE(AJ$3,"Q","T"),Inputs!$B$2:$AZ$2,0)),Inputs!$B$2:$B$190,$B16)*Inputs!$D$1) -> 0 | AK16: =IF(ISNA(SUMIFS(INDEX(Inputs!$B$2:$AZ$190,,MATCH(SUBSTITUTE(AK$3,"Q","T"),Inputs!$B$2:$AZ$2,0)),Inputs!$B$2:$B$190,$B16)*Inputs!$D$1),"",SUMIFS(INDEX(Inputs!$B$2:$AZ$190,,MATCH(SUBSTITUTE(AK$3,"Q","T"),Inputs!$B$2:$AZ$2,0)),Inputs!$B$2:$B$190,$B16)*Inputs!$D$1) -> 0 | AL16: =IF(ISNA(SUMIFS(INDEX(Inputs!$B$2:$AZ$190,,MATCH(SUBSTITUTE(AL$3,"Q","T"),Inputs!$B$2:$AZ$2,0)),Inputs!$B$2:$B$190,$B16)*Inputs!$D$1),"",SUMIFS(INDEX(Inputs!$B$2:$AZ$190,,MATCH(SUBSTITUTE(AL$3,"Q","T"),Inputs!$B$2:$AZ$2,0)),Inputs!$B$2:$B$190,$B16)*Inputs!$D$1) -> 0 | AM16: =AL16 -> 0 | AN16: =IF(ISNA(SUMIFS(INDEX(Inputs!$B$2:$AZ$190,,MATCH(SUBSTITUTE(AN$3,"Q","T"),Inputs!$B$2:$AZ$2,0)),Inputs!$B$2:$B$190,$B16)*Inputs!$D$1),"",SUMIFS(INDEX(Inputs!$B$2:$AZ$190,,MATCH(SUBSTITUTE(AN$3,"Q","T"),Inputs!$B$2:$AZ$2,0)),Inputs!$B$2:$B$190,$B16)*Inputs!$D$1) -> 0 | AO16: =IF(ISNA(SUMIFS(INDEX(Inputs!$B$2:$AZ$190,,MATCH(SUBSTITUTE(AO$3,"Q","T"),Inputs!$B$2:$AZ$2,0)),Inputs!$B$2:$B$190,$B16)*Inputs!$D$1),"",SUMIFS(INDEX(Inputs!$B$2:$AZ$190,,MATCH(SUBSTITUTE(AO$3,"Q","T"),Inputs!$B$2:$AZ$2,0)),Inputs!$B$2:$B$190,$B16)*Inputs!$D$1) -> 0 | AP16: =IF(ISNA(SUMIFS(INDEX(Inputs!$B$2:$AZ$190,,MATCH(SUBSTITUTE(AP$3,"Q","T"),Inputs!$B$2:$AZ$2,0)),Inputs!$B$2:$B$190,$B16)*Inputs!$D$1),"",SUMIFS(INDEX(Inputs!$B$2:$AZ$190,,MATCH(SUBSTITUTE(AP$3,"Q","T"),Inputs!$B$2:$AZ$2,0)),Inputs!$B$2:$B$190,$B16)*Inputs!$D$1) -> 0 | AQ16: =IF(ISNA(SUMIFS(INDEX(Inputs!$B$2:$AZ$190,,MATCH(SUBSTITUTE(AQ$3,"Q","T"),Inputs!$B$2:$AZ$2,0)),Inputs!$B$2:$B$190,$B16)*Inputs!$D$1),"",SUMIFS(INDEX(Inputs!$B$2:$AZ$190,,MATCH(SUBSTITUTE(AQ$3,"Q","T"),Inputs!$B$2:$AZ$2,0)),Inputs!$B$2:$B$190,$B16)*Inputs!$D$1) -> 0 | AR16: =AQ16 -> 0 | AS16: =IF(ISNA(SUMIFS(INDEX(Inputs!$B$2:$AZ$190,,MATCH(SUBSTITUTE(AS$3,"Q","T"),Inputs!$B$2:$AZ$2,0)),Inputs!$B$2:$B$190,$B16)*Inputs!$D$1),"",SUMIFS(INDEX(Inputs!$B$2:$AZ$190,,MATCH(SUBSTITUTE(AS$3,"Q","T"),Inputs!$B$2:$AZ$2,0)),Inputs!$B$2:$B$190,$B16)*Inputs!$D$1) -> 0 | AT16: =IF(ISNA(SUMIFS(INDEX(Inputs!$B$2:$AZ$190,,MATCH(SUBSTITUTE(AT$3,"Q","T"),Inputs!$B$2:$AZ$2,0)),Inputs!$B$2:$B$190,$B16)*Inputs!$D$1),"",SUMIFS(INDEX(Inputs!$B$2:$AZ$190,,MATCH(SUBSTITUTE(AT$3,"Q","T"),Inputs!$B$2:$AZ$2,0)),Inputs!$B$2:$B$190,$B16)*Inputs!$D$1) -> 0 | AU16: =IF(ISNA(SUMIFS(INDEX(Inputs!$B$2:$AZ$190,,MATCH(SUBSTITUTE(AU$3,"Q","T"),Inputs!$B$2:$AZ$2,0)),Inputs!$B$2:$B$190,$B16)*Inputs!$D$1),"",SUMIFS(INDEX(Inputs!$B$2:$AZ$190,,MATCH(SUBSTITUTE(AU$3,"Q","T"),Inputs!$B$2:$AZ$2,0)),Inputs!$B$2:$B$190,$B16)*Inputs!$D$1) -> 0 | AV16: =IF(ISNA(SUMIFS(INDEX(Inputs!$B$2:$AZ$190,,MATCH(SUBSTITUTE(AV$3,"Q","T"),Inputs!$B$2:$AZ$2,0)),Inputs!$B$2:$B$190,$B16)*Inputs!$D$1),"",SUMIFS(INDEX(Inputs!$B$2:$AZ$190,,MATCH(SUBSTITUTE(AV$3,"Q","T"),Inputs!$B$2:$AZ$2,0)),Inputs!$B$2:$B$190,$B16)*Inputs!$D$1) -> 0 | AW16: =AV16 -> 0 | AX16: =IF(ISNA(SUMIFS(INDEX(Inputs!$B$2:$AZ$190,,MATCH(SUBSTITUTE(AX$3,"Q","T"),Inputs!$B$2:$AZ$2,0)),Inputs!$B$2:$B$190,$B16)*Inputs!$D$1),"",SUMIFS(INDEX(Inputs!$B$2:$AZ$190,,MATCH(SUBSTITUTE(AX$3,"Q","T"),Inputs!$B$2:$AZ$2,0)),Inputs!$B$2:$B$190,$B16)*Inputs!$D$1) -> 0 | AY16: =IF(ISNA(SUMIFS(INDEX(Inputs!$B$2:$AZ$190,,MATCH(SUBSTITUTE(AY$3,"Q","T"),Inputs!$B$2:$AZ$2,0)),Inputs!$B$2:$B$190,$B16)*Inputs!$D$1),"",SUMIFS(INDEX(Inputs!$B$2:$AZ$190,,MATCH(SUBSTITUTE(AY$3,"Q","T"),Inputs!$B$2:$AZ$2,0)),Inputs!$B$2:$B$190,$B16)*Inputs!$D$1) -> 0 | AZ16: =IF(ISNA(SUMIFS(INDEX(Inputs!$B$2:$AZ$190,,MATCH(SUBSTITUTE(AZ$3,"Q","T"),Inputs!$B$2:$AZ$2,0)),Inputs!$B$2:$B$190,$B16)*Inputs!$D$1),"",SUMIFS(INDEX(Inputs!$B$2:$AZ$190,,MATCH(SUBSTITUTE(AZ$3,"Q","T"),Inputs!$B$2:$AZ$2,0)),Inputs!$B$2:$B$190,$B16)*Inputs!$D$1) -> 0 | BA16: =IF(ISNA(SUMIFS(INDEX(Inputs!$B$2:$AZ$190,,MATCH(SUBSTITUTE(BA$3,"Q","T"),Inputs!$B$2:$AZ$2,0)),Inputs!$B$2:$B$190,$B16)*Inputs!$D$1),"",SUMIFS(INDEX(Inputs!$B$2:$AZ$190,,MATCH(SUBSTITUTE(BA$3,"Q","T"),Inputs!$B$2:$AZ$2,0)),Inputs!$B$2:$B$190,$B16)*Inputs!$D$1) -> 0 | BB16: =BA16 -> 0 | BC16: =IF(ISNA(SUMIFS(INDEX(Inputs!$B$2:$AZ$190,,MATCH(SUBSTITUTE(BC$3,"Q","T"),Inputs!$B$2:$AZ$2,0)),Inputs!$B$2:$B$190,$B16)*Inputs!$D$1),"",SUMIFS(INDEX(Inputs!$B$2:$AZ$190,,MATCH(SUBSTITUTE(BC$3,"Q","T"),Inputs!$B$2:$AZ$2,0)),Inputs!$B$2:$B$190,$B16)*Inputs!$D$1) -> 0 | BD16: =IF(ISNA(SUMIFS(INDEX(Inputs!$B$2:$AZ$190,,MATCH(SUBSTITUTE(BD$3,"Q","T"),Inputs!$B$2:$AZ$2,0)),Inputs!$B$2:$B$190,$B16)*Inputs!$D$1),"",SUMIFS(INDEX(Inputs!$B$2:$AZ$190,,MATCH(SUBSTITUTE(BD$3,"Q","T"),Inputs!$B$2:$AZ$2,0)),Inputs!$B$2:$B$190,$B16)*Inputs!$D$1) -> 0 | BE16: =IF(ISNA(SUMIFS(INDEX(Inputs!$B$2:$AZ$190,,MATCH(SUBSTITUTE(BE$3,"Q","T"),Inputs!$B$2:$AZ$2,0)),Inputs!$B$2:$B$190,$B16)*Inputs!$D$1),"",SUMIFS(INDEX(Inputs!$B$2:$AZ$190,,MATCH(SUBSTITUTE(BE$3,"Q","T"),Inputs!$B$2:$AZ$2,0)),Inputs!$B$2:$B$190,$B16)*Inputs!$D$1) -> 0 | BF16: =IF(ISNA(SUMIFS(INDEX(Inputs!$B$2:$AZ$190,,MATCH(SUBSTITUTE(BF$3,"Q","T"),Inputs!$B$2:$AZ$2,0)),Inputs!$B$2:$B$190,$B16)*Inputs!$D$1),"",SUMIFS(INDEX(Inputs!$B$2:$AZ$190,,MATCH(SUBSTITUTE(BF$3,"Q","T"),Inputs!$B$2:$AZ$2,0)),Inputs!$B$2:$B$190,$B16)*Inputs!$D$1) -> 0 | BG16: =BF16 -> 0
C17: Empréstimos | D17: Loans | E17: =IFERROR(E18+E19+E20,"") -> 0 | F17: =IFERROR(F18+F19+F20,"") -> 0 | G17: =IFERROR(G18+G19+G20,"") -> 0 | H17: =IFERROR(H18+H19+H20,"") -> 0 | I17: =H17 -> 0 | J17: =IFERROR(J18+J19+J20,"") -> 0 | K17: =IFERROR(K18+K19+K20,"") -> 0 | L17: =IFERROR(L18+L19+L20,"") -> 0 | M17: =IFERROR(M18+M19+M20,"") -> 0 | N17: =M17 -> 0 | O17: =IFERROR(O18+O19+O20,"") -> 0 | P17: =IFERROR(P18+P19+P20,"") -> 0 | Q17: =IFERROR(Q18+Q19+Q20,"") -> 0 | R17: =IFERROR(R18+R19+R20,"") -> 0 | S17: =R17 -> 0 | T17: =IFERROR(T18+T19+T20,"") -> 0 | U17: =IFERROR(U18+U19+U20,"") -> 0 | V17: =IFERROR(V18+V19+V20,"") -> 0 | W17: =IFERROR(W18+W19+W20,"") -> 0 | X17: =W17 -> 0 | Y17: =IFERROR(Y18+Y19+Y20,"") -> 0 | Z17: =IFERROR(Z18+Z19+Z20,"") -> 0 | AA17: =IFERROR(AA18+AA19+AA20,"") -> 0 | AB17: =IFERROR(AB18+AB19+AB20,"") -> 0 | AC17: =AB17 -> 0 | AD17: =IFERROR(AD18+AD19+AD20,"") -> 0 | AE17: =IFERROR(AE18+AE19+AE20,"") -> 0 | AF17: =IFERROR(AF18+AF19+AF20,"") -> 0 | AG17: =IFERROR(AG18+AG19+AG20,"") -> 0 | AH17: =AG17 -> 0 | AI17: =IFERROR(AI18+AI19+AI20,"") -> 0 | AJ17: =IFERROR(AJ18+AJ19+AJ20,"") -> 0 | AK17: =IFERROR(AK18+AK19+AK20,"") -> 0 | AL17: =IFERROR(AL18+AL19+AL20,"") -> 0 | AM17: =AL17 -> 0 | AN17: =IFERROR(AN18+AN19+AN20,"") -> 0 | AO17: =IFERROR(AO18+AO19+AO20,"") -> 0 | AP17: =IFERROR(AP18+AP19+AP20,"") -> 0 | AQ17: =IFERROR(AQ18+AQ19+AQ20,"") -> 0 | AR17: =AQ17 -> 0 | AS17: =IFERROR(AS18+AS19+AS20,"") -> 0 | AT17: =IFERROR(AT18+AT19+AT20,"") -> 0 | AU17: =IFERROR(AU18+AU19+AU20,"") -> 0 | AV17: =IFERROR(AV18+AV19+AV20,"") -> 0 | AW17: =AV17 -> 0 | AX17: =IFERROR(AX18+AX19+AX20,"") -> 0 | AY17: =IFERROR(AY18+AY19+AY20,"") -> 0 | AZ17: =IFERROR(AZ18+AZ19+AZ20,"") -> 0 | BA17: =IFERROR(BA18+BA19+BA20,"") -> 0 | BB17: =BA17 -> 0 | BC17: =IFERROR(BC18+BC19+BC20,"") -> 0 | BD17: =IFERROR(BD18+BD19+BD20,"") -> 0 | BE17: =IFERROR(BE18+BE19+BE20,"") -> 0 | BF17: =IFERROR(BF18+BF19+BF20,"") -> 0 | BG17: =BF17 -> 0
B18: loans | C18: Empréstimos, líquidos de receitas diferidas | D18: Loans, net of unearned income | E18: =IF(ISNA(SUMIFS(INDEX(Inputs!$B$2:$AZ$190,,MATCH(SUBSTITUTE(E$3,"Q","T"),Inputs!$B$2:$AZ$2,0)),Inputs!$B$2:$B$190,$B18)*Inputs!$D$1),"",SUMIFS(INDEX(Inputs!$B$2:$AZ$190,,MATCH(SUBSTITUTE(E$3,"Q","T"),Inputs!$B$2:$AZ$2,0)),Inputs!$B$2:$B$190,$B18)*Inputs!$D$1) -> 0 | F18: =IF(ISNA(SUMIFS(INDEX(Inputs!$B$2:$AZ$190,,MATCH(SUBSTITUTE(F$3,"Q","T"),Inputs!$B$2:$AZ$2,0)),Inputs!$B$2:$B$190,$B18)*Inputs!$D$1),"",SUMIFS(INDEX(Inputs!$B$2:$AZ$190,,MATCH(SUBSTITUTE(F$3,"Q","T"),Inputs!$B$2:$AZ$2,0)),Inputs!$B$2:$B$190,$B18)*Inputs!$D$1) -> 0 | G18: =IF(ISNA(SUMIFS(INDEX(Inputs!$B$2:$AZ$190,,MATCH(SUBSTITUTE(G$3,"Q","T"),Inputs!$B$2:$AZ$2,0)),Inputs!$B$2:$B$190,$B18)*Inputs!$D$1),"",SUMIFS(INDEX(Inputs!$B$2:$AZ$190,,MATCH(SUBSTITUTE(G$3,"Q","T"),Inputs!$B$2:$AZ$2,0)),Inputs!$B$2:$B$190,$B18)*Inputs!$D$1) -> 0 | H18: =IF(ISNA(SUMIFS(INDEX(Inputs!$B$2:$AZ$190,,MATCH(SUBSTITUTE(H$3,"Q","T"),Inputs!$B$2:$AZ$2,0)),Inputs!$B$2:$B$190,$B18)*Inputs!$D$1),"",SUMIFS(INDEX(Inputs!$B$2:$AZ$190,,MATCH(SUBSTITUTE(H$3,"Q","T"),Inputs!$B$2:$AZ$2,0)),Inputs!$B$2:$B$190,$B18)*Inputs!$D$1) -> 0 | I18: =H18 -> 0 | J18: =IF(ISNA(SUMIFS(INDEX(Inputs!$B$2:$AZ$190,,MATCH(SUBSTITUTE(J$3,"Q","T"),Inputs!$B$2:$AZ$2,0)),Inputs!$B$2:$B$190,$B18)*Inputs!$D$1),"",SUMIFS(INDEX(Inputs!$B$2:$AZ$190,,MATCH(SUBSTITUTE(J$3,"Q","T"),Inputs!$B$2:$AZ$2,0)),Inputs!$B$2:$B$190,$B18)*Inputs!$D$1) -> 0 | K18: =IF(ISNA(SUMIFS(INDEX(Inputs!$B$2:$AZ$190,,MATCH(SUBSTITUTE(K$3,"Q","T"),Inputs!$B$2:$AZ$2,0)),Inputs!$B$2:$B$190,$B18)*Inputs!$D$1),"",SUMIFS(INDEX(Inputs!$B$2:$AZ$190,,MATCH(SUBSTITUTE(K$3,"Q","T"),Inputs!$B$2:$AZ$2,0)),Inputs!$B$2:$B$190,$B18)*Inputs!$D$1) -> 0 | L18: =IF(ISNA(SUMIFS(INDEX(Inputs!$B$2:$AZ$190,,MATCH(SUBSTITUTE(L$3,"Q","T"),Inputs!$B$2:$AZ$2,0)),Inputs!$B$2:$B$190,$B18)*Inputs!$D$1),"",SUMIFS(INDEX(Inputs!$B$2:$AZ$190,,MATCH(SUBSTITUTE(L$3,"Q","T"),Inputs!$B$2:$AZ$2,0)),Inputs!$B$2:$B$190,$B18)*Inputs!$D$1) -> 0 | M18: =IF(ISNA(SUMIFS(INDEX(Inputs!$B$2:$AZ$190,,MATCH(SUBSTITUTE(M$3,"Q","T"),Inputs!$B$2:$AZ$2,0)),Inputs!$B$2:$B$190,$B18)*Inputs!$D$1),"",SUMIFS(INDEX(Inputs!$B$2:$AZ$190,,MATCH(SUBSTITUTE(M$3,"Q","T"),Inputs!$B$2:$AZ$2,0)),Inputs!$B$2:$B$190,$B18)*Inputs!$D$1) -> 0 | N18: =M18 -> 0 | O18: =IF(ISNA(SUMIFS(INDEX(Inputs!$B$2:$AZ$190,,MATCH(SUBSTITUTE(O$3,"Q","T"),Inputs!$B$2:$AZ$2,0)),Inputs!$B$2:$B$190,$B18)*Inputs!$D$1),"",SUMIFS(INDEX(Inputs!$B$2:$AZ$190,,MATCH(SUBSTITUTE(O$3,"Q","T"),Inputs!$B$2:$AZ$2,0)),Inputs!$B$2:$B$190,$B18)*Inputs!$D$1) -> 0 | P18: =IF(ISNA(SUMIFS(INDEX(Inputs!$B$2:$AZ$190,,MATCH(SUBSTITUTE(P$3,"Q","T"),Inputs!$B$2:$AZ$2,0)),Inputs!$B$2:$B$190,$B18)*Inputs!$D$1),"",SUMIFS(INDEX(Inputs!$B$2:$AZ$190,,MATCH(SUBSTITUTE(P$3,"Q","T"),Inputs!$B$2:$AZ$2,0)),Inputs!$B$2:$B$190,$B18)*Inputs!$D$1) -> 0 | Q18: =IF(ISNA(SUMIFS(INDEX(Inputs!$B$2:$AZ$190,,MATCH(SUBSTITUTE(Q$3,"Q","T"),Inputs!$B$2:$AZ$2,0)),Inputs!$B$2:$B$190,$B18)*Inputs!$D$1),"",SUMIFS(INDEX(Inputs!$B$2:$AZ$190,,MATCH(SUBSTITUTE(Q$3,"Q","T"),Inputs!$B$2:$AZ$2,0)),Inputs!$B$2:$B$190,$B18)*Inputs!$D$1) -> 0 | R18: =IF(ISNA(SUMIFS(INDEX(Inputs!$B$2:$AZ$190,,MATCH(SUBSTITUTE(R$3,"Q","T"),Inputs!$B$2:$AZ$2,0)),Inputs!$B$2:$B$190,$B18)*Inputs!$D$1),"",SUMIFS(INDEX(Inputs!$B$2:$AZ$190,,MATCH(SUBSTITUTE(R$3,"Q","T"),Inputs!$B$2:$AZ$2,0)),Inputs!$B$2:$B$190,$B18)*Inputs!$D$1) -> 0 | S18: =R18 -> 0 | T18: =IF(ISNA(SUMIFS(INDEX(Inputs!$B$2:$AZ$190,,MATCH(SUBSTITUTE(T$3,"Q","T"),Inputs!$B$2:$AZ$2,0)),Inputs!$B$2:$B$190,$B18)*Inputs!$D$1),"",SUMIFS(INDEX(Inputs!$B$2:$AZ$190,,MATCH(SUBSTITUTE(T$3,"Q","T"),Inputs!$B$2:$AZ$2,0)),Inputs!$B$2:$B$190,$B18)*Inputs!$D$1) -> 0 | U18: =IF(ISNA(SUMIFS(INDEX(Inputs!$B$2:$AZ$190,,MATCH(SUBSTITUTE(U$3,"Q","T"),Inputs!$B$2:$AZ$2,0)),Inputs!$B$2:$B$190,$B18)*Inputs!$D$1),"",SUMIFS(INDEX(Inputs!$B$2:$AZ$190,,MATCH(SUBSTITUTE(U$3,"Q","T"),Inputs!$B$2:$AZ$2,0)),Inputs!$B$2:$B$190,$B18)*Inputs!$D$1) -> 0 | V18: =IF(ISNA(SUMIFS(INDEX(Inputs!$B$2:$AZ$190,,MATCH(SUBSTITUTE(V$3,"Q","T"),Inputs!$B$2:$AZ$2,0)),Inputs!$B$2:$B$190,$B18)*Inputs!$D$1),"",SUMIFS(INDEX(Inputs!$B$2:$AZ$190,,MATCH(SUBSTITUTE(V$3,"Q","T"),Inputs!$B$2:$AZ$2,0)),Inputs!$B$2:$B$190,$B18)*Inputs!$D$1) -> 0 | W18: =IF(ISNA(SUMIFS(INDEX(Inputs!$B$2:$AZ$190,,MATCH(SUBSTITUTE(W$3,"Q","T"),Inputs!$B$2:$AZ$2,0)),Inputs!$B$2:$B$190,$B18)*Inputs!$D$1),"",SUMIFS(INDEX(Inputs!$B$2:$AZ$190,,MATCH(SUBSTITUTE(W$3,"Q","T"),Inputs!$B$2:$AZ$2,0)),Inputs!$B$2:$B$190,$B18)*Inputs!$D$1) -> 0 | X18: =W18 -> 0 | Y18: =IF(ISNA(SUMIFS(INDEX(Inputs!$B$2:$AZ$190,,MATCH(SUBSTITUTE(Y$3,"Q","T"),Inputs!$B$2:$AZ$2,0)),Inputs!$B$2:$B$190,$B18)*Inputs!$D$1),"",SUMIFS(INDEX(Inputs!$B$2:$AZ$190,,MATCH(SUBSTITUTE(Y$3,"Q","T"),Inputs!$B$2:$AZ$2,0)),Inputs!$B$2:$B$190,$B18)*Inputs!$D$1) -> 0 | Z18: =IF(ISNA(SUMIFS(INDEX(Inputs!$B$2:$AZ$190,,MATCH(SUBSTITUTE(Z$3,"Q","T"),Inputs!$B$2:$AZ$2,0)),Inputs!$B$2:$B$190,$B18)*Inputs!$D$1),"",SUMIFS(INDEX(Inputs!$B$2:$AZ$190,,MATCH(SUBSTITUTE(Z$3,"Q","T"),Inputs!$B$2:$AZ$2,0)),Inputs!$B$2:$B$190,$B18)*Inputs!$D$1) -> 0 | AA18: =IF(ISNA(SUMIFS(INDEX(Inputs!$B$2:$AZ$190,,MATCH(SUBSTITUTE(AA$3,"Q","T"),Inputs!$B$2:$AZ$2,0)),Inputs!$B$2:$B$190,$B18)*Inputs!$D$1),"",SUMIFS(INDEX(Inputs!$B$2:$AZ$190,,MATCH(SUBSTITUTE(AA$3,"Q","T"),Inputs!$B$2:$AZ$2,0)),Inputs!$B$2:$B$190,$B18)*Inputs!$D$1) -> 0 | AB18: =IF(ISNA(SUMIFS(INDEX(Inputs!$B$2:$AZ$190,,MATCH(SUBSTITUTE(AB$3,"Q","T"),Inputs!$B$2:$AZ$2,0)),Inputs!$B$2:$B$190,$B18)*Inputs!$D$1),"",SUMIFS(INDEX(Inputs!$B$2:$AZ$190,,MATCH(SUBSTITUTE(AB$3,"Q","T"),Inputs!$B$2:$AZ$2,0)),Inputs!$B$2:$B$190,$B18)*Inputs!$D$1) -> 0 | AC18: =AB18 -> 0 | AD18: =IF(ISNA(SUMIFS(INDEX(Inputs!$B$2:$AZ$190,,MATCH(SUBSTITUTE(AD$3,"Q","T"),Inputs!$B$2:$AZ$2,0)),Inputs!$B$2:$B$190,$B18)*Inputs!$D$1),"",SUMIFS(INDEX(Inputs!$B$2:$AZ$190,,MATCH(SUBSTITUTE(AD$3,"Q","T"),Inputs!$B$2:$AZ$2,0)),Inputs!$B$2:$B$190,$B18)*Inputs!$D$1) -> 0 | AE18: =IF(ISNA(SUMIFS(INDEX(Inputs!$B$2:$AZ$190,,MATCH(SUBSTITUTE(AE$3,"Q","T"),Inputs!$B$2:$AZ$2,0)),Inputs!$B$2:$B$190,$B18)*Inputs!$D$1),"",SUMIFS(INDEX(Inputs!$B$2:$AZ$190,,MATCH(SUBSTITUTE(AE$3,"Q","T"),Inputs!$B$2:$AZ$2,0)),Inputs!$B$2:$B$190,$B18)*Inputs!$D$1) -> 0 | AF18: =IF(ISNA(SUMIFS(INDEX(Inputs!$B$2:$AZ$190,,MATCH(SUBSTITUTE(AF$3,"Q","T"),Inputs!$B$2:$AZ$2,0)),Inputs!$B$2:$B$190,$B18)*Inputs!$D$1),"",SUMIFS(INDEX(Inputs!$B$2:$AZ$190,,MATCH(SUBSTITUTE(AF$3,"Q","T"),Inputs!$B$2:$AZ$2,0)),Inputs!$B$2:$B$190,$B18)*Inputs!$D$1) -> 0 | AG18: =IF(ISNA(SUMIFS(INDEX(Inputs!$B$2:$AZ$190,,MATCH(SUBSTITUTE(AG$3,"Q","T"),Inputs!$B$2:$AZ$2,0)),Inputs!$B$2:$B$190,$B18)*Inputs!$D$1),"",SUMIFS(INDEX(Inputs!$B$2:$AZ$190,,MATCH(SUBSTITUTE(AG$3,"Q","T"),Inputs!$B$2:$AZ$2,0)),Inputs!$B$2:$B$190,$B18)*Inputs!$D$1) -> 0 | AH18: =AG18 -> 0 | AI18: =IF(ISNA(SUMIFS(INDEX(Inputs!$B$2:$AZ$190,,MATCH(SUBSTITUTE(AI$3,"Q","T"),Inputs!$B$2:$AZ$2,0)),Inputs!$B$2:$B$190,$B18)*Inputs!$D$1),"",SUMIFS(INDEX(Inputs!$B$2:$AZ$190,,MATCH(SUBSTITUTE(AI$3,"Q","T"),Inputs!$B$2:$AZ$2,0)),Inputs!$B$2:$B$190,$B18)*Inputs!$D$1) -> 0 | AJ18: =IF(ISNA(SUMIFS(INDEX(Inputs!$B$2:$AZ$190,,MATCH(SUBSTITUTE(AJ$3,"Q","T"),Inputs!$B$2:$AZ$2,0)),Inputs!$B$2:$B$190,$B18)*Inputs!$D$1),"",SUMIFS(INDEX(Inputs!$B$2:$AZ$190,,MATCH(SUBSTITUTE(AJ$3,"Q","T"),Inputs!$B$2:$AZ$2,0)),Inputs!$B$2:$B$190,$B18)*Inputs!$D$1) -> 0 | AK18: =IF(ISNA(SUMIFS(INDEX(Inputs!$B$2:$AZ$190,,MATCH(SUBSTITUTE(AK$3,"Q","T"),Inputs!$B$2:$AZ$2,0)),Inputs!$B$2:$B$190,$B18)*Inputs!$D$1),"",SUMIFS(INDEX(Inputs!$B$2:$AZ$190,,MATCH(SUBSTITUTE(AK$3,"Q","T"),Inputs!$B$2:$AZ$2,0)),Inputs!$B$2:$B$190,$B18)*Inputs!$D$1) -> 0 | AL18: =IF(ISNA(SUMIFS(INDEX(Inputs!$B$2:$AZ$190,,MATCH(SUBSTITUTE(AL$3,"Q","T"),Inputs!$B$2:$AZ$2,0)),Inputs!$B$2:$B$190,$B18)*Inputs!$D$1),"",SUMIFS(INDEX(Inputs!$B$2:$AZ$190,,MATCH(SUBSTITUTE(AL$3,"Q","T"),Inputs!$B$2:$AZ$2,0)),Inputs!$B$2:$B$190,$B18)*Inputs!$D$1) -> 0 | AM18: =AL18 -> 0 | AN18: =IF(ISNA(SUMIFS(INDEX(Inputs!$B$2:$AZ$190,,MATCH(SUBSTITUTE(AN$3,"Q","T"),Inputs!$B$2:$AZ$2,0)),Inputs!$B$2:$B$190,$B18)*Inputs!$D$1),"",SUMIFS(INDEX(Inputs!$B$2:$AZ$190,,MATCH(SUBSTITUTE(AN$3,"Q","T"),Inputs!$B$2:$AZ$2,0)),Inputs!$B$2:$B$190,$B18)*Inputs!$D$1) -> 0 | AO18: =IF(ISNA(SUMIFS(INDEX(Inputs!$B$2:$AZ$190,,MATCH(SUBSTITUTE(AO$3,"Q","T"),Inputs!$B$2:$AZ$2,0)),Inputs!$B$2:$B$190,$B18)*Inputs!$D$1),"",SUMIFS(INDEX(Inputs!$B$2:$AZ$190,,MATCH(SUBSTITUTE(AO$3,"Q","T"),Inputs!$B$2:$AZ$2,0)),Inputs!$B$2:$B$190,$B18)*Inputs!$D$1) -> 0 | AP18: =IF(ISNA(SUMIFS(INDEX(Inputs!$B$2:$AZ$190,,MATCH(SUBSTITUTE(AP$3,"Q","T"),Inputs!$B$2:$AZ$2,0)),Inputs!$B$2:$B$190,$B18)*Inputs!$D$1),"",SUMIFS(INDEX(Inputs!$B$2:$AZ$190,,MATCH(SUBSTITUTE(AP$3,"Q","T"),Inputs!$B$2:$AZ$2,0)),Inputs!$B$2:$B$190,$B18)*Inputs!$D$1) -> 0 | AQ18: =IF(ISNA(SUMIFS(INDEX(Inputs!$B$2:$AZ$190,,MATCH(SUBSTITUTE(AQ$3,"Q","T"),Inputs!$B$2:$AZ$2,0)),Inputs!$B$2:$B$190,$B18)*Inputs!$D$1),"",SUMIFS(INDEX(Inputs!$B$2:$AZ$190,,MATCH(SUBSTITUTE(AQ$3,"Q","T"),Inputs!$B$2:$AZ$2,0)),Inputs!$B$2:$B$190,$B18)*Inputs!$D$1) -> 0 | AR18: =AQ18 -> 0 | AS18: =IF(ISNA(SUMIFS(INDEX(Inputs!$B$2:$AZ$190,,MATCH(SUBSTITUTE(AS$3,"Q","T"),Inputs!$B$2:$AZ$2,0)),Inputs!$B$2:$B$190,$B18)*Inputs!$D$1),"",SUMIFS(INDEX(Inputs!$B$2:$AZ$190,,MATCH(SUBSTITUTE(AS$3,"Q","T"),Inputs!$B$2:$AZ$2,0)),Inputs!$B$2:$B$190,$B18)*Inputs!$D$1) -> 0 | AT18: =IF(ISNA(SUMIFS(INDEX(Inputs!$B$2:$AZ$190,,MATCH(SUBSTITUTE(AT$3,"Q","T"),Inputs!$B$2:$AZ$2,0)),Inputs!$B$2:$B$190,$B18)*Inputs!$D$1),"",SUMIFS(INDEX(Inputs!$B$2:$AZ$190,,MATCH(SUBSTITUTE(AT$3,"Q","T"),Inputs!$B$2:$AZ$2,0)),Inputs!$B$2:$B$190,$B18)*Inputs!$D$1) -> 0 | AU18: =IF(ISNA(SUMIFS(INDEX(Inputs!$B$2:$AZ$190,,MATCH(SUBSTITUTE(AU$3,"Q","T"),Inputs!$B$2:$AZ$2,0)),Inputs!$B$2:$B$190,$B18)*Inputs!$D$1),"",SUMIFS(INDEX(Inputs!$B$2:$AZ$190,,MATCH(SUBSTITUTE(AU$3,"Q","T"),Inputs!$B$2:$AZ$2,0)),Inputs!$B$2:$B$190,$B18)*Inputs!$D$1) -> 0 | AV18: =IF(ISNA(SUMIFS(INDEX(Inputs!$B$2:$AZ$190,,MATCH(SUBSTITUTE(AV$3,"Q","T"),Inputs!$B$2:$AZ$2,0)),Inputs!$B$2:$B$190,$B18)*Inputs!$D$1),"",SUMIFS(INDEX(Inputs!$B$2:$AZ$190,,MATCH(SUBSTITUTE(AV$3,"Q","T"),Inputs!$B$2:$AZ$2,0)),Inputs!$B$2:$B$190,$B18)*Inputs!$D$1) -> 0 | AW18: =AV18 -> 0 | AX18: =IF(ISNA(SUMIFS(INDEX(Inputs!$B$2:$AZ$190,,MATCH(SUBSTITUTE(AX$3,"Q","T"),Inputs!$B$2:$AZ$2,0)),Inputs!$B$2:$B$190,$B18)*Inputs!$D$1),"",SUMIFS(INDEX(Inputs!$B$2:$AZ$190,,MATCH(SUBSTITUTE(AX$3,"Q","T"),Inputs!$B$2:$AZ$2,0)),Inputs!$B$2:$B$190,$B18)*Inputs!$D$1) -> 0 | AY18: =IF(ISNA(SUMIFS(INDEX(Inputs!$B$2:$AZ$190,,MATCH(SUBSTITUTE(AY$3,"Q","T"),Inputs!$B$2:$AZ$2,0)),Inputs!$B$2:$B$190,$B18)*Inputs!$D$1),"",SUMIFS(INDEX(Inputs!$B$2:$AZ$190,,MATCH(SUBSTITUTE(AY$3,"Q","T"),Inputs!$B$2:$AZ$2,0)),Inputs!$B$2:$B$190,$B18)*Inputs!$D$1) -> 0 | AZ18: =IF(ISNA(SUMIFS(INDEX(Inputs!$B$2:$AZ$190,,MATCH(SUBSTITUTE(AZ$3,"Q","T"),Inputs!$B$2:$AZ$2,0)),Inputs!$B$2:$B$190,$B18)*Inputs!$D$1),"",SUMIFS(INDEX(Inputs!$B$2:$AZ$190,,MATCH(SUBSTITUTE(AZ$3,"Q","T"),Inputs!$B$2:$AZ$2,0)),Inputs!$B$2:$B$190,$B18)*Inputs!$D$1) -> 0 | BA18: =IF(ISNA(SUMIFS(INDEX(Inputs!$B$2:$AZ$190,,MATCH(SUBSTITUTE(BA$3,"Q","T"),Inputs!$B$2:$AZ$2,0)),Inputs!$B$2:$B$190,$B18)*Inputs!$D$1),"",SUMIFS(INDEX(Inputs!$B$2:$AZ$190,,MATCH(SUBSTITUTE(BA$3,"Q","T"),Inputs!$B$2:$AZ$2,0)),Inputs!$B$2:$B$190,$B18)*Inputs!$D$1) -> 0 | BB18: =BA18 -> 0 | BC18: =IF(ISNA(SUMIFS(INDEX(Inputs!$B$2:$AZ$190,,MATCH(SUBSTITUTE(BC$3,"Q","T"),Inputs!$B$2:$AZ$2,0)),Inputs!$B$2:$B$190,$B18)*Inputs!$D$1),"",SUMIFS(INDEX(Inputs!$B$2:$AZ$190,,MATCH(SUBSTITUTE(BC$3,"Q","T"),Inputs!$B$2:$AZ$2,0)),Inputs!$B$2:$B$190,$B18)*Inputs!$D$1) -> 0 | BD18: =IF(ISNA(SUMIFS(INDEX(Inputs!$B$2:$AZ$190,,MATCH(SUBSTITUTE(BD$3,"Q","T"),Inputs!$B$2:$AZ$2,0)),Inputs!$B$2:$B$190,$B18)*Inputs!$D$1),"",SUMIFS(INDEX(Inputs!$B$2:$AZ$190,,MATCH(SUBSTITUTE(BD$3,"Q","T"),Inputs!$B$2:$AZ$2,0)),Inputs!$B$2:$B$190,$B18)*Inputs!$D$1) -> 0 | BE18: =IF(ISNA(SUMIFS(INDEX(Inputs!$B$2:$AZ$190,,MATCH(SUBSTITUTE(BE$3,"Q","T"),Inputs!$B$2:$AZ$2,0)),Inputs!$B$2:$B$190,$B18)*Inputs!$D$1),"",SUMIFS(INDEX(Inputs!$B$2:$AZ$190,,MATCH(SUBSTITUTE(BE$3,"Q","T"),Inputs!$B$2:$AZ$2,0)),Inputs!$B$2:$B$190,$B18)*Inputs!$D$1) -> 0 | BF18: =IF(ISNA(SUMIFS(INDEX(Inputs!$B$2:$AZ$190,,MATCH(SUBSTITUTE(BF$3,"Q","T"),Inputs!$B$2:$AZ$2,0)),Inputs!$B$2:$B$190,$B18)*Inputs!$D$1),"",SUMIFS(INDEX(Inputs!$B$2:$AZ$190,,MATCH(SUBSTITUTE(BF$3,"Q","T"),Inputs!$B$2:$AZ$2,0)),Inputs!$B$2:$B$190,$B18)*Inputs!$D$1) -> 0 | BG18: =BF18 -> 0
