Workbook
Name beta_observed: Valuation!$D$93
Name beta_observed_unlevered: #REF!
Name beta_unlev_comps: #REF!
Name cirkbreak: #REF!
Name costdebtfirm: #REF!
Name costequity: #REF!
Name Debt: #REF!
Name debt_weight: #REF!
Name last_close: Valuation!$G$7
Name Market_Equity: #REF!
Name midyear: #REF!
Name Net_Debt: #REF!
Name range: #REF!
Name relevered_beta: #REF!
Name risk_free_rate: #REF!
Name risk_premium: #REF!
Name Stub_year_fraction: #REF!
Name ticker: Valuation!$D$7
Name totalcap: #REF!
Name Useful_Life_of_Depreciable_PP_E: "PPElife"
Name wacc: #REF!
Name beta_observed: #REF!
Name ticker: #REF!
Name costdebtfirm: Valuation!$D$86
Name costequity: Valuation!$D$94
Name debt: Valuation!$G$88
Name debt_weight: Valuation!$J$88
Name g: Valuation!$D$63
Name market_equity: Valuation!$G$89
Name noplat_t1: Valuation!$D$65
Name relevered_beta: Valuation!$M$102
Name risk_free_rate: Valuation!$D$91
Name risk_premium: Valuation!$D$92
Name ronic: Valuation!$D$64
Name stub_year_fraction: Valuation!$D$11
Name totalcap: Valuation!$G$90
Name wacc: Valuation!$D$12

Sheet Inputs
A1: Fator p/ milhões: | B1: 0.001 | D1: Fleury S.A. (FLRY3) - fonte: "Dados Historicos - 2T26.xlsm" (RI Fleury), consolidado contabil. Abas "Fleury" ate 1T23; abas "Combinada" (colunas contabeis) a partir do 2T23. Moeda: BRL. Unidade dos brutos: R$ mil. Fator converte p/ R$ milhoes.
J2: Aba de origem | K2: Fleury | L2: Fleury | M2: Fleury | N2: Fleury | O2: Fleury | P2: Fleury | Q2: Fleury | R2: Fleury | S2: Fleury | T2: Fleury | U2: Fleury | V2: Fleury | W2: Fleury | X2: Combinada | Y2: Combinada | Z2: Combinada | AA2: Combinada | AB2: Combinada | AC2: Combinada | AD2: Combinada | AE2: Combinada | AF2: Combinada | AG2: Combinada | AH2: Combinada | AI2: Combinada | AJ2: Combinada
J3: Coluna lida (BP) | K3: 1T20 | L3: 2T20 | M3: 3T20 | N3: 2020 | O3: 1T21 | P3: 2T21 | Q3: 3T21 | R3: 2021 | S3: 1T22 | T3: 2T22 | U3: 3T22 | V3: 2022 | W3: 1T23 | X3: 2T23 | Y3: 3T23 | Z3: 4T23 | AA3: 1T24 | AB3: 2T24 | AC3: 3T24 | AD3: 4T24 | AE3: 1T25 | AF3: 2T25 | AG3: 3T25 | AH3: 4T25 | AI3: 1T26 | AJ3: 2T26
A4: COD1 | B4: SINAL1 | C4: COD2 | D4: SINAL2 | E4: COD3 | F4: SINAL3 | G4: UNID | H4: Conta (PT) / origem | I4: Account (EN) | J4: ORIGEM | K4: 1Q20 | L4: 2Q20 | M4: 3Q20 | N4: 4Q20 | O4: 1Q21 | P4: 2Q21 | Q4: 3Q21 | R4: 4Q21 | S4: 1Q22 | T4: 2Q22 | U4: 3Q22 | V4: 4Q22 | W4: 1Q23 | X4: 2Q23 | Y4: 3Q23 | Z4: 4Q23 | AA4: 1Q24 | AB4: 2Q24 | AC4: 3Q24 | AD4: 4Q24 | AE4: 1Q25 | AF4: 2Q25 | AG4: 3Q25 | AH4: 4Q25 | AI4: 1Q26 | AJ4: 2Q26
H5: DRE (R$ mil, trimestre isolado como divulgado; custos e despesas ja negativos na fonte)
A6: 1 | B6: 1 | G6: moeda | H6: Fleury DRE: Receita Líquida (l.15) | Combinada DRE: Receita Líquida (l.13) | J6: fonte | K6: 713933.87 | L6: 454943.9 | M6: 874583.07 | N6: 928154.74 | O6: 893807.98 | P6: 932066.36 | Q6: 1028829.9 | R6: 1017946.4 | S6: 1089912.6 | T6: 1111746 | U6: 1146634.9 | V6: 1114746.8 | W6: 1236823.3 | X6: 1659541 | Y6: 1870045 | Z6: 1704440.7 | AA6: 1904448.5 | AB6: 1978202 | AC6: 1962671.5 | AD6: 1839337 | AE6: 2015074 | AF6: 2024533 | AG6: 2190979.2 | AH6: 2060595.3 | AI6: 2223117.8 | AJ6: 2316653.7
A7: 2 | B7: 1 | G7: moeda | H7: Fleury DRE: Pessoal e Serviços Médicos (l.18) | Combinada DRE: Pessoal e Serviços Médicos (l.16) | J7: fonte | K7: -260074 | L7: -195123.14 | M7: -253006.63 | N7: -279294.72 | O7: -283198.16 | P7: -316306.2 | Q7: -339155.85 | R7: -357590.13 | S7: -363945.83 | T7: -382157.2 | U7: -387841.05 | V7: -409434.78 | W7: -415399 | X7: -528450 | Y7: -583227 | Z7: -558411 | AA7: -558172 | AB7: -593782 | AC7: -584497 | AD7: -597559 | AE7: -576724 | AF7: -628800 | AG7: -653924 | AH7: -658396 | AI7: -675490 | AJ7: -693259
A8: 2 | B8: 1 | G8: moeda | H8: Fleury DRE: Aluguéis, Serviços com Ocupação e Utilidades (l.19) | Combinada DRE: Aluguéis, Serviços com Ocupação e Utilidades (l.17) | J8: fonte | K8: -112173 | L8: -100145.95 | M8: -110722.46 | N8: -123285.78 | O8: -127743.6 | P8: -139249.3 | Q8: -143291.91 | R8: -133736.83 | S8: -143814.67 | T8: -155664.61 | U8: -150945.28 | V8: -145879.32 | W8: -157275 | X8: -215279 | Y8: -233578 | Z8: -238413 | AA8: -232772 | AB8: -243374 | AC8: -248722 | AD8: -254094 | AE8: -260595 | AF8: -268355 | AG8: -290252 | AH8: -279230 | AI8: -285077 | AJ8: -321874
A9: 2 | B9: 1 | G9: moeda | H9: Fleury DRE: Material Direto e Intermediação de Exames (l.20) | Combinada DRE: Material Direto e Intermediação de Exames (l.18) | J9: fonte | K9: -81237 | L9: -87384.566 | M9: -124293.78 | N9: -133945.14 | O9: -122595.92 | P9: -141464.99 | Q9: -153105.16 | R9: -157149.89 | S9: -163674.37 | T9: -172449.53 | U9: -171594.52 | V9: -200344.34 | W9: -200613.64 | X9: -327996 | Y9: -377692.56 | Z9: -358028 | AA9: -397723 | AB9: -418959 | AC9: -408903 | AD9: -382625 | AE9: -437908 | AF9: -424918 | AG9: -451367 | AH9: -450906 | AI9: -450940 | AJ9: -484625
A10: 2 | B10: 1 | G10: moeda | H10: Fleury DRE: Gastos Gerais (l.22) | Combinada DRE: Gastos Gerais (l.20) | J10: fonte | K10: -1149 | L10: -629.67313 | M10: -1027.3212 | N10: -2034.7602 | O10: -1142.6537 | P10: -1835.1811 | Q10: -1513.7655 | R10: -1702.9396 | S10: -1602.8696 | T10: -2717.7391 | U10: -2032.6415 | V10: -3281.9291 | W10: -3145 | X10: -3454 | Y10: -3570 | Z10: -2819 | AA10: -3425 | AB10: -4724 | AC10: -9762 | AD10: 2890 | AE10: -6855 | AF10: -4443 | AG10: -4162 | AH10: -5525 | AI10: -6136 | AJ10: -8422
A11: 4 | B11: 1 | G11: moeda | H11: Fleury DRE: Depreciação e Amortização Custos (l.21) | Combinada DRE: Depreciação e Amortização Custos (l.19) | J11: fonte | K11: -71713.215 | L11: -69081.034 | M11: -72351.61 | N11: -83214.002 | O11: -71869.529 | P11: -74966.504 | Q11: -85222.835 | R11: -92917.14 | S11: -92124.972 | T11: -98401.396 | U11: -99149.983 | V11: -105872.63 | W11: -103719.59 | X11: -129263 | Y11: -144412 | Z11: -146171 | AA11: -147107 | AB11: -150040 | AC11: -153788 | AD11: -154396 | AE11: -160872.94 | AF11: -170039 | AG11: -175424.32 | AH11: -176448.56 | AI11: -177408.86 | AJ11: -164335
A12: 3 | B12: 1 | G12: moeda | H12: Fleury DRE: SG&A (l.35) | Combinada DRE: SG&A (l.33) | J12: fonte | K12: -64744 | L12: -52518.828 | M12: -59456.928 | N12: -82130.528 | O12: -75695.035 | P12: -115884.22 | Q12: -101782.81 | R12: -123333.41 | S12: -93586.945 | T12: -108251.67 | U12: -110987.04 | V12: -125699.27 | W12: -113453.47 | X12: -179447 | Y12: -130664 | Z12: -133497 | AA12: -139962 | AB12: -145978 | AC12: -133693 | AD12: -163614 | AE12: -144996 | AF12: -126585 | AG12: -146464 | AH12: -157502.88 | AI12: -152425.16 | AJ12: -148244
A13: 3 | B13: 1 | G13: moeda | H13: Fleury DRE: [nao existe] | Combinada DRE: Comercial (l.36) [0 em 1Q20..1Q23 (13 per.): linha inexistente/vazia na fonte; total divulgado confirma] | J13: fonte | K13: 0 | L13: 0 | M13: 0 | N13: 0 | O13: 0 | P13: 0 | Q13: 0 | R13: 0 | S13: 0 | T13: 0 | U13: 0 | V13: 0 | W13: 0 | X13: -38444 | Y13: -37203 | Z13: -42613 | AA13: -34716 | AB13: -49585 | AC13: -43879 | AD13: -42222 | AE13: -41781 | AF13: -41424 | AG13: -38133 | AH13: -45673 | AI13: -46353 | AJ13: -47969
A14: 3 | B14: 1 | G14: moeda | H14: Fleury DRE: Outras receitas (despesas) operacionais líquidas (l.38) | Combinada DRE: Outras receitas (despesas) operacionais líquidas (l.37) | J14: fonte | K14: 720.91431 | L14: 529.29694 | M14: -2663.9419 | N14: 278.03022 | O14: 2480.6615 | P14: -147.2569 | Q14: 1096.8118 | R14: 18356.169 | S14: 4570.7779 | T14: 9537.9144 | U14: 10479.8 | V14: 289.28109 | W14: -904.88192 | X14: -2584 | Y14: 7912 | Z14: 6256 | AA14: -19156 | AB14: -505 | AC14: 10260 | AD14: -405 | AE14: -4986.442 | AF14: 281 | AG14: 1368.2307 | AH14: -5395.299 | AI14: -15879.574 | AJ14: -2725
A15: 3 | B15: 1 | G15: moeda | H15: Fleury DRE: Reversão de (provisão) para riscos tributários, trabalhistas e cíveis (l.39) | Combinada DRE: Reversão de (provisão) para riscos tributários, trabalhistas e cíveis (l.38) | J15: fonte | K15: 668.18386 | L15: -62.36384 | M15: 423.65675 | N15: -9669.5501 | O15: -381.01393 | P15: 2556.9986 | Q15: -2524.0718 | R15: -621.21672 | S15: -1279.3311 | T15: -2038.2282 | U15: -1269.4789 | V15: 2282.1709 | W15: -253.3337 | X15: -309 | Y15: -6058 | Z15: -1083 | AA15: -1389 | AB15: 753 | AC15: -6094 | AD15: 3679 | AE15: 6397.094 | AF15: 1801 | AG15: -8681.5093 | AH15: -2029.0015 | AI15: 15179.096 | AJ15: 3397
A16: 4 | B16: 1 | G16: moeda | H16: Fleury DRE: Depreciação e Amortização (l.36) | Combinada DRE: Depreciação e Amortização (l.34) | J16: fonte | K16: -15541.168 | L16: -15618.175 | M16: -15428.476 | N16: -15520.272 | O16: -14966.909 | P16: -15917.936 | Q16: -18610.844 | R16: -14808.018 | S16: -15334.664 | T16: -15441.169 | U16: -10602.523 | V16: -18411.974 | W16: -27542.501 | X16: -36813 | Y16: -43749 | Z16: -43708 | AA16: -42447 | AB16: -41764 | AC16: -42821 | AD16: -47620 | AE16: -51268.14 | AF16: -52364 | AG16: -53950.678 | AH16: -59943.3 | AI16: -55712.835 | AJ16: -51471
A17: 4 | B17: 1 | G17: moeda | H17: Fleury DRE: Amortização de Ágio (l.37) | Combinada DRE: Amortização de Ágio (l.35) | J17: fonte | K17: 0 | L17: 0 | M17: 0 | N17: 0 | O17: 0 | P17: 0 | Q17: 0 | R17: 0 | S17: 0 | T17: 0 | U17: 0 | V17: 0 | W17: 0 | X17: 0 | Y17: 0 | Z17: 0 | AA17: 0 | AB17: 0 | AC17: 0 | AD17: 0 | AE17: 0 | AF17: 0 | AG17: 0 | AH17: 0 | AI17: 0 | AJ17: 0
... A23: 9 | B23: 1 | G23: moeda | H23: Fleury DRE: Participação dos não-controladores (l.55) | Combinada DRE: Participação dos não-controladores (l.55) [0 em 1Q20..4Q20 (4 per.): linha inexistente/vazia na fonte; total divulgado confirma] | J23: fonte | K23: 0 | L23: 0 | M23: 0 | N23: 0 | O23: 0 | P23: 39.423182 | Q23: -1426.5906 | R23: -177.94298 | S23: -391.47077 | T23: -414.89043 | U23: -673.04117 | V23: 656.18412 | W23: 28.34465 | X23: 385.63539 | Y23: 2382 | Z23: 139 | AA23: -355 | AB23: 1423 | AC23: 4013 | AD23: 7437 | AE23: 3456.124 | AF23: 7749.179 | AG23: 2668.4488 | AH23: 2286.2558 | AI23: 3559.4445 | AJ23: 2518
H24: DRE - subtotais divulgados (memoria, sem codigo)
G25: moeda | H25: Fleury DRE: Receita Bruta (l.10) | Combinada DRE: Receita Bruta (l.7) | J25: memoria | K25: 770606.36 | L25: 492196.93 | M25: 943845.28 | N25: 1000542.7 | O25: 964269.12 | P25: 1005132.6 | Q25: 1107449.8 | R25: 1095560.8 | S25: 1173408.1 | T25: 1196381.5 | U25: 1234206.8 | V25: 1199027.3 | W25: 1330405.8 | X25: 1784525 | Y25: 2011020 | Z25: 1835383.2 | AA25: 2055579.5 | AB25: 2136902 | AC25: 2133178.5 | AD25: 1994306 | AE25: 2188441 | AF25: 2197802 | AG25: 2378625.7 | AH25: 2238166 | AI25: 2410224.2 | AJ25: 2514578.4
G26: moeda | H26: Fleury DRE: Custo do serviço prestado (l.17) | Combinada DRE: Custo do serviço prestado (l.15) | J26: memoria | K26: -526346.22 | L26: -452364.35 | M26: -561401.8 | N26: -621774.41 | O26: -606549.87 | P26: -673822.18 | Q26: -722289.52 | R26: -743096.93 | S26: -765162.71 | T26: -811390.48 | U26: -811563.48 | V26: -864813 | W26: -880152.23 | X26: -1204442 | Y26: -1342479.6 | Z26: -1303842 | AA26: -1339199 | AB26: -1410879 | AC26: -1405672 | AD26: -1385784 | AE26: -1442954.9 | AF26: -1496555 | AG26: -1575129.3 | AH26: -1570505.6 | AI26: -1595051.9 | AJ26: -1672515
G27: moeda | H27: Fleury DRE: Lucro Bruto (l.30) | Combinada DRE: Lucro Bruto (l.28) | J27: memoria | K27: 187587.66 | L27: 2579.5404 | M27: 313181.27 | N27: 306380.34 | O27: 287258.11 | P27: 258244.18 | Q27: 306540.34 | R27: 274849.5 | S27: 324749.86 | T27: 300355.48 | U27: 335071.4 | V27: 249933.77 | W27: 356671.07 | X27: 455099 | Y27: 527565.44 | Z27: 400598.7 | AA27: 565249.48 | AB27: 567323 | AC27: 556999.47 | AD27: 453553.05 | AE27: 572119.06 | AF27: 527978 | AG27: 615849.87 | AH27: 490089.78 | AI27: 628065.96 | AJ27: 644138.66
G28: moeda | H28: Fleury DRE: (Despesas) Receitas Operacionais (l.33) | Combinada DRE: (Despesas) Receitas Operacionais (l.31) | J28: memoria | K28: -78857.179 | L28: -68697.5 | M28: -76833.353 | N28: -106671.76 | O28: -88760.591 | P28: -129394.65 | Q28: -121379.82 | R28: -120097.39 | S28: -105629.96 | T28: -115778.72 | U28: -112129.47 | V28: -141601.2 | W28: -142154.19 | X28: -257342 | Y28: -209586 | Z28: -214919 | AA28: -238018 | AB28: -237881 | AC28: -216882 | AD28: -252624 | AE28: -238905.49 | AF28: -221067 | AG28: -249467.29 | AH28: -275449.13 | AI28: -260253.05 | AJ28: -252376.73
G29: moeda | H29: Fleury DRE: Lucro Operacional Antes do Resultado Financeiro (l.42) | Combinada DRE: Lucro Operacional Antes do Resultado Financeiro (l.41) | J29: memoria | K29: 108730.48 | L29: -66117.959 | M29: 236347.92 | N29: 199708.58 | O29: 198497.52 | P29: 128849.53 | Q29: 185160.52 | R29: 154752.11 | S29: 219119.89 | T29: 184576.76 | U29: 222941.93 | V29: 108332.56 | W29: 214516.88 | X29: 197757 | Y29: 317979.44 | Z29: 185679.7 | AA29: 327231.48 | AB29: 329442 | AC29: 340117.47 | AD29: 200929.05 | AE29: 333213.58 | AF29: 306911 | AG29: 366382.57 | AH29: 214640.65 | AI29: 367812.91 | AJ29: 391761.94
G30: moeda | H30: Fleury DRE: Lucro Antes do Imposto de Renda e da Contribuição Social (l.48) | Combinada DRE: Lucro Antes do Imposto de Renda e da Contribuição Social (l.48) | J30: memoria | K30: 79890.071 | L30: -102718.17 | M30: 203034.87 | N30: 160526.26 | O30: 167767.97 | P30: 92638.194 | Q30: 136335.32 | R30: 99365.421 | S30: 153507.2 | T30: 98232.865 | U30: 123530.6 | V30: 30123.158 | W30: 124977.72 | X30: 98246.951 | Y30: 215073.44 | Z30: 93027.907 | AA30: 216956.6 | AB30: 228112 | AC30: 244042.47 | AD30: 97299.925 | AE30: 229843.19 | AF30: 188954 | AG30: 236152.75 | AH30: 98256.937 | AI30: 252752.7 | AJ30: 280475.98
A31: 44 | B31: 1 | G31: moeda | H31: Fleury DRE: Lucro Líquido do Período (l.56) | Combinada DRE: Lucro Líquido do Período (l.56) - COD 44 alimenta o check IS do Model (linha 4) | J31: memoria | K31: 58719.108 | L31: -73305.546 | M31: 132064.54 | N31: 139482.62 | O31: 118611.96 | P31: 65534.626 | Q31: 94962.566 | R31: 70815.803 | S31: 110440.73 | T31: 70509.238 | U31: 96005.75 | V31: 30952.686 | W31: 93851.832 | X31: 74426.929 | Y31: 174198.44 | Z31: 81278.802 | AA31: 167959.6 | AB31: 173586 | AC31: 190705.47 | AD31: 83920.925 | AE31: 179286.29 | AF31: 152299.18 | AG31: 184916.72 | AH31: 96328.41 | AI31: 201211.96 | AJ31: 221850.21
G32: moeda | H32: Fleury DRE: EBITDA (l.65) | Combinada DRE: EBITDA (l.68) | J32: memoria | K32: 195945.97 | L32: 19608.679 | M32: 323835.67 | N32: 298072.29 | O32: 285532.25 | P32: 219736.2 | Q32: 288553.1 | R32: 262168.18 | S32: 326579.33 | T32: 298004.9 | U32: 332444.66 | V32: 232678.57 | W32: 345778.97 | X32: 363578 | Y32: 505964.44 | Z32: 375832.7 | AA32: 517133.48 | AB32: 522048 | AC32: 537381.47 | AD32: 405387.05 | AE32: 547625.65 | AF32: 532090 | AG32: 599363.91 | AH32: 455938.16 | AI32: 605996.18 | AJ32: 612932.66
H33: DFC (R$ mil, trimestre isolado)
A34: 10 | B34: 1 | G34: moeda | H34: Fleury DFC: Dividendos e/ou juros sobre capital próprio (l.63) | Combinada DFC: Dividendos e/ou juros sobre capital próprio e JCSP (l.59) | I34: Dividends / interest on equity paid | J34: fonte | K34: -31176.543 | L34: 0 | M34: 0 | N34: -197752.41 | O34: -75102.32 | P34: -156254.6 | Q34: -42227.238 | R34: -22557.335 | S34: -4129.7924 | T34: -225016.19 | U34: -1.5808 | V34: -108053.81 | W34: 0 | X34: -273224.55 | Y34: -13879.535 | Z34: -223004.92 | AA34: -496 | AB34: -80533 | AC34: 0 | AD34: -262333 | AE34: 0 | AF34: -254045 | AG34: 0 | AH34: -259010 | AI34: -391 | AJ34: -222897
G35: moeda | H35: Fleury DFC: Depreciações e amortizações (l.13) | Combinada DFC: Depreciações e amortizações (l.10) - memoria p/ conferir o cod 4 | J35: memoria | K35: 87254.384 | L35: 84699.208 | M35: 87780.086 | N35: 98734.274 | O35: 86836.438 | P35: 90884.441 | Q35: 103833.68 | R35: 107725.16 | S35: 107459.64 | T35: 113842.57 | U35: 109752.51 | V35: 124284.6 | W35: 131262.09 | X35: 166076 | Y35: 188161 | Z35: 189879 | AA35: 189554 | AB35: 191804 | AC35: 196609 | AD35: 202016 | AE35: 212141 | AF35: 222404 | AG35: 229374 | AH35: 236392 | AI35: 233122 | AJ35: 215806
H36: BALANCO (R$ mil, saldo de fim de trimestre; 4T21 e 4T22 da aba Fleury lidos da coluna anual)
A37: 11 | B37: 1 | G37: moeda | H37: Fleury BP: Caixa e Equivalente de Caixa (l.12) | Combinada BP: Caixa e Equivalente de Caixa AC (l.9) | J37: fonte | K37: 19411.322 | L37: 19598.346 | M37: 18636.41 | N37: 28183.778 | O37: 13585.437 | P37: 35432.931 | Q37: 25929.558 | R37: 33722.307 | S37: 13714.194 | T37: 20642.611 | U37: 8886.9929 | V37: 17255.941 | W37: 9869.6674 | X37: 31512 | Y37: 14117 | Z37: 21920 | AA37: 91401 | AB37: 10412 | AC37: 12634 | AD37: 21788 | AE37: 7535.596 | AF37: 7432 | AG37: 11689 | AH37: 21772 | AI37: 9720 | AJ37: 19060
A38: 11 | B38: 1 | G38: moeda | H38: Fleury BP: Títulos e Valores Mobilíarios (l.13) | Combinada BP: Títulos e Valores Mobilíarios AC (l.10) | J38: fonte | K38: 709987.47 | L38: 1064096.8 | M38: 1121191.9 | N38: 1013620.6 | O38: 1021467.6 | P38: 570834.56 | Q38: 938811.76 | R38: 763371.86 | S38: 492795.46 | T38: 699803.4 | U38: 766586.54 | V38: 1292234.3 | W38: 1271657.3 | X38: 879132 | Y38: 962521 | Z38: 902213 | AA38: 798128 | AB38: 1993649 | AC38: 2222581 | AD38: 2319955 | AE38: 2453023.2 | AF38: 2077180 | AG38: 2500949 | AH38: 2140619 | AI38: 2140485 | AJ38: 1880069
A39: 12 | B39: 1 | G39: moeda | H39: Fleury BP: Contas a Receber (l.14) | Combinada BP: Contas a Receber AC (l.11) | J39: fonte | K39: 548081.51 | L39: 425917.01 | M39: 642007.2 | N39: 704468.12 | O39: 722332.69 | P39: 710160.07 | Q39: 798879.62 | R39: 793850.85 | S39: 867743.74 | T39: 900929.93 | U39: 885466.92 | V39: 856849.06 | W39: 973701.42 | X39: 1486024 | Y39: 1558622 | Z39: 1505194 | AA39: 1731049 | AB39: 1759050 | AC39: 1763847 | AD39: 1634904 | AE39: 1789123.7 | AF39: 1859620 | AG39: 1911173 | AH39: 1747166 | AI39: 2005869 | AJ39: 2094735
A40: 13 | B40: 1 | G40: moeda | H40: Fleury BP: Estoques (l.15) | Combinada BP: Estoques AC (l.12) | J40: fonte | K40: 36868.386 | L40: 83863.152 | M40: 81687.019 | N40: 63092.53 | O40: 63834.832 | P40: 71513.511 | Q40: 68378.852 | R40: 72609.919 | S40: 95168.564 | T40: 76208.636 | U40: 85472.64 | V40: 96575.546 | W40: 99247.068 | X40: 132464 | Y40: 135196 | Z40: 134929 | AA40: 127562 | AB40: 139551 | AC40: 139511 | AD40: 155036 | AE40: 155495.58 | AF40: 149579 | AG40: 154975 | AH40: 180702 | AI40: 150818 | AJ40: 156590
A41: 15 | B41: 1 | G41: moeda | H41: Fleury BP: Despesas do Exercício Seguinte (l.18) | Combinada BP: Despesas do Exercício Seguinte AC (l.16) | J41: fonte | K41: 14324.618 | L41: 20993.925 | M41: 16034.968 | N41: 7771.9494 | O41: 21440.502 | P41: 19749.415 | Q41: 12871.004 | R41: 6918.0429 | S41: 28669.729 | T41: 27256.462 | U41: 22416.825 | V41: 0 | W41: 0 | X41: 0 | Y41: 0 | Z41: 0 | AA41: 0 | AB41: 0 | AC41: 0 | AD41: 0 | AE41: 0 | AF41: 0 | AG41: 0 | AH41: 0 | AI41: 0 | AJ41: 0
A42: 14 | B42: 1 | G42: moeda | H42: Fleury BP: Imposto de Renda e Contribuições Sociais Diferidos (l.19) | Combinada BP: Imposto de Renda e Contribuições Sociais Diferidos AC (l.17) | J42: fonte | K42: 0 | L42: 0 | M42: 0 | N42: 0 | O42: 0 | P42: 0 | Q42: 0 | R42: 0 | S42: 0 | T42: 0 | U42: 0 | V42: 0 | W42: 0 | X42: 0 | Y42: 0 | Z42: 0 | AA42: 0 | AB42: 0 | AC42: 0 | AD42: 0 | AE42: 0 | AF42: 0 | AG42: 0 | AH42: 0 | AI42: 0 | AJ42: 0
A43: 16 | B43: 1 | G43: moeda | H43: Fleury BP: Imposto a Recuperar (l.16) | Combinada BP: Imposto a Recuperar AC (l.13) | J43: fonte | K43: 71914.012 | L43: 91788.568 | M43: 61991.454 | N43: 55570.068 | O43: 60139.992 | P43: 49718.498 | Q43: 129474.39 | R43: 27296.755 | S43: 60850.371 | T43: 103606.7 | U43: 144075.21 | V43: 77022.169 | W43: 88263.759 | X43: 18671 | Y43: 16989 | Z43: 20280 | AA43: 16158 | AB43: 15285 | AC43: 16360 | AD43: 21602 | AE43: 22377 | AF43: 20753 | AG43: 18599 | AH43: 22863 | AI43: 15587 | AJ43: 243400
A44: 16 | B44: 1 | G44: moeda | H44: Fleury BP: [nao existe] | Combinada BP: IRPJ e CSLL a compensar (l.14) [0 em 1Q20..1Q23 (13 per.): linha inexistente/vazia na fonte; total divulgado confirma] | J44: fonte | K44: 0 | L44: 0 | M44: 0 | N44: 0 | O44: 0 | P44: 0 | Q44: 0 | R44: 0 | S44: 0 | T44: 0 | U44: 0 | V44: 0 | W44: 0 | X44: 112671 | Y44: 91941 | Z44: 162486 | AA44: 174335 | AB44: 169898 | AC44: 153615 | AD44: 143242 | AE44: 164655 | AF44: 174606 | AG44: 181166 | AH44: 225290 | AI44: 204296 | AJ44: 0
A45: 16 | B45: 1 | G45: moeda | H45: Fleury BP: Créditos com Partes Relacionadas (l.17) | Combinada BP: Créditos com Partes Relacionadas AC (l.15) | J45: fonte | K45: 25.5 | L45: 25.5 | M45: 0 | N45: 0 | O45: 0 | P45: 0 | Q45: 0 | R45: 0 | S45: 0 | T45: 0 | U45: 0 | V45: 0 | W45: 0 | X45: 0 | Y45: 0 | Z45: 0 | AA45: 0 | AB45: 0 | AC45: 0 | AD45: 0 | AE45: 0 | AF45: 0 | AG45: 0 | AH45: 0 | AI45: 0 | AJ45: 0
A46: 16 | B46: 1 | G46: moeda | H46: Fleury BP: Instrumentos Financeiros Derivativos (l.20) | Combinada BP: Instrumentos Financeiros Derivativos AC (l.18) | J46: fonte | K46: 1527.5554 | L46: 896.27566 | M46: 365.71655 | N46: 0.39701 | O46: 215.78719 | P46: 0 | Q46: 276.29003 | R46: 68 | S46: 0 | T46: 192.94505 | U46: 275.56128 | V46: 0 | W46: 0 | X46: 0 | Y46: 0 | Z46: 0 | AA46: 0 | AB46: 0 | AC46: 0 | AD46: 0 | AE46: 0 | AF46: 0 | AG46: 0 | AH46: 0 | AI46: 0 | AJ46: 0
A47: 16 | B47: 1 | G47: moeda | H47: Fleury BP: Notas Promissórias a Receber (l.21) | Combinada BP: Notas Promissórias a Receber AC (l.19) | J47: fonte | K47: 0 | L47: 0 | M47: 0 | N47: 0 | O47: 0 | P47: 0 | Q47: 0 | R47: 0 | S47: 0 | T47: 0 | U47: 0 | V47: 0 | W47: 0 | X47: 0 | Y47: 0 | Z47: 0 | AA47: 0 | AB47: 0 | AC47: 0 | AD47: 0 | AE47: 0 | AF47: 0 | AG47: 0 | AH47: 0 | AI47: 0 | AJ47: 0
A48: 16 | B48: 1 | G48: moeda | H48: Fleury BP: Outros (l.22) | Combinada BP: Outros AC (l.20) | J48: fonte | K48: 8861.3066 | L48: 5672.8027 | M48: 13916.284 | N48: 7491.0059 | O48: 3274.1039 | P48: 12138.585 | Q48: 21942.549 | R48: 44632.987 | S48: 43298.304 | T48: 44119.326 | U48: 36069.813 | V48: 36499 | W48: 33009 | X48: 77103 | Y48: 59173 | Z48: 56535 | AA48: 64503 | AB48: 79884 | AC48: 83678 | AD48: 79267 | AE48: 71019 | AF48: 78917 | AG48: 85544 | AH48: 83053 | AI48: 123563 | AJ48: 145076
... A105: 35 | B105: 1 | G105: moeda | H105: Fleury BP: Minoritários (l.90) | Combinada BP: Minoritários (l.98) | J105: fonte | K105: 0 | L105: 0 | M105: 0 | N105: 0 | O105: 0 | P105: 1330.7162 | Q105: 2803.5418 | R105: 9199.1796 | S105: 9990.7173 | T105: 11700.365 | U105: 16590.309 | V105: 19548.874 | W105: 22120.863 | X105: 13204 | Y105: 14811 | Z105: 27619 | AA105: 29501.955 | AB105: 74196.88 | AC105: 85252 | AD105: 85763 | AE105: 93419.046 | AF105: 91417 | AG105: 87661 | AH105: 94928 | AI105: 95020 | AJ105: 100794
H106: BALANCO - totais divulgados (memoria, sem codigo)
G107: moeda | H107: Fleury BP: Total do Circulante (l.24) | Combinada BP: Total do Circulante (l.22) | J107: memoria | K107: 1411001.7 | L107: 1712852.4 | M107: 1955830.9 | N107: 1880198.5 | O107: 1906290.9 | P107: 1469547.6 | Q107: 1996564 | R107: 1742470.7 | S107: 1602240.4 | T107: 1872760 | U107: 1949250.5 | V107: 2391404.1 | W107: 2475748.2 | X107: 2737577 | Y107: 2838559 | Z107: 2803557 | AA107: 3003136 | AB107: 4167729 | AC107: 4392226 | AD107: 4375794 | AE107: 4663229 | AF107: 4368087 | AG107: 4864095 | AH107: 4421465 | AI107: 4650338 | AJ107: 4538930
G108: moeda | H108: Fleury BP: TOTAL DO ATIVO (l.47) | Combinada BP: TOTAL DO ATIVO (l.46) | J108: memoria | K108: 5143736.6 | L108: 5468970.2 | M108: 5653505.9 | N108: 5587534.4 | O108: 5573539.5 | P108: 5405805.8 | Q108: 6285689.4 | R108: 6073768.1 | S108: 5995987 | T108: 6839714.9 | U108: 7036072.1 | V108: 7791770.5 | W108: 7863879.1 | X108: 11509984 | Y108: 11533043 | Z108: 11579968 | AA108: 11686093 | AB108: 12802394 | AC108: 13031228 | AD108: 13062410 | AE108: 13270727 | AF108: 13072446 | AG108: 13584226 | AH108: 13220481 | AI108: 13325654 | AJ108: 13558475
G109: moeda | H109: Fleury BP: Total do Circulante (l.62) | Combinada BP: Total do Circulante (l.64) | J109: memoria | K109: 726081.66 | L109: 988203.98 | M109: 1060931.1 | N109: 1109771.7 | O109: 1348197.5 | P109: 1481018.8 | Q109: 1267363.3 | R109: 1206872.2 | S109: 1188694.7 | T109: 1329356.1 | U109: 1445102.6 | V109: 1234135.5 | W109: 1235201 | X109: 1992479 | Y109: 1918079 | Z109: 1686616 | AA109: 1785033 | AB109: 1774725 | AC109: 2271091 | AD109: 1742813 | AE109: 2034615.9 | AF109: 1742951 | AG109: 2201101 | AH109: 2245680 | AI109: 2175756 | AJ109: 2438959
G110: moeda | H110: Fleury BP: Total do Passivo (l.77) | Combinada BP: Total do Passivo (l.82) | J110: memoria | K110: 3521034.2 | L110: 3919838 | M110: 3965966.3 | N110: 3836684.1 | O110: 3880661 | P110: 3647468.6 | Q110: 4467894.5 | R110: 4219287.6 | S110: 4242276.3 | T110: 5010959 | U110: 5104581 | V110: 5090685.5 | W110: 5055895 | X110: 6401400 | Y110: 6341098 | Z110: 6468898 | AA110: 6473366.6 | AB110: 7371349 | AC110: 7603373 | AD110: 7687579 | AE110: 7950503.9 | AF110: 7601926 | AG110: 8101554 | AH110: 8124213 | AI110: 8048020 | AJ110: 8040103
G111: moeda | H111: Fleury BP: Total do Patrimônio Líquido (l.91) | Combinada BP: Total do Patrimônio Líquido (l.99) | J111: memoria | K111: 1622703.3 | L111: 1549132.1 | M111: 1687539.7 | N111: 1750850.3 | O111: 1692878.5 | P111: 1758337.3 | Q111: 1817795 | R111: 1854481.2 | S111: 1753710.7 | T111: 1828755.8 | U111: 1931491.1 | V111: 2701085 | W111: 2807984 | X111: 5108584 | Y111: 5191945 | Z111: 5111070 | AA111: 5212726 | AB111: 5431045.3 | AC111: 5427855 | AD111: 5374831 | AE111: 5320223 | AF111: 5470520 | AG111: 5482672 | AH111: 5096268 | AI111: 5277634 | AJ111: 5518372
G112: moeda | H112: Fleury BP: TOTAL DO PASSIVO E PATRIMÔNIO LÍQUIDO (l.93) | Combinada BP: TOTAL DO PASSIVO E PATRIMÔNIO LÍQUIDO (l.101) | J112: memoria | K112: 5143737.5 | L112: 5468970.2 | M112: 5653505.9 | N112: 5587534.4 | O112: 5573539.5 | P112: 5405805.8 | Q112: 6285689.4 | R112: 6073768.7 | S112: 5995987 | T112: 6839714.9 | U112: 7036072.1 | V112: 7791770.5 | W112: 7863879.1 | X112: 11509984 | Y112: 11533043 | Z112: 11579968 | AA112: 11686093 | AB112: 12802394 | AC112: 13031228 | AD112: 13062410 | AE112: 13270727 | AF112: 13072446 | AG112: 13584226 | AH112: 13220481 | AI112: 13325654 | AJ112: 13558475
H113: CHECKS (devem ser 0)
G114: moeda | H114: CHECK: soma das linhas codificadas 1-9 da DRE - lucro liquido do periodo | J114: derivada | K114: =K6+K7+K8+K9+K10+K11+K12+K13+K14+K15+K16+K17+K18+K19+K20+K21+K22+K23-K31 -> 0 | L114: =L6+L7+L8+L9+L10+L11+L12+L13+L14+L15+L16+L17+L18+L19+L20+L21+L22+L23-L31 -> 0 | M114: =M6+M7+M8+M9+M10+M11+M12+M13+M14+M15+M16+M17+M18+M19+M20+M21+M22+M23-M31 -> 0 | N114: =N6+N7+N8+N9+N10+N11+N12+N13+N14+N15+N16+N17+N18+N19+N20+N21+N22+N23-N31 -> 0 | O114: =O6+O7+O8+O9+O10+O11+O12+O13+O14+O15+O16+O17+O18+O19+O20+O21+O22+O23-O31 -> 0 | P114: =P6+P7+P8+P9+P10+P11+P12+P13+P14+P15+P16+P17+P18+P19+P20+P21+P22+P23-P31 -> 0 | Q114: =Q6+Q7+Q8+Q9+Q10+Q11+Q12+Q13+Q14+Q15+Q16+Q17+Q18+Q19+Q20+Q21+Q22+Q23-Q31 -> 0 | R114: =R6+R7+R8+R9+R10+R11+R12+R13+R14+R15+R16+R17+R18+R19+R20+R21+R22+R23-R31 -> 3.783498e-10 | ... AJ114: =AJ6+AJ7+AJ8+AJ9+AJ10+AJ11+AJ12+AJ13+AJ14+AJ15+AJ16+AJ17+AJ18+AJ19+AJ20+AJ21+AJ22+AJ23-AJ31 -> 0
G115: moeda | H115: CHECK: D&A da DRE (cod 4, negativa) + D&A da DFC (positiva) | J115: derivada | K115: =K11+K16+K17+K35 -> 0 | L115: =L11+L16+L17+L35 -> 0 | M115: =M11+M16+M17+M35 -> 0 | N115: =N11+N16+N17+N35 -> 0 | O115: =O11+O16+O17+O35 -> 0 | P115: =P11+P16+P17+P35 -> 0 | Q115: =Q11+Q16+Q17+Q35 -> 0 | R115: =R11+R16+R17+R35 -> 0 | ... AJ115: =AJ11+AJ16+AJ17+AJ35 -> 0
G116: moeda | H116: CHECK: ativo (cod 11-22) - total do ativo | J116: derivada | K116: =K37+K38+K57+K39+K40+K42+K56+K41+K43+K44+K45+K46+K47+K48+K49+K61+K62+K64+K63+K50+K51+K52+K53+K54+K55+K58+K59+K60-K108 -> 0 | L116: =L37+L38+L57+L39+L40+L42+L56+L41+L43+L44+L45+L46+L47+L48+L49+L61+L62+L64+L63+L50+L51+L52+L53+L54+L55+L58+L59+L60-L108 -> 0 | M116: =M37+M38+M57+M39+M40+M42+M56+M41+M43+M44+M45+M46+M47+M48+M49+M61+M62+M64+M63+M50+M51+M52+M53+M54+M55+M58+M59+M60-M108 -> 0 | N116: =N37+N38+N57+N39+N40+N42+N56+N41+N43+N44+N45+N46+N47+N48+N49+N61+N62+N64+N63+N50+N51+N52+N53+N54+N55+N58+N59+N60-N108 -> 0 | O116: =O37+O38+O57+O39+O40+O42+O56+O41+O43+O44+O45+O46+O47+O48+O49+O61+O62+O64+O63+O50+O51+O52+O53+O54+O55+O58+O59+O60-O108 -> 0 | P116: =P37+P38+P57+P39+P40+P42+P56+P41+P43+P44+P45+P46+P47+P48+P49+P61+P62+P64+P63+P50+P51+P52+P53+P54+P55+P58+P59+P60-P108 -> 0 | Q116: =Q37+Q38+Q57+Q39+Q40+Q42+Q56+Q41+Q43+Q44+Q45+Q46+Q47+Q48+Q49+Q61+Q62+Q64+Q63+Q50+Q51+Q52+Q53+Q54+Q55+Q58+Q59+Q60-Q108 -> 0 | R116: =R37+R38+R57+R39+R40+R42+R56+R41+R43+R44+R45+R46+R47+R48+R49+R61+R62+R64+R63+R50+R51+R52+R53+R54+R55+R58+R59+R60-R108 -> 0 | ... AJ116: =AJ37+AJ38+AJ57+AJ39+AJ40+AJ42+AJ56+AJ41+AJ43+AJ44+AJ45+AJ46+AJ47+AJ48+AJ49+AJ61+AJ62+AJ64+AJ63+AJ50+AJ51+AJ52+AJ53+AJ54+AJ55+AJ58+AJ59+AJ60-AJ108 -> 0
G117: moeda | H117: CHECK: passivo (cod 23-34) - total do passivo | J117: derivada | K117: =K69+K70+K71+K72+K74+K68+K75+K76+K77+K78+K65+K66+K67+K79+K80+K81+K73+K83+K82+K84+K85+K86+K87+K88+K89+K90+K91+K92-K110 -> 0 | L117: =L69+L70+L71+L72+L74+L68+L75+L76+L77+L78+L65+L66+L67+L79+L80+L81+L73+L83+L82+L84+L85+L86+L87+L88+L89+L90+L91+L92-L110 -> 0 | M117: =M69+M70+M71+M72+M74+M68+M75+M76+M77+M78+M65+M66+M67+M79+M80+M81+M73+M83+M82+M84+M85+M86+M87+M88+M89+M90+M91+M92-M110 -> 0 | N117: =N69+N70+N71+N72+N74+N68+N75+N76+N77+N78+N65+N66+N67+N79+N80+N81+N73+N83+N82+N84+N85+N86+N87+N88+N89+N90+N91+N92-N110 -> 0 | O117: =O69+O70+O71+O72+O74+O68+O75+O76+O77+O78+O65+O66+O67+O79+O80+O81+O73+O83+O82+O84+O85+O86+O87+O88+O89+O90+O91+O92-O110 -> 0 | P117: =P69+P70+P71+P72+P74+P68+P75+P76+P77+P78+P65+P66+P67+P79+P80+P81+P73+P83+P82+P84+P85+P86+P87+P88+P89+P90+P91+P92-P110 -> 0 | Q117: =Q69+Q70+Q71+Q72+Q74+Q68+Q75+Q76+Q77+Q78+Q65+Q66+Q67+Q79+Q80+Q81+Q73+Q83+Q82+Q84+Q85+Q86+Q87+Q88+Q89+Q90+Q91+Q92-Q110 -> 0 | R117: =R69+R70+R71+R72+R74+R68+R75+R76+R77+R78+R65+R66+R67+R79+R80+R81+R73+R83+R82+R84+R85+R86+R87+R88+R89+R90+R91+R92-R110 -> 0 | ... AJ117: =AJ69+AJ70+AJ71+AJ72+AJ74+AJ68+AJ75+AJ76+AJ77+AJ78+AJ65+AJ66+AJ67+AJ79+AJ80+AJ81+AJ73+AJ83+AJ82+AJ84+AJ85+AJ86+AJ87+AJ88+AJ89+AJ90+AJ91+AJ92-AJ110 -> 0
G118: moeda | H118: CHECK: PL (cod 35-41) - total do PL | J118: derivada | K118: =K105+K93+K94+K95+K104+K102+K96+K97+K98+K100+K103+K99+K101-K111 -> 0 | L118: =L105+L93+L94+L95+L104+L102+L96+L97+L98+L100+L103+L99+L101-L111 -> 0 | M118: =M105+M93+M94+M95+M104+M102+M96+M97+M98+M100+M103+M99+M101-M111 -> 0 | N118: =N105+N93+N94+N95+N104+N102+N96+N97+N98+N100+N103+N99+N101-N111 -> 0 | O118: =O105+O93+O94+O95+O104+O102+O96+O97+O98+O100+O103+O99+O101-O111 -> 0 | P118: =P105+P93+P94+P95+P104+P102+P96+P97+P98+P100+P103+P99+P101-P111 -> 0 | Q118: =Q105+Q93+Q94+Q95+Q104+Q102+Q96+Q97+Q98+Q100+Q103+Q99+Q101-Q111 -> 0 | R118: =R105+R93+R94+R95+R104+R102+R96+R97+R98+R100+R103+R99+R101-R111 -> 0 | ... AJ118: =AJ105+AJ93+AJ94+AJ95+AJ104+AJ102+AJ96+AJ97+AJ98+AJ100+AJ103+AJ99+AJ101-AJ111 -> 0
H119: [vazio] cod 20 Goodwill: o agio esta dentro do Intangivel na fonte (cod 21); nao aberto no balanco
H120: [vazio] cod 28 Short term debt (revolving): sem linha propria; emprestimos e debentures CP estao no cod 27
H121: [vazio] cod 32 Convertible debt: inexistente
H122: [vazio] cod 36 Convertible Preferred Stock: inexistente
H163: CONVENCOES
H164: Linhas de origem: 5 a 122. As formulas da Inputs (2) varrem as linhas 5 a 160; as linhas 123 a 160 estao livres para novas contas.
H165: Periodos: colunas K a AJ (1Q20 a 2Q26 = 1T20 a 2T26). Linha 2 = aba de origem; linha 3 = coluna lida no balanco.
H166: Brutos em R$ mil, como na fonte. A Inputs (2) multiplica pelo fator da celula B1 (0,001) e entrega R$ milhoes.
H167: Fleury DRE/BP/DFC ate 1T23 (contabil pre-combinacao). Combinada a partir do 2T23, coluna "2T23 Contabil" na DRE/DFC. As colunas pro forma da Combinada (2022 a 1T23, "2T23" e "2023") nao foram usadas.
H168: ORIGEM: fonte = copiado da planilha de fundamentos; memoria = subtotal divulgado, sem codigo; derivada = check por formula.
H169: Uma linha da Inputs pode juntar a conta da aba Fleury e a da aba Combinada quando sao a mesma conta; a descricao mostra as duas linhas de origem.

Sheet Inputs (2)
A1: =COUNTIF($B$3:$B$1048576,$B$1) -> 1 | B1: =MAX($B$3:$B$1048576) -> 44
D2: 1Q21 | E2: 2Q21 | F2: 3Q21 | G2: 4Q21 | H2: 2021 | I2: 1Q22 | J2: 2Q22 | K2: 3Q22 | L2: 4Q22 | M2: 2022 | N2: 1Q23 | O2: 2Q23 | P2: 3Q23 | Q2: 4Q23 | R2: 2023 | S2: 1Q24 | T2: 2Q24 | U2: 3Q24 | V2: 4Q24 | W2: 2024 | X2: 1Q25 | Y2: 2Q25 | Z2: 3Q25 | AA2: 4Q25 | AB2: 2025 | AC2: 1Q26 | AD2: 2Q26 | AE2: 3Q26 | AF2: 4Q26 | AG2: 2026 | AH2: 1Q20 | AI2: 2Q20 | AJ2: 3Q20 | AK2: 4Q20 | AL2: 2020 | AN2: Sem dado na fonte: 3Q26, 4Q26 e 2026 (rotulo em cinza). 2020 fica nas colunas AH-AL.
B4: 1 | C4: Net Revenues | D4: =IF(ISNA(MATCH(D$2,Inputs!$K$4:$AJ$4,0)),NA(),IF(SUMPRODUCT((Inputs!$A$5:$A$160=$B4)*ISNUMBER(INDEX(Inputs!$K$5:$AJ$160,0,MATCH(D$2,Inputs!$K$4:$AJ$4,0))))+SUMPRODUCT((Inputs!$C$5:$C$160=$B4)*ISNUMBER(INDEX(Inputs!$K$5:$AJ$160,0,MATCH(D$2,Inputs!$K$4:$AJ$4,0))))+SUMPRODUCT((Inputs!$E$5:$E$160=$B4)*ISNUMBER(INDEX(Inputs!$K$5:$AJ$160,0,MATCH(D$2,Inputs!$K$4:$AJ$4,0))))=0,NA(),SUMPRODUCT((Inputs!$A$5:$A$160=$B4)*Inputs!$B$5:$B$160*(((Inputs!$G$5:$G$160="moeda")+(Inputs!$G$5:$G$160="acoes"))*Inputs!$B$1+((Inputs!$G$5:$G$160<>"moeda")*(Inputs!$G$5:$G$160<>"acoes")))*INDEX(Inputs!$K$5:$AJ$160,0,MATCH(D$2,Inputs!$K$4:$AJ$4,0)))+SUMPRODUCT((Inputs!$C$5:$C$160=$B4)*Inputs!$D$5:$D$160*(((Inputs!$G$5:$G$160="moeda")+(Inputs!$G$5:$G$160="acoes"))*Inputs!$B$1+((Inputs!$G$5:$G$160<>"moeda")*(Inputs!$G$5:$G$160<>"acoes")))*INDEX(Inputs!$K$5:$AJ$160,0,MATCH(D$2,Inputs!$K$4:$AJ$4,0)))+SUMPRODUCT((Inputs!$E$5:$E$160=$B4)*Inputs!$F$5:$F$160*(((Inputs!$G$5:$G$160="moeda")+(Inputs!$G$5:$G$160="acoes"))*Inputs!$B$1+((Inputs!$G$5:$G$160<>"moeda")*(Inputs!$G$5:$G$160<>"acoes")))*INDEX(Inputs!$K$5:$AJ$160,0,MATCH(D$2,Inputs!$K$4:$AJ$4,0))))) -> 893.80798 | E4: =IF(ISNA(MATCH(E$2,Inputs!$K$4:$AJ$4,0)),NA(),IF(SUMPRODUCT((Inputs!$A$5:$A$160=$B4)*ISNUMBER(INDEX(Inputs!$K$5:$AJ$160,0,MATCH(E$2,Inputs!$K$4:$AJ$4,0))))+SUMPRODUCT((Inputs!$C$5:$C$160=$B4)*ISNUMBER(INDEX(Inputs!$K$5:$AJ$160,0,MATCH(E$2,Inputs!$K$4:$AJ$4,0))))+SUMPRODUCT((Inputs!$E$5:$E$160=$B4)*ISNUMBER(INDEX(Inputs!$K$5:$AJ$160,0,MATCH(E$2,Inputs!$K$4:$AJ$4,0))))=0,NA(),SUMPRODUCT((Inputs!$A$5:$A$160=$B4)*Inputs!$B$5:$B$160*(((Inputs!$G$5:$G$160="moeda")+(Inputs!$G$5:$G$160="acoes"))*Inputs!$B$1+((Inputs!$G$5:$G$160<>"moeda")*(Inputs!$G$5:$G$160<>"acoes")))*INDEX(Inputs!$K$5:$AJ$160,0,MATCH(E$2,Inputs!$K$4:$AJ$4,0)))+SUMPRODUCT((Inputs!$C$5:$C$160=$B4)*Inputs!$D$5:$D$160*(((Inputs!$G$5:$G$160="moeda")+(Inputs!$G$5:$G$160="acoes"))*Inputs!$B$1+((Inputs!$G$5:$G$160<>"moeda")*(Inputs!$G$5:$G$160<>"acoes")))*INDEX(Inputs!$K$5:$AJ$160,0,MATCH(E$2,Inputs!$K$4:$AJ$4,0)))+SUMPRODUCT((Inputs!$E$5:$E$160=$B4)*Inputs!$F$5:$F$160*(((Inputs!$G$5:$G$160="moeda")+(Inputs!$G$5:$G$160="acoes"))*Inputs!$B$1+((Inputs!$G$5:$G$160<>"moeda")*(Inputs!$G$5:$G$160<>"acoes")))*INDEX(Inputs!$K$5:$AJ$160,0,MATCH(E$2,Inputs!$K$4:$AJ$4,0))))) -> 932.06636 | F4: =IF(ISNA(MATCH(F$2,Inputs!$K$4:$AJ$4,0)),NA(),IF(SUMPRODUCT((Inputs!$A$5:$A$160=$B4)*ISNUMBER(INDEX(Inputs!$K$5:$AJ$160,0,MATCH(F$2,Inputs!$K$4:$AJ$4,0))))+SUMPRODUCT((Inputs!$C$5:$C$160=$B4)*ISNUMBER(INDEX(Inputs!$K$5:$AJ$160,0,MATCH(F$2,Inputs!$K$4:$AJ$4,0))))+SUMPRODUCT((Inputs!$E$5:$E$160=$B4)*ISNUMBER(INDEX(Inputs!$K$5:$AJ$160,0,MATCH(F$2,Inputs!$K$4:$AJ$4,0))))=0,NA(),SUMPRODUCT((Inputs!$A$5:$A$160=$B4)*Inputs!$B$5:$B$160*(((Inputs!$G$5:$G$160="moeda")+(Inputs!$G$5:$G$160="acoes"))*Inputs!$B$1+((Inputs!$G$5:$G$160<>"moeda")*(Inputs!$G$5:$G$160<>"acoes")))*INDEX(Inputs!$K$5:$AJ$160,0,MATCH(F$2,Inputs!$K$4:$AJ$4,0)))+SUMPRODUCT((Inputs!$C$5:$C$160=$B4)*Inputs!$D$5:$D$160*(((Inputs!$G$5:$G$160="moeda")+(Inputs!$G$5:$G$160="acoes"))*Inputs!$B$1+((Inputs!$G$5:$G$160<>"moeda")*(Inputs!$G$5:$G$160<>"acoes")))*INDEX(Inputs!$K$5:$AJ$160,0,MATCH(F$2,Inputs!$K$4:$AJ$4,0)))+SUMPRODUCT((Inputs!$E$5:$E$160=$B4)*Inputs!$F$5:$F$160*(((Inputs!$G$5:$G$160="moeda")+(Inputs!$G$5:$G$160="acoes"))*Inputs!$B$1+((Inputs!$G$5:$G$160<>"moeda")*(Inputs!$G$5:$G$160<>"acoes")))*INDEX(Inputs!$K$5:$AJ$160,0,MATCH(F$2,Inputs!$K$4:$AJ$4,0))))) -> 1028.8299 | G4: =IF(ISNA(MATCH(G$2,Inputs!$K$4:$AJ$4,0)),NA(),IF(SUMPRODUCT((Inputs!$A$5:$A$160=$B4)*ISNUMBER(INDEX(Inputs!$K$5:$AJ$160,0,MATCH(G$2,Inputs!$K$4:$AJ$4,0))))+SUMPRODUCT((Inputs!$C$5:$C$160=$B4)*ISNUMBER(INDEX(Inputs!$K$5:$AJ$160,0,MATCH(G$2,Inputs!$K$4:$AJ$4,0))))+SUMPRODUCT((Inputs!$E$5:$E$160=$B4)*ISNUMBER(INDEX(Inputs!$K$5:$AJ$160,0,MATCH(G$2,Inputs!$K$4:$AJ$4,0))))=0,NA(),SUMPRODUCT((Inputs!$A$5:$A$160=$B4)*Inputs!$B$5:$B$160*(((Inputs!$G$5:$G$160="moeda")+(Inputs!$G$5:$G$160="acoes"))*Inputs!$B$1+((Inputs!$G$5:$G$160<>"moeda")*(Inputs!$G$5:$G$160<>"acoes")))*INDEX(Inputs!$K$5:$AJ$160,0,MATCH(G$2,Inputs!$K$4:$AJ$4,0)))+SUMPRODUCT((Inputs!$C$5:$C$160=$B4)*Inputs!$D$5:$D$160*(((Inputs!$G$5:$G$160="moeda")+(Inputs!$G$5:$G$160="acoes"))*Inputs!$B$1+((Inputs!$G$5:$G$160<>"moeda")*(Inputs!$G$5:$G$160<>"acoes")))*INDEX(Inputs!$K$5:$AJ$160,0,MATCH(G$2,Inputs!$K$4:$AJ$4,0)))+SUMPRODUCT((Inputs!$E$5:$E$160=$B4)*Inputs!$F$5:$F$160*(((Inputs!$G$5:$G$160="moeda")+(Inputs!$G$5:$G$160="acoes"))*Inputs!$B$1+((Inputs!$G$5:$G$160<>"moeda")*(Inputs!$G$5:$G$160<>"acoes")))*INDEX(Inputs!$K$5:$AJ$160,0,MATCH(G$2,Inputs!$K$4:$AJ$4,0))))) -> 1017.9464 | H4: =SUM(D4:G4) -> 3872.6506 | I4: =IF(ISNA(MATCH(I$2,Inputs!$K$4:$AJ$4,0)),NA(),IF(SUMPRODUCT((Inputs!$A$5:$A$160=$B4)*ISNUMBER(INDEX(Inputs!$K$5:$AJ$160,0,MATCH(I$2,Inputs!$K$4:$AJ$4,0))))+SUMPRODUCT((Inputs!$C$5:$C$160=$B4)*ISNUMBER(INDEX(Inputs!$K$5:$AJ$160,0,MATCH(I$2,Inputs!$K$4:$AJ$4,0))))+SUMPRODUCT((Inputs!$E$5:$E$160=$B4)*ISNUMBER(INDEX(Inputs!$K$5:$AJ$160,0,MATCH(I$2,Inputs!$K$4:$AJ$4,0))))=0,NA(),SUMPRODUCT((Inputs!$A$5:$A$160=$B4)*Inputs!$B$5:$B$160*(((Inputs!$G$5:$G$160="moeda")+(Inputs!$G$5:$G$160="acoes"))*Inputs!$B$1+((Inputs!$G$5:$G$160<>"moeda")*(Inputs!$G$5:$G$160<>"acoes")))*INDEX(Inputs!$K$5:$AJ$160,0,MATCH(I$2,Inputs!$K$4:$AJ$4,0)))+SUMPRODUCT((Inputs!$C$5:$C$160=$B4)*Inputs!$D$5:$D$160*(((Inputs!$G$5:$G$160="moeda")+(Inputs!$G$5:$G$160="acoes"))*Inputs!$B$1+((Inputs!$G$5:$G$160<>"moeda")*(Inputs!$G$5:$G$160<>"acoes")))*INDEX(Inputs!$K$5:$AJ$160,0,MATCH(I$2,Inputs!$K$4:$AJ$4,0)))+SUMPRODUCT((Inputs!$E$5:$E$160=$B4)*Inputs!$F$5:$F$160*(((Inputs!$G$5:$G$160="moeda")+(Inputs!$G$5:$G$160="acoes"))*Inputs!$B$1+((Inputs!$G$5:$G$160<>"moeda")*(Inputs!$G$5:$G$160<>"acoes")))*INDEX(Inputs!$K$5:$AJ$160,0,MATCH(I$2,Inputs!$K$4:$AJ$4,0))))) -> 1089.9126 | J4: =IF(ISNA(MATCH(J$2,Inputs!$K$4:$AJ$4,0)),NA(),IF(SUMPRODUCT((Inputs!$A$5:$A$160=$B4)*ISNUMBER(INDEX(Inputs!$K$5:$AJ$160,0,MATCH(J$2,Inputs!$K$4:$AJ$4,0))))+SUMPRODUCT((Inputs!$C$5:$C$160=$B4)*ISNUMBER(INDEX(Inputs!$K$5:$AJ$160,0,MATCH(J$2,Inputs!$K$4:$AJ$4,0))))+SUMPRODUCT((Inputs!$E$5:$E$160=$B4)*ISNUMBER(INDEX(Inputs!$K$5:$AJ$160,0,MATCH(J$2,Inputs!$K$4:$AJ$4,0))))=0,NA(),SUMPRODUCT((Inputs!$A$5:$A$160=$B4)*Inputs!$B$5:$B$160*(((Inputs!$G$5:$G$160="moeda")+(Inputs!$G$5:$G$160="acoes"))*Inputs!$B$1+((Inputs!$G$5:$G$160<>"moeda")*(Inputs!$G$5:$G$160<>"acoes")))*INDEX(Inputs!$K$5:$AJ$160,0,MATCH(J$2,Inputs!$K$4:$AJ$4,0)))+SUMPRODUCT((Inputs!$C$5:$C$160=$B4)*Inputs!$D$5:$D$160*(((Inputs!$G$5:$G$160="moeda")+(Inputs!$G$5:$G$160="acoes"))*Inputs!$B$1+((Inputs!$G$5:$G$160<>"moeda")*(Inputs!$G$5:$G$160<>"acoes")))*INDEX(Inputs!$K$5:$AJ$160,0,MATCH(J$2,Inputs!$K$4:$AJ$4,0)))+SUMPRODUCT((Inputs!$E$5:$E$160=$B4)*Inputs!$F$5:$F$160*(((Inputs!$G$5:$G$160="moeda")+(Inputs!$G$5:$G$160="acoes"))*Inputs!$B$1+((Inputs!$G$5:$G$160<>"moeda")*(Inputs!$G$5:$G$160<>"acoes")))*INDEX(Inputs!$K$5:$AJ$160,0,MATCH(J$2,Inputs!$K$4:$AJ$4,0))))) -> 1111.746 | K4: =IF(ISNA(MATCH(K$2,Inputs!$K$4:$AJ$4,0)),NA(),IF(SUMPRODUCT((Inputs!$A$5:$A$160=$B4)*ISNUMBER(INDEX(Inputs!$K$5:$AJ$160,0,MATCH(K$2,Inputs!$K$4:$AJ$4,0))))+SUMPRODUCT((Inputs!$C$5:$C$160=$B4)*ISNUMBER(INDEX(Inputs!$K$5:$AJ$160,0,MATCH(K$2,Inputs!$K$4:$AJ$4,0))))+SUMPRODUCT((Inputs!$E$5:$E$160=$B4)*ISNUMBER(INDEX(Inputs!$K$5:$AJ$160,0,MATCH(K$2,Inputs!$K$4:$AJ$4,0))))=0,NA(),SUMPRODUCT((Inputs!$A$5:$A$160=$B4)*Inputs!$B$5:$B$160*(((Inputs!$G$5:$G$160="moeda")+(Inputs!$G$5:$G$160="acoes"))*Inputs!$B$1+((Inputs!$G$5:$G$160<>"moeda")*(Inputs!$G$5:$G$160<>"acoes")))*INDEX(Inputs!$K$5:$AJ$160,0,MATCH(K$2,Inputs!$K$4:$AJ$4,0)))+SUMPRODUCT((Inputs!$C$5:$C$160=$B4)*Inputs!$D$5:$D$160*(((Inputs!$G$5:$G$160="moeda")+(Inputs!$G$5:$G$160="acoes"))*Inputs!$B$1+((Inputs!$G$5:$G$160<>"moeda")*(Inputs!$G$5:$G$160<>"acoes")))*INDEX(Inputs!$K$5:$AJ$160,0,MATCH(K$2,Inputs!$K$4:$AJ$4,0)))+SUMPRODUCT((Inputs!$E$5:$E$160=$B4)*Inputs!$F$5:$F$160*(((Inputs!$G$5:$G$160="moeda")+(Inputs!$G$5:$G$160="acoes"))*Inputs!$B$1+((Inputs!$G$5:$G$160<>"moeda")*(Inputs!$G$5:$G$160<>"acoes")))*INDEX(Inputs!$K$5:$AJ$160,0,MATCH(K$2,Inputs!$K$4:$AJ$4,0))))) -> 1146.6349 | L4: =IF(ISNA(MATCH(L$2,Inputs!$K$4:$AJ$4,0)),NA(),IF(SUMPRODUCT((Inputs!$A$5:$A$160=$B4)*ISNUMBER(INDEX(Inputs!$K$5:$AJ$160,0,MATCH(L$2,Inputs!$K$4:$AJ$4,0))))+SUMPRODUCT((Inputs!$C$5:$C$160=$B4)*ISNUMBER(INDEX(Inputs!$K$5:$AJ$160,0,MATCH(L$2,Inputs!$K$4:$AJ$4,0))))+SUMPRODUCT((Inputs!$E$5:$E$160=$B4)*ISNUMBER(INDEX(Inputs!$K$5:$AJ$160,0,MATCH(L$2,Inputs!$K$4:$AJ$4,0))))=0,NA(),SUMPRODUCT((Inputs!$A$5:$A$160=$B4)*Inputs!$B$5:$B$160*(((Inputs!$G$5:$G$160="moeda")+(Inputs!$G$5:$G$160="acoes"))*Inputs!$B$1+((Inputs!$G$5:$G$160<>"moeda")*(Inputs!$G$5:$G$160<>"acoes")))*INDEX(Inputs!$K$5:$AJ$160,0,MATCH(L$2,Inputs!$K$4:$AJ$4,0)))+SUMPRODUCT((Inputs!$C$5:$C$160=$B4)*Inputs!$D$5:$D$160*(((Inputs!$G$5:$G$160="moeda")+(Inputs!$G$5:$G$160="acoes"))*Inputs!$B$1+((Inputs!$G$5:$G$160<>"moeda")*(Inputs!$G$5:$G$160<>"acoes")))*INDEX(Inputs!$K$5:$AJ$160,0,MATCH(L$2,Inputs!$K$4:$AJ$4,0)))+SUMPRODUCT((Inputs!$E$5:$E$160=$B4)*Inputs!$F$5:$F$160*(((Inputs!$G$5:$G$160="moeda")+(Inputs!$G$5:$G$160="acoes"))*Inputs!$B$1+((Inputs!$G$5:$G$160<>"moeda")*(Inputs!$G$5:$G$160<>"acoes")))*INDEX(Inputs!$K$5:$AJ$160,0,MATCH(L$2,Inputs!$K$4:$AJ$4,0))))) -> 1114.7468 | M4: =SUM(I4:L4) -> 4463.0402 | N4: =IF(ISNA(MATCH(N$2,Inputs!$K$4:$AJ$4,0)),NA(),IF(SUMPRODUCT((Inputs!$A$5:$A$160=$B4)*ISNUMBER(INDEX(Inputs!$K$5:$AJ$160,0,MATCH(N$2,Inputs!$K$4:$AJ$4,0))))+SUMPRODUCT((Inputs!$C$5:$C$160=$B4)*ISNUMBER(INDEX(Inputs!$K$5:$AJ$160,0,MATCH(N$2,Inputs!$K$4:$AJ$4,0))))+SUMPRODUCT((Inputs!$E$5:$E$160=$B4)*ISNUMBER(INDEX(Inputs!$K$5:$AJ$160,0,MATCH(N$2,Inputs!$K$4:$AJ$4,0))))=0,NA(),SUMPRODUCT((Inputs!$A$5:$A$160=$B4)*Inputs!$B$5:$B$160*(((Inputs!$G$5:$G$160="moeda")+(Inputs!$G$5:$G$160="acoes"))*Inputs!$B$1+((Inputs!$G$5:$G$160<>"moeda")*(Inputs!$G$5:$G$160<>"acoes")))*INDEX(Inputs!$K$5:$AJ$160,0,MATCH(N$2,Inputs!$K$4:$AJ$4,0)))+SUMPRODUCT((Inputs!$C$5:$C$160=$B4)*Inputs!$D$5:$D$160*(((Inputs!$G$5:$G$160="moeda")+(Inputs!$G$5:$G$160="acoes"))*Inputs!$B$1+((Inputs!$G$5:$G$160<>"moeda")*(Inputs!$G$5:$G$160<>"acoes")))*INDEX(Inputs!$K$5:$AJ$160,0,MATCH(N$2,Inputs!$K$4:$AJ$4,0)))+SUMPRODUCT((Inputs!$E$5:$E$160=$B4)*Inputs!$F$5:$F$160*(((Inputs!$G$5:$G$160="moeda")+(Inputs!$G$5:$G$160="acoes"))*Inputs!$B$1+((Inputs!$G$5:$G$160<>"moeda")*(Inputs!$G$5:$G$160<>"acoes")))*INDEX(Inputs!$K$5:$AJ$160,0,MATCH(N$2,Inputs!$K$4:$AJ$4,0))))) -> 1236.8233 | O4: =IF(ISNA(MATCH(O$2,Inputs!$K$4:$AJ$4,0)),NA(),IF(SUMPRODUCT((Inputs!$A$5:$A$160=$B4)*ISNUMBER(INDEX(Inputs!$K$5:$AJ$160,0,MATCH(O$2,Inputs!$K$4:$AJ$4,0))))+SUMPRODUCT((Inputs!$C$5:$C$160=$B4)*ISNUMBER(INDEX(Inputs!$K$5:$AJ$160,0,MATCH(O$2,Inputs!$K$4:$AJ$4,0))))+SUMPRODUCT((Inputs!$E$5:$E$160=$B4)*ISNUMBER(INDEX(Inputs!$K$5:$AJ$160,0,MATCH(O$2,Inputs!$K$4:$AJ$4,0))))=0,NA(),SUMPRODUCT((Inputs!$A$5:$A$160=$B4)*Inputs!$B$5:$B$160*(((Inputs!$G$5:$G$160="moeda")+(Inputs!$G$5:$G$160="acoes"))*Inputs!$B$1+((Inputs!$G$5:$G$160<>"moeda")*(Inputs!$G$5:$G$160<>"acoes")))*INDEX(Inputs!$K$5:$AJ$160,0,MATCH(O$2,Inputs!$K$4:$AJ$4,0)))+SUMPRODUCT((Inputs!$C$5:$C$160=$B4)*Inputs!$D$5:$D$160*(((Inputs!$G$5:$G$160="moeda")+(Inputs!$G$5:$G$160="acoes"))*Inputs!$B$1+((Inputs!$G$5:$G$160<>"moeda")*(Inputs!$G$5:$G$160<>"acoes")))*INDEX(Inputs!$K$5:$AJ$160,0,MATCH(O$2,Inputs!$K$4:$AJ$4,0)))+SUMPRODUCT((Inputs!$E$5:$E$160=$B4)*Inputs!$F$5:$F$160*(((Inputs!$G$5:$G$160="moeda")+(Inputs!$G$5:$G$160="acoes"))*Inputs!$B$1+((Inputs!$G$5:$G$160<>"moeda")*(Inputs!$G$5:$G$160<>"acoes")))*INDEX(Inputs!$K$5:$AJ$160,0,MATCH(O$2,Inputs!$K$4:$AJ$4,0))))) -> 1659.541 | P4: =IF(ISNA(MATCH(P$2,Inputs!$K$4:$AJ$4,0)),NA(),IF(SUMPRODUCT((Inputs!$A$5:$A$160=$B4)*ISNUMBER(INDEX(Inputs!$K$5:$AJ$160,0,MATCH(P$2,Inputs!$K$4:$AJ$4,0))))+SUMPRODUCT((Inputs!$C$5:$C$160=$B4)*ISNUMBER(INDEX(Inputs!$K$5:$AJ$160,0,MATCH(P$2,Inputs!$K$4:$AJ$4,0))))+SUMPRODUCT((Inputs!$E$5:$E$160=$B4)*ISNUMBER(INDEX(Inputs!$K$5:$AJ$160,0,MATCH(P$2,Inputs!$K$4:$AJ$4,0))))=0,NA(),SUMPRODUCT((Inputs!$A$5:$A$160=$B4)*Inputs!$B$5:$B$160*(((Inputs!$G$5:$G$160="moeda")+(Inputs!$G$5:$G$160="acoes"))*Inputs!$B$1+((Inputs!$G$5:$G$160<>"moeda")*(Inputs!$G$5:$G$160<>"acoes")))*INDEX(Inputs!$K$5:$AJ$160,0,MATCH(P$2,Inputs!$K$4:$AJ$4,0)))+SUMPRODUCT((Inputs!$C$5:$C$160=$B4)*Inputs!$D$5:$D$160*(((Inputs!$G$5:$G$160="moeda")+(Inputs!$G$5:$G$160="acoes"))*Inputs!$B$1+((Inputs!$G$5:$G$160<>"moeda")*(Inputs!$G$5:$G$160<>"acoes")))*INDEX(Inputs!$K$5:$AJ$160,0,MATCH(P$2,Inputs!$K$4:$AJ$4,0)))+SUMPRODUCT((Inputs!$E$5:$E$160=$B4)*Inputs!$F$5:$F$160*(((Inputs!$G$5:$G$160="moeda")+(Inputs!$G$5:$G$160="acoes"))*Inputs!$B$1+((Inputs!$G$5:$G$160<>"moeda")*(Inputs!$G$5:$G$160<>"acoes")))*INDEX(Inputs!$K$5:$AJ$160,0,MATCH(P$2,Inputs!$K$4:$AJ$4,0))))) -> 1870.045 | Q4: =IF(ISNA(MATCH(Q$2,Inputs!$K$4:$AJ$4,0)),NA(),IF(SUMPRODUCT((Inputs!$A$5:$A$160=$B4)*ISNUMBER(INDEX(Inputs!$K$5:$AJ$160,0,MATCH(Q$2,Inputs!$K$4:$AJ$4,0))))+SUMPRODUCT((Inputs!$C$5:$C$160=$B4)*ISNUMBER(INDEX(Inputs!$K$5:$AJ$160,0,MATCH(Q$2,Inputs!$K$4:$AJ$4,0))))+SUMPRODUCT((Inputs!$E$5:$E$160=$B4)*ISNUMBER(INDEX(Inputs!$K$5:$AJ$160,0,MATCH(Q$2,Inputs!$K$4:$AJ$4,0))))=0,NA(),SUMPRODUCT((Inputs!$A$5:$A$160=$B4)*Inputs!$B$5:$B$160*(((Inputs!$G$5:$G$160="moeda")+(Inputs!$G$5:$G$160="acoes"))*Inputs!$B$1+((Inputs!$G$5:$G$160<>"moeda")*(Inputs!$G$5:$G$160<>"acoes")))*INDEX(Inputs!$K$5:$AJ$160,0,MATCH(Q$2,Inputs!$K$4:$AJ$4,0)))+SUMPRODUCT((Inputs!$C$5:$C$160=$B4)*Inputs!$D$5:$D$160*(((Inputs!$G$5:$G$160="moeda")+(Inputs!$G$5:$G$160="acoes"))*Inputs!$B$1+((Inputs!$G$5:$G$160<>"moeda")*(Inputs!$G$5:$G$160<>"acoes")))*INDEX(Inputs!$K$5:$AJ$160,0,MATCH(Q$2,Inputs!$K$4:$AJ$4,0)))+SUMPRODUCT((Inputs!$E$5:$E$160=$B4)*Inputs!$F$5:$F$160*(((Inputs!$G$5:$G$160="moeda")+(Inputs!$G$5:$G$160="acoes"))*Inputs!$B$1+((Inputs!$G$5:$G$160<>"moeda")*(Inputs!$G$5:$G$160<>"acoes")))*INDEX(Inputs!$K$5:$AJ$160,0,MATCH(Q$2,Inputs!$K$4:$AJ$4,0))))) -> 1704.4407 | R4: =SUM(N4:Q4) -> 6470.85 | S4: =IF(ISNA(MATCH(S$2,Inputs!$K$4:$AJ$4,0)),NA(),IF(SUMPRODUCT((Inputs!$A$5:$A$160=$B4)*ISNUMBER(INDEX(Inputs!$K$5:$AJ$160,0,MATCH(S$2,Inputs!$K$4:$AJ$4,0))))+SUMPRODUCT((Inputs!$C$5:$C$160=$B4)*ISNUMBER(INDEX(Inputs!$K$5:$AJ$160,0,MATCH(S$2,Inputs!$K$4:$AJ$4,0))))+SUMPRODUCT((Inputs!$E$5:$E$160=$B4)*ISNUMBER(INDEX(Inputs!$K$5:$AJ$160,0,MATCH(S$2,Inputs!$K$4:$AJ$4,0))))=0,NA(),SUMPRODUCT((Inputs!$A$5:$A$160=$B4)*Inputs!$B$5:$B$160*(((Inputs!$G$5:$G$160="moeda")+(Inputs!$G$5:$G$160="acoes"))*Inputs!$B$1+((Inputs!$G$5:$G$160<>"moeda")*(Inputs!$G$5:$G$160<>"acoes")))*INDEX(Inputs!$K$5:$AJ$160,0,MATCH(S$2,Inputs!$K$4:$AJ$4,0)))+SUMPRODUCT((Inputs!$C$5:$C$160=$B4)*Inputs!$D$5:$D$160*(((Inputs!$G$5:$G$160="moeda")+(Inputs!$G$5:$G$160="acoes"))*Inputs!$B$1+((Inputs!$G$5:$G$160<>"moeda")*(Inputs!$G$5:$G$160<>"acoes")))*INDEX(Inputs!$K$5:$AJ$160,0,MATCH(S$2,Inputs!$K$4:$AJ$4,0)))+SUMPRODUCT((Inputs!$E$5:$E$160=$B4)*Inputs!$F$5:$F$160*(((Inputs!$G$5:$G$160="moeda")+(Inputs!$G$5:$G$160="acoes"))*Inputs!$B$1+((Inputs!$G$5:$G$160<>"moeda")*(Inputs!$G$5:$G$160<>"acoes")))*INDEX(Inputs!$K$5:$AJ$160,0,MATCH(S$2,Inputs!$K$4:$AJ$4,0))))) -> 1904.4485 | T4: =IF(ISNA(MATCH(T$2,Inputs!$K$4:$AJ$4,0)),NA(),IF(SUMPRODUCT((Inputs!$A$5:$A$160=$B4)*ISNUMBER(INDEX(Inputs!$K$5:$AJ$160,0,MATCH(T$2,Inputs!$K$4:$AJ$4,0))))+SUMPRODUCT((Inputs!$C$5:$C$160=$B4)*ISNUMBER(INDEX(Inputs!$K$5:$AJ$160,0,MATCH(T$2,Inputs!$K$4:$AJ$4,0))))+SUMPRODUCT((Inputs!$E$5:$E$160=$B4)*ISNUMBER(INDEX(Inputs!$K$5:$AJ$160,0,MATCH(T$2,Inputs!$K$4:$AJ$4,0))))=0,NA(),SUMPRODUCT((Inputs!$A$5:$A$160=$B4)*Inputs!$B$5:$B$160*(((Inputs!$G$5:$G$160="moeda")+(Inputs!$G$5:$G$160="acoes"))*Inputs!$B$1+((Inputs!$G$5:$G$160<>"moeda")*(Inputs!$G$5:$G$160<>"acoes")))*INDEX(Inputs!$K$5:$AJ$160,0,MATCH(T$2,Inputs!$K$4:$AJ$4,0)))+SUMPRODUCT((Inputs!$C$5:$C$160=$B4)*Inputs!$D$5:$D$160*(((Inputs!$G$5:$G$160="moeda")+(Inputs!$G$5:$G$160="acoes"))*Inputs!$B$1+((Inputs!$G$5:$G$160<>"moeda")*(Inputs!$G$5:$G$160<>"acoes")))*INDEX(Inputs!$K$5:$AJ$160,0,MATCH(T$2,Inputs!$K$4:$AJ$4,0)))+SUMPRODUCT((Inputs!$E$5:$E$160=$B4)*Inputs!$F$5:$F$160*(((Inputs!$G$5:$G$160="moeda")+(Inputs!$G$5:$G$160="acoes"))*Inputs!$B$1+((Inputs!$G$5:$G$160<>"moeda")*(Inputs!$G$5:$G$160<>"acoes")))*INDEX(Inputs!$K$5:$AJ$160,0,MATCH(T$2,Inputs!$K$4:$AJ$4,0))))) -> 1978.202 | U4: =IF(ISNA(MATCH(U$2,Inputs!$K$4:$AJ$4,0)),NA(),IF(SUMPRODUCT((Inputs!$A$5:$A$160=$B4)*ISNUMBER(INDEX(Inputs!$K$5:$AJ$160,0,MATCH(U$2,Inputs!$K$4:$AJ$4,0))))+SUMPRODUCT((Inputs!$C$5:$C$160=$B4)*ISNUMBER(INDEX(Inputs!$K$5:$AJ$160,0,MATCH(U$2,Inputs!$K$4:$AJ$4,0))))+SUMPRODUCT((Inputs!$E$5:$E$160=$B4)*ISNUMBER(INDEX(Inputs!$K$5:$AJ$160,0,MATCH(U$2,Inputs!$K$4:$AJ$4,0))))=0,NA(),SUMPRODUCT((Inputs!$A$5:$A$160=$B4)*Inputs!$B$5:$B$160*(((Inputs!$G$5:$G$160="moeda")+(Inputs!$G$5:$G$160="acoes"))*Inputs!$B$1+((Inputs!$G$5:$G$160<>"moeda")*(Inputs!$G$5:$G$160<>"acoes")))*INDEX(Inputs!$K$5:$AJ$160,0,MATCH(U$2,Inputs!$K$4:$AJ$4,0)))+SUMPRODUCT((Inputs!$C$5:$C$160=$B4)*Inputs!$D$5:$D$160*(((Inputs!$G$5:$G$160="moeda")+(Inputs!$G$5:$G$160="acoes"))*Inputs!$B$1+((Inputs!$G$5:$G$160<>"moeda")*(Inputs!$G$5:$G$160<>"acoes")))*INDEX(Inputs!$K$5:$AJ$160,0,MATCH(U$2,Inputs!$K$4:$AJ$4,0)))+SUMPRODUCT((Inputs!$E$5:$E$160=$B4)*Inputs!$F$5:$F$160*(((Inputs!$G$5:$G$160="moeda")+(Inputs!$G$5:$G$160="acoes"))*Inputs!$B$1+((Inputs!$G$5:$G$160<>"moeda")*(Inputs!$G$5:$G$160<>"acoes")))*INDEX(Inputs!$K$5:$AJ$160,0,MATCH(U$2,Inputs!$K$4:$AJ$4,0))))) -> 1962.6715 | V4: =IF(ISNA(MATCH(V$2,Inputs!$K$4:$AJ$4,0)),NA(),IF(SUMPRODUCT((Inputs!$A$5:$A$160=$B4)*ISNUMBER(INDEX(Inputs!$K$5:$AJ$160,0,MATCH(V$2,Inputs!$K$4:$AJ$4,0))))+SUMPRODUCT((Inputs!$C$5:$C$160=$B4)*ISNUMBER(INDEX(Inputs!$K$5:$AJ$160,0,MATCH(V$2,Inputs!$K$4:$AJ$4,0))))+SUMPRODUCT((Inputs!$E$5:$E$160=$B4)*ISNUMBER(INDEX(Inputs!$K$5:$AJ$160,0,MATCH(V$2,Inputs!$K$4:$AJ$4,0))))=0,NA(),SUMPRODUCT((Inputs!$A$5:$A$160=$B4)*Inputs!$B$5:$B$160*(((Inputs!$G$5:$G$160="moeda")+(Inputs!$G$5:$G$160="acoes"))*Inputs!$B$1+((Inputs!$G$5:$G$160<>"moeda")*(Inputs!$G$5:$G$160<>"acoes")))*INDEX(Inputs!$K$5:$AJ$160,0,MATCH(V$2,Inputs!$K$4:$AJ$4,0)))+SUMPRODUCT((Inputs!$C$5:$C$160=$B4)*Inputs!$D$5:$D$160*(((Inputs!$G$5:$G$160="moeda")+(Inputs!$G$5:$G$160="acoes"))*Inputs!$B$1+((Inputs!$G$5:$G$160<>"moeda")*(Inputs!$G$5:$G$160<>"acoes")))*INDEX(Inputs!$K$5:$AJ$160,0,MATCH(V$2,Inputs!$K$4:$AJ$4,0)))+SUMPRODUCT((Inputs!$E$5:$E$160=$B4)*Inputs!$F$5:$F$160*(((Inputs!$G$5:$G$160="moeda")+(Inputs!$G$5:$G$160="acoes"))*Inputs!$B$1+((Inputs!$G$5:$G$160<>"moeda")*(Inputs!$G$5:$G$160<>"acoes")))*INDEX(Inputs!$K$5:$AJ$160,0,MATCH(V$2,Inputs!$K$4:$AJ$4,0))))) -> 1839.337 | W4: =SUM(S4:V4) -> 7684.659 | X4: =IF(ISNA(MATCH(X$2,Inputs!$K$4:$AJ$4,0)),NA(),IF(SUMPRODUCT((Inputs!$A$5:$A$160=$B4)*ISNUMBER(INDEX(Inputs!$K$5:$AJ$160,0,MATCH(X$2,Inputs!$K$4:$AJ$4,0))))+SUMPRODUCT((Inputs!$C$5:$C$160=$B4)*ISNUMBER(INDEX(Inputs!$K$5:$AJ$160,0,MATCH(X$2,Inputs!$K$4:$AJ$4,0))))+SUMPRODUCT((Inputs!$E$5:$E$160=$B4)*ISNUMBER(INDEX(Inputs!$K$5:$AJ$160,0,MATCH(X$2,Inputs!$K$4:$AJ$4,0))))=0,NA(),SUMPRODUCT((Inputs!$A$5:$A$160=$B4)*Inputs!$B$5:$B$160*(((Inputs!$G$5:$G$160="moeda")+(Inputs!$G$5:$G$160="acoes"))*Inputs!$B$1+((Inputs!$G$5:$G$160<>"moeda")*(Inputs!$G$5:$G$160<>"acoes")))*INDEX(Inputs!$K$5:$AJ$160,0,MATCH(X$2,Inputs!$K$4:$AJ$4,0)))+SUMPRODUCT((Inputs!$C$5:$C$160=$B4)*Inputs!$D$5:$D$160*(((Inputs!$G$5:$G$160="moeda")+(Inputs!$G$5:$G$160="acoes"))*Inputs!$B$1+((Inputs!$G$5:$G$160<>"moeda")*(Inputs!$G$5:$G$160<>"acoes")))*INDEX(Inputs!$K$5:$AJ$160,0,MATCH(X$2,Inputs!$K$4:$AJ$4,0)))+SUMPRODUCT((Inputs!$E$5:$E$160=$B4)*Inputs!$F$5:$F$160*(((Inputs!$G$5:$G$160="moeda")+(Inputs!$G$5:$G$160="acoes"))*Inputs!$B$1+((Inputs!$G$5:$G$160<>"moeda")*(Inputs!$G$5:$G$160<>"acoes")))*INDEX(Inputs!$K$5:$AJ$160,0,MATCH(X$2,Inputs!$K$4:$AJ$4,0))))) -> 2015.074 | Y4: =IF(ISNA(MATCH(Y$2,Inputs!$K$4:$AJ$4,0)),NA(),IF(SUMPRODUCT((Inputs!$A$5:$A$160=$B4)*ISNUMBER(INDEX(Inputs!$K$5:$AJ$160,0,MATCH(Y$2,Inputs!$K$4:$AJ$4,0))))+SUMPRODUCT((Inputs!$C$5:$C$160=$B4)*ISNUMBER(INDEX(Inputs!$K$5:$AJ$160,0,MATCH(Y$2,Inputs!$K$4:$AJ$4,0))))+SUMPRODUCT((Inputs!$E$5:$E$160=$B4)*ISNUMBER(INDEX(Inputs!$K$5:$AJ$160,0,MATCH(Y$2,Inputs!$K$4:$AJ$4,0))))=0,NA(),SUMPRODUCT((Inputs!$A$5:$A$160=$B4)*Inputs!$B$5:$B$160*(((Inputs!$G$5:$G$160="moeda")+(Inputs!$G$5:$G$160="acoes"))*Inputs!$B$1+((Inputs!$G$5:$G$160<>"moeda")*(Inputs!$G$5:$G$160<>"acoes")))*INDEX(Inputs!$K$5:$AJ$160,0,MATCH(Y$2,Inputs!$K$4:$AJ$4,0)))+SUMPRODUCT((Inputs!$C$5:$C$160=$B4)*Inputs!$D$5:$D$160*(((Inputs!$G$5:$G$160="moeda")+(Inputs!$G$5:$G$160="acoes"))*Inputs!$B$1+((Inputs!$G$5:$G$160<>"moeda")*(Inputs!$G$5:$G$160<>"acoes")))*INDEX(Inputs!$K$5:$AJ$160,0,MATCH(Y$2,Inputs!$K$4:$AJ$4,0)))+SUMPRODUCT((Inputs!$E$5:$E$160=$B4)*Inputs!$F$5:$F$160*(((Inputs!$G$5:$G$160="moeda")+(Inputs!$G$5:$G$160="acoes"))*Inputs!$B$1+((Inputs!$G$5:$G$160<>"moeda")*(Inputs!$G$5:$G$160<>"acoes")))*INDEX(Inputs!$K$5:$AJ$160,0,MATCH(Y$2,Inputs!$K$4:$AJ$4,0))))) -> 2024.533 | Z4: =IF(ISNA(MATCH(Z$2,Inputs!$K$4:$AJ$4,0)),NA(),IF(SUMPRODUCT((Inputs!$A$5:$A$160=$B4)*ISNUMBER(INDEX(Inputs!$K$5:$AJ$160,0,MATCH(Z$2,Inputs!$K$4:$AJ$4,0))))+SUMPRODUCT((Inputs!$C$5:$C$160=$B4)*ISNUMBER(INDEX(Inputs!$K$5:$AJ$160,0,MATCH(Z$2,Inputs!$K$4:$AJ$4,0))))+SUMPRODUCT((Inputs!$E$5:$E$160=$B4)*ISNUMBER(INDEX(Inputs!$K$5:$AJ$160,0,MATCH(Z$2,Inputs!$K$4:$AJ$4,0))))=0,NA(),SUMPRODUCT((Inputs!$A$5:$A$160=$B4)*Inputs!$B$5:$B$160*(((Inputs!$G$5:$G$160="moeda")+(Inputs!$G$5:$G$160="acoes"))*Inputs!$B$1+((Inputs!$G$5:$G$160<>"moeda")*(Inputs!$G$5:$G$160<>"acoes")))*INDEX(Inputs!$K$5:$AJ$160,0,MATCH(Z$2,Inputs!$K$4:$AJ$4,0)))+SUMPRODUCT((Inputs!$C$5:$C$160=$B4)*Inputs!$D$5:$D$160*(((Inputs!$G$5:$G$160="moeda")+(Inputs!$G$5:$G$160="acoes"))*Inputs!$B$1+((Inputs!$G$5:$G$160<>"moeda")*(Inputs!$G$5:$G$160<>"acoes")))*INDEX(Inputs!$K$5:$AJ$160,0,MATCH(Z$2,Inputs!$K$4:$AJ$4,0)))+SUMPRODUCT((Inputs!$E$5:$E$160=$B4)*Inputs!$F$5:$F$160*(((Inputs!$G$5:$G$160="moeda")+(Inputs!$G$5:$G$160="acoes"))*Inputs!$B$1+((Inputs!$G$5:$G$160<>"moeda")*(Inputs!$G$5:$G$160<>"acoes")))*INDEX(Inputs!$K$5:$AJ$160,0,MATCH(Z$2,Inputs!$K$4:$AJ$4,0))))) -> 2190.9792 | AA4: =IF(ISNA(MATCH(AA$2,Inputs!$K$4:$AJ$4,0)),NA(),IF(SUMPRODUCT((Inputs!$A$5:$A$160=$B4)*ISNUMBER(INDEX(Inputs!$K$5:$AJ$160,0,MATCH(AA$2,Inputs!$K$4:$AJ$4,0))))+SUMPRODUCT((Inputs!$C$5:$C$160=$B4)*ISNUMBER(INDEX(Inputs!$K$5:$AJ$160,0,MATCH(AA$2,Inputs!$K$4:$AJ$4,0))))+SUMPRODUCT((Inputs!$E$5:$E$160=$B4)*ISNUMBER(INDEX(Inputs!$K$5:$AJ$160,0,MATCH(AA$2,Inputs!$K$4:$AJ$4,0))))=0,NA(),SUMPRODUCT((Inputs!$A$5:$A$160=$B4)*Inputs!$B$5:$B$160*(((Inputs!$G$5:$G$160="moeda")+(Inputs!$G$5:$G$160="acoes"))*Inputs!$B$1+((Inputs!$G$5:$G$160<>"moeda")*(Inputs!$G$5:$G$160<>"acoes")))*INDEX(Inputs!$K$5:$AJ$160,0,MATCH(AA$2,Inputs!$K$4:$AJ$4,0)))+SUMPRODUCT((Inputs!$C$5:$C$160=$B4)*Inputs!$D$5:$D$160*(((Inputs!$G$5:$G$160="moeda")+(Inputs!$G$5:$G$160="acoes"))*Inputs!$B$1+((Inputs!$G$5:$G$160<>"moeda")*(Inputs!$G$5:$G$160<>"acoes")))*INDEX(Inputs!$K$5:$AJ$160,0,MATCH(AA$2,Inputs!$K$4:$AJ$4,0)))+SUMPRODUCT((Inputs!$E$5:$E$160=$B4)*Inputs!$F$5:$F$160*(((Inputs!$G$5:$G$160="moeda")+(Inputs!$G$5:$G$160="acoes"))*Inputs!$B$1+((Inputs!$G$5:$G$160<>"moeda")*(Inputs!$G$5:$G$160<>"acoes")))*INDEX(Inputs!$K$5:$AJ$160,0,MATCH(AA$2,Inputs!$K$4:$AJ$4,0))))) -> 2060.5953 | AB4: =SUM(X4:AA4) -> 8291.1815 | AC4: =IF(ISNA(MATCH(AC$2,Inputs!$K$4:$AJ$4,0)),NA(),IF(SUMPRODUCT((Inputs!$A$5:$A$160=$B4)*ISNUMBER(INDEX(Inputs!$K$5:$AJ$160,0,MATCH(AC$2,Inputs!$K$4:$AJ$4,0))))+SUMPRODUCT((Inputs!$C$5:$C$160=$B4)*ISNUMBER(INDEX(Inputs!$K$5:$AJ$160,0,MATCH(AC$2,Inputs!$K$4:$AJ$4,0))))+SUMPRODUCT((Inputs!$E$5:$E$160=$B4)*ISNUMBER(INDEX(Inputs!$K$5:$AJ$160,0,MATCH(AC$2,Inputs!$K$4:$AJ$4,0))))=0,NA(),SUMPRODUCT((Inputs!$A$5:$A$160=$B4)*Inputs!$B$5:$B$160*(((Inputs!$G$5:$G$160="moeda")+(Inputs!$G$5:$G$160="acoes"))*Inputs!$B$1+((Inputs!$G$5:$G$160<>"moeda")*(Inputs!$G$5:$G$160<>"acoes")))*INDEX(Inputs!$K$5:$AJ$160,0,MATCH(AC$2,Inputs!$K$4:$AJ$4,0)))+SUMPRODUCT((Inputs!$C$5:$C$160=$B4)*Inputs!$D$5:$D$160*(((Inputs!$G$5:$G$160="moeda")+(Inputs!$G$5:$G$160="acoes"))*Inputs!$B$1+((Inputs!$G$5:$G$160<>"moeda")*(Inputs!$G$5:$G$160<>"acoes")))*INDEX(Inputs!$K$5:$AJ$160,0,MATCH(AC$2,Inputs!$K$4:$AJ$4,0)))+SUMPRODUCT((Inputs!$E$5:$E$160=$B4)*Inputs!$F$5:$F$160*(((Inputs!$G$5:$G$160="moeda")+(Inputs!$G$5:$G$160="acoes"))*Inputs!$B$1+((Inputs!$G$5:$G$160<>"moeda")*(Inputs!$G$5:$G$160<>"acoes")))*INDEX(Inputs!$K$5:$AJ$160,0,MATCH(AC$2,Inputs!$K$4:$AJ$4,0))))) -> 2223.1178 | AD4: =IF(ISNA(MATCH(AD$2,Inputs!$K$4:$AJ$4,0)),NA(),IF(SUMPRODUCT((Inputs!$A$5:$A$160=$B4)*ISNUMBER(INDEX(Inputs!$K$5:$AJ$160,0,MATCH(AD$2,Inputs!$K$4:$AJ$4,0))))+SUMPRODUCT((Inputs!$C$5:$C$160=$B4)*ISNUMBER(INDEX(Inputs!$K$5:$AJ$160,0,MATCH(AD$2,Inputs!$K$4:$AJ$4,0))))+SUMPRODUCT((Inputs!$E$5:$E$160=$B4)*ISNUMBER(INDEX(Inputs!$K$5:$AJ$160,0,MATCH(AD$2,Inputs!$K$4:$AJ$4,0))))=0,NA(),SUMPRODUCT((Inputs!$A$5:$A$160=$B4)*Inputs!$B$5:$B$160*(((Inputs!$G$5:$G$160="moeda")+(Inputs!$G$5:$G$160="acoes"))*Inputs!$B$1+((Inputs!$G$5:$G$160<>"moeda")*(Inputs!$G$5:$G$160<>"acoes")))*INDEX(Inputs!$K$5:$AJ$160,0,MATCH(AD$2,Inputs!$K$4:$AJ$4,0)))+SUMPRODUCT((Inputs!$C$5:$C$160=$B4)*Inputs!$D$5:$D$160*(((Inputs!$G$5:$G$160="moeda")+(Inputs!$G$5:$G$160="acoes"))*Inputs!$B$1+((Inputs!$G$5:$G$160<>"moeda")*(Inputs!$G$5:$G$160<>"acoes")))*INDEX(Inputs!$K$5:$AJ$160,0,MATCH(AD$2,Inputs!$K$4:$AJ$4,0)))+SUMPRODUCT((Inputs!$E$5:$E$160=$B4)*Inputs!$F$5:$F$160*(((Inputs!$G$5:$G$160="moeda")+(Inputs!$G$5:$G$160="acoes"))*Inputs!$B$1+((Inputs!$G$5:$G$160<>"moeda")*(Inputs!$G$5:$G$160<>"acoes")))*INDEX(Inputs!$K$5:$AJ$160,0,MATCH(AD$2,Inputs!$K$4:$AJ$4,0))))) -> 2316.6537 | AE4: =IF(ISNA(MATCH(AE$2,Inputs!$K$4:$AJ$4,0)),NA(),IF(SUMPRODUCT((Inputs!$A$5:$A$160=$B4)*ISNUMBER(INDEX(Inputs!$K$5:$AJ$160,0,MATCH(AE$2,Inputs!$K$4:$AJ$4,0))))+SUMPRODUCT((Inputs!$C$5:$C$160=$B4)*ISNUMBER(INDEX(Inputs!$K$5:$AJ$160,0,MATCH(AE$2,Inputs!$K$4:$AJ$4,0))))+SUMPRODUCT((Inputs!$E$5:$E$160=$B4)*ISNUMBER(INDEX(Inputs!$K$5:$AJ$160,0,MATCH(AE$2,Inputs!$K$4:$AJ$4,0))))=0,NA(),SUMPRODUCT((Inputs!$A$5:$A$160=$B4)*Inputs!$B$5:$B$160*(((Inputs!$G$5:$G$160="moeda")+(Inputs!$G$5:$G$160="acoes"))*Inputs!$B$1+((Inputs!$G$5:$G$160<>"moeda")*(Inputs!$G$5:$G$160<>"acoes")))*INDEX(Inputs!$K$5:$AJ$160,0,MATCH(AE$2,Inputs!$K$4:$AJ$4,0)))+SUMPRODUCT((Inputs!$C$5:$C$160=$B4)*Inputs!$D$5:$D$160*(((Inputs!$G$5:$G$160="moeda")+(Inputs!$G$5:$G$160="acoes"))*Inputs!$B$1+((Inputs!$G$5:$G$160<>"moeda")*(Inputs!$G$5:$G$160<>"acoes")))*INDEX(Inputs!$K$5:$AJ$160,0,MATCH(AE$2,Inputs!$K$4:$AJ$4,0)))+SUMPRODUCT((Inputs!$E$5:$E$160=$B4)*Inputs!$F$5:$F$160*(((Inputs!$G$5:$G$160="moeda")+(Inputs!$G$5:$G$160="acoes"))*Inputs!$B$1+((Inputs!$G$5:$G$160<>"moeda")*(Inputs!$G$5:$G$160<>"acoes")))*INDEX(Inputs!$K$5:$AJ$160,0,MATCH(AE$2,Inputs!$K$4:$AJ$4,0))))) -> #N/A | AF4: =IF(ISNA(MATCH(AF$2,Inputs!$K$4:$AJ$4,0)),NA(),IF(SUMPRODUCT((Inputs!$A$5:$A$160=$B4)*ISNUMBER(INDEX(Inputs!$K$5:$AJ$160,0,MATCH(AF$2,Inputs!$K$4:$AJ$4,0))))+SUMPRODUCT((Inputs!$C$5:$C$160=$B4)*ISNUMBER(INDEX(Inputs!$K$5:$AJ$160,0,MATCH(AF$2,Inputs!$K$4:$AJ$4,0))))+SUMPRODUCT((Inputs!$E$5:$E$160=$B4)*ISNUMBER(INDEX(Inputs!$K$5:$AJ$160,0,MATCH(AF$2,Inputs!$K$4:$AJ$4,0))))=0,NA(),SUMPRODUCT((Inputs!$A$5:$A$160=$B4)*Inputs!$B$5:$B$160*(((Inputs!$G$5:$G$160="moeda")+(Inputs!$G$5:$G$160="acoes"))*Inputs!$B$1+((Inputs!$G$5:$G$160<>"moeda")*(Inputs!$G$5:$G$160<>"acoes")))*INDEX(Inputs!$K$5:$AJ$160,0,MATCH(AF$2,Inputs!$K$4:$AJ$4,0)))+SUMPRODUCT((Inputs!$C$5:$C$160=$B4)*Inputs!$D$5:$D$160*(((Inputs!$G$5:$G$160="moeda")+(Inputs!$G$5:$G$160="acoes"))*Inputs!$B$1+((Inputs!$G$5:$G$160<>"moeda")*(Inputs!$G$5:$G$160<>"acoes")))*INDEX(Inputs!$K$5:$AJ$160,0,MATCH(AF$2,Inputs!$K$4:$AJ$4,0)))+SUMPRODUCT((Inputs!$E$5:$E$160=$B4)*Inputs!$F$5:$F$160*(((Inputs!$G$5:$G$160="moeda")+(Inputs!$G$5:$G$160="acoes"))*Inputs!$B$1+((Inputs!$G$5:$G$160<>"moeda")*(Inputs!$G$5:$G$160<>"acoes")))*INDEX(Inputs!$K$5:$AJ$160,0,MATCH(AF$2,Inputs!$K$4:$AJ$4,0))))) -> #N/A | AG4: =SUM(AC4:AF4) -> #N/A | AH4: =IF(ISNA(MATCH(AH$2,Inputs!$K$4:$AJ$4,0)),NA(),IF(SUMPRODUCT((Inputs!$A$5:$A$160=$B4)*ISNUMBER(INDEX(Inputs!$K$5:$AJ$160,0,MATCH(AH$2,Inputs!$K$4:$AJ$4,0))))+SUMPRODUCT((Inputs!$C$5:$C$160=$B4)*ISNUMBER(INDEX(Inputs!$K$5:$AJ$160,0,MATCH(AH$2,Inputs!$K$4:$AJ$4,0))))+SUMPRODUCT((Inputs!$E$5:$E$160=$B4)*ISNUMBER(INDEX(Inputs!$K$5:$AJ$160,0,MATCH(AH$2,Inputs!$K$4:$AJ$4,0))))=0,NA(),SUMPRODUCT((Inputs!$A$5:$A$160=$B4)*Inputs!$B$5:$B$160*(((Inputs!$G$5:$G$160="moeda")+(Inputs!$G$5:$G$160="acoes"))*Inputs!$B$1+((Inputs!$G$5:$G$160<>"moeda")*(Inputs!$G$5:$G$160<>"acoes")))*INDEX(Inputs!$K$5:$AJ$160,0,MATCH(AH$2,Inputs!$K$4:$AJ$4,0)))+SUMPRODUCT((Inputs!$C$5:$C$160=$B4)*Inputs!$D$5:$D$160*(((Inputs!$G$5:$G$160="moeda")+(Inputs!$G$5:$G$160="acoes"))*Inputs!$B$1+((Inputs!$G$5:$G$160<>"moeda")*(Inputs!$G$5:$G$160<>"acoes")))*INDEX(Inputs!$K$5:$AJ$160,0,MATCH(AH$2,Inputs!$K$4:$AJ$4,0)))+SUMPRODUCT((Inputs!$E$5:$E$160=$B4)*Inputs!$F$5:$F$160*(((Inputs!$G$5:$G$160="moeda")+(Inputs!$G$5:$G$160="acoes"))*Inputs!$B$1+((Inputs!$G$5:$G$160<>"moeda")*(Inputs!$G$5:$G$160<>"acoes")))*INDEX(Inputs!$K$5:$AJ$160,0,MATCH(AH$2,Inputs!$K$4:$AJ$4,0))))) -> 713.93387 | AI4: =IF(ISNA(MATCH(AI$2,Inputs!$K$4:$AJ$4,0)),NA(),IF(SUMPRODUCT((Inputs!$A$5:$A$160=$B4)*ISNUMBER(INDEX(Inputs!$K$5:$AJ$160,0,MATCH(AI$2,Inputs!$K$4:$AJ$4,0))))+SUMPRODUCT((Inputs!$C$5:$C$160=$B4)*ISNUMBER(INDEX(Inputs!$K$5:$AJ$160,0,MATCH(AI$2,Inputs!$K$4:$AJ$4,0))))+SUMPRODUCT((Inputs!$E$5:$E$160=$B4)*ISNUMBER(INDEX(Inputs!$K$5:$AJ$160,0,MATCH(AI$2,Inputs!$K$4:$AJ$4,0))))=0,NA(),SUMPRODUCT((Inputs!$A$5:$A$160=$B4)*Inputs!$B$5:$B$160*(((Inputs!$G$5:$G$160="moeda")+(Inputs!$G$5:$G$160="acoes"))*Inputs!$B$1+((Inputs!$G$5:$G$160<>"moeda")*(Inputs!$G$5:$G$160<>"acoes")))*INDEX(Inputs!$K$5:$AJ$160,0,MATCH(AI$2,Inputs!$K$4:$AJ$4,0)))+SUMPRODUCT((Inputs!$C$5:$C$160=$B4)*Inputs!$D$5:$D$160*(((Inputs!$G$5:$G$160="moeda")+(Inputs!$G$5:$G$160="acoes"))*Inputs!$B$1+((Inputs!$G$5:$G$160<>"moeda")*(Inputs!$G$5:$G$160<>"acoes")))*INDEX(Inputs!$K$5:$AJ$160,0,MATCH(AI$2,Inputs!$K$4:$AJ$4,0)))+SUMPRODUCT((Inputs!$E$5:$E$160=$B4)*Inputs!$F$5:$F$160*(((Inputs!$G$5:$G$160="moeda")+(Inputs!$G$5:$G$160="acoes"))*Inputs!$B$1+((Inputs!$G$5:$G$160<>"moeda")*(Inputs!$G$5:$G$160<>"acoes")))*INDEX(Inputs!$K$5:$AJ$160,0,MATCH(AI$2,Inputs!$K$4:$AJ$4,0))))) -> 454.9439 | AJ4: =IF(ISNA(MATCH(AJ$2,Inputs!$K$4:$AJ$4,0)),NA(),IF(SUMPRODUCT((Inputs!$A$5:$A$160=$B4)*ISNUMBER(INDEX(Inputs!$K$5:$AJ$160,0,MATCH(AJ$2,Inputs!$K$4:$AJ$4,0))))+SUMPRODUCT((Inputs!$C$5:$C$160=$B4)*ISNUMBER(INDEX(Inputs!$K$5:$AJ$160,0,MATCH(AJ$2,Inputs!$K$4:$AJ$4,0))))+SUMPRODUCT((Inputs!$E$5:$E$160=$B4)*ISNUMBER(INDEX(Inputs!$K$5:$AJ$160,0,MATCH(AJ$2,Inputs!$K$4:$AJ$4,0))))=0,NA(),SUMPRODUCT((Inputs!$A$5:$A$160=$B4)*Inputs!$B$5:$B$160*(((Inputs!$G$5:$G$160="moeda")+(Inputs!$G$5:$G$160="acoes"))*Inputs!$B$1+((Inputs!$G$5:$G$160<>"moeda")*(Inputs!$G$5:$G$160<>"acoes")))*INDEX(Inputs!$K$5:$AJ$160,0,MATCH(AJ$2,Inputs!$K$4:$AJ$4,0)))+SUMPRODUCT((Inputs!$C$5:$C$160=$B4)*Inputs!$D$5:$D$160*(((Inputs!$G$5:$G$160="moeda")+(Inputs!$G$5:$G$160="acoes"))*Inputs!$B$1+((Inputs!$G$5:$G$160<>"moeda")*(Inputs!$G$5:$G$160<>"acoes")))*INDEX(Inputs!$K$5:$AJ$160,0,MATCH(AJ$2,Inputs!$K$4:$AJ$4,0)))+SUMPRODUCT((Inputs!$E$5:$E$160=$B4)*Inputs!$F$5:$F$160*(((Inputs!$G$5:$G$160="moeda")+(Inputs!$G$5:$G$160="acoes"))*Inputs!$B$1+((Inputs!$G$5:$G$160<>"moeda")*(Inputs!$G$5:$G$160<>"acoes")))*INDEX(Inputs!$K$5:$AJ$160,0,MATCH(AJ$2,Inputs!$K$4:$AJ$4,0))))) -> 874.58307 | AK4: =IF(ISNA(MATCH(AK$2,Inputs!$K$4:$AJ$4,0)),NA(),IF(SUMPRODUCT((Inputs!$A$5:$A$160=$B4)*ISNUMBER(INDEX(Inputs!$K$5:$AJ$160,0,MATCH(AK$2,Inputs!$K$4:$AJ$4,0))))+SUMPRODUCT((Inputs!$C$5:$C$160=$B4)*ISNUMBER(INDEX(Inputs!$K$5:$AJ$160,0,MATCH(AK$2,Inputs!$K$4:$AJ$4,0))))+SUMPRODUCT((Inputs!$E$5:$E$160=$B4)*ISNUMBER(INDEX(Inputs!$K$5:$AJ$160,0,MATCH(AK$2,Inputs!$K$4:$AJ$4,0))))=0,NA(),SUMPRODUCT((Inputs!$A$5:$A$160=$B4)*Inputs!$B$5:$B$160*(((Inputs!$G$5:$G$160="moeda")+(Inputs!$G$5:$G$160="acoes"))*Inputs!$B$1+((Inputs!$G$5:$G$160<>"moeda")*(Inputs!$G$5:$G$160<>"acoes")))*INDEX(Inputs!$K$5:$AJ$160,0,MATCH(AK$2,Inputs!$K$4:$AJ$4,0)))+SUMPRODUCT((Inputs!$C$5:$C$160=$B4)*Inputs!$D$5:$D$160*(((Inputs!$G$5:$G$160="moeda")+(Inputs!$G$5:$G$160="acoes"))*Inputs!$B$1+((Inputs!$G$5:$G$160<>"moeda")*(Inputs!$G$5:$G$160<>"acoes")))*INDEX(Inputs!$K$5:$AJ$160,0,MATCH(AK$2,Inputs!$K$4:$AJ$4,0)))+SUMPRODUCT((Inputs!$E$5:$E$160=$B4)*Inputs!$F$5:$F$160*(((Inputs!$G$5:$G$160="moeda")+(Inputs!$G$5:$G$160="acoes"))*Inputs!$B$1+((Inputs!$G$5:$G$160<>"moeda")*(Inputs!$G$5:$G$160<>"acoes")))*INDEX(Inputs!$K$5:$AJ$160,0,MATCH(AK$2,Inputs!$K$4:$AJ$4,0))))) -> 928.15474 | AL4: =SUM(AH4:AK4) -> 2971.6156
B5: 2 | C5: COGS (cash) | D5: =IF(ISNA(MATCH(D$2,Inputs!$K$4:$AJ$4,0)),NA(),IF(SUMPRODUCT((Inputs!$A$5:$A$160=$B5)*ISNUMBER(INDEX(Inputs!$K$5:$AJ$160,0,MATCH(D$2,Inputs!$K$4:$AJ$4,0))))+SUMPRODUCT((Inputs!$C$5:$C$160=$B5)*ISNUMBER(INDEX(Inputs!$K$5:$AJ$160,0,MATCH(D$2,Inputs!$K$4:$AJ$4,0))))+SUMPRODUCT((Inputs!$E$5:$E$160=$B5)*ISNUMBER(INDEX(Inputs!$K$5:$AJ$160,0,MATCH(D$2,Inputs!$K$4:$AJ$4,0))))=0,NA(),SUMPRODUCT((Inputs!$A$5:$A$160=$B5)*Inputs!$B$5:$B$160*(((Inputs!$G$5:$G$160="moeda")+(Inputs!$G$5:$G$160="acoes"))*Inputs!$B$1+((Inputs!$G$5:$G$160<>"moeda")*(Inputs!$G$5:$G$160<>"acoes")))*INDEX(Inputs!$K$5:$AJ$160,0,MATCH(D$2,Inputs!$K$4:$AJ$4,0)))+SUMPRODUCT((Inputs!$C$5:$C$160=$B5)*Inputs!$D$5:$D$160*(((Inputs!$G$5:$G$160="moeda")+(Inputs!$G$5:$G$160="acoes"))*Inputs!$B$1+((Inputs!$G$5:$G$160<>"moeda")*(Inputs!$G$5:$G$160<>"acoes")))*INDEX(Inputs!$K$5:$AJ$160,0,MATCH(D$2,Inputs!$K$4:$AJ$4,0)))+SUMPRODUCT((Inputs!$E$5:$E$160=$B5)*Inputs!$F$5:$F$160*(((Inputs!$G$5:$G$160="moeda")+(Inputs!$G$5:$G$160="acoes"))*Inputs!$B$1+((Inputs!$G$5:$G$160<>"moeda")*(Inputs!$G$5:$G$160<>"acoes")))*INDEX(Inputs!$K$5:$AJ$160,0,MATCH(D$2,Inputs!$K$4:$AJ$4,0))))) -> -534.68034 | E5: =IF(ISNA(MATCH(E$2,Inputs!$K$4:$AJ$4,0)),NA(),IF(SUMPRODUCT((Inputs!$A$5:$A$160=$B5)*ISNUMBER(INDEX(Inputs!$K$5:$AJ$160,0,MATCH(E$2,Inputs!$K$4:$AJ$4,0))))+SUMPRODUCT((Inputs!$C$5:$C$160=$B5)*ISNUMBER(INDEX(Inputs!$K$5:$AJ$160,0,MATCH(E$2,Inputs!$K$4:$AJ$4,0))))+SUMPRODUCT((Inputs!$E$5:$E$160=$B5)*ISNUMBER(INDEX(Inputs!$K$5:$AJ$160,0,MATCH(E$2,Inputs!$K$4:$AJ$4,0))))=0,NA(),SUMPRODUCT((Inputs!$A$5:$A$160=$B5)*Inputs!$B$5:$B$160*(((Inputs!$G$5:$G$160="moeda")+(Inputs!$G$5:$G$160="acoes"))*Inputs!$B$1+((Inputs!$G$5:$G$160<>"moeda")*(Inputs!$G$5:$G$160<>"acoes")))*INDEX(Inputs!$K$5:$AJ$160,0,MATCH(E$2,Inputs!$K$4:$AJ$4,0)))+SUMPRODUCT((Inputs!$C$5:$C$160=$B5)*Inputs!$D$5:$D$160*(((Inputs!$G$5:$G$160="moeda")+(Inputs!$G$5:$G$160="acoes"))*Inputs!$B$1+((Inputs!$G$5:$G$160<>"moeda")*(Inputs!$G$5:$G$160<>"acoes")))*INDEX(Inputs!$K$5:$AJ$160,0,MATCH(E$2,Inputs!$K$4:$AJ$4,0)))+SUMPRODUCT((Inputs!$E$5:$E$160=$B5)*Inputs!$F$5:$F$160*(((Inputs!$G$5:$G$160="moeda")+(Inputs!$G$5:$G$160="acoes"))*Inputs!$B$1+((Inputs!$G$5:$G$160<>"moeda")*(Inputs!$G$5:$G$160<>"acoes")))*INDEX(Inputs!$K$5:$AJ$160,0,MATCH(E$2,Inputs!$K$4:$AJ$4,0))))) -> -598.85567 | F5: =IF(ISNA(MATCH(F$2,Inputs!$K$4:$AJ$4,0)),NA(),IF(SUMPRODUCT((Inputs!$A$5:$A$160=$B5)*ISNUMBER(INDEX(Inputs!$K$5:$AJ$160,0,MATCH(F$2,Inputs!$K$4:$AJ$4,0))))+SUMPRODUCT((Inputs!$C$5:$C$160=$B5)*ISNUMBER(INDEX(Inputs!$K$5:$AJ$160,0,MATCH(F$2,Inputs!$K$4:$AJ$4,0))))+SUMPRODUCT((Inputs!$E$5:$E$160=$B5)*ISNUMBER(INDEX(Inputs!$K$5:$AJ$160,0,MATCH(F$2,Inputs!$K$4:$AJ$4,0))))=0,NA(),SUMPRODUCT((Inputs!$A$5:$A$160=$B5)*Inputs!$B$5:$B$160*(((Inputs!$G$5:$G$160="moeda")+(Inputs!$G$5:$G$160="acoes"))*Inputs!$B$1+((Inputs!$G$5:$G$160<>"moeda")*(Inputs!$G$5:$G$160<>"acoes")))*INDEX(Inputs!$K$5:$AJ$160,0,MATCH(F$2,Inputs!$K$4:$AJ$4,0)))+SUMPRODUCT((Inputs!$C$5:$C$160=$B5)*Inputs!$D$5:$D$160*(((Inputs!$G$5:$G$160="moeda")+(Inputs!$G$5:$G$160="acoes"))*Inputs!$B$1+((Inputs!$G$5:$G$160<>"moeda")*(Inputs!$G$5:$G$160<>"acoes")))*INDEX(Inputs!$K$5:$AJ$160,0,MATCH(F$2,Inputs!$K$4:$AJ$4,0)))+SUMPRODUCT((Inputs!$E$5:$E$160=$B5)*Inputs!$F$5:$F$160*(((Inputs!$G$5:$G$160="moeda")+(Inputs!$G$5:$G$160="acoes"))*Inputs!$B$1+((Inputs!$G$5:$G$160<>"moeda")*(Inputs!$G$5:$G$160<>"acoes")))*INDEX(Inputs!$K$5:$AJ$160,0,MATCH(F$2,Inputs!$K$4:$AJ$4,0))))) -> -637.06669 | G5: =IF(ISNA(MATCH(G$2,Inputs!$K$4:$AJ$4,0)),NA(),IF(SUMPRODUCT((Inputs!$A$5:$A$160=$B5)*ISNUMBER(INDEX(Inputs!$K$5:$AJ$160,0,MATCH(G$2,Inputs!$K$4:$AJ$4,0))))+SUMPRODUCT((Inputs!$C$5:$C$160=$B5)*ISNUMBER(INDEX(Inputs!$K$5:$AJ$160,0,MATCH(G$2,Inputs!$K$4:$AJ$4,0))))+SUMPRODUCT((Inputs!$E$5:$E$160=$B5)*ISNUMBER(INDEX(Inputs!$K$5:$AJ$160,0,MATCH(G$2,Inputs!$K$4:$AJ$4,0))))=0,NA(),SUMPRODUCT((Inputs!$A$5:$A$160=$B5)*Inputs!$B$5:$B$160*(((Inputs!$G$5:$G$160="moeda")+(Inputs!$G$5:$G$160="acoes"))*Inputs!$B$1+((Inputs!$G$5:$G$160<>"moeda")*(Inputs!$G$5:$G$160<>"acoes")))*INDEX(Inputs!$K$5:$AJ$160,0,MATCH(G$2,Inputs!$K$4:$AJ$4,0)))+SUMPRODUCT((Inputs!$C$5:$C$160=$B5)*Inputs!$D$5:$D$160*(((Inputs!$G$5:$G$160="moeda")+(Inputs!$G$5:$G$160="acoes"))*Inputs!$B$1+((Inputs!$G$5:$G$160<>"moeda")*(Inputs!$G$5:$G$160<>"acoes")))*INDEX(Inputs!$K$5:$AJ$160,0,MATCH(G$2,Inputs!$K$4:$AJ$4,0)))+SUMPRODUCT((Inputs!$E$5:$E$160=$B5)*Inputs!$F$5:$F$160*(((Inputs!$G$5:$G$160="moeda")+(Inputs!$G$5:$G$160="acoes"))*Inputs!$B$1+((Inputs!$G$5:$G$160<>"moeda")*(Inputs!$G$5:$G$160<>"acoes")))*INDEX(Inputs!$K$5:$AJ$160,0,MATCH(G$2,Inputs!$K$4:$AJ$4,0))))) -> -650.17979 | H5: =SUM(D5:G5) -> -2420.7825 | I5: =IF(ISNA(MATCH(I$2,Inputs!$K$4:$AJ$4,0)),NA(),IF(SUMPRODUCT((Inputs!$A$5:$A$160=$B5)*ISNUMBER(INDEX(Inputs!$K$5:$AJ$160,0,MATCH(I$2,Inputs!$K$4:$AJ$4,0))))+SUMPRODUCT((Inputs!$C$5:$C$160=$B5)*ISNUMBER(INDEX(Inputs!$K$5:$AJ$160,0,MATCH(I$2,Inputs!$K$4:$AJ$4,0))))+SUMPRODUCT((Inputs!$E$5:$E$160=$B5)*ISNUMBER(INDEX(Inputs!$K$5:$AJ$160,0,MATCH(I$2,Inputs!$K$4:$AJ$4,0))))=0,NA(),SUMPRODUCT((Inputs!$A$5:$A$160=$B5)*Inputs!$B$5:$B$160*(((Inputs!$G$5:$G$160="moeda")+(Inputs!$G$5:$G$160="acoes"))*Inputs!$B$1+((Inputs!$G$5:$G$160<>"moeda")*(Inputs!$G$5:$G$160<>"acoes")))*INDEX(Inputs!$K$5:$AJ$160,0,MATCH(I$2,Inputs!$K$4:$AJ$4,0)))+SUMPRODUCT((Inputs!$C$5:$C$160=$B5)*Inputs!$D$5:$D$160*(((Inputs!$G$5:$G$160="moeda")+(Inputs!$G$5:$G$160="acoes"))*Inputs!$B$1+((Inputs!$G$5:$G$160<>"moeda")*(Inputs!$G$5:$G$160<>"acoes")))*INDEX(Inputs!$K$5:$AJ$160,0,MATCH(I$2,Inputs!$K$4:$AJ$4,0)))+SUMPRODUCT((Inputs!$E$5:$E$160=$B5)*Inputs!$F$5:$F$160*(((Inputs!$G$5:$G$160="moeda")+(Inputs!$G$5:$G$160="acoes"))*Inputs!$B$1+((Inputs!$G$5:$G$160<>"moeda")*(Inputs!$G$5:$G$160<>"acoes")))*INDEX(Inputs!$K$5:$AJ$160,0,MATCH(I$2,Inputs!$K$4:$AJ$4,0))))) -> -673.03774 | J5: =IF(ISNA(MATCH(J$2,Inputs!$K$4:$AJ$4,0)),NA(),IF(SUMPRODUCT((Inputs!$A$5:$A$160=$B5)*ISNUMBER(INDEX(Inputs!$K$5:$AJ$160,0,MATCH(J$2,Inputs!$K$4:$AJ$4,0))))+SUMPRODUCT((Inputs!$C$5:$C$160=$B5)*ISNUMBER(INDEX(Inputs!$K$5:$AJ$160,0,MATCH(J$2,Inputs!$K$4:$AJ$4,0))))+SUMPRODUCT((Inputs!$E$5:$E$160=$B5)*ISNUMBER(INDEX(Inputs!$K$5:$AJ$160,0,MATCH(J$2,Inputs!$K$4:$AJ$4,0))))=0,NA(),SUMPRODUCT((Inputs!$A$5:$A$160=$B5)*Inputs!$B$5:$B$160*(((Inputs!$G$5:$G$160="moeda")+(Inputs!$G$5:$G$160="acoes"))*Inputs!$B$1+((Inputs!$G$5:$G$160<>"moeda")*(Inputs!$G$5:$G$160<>"acoes")))*INDEX(Inputs!$K$5:$AJ$160,0,MATCH(J$2,Inputs!$K$4:$AJ$4,0)))+SUMPRODUCT((Inputs!$C$5:$C$160=$B5)*Inputs!$D$5:$D$160*(((Inputs!$G$5:$G$160="moeda")+(Inputs!$G$5:$G$160="acoes"))*Inputs!$B$1+((Inputs!$G$5:$G$160<>"moeda")*(Inputs!$G$5:$G$160<>"acoes")))*INDEX(Inputs!$K$5:$AJ$160,0,MATCH(J$2,Inputs!$K$4:$AJ$4,0)))+SUMPRODUCT((Inputs!$E$5:$E$160=$B5)*Inputs!$F$5:$F$160*(((Inputs!$G$5:$G$160="moeda")+(Inputs!$G$5:$G$160="acoes"))*Inputs!$B$1+((Inputs!$G$5:$G$160<>"moeda")*(Inputs!$G$5:$G$160<>"acoes")))*INDEX(Inputs!$K$5:$AJ$160,0,MATCH(J$2,Inputs!$K$4:$AJ$4,0))))) -> -712.98908 | K5: =IF(ISNA(MATCH(K$2,Inputs!$K$4:$AJ$4,0)),NA(),IF(SUMPRODUCT((Inputs!$A$5:$A$160=$B5)*ISNUMBER(INDEX(Inputs!$K$5:$AJ$160,0,MATCH(K$2,Inputs!$K$4:$AJ$4,0))))+SUMPRODUCT((Inputs!$C$5:$C$160=$B5)*ISNUMBER(INDEX(Inputs!$K$5:$AJ$160,0,MATCH(K$2,Inputs!$K$4:$AJ$4,0))))+SUMPRODUCT((Inputs!$E$5:$E$160=$B5)*ISNUMBER(INDEX(Inputs!$K$5:$AJ$160,0,MATCH(K$2,Inputs!$K$4:$AJ$4,0))))=0,NA(),SUMPRODUCT((Inputs!$A$5:$A$160=$B5)*Inputs!$B$5:$B$160*(((Inputs!$G$5:$G$160="moeda")+(Inputs!$G$5:$G$160="acoes"))*Inputs!$B$1+((Inputs!$G$5:$G$160<>"moeda")*(Inputs!$G$5:$G$160<>"acoes")))*INDEX(Inputs!$K$5:$AJ$160,0,MATCH(K$2,Inputs!$K$4:$AJ$4,0)))+SUMPRODUCT((Inputs!$C$5:$C$160=$B5)*Inputs!$D$5:$D$160*(((Inputs!$G$5:$G$160="moeda")+(Inputs!$G$5:$G$160="acoes"))*Inputs!$B$1+((Inputs!$G$5:$G$160<>"moeda")*(Inputs!$G$5:$G$160<>"acoes")))*INDEX(Inputs!$K$5:$AJ$160,0,MATCH(K$2,Inputs!$K$4:$AJ$4,0)))+SUMPRODUCT((Inputs!$E$5:$E$160=$B5)*Inputs!$F$5:$F$160*(((Inputs!$G$5:$G$160="moeda")+(Inputs!$G$5:$G$160="acoes"))*Inputs!$B$1+((Inputs!$G$5:$G$160<>"moeda")*(Inputs!$G$5:$G$160<>"acoes")))*INDEX(Inputs!$K$5:$AJ$160,0,MATCH(K$2,Inputs!$K$4:$AJ$4,0))))) -> -712.4135 | L5: =IF(ISNA(MATCH(L$2,Inputs!$K$4:$AJ$4,0)),NA(),IF(SUMPRODUCT((Inputs!$A$5:$A$160=$B5)*ISNUMBER(INDEX(Inputs!$K$5:$AJ$160,0,MATCH(L$2,Inputs!$K$4:$AJ$4,0))))+SUMPRODUCT((Inputs!$C$5:$C$160=$B5)*ISNUMBER(INDEX(Inputs!$K$5:$AJ$160,0,MATCH(L$2,Inputs!$K$4:$AJ$4,0))))+SUMPRODUCT((Inputs!$E$5:$E$160=$B5)*ISNUMBER(INDEX(Inputs!$K$5:$AJ$160,0,MATCH(L$2,Inputs!$K$4:$AJ$4,0))))=0,NA(),SUMPRODUCT((Inputs!$A$5:$A$160=$B5)*Inputs!$B$5:$B$160*(((Inputs!$G$5:$G$160="moeda")+(Inputs!$G$5:$G$160="acoes"))*Inputs!$B$1+((Inputs!$G$5:$G$160<>"moeda")*(Inputs!$G$5:$G$160<>"acoes")))*INDEX(Inputs!$K$5:$AJ$160,0,MATCH(L$2,Inputs!$K$4:$AJ$4,0)))+SUMPRODUCT((Inputs!$C$5:$C$160=$B5)*Inputs!$D$5:$D$160*(((Inputs!$G$5:$G$160="moeda")+(Inputs!$G$5:$G$160="acoes"))*Inputs!$B$1+((Inputs!$G$5:$G$160<>"moeda")*(Inputs!$G$5:$G$160<>"acoes")))*INDEX(Inputs!$K$5:$AJ$160,0,MATCH(L$2,Inputs!$K$4:$AJ$4,0)))+SUMPRODUCT((Inputs!$E$5:$E$160=$B5)*Inputs!$F$5:$F$160*(((Inputs!$G$5:$G$160="moeda")+(Inputs!$G$5:$G$160="acoes"))*Inputs!$B$1+((Inputs!$G$5:$G$160<>"moeda")*(Inputs!$G$5:$G$160<>"acoes")))*INDEX(Inputs!$K$5:$AJ$160,0,MATCH(L$2,Inputs!$K$4:$AJ$4,0))))) -> -758.94037 | M5: =SUM(I5:L5) -> -2857.3807 | N5: =IF(ISNA(MATCH(N$2,Inputs!$K$4:$AJ$4,0)),NA(),IF(SUMPRODUCT((Inputs!$A$5:$A$160=$B5)*ISNUMBER(INDEX(Inputs!$K$5:$AJ$160,0,MATCH(N$2,Inputs!$K$4:$AJ$4,0))))+SUMPRODUCT((Inputs!$C$5:$C$160=$B5)*ISNUMBER(INDEX(Inputs!$K$5:$AJ$160,0,MATCH(N$2,Inputs!$K$4:$AJ$4,0))))+SUMPRODUCT((Inputs!$E$5:$E$160=$B5)*ISNUMBER(INDEX(Inputs!$K$5:$AJ$160,0,MATCH(N$2,Inputs!$K$4:$AJ$4,0))))=0,NA(),SUMPRODUCT((Inputs!$A$5:$A$160=$B5)*Inputs!$B$5:$B$160*(((Inputs!$G$5:$G$160="moeda")+(Inputs!$G$5:$G$160="acoes"))*Inputs!$B$1+((Inputs!$G$5:$G$160<>"moeda")*(Inputs!$G$5:$G$160<>"acoes")))*INDEX(Inputs!$K$5:$AJ$160,0,MATCH(N$2,Inputs!$K$4:$AJ$4,0)))+SUMPRODUCT((Inputs!$C$5:$C$160=$B5)*Inputs!$D$5:$D$160*(((Inputs!$G$5:$G$160="moeda")+(Inputs!$G$5:$G$160="acoes"))*Inputs!$B$1+((Inputs!$G$5:$G$160<>"moeda")*(Inputs!$G$5:$G$160<>"acoes")))*INDEX(Inputs!$K$5:$AJ$160,0,MATCH(N$2,Inputs!$K$4:$AJ$4,0)))+SUMPRODUCT((Inputs!$E$5:$E$160=$B5)*Inputs!$F$5:$F$160*(((Inputs!$G$5:$G$160="moeda")+(Inputs!$G$5:$G$160="acoes"))*Inputs!$B$1+((Inputs!$G$5:$G$160<>"moeda")*(Inputs!$G$5:$G$160<>"acoes")))*INDEX(Inputs!$K$5:$AJ$160,0,MATCH(N$2,Inputs!$K$4:$AJ$4,0))))) -> -776.43264 | O5: =IF(ISNA(MATCH(O$2,Inputs!$K$4:$AJ$4,0)),NA(),IF(SUMPRODUCT((Inputs!$A$5:$A$160=$B5)*ISNUMBER(INDEX(Inputs!$K$5:$AJ$160,0,MATCH(O$2,Inputs!$K$4:$AJ$4,0))))+SUMPRODUCT((Inputs!$C$5:$C$160=$B5)*ISNUMBER(INDEX(Inputs!$K$5:$AJ$160,0,MATCH(O$2,Inputs!$K$4:$AJ$4,0))))+SUMPRODUCT((Inputs!$E$5:$E$160=$B5)*ISNUMBER(INDEX(Inputs!$K$5:$AJ$160,0,MATCH(O$2,Inputs!$K$4:$AJ$4,0))))=0,NA(),SUMPRODUCT((Inputs!$A$5:$A$160=$B5)*Inputs!$B$5:$B$160*(((Inputs!$G$5:$G$160="moeda")+(Inputs!$G$5:$G$160="acoes"))*Inputs!$B$1+((Inputs!$G$5:$G$160<>"moeda")*(Inputs!$G$5:$G$160<>"acoes")))*INDEX(Inputs!$K$5:$AJ$160,0,MATCH(O$2,Inputs!$K$4:$AJ$4,0)))+SUMPRODUCT((Inputs!$C$5:$C$160=$B5)*Inputs!$D$5:$D$160*(((Inputs!$G$5:$G$160="moeda")+(Inputs!$G$5:$G$160="acoes"))*Inputs!$B$1+((Inputs!$G$5:$G$160<>"moeda")*(Inputs!$G$5:$G$160<>"acoes")))*INDEX(Inputs!$K$5:$AJ$160,0,MATCH(O$2,Inputs!$K$4:$AJ$4,0)))+SUMPRODUCT((Inputs!$E$5:$E$160=$B5)*Inputs!$F$5:$F$160*(((Inputs!$G$5:$G$160="moeda")+(Inputs!$G$5:$G$160="acoes"))*Inputs!$B$1+((Inputs!$G$5:$G$160<>"moeda")*(Inputs!$G$5:$G$160<>"acoes")))*INDEX(Inputs!$K$5:$AJ$160,0,MATCH(O$2,Inputs!$K$4:$AJ$4,0))))) -> -1075.179 | P5: =IF(ISNA(MATCH(P$2,Inputs!$K$4:$AJ$4,0)),NA(),IF(SUMPRODUCT((Inputs!$A$5:$A$160=$B5)*ISNUMBER(INDEX(Inputs!$K$5:$AJ$160,0,MATCH(P$2,Inputs!$K$4:$AJ$4,0))))+SUMPRODUCT((Inputs!$C$5:$C$160=$B5)*ISNUMBER(INDEX(Inputs!$K$5:$AJ$160,0,MATCH(P$2,Inputs!$K$4:$AJ$4,0))))+SUMPRODUCT((Inputs!$E$5:$E$160=$B5)*ISNUMBER(INDEX(Inputs!$K$5:$AJ$160,0,MATCH(P$2,Inputs!$K$4:$AJ$4,0))))=0,NA(),SUMPRODUCT((Inputs!$A$5:$A$160=$B5)*Inputs!$B$5:$B$160*(((Inputs!$G$5:$G$160="moeda")+(Inputs!$G$5:$G$160="acoes"))*Inputs!$B$1+((Inputs!$G$5:$G$160<>"moeda")*(Inputs!$G$5:$G$160<>"acoes")))*INDEX(Inputs!$K$5:$AJ$160,0,MATCH(P$2,Inputs!$K$4:$AJ$4,0)))+SUMPRODUCT((Inputs!$C$5:$C$160=$B5)*Inputs!$D$5:$D$160*(((Inputs!$G$5:$G$160="moeda")+(Inputs!$G$5:$G$160="acoes"))*Inputs!$B$1+((Inputs!$G$5:$G$160<>"moeda")*(Inputs!$G$5:$G$160<>"acoes")))*INDEX(Inputs!$K$5:$AJ$160,0,MATCH(P$2,Inputs!$K$4:$AJ$4,0)))+SUMPRODUCT((Inputs!$E$5:$E$160=$B5)*Inputs!$F$5:$F$160*(((Inputs!$G$5:$G$160="moeda")+(Inputs!$G$5:$G$160="acoes"))*Inputs!$B$1+((Inputs!$G$5:$G$160<>"moeda")*(Inputs!$G$5:$G$160<>"acoes")))*INDEX(Inputs!$K$5:$AJ$160,0,MATCH(P$2,Inputs!$K$4:$AJ$4,0))))) -> -1198.0676 | Q5: =IF(ISNA(MATCH(Q$2,Inputs!$K$4:$AJ$4,0)),NA(),IF(SUMPRODUCT((Inputs!$A$5:$A$160=$B5)*ISNUMBER(INDEX(Inputs!$K$5:$AJ$160,0,MATCH(Q$2,Inputs!$K$4:$AJ$4,0))))+SUMPRODUCT((Inputs!$C$5:$C$160=$B5)*ISNUMBER(INDEX(Inputs!$K$5:$AJ$160,0,MATCH(Q$2,Inputs!$K$4:$AJ$4,0))))+SUMPRODUCT((Inputs!$E$5:$E$160=$B5)*ISNUMBER(INDEX(Inputs!$K$5:$AJ$160,0,MATCH(Q$2,Inputs!$K$4:$AJ$4,0))))=0,NA(),SUMPRODUCT((Inputs!$A$5:$A$160=$B5)*Inputs!$B$5:$B$160*(((Inputs!$G$5:$G$160="moeda")+(Inputs!$G$5:$G$160="acoes"))*Inputs!$B$1+((Inputs!$G$5:$G$160<>"moeda")*(Inputs!$G$5:$G$160<>"acoes")))*INDEX(Inputs!$K$5:$AJ$160,0,MATCH(Q$2,Inputs!$K$4:$AJ$4,0)))+SUMPRODUCT((Inputs!$C$5:$C$160=$B5)*Inputs!$D$5:$D$160*(((Inputs!$G$5:$G$160="moeda")+(Inputs!$G$5:$G$160="acoes"))*Inputs!$B$1+((Inputs!$G$5:$G$160<>"moeda")*(Inputs!$G$5:$G$160<>"acoes")))*INDEX(Inputs!$K$5:$AJ$160,0,MATCH(Q$2,Inputs!$K$4:$AJ$4,0)))+SUMPRODUCT((Inputs!$E$5:$E$160=$B5)*Inputs!$F$5:$F$160*(((Inputs!$G$5:$G$160="moeda")+(Inputs!$G$5:$G$160="acoes"))*Inputs!$B$1+((Inputs!$G$5:$G$160<>"moeda")*(Inputs!$G$5:$G$160<>"acoes")))*INDEX(Inputs!$K$5:$AJ$160,0,MATCH(Q$2,Inputs!$K$4:$AJ$4,0))))) -> -1157.671 | R5: =SUM(N5:Q5) -> -4207.3502 | S5: =IF(ISNA(MATCH(S$2,Inputs!$K$4:$AJ$4,0)),NA(),IF(SUMPRODUCT((Inputs!$A$5:$A$160=$B5)*ISNUMBER(INDEX(Inputs!$K$5:$AJ$160,0,MATCH(S$2,Inputs!$K$4:$AJ$4,0))))+SUMPRODUCT((Inputs!$C$5:$C$160=$B5)*ISNUMBER(INDEX(Inputs!$K$5:$AJ$160,0,MATCH(S$2,Inputs!$K$4:$AJ$4,0))))+SUMPRODUCT((Inputs!$E$5:$E$160=$B5)*ISNUMBER(INDEX(Inputs!$K$5:$AJ$160,0,MATCH(S$2,Inputs!$K$4:$AJ$4,0))))=0,NA(),SUMPRODUCT((Inputs!$A$5:$A$160=$B5)*Inputs!$B$5:$B$160*(((Inputs!$G$5:$G$160="moeda")+(Inputs!$G$5:$G$160="acoes"))*Inputs!$B$1+((Inputs!$G$5:$G$160<>"moeda")*(Inputs!$G$5:$G$160<>"acoes")))*INDEX(Inputs!$K$5:$AJ$160,0,MATCH(S$2,Inputs!$K$4:$AJ$4,0)))+SUMPRODUCT((Inputs!$C$5:$C$160=$B5)*Inputs!$D$5:$D$160*(((Inputs!$G$5:$G$160="moeda")+(Inputs!$G$5:$G$160="acoes"))*Inputs!$B$1+((Inputs!$G$5:$G$160<>"moeda")*(Inputs!$G$5:$G$160<>"acoes")))*INDEX(Inputs!$K$5:$AJ$160,0,MATCH(S$2,Inputs!$K$4:$AJ$4,0)))+SUMPRODUCT((Inputs!$E$5:$E$160=$B5)*Inputs!$F$5:$F$160*(((Inputs!$G$5:$G$160="moeda")+(Inputs!$G$5:$G$160="acoes"))*Inputs!$B$1+((Inputs!$G$5:$G$160<>"moeda")*(Inputs!$G$5:$G$160<>"acoes")))*INDEX(Inputs!$K$5:$AJ$160,0,MATCH(S$2,Inputs!$K$4:$AJ$4,0))))) -> -1192.092 | T5: =IF(ISNA(MATCH(T$2,Inputs!$K$4:$AJ$4,0)),NA(),IF(SUMPRODUCT((Inputs!$A$5:$A$160=$B5)*ISNUMBER(INDEX(Inputs!$K$5:$AJ$160,0,MATCH(T$2,Inputs!$K$4:$AJ$4,0))))+SUMPRODUCT((Inputs!$C$5:$C$160=$B5)*ISNUMBER(INDEX(Inputs!$K$5:$AJ$160,0,MATCH(T$2,Inputs!$K$4:$AJ$4,0))))+SUMPRODUCT((Inputs!$E$5:$E$160=$B5)*ISNUMBER(INDEX(Inputs!$K$5:$AJ$160,0,MATCH(T$2,Inputs!$K$4:$AJ$4,0))))=0,NA(),SUMPRODUCT((Inputs!$A$5:$A$160=$B5)*Inputs!$B$5:$B$160*(((Inputs!$G$5:$G$160="moeda")+(Inputs!$G$5:$G$160="acoes"))*Inputs!$B$1+((Inputs!$G$5:$G$160<>"moeda")*(Inputs!$G$5:$G$160<>"acoes")))*INDEX(Inputs!$K$5:$AJ$160,0,MATCH(T$2,Inputs!$K$4:$AJ$4,0)))+SUMPRODUCT((Inputs!$C$5:$C$160=$B5)*Inputs!$D$5:$D$160*(((Inputs!$G$5:$G$160="moeda")+(Inputs!$G$5:$G$160="acoes"))*Inputs!$B$1+((Inputs!$G$5:$G$160<>"moeda")*(Inputs!$G$5:$G$160<>"acoes")))*INDEX(Inputs!$K$5:$AJ$160,0,MATCH(T$2,Inputs!$K$4:$AJ$4,0)))+SUMPRODUCT((Inputs!$E$5:$E$160=$B5)*Inputs!$F$5:$F$160*(((Inputs!$G$5:$G$160="moeda")+(Inputs!$G$5:$G$160="acoes"))*Inputs!$B$1+((Inputs!$G$5:$G$160<>"moeda")*(Inputs!$G$5:$G$160<>"acoes")))*INDEX(Inputs!$K$5:$AJ$160,0,MATCH(T$2,Inputs!$K$4:$AJ$4,0))))) -> -1260.839 | U5: =IF(ISNA(MATCH(U$2,Inputs!$K$4:$AJ$4,0)),NA(),IF(SUMPRODUCT((Inputs!$A$5:$A$160=$B5)*ISNUMBER(INDEX(Inputs!$K$5:$AJ$160,0,MATCH(U$2,Inputs!$K$4:$AJ$4,0))))+SUMPRODUCT((Inputs!$C$5:$C$160=$B5)*ISNUMBER(INDEX(Inputs!$K$5:$AJ$160,0,MATCH(U$2,Inputs!$K$4:$AJ$4,0))))+SUMPRODUCT((Inputs!$E$5:$E$160=$B5)*ISNUMBER(INDEX(Inputs!$K$5:$AJ$160,0,MATCH(U$2,Inputs!$K$4:$AJ$4,0))))=0,NA(),SUMPRODUCT((Inputs!$A$5:$A$160=$B5)*Inputs!$B$5:$B$160*(((Inputs!$G$5:$G$160="moeda")+(Inputs!$G$5:$G$160="acoes"))*Inputs!$B$1+((Inputs!$G$5:$G$160<>"moeda")*(Inputs!$G$5:$G$160<>"acoes")))*INDEX(Inputs!$K$5:$AJ$160,0,MATCH(U$2,Inputs!$K$4:$AJ$4,0)))+SUMPRODUCT((Inputs!$C$5:$C$160=$B5)*Inputs!$D$5:$D$160*(((Inputs!$G$5:$G$160="moeda")+(Inputs!$G$5:$G$160="acoes"))*Inputs!$B$1+((Inputs!$G$5:$G$160<>"moeda")*(Inputs!$G$5:$G$160<>"acoes")))*INDEX(Inputs!$K$5:$AJ$160,0,MATCH(U$2,Inputs!$K$4:$AJ$4,0)))+SUMPRODUCT((Inputs!$E$5:$E$160=$B5)*Inputs!$F$5:$F$160*(((Inputs!$G$5:$G$160="moeda")+(Inputs!$G$5:$G$160="acoes"))*Inputs!$B$1+((Inputs!$G$5:$G$160<>"moeda")*(Inputs!$G$5:$G$160<>"acoes")))*INDEX(Inputs!$K$5:$AJ$160,0,MATCH(U$2,Inputs!$K$4:$AJ$4,0))))) -> -1251.884 | V5: =IF(ISNA(MATCH(V$2,Inputs!$K$4:$AJ$4,0)),NA(),IF(SUMPRODUCT((Inputs!$A$5:$A$160=$B5)*ISNUMBER(INDEX(Inputs!$K$5:$AJ$160,0,MATCH(V$2,Inputs!$K$4:$AJ$4,0))))+SUMPRODUCT((Inputs!$C$5:$C$160=$B5)*ISNUMBER(INDEX(Inputs!$K$5:$AJ$160,0,MATCH(V$2,Inputs!$K$4:$AJ$4,0))))+SUMPRODUCT((Inputs!$E$5:$E$160=$B5)*ISNUMBER(INDEX(Inputs!$K$5:$AJ$160,0,MATCH(V$2,Inputs!$K$4:$AJ$4,0))))=0,NA(),SUMPRODUCT((Inputs!$A$5:$A$160=$B5)*Inputs!$B$5:$B$160*(((Inputs!$G$5:$G$160="moeda")+(Inputs!$G$5:$G$160="acoes"))*Inputs!$B$1+((Inputs!$G$5:$G$160<>"moeda")*(Inputs!$G$5:$G$160<>"acoes")))*INDEX(Inputs!$K$5:$AJ$160,0,MATCH(V$2,Inputs!$K$4:$AJ$4,0)))+SUMPRODUCT((Inputs!$C$5:$C$160=$B5)*Inputs!$D$5:$D$160*(((Inputs!$G$5:$G$160="moeda")+(Inputs!$G$5:$G$160="acoes"))*Inputs!$B$1+((Inputs!$G$5:$G$160<>"moeda")*(Inputs!$G$5:$G$160<>"acoes")))*INDEX(Inputs!$K$5:$AJ$160,0,MATCH(V$2,Inputs!$K$4:$AJ$4,0)))+SUMPRODUCT((Inputs!$E$5:$E$160=$B5)*Inputs!$F$5:$F$160*(((Inputs!$G$5:$G$160="moeda")+(Inputs!$G$5:$G$160="acoes"))*Inputs!$B$1+((Inputs!$G$5:$G$160<>"moeda")*(Inputs!$G$5:$G$160<>"acoes")))*INDEX(Inputs!$K$5:$AJ$160,0,MATCH(V$2,Inputs!$K$4:$AJ$4,0))))) -> -1231.388 | W5: =SUM(S5:V5) -> -4936.203 | X5: =IF(ISNA(MATCH(X$2,Inputs!$K$4:$AJ$4,0)),NA(),IF(SUMPRODUCT((Inputs!$A$5:$A$160=$B5)*ISNUMBER(INDEX(Inputs!$K$5:$AJ$160,0,MATCH(X$2,Inputs!$K$4:$AJ$4,0))))+SUMPRODUCT((Inputs!$C$5:$C$160=$B5)*ISNUMBER(INDEX(Inputs!$K$5:$AJ$160,0,MATCH(X$2,Inputs!$K$4:$AJ$4,0))))+SUMPRODUCT((Inputs!$E$5:$E$160=$B5)*ISNUMBER(INDEX(Inputs!$K$5:$AJ$160,0,MATCH(X$2,Inputs!$K$4:$AJ$4,0))))=0,NA(),SUMPRODUCT((Inputs!$A$5:$A$160=$B5)*Inputs!$B$5:$B$160*(((Inputs!$G$5:$G$160="moeda")+(Inputs!$G$5:$G$160="acoes"))*Inputs!$B$1+((Inputs!$G$5:$G$160<>"moeda")*(Inputs!$G$5:$G$160<>"acoes")))*INDEX(Inputs!$K$5:$AJ$160,0,MATCH(X$2,Inputs!$K$4:$AJ$4,0)))+SUMPRODUCT((Inputs!$C$5:$C$160=$B5)*Inputs!$D$5:$D$160*(((Inputs!$G$5:$G$160="moeda")+(Inputs!$G$5:$G$160="acoes"))*Inputs!$B$1+((Inputs!$G$5:$G$160<>"moeda")*(Inputs!$G$5:$G$160<>"acoes")))*INDEX(Inputs!$K$5:$AJ$160,0,MATCH(X$2,Inputs!$K$4:$AJ$4,0)))+SUMPRODUCT((Inputs!$E$5:$E$160=$B5)*Inputs!$F$5:$F$160*(((Inputs!$G$5:$G$160="moeda")+(Inputs!$G$5:$G$160="acoes"))*Inputs!$B$1+((Inputs!$G$5:$G$160<>"moeda")*(Inputs!$G$5:$G$160<>"acoes")))*INDEX(Inputs!$K$5:$AJ$160,0,MATCH(X$2,Inputs!$K$4:$AJ$4,0))))) -> -1282.082 | Y5: =IF(ISNA(MATCH(Y$2,Inputs!$K$4:$AJ$4,0)),NA(),IF(SUMPRODUCT((Inputs!$A$5:$A$160=$B5)*ISNUMBER(INDEX(Inputs!$K$5:$AJ$160,0,MATCH(Y$2,Inputs!$K$4:$AJ$4,0))))+SUMPRODUCT((Inputs!$C$5:$C$160=$B5)*ISNUMBER(INDEX(Inputs!$K$5:$AJ$160,0,MATCH(Y$2,Inputs!$K$4:$AJ$4,0))))+SUMPRODUCT((Inputs!$E$5:$E$160=$B5)*ISNUMBER(INDEX(Inputs!$K$5:$AJ$160,0,MATCH(Y$2,Inputs!$K$4:$AJ$4,0))))=0,NA(),SUMPRODUCT((Inputs!$A$5:$A$160=$B5)*Inputs!$B$5:$B$160*(((Inputs!$G$5:$G$160="moeda")+(Inputs!$G$5:$G$160="acoes"))*Inputs!$B$1+((Inputs!$G$5:$G$160<>"moeda")*(Inputs!$G$5:$G$160<>"acoes")))*INDEX(Inputs!$K$5:$AJ$160,0,MATCH(Y$2,Inputs!$K$4:$AJ$4,0)))+SUMPRODUCT((Inputs!$C$5:$C$160=$B5)*Inputs!$D$5:$D$160*(((Inputs!$G$5:$G$160="moeda")+(Inputs!$G$5:$G$160="acoes"))*Inputs!$B$1+((Inputs!$G$5:$G$160<>"moeda")*(Inputs!$G$5:$G$160<>"acoes")))*INDEX(Inputs!$K$5:$AJ$160,0,MATCH(Y$2,Inputs!$K$4:$AJ$4,0)))+SUMPRODUCT((Inputs!$E$5:$E$160=$B5)*Inputs!$F$5:$F$160*(((Inputs!$G$5:$G$160="moeda")+(Inputs!$G$5:$G$160="acoes"))*Inputs!$B$1+((Inputs!$G$5:$G$160<>"moeda")*(Inputs!$G$5:$G$160<>"acoes")))*INDEX(Inputs!$K$5:$AJ$160,0,MATCH(Y$2,Inputs!$K$4:$AJ$4,0))))) -> -1326.516 | Z5: =IF(ISNA(MATCH(Z$2,Inputs!$K$4:$AJ$4,0)),NA(),IF(SUMPRODUCT((Inputs!$A$5:$A$160=$B5)*ISNUMBER(INDEX(Inputs!$K$5:$AJ$160,0,MATCH(Z$2,Inputs!$K$4:$AJ$4,0))))+SUMPRODUCT((Inputs!$C$5:$C$160=$B5)*ISNUMBER(INDEX(Inputs!$K$5:$AJ$160,0,MATCH(Z$2,Inputs!$K$4:$AJ$4,0))))+SUMPRODUCT((Inputs!$E$5:$E$160=$B5)*ISNUMBER(INDEX(Inputs!$K$5:$AJ$160,0,MATCH(Z$2,Inputs!$K$4:$AJ$4,0))))=0,NA(),SUMPRODUCT((Inputs!$A$5:$A$160=$B5)*Inputs!$B$5:$B$160*(((Inputs!$G$5:$G$160="moeda")+(Inputs!$G$5:$G$160="acoes"))*Inputs!$B$1+((Inputs!$G$5:$G$160<>"moeda")*(Inputs!$G$5:$G$160<>"acoes")))*INDEX(Inputs!$K$5:$AJ$160,0,MATCH(Z$2,Inputs!$K$4:$AJ$4,0)))+SUMPRODUCT((Inputs!$C$5:$C$160=$B5)*Inputs!$D$5:$D$160*(((Inputs!$G$5:$G$160="moeda")+(Inputs!$G$5:$G$160="acoes"))*Inputs!$B$1+((Inputs!$G$5:$G$160<>"moeda")*(Inputs!$G$5:$G$160<>"acoes")))*INDEX(Inputs!$K$5:$AJ$160,0,MATCH(Z$2,Inputs!$K$4:$AJ$4,0)))+SUMPRODUCT((Inputs!$E$5:$E$160=$B5)*Inputs!$F$5:$F$160*(((Inputs!$G$5:$G$160="moeda")+(Inputs!$G$5:$G$160="acoes"))*Inputs!$B$1+((Inputs!$G$5:$G$160<>"moeda")*(Inputs!$G$5:$G$160<>"acoes")))*INDEX(Inputs!$K$5:$AJ$160,0,MATCH(Z$2,Inputs!$K$4:$AJ$4,0))))) -> -1399.705 | AA5: =IF(ISNA(MATCH(AA$2,Inputs!$K$4:$AJ$4,0)),NA(),IF(SUMPRODUCT((Inputs!$A$5:$A$160=$B5)*ISNUMBER(INDEX(Inputs!$K$5:$AJ$160,0,MATCH(AA$2,Inputs!$K$4:$AJ$4,0))))+SUMPRODUCT((Inputs!$C$5:$C$160=$B5)*ISNUMBER(INDEX(Inputs!$K$5:$AJ$160,0,MATCH(AA$2,Inputs!$K$4:$AJ$4,0))))+SUMPRODUCT((Inputs!$E$5:$E$160=$B5)*ISNUMBER(INDEX(Inputs!$K$5:$AJ$160,0,MATCH(AA$2,Inputs!$K$4:$AJ$4,0))))=0,NA(),SUMPRODUCT((Inputs!$A$5:$A$160=$B5)*Inputs!$B$5:$B$160*(((Inputs!$G$5:$G$160="moeda")+(Inputs!$G$5:$G$160="acoes"))*Inputs!$B$1+((Inputs!$G$5:$G$160<>"moeda")*(Inputs!$G$5:$G$160<>"acoes")))*INDEX(Inputs!$K$5:$AJ$160,0,MATCH(AA$2,Inputs!$K$4:$AJ$4,0)))+SUMPRODUCT((Inputs!$C$5:$C$160=$B5)*Inputs!$D$5:$D$160*(((Inputs!$G$5:$G$160="moeda")+(Inputs!$G$5:$G$160="acoes"))*Inputs!$B$1+((Inputs!$G$5:$G$160<>"moeda")*(Inputs!$G$5:$G$160<>"acoes")))*INDEX(Inputs!$K$5:$AJ$160,0,MATCH(AA$2,Inputs!$K$4:$AJ$4,0)))+SUMPRODUCT((Inputs!$E$5:$E$160=$B5)*Inputs!$F$5:$F$160*(((Inputs!$G$5:$G$160="moeda")+(Inputs!$G$5:$G$160="acoes"))*Inputs!$B$1+((Inputs!$G$5:$G$160<>"moeda")*(Inputs!$G$5:$G$160<>"acoes")))*INDEX(Inputs!$K$5:$AJ$160,0,MATCH(AA$2,Inputs!$K$4:$AJ$4,0))))) -> -1394.057 | AB5: =SUM(X5:AA5) -> -5402.36 | AC5: =IF(ISNA(MATCH(AC$2,Inputs!$K$4:$AJ$4,0)),NA(),IF(SUMPRODUCT((Inputs!$A$5:$A$160=$B5)*ISNUMBER(INDEX(Inputs!$K$5:$AJ$160,0,MATCH(AC$2,Inputs!$K$4:$AJ$4,0))))+SUMPRODUCT((Inputs!$C$5:$C$160=$B5)*ISNUMBER(INDEX(Inputs!$K$5:$AJ$160,0,MATCH(AC$2,Inputs!$K$4:$AJ$4,0))))+SUMPRODUCT((Inputs!$E$5:$E$160=$B5)*ISNUMBER(INDEX(Inputs!$K$5:$AJ$160,0,MATCH(AC$2,Inputs!$K$4:$AJ$4,0))))=0,NA(),SUMPRODUCT((Inputs!$A$5:$A$160=$B5)*Inputs!$B$5:$B$160*(((Inputs!$G$5:$G$160="moeda")+(Inputs!$G$5:$G$160="acoes"))*Inputs!$B$1+((Inputs!$G$5:$G$160<>"moeda")*(Inputs!$G$5:$G$160<>"acoes")))*INDEX(Inputs!$K$5:$AJ$160,0,MATCH(AC$2,Inputs!$K$4:$AJ$4,0)))+SUMPRODUCT((Inputs!$C$5:$C$160=$B5)*Inputs!$D$5:$D$160*(((Inputs!$G$5:$G$160="moeda")+(Inputs!$G$5:$G$160="acoes"))*Inputs!$B$1+((Inputs!$G$5:$G$160<>"moeda")*(Inputs!$G$5:$G$160<>"acoes")))*INDEX(Inputs!$K$5:$AJ$160,0,MATCH(AC$2,Inputs!$K$4:$AJ$4,0)))+SUMPRODUCT((Inputs!$E$5:$E$160=$B5)*Inputs!$F$5:$F$160*(((Inputs!$G$5:$G$160="moeda")+(Inputs!$G$5:$G$160="acoes"))*Inputs!$B$1+((Inputs!$G$5:$G$160<>"moeda")*(Inputs!$G$5:$G$160<>"acoes")))*INDEX(Inputs!$K$5:$AJ$160,0,MATCH(AC$2,Inputs!$K$4:$AJ$4,0))))) -> -1417.643 | AD5: =IF(ISNA(MATCH(AD$2,Inputs!$K$4:$AJ$4,0)),NA(),IF(SUMPRODUCT((Inputs!$A$5:$A$160=$B5)*ISNUMBER(INDEX(Inputs!$K$5:$AJ$160,0,MATCH(AD$2,Inputs!$K$4:$AJ$4,0))))+SUMPRODUCT((Inputs!$C$5:$C$160=$B5)*ISNUMBER(INDEX(Inputs!$K$5:$AJ$160,0,MATCH(AD$2,Inputs!$K$4:$AJ$4,0))))+SUMPRODUCT((Inputs!$E$5:$E$160=$B5)*ISNUMBER(INDEX(Inputs!$K$5:$AJ$160,0,MATCH(AD$2,Inputs!$K$4:$AJ$4,0))))=0,NA(),SUMPRODUCT((Inputs!$A$5:$A$160=$B5)*Inputs!$B$5:$B$160*(((Inputs!$G$5:$G$160="moeda")+(Inputs!$G$5:$G$160="acoes"))*Inputs!$B$1+((Inputs!$G$5:$G$160<>"moeda")*(Inputs!$G$5:$G$160<>"acoes")))*INDEX(Inputs!$K$5:$AJ$160,0,MATCH(AD$2,Inputs!$K$4:$AJ$4,0)))+SUMPRODUCT((Inputs!$C$5:$C$160=$B5)*Inputs!$D$5:$D$160*(((Inputs!$G$5:$G$160="moeda")+(Inputs!$G$5:$G$160="acoes"))*Inputs!$B$1+((Inputs!$G$5:$G$160<>"moeda")*(Inputs!$G$5:$G$160<>"acoes")))*INDEX(Inputs!$K$5:$AJ$160,0,MATCH(AD$2,Inputs!$K$4:$AJ$4,0)))+SUMPRODUCT((Inputs!$E$5:$E$160=$B5)*Inputs!$F$5:$F$160*(((Inputs!$G$5:$G$160="moeda")+(Inputs!$G$5:$G$160="acoes"))*Inputs!$B$1+((Inputs!$G$5:$G$160<>"moeda")*(Inputs!$G$5:$G$160<>"acoes")))*INDEX(Inputs!$K$5:$AJ$160,0,MATCH(AD$2,Inputs!$K$4:$AJ$4,0))))) -> -1508.18 | AE5: =IF(ISNA(MATCH(AE$2,Inputs!$K$4:$AJ$4,0)),NA(),IF(SUMPRODUCT((Inputs!$A$5:$A$160=$B5)*ISNUMBER(INDEX(Inputs!$K$5:$AJ$160,0,MATCH(AE$2,Inputs!$K$4:$AJ$4,0))))+SUMPRODUCT((Inputs!$C$5:$C$160=$B5)*ISNUMBER(INDEX(Inputs!$K$5:$AJ$160,0,MATCH(AE$2,Inputs!$K$4:$AJ$4,0))))+SUMPRODUCT((Inputs!$E$5:$E$160=$B5)*ISNUMBER(INDEX(Inputs!$K$5:$AJ$160,0,MATCH(AE$2,Inputs!$K$4:$AJ$4,0))))=0,NA(),SUMPRODUCT((Inputs!$A$5:$A$160=$B5)*Inputs!$B$5:$B$160*(((Inputs!$G$5:$G$160="moeda")+(Inputs!$G$5:$G$160="acoes"))*Inputs!$B$1+((Inputs!$G$5:$G$160<>"moeda")*(Inputs!$G$5:$G$160<>"acoes")))*INDEX(Inputs!$K$5:$AJ$160,0,MATCH(AE$2,Inputs!$K$4:$AJ$4,0)))+SUMPRODUCT((Inputs!$C$5:$C$160=$B5)*Inputs!$D$5:$D$160*(((Inputs!$G$5:$G$160="moeda")+(Inputs!$G$5:$G$160="acoes"))*Inputs!$B$1+((Inputs!$G$5:$G$160<>"moeda")*(Inputs!$G$5:$G$160<>"acoes")))*INDEX(Inputs!$K$5:$AJ$160,0,MATCH(AE$2,Inputs!$K$4:$AJ$4,0)))+SUMPRODUCT((Inputs!$E$5:$E$160=$B5)*Inputs!$F$5:$F$160*(((Inputs!$G$5:$G$160="moeda")+(Inputs!$G$5:$G$160="acoes"))*Inputs!$B$1+((Inputs!$G$5:$G$160<>"moeda")*(Inputs!$G$5:$G$160<>"acoes")))*INDEX(Inputs!$K$5:$AJ$160,0,MATCH(AE$2,Inputs!$K$4:$AJ$4,0))))) -> #N/A | AF5: =IF(ISNA(MATCH(AF$2,Inputs!$K$4:$AJ$4,0)),NA(),IF(SUMPRODUCT((Inputs!$A$5:$A$160=$B5)*ISNUMBER(INDEX(Inputs!$K$5:$AJ$160,0,MATCH(AF$2,Inputs!$K$4:$AJ$4,0))))+SUMPRODUCT((Inputs!$C$5:$C$160=$B5)*ISNUMBER(INDEX(Inputs!$K$5:$AJ$160,0,MATCH(AF$2,Inputs!$K$4:$AJ$4,0))))+SUMPRODUCT((Inputs!$E$5:$E$160=$B5)*ISNUMBER(INDEX(Inputs!$K$5:$AJ$160,0,MATCH(AF$2,Inputs!$K$4:$AJ$4,0))))=0,NA(),SUMPRODUCT((Inputs!$A$5:$A$160=$B5)*Inputs!$B$5:$B$160*(((Inputs!$G$5:$G$160="moeda")+(Inputs!$G$5:$G$160="acoes"))*Inputs!$B$1+((Inputs!$G$5:$G$160<>"moeda")*(Inputs!$G$5:$G$160<>"acoes")))*INDEX(Inputs!$K$5:$AJ$160,0,MATCH(AF$2,Inputs!$K$4:$AJ$4,0)))+SUMPRODUCT((Inputs!$C$5:$C$160=$B5)*Inputs!$D$5:$D$160*(((Inputs!$G$5:$G$160="moeda")+(Inputs!$G$5:$G$160="acoes"))*Inputs!$B$1+((Inputs!$G$5:$G$160<>"moeda")*(Inputs!$G$5:$G$160<>"acoes")))*INDEX(Inputs!$K$5:$AJ$160,0,MATCH(AF$2,Inputs!$K$4:$AJ$4,0)))+SUMPRODUCT((Inputs!$E$5:$E$160=$B5)*Inputs!$F$5:$F$160*(((Inputs!$G$5:$G$160="moeda")+(Inputs!$G$5:$G$160="acoes"))*Inputs!$B$1+((Inputs!$G$5:$G$160<>"moeda")*(Inputs!$G$5:$G$160<>"acoes")))*INDEX(Inputs!$K$5:$AJ$160,0,MATCH(AF$2,Inputs!$K$4:$AJ$4,0))))) -> #N/A | AG5: =SUM(AC5:AF5) -> #N/A | AH5: =IF(ISNA(MATCH(AH$2,Inputs!$K$4:$AJ$4,0)),NA(),IF(SUMPRODUCT((Inputs!$A$5:$A$160=$B5)*ISNUMBER(INDEX(Inputs!$K$5:$AJ$160,0,MATCH(AH$2,Inputs!$K$4:$AJ$4,0))))+SUMPRODUCT((Inputs!$C$5:$C$160=$B5)*ISNUMBER(INDEX(Inputs!$K$5:$AJ$160,0,MATCH(AH$2,Inputs!$K$4:$AJ$4,0))))+SUMPRODUCT((Inputs!$E$5:$E$160=$B5)*ISNUMBER(INDEX(Inputs!$K$5:$AJ$160,0,MATCH(AH$2,Inputs!$K$4:$AJ$4,0))))=0,NA(),SUMPRODUCT((Inputs!$A$5:$A$160=$B5)*Inputs!$B$5:$B$160*(((Inputs!$G$5:$G$160="moeda")+(Inputs!$G$5:$G$160="acoes"))*Inputs!$B$1+((Inputs!$G$5:$G$160<>"moeda")*(Inputs!$G$5:$G$160<>"acoes")))*INDEX(Inputs!$K$5:$AJ$160,0,MATCH(AH$2,Inputs!$K$4:$AJ$4,0)))+SUMPRODUCT((Inputs!$C$5:$C$160=$B5)*Inputs!$D$5:$D$160*(((Inputs!$G$5:$G$160="moeda")+(Inputs!$G$5:$G$160="acoes"))*Inputs!$B$1+((Inputs!$G$5:$G$160<>"moeda")*(Inputs!$G$5:$G$160<>"acoes")))*INDEX(Inputs!$K$5:$AJ$160,0,MATCH(AH$2,Inputs!$K$4:$AJ$4,0)))+SUMPRODUCT((Inputs!$E$5:$E$160=$B5)*Inputs!$F$5:$F$160*(((Inputs!$G$5:$G$160="moeda")+(Inputs!$G$5:$G$160="acoes"))*Inputs!$B$1+((Inputs!$G$5:$G$160<>"moeda")*(Inputs!$G$5:$G$160<>"acoes")))*INDEX(Inputs!$K$5:$AJ$160,0,MATCH(AH$2,Inputs!$K$4:$AJ$4,0))))) -> -454.633 | AI5: =IF(ISNA(MATCH(AI$2,Inputs!$K$4:$AJ$4,0)),NA(),IF(SUMPRODUCT((Inputs!$A$5:$A$160=$B5)*ISNUMBER(INDEX(Inputs!$K$5:$AJ$160,0,MATCH(AI$2,Inputs!$K$4:$AJ$4,0))))+SUMPRODUCT((Inputs!$C$5:$C$160=$B5)*ISNUMBER(INDEX(Inputs!$K$5:$AJ$160,0,MATCH(AI$2,Inputs!$K$4:$AJ$4,0))))+SUMPRODUCT((Inputs!$E$5:$E$160=$B5)*ISNUMBER(INDEX(Inputs!$K$5:$AJ$160,0,MATCH(AI$2,Inputs!$K$4:$AJ$4,0))))=0,NA(),SUMPRODUCT((Inputs!$A$5:$A$160=$B5)*Inputs!$B$5:$B$160*(((Inputs!$G$5:$G$160="moeda")+(Inputs!$G$5:$G$160="acoes"))*Inputs!$B$1+((Inputs!$G$5:$G$160<>"moeda")*(Inputs!$G$5:$G$160<>"acoes")))*INDEX(Inputs!$K$5:$AJ$160,0,MATCH(AI$2,Inputs!$K$4:$AJ$4,0)))+SUMPRODUCT((Inputs!$C$5:$C$160=$B5)*Inputs!$D$5:$D$160*(((Inputs!$G$5:$G$160="moeda")+(Inputs!$G$5:$G$160="acoes"))*Inputs!$B$1+((Inputs!$G$5:$G$160<>"moeda")*(Inputs!$G$5:$G$160<>"acoes")))*INDEX(Inputs!$K$5:$AJ$160,0,MATCH(AI$2,Inputs!$K$4:$AJ$4,0)))+SUMPRODUCT((Inputs!$E$5:$E$160=$B5)*Inputs!$F$5:$F$160*(((Inputs!$G$5:$G$160="moeda")+(Inputs!$G$5:$G$160="acoes"))*Inputs!$B$1+((Inputs!$G$5:$G$160<>"moeda")*(Inputs!$G$5:$G$160<>"acoes")))*INDEX(Inputs!$K$5:$AJ$160,0,MATCH(AI$2,Inputs!$K$4:$AJ$4,0))))) -> -383.28332 | AJ5: =IF(ISNA(MATCH(AJ$2,Inputs!$K$4:$AJ$4,0)),NA(),IF(SUMPRODUCT((Inputs!$A$5:$A$160=$B5)*ISNUMBER(INDEX(Inputs!$K$5:$AJ$160,0,MATCH(AJ$2,Inputs!$K$4:$AJ$4,0))))+SUMPRODUCT((Inputs!$C$5:$C$160=$B5)*ISNUMBER(INDEX(Inputs!$K$5:$AJ$160,0,MATCH(AJ$2,Inputs!$K$4:$AJ$4,0))))+SUMPRODUCT((Inputs!$E$5:$E$160=$B5)*ISNUMBER(INDEX(Inputs!$K$5:$AJ$160,0,MATCH(AJ$2,Inputs!$K$4:$AJ$4,0))))=0,NA(),SUMPRODUCT((Inputs!$A$5:$A$160=$B5)*Inputs!$B$5:$B$160*(((Inputs!$G$5:$G$160="moeda")+(Inputs!$G$5:$G$160="acoes"))*Inputs!$B$1+((Inputs!$G$5:$G$160<>"moeda")*(Inputs!$G$5:$G$160<>"acoes")))*INDEX(Inputs!$K$5:$AJ$160,0,MATCH(AJ$2,Inputs!$K$4:$AJ$4,0)))+SUMPRODUCT((Inputs!$C$5:$C$160=$B5)*Inputs!$D$5:$D$160*(((Inputs!$G$5:$G$160="moeda")+(Inputs!$G$5:$G$160="acoes"))*Inputs!$B$1+((Inputs!$G$5:$G$160<>"moeda")*(Inputs!$G$5:$G$160<>"acoes")))*INDEX(Inputs!$K$5:$AJ$160,0,MATCH(AJ$2,Inputs!$K$4:$AJ$4,0)))+SUMPRODUCT((Inputs!$E$5:$E$160=$B5)*Inputs!$F$5:$F$160*(((Inputs!$G$5:$G$160="moeda")+(Inputs!$G$5:$G$160="acoes"))*Inputs!$B$1+((Inputs!$G$5:$G$160<>"moeda")*(Inputs!$G$5:$G$160<>"acoes")))*INDEX(Inputs!$K$5:$AJ$160,0,MATCH(AJ$2,Inputs!$K$4:$AJ$4,0))))) -> -489.05019 | AK5: =IF(ISNA(MATCH(AK$2,Inputs!$K$4:$AJ$4,0)),NA(),IF(SUMPRODUCT((Inputs!$A$5:$A$160=$B5)*ISNUMBER(INDEX(Inputs!$K$5:$AJ$160,0,MATCH(AK$2,Inputs!$K$4:$AJ$4,0))))+SUMPRODUCT((Inputs!$C$5:$C$160=$B5)*ISNUMBER(INDEX(Inputs!$K$5:$AJ$160,0,MATCH(AK$2,Inputs!$K$4:$AJ$4,0))))+SUMPRODUCT((Inputs!$E$5:$E$160=$B5)*ISNUMBER(INDEX(Inputs!$K$5:$AJ$160,0,MATCH(AK$2,Inputs!$K$4:$AJ$4,0))))=0,NA(),SUMPRODUCT((Inputs!$A$5:$A$160=$B5)*Inputs!$B$5:$B$160*(((Inputs!$G$5:$G$160="moeda")+(Inputs!$G$5:$G$160="acoes"))*Inputs!$B$1+((Inputs!$G$5:$G$160<>"moeda")*(Inputs!$G$5:$G$160<>"acoes")))*INDEX(Inputs!$K$5:$AJ$160,0,MATCH(AK$2,Inputs!$K$4:$AJ$4,0)))+SUMPRODUCT((Inputs!$C$5:$C$160=$B5)*Inputs!$D$5:$D$160*(((Inputs!$G$5:$G$160="moeda")+(Inputs!$G$5:$G$160="acoes"))*Inputs!$B$1+((Inputs!$G$5:$G$160<>"moeda")*(Inputs!$G$5:$G$160<>"acoes")))*INDEX(Inputs!$K$5:$AJ$160,0,MATCH(AK$2,Inputs!$K$4:$AJ$4,0)))+SUMPRODUCT((Inputs!$E$5:$E$160=$B5)*Inputs!$F$5:$F$160*(((Inputs!$G$5:$G$160="moeda")+(Inputs!$G$5:$G$160="acoes"))*Inputs!$B$1+((Inputs!$G$5:$G$160<>"moeda")*(Inputs!$G$5:$G$160<>"acoes")))*INDEX(Inputs!$K$5:$AJ$160,0,MATCH(AK$2,Inputs!$K$4:$AJ$4,0))))) -> -538.5604 | AL5: =SUM(AH5:AK5) -> -1865.5269
B6: 3 | C6: SG&A and Other (cash) | D6: =IF(ISNA(MATCH(D$2,Inputs!$K$4:$AJ$4,0)),NA(),IF(SUMPRODUCT((Inputs!$A$5:$A$160=$B6)*ISNUMBER(INDEX(Inputs!$K$5:$AJ$160,0,MATCH(D$2,Inputs!$K$4:$AJ$4,0))))+SUMPRODUCT((Inputs!$C$5:$C$160=$B6)*ISNUMBER(INDEX(Inputs!$K$5:$AJ$160,0,MATCH(D$2,Inputs!$K$4:$AJ$4,0))))+SUMPRODUCT((Inputs!$E$5:$E$160=$B6)*ISNUMBER(INDEX(Inputs!$K$5:$AJ$160,0,MATCH(D$2,Inputs!$K$4:$AJ$4,0))))=0,NA(),SUMPRODUCT((Inputs!$A$5:$A$160=$B6)*Inputs!$B$5:$B$160*(((Inputs!$G$5:$G$160="moeda")+(Inputs!$G$5:$G$160="acoes"))*Inputs!$B$1+((Inputs!$G$5:$G$160<>"moeda")*(Inputs!$G$5:$G$160<>"acoes")))*INDEX(Inputs!$K$5:$AJ$160,0,MATCH(D$2,Inputs!$K$4:$AJ$4,0)))+SUMPRODUCT((Inputs!$C$5:$C$160=$B6)*Inputs!$D$5:$D$160*(((Inputs!$G$5:$G$160="moeda")+(Inputs!$G$5:$G$160="acoes"))*Inputs!$B$1+((Inputs!$G$5:$G$160<>"moeda")*(Inputs!$G$5:$G$160<>"acoes")))*INDEX(Inputs!$K$5:$AJ$160,0,MATCH(D$2,Inputs!$K$4:$AJ$4,0)))+SUMPRODUCT((Inputs!$E$5:$E$160=$B6)*Inputs!$F$5:$F$160*(((Inputs!$G$5:$G$160="moeda")+(Inputs!$G$5:$G$160="acoes"))*Inputs!$B$1+((Inputs!$G$5:$G$160<>"moeda")*(Inputs!$G$5:$G$160<>"acoes")))*INDEX(Inputs!$K$5:$AJ$160,0,MATCH(D$2,Inputs!$K$4:$AJ$4,0))))) -> -73.595387 | E6: =IF(ISNA(MATCH(E$2,Inputs!$K$4:$AJ$4,0)),NA(),IF(SUMPRODUCT((Inputs!$A$5:$A$160=$B6)*ISNUMBER(INDEX(Inputs!$K$5:$AJ$160,0,MATCH(E$2,Inputs!$K$4:$AJ$4,0))))+SUMPRODUCT((Inputs!$C$5:$C$160=$B6)*ISNUMBER(INDEX(Inputs!$K$5:$AJ$160,0,MATCH(E$2,Inputs!$K$4:$AJ$4,0))))+SUMPRODUCT((Inputs!$E$5:$E$160=$B6)*ISNUMBER(INDEX(Inputs!$K$5:$AJ$160,0,MATCH(E$2,Inputs!$K$4:$AJ$4,0))))=0,NA(),SUMPRODUCT((Inputs!$A$5:$A$160=$B6)*Inputs!$B$5:$B$160*(((Inputs!$G$5:$G$160="moeda")+(Inputs!$G$5:$G$160="acoes"))*Inputs!$B$1+((Inputs!$G$5:$G$160<>"moeda")*(Inputs!$G$5:$G$160<>"acoes")))*INDEX(Inputs!$K$5:$AJ$160,0,MATCH(E$2,Inputs!$K$4:$AJ$4,0)))+SUMPRODUCT((Inputs!$C$5:$C$160=$B6)*Inputs!$D$5:$D$160*(((Inputs!$G$5:$G$160="moeda")+(Inputs!$G$5:$G$160="acoes"))*Inputs!$B$1+((Inputs!$G$5:$G$160<>"moeda")*(Inputs!$G$5:$G$160<>"acoes")))*INDEX(Inputs!$K$5:$AJ$160,0,MATCH(E$2,Inputs!$K$4:$AJ$4,0)))+SUMPRODUCT((Inputs!$E$5:$E$160=$B6)*Inputs!$F$5:$F$160*(((Inputs!$G$5:$G$160="moeda")+(Inputs!$G$5:$G$160="acoes"))*Inputs!$B$1+((Inputs!$G$5:$G$160<>"moeda")*(Inputs!$G$5:$G$160<>"acoes")))*INDEX(Inputs!$K$5:$AJ$160,0,MATCH(E$2,Inputs!$K$4:$AJ$4,0))))) -> -113.47448 | F6: =IF(ISNA(MATCH(F$2,Inputs!$K$4:$AJ$4,0)),NA(),IF(SUMPRODUCT((Inputs!$A$5:$A$160=$B6)*ISNUMBER(INDEX(Inputs!$K$5:$AJ$160,0,MATCH(F$2,Inputs!$K$4:$AJ$4,0))))+SUMPRODUCT((Inputs!$C$5:$C$160=$B6)*ISNUMBER(INDEX(Inputs!$K$5:$AJ$160,0,MATCH(F$2,Inputs!$K$4:$AJ$4,0))))+SUMPRODUCT((Inputs!$E$5:$E$160=$B6)*ISNUMBER(INDEX(Inputs!$K$5:$AJ$160,0,MATCH(F$2,Inputs!$K$4:$AJ$4,0))))=0,NA(),SUMPRODUCT((Inputs!$A$5:$A$160=$B6)*Inputs!$B$5:$B$160*(((Inputs!$G$5:$G$160="moeda")+(Inputs!$G$5:$G$160="acoes"))*Inputs!$B$1+((Inputs!$G$5:$G$160<>"moeda")*(Inputs!$G$5:$G$160<>"acoes")))*INDEX(Inputs!$K$5:$AJ$160,0,MATCH(F$2,Inputs!$K$4:$AJ$4,0)))+SUMPRODUCT((Inputs!$C$5:$C$160=$B6)*Inputs!$D$5:$D$160*(((Inputs!$G$5:$G$160="moeda")+(Inputs!$G$5:$G$160="acoes"))*Inputs!$B$1+((Inputs!$G$5:$G$160<>"moeda")*(Inputs!$G$5:$G$160<>"acoes")))*INDEX(Inputs!$K$5:$AJ$160,0,MATCH(F$2,Inputs!$K$4:$AJ$4,0)))+SUMPRODUCT((Inputs!$E$5:$E$160=$B6)*Inputs!$F$5:$F$160*(((Inputs!$G$5:$G$160="moeda")+(Inputs!$G$5:$G$160="acoes"))*Inputs!$B$1+((Inputs!$G$5:$G$160<>"moeda")*(Inputs!$G$5:$G$160<>"acoes")))*INDEX(Inputs!$K$5:$AJ$160,0,MATCH(F$2,Inputs!$K$4:$AJ$4,0))))) -> -103.21007 | G6: =IF(ISNA(MATCH(G$2,Inputs!$K$4:$AJ$4,0)),NA(),IF(SUMPRODUCT((Inputs!$A$5:$A$160=$B6)*ISNUMBER(INDEX(Inputs!$K$5:$AJ$160,0,MATCH(G$2,Inputs!$K$4:$AJ$4,0))))+SUMPRODUCT((Inputs!$C$5:$C$160=$B6)*ISNUMBER(INDEX(Inputs!$K$5:$AJ$160,0,MATCH(G$2,Inputs!$K$4:$AJ$4,0))))+SUMPRODUCT((Inputs!$E$5:$E$160=$B6)*ISNUMBER(INDEX(Inputs!$K$5:$AJ$160,0,MATCH(G$2,Inputs!$K$4:$AJ$4,0))))=0,NA(),SUMPRODUCT((Inputs!$A$5:$A$160=$B6)*Inputs!$B$5:$B$160*(((Inputs!$G$5:$G$160="moeda")+(Inputs!$G$5:$G$160="acoes"))*Inputs!$B$1+((Inputs!$G$5:$G$160<>"moeda")*(Inputs!$G$5:$G$160<>"acoes")))*INDEX(Inputs!$K$5:$AJ$160,0,MATCH(G$2,Inputs!$K$4:$AJ$4,0)))+SUMPRODUCT((Inputs!$C$5:$C$160=$B6)*Inputs!$D$5:$D$160*(((Inputs!$G$5:$G$160="moeda")+(Inputs!$G$5:$G$160="acoes"))*Inputs!$B$1+((Inputs!$G$5:$G$160<>"moeda")*(Inputs!$G$5:$G$160<>"acoes")))*INDEX(Inputs!$K$5:$AJ$160,0,MATCH(G$2,Inputs!$K$4:$AJ$4,0)))+SUMPRODUCT((Inputs!$E$5:$E$160=$B6)*Inputs!$F$5:$F$160*(((Inputs!$G$5:$G$160="moeda")+(Inputs!$G$5:$G$160="acoes"))*Inputs!$B$1+((Inputs!$G$5:$G$160<>"moeda")*(Inputs!$G$5:$G$160<>"acoes")))*INDEX(Inputs!$K$5:$AJ$160,0,MATCH(G$2,Inputs!$K$4:$AJ$4,0))))) -> -105.59846 | H6: =SUM(D6:G6) -> -395.8784 | I6: =IF(ISNA(MATCH(I$2,Inputs!$K$4:$AJ$4,0)),NA(),IF(SUMPRODUCT((Inputs!$A$5:$A$160=$B6)*ISNUMBER(INDEX(Inputs!$K$5:$AJ$160,0,MATCH(I$2,Inputs!$K$4:$AJ$4,0))))+SUMPRODUCT((Inputs!$C$5:$C$160=$B6)*ISNUMBER(INDEX(Inputs!$K$5:$AJ$160,0,MATCH(I$2,Inputs!$K$4:$AJ$4,0))))+SUMPRODUCT((Inputs!$E$5:$E$160=$B6)*ISNUMBER(INDEX(Inputs!$K$5:$AJ$160,0,MATCH(I$2,Inputs!$K$4:$AJ$4,0))))=0,NA(),SUMPRODUCT((Inputs!$A$5:$A$160=$B6)*Inputs!$B$5:$B$160*(((Inputs!$G$5:$G$160="moeda")+(Inputs!$G$5:$G$160="acoes"))*Inputs!$B$1+((Inputs!$G$5:$G$160<>"moeda")*(Inputs!$G$5:$G$160<>"acoes")))*INDEX(Inputs!$K$5:$AJ$160,0,MATCH(I$2,Inputs!$K$4:$AJ$4,0)))+SUMPRODUCT((Inputs!$C$5:$C$160=$B6)*Inputs!$D$5:$D$160*(((Inputs!$G$5:$G$160="moeda")+(Inputs!$G$5:$G$160="acoes"))*Inputs!$B$1+((Inputs!$G$5:$G$160<>"moeda")*(Inputs!$G$5:$G$160<>"acoes")))*INDEX(Inputs!$K$5:$AJ$160,0,MATCH(I$2,Inputs!$K$4:$AJ$4,0)))+SUMPRODUCT((Inputs!$E$5:$E$160=$B6)*Inputs!$F$5:$F$160*(((Inputs!$G$5:$G$160="moeda")+(Inputs!$G$5:$G$160="acoes"))*Inputs!$B$1+((Inputs!$G$5:$G$160<>"moeda")*(Inputs!$G$5:$G$160<>"acoes")))*INDEX(Inputs!$K$5:$AJ$160,0,MATCH(I$2,Inputs!$K$4:$AJ$4,0))))) -> -90.295498 | J6: =IF(ISNA(MATCH(J$2,Inputs!$K$4:$AJ$4,0)),NA(),IF(SUMPRODUCT((Inputs!$A$5:$A$160=$B6)*ISNUMBER(INDEX(Inputs!$K$5:$AJ$160,0,MATCH(J$2,Inputs!$K$4:$AJ$4,0))))+SUMPRODUCT((Inputs!$C$5:$C$160=$B6)*ISNUMBER(INDEX(Inputs!$K$5:$AJ$160,0,MATCH(J$2,Inputs!$K$4:$AJ$4,0))))+SUMPRODUCT((Inputs!$E$5:$E$160=$B6)*ISNUMBER(INDEX(Inputs!$K$5:$AJ$160,0,MATCH(J$2,Inputs!$K$4:$AJ$4,0))))=0,NA(),SUMPRODUCT((Inputs!$A$5:$A$160=$B6)*Inputs!$B$5:$B$160*(((Inputs!$G$5:$G$160="moeda")+(Inputs!$G$5:$G$160="acoes"))*Inputs!$B$1+((Inputs!$G$5:$G$160<>"moeda")*(Inputs!$G$5:$G$160<>"acoes")))*INDEX(Inputs!$K$5:$AJ$160,0,MATCH(J$2,Inputs!$K$4:$AJ$4,0)))+SUMPRODUCT((Inputs!$C$5:$C$160=$B6)*Inputs!$D$5:$D$160*(((Inputs!$G$5:$G$160="moeda")+(Inputs!$G$5:$G$160="acoes"))*Inputs!$B$1+((Inputs!$G$5:$G$160<>"moeda")*(Inputs!$G$5:$G$160<>"acoes")))*INDEX(Inputs!$K$5:$AJ$160,0,MATCH(J$2,Inputs!$K$4:$AJ$4,0)))+SUMPRODUCT((Inputs!$E$5:$E$160=$B6)*Inputs!$F$5:$F$160*(((Inputs!$G$5:$G$160="moeda")+(Inputs!$G$5:$G$160="acoes"))*Inputs!$B$1+((Inputs!$G$5:$G$160<>"moeda")*(Inputs!$G$5:$G$160<>"acoes")))*INDEX(Inputs!$K$5:$AJ$160,0,MATCH(J$2,Inputs!$K$4:$AJ$4,0))))) -> -100.75198 | K6: =IF(ISNA(MATCH(K$2,Inputs!$K$4:$AJ$4,0)),NA(),IF(SUMPRODUCT((Inputs!$A$5:$A$160=$B6)*ISNUMBER(INDEX(Inputs!$K$5:$AJ$160,0,MATCH(K$2,Inputs!$K$4:$AJ$4,0))))+SUMPRODUCT((Inputs!$C$5:$C$160=$B6)*ISNUMBER(INDEX(Inputs!$K$5:$AJ$160,0,MATCH(K$2,Inputs!$K$4:$AJ$4,0))))+SUMPRODUCT((Inputs!$E$5:$E$160=$B6)*ISNUMBER(INDEX(Inputs!$K$5:$AJ$160,0,MATCH(K$2,Inputs!$K$4:$AJ$4,0))))=0,NA(),SUMPRODUCT((Inputs!$A$5:$A$160=$B6)*Inputs!$B$5:$B$160*(((Inputs!$G$5:$G$160="moeda")+(Inputs!$G$5:$G$160="acoes"))*Inputs!$B$1+((Inputs!$G$5:$G$160<>"moeda")*(Inputs!$G$5:$G$160<>"acoes")))*INDEX(Inputs!$K$5:$AJ$160,0,MATCH(K$2,Inputs!$K$4:$AJ$4,0)))+SUMPRODUCT((Inputs!$C$5:$C$160=$B6)*Inputs!$D$5:$D$160*(((Inputs!$G$5:$G$160="moeda")+(Inputs!$G$5:$G$160="acoes"))*Inputs!$B$1+((Inputs!$G$5:$G$160<>"moeda")*(Inputs!$G$5:$G$160<>"acoes")))*INDEX(Inputs!$K$5:$AJ$160,0,MATCH(K$2,Inputs!$K$4:$AJ$4,0)))+SUMPRODUCT((Inputs!$E$5:$E$160=$B6)*Inputs!$F$5:$F$160*(((Inputs!$G$5:$G$160="moeda")+(Inputs!$G$5:$G$160="acoes"))*Inputs!$B$1+((Inputs!$G$5:$G$160<>"moeda")*(Inputs!$G$5:$G$160<>"acoes")))*INDEX(Inputs!$K$5:$AJ$160,0,MATCH(K$2,Inputs!$K$4:$AJ$4,0))))) -> -101.77672 | L6: =IF(ISNA(MATCH(L$2,Inputs!$K$4:$AJ$4,0)),NA(),IF(SUMPRODUCT((Inputs!$A$5:$A$160=$B6)*ISNUMBER(INDEX(Inputs!$K$5:$AJ$160,0,MATCH(L$2,Inputs!$K$4:$AJ$4,0))))+SUMPRODUCT((Inputs!$C$5:$C$160=$B6)*ISNUMBER(INDEX(Inputs!$K$5:$AJ$160,0,MATCH(L$2,Inputs!$K$4:$AJ$4,0))))+SUMPRODUCT((Inputs!$E$5:$E$160=$B6)*ISNUMBER(INDEX(Inputs!$K$5:$AJ$160,0,MATCH(L$2,Inputs!$K$4:$AJ$4,0))))=0,NA(),SUMPRODUCT((Inputs!$A$5:$A$160=$B6)*Inputs!$B$5:$B$160*(((Inputs!$G$5:$G$160="moeda")+(Inputs!$G$5:$G$160="acoes"))*Inputs!$B$1+((Inputs!$G$5:$G$160<>"moeda")*(Inputs!$G$5:$G$160<>"acoes")))*INDEX(Inputs!$K$5:$AJ$160,0,MATCH(L$2,Inputs!$K$4:$AJ$4,0)))+SUMPRODUCT((Inputs!$C$5:$C$160=$B6)*Inputs!$D$5:$D$160*(((Inputs!$G$5:$G$160="moeda")+(Inputs!$G$5:$G$160="acoes"))*Inputs!$B$1+((Inputs!$G$5:$G$160<>"moeda")*(Inputs!$G$5:$G$160<>"acoes")))*INDEX(Inputs!$K$5:$AJ$160,0,MATCH(L$2,Inputs!$K$4:$AJ$4,0)))+SUMPRODUCT((Inputs!$E$5:$E$160=$B6)*Inputs!$F$5:$F$160*(((Inputs!$G$5:$G$160="moeda")+(Inputs!$G$5:$G$160="acoes"))*Inputs!$B$1+((Inputs!$G$5:$G$160<>"moeda")*(Inputs!$G$5:$G$160<>"acoes")))*INDEX(Inputs!$K$5:$AJ$160,0,MATCH(L$2,Inputs!$K$4:$AJ$4,0))))) -> -123.12782 | M6: =SUM(I6:L6) -> -415.95202 | N6: =IF(ISNA(MATCH(N$2,Inputs!$K$4:$AJ$4,0)),NA(),IF(SUMPRODUCT((Inputs!$A$5:$A$160=$B6)*ISNUMBER(INDEX(Inputs!$K$5:$AJ$160,0,MATCH(N$2,Inputs!$K$4:$AJ$4,0))))+SUMPRODUCT((Inputs!$C$5:$C$160=$B6)*ISNUMBER(INDEX(Inputs!$K$5:$AJ$160,0,MATCH(N$2,Inputs!$K$4:$AJ$4,0))))+SUMPRODUCT((Inputs!$E$5:$E$160=$B6)*ISNUMBER(INDEX(Inputs!$K$5:$AJ$160,0,MATCH(N$2,Inputs!$K$4:$AJ$4,0))))=0,NA(),SUMPRODUCT((Inputs!$A$5:$A$160=$B6)*Inputs!$B$5:$B$160*(((Inputs!$G$5:$G$160="moeda")+(Inputs!$G$5:$G$160="acoes"))*Inputs!$B$1+((Inputs!$G$5:$G$160<>"moeda")*(Inputs!$G$5:$G$160<>"acoes")))*INDEX(Inputs!$K$5:$AJ$160,0,MATCH(N$2,Inputs!$K$4:$AJ$4,0)))+SUMPRODUCT((Inputs!$C$5:$C$160=$B6)*Inputs!$D$5:$D$160*(((Inputs!$G$5:$G$160="moeda")+(Inputs!$G$5:$G$160="acoes"))*Inputs!$B$1+((Inputs!$G$5:$G$160<>"moeda")*(Inputs!$G$5:$G$160<>"acoes")))*INDEX(Inputs!$K$5:$AJ$160,0,MATCH(N$2,Inputs!$K$4:$AJ$4,0)))+SUMPRODUCT((Inputs!$E$5:$E$160=$B6)*Inputs!$F$5:$F$160*(((Inputs!$G$5:$G$160="moeda")+(Inputs!$G$5:$G$160="acoes"))*Inputs!$B$1+((Inputs!$G$5:$G$160<>"moeda")*(Inputs!$G$5:$G$160<>"acoes")))*INDEX(Inputs!$K$5:$AJ$160,0,MATCH(N$2,Inputs!$K$4:$AJ$4,0))))) -> -114.61169 | O6: =IF(ISNA(MATCH(O$2,Inputs!$K$4:$AJ$4,0)),NA(),IF(SUMPRODUCT((Inputs!$A$5:$A$160=$B6)*ISNUMBER(INDEX(Inputs!$K$5:$AJ$160,0,MATCH(O$2,Inputs!$K$4:$AJ$4,0))))+SUMPRODUCT((Inputs!$C$5:$C$160=$B6)*ISNUMBER(INDEX(Inputs!$K$5:$AJ$160,0,MATCH(O$2,Inputs!$K$4:$AJ$4,0))))+SUMPRODUCT((Inputs!$E$5:$E$160=$B6)*ISNUMBER(INDEX(Inputs!$K$5:$AJ$160,0,MATCH(O$2,Inputs!$K$4:$AJ$4,0))))=0,NA(),SUMPRODUCT((Inputs!$A$5:$A$160=$B6)*Inputs!$B$5:$B$160*(((Inputs!$G$5:$G$160="moeda")+(Inputs!$G$5:$G$160="acoes"))*Inputs!$B$1+((Inputs!$G$5:$G$160<>"moeda")*(Inputs!$G$5:$G$160<>"acoes")))*INDEX(Inputs!$K$5:$AJ$160,0,MATCH(O$2,Inputs!$K$4:$AJ$4,0)))+SUMPRODUCT((Inputs!$C$5:$C$160=$B6)*Inputs!$D$5:$D$160*(((Inputs!$G$5:$G$160="moeda")+(Inputs!$G$5:$G$160="acoes"))*Inputs!$B$1+((Inputs!$G$5:$G$160<>"moeda")*(Inputs!$G$5:$G$160<>"acoes")))*INDEX(Inputs!$K$5:$AJ$160,0,MATCH(O$2,Inputs!$K$4:$AJ$4,0)))+SUMPRODUCT((Inputs!$E$5:$E$160=$B6)*Inputs!$F$5:$F$160*(((Inputs!$G$5:$G$160="moeda")+(Inputs!$G$5:$G$160="acoes"))*Inputs!$B$1+((Inputs!$G$5:$G$160<>"moeda")*(Inputs!$G$5:$G$160<>"acoes")))*INDEX(Inputs!$K$5:$AJ$160,0,MATCH(O$2,Inputs!$K$4:$AJ$4,0))))) -> -220.784 | P6: =IF(ISNA(MATCH(P$2,Inputs!$K$4:$AJ$4,0)),NA(),IF(SUMPRODUCT((Inputs!$A$5:$A$160=$B6)*ISNUMBER(INDEX(Inputs!$K$5:$AJ$160,0,MATCH(P$2,Inputs!$K$4:$AJ$4,0))))+SUMPRODUCT((Inputs!$C$5:$C$160=$B6)*ISNUMBER(INDEX(Inputs!$K$5:$AJ$160,0,MATCH(P$2,Inputs!$K$4:$AJ$4,0))))+SUMPRODUCT((Inputs!$E$5:$E$160=$B6)*ISNUMBER(INDEX(Inputs!$K$5:$AJ$160,0,MATCH(P$2,Inputs!$K$4:$AJ$4,0))))=0,NA(),SUMPRODUCT((Inputs!$A$5:$A$160=$B6)*Inputs!$B$5:$B$160*(((Inputs!$G$5:$G$160="moeda")+(Inputs!$G$5:$G$160="acoes"))*Inputs!$B$1+((Inputs!$G$5:$G$160<>"moeda")*(Inputs!$G$5:$G$160<>"acoes")))*INDEX(Inputs!$K$5:$AJ$160,0,MATCH(P$2,Inputs!$K$4:$AJ$4,0)))+SUMPRODUCT((Inputs!$C$5:$C$160=$B6)*Inputs!$D$5:$D$160*(((Inputs!$G$5:$G$160="moeda")+(Inputs!$G$5:$G$160="acoes"))*Inputs!$B$1+((Inputs!$G$5:$G$160<>"moeda")*(Inputs!$G$5:$G$160<>"acoes")))*INDEX(Inputs!$K$5:$AJ$160,0,MATCH(P$2,Inputs!$K$4:$AJ$4,0)))+SUMPRODUCT((Inputs!$E$5:$E$160=$B6)*Inputs!$F$5:$F$160*(((Inputs!$G$5:$G$160="moeda")+(Inputs!$G$5:$G$160="acoes"))*Inputs!$B$1+((Inputs!$G$5:$G$160<>"moeda")*(Inputs!$G$5:$G$160<>"acoes")))*INDEX(Inputs!$K$5:$AJ$160,0,MATCH(P$2,Inputs!$K$4:$AJ$4,0))))) -> -166.013 | Q6: =IF(ISNA(MATCH(Q$2,Inputs!$K$4:$AJ$4,0)),NA(),IF(SUMPRODUCT((Inputs!$A$5:$A$160=$B6)*ISNUMBER(INDEX(Inputs!$K$5:$AJ$160,0,MATCH(Q$2,Inputs!$K$4:$AJ$4,0))))+SUMPRODUCT((Inputs!$C$5:$C$160=$B6)*ISNUMBER(INDEX(Inputs!$K$5:$AJ$160,0,MATCH(Q$2,Inputs!$K$4:$AJ$4,0))))+SUMPRODUCT((Inputs!$E$5:$E$160=$B6)*ISNUMBER(INDEX(Inputs!$K$5:$AJ$160,0,MATCH(Q$2,Inputs!$K$4:$AJ$4,0))))=0,NA(),SUMPRODUCT((Inputs!$A$5:$A$160=$B6)*Inputs!$B$5:$B$160*(((Inputs!$G$5:$G$160="moeda")+(Inputs!$G$5:$G$160="acoes"))*Inputs!$B$1+((Inputs!$G$5:$G$160<>"moeda")*(Inputs!$G$5:$G$160<>"acoes")))*INDEX(Inputs!$K$5:$AJ$160,0,MATCH(Q$2,Inputs!$K$4:$AJ$4,0)))+SUMPRODUCT((Inputs!$C$5:$C$160=$B6)*Inputs!$D$5:$D$160*(((Inputs!$G$5:$G$160="moeda")+(Inputs!$G$5:$G$160="acoes"))*Inputs!$B$1+((Inputs!$G$5:$G$160<>"moeda")*(Inputs!$G$5:$G$160<>"acoes")))*INDEX(Inputs!$K$5:$AJ$160,0,MATCH(Q$2,Inputs!$K$4:$AJ$4,0)))+SUMPRODUCT((Inputs!$E$5:$E$160=$B6)*Inputs!$F$5:$F$160*(((Inputs!$G$5:$G$160="moeda")+(Inputs!$G$5:$G$160="acoes"))*Inputs!$B$1+((Inputs!$G$5:$G$160<>"moeda")*(Inputs!$G$5:$G$160<>"acoes")))*INDEX(Inputs!$K$5:$AJ$160,0,MATCH(Q$2,Inputs!$K$4:$AJ$4,0))))) -> -170.937 | R6: =SUM(N6:Q6) -> -672.34569 | S6: =IF(ISNA(MATCH(S$2,Inputs!$K$4:$AJ$4,0)),NA(),IF(SUMPRODUCT((Inputs!$A$5:$A$160=$B6)*ISNUMBER(INDEX(Inputs!$K$5:$AJ$160,0,MATCH(S$2,Inputs!$K$4:$AJ$4,0))))+SUMPRODUCT((Inputs!$C$5:$C$160=$B6)*ISNUMBER(INDEX(Inputs!$K$5:$AJ$160,0,MATCH(S$2,Inputs!$K$4:$AJ$4,0))))+SUMPRODUCT((Inputs!$E$5:$E$160=$B6)*ISNUMBER(INDEX(Inputs!$K$5:$AJ$160,0,MATCH(S$2,Inputs!$K$4:$AJ$4,0))))=0,NA(),SUMPRODUCT((Inputs!$A$5:$A$160=$B6)*Inputs!$B$5:$B$160*(((Inputs!$G$5:$G$160="moeda")+(Inputs!$G$5:$G$160="acoes"))*Inputs!$B$1+((Inputs!$G$5:$G$160<>"moeda")*(Inputs!$G$5:$G$160<>"acoes")))*INDEX(Inputs!$K$5:$AJ$160,0,MATCH(S$2,Inputs!$K$4:$AJ$4,0)))+SUMPRODUCT((Inputs!$C$5:$C$160=$B6)*Inputs!$D$5:$D$160*(((Inputs!$G$5:$G$160="moeda")+(Inputs!$G$5:$G$160="acoes"))*Inputs!$B$1+((Inputs!$G$5:$G$160<>"moeda")*(Inputs!$G$5:$G$160<>"acoes")))*INDEX(Inputs!$K$5:$AJ$160,0,MATCH(S$2,Inputs!$K$4:$AJ$4,0)))+SUMPRODUCT((Inputs!$E$5:$E$160=$B6)*Inputs!$F$5:$F$160*(((Inputs!$G$5:$G$160="moeda")+(Inputs!$G$5:$G$160="acoes"))*Inputs!$B$1+((Inputs!$G$5:$G$160<>"moeda")*(Inputs!$G$5:$G$160<>"acoes")))*INDEX(Inputs!$K$5:$AJ$160,0,MATCH(S$2,Inputs!$K$4:$AJ$4,0))))) -> -195.223 | T6: =IF(ISNA(MATCH(T$2,Inputs!$K$4:$AJ$4,0)),NA(),IF(SUMPRODUCT((Inputs!$A$5:$A$160=$B6)*ISNUMBER(INDEX(Inputs!$K$5:$AJ$160,0,MATCH(T$2,Inputs!$K$4:$AJ$4,0))))+SUMPRODUCT((Inputs!$C$5:$C$160=$B6)*ISNUMBER(INDEX(Inputs!$K$5:$AJ$160,0,MATCH(T$2,Inputs!$K$4:$AJ$4,0))))+SUMPRODUCT((Inputs!$E$5:$E$160=$B6)*ISNUMBER(INDEX(Inputs!$K$5:$AJ$160,0,MATCH(T$2,Inputs!$K$4:$AJ$4,0))))=0,NA(),SUMPRODUCT((Inputs!$A$5:$A$160=$B6)*Inputs!$B$5:$B$160*(((Inputs!$G$5:$G$160="moeda")+(Inputs!$G$5:$G$160="acoes"))*Inputs!$B$1+((Inputs!$G$5:$G$160<>"moeda")*(Inputs!$G$5:$G$160<>"acoes")))*INDEX(Inputs!$K$5:$AJ$160,0,MATCH(T$2,Inputs!$K$4:$AJ$4,0)))+SUMPRODUCT((Inputs!$C$5:$C$160=$B6)*Inputs!$D$5:$D$160*(((Inputs!$G$5:$G$160="moeda")+(Inputs!$G$5:$G$160="acoes"))*Inputs!$B$1+((Inputs!$G$5:$G$160<>"moeda")*(Inputs!$G$5:$G$160<>"acoes")))*INDEX(Inputs!$K$5:$AJ$160,0,MATCH(T$2,Inputs!$K$4:$AJ$4,0)))+SUMPRODUCT((Inputs!$E$5:$E$160=$B6)*Inputs!$F$5:$F$160*(((Inputs!$G$5:$G$160="moeda")+(Inputs!$G$5:$G$160="acoes"))*Inputs!$B$1+((Inputs!$G$5:$G$160<>"moeda")*(Inputs!$G$5:$G$160<>"acoes")))*INDEX(Inputs!$K$5:$AJ$160,0,MATCH(T$2,Inputs!$K$4:$AJ$4,0))))) -> -195.315 | U6: =IF(ISNA(MATCH(U$2,Inputs!$K$4:$AJ$4,0)),NA(),IF(SUMPRODUCT((Inputs!$A$5:$A$160=$B6)*ISNUMBER(INDEX(Inputs!$K$5:$AJ$160,0,MATCH(U$2,Inputs!$K$4:$AJ$4,0))))+SUMPRODUCT((Inputs!$C$5:$C$160=$B6)*ISNUMBER(INDEX(Inputs!$K$5:$AJ$160,0,MATCH(U$2,Inputs!$K$4:$AJ$4,0))))+SUMPRODUCT((Inputs!$E$5:$E$160=$B6)*ISNUMBER(INDEX(Inputs!$K$5:$AJ$160,0,MATCH(U$2,Inputs!$K$4:$AJ$4,0))))=0,NA(),SUMPRODUCT((Inputs!$A$5:$A$160=$B6)*Inputs!$B$5:$B$160*(((Inputs!$G$5:$G$160="moeda")+(Inputs!$G$5:$G$160="acoes"))*Inputs!$B$1+((Inputs!$G$5:$G$160<>"moeda")*(Inputs!$G$5:$G$160<>"acoes")))*INDEX(Inputs!$K$5:$AJ$160,0,MATCH(U$2,Inputs!$K$4:$AJ$4,0)))+SUMPRODUCT((Inputs!$C$5:$C$160=$B6)*Inputs!$D$5:$D$160*(((Inputs!$G$5:$G$160="moeda")+(Inputs!$G$5:$G$160="acoes"))*Inputs!$B$1+((Inputs!$G$5:$G$160<>"moeda")*(Inputs!$G$5:$G$160<>"acoes")))*INDEX(Inputs!$K$5:$AJ$160,0,MATCH(U$2,Inputs!$K$4:$AJ$4,0)))+SUMPRODUCT((Inputs!$E$5:$E$160=$B6)*Inputs!$F$5:$F$160*(((Inputs!$G$5:$G$160="moeda")+(Inputs!$G$5:$G$160="acoes"))*Inputs!$B$1+((Inputs!$G$5:$G$160<>"moeda")*(Inputs!$G$5:$G$160<>"acoes")))*INDEX(Inputs!$K$5:$AJ$160,0,MATCH(U$2,Inputs!$K$4:$AJ$4,0))))) -> -173.406 | V6: =IF(ISNA(MATCH(V$2,Inputs!$K$4:$AJ$4,0)),NA(),IF(SUMPRODUCT((Inputs!$A$5:$A$160=$B6)*ISNUMBER(INDEX(Inputs!$K$5:$AJ$160,0,MATCH(V$2,Inputs!$K$4:$AJ$4,0))))+SUMPRODUCT((Inputs!$C$5:$C$160=$B6)*ISNUMBER(INDEX(Inputs!$K$5:$AJ$160,0,MATCH(V$2,Inputs!$K$4:$AJ$4,0))))+SUMPRODUCT((Inputs!$E$5:$E$160=$B6)*ISNUMBER(INDEX(Inputs!$K$5:$AJ$160,0,MATCH(V$2,Inputs!$K$4:$AJ$4,0))))=0,NA(),SUMPRODUCT((Inputs!$A$5:$A$160=$B6)*Inputs!$B$5:$B$160*(((Inputs!$G$5:$G$160="moeda")+(Inputs!$G$5:$G$160="acoes"))*Inputs!$B$1+((Inputs!$G$5:$G$160<>"moeda")*(Inputs!$G$5:$G$160<>"acoes")))*INDEX(Inputs!$K$5:$AJ$160,0,MATCH(V$2,Inputs!$K$4:$AJ$4,0)))+SUMPRODUCT((Inputs!$C$5:$C$160=$B6)*Inputs!$D$5:$D$160*(((Inputs!$G$5:$G$160="moeda")+(Inputs!$G$5:$G$160="acoes"))*Inputs!$B$1+((Inputs!$G$5:$G$160<>"moeda")*(Inputs!$G$5:$G$160<>"acoes")))*INDEX(Inputs!$K$5:$AJ$160,0,MATCH(V$2,Inputs!$K$4:$AJ$4,0)))+SUMPRODUCT((Inputs!$E$5:$E$160=$B6)*Inputs!$F$5:$F$160*(((Inputs!$G$5:$G$160="moeda")+(Inputs!$G$5:$G$160="acoes"))*Inputs!$B$1+((Inputs!$G$5:$G$160<>"moeda")*(Inputs!$G$5:$G$160<>"acoes")))*INDEX(Inputs!$K$5:$AJ$160,0,MATCH(V$2,Inputs!$K$4:$AJ$4,0))))) -> -202.562 | W6: =SUM(S6:V6) -> -766.506 | X6: =IF(ISNA(MATCH(X$2,Inputs!$K$4:$AJ$4,0)),NA(),IF(SUMPRODUCT((Inputs!$A$5:$A$160=$B6)*ISNUMBER(INDEX(Inputs!$K$5:$AJ$160,0,MATCH(X$2,Inputs!$K$4:$AJ$4,0))))+SUMPRODUCT((Inputs!$C$5:$C$160=$B6)*ISNUMBER(INDEX(Inputs!$K$5:$AJ$160,0,MATCH(X$2,Inputs!$K$4:$AJ$4,0))))+SUMPRODUCT((Inputs!$E$5:$E$160=$B6)*ISNUMBER(INDEX(Inputs!$K$5:$AJ$160,0,MATCH(X$2,Inputs!$K$4:$AJ$4,0))))=0,NA(),SUMPRODUCT((Inputs!$A$5:$A$160=$B6)*Inputs!$B$5:$B$160*(((Inputs!$G$5:$G$160="moeda")+(Inputs!$G$5:$G$160="acoes"))*Inputs!$B$1+((Inputs!$G$5:$G$160<>"moeda")*(Inputs!$G$5:$G$160<>"acoes")))*INDEX(Inputs!$K$5:$AJ$160,0,MATCH(X$2,Inputs!$K$4:$AJ$4,0)))+SUMPRODUCT((Inputs!$C$5:$C$160=$B6)*Inputs!$D$5:$D$160*(((Inputs!$G$5:$G$160="moeda")+(Inputs!$G$5:$G$160="acoes"))*Inputs!$B$1+((Inputs!$G$5:$G$160<>"moeda")*(Inputs!$G$5:$G$160<>"acoes")))*INDEX(Inputs!$K$5:$AJ$160,0,MATCH(X$2,Inputs!$K$4:$AJ$4,0)))+SUMPRODUCT((Inputs!$E$5:$E$160=$B6)*Inputs!$F$5:$F$160*(((Inputs!$G$5:$G$160="moeda")+(Inputs!$G$5:$G$160="acoes"))*Inputs!$B$1+((Inputs!$G$5:$G$160<>"moeda")*(Inputs!$G$5:$G$160<>"acoes")))*INDEX(Inputs!$K$5:$AJ$160,0,MATCH(X$2,Inputs!$K$4:$AJ$4,0))))) -> -185.36635 | Y6: =IF(ISNA(MATCH(Y$2,Inputs!$K$4:$AJ$4,0)),NA(),IF(SUMPRODUCT((Inputs!$A$5:$A$160=$B6)*ISNUMBER(INDEX(Inputs!$K$5:$AJ$160,0,MATCH(Y$2,Inputs!$K$4:$AJ$4,0))))+SUMPRODUCT((Inputs!$C$5:$C$160=$B6)*ISNUMBER(INDEX(Inputs!$K$5:$AJ$160,0,MATCH(Y$2,Inputs!$K$4:$AJ$4,0))))+SUMPRODUCT((Inputs!$E$5:$E$160=$B6)*ISNUMBER(INDEX(Inputs!$K$5:$AJ$160,0,MATCH(Y$2,Inputs!$K$4:$AJ$4,0))))=0,NA(),SUMPRODUCT((Inputs!$A$5:$A$160=$B6)*Inputs!$B$5:$B$160*(((Inputs!$G$5:$G$160="moeda")+(Inputs!$G$5:$G$160="acoes"))*Inputs!$B$1+((Inputs!$G$5:$G$160<>"moeda")*(Inputs!$G$5:$G$160<>"acoes")))*INDEX(Inputs!$K$5:$AJ$160,0,MATCH(Y$2,Inputs!$K$4:$AJ$4,0)))+SUMPRODUCT((Inputs!$C$5:$C$160=$B6)*Inputs!$D$5:$D$160*(((Inputs!$G$5:$G$160="moeda")+(Inputs!$G$5:$G$160="acoes"))*Inputs!$B$1+((Inputs!$G$5:$G$160<>"moeda")*(Inputs!$G$5:$G$160<>"acoes")))*INDEX(Inputs!$K$5:$AJ$160,0,MATCH(Y$2,Inputs!$K$4:$AJ$4,0)))+SUMPRODUCT((Inputs!$E$5:$E$160=$B6)*Inputs!$F$5:$F$160*(((Inputs!$G$5:$G$160="moeda")+(Inputs!$G$5:$G$160="acoes"))*Inputs!$B$1+((Inputs!$G$5:$G$160<>"moeda")*(Inputs!$G$5:$G$160<>"acoes")))*INDEX(Inputs!$K$5:$AJ$160,0,MATCH(Y$2,Inputs!$K$4:$AJ$4,0))))) -> -165.927 | Z6: =IF(ISNA(MATCH(Z$2,Inputs!$K$4:$AJ$4,0)),NA(),IF(SUMPRODUCT((Inputs!$A$5:$A$160=$B6)*ISNUMBER(INDEX(Inputs!$K$5:$AJ$160,0,MATCH(Z$2,Inputs!$K$4:$AJ$4,0))))+SUMPRODUCT((Inputs!$C$5:$C$160=$B6)*ISNUMBER(INDEX(Inputs!$K$5:$AJ$160,0,MATCH(Z$2,Inputs!$K$4:$AJ$4,0))))+SUMPRODUCT((Inputs!$E$5:$E$160=$B6)*ISNUMBER(INDEX(Inputs!$K$5:$AJ$160,0,MATCH(Z$2,Inputs!$K$4:$AJ$4,0))))=0,NA(),SUMPRODUCT((Inputs!$A$5:$A$160=$B6)*Inputs!$B$5:$B$160*(((Inputs!$G$5:$G$160="moeda")+(Inputs!$G$5:$G$160="acoes"))*Inputs!$B$1+((Inputs!$G$5:$G$160<>"moeda")*(Inputs!$G$5:$G$160<>"acoes")))*INDEX(Inputs!$K$5:$AJ$160,0,MATCH(Z$2,Inputs!$K$4:$AJ$4,0)))+SUMPRODUCT((Inputs!$C$5:$C$160=$B6)*Inputs!$D$5:$D$160*(((Inputs!$G$5:$G$160="moeda")+(Inputs!$G$5:$G$160="acoes"))*Inputs!$B$1+((Inputs!$G$5:$G$160<>"moeda")*(Inputs!$G$5:$G$160<>"acoes")))*INDEX(Inputs!$K$5:$AJ$160,0,MATCH(Z$2,Inputs!$K$4:$AJ$4,0)))+SUMPRODUCT((Inputs!$E$5:$E$160=$B6)*Inputs!$F$5:$F$160*(((Inputs!$G$5:$G$160="moeda")+(Inputs!$G$5:$G$160="acoes"))*Inputs!$B$1+((Inputs!$G$5:$G$160<>"moeda")*(Inputs!$G$5:$G$160<>"acoes")))*INDEX(Inputs!$K$5:$AJ$160,0,MATCH(Z$2,Inputs!$K$4:$AJ$4,0))))) -> -191.91028 | AA6: =IF(ISNA(MATCH(AA$2,Inputs!$K$4:$AJ$4,0)),NA(),IF(SUMPRODUCT((Inputs!$A$5:$A$160=$B6)*ISNUMBER(INDEX(Inputs!$K$5:$AJ$160,0,MATCH(AA$2,Inputs!$K$4:$AJ$4,0))))+SUMPRODUCT((Inputs!$C$5:$C$160=$B6)*ISNUMBER(INDEX(Inputs!$K$5:$AJ$160,0,MATCH(AA$2,Inputs!$K$4:$AJ$4,0))))+SUMPRODUCT((Inputs!$E$5:$E$160=$B6)*ISNUMBER(INDEX(Inputs!$K$5:$AJ$160,0,MATCH(AA$2,Inputs!$K$4:$AJ$4,0))))=0,NA(),SUMPRODUCT((Inputs!$A$5:$A$160=$B6)*Inputs!$B$5:$B$160*(((Inputs!$G$5:$G$160="moeda")+(Inputs!$G$5:$G$160="acoes"))*Inputs!$B$1+((Inputs!$G$5:$G$160<>"moeda")*(Inputs!$G$5:$G$160<>"acoes")))*INDEX(Inputs!$K$5:$AJ$160,0,MATCH(AA$2,Inputs!$K$4:$AJ$4,0)))+SUMPRODUCT((Inputs!$C$5:$C$160=$B6)*Inputs!$D$5:$D$160*(((Inputs!$G$5:$G$160="moeda")+(Inputs!$G$5:$G$160="acoes"))*Inputs!$B$1+((Inputs!$G$5:$G$160<>"moeda")*(Inputs!$G$5:$G$160<>"acoes")))*INDEX(Inputs!$K$5:$AJ$160,0,MATCH(AA$2,Inputs!$K$4:$AJ$4,0)))+SUMPRODUCT((Inputs!$E$5:$E$160=$B6)*Inputs!$F$5:$F$160*(((Inputs!$G$5:$G$160="moeda")+(Inputs!$G$5:$G$160="acoes"))*Inputs!$B$1+((Inputs!$G$5:$G$160<>"moeda")*(Inputs!$G$5:$G$160<>"acoes")))*INDEX(Inputs!$K$5:$AJ$160,0,MATCH(AA$2,Inputs!$K$4:$AJ$4,0))))) -> -210.60018 | AB6: =SUM(X6:AA6) -> -753.80381 | AC6: =IF(ISNA(MATCH(AC$2,Inputs!$K$4:$AJ$4,0)),NA(),IF(SUMPRODUCT((Inputs!$A$5:$A$160=$B6)*ISNUMBER(INDEX(Inputs!$K$5:$AJ$160,0,MATCH(AC$2,Inputs!$K$4:$AJ$4,0))))+SUMPRODUCT((Inputs!$C$5:$C$160=$B6)*ISNUMBER(INDEX(Inputs!$K$5:$AJ$160,0,MATCH(AC$2,Inputs!$K$4:$AJ$4,0))))+SUMPRODUCT((Inputs!$E$5:$E$160=$B6)*ISNUMBER(INDEX(Inputs!$K$5:$AJ$160,0,MATCH(AC$2,Inputs!$K$4:$AJ$4,0))))=0,NA(),SUMPRODUCT((Inputs!$A$5:$A$160=$B6)*Inputs!$B$5:$B$160*(((Inputs!$G$5:$G$160="moeda")+(Inputs!$G$5:$G$160="acoes"))*Inputs!$B$1+((Inputs!$G$5:$G$160<>"moeda")*(Inputs!$G$5:$G$160<>"acoes")))*INDEX(Inputs!$K$5:$AJ$160,0,MATCH(AC$2,Inputs!$K$4:$AJ$4,0)))+SUMPRODUCT((Inputs!$C$5:$C$160=$B6)*Inputs!$D$5:$D$160*(((Inputs!$G$5:$G$160="moeda")+(Inputs!$G$5:$G$160="acoes"))*Inputs!$B$1+((Inputs!$G$5:$G$160<>"moeda")*(Inputs!$G$5:$G$160<>"acoes")))*INDEX(Inputs!$K$5:$AJ$160,0,MATCH(AC$2,Inputs!$K$4:$AJ$4,0)))+SUMPRODUCT((Inputs!$E$5:$E$160=$B6)*Inputs!$F$5:$F$160*(((Inputs!$G$5:$G$160="moeda")+(Inputs!$G$5:$G$160="acoes"))*Inputs!$B$1+((Inputs!$G$5:$G$160<>"moeda")*(Inputs!$G$5:$G$160<>"acoes")))*INDEX(Inputs!$K$5:$AJ$160,0,MATCH(AC$2,Inputs!$K$4:$AJ$4,0))))) -> -199.47864 | AD6: =IF(ISNA(MATCH(AD$2,Inputs!$K$4:$AJ$4,0)),NA(),IF(SUMPRODUCT((Inputs!$A$5:$A$160=$B6)*ISNUMBER(INDEX(Inputs!$K$5:$AJ$160,0,MATCH(AD$2,Inputs!$K$4:$AJ$4,0))))+SUMPRODUCT((Inputs!$C$5:$C$160=$B6)*ISNUMBER(INDEX(Inputs!$K$5:$AJ$160,0,MATCH(AD$2,Inputs!$K$4:$AJ$4,0))))+SUMPRODUCT((Inputs!$E$5:$E$160=$B6)*ISNUMBER(INDEX(Inputs!$K$5:$AJ$160,0,MATCH(AD$2,Inputs!$K$4:$AJ$4,0))))=0,NA(),SUMPRODUCT((Inputs!$A$5:$A$160=$B6)*Inputs!$B$5:$B$160*(((Inputs!$G$5:$G$160="moeda")+(Inputs!$G$5:$G$160="acoes"))*Inputs!$B$1+((Inputs!$G$5:$G$160<>"moeda")*(Inputs!$G$5:$G$160<>"acoes")))*INDEX(Inputs!$K$5:$AJ$160,0,MATCH(AD$2,Inputs!$K$4:$AJ$4,0)))+SUMPRODUCT((Inputs!$C$5:$C$160=$B6)*Inputs!$D$5:$D$160*(((Inputs!$G$5:$G$160="moeda")+(Inputs!$G$5:$G$160="acoes"))*Inputs!$B$1+((Inputs!$G$5:$G$160<>"moeda")*(Inputs!$G$5:$G$160<>"acoes")))*INDEX(Inputs!$K$5:$AJ$160,0,MATCH(AD$2,Inputs!$K$4:$AJ$4,0)))+SUMPRODUCT((Inputs!$E$5:$E$160=$B6)*Inputs!$F$5:$F$160*(((Inputs!$G$5:$G$160="moeda")+(Inputs!$G$5:$G$160="acoes"))*Inputs!$B$1+((Inputs!$G$5:$G$160<>"moeda")*(Inputs!$G$5:$G$160<>"acoes")))*INDEX(Inputs!$K$5:$AJ$160,0,MATCH(AD$2,Inputs!$K$4:$AJ$4,0))))) -> -195.541 | AE6: =IF(ISNA(MATCH(AE$2,Inputs!$K$4:$AJ$4,0)),NA(),IF(SUMPRODUCT((Inputs!$A$5:$A$160=$B6)*ISNUMBER(INDEX(Inputs!$K$5:$AJ$160,0,MATCH(AE$2,Inputs!$K$4:$AJ$4,0))))+SUMPRODUCT((Inputs!$C$5:$C$160=$B6)*ISNUMBER(INDEX(Inputs!$K$5:$AJ$160,0,MATCH(AE$2,Inputs!$K$4:$AJ$4,0))))+SUMPRODUCT((Inputs!$E$5:$E$160=$B6)*ISNUMBER(INDEX(Inputs!$K$5:$AJ$160,0,MATCH(AE$2,Inputs!$K$4:$AJ$4,0))))=0,NA(),SUMPRODUCT((Inputs!$A$5:$A$160=$B6)*Inputs!$B$5:$B$160*(((Inputs!$G$5:$G$160="moeda")+(Inputs!$G$5:$G$160="acoes"))*Inputs!$B$1+((Inputs!$G$5:$G$160<>"moeda")*(Inputs!$G$5:$G$160<>"acoes")))*INDEX(Inputs!$K$5:$AJ$160,0,MATCH(AE$2,Inputs!$K$4:$AJ$4,0)))+SUMPRODUCT((Inputs!$C$5:$C$160=$B6)*Inputs!$D$5:$D$160*(((Inputs!$G$5:$G$160="moeda")+(Inputs!$G$5:$G$160="acoes"))*Inputs!$B$1+((Inputs!$G$5:$G$160<>"moeda")*(Inputs!$G$5:$G$160<>"acoes")))*INDEX(Inputs!$K$5:$AJ$160,0,MATCH(AE$2,Inputs!$K$4:$AJ$4,0)))+SUMPRODUCT((Inputs!$E$5:$E$160=$B6)*Inputs!$F$5:$F$160*(((Inputs!$G$5:$G$160="moeda")+(Inputs!$G$5:$G$160="acoes"))*Inputs!$B$1+((Inputs!$G$5:$G$160<>"moeda")*(Inputs!$G$5:$G$160<>"acoes")))*INDEX(Inputs!$K$5:$AJ$160,0,MATCH(AE$2,Inputs!$K$4:$AJ$4,0))))) -> #N/A | AF6: =IF(ISNA(MATCH(AF$2,Inputs!$K$4:$AJ$4,0)),NA(),IF(SUMPRODUCT((Inputs!$A$5:$A$160=$B6)*ISNUMBER(INDEX(Inputs!$K$5:$AJ$160,0,MATCH(AF$2,Inputs!$K$4:$AJ$4,0))))+SUMPRODUCT((Inputs!$C$5:$C$160=$B6)*ISNUMBER(INDEX(Inputs!$K$5:$AJ$160,0,MATCH(AF$2,Inputs!$K$4:$AJ$4,0))))+SUMPRODUCT((Inputs!$E$5:$E$160=$B6)*ISNUMBER(INDEX(Inputs!$K$5:$AJ$160,0,MATCH(AF$2,Inputs!$K$4:$AJ$4,0))))=0,NA(),SUMPRODUCT((Inputs!$A$5:$A$160=$B6)*Inputs!$B$5:$B$160*(((Inputs!$G$5:$G$160="moeda")+(Inputs!$G$5:$G$160="acoes"))*Inputs!$B$1+((Inputs!$G$5:$G$160<>"moeda")*(Inputs!$G$5:$G$160<>"acoes")))*INDEX(Inputs!$K$5:$AJ$160,0,MATCH(AF$2,Inputs!$K$4:$AJ$4,0)))+SUMPRODUCT((Inputs!$C$5:$C$160=$B6)*Inputs!$D$5:$D$160*(((Inputs!$G$5:$G$160="moeda")+(Inputs!$G$5:$G$160="acoes"))*Inputs!$B$1+((Inputs!$G$5:$G$160<>"moeda")*(Inputs!$G$5:$G$160<>"acoes")))*INDEX(Inputs!$K$5:$AJ$160,0,MATCH(AF$2,Inputs!$K$4:$AJ$4,0)))+SUMPRODUCT((Inputs!$E$5:$E$160=$B6)*Inputs!$F$5:$F$160*(((Inputs!$G$5:$G$160="moeda")+(Inputs!$G$5:$G$160="acoes"))*Inputs!$B$1+((Inputs!$G$5:$G$160<>"moeda")*(Inputs!$G$5:$G$160<>"acoes")))*INDEX(Inputs!$K$5:$AJ$160,0,MATCH(AF$2,Inputs!$K$4:$AJ$4,0))))) -> #N/A | AG6: =SUM(AC6:AF6) -> #N/A | AH6: =IF(ISNA(MATCH(AH$2,Inputs!$K$4:$AJ$4,0)),NA(),IF(SUMPRODUCT((Inputs!$A$5:$A$160=$B6)*ISNUMBER(INDEX(Inputs!$K$5:$AJ$160,0,MATCH(AH$2,Inputs!$K$4:$AJ$4,0))))+SUMPRODUCT((Inputs!$C$5:$C$160=$B6)*ISNUMBER(INDEX(Inputs!$K$5:$AJ$160,0,MATCH(AH$2,Inputs!$K$4:$AJ$4,0))))+SUMPRODUCT((Inputs!$E$5:$E$160=$B6)*ISNUMBER(INDEX(Inputs!$K$5:$AJ$160,0,MATCH(AH$2,Inputs!$K$4:$AJ$4,0))))=0,NA(),SUMPRODUCT((Inputs!$A$5:$A$160=$B6)*Inputs!$B$5:$B$160*(((Inputs!$G$5:$G$160="moeda")+(Inputs!$G$5:$G$160="acoes"))*Inputs!$B$1+((Inputs!$G$5:$G$160<>"moeda")*(Inputs!$G$5:$G$160<>"acoes")))*INDEX(Inputs!$K$5:$AJ$160,0,MATCH(AH$2,Inputs!$K$4:$AJ$4,0)))+SUMPRODUCT((Inputs!$C$5:$C$160=$B6)*Inputs!$D$5:$D$160*(((Inputs!$G$5:$G$160="moeda")+(Inputs!$G$5:$G$160="acoes"))*Inputs!$B$1+((Inputs!$G$5:$G$160<>"moeda")*(Inputs!$G$5:$G$160<>"acoes")))*INDEX(Inputs!$K$5:$AJ$160,0,MATCH(AH$2,Inputs!$K$4:$AJ$4,0)))+SUMPRODUCT((Inputs!$E$5:$E$160=$B6)*Inputs!$F$5:$F$160*(((Inputs!$G$5:$G$160="moeda")+(Inputs!$G$5:$G$160="acoes"))*Inputs!$B$1+((Inputs!$G$5:$G$160<>"moeda")*(Inputs!$G$5:$G$160<>"acoes")))*INDEX(Inputs!$K$5:$AJ$160,0,MATCH(AH$2,Inputs!$K$4:$AJ$4,0))))) -> -63.354902 | AI6: =IF(ISNA(MATCH(AI$2,Inputs!$K$4:$AJ$4,0)),NA(),IF(SUMPRODUCT((Inputs!$A$5:$A$160=$B6)*ISNUMBER(INDEX(Inputs!$K$5:$AJ$160,0,MATCH(AI$2,Inputs!$K$4:$AJ$4,0))))+SUMPRODUCT((Inputs!$C$5:$C$160=$B6)*ISNUMBER(INDEX(Inputs!$K$5:$AJ$160,0,MATCH(AI$2,Inputs!$K$4:$AJ$4,0))))+SUMPRODUCT((Inputs!$E$5:$E$160=$B6)*ISNUMBER(INDEX(Inputs!$K$5:$AJ$160,0,MATCH(AI$2,Inputs!$K$4:$AJ$4,0))))=0,NA(),SUMPRODUCT((Inputs!$A$5:$A$160=$B6)*Inputs!$B$5:$B$160*(((Inputs!$G$5:$G$160="moeda")+(Inputs!$G$5:$G$160="acoes"))*Inputs!$B$1+((Inputs!$G$5:$G$160<>"moeda")*(Inputs!$G$5:$G$160<>"acoes")))*INDEX(Inputs!$K$5:$AJ$160,0,MATCH(AI$2,Inputs!$K$4:$AJ$4,0)))+SUMPRODUCT((Inputs!$C$5:$C$160=$B6)*Inputs!$D$5:$D$160*(((Inputs!$G$5:$G$160="moeda")+(Inputs!$G$5:$G$160="acoes"))*Inputs!$B$1+((Inputs!$G$5:$G$160<>"moeda")*(Inputs!$G$5:$G$160<>"acoes")))*INDEX(Inputs!$K$5:$AJ$160,0,MATCH(AI$2,Inputs!$K$4:$AJ$4,0)))+SUMPRODUCT((Inputs!$E$5:$E$160=$B6)*Inputs!$F$5:$F$160*(((Inputs!$G$5:$G$160="moeda")+(Inputs!$G$5:$G$160="acoes"))*Inputs!$B$1+((Inputs!$G$5:$G$160<>"moeda")*(Inputs!$G$5:$G$160<>"acoes")))*INDEX(Inputs!$K$5:$AJ$160,0,MATCH(AI$2,Inputs!$K$4:$AJ$4,0))))) -> -52.051895 | AJ6: =IF(ISNA(MATCH(AJ$2,Inputs!$K$4:$AJ$4,0)),NA(),IF(SUMPRODUCT((Inputs!$A$5:$A$160=$B6)*ISNUMBER(INDEX(Inputs!$K$5:$AJ$160,0,MATCH(AJ$2,Inputs!$K$4:$AJ$4,0))))+SUMPRODUCT((Inputs!$C$5:$C$160=$B6)*ISNUMBER(INDEX(Inputs!$K$5:$AJ$160,0,MATCH(AJ$2,Inputs!$K$4:$AJ$4,0))))+SUMPRODUCT((Inputs!$E$5:$E$160=$B6)*ISNUMBER(INDEX(Inputs!$K$5:$AJ$160,0,MATCH(AJ$2,Inputs!$K$4:$AJ$4,0))))=0,NA(),SUMPRODUCT((Inputs!$A$5:$A$160=$B6)*Inputs!$B$5:$B$160*(((Inputs!$G$5:$G$160="moeda")+(Inputs!$G$5:$G$160="acoes"))*Inputs!$B$1+((Inputs!$G$5:$G$160<>"moeda")*(Inputs!$G$5:$G$160<>"acoes")))*INDEX(Inputs!$K$5:$AJ$160,0,MATCH(AJ$2,Inputs!$K$4:$AJ$4,0)))+SUMPRODUCT((Inputs!$C$5:$C$160=$B6)*Inputs!$D$5:$D$160*(((Inputs!$G$5:$G$160="moeda")+(Inputs!$G$5:$G$160="acoes"))*Inputs!$B$1+((Inputs!$G$5:$G$160<>"moeda")*(Inputs!$G$5:$G$160<>"acoes")))*INDEX(Inputs!$K$5:$AJ$160,0,MATCH(AJ$2,Inputs!$K$4:$AJ$4,0)))+SUMPRODUCT((Inputs!$E$5:$E$160=$B6)*Inputs!$F$5:$F$160*(((Inputs!$G$5:$G$160="moeda")+(Inputs!$G$5:$G$160="acoes"))*Inputs!$B$1+((Inputs!$G$5:$G$160<>"moeda")*(Inputs!$G$5:$G$160<>"acoes")))*INDEX(Inputs!$K$5:$AJ$160,0,MATCH(AJ$2,Inputs!$K$4:$AJ$4,0))))) -> -61.697213 | AK6: =IF(ISNA(MATCH(AK$2,Inputs!$K$4:$AJ$4,0)),NA(),IF(SUMPRODUCT((Inputs!$A$5:$A$160=$B6)*ISNUMBER(INDEX(Inputs!$K$5:$AJ$160,0,MATCH(AK$2,Inputs!$K$4:$AJ$4,0))))+SUMPRODUCT((Inputs!$C$5:$C$160=$B6)*ISNUMBER(INDEX(Inputs!$K$5:$AJ$160,0,MATCH(AK$2,Inputs!$K$4:$AJ$4,0))))+SUMPRODUCT((Inputs!$E$5:$E$160=$B6)*ISNUMBER(INDEX(Inputs!$K$5:$AJ$160,0,MATCH(AK$2,Inputs!$K$4:$AJ$4,0))))=0,NA(),SUMPRODUCT((Inputs!$A$5:$A$160=$B6)*Inputs!$B$5:$B$160*(((Inputs!$G$5:$G$160="moeda")+(Inputs!$G$5:$G$160="acoes"))*Inputs!$B$1+((Inputs!$G$5:$G$160<>"moeda")*(Inputs!$G$5:$G$160<>"acoes")))*INDEX(Inputs!$K$5:$AJ$160,0,MATCH(AK$2,Inputs!$K$4:$AJ$4,0)))+SUMPRODUCT((Inputs!$C$5:$C$160=$B6)*Inputs!$D$5:$D$160*(((Inputs!$G$5:$G$160="moeda")+(Inputs!$G$5:$G$160="acoes"))*Inputs!$B$1+((Inputs!$G$5:$G$160<>"moeda")*(Inputs!$G$5:$G$160<>"acoes")))*INDEX(Inputs!$K$5:$AJ$160,0,MATCH(AK$2,Inputs!$K$4:$AJ$4,0)))+SUMPRODUCT((Inputs!$E$5:$E$160=$B6)*Inputs!$F$5:$F$160*(((Inputs!$G$5:$G$160="moeda")+(Inputs!$G$5:$G$160="acoes"))*Inputs!$B$1+((Inputs!$G$5:$G$160<>"moeda")*(Inputs!$G$5:$G$160<>"acoes")))*INDEX(Inputs!$K$5:$AJ$160,0,MATCH(AK$2,Inputs!$K$4:$AJ$4,0))))) -> -91.522047 | AL6: =SUM(AH6:AK6) -> -268.62606
B7: 4 | C7: D&A | D7: =IF(ISNA(MATCH(D$2,Inputs!$K$4:$AJ$4,0)),NA(),IF(SUMPRODUCT((Inputs!$A$5:$A$160=$B7)*ISNUMBER(INDEX(Inputs!$K$5:$AJ$160,0,MATCH(D$2,Inputs!$K$4:$AJ$4,0))))+SUMPRODUCT((Inputs!$C$5:$C$160=$B7)*ISNUMBER(INDEX(Inputs!$K$5:$AJ$160,0,MATCH(D$2,Inputs!$K$4:$AJ$4,0))))+SUMPRODUCT((Inputs!$E$5:$E$160=$B7)*ISNUMBER(INDEX(Inputs!$K$5:$AJ$160,0,MATCH(D$2,Inputs!$K$4:$AJ$4,0))))=0,NA(),SUMPRODUCT((Inputs!$A$5:$A$160=$B7)*Inputs!$B$5:$B$160*(((Inputs!$G$5:$G$160="moeda")+(Inputs!$G$5:$G$160="acoes"))*Inputs!$B$1+((Inputs!$G$5:$G$160<>"moeda")*(Inputs!$G$5:$G$160<>"acoes")))*INDEX(Inputs!$K$5:$AJ$160,0,MATCH(D$2,Inputs!$K$4:$AJ$4,0)))+SUMPRODUCT((Inputs!$C$5:$C$160=$B7)*Inputs!$D$5:$D$160*(((Inputs!$G$5:$G$160="moeda")+(Inputs!$G$5:$G$160="acoes"))*Inputs!$B$1+((Inputs!$G$5:$G$160<>"moeda")*(Inputs!$G$5:$G$160<>"acoes")))*INDEX(Inputs!$K$5:$AJ$160,0,MATCH(D$2,Inputs!$K$4:$AJ$4,0)))+SUMPRODUCT((Inputs!$E$5:$E$160=$B7)*Inputs!$F$5:$F$160*(((Inputs!$G$5:$G$160="moeda")+(Inputs!$G$5:$G$160="acoes"))*Inputs!$B$1+((Inputs!$G$5:$G$160<>"moeda")*(Inputs!$G$5:$G$160<>"acoes")))*INDEX(Inputs!$K$5:$AJ$160,0,MATCH(D$2,Inputs!$K$4:$AJ$4,0))))) -> -86.836438 | E7: =IF(ISNA(MATCH(E$2,Inputs!$K$4:$AJ$4,0)),NA(),IF(SUMPRODUCT((Inputs!$A$5:$A$160=$B7)*ISNUMBER(INDEX(Inputs!$K$5:$AJ$160,0,MATCH(E$2,Inputs!$K$4:$AJ$4,0))))+SUMPRODUCT((Inputs!$C$5:$C$160=$B7)*ISNUMBER(INDEX(Inputs!$K$5:$AJ$160,0,MATCH(E$2,Inputs!$K$4:$AJ$4,0))))+SUMPRODUCT((Inputs!$E$5:$E$160=$B7)*ISNUMBER(INDEX(Inputs!$K$5:$AJ$160,0,MATCH(E$2,Inputs!$K$4:$AJ$4,0))))=0,NA(),SUMPRODUCT((Inputs!$A$5:$A$160=$B7)*Inputs!$B$5:$B$160*(((Inputs!$G$5:$G$160="moeda")+(Inputs!$G$5:$G$160="acoes"))*Inputs!$B$1+((Inputs!$G$5:$G$160<>"moeda")*(Inputs!$G$5:$G$160<>"acoes")))*INDEX(Inputs!$K$5:$AJ$160,0,MATCH(E$2,Inputs!$K$4:$AJ$4,0)))+SUMPRODUCT((Inputs!$C$5:$C$160=$B7)*Inputs!$D$5:$D$160*(((Inputs!$G$5:$G$160="moeda")+(Inputs!$G$5:$G$160="acoes"))*Inputs!$B$1+((Inputs!$G$5:$G$160<>"moeda")*(Inputs!$G$5:$G$160<>"acoes")))*INDEX(Inputs!$K$5:$AJ$160,0,MATCH(E$2,Inputs!$K$4:$AJ$4,0)))+SUMPRODUCT((Inputs!$E$5:$E$160=$B7)*Inputs!$F$5:$F$160*(((Inputs!$G$5:$G$160="moeda")+(Inputs!$G$5:$G$160="acoes"))*Inputs!$B$1+((Inputs!$G$5:$G$160<>"moeda")*(Inputs!$G$5:$G$160<>"acoes")))*INDEX(Inputs!$K$5:$AJ$160,0,MATCH(E$2,Inputs!$K$4:$AJ$4,0))))) -> -90.884441 | F7: =IF(ISNA(MATCH(F$2,Inputs!$K$4:$AJ$4,0)),NA(),IF(SUMPRODUCT((Inputs!$A$5:$A$160=$B7)*ISNUMBER(INDEX(Inputs!$K$5:$AJ$160,0,MATCH(F$2,Inputs!$K$4:$AJ$4,0))))+SUMPRODUCT((Inputs!$C$5:$C$160=$B7)*ISNUMBER(INDEX(Inputs!$K$5:$AJ$160,0,MATCH(F$2,Inputs!$K$4:$AJ$4,0))))+SUMPRODUCT((Inputs!$E$5:$E$160=$B7)*ISNUMBER(INDEX(Inputs!$K$5:$AJ$160,0,MATCH(F$2,Inputs!$K$4:$AJ$4,0))))=0,NA(),SUMPRODUCT((Inputs!$A$5:$A$160=$B7)*Inputs!$B$5:$B$160*(((Inputs!$G$5:$G$160="moeda")+(Inputs!$G$5:$G$160="acoes"))*Inputs!$B$1+((Inputs!$G$5:$G$160<>"moeda")*(Inputs!$G$5:$G$160<>"acoes")))*INDEX(Inputs!$K$5:$AJ$160,0,MATCH(F$2,Inputs!$K$4:$AJ$4,0)))+SUMPRODUCT((Inputs!$C$5:$C$160=$B7)*Inputs!$D$5:$D$160*(((Inputs!$G$5:$G$160="moeda")+(Inputs!$G$5:$G$160="acoes"))*Inputs!$B$1+((Inputs!$G$5:$G$160<>"moeda")*(Inputs!$G$5:$G$160<>"acoes")))*INDEX(Inputs!$K$5:$AJ$160,0,MATCH(F$2,Inputs!$K$4:$AJ$4,0)))+SUMPRODUCT((Inputs!$E$5:$E$160=$B7)*Inputs!$F$5:$F$160*(((Inputs!$G$5:$G$160="moeda")+(Inputs!$G$5:$G$160="acoes"))*Inputs!$B$1+((Inputs!$G$5:$G$160<>"moeda")*(Inputs!$G$5:$G$160<>"acoes")))*INDEX(Inputs!$K$5:$AJ$160,0,MATCH(F$2,Inputs!$K$4:$AJ$4,0))))) -> -103.83368 | G7: =IF(ISNA(MATCH(G$2,Inputs!$K$4:$AJ$4,0)),NA(),IF(SUMPRODUCT((Inputs!$A$5:$A$160=$B7)*ISNUMBER(INDEX(Inputs!$K$5:$AJ$160,0,MATCH(G$2,Inputs!$K$4:$AJ$4,0))))+SUMPRODUCT((Inputs!$C$5:$C$160=$B7)*ISNUMBER(INDEX(Inputs!$K$5:$AJ$160,0,MATCH(G$2,Inputs!$K$4:$AJ$4,0))))+SUMPRODUCT((Inputs!$E$5:$E$160=$B7)*ISNUMBER(INDEX(Inputs!$K$5:$AJ$160,0,MATCH(G$2,Inputs!$K$4:$AJ$4,0))))=0,NA(),SUMPRODUCT((Inputs!$A$5:$A$160=$B7)*Inputs!$B$5:$B$160*(((Inputs!$G$5:$G$160="moeda")+(Inputs!$G$5:$G$160="acoes"))*Inputs!$B$1+((Inputs!$G$5:$G$160<>"moeda")*(Inputs!$G$5:$G$160<>"acoes")))*INDEX(Inputs!$K$5:$AJ$160,0,MATCH(G$2,Inputs!$K$4:$AJ$4,0)))+SUMPRODUCT((Inputs!$C$5:$C$160=$B7)*Inputs!$D$5:$D$160*(((Inputs!$G$5:$G$160="moeda")+(Inputs!$G$5:$G$160="acoes"))*Inputs!$B$1+((Inputs!$G$5:$G$160<>"moeda")*(Inputs!$G$5:$G$160<>"acoes")))*INDEX(Inputs!$K$5:$AJ$160,0,MATCH(G$2,Inputs!$K$4:$AJ$4,0)))+SUMPRODUCT((Inputs!$E$5:$E$160=$B7)*Inputs!$F$5:$F$160*(((Inputs!$G$5:$G$160="moeda")+(Inputs!$G$5:$G$160="acoes"))*Inputs!$B$1+((Inputs!$G$5:$G$160<>"moeda")*(Inputs!$G$5:$G$160<>"acoes")))*INDEX(Inputs!$K$5:$AJ$160,0,MATCH(G$2,Inputs!$K$4:$AJ$4,0))))) -> -107.72516 | H7: =SUM(D7:G7) -> -389.27972 | I7: =IF(ISNA(MATCH(I$2,Inputs!$K$4:$AJ$4,0)),NA(),IF(SUMPRODUCT((Inputs!$A$5:$A$160=$B7)*ISNUMBER(INDEX(Inputs!$K$5:$AJ$160,0,MATCH(I$2,Inputs!$K$4:$AJ$4,0))))+SUMPRODUCT((Inputs!$C$5:$C$160=$B7)*ISNUMBER(INDEX(Inputs!$K$5:$AJ$160,0,MATCH(I$2,Inputs!$K$4:$AJ$4,0))))+SUMPRODUCT((Inputs!$E$5:$E$160=$B7)*ISNUMBER(INDEX(Inputs!$K$5:$AJ$160,0,MATCH(I$2,Inputs!$K$4:$AJ$4,0))))=0,NA(),SUMPRODUCT((Inputs!$A$5:$A$160=$B7)*Inputs!$B$5:$B$160*(((Inputs!$G$5:$G$160="moeda")+(Inputs!$G$5:$G$160="acoes"))*Inputs!$B$1+((Inputs!$G$5:$G$160<>"moeda")*(Inputs!$G$5:$G$160<>"acoes")))*INDEX(Inputs!$K$5:$AJ$160,0,MATCH(I$2,Inputs!$K$4:$AJ$4,0)))+SUMPRODUCT((Inputs!$C$5:$C$160=$B7)*Inputs!$D$5:$D$160*(((Inputs!$G$5:$G$160="moeda")+(Inputs!$G$5:$G$160="acoes"))*Inputs!$B$1+((Inputs!$G$5:$G$160<>"moeda")*(Inputs!$G$5:$G$160<>"acoes")))*INDEX(Inputs!$K$5:$AJ$160,0,MATCH(I$2,Inputs!$K$4:$AJ$4,0)))+SUMPRODUCT((Inputs!$E$5:$E$160=$B7)*Inputs!$F$5:$F$160*(((Inputs!$G$5:$G$160="moeda")+(Inputs!$G$5:$G$160="acoes"))*Inputs!$B$1+((Inputs!$G$5:$G$160<>"moeda")*(Inputs!$G$5:$G$160<>"acoes")))*INDEX(Inputs!$K$5:$AJ$160,0,MATCH(I$2,Inputs!$K$4:$AJ$4,0))))) -> -107.45964 | J7: =IF(ISNA(MATCH(J$2,Inputs!$K$4:$AJ$4,0)),NA(),IF(SUMPRODUCT((Inputs!$A$5:$A$160=$B7)*ISNUMBER(INDEX(Inputs!$K$5:$AJ$160,0,MATCH(J$2,Inputs!$K$4:$AJ$4,0))))+SUMPRODUCT((Inputs!$C$5:$C$160=$B7)*ISNUMBER(INDEX(Inputs!$K$5:$AJ$160,0,MATCH(J$2,Inputs!$K$4:$AJ$4,0))))+SUMPRODUCT((Inputs!$E$5:$E$160=$B7)*ISNUMBER(INDEX(Inputs!$K$5:$AJ$160,0,MATCH(J$2,Inputs!$K$4:$AJ$4,0))))=0,NA(),SUMPRODUCT((Inputs!$A$5:$A$160=$B7)*Inputs!$B$5:$B$160*(((Inputs!$G$5:$G$160="moeda")+(Inputs!$G$5:$G$160="acoes"))*Inputs!$B$1+((Inputs!$G$5:$G$160<>"moeda")*(Inputs!$G$5:$G$160<>"acoes")))*INDEX(Inputs!$K$5:$AJ$160,0,MATCH(J$2,Inputs!$K$4:$AJ$4,0)))+SUMPRODUCT((Inputs!$C$5:$C$160=$B7)*Inputs!$D$5:$D$160*(((Inputs!$G$5:$G$160="moeda")+(Inputs!$G$5:$G$160="acoes"))*Inputs!$B$1+((Inputs!$G$5:$G$160<>"moeda")*(Inputs!$G$5:$G$160<>"acoes")))*INDEX(Inputs!$K$5:$AJ$160,0,MATCH(J$2,Inputs!$K$4:$AJ$4,0)))+SUMPRODUCT((Inputs!$E$5:$E$160=$B7)*Inputs!$F$5:$F$160*(((Inputs!$G$5:$G$160="moeda")+(Inputs!$G$5:$G$160="acoes"))*Inputs!$B$1+((Inputs!$G$5:$G$160<>"moeda")*(Inputs!$G$5:$G$160<>"acoes")))*INDEX(Inputs!$K$5:$AJ$160,0,MATCH(J$2,Inputs!$K$4:$AJ$4,0))))) -> -113.84257 | K7: =IF(ISNA(MATCH(K$2,Inputs!$K$4:$AJ$4,0)),NA(),IF(SUMPRODUCT((Inputs!$A$5:$A$160=$B7)*ISNUMBER(INDEX(Inputs!$K$5:$AJ$160,0,MATCH(K$2,Inputs!$K$4:$AJ$4,0))))+SUMPRODUCT((Inputs!$C$5:$C$160=$B7)*ISNUMBER(INDEX(Inputs!$K$5:$AJ$160,0,MATCH(K$2,Inputs!$K$4:$AJ$4,0))))+SUMPRODUCT((Inputs!$E$5:$E$160=$B7)*ISNUMBER(INDEX(Inputs!$K$5:$AJ$160,0,MATCH(K$2,Inputs!$K$4:$AJ$4,0))))=0,NA(),SUMPRODUCT((Inputs!$A$5:$A$160=$B7)*Inputs!$B$5:$B$160*(((Inputs!$G$5:$G$160="moeda")+(Inputs!$G$5:$G$160="acoes"))*Inputs!$B$1+((Inputs!$G$5:$G$160<>"moeda")*(Inputs!$G$5:$G$160<>"acoes")))*INDEX(Inputs!$K$5:$AJ$160,0,MATCH(K$2,Inputs!$K$4:$AJ$4,0)))+SUMPRODUCT((Inputs!$C$5:$C$160=$B7)*Inputs!$D$5:$D$160*(((Inputs!$G$5:$G$160="moeda")+(Inputs!$G$5:$G$160="acoes"))*Inputs!$B$1+((Inputs!$G$5:$G$160<>"moeda")*(Inputs!$G$5:$G$160<>"acoes")))*INDEX(Inputs!$K$5:$AJ$160,0,MATCH(K$2,Inputs!$K$4:$AJ$4,0)))+SUMPRODUCT((Inputs!$E$5:$E$160=$B7)*Inputs!$F$5:$F$160*(((Inputs!$G$5:$G$160="moeda")+(Inputs!$G$5:$G$160="acoes"))*Inputs!$B$1+((Inputs!$G$5:$G$160<>"moeda")*(Inputs!$G$5:$G$160<>"acoes")))*INDEX(Inputs!$K$5:$AJ$160,0,MATCH(K$2,Inputs!$K$4:$AJ$4,0))))) -> -109.75251 | L7: =IF(ISNA(MATCH(L$2,Inputs!$K$4:$AJ$4,0)),NA(),IF(SUMPRODUCT((Inputs!$A$5:$A$160=$B7)*ISNUMBER(INDEX(Inputs!$K$5:$AJ$160,0,MATCH(L$2,Inputs!$K$4:$AJ$4,0))))+SUMPRODUCT((Inputs!$C$5:$C$160=$B7)*ISNUMBER(INDEX(Inputs!$K$5:$AJ$160,0,MATCH(L$2,Inputs!$K$4:$AJ$4,0))))+SUMPRODUCT((Inputs!$E$5:$E$160=$B7)*ISNUMBER(INDEX(Inputs!$K$5:$AJ$160,0,MATCH(L$2,Inputs!$K$4:$AJ$4,0))))=0,NA(),SUMPRODUCT((Inputs!$A$5:$A$160=$B7)*Inputs!$B$5:$B$160*(((Inputs!$G$5:$G$160="moeda")+(Inputs!$G$5:$G$160="acoes"))*Inputs!$B$1+((Inputs!$G$5:$G$160<>"moeda")*(Inputs!$G$5:$G$160<>"acoes")))*INDEX(Inputs!$K$5:$AJ$160,0,MATCH(L$2,Inputs!$K$4:$AJ$4,0)))+SUMPRODUCT((Inputs!$C$5:$C$160=$B7)*Inputs!$D$5:$D$160*(((Inputs!$G$5:$G$160="moeda")+(Inputs!$G$5:$G$160="acoes"))*Inputs!$B$1+((Inputs!$G$5:$G$160<>"moeda")*(Inputs!$G$5:$G$160<>"acoes")))*INDEX(Inputs!$K$5:$AJ$160,0,MATCH(L$2,Inputs!$K$4:$AJ$4,0)))+SUMPRODUCT((Inputs!$E$5:$E$160=$B7)*Inputs!$F$5:$F$160*(((Inputs!$G$5:$G$160="moeda")+(Inputs!$G$5:$G$160="acoes"))*Inputs!$B$1+((Inputs!$G$5:$G$160<>"moeda")*(Inputs!$G$5:$G$160<>"acoes")))*INDEX(Inputs!$K$5:$AJ$160,0,MATCH(L$2,Inputs!$K$4:$AJ$4,0))))) -> -124.2846 | M7: =SUM(I7:L7) -> -455.33931 | N7: =IF(ISNA(MATCH(N$2,Inputs!$K$4:$AJ$4,0)),NA(),IF(SUMPRODUCT((Inputs!$A$5:$A$160=$B7)*ISNUMBER(INDEX(Inputs!$K$5:$AJ$160,0,MATCH(N$2,Inputs!$K$4:$AJ$4,0))))+SUMPRODUCT((Inputs!$C$5:$C$160=$B7)*ISNUMBER(INDEX(Inputs!$K$5:$AJ$160,0,MATCH(N$2,Inputs!$K$4:$AJ$4,0))))+SUMPRODUCT((Inputs!$E$5:$E$160=$B7)*ISNUMBER(INDEX(Inputs!$K$5:$AJ$160,0,MATCH(N$2,Inputs!$K$4:$AJ$4,0))))=0,NA(),SUMPRODUCT((Inputs!$A$5:$A$160=$B7)*Inputs!$B$5:$B$160*(((Inputs!$G$5:$G$160="moeda")+(Inputs!$G$5:$G$160="acoes"))*Inputs!$B$1+((Inputs!$G$5:$G$160<>"moeda")*(Inputs!$G$5:$G$160<>"acoes")))*INDEX(Inputs!$K$5:$AJ$160,0,MATCH(N$2,Inputs!$K$4:$AJ$4,0)))+SUMPRODUCT((Inputs!$C$5:$C$160=$B7)*Inputs!$D$5:$D$160*(((Inputs!$G$5:$G$160="moeda")+(Inputs!$G$5:$G$160="acoes"))*Inputs!$B$1+((Inputs!$G$5:$G$160<>"moeda")*(Inputs!$G$5:$G$160<>"acoes")))*INDEX(Inputs!$K$5:$AJ$160,0,MATCH(N$2,Inputs!$K$4:$AJ$4,0)))+SUMPRODUCT((Inputs!$E$5:$E$160=$B7)*Inputs!$F$5:$F$160*(((Inputs!$G$5:$G$160="moeda")+(Inputs!$G$5:$G$160="acoes"))*Inputs!$B$1+((Inputs!$G$5:$G$160<>"moeda")*(Inputs!$G$5:$G$160<>"acoes")))*INDEX(Inputs!$K$5:$AJ$160,0,MATCH(N$2,Inputs!$K$4:$AJ$4,0))))) -> -131.26209 | O7: =IF(ISNA(MATCH(O$2,Inputs!$K$4:$AJ$4,0)),NA(),IF(SUMPRODUCT((Inputs!$A$5:$A$160=$B7)*ISNUMBER(INDEX(Inputs!$K$5:$AJ$160,0,MATCH(O$2,Inputs!$K$4:$AJ$4,0))))+SUMPRODUCT((Inputs!$C$5:$C$160=$B7)*ISNUMBER(INDEX(Inputs!$K$5:$AJ$160,0,MATCH(O$2,Inputs!$K$4:$AJ$4,0))))+SUMPRODUCT((Inputs!$E$5:$E$160=$B7)*ISNUMBER(INDEX(Inputs!$K$5:$AJ$160,0,MATCH(O$2,Inputs!$K$4:$AJ$4,0))))=0,NA(),SUMPRODUCT((Inputs!$A$5:$A$160=$B7)*Inputs!$B$5:$B$160*(((Inputs!$G$5:$G$160="moeda")+(Inputs!$G$5:$G$160="acoes"))*Inputs!$B$1+((Inputs!$G$5:$G$160<>"moeda")*(Inputs!$G$5:$G$160<>"acoes")))*INDEX(Inputs!$K$5:$AJ$160,0,MATCH(O$2,Inputs!$K$4:$AJ$4,0)))+SUMPRODUCT((Inputs!$C$5:$C$160=$B7)*Inputs!$D$5:$D$160*(((Inputs!$G$5:$G$160="moeda")+(Inputs!$G$5:$G$160="acoes"))*Inputs!$B$1+((Inputs!$G$5:$G$160<>"moeda")*(Inputs!$G$5:$G$160<>"acoes")))*INDEX(Inputs!$K$5:$AJ$160,0,MATCH(O$2,Inputs!$K$4:$AJ$4,0)))+SUMPRODUCT((Inputs!$E$5:$E$160=$B7)*Inputs!$F$5:$F$160*(((Inputs!$G$5:$G$160="moeda")+(Inputs!$G$5:$G$160="acoes"))*Inputs!$B$1+((Inputs!$G$5:$G$160<>"moeda")*(Inputs!$G$5:$G$160<>"acoes")))*INDEX(Inputs!$K$5:$AJ$160,0,MATCH(O$2,Inputs!$K$4:$AJ$4,0))))) -> -166.076 | P7: =IF(ISNA(MATCH(P$2,Inputs!$K$4:$AJ$4,0)),NA(),IF(SUMPRODUCT((Inputs!$A$5:$A$160=$B7)*ISNUMBER(INDEX(Inputs!$K$5:$AJ$160,0,MATCH(P$2,Inputs!$K$4:$AJ$4,0))))+SUMPRODUCT((Inputs!$C$5:$C$160=$B7)*ISNUMBER(INDEX(Inputs!$K$5:$AJ$160,0,MATCH(P$2,Inputs!$K$4:$AJ$4,0))))+SUMPRODUCT((Inputs!$E$5:$E$160=$B7)*ISNUMBER(INDEX(Inputs!$K$5:$AJ$160,0,MATCH(P$2,Inputs!$K$4:$AJ$4,0))))=0,NA(),SUMPRODUCT((Inputs!$A$5:$A$160=$B7)*Inputs!$B$5:$B$160*(((Inputs!$G$5:$G$160="moeda")+(Inputs!$G$5:$G$160="acoes"))*Inputs!$B$1+((Inputs!$G$5:$G$160<>"moeda")*(Inputs!$G$5:$G$160<>"acoes")))*INDEX(Inputs!$K$5:$AJ$160,0,MATCH(P$2,Inputs!$K$4:$AJ$4,0)))+SUMPRODUCT((Inputs!$C$5:$C$160=$B7)*Inputs!$D$5:$D$160*(((Inputs!$G$5:$G$160="moeda")+(Inputs!$G$5:$G$160="acoes"))*Inputs!$B$1+((Inputs!$G$5:$G$160<>"moeda")*(Inputs!$G$5:$G$160<>"acoes")))*INDEX(Inputs!$K$5:$AJ$160,0,MATCH(P$2,Inputs!$K$4:$AJ$4,0)))+SUMPRODUCT((Inputs!$E$5:$E$160=$B7)*Inputs!$F$5:$F$160*(((Inputs!$G$5:$G$160="moeda")+(Inputs!$G$5:$G$160="acoes"))*Inputs!$B$1+((Inputs!$G$5:$G$160<>"moeda")*(Inputs!$G$5:$G$160<>"acoes")))*INDEX(Inputs!$K$5:$AJ$160,0,MATCH(P$2,Inputs!$K$4:$AJ$4,0))))) -> -188.161 | Q7: =IF(ISNA(MATCH(Q$2,Inputs!$K$4:$AJ$4,0)),NA(),IF(SUMPRODUCT((Inputs!$A$5:$A$160=$B7)*ISNUMBER(INDEX(Inputs!$K$5:$AJ$160,0,MATCH(Q$2,Inputs!$K$4:$AJ$4,0))))+SUMPRODUCT((Inputs!$C$5:$C$160=$B7)*ISNUMBER(INDEX(Inputs!$K$5:$AJ$160,0,MATCH(Q$2,Inputs!$K$4:$AJ$4,0))))+SUMPRODUCT((Inputs!$E$5:$E$160=$B7)*ISNUMBER(INDEX(Inputs!$K$5:$AJ$160,0,MATCH(Q$2,Inputs!$K$4:$AJ$4,0))))=0,NA(),SUMPRODUCT((Inputs!$A$5:$A$160=$B7)*Inputs!$B$5:$B$160*(((Inputs!$G$5:$G$160="moeda")+(Inputs!$G$5:$G$160="acoes"))*Inputs!$B$1+((Inputs!$G$5:$G$160<>"moeda")*(Inputs!$G$5:$G$160<>"acoes")))*INDEX(Inputs!$K$5:$AJ$160,0,MATCH(Q$2,Inputs!$K$4:$AJ$4,0)))+SUMPRODUCT((Inputs!$C$5:$C$160=$B7)*Inputs!$D$5:$D$160*(((Inputs!$G$5:$G$160="moeda")+(Inputs!$G$5:$G$160="acoes"))*Inputs!$B$1+((Inputs!$G$5:$G$160<>"moeda")*(Inputs!$G$5:$G$160<>"acoes")))*INDEX(Inputs!$K$5:$AJ$160,0,MATCH(Q$2,Inputs!$K$4:$AJ$4,0)))+SUMPRODUCT((Inputs!$E$5:$E$160=$B7)*Inputs!$F$5:$F$160*(((Inputs!$G$5:$G$160="moeda")+(Inputs!$G$5:$G$160="acoes"))*Inputs!$B$1+((Inputs!$G$5:$G$160<>"moeda")*(Inputs!$G$5:$G$160<>"acoes")))*INDEX(Inputs!$K$5:$AJ$160,0,MATCH(Q$2,Inputs!$K$4:$AJ$4,0))))) -> -189.879 | R7: =SUM(N7:Q7) -> -675.37809 | S7: =IF(ISNA(MATCH(S$2,Inputs!$K$4:$AJ$4,0)),NA(),IF(SUMPRODUCT((Inputs!$A$5:$A$160=$B7)*ISNUMBER(INDEX(Inputs!$K$5:$AJ$160,0,MATCH(S$2,Inputs!$K$4:$AJ$4,0))))+SUMPRODUCT((Inputs!$C$5:$C$160=$B7)*ISNUMBER(INDEX(Inputs!$K$5:$AJ$160,0,MATCH(S$2,Inputs!$K$4:$AJ$4,0))))+SUMPRODUCT((Inputs!$E$5:$E$160=$B7)*ISNUMBER(INDEX(Inputs!$K$5:$AJ$160,0,MATCH(S$2,Inputs!$K$4:$AJ$4,0))))=0,NA(),SUMPRODUCT((Inputs!$A$5:$A$160=$B7)*Inputs!$B$5:$B$160*(((Inputs!$G$5:$G$160="moeda")+(Inputs!$G$5:$G$160="acoes"))*Inputs!$B$1+((Inputs!$G$5:$G$160<>"moeda")*(Inputs!$G$5:$G$160<>"acoes")))*INDEX(Inputs!$K$5:$AJ$160,0,MATCH(S$2,Inputs!$K$4:$AJ$4,0)))+SUMPRODUCT((Inputs!$C$5:$C$160=$B7)*Inputs!$D$5:$D$160*(((Inputs!$G$5:$G$160="moeda")+(Inputs!$G$5:$G$160="acoes"))*Inputs!$B$1+((Inputs!$G$5:$G$160<>"moeda")*(Inputs!$G$5:$G$160<>"acoes")))*INDEX(Inputs!$K$5:$AJ$160,0,MATCH(S$2,Inputs!$K$4:$AJ$4,0)))+SUMPRODUCT((Inputs!$E$5:$E$160=$B7)*Inputs!$F$5:$F$160*(((Inputs!$G$5:$G$160="moeda")+(Inputs!$G$5:$G$160="acoes"))*Inputs!$B$1+((Inputs!$G$5:$G$160<>"moeda")*(Inputs!$G$5:$G$160<>"acoes")))*INDEX(Inputs!$K$5:$AJ$160,0,MATCH(S$2,Inputs!$K$4:$AJ$4,0))))) -> -189.554 | T7: =IF(ISNA(MATCH(T$2,Inputs!$K$4:$AJ$4,0)),NA(),IF(SUMPRODUCT((Inputs!$A$5:$A$160=$B7)*ISNUMBER(INDEX(Inputs!$K$5:$AJ$160,0,MATCH(T$2,Inputs!$K$4:$AJ$4,0))))+SUMPRODUCT((Inputs!$C$5:$C$160=$B7)*ISNUMBER(INDEX(Inputs!$K$5:$AJ$160,0,MATCH(T$2,Inputs!$K$4:$AJ$4,0))))+SUMPRODUCT((Inputs!$E$5:$E$160=$B7)*ISNUMBER(INDEX(Inputs!$K$5:$AJ$160,0,MATCH(T$2,Inputs!$K$4:$AJ$4,0))))=0,NA(),SUMPRODUCT((Inputs!$A$5:$A$160=$B7)*Inputs!$B$5:$B$160*(((Inputs!$G$5:$G$160="moeda")+(Inputs!$G$5:$G$160="acoes"))*Inputs!$B$1+((Inputs!$G$5:$G$160<>"moeda")*(Inputs!$G$5:$G$160<>"acoes")))*INDEX(Inputs!$K$5:$AJ$160,0,MATCH(T$2,Inputs!$K$4:$AJ$4,0)))+SUMPRODUCT((Inputs!$C$5:$C$160=$B7)*Inputs!$D$5:$D$160*(((Inputs!$G$5:$G$160="moeda")+(Inputs!$G$5:$G$160="acoes"))*Inputs!$B$1+((Inputs!$G$5:$G$160<>"moeda")*(Inputs!$G$5:$G$160<>"acoes")))*INDEX(Inputs!$K$5:$AJ$160,0,MATCH(T$2,Inputs!$K$4:$AJ$4,0)))+SUMPRODUCT((Inputs!$E$5:$E$160=$B7)*Inputs!$F$5:$F$160*(((Inputs!$G$5:$G$160="moeda")+(Inputs!$G$5:$G$160="acoes"))*Inputs!$B$1+((Inputs!$G$5:$G$160<>"moeda")*(Inputs!$G$5:$G$160<>"acoes")))*INDEX(Inputs!$K$5:$AJ$160,0,MATCH(T$2,Inputs!$K$4:$AJ$4,0))))) -> -191.804 | U7: =IF(ISNA(MATCH(U$2,Inputs!$K$4:$AJ$4,0)),NA(),IF(SUMPRODUCT((Inputs!$A$5:$A$160=$B7)*ISNUMBER(INDEX(Inputs!$K$5:$AJ$160,0,MATCH(U$2,Inputs!$K$4:$AJ$4,0))))+SUMPRODUCT((Inputs!$C$5:$C$160=$B7)*ISNUMBER(INDEX(Inputs!$K$5:$AJ$160,0,MATCH(U$2,Inputs!$K$4:$AJ$4,0))))+SUMPRODUCT((Inputs!$E$5:$E$160=$B7)*ISNUMBER(INDEX(Inputs!$K$5:$AJ$160,0,MATCH(U$2,Inputs!$K$4:$AJ$4,0))))=0,NA(),SUMPRODUCT((Inputs!$A$5:$A$160=$B7)*Inputs!$B$5:$B$160*(((Inputs!$G$5:$G$160="moeda")+(Inputs!$G$5:$G$160="acoes"))*Inputs!$B$1+((Inputs!$G$5:$G$160<>"moeda")*(Inputs!$G$5:$G$160<>"acoes")))*INDEX(Inputs!$K$5:$AJ$160,0,MATCH(U$2,Inputs!$K$4:$AJ$4,0)))+SUMPRODUCT((Inputs!$C$5:$C$160=$B7)*Inputs!$D$5:$D$160*(((Inputs!$G$5:$G$160="moeda")+(Inputs!$G$5:$G$160="acoes"))*Inputs!$B$1+((Inputs!$G$5:$G$160<>"moeda")*(Inputs!$G$5:$G$160<>"acoes")))*INDEX(Inputs!$K$5:$AJ$160,0,MATCH(U$2,Inputs!$K$4:$AJ$4,0)))+SUMPRODUCT((Inputs!$E$5:$E$160=$B7)*Inputs!$F$5:$F$160*(((Inputs!$G$5:$G$160="moeda")+(Inputs!$G$5:$G$160="acoes"))*Inputs!$B$1+((Inputs!$G$5:$G$160<>"moeda")*(Inputs!$G$5:$G$160<>"acoes")))*INDEX(Inputs!$K$5:$AJ$160,0,MATCH(U$2,Inputs!$K$4:$AJ$4,0))))) -> -196.609 | V7: =IF(ISNA(MATCH(V$2,Inputs!$K$4:$AJ$4,0)),NA(),IF(SUMPRODUCT((Inputs!$A$5:$A$160=$B7)*ISNUMBER(INDEX(Inputs!$K$5:$AJ$160,0,MATCH(V$2,Inputs!$K$4:$AJ$4,0))))+SUMPRODUCT((Inputs!$C$5:$C$160=$B7)*ISNUMBER(INDEX(Inputs!$K$5:$AJ$160,0,MATCH(V$2,Inputs!$K$4:$AJ$4,0))))+SUMPRODUCT((Inputs!$E$5:$E$160=$B7)*ISNUMBER(INDEX(Inputs!$K$5:$AJ$160,0,MATCH(V$2,Inputs!$K$4:$AJ$4,0))))=0,NA(),SUMPRODUCT((Inputs!$A$5:$A$160=$B7)*Inputs!$B$5:$B$160*(((Inputs!$G$5:$G$160="moeda")+(Inputs!$G$5:$G$160="acoes"))*Inputs!$B$1+((Inputs!$G$5:$G$160<>"moeda")*(Inputs!$G$5:$G$160<>"acoes")))*INDEX(Inputs!$K$5:$AJ$160,0,MATCH(V$2,Inputs!$K$4:$AJ$4,0)))+SUMPRODUCT((Inputs!$C$5:$C$160=$B7)*Inputs!$D$5:$D$160*(((Inputs!$G$5:$G$160="moeda")+(Inputs!$G$5:$G$160="acoes"))*Inputs!$B$1+((Inputs!$G$5:$G$160<>"moeda")*(Inputs!$G$5:$G$160<>"acoes")))*INDEX(Inputs!$K$5:$AJ$160,0,MATCH(V$2,Inputs!$K$4:$AJ$4,0)))+SUMPRODUCT((Inputs!$E$5:$E$160=$B7)*Inputs!$F$5:$F$160*(((Inputs!$G$5:$G$160="moeda")+(Inputs!$G$5:$G$160="acoes"))*Inputs!$B$1+((Inputs!$G$5:$G$160<>"moeda")*(Inputs!$G$5:$G$160<>"acoes")))*INDEX(Inputs!$K$5:$AJ$160,0,MATCH(V$2,Inputs!$K$4:$AJ$4,0))))) -> -202.016 | W7: =SUM(S7:V7) -> -779.983 | X7: =IF(ISNA(MATCH(X$2,Inputs!$K$4:$AJ$4,0)),NA(),IF(SUMPRODUCT((Inputs!$A$5:$A$160=$B7)*ISNUMBER(INDEX(Inputs!$K$5:$AJ$160,0,MATCH(X$2,Inputs!$K$4:$AJ$4,0))))+SUMPRODUCT((Inputs!$C$5:$C$160=$B7)*ISNUMBER(INDEX(Inputs!$K$5:$AJ$160,0,MATCH(X$2,Inputs!$K$4:$AJ$4,0))))+SUMPRODUCT((Inputs!$E$5:$E$160=$B7)*ISNUMBER(INDEX(Inputs!$K$5:$AJ$160,0,MATCH(X$2,Inputs!$K$4:$AJ$4,0))))=0,NA(),SUMPRODUCT((Inputs!$A$5:$A$160=$B7)*Inputs!$B$5:$B$160*(((Inputs!$G$5:$G$160="moeda")+(Inputs!$G$5:$G$160="acoes"))*Inputs!$B$1+((Inputs!$G$5:$G$160<>"moeda")*(Inputs!$G$5:$G$160<>"acoes")))*INDEX(Inputs!$K$5:$AJ$160,0,MATCH(X$2,Inputs!$K$4:$AJ$4,0)))+SUMPRODUCT((Inputs!$C$5:$C$160=$B7)*Inputs!$D$5:$D$160*(((Inputs!$G$5:$G$160="moeda")+(Inputs!$G$5:$G$160="acoes"))*Inputs!$B$1+((Inputs!$G$5:$G$160<>"moeda")*(Inputs!$G$5:$G$160<>"acoes")))*INDEX(Inputs!$K$5:$AJ$160,0,MATCH(X$2,Inputs!$K$4:$AJ$4,0)))+SUMPRODUCT((Inputs!$E$5:$E$160=$B7)*Inputs!$F$5:$F$160*(((Inputs!$G$5:$G$160="moeda")+(Inputs!$G$5:$G$160="acoes"))*Inputs!$B$1+((Inputs!$G$5:$G$160<>"moeda")*(Inputs!$G$5:$G$160<>"acoes")))*INDEX(Inputs!$K$5:$AJ$160,0,MATCH(X$2,Inputs!$K$4:$AJ$4,0))))) -> -212.14108 | Y7: =IF(ISNA(MATCH(Y$2,Inputs!$K$4:$AJ$4,0)),NA(),IF(SUMPRODUCT((Inputs!$A$5:$A$160=$B7)*ISNUMBER(INDEX(Inputs!$K$5:$AJ$160,0,MATCH(Y$2,Inputs!$K$4:$AJ$4,0))))+SUMPRODUCT((Inputs!$C$5:$C$160=$B7)*ISNUMBER(INDEX(Inputs!$K$5:$AJ$160,0,MATCH(Y$2,Inputs!$K$4:$AJ$4,0))))+SUMPRODUCT((Inputs!$E$5:$E$160=$B7)*ISNUMBER(INDEX(Inputs!$K$5:$AJ$160,0,MATCH(Y$2,Inputs!$K$4:$AJ$4,0))))=0,NA(),SUMPRODUCT((Inputs!$A$5:$A$160=$B7)*Inputs!$B$5:$B$160*(((Inputs!$G$5:$G$160="moeda")+(Inputs!$G$5:$G$160="acoes"))*Inputs!$B$1+((Inputs!$G$5:$G$160<>"moeda")*(Inputs!$G$5:$G$160<>"acoes")))*INDEX(Inputs!$K$5:$AJ$160,0,MATCH(Y$2,Inputs!$K$4:$AJ$4,0)))+SUMPRODUCT((Inputs!$C$5:$C$160=$B7)*Inputs!$D$5:$D$160*(((Inputs!$G$5:$G$160="moeda")+(Inputs!$G$5:$G$160="acoes"))*Inputs!$B$1+((Inputs!$G$5:$G$160<>"moeda")*(Inputs!$G$5:$G$160<>"acoes")))*INDEX(Inputs!$K$5:$AJ$160,0,MATCH(Y$2,Inputs!$K$4:$AJ$4,0)))+SUMPRODUCT((Inputs!$E$5:$E$160=$B7)*Inputs!$F$5:$F$160*(((Inputs!$G$5:$G$160="moeda")+(Inputs!$G$5:$G$160="acoes"))*Inputs!$B$1+((Inputs!$G$5:$G$160<>"moeda")*(Inputs!$G$5:$G$160<>"acoes")))*INDEX(Inputs!$K$5:$AJ$160,0,MATCH(Y$2,Inputs!$K$4:$AJ$4,0))))) -> -222.403 | Z7: =IF(ISNA(MATCH(Z$2,Inputs!$K$4:$AJ$4,0)),NA(),IF(SUMPRODUCT((Inputs!$A$5:$A$160=$B7)*ISNUMBER(INDEX(Inputs!$K$5:$AJ$160,0,MATCH(Z$2,Inputs!$K$4:$AJ$4,0))))+SUMPRODUCT((Inputs!$C$5:$C$160=$B7)*ISNUMBER(INDEX(Inputs!$K$5:$AJ$160,0,MATCH(Z$2,Inputs!$K$4:$AJ$4,0))))+SUMPRODUCT((Inputs!$E$5:$E$160=$B7)*ISNUMBER(INDEX(Inputs!$K$5:$AJ$160,0,MATCH(Z$2,Inputs!$K$4:$AJ$4,0))))=0,NA(),SUMPRODUCT((Inputs!$A$5:$A$160=$B7)*Inputs!$B$5:$B$160*(((Inputs!$G$5:$G$160="moeda")+(Inputs!$G$5:$G$160="acoes"))*Inputs!$B$1+((Inputs!$G$5:$G$160<>"moeda")*(Inputs!$G$5:$G$160<>"acoes")))*INDEX(Inputs!$K$5:$AJ$160,0,MATCH(Z$2,Inputs!$K$4:$AJ$4,0)))+SUMPRODUCT((Inputs!$C$5:$C$160=$B7)*Inputs!$D$5:$D$160*(((Inputs!$G$5:$G$160="moeda")+(Inputs!$G$5:$G$160="acoes"))*Inputs!$B$1+((Inputs!$G$5:$G$160<>"moeda")*(Inputs!$G$5:$G$160<>"acoes")))*INDEX(Inputs!$K$5:$AJ$160,0,MATCH(Z$2,Inputs!$K$4:$AJ$4,0)))+SUMPRODUCT((Inputs!$E$5:$E$160=$B7)*Inputs!$F$5:$F$160*(((Inputs!$G$5:$G$160="moeda")+(Inputs!$G$5:$G$160="acoes"))*Inputs!$B$1+((Inputs!$G$5:$G$160<>"moeda")*(Inputs!$G$5:$G$160<>"acoes")))*INDEX(Inputs!$K$5:$AJ$160,0,MATCH(Z$2,Inputs!$K$4:$AJ$4,0))))) -> -229.375 | AA7: =IF(ISNA(MATCH(AA$2,Inputs!$K$4:$AJ$4,0)),NA(),IF(SUMPRODUCT((Inputs!$A$5:$A$160=$B7)*ISNUMBER(INDEX(Inputs!$K$5:$AJ$160,0,MATCH(AA$2,Inputs!$K$4:$AJ$4,0))))+SUMPRODUCT((Inputs!$C$5:$C$160=$B7)*ISNUMBER(INDEX(Inputs!$K$5:$AJ$160,0,MATCH(AA$2,Inputs!$K$4:$AJ$4,0))))+SUMPRODUCT((Inputs!$E$5:$E$160=$B7)*ISNUMBER(INDEX(Inputs!$K$5:$AJ$160,0,MATCH(AA$2,Inputs!$K$4:$AJ$4,0))))=0,NA(),SUMPRODUCT((Inputs!$A$5:$A$160=$B7)*Inputs!$B$5:$B$160*(((Inputs!$G$5:$G$160="moeda")+(Inputs!$G$5:$G$160="acoes"))*Inputs!$B$1+((Inputs!$G$5:$G$160<>"moeda")*(Inputs!$G$5:$G$160<>"acoes")))*INDEX(Inputs!$K$5:$AJ$160,0,MATCH(AA$2,Inputs!$K$4:$AJ$4,0)))+SUMPRODUCT((Inputs!$C$5:$C$160=$B7)*Inputs!$D$5:$D$160*(((Inputs!$G$5:$G$160="moeda")+(Inputs!$G$5:$G$160="acoes"))*Inputs!$B$1+((Inputs!$G$5:$G$160<>"moeda")*(Inputs!$G$5:$G$160<>"acoes")))*INDEX(Inputs!$K$5:$AJ$160,0,MATCH(AA$2,Inputs!$K$4:$AJ$4,0)))+SUMPRODUCT((Inputs!$E$5:$E$160=$B7)*Inputs!$F$5:$F$160*(((Inputs!$G$5:$G$160="moeda")+(Inputs!$G$5:$G$160="acoes"))*Inputs!$B$1+((Inputs!$G$5:$G$160<>"moeda")*(Inputs!$G$5:$G$160<>"acoes")))*INDEX(Inputs!$K$5:$AJ$160,0,MATCH(AA$2,Inputs!$K$4:$AJ$4,0))))) -> -236.39186 | AB7: =SUM(X7:AA7) -> -900.31093 | AC7: =IF(ISNA(MATCH(AC$2,Inputs!$K$4:$AJ$4,0)),NA(),IF(SUMPRODUCT((Inputs!$A$5:$A$160=$B7)*ISNUMBER(INDEX(Inputs!$K$5:$AJ$160,0,MATCH(AC$2,Inputs!$K$4:$AJ$4,0))))+SUMPRODUCT((Inputs!$C$5:$C$160=$B7)*ISNUMBER(INDEX(Inputs!$K$5:$AJ$160,0,MATCH(AC$2,Inputs!$K$4:$AJ$4,0))))+SUMPRODUCT((Inputs!$E$5:$E$160=$B7)*ISNUMBER(INDEX(Inputs!$K$5:$AJ$160,0,MATCH(AC$2,Inputs!$K$4:$AJ$4,0))))=0,NA(),SUMPRODUCT((Inputs!$A$5:$A$160=$B7)*Inputs!$B$5:$B$160*(((Inputs!$G$5:$G$160="moeda")+(Inputs!$G$5:$G$160="acoes"))*Inputs!$B$1+((Inputs!$G$5:$G$160<>"moeda")*(Inputs!$G$5:$G$160<>"acoes")))*INDEX(Inputs!$K$5:$AJ$160,0,MATCH(AC$2,Inputs!$K$4:$AJ$4,0)))+SUMPRODUCT((Inputs!$C$5:$C$160=$B7)*Inputs!$D$5:$D$160*(((Inputs!$G$5:$G$160="moeda")+(Inputs!$G$5:$G$160="acoes"))*Inputs!$B$1+((Inputs!$G$5:$G$160<>"moeda")*(Inputs!$G$5:$G$160<>"acoes")))*INDEX(Inputs!$K$5:$AJ$160,0,MATCH(AC$2,Inputs!$K$4:$AJ$4,0)))+SUMPRODUCT((Inputs!$E$5:$E$160=$B7)*Inputs!$F$5:$F$160*(((Inputs!$G$5:$G$160="moeda")+(Inputs!$G$5:$G$160="acoes"))*Inputs!$B$1+((Inputs!$G$5:$G$160<>"moeda")*(Inputs!$G$5:$G$160<>"acoes")))*INDEX(Inputs!$K$5:$AJ$160,0,MATCH(AC$2,Inputs!$K$4:$AJ$4,0))))) -> -233.1217 | AD7: =IF(ISNA(MATCH(AD$2,Inputs!$K$4:$AJ$4,0)),NA(),IF(SUMPRODUCT((Inputs!$A$5:$A$160=$B7)*ISNUMBER(INDEX(Inputs!$K$5:$AJ$160,0,MATCH(AD$2,Inputs!$K$4:$AJ$4,0))))+SUMPRODUCT((Inputs!$C$5:$C$160=$B7)*ISNUMBER(INDEX(Inputs!$K$5:$AJ$160,0,MATCH(AD$2,Inputs!$K$4:$AJ$4,0))))+SUMPRODUCT((Inputs!$E$5:$E$160=$B7)*ISNUMBER(INDEX(Inputs!$K$5:$AJ$160,0,MATCH(AD$2,Inputs!$K$4:$AJ$4,0))))=0,NA(),SUMPRODUCT((Inputs!$A$5:$A$160=$B7)*Inputs!$B$5:$B$160*(((Inputs!$G$5:$G$160="moeda")+(Inputs!$G$5:$G$160="acoes"))*Inputs!$B$1+((Inputs!$G$5:$G$160<>"moeda")*(Inputs!$G$5:$G$160<>"acoes")))*INDEX(Inputs!$K$5:$AJ$160,0,MATCH(AD$2,Inputs!$K$4:$AJ$4,0)))+SUMPRODUCT((Inputs!$C$5:$C$160=$B7)*Inputs!$D$5:$D$160*(((Inputs!$G$5:$G$160="moeda")+(Inputs!$G$5:$G$160="acoes"))*Inputs!$B$1+((Inputs!$G$5:$G$160<>"moeda")*(Inputs!$G$5:$G$160<>"acoes")))*INDEX(Inputs!$K$5:$AJ$160,0,MATCH(AD$2,Inputs!$K$4:$AJ$4,0)))+SUMPRODUCT((Inputs!$E$5:$E$160=$B7)*Inputs!$F$5:$F$160*(((Inputs!$G$5:$G$160="moeda")+(Inputs!$G$5:$G$160="acoes"))*Inputs!$B$1+((Inputs!$G$5:$G$160<>"moeda")*(Inputs!$G$5:$G$160<>"acoes")))*INDEX(Inputs!$K$5:$AJ$160,0,MATCH(AD$2,Inputs!$K$4:$AJ$4,0))))) -> -215.806 | AE7: =IF(ISNA(MATCH(AE$2,Inputs!$K$4:$AJ$4,0)),NA(),IF(SUMPRODUCT((Inputs!$A$5:$A$160=$B7)*ISNUMBER(INDEX(Inputs!$K$5:$AJ$160,0,MATCH(AE$2,Inputs!$K$4:$AJ$4,0))))+SUMPRODUCT((Inputs!$C$5:$C$160=$B7)*ISNUMBER(INDEX(Inputs!$K$5:$AJ$160,0,MATCH(AE$2,Inputs!$K$4:$AJ$4,0))))+SUMPRODUCT((Inputs!$E$5:$E$160=$B7)*ISNUMBER(INDEX(Inputs!$K$5:$AJ$160,0,MATCH(AE$2,Inputs!$K$4:$AJ$4,0))))=0,NA(),SUMPRODUCT((Inputs!$A$5:$A$160=$B7)*Inputs!$B$5:$B$160*(((Inputs!$G$5:$G$160="moeda")+(Inputs!$G$5:$G$160="acoes"))*Inputs!$B$1+((Inputs!$G$5:$G$160<>"moeda")*(Inputs!$G$5:$G$160<>"acoes")))*INDEX(Inputs!$K$5:$AJ$160,0,MATCH(AE$2,Inputs!$K$4:$AJ$4,0)))+SUMPRODUCT((Inputs!$C$5:$C$160=$B7)*Inputs!$D$5:$D$160*(((Inputs!$G$5:$G$160="moeda")+(Inputs!$G$5:$G$160="acoes"))*Inputs!$B$1+((Inputs!$G$5:$G$160<>"moeda")*(Inputs!$G$5:$G$160<>"acoes")))*INDEX(Inputs!$K$5:$AJ$160,0,MATCH(AE$2,Inputs!$K$4:$AJ$4,0)))+SUMPRODUCT((Inputs!$E$5:$E$160=$B7)*Inputs!$F$5:$F$160*(((Inputs!$G$5:$G$160="moeda")+(Inputs!$G$5:$G$160="acoes"))*Inputs!$B$1+((Inputs!$G$5:$G$160<>"moeda")*(Inputs!$G$5:$G$160<>"acoes")))*INDEX(Inputs!$K$5:$AJ$160,0,MATCH(AE$2,Inputs!$K$4:$AJ$4,0))))) -> #N/A | AF7: =IF(ISNA(MATCH(AF$2,Inputs!$K$4:$AJ$4,0)),NA(),IF(SUMPRODUCT((Inputs!$A$5:$A$160=$B7)*ISNUMBER(INDEX(Inputs!$K$5:$AJ$160,0,MATCH(AF$2,Inputs!$K$4:$AJ$4,0))))+SUMPRODUCT((Inputs!$C$5:$C$160=$B7)*ISNUMBER(INDEX(Inputs!$K$5:$AJ$160,0,MATCH(AF$2,Inputs!$K$4:$AJ$4,0))))+SUMPRODUCT((Inputs!$E$5:$E$160=$B7)*ISNUMBER(INDEX(Inputs!$K$5:$AJ$160,0,MATCH(AF$2,Inputs!$K$4:$AJ$4,0))))=0,NA(),SUMPRODUCT((Inputs!$A$5:$A$160=$B7)*Inputs!$B$5:$B$160*(((Inputs!$G$5:$G$160="moeda")+(Inputs!$G$5:$G$160="acoes"))*Inputs!$B$1+((Inputs!$G$5:$G$160<>"moeda")*(Inputs!$G$5:$G$160<>"acoes")))*INDEX(Inputs!$K$5:$AJ$160,0,MATCH(AF$2,Inputs!$K$4:$AJ$4,0)))+SUMPRODUCT((Inputs!$C$5:$C$160=$B7)*Inputs!$D$5:$D$160*(((Inputs!$G$5:$G$160="moeda")+(Inputs!$G$5:$G$160="acoes"))*Inputs!$B$1+((Inputs!$G$5:$G$160<>"moeda")*(Inputs!$G$5:$G$160<>"acoes")))*INDEX(Inputs!$K$5:$AJ$160,0,MATCH(AF$2,Inputs!$K$4:$AJ$4,0)))+SUMPRODUCT((Inputs!$E$5:$E$160=$B7)*Inputs!$F$5:$F$160*(((Inputs!$G$5:$G$160="moeda")+(Inputs!$G$5:$G$160="acoes"))*Inputs!$B$1+((Inputs!$G$5:$G$160<>"moeda")*(Inputs!$G$5:$G$160<>"acoes")))*INDEX(Inputs!$K$5:$AJ$160,0,MATCH(AF$2,Inputs!$K$4:$AJ$4,0))))) -> #N/A | AG7: =SUM(AC7:AF7) -> #N/A | AH7: =IF(ISNA(MATCH(AH$2,Inputs!$K$4:$AJ$4,0)),NA(),IF(SUMPRODUCT((Inputs!$A$5:$A$160=$B7)*ISNUMBER(INDEX(Inputs!$K$5:$AJ$160,0,MATCH(AH$2,Inputs!$K$4:$AJ$4,0))))+SUMPRODUCT((Inputs!$C$5:$C$160=$B7)*ISNUMBER(INDEX(Inputs!$K$5:$AJ$160,0,MATCH(AH$2,Inputs!$K$4:$AJ$4,0))))+SUMPRODUCT((Inputs!$E$5:$E$160=$B7)*ISNUMBER(INDEX(Inputs!$K$5:$AJ$160,0,MATCH(AH$2,Inputs!$K$4:$AJ$4,0))))=0,NA(),SUMPRODUCT((Inputs!$A$5:$A$160=$B7)*Inputs!$B$5:$B$160*(((Inputs!$G$5:$G$160="moeda")+(Inputs!$G$5:$G$160="acoes"))*Inputs!$B$1+((Inputs!$G$5:$G$160<>"moeda")*(Inputs!$G$5:$G$160<>"acoes")))*INDEX(Inputs!$K$5:$AJ$160,0,MATCH(AH$2,Inputs!$K$4:$AJ$4,0)))+SUMPRODUCT((Inputs!$C$5:$C$160=$B7)*Inputs!$D$5:$D$160*(((Inputs!$G$5:$G$160="moeda")+(Inputs!$G$5:$G$160="acoes"))*Inputs!$B$1+((Inputs!$G$5:$G$160<>"moeda")*(Inputs!$G$5:$G$160<>"acoes")))*INDEX(Inputs!$K$5:$AJ$160,0,MATCH(AH$2,Inputs!$K$4:$AJ$4,0)))+SUMPRODUCT((Inputs!$E$5:$E$160=$B7)*Inputs!$F$5:$F$160*(((Inputs!$G$5:$G$160="moeda")+(Inputs!$G$5:$G$160="acoes"))*Inputs!$B$1+((Inputs!$G$5:$G$160<>"moeda")*(Inputs!$G$5:$G$160<>"acoes")))*INDEX(Inputs!$K$5:$AJ$160,0,MATCH(AH$2,Inputs!$K$4:$AJ$4,0))))) -> -87.254384 | AI7: =IF(ISNA(MATCH(AI$2,Inputs!$K$4:$AJ$4,0)),NA(),IF(SUMPRODUCT((Inputs!$A$5:$A$160=$B7)*ISNUMBER(INDEX(Inputs!$K$5:$AJ$160,0,MATCH(AI$2,Inputs!$K$4:$AJ$4,0))))+SUMPRODUCT((Inputs!$C$5:$C$160=$B7)*ISNUMBER(INDEX(Inputs!$K$5:$AJ$160,0,MATCH(AI$2,Inputs!$K$4:$AJ$4,0))))+SUMPRODUCT((Inputs!$E$5:$E$160=$B7)*ISNUMBER(INDEX(Inputs!$K$5:$AJ$160,0,MATCH(AI$2,Inputs!$K$4:$AJ$4,0))))=0,NA(),SUMPRODUCT((Inputs!$A$5:$A$160=$B7)*Inputs!$B$5:$B$160*(((Inputs!$G$5:$G$160="moeda")+(Inputs!$G$5:$G$160="acoes"))*Inputs!$B$1+((Inputs!$G$5:$G$160<>"moeda")*(Inputs!$G$5:$G$160<>"acoes")))*INDEX(Inputs!$K$5:$AJ$160,0,MATCH(AI$2,Inputs!$K$4:$AJ$4,0)))+SUMPRODUCT((Inputs!$C$5:$C$160=$B7)*Inputs!$D$5:$D$160*(((Inputs!$G$5:$G$160="moeda")+(Inputs!$G$5:$G$160="acoes"))*Inputs!$B$1+((Inputs!$G$5:$G$160<>"moeda")*(Inputs!$G$5:$G$160<>"acoes")))*INDEX(Inputs!$K$5:$AJ$160,0,MATCH(AI$2,Inputs!$K$4:$AJ$4,0)))+SUMPRODUCT((Inputs!$E$5:$E$160=$B7)*Inputs!$F$5:$F$160*(((Inputs!$G$5:$G$160="moeda")+(Inputs!$G$5:$G$160="acoes"))*Inputs!$B$1+((Inputs!$G$5:$G$160<>"moeda")*(Inputs!$G$5:$G$160<>"acoes")))*INDEX(Inputs!$K$5:$AJ$160,0,MATCH(AI$2,Inputs!$K$4:$AJ$4,0))))) -> -84.699208 | AJ7: =IF(ISNA(MATCH(AJ$2,Inputs!$K$4:$AJ$4,0)),NA(),IF(SUMPRODUCT((Inputs!$A$5:$A$160=$B7)*ISNUMBER(INDEX(Inputs!$K$5:$AJ$160,0,MATCH(AJ$2,Inputs!$K$4:$AJ$4,0))))+SUMPRODUCT((Inputs!$C$5:$C$160=$B7)*ISNUMBER(INDEX(Inputs!$K$5:$AJ$160,0,MATCH(AJ$2,Inputs!$K$4:$AJ$4,0))))+SUMPRODUCT((Inputs!$E$5:$E$160=$B7)*ISNUMBER(INDEX(Inputs!$K$5:$AJ$160,0,MATCH(AJ$2,Inputs!$K$4:$AJ$4,0))))=0,NA(),SUMPRODUCT((Inputs!$A$5:$A$160=$B7)*Inputs!$B$5:$B$160*(((Inputs!$G$5:$G$160="moeda")+(Inputs!$G$5:$G$160="acoes"))*Inputs!$B$1+((Inputs!$G$5:$G$160<>"moeda")*(Inputs!$G$5:$G$160<>"acoes")))*INDEX(Inputs!$K$5:$AJ$160,0,MATCH(AJ$2,Inputs!$K$4:$AJ$4,0)))+SUMPRODUCT((Inputs!$C$5:$C$160=$B7)*Inputs!$D$5:$D$160*(((Inputs!$G$5:$G$160="moeda")+(Inputs!$G$5:$G$160="acoes"))*Inputs!$B$1+((Inputs!$G$5:$G$160<>"moeda")*(Inputs!$G$5:$G$160<>"acoes")))*INDEX(Inputs!$K$5:$AJ$160,0,MATCH(AJ$2,Inputs!$K$4:$AJ$4,0)))+SUMPRODUCT((Inputs!$E$5:$E$160=$B7)*Inputs!$F$5:$F$160*(((Inputs!$G$5:$G$160="moeda")+(Inputs!$G$5:$G$160="acoes"))*Inputs!$B$1+((Inputs!$G$5:$G$160<>"moeda")*(Inputs!$G$5:$G$160<>"acoes")))*INDEX(Inputs!$K$5:$AJ$160,0,MATCH(AJ$2,Inputs!$K$4:$AJ$4,0))))) -> -87.780086 | AK7: =IF(ISNA(MATCH(AK$2,Inputs!$K$4:$AJ$4,0)),NA(),IF(SUMPRODUCT((Inputs!$A$5:$A$160=$B7)*ISNUMBER(INDEX(Inputs!$K$5:$AJ$160,0,MATCH(AK$2,Inputs!$K$4:$AJ$4,0))))+SUMPRODUCT((Inputs!$C$5:$C$160=$B7)*ISNUMBER(INDEX(Inputs!$K$5:$AJ$160,0,MATCH(AK$2,Inputs!$K$4:$AJ$4,0))))+SUMPRODUCT((Inputs!$E$5:$E$160=$B7)*ISNUMBER(INDEX(Inputs!$K$5:$AJ$160,0,MATCH(AK$2,Inputs!$K$4:$AJ$4,0))))=0,NA(),SUMPRODUCT((Inputs!$A$5:$A$160=$B7)*Inputs!$B$5:$B$160*(((Inputs!$G$5:$G$160="moeda")+(Inputs!$G$5:$G$160="acoes"))*Inputs!$B$1+((Inputs!$G$5:$G$160<>"moeda")*(Inputs!$G$5:$G$160<>"acoes")))*INDEX(Inputs!$K$5:$AJ$160,0,MATCH(AK$2,Inputs!$K$4:$AJ$4,0)))+SUMPRODUCT((Inputs!$C$5:$C$160=$B7)*Inputs!$D$5:$D$160*(((Inputs!$G$5:$G$160="moeda")+(Inputs!$G$5:$G$160="acoes"))*Inputs!$B$1+((Inputs!$G$5:$G$160<>"moeda")*(Inputs!$G$5:$G$160<>"acoes")))*INDEX(Inputs!$K$5:$AJ$160,0,MATCH(AK$2,Inputs!$K$4:$AJ$4,0)))+SUMPRODUCT((Inputs!$E$5:$E$160=$B7)*Inputs!$F$5:$F$160*(((Inputs!$G$5:$G$160="moeda")+(Inputs!$G$5:$G$160="acoes"))*Inputs!$B$1+((Inputs!$G$5:$G$160<>"moeda")*(Inputs!$G$5:$G$160<>"acoes")))*INDEX(Inputs!$K$5:$AJ$160,0,MATCH(AK$2,Inputs!$K$4:$AJ$4,0))))) -> -98.734274 | AL7: =SUM(AH7:AK7) -> -358.46795
B8: 5 | C8: Interest Expense | D8: =IF(ISNA(MATCH(D$2,Inputs!$K$4:$AJ$4,0)),NA(),IF(SUMPRODUCT((Inputs!$A$5:$A$160=$B8)*ISNUMBER(INDEX(Inputs!$K$5:$AJ$160,0,MATCH(D$2,Inputs!$K$4:$AJ$4,0))))+SUMPRODUCT((Inputs!$C$5:$C$160=$B8)*ISNUMBER(INDEX(Inputs!$K$5:$AJ$160,0,MATCH(D$2,Inputs!$K$4:$AJ$4,0))))+SUMPRODUCT((Inputs!$E$5:$E$160=$B8)*ISNUMBER(INDEX(Inputs!$K$5:$AJ$160,0,MATCH(D$2,Inputs!$K$4:$AJ$4,0))))=0,NA(),SUMPRODUCT((Inputs!$A$5:$A$160=$B8)*Inputs!$B$5:$B$160*(((Inputs!$G$5:$G$160="moeda")+(Inputs!$G$5:$G$160="acoes"))*Inputs!$B$1+((Inputs!$G$5:$G$160<>"moeda")*(Inputs!$G$5:$G$160<>"acoes")))*INDEX(Inputs!$K$5:$AJ$160,0,MATCH(D$2,Inputs!$K$4:$AJ$4,0)))+SUMPRODUCT((Inputs!$C$5:$C$160=$B8)*Inputs!$D$5:$D$160*(((Inputs!$G$5:$G$160="moeda")+(Inputs!$G$5:$G$160="acoes"))*Inputs!$B$1+((Inputs!$G$5:$G$160<>"moeda")*(Inputs!$G$5:$G$160<>"acoes")))*INDEX(Inputs!$K$5:$AJ$160,0,MATCH(D$2,Inputs!$K$4:$AJ$4,0)))+SUMPRODUCT((Inputs!$E$5:$E$160=$B8)*Inputs!$F$5:$F$160*(((Inputs!$G$5:$G$160="moeda")+(Inputs!$G$5:$G$160="acoes"))*Inputs!$B$1+((Inputs!$G$5:$G$160<>"moeda")*(Inputs!$G$5:$G$160<>"acoes")))*INDEX(Inputs!$K$5:$AJ$160,0,MATCH(D$2,Inputs!$K$4:$AJ$4,0))))) -> -37.428797 | E8: =IF(ISNA(MATCH(E$2,Inputs!$K$4:$AJ$4,0)),NA(),IF(SUMPRODUCT((Inputs!$A$5:$A$160=$B8)*ISNUMBER(INDEX(Inputs!$K$5:$AJ$160,0,MATCH(E$2,Inputs!$K$4:$AJ$4,0))))+SUMPRODUCT((Inputs!$C$5:$C$160=$B8)*ISNUMBER(INDEX(Inputs!$K$5:$AJ$160,0,MATCH(E$2,Inputs!$K$4:$AJ$4,0))))+SUMPRODUCT((Inputs!$E$5:$E$160=$B8)*ISNUMBER(INDEX(Inputs!$K$5:$AJ$160,0,MATCH(E$2,Inputs!$K$4:$AJ$4,0))))=0,NA(),SUMPRODUCT((Inputs!$A$5:$A$160=$B8)*Inputs!$B$5:$B$160*(((Inputs!$G$5:$G$160="moeda")+(Inputs!$G$5:$G$160="acoes"))*Inputs!$B$1+((Inputs!$G$5:$G$160<>"moeda")*(Inputs!$G$5:$G$160<>"acoes")))*INDEX(Inputs!$K$5:$AJ$160,0,MATCH(E$2,Inputs!$K$4:$AJ$4,0)))+SUMPRODUCT((Inputs!$C$5:$C$160=$B8)*Inputs!$D$5:$D$160*(((Inputs!$G$5:$G$160="moeda")+(Inputs!$G$5:$G$160="acoes"))*Inputs!$B$1+((Inputs!$G$5:$G$160<>"moeda")*(Inputs!$G$5:$G$160<>"acoes")))*INDEX(Inputs!$K$5:$AJ$160,0,MATCH(E$2,Inputs!$K$4:$AJ$4,0)))+SUMPRODUCT((Inputs!$E$5:$E$160=$B8)*Inputs!$F$5:$F$160*(((Inputs!$G$5:$G$160="moeda")+(Inputs!$G$5:$G$160="acoes"))*Inputs!$B$1+((Inputs!$G$5:$G$160<>"moeda")*(Inputs!$G$5:$G$160<>"acoes")))*INDEX(Inputs!$K$5:$AJ$160,0,MATCH(E$2,Inputs!$K$4:$AJ$4,0))))) -> -43.008567 | F8: =IF(ISNA(MATCH(F$2,Inputs!$K$4:$AJ$4,0)),NA(),IF(SUMPRODUCT((Inputs!$A$5:$A$160=$B8)*ISNUMBER(INDEX(Inputs!$K$5:$AJ$160,0,MATCH(F$2,Inputs!$K$4:$AJ$4,0))))+SUMPRODUCT((Inputs!$C$5:$C$160=$B8)*ISNUMBER(INDEX(Inputs!$K$5:$AJ$160,0,MATCH(F$2,Inputs!$K$4:$AJ$4,0))))+SUMPRODUCT((Inputs!$E$5:$E$160=$B8)*ISNUMBER(INDEX(Inputs!$K$5:$AJ$160,0,MATCH(F$2,Inputs!$K$4:$AJ$4,0))))=0,NA(),SUMPRODUCT((Inputs!$A$5:$A$160=$B8)*Inputs!$B$5:$B$160*(((Inputs!$G$5:$G$160="moeda")+(Inputs!$G$5:$G$160="acoes"))*Inputs!$B$1+((Inputs!$G$5:$G$160<>"moeda")*(Inputs!$G$5:$G$160<>"acoes")))*INDEX(Inputs!$K$5:$AJ$160,0,MATCH(F$2,Inputs!$K$4:$AJ$4,0)))+SUMPRODUCT((Inputs!$C$5:$C$160=$B8)*Inputs!$D$5:$D$160*(((Inputs!$G$5:$G$160="moeda")+(Inputs!$G$5:$G$160="acoes"))*Inputs!$B$1+((Inputs!$G$5:$G$160<>"moeda")*(Inputs!$G$5:$G$160<>"acoes")))*INDEX(Inputs!$K$5:$AJ$160,0,MATCH(F$2,Inputs!$K$4:$AJ$4,0)))+SUMPRODUCT((Inputs!$E$5:$E$160=$B8)*Inputs!$F$5:$F$160*(((Inputs!$G$5:$G$160="moeda")+(Inputs!$G$5:$G$160="acoes"))*Inputs!$B$1+((Inputs!$G$5:$G$160<>"moeda")*(Inputs!$G$5:$G$160<>"acoes")))*INDEX(Inputs!$K$5:$AJ$160,0,MATCH(F$2,Inputs!$K$4:$AJ$4,0))))) -> -65.281097 | G8: =IF(ISNA(MATCH(G$2,Inputs!$K$4:$AJ$4,0)),NA(),IF(SUMPRODUCT((Inputs!$A$5:$A$160=$B8)*ISNUMBER(INDEX(Inputs!$K$5:$AJ$160,0,MATCH(G$2,Inputs!$K$4:$AJ$4,0))))+SUMPRODUCT((Inputs!$C$5:$C$160=$B8)*ISNUMBER(INDEX(Inputs!$K$5:$AJ$160,0,MATCH(G$2,Inputs!$K$4:$AJ$4,0))))+SUMPRODUCT((Inputs!$E$5:$E$160=$B8)*ISNUMBER(INDEX(Inputs!$K$5:$AJ$160,0,MATCH(G$2,Inputs!$K$4:$AJ$4,0))))=0,NA(),SUMPRODUCT((Inputs!$A$5:$A$160=$B8)*Inputs!$B$5:$B$160*(((Inputs!$G$5:$G$160="moeda")+(Inputs!$G$5:$G$160="acoes"))*Inputs!$B$1+((Inputs!$G$5:$G$160<>"moeda")*(Inputs!$G$5:$G$160<>"acoes")))*INDEX(Inputs!$K$5:$AJ$160,0,MATCH(G$2,Inputs!$K$4:$AJ$4,0)))+SUMPRODUCT((Inputs!$C$5:$C$160=$B8)*Inputs!$D$5:$D$160*(((Inputs!$G$5:$G$160="moeda")+(Inputs!$G$5:$G$160="acoes"))*Inputs!$B$1+((Inputs!$G$5:$G$160<>"moeda")*(Inputs!$G$5:$G$160<>"acoes")))*INDEX(Inputs!$K$5:$AJ$160,0,MATCH(G$2,Inputs!$K$4:$AJ$4,0)))+SUMPRODUCT((Inputs!$E$5:$E$160=$B8)*Inputs!$F$5:$F$160*(((Inputs!$G$5:$G$160="moeda")+(Inputs!$G$5:$G$160="acoes"))*Inputs!$B$1+((Inputs!$G$5:$G$160<>"moeda")*(Inputs!$G$5:$G$160<>"acoes")))*INDEX(Inputs!$K$5:$AJ$160,0,MATCH(G$2,Inputs!$K$4:$AJ$4,0))))) -> -74.312023 | H8: =SUM(D8:G8) -> -220.03048 | I8: =IF(ISNA(MATCH(I$2,Inputs!$K$4:$AJ$4,0)),NA(),IF(SUMPRODUCT((Inputs!$A$5:$A$160=$B8)*ISNUMBER(INDEX(Inputs!$K$5:$AJ$160,0,MATCH(I$2,Inputs!$K$4:$AJ$4,0))))+SUMPRODUCT((Inputs!$C$5:$C$160=$B8)*ISNUMBER(INDEX(Inputs!$K$5:$AJ$160,0,MATCH(I$2,Inputs!$K$4:$AJ$4,0))))+SUMPRODUCT((Inputs!$E$5:$E$160=$B8)*ISNUMBER(INDEX(Inputs!$K$5:$AJ$160,0,MATCH(I$2,Inputs!$K$4:$AJ$4,0))))=0,NA(),SUMPRODUCT((Inputs!$A$5:$A$160=$B8)*Inputs!$B$5:$B$160*(((Inputs!$G$5:$G$160="moeda")+(Inputs!$G$5:$G$160="acoes"))*Inputs!$B$1+((Inputs!$G$5:$G$160<>"moeda")*(Inputs!$G$5:$G$160<>"acoes")))*INDEX(Inputs!$K$5:$AJ$160,0,MATCH(I$2,Inputs!$K$4:$AJ$4,0)))+SUMPRODUCT((Inputs!$C$5:$C$160=$B8)*Inputs!$D$5:$D$160*(((Inputs!$G$5:$G$160="moeda")+(Inputs!$G$5:$G$160="acoes"))*Inputs!$B$1+((Inputs!$G$5:$G$160<>"moeda")*(Inputs!$G$5:$G$160<>"acoes")))*INDEX(Inputs!$K$5:$AJ$160,0,MATCH(I$2,Inputs!$K$4:$AJ$4,0)))+SUMPRODUCT((Inputs!$E$5:$E$160=$B8)*Inputs!$F$5:$F$160*(((Inputs!$G$5:$G$160="moeda")+(Inputs!$G$5:$G$160="acoes"))*Inputs!$B$1+((Inputs!$G$5:$G$160<>"moeda")*(Inputs!$G$5:$G$160<>"acoes")))*INDEX(Inputs!$K$5:$AJ$160,0,MATCH(I$2,Inputs!$K$4:$AJ$4,0))))) -> -85.808391 | J8: =IF(ISNA(MATCH(J$2,Inputs!$K$4:$AJ$4,0)),NA(),IF(SUMPRODUCT((Inputs!$A$5:$A$160=$B8)*ISNUMBER(INDEX(Inputs!$K$5:$AJ$160,0,MATCH(J$2,Inputs!$K$4:$AJ$4,0))))+SUMPRODUCT((Inputs!$C$5:$C$160=$B8)*ISNUMBER(INDEX(Inputs!$K$5:$AJ$160,0,MATCH(J$2,Inputs!$K$4:$AJ$4,0))))+SUMPRODUCT((Inputs!$E$5:$E$160=$B8)*ISNUMBER(INDEX(Inputs!$K$5:$AJ$160,0,MATCH(J$2,Inputs!$K$4:$AJ$4,0))))=0,NA(),SUMPRODUCT((Inputs!$A$5:$A$160=$B8)*Inputs!$B$5:$B$160*(((Inputs!$G$5:$G$160="moeda")+(Inputs!$G$5:$G$160="acoes"))*Inputs!$B$1+((Inputs!$G$5:$G$160<>"moeda")*(Inputs!$G$5:$G$160<>"acoes")))*INDEX(Inputs!$K$5:$AJ$160,0,MATCH(J$2,Inputs!$K$4:$AJ$4,0)))+SUMPRODUCT((Inputs!$C$5:$C$160=$B8)*Inputs!$D$5:$D$160*(((Inputs!$G$5:$G$160="moeda")+(Inputs!$G$5:$G$160="acoes"))*Inputs!$B$1+((Inputs!$G$5:$G$160<>"moeda")*(Inputs!$G$5:$G$160<>"acoes")))*INDEX(Inputs!$K$5:$AJ$160,0,MATCH(J$2,Inputs!$K$4:$AJ$4,0)))+SUMPRODUCT((Inputs!$E$5:$E$160=$B8)*Inputs!$F$5:$F$160*(((Inputs!$G$5:$G$160="moeda")+(Inputs!$G$5:$G$160="acoes"))*Inputs!$B$1+((Inputs!$G$5:$G$160<>"moeda")*(Inputs!$G$5:$G$160<>"acoes")))*INDEX(Inputs!$K$5:$AJ$160,0,MATCH(J$2,Inputs!$K$4:$AJ$4,0))))) -> -107.82061 | K8: =IF(ISNA(MATCH(K$2,Inputs!$K$4:$AJ$4,0)),NA(),IF(SUMPRODUCT((Inputs!$A$5:$A$160=$B8)*ISNUMBER(INDEX(Inputs!$K$5:$AJ$160,0,MATCH(K$2,Inputs!$K$4:$AJ$4,0))))+SUMPRODUCT((Inputs!$C$5:$C$160=$B8)*ISNUMBER(INDEX(Inputs!$K$5:$AJ$160,0,MATCH(K$2,Inputs!$K$4:$AJ$4,0))))+SUMPRODUCT((Inputs!$E$5:$E$160=$B8)*ISNUMBER(INDEX(Inputs!$K$5:$AJ$160,0,MATCH(K$2,Inputs!$K$4:$AJ$4,0))))=0,NA(),SUMPRODUCT((Inputs!$A$5:$A$160=$B8)*Inputs!$B$5:$B$160*(((Inputs!$G$5:$G$160="moeda")+(Inputs!$G$5:$G$160="acoes"))*Inputs!$B$1+((Inputs!$G$5:$G$160<>"moeda")*(Inputs!$G$5:$G$160<>"acoes")))*INDEX(Inputs!$K$5:$AJ$160,0,MATCH(K$2,Inputs!$K$4:$AJ$4,0)))+SUMPRODUCT((Inputs!$C$5:$C$160=$B8)*Inputs!$D$5:$D$160*(((Inputs!$G$5:$G$160="moeda")+(Inputs!$G$5:$G$160="acoes"))*Inputs!$B$1+((Inputs!$G$5:$G$160<>"moeda")*(Inputs!$G$5:$G$160<>"acoes")))*INDEX(Inputs!$K$5:$AJ$160,0,MATCH(K$2,Inputs!$K$4:$AJ$4,0)))+SUMPRODUCT((Inputs!$E$5:$E$160=$B8)*Inputs!$F$5:$F$160*(((Inputs!$G$5:$G$160="moeda")+(Inputs!$G$5:$G$160="acoes"))*Inputs!$B$1+((Inputs!$G$5:$G$160<>"moeda")*(Inputs!$G$5:$G$160<>"acoes")))*INDEX(Inputs!$K$5:$AJ$160,0,MATCH(K$2,Inputs!$K$4:$AJ$4,0))))) -> -128.36534 | L8: =IF(ISNA(MATCH(L$2,Inputs!$K$4:$AJ$4,0)),NA(),IF(SUMPRODUCT((Inputs!$A$5:$A$160=$B8)*ISNUMBER(INDEX(Inputs!$K$5:$AJ$160,0,MATCH(L$2,Inputs!$K$4:$AJ$4,0))))+SUMPRODUCT((Inputs!$C$5:$C$160=$B8)*ISNUMBER(INDEX(Inputs!$K$5:$AJ$160,0,MATCH(L$2,Inputs!$K$4:$AJ$4,0))))+SUMPRODUCT((Inputs!$E$5:$E$160=$B8)*ISNUMBER(INDEX(Inputs!$K$5:$AJ$160,0,MATCH(L$2,Inputs!$K$4:$AJ$4,0))))=0,NA(),SUMPRODUCT((Inputs!$A$5:$A$160=$B8)*Inputs!$B$5:$B$160*(((Inputs!$G$5:$G$160="moeda")+(Inputs!$G$5:$G$160="acoes"))*Inputs!$B$1+((Inputs!$G$5:$G$160<>"moeda")*(Inputs!$G$5:$G$160<>"acoes")))*INDEX(Inputs!$K$5:$AJ$160,0,MATCH(L$2,Inputs!$K$4:$AJ$4,0)))+SUMPRODUCT((Inputs!$C$5:$C$160=$B8)*Inputs!$D$5:$D$160*(((Inputs!$G$5:$G$160="moeda")+(Inputs!$G$5:$G$160="acoes"))*Inputs!$B$1+((Inputs!$G$5:$G$160<>"moeda")*(Inputs!$G$5:$G$160<>"acoes")))*INDEX(Inputs!$K$5:$AJ$160,0,MATCH(L$2,Inputs!$K$4:$AJ$4,0)))+SUMPRODUCT((Inputs!$E$5:$E$160=$B8)*Inputs!$F$5:$F$160*(((Inputs!$G$5:$G$160="moeda")+(Inputs!$G$5:$G$160="acoes"))*Inputs!$B$1+((Inputs!$G$5:$G$160<>"moeda")*(Inputs!$G$5:$G$160<>"acoes")))*INDEX(Inputs!$K$5:$AJ$160,0,MATCH(L$2,Inputs!$K$4:$AJ$4,0))))) -> -121.04447 | M8: =SUM(I8:L8) -> -443.03881 | N8: =IF(ISNA(MATCH(N$2,Inputs!$K$4:$AJ$4,0)),NA(),IF(SUMPRODUCT((Inputs!$A$5:$A$160=$B8)*ISNUMBER(INDEX(Inputs!$K$5:$AJ$160,0,MATCH(N$2,Inputs!$K$4:$AJ$4,0))))+SUMPRODUCT((Inputs!$C$5:$C$160=$B8)*ISNUMBER(INDEX(Inputs!$K$5:$AJ$160,0,MATCH(N$2,Inputs!$K$4:$AJ$4,0))))+SUMPRODUCT((Inputs!$E$5:$E$160=$B8)*ISNUMBER(INDEX(Inputs!$K$5:$AJ$160,0,MATCH(N$2,Inputs!$K$4:$AJ$4,0))))=0,NA(),SUMPRODUCT((Inputs!$A$5:$A$160=$B8)*Inputs!$B$5:$B$160*(((Inputs!$G$5:$G$160="moeda")+(Inputs!$G$5:$G$160="acoes"))*Inputs!$B$1+((Inputs!$G$5:$G$160<>"moeda")*(Inputs!$G$5:$G$160<>"acoes")))*INDEX(Inputs!$K$5:$AJ$160,0,MATCH(N$2,Inputs!$K$4:$AJ$4,0)))+SUMPRODUCT((Inputs!$C$5:$C$160=$B8)*Inputs!$D$5:$D$160*(((Inputs!$G$5:$G$160="moeda")+(Inputs!$G$5:$G$160="acoes"))*Inputs!$B$1+((Inputs!$G$5:$G$160<>"moeda")*(Inputs!$G$5:$G$160<>"acoes")))*INDEX(Inputs!$K$5:$AJ$160,0,MATCH(N$2,Inputs!$K$4:$AJ$4,0)))+SUMPRODUCT((Inputs!$E$5:$E$160=$B8)*Inputs!$F$5:$F$160*(((Inputs!$G$5:$G$160="moeda")+(Inputs!$G$5:$G$160="acoes"))*Inputs!$B$1+((Inputs!$G$5:$G$160<>"moeda")*(Inputs!$G$5:$G$160<>"acoes")))*INDEX(Inputs!$K$5:$AJ$160,0,MATCH(N$2,Inputs!$K$4:$AJ$4,0))))) -> -134.54669 | O8: =IF(ISNA(MATCH(O$2,Inputs!$K$4:$AJ$4,0)),NA(),IF(SUMPRODUCT((Inputs!$A$5:$A$160=$B8)*ISNUMBER(INDEX(Inputs!$K$5:$AJ$160,0,MATCH(O$2,Inputs!$K$4:$AJ$4,0))))+SUMPRODUCT((Inputs!$C$5:$C$160=$B8)*ISNUMBER(INDEX(Inputs!$K$5:$AJ$160,0,MATCH(O$2,Inputs!$K$4:$AJ$4,0))))+SUMPRODUCT((Inputs!$E$5:$E$160=$B8)*ISNUMBER(INDEX(Inputs!$K$5:$AJ$160,0,MATCH(O$2,Inputs!$K$4:$AJ$4,0))))=0,NA(),SUMPRODUCT((Inputs!$A$5:$A$160=$B8)*Inputs!$B$5:$B$160*(((Inputs!$G$5:$G$160="moeda")+(Inputs!$G$5:$G$160="acoes"))*Inputs!$B$1+((Inputs!$G$5:$G$160<>"moeda")*(Inputs!$G$5:$G$160<>"acoes")))*INDEX(Inputs!$K$5:$AJ$160,0,MATCH(O$2,Inputs!$K$4:$AJ$4,0)))+SUMPRODUCT((Inputs!$C$5:$C$160=$B8)*Inputs!$D$5:$D$160*(((Inputs!$G$5:$G$160="moeda")+(Inputs!$G$5:$G$160="acoes"))*Inputs!$B$1+((Inputs!$G$5:$G$160<>"moeda")*(Inputs!$G$5:$G$160<>"acoes")))*INDEX(Inputs!$K$5:$AJ$160,0,MATCH(O$2,Inputs!$K$4:$AJ$4,0)))+SUMPRODUCT((Inputs!$E$5:$E$160=$B8)*Inputs!$F$5:$F$160*(((Inputs!$G$5:$G$160="moeda")+(Inputs!$G$5:$G$160="acoes"))*Inputs!$B$1+((Inputs!$G$5:$G$160<>"moeda")*(Inputs!$G$5:$G$160<>"acoes")))*INDEX(Inputs!$K$5:$AJ$160,0,MATCH(O$2,Inputs!$K$4:$AJ$4,0))))) -> -158.38863 | P8: =IF(ISNA(MATCH(P$2,Inputs!$K$4:$AJ$4,0)),NA(),IF(SUMPRODUCT((Inputs!$A$5:$A$160=$B8)*ISNUMBER(INDEX(Inputs!$K$5:$AJ$160,0,MATCH(P$2,Inputs!$K$4:$AJ$4,0))))+SUMPRODUCT((Inputs!$C$5:$C$160=$B8)*ISNUMBER(INDEX(Inputs!$K$5:$AJ$160,0,MATCH(P$2,Inputs!$K$4:$AJ$4,0))))+SUMPRODUCT((Inputs!$E$5:$E$160=$B8)*ISNUMBER(INDEX(Inputs!$K$5:$AJ$160,0,MATCH(P$2,Inputs!$K$4:$AJ$4,0))))=0,NA(),SUMPRODUCT((Inputs!$A$5:$A$160=$B8)*Inputs!$B$5:$B$160*(((Inputs!$G$5:$G$160="moeda")+(Inputs!$G$5:$G$160="acoes"))*Inputs!$B$1+((Inputs!$G$5:$G$160<>"moeda")*(Inputs!$G$5:$G$160<>"acoes")))*INDEX(Inputs!$K$5:$AJ$160,0,MATCH(P$2,Inputs!$K$4:$AJ$4,0)))+SUMPRODUCT((Inputs!$C$5:$C$160=$B8)*Inputs!$D$5:$D$160*(((Inputs!$G$5:$G$160="moeda")+(Inputs!$G$5:$G$160="acoes"))*Inputs!$B$1+((Inputs!$G$5:$G$160<>"moeda")*(Inputs!$G$5:$G$160<>"acoes")))*INDEX(Inputs!$K$5:$AJ$160,0,MATCH(P$2,Inputs!$K$4:$AJ$4,0)))+SUMPRODUCT((Inputs!$E$5:$E$160=$B8)*Inputs!$F$5:$F$160*(((Inputs!$G$5:$G$160="moeda")+(Inputs!$G$5:$G$160="acoes"))*Inputs!$B$1+((Inputs!$G$5:$G$160<>"moeda")*(Inputs!$G$5:$G$160<>"acoes")))*INDEX(Inputs!$K$5:$AJ$160,0,MATCH(P$2,Inputs!$K$4:$AJ$4,0))))) -> -163.758 | Q8: =IF(ISNA(MATCH(Q$2,Inputs!$K$4:$AJ$4,0)),NA(),IF(SUMPRODUCT((Inputs!$A$5:$A$160=$B8)*ISNUMBER(INDEX(Inputs!$K$5:$AJ$160,0,MATCH(Q$2,Inputs!$K$4:$AJ$4,0))))+SUMPRODUCT((Inputs!$C$5:$C$160=$B8)*ISNUMBER(INDEX(Inputs!$K$5:$AJ$160,0,MATCH(Q$2,Inputs!$K$4:$AJ$4,0))))+SUMPRODUCT((Inputs!$E$5:$E$160=$B8)*ISNUMBER(INDEX(Inputs!$K$5:$AJ$160,0,MATCH(Q$2,Inputs!$K$4:$AJ$4,0))))=0,NA(),SUMPRODUCT((Inputs!$A$5:$A$160=$B8)*Inputs!$B$5:$B$160*(((Inputs!$G$5:$G$160="moeda")+(Inputs!$G$5:$G$160="acoes"))*Inputs!$B$1+((Inputs!$G$5:$G$160<>"moeda")*(Inputs!$G$5:$G$160<>"acoes")))*INDEX(Inputs!$K$5:$AJ$160,0,MATCH(Q$2,Inputs!$K$4:$AJ$4,0)))+SUMPRODUCT((Inputs!$C$5:$C$160=$B8)*Inputs!$D$5:$D$160*(((Inputs!$G$5:$G$160="moeda")+(Inputs!$G$5:$G$160="acoes"))*Inputs!$B$1+((Inputs!$G$5:$G$160<>"moeda")*(Inputs!$G$5:$G$160<>"acoes")))*INDEX(Inputs!$K$5:$AJ$160,0,MATCH(Q$2,Inputs!$K$4:$AJ$4,0)))+SUMPRODUCT((Inputs!$E$5:$E$160=$B8)*Inputs!$F$5:$F$160*(((Inputs!$G$5:$G$160="moeda")+(Inputs!$G$5:$G$160="acoes"))*Inputs!$B$1+((Inputs!$G$5:$G$160<>"moeda")*(Inputs!$G$5:$G$160<>"acoes")))*INDEX(Inputs!$K$5:$AJ$160,0,MATCH(Q$2,Inputs!$K$4:$AJ$4,0))))) -> -148.22368 | R8: =SUM(N8:Q8) -> -604.917 | S8: =IF(ISNA(MATCH(S$2,Inputs!$K$4:$AJ$4,0)),NA(),IF(SUMPRODUCT((Inputs!$A$5:$A$160=$B8)*ISNUMBER(INDEX(Inputs!$K$5:$AJ$160,0,MATCH(S$2,Inputs!$K$4:$AJ$4,0))))+SUMPRODUCT((Inputs!$C$5:$C$160=$B8)*ISNUMBER(INDEX(Inputs!$K$5:$AJ$160,0,MATCH(S$2,Inputs!$K$4:$AJ$4,0))))+SUMPRODUCT((Inputs!$E$5:$E$160=$B8)*ISNUMBER(INDEX(Inputs!$K$5:$AJ$160,0,MATCH(S$2,Inputs!$K$4:$AJ$4,0))))=0,NA(),SUMPRODUCT((Inputs!$A$5:$A$160=$B8)*Inputs!$B$5:$B$160*(((Inputs!$G$5:$G$160="moeda")+(Inputs!$G$5:$G$160="acoes"))*Inputs!$B$1+((Inputs!$G$5:$G$160<>"moeda")*(Inputs!$G$5:$G$160<>"acoes")))*INDEX(Inputs!$K$5:$AJ$160,0,MATCH(S$2,Inputs!$K$4:$AJ$4,0)))+SUMPRODUCT((Inputs!$C$5:$C$160=$B8)*Inputs!$D$5:$D$160*(((Inputs!$G$5:$G$160="moeda")+(Inputs!$G$5:$G$160="acoes"))*Inputs!$B$1+((Inputs!$G$5:$G$160<>"moeda")*(Inputs!$G$5:$G$160<>"acoes")))*INDEX(Inputs!$K$5:$AJ$160,0,MATCH(S$2,Inputs!$K$4:$AJ$4,0)))+SUMPRODUCT((Inputs!$E$5:$E$160=$B8)*Inputs!$F$5:$F$160*(((Inputs!$G$5:$G$160="moeda")+(Inputs!$G$5:$G$160="acoes"))*Inputs!$B$1+((Inputs!$G$5:$G$160<>"moeda")*(Inputs!$G$5:$G$160<>"acoes")))*INDEX(Inputs!$K$5:$AJ$160,0,MATCH(S$2,Inputs!$K$4:$AJ$4,0))))) -> -146.74136 | T8: =IF(ISNA(MATCH(T$2,Inputs!$K$4:$AJ$4,0)),NA(),IF(SUMPRODUCT((Inputs!$A$5:$A$160=$B8)*ISNUMBER(INDEX(Inputs!$K$5:$AJ$160,0,MATCH(T$2,Inputs!$K$4:$AJ$4,0))))+SUMPRODUCT((Inputs!$C$5:$C$160=$B8)*ISNUMBER(INDEX(Inputs!$K$5:$AJ$160,0,MATCH(T$2,Inputs!$K$4:$AJ$4,0))))+SUMPRODUCT((Inputs!$E$5:$E$160=$B8)*ISNUMBER(INDEX(Inputs!$K$5:$AJ$160,0,MATCH(T$2,Inputs!$K$4:$AJ$4,0))))=0,NA(),SUMPRODUCT((Inputs!$A$5:$A$160=$B8)*Inputs!$B$5:$B$160*(((Inputs!$G$5:$G$160="moeda")+(Inputs!$G$5:$G$160="acoes"))*Inputs!$B$1+((Inputs!$G$5:$G$160<>"moeda")*(Inputs!$G$5:$G$160<>"acoes")))*INDEX(Inputs!$K$5:$AJ$160,0,MATCH(T$2,Inputs!$K$4:$AJ$4,0)))+SUMPRODUCT((Inputs!$C$5:$C$160=$B8)*Inputs!$D$5:$D$160*(((Inputs!$G$5:$G$160="moeda")+(Inputs!$G$5:$G$160="acoes"))*Inputs!$B$1+((Inputs!$G$5:$G$160<>"moeda")*(Inputs!$G$5:$G$160<>"acoes")))*INDEX(Inputs!$K$5:$AJ$160,0,MATCH(T$2,Inputs!$K$4:$AJ$4,0)))+SUMPRODUCT((Inputs!$E$5:$E$160=$B8)*Inputs!$F$5:$F$160*(((Inputs!$G$5:$G$160="moeda")+(Inputs!$G$5:$G$160="acoes"))*Inputs!$B$1+((Inputs!$G$5:$G$160<>"moeda")*(Inputs!$G$5:$G$160<>"acoes")))*INDEX(Inputs!$K$5:$AJ$160,0,MATCH(T$2,Inputs!$K$4:$AJ$4,0))))) -> -140.543 | U8: =IF(ISNA(MATCH(U$2,Inputs!$K$4:$AJ$4,0)),NA(),IF(SUMPRODUCT((Inputs!$A$5:$A$160=$B8)*ISNUMBER(INDEX(Inputs!$K$5:$AJ$160,0,MATCH(U$2,Inputs!$K$4:$AJ$4,0))))+SUMPRODUCT((Inputs!$C$5:$C$160=$B8)*ISNUMBER(INDEX(Inputs!$K$5:$AJ$160,0,MATCH(U$2,Inputs!$K$4:$AJ$4,0))))+SUMPRODUCT((Inputs!$E$5:$E$160=$B8)*ISNUMBER(INDEX(Inputs!$K$5:$AJ$160,0,MATCH(U$2,Inputs!$K$4:$AJ$4,0))))=0,NA(),SUMPRODUCT((Inputs!$A$5:$A$160=$B8)*Inputs!$B$5:$B$160*(((Inputs!$G$5:$G$160="moeda")+(Inputs!$G$5:$G$160="acoes"))*Inputs!$B$1+((Inputs!$G$5:$G$160<>"moeda")*(Inputs!$G$5:$G$160<>"acoes")))*INDEX(Inputs!$K$5:$AJ$160,0,MATCH(U$2,Inputs!$K$4:$AJ$4,0)))+SUMPRODUCT((Inputs!$C$5:$C$160=$B8)*Inputs!$D$5:$D$160*(((Inputs!$G$5:$G$160="moeda")+(Inputs!$G$5:$G$160="acoes"))*Inputs!$B$1+((Inputs!$G$5:$G$160<>"moeda")*(Inputs!$G$5:$G$160<>"acoes")))*INDEX(Inputs!$K$5:$AJ$160,0,MATCH(U$2,Inputs!$K$4:$AJ$4,0)))+SUMPRODUCT((Inputs!$E$5:$E$160=$B8)*Inputs!$F$5:$F$160*(((Inputs!$G$5:$G$160="moeda")+(Inputs!$G$5:$G$160="acoes"))*Inputs!$B$1+((Inputs!$G$5:$G$160<>"moeda")*(Inputs!$G$5:$G$160<>"acoes")))*INDEX(Inputs!$K$5:$AJ$160,0,MATCH(U$2,Inputs!$K$4:$AJ$4,0))))) -> -158.257 | V8: =IF(ISNA(MATCH(V$2,Inputs!$K$4:$AJ$4,0)),NA(),IF(SUMPRODUCT((Inputs!$A$5:$A$160=$B8)*ISNUMBER(INDEX(Inputs!$K$5:$AJ$160,0,MATCH(V$2,Inputs!$K$4:$AJ$4,0))))+SUMPRODUCT((Inputs!$C$5:$C$160=$B8)*ISNUMBER(INDEX(Inputs!$K$5:$AJ$160,0,MATCH(V$2,Inputs!$K$4:$AJ$4,0))))+SUMPRODUCT((Inputs!$E$5:$E$160=$B8)*ISNUMBER(INDEX(Inputs!$K$5:$AJ$160,0,MATCH(V$2,Inputs!$K$4:$AJ$4,0))))=0,NA(),SUMPRODUCT((Inputs!$A$5:$A$160=$B8)*Inputs!$B$5:$B$160*(((Inputs!$G$5:$G$160="moeda")+(Inputs!$G$5:$G$160="acoes"))*Inputs!$B$1+((Inputs!$G$5:$G$160<>"moeda")*(Inputs!$G$5:$G$160<>"acoes")))*INDEX(Inputs!$K$5:$AJ$160,0,MATCH(V$2,Inputs!$K$4:$AJ$4,0)))+SUMPRODUCT((Inputs!$C$5:$C$160=$B8)*Inputs!$D$5:$D$160*(((Inputs!$G$5:$G$160="moeda")+(Inputs!$G$5:$G$160="acoes"))*Inputs!$B$1+((Inputs!$G$5:$G$160<>"moeda")*(Inputs!$G$5:$G$160<>"acoes")))*INDEX(Inputs!$K$5:$AJ$160,0,MATCH(V$2,Inputs!$K$4:$AJ$4,0)))+SUMPRODUCT((Inputs!$E$5:$E$160=$B8)*Inputs!$F$5:$F$160*(((Inputs!$G$5:$G$160="moeda")+(Inputs!$G$5:$G$160="acoes"))*Inputs!$B$1+((Inputs!$G$5:$G$160<>"moeda")*(Inputs!$G$5:$G$160<>"acoes")))*INDEX(Inputs!$K$5:$AJ$160,0,MATCH(V$2,Inputs!$K$4:$AJ$4,0))))) -> -171.25364 | W8: =SUM(S8:V8) -> -616.795 | X8: =IF(ISNA(MATCH(X$2,Inputs!$K$4:$AJ$4,0)),NA(),IF(SUMPRODUCT((Inputs!$A$5:$A$160=$B8)*ISNUMBER(INDEX(Inputs!$K$5:$AJ$160,0,MATCH(X$2,Inputs!$K$4:$AJ$4,0))))+SUMPRODUCT((Inputs!$C$5:$C$160=$B8)*ISNUMBER(INDEX(Inputs!$K$5:$AJ$160,0,MATCH(X$2,Inputs!$K$4:$AJ$4,0))))+SUMPRODUCT((Inputs!$E$5:$E$160=$B8)*ISNUMBER(INDEX(Inputs!$K$5:$AJ$160,0,MATCH(X$2,Inputs!$K$4:$AJ$4,0))))=0,NA(),SUMPRODUCT((Inputs!$A$5:$A$160=$B8)*Inputs!$B$5:$B$160*(((Inputs!$G$5:$G$160="moeda")+(Inputs!$G$5:$G$160="acoes"))*Inputs!$B$1+((Inputs!$G$5:$G$160<>"moeda")*(Inputs!$G$5:$G$160<>"acoes")))*INDEX(Inputs!$K$5:$AJ$160,0,MATCH(X$2,Inputs!$K$4:$AJ$4,0)))+SUMPRODUCT((Inputs!$C$5:$C$160=$B8)*Inputs!$D$5:$D$160*(((Inputs!$G$5:$G$160="moeda")+(Inputs!$G$5:$G$160="acoes"))*Inputs!$B$1+((Inputs!$G$5:$G$160<>"moeda")*(Inputs!$G$5:$G$160<>"acoes")))*INDEX(Inputs!$K$5:$AJ$160,0,MATCH(X$2,Inputs!$K$4:$AJ$4,0)))+SUMPRODUCT((Inputs!$E$5:$E$160=$B8)*Inputs!$F$5:$F$160*(((Inputs!$G$5:$G$160="moeda")+(Inputs!$G$5:$G$160="acoes"))*Inputs!$B$1+((Inputs!$G$5:$G$160<>"moeda")*(Inputs!$G$5:$G$160<>"acoes")))*INDEX(Inputs!$K$5:$AJ$160,0,MATCH(X$2,Inputs!$K$4:$AJ$4,0))))) -> -182.4702 | Y8: =IF(ISNA(MATCH(Y$2,Inputs!$K$4:$AJ$4,0)),NA(),IF(SUMPRODUCT((Inputs!$A$5:$A$160=$B8)*ISNUMBER(INDEX(Inputs!$K$5:$AJ$160,0,MATCH(Y$2,Inputs!$K$4:$AJ$4,0))))+SUMPRODUCT((Inputs!$C$5:$C$160=$B8)*ISNUMBER(INDEX(Inputs!$K$5:$AJ$160,0,MATCH(Y$2,Inputs!$K$4:$AJ$4,0))))+SUMPRODUCT((Inputs!$E$5:$E$160=$B8)*ISNUMBER(INDEX(Inputs!$K$5:$AJ$160,0,MATCH(Y$2,Inputs!$K$4:$AJ$4,0))))=0,NA(),SUMPRODUCT((Inputs!$A$5:$A$160=$B8)*Inputs!$B$5:$B$160*(((Inputs!$G$5:$G$160="moeda")+(Inputs!$G$5:$G$160="acoes"))*Inputs!$B$1+((Inputs!$G$5:$G$160<>"moeda")*(Inputs!$G$5:$G$160<>"acoes")))*INDEX(Inputs!$K$5:$AJ$160,0,MATCH(Y$2,Inputs!$K$4:$AJ$4,0)))+SUMPRODUCT((Inputs!$C$5:$C$160=$B8)*Inputs!$D$5:$D$160*(((Inputs!$G$5:$G$160="moeda")+(Inputs!$G$5:$G$160="acoes"))*Inputs!$B$1+((Inputs!$G$5:$G$160<>"moeda")*(Inputs!$G$5:$G$160<>"acoes")))*INDEX(Inputs!$K$5:$AJ$160,0,MATCH(Y$2,Inputs!$K$4:$AJ$4,0)))+SUMPRODUCT((Inputs!$E$5:$E$160=$B8)*Inputs!$F$5:$F$160*(((Inputs!$G$5:$G$160="moeda")+(Inputs!$G$5:$G$160="acoes"))*Inputs!$B$1+((Inputs!$G$5:$G$160<>"moeda")*(Inputs!$G$5:$G$160<>"acoes")))*INDEX(Inputs!$K$5:$AJ$160,0,MATCH(Y$2,Inputs!$K$4:$AJ$4,0))))) -> -198.558 | Z8: =IF(ISNA(MATCH(Z$2,Inputs!$K$4:$AJ$4,0)),NA(),IF(SUMPRODUCT((Inputs!$A$5:$A$160=$B8)*ISNUMBER(INDEX(Inputs!$K$5:$AJ$160,0,MATCH(Z$2,Inputs!$K$4:$AJ$4,0))))+SUMPRODUCT((Inputs!$C$5:$C$160=$B8)*ISNUMBER(INDEX(Inputs!$K$5:$AJ$160,0,MATCH(Z$2,Inputs!$K$4:$AJ$4,0))))+SUMPRODUCT((Inputs!$E$5:$E$160=$B8)*ISNUMBER(INDEX(Inputs!$K$5:$AJ$160,0,MATCH(Z$2,Inputs!$K$4:$AJ$4,0))))=0,NA(),SUMPRODUCT((Inputs!$A$5:$A$160=$B8)*Inputs!$B$5:$B$160*(((Inputs!$G$5:$G$160="moeda")+(Inputs!$G$5:$G$160="acoes"))*Inputs!$B$1+((Inputs!$G$5:$G$160<>"moeda")*(Inputs!$G$5:$G$160<>"acoes")))*INDEX(Inputs!$K$5:$AJ$160,0,MATCH(Z$2,Inputs!$K$4:$AJ$4,0)))+SUMPRODUCT((Inputs!$C$5:$C$160=$B8)*Inputs!$D$5:$D$160*(((Inputs!$G$5:$G$160="moeda")+(Inputs!$G$5:$G$160="acoes"))*Inputs!$B$1+((Inputs!$G$5:$G$160<>"moeda")*(Inputs!$G$5:$G$160<>"acoes")))*INDEX(Inputs!$K$5:$AJ$160,0,MATCH(Z$2,Inputs!$K$4:$AJ$4,0)))+SUMPRODUCT((Inputs!$E$5:$E$160=$B8)*Inputs!$F$5:$F$160*(((Inputs!$G$5:$G$160="moeda")+(Inputs!$G$5:$G$160="acoes"))*Inputs!$B$1+((Inputs!$G$5:$G$160<>"moeda")*(Inputs!$G$5:$G$160<>"acoes")))*INDEX(Inputs!$K$5:$AJ$160,0,MATCH(Z$2,Inputs!$K$4:$AJ$4,0))))) -> -220.29033 | AA8: =IF(ISNA(MATCH(AA$2,Inputs!$K$4:$AJ$4,0)),NA(),IF(SUMPRODUCT((Inputs!$A$5:$A$160=$B8)*ISNUMBER(INDEX(Inputs!$K$5:$AJ$160,0,MATCH(AA$2,Inputs!$K$4:$AJ$4,0))))+SUMPRODUCT((Inputs!$C$5:$C$160=$B8)*ISNUMBER(INDEX(Inputs!$K$5:$AJ$160,0,MATCH(AA$2,Inputs!$K$4:$AJ$4,0))))+SUMPRODUCT((Inputs!$E$5:$E$160=$B8)*ISNUMBER(INDEX(Inputs!$K$5:$AJ$160,0,MATCH(AA$2,Inputs!$K$4:$AJ$4,0))))=0,NA(),SUMPRODUCT((Inputs!$A$5:$A$160=$B8)*Inputs!$B$5:$B$160*(((Inputs!$G$5:$G$160="moeda")+(Inputs!$G$5:$G$160="acoes"))*Inputs!$B$1+((Inputs!$G$5:$G$160<>"moeda")*(Inputs!$G$5:$G$160<>"acoes")))*INDEX(Inputs!$K$5:$AJ$160,0,MATCH(AA$2,Inputs!$K$4:$AJ$4,0)))+SUMPRODUCT((Inputs!$C$5:$C$160=$B8)*Inputs!$D$5:$D$160*(((Inputs!$G$5:$G$160="moeda")+(Inputs!$G$5:$G$160="acoes"))*Inputs!$B$1+((Inputs!$G$5:$G$160<>"moeda")*(Inputs!$G$5:$G$160<>"acoes")))*INDEX(Inputs!$K$5:$AJ$160,0,MATCH(AA$2,Inputs!$K$4:$AJ$4,0)))+SUMPRODUCT((Inputs!$E$5:$E$160=$B8)*Inputs!$F$5:$F$160*(((Inputs!$G$5:$G$160="moeda")+(Inputs!$G$5:$G$160="acoes"))*Inputs!$B$1+((Inputs!$G$5:$G$160<>"moeda")*(Inputs!$G$5:$G$160<>"acoes")))*INDEX(Inputs!$K$5:$AJ$160,0,MATCH(AA$2,Inputs!$K$4:$AJ$4,0))))) -> -202.05934 | AB8: =SUM(X8:AA8) -> -803.37787 | AC8: =IF(ISNA(MATCH(AC$2,Inputs!$K$4:$AJ$4,0)),NA(),IF(SUMPRODUCT((Inputs!$A$5:$A$160=$B8)*ISNUMBER(INDEX(Inputs!$K$5:$AJ$160,0,MATCH(AC$2,Inputs!$K$4:$AJ$4,0))))+SUMPRODUCT((Inputs!$C$5:$C$160=$B8)*ISNUMBER(INDEX(Inputs!$K$5:$AJ$160,0,MATCH(AC$2,Inputs!$K$4:$AJ$4,0))))+SUMPRODUCT((Inputs!$E$5:$E$160=$B8)*ISNUMBER(INDEX(Inputs!$K$5:$AJ$160,0,MATCH(AC$2,Inputs!$K$4:$AJ$4,0))))=0,NA(),SUMPRODUCT((Inputs!$A$5:$A$160=$B8)*Inputs!$B$5:$B$160*(((Inputs!$G$5:$G$160="moeda")+(Inputs!$G$5:$G$160="acoes"))*Inputs!$B$1+((Inputs!$G$5:$G$160<>"moeda")*(Inputs!$G$5:$G$160<>"acoes")))*INDEX(Inputs!$K$5:$AJ$160,0,MATCH(AC$2,Inputs!$K$4:$AJ$4,0)))+SUMPRODUCT((Inputs!$C$5:$C$160=$B8)*Inputs!$D$5:$D$160*(((Inputs!$G$5:$G$160="moeda")+(Inputs!$G$5:$G$160="acoes"))*Inputs!$B$1+((Inputs!$G$5:$G$160<>"moeda")*(Inputs!$G$5:$G$160<>"acoes")))*INDEX(Inputs!$K$5:$AJ$160,0,MATCH(AC$2,Inputs!$K$4:$AJ$4,0)))+SUMPRODUCT((Inputs!$E$5:$E$160=$B8)*Inputs!$F$5:$F$160*(((Inputs!$G$5:$G$160="moeda")+(Inputs!$G$5:$G$160="acoes"))*Inputs!$B$1+((Inputs!$G$5:$G$160<>"moeda")*(Inputs!$G$5:$G$160<>"acoes")))*INDEX(Inputs!$K$5:$AJ$160,0,MATCH(AC$2,Inputs!$K$4:$AJ$4,0))))) -> -195.8752 | AD8: =IF(ISNA(MATCH(AD$2,Inputs!$K$4:$AJ$4,0)),NA(),IF(SUMPRODUCT((Inputs!$A$5:$A$160=$B8)*ISNUMBER(INDEX(Inputs!$K$5:$AJ$160,0,MATCH(AD$2,Inputs!$K$4:$AJ$4,0))))+SUMPRODUCT((Inputs!$C$5:$C$160=$B8)*ISNUMBER(INDEX(Inputs!$K$5:$AJ$160,0,MATCH(AD$2,Inputs!$K$4:$AJ$4,0))))+SUMPRODUCT((Inputs!$E$5:$E$160=$B8)*ISNUMBER(INDEX(Inputs!$K$5:$AJ$160,0,MATCH(AD$2,Inputs!$K$4:$AJ$4,0))))=0,NA(),SUMPRODUCT((Inputs!$A$5:$A$160=$B8)*Inputs!$B$5:$B$160*(((Inputs!$G$5:$G$160="moeda")+(Inputs!$G$5:$G$160="acoes"))*Inputs!$B$1+((Inputs!$G$5:$G$160<>"moeda")*(Inputs!$G$5:$G$160<>"acoes")))*INDEX(Inputs!$K$5:$AJ$160,0,MATCH(AD$2,Inputs!$K$4:$AJ$4,0)))+SUMPRODUCT((Inputs!$C$5:$C$160=$B8)*Inputs!$D$5:$D$160*(((Inputs!$G$5:$G$160="moeda")+(Inputs!$G$5:$G$160="acoes"))*Inputs!$B$1+((Inputs!$G$5:$G$160<>"moeda")*(Inputs!$G$5:$G$160<>"acoes")))*INDEX(Inputs!$K$5:$AJ$160,0,MATCH(AD$2,Inputs!$K$4:$AJ$4,0)))+SUMPRODUCT((Inputs!$E$5:$E$160=$B8)*Inputs!$F$5:$F$160*(((Inputs!$G$5:$G$160="moeda")+(Inputs!$G$5:$G$160="acoes"))*Inputs!$B$1+((Inputs!$G$5:$G$160<>"moeda")*(Inputs!$G$5:$G$160<>"acoes")))*INDEX(Inputs!$K$5:$AJ$160,0,MATCH(AD$2,Inputs!$K$4:$AJ$4,0))))) -> -190.78458 | AE8: =IF(ISNA(MATCH(AE$2,Inputs!$K$4:$AJ$4,0)),NA(),IF(SUMPRODUCT((Inputs!$A$5:$A$160=$B8)*ISNUMBER(INDEX(Inputs!$K$5:$AJ$160,0,MATCH(AE$2,Inputs!$K$4:$AJ$4,0))))+SUMPRODUCT((Inputs!$C$5:$C$160=$B8)*ISNUMBER(INDEX(Inputs!$K$5:$AJ$160,0,MATCH(AE$2,Inputs!$K$4:$AJ$4,0))))+SUMPRODUCT((Inputs!$E$5:$E$160=$B8)*ISNUMBER(INDEX(Inputs!$K$5:$AJ$160,0,MATCH(AE$2,Inputs!$K$4:$AJ$4,0))))=0,NA(),SUMPRODUCT((Inputs!$A$5:$A$160=$B8)*Inputs!$B$5:$B$160*(((Inputs!$G$5:$G$160="moeda")+(Inputs!$G$5:$G$160="acoes"))*Inputs!$B$1+((Inputs!$G$5:$G$160<>"moeda")*(Inputs!$G$5:$G$160<>"acoes")))*INDEX(Inputs!$K$5:$AJ$160,0,MATCH(AE$2,Inputs!$K$4:$AJ$4,0)))+SUMPRODUCT((Inputs!$C$5:$C$160=$B8)*Inputs!$D$5:$D$160*(((Inputs!$G$5:$G$160="moeda")+(Inputs!$G$5:$G$160="acoes"))*Inputs!$B$1+((Inputs!$G$5:$G$160<>"moeda")*(Inputs!$G$5:$G$160<>"acoes")))*INDEX(Inputs!$K$5:$AJ$160,0,MATCH(AE$2,Inputs!$K$4:$AJ$4,0)))+SUMPRODUCT((Inputs!$E$5:$E$160=$B8)*Inputs!$F$5:$F$160*(((Inputs!$G$5:$G$160="moeda")+(Inputs!$G$5:$G$160="acoes"))*Inputs!$B$1+((Inputs!$G$5:$G$160<>"moeda")*(Inputs!$G$5:$G$160<>"acoes")))*INDEX(Inputs!$K$5:$AJ$160,0,MATCH(AE$2,Inputs!$K$4:$AJ$4,0))))) -> #N/A | AF8: =IF(ISNA(MATCH(AF$2,Inputs!$K$4:$AJ$4,0)),NA(),IF(SUMPRODUCT((Inputs!$A$5:$A$160=$B8)*ISNUMBER(INDEX(Inputs!$K$5:$AJ$160,0,MATCH(AF$2,Inputs!$K$4:$AJ$4,0))))+SUMPRODUCT((Inputs!$C$5:$C$160=$B8)*ISNUMBER(INDEX(Inputs!$K$5:$AJ$160,0,MATCH(AF$2,Inputs!$K$4:$AJ$4,0))))+SUMPRODUCT((Inputs!$E$5:$E$160=$B8)*ISNUMBER(INDEX(Inputs!$K$5:$AJ$160,0,MATCH(AF$2,Inputs!$K$4:$AJ$4,0))))=0,NA(),SUMPRODUCT((Inputs!$A$5:$A$160=$B8)*Inputs!$B$5:$B$160*(((Inputs!$G$5:$G$160="moeda")+(Inputs!$G$5:$G$160="acoes"))*Inputs!$B$1+((Inputs!$G$5:$G$160<>"moeda")*(Inputs!$G$5:$G$160<>"acoes")))*INDEX(Inputs!$K$5:$AJ$160,0,MATCH(AF$2,Inputs!$K$4:$AJ$4,0)))+SUMPRODUCT((Inputs!$C$5:$C$160=$B8)*Inputs!$D$5:$D$160*(((Inputs!$G$5:$G$160="moeda")+(Inputs!$G$5:$G$160="acoes"))*Inputs!$B$1+((Inputs!$G$5:$G$160<>"moeda")*(Inputs!$G$5:$G$160<>"acoes")))*INDEX(Inputs!$K$5:$AJ$160,0,MATCH(AF$2,Inputs!$K$4:$AJ$4,0)))+SUMPRODUCT((Inputs!$E$5:$E$160=$B8)*Inputs!$F$5:$F$160*(((Inputs!$G$5:$G$160="moeda")+(Inputs!$G$5:$G$160="acoes"))*Inputs!$B$1+((Inputs!$G$5:$G$160<>"moeda")*(Inputs!$G$5:$G$160<>"acoes")))*INDEX(Inputs!$K$5:$AJ$160,0,MATCH(AF$2,Inputs!$K$4:$AJ$4,0))))) -> #N/A | AG8: =SUM(AC8:AF8) -> #N/A | AH8: =IF(ISNA(MATCH(AH$2,Inputs!$K$4:$AJ$4,0)),NA(),IF(SUMPRODUCT((Inputs!$A$5:$A$160=$B8)*ISNUMBER(INDEX(Inputs!$K$5:$AJ$160,0,MATCH(AH$2,Inputs!$K$4:$AJ$4,0))))+SUMPRODUCT((Inputs!$C$5:$C$160=$B8)*ISNUMBER(INDEX(Inputs!$K$5:$AJ$160,0,MATCH(AH$2,Inputs!$K$4:$AJ$4,0))))+SUMPRODUCT((Inputs!$E$5:$E$160=$B8)*ISNUMBER(INDEX(Inputs!$K$5:$AJ$160,0,MATCH(AH$2,Inputs!$K$4:$AJ$4,0))))=0,NA(),SUMPRODUCT((Inputs!$A$5:$A$160=$B8)*Inputs!$B$5:$B$160*(((Inputs!$G$5:$G$160="moeda")+(Inputs!$G$5:$G$160="acoes"))*Inputs!$B$1+((Inputs!$G$5:$G$160<>"moeda")*(Inputs!$G$5:$G$160<>"acoes")))*INDEX(Inputs!$K$5:$AJ$160,0,MATCH(AH$2,Inputs!$K$4:$AJ$4,0)))+SUMPRODUCT((Inputs!$C$5:$C$160=$B8)*Inputs!$D$5:$D$160*(((Inputs!$G$5:$G$160="moeda")+(Inputs!$G$5:$G$160="acoes"))*Inputs!$B$1+((Inputs!$G$5:$G$160<>"moeda")*(Inputs!$G$5:$G$160<>"acoes")))*INDEX(Inputs!$K$5:$AJ$160,0,MATCH(AH$2,Inputs!$K$4:$AJ$4,0)))+SUMPRODUCT((Inputs!$E$5:$E$160=$B8)*Inputs!$F$5:$F$160*(((Inputs!$G$5:$G$160="moeda")+(Inputs!$G$5:$G$160="acoes"))*Inputs!$B$1+((Inputs!$G$5:$G$160<>"moeda")*(Inputs!$G$5:$G$160<>"acoes")))*INDEX(Inputs!$K$5:$AJ$160,0,MATCH(AH$2,Inputs!$K$4:$AJ$4,0))))) -> -38.718506 | AI8: =IF(ISNA(MATCH(AI$2,Inputs!$K$4:$AJ$4,0)),NA(),IF(SUMPRODUCT((Inputs!$A$5:$A$160=$B8)*ISNUMBER(INDEX(Inputs!$K$5:$AJ$160,0,MATCH(AI$2,Inputs!$K$4:$AJ$4,0))))+SUMPRODUCT((Inputs!$C$5:$C$160=$B8)*ISNUMBER(INDEX(Inputs!$K$5:$AJ$160,0,MATCH(AI$2,Inputs!$K$4:$AJ$4,0))))+SUMPRODUCT((Inputs!$E$5:$E$160=$B8)*ISNUMBER(INDEX(Inputs!$K$5:$AJ$160,0,MATCH(AI$2,Inputs!$K$4:$AJ$4,0))))=0,NA(),SUMPRODUCT((Inputs!$A$5:$A$160=$B8)*Inputs!$B$5:$B$160*(((Inputs!$G$5:$G$160="moeda")+(Inputs!$G$5:$G$160="acoes"))*Inputs!$B$1+((Inputs!$G$5:$G$160<>"moeda")*(Inputs!$G$5:$G$160<>"acoes")))*INDEX(Inputs!$K$5:$AJ$160,0,MATCH(AI$2,Inputs!$K$4:$AJ$4,0)))+SUMPRODUCT((Inputs!$C$5:$C$160=$B8)*Inputs!$D$5:$D$160*(((Inputs!$G$5:$G$160="moeda")+(Inputs!$G$5:$G$160="acoes"))*Inputs!$B$1+((Inputs!$G$5:$G$160<>"moeda")*(Inputs!$G$5:$G$160<>"acoes")))*INDEX(Inputs!$K$5:$AJ$160,0,MATCH(AI$2,Inputs!$K$4:$AJ$4,0)))+SUMPRODUCT((Inputs!$E$5:$E$160=$B8)*Inputs!$F$5:$F$160*(((Inputs!$G$5:$G$160="moeda")+(Inputs!$G$5:$G$160="acoes"))*Inputs!$B$1+((Inputs!$G$5:$G$160<>"moeda")*(Inputs!$G$5:$G$160<>"acoes")))*INDEX(Inputs!$K$5:$AJ$160,0,MATCH(AI$2,Inputs!$K$4:$AJ$4,0))))) -> -45.377891 | AJ8: =IF(ISNA(MATCH(AJ$2,Inputs!$K$4:$AJ$4,0)),NA(),IF(SUMPRODUCT((Inputs!$A$5:$A$160=$B8)*ISNUMBER(INDEX(Inputs!$K$5:$AJ$160,0,MATCH(AJ$2,Inputs!$K$4:$AJ$4,0))))+SUMPRODUCT((Inputs!$C$5:$C$160=$B8)*ISNUMBER(INDEX(Inputs!$K$5:$AJ$160,0,MATCH(AJ$2,Inputs!$K$4:$AJ$4,0))))+SUMPRODUCT((Inputs!$E$5:$E$160=$B8)*ISNUMBER(INDEX(Inputs!$K$5:$AJ$160,0,MATCH(AJ$2,Inputs!$K$4:$AJ$4,0))))=0,NA(),SUMPRODUCT((Inputs!$A$5:$A$160=$B8)*Inputs!$B$5:$B$160*(((Inputs!$G$5:$G$160="moeda")+(Inputs!$G$5:$G$160="acoes"))*Inputs!$B$1+((Inputs!$G$5:$G$160<>"moeda")*(Inputs!$G$5:$G$160<>"acoes")))*INDEX(Inputs!$K$5:$AJ$160,0,MATCH(AJ$2,Inputs!$K$4:$AJ$4,0)))+SUMPRODUCT((Inputs!$C$5:$C$160=$B8)*Inputs!$D$5:$D$160*(((Inputs!$G$5:$G$160="moeda")+(Inputs!$G$5:$G$160="acoes"))*Inputs!$B$1+((Inputs!$G$5:$G$160<>"moeda")*(Inputs!$G$5:$G$160<>"acoes")))*INDEX(Inputs!$K$5:$AJ$160,0,MATCH(AJ$2,Inputs!$K$4:$AJ$4,0)))+SUMPRODUCT((Inputs!$E$5:$E$160=$B8)*Inputs!$F$5:$F$160*(((Inputs!$G$5:$G$160="moeda")+(Inputs!$G$5:$G$160="acoes"))*Inputs!$B$1+((Inputs!$G$5:$G$160<>"moeda")*(Inputs!$G$5:$G$160<>"acoes")))*INDEX(Inputs!$K$5:$AJ$160,0,MATCH(AJ$2,Inputs!$K$4:$AJ$4,0))))) -> -43.124065 | AK8: =IF(ISNA(MATCH(AK$2,Inputs!$K$4:$AJ$4,0)),NA(),IF(SUMPRODUCT((Inputs!$A$5:$A$160=$B8)*ISNUMBER(INDEX(Inputs!$K$5:$AJ$160,0,MATCH(AK$2,Inputs!$K$4:$AJ$4,0))))+SUMPRODUCT((Inputs!$C$5:$C$160=$B8)*ISNUMBER(INDEX(Inputs!$K$5:$AJ$160,0,MATCH(AK$2,Inputs!$K$4:$AJ$4,0))))+SUMPRODUCT((Inputs!$E$5:$E$160=$B8)*ISNUMBER(INDEX(Inputs!$K$5:$AJ$160,0,MATCH(AK$2,Inputs!$K$4:$AJ$4,0))))=0,NA(),SUMPRODUCT((Inputs!$A$5:$A$160=$B8)*Inputs!$B$5:$B$160*(((Inputs!$G$5:$G$160="moeda")+(Inputs!$G$5:$G$160="acoes"))*Inputs!$B$1+((Inputs!$G$5:$G$160<>"moeda")*(Inputs!$G$5:$G$160<>"acoes")))*INDEX(Inputs!$K$5:$AJ$160,0,MATCH(AK$2,Inputs!$K$4:$AJ$4,0)))+SUMPRODUCT((Inputs!$C$5:$C$160=$B8)*Inputs!$D$5:$D$160*(((Inputs!$G$5:$G$160="moeda")+(Inputs!$G$5:$G$160="acoes"))*Inputs!$B$1+((Inputs!$G$5:$G$160<>"moeda")*(Inputs!$G$5:$G$160<>"acoes")))*INDEX(Inputs!$K$5:$AJ$160,0,MATCH(AK$2,Inputs!$K$4:$AJ$4,0)))+SUMPRODUCT((Inputs!$E$5:$E$160=$B8)*Inputs!$F$5:$F$160*(((Inputs!$G$5:$G$160="moeda")+(Inputs!$G$5:$G$160="acoes"))*Inputs!$B$1+((Inputs!$G$5:$G$160<>"moeda")*(Inputs!$G$5:$G$160<>"acoes")))*INDEX(Inputs!$K$5:$AJ$160,0,MATCH(AK$2,Inputs!$K$4:$AJ$4,0))))) -> -47.822657 | AL8: =SUM(AH8:AK8) -> -175.04312
