Workbook
Name beta_observed: Valuation!$D$93
Name last_close: Valuation!$G$7
Name ticker: Valuation!$D$7
Name Useful_Life_of_Depreciable_PP_E: "PPElife"
Name beta_observed: #REF!
Name ticker: #REF!
Name costdebtfirm: Valuation!$D$86
Name costequity: Valuation!$D$94
Name debt: Valuation!$G$88
Name debt_weight: Valuation!$J$88
Name g: Valuation!$D$63
Name market_equity: Valuation!$G$89
Name noplat_t1: Valuation!$D$65
Name relevered_beta: Valuation!$M$102
Name risk_free_rate: Valuation!$D$91
Name risk_premium: Valuation!$D$92
Name ronic: Valuation!$D$64
Name stub_year_fraction: Valuation!$D$11
Name totalcap: Valuation!$G$90
Name wacc: Valuation!$D$12

Sheet Inputs
A1: Base histórica normalizada (US$ mil) — convertida da máscara anterior; linhas de origem auditáveis
A2: Fonte / conta original | B2: Código | C2: Conta padronizada | D2: 1Q21 | E2: 2Q21 | F2: 3Q21 | G2: 4Q21 | H2: 2021 | I2: 1Q22 | J2: 2Q22 | K2: 3Q22 | L2: 4Q22 | M2: 2022 | N2: 1Q23 | O2: 2Q23 | P2: 3Q23 | Q2: 4Q23 | R2: 2023 | S2: 1Q24 | T2: 2Q24 | U2: 3Q24 | V2: 4Q24 | W2: 2024 | X2: 1Q25 | Y2: 2Q25 | Z2: 3Q25 | AA2: 4Q25 | AB2: 2025 | AC2: 1Q26 | AD2: 2Q26 | AE2: 3Q26 | AF2: 4Q26 | AG2: 2026
A3: Fonte: ver coluna A de cada linha | C3: Unidade: US$ mil (monetário); demais unidades × 1.000
A4: DRE - BRUTO COMO DIVULGADO (USD). 3M = trimestre do 10-Q (FQ1-FQ3 = 4T, 1T, 2T calendário); 12M = ano fiscal do 10-K (na coluna do 3T calendário); 9M = acumulado do 10-Q de jun (coluna do 2T) | C4: [linha bruta, sem código; lançada nas linhas abaixo]
A5: Receita líquida (net sales) - 3M (10-Q) [us-gaap:RevenueFromContractWithCustomerExcludingAssessedTax] · memoria · unid. moeda | C5: [linha bruta, sem código; lançada nas linhas abaixo] | D5: 89584000 | E5: 81434000 | G5: 123945000 | I5: 97278000 | J5: 82959000 | L5: 117154000 | N5: 94836000 | O5: 81797000 | Q5: 119575000 | S5: 90753000 | T5: 85777000 | V5: 124300000 | X5: 95359000 | Y5: 94036000 | AA5: 143756000 | AC5: 111184000 | AD5: 109417000
A6: Receita líquida (net sales) - ano fiscal 12M (10-K; na coluna do 3T) · memoria · unid. moeda | C6: [linha bruta, sem código; lançada nas linhas abaixo] | F6: 365817000 | K6: 394328000 | P6: 383285000 | U6: 391035000 | Z6: 416161000
A7: Receita líquida (net sales) - 9M acumulado (10-Q de jun; na coluna do 2T) · memoria · unid. moeda | C7: [linha bruta, sem código; lançada nas linhas abaixo] | E7: 282457000 | J7: 304182000 | O7: 293787000 | T7: 296105000 | Y7: 313695000 | AD7: 364357000
A8: Custo das vendas (divulgado positivo) - 3M (10-Q) [us-gaap:CostOfGoodsAndServicesSold] · memoria · unid. moeda | C8: [linha bruta, sem código; lançada nas linhas abaixo] | D8: 51505000 | E8: 46179000 | G8: 69702000 | I8: 54719000 | J8: 47074000 | L8: 66822000 | N8: 52860000 | O8: 45384000 | Q8: 64720000 | S8: 48482000 | T8: 46099000 | V8: 66025000 | X8: 50492000 | Y8: 50318000 | AA8: 74525000 | AC8: 56403000 | AD8: 54647000
A9: Custo das vendas (divulgado positivo) - ano fiscal 12M (10-K; na coluna do 3T) · memoria · unid. moeda | C9: [linha bruta, sem código; lançada nas linhas abaixo] | F9: 212981000 | K9: 223546000 | P9: 214137000 | U9: 210352000 | Z9: 220960000
A10: Custo das vendas (divulgado positivo) - 9M acumulado (10-Q de jun; na coluna do 2T) · memoria · unid. moeda | C10: [linha bruta, sem código; lançada nas linhas abaixo] | E10: 164795000 | J10: 171495000 | O10: 165066000 | T10: 159301000 | Y10: 166835000 | AD10: 185575000
A11: Despesas operacionais totais = P&D + SG&A (divulgado positivo) - 3M (10-Q) [us-gaap:OperatingExpenses] · memoria · unid. moeda | C11: [linha bruta, sem código; lançada nas linhas abaixo] | D11: 10576000 | E11: 11129000 | G11: 12755000 | I11: 12580000 | J11: 12809000 | L11: 14316000 | N11: 13658000 | O11: 13415000 | Q11: 14482000 | S11: 14371000 | T11: 14326000 | V11: 15443000 | X11: 15278000 | Y11: 15516000 | AA11: 18379000 | AC11: 18896000 | AD11: 19075000
A12: Despesas operacionais totais = P&D + SG&A (divulgado positivo) - ano fiscal 12M (10-K; na coluna do 3T) · memoria · unid. moeda | C12: [linha bruta, sem código; lançada nas linhas abaixo] | F12: 43887000 | K12: 51345000 | P12: 54847000 | U12: 57467000 | Z12: 62151000
A13: Despesas operacionais totais = P&D + SG&A (divulgado positivo) - 9M acumulado (10-Q de jun; na coluna do 2T) · memoria · unid. moeda | C13: [linha bruta, sem código; lançada nas linhas abaixo] | E13: 32499000 | J13: 38144000 | O13: 41389000 | T13: 43179000 | Y13: 46237000 | AD13: 56350000
A14: Outras receitas/(despesas), líquido (inclui juros) - 3M (10-Q) [us-gaap:NonoperatingIncomeExpense] · memoria · unid. moeda | C14: [linha bruta, sem código; lançada nas linhas abaixo] | D14: 508000 | E14: 243000 | G14: -247000 | I14: 160000 | J14: -10000 | L14: -393000 | N14: 64000 | O14: -265000 | Q14: -50000 | S14: 158000 | T14: 142000 | V14: -248000 | X14: -279000 | Y14: -171000 | AA14: 150000 | AC14: -52000 | AD14: 572000
A15: Outras receitas/(despesas), líquido (inclui juros) - ano fiscal 12M (10-K; na coluna do 3T) · memoria · unid. moeda | C15: [linha bruta, sem código; lançada nas linhas abaixo] | F15: 258000 | K15: -334000 | P15: -565000 | U15: 269000 | Z15: -321000
A16: Outras receitas/(despesas), líquido (inclui juros) - 9M acumulado (10-Q de jun; na coluna do 2T) · memoria · unid. moeda | C16: [linha bruta, sem código; lançada nas linhas abaixo] | E16: 796000 | J16: -97000 | O16: -594000 | T16: 250000 | Y16: -698000 | AD16: 670000
A17: Imposto de renda (divulgado positivo) - 3M (10-Q) [us-gaap:IncomeTaxExpenseBenefit] · memoria · unid. moeda | C17: [linha bruta, sem código; lançada nas linhas abaixo] | D17: 4381000 | E17: 2625000 | G17: 6611000 | I17: 5129000 | J17: 3624000 | L17: 5625000 | N17: 4222000 | O17: 2852000 | Q17: 6407000 | S17: 4422000 | T17: 4046000 | V17: 6254000 | X17: 4530000 | Y17: 4597000 | AA17: 8905000 | AC17: 6255000 | AD17: 6478000
A18: Imposto de renda (divulgado positivo) - ano fiscal 12M (10-K; na coluna do 3T) · memoria · unid. moeda | C18: [linha bruta, sem código; lançada nas linhas abaixo] | F18: 14527000 | K18: 19300000 | P18: 16741000 | U18: 29749000 | Z18: 20719000
A19: Imposto de renda (divulgado positivo) - 9M acumulado (10-Q de jun; na coluna do 2T) · memoria · unid. moeda | C19: [linha bruta, sem código; lançada nas linhas abaixo] | E19: 11830000 | J19: 15364000 | O19: 12699000 | T19: 14875000 | Y19: 15381000 | AD19: 21638000
A20: Lucro líquido - 3M (10-Q) [us-gaap:NetIncomeLoss] · memoria · unid. moeda | C20: [linha bruta, sem código; lançada nas linhas abaixo] | D20: 23630000 | E20: 21744000 | G20: 34630000 | I20: 25010000 | J20: 19442000 | L20: 29998000 | N20: 24160000 | O20: 19881000 | Q20: 33916000 | S20: 23636000 | T20: 21448000 | V20: 36330000 | X20: 24780000 | Y20: 23434000 | AA20: 42097000 | AC20: 29578000 | AD20: 29789000
A21: Lucro líquido - ano fiscal 12M (10-K; na coluna do 3T) · memoria · unid. moeda | C21: [linha bruta, sem código; lançada nas linhas abaixo] | F21: 94680000 | K21: 99803000 | P21: 96995000 | U21: 93736000 | Z21: 112010000
A22: Lucro líquido - 9M acumulado (10-Q de jun; na coluna do 2T) · memoria · unid. moeda | C22: [linha bruta, sem código; lançada nas linhas abaixo] | E22: 74129000 | J22: 79082000 | O22: 74039000 | T22: 79000000 | Y22: 84544000 | AD22: 101464000
A23: DRE TRIMESTRALIZADA (derivada por fórmula): 3T calendário = ano fiscal - 9M | C23: [linha bruta, sem código; lançada nas linhas abaixo]
A24: Receita líquida (net sales) - trimestre · derivada · unid. moeda | B24: 1 | C24: Net Revenues | D24: =D5 -> 89584000 | E24: =E5 -> 81434000 | F24: =N(F6)-N(E7) -> 83360000 | G24: =G5 -> 123945000 | I24: =I5 -> 97278000 | J24: =J5 -> 82959000 | K24: =N(K6)-N(J7) -> 90146000 | L24: =L5 -> 117154000 | N24: =N5 -> 94836000 | O24: =O5 -> 81797000 | P24: =N(P6)-N(O7) -> 89498000 | Q24: =Q5 -> 119575000 | S24: =S5 -> 90753000 | T24: =T5 -> 85777000 | U24: =N(U6)-N(T7) -> 94930000 | V24: =V5 -> 124300000 | X24: =X5 -> 95359000 | Y24: =Y5 -> 94036000 | Z24: =N(Z6)-N(Y7) -> 102466000 | AA24: =AA5 -> 143756000 | AC24: =AC5 -> 111184000 | AD24: =AD5 -> 109417000
A25: Custo das vendas (divulgado positivo) - trimestre · derivada · unid. moeda | C25: [linha bruta, sem código; lançada nas linhas abaixo] | D25: =D8 -> 51505000 | E25: =E8 -> 46179000 | F25: =N(F9)-N(E10) -> 48186000 | G25: =G8 -> 69702000 | I25: =I8 -> 54719000 | J25: =J8 -> 47074000 | K25: =N(K9)-N(J10) -> 52051000 | L25: =L8 -> 66822000 | N25: =N8 -> 52860000 | O25: =O8 -> 45384000 | P25: =N(P9)-N(O10) -> 49071000 | Q25: =Q8 -> 64720000 | S25: =S8 -> 48482000 | T25: =T8 -> 46099000 | U25: =N(U9)-N(T10) -> 51051000 | V25: =V8 -> 66025000 | X25: =X8 -> 50492000 | Y25: =Y8 -> 50318000 | Z25: =N(Z9)-N(Y10) -> 54125000 | AA25: =AA8 -> 74525000 | AC25: =AC8 -> 56403000 | AD25: =AD8 -> 54647000
A26: (lançamento) código 2, sinal -1 sobre a linha bruta 25: Custo das vendas (divulgado positivo) - trimestre | B26: 2 | C26: COGS (cash) | D26: =IF(D25="","",-1*D25) -> -51505000 | E26: =IF(E25="","",-1*E25) -> -46179000 | F26: =IF(F25="","",-1*F25) -> -48186000 | G26: =IF(G25="","",-1*G25) -> -69702000 | I26: =IF(I25="","",-1*I25) -> -54719000 | J26: =IF(J25="","",-1*J25) -> -47074000 | K26: =IF(K25="","",-1*K25) -> -52051000 | L26: =IF(L25="","",-1*L25) -> -66822000 | N26: =IF(N25="","",-1*N25) -> -52860000 | O26: =IF(O25="","",-1*O25) -> -45384000 | P26: =IF(P25="","",-1*P25) -> -49071000 | Q26: =IF(Q25="","",-1*Q25) -> -64720000 | S26: =IF(S25="","",-1*S25) -> -48482000 | T26: =IF(T25="","",-1*T25) -> -46099000 | U26: =IF(U25="","",-1*U25) -> -51051000 | V26: =IF(V25="","",-1*V25) -> -66025000 | X26: =IF(X25="","",-1*X25) -> -50492000 | Y26: =IF(Y25="","",-1*Y25) -> -50318000 | Z26: =IF(Z25="","",-1*Z25) -> -54125000 | AA26: =IF(AA25="","",-1*AA25) -> -74525000 | AC26: =IF(AC25="","",-1*AC25) -> -56403000 | AD26: =IF(AD25="","",-1*AD25) -> -54647000
A27: Despesas operacionais totais = P&D + SG&A (divulgado positivo) - trimestre · derivada · unid. moeda | C27: [linha bruta, sem código; lançada nas linhas abaixo] | D27: =D11 -> 10576000 | E27: =E11 -> 11129000 | F27: =N(F12)-N(E13) -> 11388000 | G27: =G11 -> 12755000 | I27: =I11 -> 12580000 | J27: =J11 -> 12809000 | K27: =N(K12)-N(J13) -> 13201000 | L27: =L11 -> 14316000 | N27: =N11 -> 13658000 | O27: =O11 -> 13415000 | P27: =N(P12)-N(O13) -> 13458000 | Q27: =Q11 -> 14482000 | S27: =S11 -> 14371000 | T27: =T11 -> 14326000 | U27: =N(U12)-N(T13) -> 14288000 | V27: =V11 -> 15443000 | X27: =X11 -> 15278000 | Y27: =Y11 -> 15516000 | Z27: =N(Z12)-N(Y13) -> 15914000 | AA27: =AA11 -> 18379000 | AC27: =AC11 -> 18896000 | AD27: =AD11 -> 19075000
A28: (lançamento) código 3, sinal -1 sobre a linha bruta 27: Despesas operacionais totais = P&D + SG&A (divulgado positivo) - trimestre | B28: 3 | C28: SG&A and Other (cash) | D28: =IF(D27="","",-1*D27) -> -10576000 | E28: =IF(E27="","",-1*E27) -> -11129000 | F28: =IF(F27="","",-1*F27) -> -11388000 | G28: =IF(G27="","",-1*G27) -> -12755000 | I28: =IF(I27="","",-1*I27) -> -12580000 | J28: =IF(J27="","",-1*J27) -> -12809000 | K28: =IF(K27="","",-1*K27) -> -13201000 | L28: =IF(L27="","",-1*L27) -> -14316000 | N28: =IF(N27="","",-1*N27) -> -13658000 | O28: =IF(O27="","",-1*O27) -> -13415000 | P28: =IF(P27="","",-1*P27) -> -13458000 | Q28: =IF(Q27="","",-1*Q27) -> -14482000 | S28: =IF(S27="","",-1*S27) -> -14371000 | T28: =IF(T27="","",-1*T27) -> -14326000 | U28: =IF(U27="","",-1*U27) -> -14288000 | V28: =IF(V27="","",-1*V27) -> -15443000 | X28: =IF(X27="","",-1*X27) -> -15278000 | Y28: =IF(Y27="","",-1*Y27) -> -15516000 | Z28: =IF(Z27="","",-1*Z27) -> -15914000 | AA28: =IF(AA27="","",-1*AA27) -> -18379000 | AC28: =IF(AC27="","",-1*AC27) -> -18896000 | AD28: =IF(AD27="","",-1*AD27) -> -19075000
A29: Outras receitas/(despesas), líquido (inclui juros) - trimestre · derivada · unid. moeda | B29: 6 | C29: Nonoperating Income / (Loss) | D29: =D14 -> 508000 | E29: =E14 -> 243000 | F29: =N(F15)-N(E16) -> -538000 | G29: =G14 -> -247000 | I29: =I14 -> 160000 | J29: =J14 -> -10000 | K29: =N(K15)-N(J16) -> -237000 | L29: =L14 -> -393000 | N29: =N14 -> 64000 | O29: =O14 -> -265000 | P29: =N(P15)-N(O16) -> 29000 | Q29: =Q14 -> -50000 | S29: =S14 -> 158000 | T29: =T14 -> 142000 | U29: =N(U15)-N(T16) -> 19000 | V29: =V14 -> -248000 | X29: =X14 -> -279000 | Y29: =Y14 -> -171000 | Z29: =N(Z15)-N(Y16) -> 377000 | AA29: =AA14 -> 150000 | AC29: =AC14 -> -52000 | AD29: =AD14 -> 572000
A30: Imposto de renda (divulgado positivo) - trimestre · derivada · unid. moeda | C30: [linha bruta, sem código; lançada nas linhas abaixo] | D30: =D17 -> 4381000 | E30: =E17 -> 2625000 | F30: =N(F18)-N(E19) -> 2697000 | G30: =G17 -> 6611000 | I30: =I17 -> 5129000 | J30: =J17 -> 3624000 | K30: =N(K18)-N(J19) -> 3936000 | L30: =L17 -> 5625000 | N30: =N17 -> 4222000 | O30: =O17 -> 2852000 | P30: =N(P18)-N(O19) -> 4042000 | Q30: =Q17 -> 6407000 | S30: =S17 -> 4422000 | T30: =T17 -> 4046000 | U30: =N(U18)-N(T19) -> 14874000 | V30: =V17 -> 6254000 | X30: =X17 -> 4530000 | Y30: =Y17 -> 4597000 | Z30: =N(Z18)-N(Y19) -> 5338000 | AA30: =AA17 -> 8905000 | AC30: =AC17 -> 6255000 | AD30: =AD17 -> 6478000
A31: (lançamento) código 7, sinal -1 sobre a linha bruta 30: Imposto de renda (divulgado positivo) - trimestre | B31: 7 | C31: Taxes | D31: =IF(D30="","",-1*D30) -> -4381000 | E31: =IF(E30="","",-1*E30) -> -2625000 | F31: =IF(F30="","",-1*F30) -> -2697000 | G31: =IF(G30="","",-1*G30) -> -6611000 | I31: =IF(I30="","",-1*I30) -> -5129000 | J31: =IF(J30="","",-1*J30) -> -3624000 | K31: =IF(K30="","",-1*K30) -> -3936000 | L31: =IF(L30="","",-1*L30) -> -5625000 | N31: =IF(N30="","",-1*N30) -> -4222000 | O31: =IF(O30="","",-1*O30) -> -2852000 | P31: =IF(P30="","",-1*P30) -> -4042000 | Q31: =IF(Q30="","",-1*Q30) -> -6407000 | S31: =IF(S30="","",-1*S30) -> -4422000 | T31: =IF(T30="","",-1*T30) -> -4046000 | U31: =IF(U30="","",-1*U30) -> -14874000 | V31: =IF(V30="","",-1*V30) -> -6254000 | X31: =IF(X30="","",-1*X30) -> -4530000 | Y31: =IF(Y30="","",-1*Y30) -> -4597000 | Z31: =IF(Z30="","",-1*Z30) -> -5338000 | AA31: =IF(AA30="","",-1*AA30) -> -8905000 | AC31: =IF(AC30="","",-1*AC30) -> -6255000 | AD31: =IF(AD30="","",-1*AD30) -> -6478000
A32: Lucro líquido - trimestre · derivada · unid. moeda | B32: 44 | C32: Lucro líquido - trimestre | D32: =D20 -> 23630000 | E32: =E20 -> 21744000 | F32: =N(F21)-N(E22) -> 20551000 | G32: =G20 -> 34630000 | I32: =I20 -> 25010000 | J32: =J20 -> 19442000 | K32: =N(K21)-N(J22) -> 20721000 | L32: =L20 -> 29998000 | N32: =N20 -> 24160000 | O32: =O20 -> 19881000 | P32: =N(P21)-N(O22) -> 22956000 | Q32: =Q20 -> 33916000 | S32: =S20 -> 23636000 | T32: =T20 -> 21448000 | U32: =N(U21)-N(T22) -> 14736000 | V32: =V20 -> 36330000 | X32: =X20 -> 24780000 | Y32: =Y20 -> 23434000 | Z32: =N(Z21)-N(Y22) -> 27466000 | AA32: =AA20 -> 42097000 | AC32: =AC20 -> 29578000 | AD32: =AD20 -> 29789000
A33: DFC - ACUMULADO NO ANO FISCAL (USD): 3M (dez), 6M (mar), 9M (jun), 12M (set) | C33: [linha bruta, sem código; lançada nas linhas abaixo]
A34: Depreciação e amortização - acumulado no ano fiscal [us-gaap:DepreciationDepletionAndAmortization] · memoria · unid. moeda | C34: [linha bruta, sem código; lançada nas linhas abaixo] | D34: 5463000 | E34: 8295000 | F34: 11284000 | G34: 2697000 | I34: 5434000 | J34: 8239000 | K34: 11104000 | L34: 2916000 | N34: 5814000 | O34: 8866000 | P34: 11519000 | Q34: 2848000 | S34: 5684000 | T34: 8534000 | U34: 11445000 | V34: 3080000 | X34: 5741000 | Y34: 8571000 | Z34: 11698000 | AA34: 3214000 | AC34: 6653000 | AD34: 9973000
A35: Depreciação e amortização - out-dez/2019 (3M do 10-Q de dez/19), para desacumular o 1T20 · memoria · unid. moeda | C35: [linha bruta, sem código; lançada nas linhas abaixo]
A36: Dividendos pagos - acumulado no ano fiscal [us-gaap:PaymentsOfDividends] · memoria · unid. moeda | C36: [linha bruta, sem código; lançada nas linhas abaixo] | D36: 7060000 | E36: 10827000 | F36: 14467000 | G36: 3732000 | I36: 7327000 | J36: 11138000 | K36: 14841000 | L36: 3768000 | N36: 7418000 | O36: 11267000 | P36: 15025000 | Q36: 3825000 | S36: 7535000 | T36: 11430000 | U36: 15234000 | V36: 3856000 | X36: 7614000 | Y36: 11559000 | Z36: 15421000 | AA36: 3921000 | AC36: 7743000 | AD36: 11778000
A37: Dividendos pagos - out-dez/2019 (3M do 10-Q de dez/19), para desacumular o 1T20 · memoria · unid. moeda | C37: [linha bruta, sem código; lançada nas linhas abaixo]
A38: D&A trimestral (desacumulada). COD1=4 lança (positivo -> -1); COD2=3 devolve às despesas operacionais (a Apple não abre D&A entre custo e despesa) · derivada · unid. moeda | C38: [linha bruta, sem código; lançada nas linhas abaixo] | D38: =N(D34)-N(N34) -> -351000 | E38: =N(E34)-N(D34) -> 2832000 | F38: =N(F34)-N(E34) -> 2989000 | G38: =N(G34) -> 2697000 | I38: =N(I34)-N(G34) -> 2737000 | J38: =N(J34)-N(I34) -> 2805000 | K38: =N(K34)-N(J34) -> 2865000 | L38: =N(L34) -> 2916000 | N38: =N(N34)-N(L34) -> 2898000 | O38: =N(O34)-N(N34) -> 3052000 | P38: =N(P34)-N(O34) -> 2653000 | Q38: =N(Q34) -> 2848000 | S38: =N(S34)-N(Q34) -> 2836000 | T38: =N(T34)-N(S34) -> 2850000 | U38: =N(U34)-N(T34) -> 2911000 | V38: =N(V34) -> 3080000 | X38: =N(X34)-N(V34) -> 2661000 | Y38: =N(Y34)-N(X34) -> 2830000 | Z38: =N(Z34)-N(Y34) -> 3127000 | AA38: =N(AA34) -> 3214000 | AC38: =N(AC34)-N(AA34) -> 3439000 | AD38: =N(AD34)-N(AC34) -> 3320000
A39: (lançamento) código 4, sinal -1 sobre a linha bruta 38: D&A trimestral (desacumulada). COD1=4 lança (positivo -> -1); COD2=3 devolve às despesas o | B39: 4 | C39: D&A | D39: =IF(D38="","",-1*D38) -> 351000 | E39: =IF(E38="","",-1*E38) -> -2832000 | F39: =IF(F38="","",-1*F38) -> -2989000 | G39: =IF(G38="","",-1*G38) -> -2697000 | I39: =IF(I38="","",-1*I38) -> -2737000 | J39: =IF(J38="","",-1*J38) -> -2805000 | K39: =IF(K38="","",-1*K38) -> -2865000 | L39: =IF(L38="","",-1*L38) -> -2916000 | N39: =IF(N38="","",-1*N38) -> -2898000 | O39: =IF(O38="","",-1*O38) -> -3052000 | P39: =IF(P38="","",-1*P38) -> -2653000 | Q39: =IF(Q38="","",-1*Q38) -> -2848000 | S39: =IF(S38="","",-1*S38) -> -2836000 | T39: =IF(T38="","",-1*T38) -> -2850000 | U39: =IF(U38="","",-1*U38) -> -2911000 | V39: =IF(V38="","",-1*V38) -> -3080000 | X39: =IF(X38="","",-1*X38) -> -2661000 | Y39: =IF(Y38="","",-1*Y38) -> -2830000 | Z39: =IF(Z38="","",-1*Z38) -> -3127000 | AA39: =IF(AA38="","",-1*AA38) -> -3214000 | AC39: =IF(AC38="","",-1*AC38) -> -3439000 | AD39: =IF(AD38="","",-1*AD38) -> -3320000
A40: (lançamento) código 3, sinal +1 sobre a linha bruta 38: D&A trimestral (desacumulada). COD1=4 lança (positivo -> -1); COD2=3 devolve às despesas o | B40: 3 | C40: SG&A and Other (cash) | D40: =IF(D38="","",D38) -> -351000 | E40: =IF(E38="","",E38) -> 2832000 | F40: =IF(F38="","",F38) -> 2989000 | G40: =IF(G38="","",G38) -> 2697000 | I40: =IF(I38="","",I38) -> 2737000 | J40: =IF(J38="","",J38) -> 2805000 | K40: =IF(K38="","",K38) -> 2865000 | L40: =IF(L38="","",L38) -> 2916000 | N40: =IF(N38="","",N38) -> 2898000 | O40: =IF(O38="","",O38) -> 3052000 | P40: =IF(P38="","",P38) -> 2653000 | Q40: =IF(Q38="","",Q38) -> 2848000 | S40: =IF(S38="","",S38) -> 2836000 | T40: =IF(T38="","",T38) -> 2850000 | U40: =IF(U38="","",U38) -> 2911000 | V40: =IF(V38="","",V38) -> 3080000 | X40: =IF(X38="","",X38) -> 2661000 | Y40: =IF(Y38="","",Y38) -> 2830000 | Z40: =IF(Z38="","",Z38) -> 3127000 | AA40: =IF(AA38="","",AA38) -> 3214000 | AC40: =IF(AC38="","",AC38) -> 3439000 | AD40: =IF(AD38="","",AD38) -> 3320000
A41: Dividendos pagos - trimestre (desacumulado) · derivada · unid. moeda | C41: [linha bruta, sem código; lançada nas linhas abaixo] | D41: =N(D36)-N(N36) -> -358000 | E41: =N(E36)-N(D36) -> 3767000 | F41: =N(F36)-N(E36) -> 3640000 | G41: =N(G36) -> 3732000 | I41: =N(I36)-N(G36) -> 3595000 | J41: =N(J36)-N(I36) -> 3811000 | K41: =N(K36)-N(J36) -> 3703000 | L41: =N(L36) -> 3768000 | N41: =N(N36)-N(L36) -> 3650000 | O41: =N(O36)-N(N36) -> 3849000 | P41: =N(P36)-N(O36) -> 3758000 | Q41: =N(Q36) -> 3825000 | S41: =N(S36)-N(Q36) -> 3710000 | T41: =N(T36)-N(S36) -> 3895000 | U41: =N(U36)-N(T36) -> 3804000 | V41: =N(V36) -> 3856000 | X41: =N(X36)-N(V36) -> 3758000 | Y41: =N(Y36)-N(X36) -> 3945000 | Z41: =N(Z36)-N(Y36) -> 3862000 | AA41: =N(AA36) -> 3921000 | AC41: =N(AC36)-N(AA36) -> 3822000 | AD41: =N(AD36)-N(AC36) -> 4035000
A42: (lançamento) código 10, sinal -1 sobre a linha bruta 41: Dividendos pagos - trimestre (desacumulado) | B42: 10 | C42: Common Dividends | D42: =IF(D41="","",-1*D41) -> 358000 | E42: =IF(E41="","",-1*E41) -> -3767000 | F42: =IF(F41="","",-1*F41) -> -3640000 | G42: =IF(G41="","",-1*G41) -> -3732000 | I42: =IF(I41="","",-1*I41) -> -3595000 | J42: =IF(J41="","",-1*J41) -> -3811000 | K42: =IF(K41="","",-1*K41) -> -3703000 | L42: =IF(L41="","",-1*L41) -> -3768000 | N42: =IF(N41="","",-1*N41) -> -3650000 | O42: =IF(O41="","",-1*O41) -> -3849000 | P42: =IF(P41="","",-1*P41) -> -3758000 | Q42: =IF(Q41="","",-1*Q41) -> -3825000 | S42: =IF(S41="","",-1*S41) -> -3710000 | T42: =IF(T41="","",-1*T41) -> -3895000 | U42: =IF(U41="","",-1*U41) -> -3804000 | V42: =IF(V41="","",-1*V41) -> -3856000 | X42: =IF(X41="","",-1*X41) -> -3758000 | Y42: =IF(Y41="","",-1*Y41) -> -3945000 | Z42: =IF(Z41="","",-1*Z41) -> -3862000 | AA42: =IF(AA41="","",-1*AA41) -> -3921000 | AC42: =IF(AC41="","",-1*AC41) -> -3822000 | AD42: =IF(AD41="","",-1*AD41) -> -4035000
A43: BALANÇO (USD, saldo no fim do trimestre) | C43: [linha bruta, sem código; lançada nas linhas abaixo]
A44: Caixa + títulos negociáveis CP e LP (a Apple considera o LP na sua caixa líquida) [us-gaap:CashAndCashEquivalentsAtCarryingValue] · fonte · unid. moeda | B44: 11 | C44: Cash and equivalents (inc. investment securities) | D44: 38466000 | E44: 34050000 | F44: 34940000 | G44: 37119000 | I44: 28098000 | J44: 27502000 | K44: 23646000 | L44: 20535000 | N44: 24687000 | O44: 28408000 | P44: 29965000 | Q44: 40760000 | S44: 32695000 | T44: 25565000 | U44: 29943000 | V44: 30299000 | X44: 28162000 | Y44: 36269000 | Z44: 35934000 | AA44: 45317000 | AC44: 45572000 | AD44: 39544000
A45: Caixa + títulos negociáveis CP e LP (a Apple considera o LP na sua caixa líquida) [us-gaap:MarketableSecuritiesCurrent] · fonte · unid. moeda | B45: 11 | C45: Cash and equivalents (inc. investment securities) | D45: 31368000 | E45: 27646000 | F45: 27699000 | G45: 26794000 | I45: 23413000 | J45: 20729000 | K45: 24658000 | L45: 30820000 | N45: 31185000 | O45: 34074000 | P45: 31590000 | Q45: 32340000 | S45: 34455000 | T45: 36236000 | U45: 35228000 | V45: 23476000 | X45: 20336000 | Y45: 19103000 | Z45: 18763000 | AA45: 21590000 | AC45: 22935000 | AD45: 22855000
A46: Caixa + títulos negociáveis CP e LP (a Apple considera o LP na sua caixa líquida) [us-gaap:MarketableSecuritiesNoncurrent] · fonte · unid. moeda | B46: 11 | C46: Cash and equivalents (inc. investment securities) | D46: 134539000 | E46: 131948000 | F46: 127877000 | G46: 138683000 | I46: 141219000 | J46: 131077000 | K46: 120805000 | L46: 114095000 | N46: 110461000 | O46: 104061000 | P46: 100544000 | Q46: 99475000 | S46: 95187000 | T46: 91240000 | U46: 91479000 | V46: 87593000 | X46: 84424000 | Y46: 77614000 | Z46: 77723000 | AA46: 77888000 | AC46: 78088000 | AD46: 84118000
A47: Contas a receber de clientes [us-gaap:AccountsReceivableNetCurrent] · fonte · unid. moeda | B47: 12 | C47: Accounts receivable | D47: 18503000 | E47: 17475000 | F47: 26278000 | G47: 30213000 | I47: 20815000 | J47: 21803000 | K47: 28184000 | L47: 23752000 | N47: 17936000 | O47: 19549000 | P47: 29508000 | Q47: 23194000 | S47: 21837000 | T47: 22795000 | U47: 33410000 | V47: 29639000 | X47: 26136000 | Y47: 27557000 | Z47: 39777000 | AA47: 39921000 | AC47: 30339000 | AD47: 31398000
A48: Estoques [us-gaap:InventoryNet] · fonte · unid. moeda | B48: 13 | C48: Inventories | D48: 5219000 | E48: 5178000 | F48: 6580000 | G48: 5876000 | I48: 5460000 | J48: 5433000 | K48: 4946000 | L48: 6820000 | N48: 7482000 | O48: 7351000 | P48: 6331000 | Q48: 6511000 | S48: 6232000 | T48: 6165000 | U48: 7286000 | V48: 6911000 | X48: 6269000 | Y48: 5925000 | Z48: 5718000 | AA48: 5875000 | AC48: 6747000 | AD48: 11092000
A49: Recebíveis de fornecedores (non-trade) + outros ativos circulantes [us-gaap:NontradeReceivablesCurrent] · fonte · unid. moeda | B49: 16 | C49: Other current assets | D49: 14533000 | E49: 16433000 | F49: 25228000 | G49: 35040000 | I49: 24585000 | J49: 20439000 | K49: 32748000 | L49: 30428000 | N49: 17963000 | O49: 19637000 | P49: 31477000 | Q49: 26908000 | S49: 19313000 | T49: 20377000 | U49: 32833000 | V49: 29667000 | X49: 23662000 | Y49: 19278000 | Z49: 33180000 | AA49: 30399000 | AC49: 23172000 | AD49: 27509000
A50: Recebíveis de fornecedores (non-trade) + outros ativos circulantes [us-gaap:OtherAssetsCurrent] · fonte · unid. moeda | B50: 16 | C50: Other current assets | D50: 13376000 | E50: 13641000 | F50: 14111000 | G50: 18112000 | I50: 15809000 | J50: 16386000 | K50: 21223000 | L50: 16422000 | N50: 13660000 | O50: 13640000 | P50: 14695000 | Q50: 13979000 | S50: 13884000 | T50: 14297000 | U50: 14287000 | V50: 13248000 | X50: 14109000 | Y50: 14359000 | Z50: 14585000 | AA50: 15002000 | AC50: 15349000 | AD50: 17420000
A51: Imobilizado líquido [us-gaap:PropertyPlantAndEquipmentNet] · fonte · unid. moeda | B51: 18 | C51: PP&E | D51: 37815000 | E51: 38615000 | F51: 39440000 | G51: 39245000 | I51: 39304000 | J51: 40335000 | K51: 42117000 | L51: 42951000 | N51: 43398000 | O51: 43550000 | P51: 43715000 | Q51: 43666000 | S51: 43546000 | T51: 44502000 | U51: 45680000 | V51: 46069000 | X51: 46876000 | Y51: 48508000 | Z51: 49834000 | AA51: 50159000 | AC51: 50116000 | AD51: 51431000
A52: Intangíveis não circulantes (linha própria no balanço a partir de dez/25) [us-gaap:IntangibleAssetsNetExcludingGoodwillNoncurrent] · fonte · unid. moeda | B52: 21 | C52: Intangibles | D52: 0 | E52: 0 | F52: 0 | G52: 0 | I52: 0 | J52: 0 | K52: 0 | L52: 0 | N52: 0 | O52: 0 | P52: 0 | Q52: 0 | S52: 0 | T52: 0 | U52: 0 | V52: 0 | X52: 0 | Y52: 0 | Z52: 11093000 | AA52: 0 | AC52: 21334000 | AD52: 20342000
A53: Outros ativos não circulantes (inclui IR diferido e direito de uso) [us-gaap:OtherAssetsNoncurrent] · fonte · unid. moeda | B53: 22 | C53: Other non-current assets | D53: 43339000 | E53: 44854000 | F53: 48849000 | G53: 50109000 | I53: 51959000 | J53: 52605000 | K53: 54428000 | L53: 60924000 | N53: 65388000 | O53: 64768000 | P53: 64758000 | Q53: 66681000 | S53: 70262000 | T53: 70435000 | U53: 74834000 | V53: 77183000 | X53: 81259000 | Y53: 82882000 | Z53: 72634000 | AA53: 93146000 | AC53: 77430000 | AD53: 77557000
A54: Fornecedores [us-gaap:AccountsPayableCurrent] · fonte · unid. moeda | B54: 23 | C54: Accounts payable | D54: 40127000 | E54: 40409000 | F54: 54763000 | G54: 74362000 | I54: 52682000 | J54: 48343000 | K54: 64115000 | L54: 57918000 | N54: 42945000 | O54: 46699000 | P54: 62611000 | Q54: 58146000 | S54: 45753000 | T54: 47574000 | U54: 68960000 | V54: 61910000 | X54: 54126000 | Y54: 50374000 | Z54: 69860000 | AA54: 70587000 | AC54: 57349000 | AD54: 64525000
A55: Outros passivos circulantes + receita diferida [us-gaap:OtherLiabilitiesCurrent] · fonte · unid. moeda | B55: 26 | C55: Other current liabilities (non-debt) | D55: 45660000 | E55: 43625000 | F55: 47493000 | G55: 49167000 | I55: 50248000 | J55: 48811000 | K55: 60845000 | L55: 59893000 | N55: 56425000 | O55: 58897000 | P55: 58829000 | Q55: 54611000 | S55: 57298000 | T55: 60889000 | U55: 78304000 | V55: 61151000 | X55: 61849000 | Y55: 62499000 | Z55: 66387000 | AA55: 68543000 | AC55: 57654000 | AD55: 62259000
... A63: Lucros retidos / (prejuízos acumulados) [us-gaap:RetainedEarningsAccumulatedDeficit] · fonte · unid. moeda | B63: 41 | C63: Retained earnings | D63: 15261000 | E63: 9233000 | F63: 5562000 | G63: 14435000 | I63: 12712000 | J63: 5289000 | K63: -3068000 | L63: 3240000 | N63: 4336000 | O63: 1408000 | P63: -214000 | Q63: 8242000 | S63: 4339000 | T63: -4726000 | U63: -19154000 | V63: -11221000 | X63: -15552000 | Y63: -17607000 | Z63: -14264000 | AA63: -2177000 | AC63: 12359000 | AD63: 11326000
A64: Dívida CP marcada como OtherShortTermBorrowings nos 10-Q de mar/20 e jun/20 (linha de outros empréstimos de CP no balanço desses trimestres) [us-gaap:OtherShortTermBorrowings] · fonte · unid. moeda | B64: 27 | C64: Current portion of long-term debt
A65: BALANÇO - totais divulgados (memória) | C65: [linha bruta, sem código; lançada nas linhas abaixo]
A66: Total do ativo [us-gaap:Assets] · memoria · unid. moeda | C66: [linha bruta, sem código; lançada nas linhas abaixo] | D66: 337158000 | E66: 329840000 | F66: 351002000 | G66: 381191000 | I66: 350662000 | J66: 336309000 | K66: 352755000 | L66: 346747000 | N66: 332160000 | O66: 335038000 | P66: 352583000 | Q66: 353514000 | S66: 337411000 | T66: 331612000 | U66: 364980000 | V66: 344085000 | X66: 331233000 | Y66: 331495000 | Z66: 359241000 | AA66: 379297000 | AC66: 371082000 | AD66: 383266000
A67: Total do passivo [us-gaap:Liabilities] · memoria · unid. moeda | C67: [linha bruta, sem código; lançada nas linhas abaixo] | D67: 267980000 | E67: 265560000 | F67: 287912000 | G67: 309259000 | I67: 283263000 | J67: 278202000 | K67: 302083000 | L67: 290020000 | N67: 270002000 | O67: 274764000 | P67: 290437000 | Q67: 279414000 | S67: 263217000 | T67: 264904000 | U67: 308030000 | V67: 277327000 | X67: 264437000 | Y67: 265665000 | Z67: 285508000 | AA67: 291107000 | AC67: 264591000 | AD67: 275746000
A68: Total do PL [us-gaap:StockholdersEquity] · memoria · unid. moeda | C68: [linha bruta, sem código; lançada nas linhas abaixo] | D68: 69178000 | E68: 64280000 | F68: 63090000 | G68: 71932000 | I68: 67399000 | J68: 58107000 | K68: 50672000 | L68: 56727000 | N68: 62158000 | O68: 60274000 | P68: 62146000 | Q68: 74100000 | S68: 74194000 | T68: 66708000 | U68: 56950000 | V68: 66758000 | X68: 66796000 | Y68: 65830000 | Z68: 73733000 | AA68: 88190000 | AC68: 106491000 | AD68: 107520000
A69: CHECKS (devem ser 0) | C69: [linha bruta, sem código; lançada nas linhas abaixo]
A70: CHECK: contas de ativo - ativo total (USD, arredondado a 100 mil) · derivada · unid. moeda | C70: [linha bruta, sem código; lançada nas linhas abaixo] | D70: =ROUND(N(D44)+N(D45)+N(D46)+N(D47)+N(D48)+N(D49)+N(D50)+N(D51)+N(D52)+N(D53)-N(D66),-2) -> 0 | E70: =ROUND(N(E44)+N(E45)+N(E46)+N(E47)+N(E48)+N(E49)+N(E50)+N(E51)+N(E52)+N(E53)-N(E66),-2) -> 0 | F70: =ROUND(N(F44)+N(F45)+N(F46)+N(F47)+N(F48)+N(F49)+N(F50)+N(F51)+N(F52)+N(F53)-N(F66),-2) -> 0 | G70: =ROUND(N(G44)+N(G45)+N(G46)+N(G47)+N(G48)+N(G49)+N(G50)+N(G51)+N(G52)+N(G53)-N(G66),-2) -> 0 | I70: =ROUND(N(I44)+N(I45)+N(I46)+N(I47)+N(I48)+N(I49)+N(I50)+N(I51)+N(I52)+N(I53)-N(I66),-2) -> 0 | J70: =ROUND(N(J44)+N(J45)+N(J46)+N(J47)+N(J48)+N(J49)+N(J50)+N(J51)+N(J52)+N(J53)-N(J66),-2) -> 0 | K70: =ROUND(N(K44)+N(K45)+N(K46)+N(K47)+N(K48)+N(K49)+N(K50)+N(K51)+N(K52)+N(K53)-N(K66),-2) -> 0 | L70: =ROUND(N(L44)+N(L45)+N(L46)+N(L47)+N(L48)+N(L49)+N(L50)+N(L51)+N(L52)+N(L53)-N(L66),-2) -> 0 | N70: =ROUND(N(N44)+N(N45)+N(N46)+N(N47)+N(N48)+N(N49)+N(N50)+N(N51)+N(N52)+N(N53)-N(N66),-2) -> 0 | O70: =ROUND(N(O44)+N(O45)+N(O46)+N(O47)+N(O48)+N(O49)+N(O50)+N(O51)+N(O52)+N(O53)-N(O66),-2) -> 0 | P70: =ROUND(N(P44)+N(P45)+N(P46)+N(P47)+N(P48)+N(P49)+N(P50)+N(P51)+N(P52)+N(P53)-N(P66),-2) -> 0 | Q70: =ROUND(N(Q44)+N(Q45)+N(Q46)+N(Q47)+N(Q48)+N(Q49)+N(Q50)+N(Q51)+N(Q52)+N(Q53)-N(Q66),-2) -> 0 | S70: =ROUND(N(S44)+N(S45)+N(S46)+N(S47)+N(S48)+N(S49)+N(S50)+N(S51)+N(S52)+N(S53)-N(S66),-2) -> 0 | T70: =ROUND(N(T44)+N(T45)+N(T46)+N(T47)+N(T48)+N(T49)+N(T50)+N(T51)+N(T52)+N(T53)-N(T66),-2) -> 0 | U70: =ROUND(N(U44)+N(U45)+N(U46)+N(U47)+N(U48)+N(U49)+N(U50)+N(U51)+N(U52)+N(U53)-N(U66),-2) -> 0 | V70: =ROUND(N(V44)+N(V45)+N(V46)+N(V47)+N(V48)+N(V49)+N(V50)+N(V51)+N(V52)+N(V53)-N(V66),-2) -> 0 | X70: =ROUND(N(X44)+N(X45)+N(X46)+N(X47)+N(X48)+N(X49)+N(X50)+N(X51)+N(X52)+N(X53)-N(X66),-2) -> 0 | Y70: =ROUND(N(Y44)+N(Y45)+N(Y46)+N(Y47)+N(Y48)+N(Y49)+N(Y50)+N(Y51)+N(Y52)+N(Y53)-N(Y66),-2) -> 0 | Z70: =ROUND(N(Z44)+N(Z45)+N(Z46)+N(Z47)+N(Z48)+N(Z49)+N(Z50)+N(Z51)+N(Z52)+N(Z53)-N(Z66),-2) -> 0 | AA70: =ROUND(N(AA44)+N(AA45)+N(AA46)+N(AA47)+N(AA48)+N(AA49)+N(AA50)+N(AA51)+N(AA52)+N(AA53)-N(AA66),-2) -> 0 | AC70: =ROUND(N(AC44)+N(AC45)+N(AC46)+N(AC47)+N(AC48)+N(AC49)+N(AC50)+N(AC51)+N(AC52)+N(AC53)-N(AC66),-2) -> 0 | AD70: =ROUND(N(AD44)+N(AD45)+N(AD46)+N(AD47)+N(AD48)+N(AD49)+N(AD50)+N(AD51)+N(AD52)+N(AD53)-N(AD66),-2) -> 0
A71: CHECK: contas de passivo - passivo total · derivada · unid. moeda | C71: [linha bruta, sem código; lançada nas linhas abaixo] | D71: =ROUND(N(D54)+N(D55)+N(D56)+N(D57)+N(D58)+N(D59)+N(D60)+N(D64)-N(D67),-2) -> 0 | E71: =ROUND(N(E54)+N(E55)+N(E56)+N(E57)+N(E58)+N(E59)+N(E60)+N(E64)-N(E67),-2) -> 0 | F71: =ROUND(N(F54)+N(F55)+N(F56)+N(F57)+N(F58)+N(F59)+N(F60)+N(F64)-N(F67),-2) -> 0 | G71: =ROUND(N(G54)+N(G55)+N(G56)+N(G57)+N(G58)+N(G59)+N(G60)+N(G64)-N(G67),-2) -> 0 | I71: =ROUND(N(I54)+N(I55)+N(I56)+N(I57)+N(I58)+N(I59)+N(I60)+N(I64)-N(I67),-2) -> 0 | J71: =ROUND(N(J54)+N(J55)+N(J56)+N(J57)+N(J58)+N(J59)+N(J60)+N(J64)-N(J67),-2) -> 0 | K71: =ROUND(N(K54)+N(K55)+N(K56)+N(K57)+N(K58)+N(K59)+N(K60)+N(K64)-N(K67),-2) -> 0 | L71: =ROUND(N(L54)+N(L55)+N(L56)+N(L57)+N(L58)+N(L59)+N(L60)+N(L64)-N(L67),-2) -> 0 | N71: =ROUND(N(N54)+N(N55)+N(N56)+N(N57)+N(N58)+N(N59)+N(N60)+N(N64)-N(N67),-2) -> 0 | O71: =ROUND(N(O54)+N(O55)+N(O56)+N(O57)+N(O58)+N(O59)+N(O60)+N(O64)-N(O67),-2) -> 0 | P71: =ROUND(N(P54)+N(P55)+N(P56)+N(P57)+N(P58)+N(P59)+N(P60)+N(P64)-N(P67),-2) -> 0 | Q71: =ROUND(N(Q54)+N(Q55)+N(Q56)+N(Q57)+N(Q58)+N(Q59)+N(Q60)+N(Q64)-N(Q67),-2) -> 0 | S71: =ROUND(N(S54)+N(S55)+N(S56)+N(S57)+N(S58)+N(S59)+N(S60)+N(S64)-N(S67),-2) -> 0 | T71: =ROUND(N(T54)+N(T55)+N(T56)+N(T57)+N(T58)+N(T59)+N(T60)+N(T64)-N(T67),-2) -> 0 | U71: =ROUND(N(U54)+N(U55)+N(U56)+N(U57)+N(U58)+N(U59)+N(U60)+N(U64)-N(U67),-2) -> 0 | V71: =ROUND(N(V54)+N(V55)+N(V56)+N(V57)+N(V58)+N(V59)+N(V60)+N(V64)-N(V67),-2) -> 0 | X71: =ROUND(N(X54)+N(X55)+N(X56)+N(X57)+N(X58)+N(X59)+N(X60)+N(X64)-N(X67),-2) -> 0 | Y71: =ROUND(N(Y54)+N(Y55)+N(Y56)+N(Y57)+N(Y58)+N(Y59)+N(Y60)+N(Y64)-N(Y67),-2) -> 0 | Z71: =ROUND(N(Z54)+N(Z55)+N(Z56)+N(Z57)+N(Z58)+N(Z59)+N(Z60)+N(Z64)-N(Z67),-2) -> 0 | AA71: =ROUND(N(AA54)+N(AA55)+N(AA56)+N(AA57)+N(AA58)+N(AA59)+N(AA60)+N(AA64)-N(AA67),-2) -> 0 | AC71: =ROUND(N(AC54)+N(AC55)+N(AC56)+N(AC57)+N(AC58)+N(AC59)+N(AC60)+N(AC64)-N(AC67),-2) -> 0 | AD71: =ROUND(N(AD54)+N(AD55)+N(AD56)+N(AD57)+N(AD58)+N(AD59)+N(AD60)+N(AD64)-N(AD67),-2) -> 0
A72: CHECK: contas de PL - PL total · derivada · unid. moeda | C72: [linha bruta, sem código; lançada nas linhas abaixo] | D72: =ROUND(N(D61)+N(D62)+N(D63)-N(D68),-2) -> 0 | E72: =ROUND(N(E61)+N(E62)+N(E63)-N(E68),-2) -> 0 | F72: =ROUND(N(F61)+N(F62)+N(F63)-N(F68),-2) -> 0 | G72: =ROUND(N(G61)+N(G62)+N(G63)-N(G68),-2) -> 0 | I72: =ROUND(N(I61)+N(I62)+N(I63)-N(I68),-2) -> 0 | J72: =ROUND(N(J61)+N(J62)+N(J63)-N(J68),-2) -> 0 | K72: =ROUND(N(K61)+N(K62)+N(K63)-N(K68),-2) -> 0 | L72: =ROUND(N(L61)+N(L62)+N(L63)-N(L68),-2) -> 0 | N72: =ROUND(N(N61)+N(N62)+N(N63)-N(N68),-2) -> 0 | O72: =ROUND(N(O61)+N(O62)+N(O63)-N(O68),-2) -> 0 | P72: =ROUND(N(P61)+N(P62)+N(P63)-N(P68),-2) -> 0 | Q72: =ROUND(N(Q61)+N(Q62)+N(Q63)-N(Q68),-2) -> 0 | S72: =ROUND(N(S61)+N(S62)+N(S63)-N(S68),-2) -> 0 | T72: =ROUND(N(T61)+N(T62)+N(T63)-N(T68),-2) -> 0 | U72: =ROUND(N(U61)+N(U62)+N(U63)-N(U68),-2) -> 0 | V72: =ROUND(N(V61)+N(V62)+N(V63)-N(V68),-2) -> 0 | X72: =ROUND(N(X61)+N(X62)+N(X63)-N(X68),-2) -> 0 | Y72: =ROUND(N(Y61)+N(Y62)+N(Y63)-N(Y68),-2) -> 0 | Z72: =ROUND(N(Z61)+N(Z62)+N(Z63)-N(Z68),-2) -> 0 | AA72: =ROUND(N(AA61)+N(AA62)+N(AA63)-N(AA68),-2) -> 0 | AC72: =ROUND(N(AC61)+N(AC62)+N(AC63)-N(AC68),-2) -> 0 | AD72: =ROUND(N(AD61)+N(AD62)+N(AD63)-N(AD68),-2) -> 0
A73: CHECK: receita - custo - despesas + outras - IR - lucro (deve ser 0) · derivada | C73: [linha bruta, sem código; lançada nas linhas abaixo] | D73: =ROUND(N(D24)-N(D25)-N(D27)+N(D29)-N(D30)-N(D32),-2) -> 0 | E73: =ROUND(N(E24)-N(E25)-N(E27)+N(E29)-N(E30)-N(E32),-2) -> 0 | F73: =ROUND(N(F24)-N(F25)-N(F27)+N(F29)-N(F30)-N(F32),-2) -> 0 | G73: =ROUND(N(G24)-N(G25)-N(G27)+N(G29)-N(G30)-N(G32),-2) -> 0 | I73: =ROUND(N(I24)-N(I25)-N(I27)+N(I29)-N(I30)-N(I32),-2) -> 0 | J73: =ROUND(N(J24)-N(J25)-N(J27)+N(J29)-N(J30)-N(J32),-2) -> 0 | K73: =ROUND(N(K24)-N(K25)-N(K27)+N(K29)-N(K30)-N(K32),-2) -> 0 | L73: =ROUND(N(L24)-N(L25)-N(L27)+N(L29)-N(L30)-N(L32),-2) -> 0 | N73: =ROUND(N(N24)-N(N25)-N(N27)+N(N29)-N(N30)-N(N32),-2) -> 0 | O73: =ROUND(N(O24)-N(O25)-N(O27)+N(O29)-N(O30)-N(O32),-2) -> 0 | P73: =ROUND(N(P24)-N(P25)-N(P27)+N(P29)-N(P30)-N(P32),-2) -> 0 | Q73: =ROUND(N(Q24)-N(Q25)-N(Q27)+N(Q29)-N(Q30)-N(Q32),-2) -> 0 | S73: =ROUND(N(S24)-N(S25)-N(S27)+N(S29)-N(S30)-N(S32),-2) -> 0 | T73: =ROUND(N(T24)-N(T25)-N(T27)+N(T29)-N(T30)-N(T32),-2) -> 0 | U73: =ROUND(N(U24)-N(U25)-N(U27)+N(U29)-N(U30)-N(U32),-2) -> 0 | V73: =ROUND(N(V24)-N(V25)-N(V27)+N(V29)-N(V30)-N(V32),-2) -> 0 | X73: =ROUND(N(X24)-N(X25)-N(X27)+N(X29)-N(X30)-N(X32),-2) -> 0 | Y73: =ROUND(N(Y24)-N(Y25)-N(Y27)+N(Y29)-N(Y30)-N(Y32),-2) -> 0 | Z73: =ROUND(N(Z24)-N(Z25)-N(Z27)+N(Z29)-N(Z30)-N(Z32),-2) -> 0 | AA73: =ROUND(N(AA24)-N(AA25)-N(AA27)+N(AA29)-N(AA30)-N(AA32),-2) -> 0 | AC73: =ROUND(N(AC24)-N(AC25)-N(AC27)+N(AC29)-N(AC30)-N(AC32),-2) -> 0 | AD73: =ROUND(N(AD24)-N(AD25)-N(AD27)+N(AD29)-N(AD30)-N(AD32),-2) -> 0
A74: [vazio] cod 5 Interest expense: a Apple não abre juros trimestrais na DRE (dentro de outras receitas, cod 6) | C74: [linha bruta, sem código; lançada nas linhas abaixo]
A75: [vazio] cod 8 Equity in affiliates: inexistente | C75: [linha bruta, sem código; lançada nas linhas abaixo]
A76: [vazio] cod 9 Minority interest: inexistente | C76: [linha bruta, sem código; lançada nas linhas abaixo]
A77: [vazio] cod 14 IR diferido ativo: dentro de outros ativos não circulantes | C77: [linha bruta, sem código; lançada nas linhas abaixo]
A78: [vazio] cod 15 Prepaid: dentro de outros ativos circulantes | C78: [linha bruta, sem código; lançada nas linhas abaixo]
A79: [vazio] cod 17 Equity in affiliates: inexistente | C79: [linha bruta, sem código; lançada nas linhas abaixo]
A80: [vazio] cod 19 Direito de uso: dentro de outros ativos não circulantes | C80: [linha bruta, sem código; lançada nas linhas abaixo]
A81: [vazio] cod 20 Goodwill: não aberto | C81: [linha bruta, sem código; lançada nas linhas abaixo]
A82: [vazio] cod 24 Accrued: dentro de outros passivos circulantes | C82: [linha bruta, sem código; lançada nas linhas abaixo]
A83: [vazio] cod 25 IR a pagar CP: dentro de outros passivos circulantes | C83: [linha bruta, sem código; lançada nas linhas abaixo]
A84: [vazio] cod 29 Arrendamento CP: dentro de outros passivos circulantes | C84: [linha bruta, sem código; lançada nas linhas abaixo]
A85: [vazio] cod 31 Arrendamento LP: dentro de outros passivos não circulantes | C85: [linha bruta, sem código; lançada nas linhas abaixo]
... A89: DRIVERS DE RECEITA (codigos 45+): receita por categoria (iPhone, Mac, iPad, Wearables, Services), custo por Produtos/Serviços e receita por segmento geográfico - SEC XBRL (instâncias dos 10-Q/10-K; USD, fator 0,000001). | C89: [linha bruta, sem código; lançada nas linhas abaixo]
A90: Receita iPhone (USD; trimestre-calendário; o 3T (jul-set, FQ4) = ano fiscal do 10-K menos 9M do 10-Q de jun) · fonte · unid. moeda | B90: 45 | C90: Receita iPhone (USD; trimestre-calendário; o 3T (jul-set, FQ | D90: 47938000 | E90: 39570000 | F90: 38868000 | G90: 71628000 | I90: 50570000 | J90: 40665000 | K90: 42626000 | L90: 65775000 | N90: 51334000 | O90: 39669000 | P90: 43805000 | Q90: 69702000 | S90: 45963000 | T90: 39296000 | U90: 46222000 | V90: 69138000 | X90: 46841000 | Y90: 44582000 | Z90: 49025000 | AA90: 85269000 | AC90: 56994000 | AD90: 54252000
A91: Receita Mac (USD) · fonte · unid. moeda | B91: 46 | C91: Receita Mac (USD) | D91: 9102000 | E91: 8235000 | F91: 9178000 | G91: 10852000 | I91: 10435000 | J91: 7382000 | K91: 11508000 | L91: 7735000 | N91: 7168000 | O91: 6840000 | P91: 7614000 | Q91: 7780000 | S91: 7451000 | T91: 7009000 | U91: 7744000 | V91: 8987000 | X91: 7949000 | Y91: 8046000 | Z91: 8726000 | AA91: 8386000 | AC91: 8399000 | AD91: 10352000
A92: Receita iPad (USD) · fonte · unid. moeda | B92: 47 | C92: Receita iPad (USD) | D92: 7807000 | E92: 7368000 | F92: 8252000 | G92: 7248000 | I92: 7646000 | J92: 7224000 | K92: 7174000 | L92: 9396000 | N92: 6670000 | O92: 5791000 | P92: 6443000 | Q92: 7023000 | S92: 5559000 | T92: 7162000 | U92: 6950000 | V92: 8088000 | X92: 6402000 | Y92: 6581000 | Z92: 6952000 | AA92: 8595000 | AC92: 6914000 | AD92: 6191000
A93: Receita Wearables, Home and Accessories (USD) · fonte · unid. moeda | B93: 48 | C93: Receita Wearables, Home and Accessories (USD) | D93: 7836000 | E93: 8775000 | F93: 8785000 | G93: 14701000 | I93: 8806000 | J93: 8084000 | K93: 9650000 | L93: 13482000 | N93: 8757000 | O93: 8284000 | P93: 9322000 | Q93: 11953000 | S93: 7913000 | T93: 8097000 | U93: 9042000 | V93: 11747000 | X93: 7522000 | Y93: 7404000 | Z93: 9013000 | AA93: 11493000 | AC93: 7901000 | AD93: 7883000
A94: Receita Services (USD) · fonte · unid. moeda | B94: 49 | C94: Receita Services (USD) | D94: 16901000 | E94: 17486000 | F94: 18277000 | G94: 19516000 | I94: 19821000 | J94: 19604000 | K94: 19188000 | L94: 20766000 | N94: 20907000 | O94: 21213000 | P94: 22314000 | Q94: 23117000 | S94: 23867000 | T94: 24213000 | U94: 24972000 | V94: 26340000 | X94: 26645000 | Y94: 27423000 | Z94: 28750000 | AA94: 30013000 | AC94: 30976000 | AD94: 30739000
A95: Custo das vendas - Produtos (USD) · fonte · unid. moeda | B95: 50 | C95: Custo das vendas - Produtos (USD) | D95: 46447000 | E95: 40899000 | F95: 42790000 | G95: 64309000 | I95: 49290000 | J95: 41485000 | K95: 46387000 | L95: 60765000 | N95: 46795000 | O95: 39136000 | P95: 42586000 | Q95: 58440000 | S95: 42424000 | T95: 39803000 | U95: 44566000 | V95: 59447000 | X95: 44030000 | Y95: 43620000 | Z95: 47019000 | AA95: 67478000 | AC95: 49179000 | AD95: 47153000
A96: Custo das vendas - Serviços (USD) · fonte · unid. moeda | B96: 51 | C96: Custo das vendas - Serviços (USD) | D96: 5058000 | E96: 5280000 | F96: 5396000 | G96: 5393000 | I96: 5429000 | J96: 5589000 | K96: 5664000 | L96: 6057000 | N96: 6065000 | O96: 6248000 | P96: 6485000 | Q96: 6280000 | S96: 6058000 | T96: 6296000 | U96: 6485000 | V96: 6578000 | X96: 6462000 | Y96: 6698000 | Z96: 7106000 | AA96: 7047000 | AC96: 7224000 | AD96: 7494000
A97: Receita segmento Américas (USD) · fonte · unid. moeda | B97: 52 | C97: Receita segmento Américas (USD) | D97: 34306000 | E97: 35870000 | F97: 36820000 | G97: 51496000 | I97: 40882000 | J97: 37472000 | K97: 39808000 | L97: 49278000 | N97: 37784000 | O97: 35383000 | P97: 40115000 | Q97: 50430000 | S97: 37273000 | T97: 37678000 | U97: 41664000 | V97: 52648000 | X97: 40315000 | Y97: 41198000 | Z97: 44192000 | AA97: 58529000 | AC97: 45093000 | AD97: 45781000
A98: Receita segmento Europa (USD; inclui Índia, Oriente Médio e África) · fonte · unid. moeda | B98: 53 | C98: Receita segmento Europa (USD; inclui Índia, Oriente Médio e | D98: 22264000 | E98: 18943000 | F98: 20794000 | G98: 29749000 | I98: 23287000 | J98: 19287000 | K98: 22795000 | L98: 27681000 | N98: 23945000 | O98: 20205000 | P98: 22463000 | Q98: 30397000 | S98: 24123000 | T98: 21884000 | U98: 24924000 | V98: 33861000 | X98: 24454000 | Y98: 24014000 | Z98: 28703000 | AA98: 38146000 | AC98: 28055000 | AD98: 29395000
A99: Receita segmento Grande China (USD) · fonte · unid. moeda | B99: 54 | C99: Receita segmento Grande China (USD) | D99: 17728000 | E99: 14762000 | F99: 14563000 | G99: 25783000 | I99: 18343000 | J99: 14604000 | K99: 15470000 | L99: 23905000 | N99: 17812000 | O99: 15758000 | P99: 15084000 | Q99: 20819000 | S99: 16372000 | T99: 14728000 | U99: 15033000 | V99: 18513000 | X99: 16002000 | Y99: 15369000 | Z99: 14493000 | AA99: 25526000 | AC99: 20497000 | AD99: 18816000
A100: Receita segmento Japão (USD) · fonte · unid. moeda | B100: 55 | C100: Receita segmento Japão (USD) | D100: 7742000 | E100: 6464000 | F100: 5991000 | G100: 7107000 | I100: 7724000 | J100: 5446000 | K100: 5700000 | L100: 6755000 | N100: 7176000 | O100: 4821000 | P100: 5505000 | Q100: 7767000 | S100: 6262000 | T100: 5097000 | U100: 5926000 | V100: 8987000 | X100: 7298000 | Y100: 5782000 | Z100: 6636000 | AA100: 9413000 | AC100: 8401000 | AD100: 6554000
A101: Receita segmento Resto da Ásia-Pacífico (USD) · fonte · unid. moeda | B101: 56 | C101: Receita segmento Resto da Ásia-Pacífico (USD) | D101: 7544000 | E101: 5395000 | F101: 5192000 | G101: 9810000 | I101: 7042000 | J101: 6150000 | K101: 6373000 | L101: 9535000 | N101: 8119000 | O101: 5630000 | P101: 6331000 | Q101: 10162000 | S101: 6723000 | T101: 6390000 | U101: 7383000 | V101: 10291000 | X101: 7290000 | Y101: 7673000 | Z101: 8442000 | AA101: 12142000 | AC101: 9138000 | AD101: 8871000
A102: Notas: valores dimensionais lidos das instâncias XBRL; o trimestre de set (FQ4) é o ano fiscal menos 9M, calculado na extração. | C102: [linha bruta, sem código; lançada nas linhas abaixo]
A104: Linhas de origem: 4 a 102. A Inputs (2) varre as linhas 4 a 150; as linhas 103 a 150 estão livres. Linhas "(lançamento)" aplicam código e sinal sobre a linha bruta indicada (a máscara tem uma só coluna de código).

Sheet Inputs (2)
A1: =IF(Control!B3="","EMPRESA",Control!B3) -> Apple Inc. | B1: Código | C1: Conta padronizada | D1: 2021 | E1: 2021 | F1: 2021 | G1: 2021 | H1: 2021 | I1: 2022 | J1: 2022 | K1: 2022 | L1: 2022 | M1: 2022 | N1: 2023 | O1: 2023 | P1: 2023 | Q1: 2023 | R1: 2023 | S1: 2024 | T1: 2024 | U1: 2024 | V1: 2024 | W1: 2024 | X1: 2025 | Y1: 2025 | Z1: 2025 | AA1: 2025 | AB1: 2025 | AC1: 2026 | AD1: 2026 | AE1: 2026 | AF1: 2026 | AG1: 2026
A2: US$ milhões | C2: Período | D2: 1Q21 | E2: 2Q21 | F2: 3Q21 | G2: 4Q21 | H2: 2021 | I2: 1Q22 | J2: 2Q22 | K2: 3Q22 | L2: 4Q22 | M2: 2022 | N2: 1Q23 | O2: 2Q23 | P2: 3Q23 | Q2: 4Q23 | R2: 2023 | S2: 1Q24 | T2: 2Q24 | U2: 3Q24 | V2: 4Q24 | W2: 2024 | X2: 1Q25 | Y2: 2Q25 | Z2: 3Q25 | AA2: 4Q25 | AB2: 2025 | AC2: 1Q26 | AD2: 2Q26 | AE2: 3Q26 | AF2: 4Q26 | AG2: 2026
A3: Actual flag | C3: 0 = sem dados / 1 = realizado | D3: 1 | E3: 1 | F3: 1 | G3: 1 | H3: 1 | I3: 1 | J3: 1 | K3: 1 | L3: 1 | M3: 1 | N3: 1 | O3: 1 | P3: 1 | Q3: 1 | R3: 1 | S3: 1 | T3: 1 | U3: 1 | V3: 1 | W3: 1 | X3: 1 | Y3: 1 | Z3: 1 | AA3: 1 | AB3: 1 | AC3: 1 | AD3: 1 | AE3: 0 | AF3: 0 | AG3: 0
B4: 1 | C4: Net Revenues | D4: =IF(D$3=0,"",SUMIFS(INDEX(Inputs!$D$4:$AG$150,0,MATCH(D$2,Inputs!$D$2:$AG$2,0)),Inputs!$B$4:$B$150,$B4)/1000) -> 89584 | E4: =IF(E$3=0,"",SUMIFS(INDEX(Inputs!$D$4:$AG$150,0,MATCH(E$2,Inputs!$D$2:$AG$2,0)),Inputs!$B$4:$B$150,$B4)/1000) -> 81434 | F4: =IF(F$3=0,"",SUMIFS(INDEX(Inputs!$D$4:$AG$150,0,MATCH(F$2,Inputs!$D$2:$AG$2,0)),Inputs!$B$4:$B$150,$B4)/1000) -> 83360 | G4: =IF(G$3=0,"",SUMIFS(INDEX(Inputs!$D$4:$AG$150,0,MATCH(G$2,Inputs!$D$2:$AG$2,0)),Inputs!$B$4:$B$150,$B4)/1000) -> 123945 | H4: =IF(COUNT(D4:G4)=4,SUM(D4:G4),"") -> 378323 | I4: =IF(I$3=0,"",SUMIFS(INDEX(Inputs!$D$4:$AG$150,0,MATCH(I$2,Inputs!$D$2:$AG$2,0)),Inputs!$B$4:$B$150,$B4)/1000) -> 97278 | J4: =IF(J$3=0,"",SUMIFS(INDEX(Inputs!$D$4:$AG$150,0,MATCH(J$2,Inputs!$D$2:$AG$2,0)),Inputs!$B$4:$B$150,$B4)/1000) -> 82959 | K4: =IF(K$3=0,"",SUMIFS(INDEX(Inputs!$D$4:$AG$150,0,MATCH(K$2,Inputs!$D$2:$AG$2,0)),Inputs!$B$4:$B$150,$B4)/1000) -> 90146 | L4: =IF(L$3=0,"",SUMIFS(INDEX(Inputs!$D$4:$AG$150,0,MATCH(L$2,Inputs!$D$2:$AG$2,0)),Inputs!$B$4:$B$150,$B4)/1000) -> 117154 | M4: =IF(COUNT(I4:L4)=4,SUM(I4:L4),"") -> 387537 | N4: =IF(N$3=0,"",SUMIFS(INDEX(Inputs!$D$4:$AG$150,0,MATCH(N$2,Inputs!$D$2:$AG$2,0)),Inputs!$B$4:$B$150,$B4)/1000) -> 94836 | O4: =IF(O$3=0,"",SUMIFS(INDEX(Inputs!$D$4:$AG$150,0,MATCH(O$2,Inputs!$D$2:$AG$2,0)),Inputs!$B$4:$B$150,$B4)/1000) -> 81797 | P4: =IF(P$3=0,"",SUMIFS(INDEX(Inputs!$D$4:$AG$150,0,MATCH(P$2,Inputs!$D$2:$AG$2,0)),Inputs!$B$4:$B$150,$B4)/1000) -> 89498 | Q4: =IF(Q$3=0,"",SUMIFS(INDEX(Inputs!$D$4:$AG$150,0,MATCH(Q$2,Inputs!$D$2:$AG$2,0)),Inputs!$B$4:$B$150,$B4)/1000) -> 119575 | R4: =IF(COUNT(N4:Q4)=4,SUM(N4:Q4),"") -> 385706 | S4: =IF(S$3=0,"",SUMIFS(INDEX(Inputs!$D$4:$AG$150,0,MATCH(S$2,Inputs!$D$2:$AG$2,0)),Inputs!$B$4:$B$150,$B4)/1000) -> 90753 | T4: =IF(T$3=0,"",SUMIFS(INDEX(Inputs!$D$4:$AG$150,0,MATCH(T$2,Inputs!$D$2:$AG$2,0)),Inputs!$B$4:$B$150,$B4)/1000) -> 85777 | U4: =IF(U$3=0,"",SUMIFS(INDEX(Inputs!$D$4:$AG$150,0,MATCH(U$2,Inputs!$D$2:$AG$2,0)),Inputs!$B$4:$B$150,$B4)/1000) -> 94930 | V4: =IF(V$3=0,"",SUMIFS(INDEX(Inputs!$D$4:$AG$150,0,MATCH(V$2,Inputs!$D$2:$AG$2,0)),Inputs!$B$4:$B$150,$B4)/1000) -> 124300 | W4: =IF(COUNT(S4:V4)=4,SUM(S4:V4),"") -> 395760 | X4: =IF(X$3=0,"",SUMIFS(INDEX(Inputs!$D$4:$AG$150,0,MATCH(X$2,Inputs!$D$2:$AG$2,0)),Inputs!$B$4:$B$150,$B4)/1000) -> 95359 | Y4: =IF(Y$3=0,"",SUMIFS(INDEX(Inputs!$D$4:$AG$150,0,MATCH(Y$2,Inputs!$D$2:$AG$2,0)),Inputs!$B$4:$B$150,$B4)/1000) -> 94036 | Z4: =IF(Z$3=0,"",SUMIFS(INDEX(Inputs!$D$4:$AG$150,0,MATCH(Z$2,Inputs!$D$2:$AG$2,0)),Inputs!$B$4:$B$150,$B4)/1000) -> 102466 | AA4: =IF(AA$3=0,"",SUMIFS(INDEX(Inputs!$D$4:$AG$150,0,MATCH(AA$2,Inputs!$D$2:$AG$2,0)),Inputs!$B$4:$B$150,$B4)/1000) -> 143756 | AB4: =IF(COUNT(X4:AA4)=4,SUM(X4:AA4),"") -> 435617 | AC4: =IF(AC$3=0,"",SUMIFS(INDEX(Inputs!$D$4:$AG$150,0,MATCH(AC$2,Inputs!$D$2:$AG$2,0)),Inputs!$B$4:$B$150,$B4)/1000) -> 111184 | AD4: =IF(AD$3=0,"",SUMIFS(INDEX(Inputs!$D$4:$AG$150,0,MATCH(AD$2,Inputs!$D$2:$AG$2,0)),Inputs!$B$4:$B$150,$B4)/1000) -> 109417 | AE4: =IF(AE$3=0,"",SUMIFS(INDEX(Inputs!$D$4:$AG$150,0,MATCH(AE$2,Inputs!$D$2:$AG$2,0)),Inputs!$B$4:$B$150,$B4)/1000) | AF4: =IF(AF$3=0,"",SUMIFS(INDEX(Inputs!$D$4:$AG$150,0,MATCH(AF$2,Inputs!$D$2:$AG$2,0)),Inputs!$B$4:$B$150,$B4)/1000) | AG4: =IF(COUNT(AC4:AF4)=4,SUM(AC4:AF4),"")
B5: 2 | C5: COGS (cash) | D5: =IF(D$3=0,"",SUMIFS(INDEX(Inputs!$D$4:$AG$150,0,MATCH(D$2,Inputs!$D$2:$AG$2,0)),Inputs!$B$4:$B$150,$B5)/1000) -> -51505 | E5: =IF(E$3=0,"",SUMIFS(INDEX(Inputs!$D$4:$AG$150,0,MATCH(E$2,Inputs!$D$2:$AG$2,0)),Inputs!$B$4:$B$150,$B5)/1000) -> -46179 | F5: =IF(F$3=0,"",SUMIFS(INDEX(Inputs!$D$4:$AG$150,0,MATCH(F$2,Inputs!$D$2:$AG$2,0)),Inputs!$B$4:$B$150,$B5)/1000) -> -48186 | G5: =IF(G$3=0,"",SUMIFS(INDEX(Inputs!$D$4:$AG$150,0,MATCH(G$2,Inputs!$D$2:$AG$2,0)),Inputs!$B$4:$B$150,$B5)/1000) -> -69702 | H5: =IF(COUNT(D5:G5)=4,SUM(D5:G5),"") -> -215572 | I5: =IF(I$3=0,"",SUMIFS(INDEX(Inputs!$D$4:$AG$150,0,MATCH(I$2,Inputs!$D$2:$AG$2,0)),Inputs!$B$4:$B$150,$B5)/1000) -> -54719 | J5: =IF(J$3=0,"",SUMIFS(INDEX(Inputs!$D$4:$AG$150,0,MATCH(J$2,Inputs!$D$2:$AG$2,0)),Inputs!$B$4:$B$150,$B5)/1000) -> -47074 | K5: =IF(K$3=0,"",SUMIFS(INDEX(Inputs!$D$4:$AG$150,0,MATCH(K$2,Inputs!$D$2:$AG$2,0)),Inputs!$B$4:$B$150,$B5)/1000) -> -52051 | L5: =IF(L$3=0,"",SUMIFS(INDEX(Inputs!$D$4:$AG$150,0,MATCH(L$2,Inputs!$D$2:$AG$2,0)),Inputs!$B$4:$B$150,$B5)/1000) -> -66822 | M5: =IF(COUNT(I5:L5)=4,SUM(I5:L5),"") -> -220666 | N5: =IF(N$3=0,"",SUMIFS(INDEX(Inputs!$D$4:$AG$150,0,MATCH(N$2,Inputs!$D$2:$AG$2,0)),Inputs!$B$4:$B$150,$B5)/1000) -> -52860 | O5: =IF(O$3=0,"",SUMIFS(INDEX(Inputs!$D$4:$AG$150,0,MATCH(O$2,Inputs!$D$2:$AG$2,0)),Inputs!$B$4:$B$150,$B5)/1000) -> -45384 | P5: =IF(P$3=0,"",SUMIFS(INDEX(Inputs!$D$4:$AG$150,0,MATCH(P$2,Inputs!$D$2:$AG$2,0)),Inputs!$B$4:$B$150,$B5)/1000) -> -49071 | Q5: =IF(Q$3=0,"",SUMIFS(INDEX(Inputs!$D$4:$AG$150,0,MATCH(Q$2,Inputs!$D$2:$AG$2,0)),Inputs!$B$4:$B$150,$B5)/1000) -> -64720 | R5: =IF(COUNT(N5:Q5)=4,SUM(N5:Q5),"") -> -212035 | S5: =IF(S$3=0,"",SUMIFS(INDEX(Inputs!$D$4:$AG$150,0,MATCH(S$2,Inputs!$D$2:$AG$2,0)),Inputs!$B$4:$B$150,$B5)/1000) -> -48482 | T5: =IF(T$3=0,"",SUMIFS(INDEX(Inputs!$D$4:$AG$150,0,MATCH(T$2,Inputs!$D$2:$AG$2,0)),Inputs!$B$4:$B$150,$B5)/1000) -> -46099 | U5: =IF(U$3=0,"",SUMIFS(INDEX(Inputs!$D$4:$AG$150,0,MATCH(U$2,Inputs!$D$2:$AG$2,0)),Inputs!$B$4:$B$150,$B5)/1000) -> -51051 | V5: =IF(V$3=0,"",SUMIFS(INDEX(Inputs!$D$4:$AG$150,0,MATCH(V$2,Inputs!$D$2:$AG$2,0)),Inputs!$B$4:$B$150,$B5)/1000) -> -66025 | W5: =IF(COUNT(S5:V5)=4,SUM(S5:V5),"") -> -211657 | X5: =IF(X$3=0,"",SUMIFS(INDEX(Inputs!$D$4:$AG$150,0,MATCH(X$2,Inputs!$D$2:$AG$2,0)),Inputs!$B$4:$B$150,$B5)/1000) -> -50492 | Y5: =IF(Y$3=0,"",SUMIFS(INDEX(Inputs!$D$4:$AG$150,0,MATCH(Y$2,Inputs!$D$2:$AG$2,0)),Inputs!$B$4:$B$150,$B5)/1000) -> -50318 | Z5: =IF(Z$3=0,"",SUMIFS(INDEX(Inputs!$D$4:$AG$150,0,MATCH(Z$2,Inputs!$D$2:$AG$2,0)),Inputs!$B$4:$B$150,$B5)/1000) -> -54125 | AA5: =IF(AA$3=0,"",SUMIFS(INDEX(Inputs!$D$4:$AG$150,0,MATCH(AA$2,Inputs!$D$2:$AG$2,0)),Inputs!$B$4:$B$150,$B5)/1000) -> -74525 | AB5: =IF(COUNT(X5:AA5)=4,SUM(X5:AA5),"") -> -229460 | AC5: =IF(AC$3=0,"",SUMIFS(INDEX(Inputs!$D$4:$AG$150,0,MATCH(AC$2,Inputs!$D$2:$AG$2,0)),Inputs!$B$4:$B$150,$B5)/1000) -> -56403 | AD5: =IF(AD$3=0,"",SUMIFS(INDEX(Inputs!$D$4:$AG$150,0,MATCH(AD$2,Inputs!$D$2:$AG$2,0)),Inputs!$B$4:$B$150,$B5)/1000) -> -54647 | AE5: =IF(AE$3=0,"",SUMIFS(INDEX(Inputs!$D$4:$AG$150,0,MATCH(AE$2,Inputs!$D$2:$AG$2,0)),Inputs!$B$4:$B$150,$B5)/1000) | AF5: =IF(AF$3=0,"",SUMIFS(INDEX(Inputs!$D$4:$AG$150,0,MATCH(AF$2,Inputs!$D$2:$AG$2,0)),Inputs!$B$4:$B$150,$B5)/1000) | AG5: =IF(COUNT(AC5:AF5)=4,SUM(AC5:AF5),"")
B6: 3 | C6: SG&A and Other (cash) | D6: =IF(D$3=0,"",SUMIFS(INDEX(Inputs!$D$4:$AG$150,0,MATCH(D$2,Inputs!$D$2:$AG$2,0)),Inputs!$B$4:$B$150,$B6)/1000) -> -10927 | E6: =IF(E$3=0,"",SUMIFS(INDEX(Inputs!$D$4:$AG$150,0,MATCH(E$2,Inputs!$D$2:$AG$2,0)),Inputs!$B$4:$B$150,$B6)/1000) -> -8297 | F6: =IF(F$3=0,"",SUMIFS(INDEX(Inputs!$D$4:$AG$150,0,MATCH(F$2,Inputs!$D$2:$AG$2,0)),Inputs!$B$4:$B$150,$B6)/1000) -> -8399 | G6: =IF(G$3=0,"",SUMIFS(INDEX(Inputs!$D$4:$AG$150,0,MATCH(G$2,Inputs!$D$2:$AG$2,0)),Inputs!$B$4:$B$150,$B6)/1000) -> -10058 | H6: =IF(COUNT(D6:G6)=4,SUM(D6:G6),"") -> -37681 | I6: =IF(I$3=0,"",SUMIFS(INDEX(Inputs!$D$4:$AG$150,0,MATCH(I$2,Inputs!$D$2:$AG$2,0)),Inputs!$B$4:$B$150,$B6)/1000) -> -9843 | J6: =IF(J$3=0,"",SUMIFS(INDEX(Inputs!$D$4:$AG$150,0,MATCH(J$2,Inputs!$D$2:$AG$2,0)),Inputs!$B$4:$B$150,$B6)/1000) -> -10004 | K6: =IF(K$3=0,"",SUMIFS(INDEX(Inputs!$D$4:$AG$150,0,MATCH(K$2,Inputs!$D$2:$AG$2,0)),Inputs!$B$4:$B$150,$B6)/1000) -> -10336 | L6: =IF(L$3=0,"",SUMIFS(INDEX(Inputs!$D$4:$AG$150,0,MATCH(L$2,Inputs!$D$2:$AG$2,0)),Inputs!$B$4:$B$150,$B6)/1000) -> -11400 | M6: =IF(COUNT(I6:L6)=4,SUM(I6:L6),"") -> -41583 | N6: =IF(N$3=0,"",SUMIFS(INDEX(Inputs!$D$4:$AG$150,0,MATCH(N$2,Inputs!$D$2:$AG$2,0)),Inputs!$B$4:$B$150,$B6)/1000) -> -10760 | O6: =IF(O$3=0,"",SUMIFS(INDEX(Inputs!$D$4:$AG$150,0,MATCH(O$2,Inputs!$D$2:$AG$2,0)),Inputs!$B$4:$B$150,$B6)/1000) -> -10363 | P6: =IF(P$3=0,"",SUMIFS(INDEX(Inputs!$D$4:$AG$150,0,MATCH(P$2,Inputs!$D$2:$AG$2,0)),Inputs!$B$4:$B$150,$B6)/1000) -> -10805 | Q6: =IF(Q$3=0,"",SUMIFS(INDEX(Inputs!$D$4:$AG$150,0,MATCH(Q$2,Inputs!$D$2:$AG$2,0)),Inputs!$B$4:$B$150,$B6)/1000) -> -11634 | R6: =IF(COUNT(N6:Q6)=4,SUM(N6:Q6),"") -> -43562 | S6: =IF(S$3=0,"",SUMIFS(INDEX(Inputs!$D$4:$AG$150,0,MATCH(S$2,Inputs!$D$2:$AG$2,0)),Inputs!$B$4:$B$150,$B6)/1000) -> -11535 | T6: =IF(T$3=0,"",SUMIFS(INDEX(Inputs!$D$4:$AG$150,0,MATCH(T$2,Inputs!$D$2:$AG$2,0)),Inputs!$B$4:$B$150,$B6)/1000) -> -11476 | U6: =IF(U$3=0,"",SUMIFS(INDEX(Inputs!$D$4:$AG$150,0,MATCH(U$2,Inputs!$D$2:$AG$2,0)),Inputs!$B$4:$B$150,$B6)/1000) -> -11377 | V6: =IF(V$3=0,"",SUMIFS(INDEX(Inputs!$D$4:$AG$150,0,MATCH(V$2,Inputs!$D$2:$AG$2,0)),Inputs!$B$4:$B$150,$B6)/1000) -> -12363 | W6: =IF(COUNT(S6:V6)=4,SUM(S6:V6),"") -> -46751 | X6: =IF(X$3=0,"",SUMIFS(INDEX(Inputs!$D$4:$AG$150,0,MATCH(X$2,Inputs!$D$2:$AG$2,0)),Inputs!$B$4:$B$150,$B6)/1000) -> -12617 | Y6: =IF(Y$3=0,"",SUMIFS(INDEX(Inputs!$D$4:$AG$150,0,MATCH(Y$2,Inputs!$D$2:$AG$2,0)),Inputs!$B$4:$B$150,$B6)/1000) -> -12686 | Z6: =IF(Z$3=0,"",SUMIFS(INDEX(Inputs!$D$4:$AG$150,0,MATCH(Z$2,Inputs!$D$2:$AG$2,0)),Inputs!$B$4:$B$150,$B6)/1000) -> -12787 | AA6: =IF(AA$3=0,"",SUMIFS(INDEX(Inputs!$D$4:$AG$150,0,MATCH(AA$2,Inputs!$D$2:$AG$2,0)),Inputs!$B$4:$B$150,$B6)/1000) -> -15165 | AB6: =IF(COUNT(X6:AA6)=4,SUM(X6:AA6),"") -> -53255 | AC6: =IF(AC$3=0,"",SUMIFS(INDEX(Inputs!$D$4:$AG$150,0,MATCH(AC$2,Inputs!$D$2:$AG$2,0)),Inputs!$B$4:$B$150,$B6)/1000) -> -15457 | AD6: =IF(AD$3=0,"",SUMIFS(INDEX(Inputs!$D$4:$AG$150,0,MATCH(AD$2,Inputs!$D$2:$AG$2,0)),Inputs!$B$4:$B$150,$B6)/1000) -> -15755 | AE6: =IF(AE$3=0,"",SUMIFS(INDEX(Inputs!$D$4:$AG$150,0,MATCH(AE$2,Inputs!$D$2:$AG$2,0)),Inputs!$B$4:$B$150,$B6)/1000) | AF6: =IF(AF$3=0,"",SUMIFS(INDEX(Inputs!$D$4:$AG$150,0,MATCH(AF$2,Inputs!$D$2:$AG$2,0)),Inputs!$B$4:$B$150,$B6)/1000) | AG6: =IF(COUNT(AC6:AF6)=4,SUM(AC6:AF6),"")
B7: 4 | C7: D&A | D7: =IF(D$3=0,"",SUMIFS(INDEX(Inputs!$D$4:$AG$150,0,MATCH(D$2,Inputs!$D$2:$AG$2,0)),Inputs!$B$4:$B$150,$B7)/1000) -> 351 | E7: =IF(E$3=0,"",SUMIFS(INDEX(Inputs!$D$4:$AG$150,0,MATCH(E$2,Inputs!$D$2:$AG$2,0)),Inputs!$B$4:$B$150,$B7)/1000) -> -2832 | F7: =IF(F$3=0,"",SUMIFS(INDEX(Inputs!$D$4:$AG$150,0,MATCH(F$2,Inputs!$D$2:$AG$2,0)),Inputs!$B$4:$B$150,$B7)/1000) -> -2989 | G7: =IF(G$3=0,"",SUMIFS(INDEX(Inputs!$D$4:$AG$150,0,MATCH(G$2,Inputs!$D$2:$AG$2,0)),Inputs!$B$4:$B$150,$B7)/1000) -> -2697 | H7: =IF(COUNT(D7:G7)=4,SUM(D7:G7),"") -> -8167 | I7: =IF(I$3=0,"",SUMIFS(INDEX(Inputs!$D$4:$AG$150,0,MATCH(I$2,Inputs!$D$2:$AG$2,0)),Inputs!$B$4:$B$150,$B7)/1000) -> -2737 | J7: =IF(J$3=0,"",SUMIFS(INDEX(Inputs!$D$4:$AG$150,0,MATCH(J$2,Inputs!$D$2:$AG$2,0)),Inputs!$B$4:$B$150,$B7)/1000) -> -2805 | K7: =IF(K$3=0,"",SUMIFS(INDEX(Inputs!$D$4:$AG$150,0,MATCH(K$2,Inputs!$D$2:$AG$2,0)),Inputs!$B$4:$B$150,$B7)/1000) -> -2865 | L7: =IF(L$3=0,"",SUMIFS(INDEX(Inputs!$D$4:$AG$150,0,MATCH(L$2,Inputs!$D$2:$AG$2,0)),Inputs!$B$4:$B$150,$B7)/1000) -> -2916 | M7: =IF(COUNT(I7:L7)=4,SUM(I7:L7),"") -> -11323 | N7: =IF(N$3=0,"",SUMIFS(INDEX(Inputs!$D$4:$AG$150,0,MATCH(N$2,Inputs!$D$2:$AG$2,0)),Inputs!$B$4:$B$150,$B7)/1000) -> -2898 | O7: =IF(O$3=0,"",SUMIFS(INDEX(Inputs!$D$4:$AG$150,0,MATCH(O$2,Inputs!$D$2:$AG$2,0)),Inputs!$B$4:$B$150,$B7)/1000) -> -3052 | P7: =IF(P$3=0,"",SUMIFS(INDEX(Inputs!$D$4:$AG$150,0,MATCH(P$2,Inputs!$D$2:$AG$2,0)),Inputs!$B$4:$B$150,$B7)/1000) -> -2653 | Q7: =IF(Q$3=0,"",SUMIFS(INDEX(Inputs!$D$4:$AG$150,0,MATCH(Q$2,Inputs!$D$2:$AG$2,0)),Inputs!$B$4:$B$150,$B7)/1000) -> -2848 | R7: =IF(COUNT(N7:Q7)=4,SUM(N7:Q7),"") -> -11451 | S7: =IF(S$3=0,"",SUMIFS(INDEX(Inputs!$D$4:$AG$150,0,MATCH(S$2,Inputs!$D$2:$AG$2,0)),Inputs!$B$4:$B$150,$B7)/1000) -> -2836 | T7: =IF(T$3=0,"",SUMIFS(INDEX(Inputs!$D$4:$AG$150,0,MATCH(T$2,Inputs!$D$2:$AG$2,0)),Inputs!$B$4:$B$150,$B7)/1000) -> -2850 | U7: =IF(U$3=0,"",SUMIFS(INDEX(Inputs!$D$4:$AG$150,0,MATCH(U$2,Inputs!$D$2:$AG$2,0)),Inputs!$B$4:$B$150,$B7)/1000) -> -2911 | V7: =IF(V$3=0,"",SUMIFS(INDEX(Inputs!$D$4:$AG$150,0,MATCH(V$2,Inputs!$D$2:$AG$2,0)),Inputs!$B$4:$B$150,$B7)/1000) -> -3080 | W7: =IF(COUNT(S7:V7)=4,SUM(S7:V7),"") -> -11677 | X7: =IF(X$3=0,"",SUMIFS(INDEX(Inputs!$D$4:$AG$150,0,MATCH(X$2,Inputs!$D$2:$AG$2,0)),Inputs!$B$4:$B$150,$B7)/1000) -> -2661 | Y7: =IF(Y$3=0,"",SUMIFS(INDEX(Inputs!$D$4:$AG$150,0,MATCH(Y$2,Inputs!$D$2:$AG$2,0)),Inputs!$B$4:$B$150,$B7)/1000) -> -2830 | Z7: =IF(Z$3=0,"",SUMIFS(INDEX(Inputs!$D$4:$AG$150,0,MATCH(Z$2,Inputs!$D$2:$AG$2,0)),Inputs!$B$4:$B$150,$B7)/1000) -> -3127 | AA7: =IF(AA$3=0,"",SUMIFS(INDEX(Inputs!$D$4:$AG$150,0,MATCH(AA$2,Inputs!$D$2:$AG$2,0)),Inputs!$B$4:$B$150,$B7)/1000) -> -3214 | AB7: =IF(COUNT(X7:AA7)=4,SUM(X7:AA7),"") -> -11832 | AC7: =IF(AC$3=0,"",SUMIFS(INDEX(Inputs!$D$4:$AG$150,0,MATCH(AC$2,Inputs!$D$2:$AG$2,0)),Inputs!$B$4:$B$150,$B7)/1000) -> -3439 | AD7: =IF(AD$3=0,"",SUMIFS(INDEX(Inputs!$D$4:$AG$150,0,MATCH(AD$2,Inputs!$D$2:$AG$2,0)),Inputs!$B$4:$B$150,$B7)/1000) -> -3320 | AE7: =IF(AE$3=0,"",SUMIFS(INDEX(Inputs!$D$4:$AG$150,0,MATCH(AE$2,Inputs!$D$2:$AG$2,0)),Inputs!$B$4:$B$150,$B7)/1000) | AF7: =IF(AF$3=0,"",SUMIFS(INDEX(Inputs!$D$4:$AG$150,0,MATCH(AF$2,Inputs!$D$2:$AG$2,0)),Inputs!$B$4:$B$150,$B7)/1000) | AG7: =IF(COUNT(AC7:AF7)=4,SUM(AC7:AF7),"")
B8: 5 | C8: Interest Expense | D8: =IF(D$3=0,"",SUMIFS(INDEX(Inputs!$D$4:$AG$150,0,MATCH(D$2,Inputs!$D$2:$AG$2,0)),Inputs!$B$4:$B$150,$B8)/1000) -> 0 | E8: =IF(E$3=0,"",SUMIFS(INDEX(Inputs!$D$4:$AG$150,0,MATCH(E$2,Inputs!$D$2:$AG$2,0)),Inputs!$B$4:$B$150,$B8)/1000) -> 0 | F8: =IF(F$3=0,"",SUMIFS(INDEX(Inputs!$D$4:$AG$150,0,MATCH(F$2,Inputs!$D$2:$AG$2,0)),Inputs!$B$4:$B$150,$B8)/1000) -> 0 | G8: =IF(G$3=0,"",SUMIFS(INDEX(Inputs!$D$4:$AG$150,0,MATCH(G$2,Inputs!$D$2:$AG$2,0)),Inputs!$B$4:$B$150,$B8)/1000) -> 0 | H8: =IF(COUNT(D8:G8)=4,SUM(D8:G8),"") -> 0 | I8: =IF(I$3=0,"",SUMIFS(INDEX(Inputs!$D$4:$AG$150,0,MATCH(I$2,Inputs!$D$2:$AG$2,0)),Inputs!$B$4:$B$150,$B8)/1000) -> 0 | J8: =IF(J$3=0,"",SUMIFS(INDEX(Inputs!$D$4:$AG$150,0,MATCH(J$2,Inputs!$D$2:$AG$2,0)),Inputs!$B$4:$B$150,$B8)/1000) -> 0 | K8: =IF(K$3=0,"",SUMIFS(INDEX(Inputs!$D$4:$AG$150,0,MATCH(K$2,Inputs!$D$2:$AG$2,0)),Inputs!$B$4:$B$150,$B8)/1000) -> 0 | L8: =IF(L$3=0,"",SUMIFS(INDEX(Inputs!$D$4:$AG$150,0,MATCH(L$2,Inputs!$D$2:$AG$2,0)),Inputs!$B$4:$B$150,$B8)/1000) -> 0 | M8: =IF(COUNT(I8:L8)=4,SUM(I8:L8),"") -> 0 | N8: =IF(N$3=0,"",SUMIFS(INDEX(Inputs!$D$4:$AG$150,0,MATCH(N$2,Inputs!$D$2:$AG$2,0)),Inputs!$B$4:$B$150,$B8)/1000) -> 0 | O8: =IF(O$3=0,"",SUMIFS(INDEX(Inputs!$D$4:$AG$150,0,MATCH(O$2,Inputs!$D$2:$AG$2,0)),Inputs!$B$4:$B$150,$B8)/1000) -> 0 | P8: =IF(P$3=0,"",SUMIFS(INDEX(Inputs!$D$4:$AG$150,0,MATCH(P$2,Inputs!$D$2:$AG$2,0)),Inputs!$B$4:$B$150,$B8)/1000) -> 0 | Q8: =IF(Q$3=0,"",SUMIFS(INDEX(Inputs!$D$4:$AG$150,0,MATCH(Q$2,Inputs!$D$2:$AG$2,0)),Inputs!$B$4:$B$150,$B8)/1000) -> 0 | R8: =IF(COUNT(N8:Q8)=4,SUM(N8:Q8),"") -> 0 | S8: =IF(S$3=0,"",SUMIFS(INDEX(Inputs!$D$4:$AG$150,0,MATCH(S$2,Inputs!$D$2:$AG$2,0)),Inputs!$B$4:$B$150,$B8)/1000) -> 0 | T8: =IF(T$3=0,"",SUMIFS(INDEX(Inputs!$D$4:$AG$150,0,MATCH(T$2,Inputs!$D$2:$AG$2,0)),Inputs!$B$4:$B$150,$B8)/1000) -> 0 | U8: =IF(U$3=0,"",SUMIFS(INDEX(Inputs!$D$4:$AG$150,0,MATCH(U$2,Inputs!$D$2:$AG$2,0)),Inputs!$B$4:$B$150,$B8)/1000) -> 0 | V8: =IF(V$3=0,"",SUMIFS(INDEX(Inputs!$D$4:$AG$150,0,MATCH(V$2,Inputs!$D$2:$AG$2,0)),Inputs!$B$4:$B$150,$B8)/1000) -> 0 | W8: =IF(COUNT(S8:V8)=4,SUM(S8:V8),"") -> 0 | X8: =IF(X$3=0,"",SUMIFS(INDEX(Inputs!$D$4:$AG$150,0,MATCH(X$2,Inputs!$D$2:$AG$2,0)),Inputs!$B$4:$B$150,$B8)/1000) -> 0 | Y8: =IF(Y$3=0,"",SUMIFS(INDEX(Inputs!$D$4:$AG$150,0,MATCH(Y$2,Inputs!$D$2:$AG$2,0)),Inputs!$B$4:$B$150,$B8)/1000) -> 0 | Z8: =IF(Z$3=0,"",SUMIFS(INDEX(Inputs!$D$4:$AG$150,0,MATCH(Z$2,Inputs!$D$2:$AG$2,0)),Inputs!$B$4:$B$150,$B8)/1000) -> 0 | AA8: =IF(AA$3=0,"",SUMIFS(INDEX(Inputs!$D$4:$AG$150,0,MATCH(AA$2,Inputs!$D$2:$AG$2,0)),Inputs!$B$4:$B$150,$B8)/1000) -> 0 | AB8: =IF(COUNT(X8:AA8)=4,SUM(X8:AA8),"") -> 0 | AC8: =IF(AC$3=0,"",SUMIFS(INDEX(Inputs!$D$4:$AG$150,0,MATCH(AC$2,Inputs!$D$2:$AG$2,0)),Inputs!$B$4:$B$150,$B8)/1000) -> 0 | AD8: =IF(AD$3=0,"",SUMIFS(INDEX(Inputs!$D$4:$AG$150,0,MATCH(AD$2,Inputs!$D$2:$AG$2,0)),Inputs!$B$4:$B$150,$B8)/1000) -> 0 | AE8: =IF(AE$3=0,"",SUMIFS(INDEX(Inputs!$D$4:$AG$150,0,MATCH(AE$2,Inputs!$D$2:$AG$2,0)),Inputs!$B$4:$B$150,$B8)/1000) | AF8: =IF(AF$3=0,"",SUMIFS(INDEX(Inputs!$D$4:$AG$150,0,MATCH(AF$2,Inputs!$D$2:$AG$2,0)),Inputs!$B$4:$B$150,$B8)/1000) | AG8: =IF(COUNT(AC8:AF8)=4,SUM(AC8:AF8),"")
B9: 6 | C9: Nonoperating Income / (Loss) | D9: =IF(D$3=0,"",SUMIFS(INDEX(Inputs!$D$4:$AG$150,0,MATCH(D$2,Inputs!$D$2:$AG$2,0)),Inputs!$B$4:$B$150,$B9)/1000) -> 508 | E9: =IF(E$3=0,"",SUMIFS(INDEX(Inputs!$D$4:$AG$150,0,MATCH(E$2,Inputs!$D$2:$AG$2,0)),Inputs!$B$4:$B$150,$B9)/1000) -> 243 | F9: =IF(F$3=0,"",SUMIFS(INDEX(Inputs!$D$4:$AG$150,0,MATCH(F$2,Inputs!$D$2:$AG$2,0)),Inputs!$B$4:$B$150,$B9)/1000) -> -538 | G9: =IF(G$3=0,"",SUMIFS(INDEX(Inputs!$D$4:$AG$150,0,MATCH(G$2,Inputs!$D$2:$AG$2,0)),Inputs!$B$4:$B$150,$B9)/1000) -> -247 | H9: =IF(COUNT(D9:G9)=4,SUM(D9:G9),"") -> -34 | I9: =IF(I$3=0,"",SUMIFS(INDEX(Inputs!$D$4:$AG$150,0,MATCH(I$2,Inputs!$D$2:$AG$2,0)),Inputs!$B$4:$B$150,$B9)/1000) -> 160 | J9: =IF(J$3=0,"",SUMIFS(INDEX(Inputs!$D$4:$AG$150,0,MATCH(J$2,Inputs!$D$2:$AG$2,0)),Inputs!$B$4:$B$150,$B9)/1000) -> -10 | K9: =IF(K$3=0,"",SUMIFS(INDEX(Inputs!$D$4:$AG$150,0,MATCH(K$2,Inputs!$D$2:$AG$2,0)),Inputs!$B$4:$B$150,$B9)/1000) -> -237 | L9: =IF(L$3=0,"",SUMIFS(INDEX(Inputs!$D$4:$AG$150,0,MATCH(L$2,Inputs!$D$2:$AG$2,0)),Inputs!$B$4:$B$150,$B9)/1000) -> -393 | M9: =IF(COUNT(I9:L9)=4,SUM(I9:L9),"") -> -480 | N9: =IF(N$3=0,"",SUMIFS(INDEX(Inputs!$D$4:$AG$150,0,MATCH(N$2,Inputs!$D$2:$AG$2,0)),Inputs!$B$4:$B$150,$B9)/1000) -> 64 | O9: =IF(O$3=0,"",SUMIFS(INDEX(Inputs!$D$4:$AG$150,0,MATCH(O$2,Inputs!$D$2:$AG$2,0)),Inputs!$B$4:$B$150,$B9)/1000) -> -265 | P9: =IF(P$3=0,"",SUMIFS(INDEX(Inputs!$D$4:$AG$150,0,MATCH(P$2,Inputs!$D$2:$AG$2,0)),Inputs!$B$4:$B$150,$B9)/1000) -> 29 | Q9: =IF(Q$3=0,"",SUMIFS(INDEX(Inputs!$D$4:$AG$150,0,MATCH(Q$2,Inputs!$D$2:$AG$2,0)),Inputs!$B$4:$B$150,$B9)/1000) -> -50 | R9: =IF(COUNT(N9:Q9)=4,SUM(N9:Q9),"") -> -222 | S9: =IF(S$3=0,"",SUMIFS(INDEX(Inputs!$D$4:$AG$150,0,MATCH(S$2,Inputs!$D$2:$AG$2,0)),Inputs!$B$4:$B$150,$B9)/1000) -> 158 | T9: =IF(T$3=0,"",SUMIFS(INDEX(Inputs!$D$4:$AG$150,0,MATCH(T$2,Inputs!$D$2:$AG$2,0)),Inputs!$B$4:$B$150,$B9)/1000) -> 142 | U9: =IF(U$3=0,"",SUMIFS(INDEX(Inputs!$D$4:$AG$150,0,MATCH(U$2,Inputs!$D$2:$AG$2,0)),Inputs!$B$4:$B$150,$B9)/1000) -> 19 | V9: =IF(V$3=0,"",SUMIFS(INDEX(Inputs!$D$4:$AG$150,0,MATCH(V$2,Inputs!$D$2:$AG$2,0)),Inputs!$B$4:$B$150,$B9)/1000) -> -248 | W9: =IF(COUNT(S9:V9)=4,SUM(S9:V9),"") -> 71 | X9: =IF(X$3=0,"",SUMIFS(INDEX(Inputs!$D$4:$AG$150,0,MATCH(X$2,Inputs!$D$2:$AG$2,0)),Inputs!$B$4:$B$150,$B9)/1000) -> -279 | Y9: =IF(Y$3=0,"",SUMIFS(INDEX(Inputs!$D$4:$AG$150,0,MATCH(Y$2,Inputs!$D$2:$AG$2,0)),Inputs!$B$4:$B$150,$B9)/1000) -> -171 | Z9: =IF(Z$3=0,"",SUMIFS(INDEX(Inputs!$D$4:$AG$150,0,MATCH(Z$2,Inputs!$D$2:$AG$2,0)),Inputs!$B$4:$B$150,$B9)/1000) -> 377 | AA9: =IF(AA$3=0,"",SUMIFS(INDEX(Inputs!$D$4:$AG$150,0,MATCH(AA$2,Inputs!$D$2:$AG$2,0)),Inputs!$B$4:$B$150,$B9)/1000) -> 150 | AB9: =IF(COUNT(X9:AA9)=4,SUM(X9:AA9),"") -> 77 | AC9: =IF(AC$3=0,"",SUMIFS(INDEX(Inputs!$D$4:$AG$150,0,MATCH(AC$2,Inputs!$D$2:$AG$2,0)),Inputs!$B$4:$B$150,$B9)/1000) -> -52 | AD9: =IF(AD$3=0,"",SUMIFS(INDEX(Inputs!$D$4:$AG$150,0,MATCH(AD$2,Inputs!$D$2:$AG$2,0)),Inputs!$B$4:$B$150,$B9)/1000) -> 572 | AE9: =IF(AE$3=0,"",SUMIFS(INDEX(Inputs!$D$4:$AG$150,0,MATCH(AE$2,Inputs!$D$2:$AG$2,0)),Inputs!$B$4:$B$150,$B9)/1000) | AF9: =IF(AF$3=0,"",SUMIFS(INDEX(Inputs!$D$4:$AG$150,0,MATCH(AF$2,Inputs!$D$2:$AG$2,0)),Inputs!$B$4:$B$150,$B9)/1000) | AG9: =IF(COUNT(AC9:AF9)=4,SUM(AC9:AF9),"")
B10: 7 | C10: Taxes | D10: =IF(D$3=0,"",SUMIFS(INDEX(Inputs!$D$4:$AG$150,0,MATCH(D$2,Inputs!$D$2:$AG$2,0)),Inputs!$B$4:$B$150,$B10)/1000) -> -4381 | E10: =IF(E$3=0,"",SUMIFS(INDEX(Inputs!$D$4:$AG$150,0,MATCH(E$2,Inputs!$D$2:$AG$2,0)),Inputs!$B$4:$B$150,$B10)/1000) -> -2625 | F10: =IF(F$3=0,"",SUMIFS(INDEX(Inputs!$D$4:$AG$150,0,MATCH(F$2,Inputs!$D$2:$AG$2,0)),Inputs!$B$4:$B$150,$B10)/1000) -> -2697 | G10: =IF(G$3=0,"",SUMIFS(INDEX(Inputs!$D$4:$AG$150,0,MATCH(G$2,Inputs!$D$2:$AG$2,0)),Inputs!$B$4:$B$150,$B10)/1000) -> -6611 | H10: =IF(COUNT(D10:G10)=4,SUM(D10:G10),"") -> -16314 | I10: =IF(I$3=0,"",SUMIFS(INDEX(Inputs!$D$4:$AG$150,0,MATCH(I$2,Inputs!$D$2:$AG$2,0)),Inputs!$B$4:$B$150,$B10)/1000) -> -5129 | J10: =IF(J$3=0,"",SUMIFS(INDEX(Inputs!$D$4:$AG$150,0,MATCH(J$2,Inputs!$D$2:$AG$2,0)),Inputs!$B$4:$B$150,$B10)/1000) -> -3624 | K10: =IF(K$3=0,"",SUMIFS(INDEX(Inputs!$D$4:$AG$150,0,MATCH(K$2,Inputs!$D$2:$AG$2,0)),Inputs!$B$4:$B$150,$B10)/1000) -> -3936 | L10: =IF(L$3=0,"",SUMIFS(INDEX(Inputs!$D$4:$AG$150,0,MATCH(L$2,Inputs!$D$2:$AG$2,0)),Inputs!$B$4:$B$150,$B10)/1000) -> -5625 | M10: =IF(COUNT(I10:L10)=4,SUM(I10:L10),"") -> -18314 | N10: =IF(N$3=0,"",SUMIFS(INDEX(Inputs!$D$4:$AG$150,0,MATCH(N$2,Inputs!$D$2:$AG$2,0)),Inputs!$B$4:$B$150,$B10)/1000) -> -4222 | O10: =IF(O$3=0,"",SUMIFS(INDEX(Inputs!$D$4:$AG$150,0,MATCH(O$2,Inputs!$D$2:$AG$2,0)),Inputs!$B$4:$B$150,$B10)/1000) -> -2852 | P10: =IF(P$3=0,"",SUMIFS(INDEX(Inputs!$D$4:$AG$150,0,MATCH(P$2,Inputs!$D$2:$AG$2,0)),Inputs!$B$4:$B$150,$B10)/1000) -> -4042 | Q10: =IF(Q$3=0,"",SUMIFS(INDEX(Inputs!$D$4:$AG$150,0,MATCH(Q$2,Inputs!$D$2:$AG$2,0)),Inputs!$B$4:$B$150,$B10)/1000) -> -6407 | R10: =IF(COUNT(N10:Q10)=4,SUM(N10:Q10),"") -> -17523 | S10: =IF(S$3=0,"",SUMIFS(INDEX(Inputs!$D$4:$AG$150,0,MATCH(S$2,Inputs!$D$2:$AG$2,0)),Inputs!$B$4:$B$150,$B10)/1000) -> -4422 | T10: =IF(T$3=0,"",SUMIFS(INDEX(Inputs!$D$4:$AG$150,0,MATCH(T$2,Inputs!$D$2:$AG$2,0)),Inputs!$B$4:$B$150,$B10)/1000) -> -4046 | U10: =IF(U$3=0,"",SUMIFS(INDEX(Inputs!$D$4:$AG$150,0,MATCH(U$2,Inputs!$D$2:$AG$2,0)),Inputs!$B$4:$B$150,$B10)/1000) -> -14874 | V10: =IF(V$3=0,"",SUMIFS(INDEX(Inputs!$D$4:$AG$150,0,MATCH(V$2,Inputs!$D$2:$AG$2,0)),Inputs!$B$4:$B$150,$B10)/1000) -> -6254 | W10: =IF(COUNT(S10:V10)=4,SUM(S10:V10),"") -> -29596 | X10: =IF(X$3=0,"",SUMIFS(INDEX(Inputs!$D$4:$AG$150,0,MATCH(X$2,Inputs!$D$2:$AG$2,0)),Inputs!$B$4:$B$150,$B10)/1000) -> -4530 | Y10: =IF(Y$3=0,"",SUMIFS(INDEX(Inputs!$D$4:$AG$150,0,MATCH(Y$2,Inputs!$D$2:$AG$2,0)),Inputs!$B$4:$B$150,$B10)/1000) -> -4597 | Z10: =IF(Z$3=0,"",SUMIFS(INDEX(Inputs!$D$4:$AG$150,0,MATCH(Z$2,Inputs!$D$2:$AG$2,0)),Inputs!$B$4:$B$150,$B10)/1000) -> -5338 | AA10: =IF(AA$3=0,"",SUMIFS(INDEX(Inputs!$D$4:$AG$150,0,MATCH(AA$2,Inputs!$D$2:$AG$2,0)),Inputs!$B$4:$B$150,$B10)/1000) -> -8905 | AB10: =IF(COUNT(X10:AA10)=4,SUM(X10:AA10),"") -> -23370 | AC10: =IF(AC$3=0,"",SUMIFS(INDEX(Inputs!$D$4:$AG$150,0,MATCH(AC$2,Inputs!$D$2:$AG$2,0)),Inputs!$B$4:$B$150,$B10)/1000) -> -6255 | AD10: =IF(AD$3=0,"",SUMIFS(INDEX(Inputs!$D$4:$AG$150,0,MATCH(AD$2,Inputs!$D$2:$AG$2,0)),Inputs!$B$4:$B$150,$B10)/1000) -> -6478 | AE10: =IF(AE$3=0,"",SUMIFS(INDEX(Inputs!$D$4:$AG$150,0,MATCH(AE$2,Inputs!$D$2:$AG$2,0)),Inputs!$B$4:$B$150,$B10)/1000) | AF10: =IF(AF$3=0,"",SUMIFS(INDEX(Inputs!$D$4:$AG$150,0,MATCH(AF$2,Inputs!$D$2:$AG$2,0)),Inputs!$B$4:$B$150,$B10)/1000) | AG10: =IF(COUNT(AC10:AF10)=4,SUM(AC10:AF10),"")
B11: 8 | C11: Equity in Income of Affiliates, after tax (enter as +) | D11: =IF(D$3=0,"",SUMIFS(INDEX(Inputs!$D$4:$AG$150,0,MATCH(D$2,Inputs!$D$2:$AG$2,0)),Inputs!$B$4:$B$150,$B11)/1000) -> 0 | E11: =IF(E$3=0,"",SUMIFS(INDEX(Inputs!$D$4:$AG$150,0,MATCH(E$2,Inputs!$D$2:$AG$2,0)),Inputs!$B$4:$B$150,$B11)/1000) -> 0 | F11: =IF(F$3=0,"",SUMIFS(INDEX(Inputs!$D$4:$AG$150,0,MATCH(F$2,Inputs!$D$2:$AG$2,0)),Inputs!$B$4:$B$150,$B11)/1000) -> 0 | G11: =IF(G$3=0,"",SUMIFS(INDEX(Inputs!$D$4:$AG$150,0,MATCH(G$2,Inputs!$D$2:$AG$2,0)),Inputs!$B$4:$B$150,$B11)/1000) -> 0 | H11: =IF(COUNT(D11:G11)=4,SUM(D11:G11),"") -> 0 | I11: =IF(I$3=0,"",SUMIFS(INDEX(Inputs!$D$4:$AG$150,0,MATCH(I$2,Inputs!$D$2:$AG$2,0)),Inputs!$B$4:$B$150,$B11)/1000) -> 0 | J11: =IF(J$3=0,"",SUMIFS(INDEX(Inputs!$D$4:$AG$150,0,MATCH(J$2,Inputs!$D$2:$AG$2,0)),Inputs!$B$4:$B$150,$B11)/1000) -> 0 | K11: =IF(K$3=0,"",SUMIFS(INDEX(Inputs!$D$4:$AG$150,0,MATCH(K$2,Inputs!$D$2:$AG$2,0)),Inputs!$B$4:$B$150,$B11)/1000) -> 0 | L11: =IF(L$3=0,"",SUMIFS(INDEX(Inputs!$D$4:$AG$150,0,MATCH(L$2,Inputs!$D$2:$AG$2,0)),Inputs!$B$4:$B$150,$B11)/1000) -> 0 | M11: =IF(COUNT(I11:L11)=4,SUM(I11:L11),"") -> 0 | N11: =IF(N$3=0,"",SUMIFS(INDEX(Inputs!$D$4:$AG$150,0,MATCH(N$2,Inputs!$D$2:$AG$2,0)),Inputs!$B$4:$B$150,$B11)/1000) -> 0 | O11: =IF(O$3=0,"",SUMIFS(INDEX(Inputs!$D$4:$AG$150,0,MATCH(O$2,Inputs!$D$2:$AG$2,0)),Inputs!$B$4:$B$150,$B11)/1000) -> 0 | P11: =IF(P$3=0,"",SUMIFS(INDEX(Inputs!$D$4:$AG$150,0,MATCH(P$2,Inputs!$D$2:$AG$2,0)),Inputs!$B$4:$B$150,$B11)/1000) -> 0 | Q11: =IF(Q$3=0,"",SUMIFS(INDEX(Inputs!$D$4:$AG$150,0,MATCH(Q$2,Inputs!$D$2:$AG$2,0)),Inputs!$B$4:$B$150,$B11)/1000) -> 0 | R11: =IF(COUNT(N11:Q11)=4,SUM(N11:Q11),"") -> 0 | S11: =IF(S$3=0,"",SUMIFS(INDEX(Inputs!$D$4:$AG$150,0,MATCH(S$2,Inputs!$D$2:$AG$2,0)),Inputs!$B$4:$B$150,$B11)/1000) -> 0 | T11: =IF(T$3=0,"",SUMIFS(INDEX(Inputs!$D$4:$AG$150,0,MATCH(T$2,Inputs!$D$2:$AG$2,0)),Inputs!$B$4:$B$150,$B11)/1000) -> 0 | U11: =IF(U$3=0,"",SUMIFS(INDEX(Inputs!$D$4:$AG$150,0,MATCH(U$2,Inputs!$D$2:$AG$2,0)),Inputs!$B$4:$B$150,$B11)/1000) -> 0 | V11: =IF(V$3=0,"",SUMIFS(INDEX(Inputs!$D$4:$AG$150,0,MATCH(V$2,Inputs!$D$2:$AG$2,0)),Inputs!$B$4:$B$150,$B11)/1000) -> 0 | W11: =IF(COUNT(S11:V11)=4,SUM(S11:V11),"") -> 0 | X11: =IF(X$3=0,"",SUMIFS(INDEX(Inputs!$D$4:$AG$150,0,MATCH(X$2,Inputs!$D$2:$AG$2,0)),Inputs!$B$4:$B$150,$B11)/1000) -> 0 | Y11: =IF(Y$3=0,"",SUMIFS(INDEX(Inputs!$D$4:$AG$150,0,MATCH(Y$2,Inputs!$D$2:$AG$2,0)),Inputs!$B$4:$B$150,$B11)/1000) -> 0 | Z11: =IF(Z$3=0,"",SUMIFS(INDEX(Inputs!$D$4:$AG$150,0,MATCH(Z$2,Inputs!$D$2:$AG$2,0)),Inputs!$B$4:$B$150,$B11)/1000) -> 0 | AA11: =IF(AA$3=0,"",SUMIFS(INDEX(Inputs!$D$4:$AG$150,0,MATCH(AA$2,Inputs!$D$2:$AG$2,0)),Inputs!$B$4:$B$150,$B11)/1000) -> 0 | AB11: =IF(COUNT(X11:AA11)=4,SUM(X11:AA11),"") -> 0 | AC11: =IF(AC$3=0,"",SUMIFS(INDEX(Inputs!$D$4:$AG$150,0,MATCH(AC$2,Inputs!$D$2:$AG$2,0)),Inputs!$B$4:$B$150,$B11)/1000) -> 0 | AD11: =IF(AD$3=0,"",SUMIFS(INDEX(Inputs!$D$4:$AG$150,0,MATCH(AD$2,Inputs!$D$2:$AG$2,0)),Inputs!$B$4:$B$150,$B11)/1000) -> 0 | AE11: =IF(AE$3=0,"",SUMIFS(INDEX(Inputs!$D$4:$AG$150,0,MATCH(AE$2,Inputs!$D$2:$AG$2,0)),Inputs!$B$4:$B$150,$B11)/1000) | AF11: =IF(AF$3=0,"",SUMIFS(INDEX(Inputs!$D$4:$AG$150,0,MATCH(AF$2,Inputs!$D$2:$AG$2,0)),Inputs!$B$4:$B$150,$B11)/1000) | AG11: =IF(COUNT(AC11:AF11)=4,SUM(AC11:AF11),"")
B12: 9 | C12: Minority Interest Expense, after tax (enter as - ) | D12: =IF(D$3=0,"",SUMIFS(INDEX(Inputs!$D$4:$AG$150,0,MATCH(D$2,Inputs!$D$2:$AG$2,0)),Inputs!$B$4:$B$150,$B12)/1000) -> 0 | E12: =IF(E$3=0,"",SUMIFS(INDEX(Inputs!$D$4:$AG$150,0,MATCH(E$2,Inputs!$D$2:$AG$2,0)),Inputs!$B$4:$B$150,$B12)/1000) -> 0 | F12: =IF(F$3=0,"",SUMIFS(INDEX(Inputs!$D$4:$AG$150,0,MATCH(F$2,Inputs!$D$2:$AG$2,0)),Inputs!$B$4:$B$150,$B12)/1000) -> 0 | G12: =IF(G$3=0,"",SUMIFS(INDEX(Inputs!$D$4:$AG$150,0,MATCH(G$2,Inputs!$D$2:$AG$2,0)),Inputs!$B$4:$B$150,$B12)/1000) -> 0 | H12: =IF(COUNT(D12:G12)=4,SUM(D12:G12),"") -> 0 | I12: =IF(I$3=0,"",SUMIFS(INDEX(Inputs!$D$4:$AG$150,0,MATCH(I$2,Inputs!$D$2:$AG$2,0)),Inputs!$B$4:$B$150,$B12)/1000) -> 0 | J12: =IF(J$3=0,"",SUMIFS(INDEX(Inputs!$D$4:$AG$150,0,MATCH(J$2,Inputs!$D$2:$AG$2,0)),Inputs!$B$4:$B$150,$B12)/1000) -> 0 | K12: =IF(K$3=0,"",SUMIFS(INDEX(Inputs!$D$4:$AG$150,0,MATCH(K$2,Inputs!$D$2:$AG$2,0)),Inputs!$B$4:$B$150,$B12)/1000) -> 0 | L12: =IF(L$3=0,"",SUMIFS(INDEX(Inputs!$D$4:$AG$150,0,MATCH(L$2,Inputs!$D$2:$AG$2,0)),Inputs!$B$4:$B$150,$B12)/1000) -> 0 | M12: =IF(COUNT(I12:L12)=4,SUM(I12:L12),"") -> 0 | N12: =IF(N$3=0,"",SUMIFS(INDEX(Inputs!$D$4:$AG$150,0,MATCH(N$2,Inputs!$D$2:$AG$2,0)),Inputs!$B$4:$B$150,$B12)/1000) -> 0 | O12: =IF(O$3=0,"",SUMIFS(INDEX(Inputs!$D$4:$AG$150,0,MATCH(O$2,Inputs!$D$2:$AG$2,0)),Inputs!$B$4:$B$150,$B12)/1000) -> 0 | P12: =IF(P$3=0,"",SUMIFS(INDEX(Inputs!$D$4:$AG$150,0,MATCH(P$2,Inputs!$D$2:$AG$2,0)),Inputs!$B$4:$B$150,$B12)/1000) -> 0 | Q12: =IF(Q$3=0,"",SUMIFS(INDEX(Inputs!$D$4:$AG$150,0,MATCH(Q$2,Inputs!$D$2:$AG$2,0)),Inputs!$B$4:$B$150,$B12)/1000) -> 0 | R12: =IF(COUNT(N12:Q12)=4,SUM(N12:Q12),"") -> 0 | S12: =IF(S$3=0,"",SUMIFS(INDEX(Inputs!$D$4:$AG$150,0,MATCH(S$2,Inputs!$D$2:$AG$2,0)),Inputs!$B$4:$B$150,$B12)/1000) -> 0 | T12: =IF(T$3=0,"",SUMIFS(INDEX(Inputs!$D$4:$AG$150,0,MATCH(T$2,Inputs!$D$2:$AG$2,0)),Inputs!$B$4:$B$150,$B12)/1000) -> 0 | U12: =IF(U$3=0,"",SUMIFS(INDEX(Inputs!$D$4:$AG$150,0,MATCH(U$2,Inputs!$D$2:$AG$2,0)),Inputs!$B$4:$B$150,$B12)/1000) -> 0 | V12: =IF(V$3=0,"",SUMIFS(INDEX(Inputs!$D$4:$AG$150,0,MATCH(V$2,Inputs!$D$2:$AG$2,0)),Inputs!$B$4:$B$150,$B12)/1000) -> 0 | W12: =IF(COUNT(S12:V12)=4,SUM(S12:V12),"") -> 0 | X12: =IF(X$3=0,"",SUMIFS(INDEX(Inputs!$D$4:$AG$150,0,MATCH(X$2,Inputs!$D$2:$AG$2,0)),Inputs!$B$4:$B$150,$B12)/1000) -> 0 | Y12: =IF(Y$3=0,"",SUMIFS(INDEX(Inputs!$D$4:$AG$150,0,MATCH(Y$2,Inputs!$D$2:$AG$2,0)),Inputs!$B$4:$B$150,$B12)/1000) -> 0 | Z12: =IF(Z$3=0,"",SUMIFS(INDEX(Inputs!$D$4:$AG$150,0,MATCH(Z$2,Inputs!$D$2:$AG$2,0)),Inputs!$B$4:$B$150,$B12)/1000) -> 0 | AA12: =IF(AA$3=0,"",SUMIFS(INDEX(Inputs!$D$4:$AG$150,0,MATCH(AA$2,Inputs!$D$2:$AG$2,0)),Inputs!$B$4:$B$150,$B12)/1000) -> 0 | AB12: =IF(COUNT(X12:AA12)=4,SUM(X12:AA12),"") -> 0 | AC12: =IF(AC$3=0,"",SUMIFS(INDEX(Inputs!$D$4:$AG$150,0,MATCH(AC$2,Inputs!$D$2:$AG$2,0)),Inputs!$B$4:$B$150,$B12)/1000) -> 0 | AD12: =IF(AD$3=0,"",SUMIFS(INDEX(Inputs!$D$4:$AG$150,0,MATCH(AD$2,Inputs!$D$2:$AG$2,0)),Inputs!$B$4:$B$150,$B12)/1000) -> 0 | AE12: =IF(AE$3=0,"",SUMIFS(INDEX(Inputs!$D$4:$AG$150,0,MATCH(AE$2,Inputs!$D$2:$AG$2,0)),Inputs!$B$4:$B$150,$B12)/1000) | AF12: =IF(AF$3=0,"",SUMIFS(INDEX(Inputs!$D$4:$AG$150,0,MATCH(AF$2,Inputs!$D$2:$AG$2,0)),Inputs!$B$4:$B$150,$B12)/1000) | AG12: =IF(COUNT(AC12:AF12)=4,SUM(AC12:AF12),"")
B13: 10 | C13: Common Dividends | D13: =IF(D$3=0,"",SUMIFS(INDEX(Inputs!$D$4:$AG$150,0,MATCH(D$2,Inputs!$D$2:$AG$2,0)),Inputs!$B$4:$B$150,$B13)/1000) -> 358 | E13: =IF(E$3=0,"",SUMIFS(INDEX(Inputs!$D$4:$AG$150,0,MATCH(E$2,Inputs!$D$2:$AG$2,0)),Inputs!$B$4:$B$150,$B13)/1000) -> -3767 | F13: =IF(F$3=0,"",SUMIFS(INDEX(Inputs!$D$4:$AG$150,0,MATCH(F$2,Inputs!$D$2:$AG$2,0)),Inputs!$B$4:$B$150,$B13)/1000) -> -3640 | G13: =IF(G$3=0,"",SUMIFS(INDEX(Inputs!$D$4:$AG$150,0,MATCH(G$2,Inputs!$D$2:$AG$2,0)),Inputs!$B$4:$B$150,$B13)/1000) -> -3732 | H13: =IF(COUNT(D13:G13)=4,SUM(D13:G13),"") -> -10781 | I13: =IF(I$3=0,"",SUMIFS(INDEX(Inputs!$D$4:$AG$150,0,MATCH(I$2,Inputs!$D$2:$AG$2,0)),Inputs!$B$4:$B$150,$B13)/1000) -> -3595 | J13: =IF(J$3=0,"",SUMIFS(INDEX(Inputs!$D$4:$AG$150,0,MATCH(J$2,Inputs!$D$2:$AG$2,0)),Inputs!$B$4:$B$150,$B13)/1000) -> -3811 | K13: =IF(K$3=0,"",SUMIFS(INDEX(Inputs!$D$4:$AG$150,0,MATCH(K$2,Inputs!$D$2:$AG$2,0)),Inputs!$B$4:$B$150,$B13)/1000) -> -3703 | L13: =IF(L$3=0,"",SUMIFS(INDEX(Inputs!$D$4:$AG$150,0,MATCH(L$2,Inputs!$D$2:$AG$2,0)),Inputs!$B$4:$B$150,$B13)/1000) -> -3768 | M13: =IF(COUNT(I13:L13)=4,SUM(I13:L13),"") -> -14877 | N13: =IF(N$3=0,"",SUMIFS(INDEX(Inputs!$D$4:$AG$150,0,MATCH(N$2,Inputs!$D$2:$AG$2,0)),Inputs!$B$4:$B$150,$B13)/1000) -> -3650 | O13: =IF(O$3=0,"",SUMIFS(INDEX(Inputs!$D$4:$AG$150,0,MATCH(O$2,Inputs!$D$2:$AG$2,0)),Inputs!$B$4:$B$150,$B13)/1000) -> -3849 | P13: =IF(P$3=0,"",SUMIFS(INDEX(Inputs!$D$4:$AG$150,0,MATCH(P$2,Inputs!$D$2:$AG$2,0)),Inputs!$B$4:$B$150,$B13)/1000) -> -3758 | Q13: =IF(Q$3=0,"",SUMIFS(INDEX(Inputs!$D$4:$AG$150,0,MATCH(Q$2,Inputs!$D$2:$AG$2,0)),Inputs!$B$4:$B$150,$B13)/1000) -> -3825 | R13: =IF(COUNT(N13:Q13)=4,SUM(N13:Q13),"") -> -15082 | S13: =IF(S$3=0,"",SUMIFS(INDEX(Inputs!$D$4:$AG$150,0,MATCH(S$2,Inputs!$D$2:$AG$2,0)),Inputs!$B$4:$B$150,$B13)/1000) -> -3710 | T13: =IF(T$3=0,"",SUMIFS(INDEX(Inputs!$D$4:$AG$150,0,MATCH(T$2,Inputs!$D$2:$AG$2,0)),Inputs!$B$4:$B$150,$B13)/1000) -> -3895 | U13: =IF(U$3=0,"",SUMIFS(INDEX(Inputs!$D$4:$AG$150,0,MATCH(U$2,Inputs!$D$2:$AG$2,0)),Inputs!$B$4:$B$150,$B13)/1000) -> -3804 | V13: =IF(V$3=0,"",SUMIFS(INDEX(Inputs!$D$4:$AG$150,0,MATCH(V$2,Inputs!$D$2:$AG$2,0)),Inputs!$B$4:$B$150,$B13)/1000) -> -3856 | W13: =IF(COUNT(S13:V13)=4,SUM(S13:V13),"") -> -15265 | X13: =IF(X$3=0,"",SUMIFS(INDEX(Inputs!$D$4:$AG$150,0,MATCH(X$2,Inputs!$D$2:$AG$2,0)),Inputs!$B$4:$B$150,$B13)/1000) -> -3758 | Y13: =IF(Y$3=0,"",SUMIFS(INDEX(Inputs!$D$4:$AG$150,0,MATCH(Y$2,Inputs!$D$2:$AG$2,0)),Inputs!$B$4:$B$150,$B13)/1000) -> -3945 | Z13: =IF(Z$3=0,"",SUMIFS(INDEX(Inputs!$D$4:$AG$150,0,MATCH(Z$2,Inputs!$D$2:$AG$2,0)),Inputs!$B$4:$B$150,$B13)/1000) -> -3862 | AA13: =IF(AA$3=0,"",SUMIFS(INDEX(Inputs!$D$4:$AG$150,0,MATCH(AA$2,Inputs!$D$2:$AG$2,0)),Inputs!$B$4:$B$150,$B13)/1000) -> -3921 | AB13: =IF(COUNT(X13:AA13)=4,SUM(X13:AA13),"") -> -15486 | AC13: =IF(AC$3=0,"",SUMIFS(INDEX(Inputs!$D$4:$AG$150,0,MATCH(AC$2,Inputs!$D$2:$AG$2,0)),Inputs!$B$4:$B$150,$B13)/1000) -> -3822 | AD13: =IF(AD$3=0,"",SUMIFS(INDEX(Inputs!$D$4:$AG$150,0,MATCH(AD$2,Inputs!$D$2:$AG$2,0)),Inputs!$B$4:$B$150,$B13)/1000) -> -4035 | AE13: =IF(AE$3=0,"",SUMIFS(INDEX(Inputs!$D$4:$AG$150,0,MATCH(AE$2,Inputs!$D$2:$AG$2,0)),Inputs!$B$4:$B$150,$B13)/1000) | AF13: =IF(AF$3=0,"",SUMIFS(INDEX(Inputs!$D$4:$AG$150,0,MATCH(AF$2,Inputs!$D$2:$AG$2,0)),Inputs!$B$4:$B$150,$B13)/1000) | AG13: =IF(COUNT(AC13:AF13)=4,SUM(AC13:AF13),"")
B15: 11 | C15: Cash and equivalents (inc. investment securities) | D15: =IF(D$3=0,"",SUMIFS(INDEX(Inputs!$D$4:$AG$150,0,MATCH(D$2,Inputs!$D$2:$AG$2,0)),Inputs!$B$4:$B$150,$B15)/1000) -> 204373 | E15: =IF(E$3=0,"",SUMIFS(INDEX(Inputs!$D$4:$AG$150,0,MATCH(E$2,Inputs!$D$2:$AG$2,0)),Inputs!$B$4:$B$150,$B15)/1000) -> 193644 | F15: =IF(F$3=0,"",SUMIFS(INDEX(Inputs!$D$4:$AG$150,0,MATCH(F$2,Inputs!$D$2:$AG$2,0)),Inputs!$B$4:$B$150,$B15)/1000) -> 190516 | G15: =IF(G$3=0,"",SUMIFS(INDEX(Inputs!$D$4:$AG$150,0,MATCH(G$2,Inputs!$D$2:$AG$2,0)),Inputs!$B$4:$B$150,$B15)/1000) -> 202596 | H15: =IF(G15="","",G15) -> 202596 | I15: =IF(I$3=0,"",SUMIFS(INDEX(Inputs!$D$4:$AG$150,0,MATCH(I$2,Inputs!$D$2:$AG$2,0)),Inputs!$B$4:$B$150,$B15)/1000) -> 192730 | J15: =IF(J$3=0,"",SUMIFS(INDEX(Inputs!$D$4:$AG$150,0,MATCH(J$2,Inputs!$D$2:$AG$2,0)),Inputs!$B$4:$B$150,$B15)/1000) -> 179308 | K15: =IF(K$3=0,"",SUMIFS(INDEX(Inputs!$D$4:$AG$150,0,MATCH(K$2,Inputs!$D$2:$AG$2,0)),Inputs!$B$4:$B$150,$B15)/1000) -> 169109 | L15: =IF(L$3=0,"",SUMIFS(INDEX(Inputs!$D$4:$AG$150,0,MATCH(L$2,Inputs!$D$2:$AG$2,0)),Inputs!$B$4:$B$150,$B15)/1000) -> 165450 | M15: =IF(L15="","",L15) -> 165450 | N15: =IF(N$3=0,"",SUMIFS(INDEX(Inputs!$D$4:$AG$150,0,MATCH(N$2,Inputs!$D$2:$AG$2,0)),Inputs!$B$4:$B$150,$B15)/1000) -> 166333 | O15: =IF(O$3=0,"",SUMIFS(INDEX(Inputs!$D$4:$AG$150,0,MATCH(O$2,Inputs!$D$2:$AG$2,0)),Inputs!$B$4:$B$150,$B15)/1000) -> 166543 | P15: =IF(P$3=0,"",SUMIFS(INDEX(Inputs!$D$4:$AG$150,0,MATCH(P$2,Inputs!$D$2:$AG$2,0)),Inputs!$B$4:$B$150,$B15)/1000) -> 162099 | Q15: =IF(Q$3=0,"",SUMIFS(INDEX(Inputs!$D$4:$AG$150,0,MATCH(Q$2,Inputs!$D$2:$AG$2,0)),Inputs!$B$4:$B$150,$B15)/1000) -> 172575 | R15: =IF(Q15="","",Q15) -> 172575 | S15: =IF(S$3=0,"",SUMIFS(INDEX(Inputs!$D$4:$AG$150,0,MATCH(S$2,Inputs!$D$2:$AG$2,0)),Inputs!$B$4:$B$150,$B15)/1000) -> 162337 | T15: =IF(T$3=0,"",SUMIFS(INDEX(Inputs!$D$4:$AG$150,0,MATCH(T$2,Inputs!$D$2:$AG$2,0)),Inputs!$B$4:$B$150,$B15)/1000) -> 153041 | U15: =IF(U$3=0,"",SUMIFS(INDEX(Inputs!$D$4:$AG$150,0,MATCH(U$2,Inputs!$D$2:$AG$2,0)),Inputs!$B$4:$B$150,$B15)/1000) -> 156650 | V15: =IF(V$3=0,"",SUMIFS(INDEX(Inputs!$D$4:$AG$150,0,MATCH(V$2,Inputs!$D$2:$AG$2,0)),Inputs!$B$4:$B$150,$B15)/1000) -> 141368 | W15: =IF(V15="","",V15) -> 141368 | X15: =IF(X$3=0,"",SUMIFS(INDEX(Inputs!$D$4:$AG$150,0,MATCH(X$2,Inputs!$D$2:$AG$2,0)),Inputs!$B$4:$B$150,$B15)/1000) -> 132922 | Y15: =IF(Y$3=0,"",SUMIFS(INDEX(Inputs!$D$4:$AG$150,0,MATCH(Y$2,Inputs!$D$2:$AG$2,0)),Inputs!$B$4:$B$150,$B15)/1000) -> 132986 | Z15: =IF(Z$3=0,"",SUMIFS(INDEX(Inputs!$D$4:$AG$150,0,MATCH(Z$2,Inputs!$D$2:$AG$2,0)),Inputs!$B$4:$B$150,$B15)/1000) -> 132420 | AA15: =IF(AA$3=0,"",SUMIFS(INDEX(Inputs!$D$4:$AG$150,0,MATCH(AA$2,Inputs!$D$2:$AG$2,0)),Inputs!$B$4:$B$150,$B15)/1000) -> 144795 | AB15: =IF(AA15="","",AA15) -> 144795 | AC15: =IF(AC$3=0,"",SUMIFS(INDEX(Inputs!$D$4:$AG$150,0,MATCH(AC$2,Inputs!$D$2:$AG$2,0)),Inputs!$B$4:$B$150,$B15)/1000) -> 146595 | AD15: =IF(AD$3=0,"",SUMIFS(INDEX(Inputs!$D$4:$AG$150,0,MATCH(AD$2,Inputs!$D$2:$AG$2,0)),Inputs!$B$4:$B$150,$B15)/1000) -> 146517 | AE15: =IF(AE$3=0,"",SUMIFS(INDEX(Inputs!$D$4:$AG$150,0,MATCH(AE$2,Inputs!$D$2:$AG$2,0)),Inputs!$B$4:$B$150,$B15)/1000) | AF15: =IF(AF$3=0,"",SUMIFS(INDEX(Inputs!$D$4:$AG$150,0,MATCH(AF$2,Inputs!$D$2:$AG$2,0)),Inputs!$B$4:$B$150,$B15)/1000) | AG15: =IF(AF15="","",AF15)
B16: 12 | C16: Accounts receivable | D16: =IF(D$3=0,"",SUMIFS(INDEX(Inputs!$D$4:$AG$150,0,MATCH(D$2,Inputs!$D$2:$AG$2,0)),Inputs!$B$4:$B$150,$B16)/1000) -> 18503 | E16: =IF(E$3=0,"",SUMIFS(INDEX(Inputs!$D$4:$AG$150,0,MATCH(E$2,Inputs!$D$2:$AG$2,0)),Inputs!$B$4:$B$150,$B16)/1000) -> 17475 | F16: =IF(F$3=0,"",SUMIFS(INDEX(Inputs!$D$4:$AG$150,0,MATCH(F$2,Inputs!$D$2:$AG$2,0)),Inputs!$B$4:$B$150,$B16)/1000) -> 26278 | G16: =IF(G$3=0,"",SUMIFS(INDEX(Inputs!$D$4:$AG$150,0,MATCH(G$2,Inputs!$D$2:$AG$2,0)),Inputs!$B$4:$B$150,$B16)/1000) -> 30213 | H16: =IF(G16="","",G16) -> 30213 | I16: =IF(I$3=0,"",SUMIFS(INDEX(Inputs!$D$4:$AG$150,0,MATCH(I$2,Inputs!$D$2:$AG$2,0)),Inputs!$B$4:$B$150,$B16)/1000) -> 20815 | J16: =IF(J$3=0,"",SUMIFS(INDEX(Inputs!$D$4:$AG$150,0,MATCH(J$2,Inputs!$D$2:$AG$2,0)),Inputs!$B$4:$B$150,$B16)/1000) -> 21803 | K16: =IF(K$3=0,"",SUMIFS(INDEX(Inputs!$D$4:$AG$150,0,MATCH(K$2,Inputs!$D$2:$AG$2,0)),Inputs!$B$4:$B$150,$B16)/1000) -> 28184 | L16: =IF(L$3=0,"",SUMIFS(INDEX(Inputs!$D$4:$AG$150,0,MATCH(L$2,Inputs!$D$2:$AG$2,0)),Inputs!$B$4:$B$150,$B16)/1000) -> 23752 | M16: =IF(L16="","",L16) -> 23752 | N16: =IF(N$3=0,"",SUMIFS(INDEX(Inputs!$D$4:$AG$150,0,MATCH(N$2,Inputs!$D$2:$AG$2,0)),Inputs!$B$4:$B$150,$B16)/1000) -> 17936 | O16: =IF(O$3=0,"",SUMIFS(INDEX(Inputs!$D$4:$AG$150,0,MATCH(O$2,Inputs!$D$2:$AG$2,0)),Inputs!$B$4:$B$150,$B16)/1000) -> 19549 | P16: =IF(P$3=0,"",SUMIFS(INDEX(Inputs!$D$4:$AG$150,0,MATCH(P$2,Inputs!$D$2:$AG$2,0)),Inputs!$B$4:$B$150,$B16)/1000) -> 29508 | Q16: =IF(Q$3=0,"",SUMIFS(INDEX(Inputs!$D$4:$AG$150,0,MATCH(Q$2,Inputs!$D$2:$AG$2,0)),Inputs!$B$4:$B$150,$B16)/1000) -> 23194 | R16: =IF(Q16="","",Q16) -> 23194 | S16: =IF(S$3=0,"",SUMIFS(INDEX(Inputs!$D$4:$AG$150,0,MATCH(S$2,Inputs!$D$2:$AG$2,0)),Inputs!$B$4:$B$150,$B16)/1000) -> 21837 | T16: =IF(T$3=0,"",SUMIFS(INDEX(Inputs!$D$4:$AG$150,0,MATCH(T$2,Inputs!$D$2:$AG$2,0)),Inputs!$B$4:$B$150,$B16)/1000) -> 22795 | U16: =IF(U$3=0,"",SUMIFS(INDEX(Inputs!$D$4:$AG$150,0,MATCH(U$2,Inputs!$D$2:$AG$2,0)),Inputs!$B$4:$B$150,$B16)/1000) -> 33410 | V16: =IF(V$3=0,"",SUMIFS(INDEX(Inputs!$D$4:$AG$150,0,MATCH(V$2,Inputs!$D$2:$AG$2,0)),Inputs!$B$4:$B$150,$B16)/1000) -> 29639 | W16: =IF(V16="","",V16) -> 29639 | X16: =IF(X$3=0,"",SUMIFS(INDEX(Inputs!$D$4:$AG$150,0,MATCH(X$2,Inputs!$D$2:$AG$2,0)),Inputs!$B$4:$B$150,$B16)/1000) -> 26136 | Y16: =IF(Y$3=0,"",SUMIFS(INDEX(Inputs!$D$4:$AG$150,0,MATCH(Y$2,Inputs!$D$2:$AG$2,0)),Inputs!$B$4:$B$150,$B16)/1000) -> 27557 | Z16: =IF(Z$3=0,"",SUMIFS(INDEX(Inputs!$D$4:$AG$150,0,MATCH(Z$2,Inputs!$D$2:$AG$2,0)),Inputs!$B$4:$B$150,$B16)/1000) -> 39777 | AA16: =IF(AA$3=0,"",SUMIFS(INDEX(Inputs!$D$4:$AG$150,0,MATCH(AA$2,Inputs!$D$2:$AG$2,0)),Inputs!$B$4:$B$150,$B16)/1000) -> 39921 | AB16: =IF(AA16="","",AA16) -> 39921 | AC16: =IF(AC$3=0,"",SUMIFS(INDEX(Inputs!$D$4:$AG$150,0,MATCH(AC$2,Inputs!$D$2:$AG$2,0)),Inputs!$B$4:$B$150,$B16)/1000) -> 30339 | AD16: =IF(AD$3=0,"",SUMIFS(INDEX(Inputs!$D$4:$AG$150,0,MATCH(AD$2,Inputs!$D$2:$AG$2,0)),Inputs!$B$4:$B$150,$B16)/1000) -> 31398 | AE16: =IF(AE$3=0,"",SUMIFS(INDEX(Inputs!$D$4:$AG$150,0,MATCH(AE$2,Inputs!$D$2:$AG$2,0)),Inputs!$B$4:$B$150,$B16)/1000) | AF16: =IF(AF$3=0,"",SUMIFS(INDEX(Inputs!$D$4:$AG$150,0,MATCH(AF$2,Inputs!$D$2:$AG$2,0)),Inputs!$B$4:$B$150,$B16)/1000) | AG16: =IF(AF16="","",AF16)
B17: 13 | C17: Inventories | D17: =IF(D$3=0,"",SUMIFS(INDEX(Inputs!$D$4:$AG$150,0,MATCH(D$2,Inputs!$D$2:$AG$2,0)),Inputs!$B$4:$B$150,$B17)/1000) -> 5219 | E17: =IF(E$3=0,"",SUMIFS(INDEX(Inputs!$D$4:$AG$150,0,MATCH(E$2,Inputs!$D$2:$AG$2,0)),Inputs!$B$4:$B$150,$B17)/1000) -> 5178 | F17: =IF(F$3=0,"",SUMIFS(INDEX(Inputs!$D$4:$AG$150,0,MATCH(F$2,Inputs!$D$2:$AG$2,0)),Inputs!$B$4:$B$150,$B17)/1000) -> 6580 | G17: =IF(G$3=0,"",SUMIFS(INDEX(Inputs!$D$4:$AG$150,0,MATCH(G$2,Inputs!$D$2:$AG$2,0)),Inputs!$B$4:$B$150,$B17)/1000) -> 5876 | H17: =IF(G17="","",G17) -> 5876 | I17: =IF(I$3=0,"",SUMIFS(INDEX(Inputs!$D$4:$AG$150,0,MATCH(I$2,Inputs!$D$2:$AG$2,0)),Inputs!$B$4:$B$150,$B17)/1000) -> 5460 | J17: =IF(J$3=0,"",SUMIFS(INDEX(Inputs!$D$4:$AG$150,0,MATCH(J$2,Inputs!$D$2:$AG$2,0)),Inputs!$B$4:$B$150,$B17)/1000) -> 5433 | K17: =IF(K$3=0,"",SUMIFS(INDEX(Inputs!$D$4:$AG$150,0,MATCH(K$2,Inputs!$D$2:$AG$2,0)),Inputs!$B$4:$B$150,$B17)/1000) -> 4946 | L17: =IF(L$3=0,"",SUMIFS(INDEX(Inputs!$D$4:$AG$150,0,MATCH(L$2,Inputs!$D$2:$AG$2,0)),Inputs!$B$4:$B$150,$B17)/1000) -> 6820 | M17: =IF(L17="","",L17) -> 6820 | N17: =IF(N$3=0,"",SUMIFS(INDEX(Inputs!$D$4:$AG$150,0,MATCH(N$2,Inputs!$D$2:$AG$2,0)),Inputs!$B$4:$B$150,$B17)/1000) -> 7482 | O17: =IF(O$3=0,"",SUMIFS(INDEX(Inputs!$D$4:$AG$150,0,MATCH(O$2,Inputs!$D$2:$AG$2,0)),Inputs!$B$4:$B$150,$B17)/1000) -> 7351 | P17: =IF(P$3=0,"",SUMIFS(INDEX(Inputs!$D$4:$AG$150,0,MATCH(P$2,Inputs!$D$2:$AG$2,0)),Inputs!$B$4:$B$150,$B17)/1000) -> 6331 | Q17: =IF(Q$3=0,"",SUMIFS(INDEX(Inputs!$D$4:$AG$150,0,MATCH(Q$2,Inputs!$D$2:$AG$2,0)),Inputs!$B$4:$B$150,$B17)/1000) -> 6511 | R17: =IF(Q17="","",Q17) -> 6511 | S17: =IF(S$3=0,"",SUMIFS(INDEX(Inputs!$D$4:$AG$150,0,MATCH(S$2,Inputs!$D$2:$AG$2,0)),Inputs!$B$4:$B$150,$B17)/1000) -> 6232 | T17: =IF(T$3=0,"",SUMIFS(INDEX(Inputs!$D$4:$AG$150,0,MATCH(T$2,Inputs!$D$2:$AG$2,0)),Inputs!$B$4:$B$150,$B17)/1000) -> 6165 | U17: =IF(U$3=0,"",SUMIFS(INDEX(Inputs!$D$4:$AG$150,0,MATCH(U$2,Inputs!$D$2:$AG$2,0)),Inputs!$B$4:$B$150,$B17)/1000) -> 7286 | V17: =IF(V$3=0,"",SUMIFS(INDEX(Inputs!$D$4:$AG$150,0,MATCH(V$2,Inputs!$D$2:$AG$2,0)),Inputs!$B$4:$B$150,$B17)/1000) -> 6911 | W17: =IF(V17="","",V17) -> 6911 | X17: =IF(X$3=0,"",SUMIFS(INDEX(Inputs!$D$4:$AG$150,0,MATCH(X$2,Inputs!$D$2:$AG$2,0)),Inputs!$B$4:$B$150,$B17)/1000) -> 6269 | Y17: =IF(Y$3=0,"",SUMIFS(INDEX(Inputs!$D$4:$AG$150,0,MATCH(Y$2,Inputs!$D$2:$AG$2,0)),Inputs!$B$4:$B$150,$B17)/1000) -> 5925 | Z17: =IF(Z$3=0,"",SUMIFS(INDEX(Inputs!$D$4:$AG$150,0,MATCH(Z$2,Inputs!$D$2:$AG$2,0)),Inputs!$B$4:$B$150,$B17)/1000) -> 5718 | AA17: =IF(AA$3=0,"",SUMIFS(INDEX(Inputs!$D$4:$AG$150,0,MATCH(AA$2,Inputs!$D$2:$AG$2,0)),Inputs!$B$4:$B$150,$B17)/1000) -> 5875 | AB17: =IF(AA17="","",AA17) -> 5875 | AC17: =IF(AC$3=0,"",SUMIFS(INDEX(Inputs!$D$4:$AG$150,0,MATCH(AC$2,Inputs!$D$2:$AG$2,0)),Inputs!$B$4:$B$150,$B17)/1000) -> 6747 | AD17: =IF(AD$3=0,"",SUMIFS(INDEX(Inputs!$D$4:$AG$150,0,MATCH(AD$2,Inputs!$D$2:$AG$2,0)),Inputs!$B$4:$B$150,$B17)/1000) -> 11092 | AE17: =IF(AE$3=0,"",SUMIFS(INDEX(Inputs!$D$4:$AG$150,0,MATCH(AE$2,Inputs!$D$2:$AG$2,0)),Inputs!$B$4:$B$150,$B17)/1000) | AF17: =IF(AF$3=0,"",SUMIFS(INDEX(Inputs!$D$4:$AG$150,0,MATCH(AF$2,Inputs!$D$2:$AG$2,0)),Inputs!$B$4:$B$150,$B17)/1000) | AG17: =IF(AF17="","",AF17)
B18: 14 | C18: Deferred income taxes | D18: =IF(D$3=0,"",SUMIFS(INDEX(Inputs!$D$4:$AG$150,0,MATCH(D$2,Inputs!$D$2:$AG$2,0)),Inputs!$B$4:$B$150,$B18)/1000) -> 0 | E18: =IF(E$3=0,"",SUMIFS(INDEX(Inputs!$D$4:$AG$150,0,MATCH(E$2,Inputs!$D$2:$AG$2,0)),Inputs!$B$4:$B$150,$B18)/1000) -> 0 | F18: =IF(F$3=0,"",SUMIFS(INDEX(Inputs!$D$4:$AG$150,0,MATCH(F$2,Inputs!$D$2:$AG$2,0)),Inputs!$B$4:$B$150,$B18)/1000) -> 0 | G18: =IF(G$3=0,"",SUMIFS(INDEX(Inputs!$D$4:$AG$150,0,MATCH(G$2,Inputs!$D$2:$AG$2,0)),Inputs!$B$4:$B$150,$B18)/1000) -> 0 | H18: =IF(G18="","",G18) -> 0 | I18: =IF(I$3=0,"",SUMIFS(INDEX(Inputs!$D$4:$AG$150,0,MATCH(I$2,Inputs!$D$2:$AG$2,0)),Inputs!$B$4:$B$150,$B18)/1000) -> 0 | J18: =IF(J$3=0,"",SUMIFS(INDEX(Inputs!$D$4:$AG$150,0,MATCH(J$2,Inputs!$D$2:$AG$2,0)),Inputs!$B$4:$B$150,$B18)/1000) -> 0 | K18: =IF(K$3=0,"",SUMIFS(INDEX(Inputs!$D$4:$AG$150,0,MATCH(K$2,Inputs!$D$2:$AG$2,0)),Inputs!$B$4:$B$150,$B18)/1000) -> 0 | L18: =IF(L$3=0,"",SUMIFS(INDEX(Inputs!$D$4:$AG$150,0,MATCH(L$2,Inputs!$D$2:$AG$2,0)),Inputs!$B$4:$B$150,$B18)/1000) -> 0 | M18: =IF(L18="","",L18) -> 0 | N18: =IF(N$3=0,"",SUMIFS(INDEX(Inputs!$D$4:$AG$150,0,MATCH(N$2,Inputs!$D$2:$AG$2,0)),Inputs!$B$4:$B$150,$B18)/1000) -> 0 | O18: =IF(O$3=0,"",SUMIFS(INDEX(Inputs!$D$4:$AG$150,0,MATCH(O$2,Inputs!$D$2:$AG$2,0)),Inputs!$B$4:$B$150,$B18)/1000) -> 0 | P18: =IF(P$3=0,"",SUMIFS(INDEX(Inputs!$D$4:$AG$150,0,MATCH(P$2,Inputs!$D$2:$AG$2,0)),Inputs!$B$4:$B$150,$B18)/1000) -> 0 | Q18: =IF(Q$3=0,"",SUMIFS(INDEX(Inputs!$D$4:$AG$150,0,MATCH(Q$2,Inputs!$D$2:$AG$2,0)),Inputs!$B$4:$B$150,$B18)/1000) -> 0 | R18: =IF(Q18="","",Q18) -> 0 | S18: =IF(S$3=0,"",SUMIFS(INDEX(Inputs!$D$4:$AG$150,0,MATCH(S$2,Inputs!$D$2:$AG$2,0)),Inputs!$B$4:$B$150,$B18)/1000) -> 0 | T18: =IF(T$3=0,"",SUMIFS(INDEX(Inputs!$D$4:$AG$150,0,MATCH(T$2,Inputs!$D$2:$AG$2,0)),Inputs!$B$4:$B$150,$B18)/1000) -> 0 | U18: =IF(U$3=0,"",SUMIFS(INDEX(Inputs!$D$4:$AG$150,0,MATCH(U$2,Inputs!$D$2:$AG$2,0)),Inputs!$B$4:$B$150,$B18)/1000) -> 0 | V18: =IF(V$3=0,"",SUMIFS(INDEX(Inputs!$D$4:$AG$150,0,MATCH(V$2,Inputs!$D$2:$AG$2,0)),Inputs!$B$4:$B$150,$B18)/1000) -> 0 | W18: =IF(V18="","",V18) -> 0 | X18: =IF(X$3=0,"",SUMIFS(INDEX(Inputs!$D$4:$AG$150,0,MATCH(X$2,Inputs!$D$2:$AG$2,0)),Inputs!$B$4:$B$150,$B18)/1000) -> 0 | Y18: =IF(Y$3=0,"",SUMIFS(INDEX(Inputs!$D$4:$AG$150,0,MATCH(Y$2,Inputs!$D$2:$AG$2,0)),Inputs!$B$4:$B$150,$B18)/1000) -> 0 | Z18: =IF(Z$3=0,"",SUMIFS(INDEX(Inputs!$D$4:$AG$150,0,MATCH(Z$2,Inputs!$D$2:$AG$2,0)),Inputs!$B$4:$B$150,$B18)/1000) -> 0 | AA18: =IF(AA$3=0,"",SUMIFS(INDEX(Inputs!$D$4:$AG$150,0,MATCH(AA$2,Inputs!$D$2:$AG$2,0)),Inputs!$B$4:$B$150,$B18)/1000) -> 0 | AB18: =IF(AA18="","",AA18) -> 0 | AC18: =IF(AC$3=0,"",SUMIFS(INDEX(Inputs!$D$4:$AG$150,0,MATCH(AC$2,Inputs!$D$2:$AG$2,0)),Inputs!$B$4:$B$150,$B18)/1000) -> 0 | AD18: =IF(AD$3=0,"",SUMIFS(INDEX(Inputs!$D$4:$AG$150,0,MATCH(AD$2,Inputs!$D$2:$AG$2,0)),Inputs!$B$4:$B$150,$B18)/1000) -> 0 | AE18: =IF(AE$3=0,"",SUMIFS(INDEX(Inputs!$D$4:$AG$150,0,MATCH(AE$2,Inputs!$D$2:$AG$2,0)),Inputs!$B$4:$B$150,$B18)/1000) | AF18: =IF(AF$3=0,"",SUMIFS(INDEX(Inputs!$D$4:$AG$150,0,MATCH(AF$2,Inputs!$D$2:$AG$2,0)),Inputs!$B$4:$B$150,$B18)/1000) | AG18: =IF(AF18="","",AF18)
B19: 15 | C19: Prepaid expenses | D19: =IF(D$3=0,"",SUMIFS(INDEX(Inputs!$D$4:$AG$150,0,MATCH(D$2,Inputs!$D$2:$AG$2,0)),Inputs!$B$4:$B$150,$B19)/1000) -> 0 | E19: =IF(E$3=0,"",SUMIFS(INDEX(Inputs!$D$4:$AG$150,0,MATCH(E$2,Inputs!$D$2:$AG$2,0)),Inputs!$B$4:$B$150,$B19)/1000) -> 0 | F19: =IF(F$3=0,"",SUMIFS(INDEX(Inputs!$D$4:$AG$150,0,MATCH(F$2,Inputs!$D$2:$AG$2,0)),Inputs!$B$4:$B$150,$B19)/1000) -> 0 | G19: =IF(G$3=0,"",SUMIFS(INDEX(Inputs!$D$4:$AG$150,0,MATCH(G$2,Inputs!$D$2:$AG$2,0)),Inputs!$B$4:$B$150,$B19)/1000) -> 0 | H19: =IF(G19="","",G19) -> 0 | I19: =IF(I$3=0,"",SUMIFS(INDEX(Inputs!$D$4:$AG$150,0,MATCH(I$2,Inputs!$D$2:$AG$2,0)),Inputs!$B$4:$B$150,$B19)/1000) -> 0 | J19: =IF(J$3=0,"",SUMIFS(INDEX(Inputs!$D$4:$AG$150,0,MATCH(J$2,Inputs!$D$2:$AG$2,0)),Inputs!$B$4:$B$150,$B19)/1000) -> 0 | K19: =IF(K$3=0,"",SUMIFS(INDEX(Inputs!$D$4:$AG$150,0,MATCH(K$2,Inputs!$D$2:$AG$2,0)),Inputs!$B$4:$B$150,$B19)/1000) -> 0 | L19: =IF(L$3=0,"",SUMIFS(INDEX(Inputs!$D$4:$AG$150,0,MATCH(L$2,Inputs!$D$2:$AG$2,0)),Inputs!$B$4:$B$150,$B19)/1000) -> 0 | M19: =IF(L19="","",L19) -> 0 | N19: =IF(N$3=0,"",SUMIFS(INDEX(Inputs!$D$4:$AG$150,0,MATCH(N$2,Inputs!$D$2:$AG$2,0)),Inputs!$B$4:$B$150,$B19)/1000) -> 0 | O19: =IF(O$3=0,"",SUMIFS(INDEX(Inputs!$D$4:$AG$150,0,MATCH(O$2,Inputs!$D$2:$AG$2,0)),Inputs!$B$4:$B$150,$B19)/1000) -> 0 | P19: =IF(P$3=0,"",SUMIFS(INDEX(Inputs!$D$4:$AG$150,0,MATCH(P$2,Inputs!$D$2:$AG$2,0)),Inputs!$B$4:$B$150,$B19)/1000) -> 0 | Q19: =IF(Q$3=0,"",SUMIFS(INDEX(Inputs!$D$4:$AG$150,0,MATCH(Q$2,Inputs!$D$2:$AG$2,0)),Inputs!$B$4:$B$150,$B19)/1000) -> 0 | R19: =IF(Q19="","",Q19) -> 0 | S19: =IF(S$3=0,"",SUMIFS(INDEX(Inputs!$D$4:$AG$150,0,MATCH(S$2,Inputs!$D$2:$AG$2,0)),Inputs!$B$4:$B$150,$B19)/1000) -> 0 | T19: =IF(T$3=0,"",SUMIFS(INDEX(Inputs!$D$4:$AG$150,0,MATCH(T$2,Inputs!$D$2:$AG$2,0)),Inputs!$B$4:$B$150,$B19)/1000) -> 0 | U19: =IF(U$3=0,"",SUMIFS(INDEX(Inputs!$D$4:$AG$150,0,MATCH(U$2,Inputs!$D$2:$AG$2,0)),Inputs!$B$4:$B$150,$B19)/1000) -> 0 | V19: =IF(V$3=0,"",SUMIFS(INDEX(Inputs!$D$4:$AG$150,0,MATCH(V$2,Inputs!$D$2:$AG$2,0)),Inputs!$B$4:$B$150,$B19)/1000) -> 0 | W19: =IF(V19="","",V19) -> 0 | X19: =IF(X$3=0,"",SUMIFS(INDEX(Inputs!$D$4:$AG$150,0,MATCH(X$2,Inputs!$D$2:$AG$2,0)),Inputs!$B$4:$B$150,$B19)/1000) -> 0 | Y19: =IF(Y$3=0,"",SUMIFS(INDEX(Inputs!$D$4:$AG$150,0,MATCH(Y$2,Inputs!$D$2:$AG$2,0)),Inputs!$B$4:$B$150,$B19)/1000) -> 0 | Z19: =IF(Z$3=0,"",SUMIFS(INDEX(Inputs!$D$4:$AG$150,0,MATCH(Z$2,Inputs!$D$2:$AG$2,0)),Inputs!$B$4:$B$150,$B19)/1000) -> 0 | AA19: =IF(AA$3=0,"",SUMIFS(INDEX(Inputs!$D$4:$AG$150,0,MATCH(AA$2,Inputs!$D$2:$AG$2,0)),Inputs!$B$4:$B$150,$B19)/1000) -> 0 | AB19: =IF(AA19="","",AA19) -> 0 | AC19: =IF(AC$3=0,"",SUMIFS(INDEX(Inputs!$D$4:$AG$150,0,MATCH(AC$2,Inputs!$D$2:$AG$2,0)),Inputs!$B$4:$B$150,$B19)/1000) -> 0 | AD19: =IF(AD$3=0,"",SUMIFS(INDEX(Inputs!$D$4:$AG$150,0,MATCH(AD$2,Inputs!$D$2:$AG$2,0)),Inputs!$B$4:$B$150,$B19)/1000) -> 0 | AE19: =IF(AE$3=0,"",SUMIFS(INDEX(Inputs!$D$4:$AG$150,0,MATCH(AE$2,Inputs!$D$2:$AG$2,0)),Inputs!$B$4:$B$150,$B19)/1000) | AF19: =IF(AF$3=0,"",SUMIFS(INDEX(Inputs!$D$4:$AG$150,0,MATCH(AF$2,Inputs!$D$2:$AG$2,0)),Inputs!$B$4:$B$150,$B19)/1000) | AG19: =IF(AF19="","",AF19)
B20: 16 | C20: Other current assets | D20: =IF(D$3=0,"",SUMIFS(INDEX(Inputs!$D$4:$AG$150,0,MATCH(D$2,Inputs!$D$2:$AG$2,0)),Inputs!$B$4:$B$150,$B20)/1000) -> 27909 | E20: =IF(E$3=0,"",SUMIFS(INDEX(Inputs!$D$4:$AG$150,0,MATCH(E$2,Inputs!$D$2:$AG$2,0)),Inputs!$B$4:$B$150,$B20)/1000) -> 30074 | F20: =IF(F$3=0,"",SUMIFS(INDEX(Inputs!$D$4:$AG$150,0,MATCH(F$2,Inputs!$D$2:$AG$2,0)),Inputs!$B$4:$B$150,$B20)/1000) -> 39339 | G20: =IF(G$3=0,"",SUMIFS(INDEX(Inputs!$D$4:$AG$150,0,MATCH(G$2,Inputs!$D$2:$AG$2,0)),Inputs!$B$4:$B$150,$B20)/1000) -> 53152 | H20: =IF(G20="","",G20) -> 53152 | I20: =IF(I$3=0,"",SUMIFS(INDEX(Inputs!$D$4:$AG$150,0,MATCH(I$2,Inputs!$D$2:$AG$2,0)),Inputs!$B$4:$B$150,$B20)/1000) -> 40394 | J20: =IF(J$3=0,"",SUMIFS(INDEX(Inputs!$D$4:$AG$150,0,MATCH(J$2,Inputs!$D$2:$AG$2,0)),Inputs!$B$4:$B$150,$B20)/1000) -> 36825 | K20: =IF(K$3=0,"",SUMIFS(INDEX(Inputs!$D$4:$AG$150,0,MATCH(K$2,Inputs!$D$2:$AG$2,0)),Inputs!$B$4:$B$150,$B20)/1000) -> 53971 | L20: =IF(L$3=0,"",SUMIFS(INDEX(Inputs!$D$4:$AG$150,0,MATCH(L$2,Inputs!$D$2:$AG$2,0)),Inputs!$B$4:$B$150,$B20)/1000) -> 46850 | M20: =IF(L20="","",L20) -> 46850 | N20: =IF(N$3=0,"",SUMIFS(INDEX(Inputs!$D$4:$AG$150,0,MATCH(N$2,Inputs!$D$2:$AG$2,0)),Inputs!$B$4:$B$150,$B20)/1000) -> 31623 | O20: =IF(O$3=0,"",SUMIFS(INDEX(Inputs!$D$4:$AG$150,0,MATCH(O$2,Inputs!$D$2:$AG$2,0)),Inputs!$B$4:$B$150,$B20)/1000) -> 33277 | P20: =IF(P$3=0,"",SUMIFS(INDEX(Inputs!$D$4:$AG$150,0,MATCH(P$2,Inputs!$D$2:$AG$2,0)),Inputs!$B$4:$B$150,$B20)/1000) -> 46172 | Q20: =IF(Q$3=0,"",SUMIFS(INDEX(Inputs!$D$4:$AG$150,0,MATCH(Q$2,Inputs!$D$2:$AG$2,0)),Inputs!$B$4:$B$150,$B20)/1000) -> 40887 | R20: =IF(Q20="","",Q20) -> 40887 | S20: =IF(S$3=0,"",SUMIFS(INDEX(Inputs!$D$4:$AG$150,0,MATCH(S$2,Inputs!$D$2:$AG$2,0)),Inputs!$B$4:$B$150,$B20)/1000) -> 33197 | T20: =IF(T$3=0,"",SUMIFS(INDEX(Inputs!$D$4:$AG$150,0,MATCH(T$2,Inputs!$D$2:$AG$2,0)),Inputs!$B$4:$B$150,$B20)/1000) -> 34674 | U20: =IF(U$3=0,"",SUMIFS(INDEX(Inputs!$D$4:$AG$150,0,MATCH(U$2,Inputs!$D$2:$AG$2,0)),Inputs!$B$4:$B$150,$B20)/1000) -> 47120 | V20: =IF(V$3=0,"",SUMIFS(INDEX(Inputs!$D$4:$AG$150,0,MATCH(V$2,Inputs!$D$2:$AG$2,0)),Inputs!$B$4:$B$150,$B20)/1000) -> 42915 | W20: =IF(V20="","",V20) -> 42915 | X20: =IF(X$3=0,"",SUMIFS(INDEX(Inputs!$D$4:$AG$150,0,MATCH(X$2,Inputs!$D$2:$AG$2,0)),Inputs!$B$4:$B$150,$B20)/1000) -> 37771 | Y20: =IF(Y$3=0,"",SUMIFS(INDEX(Inputs!$D$4:$AG$150,0,MATCH(Y$2,Inputs!$D$2:$AG$2,0)),Inputs!$B$4:$B$150,$B20)/1000) -> 33637 | Z20: =IF(Z$3=0,"",SUMIFS(INDEX(Inputs!$D$4:$AG$150,0,MATCH(Z$2,Inputs!$D$2:$AG$2,0)),Inputs!$B$4:$B$150,$B20)/1000) -> 47765 | AA20: =IF(AA$3=0,"",SUMIFS(INDEX(Inputs!$D$4:$AG$150,0,MATCH(AA$2,Inputs!$D$2:$AG$2,0)),Inputs!$B$4:$B$150,$B20)/1000) -> 45401 | AB20: =IF(AA20="","",AA20) -> 45401 | AC20: =IF(AC$3=0,"",SUMIFS(INDEX(Inputs!$D$4:$AG$150,0,MATCH(AC$2,Inputs!$D$2:$AG$2,0)),Inputs!$B$4:$B$150,$B20)/1000) -> 38521 | AD20: =IF(AD$3=0,"",SUMIFS(INDEX(Inputs!$D$4:$AG$150,0,MATCH(AD$2,Inputs!$D$2:$AG$2,0)),Inputs!$B$4:$B$150,$B20)/1000) -> 44929 | AE20: =IF(AE$3=0,"",SUMIFS(INDEX(Inputs!$D$4:$AG$150,0,MATCH(AE$2,Inputs!$D$2:$AG$2,0)),Inputs!$B$4:$B$150,$B20)/1000) | AF20: =IF(AF$3=0,"",SUMIFS(INDEX(Inputs!$D$4:$AG$150,0,MATCH(AF$2,Inputs!$D$2:$AG$2,0)),Inputs!$B$4:$B$150,$B20)/1000) | AG20: =IF(AF20="","",AF20)
B21: 17 | C21: Equity in affiliates | D21: =IF(D$3=0,"",SUMIFS(INDEX(Inputs!$D$4:$AG$150,0,MATCH(D$2,Inputs!$D$2:$AG$2,0)),Inputs!$B$4:$B$150,$B21)/1000) -> 0 | E21: =IF(E$3=0,"",SUMIFS(INDEX(Inputs!$D$4:$AG$150,0,MATCH(E$2,Inputs!$D$2:$AG$2,0)),Inputs!$B$4:$B$150,$B21)/1000) -> 0 | F21: =IF(F$3=0,"",SUMIFS(INDEX(Inputs!$D$4:$AG$150,0,MATCH(F$2,Inputs!$D$2:$AG$2,0)),Inputs!$B$4:$B$150,$B21)/1000) -> 0 | G21: =IF(G$3=0,"",SUMIFS(INDEX(Inputs!$D$4:$AG$150,0,MATCH(G$2,Inputs!$D$2:$AG$2,0)),Inputs!$B$4:$B$150,$B21)/1000) -> 0 | H21: =IF(G21="","",G21) -> 0 | I21: =IF(I$3=0,"",SUMIFS(INDEX(Inputs!$D$4:$AG$150,0,MATCH(I$2,Inputs!$D$2:$AG$2,0)),Inputs!$B$4:$B$150,$B21)/1000) -> 0 | J21: =IF(J$3=0,"",SUMIFS(INDEX(Inputs!$D$4:$AG$150,0,MATCH(J$2,Inputs!$D$2:$AG$2,0)),Inputs!$B$4:$B$150,$B21)/1000) -> 0 | K21: =IF(K$3=0,"",SUMIFS(INDEX(Inputs!$D$4:$AG$150,0,MATCH(K$2,Inputs!$D$2:$AG$2,0)),Inputs!$B$4:$B$150,$B21)/1000) -> 0 | L21: =IF(L$3=0,"",SUMIFS(INDEX(Inputs!$D$4:$AG$150,0,MATCH(L$2,Inputs!$D$2:$AG$2,0)),Inputs!$B$4:$B$150,$B21)/1000) -> 0 | M21: =IF(L21="","",L21) -> 0 | N21: =IF(N$3=0,"",SUMIFS(INDEX(Inputs!$D$4:$AG$150,0,MATCH(N$2,Inputs!$D$2:$AG$2,0)),Inputs!$B$4:$B$150,$B21)/1000) -> 0 | O21: =IF(O$3=0,"",SUMIFS(INDEX(Inputs!$D$4:$AG$150,0,MATCH(O$2,Inputs!$D$2:$AG$2,0)),Inputs!$B$4:$B$150,$B21)/1000) -> 0 | P21: =IF(P$3=0,"",SUMIFS(INDEX(Inputs!$D$4:$AG$150,0,MATCH(P$2,Inputs!$D$2:$AG$2,0)),Inputs!$B$4:$B$150,$B21)/1000) -> 0 | Q21: =IF(Q$3=0,"",SUMIFS(INDEX(Inputs!$D$4:$AG$150,0,MATCH(Q$2,Inputs!$D$2:$AG$2,0)),Inputs!$B$4:$B$150,$B21)/1000) -> 0 | R21: =IF(Q21="","",Q21) -> 0 | S21: =IF(S$3=0,"",SUMIFS(INDEX(Inputs!$D$4:$AG$150,0,MATCH(S$2,Inputs!$D$2:$AG$2,0)),Inputs!$B$4:$B$150,$B21)/1000) -> 0 | T21: =IF(T$3=0,"",SUMIFS(INDEX(Inputs!$D$4:$AG$150,0,MATCH(T$2,Inputs!$D$2:$AG$2,0)),Inputs!$B$4:$B$150,$B21)/1000) -> 0 | U21: =IF(U$3=0,"",SUMIFS(INDEX(Inputs!$D$4:$AG$150,0,MATCH(U$2,Inputs!$D$2:$AG$2,0)),Inputs!$B$4:$B$150,$B21)/1000) -> 0 | V21: =IF(V$3=0,"",SUMIFS(INDEX(Inputs!$D$4:$AG$150,0,MATCH(V$2,Inputs!$D$2:$AG$2,0)),Inputs!$B$4:$B$150,$B21)/1000) -> 0 | W21: =IF(V21="","",V21) -> 0 | X21: =IF(X$3=0,"",SUMIFS(INDEX(Inputs!$D$4:$AG$150,0,MATCH(X$2,Inputs!$D$2:$AG$2,0)),Inputs!$B$4:$B$150,$B21)/1000) -> 0 | Y21: =IF(Y$3=0,"",SUMIFS(INDEX(Inputs!$D$4:$AG$150,0,MATCH(Y$2,Inputs!$D$2:$AG$2,0)),Inputs!$B$4:$B$150,$B21)/1000) -> 0 | Z21: =IF(Z$3=0,"",SUMIFS(INDEX(Inputs!$D$4:$AG$150,0,MATCH(Z$2,Inputs!$D$2:$AG$2,0)),Inputs!$B$4:$B$150,$B21)/1000) -> 0 | AA21: =IF(AA$3=0,"",SUMIFS(INDEX(Inputs!$D$4:$AG$150,0,MATCH(AA$2,Inputs!$D$2:$AG$2,0)),Inputs!$B$4:$B$150,$B21)/1000) -> 0 | AB21: =IF(AA21="","",AA21) -> 0 | AC21: =IF(AC$3=0,"",SUMIFS(INDEX(Inputs!$D$4:$AG$150,0,MATCH(AC$2,Inputs!$D$2:$AG$2,0)),Inputs!$B$4:$B$150,$B21)/1000) -> 0 | AD21: =IF(AD$3=0,"",SUMIFS(INDEX(Inputs!$D$4:$AG$150,0,MATCH(AD$2,Inputs!$D$2:$AG$2,0)),Inputs!$B$4:$B$150,$B21)/1000) -> 0 | AE21: =IF(AE$3=0,"",SUMIFS(INDEX(Inputs!$D$4:$AG$150,0,MATCH(AE$2,Inputs!$D$2:$AG$2,0)),Inputs!$B$4:$B$150,$B21)/1000) | AF21: =IF(AF$3=0,"",SUMIFS(INDEX(Inputs!$D$4:$AG$150,0,MATCH(AF$2,Inputs!$D$2:$AG$2,0)),Inputs!$B$4:$B$150,$B21)/1000) | AG21: =IF(AF21="","",AF21)
B22: 18 | C22: PP&E | D22: =IF(D$3=0,"",SUMIFS(INDEX(Inputs!$D$4:$AG$150,0,MATCH(D$2,Inputs!$D$2:$AG$2,0)),Inputs!$B$4:$B$150,$B22)/1000) -> 37815 | E22: =IF(E$3=0,"",SUMIFS(INDEX(Inputs!$D$4:$AG$150,0,MATCH(E$2,Inputs!$D$2:$AG$2,0)),Inputs!$B$4:$B$150,$B22)/1000) -> 38615 | F22: =IF(F$3=0,"",SUMIFS(INDEX(Inputs!$D$4:$AG$150,0,MATCH(F$2,Inputs!$D$2:$AG$2,0)),Inputs!$B$4:$B$150,$B22)/1000) -> 39440 | G22: =IF(G$3=0,"",SUMIFS(INDEX(Inputs!$D$4:$AG$150,0,MATCH(G$2,Inputs!$D$2:$AG$2,0)),Inputs!$B$4:$B$150,$B22)/1000) -> 39245 | H22: =IF(G22="","",G22) -> 39245 | I22: =IF(I$3=0,"",SUMIFS(INDEX(Inputs!$D$4:$AG$150,0,MATCH(I$2,Inputs!$D$2:$AG$2,0)),Inputs!$B$4:$B$150,$B22)/1000) -> 39304 | J22: =IF(J$3=0,"",SUMIFS(INDEX(Inputs!$D$4:$AG$150,0,MATCH(J$2,Inputs!$D$2:$AG$2,0)),Inputs!$B$4:$B$150,$B22)/1000) -> 40335 | K22: =IF(K$3=0,"",SUMIFS(INDEX(Inputs!$D$4:$AG$150,0,MATCH(K$2,Inputs!$D$2:$AG$2,0)),Inputs!$B$4:$B$150,$B22)/1000) -> 42117 | L22: =IF(L$3=0,"",SUMIFS(INDEX(Inputs!$D$4:$AG$150,0,MATCH(L$2,Inputs!$D$2:$AG$2,0)),Inputs!$B$4:$B$150,$B22)/1000) -> 42951 | M22: =IF(L22="","",L22) -> 42951 | N22: =IF(N$3=0,"",SUMIFS(INDEX(Inputs!$D$4:$AG$150,0,MATCH(N$2,Inputs!$D$2:$AG$2,0)),Inputs!$B$4:$B$150,$B22)/1000) -> 43398 | O22: =IF(O$3=0,"",SUMIFS(INDEX(Inputs!$D$4:$AG$150,0,MATCH(O$2,Inputs!$D$2:$AG$2,0)),Inputs!$B$4:$B$150,$B22)/1000) -> 43550 | P22: =IF(P$3=0,"",SUMIFS(INDEX(Inputs!$D$4:$AG$150,0,MATCH(P$2,Inputs!$D$2:$AG$2,0)),Inputs!$B$4:$B$150,$B22)/1000) -> 43715 | Q22: =IF(Q$3=0,"",SUMIFS(INDEX(Inputs!$D$4:$AG$150,0,MATCH(Q$2,Inputs!$D$2:$AG$2,0)),Inputs!$B$4:$B$150,$B22)/1000) -> 43666 | R22: =IF(Q22="","",Q22) -> 43666 | S22: =IF(S$3=0,"",SUMIFS(INDEX(Inputs!$D$4:$AG$150,0,MATCH(S$2,Inputs!$D$2:$AG$2,0)),Inputs!$B$4:$B$150,$B22)/1000) -> 43546 | T22: =IF(T$3=0,"",SUMIFS(INDEX(Inputs!$D$4:$AG$150,0,MATCH(T$2,Inputs!$D$2:$AG$2,0)),Inputs!$B$4:$B$150,$B22)/1000) -> 44502 | U22: =IF(U$3=0,"",SUMIFS(INDEX(Inputs!$D$4:$AG$150,0,MATCH(U$2,Inputs!$D$2:$AG$2,0)),Inputs!$B$4:$B$150,$B22)/1000) -> 45680 | V22: =IF(V$3=0,"",SUMIFS(INDEX(Inputs!$D$4:$AG$150,0,MATCH(V$2,Inputs!$D$2:$AG$2,0)),Inputs!$B$4:$B$150,$B22)/1000) -> 46069 | W22: =IF(V22="","",V22) -> 46069 | X22: =IF(X$3=0,"",SUMIFS(INDEX(Inputs!$D$4:$AG$150,0,MATCH(X$2,Inputs!$D$2:$AG$2,0)),Inputs!$B$4:$B$150,$B22)/1000) -> 46876 | Y22: =IF(Y$3=0,"",SUMIFS(INDEX(Inputs!$D$4:$AG$150,0,MATCH(Y$2,Inputs!$D$2:$AG$2,0)),Inputs!$B$4:$B$150,$B22)/1000) -> 48508 | Z22: =IF(Z$3=0,"",SUMIFS(INDEX(Inputs!$D$4:$AG$150,0,MATCH(Z$2,Inputs!$D$2:$AG$2,0)),Inputs!$B$4:$B$150,$B22)/1000) -> 49834 | AA22: =IF(AA$3=0,"",SUMIFS(INDEX(Inputs!$D$4:$AG$150,0,MATCH(AA$2,Inputs!$D$2:$AG$2,0)),Inputs!$B$4:$B$150,$B22)/1000) -> 50159 | AB22: =IF(AA22="","",AA22) -> 50159 | AC22: =IF(AC$3=0,"",SUMIFS(INDEX(Inputs!$D$4:$AG$150,0,MATCH(AC$2,Inputs!$D$2:$AG$2,0)),Inputs!$B$4:$B$150,$B22)/1000) -> 50116 | AD22: =IF(AD$3=0,"",SUMIFS(INDEX(Inputs!$D$4:$AG$150,0,MATCH(AD$2,Inputs!$D$2:$AG$2,0)),Inputs!$B$4:$B$150,$B22)/1000) -> 51431 | AE22: =IF(AE$3=0,"",SUMIFS(INDEX(Inputs!$D$4:$AG$150,0,MATCH(AE$2,Inputs!$D$2:$AG$2,0)),Inputs!$B$4:$B$150,$B22)/1000) | AF22: =IF(AF$3=0,"",SUMIFS(INDEX(Inputs!$D$4:$AG$150,0,MATCH(AF$2,Inputs!$D$2:$AG$2,0)),Inputs!$B$4:$B$150,$B22)/1000) | AG22: =IF(AF22="","",AF22)
B23: 19 | C23: Right-of-use-assets | D23: =IF(D$3=0,"",SUMIFS(INDEX(Inputs!$D$4:$AG$150,0,MATCH(D$2,Inputs!$D$2:$AG$2,0)),Inputs!$B$4:$B$150,$B23)/1000) -> 0 | E23: =IF(E$3=0,"",SUMIFS(INDEX(Inputs!$D$4:$AG$150,0,MATCH(E$2,Inputs!$D$2:$AG$2,0)),Inputs!$B$4:$B$150,$B23)/1000) -> 0 | F23: =IF(F$3=0,"",SUMIFS(INDEX(Inputs!$D$4:$AG$150,0,MATCH(F$2,Inputs!$D$2:$AG$2,0)),Inputs!$B$4:$B$150,$B23)/1000) -> 0 | G23: =IF(G$3=0,"",SUMIFS(INDEX(Inputs!$D$4:$AG$150,0,MATCH(G$2,Inputs!$D$2:$AG$2,0)),Inputs!$B$4:$B$150,$B23)/1000) -> 0 | H23: =IF(G23="","",G23) -> 0 | I23: =IF(I$3=0,"",SUMIFS(INDEX(Inputs!$D$4:$AG$150,0,MATCH(I$2,Inputs!$D$2:$AG$2,0)),Inputs!$B$4:$B$150,$B23)/1000) -> 0 | J23: =IF(J$3=0,"",SUMIFS(INDEX(Inputs!$D$4:$AG$150,0,MATCH(J$2,Inputs!$D$2:$AG$2,0)),Inputs!$B$4:$B$150,$B23)/1000) -> 0 | K23: =IF(K$3=0,"",SUMIFS(INDEX(Inputs!$D$4:$AG$150,0,MATCH(K$2,Inputs!$D$2:$AG$2,0)),Inputs!$B$4:$B$150,$B23)/1000) -> 0 | L23: =IF(L$3=0,"",SUMIFS(INDEX(Inputs!$D$4:$AG$150,0,MATCH(L$2,Inputs!$D$2:$AG$2,0)),Inputs!$B$4:$B$150,$B23)/1000) -> 0 | M23: =IF(L23="","",L23) -> 0 | N23: =IF(N$3=0,"",SUMIFS(INDEX(Inputs!$D$4:$AG$150,0,MATCH(N$2,Inputs!$D$2:$AG$2,0)),Inputs!$B$4:$B$150,$B23)/1000) -> 0 | O23: =IF(O$3=0,"",SUMIFS(INDEX(Inputs!$D$4:$AG$150,0,MATCH(O$2,Inputs!$D$2:$AG$2,0)),Inputs!$B$4:$B$150,$B23)/1000) -> 0 | P23: =IF(P$3=0,"",SUMIFS(INDEX(Inputs!$D$4:$AG$150,0,MATCH(P$2,Inputs!$D$2:$AG$2,0)),Inputs!$B$4:$B$150,$B23)/1000) -> 0 | Q23: =IF(Q$3=0,"",SUMIFS(INDEX(Inputs!$D$4:$AG$150,0,MATCH(Q$2,Inputs!$D$2:$AG$2,0)),Inputs!$B$4:$B$150,$B23)/1000) -> 0 | R23: =IF(Q23="","",Q23) -> 0 | S23: =IF(S$3=0,"",SUMIFS(INDEX(Inputs!$D$4:$AG$150,0,MATCH(S$2,Inputs!$D$2:$AG$2,0)),Inputs!$B$4:$B$150,$B23)/1000) -> 0 | T23: =IF(T$3=0,"",SUMIFS(INDEX(Inputs!$D$4:$AG$150,0,MATCH(T$2,Inputs!$D$2:$AG$2,0)),Inputs!$B$4:$B$150,$B23)/1000) -> 0 | U23: =IF(U$3=0,"",SUMIFS(INDEX(Inputs!$D$4:$AG$150,0,MATCH(U$2,Inputs!$D$2:$AG$2,0)),Inputs!$B$4:$B$150,$B23)/1000) -> 0 | V23: =IF(V$3=0,"",SUMIFS(INDEX(Inputs!$D$4:$AG$150,0,MATCH(V$2,Inputs!$D$2:$AG$2,0)),Inputs!$B$4:$B$150,$B23)/1000) -> 0 | W23: =IF(V23="","",V23) -> 0 | X23: =IF(X$3=0,"",SUMIFS(INDEX(Inputs!$D$4:$AG$150,0,MATCH(X$2,Inputs!$D$2:$AG$2,0)),Inputs!$B$4:$B$150,$B23)/1000) -> 0 | Y23: =IF(Y$3=0,"",SUMIFS(INDEX(Inputs!$D$4:$AG$150,0,MATCH(Y$2,Inputs!$D$2:$AG$2,0)),Inputs!$B$4:$B$150,$B23)/1000) -> 0 | Z23: =IF(Z$3=0,"",SUMIFS(INDEX(Inputs!$D$4:$AG$150,0,MATCH(Z$2,Inputs!$D$2:$AG$2,0)),Inputs!$B$4:$B$150,$B23)/1000) -> 0 | AA23: =IF(AA$3=0,"",SUMIFS(INDEX(Inputs!$D$4:$AG$150,0,MATCH(AA$2,Inputs!$D$2:$AG$2,0)),Inputs!$B$4:$B$150,$B23)/1000) -> 0 | AB23: =IF(AA23="","",AA23) -> 0 | AC23: =IF(AC$3=0,"",SUMIFS(INDEX(Inputs!$D$4:$AG$150,0,MATCH(AC$2,Inputs!$D$2:$AG$2,0)),Inputs!$B$4:$B$150,$B23)/1000) -> 0 | AD23: =IF(AD$3=0,"",SUMIFS(INDEX(Inputs!$D$4:$AG$150,0,MATCH(AD$2,Inputs!$D$2:$AG$2,0)),Inputs!$B$4:$B$150,$B23)/1000) -> 0 | AE23: =IF(AE$3=0,"",SUMIFS(INDEX(Inputs!$D$4:$AG$150,0,MATCH(AE$2,Inputs!$D$2:$AG$2,0)),Inputs!$B$4:$B$150,$B23)/1000) | AF23: =IF(AF$3=0,"",SUMIFS(INDEX(Inputs!$D$4:$AG$150,0,MATCH(AF$2,Inputs!$D$2:$AG$2,0)),Inputs!$B$4:$B$150,$B23)/1000) | AG23: =IF(AF23="","",AF23)
B24: 20 | C24: Goodwill | D24: =IF(D$3=0,"",SUMIFS(INDEX(Inputs!$D$4:$AG$150,0,MATCH(D$2,Inputs!$D$2:$AG$2,0)),Inputs!$B$4:$B$150,$B24)/1000) -> 0 | E24: =IF(E$3=0,"",SUMIFS(INDEX(Inputs!$D$4:$AG$150,0,MATCH(E$2,Inputs!$D$2:$AG$2,0)),Inputs!$B$4:$B$150,$B24)/1000) -> 0 | F24: =IF(F$3=0,"",SUMIFS(INDEX(Inputs!$D$4:$AG$150,0,MATCH(F$2,Inputs!$D$2:$AG$2,0)),Inputs!$B$4:$B$150,$B24)/1000) -> 0 | G24: =IF(G$3=0,"",SUMIFS(INDEX(Inputs!$D$4:$AG$150,0,MATCH(G$2,Inputs!$D$2:$AG$2,0)),Inputs!$B$4:$B$150,$B24)/1000) -> 0 | H24: =IF(G24="","",G24) -> 0 | I24: =IF(I$3=0,"",SUMIFS(INDEX(Inputs!$D$4:$AG$150,0,MATCH(I$2,Inputs!$D$2:$AG$2,0)),Inputs!$B$4:$B$150,$B24)/1000) -> 0 | J24: =IF(J$3=0,"",SUMIFS(INDEX(Inputs!$D$4:$AG$150,0,MATCH(J$2,Inputs!$D$2:$AG$2,0)),Inputs!$B$4:$B$150,$B24)/1000) -> 0 | K24: =IF(K$3=0,"",SUMIFS(INDEX(Inputs!$D$4:$AG$150,0,MATCH(K$2,Inputs!$D$2:$AG$2,0)),Inputs!$B$4:$B$150,$B24)/1000) -> 0 | L24: =IF(L$3=0,"",SUMIFS(INDEX(Inputs!$D$4:$AG$150,0,MATCH(L$2,Inputs!$D$2:$AG$2,0)),Inputs!$B$4:$B$150,$B24)/1000) -> 0 | M24: =IF(L24="","",L24) -> 0 | N24: =IF(N$3=0,"",SUMIFS(INDEX(Inputs!$D$4:$AG$150,0,MATCH(N$2,Inputs!$D$2:$AG$2,0)),Inputs!$B$4:$B$150,$B24)/1000) -> 0 | O24: =IF(O$3=0,"",SUMIFS(INDEX(Inputs!$D$4:$AG$150,0,MATCH(O$2,Inputs!$D$2:$AG$2,0)),Inputs!$B$4:$B$150,$B24)/1000) -> 0 | P24: =IF(P$3=0,"",SUMIFS(INDEX(Inputs!$D$4:$AG$150,0,MATCH(P$2,Inputs!$D$2:$AG$2,0)),Inputs!$B$4:$B$150,$B24)/1000) -> 0 | Q24: =IF(Q$3=0,"",SUMIFS(INDEX(Inputs!$D$4:$AG$150,0,MATCH(Q$2,Inputs!$D$2:$AG$2,0)),Inputs!$B$4:$B$150,$B24)/1000) -> 0 | R24: =IF(Q24="","",Q24) -> 0 | S24: =IF(S$3=0,"",SUMIFS(INDEX(Inputs!$D$4:$AG$150,0,MATCH(S$2,Inputs!$D$2:$AG$2,0)),Inputs!$B$4:$B$150,$B24)/1000) -> 0 | T24: =IF(T$3=0,"",SUMIFS(INDEX(Inputs!$D$4:$AG$150,0,MATCH(T$2,Inputs!$D$2:$AG$2,0)),Inputs!$B$4:$B$150,$B24)/1000) -> 0 | U24: =IF(U$3=0,"",SUMIFS(INDEX(Inputs!$D$4:$AG$150,0,MATCH(U$2,Inputs!$D$2:$AG$2,0)),Inputs!$B$4:$B$150,$B24)/1000) -> 0 | V24: =IF(V$3=0,"",SUMIFS(INDEX(Inputs!$D$4:$AG$150,0,MATCH(V$2,Inputs!$D$2:$AG$2,0)),Inputs!$B$4:$B$150,$B24)/1000) -> 0 | W24: =IF(V24="","",V24) -> 0 | X24: =IF(X$3=0,"",SUMIFS(INDEX(Inputs!$D$4:$AG$150,0,MATCH(X$2,Inputs!$D$2:$AG$2,0)),Inputs!$B$4:$B$150,$B24)/1000) -> 0 | Y24: =IF(Y$3=0,"",SUMIFS(INDEX(Inputs!$D$4:$AG$150,0,MATCH(Y$2,Inputs!$D$2:$AG$2,0)),Inputs!$B$4:$B$150,$B24)/1000) -> 0 | Z24: =IF(Z$3=0,"",SUMIFS(INDEX(Inputs!$D$4:$AG$150,0,MATCH(Z$2,Inputs!$D$2:$AG$2,0)),Inputs!$B$4:$B$150,$B24)/1000) -> 0 | AA24: =IF(AA$3=0,"",SUMIFS(INDEX(Inputs!$D$4:$AG$150,0,MATCH(AA$2,Inputs!$D$2:$AG$2,0)),Inputs!$B$4:$B$150,$B24)/1000) -> 0 | AB24: =IF(AA24="","",AA24) -> 0 | AC24: =IF(AC$3=0,"",SUMIFS(INDEX(Inputs!$D$4:$AG$150,0,MATCH(AC$2,Inputs!$D$2:$AG$2,0)),Inputs!$B$4:$B$150,$B24)/1000) -> 0 | AD24: =IF(AD$3=0,"",SUMIFS(INDEX(Inputs!$D$4:$AG$150,0,MATCH(AD$2,Inputs!$D$2:$AG$2,0)),Inputs!$B$4:$B$150,$B24)/1000) -> 0 | AE24: =IF(AE$3=0,"",SUMIFS(INDEX(Inputs!$D$4:$AG$150,0,MATCH(AE$2,Inputs!$D$2:$AG$2,0)),Inputs!$B$4:$B$150,$B24)/1000) | AF24: =IF(AF$3=0,"",SUMIFS(INDEX(Inputs!$D$4:$AG$150,0,MATCH(AF$2,Inputs!$D$2:$AG$2,0)),Inputs!$B$4:$B$150,$B24)/1000) | AG24: =IF(AF24="","",AF24)
B25: 21 | C25: Intangibles | D25: =IF(D$3=0,"",SUMIFS(INDEX(Inputs!$D$4:$AG$150,0,MATCH(D$2,Inputs!$D$2:$AG$2,0)),Inputs!$B$4:$B$150,$B25)/1000) -> 0 | E25: =IF(E$3=0,"",SUMIFS(INDEX(Inputs!$D$4:$AG$150,0,MATCH(E$2,Inputs!$D$2:$AG$2,0)),Inputs!$B$4:$B$150,$B25)/1000) -> 0 | F25: =IF(F$3=0,"",SUMIFS(INDEX(Inputs!$D$4:$AG$150,0,MATCH(F$2,Inputs!$D$2:$AG$2,0)),Inputs!$B$4:$B$150,$B25)/1000) -> 0 | G25: =IF(G$3=0,"",SUMIFS(INDEX(Inputs!$D$4:$AG$150,0,MATCH(G$2,Inputs!$D$2:$AG$2,0)),Inputs!$B$4:$B$150,$B25)/1000) -> 0 | H25: =IF(G25="","",G25) -> 0 | I25: =IF(I$3=0,"",SUMIFS(INDEX(Inputs!$D$4:$AG$150,0,MATCH(I$2,Inputs!$D$2:$AG$2,0)),Inputs!$B$4:$B$150,$B25)/1000) -> 0 | J25: =IF(J$3=0,"",SUMIFS(INDEX(Inputs!$D$4:$AG$150,0,MATCH(J$2,Inputs!$D$2:$AG$2,0)),Inputs!$B$4:$B$150,$B25)/1000) -> 0 | K25: =IF(K$3=0,"",SUMIFS(INDEX(Inputs!$D$4:$AG$150,0,MATCH(K$2,Inputs!$D$2:$AG$2,0)),Inputs!$B$4:$B$150,$B25)/1000) -> 0 | L25: =IF(L$3=0,"",SUMIFS(INDEX(Inputs!$D$4:$AG$150,0,MATCH(L$2,Inputs!$D$2:$AG$2,0)),Inputs!$B$4:$B$150,$B25)/1000) -> 0 | M25: =IF(L25="","",L25) -> 0 | N25: =IF(N$3=0,"",SUMIFS(INDEX(Inputs!$D$4:$AG$150,0,MATCH(N$2,Inputs!$D$2:$AG$2,0)),Inputs!$B$4:$B$150,$B25)/1000) -> 0 | O25: =IF(O$3=0,"",SUMIFS(INDEX(Inputs!$D$4:$AG$150,0,MATCH(O$2,Inputs!$D$2:$AG$2,0)),Inputs!$B$4:$B$150,$B25)/1000) -> 0 | P25: =IF(P$3=0,"",SUMIFS(INDEX(Inputs!$D$4:$AG$150,0,MATCH(P$2,Inputs!$D$2:$AG$2,0)),Inputs!$B$4:$B$150,$B25)/1000) -> 0 | Q25: =IF(Q$3=0,"",SUMIFS(INDEX(Inputs!$D$4:$AG$150,0,MATCH(Q$2,Inputs!$D$2:$AG$2,0)),Inputs!$B$4:$B$150,$B25)/1000) -> 0 | R25: =IF(Q25="","",Q25) -> 0 | S25: =IF(S$3=0,"",SUMIFS(INDEX(Inputs!$D$4:$AG$150,0,MATCH(S$2,Inputs!$D$2:$AG$2,0)),Inputs!$B$4:$B$150,$B25)/1000) -> 0 | T25: =IF(T$3=0,"",SUMIFS(INDEX(Inputs!$D$4:$AG$150,0,MATCH(T$2,Inputs!$D$2:$AG$2,0)),Inputs!$B$4:$B$150,$B25)/1000) -> 0 | U25: =IF(U$3=0,"",SUMIFS(INDEX(Inputs!$D$4:$AG$150,0,MATCH(U$2,Inputs!$D$2:$AG$2,0)),Inputs!$B$4:$B$150,$B25)/1000) -> 0 | V25: =IF(V$3=0,"",SUMIFS(INDEX(Inputs!$D$4:$AG$150,0,MATCH(V$2,Inputs!$D$2:$AG$2,0)),Inputs!$B$4:$B$150,$B25)/1000) -> 0 | W25: =IF(V25="","",V25) -> 0 | X25: =IF(X$3=0,"",SUMIFS(INDEX(Inputs!$D$4:$AG$150,0,MATCH(X$2,Inputs!$D$2:$AG$2,0)),Inputs!$B$4:$B$150,$B25)/1000) -> 0 | Y25: =IF(Y$3=0,"",SUMIFS(INDEX(Inputs!$D$4:$AG$150,0,MATCH(Y$2,Inputs!$D$2:$AG$2,0)),Inputs!$B$4:$B$150,$B25)/1000) -> 0 | Z25: =IF(Z$3=0,"",SUMIFS(INDEX(Inputs!$D$4:$AG$150,0,MATCH(Z$2,Inputs!$D$2:$AG$2,0)),Inputs!$B$4:$B$150,$B25)/1000) -> 11093 | AA25: =IF(AA$3=0,"",SUMIFS(INDEX(Inputs!$D$4:$AG$150,0,MATCH(AA$2,Inputs!$D$2:$AG$2,0)),Inputs!$B$4:$B$150,$B25)/1000) -> 0 | AB25: =IF(AA25="","",AA25) -> 0 | AC25: =IF(AC$3=0,"",SUMIFS(INDEX(Inputs!$D$4:$AG$150,0,MATCH(AC$2,Inputs!$D$2:$AG$2,0)),Inputs!$B$4:$B$150,$B25)/1000) -> 21334 | AD25: =IF(AD$3=0,"",SUMIFS(INDEX(Inputs!$D$4:$AG$150,0,MATCH(AD$2,Inputs!$D$2:$AG$2,0)),Inputs!$B$4:$B$150,$B25)/1000) -> 20342 | AE25: =IF(AE$3=0,"",SUMIFS(INDEX(Inputs!$D$4:$AG$150,0,MATCH(AE$2,Inputs!$D$2:$AG$2,0)),Inputs!$B$4:$B$150,$B25)/1000) | AF25: =IF(AF$3=0,"",SUMIFS(INDEX(Inputs!$D$4:$AG$150,0,MATCH(AF$2,Inputs!$D$2:$AG$2,0)),Inputs!$B$4:$B$150,$B25)/1000) | AG25: =IF(AF25="","",AF25)
B26: 22 | C26: Other non-current assets | D26: =IF(D$3=0,"",SUMIFS(INDEX(Inputs!$D$4:$AG$150,0,MATCH(D$2,Inputs!$D$2:$AG$2,0)),Inputs!$B$4:$B$150,$B26)/1000) -> 43339 | E26: =IF(E$3=0,"",SUMIFS(INDEX(Inputs!$D$4:$AG$150,0,MATCH(E$2,Inputs!$D$2:$AG$2,0)),Inputs!$B$4:$B$150,$B26)/1000) -> 44854 | F26: =IF(F$3=0,"",SUMIFS(INDEX(Inputs!$D$4:$AG$150,0,MATCH(F$2,Inputs!$D$2:$AG$2,0)),Inputs!$B$4:$B$150,$B26)/1000) -> 48849 | G26: =IF(G$3=0,"",SUMIFS(INDEX(Inputs!$D$4:$AG$150,0,MATCH(G$2,Inputs!$D$2:$AG$2,0)),Inputs!$B$4:$B$150,$B26)/1000) -> 50109 | H26: =IF(G26="","",G26) -> 50109 | I26: =IF(I$3=0,"",SUMIFS(INDEX(Inputs!$D$4:$AG$150,0,MATCH(I$2,Inputs!$D$2:$AG$2,0)),Inputs!$B$4:$B$150,$B26)/1000) -> 51959 | J26: =IF(J$3=0,"",SUMIFS(INDEX(Inputs!$D$4:$AG$150,0,MATCH(J$2,Inputs!$D$2:$AG$2,0)),Inputs!$B$4:$B$150,$B26)/1000) -> 52605 | K26: =IF(K$3=0,"",SUMIFS(INDEX(Inputs!$D$4:$AG$150,0,MATCH(K$2,Inputs!$D$2:$AG$2,0)),Inputs!$B$4:$B$150,$B26)/1000) -> 54428 | L26: =IF(L$3=0,"",SUMIFS(INDEX(Inputs!$D$4:$AG$150,0,MATCH(L$2,Inputs!$D$2:$AG$2,0)),Inputs!$B$4:$B$150,$B26)/1000) -> 60924 | M26: =IF(L26="","",L26) -> 60924 | N26: =IF(N$3=0,"",SUMIFS(INDEX(Inputs!$D$4:$AG$150,0,MATCH(N$2,Inputs!$D$2:$AG$2,0)),Inputs!$B$4:$B$150,$B26)/1000) -> 65388 | O26: =IF(O$3=0,"",SUMIFS(INDEX(Inputs!$D$4:$AG$150,0,MATCH(O$2,Inputs!$D$2:$AG$2,0)),Inputs!$B$4:$B$150,$B26)/1000) -> 64768 | P26: =IF(P$3=0,"",SUMIFS(INDEX(Inputs!$D$4:$AG$150,0,MATCH(P$2,Inputs!$D$2:$AG$2,0)),Inputs!$B$4:$B$150,$B26)/1000) -> 64758 | Q26: =IF(Q$3=0,"",SUMIFS(INDEX(Inputs!$D$4:$AG$150,0,MATCH(Q$2,Inputs!$D$2:$AG$2,0)),Inputs!$B$4:$B$150,$B26)/1000) -> 66681 | R26: =IF(Q26="","",Q26) -> 66681 | S26: =IF(S$3=0,"",SUMIFS(INDEX(Inputs!$D$4:$AG$150,0,MATCH(S$2,Inputs!$D$2:$AG$2,0)),Inputs!$B$4:$B$150,$B26)/1000) -> 70262 | T26: =IF(T$3=0,"",SUMIFS(INDEX(Inputs!$D$4:$AG$150,0,MATCH(T$2,Inputs!$D$2:$AG$2,0)),Inputs!$B$4:$B$150,$B26)/1000) -> 70435 | U26: =IF(U$3=0,"",SUMIFS(INDEX(Inputs!$D$4:$AG$150,0,MATCH(U$2,Inputs!$D$2:$AG$2,0)),Inputs!$B$4:$B$150,$B26)/1000) -> 74834 | V26: =IF(V$3=0,"",SUMIFS(INDEX(Inputs!$D$4:$AG$150,0,MATCH(V$2,Inputs!$D$2:$AG$2,0)),Inputs!$B$4:$B$150,$B26)/1000) -> 77183 | W26: =IF(V26="","",V26) -> 77183 | X26: =IF(X$3=0,"",SUMIFS(INDEX(Inputs!$D$4:$AG$150,0,MATCH(X$2,Inputs!$D$2:$AG$2,0)),Inputs!$B$4:$B$150,$B26)/1000) -> 81259 | Y26: =IF(Y$3=0,"",SUMIFS(INDEX(Inputs!$D$4:$AG$150,0,MATCH(Y$2,Inputs!$D$2:$AG$2,0)),Inputs!$B$4:$B$150,$B26)/1000) -> 82882 | Z26: =IF(Z$3=0,"",SUMIFS(INDEX(Inputs!$D$4:$AG$150,0,MATCH(Z$2,Inputs!$D$2:$AG$2,0)),Inputs!$B$4:$B$150,$B26)/1000) -> 72634 | AA26: =IF(AA$3=0,"",SUMIFS(INDEX(Inputs!$D$4:$AG$150,0,MATCH(AA$2,Inputs!$D$2:$AG$2,0)),Inputs!$B$4:$B$150,$B26)/1000) -> 93146 | AB26: =IF(AA26="","",AA26) -> 93146 | AC26: =IF(AC$3=0,"",SUMIFS(INDEX(Inputs!$D$4:$AG$150,0,MATCH(AC$2,Inputs!$D$2:$AG$2,0)),Inputs!$B$4:$B$150,$B26)/1000) -> 77430 | AD26: =IF(AD$3=0,"",SUMIFS(INDEX(Inputs!$D$4:$AG$150,0,MATCH(AD$2,Inputs!$D$2:$AG$2,0)),Inputs!$B$4:$B$150,$B26)/1000) -> 77557 | AE26: =IF(AE$3=0,"",SUMIFS(INDEX(Inputs!$D$4:$AG$150,0,MATCH(AE$2,Inputs!$D$2:$AG$2,0)),Inputs!$B$4:$B$150,$B26)/1000) | AF26: =IF(AF$3=0,"",SUMIFS(INDEX(Inputs!$D$4:$AG$150,0,MATCH(AF$2,Inputs!$D$2:$AG$2,0)),Inputs!$B$4:$B$150,$B26)/1000) | AG26: =IF(AF26="","",AF26)
... B47: 41 | C47: Retained earnings | D47: =IF(D$3=0,"",SUMIFS(INDEX(Inputs!$D$4:$AG$150,0,MATCH(D$2,Inputs!$D$2:$AG$2,0)),Inputs!$B$4:$B$150,$B47)/1000) -> 15261 | E47: =IF(E$3=0,"",SUMIFS(INDEX(Inputs!$D$4:$AG$150,0,MATCH(E$2,Inputs!$D$2:$AG$2,0)),Inputs!$B$4:$B$150,$B47)/1000) -> 9233 | F47: =IF(F$3=0,"",SUMIFS(INDEX(Inputs!$D$4:$AG$150,0,MATCH(F$2,Inputs!$D$2:$AG$2,0)),Inputs!$B$4:$B$150,$B47)/1000) -> 5562 | G47: =IF(G$3=0,"",SUMIFS(INDEX(Inputs!$D$4:$AG$150,0,MATCH(G$2,Inputs!$D$2:$AG$2,0)),Inputs!$B$4:$B$150,$B47)/1000) -> 14435 | H47: =IF(G47="","",G47) -> 14435 | I47: =IF(I$3=0,"",SUMIFS(INDEX(Inputs!$D$4:$AG$150,0,MATCH(I$2,Inputs!$D$2:$AG$2,0)),Inputs!$B$4:$B$150,$B47)/1000) -> 12712 | J47: =IF(J$3=0,"",SUMIFS(INDEX(Inputs!$D$4:$AG$150,0,MATCH(J$2,Inputs!$D$2:$AG$2,0)),Inputs!$B$4:$B$150,$B47)/1000) -> 5289 | K47: =IF(K$3=0,"",SUMIFS(INDEX(Inputs!$D$4:$AG$150,0,MATCH(K$2,Inputs!$D$2:$AG$2,0)),Inputs!$B$4:$B$150,$B47)/1000) -> -3068 | L47: =IF(L$3=0,"",SUMIFS(INDEX(Inputs!$D$4:$AG$150,0,MATCH(L$2,Inputs!$D$2:$AG$2,0)),Inputs!$B$4:$B$150,$B47)/1000) -> 3240 | M47: =IF(L47="","",L47) -> 3240 | N47: =IF(N$3=0,"",SUMIFS(INDEX(Inputs!$D$4:$AG$150,0,MATCH(N$2,Inputs!$D$2:$AG$2,0)),Inputs!$B$4:$B$150,$B47)/1000) -> 4336 | O47: =IF(O$3=0,"",SUMIFS(INDEX(Inputs!$D$4:$AG$150,0,MATCH(O$2,Inputs!$D$2:$AG$2,0)),Inputs!$B$4:$B$150,$B47)/1000) -> 1408 | P47: =IF(P$3=0,"",SUMIFS(INDEX(Inputs!$D$4:$AG$150,0,MATCH(P$2,Inputs!$D$2:$AG$2,0)),Inputs!$B$4:$B$150,$B47)/1000) -> -214 | Q47: =IF(Q$3=0,"",SUMIFS(INDEX(Inputs!$D$4:$AG$150,0,MATCH(Q$2,Inputs!$D$2:$AG$2,0)),Inputs!$B$4:$B$150,$B47)/1000) -> 8242 | R47: =IF(Q47="","",Q47) -> 8242 | S47: =IF(S$3=0,"",SUMIFS(INDEX(Inputs!$D$4:$AG$150,0,MATCH(S$2,Inputs!$D$2:$AG$2,0)),Inputs!$B$4:$B$150,$B47)/1000) -> 4339 | T47: =IF(T$3=0,"",SUMIFS(INDEX(Inputs!$D$4:$AG$150,0,MATCH(T$2,Inputs!$D$2:$AG$2,0)),Inputs!$B$4:$B$150,$B47)/1000) -> -4726 | U47: =IF(U$3=0,"",SUMIFS(INDEX(Inputs!$D$4:$AG$150,0,MATCH(U$2,Inputs!$D$2:$AG$2,0)),Inputs!$B$4:$B$150,$B47)/1000) -> -19154 | V47: =IF(V$3=0,"",SUMIFS(INDEX(Inputs!$D$4:$AG$150,0,MATCH(V$2,Inputs!$D$2:$AG$2,0)),Inputs!$B$4:$B$150,$B47)/1000) -> -11221 | W47: =IF(V47="","",V47) -> -11221 | X47: =IF(X$3=0,"",SUMIFS(INDEX(Inputs!$D$4:$AG$150,0,MATCH(X$2,Inputs!$D$2:$AG$2,0)),Inputs!$B$4:$B$150,$B47)/1000) -> -15552 | Y47: =IF(Y$3=0,"",SUMIFS(INDEX(Inputs!$D$4:$AG$150,0,MATCH(Y$2,Inputs!$D$2:$AG$2,0)),Inputs!$B$4:$B$150,$B47)/1000) -> -17607 | Z47: =IF(Z$3=0,"",SUMIFS(INDEX(Inputs!$D$4:$AG$150,0,MATCH(Z$2,Inputs!$D$2:$AG$2,0)),Inputs!$B$4:$B$150,$B47)/1000) -> -14264 | AA47: =IF(AA$3=0,"",SUMIFS(INDEX(Inputs!$D$4:$AG$150,0,MATCH(AA$2,Inputs!$D$2:$AG$2,0)),Inputs!$B$4:$B$150,$B47)/1000) -> -2177 | AB47: =IF(AA47="","",AA47) -> -2177 | AC47: =IF(AC$3=0,"",SUMIFS(INDEX(Inputs!$D$4:$AG$150,0,MATCH(AC$2,Inputs!$D$2:$AG$2,0)),Inputs!$B$4:$B$150,$B47)/1000) -> 12359 | AD47: =IF(AD$3=0,"",SUMIFS(INDEX(Inputs!$D$4:$AG$150,0,MATCH(AD$2,Inputs!$D$2:$AG$2,0)),Inputs!$B$4:$B$150,$B47)/1000) -> 11326 | AE47: =IF(AE$3=0,"",SUMIFS(INDEX(Inputs!$D$4:$AG$150,0,MATCH(AE$2,Inputs!$D$2:$AG$2,0)),Inputs!$B$4:$B$150,$B47)/1000) | AF47: =IF(AF$3=0,"",SUMIFS(INDEX(Inputs!$D$4:$AG$150,0,MATCH(AF$2,Inputs!$D$2:$AG$2,0)),Inputs!$B$4:$B$150,$B47)/1000) | AG47: =IF(AF47="","",AF47)
B50: 44 | C50: Net income reported (lucro líquido reportado) — base do check de DRE [Model linha 4] | D50: =IF(SUMPRODUCT((Inputs!$B$4:$B$150=$B50)*ISNUMBER(INDEX(Inputs!$D$4:$AG$150,0,MATCH(D$2,Inputs!$D$2:$AG$2,0))))=0,"",SUMIFS(INDEX(Inputs!$D$4:$AG$150,0,MATCH(D$2,Inputs!$D$2:$AG$2,0)),Inputs!$B$4:$B$150,$B50)/1000) -> 23630 | E50: =IF(SUMPRODUCT((Inputs!$B$4:$B$150=$B50)*ISNUMBER(INDEX(Inputs!$D$4:$AG$150,0,MATCH(E$2,Inputs!$D$2:$AG$2,0))))=0,"",SUMIFS(INDEX(Inputs!$D$4:$AG$150,0,MATCH(E$2,Inputs!$D$2:$AG$2,0)),Inputs!$B$4:$B$150,$B50)/1000) -> 21744 | F50: =IF(SUMPRODUCT((Inputs!$B$4:$B$150=$B50)*ISNUMBER(INDEX(Inputs!$D$4:$AG$150,0,MATCH(F$2,Inputs!$D$2:$AG$2,0))))=0,"",SUMIFS(INDEX(Inputs!$D$4:$AG$150,0,MATCH(F$2,Inputs!$D$2:$AG$2,0)),Inputs!$B$4:$B$150,$B50)/1000) -> 20551 | G50: =IF(SUMPRODUCT((Inputs!$B$4:$B$150=$B50)*ISNUMBER(INDEX(Inputs!$D$4:$AG$150,0,MATCH(G$2,Inputs!$D$2:$AG$2,0))))=0,"",SUMIFS(INDEX(Inputs!$D$4:$AG$150,0,MATCH(G$2,Inputs!$D$2:$AG$2,0)),Inputs!$B$4:$B$150,$B50)/1000) -> 34630 | H50: =IF(COUNT(D50:G50)=4,SUM(D50:G50),"") -> 100555 | I50: =IF(SUMPRODUCT((Inputs!$B$4:$B$150=$B50)*ISNUMBER(INDEX(Inputs!$D$4:$AG$150,0,MATCH(I$2,Inputs!$D$2:$AG$2,0))))=0,"",SUMIFS(INDEX(Inputs!$D$4:$AG$150,0,MATCH(I$2,Inputs!$D$2:$AG$2,0)),Inputs!$B$4:$B$150,$B50)/1000) -> 25010 | J50: =IF(SUMPRODUCT((Inputs!$B$4:$B$150=$B50)*ISNUMBER(INDEX(Inputs!$D$4:$AG$150,0,MATCH(J$2,Inputs!$D$2:$AG$2,0))))=0,"",SUMIFS(INDEX(Inputs!$D$4:$AG$150,0,MATCH(J$2,Inputs!$D$2:$AG$2,0)),Inputs!$B$4:$B$150,$B50)/1000) -> 19442 | K50: =IF(SUMPRODUCT((Inputs!$B$4:$B$150=$B50)*ISNUMBER(INDEX(Inputs!$D$4:$AG$150,0,MATCH(K$2,Inputs!$D$2:$AG$2,0))))=0,"",SUMIFS(INDEX(Inputs!$D$4:$AG$150,0,MATCH(K$2,Inputs!$D$2:$AG$2,0)),Inputs!$B$4:$B$150,$B50)/1000) -> 20721 | L50: =IF(SUMPRODUCT((Inputs!$B$4:$B$150=$B50)*ISNUMBER(INDEX(Inputs!$D$4:$AG$150,0,MATCH(L$2,Inputs!$D$2:$AG$2,0))))=0,"",SUMIFS(INDEX(Inputs!$D$4:$AG$150,0,MATCH(L$2,Inputs!$D$2:$AG$2,0)),Inputs!$B$4:$B$150,$B50)/1000) -> 29998 | M50: =IF(COUNT(I50:L50)=4,SUM(I50:L50),"") -> 95171 | N50: =IF(SUMPRODUCT((Inputs!$B$4:$B$150=$B50)*ISNUMBER(INDEX(Inputs!$D$4:$AG$150,0,MATCH(N$2,Inputs!$D$2:$AG$2,0))))=0,"",SUMIFS(INDEX(Inputs!$D$4:$AG$150,0,MATCH(N$2,Inputs!$D$2:$AG$2,0)),Inputs!$B$4:$B$150,$B50)/1000) -> 24160 | O50: =IF(SUMPRODUCT((Inputs!$B$4:$B$150=$B50)*ISNUMBER(INDEX(Inputs!$D$4:$AG$150,0,MATCH(O$2,Inputs!$D$2:$AG$2,0))))=0,"",SUMIFS(INDEX(Inputs!$D$4:$AG$150,0,MATCH(O$2,Inputs!$D$2:$AG$2,0)),Inputs!$B$4:$B$150,$B50)/1000) -> 19881 | P50: =IF(SUMPRODUCT((Inputs!$B$4:$B$150=$B50)*ISNUMBER(INDEX(Inputs!$D$4:$AG$150,0,MATCH(P$2,Inputs!$D$2:$AG$2,0))))=0,"",SUMIFS(INDEX(Inputs!$D$4:$AG$150,0,MATCH(P$2,Inputs!$D$2:$AG$2,0)),Inputs!$B$4:$B$150,$B50)/1000) -> 22956 | Q50: =IF(SUMPRODUCT((Inputs!$B$4:$B$150=$B50)*ISNUMBER(INDEX(Inputs!$D$4:$AG$150,0,MATCH(Q$2,Inputs!$D$2:$AG$2,0))))=0,"",SUMIFS(INDEX(Inputs!$D$4:$AG$150,0,MATCH(Q$2,Inputs!$D$2:$AG$2,0)),Inputs!$B$4:$B$150,$B50)/1000) -> 33916 | R50: =IF(COUNT(N50:Q50)=4,SUM(N50:Q50),"") -> 100913 | S50: =IF(SUMPRODUCT((Inputs!$B$4:$B$150=$B50)*ISNUMBER(INDEX(Inputs!$D$4:$AG$150,0,MATCH(S$2,Inputs!$D$2:$AG$2,0))))=0,"",SUMIFS(INDEX(Inputs!$D$4:$AG$150,0,MATCH(S$2,Inputs!$D$2:$AG$2,0)),Inputs!$B$4:$B$150,$B50)/1000) -> 23636 | T50: =IF(SUMPRODUCT((Inputs!$B$4:$B$150=$B50)*ISNUMBER(INDEX(Inputs!$D$4:$AG$150,0,MATCH(T$2,Inputs!$D$2:$AG$2,0))))=0,"",SUMIFS(INDEX(Inputs!$D$4:$AG$150,0,MATCH(T$2,Inputs!$D$2:$AG$2,0)),Inputs!$B$4:$B$150,$B50)/1000) -> 21448 | U50: =IF(SUMPRODUCT((Inputs!$B$4:$B$150=$B50)*ISNUMBER(INDEX(Inputs!$D$4:$AG$150,0,MATCH(U$2,Inputs!$D$2:$AG$2,0))))=0,"",SUMIFS(INDEX(Inputs!$D$4:$AG$150,0,MATCH(U$2,Inputs!$D$2:$AG$2,0)),Inputs!$B$4:$B$150,$B50)/1000) -> 14736 | V50: =IF(SUMPRODUCT((Inputs!$B$4:$B$150=$B50)*ISNUMBER(INDEX(Inputs!$D$4:$AG$150,0,MATCH(V$2,Inputs!$D$2:$AG$2,0))))=0,"",SUMIFS(INDEX(Inputs!$D$4:$AG$150,0,MATCH(V$2,Inputs!$D$2:$AG$2,0)),Inputs!$B$4:$B$150,$B50)/1000) -> 36330 | W50: =IF(COUNT(S50:V50)=4,SUM(S50:V50),"") -> 96150 | X50: =IF(SUMPRODUCT((Inputs!$B$4:$B$150=$B50)*ISNUMBER(INDEX(Inputs!$D$4:$AG$150,0,MATCH(X$2,Inputs!$D$2:$AG$2,0))))=0,"",SUMIFS(INDEX(Inputs!$D$4:$AG$150,0,MATCH(X$2,Inputs!$D$2:$AG$2,0)),Inputs!$B$4:$B$150,$B50)/1000) -> 24780 | Y50: =IF(SUMPRODUCT((Inputs!$B$4:$B$150=$B50)*ISNUMBER(INDEX(Inputs!$D$4:$AG$150,0,MATCH(Y$2,Inputs!$D$2:$AG$2,0))))=0,"",SUMIFS(INDEX(Inputs!$D$4:$AG$150,0,MATCH(Y$2,Inputs!$D$2:$AG$2,0)),Inputs!$B$4:$B$150,$B50)/1000) -> 23434 | Z50: =IF(SUMPRODUCT((Inputs!$B$4:$B$150=$B50)*ISNUMBER(INDEX(Inputs!$D$4:$AG$150,0,MATCH(Z$2,Inputs!$D$2:$AG$2,0))))=0,"",SUMIFS(INDEX(Inputs!$D$4:$AG$150,0,MATCH(Z$2,Inputs!$D$2:$AG$2,0)),Inputs!$B$4:$B$150,$B50)/1000) -> 27466 | AA50: =IF(SUMPRODUCT((Inputs!$B$4:$B$150=$B50)*ISNUMBER(INDEX(Inputs!$D$4:$AG$150,0,MATCH(AA$2,Inputs!$D$2:$AG$2,0))))=0,"",SUMIFS(INDEX(Inputs!$D$4:$AG$150,0,MATCH(AA$2,Inputs!$D$2:$AG$2,0)),Inputs!$B$4:$B$150,$B50)/1000) -> 42097 | AB50: =IF(COUNT(X50:AA50)=4,SUM(X50:AA50),"") -> 117777 | AC50: =IF(SUMPRODUCT((Inputs!$B$4:$B$150=$B50)*ISNUMBER(INDEX(Inputs!$D$4:$AG$150,0,MATCH(AC$2,Inputs!$D$2:$AG$2,0))))=0,"",SUMIFS(INDEX(Inputs!$D$4:$AG$150,0,MATCH(AC$2,Inputs!$D$2:$AG$2,0)),Inputs!$B$4:$B$150,$B50)/1000) -> 29578 | AD50: =IF(SUMPRODUCT((Inputs!$B$4:$B$150=$B50)*ISNUMBER(INDEX(Inputs!$D$4:$AG$150,0,MATCH(AD$2,Inputs!$D$2:$AG$2,0))))=0,"",SUMIFS(INDEX(Inputs!$D$4:$AG$150,0,MATCH(AD$2,Inputs!$D$2:$AG$2,0)),Inputs!$B$4:$B$150,$B50)/1000) -> 29789 | AE50: =IF(SUMPRODUCT((Inputs!$B$4:$B$150=$B50)*ISNUMBER(INDEX(Inputs!$D$4:$AG$150,0,MATCH(AE$2,Inputs!$D$2:$AG$2,0))))=0,"",SUMIFS(INDEX(Inputs!$D$4:$AG$150,0,MATCH(AE$2,Inputs!$D$2:$AG$2,0)),Inputs!$B$4:$B$150,$B50)/1000) | AF50: =IF(SUMPRODUCT((Inputs!$B$4:$B$150=$B50)*ISNUMBER(INDEX(Inputs!$D$4:$AG$150,0,MATCH(AF$2,Inputs!$D$2:$AG$2,0))))=0,"",SUMIFS(INDEX(Inputs!$D$4:$AG$150,0,MATCH(AF$2,Inputs!$D$2:$AG$2,0)),Inputs!$B$4:$B$150,$B50)/1000) | AG50: =IF(COUNT(AC50:AF50)=4,SUM(AC50:AF50),"")
C52: Drivers de receita (memo) - codigos 45+ [Model, bloco abaixo da receita liquida]
B53: 45 | C53: Receita iPhone (USD; trimestre-calendário; o 3T (jul-set, FQ4) = ano fiscal do 10-K menos 9M do 10-Q de jun) | D53: =IF(SUMPRODUCT((Inputs!$B$4:$B$150=$B53)*ISNUMBER(INDEX(Inputs!$D$4:$AG$150,0,MATCH(D$2,Inputs!$D$2:$AG$2,0))))=0,"",SUMIFS(INDEX(Inputs!$D$4:$AG$150,0,MATCH(D$2,Inputs!$D$2:$AG$2,0)),Inputs!$B$4:$B$150,$B53)/1000) -> 47938 | E53: =IF(SUMPRODUCT((Inputs!$B$4:$B$150=$B53)*ISNUMBER(INDEX(Inputs!$D$4:$AG$150,0,MATCH(E$2,Inputs!$D$2:$AG$2,0))))=0,"",SUMIFS(INDEX(Inputs!$D$4:$AG$150,0,MATCH(E$2,Inputs!$D$2:$AG$2,0)),Inputs!$B$4:$B$150,$B53)/1000) -> 39570 | F53: =IF(SUMPRODUCT((Inputs!$B$4:$B$150=$B53)*ISNUMBER(INDEX(Inputs!$D$4:$AG$150,0,MATCH(F$2,Inputs!$D$2:$AG$2,0))))=0,"",SUMIFS(INDEX(Inputs!$D$4:$AG$150,0,MATCH(F$2,Inputs!$D$2:$AG$2,0)),Inputs!$B$4:$B$150,$B53)/1000) -> 38868 | G53: =IF(SUMPRODUCT((Inputs!$B$4:$B$150=$B53)*ISNUMBER(INDEX(Inputs!$D$4:$AG$150,0,MATCH(G$2,Inputs!$D$2:$AG$2,0))))=0,"",SUMIFS(INDEX(Inputs!$D$4:$AG$150,0,MATCH(G$2,Inputs!$D$2:$AG$2,0)),Inputs!$B$4:$B$150,$B53)/1000) -> 71628 | H53: =IF(COUNT(D53:G53)=4,SUM(D53:G53),"") -> 198004 | I53: =IF(SUMPRODUCT((Inputs!$B$4:$B$150=$B53)*ISNUMBER(INDEX(Inputs!$D$4:$AG$150,0,MATCH(I$2,Inputs!$D$2:$AG$2,0))))=0,"",SUMIFS(INDEX(Inputs!$D$4:$AG$150,0,MATCH(I$2,Inputs!$D$2:$AG$2,0)),Inputs!$B$4:$B$150,$B53)/1000) -> 50570 | J53: =IF(SUMPRODUCT((Inputs!$B$4:$B$150=$B53)*ISNUMBER(INDEX(Inputs!$D$4:$AG$150,0,MATCH(J$2,Inputs!$D$2:$AG$2,0))))=0,"",SUMIFS(INDEX(Inputs!$D$4:$AG$150,0,MATCH(J$2,Inputs!$D$2:$AG$2,0)),Inputs!$B$4:$B$150,$B53)/1000) -> 40665 | K53: =IF(SUMPRODUCT((Inputs!$B$4:$B$150=$B53)*ISNUMBER(INDEX(Inputs!$D$4:$AG$150,0,MATCH(K$2,Inputs!$D$2:$AG$2,0))))=0,"",SUMIFS(INDEX(Inputs!$D$4:$AG$150,0,MATCH(K$2,Inputs!$D$2:$AG$2,0)),Inputs!$B$4:$B$150,$B53)/1000) -> 42626 | L53: =IF(SUMPRODUCT((Inputs!$B$4:$B$150=$B53)*ISNUMBER(INDEX(Inputs!$D$4:$AG$150,0,MATCH(L$2,Inputs!$D$2:$AG$2,0))))=0,"",SUMIFS(INDEX(Inputs!$D$4:$AG$150,0,MATCH(L$2,Inputs!$D$2:$AG$2,0)),Inputs!$B$4:$B$150,$B53)/1000) -> 65775 | M53: =IF(COUNT(I53:L53)=4,SUM(I53:L53),"") -> 199636 | N53: =IF(SUMPRODUCT((Inputs!$B$4:$B$150=$B53)*ISNUMBER(INDEX(Inputs!$D$4:$AG$150,0,MATCH(N$2,Inputs!$D$2:$AG$2,0))))=0,"",SUMIFS(INDEX(Inputs!$D$4:$AG$150,0,MATCH(N$2,Inputs!$D$2:$AG$2,0)),Inputs!$B$4:$B$150,$B53)/1000) -> 51334 | O53: =IF(SUMPRODUCT((Inputs!$B$4:$B$150=$B53)*ISNUMBER(INDEX(Inputs!$D$4:$AG$150,0,MATCH(O$2,Inputs!$D$2:$AG$2,0))))=0,"",SUMIFS(INDEX(Inputs!$D$4:$AG$150,0,MATCH(O$2,Inputs!$D$2:$AG$2,0)),Inputs!$B$4:$B$150,$B53)/1000) -> 39669 | P53: =IF(SUMPRODUCT((Inputs!$B$4:$B$150=$B53)*ISNUMBER(INDEX(Inputs!$D$4:$AG$150,0,MATCH(P$2,Inputs!$D$2:$AG$2,0))))=0,"",SUMIFS(INDEX(Inputs!$D$4:$AG$150,0,MATCH(P$2,Inputs!$D$2:$AG$2,0)),Inputs!$B$4:$B$150,$B53)/1000) -> 43805 | Q53: =IF(SUMPRODUCT((Inputs!$B$4:$B$150=$B53)*ISNUMBER(INDEX(Inputs!$D$4:$AG$150,0,MATCH(Q$2,Inputs!$D$2:$AG$2,0))))=0,"",SUMIFS(INDEX(Inputs!$D$4:$AG$150,0,MATCH(Q$2,Inputs!$D$2:$AG$2,0)),Inputs!$B$4:$B$150,$B53)/1000) -> 69702 | R53: =IF(COUNT(N53:Q53)=4,SUM(N53:Q53),"") -> 204510 | S53: =IF(SUMPRODUCT((Inputs!$B$4:$B$150=$B53)*ISNUMBER(INDEX(Inputs!$D$4:$AG$150,0,MATCH(S$2,Inputs!$D$2:$AG$2,0))))=0,"",SUMIFS(INDEX(Inputs!$D$4:$AG$150,0,MATCH(S$2,Inputs!$D$2:$AG$2,0)),Inputs!$B$4:$B$150,$B53)/1000) -> 45963 | T53: =IF(SUMPRODUCT((Inputs!$B$4:$B$150=$B53)*ISNUMBER(INDEX(Inputs!$D$4:$AG$150,0,MATCH(T$2,Inputs!$D$2:$AG$2,0))))=0,"",SUMIFS(INDEX(Inputs!$D$4:$AG$150,0,MATCH(T$2,Inputs!$D$2:$AG$2,0)),Inputs!$B$4:$B$150,$B53)/1000) -> 39296 | U53: =IF(SUMPRODUCT((Inputs!$B$4:$B$150=$B53)*ISNUMBER(INDEX(Inputs!$D$4:$AG$150,0,MATCH(U$2,Inputs!$D$2:$AG$2,0))))=0,"",SUMIFS(INDEX(Inputs!$D$4:$AG$150,0,MATCH(U$2,Inputs!$D$2:$AG$2,0)),Inputs!$B$4:$B$150,$B53)/1000) -> 46222 | V53: =IF(SUMPRODUCT((Inputs!$B$4:$B$150=$B53)*ISNUMBER(INDEX(Inputs!$D$4:$AG$150,0,MATCH(V$2,Inputs!$D$2:$AG$2,0))))=0,"",SUMIFS(INDEX(Inputs!$D$4:$AG$150,0,MATCH(V$2,Inputs!$D$2:$AG$2,0)),Inputs!$B$4:$B$150,$B53)/1000) -> 69138 | W53: =IF(COUNT(S53:V53)=4,SUM(S53:V53),"") -> 200619 | X53: =IF(SUMPRODUCT((Inputs!$B$4:$B$150=$B53)*ISNUMBER(INDEX(Inputs!$D$4:$AG$150,0,MATCH(X$2,Inputs!$D$2:$AG$2,0))))=0,"",SUMIFS(INDEX(Inputs!$D$4:$AG$150,0,MATCH(X$2,Inputs!$D$2:$AG$2,0)),Inputs!$B$4:$B$150,$B53)/1000) -> 46841 | Y53: =IF(SUMPRODUCT((Inputs!$B$4:$B$150=$B53)*ISNUMBER(INDEX(Inputs!$D$4:$AG$150,0,MATCH(Y$2,Inputs!$D$2:$AG$2,0))))=0,"",SUMIFS(INDEX(Inputs!$D$4:$AG$150,0,MATCH(Y$2,Inputs!$D$2:$AG$2,0)),Inputs!$B$4:$B$150,$B53)/1000) -> 44582 | Z53: =IF(SUMPRODUCT((Inputs!$B$4:$B$150=$B53)*ISNUMBER(INDEX(Inputs!$D$4:$AG$150,0,MATCH(Z$2,Inputs!$D$2:$AG$2,0))))=0,"",SUMIFS(INDEX(Inputs!$D$4:$AG$150,0,MATCH(Z$2,Inputs!$D$2:$AG$2,0)),Inputs!$B$4:$B$150,$B53)/1000) -> 49025 | AA53: =IF(SUMPRODUCT((Inputs!$B$4:$B$150=$B53)*ISNUMBER(INDEX(Inputs!$D$4:$AG$150,0,MATCH(AA$2,Inputs!$D$2:$AG$2,0))))=0,"",SUMIFS(INDEX(Inputs!$D$4:$AG$150,0,MATCH(AA$2,Inputs!$D$2:$AG$2,0)),Inputs!$B$4:$B$150,$B53)/1000) -> 85269 | AB53: =IF(COUNT(X53:AA53)=4,SUM(X53:AA53),"") -> 225717 | AC53: =IF(SUMPRODUCT((Inputs!$B$4:$B$150=$B53)*ISNUMBER(INDEX(Inputs!$D$4:$AG$150,0,MATCH(AC$2,Inputs!$D$2:$AG$2,0))))=0,"",SUMIFS(INDEX(Inputs!$D$4:$AG$150,0,MATCH(AC$2,Inputs!$D$2:$AG$2,0)),Inputs!$B$4:$B$150,$B53)/1000) -> 56994 | AD53: =IF(SUMPRODUCT((Inputs!$B$4:$B$150=$B53)*ISNUMBER(INDEX(Inputs!$D$4:$AG$150,0,MATCH(AD$2,Inputs!$D$2:$AG$2,0))))=0,"",SUMIFS(INDEX(Inputs!$D$4:$AG$150,0,MATCH(AD$2,Inputs!$D$2:$AG$2,0)),Inputs!$B$4:$B$150,$B53)/1000) -> 54252 | AE53: =IF(SUMPRODUCT((Inputs!$B$4:$B$150=$B53)*ISNUMBER(INDEX(Inputs!$D$4:$AG$150,0,MATCH(AE$2,Inputs!$D$2:$AG$2,0))))=0,"",SUMIFS(INDEX(Inputs!$D$4:$AG$150,0,MATCH(AE$2,Inputs!$D$2:$AG$2,0)),Inputs!$B$4:$B$150,$B53)/1000) | AF53: =IF(SUMPRODUCT((Inputs!$B$4:$B$150=$B53)*ISNUMBER(INDEX(Inputs!$D$4:$AG$150,0,MATCH(AF$2,Inputs!$D$2:$AG$2,0))))=0,"",SUMIFS(INDEX(Inputs!$D$4:$AG$150,0,MATCH(AF$2,Inputs!$D$2:$AG$2,0)),Inputs!$B$4:$B$150,$B53)/1000) | AG53: =IF(COUNT(AC53:AF53)=4,SUM(AC53:AF53),"")
B54: 46 | C54: Receita Mac (USD) | D54: =IF(SUMPRODUCT((Inputs!$B$4:$B$150=$B54)*ISNUMBER(INDEX(Inputs!$D$4:$AG$150,0,MATCH(D$2,Inputs!$D$2:$AG$2,0))))=0,"",SUMIFS(INDEX(Inputs!$D$4:$AG$150,0,MATCH(D$2,Inputs!$D$2:$AG$2,0)),Inputs!$B$4:$B$150,$B54)/1000) -> 9102 | E54: =IF(SUMPRODUCT((Inputs!$B$4:$B$150=$B54)*ISNUMBER(INDEX(Inputs!$D$4:$AG$150,0,MATCH(E$2,Inputs!$D$2:$AG$2,0))))=0,"",SUMIFS(INDEX(Inputs!$D$4:$AG$150,0,MATCH(E$2,Inputs!$D$2:$AG$2,0)),Inputs!$B$4:$B$150,$B54)/1000) -> 8235 | F54: =IF(SUMPRODUCT((Inputs!$B$4:$B$150=$B54)*ISNUMBER(INDEX(Inputs!$D$4:$AG$150,0,MATCH(F$2,Inputs!$D$2:$AG$2,0))))=0,"",SUMIFS(INDEX(Inputs!$D$4:$AG$150,0,MATCH(F$2,Inputs!$D$2:$AG$2,0)),Inputs!$B$4:$B$150,$B54)/1000) -> 9178 | G54: =IF(SUMPRODUCT((Inputs!$B$4:$B$150=$B54)*ISNUMBER(INDEX(Inputs!$D$4:$AG$150,0,MATCH(G$2,Inputs!$D$2:$AG$2,0))))=0,"",SUMIFS(INDEX(Inputs!$D$4:$AG$150,0,MATCH(G$2,Inputs!$D$2:$AG$2,0)),Inputs!$B$4:$B$150,$B54)/1000) -> 10852 | H54: =IF(COUNT(D54:G54)=4,SUM(D54:G54),"") -> 37367 | I54: =IF(SUMPRODUCT((Inputs!$B$4:$B$150=$B54)*ISNUMBER(INDEX(Inputs!$D$4:$AG$150,0,MATCH(I$2,Inputs!$D$2:$AG$2,0))))=0,"",SUMIFS(INDEX(Inputs!$D$4:$AG$150,0,MATCH(I$2,Inputs!$D$2:$AG$2,0)),Inputs!$B$4:$B$150,$B54)/1000) -> 10435 | J54: =IF(SUMPRODUCT((Inputs!$B$4:$B$150=$B54)*ISNUMBER(INDEX(Inputs!$D$4:$AG$150,0,MATCH(J$2,Inputs!$D$2:$AG$2,0))))=0,"",SUMIFS(INDEX(Inputs!$D$4:$AG$150,0,MATCH(J$2,Inputs!$D$2:$AG$2,0)),Inputs!$B$4:$B$150,$B54)/1000) -> 7382 | K54: =IF(SUMPRODUCT((Inputs!$B$4:$B$150=$B54)*ISNUMBER(INDEX(Inputs!$D$4:$AG$150,0,MATCH(K$2,Inputs!$D$2:$AG$2,0))))=0,"",SUMIFS(INDEX(Inputs!$D$4:$AG$150,0,MATCH(K$2,Inputs!$D$2:$AG$2,0)),Inputs!$B$4:$B$150,$B54)/1000) -> 11508 | L54: =IF(SUMPRODUCT((Inputs!$B$4:$B$150=$B54)*ISNUMBER(INDEX(Inputs!$D$4:$AG$150,0,MATCH(L$2,Inputs!$D$2:$AG$2,0))))=0,"",SUMIFS(INDEX(Inputs!$D$4:$AG$150,0,MATCH(L$2,Inputs!$D$2:$AG$2,0)),Inputs!$B$4:$B$150,$B54)/1000) -> 7735 | M54: =IF(COUNT(I54:L54)=4,SUM(I54:L54),"") -> 37060 | N54: =IF(SUMPRODUCT((Inputs!$B$4:$B$150=$B54)*ISNUMBER(INDEX(Inputs!$D$4:$AG$150,0,MATCH(N$2,Inputs!$D$2:$AG$2,0))))=0,"",SUMIFS(INDEX(Inputs!$D$4:$AG$150,0,MATCH(N$2,Inputs!$D$2:$AG$2,0)),Inputs!$B$4:$B$150,$B54)/1000) -> 7168 | O54: =IF(SUMPRODUCT((Inputs!$B$4:$B$150=$B54)*ISNUMBER(INDEX(Inputs!$D$4:$AG$150,0,MATCH(O$2,Inputs!$D$2:$AG$2,0))))=0,"",SUMIFS(INDEX(Inputs!$D$4:$AG$150,0,MATCH(O$2,Inputs!$D$2:$AG$2,0)),Inputs!$B$4:$B$150,$B54)/1000) -> 6840 | P54: =IF(SUMPRODUCT((Inputs!$B$4:$B$150=$B54)*ISNUMBER(INDEX(Inputs!$D$4:$AG$150,0,MATCH(P$2,Inputs!$D$2:$AG$2,0))))=0,"",SUMIFS(INDEX(Inputs!$D$4:$AG$150,0,MATCH(P$2,Inputs!$D$2:$AG$2,0)),Inputs!$B$4:$B$150,$B54)/1000) -> 7614 | Q54: =IF(SUMPRODUCT((Inputs!$B$4:$B$150=$B54)*ISNUMBER(INDEX(Inputs!$D$4:$AG$150,0,MATCH(Q$2,Inputs!$D$2:$AG$2,0))))=0,"",SUMIFS(INDEX(Inputs!$D$4:$AG$150,0,MATCH(Q$2,Inputs!$D$2:$AG$2,0)),Inputs!$B$4:$B$150,$B54)/1000) -> 7780 | R54: =IF(COUNT(N54:Q54)=4,SUM(N54:Q54),"") -> 29402 | S54: =IF(SUMPRODUCT((Inputs!$B$4:$B$150=$B54)*ISNUMBER(INDEX(Inputs!$D$4:$AG$150,0,MATCH(S$2,Inputs!$D$2:$AG$2,0))))=0,"",SUMIFS(INDEX(Inputs!$D$4:$AG$150,0,MATCH(S$2,Inputs!$D$2:$AG$2,0)),Inputs!$B$4:$B$150,$B54)/1000) -> 7451 | T54: =IF(SUMPRODUCT((Inputs!$B$4:$B$150=$B54)*ISNUMBER(INDEX(Inputs!$D$4:$AG$150,0,MATCH(T$2,Inputs!$D$2:$AG$2,0))))=0,"",SUMIFS(INDEX(Inputs!$D$4:$AG$150,0,MATCH(T$2,Inputs!$D$2:$AG$2,0)),Inputs!$B$4:$B$150,$B54)/1000) -> 7009 | U54: =IF(SUMPRODUCT((Inputs!$B$4:$B$150=$B54)*ISNUMBER(INDEX(Inputs!$D$4:$AG$150,0,MATCH(U$2,Inputs!$D$2:$AG$2,0))))=0,"",SUMIFS(INDEX(Inputs!$D$4:$AG$150,0,MATCH(U$2,Inputs!$D$2:$AG$2,0)),Inputs!$B$4:$B$150,$B54)/1000) -> 7744 | V54: =IF(SUMPRODUCT((Inputs!$B$4:$B$150=$B54)*ISNUMBER(INDEX(Inputs!$D$4:$AG$150,0,MATCH(V$2,Inputs!$D$2:$AG$2,0))))=0,"",SUMIFS(INDEX(Inputs!$D$4:$AG$150,0,MATCH(V$2,Inputs!$D$2:$AG$2,0)),Inputs!$B$4:$B$150,$B54)/1000) -> 8987 | W54: =IF(COUNT(S54:V54)=4,SUM(S54:V54),"") -> 31191 | X54: =IF(SUMPRODUCT((Inputs!$B$4:$B$150=$B54)*ISNUMBER(INDEX(Inputs!$D$4:$AG$150,0,MATCH(X$2,Inputs!$D$2:$AG$2,0))))=0,"",SUMIFS(INDEX(Inputs!$D$4:$AG$150,0,MATCH(X$2,Inputs!$D$2:$AG$2,0)),Inputs!$B$4:$B$150,$B54)/1000) -> 7949 | Y54: =IF(SUMPRODUCT((Inputs!$B$4:$B$150=$B54)*ISNUMBER(INDEX(Inputs!$D$4:$AG$150,0,MATCH(Y$2,Inputs!$D$2:$AG$2,0))))=0,"",SUMIFS(INDEX(Inputs!$D$4:$AG$150,0,MATCH(Y$2,Inputs!$D$2:$AG$2,0)),Inputs!$B$4:$B$150,$B54)/1000) -> 8046 | Z54: =IF(SUMPRODUCT((Inputs!$B$4:$B$150=$B54)*ISNUMBER(INDEX(Inputs!$D$4:$AG$150,0,MATCH(Z$2,Inputs!$D$2:$AG$2,0))))=0,"",SUMIFS(INDEX(Inputs!$D$4:$AG$150,0,MATCH(Z$2,Inputs!$D$2:$AG$2,0)),Inputs!$B$4:$B$150,$B54)/1000) -> 8726 | AA54: =IF(SUMPRODUCT((Inputs!$B$4:$B$150=$B54)*ISNUMBER(INDEX(Inputs!$D$4:$AG$150,0,MATCH(AA$2,Inputs!$D$2:$AG$2,0))))=0,"",SUMIFS(INDEX(Inputs!$D$4:$AG$150,0,MATCH(AA$2,Inputs!$D$2:$AG$2,0)),Inputs!$B$4:$B$150,$B54)/1000) -> 8386 | AB54: =IF(COUNT(X54:AA54)=4,SUM(X54:AA54),"") -> 33107 | AC54: =IF(SUMPRODUCT((Inputs!$B$4:$B$150=$B54)*ISNUMBER(INDEX(Inputs!$D$4:$AG$150,0,MATCH(AC$2,Inputs!$D$2:$AG$2,0))))=0,"",SUMIFS(INDEX(Inputs!$D$4:$AG$150,0,MATCH(AC$2,Inputs!$D$2:$AG$2,0)),Inputs!$B$4:$B$150,$B54)/1000) -> 8399 | AD54: =IF(SUMPRODUCT((Inputs!$B$4:$B$150=$B54)*ISNUMBER(INDEX(Inputs!$D$4:$AG$150,0,MATCH(AD$2,Inputs!$D$2:$AG$2,0))))=0,"",SUMIFS(INDEX(Inputs!$D$4:$AG$150,0,MATCH(AD$2,Inputs!$D$2:$AG$2,0)),Inputs!$B$4:$B$150,$B54)/1000) -> 10352 | AE54: =IF(SUMPRODUCT((Inputs!$B$4:$B$150=$B54)*ISNUMBER(INDEX(Inputs!$D$4:$AG$150,0,MATCH(AE$2,Inputs!$D$2:$AG$2,0))))=0,"",SUMIFS(INDEX(Inputs!$D$4:$AG$150,0,MATCH(AE$2,Inputs!$D$2:$AG$2,0)),Inputs!$B$4:$B$150,$B54)/1000) | AF54: =IF(SUMPRODUCT((Inputs!$B$4:$B$150=$B54)*ISNUMBER(INDEX(Inputs!$D$4:$AG$150,0,MATCH(AF$2,Inputs!$D$2:$AG$2,0))))=0,"",SUMIFS(INDEX(Inputs!$D$4:$AG$150,0,MATCH(AF$2,Inputs!$D$2:$AG$2,0)),Inputs!$B$4:$B$150,$B54)/1000) | AG54: =IF(COUNT(AC54:AF54)=4,SUM(AC54:AF54),"")
B55: 47 | C55: Receita iPad (USD) | D55: =IF(SUMPRODUCT((Inputs!$B$4:$B$150=$B55)*ISNUMBER(INDEX(Inputs!$D$4:$AG$150,0,MATCH(D$2,Inputs!$D$2:$AG$2,0))))=0,"",SUMIFS(INDEX(Inputs!$D$4:$AG$150,0,MATCH(D$2,Inputs!$D$2:$AG$2,0)),Inputs!$B$4:$B$150,$B55)/1000) -> 7807 | E55: =IF(SUMPRODUCT((Inputs!$B$4:$B$150=$B55)*ISNUMBER(INDEX(Inputs!$D$4:$AG$150,0,MATCH(E$2,Inputs!$D$2:$AG$2,0))))=0,"",SUMIFS(INDEX(Inputs!$D$4:$AG$150,0,MATCH(E$2,Inputs!$D$2:$AG$2,0)),Inputs!$B$4:$B$150,$B55)/1000) -> 7368 | F55: =IF(SUMPRODUCT((Inputs!$B$4:$B$150=$B55)*ISNUMBER(INDEX(Inputs!$D$4:$AG$150,0,MATCH(F$2,Inputs!$D$2:$AG$2,0))))=0,"",SUMIFS(INDEX(Inputs!$D$4:$AG$150,0,MATCH(F$2,Inputs!$D$2:$AG$2,0)),Inputs!$B$4:$B$150,$B55)/1000) -> 8252 | G55: =IF(SUMPRODUCT((Inputs!$B$4:$B$150=$B55)*ISNUMBER(INDEX(Inputs!$D$4:$AG$150,0,MATCH(G$2,Inputs!$D$2:$AG$2,0))))=0,"",SUMIFS(INDEX(Inputs!$D$4:$AG$150,0,MATCH(G$2,Inputs!$D$2:$AG$2,0)),Inputs!$B$4:$B$150,$B55)/1000) -> 7248 | H55: =IF(COUNT(D55:G55)=4,SUM(D55:G55),"") -> 30675 | I55: =IF(SUMPRODUCT((Inputs!$B$4:$B$150=$B55)*ISNUMBER(INDEX(Inputs!$D$4:$AG$150,0,MATCH(I$2,Inputs!$D$2:$AG$2,0))))=0,"",SUMIFS(INDEX(Inputs!$D$4:$AG$150,0,MATCH(I$2,Inputs!$D$2:$AG$2,0)),Inputs!$B$4:$B$150,$B55)/1000) -> 7646 | J55: =IF(SUMPRODUCT((Inputs!$B$4:$B$150=$B55)*ISNUMBER(INDEX(Inputs!$D$4:$AG$150,0,MATCH(J$2,Inputs!$D$2:$AG$2,0))))=0,"",SUMIFS(INDEX(Inputs!$D$4:$AG$150,0,MATCH(J$2,Inputs!$D$2:$AG$2,0)),Inputs!$B$4:$B$150,$B55)/1000) -> 7224 | K55: =IF(SUMPRODUCT((Inputs!$B$4:$B$150=$B55)*ISNUMBER(INDEX(Inputs!$D$4:$AG$150,0,MATCH(K$2,Inputs!$D$2:$AG$2,0))))=0,"",SUMIFS(INDEX(Inputs!$D$4:$AG$150,0,MATCH(K$2,Inputs!$D$2:$AG$2,0)),Inputs!$B$4:$B$150,$B55)/1000) -> 7174 | L55: =IF(SUMPRODUCT((Inputs!$B$4:$B$150=$B55)*ISNUMBER(INDEX(Inputs!$D$4:$AG$150,0,MATCH(L$2,Inputs!$D$2:$AG$2,0))))=0,"",SUMIFS(INDEX(Inputs!$D$4:$AG$150,0,MATCH(L$2,Inputs!$D$2:$AG$2,0)),Inputs!$B$4:$B$150,$B55)/1000) -> 9396 | M55: =IF(COUNT(I55:L55)=4,SUM(I55:L55),"") -> 31440 | N55: =IF(SUMPRODUCT((Inputs!$B$4:$B$150=$B55)*ISNUMBER(INDEX(Inputs!$D$4:$AG$150,0,MATCH(N$2,Inputs!$D$2:$AG$2,0))))=0,"",SUMIFS(INDEX(Inputs!$D$4:$AG$150,0,MATCH(N$2,Inputs!$D$2:$AG$2,0)),Inputs!$B$4:$B$150,$B55)/1000) -> 6670 | O55: =IF(SUMPRODUCT((Inputs!$B$4:$B$150=$B55)*ISNUMBER(INDEX(Inputs!$D$4:$AG$150,0,MATCH(O$2,Inputs!$D$2:$AG$2,0))))=0,"",SUMIFS(INDEX(Inputs!$D$4:$AG$150,0,MATCH(O$2,Inputs!$D$2:$AG$2,0)),Inputs!$B$4:$B$150,$B55)/1000) -> 5791 | P55: =IF(SUMPRODUCT((Inputs!$B$4:$B$150=$B55)*ISNUMBER(INDEX(Inputs!$D$4:$AG$150,0,MATCH(P$2,Inputs!$D$2:$AG$2,0))))=0,"",SUMIFS(INDEX(Inputs!$D$4:$AG$150,0,MATCH(P$2,Inputs!$D$2:$AG$2,0)),Inputs!$B$4:$B$150,$B55)/1000) -> 6443 | Q55: =IF(SUMPRODUCT((Inputs!$B$4:$B$150=$B55)*ISNUMBER(INDEX(Inputs!$D$4:$AG$150,0,MATCH(Q$2,Inputs!$D$2:$AG$2,0))))=0,"",SUMIFS(INDEX(Inputs!$D$4:$AG$150,0,MATCH(Q$2,Inputs!$D$2:$AG$2,0)),Inputs!$B$4:$B$150,$B55)/1000) -> 7023 | R55: =IF(COUNT(N55:Q55)=4,SUM(N55:Q55),"") -> 25927 | S55: =IF(SUMPRODUCT((Inputs!$B$4:$B$150=$B55)*ISNUMBER(INDEX(Inputs!$D$4:$AG$150,0,MATCH(S$2,Inputs!$D$2:$AG$2,0))))=0,"",SUMIFS(INDEX(Inputs!$D$4:$AG$150,0,MATCH(S$2,Inputs!$D$2:$AG$2,0)),Inputs!$B$4:$B$150,$B55)/1000) -> 5559 | T55: =IF(SUMPRODUCT((Inputs!$B$4:$B$150=$B55)*ISNUMBER(INDEX(Inputs!$D$4:$AG$150,0,MATCH(T$2,Inputs!$D$2:$AG$2,0))))=0,"",SUMIFS(INDEX(Inputs!$D$4:$AG$150,0,MATCH(T$2,Inputs!$D$2:$AG$2,0)),Inputs!$B$4:$B$150,$B55)/1000) -> 7162 | U55: =IF(SUMPRODUCT((Inputs!$B$4:$B$150=$B55)*ISNUMBER(INDEX(Inputs!$D$4:$AG$150,0,MATCH(U$2,Inputs!$D$2:$AG$2,0))))=0,"",SUMIFS(INDEX(Inputs!$D$4:$AG$150,0,MATCH(U$2,Inputs!$D$2:$AG$2,0)),Inputs!$B$4:$B$150,$B55)/1000) -> 6950 | V55: =IF(SUMPRODUCT((Inputs!$B$4:$B$150=$B55)*ISNUMBER(INDEX(Inputs!$D$4:$AG$150,0,MATCH(V$2,Inputs!$D$2:$AG$2,0))))=0,"",SUMIFS(INDEX(Inputs!$D$4:$AG$150,0,MATCH(V$2,Inputs!$D$2:$AG$2,0)),Inputs!$B$4:$B$150,$B55)/1000) -> 8088 | W55: =IF(COUNT(S55:V55)=4,SUM(S55:V55),"") -> 27759 | X55: =IF(SUMPRODUCT((Inputs!$B$4:$B$150=$B55)*ISNUMBER(INDEX(Inputs!$D$4:$AG$150,0,MATCH(X$2,Inputs!$D$2:$AG$2,0))))=0,"",SUMIFS(INDEX(Inputs!$D$4:$AG$150,0,MATCH(X$2,Inputs!$D$2:$AG$2,0)),Inputs!$B$4:$B$150,$B55)/1000) -> 6402 | Y55: =IF(SUMPRODUCT((Inputs!$B$4:$B$150=$B55)*ISNUMBER(INDEX(Inputs!$D$4:$AG$150,0,MATCH(Y$2,Inputs!$D$2:$AG$2,0))))=0,"",SUMIFS(INDEX(Inputs!$D$4:$AG$150,0,MATCH(Y$2,Inputs!$D$2:$AG$2,0)),Inputs!$B$4:$B$150,$B55)/1000) -> 6581 | Z55: =IF(SUMPRODUCT((Inputs!$B$4:$B$150=$B55)*ISNUMBER(INDEX(Inputs!$D$4:$AG$150,0,MATCH(Z$2,Inputs!$D$2:$AG$2,0))))=0,"",SUMIFS(INDEX(Inputs!$D$4:$AG$150,0,MATCH(Z$2,Inputs!$D$2:$AG$2,0)),Inputs!$B$4:$B$150,$B55)/1000) -> 6952 | AA55: =IF(SUMPRODUCT((Inputs!$B$4:$B$150=$B55)*ISNUMBER(INDEX(Inputs!$D$4:$AG$150,0,MATCH(AA$2,Inputs!$D$2:$AG$2,0))))=0,"",SUMIFS(INDEX(Inputs!$D$4:$AG$150,0,MATCH(AA$2,Inputs!$D$2:$AG$2,0)),Inputs!$B$4:$B$150,$B55)/1000) -> 8595 | AB55: =IF(COUNT(X55:AA55)=4,SUM(X55:AA55),"") -> 28530 | AC55: =IF(SUMPRODUCT((Inputs!$B$4:$B$150=$B55)*ISNUMBER(INDEX(Inputs!$D$4:$AG$150,0,MATCH(AC$2,Inputs!$D$2:$AG$2,0))))=0,"",SUMIFS(INDEX(Inputs!$D$4:$AG$150,0,MATCH(AC$2,Inputs!$D$2:$AG$2,0)),Inputs!$B$4:$B$150,$B55)/1000) -> 6914 | AD55: =IF(SUMPRODUCT((Inputs!$B$4:$B$150=$B55)*ISNUMBER(INDEX(Inputs!$D$4:$AG$150,0,MATCH(AD$2,Inputs!$D$2:$AG$2,0))))=0,"",SUMIFS(INDEX(Inputs!$D$4:$AG$150,0,MATCH(AD$2,Inputs!$D$2:$AG$2,0)),Inputs!$B$4:$B$150,$B55)/1000) -> 6191 | AE55: =IF(SUMPRODUCT((Inputs!$B$4:$B$150=$B55)*ISNUMBER(INDEX(Inputs!$D$4:$AG$150,0,MATCH(AE$2,Inputs!$D$2:$AG$2,0))))=0,"",SUMIFS(INDEX(Inputs!$D$4:$AG$150,0,MATCH(AE$2,Inputs!$D$2:$AG$2,0)),Inputs!$B$4:$B$150,$B55)/1000) | AF55: =IF(SUMPRODUCT((Inputs!$B$4:$B$150=$B55)*ISNUMBER(INDEX(Inputs!$D$4:$AG$150,0,MATCH(AF$2,Inputs!$D$2:$AG$2,0))))=0,"",SUMIFS(INDEX(Inputs!$D$4:$AG$150,0,MATCH(AF$2,Inputs!$D$2:$AG$2,0)),Inputs!$B$4:$B$150,$B55)/1000) | AG55: =IF(COUNT(AC55:AF55)=4,SUM(AC55:AF55),"")
B56: 48 | C56: Receita Wearables, Home and Accessories (USD) | D56: =IF(SUMPRODUCT((Inputs!$B$4:$B$150=$B56)*ISNUMBER(INDEX(Inputs!$D$4:$AG$150,0,MATCH(D$2,Inputs!$D$2:$AG$2,0))))=0,"",SUMIFS(INDEX(Inputs!$D$4:$AG$150,0,MATCH(D$2,Inputs!$D$2:$AG$2,0)),Inputs!$B$4:$B$150,$B56)/1000) -> 7836 | E56: =IF(SUMPRODUCT((Inputs!$B$4:$B$150=$B56)*ISNUMBER(INDEX(Inputs!$D$4:$AG$150,0,MATCH(E$2,Inputs!$D$2:$AG$2,0))))=0,"",SUMIFS(INDEX(Inputs!$D$4:$AG$150,0,MATCH(E$2,Inputs!$D$2:$AG$2,0)),Inputs!$B$4:$B$150,$B56)/1000) -> 8775 | F56: =IF(SUMPRODUCT((Inputs!$B$4:$B$150=$B56)*ISNUMBER(INDEX(Inputs!$D$4:$AG$150,0,MATCH(F$2,Inputs!$D$2:$AG$2,0))))=0,"",SUMIFS(INDEX(Inputs!$D$4:$AG$150,0,MATCH(F$2,Inputs!$D$2:$AG$2,0)),Inputs!$B$4:$B$150,$B56)/1000) -> 8785 | G56: =IF(SUMPRODUCT((Inputs!$B$4:$B$150=$B56)*ISNUMBER(INDEX(Inputs!$D$4:$AG$150,0,MATCH(G$2,Inputs!$D$2:$AG$2,0))))=0,"",SUMIFS(INDEX(Inputs!$D$4:$AG$150,0,MATCH(G$2,Inputs!$D$2:$AG$2,0)),Inputs!$B$4:$B$150,$B56)/1000) -> 14701 | H56: =IF(COUNT(D56:G56)=4,SUM(D56:G56),"") -> 40097 | I56: =IF(SUMPRODUCT((Inputs!$B$4:$B$150=$B56)*ISNUMBER(INDEX(Inputs!$D$4:$AG$150,0,MATCH(I$2,Inputs!$D$2:$AG$2,0))))=0,"",SUMIFS(INDEX(Inputs!$D$4:$AG$150,0,MATCH(I$2,Inputs!$D$2:$AG$2,0)),Inputs!$B$4:$B$150,$B56)/1000) -> 8806 | J56: =IF(SUMPRODUCT((Inputs!$B$4:$B$150=$B56)*ISNUMBER(INDEX(Inputs!$D$4:$AG$150,0,MATCH(J$2,Inputs!$D$2:$AG$2,0))))=0,"",SUMIFS(INDEX(Inputs!$D$4:$AG$150,0,MATCH(J$2,Inputs!$D$2:$AG$2,0)),Inputs!$B$4:$B$150,$B56)/1000) -> 8084 | K56: =IF(SUMPRODUCT((Inputs!$B$4:$B$150=$B56)*ISNUMBER(INDEX(Inputs!$D$4:$AG$150,0,MATCH(K$2,Inputs!$D$2:$AG$2,0))))=0,"",SUMIFS(INDEX(Inputs!$D$4:$AG$150,0,MATCH(K$2,Inputs!$D$2:$AG$2,0)),Inputs!$B$4:$B$150,$B56)/1000) -> 9650 | L56: =IF(SUMPRODUCT((Inputs!$B$4:$B$150=$B56)*ISNUMBER(INDEX(Inputs!$D$4:$AG$150,0,MATCH(L$2,Inputs!$D$2:$AG$2,0))))=0,"",SUMIFS(INDEX(Inputs!$D$4:$AG$150,0,MATCH(L$2,Inputs!$D$2:$AG$2,0)),Inputs!$B$4:$B$150,$B56)/1000) -> 13482 | M56: =IF(COUNT(I56:L56)=4,SUM(I56:L56),"") -> 40022 | N56: =IF(SUMPRODUCT((Inputs!$B$4:$B$150=$B56)*ISNUMBER(INDEX(Inputs!$D$4:$AG$150,0,MATCH(N$2,Inputs!$D$2:$AG$2,0))))=0,"",SUMIFS(INDEX(Inputs!$D$4:$AG$150,0,MATCH(N$2,Inputs!$D$2:$AG$2,0)),Inputs!$B$4:$B$150,$B56)/1000) -> 8757 | O56: =IF(SUMPRODUCT((Inputs!$B$4:$B$150=$B56)*ISNUMBER(INDEX(Inputs!$D$4:$AG$150,0,MATCH(O$2,Inputs!$D$2:$AG$2,0))))=0,"",SUMIFS(INDEX(Inputs!$D$4:$AG$150,0,MATCH(O$2,Inputs!$D$2:$AG$2,0)),Inputs!$B$4:$B$150,$B56)/1000) -> 8284 | P56: =IF(SUMPRODUCT((Inputs!$B$4:$B$150=$B56)*ISNUMBER(INDEX(Inputs!$D$4:$AG$150,0,MATCH(P$2,Inputs!$D$2:$AG$2,0))))=0,"",SUMIFS(INDEX(Inputs!$D$4:$AG$150,0,MATCH(P$2,Inputs!$D$2:$AG$2,0)),Inputs!$B$4:$B$150,$B56)/1000) -> 9322 | Q56: =IF(SUMPRODUCT((Inputs!$B$4:$B$150=$B56)*ISNUMBER(INDEX(Inputs!$D$4:$AG$150,0,MATCH(Q$2,Inputs!$D$2:$AG$2,0))))=0,"",SUMIFS(INDEX(Inputs!$D$4:$AG$150,0,MATCH(Q$2,Inputs!$D$2:$AG$2,0)),Inputs!$B$4:$B$150,$B56)/1000) -> 11953 | R56: =IF(COUNT(N56:Q56)=4,SUM(N56:Q56),"") -> 38316 | S56: =IF(SUMPRODUCT((Inputs!$B$4:$B$150=$B56)*ISNUMBER(INDEX(Inputs!$D$4:$AG$150,0,MATCH(S$2,Inputs!$D$2:$AG$2,0))))=0,"",SUMIFS(INDEX(Inputs!$D$4:$AG$150,0,MATCH(S$2,Inputs!$D$2:$AG$2,0)),Inputs!$B$4:$B$150,$B56)/1000) -> 7913 | T56: =IF(SUMPRODUCT((Inputs!$B$4:$B$150=$B56)*ISNUMBER(INDEX(Inputs!$D$4:$AG$150,0,MATCH(T$2,Inputs!$D$2:$AG$2,0))))=0,"",SUMIFS(INDEX(Inputs!$D$4:$AG$150,0,MATCH(T$2,Inputs!$D$2:$AG$2,0)),Inputs!$B$4:$B$150,$B56)/1000) -> 8097 | U56: =IF(SUMPRODUCT((Inputs!$B$4:$B$150=$B56)*ISNUMBER(INDEX(Inputs!$D$4:$AG$150,0,MATCH(U$2,Inputs!$D$2:$AG$2,0))))=0,"",SUMIFS(INDEX(Inputs!$D$4:$AG$150,0,MATCH(U$2,Inputs!$D$2:$AG$2,0)),Inputs!$B$4:$B$150,$B56)/1000) -> 9042 | V56: =IF(SUMPRODUCT((Inputs!$B$4:$B$150=$B56)*ISNUMBER(INDEX(Inputs!$D$4:$AG$150,0,MATCH(V$2,Inputs!$D$2:$AG$2,0))))=0,"",SUMIFS(INDEX(Inputs!$D$4:$AG$150,0,MATCH(V$2,Inputs!$D$2:$AG$2,0)),Inputs!$B$4:$B$150,$B56)/1000) -> 11747 | W56: =IF(COUNT(S56:V56)=4,SUM(S56:V56),"") -> 36799 | X56: =IF(SUMPRODUCT((Inputs!$B$4:$B$150=$B56)*ISNUMBER(INDEX(Inputs!$D$4:$AG$150,0,MATCH(X$2,Inputs!$D$2:$AG$2,0))))=0,"",SUMIFS(INDEX(Inputs!$D$4:$AG$150,0,MATCH(X$2,Inputs!$D$2:$AG$2,0)),Inputs!$B$4:$B$150,$B56)/1000) -> 7522 | Y56: =IF(SUMPRODUCT((Inputs!$B$4:$B$150=$B56)*ISNUMBER(INDEX(Inputs!$D$4:$AG$150,0,MATCH(Y$2,Inputs!$D$2:$AG$2,0))))=0,"",SUMIFS(INDEX(Inputs!$D$4:$AG$150,0,MATCH(Y$2,Inputs!$D$2:$AG$2,0)),Inputs!$B$4:$B$150,$B56)/1000) -> 7404 | Z56: =IF(SUMPRODUCT((Inputs!$B$4:$B$150=$B56)*ISNUMBER(INDEX(Inputs!$D$4:$AG$150,0,MATCH(Z$2,Inputs!$D$2:$AG$2,0))))=0,"",SUMIFS(INDEX(Inputs!$D$4:$AG$150,0,MATCH(Z$2,Inputs!$D$2:$AG$2,0)),Inputs!$B$4:$B$150,$B56)/1000) -> 9013 | AA56: =IF(SUMPRODUCT((Inputs!$B$4:$B$150=$B56)*ISNUMBER(INDEX(Inputs!$D$4:$AG$150,0,MATCH(AA$2,Inputs!$D$2:$AG$2,0))))=0,"",SUMIFS(INDEX(Inputs!$D$4:$AG$150,0,MATCH(AA$2,Inputs!$D$2:$AG$2,0)),Inputs!$B$4:$B$150,$B56)/1000) -> 11493 | AB56: =IF(COUNT(X56:AA56)=4,SUM(X56:AA56),"") -> 35432 | AC56: =IF(SUMPRODUCT((Inputs!$B$4:$B$150=$B56)*ISNUMBER(INDEX(Inputs!$D$4:$AG$150,0,MATCH(AC$2,Inputs!$D$2:$AG$2,0))))=0,"",SUMIFS(INDEX(Inputs!$D$4:$AG$150,0,MATCH(AC$2,Inputs!$D$2:$AG$2,0)),Inputs!$B$4:$B$150,$B56)/1000) -> 7901 | AD56: =IF(SUMPRODUCT((Inputs!$B$4:$B$150=$B56)*ISNUMBER(INDEX(Inputs!$D$4:$AG$150,0,MATCH(AD$2,Inputs!$D$2:$AG$2,0))))=0,"",SUMIFS(INDEX(Inputs!$D$4:$AG$150,0,MATCH(AD$2,Inputs!$D$2:$AG$2,0)),Inputs!$B$4:$B$150,$B56)/1000) -> 7883 | AE56: =IF(SUMPRODUCT((Inputs!$B$4:$B$150=$B56)*ISNUMBER(INDEX(Inputs!$D$4:$AG$150,0,MATCH(AE$2,Inputs!$D$2:$AG$2,0))))=0,"",SUMIFS(INDEX(Inputs!$D$4:$AG$150,0,MATCH(AE$2,Inputs!$D$2:$AG$2,0)),Inputs!$B$4:$B$150,$B56)/1000) | AF56: =IF(SUMPRODUCT((Inputs!$B$4:$B$150=$B56)*ISNUMBER(INDEX(Inputs!$D$4:$AG$150,0,MATCH(AF$2,Inputs!$D$2:$AG$2,0))))=0,"",SUMIFS(INDEX(Inputs!$D$4:$AG$150,0,MATCH(AF$2,Inputs!$D$2:$AG$2,0)),Inputs!$B$4:$B$150,$B56)/1000) | AG56: =IF(COUNT(AC56:AF56)=4,SUM(AC56:AF56),"")
B57: 49 | C57: Receita Services (USD) | D57: =IF(SUMPRODUCT((Inputs!$B$4:$B$150=$B57)*ISNUMBER(INDEX(Inputs!$D$4:$AG$150,0,MATCH(D$2,Inputs!$D$2:$AG$2,0))))=0,"",SUMIFS(INDEX(Inputs!$D$4:$AG$150,0,MATCH(D$2,Inputs!$D$2:$AG$2,0)),Inputs!$B$4:$B$150,$B57)/1000) -> 16901 | E57: =IF(SUMPRODUCT((Inputs!$B$4:$B$150=$B57)*ISNUMBER(INDEX(Inputs!$D$4:$AG$150,0,MATCH(E$2,Inputs!$D$2:$AG$2,0))))=0,"",SUMIFS(INDEX(Inputs!$D$4:$AG$150,0,MATCH(E$2,Inputs!$D$2:$AG$2,0)),Inputs!$B$4:$B$150,$B57)/1000) -> 17486 | F57: =IF(SUMPRODUCT((Inputs!$B$4:$B$150=$B57)*ISNUMBER(INDEX(Inputs!$D$4:$AG$150,0,MATCH(F$2,Inputs!$D$2:$AG$2,0))))=0,"",SUMIFS(INDEX(Inputs!$D$4:$AG$150,0,MATCH(F$2,Inputs!$D$2:$AG$2,0)),Inputs!$B$4:$B$150,$B57)/1000) -> 18277 | G57: =IF(SUMPRODUCT((Inputs!$B$4:$B$150=$B57)*ISNUMBER(INDEX(Inputs!$D$4:$AG$150,0,MATCH(G$2,Inputs!$D$2:$AG$2,0))))=0,"",SUMIFS(INDEX(Inputs!$D$4:$AG$150,0,MATCH(G$2,Inputs!$D$2:$AG$2,0)),Inputs!$B$4:$B$150,$B57)/1000) -> 19516 | H57: =IF(COUNT(D57:G57)=4,SUM(D57:G57),"") -> 72180 | I57: =IF(SUMPRODUCT((Inputs!$B$4:$B$150=$B57)*ISNUMBER(INDEX(Inputs!$D$4:$AG$150,0,MATCH(I$2,Inputs!$D$2:$AG$2,0))))=0,"",SUMIFS(INDEX(Inputs!$D$4:$AG$150,0,MATCH(I$2,Inputs!$D$2:$AG$2,0)),Inputs!$B$4:$B$150,$B57)/1000) -> 19821 | J57: =IF(SUMPRODUCT((Inputs!$B$4:$B$150=$B57)*ISNUMBER(INDEX(Inputs!$D$4:$AG$150,0,MATCH(J$2,Inputs!$D$2:$AG$2,0))))=0,"",SUMIFS(INDEX(Inputs!$D$4:$AG$150,0,MATCH(J$2,Inputs!$D$2:$AG$2,0)),Inputs!$B$4:$B$150,$B57)/1000) -> 19604 | K57: =IF(SUMPRODUCT((Inputs!$B$4:$B$150=$B57)*ISNUMBER(INDEX(Inputs!$D$4:$AG$150,0,MATCH(K$2,Inputs!$D$2:$AG$2,0))))=0,"",SUMIFS(INDEX(Inputs!$D$4:$AG$150,0,MATCH(K$2,Inputs!$D$2:$AG$2,0)),Inputs!$B$4:$B$150,$B57)/1000) -> 19188 | L57: =IF(SUMPRODUCT((Inputs!$B$4:$B$150=$B57)*ISNUMBER(INDEX(Inputs!$D$4:$AG$150,0,MATCH(L$2,Inputs!$D$2:$AG$2,0))))=0,"",SUMIFS(INDEX(Inputs!$D$4:$AG$150,0,MATCH(L$2,Inputs!$D$2:$AG$2,0)),Inputs!$B$4:$B$150,$B57)/1000) -> 20766 | M57: =IF(COUNT(I57:L57)=4,SUM(I57:L57),"") -> 79379 | N57: =IF(SUMPRODUCT((Inputs!$B$4:$B$150=$B57)*ISNUMBER(INDEX(Inputs!$D$4:$AG$150,0,MATCH(N$2,Inputs!$D$2:$AG$2,0))))=0,"",SUMIFS(INDEX(Inputs!$D$4:$AG$150,0,MATCH(N$2,Inputs!$D$2:$AG$2,0)),Inputs!$B$4:$B$150,$B57)/1000) -> 20907 | O57: =IF(SUMPRODUCT((Inputs!$B$4:$B$150=$B57)*ISNUMBER(INDEX(Inputs!$D$4:$AG$150,0,MATCH(O$2,Inputs!$D$2:$AG$2,0))))=0,"",SUMIFS(INDEX(Inputs!$D$4:$AG$150,0,MATCH(O$2,Inputs!$D$2:$AG$2,0)),Inputs!$B$4:$B$150,$B57)/1000) -> 21213 | P57: =IF(SUMPRODUCT((Inputs!$B$4:$B$150=$B57)*ISNUMBER(INDEX(Inputs!$D$4:$AG$150,0,MATCH(P$2,Inputs!$D$2:$AG$2,0))))=0,"",SUMIFS(INDEX(Inputs!$D$4:$AG$150,0,MATCH(P$2,Inputs!$D$2:$AG$2,0)),Inputs!$B$4:$B$150,$B57)/1000) -> 22314 | Q57: =IF(SUMPRODUCT((Inputs!$B$4:$B$150=$B57)*ISNUMBER(INDEX(Inputs!$D$4:$AG$150,0,MATCH(Q$2,Inputs!$D$2:$AG$2,0))))=0,"",SUMIFS(INDEX(Inputs!$D$4:$AG$150,0,MATCH(Q$2,Inputs!$D$2:$AG$2,0)),Inputs!$B$4:$B$150,$B57)/1000) -> 23117 | R57: =IF(COUNT(N57:Q57)=4,SUM(N57:Q57),"") -> 87551 | S57: =IF(SUMPRODUCT((Inputs!$B$4:$B$150=$B57)*ISNUMBER(INDEX(Inputs!$D$4:$AG$150,0,MATCH(S$2,Inputs!$D$2:$AG$2,0))))=0,"",SUMIFS(INDEX(Inputs!$D$4:$AG$150,0,MATCH(S$2,Inputs!$D$2:$AG$2,0)),Inputs!$B$4:$B$150,$B57)/1000) -> 23867 | T57: =IF(SUMPRODUCT((Inputs!$B$4:$B$150=$B57)*ISNUMBER(INDEX(Inputs!$D$4:$AG$150,0,MATCH(T$2,Inputs!$D$2:$AG$2,0))))=0,"",SUMIFS(INDEX(Inputs!$D$4:$AG$150,0,MATCH(T$2,Inputs!$D$2:$AG$2,0)),Inputs!$B$4:$B$150,$B57)/1000) -> 24213 | U57: =IF(SUMPRODUCT((Inputs!$B$4:$B$150=$B57)*ISNUMBER(INDEX(Inputs!$D$4:$AG$150,0,MATCH(U$2,Inputs!$D$2:$AG$2,0))))=0,"",SUMIFS(INDEX(Inputs!$D$4:$AG$150,0,MATCH(U$2,Inputs!$D$2:$AG$2,0)),Inputs!$B$4:$B$150,$B57)/1000) -> 24972 | V57: =IF(SUMPRODUCT((Inputs!$B$4:$B$150=$B57)*ISNUMBER(INDEX(Inputs!$D$4:$AG$150,0,MATCH(V$2,Inputs!$D$2:$AG$2,0))))=0,"",SUMIFS(INDEX(Inputs!$D$4:$AG$150,0,MATCH(V$2,Inputs!$D$2:$AG$2,0)),Inputs!$B$4:$B$150,$B57)/1000) -> 26340 | W57: =IF(COUNT(S57:V57)=4,SUM(S57:V57),"") -> 99392 | X57: =IF(SUMPRODUCT((Inputs!$B$4:$B$150=$B57)*ISNUMBER(INDEX(Inputs!$D$4:$AG$150,0,MATCH(X$2,Inputs!$D$2:$AG$2,0))))=0,"",SUMIFS(INDEX(Inputs!$D$4:$AG$150,0,MATCH(X$2,Inputs!$D$2:$AG$2,0)),Inputs!$B$4:$B$150,$B57)/1000) -> 26645 | Y57: =IF(SUMPRODUCT((Inputs!$B$4:$B$150=$B57)*ISNUMBER(INDEX(Inputs!$D$4:$AG$150,0,MATCH(Y$2,Inputs!$D$2:$AG$2,0))))=0,"",SUMIFS(INDEX(Inputs!$D$4:$AG$150,0,MATCH(Y$2,Inputs!$D$2:$AG$2,0)),Inputs!$B$4:$B$150,$B57)/1000) -> 27423 | Z57: =IF(SUMPRODUCT((Inputs!$B$4:$B$150=$B57)*ISNUMBER(INDEX(Inputs!$D$4:$AG$150,0,MATCH(Z$2,Inputs!$D$2:$AG$2,0))))=0,"",SUMIFS(INDEX(Inputs!$D$4:$AG$150,0,MATCH(Z$2,Inputs!$D$2:$AG$2,0)),Inputs!$B$4:$B$150,$B57)/1000) -> 28750 | AA57: =IF(SUMPRODUCT((Inputs!$B$4:$B$150=$B57)*ISNUMBER(INDEX(Inputs!$D$4:$AG$150,0,MATCH(AA$2,Inputs!$D$2:$AG$2,0))))=0,"",SUMIFS(INDEX(Inputs!$D$4:$AG$150,0,MATCH(AA$2,Inputs!$D$2:$AG$2,0)),Inputs!$B$4:$B$150,$B57)/1000) -> 30013 | AB57: =IF(COUNT(X57:AA57)=4,SUM(X57:AA57),"") -> 112831 | AC57: =IF(SUMPRODUCT((Inputs!$B$4:$B$150=$B57)*ISNUMBER(INDEX(Inputs!$D$4:$AG$150,0,MATCH(AC$2,Inputs!$D$2:$AG$2,0))))=0,"",SUMIFS(INDEX(Inputs!$D$4:$AG$150,0,MATCH(AC$2,Inputs!$D$2:$AG$2,0)),Inputs!$B$4:$B$150,$B57)/1000) -> 30976 | AD57: =IF(SUMPRODUCT((Inputs!$B$4:$B$150=$B57)*ISNUMBER(INDEX(Inputs!$D$4:$AG$150,0,MATCH(AD$2,Inputs!$D$2:$AG$2,0))))=0,"",SUMIFS(INDEX(Inputs!$D$4:$AG$150,0,MATCH(AD$2,Inputs!$D$2:$AG$2,0)),Inputs!$B$4:$B$150,$B57)/1000) -> 30739 | AE57: =IF(SUMPRODUCT((Inputs!$B$4:$B$150=$B57)*ISNUMBER(INDEX(Inputs!$D$4:$AG$150,0,MATCH(AE$2,Inputs!$D$2:$AG$2,0))))=0,"",SUMIFS(INDEX(Inputs!$D$4:$AG$150,0,MATCH(AE$2,Inputs!$D$2:$AG$2,0)),Inputs!$B$4:$B$150,$B57)/1000) | AF57: =IF(SUMPRODUCT((Inputs!$B$4:$B$150=$B57)*ISNUMBER(INDEX(Inputs!$D$4:$AG$150,0,MATCH(AF$2,Inputs!$D$2:$AG$2,0))))=0,"",SUMIFS(INDEX(Inputs!$D$4:$AG$150,0,MATCH(AF$2,Inputs!$D$2:$AG$2,0)),Inputs!$B$4:$B$150,$B57)/1000) | AG57: =IF(COUNT(AC57:AF57)=4,SUM(AC57:AF57),"")
B58: 50 | C58: Custo das vendas - Produtos (USD) | D58: =IF(SUMPRODUCT((Inputs!$B$4:$B$150=$B58)*ISNUMBER(INDEX(Inputs!$D$4:$AG$150,0,MATCH(D$2,Inputs!$D$2:$AG$2,0))))=0,"",SUMIFS(INDEX(Inputs!$D$4:$AG$150,0,MATCH(D$2,Inputs!$D$2:$AG$2,0)),Inputs!$B$4:$B$150,$B58)/1000) -> 46447 | E58: =IF(SUMPRODUCT((Inputs!$B$4:$B$150=$B58)*ISNUMBER(INDEX(Inputs!$D$4:$AG$150,0,MATCH(E$2,Inputs!$D$2:$AG$2,0))))=0,"",SUMIFS(INDEX(Inputs!$D$4:$AG$150,0,MATCH(E$2,Inputs!$D$2:$AG$2,0)),Inputs!$B$4:$B$150,$B58)/1000) -> 40899 | F58: =IF(SUMPRODUCT((Inputs!$B$4:$B$150=$B58)*ISNUMBER(INDEX(Inputs!$D$4:$AG$150,0,MATCH(F$2,Inputs!$D$2:$AG$2,0))))=0,"",SUMIFS(INDEX(Inputs!$D$4:$AG$150,0,MATCH(F$2,Inputs!$D$2:$AG$2,0)),Inputs!$B$4:$B$150,$B58)/1000) -> 42790 | G58: =IF(SUMPRODUCT((Inputs!$B$4:$B$150=$B58)*ISNUMBER(INDEX(Inputs!$D$4:$AG$150,0,MATCH(G$2,Inputs!$D$2:$AG$2,0))))=0,"",SUMIFS(INDEX(Inputs!$D$4:$AG$150,0,MATCH(G$2,Inputs!$D$2:$AG$2,0)),Inputs!$B$4:$B$150,$B58)/1000) -> 64309 | H58: =IF(COUNT(D58:G58)=4,SUM(D58:G58),"") -> 194445 | I58: =IF(SUMPRODUCT((Inputs!$B$4:$B$150=$B58)*ISNUMBER(INDEX(Inputs!$D$4:$AG$150,0,MATCH(I$2,Inputs!$D$2:$AG$2,0))))=0,"",SUMIFS(INDEX(Inputs!$D$4:$AG$150,0,MATCH(I$2,Inputs!$D$2:$AG$2,0)),Inputs!$B$4:$B$150,$B58)/1000) -> 49290 | J58: =IF(SUMPRODUCT((Inputs!$B$4:$B$150=$B58)*ISNUMBER(INDEX(Inputs!$D$4:$AG$150,0,MATCH(J$2,Inputs!$D$2:$AG$2,0))))=0,"",SUMIFS(INDEX(Inputs!$D$4:$AG$150,0,MATCH(J$2,Inputs!$D$2:$AG$2,0)),Inputs!$B$4:$B$150,$B58)/1000) -> 41485 | K58: =IF(SUMPRODUCT((Inputs!$B$4:$B$150=$B58)*ISNUMBER(INDEX(Inputs!$D$4:$AG$150,0,MATCH(K$2,Inputs!$D$2:$AG$2,0))))=0,"",SUMIFS(INDEX(Inputs!$D$4:$AG$150,0,MATCH(K$2,Inputs!$D$2:$AG$2,0)),Inputs!$B$4:$B$150,$B58)/1000) -> 46387 | L58: =IF(SUMPRODUCT((Inputs!$B$4:$B$150=$B58)*ISNUMBER(INDEX(Inputs!$D$4:$AG$150,0,MATCH(L$2,Inputs!$D$2:$AG$2,0))))=0,"",SUMIFS(INDEX(Inputs!$D$4:$AG$150,0,MATCH(L$2,Inputs!$D$2:$AG$2,0)),Inputs!$B$4:$B$150,$B58)/1000) -> 60765 | M58: =IF(COUNT(I58:L58)=4,SUM(I58:L58),"") -> 197927 | N58: =IF(SUMPRODUCT((Inputs!$B$4:$B$150=$B58)*ISNUMBER(INDEX(Inputs!$D$4:$AG$150,0,MATCH(N$2,Inputs!$D$2:$AG$2,0))))=0,"",SUMIFS(INDEX(Inputs!$D$4:$AG$150,0,MATCH(N$2,Inputs!$D$2:$AG$2,0)),Inputs!$B$4:$B$150,$B58)/1000) -> 46795 | O58: =IF(SUMPRODUCT((Inputs!$B$4:$B$150=$B58)*ISNUMBER(INDEX(Inputs!$D$4:$AG$150,0,MATCH(O$2,Inputs!$D$2:$AG$2,0))))=0,"",SUMIFS(INDEX(Inputs!$D$4:$AG$150,0,MATCH(O$2,Inputs!$D$2:$AG$2,0)),Inputs!$B$4:$B$150,$B58)/1000) -> 39136 | P58: =IF(SUMPRODUCT((Inputs!$B$4:$B$150=$B58)*ISNUMBER(INDEX(Inputs!$D$4:$AG$150,0,MATCH(P$2,Inputs!$D$2:$AG$2,0))))=0,"",SUMIFS(INDEX(Inputs!$D$4:$AG$150,0,MATCH(P$2,Inputs!$D$2:$AG$2,0)),Inputs!$B$4:$B$150,$B58)/1000) -> 42586 | Q58: =IF(SUMPRODUCT((Inputs!$B$4:$B$150=$B58)*ISNUMBER(INDEX(Inputs!$D$4:$AG$150,0,MATCH(Q$2,Inputs!$D$2:$AG$2,0))))=0,"",SUMIFS(INDEX(Inputs!$D$4:$AG$150,0,MATCH(Q$2,Inputs!$D$2:$AG$2,0)),Inputs!$B$4:$B$150,$B58)/1000) -> 58440 | R58: =IF(COUNT(N58:Q58)=4,SUM(N58:Q58),"") -> 186957 | S58: =IF(SUMPRODUCT((Inputs!$B$4:$B$150=$B58)*ISNUMBER(INDEX(Inputs!$D$4:$AG$150,0,MATCH(S$2,Inputs!$D$2:$AG$2,0))))=0,"",SUMIFS(INDEX(Inputs!$D$4:$AG$150,0,MATCH(S$2,Inputs!$D$2:$AG$2,0)),Inputs!$B$4:$B$150,$B58)/1000) -> 42424 | T58: =IF(SUMPRODUCT((Inputs!$B$4:$B$150=$B58)*ISNUMBER(INDEX(Inputs!$D$4:$AG$150,0,MATCH(T$2,Inputs!$D$2:$AG$2,0))))=0,"",SUMIFS(INDEX(Inputs!$D$4:$AG$150,0,MATCH(T$2,Inputs!$D$2:$AG$2,0)),Inputs!$B$4:$B$150,$B58)/1000) -> 39803 | U58: =IF(SUMPRODUCT((Inputs!$B$4:$B$150=$B58)*ISNUMBER(INDEX(Inputs!$D$4:$AG$150,0,MATCH(U$2,Inputs!$D$2:$AG$2,0))))=0,"",SUMIFS(INDEX(Inputs!$D$4:$AG$150,0,MATCH(U$2,Inputs!$D$2:$AG$2,0)),Inputs!$B$4:$B$150,$B58)/1000) -> 44566 | V58: =IF(SUMPRODUCT((Inputs!$B$4:$B$150=$B58)*ISNUMBER(INDEX(Inputs!$D$4:$AG$150,0,MATCH(V$2,Inputs!$D$2:$AG$2,0))))=0,"",SUMIFS(INDEX(Inputs!$D$4:$AG$150,0,MATCH(V$2,Inputs!$D$2:$AG$2,0)),Inputs!$B$4:$B$150,$B58)/1000) -> 59447 | W58: =IF(COUNT(S58:V58)=4,SUM(S58:V58),"") -> 186240 | X58: =IF(SUMPRODUCT((Inputs!$B$4:$B$150=$B58)*ISNUMBER(INDEX(Inputs!$D$4:$AG$150,0,MATCH(X$2,Inputs!$D$2:$AG$2,0))))=0,"",SUMIFS(INDEX(Inputs!$D$4:$AG$150,0,MATCH(X$2,Inputs!$D$2:$AG$2,0)),Inputs!$B$4:$B$150,$B58)/1000) -> 44030 | Y58: =IF(SUMPRODUCT((Inputs!$B$4:$B$150=$B58)*ISNUMBER(INDEX(Inputs!$D$4:$AG$150,0,MATCH(Y$2,Inputs!$D$2:$AG$2,0))))=0,"",SUMIFS(INDEX(Inputs!$D$4:$AG$150,0,MATCH(Y$2,Inputs!$D$2:$AG$2,0)),Inputs!$B$4:$B$150,$B58)/1000) -> 43620 | Z58: =IF(SUMPRODUCT((Inputs!$B$4:$B$150=$B58)*ISNUMBER(INDEX(Inputs!$D$4:$AG$150,0,MATCH(Z$2,Inputs!$D$2:$AG$2,0))))=0,"",SUMIFS(INDEX(Inputs!$D$4:$AG$150,0,MATCH(Z$2,Inputs!$D$2:$AG$2,0)),Inputs!$B$4:$B$150,$B58)/1000) -> 47019 | AA58: =IF(SUMPRODUCT((Inputs!$B$4:$B$150=$B58)*ISNUMBER(INDEX(Inputs!$D$4:$AG$150,0,MATCH(AA$2,Inputs!$D$2:$AG$2,0))))=0,"",SUMIFS(INDEX(Inputs!$D$4:$AG$150,0,MATCH(AA$2,Inputs!$D$2:$AG$2,0)),Inputs!$B$4:$B$150,$B58)/1000) -> 67478 | AB58: =IF(COUNT(X58:AA58)=4,SUM(X58:AA58),"") -> 202147 | AC58: =IF(SUMPRODUCT((Inputs!$B$4:$B$150=$B58)*ISNUMBER(INDEX(Inputs!$D$4:$AG$150,0,MATCH(AC$2,Inputs!$D$2:$AG$2,0))))=0,"",SUMIFS(INDEX(Inputs!$D$4:$AG$150,0,MATCH(AC$2,Inputs!$D$2:$AG$2,0)),Inputs!$B$4:$B$150,$B58)/1000) -> 49179 | AD58: =IF(SUMPRODUCT((Inputs!$B$4:$B$150=$B58)*ISNUMBER(INDEX(Inputs!$D$4:$AG$150,0,MATCH(AD$2,Inputs!$D$2:$AG$2,0))))=0,"",SUMIFS(INDEX(Inputs!$D$4:$AG$150,0,MATCH(AD$2,Inputs!$D$2:$AG$2,0)),Inputs!$B$4:$B$150,$B58)/1000) -> 47153 | AE58: =IF(SUMPRODUCT((Inputs!$B$4:$B$150=$B58)*ISNUMBER(INDEX(Inputs!$D$4:$AG$150,0,MATCH(AE$2,Inputs!$D$2:$AG$2,0))))=0,"",SUMIFS(INDEX(Inputs!$D$4:$AG$150,0,MATCH(AE$2,Inputs!$D$2:$AG$2,0)),Inputs!$B$4:$B$150,$B58)/1000) | AF58: =IF(SUMPRODUCT((Inputs!$B$4:$B$150=$B58)*ISNUMBER(INDEX(Inputs!$D$4:$AG$150,0,MATCH(AF$2,Inputs!$D$2:$AG$2,0))))=0,"",SUMIFS(INDEX(Inputs!$D$4:$AG$150,0,MATCH(AF$2,Inputs!$D$2:$AG$2,0)),Inputs!$B$4:$B$150,$B58)/1000) | AG58: =IF(COUNT(AC58:AF58)=4,SUM(AC58:AF58),"")
B59: 51 | C59: Custo das vendas - Serviços (USD) | D59: =IF(SUMPRODUCT((Inputs!$B$4:$B$150=$B59)*ISNUMBER(INDEX(Inputs!$D$4:$AG$150,0,MATCH(D$2,Inputs!$D$2:$AG$2,0))))=0,"",SUMIFS(INDEX(Inputs!$D$4:$AG$150,0,MATCH(D$2,Inputs!$D$2:$AG$2,0)),Inputs!$B$4:$B$150,$B59)/1000) -> 5058 | E59: =IF(SUMPRODUCT((Inputs!$B$4:$B$150=$B59)*ISNUMBER(INDEX(Inputs!$D$4:$AG$150,0,MATCH(E$2,Inputs!$D$2:$AG$2,0))))=0,"",SUMIFS(INDEX(Inputs!$D$4:$AG$150,0,MATCH(E$2,Inputs!$D$2:$AG$2,0)),Inputs!$B$4:$B$150,$B59)/1000) -> 5280 | F59: =IF(SUMPRODUCT((Inputs!$B$4:$B$150=$B59)*ISNUMBER(INDEX(Inputs!$D$4:$AG$150,0,MATCH(F$2,Inputs!$D$2:$AG$2,0))))=0,"",SUMIFS(INDEX(Inputs!$D$4:$AG$150,0,MATCH(F$2,Inputs!$D$2:$AG$2,0)),Inputs!$B$4:$B$150,$B59)/1000) -> 5396 | G59: =IF(SUMPRODUCT((Inputs!$B$4:$B$150=$B59)*ISNUMBER(INDEX(Inputs!$D$4:$AG$150,0,MATCH(G$2,Inputs!$D$2:$AG$2,0))))=0,"",SUMIFS(INDEX(Inputs!$D$4:$AG$150,0,MATCH(G$2,Inputs!$D$2:$AG$2,0)),Inputs!$B$4:$B$150,$B59)/1000) -> 5393 | H59: =IF(COUNT(D59:G59)=4,SUM(D59:G59),"") -> 21127 | I59: =IF(SUMPRODUCT((Inputs!$B$4:$B$150=$B59)*ISNUMBER(INDEX(Inputs!$D$4:$AG$150,0,MATCH(I$2,Inputs!$D$2:$AG$2,0))))=0,"",SUMIFS(INDEX(Inputs!$D$4:$AG$150,0,MATCH(I$2,Inputs!$D$2:$AG$2,0)),Inputs!$B$4:$B$150,$B59)/1000) -> 5429 | J59: =IF(SUMPRODUCT((Inputs!$B$4:$B$150=$B59)*ISNUMBER(INDEX(Inputs!$D$4:$AG$150,0,MATCH(J$2,Inputs!$D$2:$AG$2,0))))=0,"",SUMIFS(INDEX(Inputs!$D$4:$AG$150,0,MATCH(J$2,Inputs!$D$2:$AG$2,0)),Inputs!$B$4:$B$150,$B59)/1000) -> 5589 | K59: =IF(SUMPRODUCT((Inputs!$B$4:$B$150=$B59)*ISNUMBER(INDEX(Inputs!$D$4:$AG$150,0,MATCH(K$2,Inputs!$D$2:$AG$2,0))))=0,"",SUMIFS(INDEX(Inputs!$D$4:$AG$150,0,MATCH(K$2,Inputs!$D$2:$AG$2,0)),Inputs!$B$4:$B$150,$B59)/1000) -> 5664 | L59: =IF(SUMPRODUCT((Inputs!$B$4:$B$150=$B59)*ISNUMBER(INDEX(Inputs!$D$4:$AG$150,0,MATCH(L$2,Inputs!$D$2:$AG$2,0))))=0,"",SUMIFS(INDEX(Inputs!$D$4:$AG$150,0,MATCH(L$2,Inputs!$D$2:$AG$2,0)),Inputs!$B$4:$B$150,$B59)/1000) -> 6057 | M59: =IF(COUNT(I59:L59)=4,SUM(I59:L59),"") -> 22739 | N59: =IF(SUMPRODUCT((Inputs!$B$4:$B$150=$B59)*ISNUMBER(INDEX(Inputs!$D$4:$AG$150,0,MATCH(N$2,Inputs!$D$2:$AG$2,0))))=0,"",SUMIFS(INDEX(Inputs!$D$4:$AG$150,0,MATCH(N$2,Inputs!$D$2:$AG$2,0)),Inputs!$B$4:$B$150,$B59)/1000) -> 6065 | O59: =IF(SUMPRODUCT((Inputs!$B$4:$B$150=$B59)*ISNUMBER(INDEX(Inputs!$D$4:$AG$150,0,MATCH(O$2,Inputs!$D$2:$AG$2,0))))=0,"",SUMIFS(INDEX(Inputs!$D$4:$AG$150,0,MATCH(O$2,Inputs!$D$2:$AG$2,0)),Inputs!$B$4:$B$150,$B59)/1000) -> 6248 | P59: =IF(SUMPRODUCT((Inputs!$B$4:$B$150=$B59)*ISNUMBER(INDEX(Inputs!$D$4:$AG$150,0,MATCH(P$2,Inputs!$D$2:$AG$2,0))))=0,"",SUMIFS(INDEX(Inputs!$D$4:$AG$150,0,MATCH(P$2,Inputs!$D$2:$AG$2,0)),Inputs!$B$4:$B$150,$B59)/1000) -> 6485 | Q59: =IF(SUMPRODUCT((Inputs!$B$4:$B$150=$B59)*ISNUMBER(INDEX(Inputs!$D$4:$AG$150,0,MATCH(Q$2,Inputs!$D$2:$AG$2,0))))=0,"",SUMIFS(INDEX(Inputs!$D$4:$AG$150,0,MATCH(Q$2,Inputs!$D$2:$AG$2,0)),Inputs!$B$4:$B$150,$B59)/1000) -> 6280 | R59: =IF(COUNT(N59:Q59)=4,SUM(N59:Q59),"") -> 25078 | S59: =IF(SUMPRODUCT((Inputs!$B$4:$B$150=$B59)*ISNUMBER(INDEX(Inputs!$D$4:$AG$150,0,MATCH(S$2,Inputs!$D$2:$AG$2,0))))=0,"",SUMIFS(INDEX(Inputs!$D$4:$AG$150,0,MATCH(S$2,Inputs!$D$2:$AG$2,0)),Inputs!$B$4:$B$150,$B59)/1000) -> 6058 | T59: =IF(SUMPRODUCT((Inputs!$B$4:$B$150=$B59)*ISNUMBER(INDEX(Inputs!$D$4:$AG$150,0,MATCH(T$2,Inputs!$D$2:$AG$2,0))))=0,"",SUMIFS(INDEX(Inputs!$D$4:$AG$150,0,MATCH(T$2,Inputs!$D$2:$AG$2,0)),Inputs!$B$4:$B$150,$B59)/1000) -> 6296 | U59: =IF(SUMPRODUCT((Inputs!$B$4:$B$150=$B59)*ISNUMBER(INDEX(Inputs!$D$4:$AG$150,0,MATCH(U$2,Inputs!$D$2:$AG$2,0))))=0,"",SUMIFS(INDEX(Inputs!$D$4:$AG$150,0,MATCH(U$2,Inputs!$D$2:$AG$2,0)),Inputs!$B$4:$B$150,$B59)/1000) -> 6485 | V59: =IF(SUMPRODUCT((Inputs!$B$4:$B$150=$B59)*ISNUMBER(INDEX(Inputs!$D$4:$AG$150,0,MATCH(V$2,Inputs!$D$2:$AG$2,0))))=0,"",SUMIFS(INDEX(Inputs!$D$4:$AG$150,0,MATCH(V$2,Inputs!$D$2:$AG$2,0)),Inputs!$B$4:$B$150,$B59)/1000) -> 6578 | W59: =IF(COUNT(S59:V59)=4,SUM(S59:V59),"") -> 25417 | X59: =IF(SUMPRODUCT((Inputs!$B$4:$B$150=$B59)*ISNUMBER(INDEX(Inputs!$D$4:$AG$150,0,MATCH(X$2,Inputs!$D$2:$AG$2,0))))=0,"",SUMIFS(INDEX(Inputs!$D$4:$AG$150,0,MATCH(X$2,Inputs!$D$2:$AG$2,0)),Inputs!$B$4:$B$150,$B59)/1000) -> 6462 | Y59: =IF(SUMPRODUCT((Inputs!$B$4:$B$150=$B59)*ISNUMBER(INDEX(Inputs!$D$4:$AG$150,0,MATCH(Y$2,Inputs!$D$2:$AG$2,0))))=0,"",SUMIFS(INDEX(Inputs!$D$4:$AG$150,0,MATCH(Y$2,Inputs!$D$2:$AG$2,0)),Inputs!$B$4:$B$150,$B59)/1000) -> 6698 | Z59: =IF(SUMPRODUCT((Inputs!$B$4:$B$150=$B59)*ISNUMBER(INDEX(Inputs!$D$4:$AG$150,0,MATCH(Z$2,Inputs!$D$2:$AG$2,0))))=0,"",SUMIFS(INDEX(Inputs!$D$4:$AG$150,0,MATCH(Z$2,Inputs!$D$2:$AG$2,0)),Inputs!$B$4:$B$150,$B59)/1000) -> 7106 | AA59: =IF(SUMPRODUCT((Inputs!$B$4:$B$150=$B59)*ISNUMBER(INDEX(Inputs!$D$4:$AG$150,0,MATCH(AA$2,Inputs!$D$2:$AG$2,0))))=0,"",SUMIFS(INDEX(Inputs!$D$4:$AG$150,0,MATCH(AA$2,Inputs!$D$2:$AG$2,0)),Inputs!$B$4:$B$150,$B59)/1000) -> 7047 | AB59: =IF(COUNT(X59:AA59)=4,SUM(X59:AA59),"") -> 27313 | AC59: =IF(SUMPRODUCT((Inputs!$B$4:$B$150=$B59)*ISNUMBER(INDEX(Inputs!$D$4:$AG$150,0,MATCH(AC$2,Inputs!$D$2:$AG$2,0))))=0,"",SUMIFS(INDEX(Inputs!$D$4:$AG$150,0,MATCH(AC$2,Inputs!$D$2:$AG$2,0)),Inputs!$B$4:$B$150,$B59)/1000) -> 7224 | AD59: =IF(SUMPRODUCT((Inputs!$B$4:$B$150=$B59)*ISNUMBER(INDEX(Inputs!$D$4:$AG$150,0,MATCH(AD$2,Inputs!$D$2:$AG$2,0))))=0,"",SUMIFS(INDEX(Inputs!$D$4:$AG$150,0,MATCH(AD$2,Inputs!$D$2:$AG$2,0)),Inputs!$B$4:$B$150,$B59)/1000) -> 7494 | AE59: =IF(SUMPRODUCT((Inputs!$B$4:$B$150=$B59)*ISNUMBER(INDEX(Inputs!$D$4:$AG$150,0,MATCH(AE$2,Inputs!$D$2:$AG$2,0))))=0,"",SUMIFS(INDEX(Inputs!$D$4:$AG$150,0,MATCH(AE$2,Inputs!$D$2:$AG$2,0)),Inputs!$B$4:$B$150,$B59)/1000) | AF59: =IF(SUMPRODUCT((Inputs!$B$4:$B$150=$B59)*ISNUMBER(INDEX(Inputs!$D$4:$AG$150,0,MATCH(AF$2,Inputs!$D$2:$AG$2,0))))=0,"",SUMIFS(INDEX(Inputs!$D$4:$AG$150,0,MATCH(AF$2,Inputs!$D$2:$AG$2,0)),Inputs!$B$4:$B$150,$B59)/1000) | AG59: =IF(COUNT(AC59:AF59)=4,SUM(AC59:AF59),"")
B60: 52 | C60: Receita segmento Américas (USD) | D60: =IF(SUMPRODUCT((Inputs!$B$4:$B$150=$B60)*ISNUMBER(INDEX(Inputs!$D$4:$AG$150,0,MATCH(D$2,Inputs!$D$2:$AG$2,0))))=0,"",SUMIFS(INDEX(Inputs!$D$4:$AG$150,0,MATCH(D$2,Inputs!$D$2:$AG$2,0)),Inputs!$B$4:$B$150,$B60)/1000) -> 34306 | E60: =IF(SUMPRODUCT((Inputs!$B$4:$B$150=$B60)*ISNUMBER(INDEX(Inputs!$D$4:$AG$150,0,MATCH(E$2,Inputs!$D$2:$AG$2,0))))=0,"",SUMIFS(INDEX(Inputs!$D$4:$AG$150,0,MATCH(E$2,Inputs!$D$2:$AG$2,0)),Inputs!$B$4:$B$150,$B60)/1000) -> 35870 | F60: =IF(SUMPRODUCT((Inputs!$B$4:$B$150=$B60)*ISNUMBER(INDEX(Inputs!$D$4:$AG$150,0,MATCH(F$2,Inputs!$D$2:$AG$2,0))))=0,"",SUMIFS(INDEX(Inputs!$D$4:$AG$150,0,MATCH(F$2,Inputs!$D$2:$AG$2,0)),Inputs!$B$4:$B$150,$B60)/1000) -> 36820 | G60: =IF(SUMPRODUCT((Inputs!$B$4:$B$150=$B60)*ISNUMBER(INDEX(Inputs!$D$4:$AG$150,0,MATCH(G$2,Inputs!$D$2:$AG$2,0))))=0,"",SUMIFS(INDEX(Inputs!$D$4:$AG$150,0,MATCH(G$2,Inputs!$D$2:$AG$2,0)),Inputs!$B$4:$B$150,$B60)/1000) -> 51496 | H60: =IF(COUNT(D60:G60)=4,SUM(D60:G60),"") -> 158492 | I60: =IF(SUMPRODUCT((Inputs!$B$4:$B$150=$B60)*ISNUMBER(INDEX(Inputs!$D$4:$AG$150,0,MATCH(I$2,Inputs!$D$2:$AG$2,0))))=0,"",SUMIFS(INDEX(Inputs!$D$4:$AG$150,0,MATCH(I$2,Inputs!$D$2:$AG$2,0)),Inputs!$B$4:$B$150,$B60)/1000) -> 40882 | J60: =IF(SUMPRODUCT((Inputs!$B$4:$B$150=$B60)*ISNUMBER(INDEX(Inputs!$D$4:$AG$150,0,MATCH(J$2,Inputs!$D$2:$AG$2,0))))=0,"",SUMIFS(INDEX(Inputs!$D$4:$AG$150,0,MATCH(J$2,Inputs!$D$2:$AG$2,0)),Inputs!$B$4:$B$150,$B60)/1000) -> 37472 | K60: =IF(SUMPRODUCT((Inputs!$B$4:$B$150=$B60)*ISNUMBER(INDEX(Inputs!$D$4:$AG$150,0,MATCH(K$2,Inputs!$D$2:$AG$2,0))))=0,"",SUMIFS(INDEX(Inputs!$D$4:$AG$150,0,MATCH(K$2,Inputs!$D$2:$AG$2,0)),Inputs!$B$4:$B$150,$B60)/1000) -> 39808 | L60: =IF(SUMPRODUCT((Inputs!$B$4:$B$150=$B60)*ISNUMBER(INDEX(Inputs!$D$4:$AG$150,0,MATCH(L$2,Inputs!$D$2:$AG$2,0))))=0,"",SUMIFS(INDEX(Inputs!$D$4:$AG$150,0,MATCH(L$2,Inputs!$D$2:$AG$2,0)),Inputs!$B$4:$B$150,$B60)/1000) -> 49278 | M60: =IF(COUNT(I60:L60)=4,SUM(I60:L60),"") -> 167440 | N60: =IF(SUMPRODUCT((Inputs!$B$4:$B$150=$B60)*ISNUMBER(INDEX(Inputs!$D$4:$AG$150,0,MATCH(N$2,Inputs!$D$2:$AG$2,0))))=0,"",SUMIFS(INDEX(Inputs!$D$4:$AG$150,0,MATCH(N$2,Inputs!$D$2:$AG$2,0)),Inputs!$B$4:$B$150,$B60)/1000) -> 37784 | O60: =IF(SUMPRODUCT((Inputs!$B$4:$B$150=$B60)*ISNUMBER(INDEX(Inputs!$D$4:$AG$150,0,MATCH(O$2,Inputs!$D$2:$AG$2,0))))=0,"",SUMIFS(INDEX(Inputs!$D$4:$AG$150,0,MATCH(O$2,Inputs!$D$2:$AG$2,0)),Inputs!$B$4:$B$150,$B60)/1000) -> 35383 | P60: =IF(SUMPRODUCT((Inputs!$B$4:$B$150=$B60)*ISNUMBER(INDEX(Inputs!$D$4:$AG$150,0,MATCH(P$2,Inputs!$D$2:$AG$2,0))))=0,"",SUMIFS(INDEX(Inputs!$D$4:$AG$150,0,MATCH(P$2,Inputs!$D$2:$AG$2,0)),Inputs!$B$4:$B$150,$B60)/1000) -> 40115 | Q60: =IF(SUMPRODUCT((Inputs!$B$4:$B$150=$B60)*ISNUMBER(INDEX(Inputs!$D$4:$AG$150,0,MATCH(Q$2,Inputs!$D$2:$AG$2,0))))=0,"",SUMIFS(INDEX(Inputs!$D$4:$AG$150,0,MATCH(Q$2,Inputs!$D$2:$AG$2,0)),Inputs!$B$4:$B$150,$B60)/1000) -> 50430 | R60: =IF(COUNT(N60:Q60)=4,SUM(N60:Q60),"") -> 163712 | S60: =IF(SUMPRODUCT((Inputs!$B$4:$B$150=$B60)*ISNUMBER(INDEX(Inputs!$D$4:$AG$150,0,MATCH(S$2,Inputs!$D$2:$AG$2,0))))=0,"",SUMIFS(INDEX(Inputs!$D$4:$AG$150,0,MATCH(S$2,Inputs!$D$2:$AG$2,0)),Inputs!$B$4:$B$150,$B60)/1000) -> 37273 | T60: =IF(SUMPRODUCT((Inputs!$B$4:$B$150=$B60)*ISNUMBER(INDEX(Inputs!$D$4:$AG$150,0,MATCH(T$2,Inputs!$D$2:$AG$2,0))))=0,"",SUMIFS(INDEX(Inputs!$D$4:$AG$150,0,MATCH(T$2,Inputs!$D$2:$AG$2,0)),Inputs!$B$4:$B$150,$B60)/1000) -> 37678 | U60: =IF(SUMPRODUCT((Inputs!$B$4:$B$150=$B60)*ISNUMBER(INDEX(Inputs!$D$4:$AG$150,0,MATCH(U$2,Inputs!$D$2:$AG$2,0))))=0,"",SUMIFS(INDEX(Inputs!$D$4:$AG$150,0,MATCH(U$2,Inputs!$D$2:$AG$2,0)),Inputs!$B$4:$B$150,$B60)/1000) -> 41664 | V60: =IF(SUMPRODUCT((Inputs!$B$4:$B$150=$B60)*ISNUMBER(INDEX(Inputs!$D$4:$AG$150,0,MATCH(V$2,Inputs!$D$2:$AG$2,0))))=0,"",SUMIFS(INDEX(Inputs!$D$4:$AG$150,0,MATCH(V$2,Inputs!$D$2:$AG$2,0)),Inputs!$B$4:$B$150,$B60)/1000) -> 52648 | W60: =IF(COUNT(S60:V60)=4,SUM(S60:V60),"") -> 169263 | X60: =IF(SUMPRODUCT((Inputs!$B$4:$B$150=$B60)*ISNUMBER(INDEX(Inputs!$D$4:$AG$150,0,MATCH(X$2,Inputs!$D$2:$AG$2,0))))=0,"",SUMIFS(INDEX(Inputs!$D$4:$AG$150,0,MATCH(X$2,Inputs!$D$2:$AG$2,0)),Inputs!$B$4:$B$150,$B60)/1000) -> 40315 | Y60: =IF(SUMPRODUCT((Inputs!$B$4:$B$150=$B60)*ISNUMBER(INDEX(Inputs!$D$4:$AG$150,0,MATCH(Y$2,Inputs!$D$2:$AG$2,0))))=0,"",SUMIFS(INDEX(Inputs!$D$4:$AG$150,0,MATCH(Y$2,Inputs!$D$2:$AG$2,0)),Inputs!$B$4:$B$150,$B60)/1000) -> 41198 | Z60: =IF(SUMPRODUCT((Inputs!$B$4:$B$150=$B60)*ISNUMBER(INDEX(Inputs!$D$4:$AG$150,0,MATCH(Z$2,Inputs!$D$2:$AG$2,0))))=0,"",SUMIFS(INDEX(Inputs!$D$4:$AG$150,0,MATCH(Z$2,Inputs!$D$2:$AG$2,0)),Inputs!$B$4:$B$150,$B60)/1000) -> 44192 | AA60: =IF(SUMPRODUCT((Inputs!$B$4:$B$150=$B60)*ISNUMBER(INDEX(Inputs!$D$4:$AG$150,0,MATCH(AA$2,Inputs!$D$2:$AG$2,0))))=0,"",SUMIFS(INDEX(Inputs!$D$4:$AG$150,0,MATCH(AA$2,Inputs!$D$2:$AG$2,0)),Inputs!$B$4:$B$150,$B60)/1000) -> 58529 | AB60: =IF(COUNT(X60:AA60)=4,SUM(X60:AA60),"") -> 184234 | AC60: =IF(SUMPRODUCT((Inputs!$B$4:$B$150=$B60)*ISNUMBER(INDEX(Inputs!$D$4:$AG$150,0,MATCH(AC$2,Inputs!$D$2:$AG$2,0))))=0,"",SUMIFS(INDEX(Inputs!$D$4:$AG$150,0,MATCH(AC$2,Inputs!$D$2:$AG$2,0)),Inputs!$B$4:$B$150,$B60)/1000) -> 45093 | AD60: =IF(SUMPRODUCT((Inputs!$B$4:$B$150=$B60)*ISNUMBER(INDEX(Inputs!$D$4:$AG$150,0,MATCH(AD$2,Inputs!$D$2:$AG$2,0))))=0,"",SUMIFS(INDEX(Inputs!$D$4:$AG$150,0,MATCH(AD$2,Inputs!$D$2:$AG$2,0)),Inputs!$B$4:$B$150,$B60)/1000) -> 45781 | AE60: =IF(SUMPRODUCT((Inputs!$B$4:$B$150=$B60)*ISNUMBER(INDEX(Inputs!$D$4:$AG$150,0,MATCH(AE$2,Inputs!$D$2:$AG$2,0))))=0,"",SUMIFS(INDEX(Inputs!$D$4:$AG$150,0,MATCH(AE$2,Inputs!$D$2:$AG$2,0)),Inputs!$B$4:$B$150,$B60)/1000) | AF60: =IF(SUMPRODUCT((Inputs!$B$4:$B$150=$B60)*ISNUMBER(INDEX(Inputs!$D$4:$AG$150,0,MATCH(AF$2,Inputs!$D$2:$AG$2,0))))=0,"",SUMIFS(INDEX(Inputs!$D$4:$AG$150,0,MATCH(AF$2,Inputs!$D$2:$AG$2,0)),Inputs!$B$4:$B$150,$B60)/1000) | AG60: =IF(COUNT(AC60:AF60)=4,SUM(AC60:AF60),"")
B61: 53 | C61: Receita segmento Europa (USD; inclui Índia, Oriente Médio e África) | D61: =IF(SUMPRODUCT((Inputs!$B$4:$B$150=$B61)*ISNUMBER(INDEX(Inputs!$D$4:$AG$150,0,MATCH(D$2,Inputs!$D$2:$AG$2,0))))=0,"",SUMIFS(INDEX(Inputs!$D$4:$AG$150,0,MATCH(D$2,Inputs!$D$2:$AG$2,0)),Inputs!$B$4:$B$150,$B61)/1000) -> 22264 | E61: =IF(SUMPRODUCT((Inputs!$B$4:$B$150=$B61)*ISNUMBER(INDEX(Inputs!$D$4:$AG$150,0,MATCH(E$2,Inputs!$D$2:$AG$2,0))))=0,"",SUMIFS(INDEX(Inputs!$D$4:$AG$150,0,MATCH(E$2,Inputs!$D$2:$AG$2,0)),Inputs!$B$4:$B$150,$B61)/1000) -> 18943 | F61: =IF(SUMPRODUCT((Inputs!$B$4:$B$150=$B61)*ISNUMBER(INDEX(Inputs!$D$4:$AG$150,0,MATCH(F$2,Inputs!$D$2:$AG$2,0))))=0,"",SUMIFS(INDEX(Inputs!$D$4:$AG$150,0,MATCH(F$2,Inputs!$D$2:$AG$2,0)),Inputs!$B$4:$B$150,$B61)/1000) -> 20794 | G61: =IF(SUMPRODUCT((Inputs!$B$4:$B$150=$B61)*ISNUMBER(INDEX(Inputs!$D$4:$AG$150,0,MATCH(G$2,Inputs!$D$2:$AG$2,0))))=0,"",SUMIFS(INDEX(Inputs!$D$4:$AG$150,0,MATCH(G$2,Inputs!$D$2:$AG$2,0)),Inputs!$B$4:$B$150,$B61)/1000) -> 29749 | H61: =IF(COUNT(D61:G61)=4,SUM(D61:G61),"") -> 91750 | I61: =IF(SUMPRODUCT((Inputs!$B$4:$B$150=$B61)*ISNUMBER(INDEX(Inputs!$D$4:$AG$150,0,MATCH(I$2,Inputs!$D$2:$AG$2,0))))=0,"",SUMIFS(INDEX(Inputs!$D$4:$AG$150,0,MATCH(I$2,Inputs!$D$2:$AG$2,0)),Inputs!$B$4:$B$150,$B61)/1000) -> 23287 | J61: =IF(SUMPRODUCT((Inputs!$B$4:$B$150=$B61)*ISNUMBER(INDEX(Inputs!$D$4:$AG$150,0,MATCH(J$2,Inputs!$D$2:$AG$2,0))))=0,"",SUMIFS(INDEX(Inputs!$D$4:$AG$150,0,MATCH(J$2,Inputs!$D$2:$AG$2,0)),Inputs!$B$4:$B$150,$B61)/1000) -> 19287 | K61: =IF(SUMPRODUCT((Inputs!$B$4:$B$150=$B61)*ISNUMBER(INDEX(Inputs!$D$4:$AG$150,0,MATCH(K$2,Inputs!$D$2:$AG$2,0))))=0,"",SUMIFS(INDEX(Inputs!$D$4:$AG$150,0,MATCH(K$2,Inputs!$D$2:$AG$2,0)),Inputs!$B$4:$B$150,$B61)/1000) -> 22795 | L61: =IF(SUMPRODUCT((Inputs!$B$4:$B$150=$B61)*ISNUMBER(INDEX(Inputs!$D$4:$AG$150,0,MATCH(L$2,Inputs!$D$2:$AG$2,0))))=0,"",SUMIFS(INDEX(Inputs!$D$4:$AG$150,0,MATCH(L$2,Inputs!$D$2:$AG$2,0)),Inputs!$B$4:$B$150,$B61)/1000) -> 27681 | M61: =IF(COUNT(I61:L61)=4,SUM(I61:L61),"") -> 93050 | N61: =IF(SUMPRODUCT((Inputs!$B$4:$B$150=$B61)*ISNUMBER(INDEX(Inputs!$D$4:$AG$150,0,MATCH(N$2,Inputs!$D$2:$AG$2,0))))=0,"",SUMIFS(INDEX(Inputs!$D$4:$AG$150,0,MATCH(N$2,Inputs!$D$2:$AG$2,0)),Inputs!$B$4:$B$150,$B61)/1000) -> 23945 | O61: =IF(SUMPRODUCT((Inputs!$B$4:$B$150=$B61)*ISNUMBER(INDEX(Inputs!$D$4:$AG$150,0,MATCH(O$2,Inputs!$D$2:$AG$2,0))))=0,"",SUMIFS(INDEX(Inputs!$D$4:$AG$150,0,MATCH(O$2,Inputs!$D$2:$AG$2,0)),Inputs!$B$4:$B$150,$B61)/1000) -> 20205 | P61: =IF(SUMPRODUCT((Inputs!$B$4:$B$150=$B61)*ISNUMBER(INDEX(Inputs!$D$4:$AG$150,0,MATCH(P$2,Inputs!$D$2:$AG$2,0))))=0,"",SUMIFS(INDEX(Inputs!$D$4:$AG$150,0,MATCH(P$2,Inputs!$D$2:$AG$2,0)),Inputs!$B$4:$B$150,$B61)/1000) -> 22463 | Q61: =IF(SUMPRODUCT((Inputs!$B$4:$B$150=$B61)*ISNUMBER(INDEX(Inputs!$D$4:$AG$150,0,MATCH(Q$2,Inputs!$D$2:$AG$2,0))))=0,"",SUMIFS(INDEX(Inputs!$D$4:$AG$150,0,MATCH(Q$2,Inputs!$D$2:$AG$2,0)),Inputs!$B$4:$B$150,$B61)/1000) -> 30397 | R61: =IF(COUNT(N61:Q61)=4,SUM(N61:Q61),"") -> 97010 | S61: =IF(SUMPRODUCT((Inputs!$B$4:$B$150=$B61)*ISNUMBER(INDEX(Inputs!$D$4:$AG$150,0,MATCH(S$2,Inputs!$D$2:$AG$2,0))))=0,"",SUMIFS(INDEX(Inputs!$D$4:$AG$150,0,MATCH(S$2,Inputs!$D$2:$AG$2,0)),Inputs!$B$4:$B$150,$B61)/1000) -> 24123 | T61: =IF(SUMPRODUCT((Inputs!$B$4:$B$150=$B61)*ISNUMBER(INDEX(Inputs!$D$4:$AG$150,0,MATCH(T$2,Inputs!$D$2:$AG$2,0))))=0,"",SUMIFS(INDEX(Inputs!$D$4:$AG$150,0,MATCH(T$2,Inputs!$D$2:$AG$2,0)),Inputs!$B$4:$B$150,$B61)/1000) -> 21884 | U61: =IF(SUMPRODUCT((Inputs!$B$4:$B$150=$B61)*ISNUMBER(INDEX(Inputs!$D$4:$AG$150,0,MATCH(U$2,Inputs!$D$2:$AG$2,0))))=0,"",SUMIFS(INDEX(Inputs!$D$4:$AG$150,0,MATCH(U$2,Inputs!$D$2:$AG$2,0)),Inputs!$B$4:$B$150,$B61)/1000) -> 24924 | V61: =IF(SUMPRODUCT((Inputs!$B$4:$B$150=$B61)*ISNUMBER(INDEX(Inputs!$D$4:$AG$150,0,MATCH(V$2,Inputs!$D$2:$AG$2,0))))=0,"",SUMIFS(INDEX(Inputs!$D$4:$AG$150,0,MATCH(V$2,Inputs!$D$2:$AG$2,0)),Inputs!$B$4:$B$150,$B61)/1000) -> 33861 | W61: =IF(COUNT(S61:V61)=4,SUM(S61:V61),"") -> 104792 | X61: =IF(SUMPRODUCT((Inputs!$B$4:$B$150=$B61)*ISNUMBER(INDEX(Inputs!$D$4:$AG$150,0,MATCH(X$2,Inputs!$D$2:$AG$2,0))))=0,"",SUMIFS(INDEX(Inputs!$D$4:$AG$150,0,MATCH(X$2,Inputs!$D$2:$AG$2,0)),Inputs!$B$4:$B$150,$B61)/1000) -> 24454 | Y61: =IF(SUMPRODUCT((Inputs!$B$4:$B$150=$B61)*ISNUMBER(INDEX(Inputs!$D$4:$AG$150,0,MATCH(Y$2,Inputs!$D$2:$AG$2,0))))=0,"",SUMIFS(INDEX(Inputs!$D$4:$AG$150,0,MATCH(Y$2,Inputs!$D$2:$AG$2,0)),Inputs!$B$4:$B$150,$B61)/1000) -> 24014 | Z61: =IF(SUMPRODUCT((Inputs!$B$4:$B$150=$B61)*ISNUMBER(INDEX(Inputs!$D$4:$AG$150,0,MATCH(Z$2,Inputs!$D$2:$AG$2,0))))=0,"",SUMIFS(INDEX(Inputs!$D$4:$AG$150,0,MATCH(Z$2,Inputs!$D$2:$AG$2,0)),Inputs!$B$4:$B$150,$B61)/1000) -> 28703 | AA61: =IF(SUMPRODUCT((Inputs!$B$4:$B$150=$B61)*ISNUMBER(INDEX(Inputs!$D$4:$AG$150,0,MATCH(AA$2,Inputs!$D$2:$AG$2,0))))=0,"",SUMIFS(INDEX(Inputs!$D$4:$AG$150,0,MATCH(AA$2,Inputs!$D$2:$AG$2,0)),Inputs!$B$4:$B$150,$B61)/1000) -> 38146 | AB61: =IF(COUNT(X61:AA61)=4,SUM(X61:AA61),"") -> 115317 | AC61: =IF(SUMPRODUCT((Inputs!$B$4:$B$150=$B61)*ISNUMBER(INDEX(Inputs!$D$4:$AG$150,0,MATCH(AC$2,Inputs!$D$2:$AG$2,0))))=0,"",SUMIFS(INDEX(Inputs!$D$4:$AG$150,0,MATCH(AC$2,Inputs!$D$2:$AG$2,0)),Inputs!$B$4:$B$150,$B61)/1000) -> 28055 | AD61: =IF(SUMPRODUCT((Inputs!$B$4:$B$150=$B61)*ISNUMBER(INDEX(Inputs!$D$4:$AG$150,0,MATCH(AD$2,Inputs!$D$2:$AG$2,0))))=0,"",SUMIFS(INDEX(Inputs!$D$4:$AG$150,0,MATCH(AD$2,Inputs!$D$2:$AG$2,0)),Inputs!$B$4:$B$150,$B61)/1000) -> 29395 | AE61: =IF(SUMPRODUCT((Inputs!$B$4:$B$150=$B61)*ISNUMBER(INDEX(Inputs!$D$4:$AG$150,0,MATCH(AE$2,Inputs!$D$2:$AG$2,0))))=0,"",SUMIFS(INDEX(Inputs!$D$4:$AG$150,0,MATCH(AE$2,Inputs!$D$2:$AG$2,0)),Inputs!$B$4:$B$150,$B61)/1000) | AF61: =IF(SUMPRODUCT((Inputs!$B$4:$B$150=$B61)*ISNUMBER(INDEX(Inputs!$D$4:$AG$150,0,MATCH(AF$2,Inputs!$D$2:$AG$2,0))))=0,"",SUMIFS(INDEX(Inputs!$D$4:$AG$150,0,MATCH(AF$2,Inputs!$D$2:$AG$2,0)),Inputs!$B$4:$B$150,$B61)/1000) | AG61: =IF(COUNT(AC61:AF61)=4,SUM(AC61:AF61),"")
B62: 54 | C62: Receita segmento Grande China (USD) | D62: =IF(SUMPRODUCT((Inputs!$B$4:$B$150=$B62)*ISNUMBER(INDEX(Inputs!$D$4:$AG$150,0,MATCH(D$2,Inputs!$D$2:$AG$2,0))))=0,"",SUMIFS(INDEX(Inputs!$D$4:$AG$150,0,MATCH(D$2,Inputs!$D$2:$AG$2,0)),Inputs!$B$4:$B$150,$B62)/1000) -> 17728 | E62: =IF(SUMPRODUCT((Inputs!$B$4:$B$150=$B62)*ISNUMBER(INDEX(Inputs!$D$4:$AG$150,0,MATCH(E$2,Inputs!$D$2:$AG$2,0))))=0,"",SUMIFS(INDEX(Inputs!$D$4:$AG$150,0,MATCH(E$2,Inputs!$D$2:$AG$2,0)),Inputs!$B$4:$B$150,$B62)/1000) -> 14762 | F62: =IF(SUMPRODUCT((Inputs!$B$4:$B$150=$B62)*ISNUMBER(INDEX(Inputs!$D$4:$AG$150,0,MATCH(F$2,Inputs!$D$2:$AG$2,0))))=0,"",SUMIFS(INDEX(Inputs!$D$4:$AG$150,0,MATCH(F$2,Inputs!$D$2:$AG$2,0)),Inputs!$B$4:$B$150,$B62)/1000) -> 14563 | G62: =IF(SUMPRODUCT((Inputs!$B$4:$B$150=$B62)*ISNUMBER(INDEX(Inputs!$D$4:$AG$150,0,MATCH(G$2,Inputs!$D$2:$AG$2,0))))=0,"",SUMIFS(INDEX(Inputs!$D$4:$AG$150,0,MATCH(G$2,Inputs!$D$2:$AG$2,0)),Inputs!$B$4:$B$150,$B62)/1000) -> 25783 | H62: =IF(COUNT(D62:G62)=4,SUM(D62:G62),"") -> 72836 | I62: =IF(SUMPRODUCT((Inputs!$B$4:$B$150=$B62)*ISNUMBER(INDEX(Inputs!$D$4:$AG$150,0,MATCH(I$2,Inputs!$D$2:$AG$2,0))))=0,"",SUMIFS(INDEX(Inputs!$D$4:$AG$150,0,MATCH(I$2,Inputs!$D$2:$AG$2,0)),Inputs!$B$4:$B$150,$B62)/1000) -> 18343 | J62: =IF(SUMPRODUCT((Inputs!$B$4:$B$150=$B62)*ISNUMBER(INDEX(Inputs!$D$4:$AG$150,0,MATCH(J$2,Inputs!$D$2:$AG$2,0))))=0,"",SUMIFS(INDEX(Inputs!$D$4:$AG$150,0,MATCH(J$2,Inputs!$D$2:$AG$2,0)),Inputs!$B$4:$B$150,$B62)/1000) -> 14604 | K62: =IF(SUMPRODUCT((Inputs!$B$4:$B$150=$B62)*ISNUMBER(INDEX(Inputs!$D$4:$AG$150,0,MATCH(K$2,Inputs!$D$2:$AG$2,0))))=0,"",SUMIFS(INDEX(Inputs!$D$4:$AG$150,0,MATCH(K$2,Inputs!$D$2:$AG$2,0)),Inputs!$B$4:$B$150,$B62)/1000) -> 15470 | L62: =IF(SUMPRODUCT((Inputs!$B$4:$B$150=$B62)*ISNUMBER(INDEX(Inputs!$D$4:$AG$150,0,MATCH(L$2,Inputs!$D$2:$AG$2,0))))=0,"",SUMIFS(INDEX(Inputs!$D$4:$AG$150,0,MATCH(L$2,Inputs!$D$2:$AG$2,0)),Inputs!$B$4:$B$150,$B62)/1000) -> 23905 | M62: =IF(COUNT(I62:L62)=4,SUM(I62:L62),"") -> 72322 | N62: =IF(SUMPRODUCT((Inputs!$B$4:$B$150=$B62)*ISNUMBER(INDEX(Inputs!$D$4:$AG$150,0,MATCH(N$2,Inputs!$D$2:$AG$2,0))))=0,"",SUMIFS(INDEX(Inputs!$D$4:$AG$150,0,MATCH(N$2,Inputs!$D$2:$AG$2,0)),Inputs!$B$4:$B$150,$B62)/1000) -> 17812 | O62: =IF(SUMPRODUCT((Inputs!$B$4:$B$150=$B62)*ISNUMBER(INDEX(Inputs!$D$4:$AG$150,0,MATCH(O$2,Inputs!$D$2:$AG$2,0))))=0,"",SUMIFS(INDEX(Inputs!$D$4:$AG$150,0,MATCH(O$2,Inputs!$D$2:$AG$2,0)),Inputs!$B$4:$B$150,$B62)/1000) -> 15758 | P62: =IF(SUMPRODUCT((Inputs!$B$4:$B$150=$B62)*ISNUMBER(INDEX(Inputs!$D$4:$AG$150,0,MATCH(P$2,Inputs!$D$2:$AG$2,0))))=0,"",SUMIFS(INDEX(Inputs!$D$4:$AG$150,0,MATCH(P$2,Inputs!$D$2:$AG$2,0)),Inputs!$B$4:$B$150,$B62)/1000) -> 15084 | Q62: =IF(SUMPRODUCT((Inputs!$B$4:$B$150=$B62)*ISNUMBER(INDEX(Inputs!$D$4:$AG$150,0,MATCH(Q$2,Inputs!$D$2:$AG$2,0))))=0,"",SUMIFS(INDEX(Inputs!$D$4:$AG$150,0,MATCH(Q$2,Inputs!$D$2:$AG$2,0)),Inputs!$B$4:$B$150,$B62)/1000) -> 20819 | R62: =IF(COUNT(N62:Q62)=4,SUM(N62:Q62),"") -> 69473 | S62: =IF(SUMPRODUCT((Inputs!$B$4:$B$150=$B62)*ISNUMBER(INDEX(Inputs!$D$4:$AG$150,0,MATCH(S$2,Inputs!$D$2:$AG$2,0))))=0,"",SUMIFS(INDEX(Inputs!$D$4:$AG$150,0,MATCH(S$2,Inputs!$D$2:$AG$2,0)),Inputs!$B$4:$B$150,$B62)/1000) -> 16372 | T62: =IF(SUMPRODUCT((Inputs!$B$4:$B$150=$B62)*ISNUMBER(INDEX(Inputs!$D$4:$AG$150,0,MATCH(T$2,Inputs!$D$2:$AG$2,0))))=0,"",SUMIFS(INDEX(Inputs!$D$4:$AG$150,0,MATCH(T$2,Inputs!$D$2:$AG$2,0)),Inputs!$B$4:$B$150,$B62)/1000) -> 14728 | U62: =IF(SUMPRODUCT((Inputs!$B$4:$B$150=$B62)*ISNUMBER(INDEX(Inputs!$D$4:$AG$150,0,MATCH(U$2,Inputs!$D$2:$AG$2,0))))=0,"",SUMIFS(INDEX(Inputs!$D$4:$AG$150,0,MATCH(U$2,Inputs!$D$2:$AG$2,0)),Inputs!$B$4:$B$150,$B62)/1000) -> 15033 | V62: =IF(SUMPRODUCT((Inputs!$B$4:$B$150=$B62)*ISNUMBER(INDEX(Inputs!$D$4:$AG$150,0,MATCH(V$2,Inputs!$D$2:$AG$2,0))))=0,"",SUMIFS(INDEX(Inputs!$D$4:$AG$150,0,MATCH(V$2,Inputs!$D$2:$AG$2,0)),Inputs!$B$4:$B$150,$B62)/1000) -> 18513 | W62: =IF(COUNT(S62:V62)=4,SUM(S62:V62),"") -> 64646 | X62: =IF(SUMPRODUCT((Inputs!$B$4:$B$150=$B62)*ISNUMBER(INDEX(Inputs!$D$4:$AG$150,0,MATCH(X$2,Inputs!$D$2:$AG$2,0))))=0,"",SUMIFS(INDEX(Inputs!$D$4:$AG$150,0,MATCH(X$2,Inputs!$D$2:$AG$2,0)),Inputs!$B$4:$B$150,$B62)/1000) -> 16002 | Y62: =IF(SUMPRODUCT((Inputs!$B$4:$B$150=$B62)*ISNUMBER(INDEX(Inputs!$D$4:$AG$150,0,MATCH(Y$2,Inputs!$D$2:$AG$2,0))))=0,"",SUMIFS(INDEX(Inputs!$D$4:$AG$150,0,MATCH(Y$2,Inputs!$D$2:$AG$2,0)),Inputs!$B$4:$B$150,$B62)/1000) -> 15369 | Z62: =IF(SUMPRODUCT((Inputs!$B$4:$B$150=$B62)*ISNUMBER(INDEX(Inputs!$D$4:$AG$150,0,MATCH(Z$2,Inputs!$D$2:$AG$2,0))))=0,"",SUMIFS(INDEX(Inputs!$D$4:$AG$150,0,MATCH(Z$2,Inputs!$D$2:$AG$2,0)),Inputs!$B$4:$B$150,$B62)/1000) -> 14493 | AA62: =IF(SUMPRODUCT((Inputs!$B$4:$B$150=$B62)*ISNUMBER(INDEX(Inputs!$D$4:$AG$150,0,MATCH(AA$2,Inputs!$D$2:$AG$2,0))))=0,"",SUMIFS(INDEX(Inputs!$D$4:$AG$150,0,MATCH(AA$2,Inputs!$D$2:$AG$2,0)),Inputs!$B$4:$B$150,$B62)/1000) -> 25526 | AB62: =IF(COUNT(X62:AA62)=4,SUM(X62:AA62),"") -> 71390 | AC62: =IF(SUMPRODUCT((Inputs!$B$4:$B$150=$B62)*ISNUMBER(INDEX(Inputs!$D$4:$AG$150,0,MATCH(AC$2,Inputs!$D$2:$AG$2,0))))=0,"",SUMIFS(INDEX(Inputs!$D$4:$AG$150,0,MATCH(AC$2,Inputs!$D$2:$AG$2,0)),Inputs!$B$4:$B$150,$B62)/1000) -> 20497 | AD62: =IF(SUMPRODUCT((Inputs!$B$4:$B$150=$B62)*ISNUMBER(INDEX(Inputs!$D$4:$AG$150,0,MATCH(AD$2,Inputs!$D$2:$AG$2,0))))=0,"",SUMIFS(INDEX(Inputs!$D$4:$AG$150,0,MATCH(AD$2,Inputs!$D$2:$AG$2,0)),Inputs!$B$4:$B$150,$B62)/1000) -> 18816 | AE62: =IF(SUMPRODUCT((Inputs!$B$4:$B$150=$B62)*ISNUMBER(INDEX(Inputs!$D$4:$AG$150,0,MATCH(AE$2,Inputs!$D$2:$AG$2,0))))=0,"",SUMIFS(INDEX(Inputs!$D$4:$AG$150,0,MATCH(AE$2,Inputs!$D$2:$AG$2,0)),Inputs!$B$4:$B$150,$B62)/1000) | AF62: =IF(SUMPRODUCT((Inputs!$B$4:$B$150=$B62)*ISNUMBER(INDEX(Inputs!$D$4:$AG$150,0,MATCH(AF$2,Inputs!$D$2:$AG$2,0))))=0,"",SUMIFS(INDEX(Inputs!$D$4:$AG$150,0,MATCH(AF$2,Inputs!$D$2:$AG$2,0)),Inputs!$B$4:$B$150,$B62)/1000) | AG62: =IF(COUNT(AC62:AF62)=4,SUM(AC62:AF62),"")
B63: 55 | C63: Receita segmento Japão (USD) | D63: =IF(SUMPRODUCT((Inputs!$B$4:$B$150=$B63)*ISNUMBER(INDEX(Inputs!$D$4:$AG$150,0,MATCH(D$2,Inputs!$D$2:$AG$2,0))))=0,"",SUMIFS(INDEX(Inputs!$D$4:$AG$150,0,MATCH(D$2,Inputs!$D$2:$AG$2,0)),Inputs!$B$4:$B$150,$B63)/1000) -> 7742 | E63: =IF(SUMPRODUCT((Inputs!$B$4:$B$150=$B63)*ISNUMBER(INDEX(Inputs!$D$4:$AG$150,0,MATCH(E$2,Inputs!$D$2:$AG$2,0))))=0,"",SUMIFS(INDEX(Inputs!$D$4:$AG$150,0,MATCH(E$2,Inputs!$D$2:$AG$2,0)),Inputs!$B$4:$B$150,$B63)/1000) -> 6464 | F63: =IF(SUMPRODUCT((Inputs!$B$4:$B$150=$B63)*ISNUMBER(INDEX(Inputs!$D$4:$AG$150,0,MATCH(F$2,Inputs!$D$2:$AG$2,0))))=0,"",SUMIFS(INDEX(Inputs!$D$4:$AG$150,0,MATCH(F$2,Inputs!$D$2:$AG$2,0)),Inputs!$B$4:$B$150,$B63)/1000) -> 5991 | G63: =IF(SUMPRODUCT((Inputs!$B$4:$B$150=$B63)*ISNUMBER(INDEX(Inputs!$D$4:$AG$150,0,MATCH(G$2,Inputs!$D$2:$AG$2,0))))=0,"",SUMIFS(INDEX(Inputs!$D$4:$AG$150,0,MATCH(G$2,Inputs!$D$2:$AG$2,0)),Inputs!$B$4:$B$150,$B63)/1000) -> 7107 | H63: =IF(COUNT(D63:G63)=4,SUM(D63:G63),"") -> 27304 | I63: =IF(SUMPRODUCT((Inputs!$B$4:$B$150=$B63)*ISNUMBER(INDEX(Inputs!$D$4:$AG$150,0,MATCH(I$2,Inputs!$D$2:$AG$2,0))))=0,"",SUMIFS(INDEX(Inputs!$D$4:$AG$150,0,MATCH(I$2,Inputs!$D$2:$AG$2,0)),Inputs!$B$4:$B$150,$B63)/1000) -> 7724 | J63: =IF(SUMPRODUCT((Inputs!$B$4:$B$150=$B63)*ISNUMBER(INDEX(Inputs!$D$4:$AG$150,0,MATCH(J$2,Inputs!$D$2:$AG$2,0))))=0,"",SUMIFS(INDEX(Inputs!$D$4:$AG$150,0,MATCH(J$2,Inputs!$D$2:$AG$2,0)),Inputs!$B$4:$B$150,$B63)/1000) -> 5446 | K63: =IF(SUMPRODUCT((Inputs!$B$4:$B$150=$B63)*ISNUMBER(INDEX(Inputs!$D$4:$AG$150,0,MATCH(K$2,Inputs!$D$2:$AG$2,0))))=0,"",SUMIFS(INDEX(Inputs!$D$4:$AG$150,0,MATCH(K$2,Inputs!$D$2:$AG$2,0)),Inputs!$B$4:$B$150,$B63)/1000) -> 5700 | L63: =IF(SUMPRODUCT((Inputs!$B$4:$B$150=$B63)*ISNUMBER(INDEX(Inputs!$D$4:$AG$150,0,MATCH(L$2,Inputs!$D$2:$AG$2,0))))=0,"",SUMIFS(INDEX(Inputs!$D$4:$AG$150,0,MATCH(L$2,Inputs!$D$2:$AG$2,0)),Inputs!$B$4:$B$150,$B63)/1000) -> 6755 | M63: =IF(COUNT(I63:L63)=4,SUM(I63:L63),"") -> 25625 | N63: =IF(SUMPRODUCT((Inputs!$B$4:$B$150=$B63)*ISNUMBER(INDEX(Inputs!$D$4:$AG$150,0,MATCH(N$2,Inputs!$D$2:$AG$2,0))))=0,"",SUMIFS(INDEX(Inputs!$D$4:$AG$150,0,MATCH(N$2,Inputs!$D$2:$AG$2,0)),Inputs!$B$4:$B$150,$B63)/1000) -> 7176 | O63: =IF(SUMPRODUCT((Inputs!$B$4:$B$150=$B63)*ISNUMBER(INDEX(Inputs!$D$4:$AG$150,0,MATCH(O$2,Inputs!$D$2:$AG$2,0))))=0,"",SUMIFS(INDEX(Inputs!$D$4:$AG$150,0,MATCH(O$2,Inputs!$D$2:$AG$2,0)),Inputs!$B$4:$B$150,$B63)/1000) -> 4821 | P63: =IF(SUMPRODUCT((Inputs!$B$4:$B$150=$B63)*ISNUMBER(INDEX(Inputs!$D$4:$AG$150,0,MATCH(P$2,Inputs!$D$2:$AG$2,0))))=0,"",SUMIFS(INDEX(Inputs!$D$4:$AG$150,0,MATCH(P$2,Inputs!$D$2:$AG$2,0)),Inputs!$B$4:$B$150,$B63)/1000) -> 5505 | Q63: =IF(SUMPRODUCT((Inputs!$B$4:$B$150=$B63)*ISNUMBER(INDEX(Inputs!$D$4:$AG$150,0,MATCH(Q$2,Inputs!$D$2:$AG$2,0))))=0,"",SUMIFS(INDEX(Inputs!$D$4:$AG$150,0,MATCH(Q$2,Inputs!$D$2:$AG$2,0)),Inputs!$B$4:$B$150,$B63)/1000) -> 7767 | R63: =IF(COUNT(N63:Q63)=4,SUM(N63:Q63),"") -> 25269 | S63: =IF(SUMPRODUCT((Inputs!$B$4:$B$150=$B63)*ISNUMBER(INDEX(Inputs!$D$4:$AG$150,0,MATCH(S$2,Inputs!$D$2:$AG$2,0))))=0,"",SUMIFS(INDEX(Inputs!$D$4:$AG$150,0,MATCH(S$2,Inputs!$D$2:$AG$2,0)),Inputs!$B$4:$B$150,$B63)/1000) -> 6262 | T63: =IF(SUMPRODUCT((Inputs!$B$4:$B$150=$B63)*ISNUMBER(INDEX(Inputs!$D$4:$AG$150,0,MATCH(T$2,Inputs!$D$2:$AG$2,0))))=0,"",SUMIFS(INDEX(Inputs!$D$4:$AG$150,0,MATCH(T$2,Inputs!$D$2:$AG$2,0)),Inputs!$B$4:$B$150,$B63)/1000) -> 5097 | U63: =IF(SUMPRODUCT((Inputs!$B$4:$B$150=$B63)*ISNUMBER(INDEX(Inputs!$D$4:$AG$150,0,MATCH(U$2,Inputs!$D$2:$AG$2,0))))=0,"",SUMIFS(INDEX(Inputs!$D$4:$AG$150,0,MATCH(U$2,Inputs!$D$2:$AG$2,0)),Inputs!$B$4:$B$150,$B63)/1000) -> 5926 | V63: =IF(SUMPRODUCT((Inputs!$B$4:$B$150=$B63)*ISNUMBER(INDEX(Inputs!$D$4:$AG$150,0,MATCH(V$2,Inputs!$D$2:$AG$2,0))))=0,"",SUMIFS(INDEX(Inputs!$D$4:$AG$150,0,MATCH(V$2,Inputs!$D$2:$AG$2,0)),Inputs!$B$4:$B$150,$B63)/1000) -> 8987 | W63: =IF(COUNT(S63:V63)=4,SUM(S63:V63),"") -> 26272 | X63: =IF(SUMPRODUCT((Inputs!$B$4:$B$150=$B63)*ISNUMBER(INDEX(Inputs!$D$4:$AG$150,0,MATCH(X$2,Inputs!$D$2:$AG$2,0))))=0,"",SUMIFS(INDEX(Inputs!$D$4:$AG$150,0,MATCH(X$2,Inputs!$D$2:$AG$2,0)),Inputs!$B$4:$B$150,$B63)/1000) -> 7298 | Y63: =IF(SUMPRODUCT((Inputs!$B$4:$B$150=$B63)*ISNUMBER(INDEX(Inputs!$D$4:$AG$150,0,MATCH(Y$2,Inputs!$D$2:$AG$2,0))))=0,"",SUMIFS(INDEX(Inputs!$D$4:$AG$150,0,MATCH(Y$2,Inputs!$D$2:$AG$2,0)),Inputs!$B$4:$B$150,$B63)/1000) -> 5782 | Z63: =IF(SUMPRODUCT((Inputs!$B$4:$B$150=$B63)*ISNUMBER(INDEX(Inputs!$D$4:$AG$150,0,MATCH(Z$2,Inputs!$D$2:$AG$2,0))))=0,"",SUMIFS(INDEX(Inputs!$D$4:$AG$150,0,MATCH(Z$2,Inputs!$D$2:$AG$2,0)),Inputs!$B$4:$B$150,$B63)/1000) -> 6636 | AA63: =IF(SUMPRODUCT((Inputs!$B$4:$B$150=$B63)*ISNUMBER(INDEX(Inputs!$D$4:$AG$150,0,MATCH(AA$2,Inputs!$D$2:$AG$2,0))))=0,"",SUMIFS(INDEX(Inputs!$D$4:$AG$150,0,MATCH(AA$2,Inputs!$D$2:$AG$2,0)),Inputs!$B$4:$B$150,$B63)/1000) -> 9413 | AB63: =IF(COUNT(X63:AA63)=4,SUM(X63:AA63),"") -> 29129 | AC63: =IF(SUMPRODUCT((Inputs!$B$4:$B$150=$B63)*ISNUMBER(INDEX(Inputs!$D$4:$AG$150,0,MATCH(AC$2,Inputs!$D$2:$AG$2,0))))=0,"",SUMIFS(INDEX(Inputs!$D$4:$AG$150,0,MATCH(AC$2,Inputs!$D$2:$AG$2,0)),Inputs!$B$4:$B$150,$B63)/1000) -> 8401 | AD63: =IF(SUMPRODUCT((Inputs!$B$4:$B$150=$B63)*ISNUMBER(INDEX(Inputs!$D$4:$AG$150,0,MATCH(AD$2,Inputs!$D$2:$AG$2,0))))=0,"",SUMIFS(INDEX(Inputs!$D$4:$AG$150,0,MATCH(AD$2,Inputs!$D$2:$AG$2,0)),Inputs!$B$4:$B$150,$B63)/1000) -> 6554 | AE63: =IF(SUMPRODUCT((Inputs!$B$4:$B$150=$B63)*ISNUMBER(INDEX(Inputs!$D$4:$AG$150,0,MATCH(AE$2,Inputs!$D$2:$AG$2,0))))=0,"",SUMIFS(INDEX(Inputs!$D$4:$AG$150,0,MATCH(AE$2,Inputs!$D$2:$AG$2,0)),Inputs!$B$4:$B$150,$B63)/1000) | AF63: =IF(SUMPRODUCT((Inputs!$B$4:$B$150=$B63)*ISNUMBER(INDEX(Inputs!$D$4:$AG$150,0,MATCH(AF$2,Inputs!$D$2:$AG$2,0))))=0,"",SUMIFS(INDEX(Inputs!$D$4:$AG$150,0,MATCH(AF$2,Inputs!$D$2:$AG$2,0)),Inputs!$B$4:$B$150,$B63)/1000) | AG63: =IF(COUNT(AC63:AF63)=4,SUM(AC63:AF63),"")
B64: 56 | C64: Receita segmento Resto da Ásia-Pacífico (USD) | D64: =IF(SUMPRODUCT((Inputs!$B$4:$B$150=$B64)*ISNUMBER(INDEX(Inputs!$D$4:$AG$150,0,MATCH(D$2,Inputs!$D$2:$AG$2,0))))=0,"",SUMIFS(INDEX(Inputs!$D$4:$AG$150,0,MATCH(D$2,Inputs!$D$2:$AG$2,0)),Inputs!$B$4:$B$150,$B64)/1000) -> 7544 | E64: =IF(SUMPRODUCT((Inputs!$B$4:$B$150=$B64)*ISNUMBER(INDEX(Inputs!$D$4:$AG$150,0,MATCH(E$2,Inputs!$D$2:$AG$2,0))))=0,"",SUMIFS(INDEX(Inputs!$D$4:$AG$150,0,MATCH(E$2,Inputs!$D$2:$AG$2,0)),Inputs!$B$4:$B$150,$B64)/1000) -> 5395 | F64: =IF(SUMPRODUCT((Inputs!$B$4:$B$150=$B64)*ISNUMBER(INDEX(Inputs!$D$4:$AG$150,0,MATCH(F$2,Inputs!$D$2:$AG$2,0))))=0,"",SUMIFS(INDEX(Inputs!$D$4:$AG$150,0,MATCH(F$2,Inputs!$D$2:$AG$2,0)),Inputs!$B$4:$B$150,$B64)/1000) -> 5192 | G64: =IF(SUMPRODUCT((Inputs!$B$4:$B$150=$B64)*ISNUMBER(INDEX(Inputs!$D$4:$AG$150,0,MATCH(G$2,Inputs!$D$2:$AG$2,0))))=0,"",SUMIFS(INDEX(Inputs!$D$4:$AG$150,0,MATCH(G$2,Inputs!$D$2:$AG$2,0)),Inputs!$B$4:$B$150,$B64)/1000) -> 9810 | H64: =IF(COUNT(D64:G64)=4,SUM(D64:G64),"") -> 27941 | I64: =IF(SUMPRODUCT((Inputs!$B$4:$B$150=$B64)*ISNUMBER(INDEX(Inputs!$D$4:$AG$150,0,MATCH(I$2,Inputs!$D$2:$AG$2,0))))=0,"",SUMIFS(INDEX(Inputs!$D$4:$AG$150,0,MATCH(I$2,Inputs!$D$2:$AG$2,0)),Inputs!$B$4:$B$150,$B64)/1000) -> 7042 | J64: =IF(SUMPRODUCT((Inputs!$B$4:$B$150=$B64)*ISNUMBER(INDEX(Inputs!$D$4:$AG$150,0,MATCH(J$2,Inputs!$D$2:$AG$2,0))))=0,"",SUMIFS(INDEX(Inputs!$D$4:$AG$150,0,MATCH(J$2,Inputs!$D$2:$AG$2,0)),Inputs!$B$4:$B$150,$B64)/1000) -> 6150 | K64: =IF(SUMPRODUCT((Inputs!$B$4:$B$150=$B64)*ISNUMBER(INDEX(Inputs!$D$4:$AG$150,0,MATCH(K$2,Inputs!$D$2:$AG$2,0))))=0,"",SUMIFS(INDEX(Inputs!$D$4:$AG$150,0,MATCH(K$2,Inputs!$D$2:$AG$2,0)),Inputs!$B$4:$B$150,$B64)/1000) -> 6373 | L64: =IF(SUMPRODUCT((Inputs!$B$4:$B$150=$B64)*ISNUMBER(INDEX(Inputs!$D$4:$AG$150,0,MATCH(L$2,Inputs!$D$2:$AG$2,0))))=0,"",SUMIFS(INDEX(Inputs!$D$4:$AG$150,0,MATCH(L$2,Inputs!$D$2:$AG$2,0)),Inputs!$B$4:$B$150,$B64)/1000) -> 9535 | M64: =IF(COUNT(I64:L64)=4,SUM(I64:L64),"") -> 29100 | N64: =IF(SUMPRODUCT((Inputs!$B$4:$B$150=$B64)*ISNUMBER(INDEX(Inputs!$D$4:$AG$150,0,MATCH(N$2,Inputs!$D$2:$AG$2,0))))=0,"",SUMIFS(INDEX(Inputs!$D$4:$AG$150,0,MATCH(N$2,Inputs!$D$2:$AG$2,0)),Inputs!$B$4:$B$150,$B64)/1000) -> 8119 | O64: =IF(SUMPRODUCT((Inputs!$B$4:$B$150=$B64)*ISNUMBER(INDEX(Inputs!$D$4:$AG$150,0,MATCH(O$2,Inputs!$D$2:$AG$2,0))))=0,"",SUMIFS(INDEX(Inputs!$D$4:$AG$150,0,MATCH(O$2,Inputs!$D$2:$AG$2,0)),Inputs!$B$4:$B$150,$B64)/1000) -> 5630 | P64: =IF(SUMPRODUCT((Inputs!$B$4:$B$150=$B64)*ISNUMBER(INDEX(Inputs!$D$4:$AG$150,0,MATCH(P$2,Inputs!$D$2:$AG$2,0))))=0,"",SUMIFS(INDEX(Inputs!$D$4:$AG$150,0,MATCH(P$2,Inputs!$D$2:$AG$2,0)),Inputs!$B$4:$B$150,$B64)/1000) -> 6331 | Q64: =IF(SUMPRODUCT((Inputs!$B$4:$B$150=$B64)*ISNUMBER(INDEX(Inputs!$D$4:$AG$150,0,MATCH(Q$2,Inputs!$D$2:$AG$2,0))))=0,"",SUMIFS(INDEX(Inputs!$D$4:$AG$150,0,MATCH(Q$2,Inputs!$D$2:$AG$2,0)),Inputs!$B$4:$B$150,$B64)/1000) -> 10162 | R64: =IF(COUNT(N64:Q64)=4,SUM(N64:Q64),"") -> 30242 | S64: =IF(SUMPRODUCT((Inputs!$B$4:$B$150=$B64)*ISNUMBER(INDEX(Inputs!$D$4:$AG$150,0,MATCH(S$2,Inputs!$D$2:$AG$2,0))))=0,"",SUMIFS(INDEX(Inputs!$D$4:$AG$150,0,MATCH(S$2,Inputs!$D$2:$AG$2,0)),Inputs!$B$4:$B$150,$B64)/1000) -> 6723 | T64: =IF(SUMPRODUCT((Inputs!$B$4:$B$150=$B64)*ISNUMBER(INDEX(Inputs!$D$4:$AG$150,0,MATCH(T$2,Inputs!$D$2:$AG$2,0))))=0,"",SUMIFS(INDEX(Inputs!$D$4:$AG$150,0,MATCH(T$2,Inputs!$D$2:$AG$2,0)),Inputs!$B$4:$B$150,$B64)/1000) -> 6390 | U64: =IF(SUMPRODUCT((Inputs!$B$4:$B$150=$B64)*ISNUMBER(INDEX(Inputs!$D$4:$AG$150,0,MATCH(U$2,Inputs!$D$2:$AG$2,0))))=0,"",SUMIFS(INDEX(Inputs!$D$4:$AG$150,0,MATCH(U$2,Inputs!$D$2:$AG$2,0)),Inputs!$B$4:$B$150,$B64)/1000) -> 7383 | V64: =IF(SUMPRODUCT((Inputs!$B$4:$B$150=$B64)*ISNUMBER(INDEX(Inputs!$D$4:$AG$150,0,MATCH(V$2,Inputs!$D$2:$AG$2,0))))=0,"",SUMIFS(INDEX(Inputs!$D$4:$AG$150,0,MATCH(V$2,Inputs!$D$2:$AG$2,0)),Inputs!$B$4:$B$150,$B64)/1000) -> 10291 | W64: =IF(COUNT(S64:V64)=4,SUM(S64:V64),"") -> 30787 | X64: =IF(SUMPRODUCT((Inputs!$B$4:$B$150=$B64)*ISNUMBER(INDEX(Inputs!$D$4:$AG$150,0,MATCH(X$2,Inputs!$D$2:$AG$2,0))))=0,"",SUMIFS(INDEX(Inputs!$D$4:$AG$150,0,MATCH(X$2,Inputs!$D$2:$AG$2,0)),Inputs!$B$4:$B$150,$B64)/1000) -> 7290 | Y64: =IF(SUMPRODUCT((Inputs!$B$4:$B$150=$B64)*ISNUMBER(INDEX(Inputs!$D$4:$AG$150,0,MATCH(Y$2,Inputs!$D$2:$AG$2,0))))=0,"",SUMIFS(INDEX(Inputs!$D$4:$AG$150,0,MATCH(Y$2,Inputs!$D$2:$AG$2,0)),Inputs!$B$4:$B$150,$B64)/1000) -> 7673 | Z64: =IF(SUMPRODUCT((Inputs!$B$4:$B$150=$B64)*ISNUMBER(INDEX(Inputs!$D$4:$AG$150,0,MATCH(Z$2,Inputs!$D$2:$AG$2,0))))=0,"",SUMIFS(INDEX(Inputs!$D$4:$AG$150,0,MATCH(Z$2,Inputs!$D$2:$AG$2,0)),Inputs!$B$4:$B$150,$B64)/1000) -> 8442 | AA64: =IF(SUMPRODUCT((Inputs!$B$4:$B$150=$B64)*ISNUMBER(INDEX(Inputs!$D$4:$AG$150,0,MATCH(AA$2,Inputs!$D$2:$AG$2,0))))=0,"",SUMIFS(INDEX(Inputs!$D$4:$AG$150,0,MATCH(AA$2,Inputs!$D$2:$AG$2,0)),Inputs!$B$4:$B$150,$B64)/1000) -> 12142 | AB64: =IF(COUNT(X64:AA64)=4,SUM(X64:AA64),"") -> 35547 | AC64: =IF(SUMPRODUCT((Inputs!$B$4:$B$150=$B64)*ISNUMBER(INDEX(Inputs!$D$4:$AG$150,0,MATCH(AC$2,Inputs!$D$2:$AG$2,0))))=0,"",SUMIFS(INDEX(Inputs!$D$4:$AG$150,0,MATCH(AC$2,Inputs!$D$2:$AG$2,0)),Inputs!$B$4:$B$150,$B64)/1000) -> 9138 | AD64: =IF(SUMPRODUCT((Inputs!$B$4:$B$150=$B64)*ISNUMBER(INDEX(Inputs!$D$4:$AG$150,0,MATCH(AD$2,Inputs!$D$2:$AG$2,0))))=0,"",SUMIFS(INDEX(Inputs!$D$4:$AG$150,0,MATCH(AD$2,Inputs!$D$2:$AG$2,0)),Inputs!$B$4:$B$150,$B64)/1000) -> 8871 | AE64: =IF(SUMPRODUCT((Inputs!$B$4:$B$150=$B64)*ISNUMBER(INDEX(Inputs!$D$4:$AG$150,0,MATCH(AE$2,Inputs!$D$2:$AG$2,0))))=0,"",SUMIFS(INDEX(Inputs!$D$4:$AG$150,0,MATCH(AE$2,Inputs!$D$2:$AG$2,0)),Inputs!$B$4:$B$150,$B64)/1000) | AF64: =IF(SUMPRODUCT((Inputs!$B$4:$B$150=$B64)*ISNUMBER(INDEX(Inputs!$D$4:$AG$150,0,MATCH(AF$2,Inputs!$D$2:$AG$2,0))))=0,"",SUMIFS(INDEX(Inputs!$D$4:$AG$150,0,MATCH(AF$2,Inputs!$D$2:$AG$2,0)),Inputs!$B$4:$B$150,$B64)/1000) | AG64: =IF(COUNT(AC64:AF64)=4,SUM(AC64:AF64),"")

Sheet Model
C1: CHECKS | I1: =IF(I2="","",SUM(I2,I3)) -> 0 | J1: =IF(J2="","",SUM(J2,J3)) -> 0 | K1: =IF(K2="","",SUM(K2,K3)) -> 0 | L1: =IF(L2="","",SUM(L2,L3)) -> 0 | M1: =IF(M2="","",SUM(M2,M3)) -> 0 | N1: =IF(N2="","",SUM(N2,N3)) -> 0 | O1: =IF(O2="","",SUM(O2,O3)) -> 0 | P1: =IF(P2="","",SUM(P2,P3)) -> 0 | ... BF1: =IF(BF2="","",SUM(BF2,BF3)) -> 202897.15
C2: BS | I2: =IF(COUNT(I191,I267)<2,"",ABS(I191-I267)) -> 0 | J2: =IF(COUNT(J191,J267)<2,"",ABS(J191-J267)) -> 0 | K2: =IF(COUNT(K191,K267)<2,"",ABS(K191-K267)) -> 0 | L2: =IF(COUNT(L191,L267)<2,"",ABS(L191-L267)) -> 0 | M2: =IF(COUNT(M191,M267)<2,"",ABS(M191-M267)) -> 0 | N2: =IF(COUNT(N191,N267)<2,"",ABS(N191-N267)) -> 0 | O2: =IF(COUNT(O191,O267)<2,"",ABS(O191-O267)) -> 0 | P2: =IF(COUNT(P191,P267)<2,"",ABS(P191-P267)) -> 0 | ... BF2: =IF(COUNT(BF191,BF267)<2,"",ABS(BF191-BF267)) -> 0
